Workbook
Name __S1: {"Book1"}
Name __S1: {"Book1"}
Name __S1: {"Book1"}
Name __S1: {"Book1"}
Name _a1: {"'Sheet1'!$L$16"}
Name _a1: {"'Sheet1'!$L$16"}
Name _a1: {"'Sheet1'!$L$16"}
Name _a1: {"'Sheet1'!$L$16"}
Name _S1: {"Book1"}
Name _S1: {"Book1"}
Name _S1: {"Book1"}
Name _S1: {"Book1"}
Name Ă: #REF!
Name Ạ196: #REF!
Name â259: #REF!
Name â259: #REF!
Name â312: #REF!
Name â312: #REF!
Name Acquisition_PlanA: #REF!
Name Acquisition_PlanB: #REF!
Name Actual: (PeriodInActual*(#REF!>0))*PeriodInPlan
Name Actual: (PeriodInActual*(#REF!>0))*PeriodInPlan
Name Actual: (PeriodInActual*(#REF!>0))*PeriodInPlan
Name Actual: (PeriodInActual*(#REF!>0))*PeriodInPlan
Name ActualBeyond: PeriodInActual*(#REF!>0)
Name ActualBeyond: PeriodInActual*(#REF!>0)
Name ActualBeyond: PeriodInActual*(#REF!>0)
Name ActualBeyond: PeriodInActual*(#REF!>0)
Name adf: #REF!
Name adf: #REF!
Name AdvIncQ12020: #REF!
Name AdvIncQ12021: #REF!
Name AdvIncQ12022: #REF!
Name AdvIncQ12023: #REF!
Name AdvIncQ12024: #REF!
Name AdvIncQ22020: #REF!
Name AdvIncQ22021: #REF!
Name AdvIncQ22022: #REF!
Name AdvIncQ22023: #REF!
Name AdvIncQ22024: #REF!
Name AdvIncQ32020: #REF!
Name AdvIncQ32021: #REF!
Name AdvIncQ32022: #REF!
Name AdvIncQ32023: #REF!
Name AdvIncQ32024: #REF!
Name AdvIncQ42020: #REF!
Name AdvIncQ42021: #REF!
Name AdvIncQ42022: #REF!
Name AdvIncQ42023: #REF!
Name AdvIncQ42024: #REF!
Name AdvPenRate2020: #REF!
Name AdvPenRate2021: #REF!
Name AdvPenRate2022: #REF!
Name AdvPenRate2023: #REF!
Name AdvPenRate2024: #REF!
Name AllReportList: #REF!
Name Amount_act: #REF!
Name Amount_CF: #REF!
Name Amount_F: #REF!
Name Amount_KPI_act: #REF!

Sheet IR
D3: category_product_name_final | E3: report_date | F3: closing_balance_total | G3: closing_balance_overdue | H3: closing_balance_indue | I3: closing_balance_dpd_under10
D4: Bikeloan | E4: 45839 | F4: 14756199 | G4: 9366003 | H4: 5390196 | I4: 14756199
D5: Bikeloan | E5: 45840 | F5: 14756199 | G5: 9366003 | H5: 5390196 | I5: 14756199 | J5: 45839 | W5: Only DPD 0 | Y5: DPDto10
D6: Bikeloan | E6: 45841 | F6: 14756199 | G6: 9366003 | H6: 5390196 | I6: 14756199 | J6: 45840 | P6: Sum of closing_balance_dpd_under10 | Q6: Column Labels | V6: IR | W6: =ROUND(SUM(Q18:S20)/SUM(Q15:S17)*365,3) -> 0.498 | Y6: =SUM(Q18:S20)/SUM(Y15:AA17)*365 -> 0.48738193
D7: Bikeloan | E7: 45842 | F7: 14756199 | G7: 9366003 | H7: 5390196 | I7: 14756199 | J7: 45841 | P7: Row Labels | Q7: Jul | R7: Aug | S7: Sep | T7: Grand Total
D8: Bikeloan | E8: 45843 | F8: 14756199 | G8: 9366003 | H8: 5390196 | I8: 14756199 | J8: 45842 | P8: Bikeloan | Q8: 239812300 | R8: 147123641 | S8: 125836026 | T8: 512771967
D9: Bikeloan | E9: 45844 | F9: 14756199 | G9: 9366003 | H9: 5390196 | I9: 14756199 | J9: 45843 | P9: Cashloan | Q9: 78436590748098 | R9: 90255148949428 | S9: 100589895287302 | T9: 269281634984828
D10: Bikeloan | E10: 45845 | F10: 14756199 | G10: 9366003 | H10: 5390196 | I10: 14756199 | J10: 45844 | P10: Overdraft | Q10: 7136242574215 | R10: 6746808038715 | S10: 5974343866384 | T10: 19857394479314
D11: Bikeloan | E11: 45846 | F11: 14756199 | G11: 9366003 | H11: 5390196 | I11: 14756199 | J11: 45845 | P11: Payday | Q11: 4622575283656 | R11: 6916178026946 | S11: 9155304671675 | T11: 20694057982277
D12: Bikeloan | E12: 45847 | F12: 14756199 | G12: 9366003 | H12: 5390196 | I12: 5390196 | J12: 45846 | P12: Paylater | Q12: 1614363094217 | R12: 1979638013131 | S12: 2393220164489 | T12: 5987221271837
D13: Bikeloan | E13: 45848 | F13: 14756199 | G13: 9366003 | H13: 5390196 | I13: 5390196 | J13: 45847 | P13: Grand Total | Q13: 91810011512486 | R13: 105897920151861 | S13: 118112889825876 | T13: 315820821490223
D14: Bikeloan | E14: 45849 | F14: 14756199 | G14: 9366003 | H14: 5390196 | I14: 5390196 | J14: 45848 | Q14: Indue | U14: Indue | Y14: Indue 10
D15: Bikeloan | E15: 45850 | F15: 14756199 | G15: 9366003 | H15: 5390196 | I15: 5390196 | J15: 45849 | O15: Balance | P15: CL | Q15: 76815377331487 | R15: 88356842904043 | S15: 98510201219076 | Y15: 78436590748098 | Z15: 90255148949428 | AA15: 100589895287302 | AD15: =SUM(Q18:S18)/SUM(Y15:AA15)*365 -> 0.49171714
D16: Bikeloan | E16: 45851 | F16: 14756199 | G16: 9366003 | H16: 5390196 | I16: 5390196 | J16: 45850 | P16: PD | Q16: 4524046156012 | R16: 6752896242376 | S16: 8931338959705 | Y16: 4622575283656 | Z16: 6916178026946 | AA16: 9155304671675 | AD16: =SUM(Q19:S19)/SUM(Y16:AA16)*365 -> 0.55165627
D17: Bikeloan | E17: 45852 | F17: 14756199 | G17: 9366003 | H17: 5390196 | I17: 5390196 | J17: 45851 | P17: OD | Q17: 7046693541652 | R17: 6663812994227 | S17: 5882758745896 | Y17: 7136242574215 | Z17: 6746808038715 | AA17: 5974343866384 | AD17: =SUM(Q20:S20)/SUM(Y17:AA17)*365 -> 0.36161072
D18: Bikeloan | E18: 45853 | F18: 14756199 | G18: 9366003 | H18: 5390196 | I18: 5390196 | J18: 45852 | O18: Thu lãi | P18: CL | Q18: =SUM(Q24:Q32) -> 106108627740 | R18: =SUM(R24:R32) -> 121377125554 | S18: =SUM(S24:S32) -> 135282451913 | U18: =Q18/Q15*365 -> 0.50419135 | V18: =R18/R15*365 -> 0.501406 | W18: =S18/S15*365 -> 0.50124854
D19: Bikeloan | E19: 45854 | F19: 14756199 | G19: 9366003 | H19: 5390196 | I19: 5390196 | J19: 45853 | P19: PD | Q19: =SUM(Q34:Q36) -> 7243462161 | R19: =SUM(R34:R36) -> 10646665908 | S19: =SUM(S34:S36) -> 13386602820 | U19: =Q19/Q16*365 -> 0.58440246 | V19: =R19/R16*365 -> 0.57546169 | W19: =S19/S16*365 -> 0.54707475
D20: Bikeloan | E20: 45855 | F20: 14756199 | G20: 9366003 | H20: 5390196 | I20: 5390196 | J20: 45854 | P20: OD | Q20: =Q39 -> 7097575425 | R20: =R39 -> 6741642587 | S20: =S39 -> 5833786603 | U20: =Q20/Q17*365 -> 0.36763555 | V20: =R20/R17*365 -> 0.36926299 | W20: =S20/S17*365 -> 0.36196149
D21: Bikeloan | E21: 45856 | F21: 14756199 | G21: 9366003 | H21: 5390196 | I21: 5390196 | J21: 45855
D22: Bikeloan | E22: 45857 | F22: 14756199 | G22: 9366003 | H22: 5390196 | I22: 5390196 | J22: 45856
D23: Bikeloan | E23: 45858 | F23: 14756199 | G23: 9366003 | H23: 5390196 | I23: 5390196 | J23: 45857
D24: Bikeloan | E24: 45859 | F24: 14756199 | G24: 9366003 | H24: 5390196 | I24: 5390196 | J24: 45858 | N24: cashloan | O24: cashloan | P24: VDS | Q24: 48463084122 | R24: 53272770215 | S24: 57987623749
D25: Bikeloan | E25: 45860 | F25: 14756199 | G25: 9366003 | H25: 5390196 | I25: 5390196 | J25: 45859 | N25: cashloan | O25: payroll | P25: VDS | Q25: 180134709 | R25: 177793395 | S25: 162715192
D26: Bikeloan | E26: 45861 | F26: 14756199 | G26: 9366003 | H26: 5390196 | I26: 5390196 | J26: 45860 | N26: cashloan | O26: cashloan | P26: BEG | Q26: 208673555 | R26: 170907800 | S26: 140807807
D27: Bikeloan | E27: 45862 | F27: 14756199 | G27: 9366003 | H27: 5390196 | I27: 5390196 | J27: 45861 | N27: cashloan | O27: cashloan | P27: NGS | Q27: 619417378 | R27: 493982632 | S27: 409380520
D28: Bikeloan | E28: 45863 | F28: 14756199 | G28: 9366003 | H28: 5390196 | I28: 5390196 | J28: 45862 | N28: cashloan | O28: cashloan | P28: CAKE | Q28: 42400864409 | R28: 48200259590 | S28: 53511511977
D29: Bikeloan | E29: 45864 | F29: 14756199 | G29: 9366003 | H29: 5390196 | I29: 5390196 | J29: 45863 | N29: cashloan | O29: cashloan | P29: MWG | Q29: 6378275744 | R29: 8067738498 | S29: 10087675211
D30: Bikeloan | E30: 45865 | F30: 14756199 | G30: 9366003 | H30: 5390196 | I30: 5390196 | J30: 45864 | N30: cashloan | O30: cashloan | P30: VNPAY | Q30: 2629288891 | R30: 2780395647 | S30: 2886582366
D31: Bikeloan | E31: 45866 | F31: 14203249 | G31: 9366003 | H31: 4837246 | I31: 4837246 | J31: 45865 | N31: cashloan | O31: cashloan | P31: ZALOPAY | Q31: 5190014930 | R31: 8151740830 | S31: 9991296076
D32: Bikeloan | E32: 45867 | F32: 14203249 | G32: 9366003 | H32: 4837246 | I32: 4837246 | J32: 45866 | N32: cashloan | O32: cashloan | P32: VNPOST | Q32: 38874002 | R32: 61536947 | S32: 104859015
D33: Bikeloan | E33: 45868 | F33: 14203249 | G33: 9366003 | H33: 4837246 | I33: 4837246 | J33: 45867
D34: Bikeloan | E34: 45869 | F34: 14203249 | G34: 9366003 | H34: 4837246 | I34: 4837246 | J34: 45868 | N34: Payday | O34: payday | P34: VDS | Q34: 6851571155 | R34: 7025398016 | S34: 8428697029
D35: Bikeloan | E35: 45870 | F35: 14203249 | G35: 9366003 | H35: 4837246 | I35: 4837246 | J35: 45869 | N35: Payday | O35: payroll | P35: VDS
D36: Bikeloan | E36: 45871 | F36: 14203249 | G36: 9366003 | H36: 4837246 | I36: 4837246 | J36: 45870 | N36: Payday | O36: payday | P36: CAKE | Q36: 391891006 | R36: 3621267892 | S36: 4957905791
D37: Bikeloan | E37: 45872 | F37: 14203249 | G37: 9366003 | H37: 4837246 | I37: 4837246 | J37: 45871 | N37: Payday | O37: payday | P37: VNPAY | Q37: 0 | R37: 0 | S37: 2307342
D38: Bikeloan | E38: 45873 | F38: 14203249 | G38: 9366003 | H38: 4837246 | I38: 4837246 | J38: 45872
D39: Bikeloan | E39: 45874 | F39: 14203249 | G39: 9366003 | H39: 4837246 | I39: 4837246 | J39: 45873 | N39: overdraft | P39: CAKE | Q39: 7097575425 | R39: 6741642587 | S39: 5833786603
D40: Bikeloan | E40: 45875 | F40: 14203249 | G40: 9366003 | H40: 4837246 | I40: 4837246 | J40: 45874
D41: Bikeloan | E41: 45876 | F41: 14203249 | G41: 9366003 | H41: 4837246 | I41: 4837246 | J41: 45875
D42: Bikeloan | E42: 45877 | F42: 14203249 | G42: 9366003 | H42: 4837246 | I42: 4837246 | J42: 45876
D43: Bikeloan | E43: 45878 | F43: 14203249 | G43: 9366003 | H43: 4837246 | I43: 4837246 | J43: 45877
D44: Bikeloan | E44: 45879 | F44: 14203249 | G44: 9366003 | H44: 4837246 | I44: 4837246 | J44: 45878
D45: Bikeloan | E45: 45880 | F45: 14203249 | G45: 9366003 | H45: 4837246 | I45: 4837246 | J45: 45879
D46: Bikeloan | E46: 45881 | F46: 14203249 | G46: 9366003 | H46: 4837246 | I46: 4837246 | J46: 45880
D47: Bikeloan | E47: 45882 | F47: 14203249 | G47: 9366003 | H47: 4837246 | I47: 4837246 | J47: 45881
D48: Bikeloan | E48: 45883 | F48: 14203249 | G48: 9366003 | H48: 4837246 | I48: 4837246 | J48: 45882
D49: Bikeloan | E49: 45884 | F49: 14203249 | G49: 9366003 | H49: 4837246 | I49: 4837246 | J49: 45883
D50: Bikeloan | E50: 45885 | F50: 14203249 | G50: 9366003 | H50: 4837246 | I50: 4837246 | J50: 45884
D51: Bikeloan | E51: 45886 | F51: 14203249 | G51: 9366003 | H51: 4837246 | I51: 4837246 | J51: 45885
... D96: Cashloan | E96: 45839 | F96: 2902399733643 | G96: 660200592686 | H96: 2242199140957 | I96: 2288594563696 | J96: 45930
D97: Cashloan | E97: 45840 | F97: 2932754939272 | G97: 662880676500 | H97: 2269874262772 | I97: 2317176397929
D98: Cashloan | E98: 45841 | F98: 2950568334295 | G98: 666504316809 | H98: 2284064017486 | I98: 2335928371557
D99: Cashloan | E99: 45842 | F99: 2971365399224 | G99: 669080301041 | H99: 2302285098183 | I99: 2350967631736
D100: Cashloan | E100: 45843 | F100: 2992546280340 | G100: 673220276193 | H100: 2319326004147 | I100: 2369924242290
D101: Cashloan | E101: 45844 | F101: 3013845866748 | G101: 679246533221 | H101: 2334599333527 | I101: 2388998772568
D102: Cashloan | E102: 45845 | F102: 3027424615803 | G102: 671404011778 | H102: 2356020604025 | I102: 2400114880849
D103: Cashloan | E103: 45846 | F103: 3045779389381 | G103: 683330732027 | H103: 2362448657354 | I103: 2416464263642
D104: Cashloan | E104: 45847 | F104: 3063403106918 | G104: 685572771439 | H104: 2377830335479 | I104: 2425312444712
D105: Cashloan | E105: 45848 | F105: 3084437426416 | G105: 683943401227 | H105: 2400494025189 | I105: 2449020841427
D106: Cashloan | E106: 45849 | F106: 3102817658547 | G106: 684953636094 | H106: 2417864022453 | I106: 2469542425901
D107: Cashloan | E107: 45850 | F107: 3119361299415 | G107: 688049526267 | H107: 2431311773148 | I107: 2484476613720
D108: Cashloan | E108: 45851 | F108: 3141087961345 | G108: 694414625078 | H108: 2446673336267 | I108: 2503766935053
... D463: Paylater | E463: 45930 | F463: 121764644082 | G463: 36792731093 | H463: 84971912989 | I463: 84971912989

Sheet NOTE
A1: SAP MODEL - CASHLOAN
B2: OFFICIAL | N2: HKN | O2: v9 | P2: 20251001
B3: 1. Notes and disclaimer
C4: a. Giới thiệu về SAP
D5: - SAP: Single Account Profitability (Hiệu quả sản phẩm trên từng đơn vị sản phẩm)
D6: - Model SAP được sử dụng như một (01) trong các mô hình dự đoán hiệu quả vòng đời của sản phẩm.
D7: - Do sự phức tạp của sản phẩm, các hệ thống vận hành (hệ thống hạch kế toán, hệ thống quản trị rủi ro, hệ thống quản trị…), hành vi người sử dụng hành vi người sử dụng, model chỉ có thể mô phỏng tương đối trung bình vòng đời của sản phẩm.
D8: - Do tính chất thời điểm, mô hình được xây dựng mô phỏng theo cách vận hành sản phẩm tại thời điểm phát hành. Trường hợp hệ thống thay đổi, sản phẩm thay đổi, mô hình sẽ không thể phản ánh đúng bản chất vận hành sản phẩm.
D9: - Mô hình được tính toán dựa vào các yếu tố đầu vào xác định tại một thời điểm xác định, do đó kết quả của mô hình có thể có sự khác biệt so với thực tế vận hành sản phẩm.
D10: - Mô hình SAP Cashloan tính hiệu quả của khoản vay giải ngân và thời hạn tối đa được áp dụng là 5 năm ( 60 tháng) kể từ ngày bắt đầu sản phẩm đối với sử dụng phương pháp dự phòng IFRS
E11: - Lưu ý rằng trường hợp áp dụng cho khoản vay 5 năm, thì các chi phí sẽ không được tính toán đầy đủ do chi phí COF cho thời gian từ lúc khoản vay kết thúc tới lúc được xóa trên sổ kế toán.
E12: - Chỉ nên sử dụng với khoản vay dưới 4 năm (48 tháng) để được tính toán đầy đủ chi phí
E13: - Đối với phương pháp tính rủi ro VAS, thời hạn khoản vay tối đa sử dụng là 4 năm (48 tháng)
C15: b. Giới thiệu về PnL
D16: - Trong file tính này, Profit & Lost (PnL) được dự phóng từ trung bình cộng kết quả kinh doanh trên từng sản phẩm (SAP) với yếu tố "sale plan" (số giải ngân) qua từng tháng, do đó có thể khác biệt so với kết quả thực tế vận hành.
D17: - Dòng tiền thực tế qua từng tháng có thể khác biệt với mô hình tính toán do nhiều yếu tố tác động bên ngoài thay đổi, do đó, vui lòng chỉ sử dụng mô hình cho mục đích tham khảo.
D18: - Cho mục đích tính dự phòng dòng tiền ngắn và trung hạn, mô hình PnL được cutoff tại thời điểm 5 năm (60 tháng) kể từ ngày bắt đầu khởi chạy sản phẩm đầu tiên.
B20: 2. Instruction
D21: - Dành cho người sử dụng
E22: - Chỉ chỉnh sửa vào các ô màu vàng
E23: - 2 sheets "SAP_Leadsheet" và "Sale plan&PnL" cung cấp yếu tố đầu vào và đầu ra để tính toán mô hình SAP cũng như PnL.
F24: - Sheet SAP_Leadsheet được cấu trúc 2 phần, bên trái là các yếu tố đầu vào (input) và bên phải là kết quả dự đoán (output). Đơn vị sử dụng tại bảng tính là triệu VND (mVND) và phần trăm (%)
F25: - Sheet "Sale plan & PL" được cấu trúc 2 phần, bên trên là sale plan và bên dưới là kết quả PnL
E26: - 2 sheets "SAP_Spreadsheet" và "PL projection speadsheet" là các file tính toán cho 2 sheet "SAP_Leadsheet", "Sales plan & PL"
F27: - 2 sheets được cấu trúc từ trên xuống dưới theo thứ tự tính toán mô phỏng để đưa ra kết quả kinh doanh cuối cùng
F28: - 2 sheets đã được tạm khóa. Trường hợp cần mở khóa, điều chỉnh các yếu tố, vui lòng liên hệ với nhóm vận hành để được hỗ trợ.
D30: - Dành riêng cho người vận hành, hiệu chỉnh
E31: - Cần cẩn trọng khi điều chỉnh ở các file "speadsheet" vì 1 khi sai lệch rất khó tìm ra lỗi (VD: sửa nhầm ô, link nhầm vị trí,…)
B34: 3. Legend
C35: GENERAL INPUT
G37: Diễn giải | L37: Chú thích
D38: Risk input | G38: Loại phương pháp tính rủi ro | L38: Lựa chon phương pháp tính rủi ro VAS và IFRS
D39: Write off | G39: Thời điểm WO | L39: Lựa chọn thời điểm ghi nhận WO là 360 hoặc 180
C40: REVENUE INPUT
G42: Diễn giải | L42: Chú thích
C43: Amount & Tenor
D44: Loan amount | G44: Số tiền vay giải ngân (có thể bao gồm bảo hiểm hoặc không) | L44: Trường hợp số tiền giải ngân > giá trị hàng hóa, chỉ ghi = số thực tế giải ngân
D45: Payment Method | G45: Phương pháp tính lãi | L45: EMI (Equated monthly Installment)- số tiền thanh toán cố định hàng tháng
D46: Nominal Tenor | G46: Thời hạn vay | L46: Thời hạn ghi nhận trên khoản vay ( VD: 1 tháng, 3 tháng, 12 tháng,…)
D47: Maturity to Termination | G47: Thời hạn từ lúc đáo hạn tới lúc tới khi ra ngoại bảng | L47: Nên để 6 tháng để khớp với hệ thống kế toán, rủi ro đang ghi nhận WO180+
D48: Month on book | G48: Thời gian ghi nhận trên sổ sách | L48: = Nominal tenor + Maturity to termination
C50: Pricing
D51: From- To | G51: Từ tháng… tới tháng
D52: IR | G52: Interest rate- lãi suất khoản vay
D53: COF | G53: Cost of fund - Giá vốn | L53: Sử dụng matrix mua vốn của VPB
D54: NIM | G54: Net interest margin - Biên lãi ròng
C56: Early prepayment
D57: From- To | G57: Từ tháng… tới tháng
D58: Penalty fee | G58: Phí phạt
D59: Penalty IR | G59: Lãi phạt
D60: %Attrition | G60: Tỉ lệ trả trước hạn | L60: Tỉ lệ trả trước tính theo cohort, thông thường quan sát trung bình 6 tháng
C61: Credit insurrance
D62: Banca Premium (excl. in loan) | G62: Tỉ lệ bảo hiểm khoản vay (dư nợ không bao gồm bảo hiểm khoản vay) | L62: VD: 7% khoản vay, 8% khoản vay
D63: Banca Premium (incl. in loan) | G63: Tỉ lệ bảo hiểm khoản vay (dư nợ có bao gồm bảo hiểm khoản vay)
D64: Penetration | G64: Tỉ lệ khoản vay có bảo hiểm/tổng khoản vay giải ngân
D65: Commission to CAKE | G65: Tỉ lệ nhận được từ số tiền bảo hiểm | L65: Hiện tai, số này là khoàng 85% tổng số tiền thu từ bảo hiểm
C66: Support fee
D67: Các khoản thu khác | L67: Hiện tại chưa có
C72: COST INPUT
G74: Diễn giải | L74: Chú thích
C75: Inflation rate | G75: Tỉ lệ tăng giá chi phí qua các năm
C77: Acquisition cost | G77: Chi phí mở rộng khách hàng
D78: Sale incentive | G78: Chi phí sales, trả đối tác kinh doanh
D79: Sharing TOI and Risk DPD90+ | G79: Chia sẻ doanh thu, rủi ro(DPD90+) | L79: xem giải thích DPD+ tại đây
D80: Sharing TOI and Risk DPD180+ | G80: Chia sẻ doanh thu, rủi ro(DPD180+) | L80: xem giải thích DPD+ tại đây
D82: Sharing CII (only) | G82: Chỉ chia sẻ doanh thu từ lãi
D83: Sharing COF (only) | G83: Chỉ chia sẻ chi phí vốn
D84: Sharing NFI (only) | G84: Chỉ chia sẻ doanh thu từ vốn
D85: Sharing Risk DPD90+ (Only) | G85: Chỉ chia sẻ rủi ro (DPD90+) | L85: xem giải thích DPD+ tại đây
D86: Sharing Risk DPD180+ (only) | G86: Chỉ chia sẻ rủi ro (DPD180+) | L86: xem giải thích DPD+ tại đây
D88: Partner Lead Acquistion | G88: Chi phí leadgen đối tác
C90: * Chú thích
C91: Chia sẻ rủi ro DPD90/ (DPD180+) là phương pháp tính rủi ro = 100% duy nhất 1 lần tại thời điểm dư nợ DPD90 +(tức quá hạn >90 ngày, chuyển nợ nhóm 3)/ DPD180+(tức qua hạn >180 ngày, chuyển nợ nhóm 4) mà ko tính tại các bucket khác.
C92: Phương pháp này chỉ sử dụng đối với các đối tác chia sẻ doanh thu chi phí.
D94: Marketing cost | G94: Chi phí marketing để mở khoản vay
D96: UW & Disbursal
E97: Underwriting cost & Score | G97: Chi phí kiểm tra điều kiện mở khoản vay
E98: DOP cost | G98: Chi phí luồng DOP (nếu có) (SMS,…)
E99: Disbursement cost | G99: Chi phí mở khoản vay (chi phí esign, sms,…)
E100: Approval rate | G100: Tỉ lệ phê duyệt | L100: Tỉ lệ khách hàng được phê duyệt/khách hàng vào luồng LOS
E101: Disbursement rate | G101: Tỉ lệ giải ngân | L101: Tỉ lệ khách hàng giải ngân/khách hàng được phê duyệt
D103: Collection & AMC
E104: Collections_all | G104: Đơn giá thu nợ tính trung bình cho các khoản vay
D106: Aftersale service
E107: Email & SMS | G107: Chi phí Email, SMS hàng tháng
D109: Supporting units | G109: Chi phí phân bổ
E110: Direct HR | G110: Chi phí nhân sự trực tiếp
E111: Indirect HR | G111: Chi phí nhân sự hỗ trợ
E112: IT | G112: Chi phí IT
E113: Other supports | G113: Chi phí khác (Chi phí thuê VP, CS, khác…)
C115: RISK INPUT
D117: NF | G117: Netflow- Tỉ lệ chuyển nợ
D118: PD | G118: Percentage of debt (tỉ lệ vỡ nợ)
D119: Pro. Rate | G119: Tỉ lệ vỡ nợ đã điều chỉnh thu hồi nợ
D121: Recovery rate | G121: Tỉ lệ thu hồi nợ sau WO
D122: Collect after WO
D123: Fee and others | G123: Tỉ lệ thu được phí, phạt, khác
B128: Write-off mode | E128: Provision mode
B129: DPD360+ | E129: IFRS
B130: DPD180+ | E130: VAS

Sheet Leadsheet
B1: SAP CASHLOAN MODEL | D1: 1
B2: =NOTE!N2 -> HKN | C2: =NOTE!P2 -> 20251001 | D2: =NOTE!O2 -> v9 | K2: NOTE
K3: Please read carefully about before using model
B4: Product | C4: Unsecured Cashloan | D4: UPL | E4: Risk input | G4: IFRS | H4: =G4 -> IFRS | L4: Disclaimer
B5: Sub-Product | C5: Cashloan | D5: ALL | E5: Write off | G5: DPD180+ | H5: =G5 -> DPD180+ | L5: Instruction
B6: Sub-Segments | C6: ALL | D6: ALL | E6: Quarter | G6: Q3.2025 | H6: =G6 -> Q3.2025 | L6: Legend
B8: REVENUE INPUT | H8: Cur: mVND | K8: GENERAL OUTPUT | U8: Cur: mVND
B10: Amount & Tenor | C10: Loan amount | E10: =DATA!G20 -> 16.17916 | N10: Life time | O10: Year 1 | P10: Year 2 | Q10: Year 3 | R10: Year 4 | S10: Year 5 | T10: % ANR | U10: % Disbursement
C11: Payment Method | E11: EMI | K11: ANR | N11: =N29 -> 5.0874047 | O11: =O29 -> 8.1418252 | P11: =P29 -> 0.50577392 | Q11: =Q29 -> 0 | R11: =R29 -> 0 | S11: =S29 -> 0 | U11: =N11/$E$10 -> 0.31444183
C12: Nominal Tenor | E12: =DATA!H21 -> 14 | K12: TOI | N12: =SUM(N13:N15) -> 3.957503 | O12: =SUM(O13:O15) -> 3.9068384 | P12: =SUM(P13:P15) -> 0.050664579 | Q12: =SUM(Q13:Q15) -> 0 | R12: =SUM(R13:R15) -> 0 | S12: =SUM(S13:S15) -> 0 | T12: =N12/$E$14*12/$N$11 -> 0.46674129 | U12: =N12/$E$10 -> 0.24460497
C13: Maturity to Termination | E13: 6 | K13: Net interest income | N13: =N31 -> 2.9290827 | O13: =O31 -> 2.8807437 | P13: =P31 -> 0.048339043 | Q13: =Q31 -> 0 | R13: =R31 -> 0 | S13: =S31 -> 0 | T13: =N13/$E$14*12/$N$11 -> 0.34545112 | U13: =N13/$E$10 -> 0.18104047
C14: Month on book | E14: =E12+E13 -> 20 | K14: Net fee income | N14: =N34 -> 1.0284203 | O14: =O34 -> 1.0260947 | P14: =P34 -> 0.0023255362 | Q14: =Q34 -> 0 | R14: =R34 -> 0 | S14: =S34 -> 0 | T14: =N14/$E$14*12/$N$11 -> 0.12129017 | U14: =N14/$E$10 -> 0.063564503
K15: Other income | N15: =N38 -> 0 | O15: =O38 -> 0 | P15: =P38 -> 0 | Q15: =Q38 -> 0 | R15: =R38 -> 0 | S15: =S38 -> 0 | T15: =N15/$E$14*12/$N$11 -> 0 | U15: =N15/$E$10 -> 0
K16: PROVISION | N16: =N39 -> -2.4867754 | O16: =O39 -> -2.4144567 | P16: =P39 -> -0.072318713 | Q16: =Q39 -> 0 | R16: =R39 -> 0 | S16: =S39 -> 0 | T16: =N16/$E$14*12/$N$11 -> -0.29328614 | U16: =N16/$E$10 -> -0.15370238
B17: Pricing | C17: From | D17: To | E17: IR | F17: COF | G17: NIM | K17: OPEX | N17: =SUM(N18:N21) -> -1.051908 | O17: =SUM(O18:O21) -> -1.0208987 | P17: =SUM(P18:P21) -> -0.03100928 | Q17: =SUM(Q18:Q21) -> 0 | R17: =SUM(R18:R21) -> 0 | S17: =SUM(S18:S21) -> 0 | T17: =N17/$E$14*12/$N$11 -> -0.12406027 | U17: =N17/$E$10 -> -0.065016228
A18: 1 | B18: 1 | C18: 1 | D18: =E12 -> 14 | E18: =IR!AD15 -> 0.49171714 | F18: =COF!J1 -> 0.069062919 | G18: =E18-F18 -> 0.42265422 | K18: Acquisition cost | N18: =SUM(N41) -> -0.38973564 | O18: =SUM(O41) -> -0.4343572 | P18: =SUM(P41) -> 0.044621561 | Q18: =SUM(Q41) -> 0 | R18: =SUM(R41) -> 0 | S18: =SUM(S41) -> 0 | T18: =N18/$E$14*12/$N$11 -> -0.045964769 | U18: =N18/$E$10 -> -0.024088743
A19: 2 | B19: 2 | C19: =IF(D18="","",IF(D18>$E$12,"",D18+1)) -> 15 | D19: =E14 -> 20 | E19: =E18 -> 0.49171714 | F19: =COF!J1 -> 0.069062919 | G19: =E19-F19 -> 0.42265422 | K19: UW & Disbursal | N19: =N45 -> -0.066756457 | O19: =O45 -> -0.066756457 | P19: =P45 -> 0 | Q19: =Q45 -> 0 | R19: =R45 -> 0 | S19: =S45 -> 0 | T19: =N19/$E$14*12/$N$11 -> -0.0078731449 | U19: =N19/$E$10 -> -0.0041260768
A20: 3 | B20: 3 | K20: Collection & aftersale service | N20: =N48 -> -0.098911856 | O20: =O48 -> -0.080561609 | P20: =P48 -> -0.018350247 | Q20: =Q48 -> 0 | R20: =R48 -> 0 | S20: =S48 -> 0 | T20: =N20/$E$14*12/$N$11 -> -0.011665499 | U20: =N20/$E$10 -> -0.0061135347
A21: 4 | B21: 4 | K21: Support unit | N21: =N52 -> -0.49650401 | O21: =O52 -> -0.43922342 | P21: =P52 -> -0.057280595 | Q21: =Q52 -> 0 | R21: =R52 -> 0 | S21: =S52 -> 0 | T21: =N21/$E$14*12/$N$11 -> -0.058556853 | U21: =N21/$E$10 -> -0.030687873
A22: 5 | B22: 5 | K22: PBT | N22: =N12+N16+N17 -> 0.41881959 | O22: =O12+O16+O17 -> 0.47148301 | P22: =P12+P16+P17 -> -0.052663414 | Q22: =Q12+Q16+Q17 -> 0 | R22: =R12+R16+R17 -> 0 | S22: =S12+S16+S17 -> 0 | T22: =N22/$E$14*12/$N$11 -> 0.049394883 | U22: =N22/$E$10 -> 0.025886362
B23: 6 | K23: In which: PROFIT BEFORE SU | N23: =N22-N21 -> 0.91532361 | O23: =O22-O21 -> 0.91070643 | P23: =P22-P21 -> 0.0046171806 | Q23: =Q22-Q21 -> 0 | R23: =R22-R21 -> 0 | S23: =S22-S21 -> 0 | T23: =N23/$E$14*12/$N$11 -> 0.10795174 | U23: =N23/$E$10 -> 0.056574235
B25: Early prepayment | C25: From | D25: To | E25: Penalty fee | F25: Penalty IR | G25: %Attrition
B26: 1 | C26: 1 | D26: 1 | E26: =DATA!E73 -> 0.075631948 | G26: =DATA!G73 -> 0.11584981 | H26: per cohort | I26: 0.10601949 | K26: PERFORMANCE OUTPUT | U26: Cur: mVND
B27: 2 | C27: =D26+1 -> 2 | D27: 3 | E27: =DATA!E74 -> 0.075631948 | G27: =DATA!G74 -> 0.047684839 | H27: per cohort | I27: 0.047922919
B28: 3 | C28: =D27+1 -> 4 | D28: 14 | E28: =DATA!E75 -> 0.048252779 | G28: =DATA!G75 -> 0.023340862 | H28: per cohort | I28: 0.029 | N28: Life time | O28: Year 1 | P28: Year 2 | Q28: Year 3 | R28: Year 4 | S28: Year 5 | T28: % ANR | U28: % Disbursement
B29: 4 | C29: =IF(D28="","",IF(D28>$E$12,"",D28+1)) -> 15 | K29: ANR | N29: =SUM(SAP_Speadsheet!$D$50:$BF$50)/COUNTIF(SAP_Speadsheet!$D$50:$BF$50,">0") -> 5.0874047 | O29: =IFERROR(SUM(SAP_Speadsheet!$D$50:$P$50)/COUNTIF(SAP_Speadsheet!$D$50:$P$50,">0"),0) -> 8.1418252 | P29: =IFERROR(SUM(SAP_Speadsheet!$Q$50:$AB$50)/COUNTIF(SAP_Speadsheet!$Q$50:$AB$50,">0"),0) -> 0.50577392 | Q29: =IFERROR(SUM(SAP_Speadsheet!$AC$50:$AN$50)/COUNTIF(SAP_Speadsheet!$AC$50:$AN$50,">0"),0) -> 0 | R29: =IFERROR(SUM(SAP_Speadsheet!$AO$50:$AZ$50)/COUNTIF(SAP_Speadsheet!$AO$50:$AZ$50,">0"),0) -> 0 | S29: =IFERROR(SUM(SAP_Speadsheet!$BA$50:$BF$50)/COUNTIF(SAP_Speadsheet!$BA$50:$BF$50,">0"),0) -> 0 | U29: =N29/$E$10 -> 0.31444183
B30: 5 | C30: =IF(D29="","",IF(D29>$E$12,"",D29+1)) | E30: =IF(D30="",0,SUMIFS(#REF!,#REF!,Leadsheet!G$24,#REF!,Leadsheet!$A30,#REF!,Leadsheet!$C$4,#REF!,Leadsheet!$G$5,#REF!,Leadsheet!$D$5,#REF!,Leadsheet!G4)) -> 0 | F30: 0 | K30: TOI | N30: =SUM(O30:S30) -> 3.957503 | O30: =SUM(SAP_Speadsheet!$E$55:$P$55) -> 3.9068384 | P30: =SUM(SAP_Speadsheet!$Q$55:$AB$55) -> 0.050664579 | Q30: =SUM(SAP_Speadsheet!$AC$55:$AN$55) -> 0 | R30: =SUM(SAP_Speadsheet!$AO$55:$AZ$55) -> 0 | S30: =SUM(SAP_Speadsheet!$BA$55:$BF$55) -> 0 | T30: =N30/$E$14*12/$N$29 -> 0.46674129 | U30: =N30/$E$10 -> 0.24460497
B31: 6 | C31: =IF(D30="","",IF(D30>$E$12,"",D30+1)) | E31: =IF(D31="",0,SUMIFS(#REF!,#REF!,Leadsheet!G$24,#REF!,Leadsheet!$A31,#REF!,Leadsheet!$C$4,#REF!,Leadsheet!$G$5,#REF!,Leadsheet!$D$5,#REF!,Leadsheet!G4)) -> 0 | F31: 0 | K31: Net interest income | N31: =SUM(O31:S31) -> 2.9290827 | O31: =SUM(SAP_Speadsheet!$E$57:$P$57) -> 2.8807437 | P31: =SUM(SAP_Speadsheet!$Q$57:$AB$57) -> 0.048339043 | Q31: =SUM(SAP_Speadsheet!$AC$57:$AN$57) -> 0 | R31: =SUM(SAP_Speadsheet!$AO$57:$AZ$57) -> 0 | S31: =SUM(SAP_Speadsheet!$BA$57:$BF$57) -> 0 | T31: =N31/$E$14*12/$N$29 -> 0.34545112 | U31: =N31/$E$10 -> 0.18104047
K32: Interest income | N32: =SUM(O32:S32) -> 3.5146678 | O32: =SUM(SAP_Speadsheet!$E$58:$P$58) -> 3.4430419 | P32: =SUM(SAP_Speadsheet!$Q$58:$AB$58) -> 0.071625858 | Q32: =SUM(SAP_Speadsheet!$AC$58:$AN$58) -> 0 | R32: =SUM(SAP_Speadsheet!$AO$58:$AZ$58) -> 0 | S32: =SUM(SAP_Speadsheet!$BA$58:$BF$58) -> 0 | T32: =N32/$E$14*12/$N$29 -> 0.41451404 | U32: =N32/$E$10 -> 0.21723425
B33: Credit insurrance | C33: Banca Premium (excl. in loan) | F33: per disbursement amount | K33: Cost of fund | N33: =SUM(O33:S33) -> -0.58558503 | O33: =SUM(SAP_Speadsheet!$E$59:$P$59) -> -0.56229821 | P33: =SUM(SAP_Speadsheet!$Q$59:$AB$59) -> -0.023286816 | Q33: =SUM(SAP_Speadsheet!$AC$59:$AN$59) -> 0 | R33: =SUM(SAP_Speadsheet!$AO$59:$AZ$59) -> 0 | S33: =SUM(SAP_Speadsheet!$BA$59:$BF$59) -> 0 | T33: =N33/$E$14*12/$N$29 -> -0.069062919 | U33: =N33/$E$10 -> -0.036193784
C34: Banca Premium (incl. in loan) | E34: =DATA!J20 -> 0.068797748 | F34: per disbursement amount | K34: Net fee income | N34: =SUM(O34:S34) -> 1.0284203 | O34: =SUM(SAP_Speadsheet!$E$61:$P$61) -> 1.0260947 | P34: =SUM(SAP_Speadsheet!$Q$61:$AB$61) -> 0.0023255362 | Q34: =SUM(SAP_Speadsheet!$AC$61:$AN$61) -> 0 | R34: =SUM(SAP_Speadsheet!$AO$61:$AZ$61) -> 0 | S34: =SUM(SAP_Speadsheet!$BA$61:$BF$61) -> 0 | T34: =N34/$E$14*12/$N$29 -> 0.12129017 | U34: =N34/$E$10 -> 0.063564503
C35: Penetration | E35: =DATA!K20 -> 0.78737421 | F35: per disbursement amount | K35: Early termination fee | N35: =SUM(O35:S35) -> 0.31675681 | O35: =SUM(SAP_Speadsheet!$E$62:$P$62) -> 0.31443127 | P35: =SUM(SAP_Speadsheet!$Q$62:$AB$62) -> 0.0023255362 | Q35: =SUM(SAP_Speadsheet!$AC$62:$AN$62) -> 0 | R35: =SUM(SAP_Speadsheet!$AO$62:$AZ$62) -> 0 | S35: =SUM(SAP_Speadsheet!$BA$62:$BF$62) -> 0 | T35: =N35/$E$14*12/$N$29 -> 0.037357768 | U35: =N35/$E$10 -> 0.019578075
C36: Commission to CAKE | E36: 0.856 | F36: per disbursement amount | H36: done | K36: Insurance commission | N36: =SUM(O36:S36) -> 0.71166346 | O36: =SUM(SAP_Speadsheet!$E$63:$P$63) -> 0.71166346 | P36: =SUM(SAP_Speadsheet!$Q$63:$AB$63) -> 0 | Q36: =SUM(SAP_Speadsheet!$AC$63:$AN$63) -> 0 | R36: =SUM(SAP_Speadsheet!$AO$63:$AZ$63) -> 0 | S36: =SUM(SAP_Speadsheet!$BA$63:$BF$63) -> 0 | T36: =N36/$E$14*12/$N$29 -> 0.083932399 | U36: =N36/$E$10 -> 0.043986428
H37: done | K37: Support fee | N37: =SUM(O37:S37) -> 0 | O37: =SUM(SAP_Speadsheet!$E$64:$P$64) -> 0 | P37: =SUM(SAP_Speadsheet!$Q$64:$AB$64) -> 0 | Q37: =SUM(SAP_Speadsheet!$AC$64:$AN$64) -> 0 | R37: =SUM(SAP_Speadsheet!$AO$64:$AZ$64) -> 0 | S37: =SUM(SAP_Speadsheet!$BA$64:$BF$64) -> 0 | T37: =N37/$E$14*12/$N$29 -> 0 | U37: =N37/$E$10 -> 0
B38: Support fee | C38: One-time | F38: $ per account | K38: Other income | N38: =SUM(O38:S38) -> 0 | O38: =SUM(SAP_Speadsheet!$E$68:$P$68) -> 0 | P38: =SUM(SAP_Speadsheet!$Q$68:$AB$68) -> 0 | Q38: =SUM(SAP_Speadsheet!$AC$68:$AN$68) -> 0 | R38: =SUM(SAP_Speadsheet!$AO$68:$AZ$68) -> 0 | S38: =SUM(SAP_Speadsheet!$BA$68:$BF$68) -> 0 | T38: =N38/$E$14*12/$N$29 -> 0 | U38: =N38/$E$10 -> 0
C39: One-time | F39: % per ticketsize | K39: PROVISION | N39: =SUM(O39:S39) -> -2.4867754 | O39: =SUM(SAP_Speadsheet!$E$183:$P$183) -> -2.4144567 | P39: =SUM(SAP_Speadsheet!$Q$183:$AB$183) -> -0.072318713 | Q39: =SUM(SAP_Speadsheet!$AC$183:$AN$183) -> 0 | R39: =SUM(SAP_Speadsheet!$AO$183:$AZ$183) -> 0 | S39: =SUM(SAP_Speadsheet!$BA$183:$BF$183) -> 0 | T39: =N39/$E$14*12/$N$29 -> -0.29328614 | U39: =N39/$E$10 -> -0.15370238
C40: Monthly fee | F40: %monthly per ticketsize | K40: OPEX | N40: =SUM(O40:S40) -> -1.051908 | O40: =+SUM(O41,O45,O48,O52) -> -1.0208987 | P40: =+SUM(P41,P45,P48,P52) -> -0.03100928 | Q40: =+SUM(Q41,Q45,Q48,Q52) -> 0 | R40: =+SUM(R41,R45,R48,R52) -> 0 | S40: =+SUM(S41,S45,S48,S52) -> 0 | T40: =N40/$E$14*12/$N$29 -> -0.12406027 | U40: =N40/$E$10 -> -0.065016228
B41: COST INPUT | H41: Cur: mVND | K41: Acquisition cost | N41: =SUM(O41:S41) -> -0.38973564 | O41: =SUM(O42:O44) -> -0.4343572 | P41: =SUM(P42:P44) -> 0.044621561 | Q41: =SUM(Q42:Q44) -> 0 | R41: =SUM(R42:R44) -> 0 | S41: =SUM(S42:S44) -> 0 | T41: =N41/$E$14*12/$N$29 -> -0.045964769 | U41: =N41/$E$10 -> -0.024088743
K42: Lead Acquisition | N42: =SUM(O42:S42) -> 0 | O42: =SUM(SAP_Speadsheet!$E$73:$P$73) -> 0 | P42: =SUM(SAP_Speadsheet!$Q$73:$AB$73) -> 0 | Q42: =SUM(SAP_Speadsheet!$AC$73:$AN$73) -> 0 | R42: =SUM(SAP_Speadsheet!$AO$73:$AZ$73) -> 0 | S42: =SUM(SAP_Speadsheet!$BA$73:$BF$73) -> 0 | T42: =N42/$E$14*12/$N$29 -> 0 | U42: =N42/$E$10 -> 0
B43: Inflation rate | E43: 0.035 | F43: % per year | K43: Sharing performance | N43: =SUM(O43:S43) -> -0.3254024 | O43: =SUM(SAP_Speadsheet!$E$74:$P$74) -> -0.37002396 | P43: =SUM(SAP_Speadsheet!$Q$74:$AB$74) -> 0.044621561 | Q43: =SUM(SAP_Speadsheet!$AC$74:$AN$74) -> 0 | R43: =SUM(SAP_Speadsheet!$AO$74:$AZ$74) -> 0 | S43: =SUM(SAP_Speadsheet!$BA$74:$BF$74) -> 0 | T43: =N43/$E$14*12/$N$29 -> -0.038377415 | U43: =N43/$E$10 -> -0.020112441
K44: Marketing | N44: =SUM(O44:S44) -> -0.064333234 | O44: =SUM(SAP_Speadsheet!$E$86:$P$86) -> -0.064333234 | P44: =SUM(SAP_Speadsheet!$Q$86:$AB$86) -> 0 | Q44: =SUM(SAP_Speadsheet!$AC$86:$AN$86) -> 0 | R44: =SUM(SAP_Speadsheet!$AO$86:$AZ$86) -> 0 | S44: =SUM(SAP_Speadsheet!$BA$86:$BF$86) -> 0 | T44: =N44/$E$14*12/$N$29 -> -0.007587354 | U44: =N44/$E$10 -> -0.0039763024
B45: Acquisition cost | K45: UW & Disbursal | N45: =SUM(O45:S45) -> -0.066756457 | O45: =SUM(O46:O47) -> -0.066756457 | P45: =SUM(P46:P47) -> 0 | Q45: =SUM(Q46:Q47) -> 0 | R45: =SUM(R46:R47) -> 0 | S45: =SUM(S46:S47) -> 0 | T45: =N45/$E$14*12/$N$29 -> -0.0078731449 | U45: =N45/$E$10 -> -0.0041260768
C46: Sale incentive | E46: Auto MODE | K46: Underwriting | N46: =SUM(O46:S46) -> -0.062756457 | O46: =SUM(SAP_Speadsheet!$E$89:$P$89) -> -0.062756457 | P46: =SUM(SAP_Speadsheet!$Q$89:$AB$89) -> 0 | Q46: =SUM(SAP_Speadsheet!$AC$89:$AN$89) -> 0 | R46: =SUM(SAP_Speadsheet!$AO$89:$AZ$89) -> 0 | S46: =SUM(SAP_Speadsheet!$BA$89:$BF$89) -> 0 | T46: =N46/$E$14*12/$N$29 -> -0.0074013916 | U46: =N46/$E$10 -> -0.0038788451
C47: Sharing TOI and Risk DPD90+ | E47: =DATA!D58 -> 0.23097591 | F47: % per month | K47: Disbursement | N47: =SUM(O47:S47) -> -0.004 | O47: =SUM(SAP_Speadsheet!$E$90:$P$90) -> -0.004 | P47: =SUM(SAP_Speadsheet!$Q$90:$AB$90) -> 0 | Q47: =SUM(SAP_Speadsheet!$AC$90:$AN$90) -> 0 | R47: =SUM(SAP_Speadsheet!$AO$90:$AZ$90) -> 0 | S47: =SUM(SAP_Speadsheet!$BA$90:$BF$90) -> 0 | T47: =N47/$E$14*12/$N$29 -> -0.00047175331 | U47: =N47/$E$10 -> -0.00024723162
C48: Sharing TOI and Risk DPD180+ | F48: % per month | K48: Collection & after sale service | N48: =SUM(O48:S48) -> -0.098911856 | O48: =SUM(O49:O51) -> -0.080561609 | P48: =SUM(P49:P51) -> -0.018350247 | Q48: =SUM(Q49:Q51) -> 0 | R48: =SUM(R49:R51) -> 0 | S48: =SUM(S49:S51) -> 0 | T48: =N48/$E$14*12/$N$29 -> -0.011665499 | U48: =N48/$E$10 -> -0.0061135347
E49: Adjust MODE | K49: Early collections | N49: =SUM(O49:S49) -> -0.089243031 | O49: =SUM(SAP_Speadsheet!$E$96:$P$96) -> -0.072003528 | P49: =SUM(SAP_Speadsheet!$Q$96:$AB$96) -> -0.017239503 | Q49: =SUM(SAP_Speadsheet!$AC$96:$AN$96) -> 0 | R49: =SUM(SAP_Speadsheet!$AO$96:$AZ$96) -> 0 | S49: =SUM(SAP_Speadsheet!$BA$96:$BF$96) -> 0 | T49: =N49/$E$14*12/$N$29 -> -0.010525174 | U49: =N49/$E$10 -> -0.0055159248
C50: Sharing CII (only) | F50: % per month | K50: AMC | N50: =SUM(O50:S50) -> 0 | O50: =SUM(SAP_Speadsheet!$E$97:$P$97) -> 0 | P50: =SUM(SAP_Speadsheet!$Q$97:$AB$97) -> 0 | Q50: =SUM(SAP_Speadsheet!$AC$97:$AN$97) -> 0 | R50: =SUM(SAP_Speadsheet!$AO$97:$AZ$97) -> 0 | S50: =SUM(SAP_Speadsheet!$BA$97:$BF$97) -> 0 | T50: =N50/$E$14*12/$N$29 -> 0 | U50: =N50/$E$10 -> 0
C51: Sharing COF (only) | F51: % per month | K51: Aftersale service | N51: =SUM(O51:S51) -> -0.0096688256 | O51: =SUM(SAP_Speadsheet!$E$99:$P$99) -> -0.0085580818 | P51: =SUM(SAP_Speadsheet!$Q$99:$AB$99) -> -0.0011107438 | Q51: =SUM(SAP_Speadsheet!$AC$99:$AN$99) -> 0 | R51: =SUM(SAP_Speadsheet!$AO$99:$AZ$99) -> 0 | S51: =SUM(SAP_Speadsheet!$BA$99:$BF$99) -> 0 | T51: =N51/$E$14*12/$N$29 -> -0.0011403251 | U51: =N51/$E$10 -> -0.00059760986
C52: Sharing NFI (only) | F52: % per month | K52: Supporting Units | N52: =SUM(O52:S52) -> -0.49650401 | O52: =SUM(O53:O56) -> -0.43922342 | P52: =SUM(P53:P56) -> -0.057280595 | Q52: =SUM(Q53:Q56) -> 0 | R52: =SUM(R53:R56) -> 0 | S52: =SUM(S53:S56) -> 0 | T52: =N52/$E$14*12/$N$29 -> -0.058556853 | U52: =N52/$E$10 -> -0.030687873
C53: Sharing Risk DPD90+ (Only) | F53: % per month | K53: Direct HR | N53: =SUM(O53:S53) -> -0.096120874 | O53: =SUM(SAP_Speadsheet!$E$104:$P$104) -> -0.085031616 | P53: =SUM(SAP_Speadsheet!$Q$104:$AB$104) -> -0.011089257 | Q53: =SUM(SAP_Speadsheet!$AC$104:$AN$104) -> 0 | R53: =SUM(SAP_Speadsheet!$AO$104:$AZ$104) -> 0 | S53: =SUM(SAP_Speadsheet!$BA$104:$BF$104) -> 0 | T53: =N53/$E$14*12/$N$29 -> -0.011336335 | U53: =N53/$E$10 -> -0.0059410299
C54: Sharing Risk DPD180+ (only) | F54: % per month | K54: Indiect HR | N54: =SUM(O54:S54) -> -0.15610391 | O54: =SUM(SAP_Speadsheet!$E$105:$P$105) -> -0.13809454 | P54: =SUM(SAP_Speadsheet!$Q$105:$AB$105) -> -0.018009371 | Q54: =SUM(SAP_Speadsheet!$AC$105:$AN$105) -> 0 | R54: =SUM(SAP_Speadsheet!$AO$105:$AZ$105) -> 0 | S54: =SUM(SAP_Speadsheet!$BA$105:$BF$105) -> 0 | T54: =N54/$E$14*12/$N$29 -> -0.018410634 | U54: =N54/$E$10 -> -0.0096484557
C55: Risk share from | F55: disbursement | K55: IT | N55: =SUM(O55:S55) -> -0.12101049 | O55: =SUM(SAP_Speadsheet!$E$106:$P$106) -> -0.10704977 | P55: =SUM(SAP_Speadsheet!$Q$106:$AB$106) -> -0.013960719 | Q55: =SUM(SAP_Speadsheet!$AC$106:$AN$106) -> 0 | R55: =SUM(SAP_Speadsheet!$AO$106:$AZ$106) -> 0 | S55: =SUM(SAP_Speadsheet!$BA$106:$BF$106) -> 0 | T55: =N55/$E$14*12/$N$29 -> -0.014271775 | U55: =N55/$E$10 -> -0.007479405
C56: Partner Lead Acquistion | F56: per account | K56: Other support units | N56: =SUM(O56:S56) -> -0.12326874 | O56: =SUM(SAP_Speadsheet!$E$107:$P$107) -> -0.10904749 | P56: =SUM(SAP_Speadsheet!$Q$107:$AB$107) -> -0.014221248 | Q56: =SUM(SAP_Speadsheet!$AC$107:$AN$107) -> 0 | R56: =SUM(SAP_Speadsheet!$AO$107:$AZ$107) -> 0 | S56: =SUM(SAP_Speadsheet!$BA$107:$BF$107) -> 0 | T56: =N56/$E$14*12/$N$29 -> -0.014538109 | U56: =N56/$E$10 -> -0.0076189827
F57: per ticketsize | K57: PBT | N57: =SUM(O57:S57) -> 0.41881959 | O57: =SUM(SAP_Speadsheet!$E$189:$P$189) -> 0.47148301 | P57: =SUM(SAP_Speadsheet!$Q$189:$AB$189) -> -0.052663414 | Q57: =SUM(SAP_Speadsheet!$AC$189:$AN$189) -> 0 | R57: =SUM(SAP_Speadsheet!$AO$189:$AZ$189) -> 0 | S57: =SUM(SAP_Speadsheet!$BA$189:$BF$189) -> 0 | T57: =N57/$E$14*12/$N$29 -> 0.049394883 | U57: =N57/$E$10 -> 0.025886362
C59: Marketing cost
C61: Marketing cost | E61: =DATA!C41 -> 0.064333234 | F61: per account
B63: UW & Disbursal | C63: Underwriting cost & Score | E63: =DATA!C42*Leadsheet!E66*Leadsheet!E67 -> 0.015432064 | F63: of application
A64: Inflation | C64: DOP cost | F64: of account
C65: Disbursement cost | E65: 0.004 | F65: of account
A66: Incentive | C66: Approval rate | E66: =DATA!E4 -> 0.282 | F66: of submitted application
A67: Sale team | C67: Disbursement rate | E67: =DATA!E5 -> 0.872 | F67: of aproved application
A68: Sale Mgt
A69: MA
B71: Collection & AMC | C71: Collections_all | E71: =DATA!C43 -> 0.008 | F71: per account/month
C72: Collections_B1+ | F72: per account/month
C73: AMC_principal collected | F73: per 1mVND collected amount
C74: AMC_interest collected | F74: per 1mVND collected amount
C75: AMC_penalty collected | F75: per 1mVND collected amount
B77: Aftersale service
C78: Email & SMS | E78: 0.001 | F78: per account/month
A79: CPCUW
A80: CPCUW_SCORE
A81: CPCCA | B81: Supporting units | C81: Direct HR | E81: 0.0094474945 | F81: per account/month
A82: Approval rate | C82: Indirect HR | E82: 0.015343086 | F82: per account/month
C83: IT | E83: 0.011893836 | F83: per account/month
C84: Other supports | E84: 0.012115794 | F84: per account/month
A86: AMC_PR
B88: RISK INPUT
B90: Net flow | D90: NF | E90: PD | F90: Pro. Rate
C91: B0 - B1 | D91: =DATA!G118 -> 0.051 | E91: =PRODUCT(D91:$D$104) -> 0.028694638 | F91: =E91*(1-$E$110)*(1-$E$111)*(1-$E$112)*(1-$E$113) -> 0.02700992
C92: B1 - B2 | D92: =DATA!G119 -> 0.67035902 | E92: =PRODUCT(D92:$D$104) -> 0.56263997 | F92: =E92*(1-$E$110)*(1-$E$111)*(1-$E$112)*(1-$E$113) -> 0.52960627
C93: B2 - B3 | D93: =DATA!G120 -> 0.91 | E93: =PRODUCT(D93:$D$104) -> 0.83931141 | F93: =E93*(1-$E$110)*(1-$E$111)*(1-$E$112)*(1-$E$113) -> 0.79003379
C94: B3 - B4 | D94: =DATA!G121 -> 0.99718579 | E94: =PRODUCT(D94:$D$104) -> 0.92232023 | F94: =E94*(1-$E$110)*(1-$E$111)*(1-$E$112)*(1-$E$113) -> 0.868169
C95: B4 - B5 | D95: =DATA!G122 -> 0.97298881 | E95: =PRODUCT(D95:$D$104) -> 0.92492316 | F95: =E95*(1-$E$110)*(1-$E$111)*(1-$E$112)*(1-$E$113) -> 0.87061911
C96: B5 - B6 | D96: =DATA!G123 -> 1 | E96: =PRODUCT(D96:$D$104) -> 0.9506 | F96: =E96*(1-$E$110)*(1-$E$111)*(1-$E$112)*(1-$E$113) -> 0.89478841
C97: B6 - B7 | D97: =DATA!G124 -> 0.97 | E97: =PRODUCT(D97:$D$104) -> 0.9506 | F97: =E97*(1-$E$110)*(1-$E$111)*(1-$E$112)*(1-$E$113) -> 0.89478841
C98: B7 - B8 | D98: =DATA!G125 -> 0.98 | E98: =PRODUCT(D98:$D$104) -> 0.98 | F98: =E98*(1-$E$110)*(1-$E$111)*(1-$E$112)*(1-$E$113) -> 0.92246228
C99: B8 - B9 | D99: =DATA!G126 -> 1 | E99: =PRODUCT(D99:$D$104) -> 1 | F99: =E99*(1-$E$111)*(1-$E$112)*(1-$E$113) -> 0.960498
C100: B9 - B10 | D100: 1 | E100: =PRODUCT(D100:$D$104) -> 1 | F100: =E100*(1-$E$111)*(1-$E$112)*(1-$E$113) -> 0.960498
C101: B10 - B11 | D101: 1 | E101: =PRODUCT(D101:$D$104) -> 1 | F101: =E101*(1-$E$111)*(1-$E$112)*(1-$E$113) -> 0.960498
C102: B11 - B12 | D102: 1 | E102: =PRODUCT(D102:$D$104) -> 1 | F102: =E102*(1-$E$111)*(1-$E$112)*(1-$E$113) -> 0.960498
C103: B12 - B13 | D103: 1 | E103: =PRODUCT(D103:$D$104) -> 1 | F103: =E103*(1-$E$111)*(1-$E$112)*(1-$E$113) -> 0.960498
C104: B13-B24 | F104: =(1-$E$111)*(1-$E$112)*(1-$E$113) -> 0.960498
C105: B25-B36 | F105: =(1-$E$112)*(1-$E$113) -> 0.9801
A106: Recovery rate B13-B24 | C106: B36+ | F106: =(1-$E$113) -> 0.99
A107: Recovery rate B24-B36 | C107: Risk cost/ Disburse | D107: =N39/E10 -> -0.15370238
A108: Recovery rate B36+ | C108: Riskcost/ANR | D108: =T39 -> -0.29328614
B110: Recovery rate | C110: B8- B12 | E110: 0.02
C111: B13-B24 | D111: Recovery rate B13-B24 | E111: 0.02
C112: B24-B36 | D112: Recovery rate B24-B36 | E112: 0.01
...

Sheet COF
E1: =SUBTOTAL(9,E3:E43) -> 301221724219420 | F1: =SUBTOTAL(9,F3:F43) -> 5.699521e+10 | H1: =F1/E1*365 -> 0.069062919 | J1: 0.069062919
E2: =SUM(E4:E42) -> 348822682508025 | F2: =SUM(F4:F42) -> 6.3783621e+10 | H2: =SUM(H4:H42) -> 1173
B3: Nhom | C3: SP | D3: pl | E3: Sum of BALANCE | F3: Sum of Lai DCV | G3: Month | H3: Day
B4: UPL | C4: cl | D4: BE CASHLOAN | E4: 175237237692 | F4: 35108054 | G4: 9 | H4: 30
B5: UPL | C5: cl | D5: CAKE CASHLOAN | E5: 45792086198052 | F5: 8.8220401e+09 | G5: 9 | H5: 30
B6: UPL | C6: OD | D6: CAKE OVERDRAFT | E6: 7169005435909 | F6: 9.9109849e+08 | G6: 9 | H6: 30
B7: UPL | C7: PD | D7: CAKE PAYDAY | E7: 3672603510227 | F7: 5.4667902e+08 | G7: 9 | H7: 30
B8: UPL | C8: cl | D8: MWG CASHLOAN | E8: 7860835561894 | F8: 1.5211837e+09 | G8: 9 | H8: 30
B9: UPL | C9: cl | D9: NGS CASHLOAN | E9: 530282165595 | F9: 1.1619612e+08 | G9: 9 | H9: 30
B10: UPL | C10: cl | D10: VIETTEL CASHLOAN | E10: 47500871433668 | F10: 9.1994775e+09 | G10: 9 | H10: 30
B11: UPL | C11: PD | D11: VIETTEL PAYDAY | E11: 6555226346162 | F11: 1.021781e+09 | G11: 9 | H11: 30
B12: UPL | C12: PD | D12: VIETTEL PAYDAYPAYROLL | E12: 25934847005 | F12: 3828070.8 | G12: 9 | H12: 30
B13: UPL | C13: cl | D13: VIETTEL PAYROLL CASHLOAN | E13: 234239258102 | F13: 44742343 | G13: 9 | H13: 30
B14: UPL | C14: cl | D14: VNPAY CASHLOAN | E14: 2538375718443 | F14: 4.6902939e+08 | G14: 9 | H14: 30
B15: UPL | C15: cl | D15: VNPOST CASHLOAN | E15: 74534379401 | F15: 14917048 | G15: 9 | H15: 30
... B42: UPL | C42: cl | D42: Zalopay CASHLOAN | E42: 3450971717669 | F42: 6.384429e+08 | G42: 7 | H42: 31

Sheet DATA
B2: 1 | C2: Aproval rate, signed rate
C4: aprroval rate | E4: 0.282
C5: Signed rate | E5: 0.872
B14: 2 | C14: Disburse, Tenor, Insurance, IR
C16: Disburse date | D16: # Disburse | E16: Disburse amount (VND) | F16: Current balance (VND) | G16: Ticket size (VND) | H16: Avg tenor (Month) | I16: Avg IR (%) | J16: Insurance fee (VND) | K16: % Insurance penetration by date
C17: 45901 | D17: 64399 | E17: 1159826780000 | F17: 975998286085 | G17: 18010012 | H17: 16.439712 | I17: 0.510707 | J17: 60006780000 | K17: 0.78936008 | L17: =E17-J17 -> 1099820000000
C18: 45870 | D18: 55372 | E18: 847454320000 | F18: 634711890892 | G18: 15304745 | H18: 14.340967 | I18: 0.51144044 | J18: 43161320000 | K18: 0.78330203 | L18: =E18-J18 -> 804293000000
C19: 45839 | D19: 60775 | E19: 913801540000 | F19: 618505332727 | G19: 15035813 | H19: 14.339729 | I19: 0.51137145 | J19: 46934540000 | K19: 0.78863019 | L19: =E19-J19 -> 866867000000
C20: AVG | E20: =SUM(E17:E19)/10^9 -> 2921.0826 | G20: =SUM(E17:E19)/SUM(D17:D19)/10^6 -> 16.17916 | H20: =ROUND(SUMPRODUCT(H17:H19,$E$17:$E$19)/SUM($E$17:$E$19),0) -> 15 | I20: =SUMPRODUCT(I17:I19,E17:E19)/SUM(E17:E19) -> 0.51112764 | J20: =SUM(J17:J19)/SUMPRODUCT(K17:K19,L17:L19) -> 0.068797748 | K20: =SUMPRODUCT(K17:K19,E17:E19)/SUM(E17:E19) -> 0.78737421
G21: adjust tenor | H21: 14
B24: 3 | C24: UW, collection, MKT
C28: Chanel | D28: Catergory | E28: 45809 | F28: 45839 | G28: 45870 | H28: 45901 | M28: 45809 | N28: 45839 | O28: 45870 | P28: 45901 | R28: Chanel | S28: Catergory | T28: 45809 | U28: 45839 | V28: 45870 | W28: 45901
C29: VDS | D29: new_account | E29: 17951 | F29: 25713 | G29: 23272 | H29: 26446 | K29: VDS | L29: active_account | M29: 130324 | N29: 138380 | O29: 143825 | P29: 150208 | R29: VDS | S29: disburse/spend | U29: 380965670000 | V29: 346289200000 | W29: 465278440000 | X29: =SUM(U29:W29) -> 1192533310000 | Y29: =X29/SUM($X$29:$X$37) -> 0.40825045
C30: VDS | D30: new_account | E30: 24 | F30: 52 | G30: 63 | H30: 59 | K30: VDS | L30: active_account | M30: 777 | N30: 769 | O30: 762 | P30: 743 | R30: VDS | S30: disburse/spend | U30: 809800000 | V30: 1040200000 | W30: 953500000 | X30: =SUM(U30:W30) -> 2803500000 | Y30: =X30/SUM($X$29:$X$37) -> 0.0009597469
C31: BEG | D31: new_account | E31: 4 | F31: 5 | G31: 1 | H31: 3 | K31: BEG | L31: active_account | M31: 1241 | N31: 1035 | O31: 852 | P31: 714 | R31: BEG | S31: disburse/spend | U31: 98750000 | V31: 18900000 | W31: 42000000 | X31: =SUM(U31:W31) -> 159650000 | Y31: =X31/SUM($X$29:$X$37) -> 5.4654393e-05
C32: NGS | D32: new_account | K32: NGS | L32: active_account | M32: 3581 | N32: 2876 | O32: 2390 | P32: 2116 | R32: NGS | S32: disburse/spend | X32: =SUM(U32:W32) -> 0 | Y32: =X32/SUM($X$29:$X$37) -> 0
C33: CAKE | D33: new_account | E33: 18609 | F33: 24183 | G33: 21277 | H33: 25356 | K33: CAKE | L33: active_account | M33: 107363 | N33: 119486 | O33: 128198 | P33: 138424 | R33: CAKE | S33: disburse/spend | U33: 377695150000 | V33: 338629710000 | W33: 486195060000 | X33: =SUM(U33:W33) -> 1202519920000 | Y33: =X33/SUM($X$29:$X$37) -> 0.41166926
C34: MWG | D34: new_account | E34: 2611 | F34: 3066 | G34: 3734 | H34: 5548 | K34: MWG | L34: active_account | M34: 11727 | N34: 14390 | O34: 17656 | P34: 22600 | R34: MWG | S34: disburse/spend | U34: 52339690000 | V34: 63562000000 | W34: 100769400000 | X34: =SUM(U34:W34) -> 216671090000 | Y34: =X34/SUM($X$29:$X$37) -> 0.074174926
C35: VNPAY | D35: new_account | E35: 1354 | F35: 1192 | G35: 1135 | H35: 1479 | K35: VNPAY | L35: active_account | M35: 7123 | N35: 8013 | O35: 8674 | P35: 9522 | R35: VNPAY | S35: disburse/spend | U35: 13288530000 | V35: 13484550000 | W35: 21050400000 | X35: =SUM(U35:W35) -> 47823480000 | Y35: =X35/SUM($X$29:$X$37) -> 0.016371834
C36: ZALOPAY | D36: new_account | E36: 4759 | F36: 6515 | G36: 5840 | H36: 5356 | K36: ZALOPAY | L36: active_account | M36: 7243 | N36: 13144 | O36: 17888 | P36: 21762 | R36: ZALOPAY | S36: disburse/spend | U36: 87997150000 | V36: 83818310000 | W36: 83034230000 | X36: =SUM(U36:W36) -> 254849690000 | Y36: =X36/SUM($X$29:$X$37) -> 0.087244944
C37: VNPOST | D37: new_account | E37: 46 | F37: 49 | G37: 50 | H37: 152 | K37: VNPOST | L37: active_account | M37: 55 | N37: 103 | O37: 152 | P37: 301 | R37: VNPOST | S37: disburse/spend | U37: 606800000 | V37: 611450000 | W37: 2503750000 | X37: =SUM(U37:W37) -> 3722000000 | Y37: =X37/SUM($X$29:$X$37) -> 0.0012741851
E38: =SUM(E29:E37) -> 45358 | F38: =SUM(F29:F37) -> 60775 | G38: =SUM(G29:G37) -> 55372 | H38: =SUM(H29:H37) -> 64399 | M38: =SUM(M29:M37) -> 269434 | N38: =SUM(N29:N37) -> 298196 | O38: =SUM(O29:O37) -> 320397 | P38: =SUM(P29:P37) -> 346390 | U38: =SUM(U29:U37) -> 913801540000 | V38: =SUM(V29:V37) -> 847454320000 | W38: =SUM(W29:W37) -> 1159826780000
C41: =SUM(F41:H41)/SUM(F38:H38)/10^6 -> 0.064333234 | D41: marketing_acquisition_cost | F41: 5215708344 | G41: 4069855327 | H41: 2329544305
C42: =SUM(F42:H42)/SUM(F38:H38)/10^6 -> 0.062756457 | D42: Underwriting | F42: 2.8988283e+09 | G42: 3959670920 | H42: 4471927973
C43: 0.008 | D43: Collection | F43: 995176950 | G43: 1.0483845e+09 | H43: 1.2973813e+09 | I43: (Chi phi Q3 không đầy đủ do chuyển đổi hệ thống)
B47: 4 | C47: Partner acquisition cost | D47: (tính theo tỉ lệ giải ngân)
D48: Sharing TOI | E48: Leadgen
C49: VDS | D49: 0.5 | E49: 0
C50: VDS | D50: 0.5 | E50: 0
C51: BEG | D51: 0.5 | E51: 0
C52: NGS | D52: 0.35 | E52: 0
C53: CAKE | D53: 0 | E53: 0
C54: MWG | D54: 0.35 | E54: 0.005
C55: VNPAY | E55: 0.02
C56: ZALOPAY | E56: 0.025
C57: VNPOST | D57: 0.3 | E57: 0
C58: AVERAGE | D58: =SUMPRODUCT(D49:D57,X29:X37)/SUM(X29:X37) -> 0.23097591 | E58: =SUMPRODUCT(E49:E57,X29:X37)/SUM(X29:X37) -> 0.0028794349
B60: 5
C61: CAKE
C62: From | D62: To | E62: Penalty fee | F62: Penalty IR | G62: %Attrition | J62: From | K62: To | L62: Penalty fee | M62: Penalty IR | N62: %Attrition | Q62: From | R62: To | S62: Penalty fee | T62: Penalty IR | U62: %Attrition
B63: VDS | C63: 1 | D63: 1 | E63: 0.08 | G63: 0.12 | I63: VDS | J63: 2 | K63: 3 | L63: 0.08 | N63: 0.045 | P63: VDS | Q63: 4 | R63: 14 | S63: 0.05 | U63: 0.028
B64: VDS | C64: 1 | D64: 1 | E64: 0.08 | G64: 0.12 | I64: VDS | J64: 2 | K64: 3 | L64: 0.08 | N64: 0.06 | P64: VDS | Q64: 4 | R64: 14 | S64: 0.05 | U64: 0.025
B65: CAKE | C65: 1 | D65: 1 | E65: 0.08 | G65: 0.12 | I65: CAKE | J65: 2 | K65: 3 | L65: 0.08 | N65: 0.045 | P65: CAKE | Q65: 4 | R65: 14 | S65: 0.05 | U65: 0.018
B66: MWG | C66: 1 | D66: 1 | E66: 0.08 | G66: 0.12 | I66: MWG | J66: 2 | K66: 3 | L66: 0.08 | N66: 0.06 | P66: MWG | Q66: 4 | R66: 14 | S66: 0.05 | U66: 0.025
B67: VNPAY | C67: 1 | D67: 1 | E67: 0.08 | G67: 0.08 | I67: VNPAY | J67: 2 | K67: 3 | L67: 0.08 | N67: 0.06 | P67: VNPAY | Q67: 4 | R67: 14 | S67: 0.05 | U67: 0.025
B68: ZaloPAY | C68: 1 | D68: 1 | E68: 0.03 | G68: 0.08 | I68: ZaloPAY | J68: 2 | K68: 3 | L68: 0.03 | N68: 0.06 | P68: ZaloPAY | Q68: 4 | R68: 14 | S68: 0.03 | U68: 0.025
B72: VDS | C72: 1192533310000 | E72: Penalty fee | F72: Penalty IR | G72: %Attrition
B73: VDS | C73: 2803500000 | D73: 1 | E73: =SUMPRODUCT(E63:E68,$C$72:$C$77)/SUM($C$72:$C$77) -> 0.075631948 | G73: =SUMPRODUCT(G63:G68,$C$72:$C$77)/SUM($C$72:$C$77) -> 0.11584981
B74: CAKE | C74: 1202519920000 | D74: 2-3 | E74: =SUMPRODUCT(L63:L68,$C$72:$C$77)/SUM($C$72:$C$77) -> 0.075631948 | G74: =SUMPRODUCT(N63:N68,$C$72:$C$77)/SUM($C$72:$C$77) -> 0.047684839
B75: MWG | C75: 216671090000 | D75: other | E75: =SUMPRODUCT(S63:S68,$C$72:$C$77)/SUM($C$72:$C$77) -> 0.048252779 | G75: =SUMPRODUCT(U63:U68,$C$72:$C$77)/SUM($C$72:$C$77) -> 0.023340862
B76: VNPAY | C76: 47823480000
B77: ZaloPAY | C77: 254849690000
B79: 5 | C79: RR
C83: Sum of principal_balance_at_report_month | D83: Column Labels
C84: Row Labels | D84: 202506 | E84: 202507 | F84: 202508 | G84: 202509 | H84: Grand Total
C85: 0 | D85: 2227170638646 | E85: 2678490554874 | F85: 2995257670063 | G85: 3525599566229 | H85: 11426518429812
C86: 1 | D86: 106807795863 | E86: 104459872089 | F86: 135744014157 | G86: 173589291968 | H86: 520600974077
C87: 2 | D87: 57958242199 | E87: 68528948674 | F87: 71524973797 | G87: 92951340535 | H87: 290963505205
C88: 3 | D88: 46220122367 | E88: 50991182415 | F88: 63042309190 | G88: 67300977396 | H88: 227554591368
C89: 4 | D89: 42427950160 | E89: 46997805330 | F89: 51301182602 | G89: 61066073693 | H89: 201793011785
C90: 5 | D90: 51506266743 | E90: 40402005892 | F90: 46266352135 | G90: 50392136121 | H90: 188566760891
C91: 6 | D91: 36271430125 | E91: 53548682057 | F91: 39845322295 | G91: 45566486496 | H91: 175231920973
C92: 7 | D92: 40846476885 | E92: 33460456609 | F92: 54576830011 | G92: 39636683707 | H92: 168520447212
C93: 8 | D93: 44360929585 | E93: 41716545845 | F93: 31732866197 | G93: 54110235723 | H93: 171920577350
C94: 9 | D94: 40163098197 | E94: 45373137792 | F94: 41396389450 | G94: 31732866197 | H94: 158665491636
C95: 10 | D95: 37879942573 | E95: 39017936400 | F95: 44047941303 | G95: 41396068450 | H95: 162341888726
C96: 11 | D96: 34961115219 | E96: 36526849931 | F96: 40648759997 | G96: 44044905995 | H96: 156181631142
... C109: 24 | D109: 11550000 | E109: 6537688481 | F109: 7555829276 | G109: 6250770622 | H109: 20355838379
C110: 25 | E110: 66149400 | F110: 7495709672 | G110: 7555829276 | H110: 15117688348
C111: 26 | F111: 232734400 | G111: 7495709672 | H111: 7728444072
C112: 27 | G112: 232734400 | H112: 232734400
C113: Grand Total | D113: 2890952972498 | E113: 3401349818415 | F113: 3814909653338 | G113: 4467560434648 | H113: 14574772878899
B117: Row Labels | C117: 7 | D117: 8 | E117: 9 | F117: AVG | G117: ADJ | H117: 202506 | I117: 202507 | J117: 202508 | K117: 202509 | N117: EOM Bucket | O117: report_month | P117: principal_balance_at_report_month
B118: 0 | C118: =I119/H118 -> 0.046902501 | D118: =J119/I118 -> 0.050679295 | E118: =K119/J118 -> 0.057954711 | F118: =AVERAGE(C118:E118) -> 0.051845502 | G118: 0.051 | H118: 2227170638646 | I118: 2678490554874 | J118: 2995257670063 | K118: 3525599566229 | N118: 0 | O118: 202510 | P118: 3779547383680
B119: 1 | C119: =I120/H119 -> 0.64160999 | D119: =J120/I119 -> 0.68471244 | E119: =K120/J119 -> 0.68475462 | F119: =AVERAGE(C119:E119) -> 0.67035902 | G119: =F119 -> 0.67035902 | H119: 106807795863 | I119: 104459872089 | J119: 135744014157 | K119: 173589291968 | N119: 0 | O119: 202504 | P119: 1807299742573
B120: 2 | C120: =I121/H120 -> 0.87979173 | D120: =J121/I120 -> 0.91993691 | E120: =K121/J120 -> 0.94094375 | F120: =AVERAGE(C120:E120) -> 0.91355747 | G120: 0.91 | H120: 57958242199 | I120: 68528948674 | J120: 71524973797 | K120: 92951340535 | N120: 0 | O120: 202409 | P120: 1106960755025
B121: 3 | C121: =I122/H121 -> 1.0168256 | D121: =J122/I121 -> 1.0060795 | E121: =K122/J121 -> 0.96865223 | F121: =AVERAGE(C121:E121) -> 0.99718579 | G121: =F121 -> 0.99718579 | H121: 46220122367 | I121: 50991182415 | J121: 63042309190 | K121: 67300977396 | N121: 0 | O121: 202410 | P121: 1248622751759
B122: 4 | C122: =I123/H122 -> 0.95224977 | D122: =J123/I122 -> 0.98443644 | E122: =K123/J122 -> 0.9822802 | F122: =AVERAGE(C122:E122) -> 0.97298881 | G122: =F122 -> 0.97298881 | H122: 42427950160 | I122: 46997805330 | J122: 51301182602 | K122: 61066073693 | N122: 0 | O122: 202508 | P122: 2995257670063
B123: 5 | C123: =I124/H123 -> 1.0396537 | D123: =J124/I123 -> 0.98622139 | E123: =K124/J123 -> 0.98487312 | F123: =AVERAGE(C123:E123) -> 1.0035827 | G123: 1 | H123: 51506266743 | I123: 40402005892 | J123: 46266352135 | K123: 50392136121 | N123: 0 | O123: 202501 | P123: 1573077129141
B124: 6 | C124: =I125/H124 -> 0.92250172 | D124: =J125/I124 -> 1.0192002 | E124: =K125/J124 -> 0.99476379 | F124: =AVERAGE(C124:E124) -> 0.97882192 | G124: 0.97 | H124: 36271430125 | I124: 53548682057 | J124: 39845322295 | K124: 45566486496 | N124: 0 | O124: 202509 | P124: 3525599566229
B125: 7 | C125: =I126/H125 -> 1.021301 | D125: =J126/I125 -> 0.94836919 | E125: =K126/J125 -> 0.99145069 | F125: =AVERAGE(C125:E125) -> 0.98704028 | G125: 0.98 | H125: 40846476885 | I125: 33460456609 | J125: 54576830011 | K125: 39636683707 | N125: 0 | O125: 202408 | P125: 975380154984
B126: 8 | C126: =I127/H126 -> 1.0228176 | D126: =J127/I126 -> 0.99232543 | E126: =K127/J126 -> 1 | F126: =AVERAGE(C126:E126) -> 1.0050477 | G126: 1 | H126: 44360929585 | I126: 41716545845 | J126: 31732866197 | K126: 54110235723 | N126: 0 | O126: 202412 | P126: 1441984934899
B127: 9 | C127: =I128/H127 -> 0.97148721 | D127: =J128/I127 -> 0.97079337 | E127: =K128/J127 -> 0.99999225 | H127: 40163098197 | I127: 45373137792 | J127: 41396389450 | K127: 31732866197 | N127: 0 | O127: 202312 | P127: 260794942129
B128: 10 | C128: =I129/H128 -> 0.96427944 | D128: =J129/I128 -> 1.0417968 | E128: =K129/J128 -> 0.99993109 | H128: 37879942573 | I128: 39017936400 | J128: 44047941303 | K128: 41396068450 | N128: 0 | O128: 202403 | P128: 326805264954
B129: 11 | C129: =I130/H129 -> 1.0124011 | D129: =J130/I129 -> 0.99108312 | E129: =K130/J129 -> 1 | H129: 34961115219 | I129: 36526849931 | J129: 40648759997 | K129: 44044905995 | N129: 0 | O129: 202309 | P129: 104850759423
B130: 12 | C130: =I131/H130 -> 1.062176 | D130: =J131/I130 -> 1.007204 | E130: =K131/J130 -> 1 | H130: 22717393827 | I130: 35394671659 | J130: 36201144523 | K130: 40648759997 | N130: 0 | O130: 202308 | P130: 71564310617
B131: 13 | D131: =J132/I131 -> 1.0511016 | E131: =K132/J131 -> 1 | H131: 13794323991 | I131: 24129869875 | J131: 35649654116 | K131: 36201144523 | N131: 0 | O131: 202502 | P131: 1504460906442
B132: 14 | E132: =K133/J132 -> 1 | H132: 9199022744 | I132: 13974222080 | J132: 25362944529 | K132: 35649654116 | N132: 0 | O132: 202503 | P132: 1631604760870
B133: 15 | H133: 9713452543 | I133: 9361358696 | J133: 13629862748 | K133: 25362944529 | N133: 0 | O133: 202311 | P133: 182020699242
H134: 8396129663 | I134: 10020947366 | J134: 9215914030 | K134: 13629862748 | N134: 0 | O134: 202405 | P134: 439305650323
H135: 12013452758 | I135: 8075921743 | J135: 9804510477 | K135: 9215914030 | N135: 0 | O135: 202401 | P135: 307474504926
H136: 11808943725 | I136: 11834374774 | J136: 8585903715 | K136: 9804510477 | N136: 0 | O136: 202310 | P136: 144269810181
H137: 8794083809 | I137: 11328250640 | J137: 11331098414 | K137: 8585903715 | N137: 0 | O137: 202307 | P137: 32839950000
H138: 7170428913 | I138: 9537181059 | J138: 11647337825 | K138: 11331098414 | N138: 0 | O138: 202411 | P138: 1334343401879
H139: 6337836660 | I139: 6975282473 | J139: 9917629149 | K139: 11647337825 | N139: 0 | O139: 202507 | P139: 2678490554874
H140: 7830057422 | I140: 6463543221 | J140: 6643998645 | K140: 9917629149 | N140: 0 | O140: 202506 | P140: 2227170638646
H141: 6592287881 | I141: 8136379040 | J141: 6250770622 | K141: 6643998645 | N141: 0 | O141: 202505 | P141: 2010292221460
H142: 11550000 | I142: 6537688481 | J142: 7555829276 | K142: 6250770622 | N142: 0 | O142: 202406 | P142: 617172076286
I143: 66149400 | J143: 7495709672 | K143: 7555829276 | N143: 0 | O143: 202404 | P143: 373997425567
J144: 232734400 | K144: 7495709672 | N144: 0 | O144: 202407 | P144: 847716536036
...

Sheet SAP_Speadsheet
B1: SAP Speadsheet
C4: Method
C5: Month on book | D5: 0 | E5: =D5+1 -> 1 | F5: =E5+1 -> 2 | G5: =F5+1 -> 3 | H5: =G5+1 -> 4 | I5: =H5+1 -> 5 | J5: =I5+1 -> 6 | K5: =J5+1 -> 7 | L5: =K5+1 -> 8 | ... BL5: =BK5+1 -> 60
C6: Oustanding tenor | D6: =IF(Leadsheet!$E$12-SAP_Speadsheet!D5<0,0,Leadsheet!$E$12-SAP_Speadsheet!D5) -> 14 | E6: =IF(Leadsheet!$E$12-SAP_Speadsheet!E5<0,0,Leadsheet!$E$12-SAP_Speadsheet!E5) -> 13 | F6: =IF(Leadsheet!$E$12-SAP_Speadsheet!F5<0,0,Leadsheet!$E$12-SAP_Speadsheet!F5) -> 12 | G6: =IF(Leadsheet!$E$12-SAP_Speadsheet!G5<0,0,Leadsheet!$E$12-SAP_Speadsheet!G5) -> 11 | H6: =IF(Leadsheet!$E$12-SAP_Speadsheet!H5<0,0,Leadsheet!$E$12-SAP_Speadsheet!H5) -> 10 | I6: =IF(Leadsheet!$E$12-SAP_Speadsheet!I5<0,0,Leadsheet!$E$12-SAP_Speadsheet!I5) -> 9 | J6: =IF(Leadsheet!$E$12-SAP_Speadsheet!J5<0,0,Leadsheet!$E$12-SAP_Speadsheet!J5) -> 8 | K6: =IF(Leadsheet!$E$12-SAP_Speadsheet!K5<0,0,Leadsheet!$E$12-SAP_Speadsheet!K5) -> 7 | ... BL6: =IF(Leadsheet!$E$12-SAP_Speadsheet!BL5<0,0,Leadsheet!$E$12-SAP_Speadsheet!BL5) -> 0
C7: Last month on book | D7: =Leadsheet!E13+Leadsheet!E12 -> 20
B9: Balance
B10: Interest rate
C11: INR rate | D11: =Leadsheet!E18 -> 0.49171714 | E11: =IF(E$5>$D$7,0,VLOOKUP(SAP_Speadsheet!E$5,Leadsheet!$C$18:$F$23,3,1)) -> 0.49171714 | F11: =IF(F$5>$D$7,0,VLOOKUP(SAP_Speadsheet!F$5,Leadsheet!$C$18:$F$23,3,1)) -> 0.49171714 | G11: =IF(G$5>$D$7,0,VLOOKUP(SAP_Speadsheet!G$5,Leadsheet!$C$18:$F$23,3,1)) -> 0.49171714 | H11: =IF(H$5>$D$7,0,VLOOKUP(SAP_Speadsheet!H$5,Leadsheet!$C$18:$F$23,3,1)) -> 0.49171714 | I11: =IF(I$5>$D$7,0,VLOOKUP(SAP_Speadsheet!I$5,Leadsheet!$C$18:$F$23,3,1)) -> 0.49171714 | J11: =IF(J$5>$D$7,0,VLOOKUP(SAP_Speadsheet!J$5,Leadsheet!$C$18:$F$23,3,1)) -> 0.49171714 | K11: =IF(K$5>$D$7,0,VLOOKUP(SAP_Speadsheet!K$5,Leadsheet!$C$18:$F$23,3,1)) -> 0.49171714 | L11: =IF(L$5>$D$7,0,VLOOKUP(SAP_Speadsheet!L$5,Leadsheet!$C$18:$F$23,3,1)) -> 0.49171714 | ... BL11: =IF(BL$5>$D$7,0,VLOOKUP(SAP_Speadsheet!BL$5,Leadsheet!$C$18:$F$23,3,1)) -> 0
C12: COF rate | D12: =Leadsheet!F18 -> 0.069062919 | E12: =IF(E$5>$D$7,0,VLOOKUP(SAP_Speadsheet!E$5,Leadsheet!$C$18:$F$23,4,1)) -> 0.069062919 | F12: =IF(F$5>$D$7,0,VLOOKUP(SAP_Speadsheet!F$5,Leadsheet!$C$18:$F$23,4,1)) -> 0.069062919 | G12: =IF(G$5>$D$7,0,VLOOKUP(SAP_Speadsheet!G$5,Leadsheet!$C$18:$F$23,4,1)) -> 0.069062919 | H12: =IF(H$5>$D$7,0,VLOOKUP(SAP_Speadsheet!H$5,Leadsheet!$C$18:$F$23,4,1)) -> 0.069062919 | I12: =IF(I$5>$D$7,0,VLOOKUP(SAP_Speadsheet!I$5,Leadsheet!$C$18:$F$23,4,1)) -> 0.069062919 | J12: =IF(J$5>$D$7,0,VLOOKUP(SAP_Speadsheet!J$5,Leadsheet!$C$18:$F$23,4,1)) -> 0.069062919 | K12: =IF(K$5>$D$7,0,VLOOKUP(SAP_Speadsheet!K$5,Leadsheet!$C$18:$F$23,4,1)) -> 0.069062919 | L12: =IF(L$5>$D$7,0,VLOOKUP(SAP_Speadsheet!L$5,Leadsheet!$C$18:$F$23,4,1)) -> 0.069062919 | ... BL12: =IF(BL$5>$D$7,0,VLOOKUP(SAP_Speadsheet!BL$5,Leadsheet!$C$18:$F$23,4,1)) -> 0
C13: Attrition rate | E13: =IF(E$5<Leadsheet!$E$12,VLOOKUP(SAP_Speadsheet!E$5,Leadsheet!$C$26:$G$30,5,1),0) -> 0.11584981 | F13: =IF(F$5<Leadsheet!$E$12,VLOOKUP(SAP_Speadsheet!F$5,Leadsheet!$C$26:$G$30,5,1),0) -> 0.047684839 | G13: =IF(G$5<Leadsheet!$E$12,VLOOKUP(SAP_Speadsheet!G$5,Leadsheet!$C$26:$G$30,5,1),0) -> 0.047684839 | H13: =IF(H$5<Leadsheet!$E$12,VLOOKUP(SAP_Speadsheet!H$5,Leadsheet!$C$26:$G$30,5,1),0) -> 0.023340862 | I13: =IF(I$5<Leadsheet!$E$12,VLOOKUP(SAP_Speadsheet!I$5,Leadsheet!$C$26:$G$30,5,1),0) -> 0.023340862 | J13: =IF(J$5<Leadsheet!$E$12,VLOOKUP(SAP_Speadsheet!J$5,Leadsheet!$C$26:$G$30,5,1),0) -> 0.023340862 | K13: =IF(K$5<Leadsheet!$E$12,VLOOKUP(SAP_Speadsheet!K$5,Leadsheet!$C$26:$G$30,5,1),0) -> 0.023340862 | L13: =IF(L$5<Leadsheet!$E$12,VLOOKUP(SAP_Speadsheet!L$5,Leadsheet!$C$26:$G$30,5,1),0) -> 0.023340862 | ... BL13: =IF(BL$5<Leadsheet!$E$12,VLOOKUP(SAP_Speadsheet!BL$5,Leadsheet!$C$26:$G$30,5,1),0) -> 0
C14: Prepayment Penalty | E14: =IF(E$5<Leadsheet!$E$12,VLOOKUP(SAP_Speadsheet!E$5,Leadsheet!$C$26:$F$30,3,1),0) -> 0.075631948 | F14: =IF(F$5<Leadsheet!$E$12,VLOOKUP(SAP_Speadsheet!F$5,Leadsheet!$C$26:$F$30,3,1),0) -> 0.075631948 | G14: =IF(G$5<Leadsheet!$E$12,VLOOKUP(SAP_Speadsheet!G$5,Leadsheet!$C$26:$F$30,3,1),0) -> 0.075631948 | H14: =IF(H$5<Leadsheet!$E$12,VLOOKUP(SAP_Speadsheet!H$5,Leadsheet!$C$26:$F$30,3,1),0) -> 0.048252779 | I14: =IF(I$5<Leadsheet!$E$12,VLOOKUP(SAP_Speadsheet!I$5,Leadsheet!$C$26:$F$30,3,1),0) -> 0.048252779 | J14: =IF(J$5<Leadsheet!$E$12,VLOOKUP(SAP_Speadsheet!J$5,Leadsheet!$C$26:$F$30,3,1),0) -> 0.048252779 | K14: =IF(K$5<Leadsheet!$E$12,VLOOKUP(SAP_Speadsheet!K$5,Leadsheet!$C$26:$F$30,3,1),0) -> 0.048252779 | L14: =IF(L$5<Leadsheet!$E$12,VLOOKUP(SAP_Speadsheet!L$5,Leadsheet!$C$26:$F$30,3,1),0) -> 0.048252779 | ... BL14: =IF(BL$5<Leadsheet!$E$12,VLOOKUP(SAP_Speadsheet!BL$5,Leadsheet!$C$26:$F$30,3,1),0) -> 0
B16: EMI | C16: Account accumulated | D16: 1 | E16: =IF(E5>$D$7,0,D16-E13) -> 0.88415019 | F16: =IF(F5>$D$7,0,E16-F13) -> 0.83646535 | G16: =IF(G5>$D$7,0,F16-G13) -> 0.78878051 | H16: =IF(H5>$D$7,0,G16-H13) -> 0.76543965 | I16: =IF(I5>$D$7,0,H16-I13) -> 0.74209878 | J16: =IF(J5>$D$7,0,I16-J13) -> 0.71875792 | K16: =IF(K5>$D$7,0,J16-K13) -> 0.69541706 | L16: =IF(L5>$D$7,0,K16-L13) -> 0.6720762 | ... BL16: =IF(BL5>$D$7,0,BK16-BL13) -> 0
C17: Nominal ENR | D17: =Leadsheet!E10 -> 16.17916 | E17: =IF(E$5>Leadsheet!$E$12,0,D17+E21+E18) -> 13.426217 | F17: =IF(F$5>Leadsheet!$E$12,0,SAP_Speadsheet!E17+SAP_Speadsheet!F21+F18) -> 11.941635 | G17: =IF(G$5>Leadsheet!$E$12,0,SAP_Speadsheet!F17+SAP_Speadsheet!G21+G18) -> 10.531459 | H17: =IF(H$5>Leadsheet!$E$12,0,SAP_Speadsheet!G17+SAP_Speadsheet!H21+H18) -> 9.479942 | I17: =IF(I$5>Leadsheet!$E$12,0,SAP_Speadsheet!H17+SAP_Speadsheet!I21+I18) -> 8.4467879 | J17: =IF(J$5>Leadsheet!$E$12,0,SAP_Speadsheet!I17+SAP_Speadsheet!J21+J18) -> 7.4313214 | K17: =IF(K$5>Leadsheet!$E$12,0,SAP_Speadsheet!J17+SAP_Speadsheet!K21+K18) -> 6.4333425 | L17: =IF(L$5>Leadsheet!$E$12,0,SAP_Speadsheet!K17+SAP_Speadsheet!L21+L18) -> 5.4521869 | M17: =IF(M$5>Leadsheet!$E$12,0,SAP_Speadsheet!L17+SAP_Speadsheet!M21+M18) -> 4.4877879 | ... BL17: =IF(BL$5>Leadsheet!$E$12,0,SAP_Speadsheet!BK17+SAP_Speadsheet!BL21+BL18) -> 0
C18: Fully Prepayment Amount | E18: =-IF(E6>0,IFERROR(D27*(D16-E16)/D16,0),0) -> -1.8743527 | F18: =-IF(F6>0,IFERROR(E27*(E16-F16)/E16,0),0) -> -0.68203023 | G18: =-IF(G6>0,IFERROR(F27*(F16-G16)/F16,0),0) -> -0.61987502 | H18: =-IF(H6>0,IFERROR(G27*(G16-H16)/G16,0),0) -> -0.27456373 | I18: =-IF(I6>0,IFERROR(H27*(H16-I16)/H16,0),0) -> -0.24712905 | J18: =-IF(J6>0,IFERROR(I27*(I16-J16)/I16,0),0) -> -0.22049169 | K18: =-IF(K6>0,IFERROR(J27*(J16-K16)/J16,0),0) -> -0.19427521 | L18: =-IF(L6>0,IFERROR(K27*(K16-L16)/K16,0),0) -> -0.1690434 | ... BL18: =-IF(BL6>0,IFERROR(BK27*(BK16-BL16)/BK16,0),0) -> 0
C19: EMI payment | E19: =-IFERROR(PMT(D11/12,D6,-D17),0) -> -1.5415542 | F19: =-IFERROR(PMT(E11/12,E6,-E17),0) -> -1.3527105 | G19: =-IFERROR(PMT(F11/12,F6,-F17),0) -> -1.2796264 | H19: =-IFERROR(PMT(G11/12,G6,-G17),0) -> -1.2084951 | I19: =-IFERROR(PMT(H11/12,H6,-H17),0) -> -1.1744792 | J19: =-IFERROR(PMT(I11/12,I6,-I17),0) -> -1.141094 | K19: =-IFERROR(PMT(J11/12,J6,-J17),0) -> -1.1082127 | L19: =-IFERROR(PMT(K11/12,K6,-K17),0) -> -1.0757277 | ... BL19: =-IFERROR(PMT(BK11/12,BK6,-BK17),0) -> 0
C20: Nominal Interest | E20: =-IF(E5>$D$6,0,D17*D11/12) -> -0.66296419 | F20: =-IF(F5>$D$6,0,E17*E11/12) -> -0.55015843 | G20: =-IF(G5>$D$6,0,F17*F11/12) -> -0.48932555 | H20: =-IF(H5>$D$6,0,G17*G11/12) -> -0.43154158 | I20: =-IF(I5>$D$6,0,H17*H11/12) -> -0.38845416 | J20: =-IF(J5>$D$6,0,I17*I11/12) -> -0.3461192 | K20: =-IF(K5>$D$6,0,J17*J11/12) -> -0.30450901 | L20: =-IF(L5>$D$6,0,K17*K11/12) -> -0.2636154 | ... BL20: =-IF(BL5>$D$6,0,BK17*BK11/12) -> 0
C21: Nominal Payment | E21: =E19-E20 -> -0.87859002 | F21: =F19-F20 -> -0.80255208 | G21: =G19-G20 -> -0.79030084 | H21: =H19-H20 -> -0.77695355 | I21: =I19-I20 -> -0.78602501 | J21: =J19-J20 -> -0.7949748 | K21: =K19-K20 -> -0.80370366 | L21: =L19-L20 -> -0.81211226 | ... BL21: =BL19-BL20 -> 0
C24: Schedule Payment | E24: =IF(E5>Leadsheet!$E$12,0,IFERROR(E21/D17*D27*(1-Leadsheet!$D$91)+E18,0)) -> -2.7081346 | F24: =IF(F5>Leadsheet!$E$12,0,IFERROR(F21/E17*E27*(1-Leadsheet!$D$91)+F18,0)) -> -1.3993868 | G24: =IF(G5>Leadsheet!$E$12,0,IFERROR(G21/F17*F27*(1-Leadsheet!$D$91)+G18,0)) -> -1.30279 | H24: =IF(H5>Leadsheet!$E$12,0,IFERROR(H21/G17*G27*(1-Leadsheet!$D$91)+H18,0)) -> -0.92417741 | I24: =IF(I5>Leadsheet!$E$12,0,IFERROR(I21/H17*H27*(1-Leadsheet!$D$91)+I18,0)) -> -0.88482663 | J24: =IF(J5>Leadsheet!$E$12,0,IFERROR(J21/I17*I27*(1-Leadsheet!$D$91)+J18,0)) -> -0.84662246 | K24: =IF(K5>Leadsheet!$E$12,0,IFERROR(K21/J17*J27*(1-Leadsheet!$D$91)+K18,0)) -> -0.80829059 | L24: =IF(L5>Leadsheet!$E$12,0,IFERROR(L21/K17*K27*(1-Leadsheet!$D$91)+L18,0)) -> -0.77239753 | ... BL24: =IF(BL5>Leadsheet!$E$12,0,IFERROR(BL21/BK17*BK27*(1-Leadsheet!$D$91)+BL18,0)) -> 0
A26: SBV | B26: Overdue | C26: Balance by Bucket/Group
A27: G1 | B27: 0 | C27: B0 | D27: =Leadsheet!E10 -> 16.17916 | E27: =IF(E5>=Leadsheet!$E$12,0,D44+E24-SUM(E28:E41)) -> 12.645888 | F27: =IF(F5>=Leadsheet!$E$12,0,E44+F24-SUM(F28:F41)) -> 10.87356 | G27: =IF(G5>=Leadsheet!$E$12,0,F44+G24-SUM(G28:G41)) -> 9.2785999 | H27: =IF(H5>=Leadsheet!$E$12,0,G44+H24-SUM(H28:H41)) -> 8.1043441 | I27: =IF(I5>=Leadsheet!$E$12,0,H44+I24-SUM(I28:I41)) -> 7.0103074 | J27: =IF(J5>=Leadsheet!$E$12,0,I44+J24-SUM(J28:J41)) -> 5.9825059 | K27: =IF(K5>=Leadsheet!$E$12,0,J44+K24-SUM(K28:K41)) -> 5.036475 | L27: =IF(L5>=Leadsheet!$E$12,0,K44+L24-SUM(L28:L41)) -> 4.158775 | ... BL27: =IF(BL5>=Leadsheet!$E$12,0,BK44+BL24-SUM(BL28:BL41)) -> 0
A28: G2 | B28: 30 | C28: B1 | E28: =IF(E$5>$D$7,0,D27*Leadsheet!$D91) -> 0.82513717 | F28: =IF(F$5>$D$7,0,E27*Leadsheet!$D91) -> 0.6449403 | G28: =IF(G$5>$D$7,0,F27*Leadsheet!$D91) -> 0.55455157 | H28: =IF(H$5>$D$7,0,G27*Leadsheet!$D91) -> 0.47320859 | I28: =IF(I$5>$D$7,0,H27*Leadsheet!$D91) -> 0.41332155 | J28: =IF(J$5>$D$7,0,I27*Leadsheet!$D91) -> 0.35752568 | K28: =IF(K$5>$D$7,0,J27*Leadsheet!$D91) -> 0.3051078 | L28: =IF(L$5>$D$7,0,K27*Leadsheet!$D91) -> 0.25686023 | ... BL28: =IF(BL$5>$D$7,0,BK27*Leadsheet!$D91) -> 0
A29: G2 | B29: 60 | C29: B2 | E29: =IF(E$5>$D$7,0,D28*Leadsheet!$D92) -> 0 | F29: =IF(F$5>$D$7,0,E28*Leadsheet!$D92) -> 0.55313814 | G29: =IF(G$5>$D$7,0,F28*Leadsheet!$D92) -> 0.43234155 | H29: =IF(H$5>$D$7,0,G28*Leadsheet!$D92) -> 0.37174864 | I29: =IF(I$5>$D$7,0,H28*Leadsheet!$D92) -> 0.31721965 | J29: =IF(J$5>$D$7,0,I28*Leadsheet!$D92) -> 0.27707383 | K29: =IF(K$5>$D$7,0,J28*Leadsheet!$D92) -> 0.23967056 | L29: =IF(L$5>$D$7,0,K28*Leadsheet!$D92) -> 0.20453176 | ... BL29: =IF(BL$5>$D$7,0,BK28*Leadsheet!$D92) -> 0
A30: G2 | B30: 90 | C30: B3 | E30: =IF(E$5>$D$7,0,D29*Leadsheet!$D93) -> 0 | F30: =IF(F$5>$D$7,0,E29*Leadsheet!$D93) -> 0 | G30: =IF(G$5>$D$7,0,F29*Leadsheet!$D93) -> 0.50335571 | H30: =IF(H$5>$D$7,0,G29*Leadsheet!$D93) -> 0.39343081 | I30: =IF(I$5>$D$7,0,H29*Leadsheet!$D93) -> 0.33829127 | J30: =IF(J$5>$D$7,0,I29*Leadsheet!$D93) -> 0.28866988 | K30: =IF(K$5>$D$7,0,J29*Leadsheet!$D93) -> 0.25213718 | L30: =IF(L$5>$D$7,0,K29*Leadsheet!$D93) -> 0.21810021 | ... AU30: =IF(AU$5>$D$7,0,AT29*Leadsheet!$D93) -> 0 | AV30: 0 | AW30: =IF(AW$5>$D$7,0,AV29*Leadsheet!$D93) -> 0 | AX30: =IF(AX$5>$D$7,0,AW29*Leadsheet!$D93) -> 0 | AY30: =IF(AY$5>$D$7,0,AX29*Leadsheet!$D93) -> 0 | AZ30: =IF(AZ$5>$D$7,0,AY29*Leadsheet!$D93) -> 0 | BA30: =IF(BA$5>$D$7,0,AZ29*Leadsheet!$D93) -> 0 | BB30: =IF(BB$5>$D$7,0,BA29*Leadsheet!$D93) -> 0 | BC30: =IF(BC$5>$D$7,0,BB29*Leadsheet!$D93) -> 0 | BD30: =IF(BD$5>$D$7,0,BC29*Leadsheet!$D93) -> 0 | ... BL30: =IF(BL$5>$D$7,0,BK29*Leadsheet!$D93) -> 0
A31: G3 | B31: 120 | C31: B4 | E31: =IF(E$5>$D$7,0,D30*Leadsheet!$D94) -> 0 | F31: =IF(F$5>$D$7,0,E30*Leadsheet!$D94) -> 0 | G31: =IF(G$5>$D$7,0,F30*Leadsheet!$D94) -> 0 | H31: =IF(H$5>$D$7,0,G30*Leadsheet!$D94) -> 0.50193915 | I31: =IF(I$5>$D$7,0,H30*Leadsheet!$D94) -> 0.39232361 | J31: =IF(J$5>$D$7,0,I30*Leadsheet!$D94) -> 0.33733924 | K31: =IF(K$5>$D$7,0,J30*Leadsheet!$D94) -> 0.2878575 | L31: =IF(L$5>$D$7,0,K30*Leadsheet!$D94) -> 0.25142761 | ... BL31: =IF(BL$5>$D$7,0,BK30*Leadsheet!$D94) -> 0
A32: G3 | B32: 150 | C32: B5 | E32: =IF(E$5>$D$7,0,D31*Leadsheet!$D95) -> 0 | F32: =IF(F$5>$D$7,0,E31*Leadsheet!$D95) -> 0 | G32: =IF(G$5>$D$7,0,F31*Leadsheet!$D95) -> 0 | H32: =IF(H$5>$D$7,0,G31*Leadsheet!$D95) -> 0 | I32: =IF(I$5>$D$7,0,H31*Leadsheet!$D95) -> 0.48838118 | J32: =IF(J$5>$D$7,0,I31*Leadsheet!$D95) -> 0.38172648 | K32: =IF(K$5>$D$7,0,J31*Leadsheet!$D95) -> 0.32822731 | L32: =IF(L$5>$D$7,0,K31*Leadsheet!$D95) -> 0.28008212 | ... BL32: =IF(BL$5>$D$7,0,BK31*Leadsheet!$D95) -> 0
A33: G3 | B33: 180 | C33: B6 | E33: =IF(E$5>$D$7,0,D32*Leadsheet!$D96) -> 0 | F33: =IF(F$5>$D$7,0,E32*Leadsheet!$D96) -> 0 | G33: =IF(G$5>$D$7,0,F32*Leadsheet!$D96) -> 0 | H33: =IF(H$5>$D$7,0,G32*Leadsheet!$D96) -> 0 | I33: =IF(I$5>$D$7,0,H32*Leadsheet!$D96) -> 0 | J33: =IF(J$5>$D$7,0,I32*Leadsheet!$D96) -> 0.48838118 | K33: =IF(K$5>$D$7,0,J32*Leadsheet!$D96) -> 0.38172648 | L33: =IF(L$5>$D$7,0,K32*Leadsheet!$D96) -> 0.32822731 | ... BL33: =IF(BL$5>$D$7,0,BK32*Leadsheet!$D96) -> 0
A34: G4 | B34: 210 | C34: B7 | E34: =IF(E$5>$D$7,0,D33*Leadsheet!$D97) -> 0 | F34: =IF(F$5>$D$7,0,E33*Leadsheet!$D97) -> 0 | G34: =IF(G$5>$D$7,0,F33*Leadsheet!$D97) -> 0 | H34: =IF(H$5>$D$7,0,G33*Leadsheet!$D97) -> 0 | I34: =IF(I$5>$D$7,0,H33*Leadsheet!$D97) -> 0 | J34: =IF(J$5>$D$7,0,I33*Leadsheet!$D97) -> 0 | K34: =IF(K$5>$D$7,0,J33*Leadsheet!$D97) -> 0.47372974 | L34: =IF(L$5>$D$7,0,K33*Leadsheet!$D97) -> 0.37027469 | ... BL34: =IF(BL$5>$D$7,0,BK33*Leadsheet!$D97) -> 0
A35: G4 | B35: 240 | C35: B8 | E35: =IF(E$5>$D$7,0,D34*Leadsheet!$D98) -> 0 | F35: =IF(F$5>$D$7,0,E34*Leadsheet!$D98) -> 0 | G35: =IF(G$5>$D$7,0,F34*Leadsheet!$D98) -> 0 | H35: =IF(H$5>$D$7,0,G34*Leadsheet!$D98) -> 0 | I35: =IF(I$5>$D$7,0,H34*Leadsheet!$D98) -> 0 | J35: =IF(J$5>$D$7,0,I34*Leadsheet!$D98) -> 0 | K35: =IF(K$5>$D$7,0,J34*Leadsheet!$D98) -> 0 | L35: =IF(L$5>$D$7,0,K34*Leadsheet!$D98) -> 0.46425515 | ... BL35: =IF(BL$5>$D$7,0,BK34*Leadsheet!$D98) -> 0
A36: G4 | B36: 270 | C36: B9 | E36: =IF(E$5>$D$7,0,D35*Leadsheet!$D99) -> 0 | F36: =IF(F$5>$D$7,0,E35*Leadsheet!$D99) -> 0 | G36: =IF(G$5>$D$7,0,F35*Leadsheet!$D99) -> 0 | H36: =IF(H$5>$D$7,0,G35*Leadsheet!$D99) -> 0 | I36: =IF(I$5>$D$7,0,H35*Leadsheet!$D99) -> 0 | J36: =IF(J$5>$D$7,0,I35*Leadsheet!$D99) -> 0 | K36: =IF(K$5>$D$7,0,J35*Leadsheet!$D99) -> 0 | L36: =IF(L$5>$D$7,0,K35*Leadsheet!$D99) -> 0 | ... BL36: =IF(BL$5>$D$7,0,BK35*Leadsheet!$D99) -> 0
A37: G4 | B37: 300 | C37: B10 | E37: =IF(E$5>$D$7,0,D36*Leadsheet!$D100) -> 0 | F37: =IF(F$5>$D$7,0,E36*Leadsheet!$D100) -> 0 | G37: =IF(G$5>$D$7,0,F36*Leadsheet!$D100) -> 0 | H37: =IF(H$5>$D$7,0,G36*Leadsheet!$D100) -> 0 | I37: =IF(I$5>$D$7,0,H36*Leadsheet!$D100) -> 0 | J37: =IF(J$5>$D$7,0,I36*Leadsheet!$D100) -> 0 | K37: =IF(K$5>$D$7,0,J36*Leadsheet!$D100) -> 0 | L37: =IF(L$5>$D$7,0,K36*Leadsheet!$D100) -> 0 | ... BL37: =IF(BL$5>$D$7,0,BK36*Leadsheet!$D100) -> 0
A38: G4 | B38: 330 | C38: B11 | E38: =IF(E$5>$D$7,0,D37*Leadsheet!$D101) -> 0 | F38: =IF(F$5>$D$7,0,E37*Leadsheet!$D101) -> 0 | G38: =IF(G$5>$D$7,0,F37*Leadsheet!$D101) -> 0 | H38: =IF(H$5>$D$7,0,G37*Leadsheet!$D101) -> 0 | I38: =IF(I$5>$D$7,0,H37*Leadsheet!$D101) -> 0 | J38: =IF(J$5>$D$7,0,I37*Leadsheet!$D101) -> 0 | K38: =IF(K$5>$D$7,0,J37*Leadsheet!$D101) -> 0 | L38: =IF(L$5>$D$7,0,K37*Leadsheet!$D101) -> 0 | ... BL38: =IF(BL$5>$D$7,0,BK37*Leadsheet!$D101) -> 0
A39: G4 | B39: 360 | C39: B12 | E39: =IF(E$5>$D$7,0,D38*Leadsheet!$D102) -> 0 | F39: =IF(F$5>$D$7,0,E38*Leadsheet!$D102) -> 0 | G39: =IF(G$5>$D$7,0,F38*Leadsheet!$D102) -> 0 | H39: =IF(H$5>$D$7,0,G38*Leadsheet!$D102) -> 0 | I39: =IF(I$5>$D$7,0,H38*Leadsheet!$D102) -> 0 | J39: =IF(J$5>$D$7,0,I38*Leadsheet!$D102) -> 0 | K39: =IF(K$5>$D$7,0,J38*Leadsheet!$D102) -> 0 | L39: =IF(L$5>$D$7,0,K38*Leadsheet!$D102) -> 0 | ... BL39: =IF(BL$5>$D$7,0,BK38*Leadsheet!$D102) -> 0
A40: G5 | B40: 390 | C40: B13 | E40: =IF(E$5>$D$7,0,D39*Leadsheet!$D103) -> 0 | F40: =IF(F$5>$D$7,0,E39*Leadsheet!$D103) -> 0 | G40: =IF(G$5>$D$7,0,F39*Leadsheet!$D103) -> 0 | H40: =IF(H$5>$D$7,0,G39*Leadsheet!$D103) -> 0 | I40: =IF(I$5>$D$7,0,H39*Leadsheet!$D103) -> 0 | J40: =IF(J$5>$D$7,0,I39*Leadsheet!$D103) -> 0 | K40: =IF(K$5>$D$7,0,J39*Leadsheet!$D103) -> 0 | L40: =IF(L$5>$D$7,0,K39*Leadsheet!$D103) -> 0 | ... BL40: =IF(BL$5>$D$7,0,BK39*Leadsheet!$D103) -> 0
A41: G5 | B41: 420+ | C41: B14+ | E41: =IF(E5>$D$7,0,D40+D41) -> 0 | F41: =IF(F5>$D$7,0,E40+E41) -> 0 | G41: =IF(G5>$D$7,0,F40+F41) -> 0 | H41: =IF(H5>$D$7,0,G40+G41) -> 0 | I41: =IF(I5>$D$7,0,H40+H41) -> 0 | J41: =IF(J5>$D$7,0,I40+I41) -> 0 | K41: =IF(K5>$D$7,0,J40+J41) -> 0 | L41: =IF(L5>$D$7,0,K40+K41) -> 0 | ... BL41: =IF(BL5>$D$7,0,BK40+BK41) -> 0
B43: ENR
C44: Total bank | D44: =SUM(D27:D41) -> 16.17916 | E44: =SUM(E27:E41) -> 13.471025 | F44: =SUM(F27:F41) -> 12.071639 | G44: =SUM(G27:G41) -> 10.768849 | H44: =SUM(H27:H41) -> 9.8446713 | I44: =SUM(I27:I41) -> 8.9598446 | J44: =SUM(J27:J41) -> 8.1132222 | K44: =SUM(K27:K41) -> 7.3049316 | ... BL44: =SUM(BL27:BL41) -> 0
C45: Outstanding balance | D45: {=IF(D5=$D$7,0,_xlfn.IFS(Leadsheet!$G$5="DPD360+",SUM(SAP_Speadsheet!D27:D40),Leadsheet!$G$5="DPD180+",SUM(SAP_Speadsheet!D27:D34)))} -> 16.17916 | E45: {=IF(E5=$D$7,0,_xlfn.IFS(Leadsheet!$G$5="DPD360+",SUM(SAP_Speadsheet!E27:E40),Leadsheet!$G$5="DPD180+",SUM(SAP_Speadsheet!E27:E34)))} -> 13.471025 | F45: {=IF(F5=$D$7,0,_xlfn.IFS(Leadsheet!$G$5="DPD360+",SUM(SAP_Speadsheet!F27:F40),Leadsheet!$G$5="DPD180+",SUM(SAP_Speadsheet!F27:F34)))} -> 12.071639 | G45: {=IF(G5=$D$7,0,_xlfn.IFS(Leadsheet!$G$5="DPD360+",SUM(SAP_Speadsheet!G27:G40),Leadsheet!$G$5="DPD180+",SUM(SAP_Speadsheet!G27:G34)))} -> 10.768849 | H45: {=IF(H5=$D$7,0,_xlfn.IFS(Leadsheet!$G$5="DPD360+",SUM(SAP_Speadsheet!H27:H40),Leadsheet!$G$5="DPD180+",SUM(SAP_Speadsheet!H27:H34)))} -> 9.8446713 | I45: {=IF(I5=$D$7,0,_xlfn.IFS(Leadsheet!$G$5="DPD360+",SUM(SAP_Speadsheet!I27:I40),Leadsheet!$G$5="DPD180+",SUM(SAP_Speadsheet!I27:I34)))} -> 8.9598446 | J45: {=IF(J5=$D$7,0,_xlfn.IFS(Leadsheet!$G$5="DPD360+",SUM(SAP_Speadsheet!J27:J40),Leadsheet!$G$5="DPD180+",SUM(SAP_Speadsheet!J27:J34)))} -> 8.1132222 | K45: {=IF(K5=$D$7,0,_xlfn.IFS(Leadsheet!$G$5="DPD360+",SUM(SAP_Speadsheet!K27:K40),Leadsheet!$G$5="DPD180+",SUM(SAP_Speadsheet!K27:K34)))} -> 7.3049316 | ... BL45: {=IF(BL5=$D$7,0,_xlfn.IFS(Leadsheet!$G$5="DPD360+",SUM(SAP_Speadsheet!BL27:BL40),Leadsheet!$G$5="DPD180+",SUM(SAP_Speadsheet!BL27:BL34)))} -> 0
C46: Writeoff balance | D46: =D44-D45 -> 0 | E46: =E44-E45 -> 0 | F46: =F44-F45 -> 0 | G46: =G44-G45 -> 0 | H46: =H44-H45 -> 0 | I46: =I44-I45 -> 0 | J46: =J44-J45 -> 0 | K46: =K44-K45 -> 0 | ... BL46: =BL44-BL45 -> 0
C47: Outstanding Bal/TB | D47: =IFERROR(D45/D44,"") -> 1 | E47: =IFERROR(E45/E44,"") -> 1 | F47: =IFERROR(F45/F44,"") -> 1 | G47: =IFERROR(G45/G44,"") -> 1 | H47: =IFERROR(H45/H44,"") -> 1 | I47: =IFERROR(I45/I44,"") -> 1 | J47: =IFERROR(J45/J44,"") -> 1 | K47: =IFERROR(K45/K44,"") -> 1 | ... BL47: =IFERROR(BL45/BL44,"")
B49: ANR
C50: Outstanding balance | E50: =IF(E5>$D$7,0,AVERAGE(D45:E45)) -> 14.825093 | F50: =IF(F5>$D$7,0,AVERAGE(E45:F45)) -> 12.771332 | G50: =IF(G5>$D$7,0,AVERAGE(F45:G45)) -> 11.420244 | H50: =IF(H5>$D$7,0,AVERAGE(G45:H45)) -> 10.30676 | I50: =IF(I5>$D$7,0,AVERAGE(H45:I45)) -> 9.402258 | J50: =IF(J5>$D$7,0,AVERAGE(I45:J45)) -> 8.5365334 | K50: =IF(K5>$D$7,0,AVERAGE(J45:K45)) -> 7.7090769 | L50: =IF(L5>$D$7,0,AVERAGE(K45:L45)) -> 6.6866052 | ... BL50: =IF(BL5>$D$7,0,AVERAGE(BK45:BL45)) -> 0
C51: ANR for CII (B0+B1A) | E51: =D27*(1-Leadsheet!$D$91)+D28*Leadsheet!$E$117 -> 15.354023 | F51: =E27*(1-Leadsheet!$D$91)+E28*Leadsheet!$E$117 -> 12.272947 | G51: =F27*(1-Leadsheet!$D$91)+F28*Leadsheet!$E$117 -> 10.531607 | H51: =G27*(1-Leadsheet!$D$91)+G28*Leadsheet!$E$117 -> 8.9881942 | I51: =H27*(1-Leadsheet!$D$91)+H28*Leadsheet!$E$117 -> 7.8470115 | J51: =I27*(1-Leadsheet!$D$91)+I28*Leadsheet!$E$117 -> 6.7890294 | K51: =J27*(1-Leadsheet!$D$91)+J28*Leadsheet!$E$117 -> 5.7952532 | L51: =K27*(1-Leadsheet!$D$91)+K28*Leadsheet!$E$117 -> 4.8801908 | ... BL51: =BK27*(1-Leadsheet!$D$91)+BK28*Leadsheet!$E$117 -> 0
B53: Performance
B55: TOI | E55: =E57+E61+E68 -> 1.3972554 | F55: =F57+F61+F68 -> 0.48098269 | G55: =G57+G61+G68 -> 0.41270373 | H55: =H57+H61+H68 -> 0.32223465 | I55: =I57+I61+I68 -> 0.27935488 | J55: =J57+J61+J68 -> 0.23969969 | K55: =K57+K61+K68 -> 0.20247548 | L55: =L57+L61+L68 -> 0.16964656 | ... BL55: =BL57+BL61+BL68 -> 0
C57: Net interest income | E57: =E58+E59 -> 0.543831 | F57: =F58+F59 -> 0.42939941 | G57: =G58+G59 -> 0.36582137 | H57: =H58+H59 -> 0.30898618 | I57: =I58+I59 -> 0.26743022 | J57: =J58+J59 -> 0.22906035 | K57: =K58+K59 -> 0.19310116 | L57: =L58+L59 -> 0.16148975 | ... BL57: =BL58+BL59 -> 0
C58: Interest income | E58: =IFERROR(E$51*D$11/12,0) -> 0.62915302 | F58: =IFERROR(F$51*E$11/12,0) -> 0.50290153 | G58: =IFERROR(G$51*F$11/12,0) -> 0.43154765 | H58: =IFERROR(H$51*G$11/12,0) -> 0.36830409 | I58: =IFERROR(I$51*H$11/12,0) -> 0.3215425 | J58: =IFERROR(J$51*I$11/12,0) -> 0.27819018 | K58: =IFERROR(K$51*J$11/12,0) -> 0.23746878 | L58: =IFERROR(L$51*K$11/12,0) -> 0.19997279 | ... BL58: =IFERROR(BL$51*BK$11/12,0) -> 0
C59: Cost of fund | E59: =-IFERROR(E50*D12/12,0) -> -0.085322015 | F59: =-IFERROR(F50*E12/12,0) -> -0.073502122 | G59: =-IFERROR(G50*F12/12,0) -> -0.06572628 | H59: =-IFERROR(H50*G12/12,0) -> -0.059317911 | I59: =-IFERROR(I50*H12/12,0) -> -0.054112281 | J59: =-IFERROR(J50*I12/12,0) -> -0.049129826 | K59: =-IFERROR(K50*J12/12,0) -> -0.044367613 | L59: =-IFERROR(L50*K12/12,0) -> -0.03848304 | ... BL59: =-IFERROR(BL50*BK12/12,0) -> 0
C61: Net fee income | E61: =SUM(E62:E64) -> 0.85342441 | F61: =SUM(F62:F64) -> 0.051583275 | G61: =SUM(G62:G64) -> 0.046882355 | H61: =SUM(H62:H64) -> 0.013248463 | I61: =SUM(I62:I64) -> 0.011924664 | J61: =SUM(J62:J64) -> 0.010639337 | K61: =SUM(K62:K64) -> 0.0093743187 | L61: =SUM(L62:L64) -> 0.0081568141 | ... BL61: =SUM(BL62:BL64) -> 0
C62: Early termination fee | E62: =-E18*E14 -> 0.14176095 | F62: =-F18*F14 -> 0.051583275 | G62: =-G18*G14 -> 0.046882355 | H62: =-H18*H14 -> 0.013248463 | I62: =-I18*I14 -> 0.011924664 | J62: =-J18*J14 -> 0.010639337 | K62: =-K18*K14 -> 0.0093743187 | L62: =-L18*L14 -> 0.0081568141 | ... BL62: =-BL18*BL14 -> 0
C63: Insurrance fee | E63: =Leadsheet!E10*Leadsheet!E33*Leadsheet!E35*Leadsheet!E36+Leadsheet!E10/(1+Leadsheet!E34*Leadsheet!E35)*Leadsheet!E34*Leadsheet!E35*Leadsheet!E36 -> 0.71166346
C64: Support fee | E64: =SUM(E65:E66) -> 0 | F64: =SUM(F65:F66) -> 0 | G64: =SUM(G65:G66) -> 0 | H64: =SUM(H65:H66) -> 0 | I64: =SUM(I65:I66) -> 0 | J64: =SUM(J65:J66) -> 0 | K64: =SUM(K65:K66) -> 0 | L64: =SUM(L65:L66) -> 0 | ... BL64: =SUM(BL65:BL66) -> 0
C65: One-time | E65: =Leadsheet!E10*Leadsheet!E39+Leadsheet!E38 -> 0
C66: Monthly fee | E66: =IF(E5>$D$6,0,$D$17*Leadsheet!$E$40*D16*((D27*(1-Leadsheet!$D$91)+D28*Leadsheet!$E$117)/D45)) -> 0 | F66: =IF(F5>$D$6,0,$D$17*Leadsheet!$E$40*E16*((E27*(1-Leadsheet!$D$91)+E28*Leadsheet!$E$117)/E45)) -> 0 | G66: =IF(G5>$D$6,0,$D$17*Leadsheet!$E$40*F16*((F27*(1-Leadsheet!$D$91)+F28*Leadsheet!$E$117)/F45)) -> 0 | H66: =IF(H5>$D$6,0,$D$17*Leadsheet!$E$40*G16*((G27*(1-Leadsheet!$D$91)+G28*Leadsheet!$E$117)/G45)) -> 0 | I66: =IF(I5>$D$6,0,$D$17*Leadsheet!$E$40*H16*((H27*(1-Leadsheet!$D$91)+H28*Leadsheet!$E$117)/H45)) -> 0 | J66: =IF(J5>$D$6,0,$D$17*Leadsheet!$E$40*I16*((I27*(1-Leadsheet!$D$91)+I28*Leadsheet!$E$117)/I45)) -> 0 | K66: =IF(K5>$D$6,0,$D$17*Leadsheet!$E$40*J16*((J27*(1-Leadsheet!$D$91)+J28*Leadsheet!$E$117)/J45)) -> 0 | L66: =IF(L5>$D$6,0,$D$17*Leadsheet!$E$40*K16*((K27*(1-Leadsheet!$D$91)+K28*Leadsheet!$E$117)/K45)) -> 0 | ... BL66: =IF(BL5>$D$6,0,$D$17*Leadsheet!$E$40*BK16*((BK27*(1-Leadsheet!$D$91)+BK28*Leadsheet!$E$117)/BK45)) -> 0
B68: Other Income | E68: {=IF(E5=$D$7,_xlfn.IFS(Leadsheet!$G$4="IFRS",0,Leadsheet!$G$5="DPD180+",(E180-E145)*(1+Leadsheet!$E$115),Leadsheet!$G$5="DPD360+",(E165-E145)*(1+Leadsheet!$E$115)),0)} -> 0 | F68: {=IF(F5=$D$7,_xlfn.IFS(Leadsheet!$G$4="IFRS",0,Leadsheet!$G$5="DPD180+",(F180-F145)*(1+Leadsheet!$E$115),Leadsheet!$G$5="DPD360+",(F165-F145)*(1+Leadsheet!$E$115)),0)} -> 0 | G68: {=IF(G5=$D$7,_xlfn.IFS(Leadsheet!$G$4="IFRS",0,Leadsheet!$G$5="DPD180+",(G180-G145)*(1+Leadsheet!$E$115),Leadsheet!$G$5="DPD360+",(G165-G145)*(1+Leadsheet!$E$115)),0)} -> 0 | H68: {=IF(H5=$D$7,_xlfn.IFS(Leadsheet!$G$4="IFRS",0,Leadsheet!$G$5="DPD180+",(H180-H145)*(1+Leadsheet!$E$115),Leadsheet!$G$5="DPD360+",(H165-H145)*(1+Leadsheet!$E$115)),0)} -> 0 | I68: {=IF(I5=$D$7,_xlfn.IFS(Leadsheet!$G$4="IFRS",0,Leadsheet!$G$5="DPD180+",(I180-I145)*(1+Leadsheet!$E$115),Leadsheet!$G$5="DPD360+",(I165-I145)*(1+Leadsheet!$E$115)),0)} -> 0 | J68: {=IF(J5=$D$7,_xlfn.IFS(Leadsheet!$G$4="IFRS",0,Leadsheet!$G$5="DPD180+",(J180-J145)*(1+Leadsheet!$E$115),Leadsheet!$G$5="DPD360+",(J165-J145)*(1+Leadsheet!$E$115)),0)} -> 0 | K68: {=IF(K5=$D$7,_xlfn.IFS(Leadsheet!$G$4="IFRS",0,Leadsheet!$G$5="DPD180+",(K180-K145)*(1+Leadsheet!$E$115),Leadsheet!$G$5="DPD360+",(K165-K145)*(1+Leadsheet!$E$115)),0)} -> 0 | L68: {=IF(L5=$D$7,_xlfn.IFS(Leadsheet!$G$4="IFRS",0,Leadsheet!$G$5="DPD180+",(L180-L145)*(1+Leadsheet!$E$115),Leadsheet!$G$5="DPD360+",(L165-L145)*(1+Leadsheet!$E$115)),0)} -> 0 | ... BL68: {=IF(BL5=$D$7,_xlfn.IFS(Leadsheet!$G$4="IFRS",0,Leadsheet!$G$5="DPD180+",(BL180-BL145)*(1+Leadsheet!$E$115),Leadsheet!$G$5="DPD360+",(BL165-BL145)*(1+Leadsheet!$E$115)),0)} -> 0
B71: VARIABLE EXPENSES | E71: =E72+E85+E88+E95+E99 -> -0.46270618 | F71: =F72+F85+F88+F95+F99 -> -0.11900508 | G71: =G72+G85+G88+G95+G99 -> -0.10280512 | H71: =H72+H85+H88+H95+H99 -> 0.034431728 | I71: =I72+I85+I88+I95+I99 -> 0.016095872 | J71: =J72+J85+J88+J95+J99 -> 0.013449155 | K71: =K72+K85+K88+K95+K99 -> 0.0077869419 | L71: =L72+L85+L88+L95+L99 -> 0.0060246234 | ... BL71: =BL72+BL85+BL88+BL95+BL99 -> 0
B72: Sale incentive | E72: =E73+E74 -> -0.32273234 | F72: =F73+F74 -> -0.11109541 | G72: =G73+G74 -> -0.095324618 | H72: =H73+H74 -> 0.041507412 | I72: =I73+I74 -> 0.022961488 | J72: =J73+J74 -> 0.020104703 | K72: =K73+K74 -> 0.014232422 | L72: =L73+L74 -> 0.012260036 | ... BL72: =BL73+BL74 -> 0
C73: Lead Acquistion | E73: =-Leadsheet!E56-Leadsheet!E57*Leadsheet!E10 -> 0
C74: Sharing Performance | E74: =SUM(E75:E82) -> -0.32273234 | F74: =SUM(F75:F82) -> -0.11109541 | G74: =SUM(G75:G82) -> -0.095324618 | H74: =SUM(H75:H82) -> 0.041507412 | I74: =SUM(I75:I82) -> 0.022961488 | J74: =SUM(J75:J82) -> 0.020104703 | K74: =SUM(K75:K82) -> 0.014232422 | L74: =SUM(L75:L82) -> 0.012260036 | ... BL74: =SUM(BL75:BL82) -> 0
C75: Sharing CII (only) | E75: =-SUM(E58:E58)*Leadsheet!$E$50 -> 0 | F75: =-SUM(F58:F58)*Leadsheet!$E$50 -> 0 | G75: =-SUM(G58:G58)*Leadsheet!$E$50 -> 0 | H75: =-SUM(H58:H58)*Leadsheet!$E$50 -> 0 | I75: =-SUM(I58:I58)*Leadsheet!$E$50 -> 0 | J75: =-SUM(J58:J58)*Leadsheet!$E$50 -> 0 | K75: =-SUM(K58:K58)*Leadsheet!$E$50 -> 0 | L75: =-SUM(L58:L58)*Leadsheet!$E$50 -> 0 | ... BL75: =-SUM(BL58:BL58)*Leadsheet!$E$50 -> 0
C76: Sharing COF (only) | E76: =-E59*Leadsheet!$E$51 -> 0 | F76: =-F59*Leadsheet!$E$51 -> 0 | G76: =-G59*Leadsheet!$E$51 -> 0 | H76: =-H59*Leadsheet!$E$51 -> 0 | I76: =-I59*Leadsheet!$E$51 -> 0 | J76: =-J59*Leadsheet!$E$51 -> 0 | K76: =-K59*Leadsheet!$E$51 -> 0 | L76: =-L59*Leadsheet!$E$51 -> 0 | ... BL76: =-BL59*Leadsheet!$E$51 -> 0
C77: Sharing NFI (only) | E77: =-E61*Leadsheet!$E$52 -> 0 | F77: =-F61*Leadsheet!$E$52 -> 0 | G77: =-G61*Leadsheet!$E$52 -> 0 | H77: =-H61*Leadsheet!$E$52 -> 0 | I77: =-I61*Leadsheet!$E$52 -> 0 | J77: =-J61*Leadsheet!$E$52 -> 0 | K77: =-K61*Leadsheet!$E$52 -> 0 | L77: =-L61*Leadsheet!$E$52 -> 0 | ... BL77: =-BL61*Leadsheet!$E$52 -> 0
C78: Sharing Risk DPD90+ (Only) | E78: =IF(E5>$D$7,0,Leadsheet!$E$53*(E31-SUM(D31:D39)+SUM(E32:E40))) -> 0 | F78: =IF(F5>$D$7,0,Leadsheet!$E$53*(F31-SUM(E31:E39)+SUM(F32:F40))) -> 0 | G78: =IF(G5>$D$7,0,Leadsheet!$E$53*(G31-SUM(F31:F39)+SUM(G32:G40))) -> 0 | H78: =IF(H5>$D$7,0,Leadsheet!$E$53*(H31-SUM(G31:G39)+SUM(H32:H40))) -> 0 | I78: =IF(I5>$D$7,0,Leadsheet!$E$53*(I31-SUM(H31:H39)+SUM(I32:I40))) -> 0 | J78: =IF(J5>$D$7,0,Leadsheet!$E$53*(J31-SUM(I31:I39)+SUM(J32:J40))) -> 0 | K78: =IF(K5>$D$7,0,Leadsheet!$E$53*(K31-SUM(J31:J39)+SUM(K32:K40))) -> 0 | L78: =IF(L5>$D$7,0,Leadsheet!$E$53*(L31-SUM(K31:K39)+SUM(L32:L40))) -> 0 | ... BL78: =IF(BL5>$D$7,0,Leadsheet!$E$53*(BL31-SUM(BK31:BK39)+SUM(BL32:BL40))) -> 0
C79: Sharing Risk DPD180+ (only) | E79: =IF(E5>$D$7,0,Leadsheet!$E$54*(E34-SUM(D34:D39)+SUM(E35:E40))) -> 0 | F79: =IF(F5>$D$7,0,Leadsheet!$E$54*(F34-SUM(E34:E39)+SUM(F35:F40))) -> 0 | G79: =IF(G5>$D$7,0,Leadsheet!$E$54*(G34-SUM(F34:F39)+SUM(G35:G40))) -> 0 | H79: =IF(H5>$D$7,0,Leadsheet!$E$54*(H34-SUM(G34:G39)+SUM(H35:H40))) -> 0 | I79: =IF(I5>$D$7,0,Leadsheet!$E$54*(I34-SUM(H34:H39)+SUM(I35:I40))) -> 0 | J79: =IF(J5>$D$7,0,Leadsheet!$E$54*(J34-SUM(I34:I39)+SUM(J35:J40))) -> 0 | K79: =IF(K5>$D$7,0,Leadsheet!$E$54*(K34-SUM(J34:J39)+SUM(K35:K40))) -> 0 | L79: =IF(L5>$D$7,0,Leadsheet!$E$54*(L34-SUM(K34:K39)+SUM(L35:L40))) -> 0 | ... BL79: =IF(BL5>$D$7,0,Leadsheet!$E$54*(BL34-SUM(BK34:BK39)+SUM(BL35:BL40))) -> 0
C80: Risk cap to CAKE | G80: =IF(SUM(SAP_Speadsheet!E78:BL79)>(SAP_Speadsheet!E84*Leadsheet!E53+SAP_Speadsheet!E84*Leadsheet!E54),-Leadsheet!E10*Leadsheet!E55,-SUM(SAP_Speadsheet!E78:BL79)) -> 0
C81: Sharing TOI+ Risk DPD90+ | E81: =IF(E5>$D$7,0,Leadsheet!$E$47*(-(E57+E61)+E31-SUM(D31:D39)+SUM(E32:E40))) -> -0.32273234 | F81: =IF(F5>$D$7,0,Leadsheet!$E$47*(-(F57+F61)+F31-SUM(E31:E39)+SUM(F32:F40))) -> -0.11109541 | G81: =IF(G5>$D$7,0,Leadsheet!$E$47*(-(G57+G61)+G31-SUM(F31:F39)+SUM(G32:G40))) -> -0.095324618 | H81: =IF(H5>$D$7,0,Leadsheet!$E$47*(-(H57+H61)+H31-SUM(G31:G39)+SUM(H32:H40))) -> 0.041507412 | I81: =IF(I5>$D$7,0,Leadsheet!$E$47*(-(I57+I61)+I31-SUM(H31:H39)+SUM(I32:I40))) -> 0.022961488 | J81: =IF(J5>$D$7,0,Leadsheet!$E$47*(-(J57+J61)+J31-SUM(I31:I39)+SUM(J32:J40))) -> 0.020104703 | K81: =IF(K5>$D$7,0,Leadsheet!$E$47*(-(K57+K61)+K31-SUM(J31:J39)+SUM(K32:K40))) -> 0.014232422 | L81: =IF(L5>$D$7,0,Leadsheet!$E$47*(-(L57+L61)+L31-SUM(K31:K39)+SUM(L32:L40))) -> 0.012260036 | ... BL81: =IF(BL5>$D$7,0,Leadsheet!$E$47*(-(BL57+BL61)+BL31-SUM(BK31:BK39)+SUM(BL32:BL40))) -> 0
C82: Sharing TOI+ Risk DPD180+ | E82: =IF(E5>$D$7,0,Leadsheet!$E$48*(-(E57+E61)+E34-SUM(D34:D39)+SUM(E35:E40))) -> 0 | F82: =IF(F5>$D$7,0,Leadsheet!$E$48*(-(F57+F61)+F34-SUM(E34:E39)+SUM(F35:F40))) -> 0 | G82: =IF(G5>$D$7,0,Leadsheet!$E$48*(-(G57+G61)+G34-SUM(F34:F39)+SUM(G35:G40))) -> 0 | H82: =IF(H5>$D$7,0,Leadsheet!$E$48*(-(H57+H61)+H34-SUM(G34:G39)+SUM(H35:H40))) -> 0 | I82: =IF(I5>$D$7,0,Leadsheet!$E$48*(-(I57+I61)+I34-SUM(H34:H39)+SUM(I35:I40))) -> 0 | J82: =IF(J5>$D$7,0,Leadsheet!$E$48*(-(J57+J61)+J34-SUM(I34:I39)+SUM(J35:J40))) -> 0 | K82: =IF(K5>$D$7,0,Leadsheet!$E$48*(-(K57+K61)+K34-SUM(J34:J39)+SUM(K35:K40))) -> 0 | L82: =IF(L5>$D$7,0,Leadsheet!$E$48*(-(L57+L61)+L34-SUM(K34:K39)+SUM(L35:L40))) -> 0 | ... BL82: =IF(BL5>$D$7,0,Leadsheet!$E$48*(-(BL57+BL61)+BL34-SUM(BK34:BK39)+SUM(BL35:BL40))) -> 0
B85: Marketing | E85: =E86+E67 -> -0.064333234
C86: Marketing_acquisition | E86: =-Leadsheet!E61 -> -0.064333234
B88: UW & Disbursal | E88: =E89+E90+E91 -> -0.066756457
C89: Underwriting Cost | E89: =-Leadsheet!E63/Leadsheet!E66/Leadsheet!E67-Leadsheet!E64 -> -0.062756457
C90: Disbursement cost | E90: =-Leadsheet!E65 -> -0.004
C91: DOP cost | E91: =-Leadsheet!E64 -> 0
C93: Expense Increase | E93: 1 | F93: =IF(F$5>$D$7,0,IF(F$5<12,1,(1+Leadsheet!$E$43)^(ROUNDDOWN(F$5/12,0)))) -> 1 | G93: =IF(G$5>$D$7,0,IF(G$5<12,1,(1+Leadsheet!$E$43)^(ROUNDDOWN(G$5/12,0)))) -> 1 | H93: =IF(H$5>$D$7,0,IF(H$5<12,1,(1+Leadsheet!$E$43)^(ROUNDDOWN(H$5/12,0)))) -> 1 | I93: =IF(I$5>$D$7,0,IF(I$5<12,1,(1+Leadsheet!$E$43)^(ROUNDDOWN(I$5/12,0)))) -> 1 | J93: =IF(J$5>$D$7,0,IF(J$5<12,1,(1+Leadsheet!$E$43)^(ROUNDDOWN(J$5/12,0)))) -> 1 | K93: =IF(K$5>$D$7,0,IF(K$5<12,1,(1+Leadsheet!$E$43)^(ROUNDDOWN(K$5/12,0)))) -> 1 | L93: =IF(L$5>$D$7,0,IF(L$5<12,1,(1+Leadsheet!$E$43)^(ROUNDDOWN(L$5/12,0)))) -> 1 | M93: =IF(M$5>$D$7,0,IF(M$5<12,1,(1+Leadsheet!$E$43)^(ROUNDDOWN(M$5/12,0)))) -> 1 | ... BL93: =IF(BL$5>$D$7,0,IF(BL$5<12,1,(1+Leadsheet!$E$43)^(ROUNDDOWN(BL$5/12,0)))) -> 0
B95: Collection & AMC | E95: =SUM(E96:E97) -> -0.008 | F95: =SUM(F96:F97) -> -0.0070732015 | G95: =SUM(G96:G97) -> -0.0066917228 | H95: =SUM(H96:H97) -> -0.0063102441 | I95: =SUM(I96:I97) -> -0.0061235172 | J95: =SUM(J96:J97) -> -0.0059367903 | K95: =SUM(K96:K97) -> -0.0057500634 | L95: =SUM(L96:L97) -> -0.0055633365 | ... BL95: =SUM(BL96:BL97) -> 0
C96: Early collections | E96: =-IF(E5>Leadsheet!$E$12,Leadsheet!$E$71*E$93*E44/$D$44,Leadsheet!$E$71*E$93*D16) -> -0.008 | F96: =-IF(F5>Leadsheet!$E$12,Leadsheet!$E$71*F$93*F44/$D$44,Leadsheet!$E$71*F$93*E16) -> -0.0070732015 | G96: =-IF(G5>Leadsheet!$E$12,Leadsheet!$E$71*G$93*G44/$D$44,Leadsheet!$E$71*G$93*F16) -> -0.0066917228 | H96: =-IF(H5>Leadsheet!$E$12,Leadsheet!$E$71*H$93*H44/$D$44,Leadsheet!$E$71*H$93*G16) -> -0.0063102441 | I96: =-IF(I5>Leadsheet!$E$12,Leadsheet!$E$71*I$93*I44/$D$44,Leadsheet!$E$71*I$93*H16) -> -0.0061235172 | J96: =-IF(J5>Leadsheet!$E$12,Leadsheet!$E$71*J$93*J44/$D$44,Leadsheet!$E$71*J$93*I16) -> -0.0059367903 | K96: =-IF(K5>Leadsheet!$E$12,Leadsheet!$E$71*K$93*K44/$D$44,Leadsheet!$E$71*K$93*J16) -> -0.0057500634 | L96: =-IF(L5>Leadsheet!$E$12,Leadsheet!$E$71*L$93*L44/$D$44,Leadsheet!$E$71*L$93*K16) -> -0.0055633365 | ... BL96: =-IF(BL5>Leadsheet!$E$12,Leadsheet!$E$71*BL$93*BL44/$D$44,Leadsheet!$E$71*BL$93*BK16) -> 0
C97: AMC
B99: After sale service | E99: =SUM(E100:E101) -> -0.00088415019 | F99: =SUM(F100:F101) -> -0.00083646535 | G99: =SUM(G100:G101) -> -0.00078878051 | H99: =SUM(H100:H101) -> -0.00076543965 | I99: =SUM(I100:I101) -> -0.00074209878 | J99: =SUM(J100:J101) -> -0.00071875792 | K99: =SUM(K100:K101) -> -0.00069541706 | L99: =SUM(L100:L101) -> -0.0006720762 | ... BL99: =SUM(BL100:BL101) -> 0
C100: SMS & Email | E100: =IF(E5>Leadsheet!$E$12,0,-E16*Leadsheet!$E$78) -> -0.00088415019 | F100: =IF(F5>Leadsheet!$E$12,0,-F16*Leadsheet!$E$78) -> -0.00083646535 | G100: =IF(G5>Leadsheet!$E$12,0,-G16*Leadsheet!$E$78) -> -0.00078878051 | H100: =IF(H5>Leadsheet!$E$12,0,-H16*Leadsheet!$E$78) -> -0.00076543965 | I100: =IF(I5>Leadsheet!$E$12,0,-I16*Leadsheet!$E$78) -> -0.00074209878 | J100: =IF(J5>Leadsheet!$E$12,0,-J16*Leadsheet!$E$78) -> -0.00071875792 | K100: =IF(K5>Leadsheet!$E$12,0,-K16*Leadsheet!$E$78) -> -0.00069541706 | L100: =IF(L5>Leadsheet!$E$12,0,-L16*Leadsheet!$E$78) -> -0.0006720762 | ... BL100: =IF(BL5>Leadsheet!$E$12,0,-BL16*Leadsheet!$E$78) -> 0
B103: OVERHEAD EXPENSES | E103: =SUM(E104:E107) -> -0.048800211 | F103: =SUM(F104:F107) -> -0.043146716 | G103: =SUM(G104:G107) -> -0.040819686 | H103: =SUM(H104:H107) -> -0.038492655 | I103: =SUM(I104:I107) -> -0.037353616 | J103: =SUM(J104:J107) -> -0.036214577 | K103: =SUM(K104:K107) -> -0.035075538 | L103: =SUM(L104:L107) -> -0.033936499 | ... BL103: =SUM(BL104:BL107) -> 0
C104: Direct HR | E104: =-IF(E$5>Leadsheet!$E$12,0,Leadsheet!$E81*SAP_Speadsheet!E$93*D$16) -> -0.0094474945 | F104: =-IF(F$5>Leadsheet!$E$12,0,Leadsheet!$E81*SAP_Speadsheet!F$93*E$16) -> -0.008353004 | G104: =-IF(G$5>Leadsheet!$E$12,0,Leadsheet!$E81*SAP_Speadsheet!G$93*F$16) -> -0.0079025017 | H104: =-IF(H$5>Leadsheet!$E$12,0,Leadsheet!$E81*SAP_Speadsheet!H$93*G$16) -> -0.0074519995 | I104: =-IF(I$5>Leadsheet!$E$12,0,Leadsheet!$E81*SAP_Speadsheet!I$93*H$16) -> -0.0072314868 | J104: =-IF(J$5>Leadsheet!$E$12,0,Leadsheet!$E81*SAP_Speadsheet!J$93*I$16) -> -0.0070109742 | K104: =-IF(K$5>Leadsheet!$E$12,0,Leadsheet!$E81*SAP_Speadsheet!K$93*J$16) -> -0.0067904615 | L104: =-IF(L$5>Leadsheet!$E$12,0,Leadsheet!$E81*SAP_Speadsheet!L$93*K$16) -> -0.0065699488 | ... BL104: =-IF(BL$5>Leadsheet!$E$12,0,Leadsheet!$E81*SAP_Speadsheet!BL$93*BK$16) -> 0
C105: Indirect HR | E105: =-IF(E$5>Leadsheet!$E$12,0,Leadsheet!$E82*SAP_Speadsheet!E$93*D$16) -> -0.015343086 | F105: =-IF(F$5>Leadsheet!$E$12,0,Leadsheet!$E82*SAP_Speadsheet!F$93*E$16) -> -0.013565592 | G105: =-IF(G$5>Leadsheet!$E$12,0,Leadsheet!$E82*SAP_Speadsheet!G$93*F$16) -> -0.01283396 | H105: =-IF(H$5>Leadsheet!$E$12,0,Leadsheet!$E82*SAP_Speadsheet!H$93*G$16) -> -0.012102327 | I105: =-IF(I$5>Leadsheet!$E$12,0,Leadsheet!$E82*SAP_Speadsheet!I$93*H$16) -> -0.011744206 | J105: =-IF(J$5>Leadsheet!$E$12,0,Leadsheet!$E82*SAP_Speadsheet!J$93*I$16) -> -0.011386085 | K105: =-IF(K$5>Leadsheet!$E$12,0,Leadsheet!$E82*SAP_Speadsheet!K$93*J$16) -> -0.011027965 | L105: =-IF(L$5>Leadsheet!$E$12,0,Leadsheet!$E82*SAP_Speadsheet!L$93*K$16) -> -0.010669844 | ... BL105: =-IF(BL$5>Leadsheet!$E$12,0,Leadsheet!$E82*SAP_Speadsheet!BL$93*BK$16) -> 0
C106: IT | E106: =-IF(E$5>Leadsheet!$E$12,0,Leadsheet!$E83*SAP_Speadsheet!E$93*D$16) -> -0.011893836 | F106: =-IF(F$5>Leadsheet!$E$12,0,Leadsheet!$E83*SAP_Speadsheet!F$93*E$16) -> -0.010515938 | G106: =-IF(G$5>Leadsheet!$E$12,0,Leadsheet!$E83*SAP_Speadsheet!G$93*F$16) -> -0.0099487819 | H106: =-IF(H$5>Leadsheet!$E$12,0,Leadsheet!$E83*SAP_Speadsheet!H$93*G$16) -> -0.0093816263 | I106: =-IF(I$5>Leadsheet!$E$12,0,Leadsheet!$E83*SAP_Speadsheet!I$93*H$16) -> -0.0091040139 | J106: =-IF(J$5>Leadsheet!$E$12,0,Leadsheet!$E83*SAP_Speadsheet!J$93*I$16) -> -0.0088264015 | K106: =-IF(K$5>Leadsheet!$E$12,0,Leadsheet!$E83*SAP_Speadsheet!K$93*J$16) -> -0.0085487891 | L106: =-IF(L$5>Leadsheet!$E$12,0,Leadsheet!$E83*SAP_Speadsheet!L$93*K$16) -> -0.0082711767 | ... BL106: =-IF(BL$5>Leadsheet!$E$12,0,Leadsheet!$E83*SAP_Speadsheet!BL$93*BK$16) -> 0
C107: Other support units | E107: =-IF(E$5>Leadsheet!$E$12,0,Leadsheet!$E84*SAP_Speadsheet!E$93*D$16) -> -0.012115794 | F107: =-IF(F$5>Leadsheet!$E$12,0,Leadsheet!$E84*SAP_Speadsheet!F$93*E$16) -> -0.010712182 | G107: =-IF(G$5>Leadsheet!$E$12,0,Leadsheet!$E84*SAP_Speadsheet!G$93*F$16) -> -0.010134442 | H107: =-IF(H$5>Leadsheet!$E$12,0,Leadsheet!$E84*SAP_Speadsheet!H$93*G$16) -> -0.0095567025 | I107: =-IF(I$5>Leadsheet!$E$12,0,Leadsheet!$E84*SAP_Speadsheet!I$93*H$16) -> -0.0092739094 | J107: =-IF(J$5>Leadsheet!$E$12,0,Leadsheet!$E84*SAP_Speadsheet!J$93*I$16) -> -0.0089911164 | K107: =-IF(K$5>Leadsheet!$E$12,0,Leadsheet!$E84*SAP_Speadsheet!K$93*J$16) -> -0.0087083233 | L107: =-IF(L$5>Leadsheet!$E$12,0,Leadsheet!$E84*SAP_Speadsheet!L$93*K$16) -> -0.0084255302 | ... BL107: =-IF(BL$5>Leadsheet!$E$12,0,Leadsheet!$E84*SAP_Speadsheet!BL$93*BK$16) -> 0
B110: Provision
C111: Provision Rate | E111: IFRS | F111: VAS360 | G111: VAS180
C112: B0 | E112: =Leadsheet!F91 -> 0.02700992 | F112: 0.0075 | G112: 0.0075
C113: B1 | E113: =Leadsheet!F92 -> 0.52960627 | F113: 0.0575 | G113: 0.0575
C114: B2 | E114: =Leadsheet!F93 -> 0.79003379 | F114: 0.0575 | G114: 0.0575
C115: B3 | E115: =Leadsheet!F94 -> 0.868169 | F115: 0.0575 | G115: 0.0575
C116: B4 | E116: =Leadsheet!F95 -> 0.87061911 | F116: 0.2075 | G116: 0.2075
C117: B5 | E117: =Leadsheet!F96 -> 0.89478841 | F117: 0.2075 | G117: 0.2075
C118: B6 | E118: =Leadsheet!F97 -> 0.89478841 | F118: 0.2075 | G118: 0.2075
C119: B7 | E119: =Leadsheet!F98 -> 0.92246228 | F119: 0.5075 | G119: 0.5075
C120: B8 | E120: =Leadsheet!F99 -> 0.960498 | F120: 0.5075 | G120: 1
C121: B9 | E121: =Leadsheet!F100 -> 0.960498 | F121: 0.5075
C122: B10 | E122: =Leadsheet!F101 -> 0.960498 | F122: 0.5075
C123: B11 | E123: =Leadsheet!F102 -> 0.960498 | F123: 0.5075
C124: B12 | E124: =Leadsheet!F103 -> 0.960498 | F124: 0.5075
C125: B13 | E125: =Leadsheet!F104 -> 0.960498 | F125: 1
C126: B14+ | E126: =Leadsheet!F105 -> 0.9801 | F126: 1
...

Sheet Saleplan&PnL
C1: PROFIT & LOSS 60M
C2: I. | D2: SALES PLAN
C4: Business month | D4: 45658 | E4: =EOMONTH(D4,1) -> 45716 | F4: =EOMONTH(E4,1) -> 45747 | G4: =EOMONTH(F4,1) -> 45777 | H4: =EOMONTH(G4,1) -> 45808 | I4: =EOMONTH(H4,1) -> 45838 | J4: =EOMONTH(I4,1) -> 45869 | K4: =EOMONTH(J4,1) -> 45900 | L4: =EOMONTH(K4,1) -> 45930 | ... BL4: =EOMONTH(BK4,1) -> 47514
C5: Don't delete | D5: =YEAR(D4) -> 2025 | E5: =YEAR(E4) -> 2025 | F5: =YEAR(F4) -> 2025 | G5: =YEAR(G4) -> 2025 | H5: =YEAR(H4) -> 2025 | I5: =YEAR(I4) -> 2025 | J5: =YEAR(J4) -> 2025 | K5: =YEAR(K4) -> 2025 | ... BL5: =YEAR(BL4) -> 2030
C6: New disbursement (bVND) | J6: =DATA!E19/10^9 -> 913.80154 | K6: =DATA!E18/10^9 -> 847.45432 | L6: =DATA!E17/10^9 -> 1159.8268
C8: II. | D8: PROFIT & LOSS
C10: FISCAL YEAR | E10: Total | F10: =YEAR(D4) -> 2025 | G10: =F10+1 -> 2026 | H10: =G10+1 -> 2027 | I10: =H10+1 -> 2028 | J10: =I10+1 -> 2029 | K10: =J10+1 -> 2030
E11: bVND | F11: bVND | G11: bVND | H11: bVND | I11: bVND | J11: bVND | K11: bVND
C13: NEW DISBURSAL | E13: =SUM(F13:O13) -> 2921.0826 | F13: =SUMIF($D$5:$BL$5,F$10,$D$6:$BL$6) -> 2921.0826 | G13: =SUMIF($D$5:$BL$5,G$10,$D$6:$BL$6) -> 0 | H13: =SUMIF($D$5:$BL$5,H$10,$D$6:$BL$6) -> 0 | I13: =SUMIF($D$5:$BL$5,I$10,$D$6:$BL$6) -> 0 | J13: =SUMIF($D$5:$BL$5,J$10,$D$6:$BL$6) -> 0 | K13: =SUMIF($D$5:$BL$5,K$10,$D$6:$BL$6) -> 0
C14: Monthly disbursement | E14: =AVERAGE(D6:AM6) -> 973.69421 | F14: =IFERROR(F13/COUNTIFS($D$5:$BL$5,F10,$D$6:$BL$6,"<>"&""),0) -> 973.69421 | G14: =IFERROR(G13/COUNTIFS($D$5:$BL$5,G10,$D$6:$BL$6,"<>"&""),0) -> 0 | H14: =IFERROR(H13/COUNTIFS($D$5:$BL$5,H10,$D$6:$BL$6,"<>"&""),0) -> 0 | I14: =IFERROR(I13/COUNTIFS($D$5:$BL$5,I10,$D$6:$BL$6,"<>"&""),0) -> 0 | J14: =IFERROR(J13/COUNTIFS($D$5:$BL$5,J10,$D$6:$BL$6,"<>"&""),0) -> 0 | K14: =IFERROR(K13/COUNTIFS($D$5:$BL$5,K10,$D$6:$BL$6,"<>"&""),0) -> 0
C16: EOP | F16: =OFFSET(PnL_Speadsheet!$A$7,0,MATCH(DATE('Saleplan&PnL'!F$10,12,31),PnL_Speadsheet!$B$4:$BI$4,0))/1000 -> 1633.2676 | G16: =OFFSET(PnL_Speadsheet!$A$7,0,MATCH(DATE('Saleplan&PnL'!G$10,12,31),PnL_Speadsheet!$B$4:$BI$4,0))/1000 -> 461.60411 | H16: =OFFSET(PnL_Speadsheet!$A$7,0,MATCH(DATE('Saleplan&PnL'!H$10,12,31),PnL_Speadsheet!$B$4:$BI$4,0))/1000 -> 0 | I16: =OFFSET(PnL_Speadsheet!$A$7,0,MATCH(DATE('Saleplan&PnL'!I$10,12,31),PnL_Speadsheet!$B$4:$BI$4,0))/1000 -> 0 | J16: =OFFSET(PnL_Speadsheet!$A$7,0,MATCH(DATE('Saleplan&PnL'!J$10,12,31),PnL_Speadsheet!$B$4:$BI$4,0))/1000 -> 0 | K16: =IFERROR(OFFSET(PnL_Speadsheet!$A$7,0,MATCH(DATE('Saleplan&PnL'!K$10,12,31),PnL_Speadsheet!$B$4:$BI$4,0))/1000,0) -> 0
C17: ADB | E17: =IFERROR(SUM(PnL_Speadsheet!B8:AK8)/1000/COUNTIF(PnL_Speadsheet!B8:BI8,"<>0"),0) -> 835.00498 | F17: =IFERROR(SUMIF(PnL_Speadsheet!$B$3:$BI$3,F$10,PnL_Speadsheet!$B8:$BI8)/1000/COUNTIFS(PnL_Speadsheet!$B$3:$BI$3,'Saleplan&PnL'!F$10,PnL_Speadsheet!$B$8:$BI$8,"<>0"),0) -> 1735.127 | G17: =IFERROR(SUMIF(PnL_Speadsheet!$B$3:$BI$3,G$10,PnL_Speadsheet!$B8:$BI8)/1000/COUNTIFS(PnL_Speadsheet!$B$3:$BI$3,'Saleplan&PnL'!G$10,PnL_Speadsheet!$B$8:$BI$8,"<>0"),0) -> 658.74919 | H17: =IFERROR(SUMIF(PnL_Speadsheet!$B$3:$BI$3,H$10,PnL_Speadsheet!$B8:$BI8)/1000/COUNTIFS(PnL_Speadsheet!$B$3:$BI$3,'Saleplan&PnL'!H$10,PnL_Speadsheet!$B$8:$BI$8,"<>0"),0) -> 13.589247 | I17: =IFERROR(SUMIF(PnL_Speadsheet!$B$3:$BI$3,I$10,PnL_Speadsheet!$B8:$BI8)/1000/COUNTIFS(PnL_Speadsheet!$B$3:$BI$3,'Saleplan&PnL'!I$10,PnL_Speadsheet!$B$8:$BI$8,"<>0"),0) -> 0 | J17: =IFERROR(SUMIF(PnL_Speadsheet!$B$3:$BI$3,J$10,PnL_Speadsheet!$B8:$BI8)/1000/COUNTIFS(PnL_Speadsheet!$B$3:$BI$3,'Saleplan&PnL'!J$10,PnL_Speadsheet!$B$8:$BI$8,"<>0"),0) -> 0 | K17: =IFERROR(SUMIF(PnL_Speadsheet!$B$3:$BI$3,K$10,PnL_Speadsheet!$B8:$BI8)/1000/COUNTIFS(PnL_Speadsheet!$B$3:$BI$3,'Saleplan&PnL'!K$10,PnL_Speadsheet!$B$8:$BI$8,"<>0"),0) -> 0
C19: TOI | E19: =SUM(F19:O19) -> 714.50738 | F19: =SUMIF(PnL_Speadsheet!$B$3:$BI$3,F$10,PnL_Speadsheet!$B9:$BI9)/1000 -> 515.74448 | G19: =SUMIF(PnL_Speadsheet!$B$3:$BI$3,G$10,PnL_Speadsheet!$B9:$BI9)/1000 -> 199.07574 | H19: =SUMIF(PnL_Speadsheet!$B$3:$BI$3,H$10,PnL_Speadsheet!$B9:$BI9)/1000 -> -0.31283769 | I19: =SUMIF(PnL_Speadsheet!$B$3:$BI$3,I$10,PnL_Speadsheet!$B9:$BI9)/1000 -> 0 | J19: =SUMIF(PnL_Speadsheet!$B$3:$BI$3,J$10,PnL_Speadsheet!$B9:$BI9)/1000 -> 0 | K19: =SUMIF(PnL_Speadsheet!$B$3:$BI$3,K$10,PnL_Speadsheet!$B9:$BI9)/1000 -> 0
C20: NII | E20: =SUM(F20:O20) -> 528.83124 | F20: =SUMIF(PnL_Speadsheet!$B$3:$BI$3,F$10,PnL_Speadsheet!$B11:$BI11)/1000 -> 339.59453 | G20: =SUMIF(PnL_Speadsheet!$B$3:$BI$3,G$10,PnL_Speadsheet!$B11:$BI11)/1000 -> 189.54955 | H20: =SUMIF(PnL_Speadsheet!$B$3:$BI$3,H$10,PnL_Speadsheet!$B11:$BI11)/1000 -> -0.31283769 | I20: =SUMIF(PnL_Speadsheet!$B$3:$BI$3,I$10,PnL_Speadsheet!$B11:$BI11)/1000 -> 0 | J20: =SUMIF(PnL_Speadsheet!$B$3:$BI$3,J$10,PnL_Speadsheet!$B11:$BI11)/1000 -> 0 | K20: =SUMIF(PnL_Speadsheet!$B$3:$BI$3,K$10,PnL_Speadsheet!$B11:$BI11)/1000 -> 0
C21: NFI | E21: =SUM(F21:O21) -> 185.67614 | F21: =SUMIF(PnL_Speadsheet!$B$3:$BI$3,F$10,PnL_Speadsheet!$B14:$BI14)/1000 -> 176.14995 | G21: =SUMIF(PnL_Speadsheet!$B$3:$BI$3,G$10,PnL_Speadsheet!$B14:$BI14)/1000 -> 9.5261898 | H21: =SUMIF(PnL_Speadsheet!$B$3:$BI$3,H$10,PnL_Speadsheet!$B14:$BI14)/1000 -> 0 | I21: =SUMIF(PnL_Speadsheet!$B$3:$BI$3,I$10,PnL_Speadsheet!$B14:$BI14)/1000 -> 0 | J21: =SUMIF(PnL_Speadsheet!$B$3:$BI$3,J$10,PnL_Speadsheet!$B14:$BI14)/1000 -> 0 | K21: =SUMIF(PnL_Speadsheet!$B$3:$BI$3,K$10,PnL_Speadsheet!$B14:$BI14)/1000 -> 0
C22: Other TOI | E22: =SUM(F22:O22) -> 0 | F22: =SUMIF(PnL_Speadsheet!$B$3:$BI$3,F$10,PnL_Speadsheet!$B18:$BI18)/1000 -> 0 | G22: =SUMIF(PnL_Speadsheet!$B$3:$BI$3,G$10,PnL_Speadsheet!$B18:$BI18)/1000 -> 0 | H22: =SUMIF(PnL_Speadsheet!$B$3:$BI$3,H$10,PnL_Speadsheet!$B18:$BI18)/1000 -> 0 | I22: =SUMIF(PnL_Speadsheet!$B$3:$BI$3,I$10,PnL_Speadsheet!$B18:$BI18)/1000 -> 0 | J22: =SUMIF(PnL_Speadsheet!$B$3:$BI$3,J$10,PnL_Speadsheet!$B18:$BI18)/1000 -> 0 | K22: =SUMIF(PnL_Speadsheet!$B$3:$BI$3,K$10,PnL_Speadsheet!$B18:$BI18)/1000 -> 0
C23: PROVISION | E23: =SUM(F23:O23) -> -448.97487 | F23: =SUMIF(PnL_Speadsheet!$B$3:$BI$3,F$10,PnL_Speadsheet!$B31:$BI31)/1000 -> -308.09718 | G23: =SUMIF(PnL_Speadsheet!$B$3:$BI$3,G$10,PnL_Speadsheet!$B31:$BI31)/1000 -> -138.00738 | H23: =SUMIF(PnL_Speadsheet!$B$3:$BI$3,H$10,PnL_Speadsheet!$B31:$BI31)/1000 -> -2.8703149 | I23: =SUMIF(PnL_Speadsheet!$B$3:$BI$3,I$10,PnL_Speadsheet!$B31:$BI31)/1000 -> 0 | J23: =SUMIF(PnL_Speadsheet!$B$3:$BI$3,J$10,PnL_Speadsheet!$B31:$BI31)/1000 -> 0 | K23: =SUMIF(PnL_Speadsheet!$B$3:$BI$3,K$10,PnL_Speadsheet!$B31:$BI31)/1000 -> 0
C24: OPEX | E24: =SUM(F24:O24) -> -189.91672 | F24: =SUMIF(PnL_Speadsheet!$B$3:$BI$3,F$10,PnL_Speadsheet!$B19:$BI19)/1000 -> -151.88943 | G24: =SUMIF(PnL_Speadsheet!$B$3:$BI$3,G$10,PnL_Speadsheet!$B19:$BI19)/1000 -> -37.33756 | H24: =SUMIF(PnL_Speadsheet!$B$3:$BI$3,H$10,PnL_Speadsheet!$B19:$BI19)/1000 -> -0.68973811 | I24: =SUMIF(PnL_Speadsheet!$B$3:$BI$3,I$10,PnL_Speadsheet!$B19:$BI19)/1000 -> 0 | J24: =SUMIF(PnL_Speadsheet!$B$3:$BI$3,J$10,PnL_Speadsheet!$B19:$BI19)/1000 -> 0 | K24: =SUMIF(PnL_Speadsheet!$B$3:$BI$3,K$10,PnL_Speadsheet!$B19:$BI19)/1000 -> 0
C25: Sales incentives | E25: =SUM(F25:O25) -> -58.749777 | F25: =(SUMIF(PnL_Speadsheet!$B$3:$BI$3,F$10,PnL_Speadsheet!$B21:$BI22)/1000+SUMIF(PnL_Speadsheet!$B$3:$BI$3,F$10,PnL_Speadsheet!$B22:$BI22)/1000) -> -84.40678 | G25: =(SUMIF(PnL_Speadsheet!$B$3:$BI$3,G$10,PnL_Speadsheet!$B21:$BI22)/1000+SUMIF(PnL_Speadsheet!$B$3:$BI$3,G$10,PnL_Speadsheet!$B22:$BI22)/1000) -> 25.619843 | H25: =(SUMIF(PnL_Speadsheet!$B$3:$BI$3,H$10,PnL_Speadsheet!$B21:$BI22)/1000+SUMIF(PnL_Speadsheet!$B$3:$BI$3,H$10,PnL_Speadsheet!$B22:$BI22)/1000) -> 0.037160601 | I25: =(SUMIF(PnL_Speadsheet!$B$3:$BI$3,I$10,PnL_Speadsheet!$B21:$BI22)/1000+SUMIF(PnL_Speadsheet!$B$3:$BI$3,I$10,PnL_Speadsheet!$B22:$BI22)/1000) -> 0 | J25: =(SUMIF(PnL_Speadsheet!$B$3:$BI$3,J$10,PnL_Speadsheet!$B21:$BI22)/1000+SUMIF(PnL_Speadsheet!$B$3:$BI$3,J$10,PnL_Speadsheet!$B22:$BI22)/1000) -> 0 | K25: =(SUMIF(PnL_Speadsheet!$B$3:$BI$3,K$10,PnL_Speadsheet!$B21:$BI22)/1000+SUMIF(PnL_Speadsheet!$B$3:$BI$3,K$10,PnL_Speadsheet!$B22:$BI22)/1000) -> 0
C26: Marketing | E26: =SUM(F26:O26) -> -11.615044 | F26: =SUMIF(PnL_Speadsheet!$B$3:$BI$3,F$10,PnL_Speadsheet!$B23:$BI23)/1000 -> -11.615044 | G26: =SUMIF(PnL_Speadsheet!$B$3:$BI$3,G$10,PnL_Speadsheet!$B23:$BI23)/1000 -> 0 | H26: =SUMIF(PnL_Speadsheet!$B$3:$BI$3,H$10,PnL_Speadsheet!$B23:$BI23)/1000 -> 0 | I26: =SUMIF(PnL_Speadsheet!$B$3:$BI$3,I$10,PnL_Speadsheet!$B23:$BI23)/1000 -> 0 | J26: =SUMIF(PnL_Speadsheet!$B$3:$BI$3,J$10,PnL_Speadsheet!$B23:$BI23)/1000 -> 0 | K26: =SUMIF(PnL_Speadsheet!$B$3:$BI$3,K$10,PnL_Speadsheet!$B23:$BI23)/1000 -> 0
C27: UW & Disbursal | E27: =SUM(F27:O27) -> -12.052544 | F27: =SUMIF(PnL_Speadsheet!$B$3:$BI$3,F$10,PnL_Speadsheet!$B24:$BI24)/1000 -> -12.052544 | G27: =SUMIF(PnL_Speadsheet!$B$3:$BI$3,G$10,PnL_Speadsheet!$B24:$BI24)/1000 -> 0 | H27: =SUMIF(PnL_Speadsheet!$B$3:$BI$3,H$10,PnL_Speadsheet!$B24:$BI24)/1000 -> 0 | I27: =SUMIF(PnL_Speadsheet!$B$3:$BI$3,I$10,PnL_Speadsheet!$B24:$BI24)/1000 -> 0 | J27: =SUMIF(PnL_Speadsheet!$B$3:$BI$3,J$10,PnL_Speadsheet!$B24:$BI24)/1000 -> 0 | K27: =SUMIF(PnL_Speadsheet!$B$3:$BI$3,K$10,PnL_Speadsheet!$B24:$BI24)/1000 -> 0
C28: Collection & AMC | E28: =SUM(F28:O28) -> -16.112383 | F28: =SUMIF(PnL_Speadsheet!$B$3:$BI$3,F$10,PnL_Speadsheet!$B28:$BI28)/1000 -> -6.0707411 | G28: =SUMIF(PnL_Speadsheet!$B$3:$BI$3,G$10,PnL_Speadsheet!$B28:$BI28)/1000 -> -9.3147432 | H28: =SUMIF(PnL_Speadsheet!$B$3:$BI$3,H$10,PnL_Speadsheet!$B28:$BI28)/1000 -> -0.72689871 | I28: =SUMIF(PnL_Speadsheet!$B$3:$BI$3,I$10,PnL_Speadsheet!$B28:$BI28)/1000 -> 0 | J28: =SUMIF(PnL_Speadsheet!$B$3:$BI$3,J$10,PnL_Speadsheet!$B28:$BI28)/1000 -> 0 | K28: =SUMIF(PnL_Speadsheet!$B$3:$BI$3,K$10,PnL_Speadsheet!$B28:$BI28)/1000 -> 0
C29: After-sales services | E29: =SUM(F29:O29) -> -1.7456581 | F29: =SUMIF(PnL_Speadsheet!$B$3:$BI$3,F$10,PnL_Speadsheet!$B29:$BI29)/1000 -> -0.71263479 | G29: =SUMIF(PnL_Speadsheet!$B$3:$BI$3,G$10,PnL_Speadsheet!$B29:$BI29)/1000 -> -1.0330233 | H29: =SUMIF(PnL_Speadsheet!$B$3:$BI$3,H$10,PnL_Speadsheet!$B29:$BI29)/1000 -> 0 | I29: =SUMIF(PnL_Speadsheet!$B$3:$BI$3,I$10,PnL_Speadsheet!$B29:$BI29)/1000 -> 0 | J29: =SUMIF(PnL_Speadsheet!$B$3:$BI$3,J$10,PnL_Speadsheet!$B29:$BI29)/1000 -> 0 | K29: =SUMIF(PnL_Speadsheet!$B$3:$BI$3,K$10,PnL_Speadsheet!$B29:$BI29)/1000 -> 0
C30: Other support units | E30: =SUM(F30:O30) -> -89.641317 | F30: =SUMIF(PnL_Speadsheet!$B$3:$BI$3,F$10,PnL_Speadsheet!$B30:$BI30)/1000 -> -37.031681 | G30: =SUMIF(PnL_Speadsheet!$B$3:$BI$3,G$10,PnL_Speadsheet!$B30:$BI30)/1000 -> -52.609636 | H30: =SUMIF(PnL_Speadsheet!$B$3:$BI$3,H$10,PnL_Speadsheet!$B30:$BI30)/1000 -> 0 | I30: =SUMIF(PnL_Speadsheet!$B$3:$BI$3,I$10,PnL_Speadsheet!$B30:$BI30)/1000 -> 0 | J30: =SUMIF(PnL_Speadsheet!$B$3:$BI$3,J$10,PnL_Speadsheet!$B30:$BI30)/1000 -> 0 | K30: =SUMIF(PnL_Speadsheet!$B$3:$BI$3,K$10,PnL_Speadsheet!$B30:$BI30)/1000 -> 0
C31: PBT | E31: =SUM(F31:O31) -> 75.615783 | F31: =SUMIF(PnL_Speadsheet!$B$3:$BI$3,F$10,PnL_Speadsheet!$B32:$BI32)/1000 -> 55.757869 | G31: =SUMIF(PnL_Speadsheet!$B$3:$BI$3,G$10,PnL_Speadsheet!$B32:$BI32)/1000 -> 23.730805 | H31: =SUMIF(PnL_Speadsheet!$B$3:$BI$3,H$10,PnL_Speadsheet!$B32:$BI32)/1000 -> -3.8728907 | I31: =SUMIF(PnL_Speadsheet!$B$3:$BI$3,I$10,PnL_Speadsheet!$B32:$BI32)/1000 -> 0 | J31: =SUMIF(PnL_Speadsheet!$B$3:$BI$3,J$10,PnL_Speadsheet!$B32:$BI32)/1000 -> 0 | K31: =SUMIF(PnL_Speadsheet!$B$3:$BI$3,K$10,PnL_Speadsheet!$B32:$BI32)/1000 -> 0
C32: In which: PROFIT BEFORE SU | E32: =E19+E23+SUM(E25:E29) -> 165.2571 | F32: =F19+F23+SUM(F25:F29) -> 92.78955 | G32: =G19+G23+SUM(G25:G29) -> 76.340441 | H32: =H19+H23+SUM(H25:H29) -> -3.8728907 | I32: =I19+I23+SUM(I25:I29) -> 0 | J32: =J19+J23+SUM(J25:J29) -> 0 | K32: =K19+K23+SUM(K25:K29) -> 0

Sheet PnL_Speadsheet
A1: PL PROJECTION
A2: 60 months
B3: =YEAR(B4) -> 2025 | C3: =YEAR(C4) -> 2025 | D3: =YEAR(D4) -> 2025 | E3: =YEAR(E4) -> 2025 | F3: =YEAR(F4) -> 2025 | G3: =YEAR(G4) -> 2025 | H3: =YEAR(H4) -> 2025 | I3: =YEAR(I4) -> 2025 | ... BI3: =YEAR(BI4) -> 2029
A4: Business month | B4: ='Saleplan&PnL'!D4 -> 45658 | C4: ='Saleplan&PnL'!E4 -> 45716 | D4: ='Saleplan&PnL'!F4 -> 45747 | E4: ='Saleplan&PnL'!G4 -> 45777 | F4: ='Saleplan&PnL'!H4 -> 45808 | G4: ='Saleplan&PnL'!I4 -> 45838 | H4: ='Saleplan&PnL'!J4 -> 45869 | I4: ='Saleplan&PnL'!K4 -> 45900 | ... BI4: ='Saleplan&PnL'!BK4 -> 47483
A5: Month on board | B5: 1 | C5: 2 | D5: 3 | E5: 4 | F5: 5 | G5: 6 | H5: 7 | I5: 8 | J5: 9 | K5: 10 | L5: 11 | M5: 12 | N5: 13 | O5: 14 | P5: 15 | Q5: 16 | R5: 17 | S5: 18 | T5: 19 | U5: 20 | V5: 21 | W5: 22 | X5: 23 | Y5: 24 | Z5: 25 | AA5: 26 | AB5: 27 | AC5: 28 | AD5: 29 | AE5: 30 | AF5: 31 | AG5: 32 | AH5: 33 | AI5: 34 | AJ5: 35 | AK5: 36 | AL5: =AK5+1 -> 37 | AM5: =AL5+1 -> 38 | AN5: =AM5+1 -> 39 | AO5: =AN5+1 -> 40 | AP5: =AO5+1 -> 41 | AQ5: =AP5+1 -> 42 | AR5: =AQ5+1 -> 43 | AS5: =AR5+1 -> 44 | ... BI5: =BH5+1 -> 60
A6: Unit: mVND
A7: ENR | B7: {=SUMPRODUCT(B$55:B$114,TRANSPOSE(SAP_Speadsheet!$E$44:$BL$44))} -> 0 | C7: {=SUMPRODUCT(C$55:C$114,TRANSPOSE(SAP_Speadsheet!$E$44:$BL$44))} -> 0 | D7: {=SUMPRODUCT(D$55:D$114,TRANSPOSE(SAP_Speadsheet!$E$44:$BL$44))} -> 0 | E7: {=SUMPRODUCT(E$55:E$114,TRANSPOSE(SAP_Speadsheet!$E$44:$BL$44))} -> 0 | F7: {=SUMPRODUCT(F$55:F$114,TRANSPOSE(SAP_Speadsheet!$E$44:$BL$44))} -> 0 | G7: {=SUMPRODUCT(G$55:G$114,TRANSPOSE(SAP_Speadsheet!$E$44:$BL$44))} -> 0 | H7: {=SUMPRODUCT(H$55:H$114,TRANSPOSE(SAP_Speadsheet!$E$44:$BL$44))} -> 760843.52 | I7: {=SUMPRODUCT(I$55:I$114,TRANSPOSE(SAP_Speadsheet!$E$44:$BL$44))} -> 1387405 | ... BI7: {=SUMPRODUCT(BI$55:BI$114,TRANSPOSE(SAP_Speadsheet!$E$44:$BL$44))} -> 0
A8: ANR | B8: {=SUMPRODUCT(B$55:B$114,TRANSPOSE(SAP_Speadsheet!$E$50:$BL$50))} -> 0 | C8: {=SUMPRODUCT(C$55:C$114,TRANSPOSE(SAP_Speadsheet!$E$50:$BL$50))} -> 0 | D8: {=SUMPRODUCT(D$55:D$114,TRANSPOSE(SAP_Speadsheet!$E$50:$BL$50))} -> 0 | E8: {=SUMPRODUCT(E$55:E$114,TRANSPOSE(SAP_Speadsheet!$E$50:$BL$50))} -> 0 | F8: {=SUMPRODUCT(F$55:F$114,TRANSPOSE(SAP_Speadsheet!$E$50:$BL$50))} -> 0 | G8: {=SUMPRODUCT(G$55:G$114,TRANSPOSE(SAP_Speadsheet!$E$50:$BL$50))} -> 0 | H8: {=SUMPRODUCT(H$55:H$114,TRANSPOSE(SAP_Speadsheet!$E$50:$BL$50))} -> 837321.24 | I8: {=SUMPRODUCT(I$55:I$114,TRANSPOSE(SAP_Speadsheet!$E$50:$BL$50))} -> 1497848.4 | ... BI8: {=SUMPRODUCT(BI$55:BI$114,TRANSPOSE(SAP_Speadsheet!$E$50:$BL$50))} -> 0
A9: TOI | B9: {=SUMPRODUCT(B$55:B$114,TRANSPOSE(SAP_Speadsheet!$E$55:$BL$55))} -> 0 | C9: {=SUMPRODUCT(C$55:C$114,TRANSPOSE(SAP_Speadsheet!$E$55:$BL$55))} -> 0 | D9: {=SUMPRODUCT(D$55:D$114,TRANSPOSE(SAP_Speadsheet!$E$55:$BL$55))} -> 0 | E9: {=SUMPRODUCT(E$55:E$114,TRANSPOSE(SAP_Speadsheet!$E$55:$BL$55))} -> 0 | F9: {=SUMPRODUCT(F$55:F$114,TRANSPOSE(SAP_Speadsheet!$E$55:$BL$55))} -> 0 | G9: {=SUMPRODUCT(G$55:G$114,TRANSPOSE(SAP_Speadsheet!$E$55:$BL$55))} -> 0 | H9: {=SUMPRODUCT(H$55:H$114,TRANSPOSE(SAP_Speadsheet!$E$55:$BL$55))} -> 78916.986 | I9: {=SUMPRODUCT(I$55:I$114,TRANSPOSE(SAP_Speadsheet!$E$55:$BL$55))} -> 100352.74 | ... BI9: {=SUMPRODUCT(BI$55:BI$114,TRANSPOSE(SAP_Speadsheet!$E$55:$BL$55))} -> 0
A10: Checking | B10: =B9-B11-B14 -> 0 | C10: =C9-C11-C14 -> 0 | D10: =D9-D11-D14 -> 0 | E10: =E9-E11-E14 -> 0 | F10: =F9-F11-F14 -> 0 | G10: =G9-G11-G14 -> 0 | H10: =H9-H11-H14 -> 0 | I10: =I9-I11-I14 -> 0 | ... BI10: =BI9-BI11-BI14 -> 0
A11: Net interest income | B11: {=SUMPRODUCT(B$55:B$114,TRANSPOSE(SAP_Speadsheet!$E$57:$BL$57))} -> 0 | C11: {=SUMPRODUCT(C$55:C$114,TRANSPOSE(SAP_Speadsheet!$E$57:$BL$57))} -> 0 | D11: {=SUMPRODUCT(D$55:D$114,TRANSPOSE(SAP_Speadsheet!$E$57:$BL$57))} -> 0 | E11: {=SUMPRODUCT(E$55:E$114,TRANSPOSE(SAP_Speadsheet!$E$57:$BL$57))} -> 0 | F11: {=SUMPRODUCT(F$55:F$114,TRANSPOSE(SAP_Speadsheet!$E$57:$BL$57))} -> 0 | G11: {=SUMPRODUCT(G$55:G$114,TRANSPOSE(SAP_Speadsheet!$E$57:$BL$57))} -> 0 | H11: {=SUMPRODUCT(H$55:H$114,TRANSPOSE(SAP_Speadsheet!$E$57:$BL$57))} -> 30715.575 | I11: {=SUMPRODUCT(I$55:I$114,TRANSPOSE(SAP_Speadsheet!$E$57:$BL$57))} -> 52737.803 | ... BI11: {=SUMPRODUCT(BI$55:BI$114,TRANSPOSE(SAP_Speadsheet!$E$57:$BL$57))} -> 0
A12: Interest income | B12: {=SUMPRODUCT(B$55:B$114,TRANSPOSE(SAP_Speadsheet!$E$58:$BL$58))} -> 0 | C12: {=SUMPRODUCT(C$55:C$114,TRANSPOSE(SAP_Speadsheet!$E$58:$BL$58))} -> 0 | D12: {=SUMPRODUCT(D$55:D$114,TRANSPOSE(SAP_Speadsheet!$E$58:$BL$58))} -> 0 | E12: {=SUMPRODUCT(E$55:E$114,TRANSPOSE(SAP_Speadsheet!$E$58:$BL$58))} -> 0 | F12: {=SUMPRODUCT(F$55:F$114,TRANSPOSE(SAP_Speadsheet!$E$58:$BL$58))} -> 0 | G12: {=SUMPRODUCT(G$55:G$114,TRANSPOSE(SAP_Speadsheet!$E$58:$BL$58))} -> 0 | H12: {=SUMPRODUCT(H$55:H$114,TRANSPOSE(SAP_Speadsheet!$E$58:$BL$58))} -> 35534.562 | I12: {=SUMPRODUCT(I$55:I$114,TRANSPOSE(SAP_Speadsheet!$E$58:$BL$58))} -> 61358.285 | ... BI12: {=SUMPRODUCT(BI$55:BI$114,TRANSPOSE(SAP_Speadsheet!$E$58:$BL$58))} -> 0
A13: Cost of fund | B13: {=SUMPRODUCT(B$55:B$114,TRANSPOSE(SAP_Speadsheet!$E$59:$BL$59))} -> 0 | C13: {=SUMPRODUCT(C$55:C$114,TRANSPOSE(SAP_Speadsheet!$E$59:$BL$59))} -> 0 | D13: {=SUMPRODUCT(D$55:D$114,TRANSPOSE(SAP_Speadsheet!$E$59:$BL$59))} -> 0 | E13: {=SUMPRODUCT(E$55:E$114,TRANSPOSE(SAP_Speadsheet!$E$59:$BL$59))} -> 0 | F13: {=SUMPRODUCT(F$55:F$114,TRANSPOSE(SAP_Speadsheet!$E$59:$BL$59))} -> 0 | G13: {=SUMPRODUCT(G$55:G$114,TRANSPOSE(SAP_Speadsheet!$E$59:$BL$59))} -> 0 | H13: {=SUMPRODUCT(H$55:H$114,TRANSPOSE(SAP_Speadsheet!$E$59:$BL$59))} -> -4818.9874 | I13: {=SUMPRODUCT(I$55:I$114,TRANSPOSE(SAP_Speadsheet!$E$59:$BL$59))} -> -8620.4817 | ... BI13: {=SUMPRODUCT(BI$55:BI$114,TRANSPOSE(SAP_Speadsheet!$E$59:$BL$59))} -> 0
A14: Net fee income | B14: {=SUMPRODUCT(B$55:B$114,TRANSPOSE(SAP_Speadsheet!$E$61:$BL$61))} -> 0 | C14: {=SUMPRODUCT(C$55:C$114,TRANSPOSE(SAP_Speadsheet!$E$61:$BL$61))} -> 0 | D14: {=SUMPRODUCT(D$55:D$114,TRANSPOSE(SAP_Speadsheet!$E$61:$BL$61))} -> 0 | E14: {=SUMPRODUCT(E$55:E$114,TRANSPOSE(SAP_Speadsheet!$E$61:$BL$61))} -> 0 | F14: {=SUMPRODUCT(F$55:F$114,TRANSPOSE(SAP_Speadsheet!$E$61:$BL$61))} -> 0 | G14: {=SUMPRODUCT(G$55:G$114,TRANSPOSE(SAP_Speadsheet!$E$61:$BL$61))} -> 0 | H14: {=SUMPRODUCT(H$55:H$114,TRANSPOSE(SAP_Speadsheet!$E$61:$BL$61))} -> 48201.411 | I14: {=SUMPRODUCT(I$55:I$114,TRANSPOSE(SAP_Speadsheet!$E$61:$BL$61))} -> 47614.94 | ... BI14: {=SUMPRODUCT(BI$55:BI$114,TRANSPOSE(SAP_Speadsheet!$E$61:$BL$61))} -> 0
A15: Early termination income | B15: {=SUMPRODUCT(B$55:B$114,TRANSPOSE(SAP_Speadsheet!$E$62:$BL$62))} -> 0 | C15: {=SUMPRODUCT(C$55:C$114,TRANSPOSE(SAP_Speadsheet!$E$62:$BL$62))} -> 0 | D15: {=SUMPRODUCT(D$55:D$114,TRANSPOSE(SAP_Speadsheet!$E$62:$BL$62))} -> 0 | E15: {=SUMPRODUCT(E$55:E$114,TRANSPOSE(SAP_Speadsheet!$E$62:$BL$62))} -> 0 | F15: {=SUMPRODUCT(F$55:F$114,TRANSPOSE(SAP_Speadsheet!$E$62:$BL$62))} -> 0 | G15: {=SUMPRODUCT(G$55:G$114,TRANSPOSE(SAP_Speadsheet!$E$62:$BL$62))} -> 0 | H15: {=SUMPRODUCT(H$55:H$114,TRANSPOSE(SAP_Speadsheet!$E$62:$BL$62))} -> 8006.6582 | I15: {=SUMPRODUCT(I$55:I$114,TRANSPOSE(SAP_Speadsheet!$E$62:$BL$62))} -> 10338.72 | ... BI15: {=SUMPRODUCT(BI$55:BI$114,TRANSPOSE(SAP_Speadsheet!$E$62:$BL$62))} -> 0
A16: Insurance fee | B16: {=SUMPRODUCT(B$55:B$114,TRANSPOSE(SAP_Speadsheet!$E$63:$BL$63))} -> 0 | C16: {=SUMPRODUCT(C$55:C$114,TRANSPOSE(SAP_Speadsheet!$E$63:$BL$63))} -> 0 | D16: {=SUMPRODUCT(D$55:D$114,TRANSPOSE(SAP_Speadsheet!$E$63:$BL$63))} -> 0 | E16: {=SUMPRODUCT(E$55:E$114,TRANSPOSE(SAP_Speadsheet!$E$63:$BL$63))} -> 0 | F16: {=SUMPRODUCT(F$55:F$114,TRANSPOSE(SAP_Speadsheet!$E$63:$BL$63))} -> 0 | G16: {=SUMPRODUCT(G$55:G$114,TRANSPOSE(SAP_Speadsheet!$E$63:$BL$63))} -> 0 | H16: {=SUMPRODUCT(H$55:H$114,TRANSPOSE(SAP_Speadsheet!$E$63:$BL$63))} -> 40194.752 | I16: {=SUMPRODUCT(I$55:I$114,TRANSPOSE(SAP_Speadsheet!$E$63:$BL$63))} -> 37276.22 | ... BI16: {=SUMPRODUCT(BI$55:BI$114,TRANSPOSE(SAP_Speadsheet!$E$63:$BL$63))} -> 0
A17: Support fee | B17: {=SUMPRODUCT(B$55:B$114,TRANSPOSE(SAP_Speadsheet!$E$64:$BL$64))} -> 0 | C17: {=SUMPRODUCT(C$55:C$114,TRANSPOSE(SAP_Speadsheet!$E$64:$BL$64))} -> 0 | D17: {=SUMPRODUCT(D$55:D$114,TRANSPOSE(SAP_Speadsheet!$E$64:$BL$64))} -> 0 | E17: {=SUMPRODUCT(E$55:E$114,TRANSPOSE(SAP_Speadsheet!$E$64:$BL$64))} -> 0 | F17: {=SUMPRODUCT(F$55:F$114,TRANSPOSE(SAP_Speadsheet!$E$64:$BL$64))} -> 0 | G17: {=SUMPRODUCT(G$55:G$114,TRANSPOSE(SAP_Speadsheet!$E$64:$BL$64))} -> 0 | H17: {=SUMPRODUCT(H$55:H$114,TRANSPOSE(SAP_Speadsheet!$E$64:$BL$64))} -> 0 | I17: {=SUMPRODUCT(I$55:I$114,TRANSPOSE(SAP_Speadsheet!$E$64:$BL$64))} -> 0 | ... BI17: {=SUMPRODUCT(BI$55:BI$114,TRANSPOSE(SAP_Speadsheet!$E$64:$BL$64))} -> 0
A18: Other income | B18: {=SUMPRODUCT(B$55:B$114,TRANSPOSE(SAP_Speadsheet!$E$68:$BL$68))} -> 0 | C18: {=SUMPRODUCT(C$55:C$114,TRANSPOSE(SAP_Speadsheet!$E$68:$BL$68))} -> 0 | D18: {=SUMPRODUCT(D$55:D$114,TRANSPOSE(SAP_Speadsheet!$E$68:$BL$68))} -> 0 | E18: {=SUMPRODUCT(E$55:E$114,TRANSPOSE(SAP_Speadsheet!$E$68:$BL$68))} -> 0 | F18: {=SUMPRODUCT(F$55:F$114,TRANSPOSE(SAP_Speadsheet!$E$68:$BL$68))} -> 0 | G18: {=SUMPRODUCT(G$55:G$114,TRANSPOSE(SAP_Speadsheet!$E$68:$BL$68))} -> 0 | H18: {=SUMPRODUCT(H$55:H$114,TRANSPOSE(SAP_Speadsheet!$E$68:$BL$68))} -> 0 | I18: {=SUMPRODUCT(I$55:I$114,TRANSPOSE(SAP_Speadsheet!$E$68:$BL$68))} -> 0 | ... BI18: {=SUMPRODUCT(BI$55:BI$114,TRANSPOSE(SAP_Speadsheet!$E$68:$BL$68))} -> 0
A19: OPEX | B19: =B20+B24+B28+B29+B30 -> 0 | C19: =C20+C24+C28+C29+C30 -> 0 | D19: =D20+D24+D28+D29+D30 -> 0 | E19: =E20+E24+E28+E29+E30 -> 0 | F19: =F20+F24+F28+F29+F30 -> 0 | G19: =G20+G24+G28+G29+G30 -> 0 | H19: =H20+H24+H28+H29+H30 -> -28889.881 | I19: =I20+I24+I28+I29+I30 -> -35950.526 | ... BI19: =BI20+BI24+BI28+BI29+BI30 -> 0
A20: Sale incentive&mkt | B20: =SUM(B21:B23) -> 0 | C20: =SUM(C21:C23) -> 0 | D20: =SUM(D21:D23) -> 0 | E20: =SUM(E21:E23) -> 0 | F20: =SUM(F21:F23) -> 0 | G20: =SUM(G21:G23) -> 0 | H20: =SUM(H21:H23) -> -21861.463 | I20: =SUM(I21:I23) -> -26548.776 | ... BI20: =SUM(BI21:BI23) -> 0
A21: Lead Acquisition | B21: {=SUMPRODUCT(B$55:B$114,TRANSPOSE(SAP_Speadsheet!$E$73:$BL$73))} -> 0 | C21: {=SUMPRODUCT(C$55:C$114,TRANSPOSE(SAP_Speadsheet!$E$73:$BL$73))} -> 0 | D21: {=SUMPRODUCT(D$55:D$114,TRANSPOSE(SAP_Speadsheet!$E$73:$BL$73))} -> 0 | E21: {=SUMPRODUCT(E$55:E$114,TRANSPOSE(SAP_Speadsheet!$E$73:$BL$73))} -> 0 | F21: {=SUMPRODUCT(F$55:F$114,TRANSPOSE(SAP_Speadsheet!$E$73:$BL$73))} -> 0 | G21: {=SUMPRODUCT(G$55:G$114,TRANSPOSE(SAP_Speadsheet!$E$73:$BL$73))} -> 0 | H21: {=SUMPRODUCT(H$55:H$114,TRANSPOSE(SAP_Speadsheet!$E$73:$BL$73))} -> 0 | I21: {=SUMPRODUCT(I$55:I$114,TRANSPOSE(SAP_Speadsheet!$E$73:$BL$73))} -> 0 | ... BI21: {=SUMPRODUCT(BI$55:BI$114,TRANSPOSE(SAP_Speadsheet!$E$73:$BL$73))} -> 0
A22: Sharing performance | B22: {=SUMPRODUCT(B$55:B$114,TRANSPOSE(SAP_Speadsheet!$E$74:$BL$74))} -> 0 | C22: {=SUMPRODUCT(C$55:C$114,TRANSPOSE(SAP_Speadsheet!$E$74:$BL$74))} -> 0 | D22: {=SUMPRODUCT(D$55:D$114,TRANSPOSE(SAP_Speadsheet!$E$74:$BL$74))} -> 0 | E22: {=SUMPRODUCT(E$55:E$114,TRANSPOSE(SAP_Speadsheet!$E$74:$BL$74))} -> 0 | F22: {=SUMPRODUCT(F$55:F$114,TRANSPOSE(SAP_Speadsheet!$E$74:$BL$74))} -> 0 | G22: {=SUMPRODUCT(G$55:G$114,TRANSPOSE(SAP_Speadsheet!$E$74:$BL$74))} -> 0 | H22: {=SUMPRODUCT(H$55:H$114,TRANSPOSE(SAP_Speadsheet!$E$74:$BL$74))} -> -18227.922 | I22: {=SUMPRODUCT(I$55:I$114,TRANSPOSE(SAP_Speadsheet!$E$74:$BL$74))} -> -23179.066 | ... BI22: {=SUMPRODUCT(BI$55:BI$114,TRANSPOSE(SAP_Speadsheet!$E$74:$BL$74))} -> 0
A23: Marketing | B23: {=SUMPRODUCT(B$55:B$114,TRANSPOSE(SAP_Speadsheet!$E$86:$BL$86))} -> 0 | C23: {=SUMPRODUCT(C$55:C$114,TRANSPOSE(SAP_Speadsheet!$E$86:$BL$86))} -> 0 | D23: {=SUMPRODUCT(D$55:D$114,TRANSPOSE(SAP_Speadsheet!$E$86:$BL$86))} -> 0 | E23: {=SUMPRODUCT(E$55:E$114,TRANSPOSE(SAP_Speadsheet!$E$86:$BL$86))} -> 0 | F23: {=SUMPRODUCT(F$55:F$114,TRANSPOSE(SAP_Speadsheet!$E$86:$BL$86))} -> 0 | G23: {=SUMPRODUCT(G$55:G$114,TRANSPOSE(SAP_Speadsheet!$E$86:$BL$86))} -> 0 | H23: {=SUMPRODUCT(H$55:H$114,TRANSPOSE(SAP_Speadsheet!$E$86:$BL$86))} -> -3633.541 | I23: {=SUMPRODUCT(I$55:I$114,TRANSPOSE(SAP_Speadsheet!$E$86:$BL$86))} -> -3369.7104 | ... AV23: {=SUMPRODUCT(AV$55:AV$114,TRANSPOSE(SAP_Speadsheet!$E$86:$BL$86))} -> 0 | AW23: 0 | AX23: {=SUMPRODUCT(AX$55:AX$114,TRANSPOSE(SAP_Speadsheet!$E$86:$BL$86))} -> 0 | AY23: {=SUMPRODUCT(AY$55:AY$114,TRANSPOSE(SAP_Speadsheet!$E$86:$BL$86))} -> 0 | AZ23: {=SUMPRODUCT(AZ$55:AZ$114,TRANSPOSE(SAP_Speadsheet!$E$86:$BL$86))} -> 0 | BA23: {=SUMPRODUCT(BA$55:BA$114,TRANSPOSE(SAP_Speadsheet!$E$86:$BL$86))} -> 0 | BB23: {=SUMPRODUCT(BB$55:BB$114,TRANSPOSE(SAP_Speadsheet!$E$86:$BL$86))} -> 0 | BC23: {=SUMPRODUCT(BC$55:BC$114,TRANSPOSE(SAP_Speadsheet!$E$86:$BL$86))} -> 0 | BD23: {=SUMPRODUCT(BD$55:BD$114,TRANSPOSE(SAP_Speadsheet!$E$86:$BL$86))} -> 0 | BE23: {=SUMPRODUCT(BE$55:BE$114,TRANSPOSE(SAP_Speadsheet!$E$86:$BL$86))} -> 0 | ... BI23: {=SUMPRODUCT(BI$55:BI$114,TRANSPOSE(SAP_Speadsheet!$E$86:$BL$86))} -> 0
A24: UW & Disbursal | B24: {=SUMPRODUCT(B$55:B$114,TRANSPOSE(SAP_Speadsheet!$E$88:$BL$88))} -> 0 | C24: {=SUMPRODUCT(C$55:C$114,TRANSPOSE(SAP_Speadsheet!$E$88:$BL$88))} -> 0 | D24: {=SUMPRODUCT(D$55:D$114,TRANSPOSE(SAP_Speadsheet!$E$88:$BL$88))} -> 0 | E24: {=SUMPRODUCT(E$55:E$114,TRANSPOSE(SAP_Speadsheet!$E$88:$BL$88))} -> 0 | F24: {=SUMPRODUCT(F$55:F$114,TRANSPOSE(SAP_Speadsheet!$E$88:$BL$88))} -> 0 | G24: {=SUMPRODUCT(G$55:G$114,TRANSPOSE(SAP_Speadsheet!$E$88:$BL$88))} -> 0 | H24: {=SUMPRODUCT(H$55:H$114,TRANSPOSE(SAP_Speadsheet!$E$88:$BL$88))} -> -3770.4047 | I24: {=SUMPRODUCT(I$55:I$114,TRANSPOSE(SAP_Speadsheet!$E$88:$BL$88))} -> -3496.6364 | ... BI24: {=SUMPRODUCT(BI$55:BI$114,TRANSPOSE(SAP_Speadsheet!$E$88:$BL$88))} -> 0
A25: Underwriting | B25: {=SUMPRODUCT(B$55:B$114,TRANSPOSE(SAP_Speadsheet!$E$89:$BL$89))} -> 0 | C25: {=SUMPRODUCT(C$55:C$114,TRANSPOSE(SAP_Speadsheet!$E$89:$BL$89))} -> 0 | D25: {=SUMPRODUCT(D$55:D$114,TRANSPOSE(SAP_Speadsheet!$E$89:$BL$89))} -> 0 | E25: {=SUMPRODUCT(E$55:E$114,TRANSPOSE(SAP_Speadsheet!$E$89:$BL$89))} -> 0 | F25: {=SUMPRODUCT(F$55:F$114,TRANSPOSE(SAP_Speadsheet!$E$89:$BL$89))} -> 0 | G25: {=SUMPRODUCT(G$55:G$114,TRANSPOSE(SAP_Speadsheet!$E$89:$BL$89))} -> 0 | H25: {=SUMPRODUCT(H$55:H$114,TRANSPOSE(SAP_Speadsheet!$E$89:$BL$89))} -> -3544.4847 | I25: {=SUMPRODUCT(I$55:I$114,TRANSPOSE(SAP_Speadsheet!$E$89:$BL$89))} -> -3287.1204 | ... BI25: {=SUMPRODUCT(BI$55:BI$114,TRANSPOSE(SAP_Speadsheet!$E$89:$BL$89))} -> 0
A26: Disbursement | B26: {=SUMPRODUCT(B$55:B$114,TRANSPOSE(SAP_Speadsheet!$E$90:$BL$90))} -> 0 | C26: {=SUMPRODUCT(C$55:C$114,TRANSPOSE(SAP_Speadsheet!$E$90:$BL$90))} -> 0 | D26: {=SUMPRODUCT(D$55:D$114,TRANSPOSE(SAP_Speadsheet!$E$90:$BL$90))} -> 0 | E26: {=SUMPRODUCT(E$55:E$114,TRANSPOSE(SAP_Speadsheet!$E$90:$BL$90))} -> 0 | F26: {=SUMPRODUCT(F$55:F$114,TRANSPOSE(SAP_Speadsheet!$E$90:$BL$90))} -> 0 | G26: {=SUMPRODUCT(G$55:G$114,TRANSPOSE(SAP_Speadsheet!$E$90:$BL$90))} -> 0 | H26: {=SUMPRODUCT(H$55:H$114,TRANSPOSE(SAP_Speadsheet!$E$90:$BL$90))} -> -225.92 | I26: {=SUMPRODUCT(I$55:I$114,TRANSPOSE(SAP_Speadsheet!$E$90:$BL$90))} -> -209.516 | ... BI26: {=SUMPRODUCT(BI$55:BI$114,TRANSPOSE(SAP_Speadsheet!$E$90:$BL$90))} -> 0
A27: DOP | B27: {=SUMPRODUCT(B$55:B$114,TRANSPOSE(SAP_Speadsheet!$E$91:$BL$91))} -> 0 | C27: {=SUMPRODUCT(C$55:C$114,TRANSPOSE(SAP_Speadsheet!$E$91:$BL$91))} -> 0 | D27: {=SUMPRODUCT(D$55:D$114,TRANSPOSE(SAP_Speadsheet!$E$91:$BL$91))} -> 0 | E27: {=SUMPRODUCT(E$55:E$114,TRANSPOSE(SAP_Speadsheet!$E$91:$BL$91))} -> 0 | F27: {=SUMPRODUCT(F$55:F$114,TRANSPOSE(SAP_Speadsheet!$E$91:$BL$91))} -> 0 | G27: {=SUMPRODUCT(G$55:G$114,TRANSPOSE(SAP_Speadsheet!$E$91:$BL$91))} -> 0 | H27: {=SUMPRODUCT(H$55:H$114,TRANSPOSE(SAP_Speadsheet!$E$91:$BL$91))} -> 0 | I27: {=SUMPRODUCT(I$55:I$114,TRANSPOSE(SAP_Speadsheet!$E$91:$BL$91))} -> 0 | ... BI27: {=SUMPRODUCT(BI$55:BI$114,TRANSPOSE(SAP_Speadsheet!$E$91:$BL$91))} -> 0
A28: Collection | B28: {=SUMPRODUCT(B$55:B$114,TRANSPOSE(SAP_Speadsheet!$E$95:$BL$95))} -> 0 | C28: {=SUMPRODUCT(C$55:C$114,TRANSPOSE(SAP_Speadsheet!$E$95:$BL$95))} -> 0 | D28: {=SUMPRODUCT(D$55:D$114,TRANSPOSE(SAP_Speadsheet!$E$95:$BL$95))} -> 0 | E28: {=SUMPRODUCT(E$55:E$114,TRANSPOSE(SAP_Speadsheet!$E$95:$BL$95))} -> 0 | F28: {=SUMPRODUCT(F$55:F$114,TRANSPOSE(SAP_Speadsheet!$E$95:$BL$95))} -> 0 | G28: {=SUMPRODUCT(G$55:G$114,TRANSPOSE(SAP_Speadsheet!$E$95:$BL$95))} -> 0 | H28: {=SUMPRODUCT(H$55:H$114,TRANSPOSE(SAP_Speadsheet!$E$95:$BL$95))} -> -451.84 | I28: {=SUMPRODUCT(I$55:I$114,TRANSPOSE(SAP_Speadsheet!$E$95:$BL$95))} -> -818.52642 | ... BI28: {=SUMPRODUCT(BI$55:BI$114,TRANSPOSE(SAP_Speadsheet!$E$95:$BL$95))} -> 0
A29: After-sales services | B29: {=SUMPRODUCT(B$55:B$114,TRANSPOSE(SAP_Speadsheet!$E$99:$BL$99))} -> 0 | C29: {=SUMPRODUCT(C$55:C$114,TRANSPOSE(SAP_Speadsheet!$E$99:$BL$99))} -> 0 | D29: {=SUMPRODUCT(D$55:D$114,TRANSPOSE(SAP_Speadsheet!$E$99:$BL$99))} -> 0 | E29: {=SUMPRODUCT(E$55:E$114,TRANSPOSE(SAP_Speadsheet!$E$99:$BL$99))} -> 0 | F29: {=SUMPRODUCT(F$55:F$114,TRANSPOSE(SAP_Speadsheet!$E$99:$BL$99))} -> 0 | G29: {=SUMPRODUCT(G$55:G$114,TRANSPOSE(SAP_Speadsheet!$E$99:$BL$99))} -> 0 | H29: {=SUMPRODUCT(H$55:H$114,TRANSPOSE(SAP_Speadsheet!$E$99:$BL$99))} -> -49.936803 | I29: {=SUMPRODUCT(I$55:I$114,TRANSPOSE(SAP_Speadsheet!$E$99:$BL$99))} -> -93.554465 | ... BI29: {=SUMPRODUCT(BI$55:BI$114,TRANSPOSE(SAP_Speadsheet!$E$99:$BL$99))} -> 0
A30: Other support units | B30: {=SUMPRODUCT(B$55:B$114,TRANSPOSE(SAP_Speadsheet!$E$103:$BL$103))} -> 0 | C30: {=SUMPRODUCT(C$55:C$114,TRANSPOSE(SAP_Speadsheet!$E$103:$BL$103))} -> 0 | D30: {=SUMPRODUCT(D$55:D$114,TRANSPOSE(SAP_Speadsheet!$E$103:$BL$103))} -> 0 | E30: {=SUMPRODUCT(E$55:E$114,TRANSPOSE(SAP_Speadsheet!$E$103:$BL$103))} -> 0 | F30: {=SUMPRODUCT(F$55:F$114,TRANSPOSE(SAP_Speadsheet!$E$103:$BL$103))} -> 0 | G30: {=SUMPRODUCT(G$55:G$114,TRANSPOSE(SAP_Speadsheet!$E$103:$BL$103))} -> 0 | H30: {=SUMPRODUCT(H$55:H$114,TRANSPOSE(SAP_Speadsheet!$E$103:$BL$103))} -> -2756.2359 | I30: {=SUMPRODUCT(I$55:I$114,TRANSPOSE(SAP_Speadsheet!$E$103:$BL$103))} -> -4993.0328 | ... BI30: {=SUMPRODUCT(BI$55:BI$114,TRANSPOSE(SAP_Speadsheet!$E$103:$BL$103))} -> 0
A31: PROVISION | B31: {=SUMPRODUCT(B$55:B$114,TRANSPOSE(SAP_Speadsheet!$E$183:$BL$183))} -> 0 | C31: {=SUMPRODUCT(C$55:C$114,TRANSPOSE(SAP_Speadsheet!$E$183:$BL$183))} -> 0 | D31: {=SUMPRODUCT(D$55:D$114,TRANSPOSE(SAP_Speadsheet!$E$183:$BL$183))} -> 0 | E31: {=SUMPRODUCT(E$55:E$114,TRANSPOSE(SAP_Speadsheet!$E$183:$BL$183))} -> 0 | F31: {=SUMPRODUCT(F$55:F$114,TRANSPOSE(SAP_Speadsheet!$E$183:$BL$183))} -> 0 | G31: {=SUMPRODUCT(G$55:G$114,TRANSPOSE(SAP_Speadsheet!$E$183:$BL$183))} -> 0 | H31: {=SUMPRODUCT(H$55:H$114,TRANSPOSE(SAP_Speadsheet!$E$183:$BL$183))} -> -43973.196 | I31: {=SUMPRODUCT(I$55:I$114,TRANSPOSE(SAP_Speadsheet!$E$183:$BL$183))} -> -57368.149 | ... BI31: {=SUMPRODUCT(BI$55:BI$114,TRANSPOSE(SAP_Speadsheet!$E$183:$BL$183))} -> 0
A32: PBT | B32: {=SUMPRODUCT(B$55:B$114,TRANSPOSE(SAP_Speadsheet!$E$189:$BL$189))} -> 0 | C32: {=SUMPRODUCT(C$55:C$114,TRANSPOSE(SAP_Speadsheet!$E$189:$BL$189))} -> 0 | D32: {=SUMPRODUCT(D$55:D$114,TRANSPOSE(SAP_Speadsheet!$E$189:$BL$189))} -> 0 | E32: {=SUMPRODUCT(E$55:E$114,TRANSPOSE(SAP_Speadsheet!$E$189:$BL$189))} -> 0 | F32: {=SUMPRODUCT(F$55:F$114,TRANSPOSE(SAP_Speadsheet!$E$189:$BL$189))} -> 0 | G32: {=SUMPRODUCT(G$55:G$114,TRANSPOSE(SAP_Speadsheet!$E$189:$BL$189))} -> 0 | H32: {=SUMPRODUCT(H$55:H$114,TRANSPOSE(SAP_Speadsheet!$E$189:$BL$189))} -> 6053.909 | I32: {=SUMPRODUCT(I$55:I$114,TRANSPOSE(SAP_Speadsheet!$E$189:$BL$189))} -> 7034.0683 | ... BI32: {=SUMPRODUCT(BI$55:BI$114,TRANSPOSE(SAP_Speadsheet!$E$189:$BL$189))} -> 0
A33: Checking | B33: =B9+B19+B31-B32 -> 0 | C33: =C9+C19+C31-C32 -> 0 | D33: =D9+D19+D31-D32 -> 0 | E33: =E9+E19+E31-E32 -> 0 | F33: =F9+F19+F31-F32 -> 0 | G33: =G9+G19+G31-G32 -> 0 | H33: =H9+H19+H31-H32 -> -1.0004442e-11 | I33: =I9+I19+I31-I32 -> -1.6370905e-11 | ... BI33: =BI9+BI19+BI31-BI32 -> 0
A35: EOP BY BUCKET
A36: B0 | B36: {=SUMPRODUCT(B$55:B$114,TRANSPOSE(SAP_Speadsheet!$E$27:$BL$27))} -> 0 | C36: {=SUMPRODUCT(C$55:C$114,TRANSPOSE(SAP_Speadsheet!$E$27:$BL$27))} -> 0 | D36: {=SUMPRODUCT(D$55:D$114,TRANSPOSE(SAP_Speadsheet!$E$27:$BL$27))} -> 0 | E36: {=SUMPRODUCT(E$55:E$114,TRANSPOSE(SAP_Speadsheet!$E$27:$BL$27))} -> 0 | F36: {=SUMPRODUCT(F$55:F$114,TRANSPOSE(SAP_Speadsheet!$E$27:$BL$27))} -> 0 | G36: {=SUMPRODUCT(G$55:G$114,TRANSPOSE(SAP_Speadsheet!$E$27:$BL$27))} -> 0 | H36: {=SUMPRODUCT(H$55:H$114,TRANSPOSE(SAP_Speadsheet!$E$27:$BL$27))} -> 714239.77 | I36: {=SUMPRODUCT(I$55:I$114,TRANSPOSE(SAP_Speadsheet!$E$27:$BL$27))} -> 1276517.7 | ... BI36: {=SUMPRODUCT(BI$55:BI$114,TRANSPOSE(SAP_Speadsheet!$E$27:$BL$27))} -> 0
A37: B1 | B37: {=SUMPRODUCT(B$55:B$114,TRANSPOSE(SAP_Speadsheet!$E$28:$BL$28))} -> 0 | C37: {=SUMPRODUCT(C$55:C$114,TRANSPOSE(SAP_Speadsheet!$E$28:$BL$28))} -> 0 | D37: {=SUMPRODUCT(D$55:D$114,TRANSPOSE(SAP_Speadsheet!$E$28:$BL$28))} -> 0 | E37: {=SUMPRODUCT(E$55:E$114,TRANSPOSE(SAP_Speadsheet!$E$28:$BL$28))} -> 0 | F37: {=SUMPRODUCT(F$55:F$114,TRANSPOSE(SAP_Speadsheet!$E$28:$BL$28))} -> 0 | G37: {=SUMPRODUCT(G$55:G$114,TRANSPOSE(SAP_Speadsheet!$E$28:$BL$28))} -> 0 | H37: {=SUMPRODUCT(H$55:H$114,TRANSPOSE(SAP_Speadsheet!$E$28:$BL$28))} -> 46603.747 | I37: {=SUMPRODUCT(I$55:I$114,TRANSPOSE(SAP_Speadsheet!$E$28:$BL$28))} -> 79646.088 | ... BI37: {=SUMPRODUCT(BI$55:BI$114,TRANSPOSE(SAP_Speadsheet!$E$28:$BL$28))} -> 0
A38: B2 | B38: {=SUMPRODUCT(B$55:B$114,TRANSPOSE(SAP_Speadsheet!$E$29:$BL$29))} -> 0 | C38: {=SUMPRODUCT(C$55:C$114,TRANSPOSE(SAP_Speadsheet!$E$29:$BL$29))} -> 0 | D38: {=SUMPRODUCT(D$55:D$114,TRANSPOSE(SAP_Speadsheet!$E$29:$BL$29))} -> 0 | E38: {=SUMPRODUCT(E$55:E$114,TRANSPOSE(SAP_Speadsheet!$E$29:$BL$29))} -> 0 | F38: {=SUMPRODUCT(F$55:F$114,TRANSPOSE(SAP_Speadsheet!$E$29:$BL$29))} -> 0 | G38: {=SUMPRODUCT(G$55:G$114,TRANSPOSE(SAP_Speadsheet!$E$29:$BL$29))} -> 0 | H38: {=SUMPRODUCT(H$55:H$114,TRANSPOSE(SAP_Speadsheet!$E$29:$BL$29))} -> 0 | I38: {=SUMPRODUCT(I$55:I$114,TRANSPOSE(SAP_Speadsheet!$E$29:$BL$29))} -> 31241.242 | ... BI38: {=SUMPRODUCT(BI$55:BI$114,TRANSPOSE(SAP_Speadsheet!$E$29:$BL$29))} -> 0
A39: B3 | B39: {=SUMPRODUCT(B$55:B$114,TRANSPOSE(SAP_Speadsheet!$E$30:$BL$30))} -> 0 | C39: {=SUMPRODUCT(C$55:C$114,TRANSPOSE(SAP_Speadsheet!$E$30:$BL$30))} -> 0 | D39: {=SUMPRODUCT(D$55:D$114,TRANSPOSE(SAP_Speadsheet!$E$30:$BL$30))} -> 0 | E39: {=SUMPRODUCT(E$55:E$114,TRANSPOSE(SAP_Speadsheet!$E$30:$BL$30))} -> 0 | F39: {=SUMPRODUCT(F$55:F$114,TRANSPOSE(SAP_Speadsheet!$E$30:$BL$30))} -> 0 | G39: {=SUMPRODUCT(G$55:G$114,TRANSPOSE(SAP_Speadsheet!$E$30:$BL$30))} -> 0 | H39: {=SUMPRODUCT(H$55:H$114,TRANSPOSE(SAP_Speadsheet!$E$30:$BL$30))} -> 0 | I39: {=SUMPRODUCT(I$55:I$114,TRANSPOSE(SAP_Speadsheet!$E$30:$BL$30))} -> 0 | ... BI39: {=SUMPRODUCT(BI$55:BI$114,TRANSPOSE(SAP_Speadsheet!$E$30:$BL$30))} -> 0
A40: B4 | B40: {=SUMPRODUCT(B$55:B$114,TRANSPOSE(SAP_Speadsheet!$E$31:$BL$31))} -> 0 | C40: {=SUMPRODUCT(C$55:C$114,TRANSPOSE(SAP_Speadsheet!$E$31:$BL$31))} -> 0 | D40: {=SUMPRODUCT(D$55:D$114,TRANSPOSE(SAP_Speadsheet!$E$31:$BL$31))} -> 0 | E40: {=SUMPRODUCT(E$55:E$114,TRANSPOSE(SAP_Speadsheet!$E$31:$BL$31))} -> 0 | F40: {=SUMPRODUCT(F$55:F$114,TRANSPOSE(SAP_Speadsheet!$E$31:$BL$31))} -> 0 | G40: {=SUMPRODUCT(G$55:G$114,TRANSPOSE(SAP_Speadsheet!$E$31:$BL$31))} -> 0 | H40: {=SUMPRODUCT(H$55:H$114,TRANSPOSE(SAP_Speadsheet!$E$31:$BL$31))} -> 0 | I40: {=SUMPRODUCT(I$55:I$114,TRANSPOSE(SAP_Speadsheet!$E$31:$BL$31))} -> 0 | ... BI40: {=SUMPRODUCT(BI$55:BI$114,TRANSPOSE(SAP_Speadsheet!$E$31:$BL$31))} -> 0
A41: B5 | B41: {=SUMPRODUCT(B$55:B$114,TRANSPOSE(SAP_Speadsheet!$E$32:$BL$32))} -> 0 | C41: {=SUMPRODUCT(C$55:C$114,TRANSPOSE(SAP_Speadsheet!$E$32:$BL$32))} -> 0 | D41: {=SUMPRODUCT(D$55:D$114,TRANSPOSE(SAP_Speadsheet!$E$32:$BL$32))} -> 0 | E41: {=SUMPRODUCT(E$55:E$114,TRANSPOSE(SAP_Speadsheet!$E$32:$BL$32))} -> 0 | F41: {=SUMPRODUCT(F$55:F$114,TRANSPOSE(SAP_Speadsheet!$E$32:$BL$32))} -> 0 | G41: {=SUMPRODUCT(G$55:G$114,TRANSPOSE(SAP_Speadsheet!$E$32:$BL$32))} -> 0 | H41: {=SUMPRODUCT(H$55:H$114,TRANSPOSE(SAP_Speadsheet!$E$32:$BL$32))} -> 0 | I41: {=SUMPRODUCT(I$55:I$114,TRANSPOSE(SAP_Speadsheet!$E$32:$BL$32))} -> 0 | ... BI41: {=SUMPRODUCT(BI$55:BI$114,TRANSPOSE(SAP_Speadsheet!$E$32:$BL$32))} -> 0
A42: B6 | B42: {=SUMPRODUCT(B$55:B$114,TRANSPOSE(SAP_Speadsheet!$E$33:$BL$33))} -> 0 | C42: {=SUMPRODUCT(C$55:C$114,TRANSPOSE(SAP_Speadsheet!$E$33:$BL$33))} -> 0 | D42: {=SUMPRODUCT(D$55:D$114,TRANSPOSE(SAP_Speadsheet!$E$33:$BL$33))} -> 0 | E42: {=SUMPRODUCT(E$55:E$114,TRANSPOSE(SAP_Speadsheet!$E$33:$BL$33))} -> 0 | F42: {=SUMPRODUCT(F$55:F$114,TRANSPOSE(SAP_Speadsheet!$E$33:$BL$33))} -> 0 | G42: {=SUMPRODUCT(G$55:G$114,TRANSPOSE(SAP_Speadsheet!$E$33:$BL$33))} -> 0 | H42: {=SUMPRODUCT(H$55:H$114,TRANSPOSE(SAP_Speadsheet!$E$33:$BL$33))} -> 0 | I42: {=SUMPRODUCT(I$55:I$114,TRANSPOSE(SAP_Speadsheet!$E$33:$BL$33))} -> 0 | ... BI42: {=SUMPRODUCT(BI$55:BI$114,TRANSPOSE(SAP_Speadsheet!$E$33:$BL$33))} -> 0
A43: B7 | B43: {=SUMPRODUCT(B$55:B$114,TRANSPOSE(SAP_Speadsheet!$E$34:$BL$34))} -> 0 | C43: {=SUMPRODUCT(C$55:C$114,TRANSPOSE(SAP_Speadsheet!$E$34:$BL$34))} -> 0 | D43: {=SUMPRODUCT(D$55:D$114,TRANSPOSE(SAP_Speadsheet!$E$34:$BL$34))} -> 0 | E43: {=SUMPRODUCT(E$55:E$114,TRANSPOSE(SAP_Speadsheet!$E$34:$BL$34))} -> 0 | F43: {=SUMPRODUCT(F$55:F$114,TRANSPOSE(SAP_Speadsheet!$E$34:$BL$34))} -> 0 | G43: {=SUMPRODUCT(G$55:G$114,TRANSPOSE(SAP_Speadsheet!$E$34:$BL$34))} -> 0 | H43: {=SUMPRODUCT(H$55:H$114,TRANSPOSE(SAP_Speadsheet!$E$34:$BL$34))} -> 0 | I43: {=SUMPRODUCT(I$55:I$114,TRANSPOSE(SAP_Speadsheet!$E$34:$BL$34))} -> 0 | ... BI43: {=SUMPRODUCT(BI$55:BI$114,TRANSPOSE(SAP_Speadsheet!$E$34:$BL$34))} -> 0
A44: B8 | B44: {=SUMPRODUCT(B$55:B$114,TRANSPOSE(SAP_Speadsheet!$E$35:$BL$35))} -> 0 | C44: {=SUMPRODUCT(C$55:C$114,TRANSPOSE(SAP_Speadsheet!$E$35:$BL$35))} -> 0 | D44: {=SUMPRODUCT(D$55:D$114,TRANSPOSE(SAP_Speadsheet!$E$35:$BL$35))} -> 0 | E44: {=SUMPRODUCT(E$55:E$114,TRANSPOSE(SAP_Speadsheet!$E$35:$BL$35))} -> 0 | F44: {=SUMPRODUCT(F$55:F$114,TRANSPOSE(SAP_Speadsheet!$E$35:$BL$35))} -> 0 | G44: {=SUMPRODUCT(G$55:G$114,TRANSPOSE(SAP_Speadsheet!$E$35:$BL$35))} -> 0 | H44: {=SUMPRODUCT(H$55:H$114,TRANSPOSE(SAP_Speadsheet!$E$35:$BL$35))} -> 0 | I44: {=SUMPRODUCT(I$55:I$114,TRANSPOSE(SAP_Speadsheet!$E$35:$BL$35))} -> 0 | ... BI44: {=SUMPRODUCT(BI$55:BI$114,TRANSPOSE(SAP_Speadsheet!$E$35:$BL$35))} -> 0
A45: B9 | B45: {=SUMPRODUCT(B$55:B$114,TRANSPOSE(SAP_Speadsheet!$E$36:$BL$36))} -> 0 | C45: {=SUMPRODUCT(C$55:C$114,TRANSPOSE(SAP_Speadsheet!$E$36:$BL$36))} -> 0 | D45: {=SUMPRODUCT(D$55:D$114,TRANSPOSE(SAP_Speadsheet!$E$36:$BL$36))} -> 0 | E45: {=SUMPRODUCT(E$55:E$114,TRANSPOSE(SAP_Speadsheet!$E$36:$BL$36))} -> 0 | F45: {=SUMPRODUCT(F$55:F$114,TRANSPOSE(SAP_Speadsheet!$E$36:$BL$36))} -> 0 | G45: {=SUMPRODUCT(G$55:G$114,TRANSPOSE(SAP_Speadsheet!$E$36:$BL$36))} -> 0 | H45: {=SUMPRODUCT(H$55:H$114,TRANSPOSE(SAP_Speadsheet!$E$36:$BL$36))} -> 0 | I45: {=SUMPRODUCT(I$55:I$114,TRANSPOSE(SAP_Speadsheet!$E$36:$BL$36))} -> 0 | ... BI45: {=SUMPRODUCT(BI$55:BI$114,TRANSPOSE(SAP_Speadsheet!$E$36:$BL$36))} -> 0
A46: B10 | B46: {=SUMPRODUCT(B$55:B$114,TRANSPOSE(SAP_Speadsheet!$E$37:$BL$37))} -> 0 | C46: {=SUMPRODUCT(C$55:C$114,TRANSPOSE(SAP_Speadsheet!$E$37:$BL$37))} -> 0 | D46: {=SUMPRODUCT(D$55:D$114,TRANSPOSE(SAP_Speadsheet!$E$37:$BL$37))} -> 0 | E46: {=SUMPRODUCT(E$55:E$114,TRANSPOSE(SAP_Speadsheet!$E$37:$BL$37))} -> 0 | F46: {=SUMPRODUCT(F$55:F$114,TRANSPOSE(SAP_Speadsheet!$E$37:$BL$37))} -> 0 | G46: {=SUMPRODUCT(G$55:G$114,TRANSPOSE(SAP_Speadsheet!$E$37:$BL$37))} -> 0 | H46: {=SUMPRODUCT(H$55:H$114,TRANSPOSE(SAP_Speadsheet!$E$37:$BL$37))} -> 0 | I46: {=SUMPRODUCT(I$55:I$114,TRANSPOSE(SAP_Speadsheet!$E$37:$BL$37))} -> 0 | ... BI46: {=SUMPRODUCT(BI$55:BI$114,TRANSPOSE(SAP_Speadsheet!$E$37:$BL$37))} -> 0
A47: B11 | B47: {=SUMPRODUCT(B$55:B$114,TRANSPOSE(SAP_Speadsheet!$E$38:$BL$38))} -> 0 | C47: {=SUMPRODUCT(C$55:C$114,TRANSPOSE(SAP_Speadsheet!$E$38:$BL$38))} -> 0 | D47: {=SUMPRODUCT(D$55:D$114,TRANSPOSE(SAP_Speadsheet!$E$38:$BL$38))} -> 0 | E47: {=SUMPRODUCT(E$55:E$114,TRANSPOSE(SAP_Speadsheet!$E$38:$BL$38))} -> 0 | F47: {=SUMPRODUCT(F$55:F$114,TRANSPOSE(SAP_Speadsheet!$E$38:$BL$38))} -> 0 | G47: {=SUMPRODUCT(G$55:G$114,TRANSPOSE(SAP_Speadsheet!$E$38:$BL$38))} -> 0 | H47: {=SUMPRODUCT(H$55:H$114,TRANSPOSE(SAP_Speadsheet!$E$38:$BL$38))} -> 0 | I47: {=SUMPRODUCT(I$55:I$114,TRANSPOSE(SAP_Speadsheet!$E$38:$BL$38))} -> 0 | ... BI47: {=SUMPRODUCT(BI$55:BI$114,TRANSPOSE(SAP_Speadsheet!$E$38:$BL$38))} -> 0
A48: B12 | B48: {=SUMPRODUCT(B$55:B$114,TRANSPOSE(SAP_Speadsheet!$E$39:$BL$39))} -> 0 | C48: {=SUMPRODUCT(C$55:C$114,TRANSPOSE(SAP_Speadsheet!$E$39:$BL$39))} -> 0 | D48: {=SUMPRODUCT(D$55:D$114,TRANSPOSE(SAP_Speadsheet!$E$39:$BL$39))} -> 0 | E48: {=SUMPRODUCT(E$55:E$114,TRANSPOSE(SAP_Speadsheet!$E$39:$BL$39))} -> 0 | F48: {=SUMPRODUCT(F$55:F$114,TRANSPOSE(SAP_Speadsheet!$E$39:$BL$39))} -> 0 | G48: {=SUMPRODUCT(G$55:G$114,TRANSPOSE(SAP_Speadsheet!$E$39:$BL$39))} -> 0 | H48: {=SUMPRODUCT(H$55:H$114,TRANSPOSE(SAP_Speadsheet!$E$39:$BL$39))} -> 0 | I48: {=SUMPRODUCT(I$55:I$114,TRANSPOSE(SAP_Speadsheet!$E$39:$BL$39))} -> 0 | ... BI48: {=SUMPRODUCT(BI$55:BI$114,TRANSPOSE(SAP_Speadsheet!$E$39:$BL$39))} -> 0
A49: B13+ | B49: {=SUMPRODUCT(B$55:B$114,TRANSPOSE(SAP_Speadsheet!$E$40:$BL$40))} -> 0 | C49: {=SUMPRODUCT(C$55:C$114,TRANSPOSE(SAP_Speadsheet!$E$40:$BL$40))} -> 0 | D49: {=SUMPRODUCT(D$55:D$114,TRANSPOSE(SAP_Speadsheet!$E$40:$BL$40))} -> 0 | E49: {=SUMPRODUCT(E$55:E$114,TRANSPOSE(SAP_Speadsheet!$E$40:$BL$40))} -> 0 | F49: {=SUMPRODUCT(F$55:F$114,TRANSPOSE(SAP_Speadsheet!$E$40:$BL$40))} -> 0 | G49: {=SUMPRODUCT(G$55:G$114,TRANSPOSE(SAP_Speadsheet!$E$40:$BL$40))} -> 0 | H49: {=SUMPRODUCT(H$55:H$114,TRANSPOSE(SAP_Speadsheet!$E$40:$BL$40))} -> 0 | I49: {=SUMPRODUCT(I$55:I$114,TRANSPOSE(SAP_Speadsheet!$E$40:$BL$40))} -> 0 | ... BI49: {=SUMPRODUCT(BI$55:BI$114,TRANSPOSE(SAP_Speadsheet!$E$40:$BL$40))} -> 0
A50: B14+ | B50: {=SUMPRODUCT(B$55:B$114,TRANSPOSE(SAP_Speadsheet!$E$41:$BL$41))} -> 0 | C50: {=SUMPRODUCT(C$55:C$114,TRANSPOSE(SAP_Speadsheet!$E$41:$BL$41))} -> 0 | D50: {=SUMPRODUCT(D$55:D$114,TRANSPOSE(SAP_Speadsheet!$E$41:$BL$41))} -> 0 | E50: {=SUMPRODUCT(E$55:E$114,TRANSPOSE(SAP_Speadsheet!$E$41:$BL$41))} -> 0 | F50: {=SUMPRODUCT(F$55:F$114,TRANSPOSE(SAP_Speadsheet!$E$41:$BL$41))} -> 0 | G50: {=SUMPRODUCT(G$55:G$114,TRANSPOSE(SAP_Speadsheet!$E$41:$BL$41))} -> 0 | H50: {=SUMPRODUCT(H$55:H$114,TRANSPOSE(SAP_Speadsheet!$E$41:$BL$41))} -> 0 | I50: {=SUMPRODUCT(I$55:I$114,TRANSPOSE(SAP_Speadsheet!$E$41:$BL$41))} -> 0 | ... BI50: {=SUMPRODUCT(BI$55:BI$114,TRANSPOSE(SAP_Speadsheet!$E$41:$BL$41))} -> 0
A51: Checking | B51: =SUM(B36:B50)-B7 -> 0 | C51: =SUM(C36:C50)-C7 -> 0 | D51: =SUM(D36:D50)-D7 -> 0 | E51: =SUM(E36:E50)-E7 -> 0 | F51: =SUM(F36:F50)-F7 -> 0 | G51: =SUM(G36:G50)-G7 -> 0 | H51: =SUM(H36:H50)-H7 -> 0 | I51: =SUM(I36:I50)-I7 -> 0 | ... BI51: =SUM(BI36:BI50)-BI7 -> 0
A54: No. of account | B54: =ROUND('Saleplan&PnL'!D6*1000/Leadsheet!$E$10,0) -> 0 | C54: =ROUND('Saleplan&PnL'!E6*1000/Leadsheet!$E$10,0) -> 0 | D54: =ROUND('Saleplan&PnL'!F6*1000/Leadsheet!$E$10,0) -> 0 | E54: =ROUND('Saleplan&PnL'!G6*1000/Leadsheet!$E$10,0) -> 0 | F54: =ROUND('Saleplan&PnL'!H6*1000/Leadsheet!$E$10,0) -> 0 | G54: =ROUND('Saleplan&PnL'!I6*1000/Leadsheet!$E$10,0) -> 0 | H54: =ROUND('Saleplan&PnL'!J6*1000/Leadsheet!$E$10,0) -> 56480 | I54: =ROUND('Saleplan&PnL'!K6*1000/Leadsheet!$E$10,0) -> 52379 | ... BI54: =ROUND('Saleplan&PnL'!BK6*1000/Leadsheet!$E$10,0) -> 0
A55: 1 | B55: =IF($A55>B$5,"",OFFSET(B$54,0,-($A55-1))) -> 0 | C55: =IF($A55>C$5,"",OFFSET(C$54,0,-($A55-1))) -> 0 | D55: =IF($A55>D$5,"",OFFSET(D$54,0,-($A55-1))) -> 0 | E55: =IF($A55>E$5,"",OFFSET(E$54,0,-($A55-1))) -> 0 | F55: =IF($A55>F$5,"",OFFSET(F$54,0,-($A55-1))) -> 0 | G55: =IF($A55>G$5,"",OFFSET(G$54,0,-($A55-1))) -> 0 | H55: =IF($A55>H$5,"",OFFSET(H$54,0,-($A55-1))) -> 56480 | I55: =IF($A55>I$5,"",OFFSET(I$54,0,-($A55-1))) -> 52379 | ... BI55: =IF($A55>BI$5,"",OFFSET(BI$54,0,-($A55-1))) -> 0
A56: 2 | B56: =IF($A56>B$5,"",OFFSET(B$54,0,-($A56-1))) | C56: =IF($A56>C$5,"",OFFSET(C$54,0,-($A56-1))) -> 0 | D56: =IF($A56>D$5,"",OFFSET(D$54,0,-($A56-1))) -> 0 | E56: =IF($A56>E$5,"",OFFSET(E$54,0,-($A56-1))) -> 0 | F56: =IF($A56>F$5,"",OFFSET(F$54,0,-($A56-1))) -> 0 | G56: =IF($A56>G$5,"",OFFSET(G$54,0,-($A56-1))) -> 0 | H56: =IF($A56>H$5,"",OFFSET(H$54,0,-($A56-1))) -> 0 | I56: =IF($A56>I$5,"",OFFSET(I$54,0,-($A56-1))) -> 56480 | ... BI56: =IF($A56>BI$5,"",OFFSET(BI$54,0,-($A56-1))) -> 0
A57: 3 | B57: =IF($A57>B$5,"",OFFSET(B$54,0,-($A57-1))) | C57: =IF($A57>C$5,"",OFFSET(C$54,0,-($A57-1))) | D57: =IF($A57>D$5,"",OFFSET(D$54,0,-($A57-1))) -> 0 | E57: =IF($A57>E$5,"",OFFSET(E$54,0,-($A57-1))) -> 0 | F57: =IF($A57>F$5,"",OFFSET(F$54,0,-($A57-1))) -> 0 | G57: =IF($A57>G$5,"",OFFSET(G$54,0,-($A57-1))) -> 0 | H57: =IF($A57>H$5,"",OFFSET(H$54,0,-($A57-1))) -> 0 | I57: =IF($A57>I$5,"",OFFSET(I$54,0,-($A57-1))) -> 0 | ... BI57: =IF($A57>BI$5,"",OFFSET(BI$54,0,-($A57-1))) -> 0
A58: 4 | B58: =IF($A58>B$5,"",OFFSET(B$54,0,-($A58-1))) | C58: =IF($A58>C$5,"",OFFSET(C$54,0,-($A58-1))) | D58: =IF($A58>D$5,"",OFFSET(D$54,0,-($A58-1))) | E58: =IF($A58>E$5,"",OFFSET(E$54,0,-($A58-1))) -> 0 | F58: =IF($A58>F$5,"",OFFSET(F$54,0,-($A58-1))) -> 0 | G58: =IF($A58>G$5,"",OFFSET(G$54,0,-($A58-1))) -> 0 | H58: =IF($A58>H$5,"",OFFSET(H$54,0,-($A58-1))) -> 0 | I58: =IF($A58>I$5,"",OFFSET(I$54,0,-($A58-1))) -> 0 | ... BI58: =IF($A58>BI$5,"",OFFSET(BI$54,0,-($A58-1))) -> 0
A59: 5 | B59: =IF($A59>B$5,"",OFFSET(B$54,0,-($A59-1))) | C59: =IF($A59>C$5,"",OFFSET(C$54,0,-($A59-1))) | D59: =IF($A59>D$5,"",OFFSET(D$54,0,-($A59-1))) | E59: =IF($A59>E$5,"",OFFSET(E$54,0,-($A59-1))) | F59: =IF($A59>F$5,"",OFFSET(F$54,0,-($A59-1))) -> 0 | G59: =IF($A59>G$5,"",OFFSET(G$54,0,-($A59-1))) -> 0 | H59: =IF($A59>H$5,"",OFFSET(H$54,0,-($A59-1))) -> 0 | I59: =IF($A59>I$5,"",OFFSET(I$54,0,-($A59-1))) -> 0 | ... BI59: =IF($A59>BI$5,"",OFFSET(BI$54,0,-($A59-1))) -> 0
A60: 6 | B60: =IF($A60>B$5,"",OFFSET(B$54,0,-($A60-1))) | C60: =IF($A60>C$5,"",OFFSET(C$54,0,-($A60-1))) | D60: =IF($A60>D$5,"",OFFSET(D$54,0,-($A60-1))) | E60: =IF($A60>E$5,"",OFFSET(E$54,0,-($A60-1))) | F60: =IF($A60>F$5,"",OFFSET(F$54,0,-($A60-1))) | G60: =IF($A60>G$5,"",OFFSET(G$54,0,-($A60-1))) -> 0 | H60: =IF($A60>H$5,"",OFFSET(H$54,0,-($A60-1))) -> 0 | I60: =IF($A60>I$5,"",OFFSET(I$54,0,-($A60-1))) -> 0 | ... BI60: =IF($A60>BI$5,"",OFFSET(BI$54,0,-($A60-1))) -> 0
A61: 7 | B61: =IF($A61>B$5,"",OFFSET(B$54,0,-($A61-1))) | C61: =IF($A61>C$5,"",OFFSET(C$54,0,-($A61-1))) | D61: =IF($A61>D$5,"",OFFSET(D$54,0,-($A61-1))) | E61: =IF($A61>E$5,"",OFFSET(E$54,0,-($A61-1))) | F61: =IF($A61>F$5,"",OFFSET(F$54,0,-($A61-1))) | G61: =IF($A61>G$5,"",OFFSET(G$54,0,-($A61-1))) | H61: =IF($A61>H$5,"",OFFSET(H$54,0,-($A61-1))) -> 0 | I61: =IF($A61>I$5,"",OFFSET(I$54,0,-($A61-1))) -> 0 | ... BI61: =IF($A61>BI$5,"",OFFSET(BI$54,0,-($A61-1))) -> 0
A62: 8 | B62: =IF($A62>B$5,"",OFFSET(B$54,0,-($A62-1))) | C62: =IF($A62>C$5,"",OFFSET(C$54,0,-($A62-1))) | D62: =IF($A62>D$5,"",OFFSET(D$54,0,-($A62-1))) | E62: =IF($A62>E$5,"",OFFSET(E$54,0,-($A62-1))) | F62: =IF($A62>F$5,"",OFFSET(F$54,0,-($A62-1))) | G62: =IF($A62>G$5,"",OFFSET(G$54,0,-($A62-1))) | H62: =IF($A62>H$5,"",OFFSET(H$54,0,-($A62-1))) | I62: =IF($A62>I$5,"",OFFSET(I$54,0,-($A62-1))) -> 0 | ... BI62: =IF($A62>BI$5,"",OFFSET(BI$54,0,-($A62-1))) -> 0
A63: 9 | B63: =IF($A63>B$5,"",OFFSET(B$54,0,-($A63-1))) | C63: =IF($A63>C$5,"",OFFSET(C$54,0,-($A63-1))) | D63: =IF($A63>D$5,"",OFFSET(D$54,0,-($A63-1))) | E63: =IF($A63>E$5,"",OFFSET(E$54,0,-($A63-1))) | F63: =IF($A63>F$5,"",OFFSET(F$54,0,-($A63-1))) | G63: =IF($A63>G$5,"",OFFSET(G$54,0,-($A63-1))) | H63: =IF($A63>H$5,"",OFFSET(H$54,0,-($A63-1))) | I63: =IF($A63>I$5,"",OFFSET(I$54,0,-($A63-1))) | ... BI63: =IF($A63>BI$5,"",OFFSET(BI$54,0,-($A63-1))) -> 0
A64: 10 | B64: =IF($A64>B$5,"",OFFSET(B$54,0,-($A64-1))) | C64: =IF($A64>C$5,"",OFFSET(C$54,0,-($A64-1))) | D64: =IF($A64>D$5,"",OFFSET(D$54,0,-($A64-1))) | E64: =IF($A64>E$5,"",OFFSET(E$54,0,-($A64-1))) | F64: =IF($A64>F$5,"",OFFSET(F$54,0,-($A64-1))) | G64: =IF($A64>G$5,"",OFFSET(G$54,0,-($A64-1))) | H64: =IF($A64>H$5,"",OFFSET(H$54,0,-($A64-1))) | I64: =IF($A64>I$5,"",OFFSET(I$54,0,-($A64-1))) | ... BI64: =IF($A64>BI$5,"",OFFSET(BI$54,0,-($A64-1))) -> 0
A65: 11 | B65: =IF($A65>B$5,"",OFFSET(B$54,0,-($A65-1))) | C65: =IF($A65>C$5,"",OFFSET(C$54,0,-($A65-1))) | D65: =IF($A65>D$5,"",OFFSET(D$54,0,-($A65-1))) | E65: =IF($A65>E$5,"",OFFSET(E$54,0,-($A65-1))) | F65: =IF($A65>F$5,"",OFFSET(F$54,0,-($A65-1))) | G65: =IF($A65>G$5,"",OFFSET(G$54,0,-($A65-1))) | H65: =IF($A65>H$5,"",OFFSET(H$54,0,-($A65-1))) | I65: =IF($A65>I$5,"",OFFSET(I$54,0,-($A65-1))) | ... BI65: =IF($A65>BI$5,"",OFFSET(BI$54,0,-($A65-1))) -> 0
A66: 12 | B66: =IF($A66>B$5,"",OFFSET(B$54,0,-($A66-1))) | C66: =IF($A66>C$5,"",OFFSET(C$54,0,-($A66-1))) | D66: =IF($A66>D$5,"",OFFSET(D$54,0,-($A66-1))) | E66: =IF($A66>E$5,"",OFFSET(E$54,0,-($A66-1))) | F66: =IF($A66>F$5,"",OFFSET(F$54,0,-($A66-1))) | G66: =IF($A66>G$5,"",OFFSET(G$54,0,-($A66-1))) | H66: =IF($A66>H$5,"",OFFSET(H$54,0,-($A66-1))) | I66: =IF($A66>I$5,"",OFFSET(I$54,0,-($A66-1))) | ... BI66: =IF($A66>BI$5,"",OFFSET(BI$54,0,-($A66-1))) -> 0
... A114: 60 | B114: =IF($A114>B$5,"",OFFSET(B$54,0,-($A114-1))) | C114: =IF($A114>C$5,"",OFFSET(C$54,0,-($A114-1))) | D114: =IF($A114>D$5,"",OFFSET(D$54,0,-($A114-1))) | E114: =IF($A114>E$5,"",OFFSET(E$54,0,-($A114-1))) | F114: =IF($A114>F$5,"",OFFSET(F$54,0,-($A114-1))) | G114: =IF($A114>G$5,"",OFFSET(G$54,0,-($A114-1))) | H114: =IF($A114>H$5,"",OFFSET(H$54,0,-($A114-1))) | I114: =IF($A114>I$5,"",OFFSET(I$54,0,-($A114-1))) | ... BI114: =IF($A114>BI$5,"",OFFSET(BI$54,0,-($A114-1))) -> 0

Sheet Sheet1
