Workbook
Name __S1: {"Book1"}
Name __S1: {"Book1"}
Name __S1: {"Book1"}
Name _a1: {"'Sheet1'!$L$16"}
Name _a1: {"'Sheet1'!$L$16"}
Name _a1: {"'Sheet1'!$L$16"}
Name _S1: {"Book1"}
Name _S1: {"Book1"}
Name _S1: {"Book1"}
Name Ă: #REF!
Name Ạ196: #REF!
Name â259: #REF!
Name â259: #REF!
Name â312: #REF!
Name â312: #REF!
Name Acquisition_PlanA: #REF!
Name Acquisition_PlanB: #REF!
Name Actual: (PeriodInActual*(#REF!>0))*PeriodInPlan
Name Actual: (PeriodInActual*(#REF!>0))*PeriodInPlan
Name Actual: (PeriodInActual*(#REF!>0))*PeriodInPlan
Name ActualBeyond: PeriodInActual*(#REF!>0)
Name ActualBeyond: PeriodInActual*(#REF!>0)
Name ActualBeyond: PeriodInActual*(#REF!>0)
Name adf: #REF!
Name adf: #REF!
Name AdvIncQ12020: #REF!
Name AdvIncQ12021: #REF!
Name AdvIncQ12022: #REF!
Name AdvIncQ12023: #REF!
Name AdvIncQ12024: #REF!
Name AdvIncQ22020: #REF!
Name AdvIncQ22021: #REF!
Name AdvIncQ22022: #REF!
Name AdvIncQ22023: #REF!
Name AdvIncQ22024: #REF!
Name AdvIncQ32020: #REF!
Name AdvIncQ32021: #REF!
Name AdvIncQ32022: #REF!
Name AdvIncQ32023: #REF!
Name AdvIncQ32024: #REF!
Name AdvIncQ42020: #REF!
Name AdvIncQ42021: #REF!
Name AdvIncQ42022: #REF!
Name AdvIncQ42023: #REF!
Name AdvIncQ42024: #REF!
Name AdvPenRate2020: #REF!
Name AdvPenRate2021: #REF!
Name AdvPenRate2022: #REF!
Name AdvPenRate2023: #REF!
Name AdvPenRate2024: #REF!
Name AllReportList: #REF!
Name Amount_act: #REF!
Name Amount_CF: #REF!
Name Amount_F: #REF!
Name Amount_KPI_act: #REF!
Name approval: #REF!
Name approval: #REF!
Name Attribute_F: #REF!
Name B: #REF!
Name b2bSpr: #REF!

Sheet IR
A1: product_final | B1: Product | C1: Partner | D1: report_date | E1: closing_balance_total | F1: closing_balance_dpd_above0 | G1: closing_balance_dpd_0 | H1: closing_balance_dpd_above10 | I1: closing_balance_dpd_under10
A2: [BE] - Bikeloan VFS | B2: BL | C2: BEG | D2: 45839 | E2: 0 | F2: 0 | G2: 0 | H2: 0 | I2: 0
A3: [BE] - Bikeloan VFS | B3: BL | C3: BEG | D3: 45840 | E3: 0 | F3: 0 | G3: 0 | H3: 0 | I3: 0
A4: [BE] - Bikeloan VFS | B4: BL | C4: BEG | D4: 45841 | E4: 0 | F4: 0 | G4: 0 | H4: 0 | I4: 0
A5: [BE] - Bikeloan VFS | B5: BL | C5: BEG | D5: 45842 | E5: 0 | F5: 0 | G5: 0 | H5: 0 | I5: 0 | O5: Product | P5: CL
A6: [BE] - Bikeloan VFS | B6: BL | C6: BEG | D6: 45843 | E6: 0 | F6: 0 | G6: 0 | H6: 0 | I6: 0
A7: [BE] - Bikeloan VFS | B7: BL | C7: BEG | D7: 45844 | E7: 0 | F7: 0 | G7: 0 | H7: 0 | I7: 0 | O7: Sum of closing_balance_dpd_under10 | P7: Column Labels
A8: [BE] - Bikeloan VFS | B8: BL | C8: BEG | D8: 45845 | E8: 0 | F8: 0 | G8: 0 | H8: 0 | I8: 0 | P8: Jul | Q8: Aug | R8: Sep | S8: Grand Total
A9: [BE] - Bikeloan VFS | B9: BL | C9: BEG | D9: 45846 | E9: 0 | F9: 0 | G9: 0 | H9: 0 | I9: 0
A10: [BE] - Bikeloan VFS | B10: BL | C10: BEG | D10: 45847 | E10: 0 | F10: 0 | G10: 0 | H10: 0 | I10: 0 | O10: Row Labels
A11: [BE] - Bikeloan VFS | B11: BL | C11: BEG | D11: 45848 | E11: 0 | F11: 0 | G11: 0 | H11: 0 | I11: 0 | O11: BEG | P11: 170179815390 | Q11: 140268239545 | R11: 112615949748 | S11: 423064004683
A12: [BE] - Bikeloan VFS | B12: BL | C12: BEG | D12: 45849 | E12: 0 | F12: 0 | G12: 0 | H12: 0 | I12: 0 | O12: CAKE | P12: 32022506029594 | Q12: 36743192910881 | R12: 41010445577689 | S12: 109776144518164
A13: [BE] - Bikeloan VFS | B13: BL | C13: BEG | D13: 45850 | E13: 0 | F13: 0 | G13: 0 | H13: 0 | I13: 0 | O13: MWG | P13: 4698496703097 | Q13: 5972450288857 | R13: 7508268877050 | S13: 18179215869004
A14: [BE] - Bikeloan VFS | B14: BL | C14: BEG | D14: 45851 | E14: 0 | F14: 0 | G14: 0 | H14: 0 | I14: 0 | O14: NGS | P14: 469139173426 | Q14: 394181683617 | R14: 324147875998 | S14: 1187468733041
A15: [BE] - Bikeloan VFS | B15: BL | C15: BEG | D15: 45852 | E15: 0 | F15: 0 | G15: 0 | H15: 0 | I15: 0 | O15: VDS | P15: 35304282404241 | Q15: 38988498527615 | R15: 42211543513670 | S15: 116504324445526
A16: [BE] - Bikeloan VFS | B16: BL | C16: BEG | D16: 45853 | E16: 0 | F16: 0 | G16: 0 | H16: 0 | I16: 0 | O16: VNPAY | P16: 2095037806093 | Q16: 2230103452703 | R16: 2307997283046 | S16: 6633138541842
A17: [BE] - Bikeloan VFS | B17: BL | C17: BEG | D17: 45854 | E17: 0 | F17: 0 | G17: 0 | H17: 0 | I17: 0 | O17: VNPOST | P17: 29336097917 | Q17: 46333290385 | R17: 80785915191 | S17: 156455303493
A18: [BE] - Bikeloan VFS | B18: BL | C18: BEG | D18: 45855 | E18: 0 | F18: 0 | G18: 0 | H18: 0 | I18: 0 | O18: ZALOPAY | P18: 3647612718340 | Q18: 5740120555825 | R18: 7034090294910 | S18: 16421823569075
A19: [BE] - Bikeloan VFS | B19: BL | C19: BEG | D19: 45856 | E19: 0 | F19: 0 | G19: 0 | H19: 0 | I19: 0 | O19: Grand Total | P19: 78436590748098 | Q19: 90255148949428 | R19: 100589895287302 | S19: 269281634984828
A20: [BE] - Bikeloan VFS | B20: BL | C20: BEG | D20: 45857 | E20: 0 | F20: 0 | G20: 0 | H20: 0 | I20: 0
A21: [BE] - Bikeloan VFS | B21: BL | C21: BEG | D21: 45858 | E21: 0 | F21: 0 | G21: 0 | H21: 0 | I21: 0
A22: [BE] - Bikeloan VFS | B22: BL | C22: BEG | D22: 45859 | E22: 0 | F22: 0 | G22: 0 | H22: 0 | I22: 0
A23: [BE] - Bikeloan VFS | B23: BL | C23: BEG | D23: 45860 | E23: 0 | F23: 0 | G23: 0 | H23: 0 | I23: 0
A24: [BE] - Bikeloan VFS | B24: BL | C24: BEG | D24: 45861 | E24: 0 | F24: 0 | G24: 0 | H24: 0 | I24: 0 | T24: CAKE | U24: =SUM(P29:R29)/GETPIVOTDATA("closing_balance_dpd_under10",$O$7,"Partner","CAKE")*365 -> 0.47916706
A25: [BE] - Bikeloan VFS | B25: BL | C25: BEG | D25: 45862 | E25: 0 | F25: 0 | G25: 0 | H25: 0 | I25: 0 | M25: cashloan | N25: cashloan | O25: VDS | P25: 48463084122 | Q25: 53272770215 | R25: 57987623749 | T25: VDS | U25: =SUM(P25:R26)/GETPIVOTDATA("closing_balance_dpd_under10",$O$7,"Partner","VDS")*365 -> 0.50203376
A26: [BE] - Bikeloan VFS | B26: BL | C26: BEG | D26: 45863 | E26: 0 | F26: 0 | G26: 0 | H26: 0 | I26: 0 | M26: cashloan | N26: payroll | O26: VDS | P26: 180134709 | Q26: 177793395 | R26: 162715192 | T26: MWG | U26: =SUM(P30:R30)/GETPIVOTDATA("closing_balance_dpd_under10",$O$7,"Partner","MWG")*365 -> 0.49258432
A27: [BE] - Bikeloan VFS | B27: BL | C27: BEG | D27: 45864 | E27: 0 | F27: 0 | G27: 0 | H27: 0 | I27: 0 | M27: cashloan | N27: cashloan | O27: BEG | P27: 208673555 | Q27: 170907800 | R27: 140807807 | T27: VNPAY | U27: =SUM(P31:R31)/GETPIVOTDATA("closing_balance_dpd_under10",$O$7,"Partner","VNPAY")*365 -> 0.45651653
A28: [BE] - Bikeloan VFS | B28: BL | C28: BEG | D28: 45865 | E28: 0 | F28: 0 | G28: 0 | H28: 0 | I28: 0 | M28: cashloan | N28: cashloan | O28: NGS | P28: 619417378 | Q28: 493982632 | R28: 409380520 | T28: ZALOPAY | U28: =SUM(P32:R32)/GETPIVOTDATA("closing_balance_dpd_under10",$O$7,"Partner","ZALOPAY")*365 -> 0.51861256
A29: [BE] - Bikeloan VFS | B29: BL | C29: BEG | D29: 45866 | E29: 0 | F29: 0 | G29: 0 | H29: 0 | I29: 0 | M29: cashloan | N29: cashloan | O29: CAKE | P29: 42400864409 | Q29: 48200259590 | R29: 53511511977
A30: [BE] - Bikeloan VFS | B30: BL | C30: BEG | D30: 45867 | E30: 0 | F30: 0 | G30: 0 | H30: 0 | I30: 0 | M30: cashloan | N30: cashloan | O30: MWG | P30: 6378275744 | Q30: 8067738498 | R30: 10087675211
A31: [BE] - Bikeloan VFS | B31: BL | C31: BEG | D31: 45868 | E31: 0 | F31: 0 | G31: 0 | H31: 0 | I31: 0 | M31: cashloan | N31: cashloan | O31: VNPAY | P31: 2629288891 | Q31: 2780395647 | R31: 2886582366
A32: [BE] - Bikeloan VFS | B32: BL | C32: BEG | D32: 45869 | E32: 0 | F32: 0 | G32: 0 | H32: 0 | I32: 0 | M32: cashloan | N32: cashloan | O32: ZALOPAY | P32: 5190014930 | Q32: 8151740830 | R32: 9991296076
A33: [BE] - Bikeloan VFS | B33: BL | C33: BEG | D33: 45870 | E33: 0 | F33: 0 | G33: 0 | H33: 0 | I33: 0 | M33: cashloan | N33: cashloan | O33: VNPOST | P33: 38874002 | Q33: 61536947 | R33: 104859015
A34: [BE] - Bikeloan VFS | B34: BL | C34: BEG | D34: 45871 | E34: 0 | F34: 0 | G34: 0 | H34: 0 | I34: 0
A35: [BE] - Bikeloan VFS | B35: BL | C35: BEG | D35: 45872 | E35: 0 | F35: 0 | G35: 0 | H35: 0 | I35: 0
A36: [BE] - Bikeloan VFS | B36: BL | C36: BEG | D36: 45873 | E36: 0 | F36: 0 | G36: 0 | H36: 0 | I36: 0
A37: [BE] - Bikeloan VFS | B37: BL | C37: BEG | D37: 45874 | E37: 0 | F37: 0 | G37: 0 | H37: 0 | I37: 0
A38: [BE] - Bikeloan VFS | B38: BL | C38: BEG | D38: 45875 | E38: 0 | F38: 0 | G38: 0 | H38: 0 | I38: 0
A39: [BE] - Bikeloan VFS | B39: BL | C39: BEG | D39: 45876 | E39: 0 | F39: 0 | G39: 0 | H39: 0 | I39: 0
A40: [BE] - Bikeloan VFS | B40: BL | C40: BEG | D40: 45877 | E40: 0 | F40: 0 | G40: 0 | H40: 0 | I40: 0
A41: [BE] - Bikeloan VFS | B41: BL | C41: BEG | D41: 45878 | E41: 0 | F41: 0 | G41: 0 | H41: 0 | I41: 0
A42: [BE] - Bikeloan VFS | B42: BL | C42: BEG | D42: 45879 | E42: 0 | F42: 0 | G42: 0 | H42: 0 | I42: 0
A43: [BE] - Bikeloan VFS | B43: BL | C43: BEG | D43: 45880 | E43: 0 | F43: 0 | G43: 0 | H43: 0 | I43: 0
A44: [BE] - Bikeloan VFS | B44: BL | C44: BEG | D44: 45881 | E44: 0 | F44: 0 | G44: 0 | H44: 0 | I44: 0
A45: [BE] - Bikeloan VFS | B45: BL | C45: BEG | D45: 45882 | E45: 0 | F45: 0 | G45: 0 | H45: 0 | I45: 0
... A2246: [ZALOPAY] - Cashloan | B2246: CL | C2246: ZALOPAY | D2246: 45930 | E2246: 265187908930 | F2246: 13122834466 | G2246: 252065074464 | H2246: 9728610374 | I2246: 255459298556

Sheet COF
F1: =SUBTOTAL(9,F3:F43) -> 16198720096480 | G1: =SUBTOTAL(9,G3:G43) -> 3.1233841e+09 | I1: =G1/F1*365 -> 0.070378103 | K1: 0.070378103
F2: =SUM(F4:F42) -> 348822682508025 | G2: =SUM(G4:G42) -> 6.3783621e+10 | I2: =SUM(I4:I42) -> 1173
B3: Nhom | C3: SP | D3: Partner | E3: pl | F3: Sum of BALANCE | G3: Sum of Lai DCV | H3: Month | I3: Day
B4: UPL | C4: cl | D4: BE | E4: BE CASHLOAN | F4: 175237237692 | G4: 35108054 | H4: 9 | I4: 30
B5: UPL | C5: cl | D5: CAKE | E5: CAKE CASHLOAN | F5: 45792086198052 | G5: 8.8220401e+09 | H5: 9 | I5: 30
B6: UPL | C6: OD | D6: CAKE | E6: CAKE OVERDRAFT | F6: 7169005435909 | G6: 9.9109849e+08 | H6: 9 | I6: 30
B7: UPL | C7: PD | D7: CAKE | E7: CAKE PAYDAY | F7: 3672603510227 | G7: 5.4667902e+08 | H7: 9 | I7: 30
B8: UPL | C8: cl | D8: MWG | E8: MWG CASHLOAN | F8: 7860835561894 | G8: 1.5211837e+09 | H8: 9 | I8: 30
B9: UPL | C9: cl | D9: NGS | E9: NGS CASHLOAN | F9: 530282165595 | G9: 1.1619612e+08 | H9: 9 | I9: 30
B10: UPL | C10: cl | D10: VDS | E10: VIETTEL CASHLOAN | F10: 47500871433668 | G10: 9.1994775e+09 | H10: 9 | I10: 30
B11: UPL | C11: PD | D11: VDS | E11: VIETTEL PAYDAY | F11: 6555226346162 | G11: 1.021781e+09 | H11: 9 | I11: 30
B12: UPL | C12: PD | D12: VDS | E12: VIETTEL PAYDAYPAYROLL | F12: 25934847005 | G12: 3828070.8 | H12: 9 | I12: 30
B13: UPL | C13: cl | D13: VDS | E13: VIETTEL PAYROLL CASHLOAN | F13: 234239258102 | G13: 44742343 | H13: 9 | I13: 30
B14: UPL | C14: cl | D14: VNPAY | E14: VNPAY CASHLOAN | F14: 2538375718443 | G14: 4.6902939e+08 | H14: 9 | I14: 30
B15: UPL | C15: cl | D15: VNPOST | E15: VNPOST CASHLOAN | F15: 74534379401 | G15: 14917048 | H15: 9 | I15: 30
... B42: UPL | C42: cl | D42: ZALOPAY | E42: Zalopay CASHLOAN | F42: 3450971717669 | G42: 6.384429e+08 | H42: 7 | I42: 31

Sheet NOTE
A1: SAP MODEL - CASHLOAN
B2: OFFICIAL | N2: HKN | O2: v9 | P2: 20251001
B3: 1. Notes and disclaimer
C4: a. Giới thiệu về SAP
D5: - SAP: Single Account Profitability (Hiệu quả sản phẩm trên từng đơn vị sản phẩm)
D6: - Model SAP được sử dụng như một (01) trong các mô hình dự đoán hiệu quả vòng đời của sản phẩm.
D7: - Do sự phức tạp của sản phẩm, các hệ thống vận hành (hệ thống hạch kế toán, hệ thống quản trị rủi ro, hệ thống quản trị…), hành vi người sử dụng hành vi người sử dụng, model chỉ có thể mô phỏng tương đối trung bình vòng đời của sản phẩm.
D8: - Do tính chất thời điểm, mô hình được xây dựng mô phỏng theo cách vận hành sản phẩm tại thời điểm phát hành. Trường hợp hệ thống thay đổi, sản phẩm thay đổi, mô hình sẽ không thể phản ánh đúng bản chất vận hành sản phẩm.
D9: - Mô hình được tính toán dựa vào các yếu tố đầu vào xác định tại một thời điểm xác định, do đó kết quả của mô hình có thể có sự khác biệt so với thực tế vận hành sản phẩm.
D10: - Mô hình SAP Cashloan tính hiệu quả của khoản vay giải ngân và thời hạn tối đa được áp dụng là 5 năm ( 60 tháng) kể từ ngày bắt đầu sản phẩm đối với sử dụng phương pháp dự phòng IFRS
E11: - Lưu ý rằng trường hợp áp dụng cho khoản vay 5 năm, thì các chi phí sẽ không được tính toán đầy đủ do chi phí COF cho thời gian từ lúc khoản vay kết thúc tới lúc được xóa trên sổ kế toán.
E12: - Chỉ nên sử dụng với khoản vay dưới 4 năm (48 tháng) để được tính toán đầy đủ chi phí
E13: - Đối với phương pháp tính rủi ro VAS, thời hạn khoản vay tối đa sử dụng là 4 năm (48 tháng)
C15: b. Giới thiệu về PnL
D16: - Trong file tính này, Profit & Lost (PnL) được dự phóng từ trung bình cộng kết quả kinh doanh trên từng sản phẩm (SAP) với yếu tố "sale plan" (số giải ngân) qua từng tháng, do đó có thể khác biệt so với kết quả thực tế vận hành.
D17: - Dòng tiền thực tế qua từng tháng có thể khác biệt với mô hình tính toán do nhiều yếu tố tác động bên ngoài thay đổi, do đó, vui lòng chỉ sử dụng mô hình cho mục đích tham khảo.
D18: - Cho mục đích tính dự phòng dòng tiền ngắn và trung hạn, mô hình PnL được cutoff tại thời điểm 5 năm (60 tháng) kể từ ngày bắt đầu khởi chạy sản phẩm đầu tiên.
B20: 2. Instruction
D21: - Dành cho người sử dụng
E22: - Chỉ chỉnh sửa vào các ô màu vàng
E23: - 2 sheets "SAP_Leadsheet" và "Sale plan&PnL" cung cấp yếu tố đầu vào và đầu ra để tính toán mô hình SAP cũng như PnL.
F24: - Sheet SAP_Leadsheet được cấu trúc 2 phần, bên trái là các yếu tố đầu vào (input) và bên phải là kết quả dự đoán (output). Đơn vị sử dụng tại bảng tính là triệu VND (mVND) và phần trăm (%)
F25: - Sheet "Sale plan & PL" được cấu trúc 2 phần, bên trên là sale plan và bên dưới là kết quả PnL
E26: - 2 sheets "SAP_Spreadsheet" và "PL projection speadsheet" là các file tính toán cho 2 sheet "SAP_Leadsheet", "Sales plan & PL"
F27: - 2 sheets được cấu trúc từ trên xuống dưới theo thứ tự tính toán mô phỏng để đưa ra kết quả kinh doanh cuối cùng
F28: - 2 sheets đã được tạm khóa. Trường hợp cần mở khóa, điều chỉnh các yếu tố, vui lòng liên hệ với nhóm vận hành để được hỗ trợ.
D30: - Dành riêng cho người vận hành, hiệu chỉnh
E31: - Cần cẩn trọng khi điều chỉnh ở các file "speadsheet" vì 1 khi sai lệch rất khó tìm ra lỗi (VD: sửa nhầm ô, link nhầm vị trí,…)
B34: 3. Legend
C35: GENERAL INPUT
G37: Diễn giải | L37: Chú thích
D38: Risk input | G38: Loại phương pháp tính rủi ro | L38: Lựa chon phương pháp tính rủi ro VAS và IFRS
D39: Write off | G39: Thời điểm WO | L39: Lựa chọn thời điểm ghi nhận WO là 360 hoặc 180
C40: REVENUE INPUT
G42: Diễn giải | L42: Chú thích
C43: Amount & Tenor
D44: Loan amount | G44: Số tiền vay giải ngân (có thể bao gồm bảo hiểm hoặc không) | L44: Trường hợp số tiền giải ngân > giá trị hàng hóa, chỉ ghi = số thực tế giải ngân
D45: Payment Method | G45: Phương pháp tính lãi | L45: EMI (Equated monthly Installment)- số tiền thanh toán cố định hàng tháng
D46: Nominal Tenor | G46: Thời hạn vay | L46: Thời hạn ghi nhận trên khoản vay ( VD: 1 tháng, 3 tháng, 12 tháng,…)
D47: Maturity to Termination | G47: Thời hạn từ lúc đáo hạn tới lúc tới khi ra ngoại bảng | L47: Nên để 6 tháng để khớp với hệ thống kế toán, rủi ro đang ghi nhận WO180+
D48: Month on book | G48: Thời gian ghi nhận trên sổ sách | L48: = Nominal tenor + Maturity to termination
C50: Pricing
D51: From- To | G51: Từ tháng… tới tháng
D52: IR | G52: Interest rate- lãi suất khoản vay
D53: COF | G53: Cost of fund - Giá vốn | L53: Sử dụng matrix mua vốn của VPB
D54: NIM | G54: Net interest margin - Biên lãi ròng
C56: Early prepayment
D57: From- To | G57: Từ tháng… tới tháng
D58: Penalty fee | G58: Phí phạt
D59: Penalty IR | G59: Lãi phạt
D60: %Attrition | G60: Tỉ lệ trả trước hạn | L60: Tỉ lệ trả trước tính theo cohort, thông thường quan sát trung bình 6 tháng
C61: Credit insurrance
D62: Banca Premium (excl. in loan) | G62: Tỉ lệ bảo hiểm khoản vay (dư nợ không bao gồm bảo hiểm khoản vay) | L62: VD: 7% khoản vay, 8% khoản vay
D63: Banca Premium (incl. in loan) | G63: Tỉ lệ bảo hiểm khoản vay (dư nợ có bao gồm bảo hiểm khoản vay)
D64: Penetration | G64: Tỉ lệ khoản vay có bảo hiểm/tổng khoản vay giải ngân
D65: Commission to CAKE | G65: Tỉ lệ nhận được từ số tiền bảo hiểm | L65: Hiện tai, số này là khoàng 85% tổng số tiền thu từ bảo hiểm
C66: Support fee
D67: Các khoản thu khác | L67: Hiện tại chưa có
C72: COST INPUT
G74: Diễn giải | L74: Chú thích
C75: Inflation rate | G75: Tỉ lệ tăng giá chi phí qua các năm
C77: Acquisition cost | G77: Chi phí mở rộng khách hàng
D78: Sale incentive | G78: Chi phí sales, trả đối tác kinh doanh
D79: Sharing TOI and Risk DPD90+ | G79: Chia sẻ doanh thu, rủi ro(DPD90+) | L79: xem giải thích DPD+ tại đây
D80: Sharing TOI and Risk DPD180+ | G80: Chia sẻ doanh thu, rủi ro(DPD180+) | L80: xem giải thích DPD+ tại đây
D82: Sharing CII (only) | G82: Chỉ chia sẻ doanh thu từ lãi
D83: Sharing COF (only) | G83: Chỉ chia sẻ chi phí vốn
D84: Sharing NFI (only) | G84: Chỉ chia sẻ doanh thu từ vốn
D85: Sharing Risk DPD90+ (Only) | G85: Chỉ chia sẻ rủi ro (DPD90+) | L85: xem giải thích DPD+ tại đây
D86: Sharing Risk DPD180+ (only) | G86: Chỉ chia sẻ rủi ro (DPD180+) | L86: xem giải thích DPD+ tại đây
D88: Partner Lead Acquistion | G88: Chi phí leadgen đối tác
C90: * Chú thích
C91: Chia sẻ rủi ro DPD90/ (DPD180+) là phương pháp tính rủi ro = 100% duy nhất 1 lần tại thời điểm dư nợ DPD90 +(tức quá hạn >90 ngày, chuyển nợ nhóm 3)/ DPD180+(tức qua hạn >180 ngày, chuyển nợ nhóm 4) mà ko tính tại các bucket khác.
C92: Phương pháp này chỉ sử dụng đối với các đối tác chia sẻ doanh thu chi phí.
D94: Marketing cost | G94: Chi phí marketing để mở khoản vay
D96: UW & Disbursal
E97: Underwriting cost & Score | G97: Chi phí kiểm tra điều kiện mở khoản vay
E98: DOP cost | G98: Chi phí luồng DOP (nếu có) (SMS,…)
E99: Disbursement cost | G99: Chi phí mở khoản vay (chi phí esign, sms,…)
E100: Approval rate | G100: Tỉ lệ phê duyệt | L100: Tỉ lệ khách hàng được phê duyệt/khách hàng vào luồng LOS
E101: Disbursement rate | G101: Tỉ lệ giải ngân | L101: Tỉ lệ khách hàng giải ngân/khách hàng được phê duyệt
D103: Collection & AMC
E104: Collections_all | G104: Đơn giá thu nợ tính trung bình cho các khoản vay
D106: Aftersale service
E107: Email & SMS | G107: Chi phí Email, SMS hàng tháng
D109: Supporting units | G109: Chi phí phân bổ
E110: Direct HR | G110: Chi phí nhân sự trực tiếp
E111: Indirect HR | G111: Chi phí nhân sự hỗ trợ
E112: IT | G112: Chi phí IT
E113: Other supports | G113: Chi phí khác (Chi phí thuê VP, CS, khác…)
C115: RISK INPUT
D117: NF | G117: Netflow- Tỉ lệ chuyển nợ
D118: PD | G118: Percentage of debt (tỉ lệ vỡ nợ)
D119: Pro. Rate | G119: Tỉ lệ vỡ nợ đã điều chỉnh thu hồi nợ
D121: Recovery rate | G121: Tỉ lệ thu hồi nợ sau WO
D122: Collect after WO
D123: Fee and others | G123: Tỉ lệ thu được phí, phạt, khác
B128: Write-off mode | E128: Provision mode
B129: DPD360+ | E129: IFRS
B130: DPD180+ | E130: VAS

Sheet Leadsheet
B1: SAP CASHLOAN MODEL | D1: 1
B2: =NOTE!N2 -> HKN | C2: =NOTE!P2 -> 20251001 | D2: =NOTE!O2 -> v9 | K2: NOTE
K3: Please read carefully about before using model
B4: Product | C4: Unsecured Cashloan | D4: UPL | E4: Risk input | G4: IFRS | H4: =G4 -> IFRS | L4: Disclaimer
B5: Sub-Product | C5: Cashloan | D5: ALL | E5: Write off | G5: DPD180+ | H5: =G5 -> DPD180+ | L5: Instruction
B6: Sub-Segments | C6: ZALOPAY | D6: ALL | E6: Quarter | G6: Q3.2025 | H6: =G6 -> Q3.2025 | L6: Legend
B8: REVENUE INPUT | H8: Cur: mVND | K8: GENERAL OUTPUT | U8: Cur: mVND
B10: Amount & Tenor | C10: Loan amount | E10: =DATA!G20 -> 14.389345 | N10: Life time | O10: Year 1 | P10: Year 2 | Q10: Year 3 | R10: Year 4 | S10: Year 5 | T10: % ANR | U10: % Disbursement
C11: Payment Method | E11: EMI | K11: ANR | N11: =N29 -> 4.491385 | O11: =O29 -> 7.2311727 | P11: =P29 -> 0.3817034 | Q11: =Q29 -> 0 | R11: =R29 -> 0 | S11: =S29 -> 0 | U11: =N11/$E$10 -> 0.31213269
C12: Nominal Tenor | E12: =DATA!H20 -> 14 | K12: TOI | N12: =SUM(N13:N15) -> 3.4971427 | O12: =SUM(O13:O15) -> 3.4461461 | P12: =SUM(P13:P15) -> 0.050996647 | Q12: =SUM(Q13:Q15) -> 0 | R12: =SUM(R13:R15) -> 0 | S12: =SUM(S13:S15) -> 0 | T12: =N12/$E$14*12/$N$11 -> 0.46718009 | U12: =N12/$E$10 -> 0.24303697
C13: Maturity to Termination | E13: 6 | K13: Net interest income | N13: =N31 -> 2.9659145 | O13: =O31 -> 2.9163234 | P13: =P31 -> 0.049591122 | Q13: =Q31 -> 0 | R13: =R31 -> 0 | S13: =S31 -> 0 | T13: =N13/$E$14*12/$N$11 -> 0.3962138 | U13: =N13/$E$10 -> 0.2061188
C14: Month on book | E14: =E12+E13 -> 20 | K14: Net fee income | N14: =N34 -> 0.53122822 | O14: =O34 -> 0.52982269 | P14: =P34 -> 0.0014055248 | Q14: =Q34 -> 0 | R14: =R34 -> 0 | S14: =S34 -> 0 | T14: =N14/$E$14*12/$N$11 -> 0.070966291 | U14: =N14/$E$10 -> 0.036918165
K15: Other income | N15: =N38 -> 0 | O15: =O38 -> 0 | P15: =P38 -> 0 | Q15: =Q38 -> 0 | R15: =R38 -> 0 | S15: =S38 -> 0 | T15: =N15/$E$14*12/$N$11 -> 0 | U15: =N15/$E$10 -> 0
K16: PROVISION | N16: =N39 -> -1.8345326 | O16: =O39 -> -1.7819252 | P16: =P39 -> -0.052607412 | Q16: =Q39 -> 0 | R16: =R39 -> 0 | S16: =S39 -> 0 | T16: =N16/$E$14*12/$N$11 -> -0.24507353 | U16: =N16/$E$10 -> -0.12749243
B17: Pricing | C17: From | D17: To | E17: IR | F17: COF | G17: NIM | K17: OPEX | N17: =SUM(N18:N21) -> -0.99439331 | O17: =SUM(O18:O21) -> -0.92092924 | P17: =SUM(P18:P21) -> -0.07346407 | Q17: =SUM(Q18:Q21) -> 0 | R17: =SUM(R18:R21) -> 0 | S17: =SUM(S18:S21) -> 0 | T17: =N17/$E$14*12/$N$11 -> -0.13284009 | U17: =N17/$E$10 -> -0.069106225
A18: 1 | B18: 1 | C18: 1 | D18: =E12 -> 14 | E18: =IR!U28 -> 0.51861256 | F18: =COF!K1 -> 0.070378103 | G18: =E18-F18 -> 0.44823445 | K18: Acquisition cost | N18: =SUM(N41) -> -0.35973363 | O18: =SUM(O41) -> -0.35973363 | P18: =SUM(P41) -> 0 | Q18: =SUM(Q41) -> 0 | R18: =SUM(R41) -> 0 | S18: =SUM(S41) -> 0 | T18: =N18/$E$14*12/$N$11 -> -0.048056485 | U18: =N18/$E$10 -> -0.025
A19: 2 | B19: 2 | C19: =IF(D18="","",IF(D18>$E$12,"",D18+1)) -> 15 | D19: =E14 -> 20 | E19: =E18 -> 0.51861256 | F19: =F18 -> 0.070378103 | G19: =E19-F19 -> 0.44823445 | K19: UW & Disbursal | N19: =N45 -> -0.038198394 | O19: =O45 -> -0.038198394 | P19: =P45 -> 0 | Q19: =Q45 -> 0 | R19: =R45 -> 0 | S19: =S45 -> 0 | T19: =N19/$E$14*12/$N$11 -> -0.0051028885 | U19: =N19/$E$10 -> -0.0026546305
A20: 3 | B20: 3 | K20: Collection & aftersale service | N20: =N48 -> -0.095508824 | O20: =O48 -> -0.0788665 | P20: =P48 -> -0.016642324 | Q20: =Q48 -> 0 | R20: =R48 -> 0 | S20: =S48 -> 0 | T20: =N20/$E$14*12/$N$11 -> -0.012758936 | U20: =N20/$E$10 -> -0.0066374685
A21: 4 | B21: 4 | K21: Support unit | N21: =N52 -> -0.50095247 | O21: =O52 -> -0.44413072 | P21: =P52 -> -0.056821746 | Q21: =Q52 -> 0 | R21: =R52 -> 0 | S21: =S52 -> 0 | T21: =N21/$E$14*12/$N$11 -> -0.066921781 | U21: =N21/$E$10 -> -0.034814126
A22: 5 | B22: 5 | K22: PBT | N22: =N12+N16+N17 -> 0.66821686 | O22: =O12+O16+O17 -> 0.74329169 | P22: =P12+P16+P17 -> -0.075074836 | Q22: =Q12+Q16+Q17 -> 0 | R22: =R12+R16+R17 -> 0 | S22: =S12+S16+S17 -> 0 | T22: =N22/$E$14*12/$N$11 -> 0.089266478 | U22: =N22/$E$10 -> 0.04643831
B23: 6 | K23: In which: PROFIT BEFORE SU | N23: =N22-N21 -> 1.1691693 | O23: =O22-O21 -> 1.1874224 | P23: =P22-P21 -> -0.01825309 | Q23: =Q22-Q21 -> 0 | R23: =R22-R21 -> 0 | S23: =S22-S21 -> 0 | T23: =N23/$E$14*12/$N$11 -> 0.15618826 | U23: =N23/$E$10 -> 0.081252435
B25: Early prepayment | C25: From | D25: To | E25: Penalty fee | F25: Penalty IR | G25: %Attrition
B26: 1 | C26: 1 | D26: 1 | E26: 0.03 | G26: 0.08 | H26: per cohort | K26: PERFORMANCE OUTPUT | U26: Cur: mVND
B27: 2 | C27: =D26+1 -> 2 | D27: 3 | E27: 0.03 | G27: 0.06 | H27: per cohort
B28: 3 | C28: =D27+1 -> 4 | D28: 14 | E28: 0.03 | G28: 0.025 | H28: per cohort | N28: Life time | O28: Year 1 | P28: Year 2 | Q28: Year 3 | R28: Year 4 | S28: Year 5 | T28: % ANR | U28: % Disbursement
B29: 4 | C29: =IF(D28="","",IF(D28>$E$12,"",D28+1)) -> 15 | K29: ANR | N29: =SUM(SAP_Speadsheet!$D$50:$BF$50)/COUNTIF(SAP_Speadsheet!$D$50:$BF$50,">0") -> 4.491385 | O29: =IFERROR(SUM(SAP_Speadsheet!$D$50:$P$50)/COUNTIF(SAP_Speadsheet!$D$50:$P$50,">0"),0) -> 7.2311727 | P29: =IFERROR(SUM(SAP_Speadsheet!$Q$50:$AB$50)/COUNTIF(SAP_Speadsheet!$Q$50:$AB$50,">0"),0) -> 0.3817034 | Q29: =IFERROR(SUM(SAP_Speadsheet!$AC$50:$AN$50)/COUNTIF(SAP_Speadsheet!$AC$50:$AN$50,">0"),0) -> 0 | R29: =IFERROR(SUM(SAP_Speadsheet!$AO$50:$AZ$50)/COUNTIF(SAP_Speadsheet!$AO$50:$AZ$50,">0"),0) -> 0 | S29: =IFERROR(SUM(SAP_Speadsheet!$BA$50:$BF$50)/COUNTIF(SAP_Speadsheet!$BA$50:$BF$50,">0"),0) -> 0 | U29: =N29/$E$10 -> 0.31213269
B30: 5 | C30: =IF(D29="","",IF(D29>$E$12,"",D29+1)) | E30: =IF(D30="",0,SUMIFS(#REF!,#REF!,Leadsheet!G$24,#REF!,Leadsheet!$A30,#REF!,Leadsheet!$C$4,#REF!,Leadsheet!$G$5,#REF!,Leadsheet!$D$5,#REF!,Leadsheet!G4)) -> 0 | F30: 0 | K30: TOI | N30: =SUM(O30:S30) -> 3.4971427 | O30: =SUM(SAP_Speadsheet!$E$55:$P$55) -> 3.4461461 | P30: =SUM(SAP_Speadsheet!$Q$55:$AB$55) -> 0.050996647 | Q30: =SUM(SAP_Speadsheet!$AC$55:$AN$55) -> 0 | R30: =SUM(SAP_Speadsheet!$AO$55:$AZ$55) -> 0 | S30: =SUM(SAP_Speadsheet!$BA$55:$BF$55) -> 0 | T30: =N30/$E$14*12/$N$29 -> 0.46718009 | U30: =N30/$E$10 -> 0.24303697
B31: 6 | C31: =IF(D30="","",IF(D30>$E$12,"",D30+1)) | E31: =IF(D31="",0,SUMIFS(#REF!,#REF!,Leadsheet!G$24,#REF!,Leadsheet!$A31,#REF!,Leadsheet!$C$4,#REF!,Leadsheet!$G$5,#REF!,Leadsheet!$D$5,#REF!,Leadsheet!G4)) -> 0 | F31: 0 | K31: Net interest income | N31: =SUM(O31:S31) -> 2.9659145 | O31: =SUM(SAP_Speadsheet!$E$57:$P$57) -> 2.9163234 | P31: =SUM(SAP_Speadsheet!$Q$57:$AB$57) -> 0.049591122 | Q31: =SUM(SAP_Speadsheet!$AC$57:$AN$57) -> 0 | R31: =SUM(SAP_Speadsheet!$AO$57:$AZ$57) -> 0 | S31: =SUM(SAP_Speadsheet!$BA$57:$BF$57) -> 0 | T31: =N31/$E$14*12/$N$29 -> 0.3962138 | U31: =N31/$E$10 -> 0.2061188
K32: Interest income | N32: =SUM(O32:S32) -> 3.4927398 | O32: =SUM(SAP_Speadsheet!$E$58:$P$58) -> 3.4252396 | P32: =SUM(SAP_Speadsheet!$Q$58:$AB$58) -> 0.067500163 | Q32: =SUM(SAP_Speadsheet!$AC$58:$AN$58) -> 0 | R32: =SUM(SAP_Speadsheet!$AO$58:$AZ$58) -> 0 | S32: =SUM(SAP_Speadsheet!$BA$58:$BF$58) -> 0 | T32: =N32/$E$14*12/$N$29 -> 0.46659191 | U32: =N32/$E$10 -> 0.24273098
B33: Credit insurrance | C33: Banca Premium (excl. in loan) | F33: per disbursement amount | K33: Cost of fund | N33: =SUM(O33:S33) -> -0.52682525 | O33: =SUM(SAP_Speadsheet!$E$59:$P$59) -> -0.50891621 | P33: =SUM(SAP_Speadsheet!$Q$59:$AB$59) -> -0.017909041 | Q33: =SUM(SAP_Speadsheet!$AC$59:$AN$59) -> 0 | R33: =SUM(SAP_Speadsheet!$AO$59:$AZ$59) -> 0 | S33: =SUM(SAP_Speadsheet!$BA$59:$BF$59) -> 0 | T33: =N33/$E$14*12/$N$29 -> -0.070378103 | U33: =N33/$E$10 -> -0.036612177
C34: Banca Premium (incl. in loan) | E34: =DATA!J20 -> 0.070807838 | F34: per disbursement amount | K34: Net fee income | N34: =SUM(O34:S34) -> 0.53122822 | O34: =SUM(SAP_Speadsheet!$E$61:$P$61) -> 0.52982269 | P34: =SUM(SAP_Speadsheet!$Q$61:$AB$61) -> 0.0014055248 | Q34: =SUM(SAP_Speadsheet!$AC$61:$AN$61) -> 0 | R34: =SUM(SAP_Speadsheet!$AO$61:$AZ$61) -> 0 | S34: =SUM(SAP_Speadsheet!$BA$61:$BF$61) -> 0 | T34: =N34/$E$14*12/$N$29 -> 0.070966291 | U34: =N34/$E$10 -> 0.036918165
C35: Penetration | E35: =DATA!K20 -> 0.47917585 | F35: per disbursement amount | K35: Early termination fee | N35: =SUM(O35:S35) -> 0.12702464 | O35: =SUM(SAP_Speadsheet!$E$62:$P$62) -> 0.12561911 | P35: =SUM(SAP_Speadsheet!$Q$62:$AB$62) -> 0.0014055248 | Q35: =SUM(SAP_Speadsheet!$AC$62:$AN$62) -> 0 | R35: =SUM(SAP_Speadsheet!$AO$62:$AZ$62) -> 0 | S35: =SUM(SAP_Speadsheet!$BA$62:$BF$62) -> 0 | T35: =N35/$E$14*12/$N$29 -> 0.016969105 | U35: =N35/$E$10 -> 0.0088276873
C36: Commission to CAKE | E36: 0.856 | F36: per disbursement amount | H36: done | K36: Insurance commission | N36: =SUM(O36:S36) -> 0.40420358 | O36: =SUM(SAP_Speadsheet!$E$63:$P$63) -> 0.40420358 | P36: =SUM(SAP_Speadsheet!$Q$63:$AB$63) -> 0 | Q36: =SUM(SAP_Speadsheet!$AC$63:$AN$63) -> 0 | R36: =SUM(SAP_Speadsheet!$AO$63:$AZ$63) -> 0 | S36: =SUM(SAP_Speadsheet!$BA$63:$BF$63) -> 0 | T36: =N36/$E$14*12/$N$29 -> 0.053997186 | U36: =N36/$E$10 -> 0.028090478
H37: done | K37: Support fee | N37: =SUM(O37:S37) -> 0 | O37: =SUM(SAP_Speadsheet!$E$64:$P$64) -> 0 | P37: =SUM(SAP_Speadsheet!$Q$64:$AB$64) -> 0 | Q37: =SUM(SAP_Speadsheet!$AC$64:$AN$64) -> 0 | R37: =SUM(SAP_Speadsheet!$AO$64:$AZ$64) -> 0 | S37: =SUM(SAP_Speadsheet!$BA$64:$BF$64) -> 0 | T37: =N37/$E$14*12/$N$29 -> 0 | U37: =N37/$E$10 -> 0
B38: Support fee | C38: One-time | F38: $ per account | K38: Other income | N38: =SUM(O38:S38) -> 0 | O38: =SUM(SAP_Speadsheet!$E$68:$P$68) -> 0 | P38: =SUM(SAP_Speadsheet!$Q$68:$AB$68) -> 0 | Q38: =SUM(SAP_Speadsheet!$AC$68:$AN$68) -> 0 | R38: =SUM(SAP_Speadsheet!$AO$68:$AZ$68) -> 0 | S38: =SUM(SAP_Speadsheet!$BA$68:$BF$68) -> 0 | T38: =N38/$E$14*12/$N$29 -> 0 | U38: =N38/$E$10 -> 0
C39: One-time | F39: % per ticketsize | K39: PROVISION | N39: =SUM(O39:S39) -> -1.8345326 | O39: =SUM(SAP_Speadsheet!$E$183:$P$183) -> -1.7819252 | P39: =SUM(SAP_Speadsheet!$Q$183:$AB$183) -> -0.052607412 | Q39: =SUM(SAP_Speadsheet!$AC$183:$AN$183) -> 0 | R39: =SUM(SAP_Speadsheet!$AO$183:$AZ$183) -> 0 | S39: =SUM(SAP_Speadsheet!$BA$183:$BF$183) -> 0 | T39: =N39/$E$14*12/$N$29 -> -0.24507353 | U39: =N39/$E$10 -> -0.12749243
C40: Monthly fee | F40: %monthly per ticketsize | K40: OPEX | N40: =SUM(O40:S40) -> -0.99439331 | O40: =+SUM(O41,O45,O48,O52) -> -0.92092924 | P40: =+SUM(P41,P45,P48,P52) -> -0.07346407 | Q40: =+SUM(Q41,Q45,Q48,Q52) -> 0 | R40: =+SUM(R41,R45,R48,R52) -> 0 | S40: =+SUM(S41,S45,S48,S52) -> 0 | T40: =N40/$E$14*12/$N$29 -> -0.13284009 | U40: =N40/$E$10 -> -0.069106225
B41: COST INPUT | H41: Cur: mVND | K41: Acquisition cost | N41: =SUM(O41:S41) -> -0.35973363 | O41: =SUM(O42:O44) -> -0.35973363 | P41: =SUM(P42:P44) -> 0 | Q41: =SUM(Q42:Q44) -> 0 | R41: =SUM(R42:R44) -> 0 | S41: =SUM(S42:S44) -> 0 | T41: =N41/$E$14*12/$N$29 -> -0.048056485 | U41: =N41/$E$10 -> -0.025
K42: Lead Acquisition | N42: =SUM(O42:S42) -> -0.35973363 | O42: =SUM(SAP_Speadsheet!$E$73:$P$73) -> -0.35973363 | P42: =SUM(SAP_Speadsheet!$Q$73:$AB$73) -> 0 | Q42: =SUM(SAP_Speadsheet!$AC$73:$AN$73) -> 0 | R42: =SUM(SAP_Speadsheet!$AO$73:$AZ$73) -> 0 | S42: =SUM(SAP_Speadsheet!$BA$73:$BF$73) -> 0 | T42: =N42/$E$14*12/$N$29 -> -0.048056485 | U42: =N42/$E$10 -> -0.025
B43: Inflation rate | E43: 0.035 | F43: % per year | K43: Sharing performance | N43: =SUM(O43:S43) -> 0 | O43: =SUM(SAP_Speadsheet!$E$74:$P$74) -> 0 | P43: =SUM(SAP_Speadsheet!$Q$74:$AB$74) -> 0 | Q43: =SUM(SAP_Speadsheet!$AC$74:$AN$74) -> 0 | R43: =SUM(SAP_Speadsheet!$AO$74:$AZ$74) -> 0 | S43: =SUM(SAP_Speadsheet!$BA$74:$BF$74) -> 0 | T43: =N43/$E$14*12/$N$29 -> 0 | U43: =N43/$E$10 -> 0
K44: Marketing | N44: =SUM(O44:S44) -> 0 | O44: =SUM(SAP_Speadsheet!$E$86:$P$86) -> 0 | P44: =SUM(SAP_Speadsheet!$Q$86:$AB$86) -> 0 | Q44: =SUM(SAP_Speadsheet!$AC$86:$AN$86) -> 0 | R44: =SUM(SAP_Speadsheet!$AO$86:$AZ$86) -> 0 | S44: =SUM(SAP_Speadsheet!$BA$86:$BF$86) -> 0 | T44: =N44/$E$14*12/$N$29 -> 0 | U44: =N44/$E$10 -> 0
B45: Acquisition cost | K45: UW & Disbursal | N45: =SUM(O45:S45) -> -0.038198394 | O45: =SUM(O46:O47) -> -0.038198394 | P45: =SUM(P46:P47) -> 0 | Q45: =SUM(Q46:Q47) -> 0 | R45: =SUM(R46:R47) -> 0 | S45: =SUM(S46:S47) -> 0 | T45: =N45/$E$14*12/$N$29 -> -0.0051028885 | U45: =N45/$E$10 -> -0.0026546305
C46: Sale incentive | E46: Auto MODE | K46: Underwriting | N46: =SUM(O46:S46) -> -0.034198394 | O46: =SUM(SAP_Speadsheet!$E$89:$P$89) -> -0.034198394 | P46: =SUM(SAP_Speadsheet!$Q$89:$AB$89) -> 0 | Q46: =SUM(SAP_Speadsheet!$AC$89:$AN$89) -> 0 | R46: =SUM(SAP_Speadsheet!$AO$89:$AZ$89) -> 0 | S46: =SUM(SAP_Speadsheet!$BA$89:$BF$89) -> 0 | T46: =N46/$E$14*12/$N$29 -> -0.0045685321 | U46: =N46/$E$10 -> -0.002376647
C47: Sharing TOI and Risk DPD90+ | F47: % per month | K47: Disbursement | N47: =SUM(O47:S47) -> -0.004 | O47: =SUM(SAP_Speadsheet!$E$90:$P$90) -> -0.004 | P47: =SUM(SAP_Speadsheet!$Q$90:$AB$90) -> 0 | Q47: =SUM(SAP_Speadsheet!$AC$90:$AN$90) -> 0 | R47: =SUM(SAP_Speadsheet!$AO$90:$AZ$90) -> 0 | S47: =SUM(SAP_Speadsheet!$BA$90:$BF$90) -> 0 | T47: =N47/$E$14*12/$N$29 -> -0.00053435633 | U47: =N47/$E$10 -> -0.00027798347
C48: Sharing TOI and Risk DPD180+ | F48: % per month | K48: Collection & after sale service | N48: =SUM(O48:S48) -> -0.095508824 | O48: =SUM(O49:O51) -> -0.0788665 | P48: =SUM(P49:P51) -> -0.016642324 | Q48: =SUM(Q49:Q51) -> 0 | R48: =SUM(R49:R51) -> 0 | S48: =SUM(S49:S51) -> 0 | T48: =N48/$E$14*12/$N$29 -> -0.012758936 | U48: =N48/$E$10 -> -0.0066374685
E49: Adjust MODE | K49: Early collections | N49: =SUM(O49:S49) -> -0.088680324 | O49: =SUM(SAP_Speadsheet!$E$96:$P$96) -> -0.072808 | P49: =SUM(SAP_Speadsheet!$Q$96:$AB$96) -> -0.015872324 | Q49: =SUM(SAP_Speadsheet!$AC$96:$AN$96) -> 0 | R49: =SUM(SAP_Speadsheet!$AO$96:$AZ$96) -> 0 | S49: =SUM(SAP_Speadsheet!$BA$96:$BF$96) -> 0 | T49: =N49/$E$14*12/$N$29 -> -0.011846723 | U49: =N49/$E$10 -> -0.006162916
C50: Sharing CII (only) | F50: % per month | K50: AMC | N50: =SUM(O50:S50) -> 0 | O50: =SUM(SAP_Speadsheet!$E$97:$P$97) -> 0 | P50: =SUM(SAP_Speadsheet!$Q$97:$AB$97) -> 0 | Q50: =SUM(SAP_Speadsheet!$AC$97:$AN$97) -> 0 | R50: =SUM(SAP_Speadsheet!$AO$97:$AZ$97) -> 0 | S50: =SUM(SAP_Speadsheet!$BA$97:$BF$97) -> 0 | T50: =N50/$E$14*12/$N$29 -> 0 | U50: =N50/$E$10 -> 0
C51: Sharing COF (only) | F51: % per month | K51: Aftersale service | N51: =SUM(O51:S51) -> -0.0068285 | O51: =SUM(SAP_Speadsheet!$E$99:$P$99) -> -0.0060585 | P51: =SUM(SAP_Speadsheet!$Q$99:$AB$99) -> -0.00077 | Q51: =SUM(SAP_Speadsheet!$AC$99:$AN$99) -> 0 | R51: =SUM(SAP_Speadsheet!$AO$99:$AZ$99) -> 0 | S51: =SUM(SAP_Speadsheet!$BA$99:$BF$99) -> 0 | T51: =N51/$E$14*12/$N$29 -> -0.00091221306 | U51: =N51/$E$10 -> -0.00047455252
C52: Sharing NFI (only) | F52: % per month | K52: Supporting Units | N52: =SUM(O52:S52) -> -0.50095247 | O52: =SUM(O53:O56) -> -0.44413072 | P52: =SUM(P53:P56) -> -0.056821746 | Q52: =SUM(Q53:Q56) -> 0 | R52: =SUM(R53:R56) -> 0 | S52: =SUM(S53:S56) -> 0 | T52: =N52/$E$14*12/$N$29 -> -0.066921781 | U52: =N52/$E$10 -> -0.034814126
C53: Sharing Risk DPD90+ (Only) | F53: % per month | K53: Direct HR | N53: =SUM(O53:S53) -> -0.096982074 | O53: =SUM(SAP_Speadsheet!$E$104:$P$104) -> -0.085981647 | P53: =SUM(SAP_Speadsheet!$Q$104:$AB$104) -> -0.011000426 | Q53: =SUM(SAP_Speadsheet!$AC$104:$AN$104) -> 0 | R53: =SUM(SAP_Speadsheet!$AO$104:$AZ$104) -> 0 | S53: =SUM(SAP_Speadsheet!$BA$104:$BF$104) -> 0 | T53: =N53/$E$14*12/$N$29 -> -0.012955746 | U53: =N53/$E$10 -> -0.0067398532
C54: Sharing Risk DPD180+ (only) | F54: % per month | K54: Indiect HR | N54: =SUM(O54:S54) -> -0.15750253 | O54: =SUM(SAP_Speadsheet!$E$105:$P$105) -> -0.13963742 | P54: =SUM(SAP_Speadsheet!$Q$105:$AB$105) -> -0.017865106 | Q54: =SUM(SAP_Speadsheet!$AC$105:$AN$105) -> 0 | R54: =SUM(SAP_Speadsheet!$AO$105:$AZ$105) -> 0 | S54: =SUM(SAP_Speadsheet!$BA$105:$BF$105) -> 0 | T54: =N54/$E$14*12/$N$29 -> -0.021040619 | U54: =N54/$E$10 -> -0.010945775
C55: Risk share from | F55: disbursement | K55: IT | N55: =SUM(O55:S55) -> -0.12209469 | O55: =SUM(SAP_Speadsheet!$E$106:$P$106) -> -0.1082458 | P55: =SUM(SAP_Speadsheet!$Q$106:$AB$106) -> -0.013848886 | Q55: =SUM(SAP_Speadsheet!$AC$106:$AN$106) -> 0 | R55: =SUM(SAP_Speadsheet!$AO$106:$AZ$106) -> 0 | S55: =SUM(SAP_Speadsheet!$BA$106:$BF$106) -> 0 | T55: =N55/$E$14*12/$N$29 -> -0.016310518 | U55: =N55/$E$10 -> -0.0084850763
C56: Partner Lead Acquistion | F56: per account | K56: Other support units | N56: =SUM(O56:S56) -> -0.12437317 | O56: =SUM(SAP_Speadsheet!$E$107:$P$107) -> -0.11026585 | P56: =SUM(SAP_Speadsheet!$Q$107:$AB$107) -> -0.014107328 | Q56: =SUM(SAP_Speadsheet!$AC$107:$AN$107) -> 0 | R56: =SUM(SAP_Speadsheet!$AO$107:$AZ$107) -> 0 | S56: =SUM(SAP_Speadsheet!$BA$107:$BF$107) -> 0 | T56: =N56/$E$14*12/$N$29 -> -0.016614898 | U56: =N56/$E$10 -> -0.0086434215
E57: 0.025 | F57: per ticketsize | K57: PBT | N57: =SUM(O57:S57) -> 0.66821686 | O57: =SUM(SAP_Speadsheet!$E$189:$P$189) -> 0.74329169 | P57: =SUM(SAP_Speadsheet!$Q$189:$AB$189) -> -0.075074836 | Q57: =SUM(SAP_Speadsheet!$AC$189:$AN$189) -> 0 | R57: =SUM(SAP_Speadsheet!$AO$189:$AZ$189) -> 0 | S57: =SUM(SAP_Speadsheet!$BA$189:$BF$189) -> 0 | T57: =N57/$E$14*12/$N$29 -> 0.089266478 | U57: =N57/$E$10 -> 0.04643831
C59: Marketing cost
C61: Marketing cost | E61: =DATA!I29 -> 0 | F61: per account
B63: UW & Disbursal | C63: Underwriting cost & Score | E63: =DATA!I30*Leadsheet!E66*Leadsheet!E67 -> 0.014844497 | F63: of application
A64: Inflation | C64: DOP cost | F64: of account
C65: Disbursement cost | E65: 0.004 | F65: of account
A66: Incentive | C66: Approval rate | E66: =DATA!E4 -> 0.455 | F66: of submitted application
A67: Sale team | C67: Disbursement rate | E67: =DATA!E5 -> 0.954 | F67: of aproved application
A68: Sale Mgt
A69: MA
B71: Collection & AMC | C71: Collections_all | E71: =DATA!I31 -> 0.008 | F71: per account/month
C72: Collections_B1+ | F72: per account/month
C73: AMC_principal collected | F73: per 1mVND collected amount
C74: AMC_interest collected | F74: per 1mVND collected amount
C75: AMC_penalty collected | F75: per 1mVND collected amount
B77: Aftersale service
C78: Email & SMS | E78: =DATA!I32 -> 0.0007 | F78: per account/month
A79: CPCUW
A80: CPCUW_SCORE
A81: CPCCA | B81: Supporting units | C81: Direct HR | E81: 0.0094474945 | F81: per account/month
A82: Approval rate | C82: Indirect HR | E82: 0.015343086 | F82: per account/month
C83: IT | E83: 0.011893836 | F83: per account/month
C84: Other supports | E84: 0.012115794 | F84: per account/month
A86: AMC_PR
B88: RISK INPUT
B90: Net flow | D90: NF | E90: PD | F90: Pro. Rate
C91: B0 - B1 | D91: =DATA!G59 -> 0.033819992 | E91: =PRODUCT(D91:$D$104) -> 0.022946314 | F91: =E91*(1-$E$110)*(1-$E$111)*(1-$E$112)*(1-$E$113) -> 0.021380918
C92: B1 - B2 | D92: =DATA!G60 -> 0.69546266 | E92: =PRODUCT(D92:$D$104) -> 0.67848372 | F92: =E92*(1-$E$110)*(1-$E$111)*(1-$E$112)*(1-$E$113) -> 0.63219761
C93: B2 - B3 | D93: =DATA!G61 -> 0.99027258 | E93: =PRODUCT(D93:$D$104) -> 0.97558612 | F93: =E93*(1-$E$110)*(1-$E$111)*(1-$E$112)*(1-$E$113) -> 0.90903171
C94: B3 - B4 | D94: =DATA!G62 -> 0.98516927 | E94: =PRODUCT(D94:$D$104) -> 0.98516927 | F94: =E94*(1-$E$110)*(1-$E$111)*(1-$E$112)*(1-$E$113) -> 0.9179611
C95: B4 - B5 | D95: =DATA!G63 -> 1 | E95: =PRODUCT(D95:$D$104) -> 1 | F95: =E95*(1-$E$110)*(1-$E$111)*(1-$E$112)*(1-$E$113) -> 0.93178008
C96: B5 - B6 | D96: =DATA!G64 -> 1 | E96: =PRODUCT(D96:$D$104) -> 1 | F96: =E96*(1-$E$110)*(1-$E$111)*(1-$E$112)*(1-$E$113) -> 0.93178008
C97: B6 - B7 | D97: =DATA!G65 -> 1 | E97: =PRODUCT(D97:$D$104) -> 1 | F97: =E97*(1-$E$110)*(1-$E$111)*(1-$E$112)*(1-$E$113) -> 0.93178008
C98: B7 - B8 | D98: =DATA!G66 -> 1 | E98: =PRODUCT(D98:$D$104) -> 1 | F98: =E98*(1-$E$110)*(1-$E$111)*(1-$E$112)*(1-$E$113) -> 0.93178008
C99: B8 - B9 | D99: =DATA!G67 -> 1 | E99: =PRODUCT(D99:$D$104) -> 1 | F99: =E99*(1-$E$111)*(1-$E$112)*(1-$E$113) -> 0.950796
C100: B9 - B10 | D100: 1 | E100: =PRODUCT(D100:$D$104) -> 1 | F100: =E100*(1-$E$111)*(1-$E$112)*(1-$E$113) -> 0.950796
C101: B10 - B11 | D101: 1 | E101: =PRODUCT(D101:$D$104) -> 1 | F101: =E101*(1-$E$111)*(1-$E$112)*(1-$E$113) -> 0.950796
C102: B11 - B12 | D102: 1 | E102: =PRODUCT(D102:$D$104) -> 1 | F102: =E102*(1-$E$111)*(1-$E$112)*(1-$E$113) -> 0.950796
C103: B12 - B13 | D103: 1 | E103: =PRODUCT(D103:$D$104) -> 1 | F103: =E103*(1-$E$111)*(1-$E$112)*(1-$E$113) -> 0.950796
C104: B13-B24 | F104: =(1-$E$111)*(1-$E$112)*(1-$E$113) -> 0.950796
C105: B25-B36 | F105: =(1-$E$112)*(1-$E$113) -> 0.9702
A106: Recovery rate B13-B24 | C106: B36+ | F106: =(1-$E$113) -> 0.99
A107: Recovery rate B24-B36 | C107: Risk cost/ Disburse | D107: =N39/E10 -> -0.12749243
A108: Recovery rate B36+ | C108: Riskcost/ANR | D108: =T39 -> -0.24507353
B110: Recovery rate | C110: B8- B12 | E110: 0.02
C111: B13-B24 | D111: Recovery rate B13-B24 | E111: 0.02
C112: B24-B36 | D112: Recovery rate B24-B36 | E112: 0.02
...

Sheet DATA
B2: 1 | C2: Aproval rate, signed rate
C4: aprroval rate | E4: 0.455
C5: Signed rate | E5: 0.954
B14: 2 | C14: Disburse, Tenor, Insurance, IR
C16: Disburse date | D16: # Disburse | E16: Disburse amount (VND) | F16: Current balance (VND) | G16: Ticket size (VND) | H16: Avg tenor (Month) | I16: Avg IR (%) | J16: Insurance fee (VND) | K16: % Insurance penetration by date
C17: 45901 | D17: 5356 | E17: 83034230000 | F17: 72384844421 | G17: 15503030 | H17: 13.371733 | I17: 0.52493465 | J17: 2862230000 | K17: 0.50130695 | L17: =E17-J17 -> 80172000000
C18: 45870 | D18: 5840 | E18: 83818310000 | F18: 66141256151 | G18: 14352450 | H18: 13.956678 | I18: 0.52588185 | J18: 2760310000 | K18: 0.48236301 | L18: =E18-J18 -> 81058000000
C19: 45839 | D19: 6515 | E19: 87997150000 | F19: 62650264764 | G19: 13506853 | H19: 13.730008 | I19: 0.52723715 | J19: 2740150000 | K19: 0.4552571 | L19: =E19-J19 -> 85257000000
C20: AVG | G20: =SUM(E17:E19)/SUM(D17:D19)/10^6 -> 14.389345 | H20: =ROUND(SUMPRODUCT(H17:H19,$E$17:$E$19)/SUM($E$17:$E$19),0) -> 14 | I20: =SUMPRODUCT(I17:I19,E17:E19)/SUM(E17:E19) -> 0.52604121 | J20: =SUM(J17:J19)/SUMPRODUCT(K17:K19,L17:L19) -> 0.070807838 | K20: =SUMPRODUCT(K17:K19,E17:E19)/SUM(E17:E19) -> 0.47917585
B24: 3 | C24: UW, collection, MKT
D25: 6 | E25: 7 | F25: 8 | G25: 9 | I25: AVG
C26: New ACC | E26: 6515 | F26: 5840 | G26: 5356
C27: Active acc | D27: 7243 | E27: 13144 | F27: 17888 | G27: 21762
C29: MKT acquisition | I29: =SUM(E29:G29)/SUM(E26:G26)/10^6 -> 0
C30: UW | E30: 1.237893e+08 | F30: 2.3264011e+08 | G30: 2.4925835e+08 | I30: =SUM(E30:G30)/SUM(E26:G26)/10^6 -> 0.034198394
C31: Collection | E31: 26828762 | F31: 46328553 | G31: 72622946 | H31: =SUM(E31:G31)/SUM(D27:F27) -> 3808.7593 | I31: =8000/10^6 -> 0.008 | J31: Sử dụng mức tương đương Q2 do quý 3 thay đổi collection, chi phí ko đầy đủ
C32: SMS | E32: 4183841.8 | F32: 5100190.9 | G32: 9493145.7 | H32: =SUM(E32:G32)/SUM(E27:G27) -> 355.6688 | I32: 0.0007
C33: Partner acquisition | I33: =SUM(E33:G33)/SUM(E17:E19) -> 0
B36: 4 | C36: RR
C38: Sum of principal_balance_at_report_month | D38: Column Labels
C39: Row Labels | D39: 202506 | E39: 202507 | F39: 202508 | G39: 202509 | H39: Grand Total
C40: 0 | D40: 69480875106 | E40: 144317132226 | F40: 203122629388 | G40: 252065074464 | H40: 668985711184
C41: 1 | D41: 1249099314 | E41: 2262297913 | F41: 4759822395 | G41: 7295815497 | H41: 15567035119
C42: 2 | E42: 753631097 | F42: 1728253388 | G42: 3422841764 | H42: 5904726249
C43: 3 | F43: 778788469 | G43: 1636938736 | H43: 2415727205
C44: 4 | G44: 767238469 | H44: 767238469
C45: Grand Total | D45: 70729974420 | E45: 147333061236 | F45: 210389493640 | G45: 265187908930 | H45: 693640438226
B58: Row Labels | C58: 7 | D58: 8 | E58: 9 | F58: AVG | G58: ADJ | H58: 202506 | I58: 202507 | J58: 202508 | K58: 202509 | N58: EOM Bucket | O58: report_month | P58: principal_balance_at_report_month
B59: 0 | C59: =I60/H59 -> 0.032560009 | D59: =J60/I59 -> 0.032981686 | E59: =K60/J59 -> 0.03591828 | F59: =AVERAGE(C59:E59) -> 0.033819992 | G59: =F59 -> 0.033819992 | H59: 69480875106 | I59: 144317132226 | J59: 203122629388 | K59: 252065074464 | N59: 0 | O59: 202510 | P59: 294414851862
B60: 1 | C60: =I61/H60 -> 0.60333961 | D60: =J61/I60 -> 0.76393714 | E60: =K61/J60 -> 0.71911124 | F60: =AVERAGE(C60:E60) -> 0.69546266 | G60: =F60 -> 0.69546266 | H60: 1249099314 | I60: 2262297913 | J60: 4759822395 | K60: 7295815497 | N60: 0 | O60: 202508 | P60: 203122629388
B61: 2 | C61: =I62/H61 -> #DIV/0! | D61: =J62/I61 -> 1.0333815 | E61: =K62/J61 -> 0.94716362 | F61: =AVERAGE(D61:E61) -> 0.99027258 | G61: =F61 -> 0.99027258 | I61: 753631097 | J61: 1728253388 | K61: 3422841764 | N61: 0 | O61: 202509 | P61: 252065074464
B62: 3 | C62: =I63/H62 -> #DIV/0! | D62: =J63/I62 -> #DIV/0! | E62: =K63/J62 -> 0.98516927 | F62: =E62 -> 0.98516927 | G62: =F62 -> 0.98516927 | J62: 778788469 | K62: 1636938736 | N62: 0 | O62: 202504 | P62: 8294394
B63: 4 | C63: =I64/H63 -> #DIV/0! | D63: =J64/I63 -> #DIV/0! | E63: =K64/J63 -> #DIV/0! | G63: 1 | K63: 767238469 | N63: 0 | O63: 202506 | P63: 69480875106
B64: 5 | C64: =I65/H64 -> #DIV/0! | D64: =J65/I64 -> #DIV/0! | E64: =K65/J64 -> #DIV/0! | G64: 1 | N64: 0 | O64: 202507 | P64: 144317132226
B65: 6 | C65: =I66/H65 -> #DIV/0! | D65: =J66/I65 -> #DIV/0! | E65: =K66/J65 -> #DIV/0! | G65: 1 | N65: 0 | O65: 202505 | P65: 28358115388
B66: 7 | C66: =I67/H66 -> #DIV/0! | D66: =J67/I66 -> #DIV/0! | E66: =K67/J66 -> #DIV/0! | G66: 1 | N66: 0 | O66: 202503 | P66: 9630000
B67: 8 | C67: =I68/H67 -> #DIV/0! | D67: =J68/I67 -> #DIV/0! | E67: =K68/J67 -> #DIV/0! | G67: 1 | N67: 1 | O67: 202506 | P67: 1249099314
B68: 9 | C68: =I69/H68 -> #DIV/0! | D68: =J69/I68 -> #DIV/0! | E68: =K69/J68 -> #DIV/0! | N68: 1 | O68: 202508 | P68: 4759822395
B69: 10 | C69: =I70/H69 -> #DIV/0! | D69: =J70/I69 -> #DIV/0! | E69: =K70/J69 -> #DIV/0! | N69: 1 | O69: 202509 | P69: 7295815497
B70: 11 | C70: =I71/H70 -> #DIV/0! | D70: =J71/I70 -> #DIV/0! | E70: =K71/J70 -> #DIV/0! | N70: 1 | O70: 202510 | P70: 9918665014
B71: 12 | C71: =I72/H71 -> #DIV/0! | D71: =J72/I71 -> #DIV/0! | E71: =K72/J71 -> #DIV/0! | N71: 1 | O71: 202507 | P71: 2262297913
B72: 13 | D72: =J73/I72 -> #DIV/0! | E72: =K73/J72 -> #DIV/0! | N72: 2 | O72: 202510 | P72: 3951677877
B73: 14 | E73: =K74/J73 -> #DIV/0! | N73: 2 | O73: 202507 | P73: 753631097
B74: 15 | N74: 2 | O74: 202508 | P74: 1728253388
N75: 2 | O75: 202509 | P75: 3422841764
N76: 3 | O76: 202510 | P76: 2850316031
N77: 3 | O77: 202509 | P77: 1636938736
N78: 3 | O78: 202508 | P78: 778788469
N79: 4 | O79: 202510 | P79: 1174750248
N80: 4 | O80: 202509 | P80: 767238469
N81: 5 | O81: 202510 | P81: 120211771

Sheet SAP_Speadsheet
B1: SAP Speadsheet
C4: Method
C5: Month on book | D5: 0 | E5: =D5+1 -> 1 | F5: =E5+1 -> 2 | G5: =F5+1 -> 3 | H5: =G5+1 -> 4 | I5: =H5+1 -> 5 | J5: =I5+1 -> 6 | K5: =J5+1 -> 7 | L5: =K5+1 -> 8 | ... BL5: =BK5+1 -> 60
C6: Oustanding tenor | D6: =IF(Leadsheet!$E$12-SAP_Speadsheet!D5<0,0,Leadsheet!$E$12-SAP_Speadsheet!D5) -> 14 | E6: =IF(Leadsheet!$E$12-SAP_Speadsheet!E5<0,0,Leadsheet!$E$12-SAP_Speadsheet!E5) -> 13 | F6: =IF(Leadsheet!$E$12-SAP_Speadsheet!F5<0,0,Leadsheet!$E$12-SAP_Speadsheet!F5) -> 12 | G6: =IF(Leadsheet!$E$12-SAP_Speadsheet!G5<0,0,Leadsheet!$E$12-SAP_Speadsheet!G5) -> 11 | H6: =IF(Leadsheet!$E$12-SAP_Speadsheet!H5<0,0,Leadsheet!$E$12-SAP_Speadsheet!H5) -> 10 | I6: =IF(Leadsheet!$E$12-SAP_Speadsheet!I5<0,0,Leadsheet!$E$12-SAP_Speadsheet!I5) -> 9 | J6: =IF(Leadsheet!$E$12-SAP_Speadsheet!J5<0,0,Leadsheet!$E$12-SAP_Speadsheet!J5) -> 8 | K6: =IF(Leadsheet!$E$12-SAP_Speadsheet!K5<0,0,Leadsheet!$E$12-SAP_Speadsheet!K5) -> 7 | ... BL6: =IF(Leadsheet!$E$12-SAP_Speadsheet!BL5<0,0,Leadsheet!$E$12-SAP_Speadsheet!BL5) -> 0
C7: Last month on book | D7: =Leadsheet!E13+Leadsheet!E12 -> 20
B9: Balance
B10: Interest rate
C11: INR rate | D11: =Leadsheet!E18 -> 0.51861256 | E11: =IF(E$5>$D$7,0,VLOOKUP(SAP_Speadsheet!E$5,Leadsheet!$C$18:$F$23,3,1)) -> 0.51861256 | F11: =IF(F$5>$D$7,0,VLOOKUP(SAP_Speadsheet!F$5,Leadsheet!$C$18:$F$23,3,1)) -> 0.51861256 | G11: =IF(G$5>$D$7,0,VLOOKUP(SAP_Speadsheet!G$5,Leadsheet!$C$18:$F$23,3,1)) -> 0.51861256 | H11: =IF(H$5>$D$7,0,VLOOKUP(SAP_Speadsheet!H$5,Leadsheet!$C$18:$F$23,3,1)) -> 0.51861256 | I11: =IF(I$5>$D$7,0,VLOOKUP(SAP_Speadsheet!I$5,Leadsheet!$C$18:$F$23,3,1)) -> 0.51861256 | J11: =IF(J$5>$D$7,0,VLOOKUP(SAP_Speadsheet!J$5,Leadsheet!$C$18:$F$23,3,1)) -> 0.51861256 | K11: =IF(K$5>$D$7,0,VLOOKUP(SAP_Speadsheet!K$5,Leadsheet!$C$18:$F$23,3,1)) -> 0.51861256 | L11: =IF(L$5>$D$7,0,VLOOKUP(SAP_Speadsheet!L$5,Leadsheet!$C$18:$F$23,3,1)) -> 0.51861256 | ... BL11: =IF(BL$5>$D$7,0,VLOOKUP(SAP_Speadsheet!BL$5,Leadsheet!$C$18:$F$23,3,1)) -> 0
C12: COF rate | D12: =Leadsheet!F18 -> 0.070378103 | E12: =IF(E$5>$D$7,0,VLOOKUP(SAP_Speadsheet!E$5,Leadsheet!$C$18:$F$23,4,1)) -> 0.070378103 | F12: =IF(F$5>$D$7,0,VLOOKUP(SAP_Speadsheet!F$5,Leadsheet!$C$18:$F$23,4,1)) -> 0.070378103 | G12: =IF(G$5>$D$7,0,VLOOKUP(SAP_Speadsheet!G$5,Leadsheet!$C$18:$F$23,4,1)) -> 0.070378103 | H12: =IF(H$5>$D$7,0,VLOOKUP(SAP_Speadsheet!H$5,Leadsheet!$C$18:$F$23,4,1)) -> 0.070378103 | I12: =IF(I$5>$D$7,0,VLOOKUP(SAP_Speadsheet!I$5,Leadsheet!$C$18:$F$23,4,1)) -> 0.070378103 | J12: =IF(J$5>$D$7,0,VLOOKUP(SAP_Speadsheet!J$5,Leadsheet!$C$18:$F$23,4,1)) -> 0.070378103 | K12: =IF(K$5>$D$7,0,VLOOKUP(SAP_Speadsheet!K$5,Leadsheet!$C$18:$F$23,4,1)) -> 0.070378103 | L12: =IF(L$5>$D$7,0,VLOOKUP(SAP_Speadsheet!L$5,Leadsheet!$C$18:$F$23,4,1)) -> 0.070378103 | ... BL12: =IF(BL$5>$D$7,0,VLOOKUP(SAP_Speadsheet!BL$5,Leadsheet!$C$18:$F$23,4,1)) -> 0
C13: Attrition rate | E13: =IF(E$5<Leadsheet!$E$12,VLOOKUP(SAP_Speadsheet!E$5,Leadsheet!$C$26:$G$30,5,1),0) -> 0.08 | F13: =IF(F$5<Leadsheet!$E$12,VLOOKUP(SAP_Speadsheet!F$5,Leadsheet!$C$26:$G$30,5,1),0) -> 0.06 | G13: =IF(G$5<Leadsheet!$E$12,VLOOKUP(SAP_Speadsheet!G$5,Leadsheet!$C$26:$G$30,5,1),0) -> 0.06 | H13: =IF(H$5<Leadsheet!$E$12,VLOOKUP(SAP_Speadsheet!H$5,Leadsheet!$C$26:$G$30,5,1),0) -> 0.025 | I13: =IF(I$5<Leadsheet!$E$12,VLOOKUP(SAP_Speadsheet!I$5,Leadsheet!$C$26:$G$30,5,1),0) -> 0.025 | J13: =IF(J$5<Leadsheet!$E$12,VLOOKUP(SAP_Speadsheet!J$5,Leadsheet!$C$26:$G$30,5,1),0) -> 0.025 | K13: =IF(K$5<Leadsheet!$E$12,VLOOKUP(SAP_Speadsheet!K$5,Leadsheet!$C$26:$G$30,5,1),0) -> 0.025 | L13: =IF(L$5<Leadsheet!$E$12,VLOOKUP(SAP_Speadsheet!L$5,Leadsheet!$C$26:$G$30,5,1),0) -> 0.025 | ... BL13: =IF(BL$5<Leadsheet!$E$12,VLOOKUP(SAP_Speadsheet!BL$5,Leadsheet!$C$26:$G$30,5,1),0) -> 0
C14: Prepayment Penalty | E14: =IF(E$5<Leadsheet!$E$12,VLOOKUP(SAP_Speadsheet!E$5,Leadsheet!$C$26:$F$30,3,1),0) -> 0.03 | F14: =IF(F$5<Leadsheet!$E$12,VLOOKUP(SAP_Speadsheet!F$5,Leadsheet!$C$26:$F$30,3,1),0) -> 0.03 | G14: =IF(G$5<Leadsheet!$E$12,VLOOKUP(SAP_Speadsheet!G$5,Leadsheet!$C$26:$F$30,3,1),0) -> 0.03 | H14: =IF(H$5<Leadsheet!$E$12,VLOOKUP(SAP_Speadsheet!H$5,Leadsheet!$C$26:$F$30,3,1),0) -> 0.03 | I14: =IF(I$5<Leadsheet!$E$12,VLOOKUP(SAP_Speadsheet!I$5,Leadsheet!$C$26:$F$30,3,1),0) -> 0.03 | J14: =IF(J$5<Leadsheet!$E$12,VLOOKUP(SAP_Speadsheet!J$5,Leadsheet!$C$26:$F$30,3,1),0) -> 0.03 | K14: =IF(K$5<Leadsheet!$E$12,VLOOKUP(SAP_Speadsheet!K$5,Leadsheet!$C$26:$F$30,3,1),0) -> 0.03 | L14: =IF(L$5<Leadsheet!$E$12,VLOOKUP(SAP_Speadsheet!L$5,Leadsheet!$C$26:$F$30,3,1),0) -> 0.03 | ... BL14: =IF(BL$5<Leadsheet!$E$12,VLOOKUP(SAP_Speadsheet!BL$5,Leadsheet!$C$26:$F$30,3,1),0) -> 0
B16: EMI | C16: Account accumulated | D16: 1 | E16: =IF(E5>$D$7,0,D16-E13) -> 0.92 | F16: =IF(F5>$D$7,0,E16-F13) -> 0.86 | G16: =IF(G5>$D$7,0,F16-G13) -> 0.8 | H16: =IF(H5>$D$7,0,G16-H13) -> 0.775 | I16: =IF(I5>$D$7,0,H16-I13) -> 0.75 | J16: =IF(J5>$D$7,0,I16-J13) -> 0.725 | K16: =IF(K5>$D$7,0,J16-K13) -> 0.7 | L16: =IF(L5>$D$7,0,K16-L13) -> 0.675 | ... BL16: =IF(BL5>$D$7,0,BK16-BL13) -> 0
C17: Nominal ENR | D17: =Leadsheet!E10 -> 14.389345 | E17: =IF(E$5>Leadsheet!$E$12,0,D17+E21+E18) -> 12.468753 | F17: =IF(F$5>Leadsheet!$E$12,0,SAP_Speadsheet!E17+SAP_Speadsheet!F21+F18) -> 10.950759 | G17: =IF(G$5>Leadsheet!$E$12,0,SAP_Speadsheet!F17+SAP_Speadsheet!G21+G18) -> 9.5178705 | H17: =IF(H$5>Leadsheet!$E$12,0,SAP_Speadsheet!G17+SAP_Speadsheet!H21+H18) -> 8.5520703 | I17: =IF(I$5>Leadsheet!$E$12,0,SAP_Speadsheet!H17+SAP_Speadsheet!I21+I18) -> 7.6041584 | J17: =IF(J$5>Leadsheet!$E$12,0,SAP_Speadsheet!I17+SAP_Speadsheet!J21+J18) -> 6.6744414 | K17: =IF(K$5>Leadsheet!$E$12,0,SAP_Speadsheet!J17+SAP_Speadsheet!K21+K18) -> 5.7631232 | L17: =IF(L$5>Leadsheet!$E$12,0,SAP_Speadsheet!K17+SAP_Speadsheet!L21+L18) -> 4.8705264 | M17: =IF(M$5>Leadsheet!$E$12,0,SAP_Speadsheet!L17+SAP_Speadsheet!M21+M18) -> 3.9971376 | ... BL17: =IF(BL$5>Leadsheet!$E$12,0,SAP_Speadsheet!BK17+SAP_Speadsheet!BL21+BL18) -> 0
C18: Fully Prepayment Amount | E18: =-IF(E6>0,IFERROR(D27*(D16-E16)/D16,0),0) -> -1.1511476 | F18: =-IF(F6>0,IFERROR(E27*(E16-F16)/E16,0),0) -> -0.78313876 | G18: =-IF(G6>0,IFERROR(F27*(F16-G16)/F16,0),0) -> -0.71743978 | H18: =-IF(H6>0,IFERROR(G27*(G16-H16)/G16,0),0) -> -0.27174787 | I18: =-IF(I6>0,IFERROR(H27*(H16-I16)/H16,0),0) -> -0.24616284 | J18: =-IF(J6>0,IFERROR(I27*(I16-J16)/I16,0),0) -> -0.2205957 | K18: =-IF(K6>0,IFERROR(J27*(J16-K16)/J16,0),0) -> -0.19521801 | L18: =-IF(L6>0,IFERROR(K27*(K16-L16)/K16,0),0) -> -0.17002458 | ... BL18: =-IF(BL6>0,IFERROR(BK27*(BK16-BL16)/BK16,0),0) -> 0
C19: EMI payment | E19: =-IFERROR(PMT(D11/12,D6,-D17),0) -> -1.3913195 | F19: =-IFERROR(PMT(E11/12,E6,-E17),0) -> -1.2737258 | G19: =-IFERROR(PMT(F11/12,F6,-F17),0) -> -1.1887154 | H19: =-IFERROR(PMT(G11/12,G6,-G17),0) -> -1.1053929 | I19: =-IFERROR(PMT(H11/12,H6,-H17),0) -> -1.07135 | J19: =-IFERROR(PMT(I11/12,I6,-I17),0) -> -1.0377556 | K19: =-IFERROR(PMT(J11/12,J6,-J17),0) -> -1.0045543 | L19: =-IFERROR(PMT(K11/12,K6,-K17),0) -> -0.97164126 | ... BL19: =-IFERROR(PMT(BK11/12,BK6,-BK17),0) -> 0
C20: Nominal Interest | E20: =-IF(E5>$D$6,0,D17*D11/12) -> -0.62187459 | F20: =-IF(F5>$D$6,0,E17*E11/12) -> -0.53887097 | G20: =-IF(G5>$D$6,0,F17*F11/12) -> -0.47326676 | H20: =-IF(H5>$D$6,0,G17*G11/12) -> -0.4113406 | I20: =-IF(I5>$D$6,0,H17*H11/12) -> -0.36960092 | J20: =-IF(J5>$D$6,0,I17*I11/12) -> -0.32863434 | K20: =-IF(K5>$D$6,0,J17*J11/12) -> -0.2884541 | L20: =-IF(L5>$D$6,0,K17*K11/12) -> -0.24906901 | ... BL20: =-IF(BL5>$D$6,0,BK17*BK11/12) -> 0
C21: Nominal Payment | E21: =E19-E20 -> -0.76944493 | F21: =F19-F20 -> -0.73485487 | G21: =G19-G20 -> -0.71544862 | H21: =H19-H20 -> -0.69405228 | I21: =I19-I20 -> -0.70174907 | J21: =J19-J20 -> -0.70912129 | K21: =K19-K20 -> -0.7161002 | L21: =L19-L20 -> -0.72257225 | ... BL21: =BL19-BL20 -> 0
C24: Schedule Payment | E24: =IF(E5>Leadsheet!$E$12,0,IFERROR(E21/D17*D27*(1-Leadsheet!$D$91)+E18,0)) -> -1.8945699 | F24: =IF(F5>Leadsheet!$E$12,0,IFERROR(F21/E17*E27*(1-Leadsheet!$D$91)+F18,0)) -> -1.4669117 | G24: =IF(G5>Leadsheet!$E$12,0,IFERROR(G21/F17*F27*(1-Leadsheet!$D$91)+G18,0)) -> -1.3665597 | H24: =IF(H5>Leadsheet!$E$12,0,IFERROR(H21/G17*G27*(1-Leadsheet!$D$91)+H18,0)) -> -0.8844178 | I24: =IF(I5>Leadsheet!$E$12,0,IFERROR(I21/H17*H27*(1-Leadsheet!$D$91)+I18,0)) -> -0.85115928 | J24: =IF(J5>Leadsheet!$E$12,0,IFERROR(J21/I17*I27*(1-Leadsheet!$D$91)+J18,0)) -> -0.81686946 | K24: =IF(K5>Leadsheet!$E$12,0,IFERROR(K21/J17*J27*(1-Leadsheet!$D$91)+K18,0)) -> -0.78207842 | L24: =IF(L5>Leadsheet!$E$12,0,IFERROR(L21/K17*K27*(1-Leadsheet!$D$91)+L18,0)) -> -0.74672621 | ... BL24: =IF(BL5>Leadsheet!$E$12,0,IFERROR(BL21/BK17*BK27*(1-Leadsheet!$D$91)+BL18,0)) -> 0
A26: SBV | B26: Overdue | C26: Balance by Bucket/Group
A27: G1 | B27: 0 | C27: B0 | D27: =Leadsheet!E10 -> 14.389345 | E27: =IF(E5>=Leadsheet!$E$12,0,D44+E24-SUM(E28:E41)) -> 12.008128 | F27: =IF(F5>=Leadsheet!$E$12,0,E44+F24-SUM(F28:F41)) -> 10.283303 | G27: =IF(G5>=Leadsheet!$E$12,0,F44+G24-SUM(G28:G41)) -> 8.6959318 | H27: =IF(H5>=Leadsheet!$E$12,0,G44+H24-SUM(H28:H41)) -> 7.631048 | I27: =IF(I5>=Leadsheet!$E$12,0,H44+I24-SUM(I28:I41)) -> 6.6178709 | J27: =IF(J5>=Leadsheet!$E$12,0,I44+J24-SUM(J28:J41)) -> 5.6613224 | K27: =IF(K5>=Leadsheet!$E$12,0,J44+K24-SUM(K28:K41)) -> 4.7606884 | L27: =IF(L5>=Leadsheet!$E$12,0,K44+L24-SUM(L28:L41)) -> 3.9154144 | ... BL27: =IF(BL5>=Leadsheet!$E$12,0,BK44+BL24-SUM(BL28:BL41)) -> 0
A28: G2 | B28: 30 | C28: B1 | E28: =IF(E$5>$D$7,0,D27*Leadsheet!$D91) -> 0.48664753 | F28: =IF(F$5>$D$7,0,E27*Leadsheet!$D91) -> 0.40611478 | G28: =IF(G$5>$D$7,0,F27*Leadsheet!$D91) -> 0.34778124 | H28: =IF(H$5>$D$7,0,G27*Leadsheet!$D91) -> 0.29409634 | I28: =IF(I$5>$D$7,0,H27*Leadsheet!$D91) -> 0.25808198 | J28: =IF(J$5>$D$7,0,I27*Leadsheet!$D91) -> 0.22381634 | K28: =IF(K$5>$D$7,0,J27*Leadsheet!$D91) -> 0.19146588 | L28: =IF(L$5>$D$7,0,K27*Leadsheet!$D91) -> 0.16100644 | ... BL28: =IF(BL$5>$D$7,0,BK27*Leadsheet!$D91) -> 0
A29: G2 | B29: 60 | C29: B2 | E29: =IF(E$5>$D$7,0,D28*Leadsheet!$D92) -> 0 | F29: =IF(F$5>$D$7,0,E28*Leadsheet!$D92) -> 0.33844519 | G29: =IF(G$5>$D$7,0,F28*Leadsheet!$D92) -> 0.28243766 | H29: =IF(H$5>$D$7,0,G28*Leadsheet!$D92) -> 0.24186887 | I29: =IF(I$5>$D$7,0,H28*Leadsheet!$D92) -> 0.20453303 | J29: =IF(J$5>$D$7,0,I28*Leadsheet!$D92) -> 0.17948638 | K29: =IF(K$5>$D$7,0,J28*Leadsheet!$D92) -> 0.15565591 | L29: =IF(L$5>$D$7,0,K28*Leadsheet!$D92) -> 0.13315737 | ... BL29: =IF(BL$5>$D$7,0,BK28*Leadsheet!$D92) -> 0
A30: G2 | B30: 90 | C30: B3 | E30: =IF(E$5>$D$7,0,D29*Leadsheet!$D93) -> 0 | F30: =IF(F$5>$D$7,0,E29*Leadsheet!$D93) -> 0 | G30: =IF(G$5>$D$7,0,F29*Leadsheet!$D93) -> 0.33515299 | H30: =IF(H$5>$D$7,0,G29*Leadsheet!$D93) -> 0.27969027 | I30: =IF(I$5>$D$7,0,H29*Leadsheet!$D93) -> 0.23951611 | J30: =IF(J$5>$D$7,0,I29*Leadsheet!$D93) -> 0.20254345 | K30: =IF(K$5>$D$7,0,J29*Leadsheet!$D93) -> 0.17774044 | L30: =IF(L$5>$D$7,0,K29*Leadsheet!$D93) -> 0.15414178 | ... AU30: =IF(AU$5>$D$7,0,AT29*Leadsheet!$D93) -> 0 | AV30: 0 | AW30: =IF(AW$5>$D$7,0,AV29*Leadsheet!$D93) -> 0 | AX30: =IF(AX$5>$D$7,0,AW29*Leadsheet!$D93) -> 0 | AY30: =IF(AY$5>$D$7,0,AX29*Leadsheet!$D93) -> 0 | AZ30: =IF(AZ$5>$D$7,0,AY29*Leadsheet!$D93) -> 0 | BA30: =IF(BA$5>$D$7,0,AZ29*Leadsheet!$D93) -> 0 | BB30: =IF(BB$5>$D$7,0,BA29*Leadsheet!$D93) -> 0 | BC30: =IF(BC$5>$D$7,0,BB29*Leadsheet!$D93) -> 0 | BD30: =IF(BD$5>$D$7,0,BC29*Leadsheet!$D93) -> 0 | ... BL30: =IF(BL$5>$D$7,0,BK29*Leadsheet!$D93) -> 0
A31: G3 | B31: 120 | C31: B4 | E31: =IF(E$5>$D$7,0,D30*Leadsheet!$D94) -> 0 | F31: =IF(F$5>$D$7,0,E30*Leadsheet!$D94) -> 0 | G31: =IF(G$5>$D$7,0,F30*Leadsheet!$D94) -> 0 | H31: =IF(H$5>$D$7,0,G30*Leadsheet!$D94) -> 0.33018243 | I31: =IF(I$5>$D$7,0,H30*Leadsheet!$D94) -> 0.27554226 | J31: =IF(J$5>$D$7,0,I30*Leadsheet!$D94) -> 0.23596391 | K31: =IF(K$5>$D$7,0,J30*Leadsheet!$D94) -> 0.19953958 | L31: =IF(L$5>$D$7,0,K30*Leadsheet!$D94) -> 0.17510442 | ... BL31: =IF(BL$5>$D$7,0,BK30*Leadsheet!$D94) -> 0
A32: G3 | B32: 150 | C32: B5 | E32: =IF(E$5>$D$7,0,D31*Leadsheet!$D95) -> 0 | F32: =IF(F$5>$D$7,0,E31*Leadsheet!$D95) -> 0 | G32: =IF(G$5>$D$7,0,F31*Leadsheet!$D95) -> 0 | H32: =IF(H$5>$D$7,0,G31*Leadsheet!$D95) -> 0 | I32: =IF(I$5>$D$7,0,H31*Leadsheet!$D95) -> 0.33018243 | J32: =IF(J$5>$D$7,0,I31*Leadsheet!$D95) -> 0.27554226 | K32: =IF(K$5>$D$7,0,J31*Leadsheet!$D95) -> 0.23596391 | L32: =IF(L$5>$D$7,0,K31*Leadsheet!$D95) -> 0.19953958 | ... BL32: =IF(BL$5>$D$7,0,BK31*Leadsheet!$D95) -> 0
A33: G3 | B33: 180 | C33: B6 | E33: =IF(E$5>$D$7,0,D32*Leadsheet!$D96) -> 0 | F33: =IF(F$5>$D$7,0,E32*Leadsheet!$D96) -> 0 | G33: =IF(G$5>$D$7,0,F32*Leadsheet!$D96) -> 0 | H33: =IF(H$5>$D$7,0,G32*Leadsheet!$D96) -> 0 | I33: =IF(I$5>$D$7,0,H32*Leadsheet!$D96) -> 0 | J33: =IF(J$5>$D$7,0,I32*Leadsheet!$D96) -> 0.33018243 | K33: =IF(K$5>$D$7,0,J32*Leadsheet!$D96) -> 0.27554226 | L33: =IF(L$5>$D$7,0,K32*Leadsheet!$D96) -> 0.23596391 | ... BL33: =IF(BL$5>$D$7,0,BK32*Leadsheet!$D96) -> 0
A34: G4 | B34: 210 | C34: B7 | E34: =IF(E$5>$D$7,0,D33*Leadsheet!$D97) -> 0 | F34: =IF(F$5>$D$7,0,E33*Leadsheet!$D97) -> 0 | G34: =IF(G$5>$D$7,0,F33*Leadsheet!$D97) -> 0 | H34: =IF(H$5>$D$7,0,G33*Leadsheet!$D97) -> 0 | I34: =IF(I$5>$D$7,0,H33*Leadsheet!$D97) -> 0 | J34: =IF(J$5>$D$7,0,I33*Leadsheet!$D97) -> 0 | K34: =IF(K$5>$D$7,0,J33*Leadsheet!$D97) -> 0.33018243 | L34: =IF(L$5>$D$7,0,K33*Leadsheet!$D97) -> 0.27554226 | ... BL34: =IF(BL$5>$D$7,0,BK33*Leadsheet!$D97) -> 0
A35: G4 | B35: 240 | C35: B8 | E35: =IF(E$5>$D$7,0,D34*Leadsheet!$D98) -> 0 | F35: =IF(F$5>$D$7,0,E34*Leadsheet!$D98) -> 0 | G35: =IF(G$5>$D$7,0,F34*Leadsheet!$D98) -> 0 | H35: =IF(H$5>$D$7,0,G34*Leadsheet!$D98) -> 0 | I35: =IF(I$5>$D$7,0,H34*Leadsheet!$D98) -> 0 | J35: =IF(J$5>$D$7,0,I34*Leadsheet!$D98) -> 0 | K35: =IF(K$5>$D$7,0,J34*Leadsheet!$D98) -> 0 | L35: =IF(L$5>$D$7,0,K34*Leadsheet!$D98) -> 0.33018243 | ... BL35: =IF(BL$5>$D$7,0,BK34*Leadsheet!$D98) -> 0
A36: G4 | B36: 270 | C36: B9 | E36: =IF(E$5>$D$7,0,D35*Leadsheet!$D99) -> 0 | F36: =IF(F$5>$D$7,0,E35*Leadsheet!$D99) -> 0 | G36: =IF(G$5>$D$7,0,F35*Leadsheet!$D99) -> 0 | H36: =IF(H$5>$D$7,0,G35*Leadsheet!$D99) -> 0 | I36: =IF(I$5>$D$7,0,H35*Leadsheet!$D99) -> 0 | J36: =IF(J$5>$D$7,0,I35*Leadsheet!$D99) -> 0 | K36: =IF(K$5>$D$7,0,J35*Leadsheet!$D99) -> 0 | L36: =IF(L$5>$D$7,0,K35*Leadsheet!$D99) -> 0 | ... BL36: =IF(BL$5>$D$7,0,BK35*Leadsheet!$D99) -> 0
A37: G4 | B37: 300 | C37: B10 | E37: =IF(E$5>$D$7,0,D36*Leadsheet!$D100) -> 0 | F37: =IF(F$5>$D$7,0,E36*Leadsheet!$D100) -> 0 | G37: =IF(G$5>$D$7,0,F36*Leadsheet!$D100) -> 0 | H37: =IF(H$5>$D$7,0,G36*Leadsheet!$D100) -> 0 | I37: =IF(I$5>$D$7,0,H36*Leadsheet!$D100) -> 0 | J37: =IF(J$5>$D$7,0,I36*Leadsheet!$D100) -> 0 | K37: =IF(K$5>$D$7,0,J36*Leadsheet!$D100) -> 0 | L37: =IF(L$5>$D$7,0,K36*Leadsheet!$D100) -> 0 | ... BL37: =IF(BL$5>$D$7,0,BK36*Leadsheet!$D100) -> 0
A38: G4 | B38: 330 | C38: B11 | E38: =IF(E$5>$D$7,0,D37*Leadsheet!$D101) -> 0 | F38: =IF(F$5>$D$7,0,E37*Leadsheet!$D101) -> 0 | G38: =IF(G$5>$D$7,0,F37*Leadsheet!$D101) -> 0 | H38: =IF(H$5>$D$7,0,G37*Leadsheet!$D101) -> 0 | I38: =IF(I$5>$D$7,0,H37*Leadsheet!$D101) -> 0 | J38: =IF(J$5>$D$7,0,I37*Leadsheet!$D101) -> 0 | K38: =IF(K$5>$D$7,0,J37*Leadsheet!$D101) -> 0 | L38: =IF(L$5>$D$7,0,K37*Leadsheet!$D101) -> 0 | ... BL38: =IF(BL$5>$D$7,0,BK37*Leadsheet!$D101) -> 0
A39: G4 | B39: 360 | C39: B12 | E39: =IF(E$5>$D$7,0,D38*Leadsheet!$D102) -> 0 | F39: =IF(F$5>$D$7,0,E38*Leadsheet!$D102) -> 0 | G39: =IF(G$5>$D$7,0,F38*Leadsheet!$D102) -> 0 | H39: =IF(H$5>$D$7,0,G38*Leadsheet!$D102) -> 0 | I39: =IF(I$5>$D$7,0,H38*Leadsheet!$D102) -> 0 | J39: =IF(J$5>$D$7,0,I38*Leadsheet!$D102) -> 0 | K39: =IF(K$5>$D$7,0,J38*Leadsheet!$D102) -> 0 | L39: =IF(L$5>$D$7,0,K38*Leadsheet!$D102) -> 0 | ... BL39: =IF(BL$5>$D$7,0,BK38*Leadsheet!$D102) -> 0
A40: G5 | B40: 390 | C40: B13 | E40: =IF(E$5>$D$7,0,D39*Leadsheet!$D103) -> 0 | F40: =IF(F$5>$D$7,0,E39*Leadsheet!$D103) -> 0 | G40: =IF(G$5>$D$7,0,F39*Leadsheet!$D103) -> 0 | H40: =IF(H$5>$D$7,0,G39*Leadsheet!$D103) -> 0 | I40: =IF(I$5>$D$7,0,H39*Leadsheet!$D103) -> 0 | J40: =IF(J$5>$D$7,0,I39*Leadsheet!$D103) -> 0 | K40: =IF(K$5>$D$7,0,J39*Leadsheet!$D103) -> 0 | L40: =IF(L$5>$D$7,0,K39*Leadsheet!$D103) -> 0 | ... BL40: =IF(BL$5>$D$7,0,BK39*Leadsheet!$D103) -> 0
A41: G5 | B41: 420+ | C41: B14+ | E41: =IF(E5>$D$7,0,D40+D41) -> 0 | F41: =IF(F5>$D$7,0,E40+E41) -> 0 | G41: =IF(G5>$D$7,0,F40+F41) -> 0 | H41: =IF(H5>$D$7,0,G40+G41) -> 0 | I41: =IF(I5>$D$7,0,H40+H41) -> 0 | J41: =IF(J5>$D$7,0,I40+I41) -> 0 | K41: =IF(K5>$D$7,0,J40+J41) -> 0 | L41: =IF(L5>$D$7,0,K40+K41) -> 0 | ... BL41: =IF(BL5>$D$7,0,BK40+BK41) -> 0
B43: ENR
C44: Total bank | D44: =SUM(D27:D41) -> 14.389345 | E44: =SUM(E27:E41) -> 12.494775 | F44: =SUM(F27:F41) -> 11.027863 | G44: =SUM(G27:G41) -> 9.6613037 | H44: =SUM(H27:H41) -> 8.7768859 | I44: =SUM(I27:I41) -> 7.9257267 | J44: =SUM(J27:J41) -> 7.1088572 | K44: =SUM(K27:K41) -> 6.3267788 | ... BL44: =SUM(BL27:BL41) -> 0
C45: Outstanding balance | D45: {=IF(D5=$D$7,0,_xlfn.IFS(Leadsheet!$G$5="DPD360+",SUM(SAP_Speadsheet!D27:D40),Leadsheet!$G$5="DPD180+",SUM(SAP_Speadsheet!D27:D34)))} -> 14.389345 | E45: {=IF(E5=$D$7,0,_xlfn.IFS(Leadsheet!$G$5="DPD360+",SUM(SAP_Speadsheet!E27:E40),Leadsheet!$G$5="DPD180+",SUM(SAP_Speadsheet!E27:E34)))} -> 12.494775 | F45: {=IF(F5=$D$7,0,_xlfn.IFS(Leadsheet!$G$5="DPD360+",SUM(SAP_Speadsheet!F27:F40),Leadsheet!$G$5="DPD180+",SUM(SAP_Speadsheet!F27:F34)))} -> 11.027863 | G45: {=IF(G5=$D$7,0,_xlfn.IFS(Leadsheet!$G$5="DPD360+",SUM(SAP_Speadsheet!G27:G40),Leadsheet!$G$5="DPD180+",SUM(SAP_Speadsheet!G27:G34)))} -> 9.6613037 | H45: {=IF(H5=$D$7,0,_xlfn.IFS(Leadsheet!$G$5="DPD360+",SUM(SAP_Speadsheet!H27:H40),Leadsheet!$G$5="DPD180+",SUM(SAP_Speadsheet!H27:H34)))} -> 8.7768859 | I45: {=IF(I5=$D$7,0,_xlfn.IFS(Leadsheet!$G$5="DPD360+",SUM(SAP_Speadsheet!I27:I40),Leadsheet!$G$5="DPD180+",SUM(SAP_Speadsheet!I27:I34)))} -> 7.9257267 | J45: {=IF(J5=$D$7,0,_xlfn.IFS(Leadsheet!$G$5="DPD360+",SUM(SAP_Speadsheet!J27:J40),Leadsheet!$G$5="DPD180+",SUM(SAP_Speadsheet!J27:J34)))} -> 7.1088572 | K45: {=IF(K5=$D$7,0,_xlfn.IFS(Leadsheet!$G$5="DPD360+",SUM(SAP_Speadsheet!K27:K40),Leadsheet!$G$5="DPD180+",SUM(SAP_Speadsheet!K27:K34)))} -> 6.3267788 | ... BL45: {=IF(BL5=$D$7,0,_xlfn.IFS(Leadsheet!$G$5="DPD360+",SUM(SAP_Speadsheet!BL27:BL40),Leadsheet!$G$5="DPD180+",SUM(SAP_Speadsheet!BL27:BL34)))} -> 0
C46: Writeoff balance | D46: =D44-D45 -> 0 | E46: =E44-E45 -> 0 | F46: =F44-F45 -> 0 | G46: =G44-G45 -> 0 | H46: =H44-H45 -> 0 | I46: =I44-I45 -> 0 | J46: =J44-J45 -> 0 | K46: =K44-K45 -> 0 | ... BL46: =BL44-BL45 -> 0
C47: Outstanding Bal/TB | D47: =IFERROR(D45/D44,"") -> 1 | E47: =IFERROR(E45/E44,"") -> 1 | F47: =IFERROR(F45/F44,"") -> 1 | G47: =IFERROR(G45/G44,"") -> 1 | H47: =IFERROR(H45/H44,"") -> 1 | I47: =IFERROR(I45/I44,"") -> 1 | J47: =IFERROR(J45/J44,"") -> 1 | K47: =IFERROR(K45/K44,"") -> 1 | ... BL47: =IFERROR(BL45/BL44,"")
B49: ANR
C50: Outstanding balance | E50: =IF(E5>$D$7,0,AVERAGE(D45:E45)) -> 13.44206 | F50: =IF(F5>$D$7,0,AVERAGE(E45:F45)) -> 11.761319 | G50: =IF(G5>$D$7,0,AVERAGE(F45:G45)) -> 10.344584 | H50: =IF(H5>$D$7,0,AVERAGE(G45:H45)) -> 9.2190948 | I50: =IF(I5>$D$7,0,AVERAGE(H45:I45)) -> 8.3513063 | J50: =IF(J5>$D$7,0,AVERAGE(I45:J45)) -> 7.5172919 | K50: =IF(K5>$D$7,0,AVERAGE(J45:K45)) -> 6.717818 | L50: =IF(L5>$D$7,0,AVERAGE(K45:L45)) -> 5.7883245 | ... BL50: =IF(BL5>$D$7,0,AVERAGE(BK45:BL45)) -> 0
C51: ANR for CII (B0+B1A) | E51: =D27*(1-Leadsheet!$D$91)+D28*Leadsheet!$E$117 -> 13.902698 | F51: =E27*(1-Leadsheet!$D$91)+E28*Leadsheet!$E$117 -> 11.750215 | G51: =F27*(1-Leadsheet!$D$91)+F28*Leadsheet!$E$117 -> 10.059199 | H51: =G27*(1-Leadsheet!$D$91)+G28*Leadsheet!$E$117 -> 8.5077479 | I51: =H27*(1-Leadsheet!$D$91)+H28*Leadsheet!$E$117 -> 7.4625294 | J51: =I27*(1-Leadsheet!$D$91)+I28*Leadsheet!$E$117 -> 6.4726501 | K51: =J27*(1-Leadsheet!$D$91)+J28*Leadsheet!$E$117 -> 5.538017 | L51: =K27*(1-Leadsheet!$D$91)+K28*Leadsheet!$E$117 -> 4.6579904 | ... BL51: =BK27*(1-Leadsheet!$D$91)+BK28*Leadsheet!$E$117 -> 0
B53: Performance
B55: TOI | E55: =E57+E61+E68 -> 0.96074524 | F55: =F57+F61+F68 -> 0.46233331 | G55: =G57+G61+G68 -> 0.39558944 | H55: =H57+H61+H68 -> 0.32176931 | I55: =I57+I61+I68 -> 0.28091925 | J55: =J57+J61+J68 -> 0.24226328 | K55: =K57+K61+K68 -> 0.20579803 | L55: =L57+L61+L68 -> 0.17246082 | ... BL55: =BL57+BL61+BL68 -> 0
C57: Net interest income | E57: =E58+E59 -> 0.52200724 | F57: =F58+F59 -> 0.43883915 | G57: =G58+G59 -> 0.37406624 | H57: =H58+H59 -> 0.31361687 | I57: =I58+I59 -> 0.27353436 | J57: =J58+J59 -> 0.23564541 | K57: =K58+K59 -> 0.19994149 | L57: =L58+L59 -> 0.16736009 | ... BL57: =BL58+BL59 -> 0
C58: Interest income | E58: =IFERROR(E$51*D$11/12,0) -> 0.60084279 | F58: =IFERROR(F$51*E$11/12,0) -> 0.50781743 | G58: =IFERROR(G$51*F$11/12,0) -> 0.43473559 | H58: =IFERROR(H$51*G$11/12,0) -> 0.36768541 | I58: =IFERROR(I$51*H$11/12,0) -> 0.32251345 | J58: =IFERROR(J$51*I$11/12,0) -> 0.27973314 | K58: =IFERROR(K$51*J$11/12,0) -> 0.23934043 | L58: =IFERROR(L$51*K$11/12,0) -> 0.20130769 | ... BL58: =IFERROR(BL$51*BK$11/12,0) -> 0
C59: Cost of fund | E59: =-IFERROR(E50*D12/12,0) -> -0.078835557 | F59: =-IFERROR(F50*E12/12,0) -> -0.068978278 | G59: =-IFERROR(G50*F12/12,0) -> -0.060669347 | H59: =-IFERROR(H50*G12/12,0) -> -0.054068534 | I59: =-IFERROR(I50*H12/12,0) -> -0.048979091 | J59: =-IFERROR(J50*I12/12,0) -> -0.044087729 | K59: =-IFERROR(K50*J12/12,0) -> -0.03939894 | L59: =-IFERROR(L50*K12/12,0) -> -0.033947608 | ... BL59: =-IFERROR(BL50*BK12/12,0) -> 0
C61: Net fee income | E61: =SUM(E62:E64) -> 0.43873801 | F61: =SUM(F62:F64) -> 0.023494163 | G61: =SUM(G62:G64) -> 0.021523193 | H61: =SUM(H62:H64) -> 0.0081524361 | I61: =SUM(I62:I64) -> 0.0073848852 | J61: =SUM(J62:J64) -> 0.0066178709 | K61: =SUM(K62:K64) -> 0.0058565404 | L61: =SUM(L62:L64) -> 0.0051007375 | ... BL61: =SUM(BL62:BL64) -> 0
C62: Early termination fee | E62: =-E18*E14 -> 0.034534428 | F62: =-F18*F14 -> 0.023494163 | G62: =-G18*G14 -> 0.021523193 | H62: =-H18*H14 -> 0.0081524361 | I62: =-I18*I14 -> 0.0073848852 | J62: =-J18*J14 -> 0.0066178709 | K62: =-K18*K14 -> 0.0058565404 | L62: =-L18*L14 -> 0.0051007375 | ... BL62: =-BL18*BL14 -> 0
C63: Insurrance fee | E63: =Leadsheet!E10*Leadsheet!E33*Leadsheet!E35*Leadsheet!E36+Leadsheet!E10/(1+Leadsheet!E34*Leadsheet!E35)*Leadsheet!E34*Leadsheet!E35*Leadsheet!E36 -> 0.40420358
C64: Support fee | E64: =SUM(E65:E66) -> 0 | F64: =SUM(F65:F66) -> 0 | G64: =SUM(G65:G66) -> 0 | H64: =SUM(H65:H66) -> 0 | I64: =SUM(I65:I66) -> 0 | J64: =SUM(J65:J66) -> 0 | K64: =SUM(K65:K66) -> 0 | L64: =SUM(L65:L66) -> 0 | ... BL64: =SUM(BL65:BL66) -> 0
C65: One-time | E65: =Leadsheet!E10*Leadsheet!E39+Leadsheet!E38 -> 0
C66: Monthly fee | E66: =IF(E5>$D$6,0,$D$17*Leadsheet!$E$40*D16*((D27*(1-Leadsheet!$D$91)+D28*Leadsheet!$E$117)/D45)) -> 0 | F66: =IF(F5>$D$6,0,$D$17*Leadsheet!$E$40*E16*((E27*(1-Leadsheet!$D$91)+E28*Leadsheet!$E$117)/E45)) -> 0 | G66: =IF(G5>$D$6,0,$D$17*Leadsheet!$E$40*F16*((F27*(1-Leadsheet!$D$91)+F28*Leadsheet!$E$117)/F45)) -> 0 | H66: =IF(H5>$D$6,0,$D$17*Leadsheet!$E$40*G16*((G27*(1-Leadsheet!$D$91)+G28*Leadsheet!$E$117)/G45)) -> 0 | I66: =IF(I5>$D$6,0,$D$17*Leadsheet!$E$40*H16*((H27*(1-Leadsheet!$D$91)+H28*Leadsheet!$E$117)/H45)) -> 0 | J66: =IF(J5>$D$6,0,$D$17*Leadsheet!$E$40*I16*((I27*(1-Leadsheet!$D$91)+I28*Leadsheet!$E$117)/I45)) -> 0 | K66: =IF(K5>$D$6,0,$D$17*Leadsheet!$E$40*J16*((J27*(1-Leadsheet!$D$91)+J28*Leadsheet!$E$117)/J45)) -> 0 | L66: =IF(L5>$D$6,0,$D$17*Leadsheet!$E$40*K16*((K27*(1-Leadsheet!$D$91)+K28*Leadsheet!$E$117)/K45)) -> 0 | ... BL66: =IF(BL5>$D$6,0,$D$17*Leadsheet!$E$40*BK16*((BK27*(1-Leadsheet!$D$91)+BK28*Leadsheet!$E$117)/BK45)) -> 0
B68: Other Income | E68: {=IF(E5=$D$7,_xlfn.IFS(Leadsheet!$G$4="IFRS",0,Leadsheet!$G$5="DPD180+",(E180-E145)*(1+Leadsheet!$E$115),Leadsheet!$G$5="DPD360+",(E165-E145)*(1+Leadsheet!$E$115)),0)} -> 0 | F68: {=IF(F5=$D$7,_xlfn.IFS(Leadsheet!$G$4="IFRS",0,Leadsheet!$G$5="DPD180+",(F180-F145)*(1+Leadsheet!$E$115),Leadsheet!$G$5="DPD360+",(F165-F145)*(1+Leadsheet!$E$115)),0)} -> 0 | G68: {=IF(G5=$D$7,_xlfn.IFS(Leadsheet!$G$4="IFRS",0,Leadsheet!$G$5="DPD180+",(G180-G145)*(1+Leadsheet!$E$115),Leadsheet!$G$5="DPD360+",(G165-G145)*(1+Leadsheet!$E$115)),0)} -> 0 | H68: {=IF(H5=$D$7,_xlfn.IFS(Leadsheet!$G$4="IFRS",0,Leadsheet!$G$5="DPD180+",(H180-H145)*(1+Leadsheet!$E$115),Leadsheet!$G$5="DPD360+",(H165-H145)*(1+Leadsheet!$E$115)),0)} -> 0 | I68: {=IF(I5=$D$7,_xlfn.IFS(Leadsheet!$G$4="IFRS",0,Leadsheet!$G$5="DPD180+",(I180-I145)*(1+Leadsheet!$E$115),Leadsheet!$G$5="DPD360+",(I165-I145)*(1+Leadsheet!$E$115)),0)} -> 0 | J68: {=IF(J5=$D$7,_xlfn.IFS(Leadsheet!$G$4="IFRS",0,Leadsheet!$G$5="DPD180+",(J180-J145)*(1+Leadsheet!$E$115),Leadsheet!$G$5="DPD360+",(J165-J145)*(1+Leadsheet!$E$115)),0)} -> 0 | K68: {=IF(K5=$D$7,_xlfn.IFS(Leadsheet!$G$4="IFRS",0,Leadsheet!$G$5="DPD180+",(K180-K145)*(1+Leadsheet!$E$115),Leadsheet!$G$5="DPD360+",(K165-K145)*(1+Leadsheet!$E$115)),0)} -> 0 | L68: {=IF(L5=$D$7,_xlfn.IFS(Leadsheet!$G$4="IFRS",0,Leadsheet!$G$5="DPD180+",(L180-L145)*(1+Leadsheet!$E$115),Leadsheet!$G$5="DPD360+",(L165-L145)*(1+Leadsheet!$E$115)),0)} -> 0 | ... BL68: {=IF(BL5=$D$7,_xlfn.IFS(Leadsheet!$G$4="IFRS",0,Leadsheet!$G$5="DPD180+",(BL180-BL145)*(1+Leadsheet!$E$115),Leadsheet!$G$5="DPD360+",(BL165-BL145)*(1+Leadsheet!$E$115)),0)} -> 0
B71: VARIABLE EXPENSES | E71: =E72+E85+E88+E95+E99 -> -0.40657602 | F71: =F72+F85+F88+F95+F99 -> -0.007962 | G71: =G72+G85+G88+G95+G99 -> -0.00744 | H71: =H72+H85+H88+H95+H99 -> -0.0069425 | I71: =I72+I85+I88+I95+I99 -> -0.006725 | J71: =J72+J85+J88+J95+J99 -> -0.0065075 | K71: =K72+K85+K88+K95+K99 -> -0.00629 | L71: =L72+L85+L88+L95+L99 -> -0.0060725 | ... BL71: =BL72+BL85+BL88+BL95+BL99 -> 0
B72: Sale incentive | E72: =E73+E74 -> -0.35973363 | F72: =F73+F74 -> 0 | G72: =G73+G74 -> 0 | H72: =H73+H74 -> 0 | I72: =I73+I74 -> 0 | J72: =J73+J74 -> 0 | K72: =K73+K74 -> 0 | L72: =L73+L74 -> 0 | ... BL72: =BL73+BL74 -> 0
C73: Lead Acquistion | E73: =-Leadsheet!E56-Leadsheet!E57*Leadsheet!E10 -> -0.35973363
C74: Sharing Performance | E74: =SUM(E75:E82) -> 0 | F74: =SUM(F75:F82) -> 0 | G74: =SUM(G75:G82) -> 0 | H74: =SUM(H75:H82) -> 0 | I74: =SUM(I75:I82) -> 0 | J74: =SUM(J75:J82) -> 0 | K74: =SUM(K75:K82) -> 0 | L74: =SUM(L75:L82) -> 0 | ... BL74: =SUM(BL75:BL82) -> 0
C75: Sharing CII (only) | E75: =-SUM(E58:E58)*Leadsheet!$E$50 -> 0 | F75: =-SUM(F58:F58)*Leadsheet!$E$50 -> 0 | G75: =-SUM(G58:G58)*Leadsheet!$E$50 -> 0 | H75: =-SUM(H58:H58)*Leadsheet!$E$50 -> 0 | I75: =-SUM(I58:I58)*Leadsheet!$E$50 -> 0 | J75: =-SUM(J58:J58)*Leadsheet!$E$50 -> 0 | K75: =-SUM(K58:K58)*Leadsheet!$E$50 -> 0 | L75: =-SUM(L58:L58)*Leadsheet!$E$50 -> 0 | ... BL75: =-SUM(BL58:BL58)*Leadsheet!$E$50 -> 0
C76: Sharing COF (only) | E76: =-E59*Leadsheet!$E$51 -> 0 | F76: =-F59*Leadsheet!$E$51 -> 0 | G76: =-G59*Leadsheet!$E$51 -> 0 | H76: =-H59*Leadsheet!$E$51 -> 0 | I76: =-I59*Leadsheet!$E$51 -> 0 | J76: =-J59*Leadsheet!$E$51 -> 0 | K76: =-K59*Leadsheet!$E$51 -> 0 | L76: =-L59*Leadsheet!$E$51 -> 0 | ... BL76: =-BL59*Leadsheet!$E$51 -> 0
C77: Sharing NFI (only) | E77: =-E61*Leadsheet!$E$52 -> 0 | F77: =-F61*Leadsheet!$E$52 -> 0 | G77: =-G61*Leadsheet!$E$52 -> 0 | H77: =-H61*Leadsheet!$E$52 -> 0 | I77: =-I61*Leadsheet!$E$52 -> 0 | J77: =-J61*Leadsheet!$E$52 -> 0 | K77: =-K61*Leadsheet!$E$52 -> 0 | L77: =-L61*Leadsheet!$E$52 -> 0 | ... BL77: =-BL61*Leadsheet!$E$52 -> 0
C78: Sharing Risk DPD90+ (Only) | E78: =IF(E5>$D$7,0,Leadsheet!$E$53*(E31-SUM(D31:D39)+SUM(E32:E40))) -> 0 | F78: =IF(F5>$D$7,0,Leadsheet!$E$53*(F31-SUM(E31:E39)+SUM(F32:F40))) -> 0 | G78: =IF(G5>$D$7,0,Leadsheet!$E$53*(G31-SUM(F31:F39)+SUM(G32:G40))) -> 0 | H78: =IF(H5>$D$7,0,Leadsheet!$E$53*(H31-SUM(G31:G39)+SUM(H32:H40))) -> 0 | I78: =IF(I5>$D$7,0,Leadsheet!$E$53*(I31-SUM(H31:H39)+SUM(I32:I40))) -> 0 | J78: =IF(J5>$D$7,0,Leadsheet!$E$53*(J31-SUM(I31:I39)+SUM(J32:J40))) -> 0 | K78: =IF(K5>$D$7,0,Leadsheet!$E$53*(K31-SUM(J31:J39)+SUM(K32:K40))) -> 0 | L78: =IF(L5>$D$7,0,Leadsheet!$E$53*(L31-SUM(K31:K39)+SUM(L32:L40))) -> 0 | ... BL78: =IF(BL5>$D$7,0,Leadsheet!$E$53*(BL31-SUM(BK31:BK39)+SUM(BL32:BL40))) -> 0
C79: Sharing Risk DPD180+ (only) | E79: =IF(E5>$D$7,0,Leadsheet!$E$54*(E34-SUM(D34:D39)+SUM(E35:E40))) -> 0 | F79: =IF(F5>$D$7,0,Leadsheet!$E$54*(F34-SUM(E34:E39)+SUM(F35:F40))) -> 0 | G79: =IF(G5>$D$7,0,Leadsheet!$E$54*(G34-SUM(F34:F39)+SUM(G35:G40))) -> 0 | H79: =IF(H5>$D$7,0,Leadsheet!$E$54*(H34-SUM(G34:G39)+SUM(H35:H40))) -> 0 | I79: =IF(I5>$D$7,0,Leadsheet!$E$54*(I34-SUM(H34:H39)+SUM(I35:I40))) -> 0 | J79: =IF(J5>$D$7,0,Leadsheet!$E$54*(J34-SUM(I34:I39)+SUM(J35:J40))) -> 0 | K79: =IF(K5>$D$7,0,Leadsheet!$E$54*(K34-SUM(J34:J39)+SUM(K35:K40))) -> 0 | L79: =IF(L5>$D$7,0,Leadsheet!$E$54*(L34-SUM(K34:K39)+SUM(L35:L40))) -> 0 | ... BL79: =IF(BL5>$D$7,0,Leadsheet!$E$54*(BL34-SUM(BK34:BK39)+SUM(BL35:BL40))) -> 0
C80: Risk cap to CAKE | G80: =IF(SUM(SAP_Speadsheet!E78:BL79)>(SAP_Speadsheet!E84*Leadsheet!E53+SAP_Speadsheet!E84*Leadsheet!E54),-Leadsheet!E10*Leadsheet!E55,-SUM(SAP_Speadsheet!E78:BL79)) -> 0
C81: Sharing TOI+ Risk DPD90+ | E81: =IF(E5>$D$7,0,Leadsheet!$E$47*(-(E57+E61)+E31-SUM(D31:D39)+SUM(E32:E40))) -> 0 | F81: =IF(F5>$D$7,0,Leadsheet!$E$47*(-(F57+F61)+F31-SUM(E31:E39)+SUM(F32:F40))) -> 0 | G81: =IF(G5>$D$7,0,Leadsheet!$E$47*(-(G57+G61)+G31-SUM(F31:F39)+SUM(G32:G40))) -> 0 | H81: =IF(H5>$D$7,0,Leadsheet!$E$47*(-(H57+H61)+H31-SUM(G31:G39)+SUM(H32:H40))) -> 0 | I81: =IF(I5>$D$7,0,Leadsheet!$E$47*(-(I57+I61)+I31-SUM(H31:H39)+SUM(I32:I40))) -> 0 | J81: =IF(J5>$D$7,0,Leadsheet!$E$47*(-(J57+J61)+J31-SUM(I31:I39)+SUM(J32:J40))) -> 0 | K81: =IF(K5>$D$7,0,Leadsheet!$E$47*(-(K57+K61)+K31-SUM(J31:J39)+SUM(K32:K40))) -> 0 | L81: =IF(L5>$D$7,0,Leadsheet!$E$47*(-(L57+L61)+L31-SUM(K31:K39)+SUM(L32:L40))) -> 0 | ... BL81: =IF(BL5>$D$7,0,Leadsheet!$E$47*(-(BL57+BL61)+BL31-SUM(BK31:BK39)+SUM(BL32:BL40))) -> 0
C82: Sharing TOI+ Risk DPD180+ | E82: =IF(E5>$D$7,0,Leadsheet!$E$48*(-(E57+E61)+E34-SUM(D34:D39)+SUM(E35:E40))) -> 0 | F82: =IF(F5>$D$7,0,Leadsheet!$E$48*(-(F57+F61)+F34-SUM(E34:E39)+SUM(F35:F40))) -> 0 | G82: =IF(G5>$D$7,0,Leadsheet!$E$48*(-(G57+G61)+G34-SUM(F34:F39)+SUM(G35:G40))) -> 0 | H82: =IF(H5>$D$7,0,Leadsheet!$E$48*(-(H57+H61)+H34-SUM(G34:G39)+SUM(H35:H40))) -> 0 | I82: =IF(I5>$D$7,0,Leadsheet!$E$48*(-(I57+I61)+I34-SUM(H34:H39)+SUM(I35:I40))) -> 0 | J82: =IF(J5>$D$7,0,Leadsheet!$E$48*(-(J57+J61)+J34-SUM(I34:I39)+SUM(J35:J40))) -> 0 | K82: =IF(K5>$D$7,0,Leadsheet!$E$48*(-(K57+K61)+K34-SUM(J34:J39)+SUM(K35:K40))) -> 0 | L82: =IF(L5>$D$7,0,Leadsheet!$E$48*(-(L57+L61)+L34-SUM(K34:K39)+SUM(L35:L40))) -> 0 | ... BL82: =IF(BL5>$D$7,0,Leadsheet!$E$48*(-(BL57+BL61)+BL34-SUM(BK34:BK39)+SUM(BL35:BL40))) -> 0
B85: Marketing | E85: =E86+E67 -> 0
C86: Marketing_acquisition | E86: =-Leadsheet!E61 -> 0
B88: UW & Disbursal | E88: =E89+E90+E91 -> -0.038198394
C89: Underwriting Cost | E89: =-Leadsheet!E63/Leadsheet!E66/Leadsheet!E67-Leadsheet!E64 -> -0.034198394
C90: Disbursement cost | E90: =-Leadsheet!E65 -> -0.004
C91: DOP cost | E91: =-Leadsheet!E64 -> 0
C93: Expense Increase | E93: 1 | F93: =IF(F$5>$D$7,0,IF(F$5<12,1,(1+Leadsheet!$E$43)^(ROUNDDOWN(F$5/12,0)))) -> 1 | G93: =IF(G$5>$D$7,0,IF(G$5<12,1,(1+Leadsheet!$E$43)^(ROUNDDOWN(G$5/12,0)))) -> 1 | H93: =IF(H$5>$D$7,0,IF(H$5<12,1,(1+Leadsheet!$E$43)^(ROUNDDOWN(H$5/12,0)))) -> 1 | I93: =IF(I$5>$D$7,0,IF(I$5<12,1,(1+Leadsheet!$E$43)^(ROUNDDOWN(I$5/12,0)))) -> 1 | J93: =IF(J$5>$D$7,0,IF(J$5<12,1,(1+Leadsheet!$E$43)^(ROUNDDOWN(J$5/12,0)))) -> 1 | K93: =IF(K$5>$D$7,0,IF(K$5<12,1,(1+Leadsheet!$E$43)^(ROUNDDOWN(K$5/12,0)))) -> 1 | L93: =IF(L$5>$D$7,0,IF(L$5<12,1,(1+Leadsheet!$E$43)^(ROUNDDOWN(L$5/12,0)))) -> 1 | M93: =IF(M$5>$D$7,0,IF(M$5<12,1,(1+Leadsheet!$E$43)^(ROUNDDOWN(M$5/12,0)))) -> 1 | ... BL93: =IF(BL$5>$D$7,0,IF(BL$5<12,1,(1+Leadsheet!$E$43)^(ROUNDDOWN(BL$5/12,0)))) -> 0
B95: Collection & AMC | E95: =SUM(E96:E97) -> -0.008 | F95: =SUM(F96:F97) -> -0.00736 | G95: =SUM(G96:G97) -> -0.00688 | H95: =SUM(H96:H97) -> -0.0064 | I95: =SUM(I96:I97) -> -0.0062 | J95: =SUM(J96:J97) -> -0.006 | K95: =SUM(K96:K97) -> -0.0058 | L95: =SUM(L96:L97) -> -0.0056 | ... BL95: =SUM(BL96:BL97) -> 0
C96: Early collections | E96: =-IF(E5>Leadsheet!$E$12,Leadsheet!$E$71*E$93*E44/$D$44,Leadsheet!$E$71*E$93*D16) -> -0.008 | F96: =-IF(F5>Leadsheet!$E$12,Leadsheet!$E$71*F$93*F44/$D$44,Leadsheet!$E$71*F$93*E16) -> -0.00736 | G96: =-IF(G5>Leadsheet!$E$12,Leadsheet!$E$71*G$93*G44/$D$44,Leadsheet!$E$71*G$93*F16) -> -0.00688 | H96: =-IF(H5>Leadsheet!$E$12,Leadsheet!$E$71*H$93*H44/$D$44,Leadsheet!$E$71*H$93*G16) -> -0.0064 | I96: =-IF(I5>Leadsheet!$E$12,Leadsheet!$E$71*I$93*I44/$D$44,Leadsheet!$E$71*I$93*H16) -> -0.0062 | J96: =-IF(J5>Leadsheet!$E$12,Leadsheet!$E$71*J$93*J44/$D$44,Leadsheet!$E$71*J$93*I16) -> -0.006 | K96: =-IF(K5>Leadsheet!$E$12,Leadsheet!$E$71*K$93*K44/$D$44,Leadsheet!$E$71*K$93*J16) -> -0.0058 | L96: =-IF(L5>Leadsheet!$E$12,Leadsheet!$E$71*L$93*L44/$D$44,Leadsheet!$E$71*L$93*K16) -> -0.0056 | ... BL96: =-IF(BL5>Leadsheet!$E$12,Leadsheet!$E$71*BL$93*BL44/$D$44,Leadsheet!$E$71*BL$93*BK16) -> 0
C97: AMC
B99: After sale service | E99: =SUM(E100:E101) -> -0.000644 | F99: =SUM(F100:F101) -> -0.000602 | G99: =SUM(G100:G101) -> -0.00056 | H99: =SUM(H100:H101) -> -0.0005425 | I99: =SUM(I100:I101) -> -0.000525 | J99: =SUM(J100:J101) -> -0.0005075 | K99: =SUM(K100:K101) -> -0.00049 | L99: =SUM(L100:L101) -> -0.0004725 | ... BL99: =SUM(BL100:BL101) -> 0
C100: SMS & Email | E100: =IF(E5>Leadsheet!$E$12,0,-E16*Leadsheet!$E$78) -> -0.000644 | F100: =IF(F5>Leadsheet!$E$12,0,-F16*Leadsheet!$E$78) -> -0.000602 | G100: =IF(G5>Leadsheet!$E$12,0,-G16*Leadsheet!$E$78) -> -0.00056 | H100: =IF(H5>Leadsheet!$E$12,0,-H16*Leadsheet!$E$78) -> -0.0005425 | I100: =IF(I5>Leadsheet!$E$12,0,-I16*Leadsheet!$E$78) -> -0.000525 | J100: =IF(J5>Leadsheet!$E$12,0,-J16*Leadsheet!$E$78) -> -0.0005075 | K100: =IF(K5>Leadsheet!$E$12,0,-K16*Leadsheet!$E$78) -> -0.00049 | L100: =IF(L5>Leadsheet!$E$12,0,-L16*Leadsheet!$E$78) -> -0.0004725 | ... BL100: =IF(BL5>Leadsheet!$E$12,0,-BL16*Leadsheet!$E$78) -> 0
B103: OVERHEAD EXPENSES | E103: =SUM(E104:E107) -> -0.048800211 | F103: =SUM(F104:F107) -> -0.044896194 | G103: =SUM(G104:G107) -> -0.041968182 | H103: =SUM(H104:H107) -> -0.039040169 | I103: =SUM(I104:I107) -> -0.037820164 | J103: =SUM(J104:J107) -> -0.036600158 | K103: =SUM(K104:K107) -> -0.035380153 | L103: =SUM(L104:L107) -> -0.034160148 | ... BL103: =SUM(BL104:BL107) -> 0
C104: Direct HR | E104: =-IF(E$5>Leadsheet!$E$12,0,Leadsheet!$E81*SAP_Speadsheet!E$93*D$16) -> -0.0094474945 | F104: =-IF(F$5>Leadsheet!$E$12,0,Leadsheet!$E81*SAP_Speadsheet!F$93*E$16) -> -0.0086916949 | G104: =-IF(G$5>Leadsheet!$E$12,0,Leadsheet!$E81*SAP_Speadsheet!G$93*F$16) -> -0.0081248453 | H104: =-IF(H$5>Leadsheet!$E$12,0,Leadsheet!$E81*SAP_Speadsheet!H$93*G$16) -> -0.0075579956 | I104: =-IF(I$5>Leadsheet!$E$12,0,Leadsheet!$E81*SAP_Speadsheet!I$93*H$16) -> -0.0073218082 | J104: =-IF(J$5>Leadsheet!$E$12,0,Leadsheet!$E81*SAP_Speadsheet!J$93*I$16) -> -0.0070856209 | K104: =-IF(K$5>Leadsheet!$E$12,0,Leadsheet!$E81*SAP_Speadsheet!K$93*J$16) -> -0.0068494335 | L104: =-IF(L$5>Leadsheet!$E$12,0,Leadsheet!$E81*SAP_Speadsheet!L$93*K$16) -> -0.0066132461 | ... BL104: =-IF(BL$5>Leadsheet!$E$12,0,Leadsheet!$E81*SAP_Speadsheet!BL$93*BK$16) -> 0
C105: Indirect HR | E105: =-IF(E$5>Leadsheet!$E$12,0,Leadsheet!$E82*SAP_Speadsheet!E$93*D$16) -> -0.015343086 | F105: =-IF(F$5>Leadsheet!$E$12,0,Leadsheet!$E82*SAP_Speadsheet!F$93*E$16) -> -0.014115639 | G105: =-IF(G$5>Leadsheet!$E$12,0,Leadsheet!$E82*SAP_Speadsheet!G$93*F$16) -> -0.013195054 | H105: =-IF(H$5>Leadsheet!$E$12,0,Leadsheet!$E82*SAP_Speadsheet!H$93*G$16) -> -0.012274469 | I105: =-IF(I$5>Leadsheet!$E$12,0,Leadsheet!$E82*SAP_Speadsheet!I$93*H$16) -> -0.011890892 | J105: =-IF(J$5>Leadsheet!$E$12,0,Leadsheet!$E82*SAP_Speadsheet!J$93*I$16) -> -0.011507314 | K105: =-IF(K$5>Leadsheet!$E$12,0,Leadsheet!$E82*SAP_Speadsheet!K$93*J$16) -> -0.011123737 | L105: =-IF(L$5>Leadsheet!$E$12,0,Leadsheet!$E82*SAP_Speadsheet!L$93*K$16) -> -0.01074016 | ... BL105: =-IF(BL$5>Leadsheet!$E$12,0,Leadsheet!$E82*SAP_Speadsheet!BL$93*BK$16) -> 0
C106: IT | E106: =-IF(E$5>Leadsheet!$E$12,0,Leadsheet!$E83*SAP_Speadsheet!E$93*D$16) -> -0.011893836 | F106: =-IF(F$5>Leadsheet!$E$12,0,Leadsheet!$E83*SAP_Speadsheet!F$93*E$16) -> -0.010942329 | G106: =-IF(G$5>Leadsheet!$E$12,0,Leadsheet!$E83*SAP_Speadsheet!G$93*F$16) -> -0.010228699 | H106: =-IF(H$5>Leadsheet!$E$12,0,Leadsheet!$E83*SAP_Speadsheet!H$93*G$16) -> -0.0095150691 | I106: =-IF(I$5>Leadsheet!$E$12,0,Leadsheet!$E83*SAP_Speadsheet!I$93*H$16) -> -0.0092177232 | J106: =-IF(J$5>Leadsheet!$E$12,0,Leadsheet!$E83*SAP_Speadsheet!J$93*I$16) -> -0.0089203773 | K106: =-IF(K$5>Leadsheet!$E$12,0,Leadsheet!$E83*SAP_Speadsheet!K$93*J$16) -> -0.0086230313 | L106: =-IF(L$5>Leadsheet!$E$12,0,Leadsheet!$E83*SAP_Speadsheet!L$93*K$16) -> -0.0083256854 | ... BL106: =-IF(BL$5>Leadsheet!$E$12,0,Leadsheet!$E83*SAP_Speadsheet!BL$93*BK$16) -> 0
C107: Other support units | E107: =-IF(E$5>Leadsheet!$E$12,0,Leadsheet!$E84*SAP_Speadsheet!E$93*D$16) -> -0.012115794 | F107: =-IF(F$5>Leadsheet!$E$12,0,Leadsheet!$E84*SAP_Speadsheet!F$93*E$16) -> -0.011146531 | G107: =-IF(G$5>Leadsheet!$E$12,0,Leadsheet!$E84*SAP_Speadsheet!G$93*F$16) -> -0.010419583 | H107: =-IF(H$5>Leadsheet!$E$12,0,Leadsheet!$E84*SAP_Speadsheet!H$93*G$16) -> -0.0096926356 | I107: =-IF(I$5>Leadsheet!$E$12,0,Leadsheet!$E84*SAP_Speadsheet!I$93*H$16) -> -0.0093897407 | J107: =-IF(J$5>Leadsheet!$E$12,0,Leadsheet!$E84*SAP_Speadsheet!J$93*I$16) -> -0.0090868459 | K107: =-IF(K$5>Leadsheet!$E$12,0,Leadsheet!$E84*SAP_Speadsheet!K$93*J$16) -> -0.008783951 | L107: =-IF(L$5>Leadsheet!$E$12,0,Leadsheet!$E84*SAP_Speadsheet!L$93*K$16) -> -0.0084810561 | ... BL107: =-IF(BL$5>Leadsheet!$E$12,0,Leadsheet!$E84*SAP_Speadsheet!BL$93*BK$16) -> 0
B110: Provision
C111: Provision Rate | E111: IFRS | F111: VAS360 | G111: VAS180
C112: B0 | E112: =Leadsheet!F91 -> 0.021380918 | F112: 0.0075 | G112: 0.0075
C113: B1 | E113: =Leadsheet!F92 -> 0.63219761 | F113: 0.0575 | G113: 0.0575
C114: B2 | E114: =Leadsheet!F93 -> 0.90903171 | F114: 0.0575 | G114: 0.0575
C115: B3 | E115: =Leadsheet!F94 -> 0.9179611 | F115: 0.0575 | G115: 0.0575
C116: B4 | E116: =Leadsheet!F95 -> 0.93178008 | F116: 0.2075 | G116: 0.2075
C117: B5 | E117: =Leadsheet!F96 -> 0.93178008 | F117: 0.2075 | G117: 0.2075
C118: B6 | E118: =Leadsheet!F97 -> 0.93178008 | F118: 0.2075 | G118: 0.2075
C119: B7 | E119: =Leadsheet!F98 -> 0.93178008 | F119: 0.5075 | G119: 0.5075
C120: B8 | E120: =Leadsheet!F99 -> 0.950796 | F120: 0.5075 | G120: 1
C121: B9 | E121: =Leadsheet!F100 -> 0.950796 | F121: 0.5075
C122: B10 | E122: =Leadsheet!F101 -> 0.950796 | F122: 0.5075
C123: B11 | E123: =Leadsheet!F102 -> 0.950796 | F123: 0.5075
C124: B12 | E124: =Leadsheet!F103 -> 0.950796 | F124: 0.5075
C125: B13 | E125: =Leadsheet!F104 -> 0.950796 | F125: 1
C126: B14+ | E126: =Leadsheet!F105 -> 0.9702 | F126: 1
...

Sheet Saleplan&PnL
C1: PROFIT & LOSS 60M
C2: I. | D2: SALES PLAN
C4: Business month | D4: 45658 | E4: =EOMONTH(D4,1) -> 45716 | F4: =EOMONTH(E4,1) -> 45747 | G4: =EOMONTH(F4,1) -> 45777 | H4: =EOMONTH(G4,1) -> 45808 | I4: =EOMONTH(H4,1) -> 45838 | J4: =EOMONTH(I4,1) -> 45869 | K4: =EOMONTH(J4,1) -> 45900 | L4: =EOMONTH(K4,1) -> 45930 | ... BL4: =EOMONTH(BK4,1) -> 47514
C5: Don't delete | D5: =YEAR(D4) -> 2025 | E5: =YEAR(E4) -> 2025 | F5: =YEAR(F4) -> 2025 | G5: =YEAR(G4) -> 2025 | H5: =YEAR(H4) -> 2025 | I5: =YEAR(I4) -> 2025 | J5: =YEAR(J4) -> 2025 | K5: =YEAR(K4) -> 2025 | ... BL5: =YEAR(BL4) -> 2030
C6: New disbursement (bVND) | J6: =DATA!E19/10^9 -> 87.99715 | K6: =DATA!E18/10^9 -> 83.81831 | L6: =DATA!E17/10^9 -> 83.03423
C8: II. | D8: PROFIT & LOSS
C10: FISCAL YEAR | E10: Total | F10: =YEAR(D4) -> 2025 | G10: =F10+1 -> 2026 | H10: =G10+1 -> 2027 | I10: =H10+1 -> 2028 | J10: =I10+1 -> 2029 | K10: =J10+1 -> 2030
E11: bVND | F11: bVND | G11: bVND | H11: bVND | I11: bVND | J11: bVND | K11: bVND
C13: NEW DISBURSAL | E13: =SUM(F13:O13) -> 254.84969 | F13: =SUMIF($D$5:$BL$5,F$10,$D$6:$BL$6) -> 254.84969 | G13: =SUMIF($D$5:$BL$5,G$10,$D$6:$BL$6) -> 0 | H13: =SUMIF($D$5:$BL$5,H$10,$D$6:$BL$6) -> 0 | I13: =SUMIF($D$5:$BL$5,I$10,$D$6:$BL$6) -> 0 | J13: =SUMIF($D$5:$BL$5,J$10,$D$6:$BL$6) -> 0 | K13: =SUMIF($D$5:$BL$5,K$10,$D$6:$BL$6) -> 0
C14: Monthly disbursement | E14: =AVERAGE(D6:AM6) -> 84.949897 | F14: =IFERROR(F13/COUNTIFS($D$5:$BL$5,F10,$D$6:$BL$6,"<>"&""),0) -> 84.949897 | G14: =IFERROR(G13/COUNTIFS($D$5:$BL$5,G10,$D$6:$BL$6,"<>"&""),0) -> 0 | H14: =IFERROR(H13/COUNTIFS($D$5:$BL$5,H10,$D$6:$BL$6,"<>"&""),0) -> 0 | I14: =IFERROR(I13/COUNTIFS($D$5:$BL$5,I10,$D$6:$BL$6,"<>"&""),0) -> 0 | J14: =IFERROR(J13/COUNTIFS($D$5:$BL$5,J10,$D$6:$BL$6,"<>"&""),0) -> 0 | K14: =IFERROR(K13/COUNTIFS($D$5:$BL$5,K10,$D$6:$BL$6,"<>"&""),0) -> 0
C16: EOP | F16: =OFFSET(PnL_Speadsheet!$A$7,0,MATCH(DATE('Saleplan&PnL'!F$10,12,31),PnL_Speadsheet!$B$4:$BI$4,0))/1000 -> 140.28943 | G16: =OFFSET(PnL_Speadsheet!$A$7,0,MATCH(DATE('Saleplan&PnL'!G$10,12,31),PnL_Speadsheet!$B$4:$BI$4,0))/1000 -> 33.636463 | H16: =OFFSET(PnL_Speadsheet!$A$7,0,MATCH(DATE('Saleplan&PnL'!H$10,12,31),PnL_Speadsheet!$B$4:$BI$4,0))/1000 -> 0 | I16: =OFFSET(PnL_Speadsheet!$A$7,0,MATCH(DATE('Saleplan&PnL'!I$10,12,31),PnL_Speadsheet!$B$4:$BI$4,0))/1000 -> 0 | J16: =OFFSET(PnL_Speadsheet!$A$7,0,MATCH(DATE('Saleplan&PnL'!J$10,12,31),PnL_Speadsheet!$B$4:$BI$4,0))/1000 -> 0 | K16: =IFERROR(OFFSET(PnL_Speadsheet!$A$7,0,MATCH(DATE('Saleplan&PnL'!K$10,12,31),PnL_Speadsheet!$B$4:$BI$4,0))/1000,0) -> 0
C17: ADB | E17: =IFERROR(SUM(PnL_Speadsheet!B8:AK8)/1000/COUNTIF(PnL_Speadsheet!B8:BI8,"<>0"),0) -> 72.315381 | F17: =IFERROR(SUMIF(PnL_Speadsheet!$B$3:$BI$3,F$10,PnL_Speadsheet!$B8:$BI8)/1000/COUNTIFS(PnL_Speadsheet!$B$3:$BI$3,'Saleplan&PnL'!F$10,PnL_Speadsheet!$B$8:$BI$8,"<>0"),0) -> 156.42537 | G17: =IFERROR(SUMIF(PnL_Speadsheet!$B$3:$BI$3,G$10,PnL_Speadsheet!$B8:$BI8)/1000/COUNTIFS(PnL_Speadsheet!$B$3:$BI$3,'Saleplan&PnL'!G$10,PnL_Speadsheet!$B$8:$BI$8,"<>0"),0) -> 54.076986 | H17: =IFERROR(SUMIF(PnL_Speadsheet!$B$3:$BI$3,H$10,PnL_Speadsheet!$B8:$BI8)/1000/COUNTIFS(PnL_Speadsheet!$B$3:$BI$3,'Saleplan&PnL'!H$10,PnL_Speadsheet!$B$8:$BI$8,"<>0"),0) -> 0.86558657 | I17: =IFERROR(SUMIF(PnL_Speadsheet!$B$3:$BI$3,I$10,PnL_Speadsheet!$B8:$BI8)/1000/COUNTIFS(PnL_Speadsheet!$B$3:$BI$3,'Saleplan&PnL'!I$10,PnL_Speadsheet!$B$8:$BI$8,"<>0"),0) -> 0 | J17: =IFERROR(SUMIF(PnL_Speadsheet!$B$3:$BI$3,J$10,PnL_Speadsheet!$B8:$BI8)/1000/COUNTIFS(PnL_Speadsheet!$B$3:$BI$3,'Saleplan&PnL'!J$10,PnL_Speadsheet!$B$8:$BI$8,"<>0"),0) -> 0 | K17: =IFERROR(SUMIF(PnL_Speadsheet!$B$3:$BI$3,K$10,PnL_Speadsheet!$B8:$BI8)/1000/COUNTIFS(PnL_Speadsheet!$B$3:$BI$3,'Saleplan&PnL'!K$10,PnL_Speadsheet!$B$8:$BI$8,"<>0"),0) -> 0
C19: TOI | E19: =SUM(F19:O19) -> 61.937895 | F19: =SUMIF(PnL_Speadsheet!$B$3:$BI$3,F$10,PnL_Speadsheet!$B9:$BI9)/1000 -> 42.744901 | G19: =SUMIF(PnL_Speadsheet!$B$3:$BI$3,G$10,PnL_Speadsheet!$B9:$BI9)/1000 -> 19.2133 | H19: =SUMIF(PnL_Speadsheet!$B$3:$BI$3,H$10,PnL_Speadsheet!$B9:$BI9)/1000 -> -0.020306113 | I19: =SUMIF(PnL_Speadsheet!$B$3:$BI$3,I$10,PnL_Speadsheet!$B9:$BI9)/1000 -> 0 | J19: =SUMIF(PnL_Speadsheet!$B$3:$BI$3,J$10,PnL_Speadsheet!$B9:$BI9)/1000 -> 0 | K19: =SUMIF(PnL_Speadsheet!$B$3:$BI$3,K$10,PnL_Speadsheet!$B9:$BI9)/1000 -> 0
C20: NII | E20: =SUM(F20:O20) -> 52.529312 | F20: =SUMIF(PnL_Speadsheet!$B$3:$BI$3,F$10,PnL_Speadsheet!$B11:$BI11)/1000 -> 33.904078 | G20: =SUMIF(PnL_Speadsheet!$B$3:$BI$3,G$10,PnL_Speadsheet!$B11:$BI11)/1000 -> 18.64554 | H20: =SUMIF(PnL_Speadsheet!$B$3:$BI$3,H$10,PnL_Speadsheet!$B11:$BI11)/1000 -> -0.020306113 | I20: =SUMIF(PnL_Speadsheet!$B$3:$BI$3,I$10,PnL_Speadsheet!$B11:$BI11)/1000 -> 0 | J20: =SUMIF(PnL_Speadsheet!$B$3:$BI$3,J$10,PnL_Speadsheet!$B11:$BI11)/1000 -> 0 | K20: =SUMIF(PnL_Speadsheet!$B$3:$BI$3,K$10,PnL_Speadsheet!$B11:$BI11)/1000 -> 0
C21: NFI | E21: =SUM(F21:O21) -> 9.408583 | F21: =SUMIF(PnL_Speadsheet!$B$3:$BI$3,F$10,PnL_Speadsheet!$B14:$BI14)/1000 -> 8.8408229 | G21: =SUMIF(PnL_Speadsheet!$B$3:$BI$3,G$10,PnL_Speadsheet!$B14:$BI14)/1000 -> 0.56776011 | H21: =SUMIF(PnL_Speadsheet!$B$3:$BI$3,H$10,PnL_Speadsheet!$B14:$BI14)/1000 -> 0 | I21: =SUMIF(PnL_Speadsheet!$B$3:$BI$3,I$10,PnL_Speadsheet!$B14:$BI14)/1000 -> 0 | J21: =SUMIF(PnL_Speadsheet!$B$3:$BI$3,J$10,PnL_Speadsheet!$B14:$BI14)/1000 -> 0 | K21: =SUMIF(PnL_Speadsheet!$B$3:$BI$3,K$10,PnL_Speadsheet!$B14:$BI14)/1000 -> 0
C22: Other TOI | E22: =SUM(F22:O22) -> 0 | F22: =SUMIF(PnL_Speadsheet!$B$3:$BI$3,F$10,PnL_Speadsheet!$B18:$BI18)/1000 -> 0 | G22: =SUMIF(PnL_Speadsheet!$B$3:$BI$3,G$10,PnL_Speadsheet!$B18:$BI18)/1000 -> 0 | H22: =SUMIF(PnL_Speadsheet!$B$3:$BI$3,H$10,PnL_Speadsheet!$B18:$BI18)/1000 -> 0 | I22: =SUMIF(PnL_Speadsheet!$B$3:$BI$3,I$10,PnL_Speadsheet!$B18:$BI18)/1000 -> 0 | J22: =SUMIF(PnL_Speadsheet!$B$3:$BI$3,J$10,PnL_Speadsheet!$B18:$BI18)/1000 -> 0 | K22: =SUMIF(PnL_Speadsheet!$B$3:$BI$3,K$10,PnL_Speadsheet!$B18:$BI18)/1000 -> 0
C23: PROVISION | E23: =SUM(F23:O23) -> -32.491406 | F23: =SUMIF(PnL_Speadsheet!$B$3:$BI$3,F$10,PnL_Speadsheet!$B31:$BI31)/1000 -> -22.502491 | G23: =SUMIF(PnL_Speadsheet!$B$3:$BI$3,G$10,PnL_Speadsheet!$B31:$BI31)/1000 -> -9.7888724 | H23: =SUMIF(PnL_Speadsheet!$B$3:$BI$3,H$10,PnL_Speadsheet!$B31:$BI31)/1000 -> -0.20004279 | I23: =SUMIF(PnL_Speadsheet!$B$3:$BI$3,I$10,PnL_Speadsheet!$B31:$BI31)/1000 -> 0 | J23: =SUMIF(PnL_Speadsheet!$B$3:$BI$3,J$10,PnL_Speadsheet!$B31:$BI31)/1000 -> 0 | K23: =SUMIF(PnL_Speadsheet!$B$3:$BI$3,K$10,PnL_Speadsheet!$B31:$BI31)/1000 -> 0
C24: OPEX | E24: =SUM(F24:O24) -> -17.6117 | F24: =SUMIF(PnL_Speadsheet!$B$3:$BI$3,F$10,PnL_Speadsheet!$B19:$BI19)/1000 -> -11.48628 | G24: =SUMIF(PnL_Speadsheet!$B$3:$BI$3,G$10,PnL_Speadsheet!$B19:$BI19)/1000 -> -6.0677319 | H24: =SUMIF(PnL_Speadsheet!$B$3:$BI$3,H$10,PnL_Speadsheet!$B19:$BI19)/1000 -> -0.057688203 | I24: =SUMIF(PnL_Speadsheet!$B$3:$BI$3,I$10,PnL_Speadsheet!$B19:$BI19)/1000 -> 0 | J24: =SUMIF(PnL_Speadsheet!$B$3:$BI$3,J$10,PnL_Speadsheet!$B19:$BI19)/1000 -> 0 | K24: =SUMIF(PnL_Speadsheet!$B$3:$BI$3,K$10,PnL_Speadsheet!$B19:$BI19)/1000 -> 0
C25: Sales incentives | E25: =SUM(F25:O25) -> -6.3712422 | F25: =(SUMIF(PnL_Speadsheet!$B$3:$BI$3,F$10,PnL_Speadsheet!$B21:$BI22)/1000+SUMIF(PnL_Speadsheet!$B$3:$BI$3,F$10,PnL_Speadsheet!$B22:$BI22)/1000) -> -6.3712422 | G25: =(SUMIF(PnL_Speadsheet!$B$3:$BI$3,G$10,PnL_Speadsheet!$B21:$BI22)/1000+SUMIF(PnL_Speadsheet!$B$3:$BI$3,G$10,PnL_Speadsheet!$B22:$BI22)/1000) -> 0 | H25: =(SUMIF(PnL_Speadsheet!$B$3:$BI$3,H$10,PnL_Speadsheet!$B21:$BI22)/1000+SUMIF(PnL_Speadsheet!$B$3:$BI$3,H$10,PnL_Speadsheet!$B22:$BI22)/1000) -> 0 | I25: =(SUMIF(PnL_Speadsheet!$B$3:$BI$3,I$10,PnL_Speadsheet!$B21:$BI22)/1000+SUMIF(PnL_Speadsheet!$B$3:$BI$3,I$10,PnL_Speadsheet!$B22:$BI22)/1000) -> 0 | J25: =(SUMIF(PnL_Speadsheet!$B$3:$BI$3,J$10,PnL_Speadsheet!$B21:$BI22)/1000+SUMIF(PnL_Speadsheet!$B$3:$BI$3,J$10,PnL_Speadsheet!$B22:$BI22)/1000) -> 0 | K25: =(SUMIF(PnL_Speadsheet!$B$3:$BI$3,K$10,PnL_Speadsheet!$B21:$BI22)/1000+SUMIF(PnL_Speadsheet!$B$3:$BI$3,K$10,PnL_Speadsheet!$B22:$BI22)/1000) -> 0
C26: Marketing | E26: =SUM(F26:O26) -> 0 | F26: =SUMIF(PnL_Speadsheet!$B$3:$BI$3,F$10,PnL_Speadsheet!$B23:$BI23)/1000 -> 0 | G26: =SUMIF(PnL_Speadsheet!$B$3:$BI$3,G$10,PnL_Speadsheet!$B23:$BI23)/1000 -> 0 | H26: =SUMIF(PnL_Speadsheet!$B$3:$BI$3,H$10,PnL_Speadsheet!$B23:$BI23)/1000 -> 0 | I26: =SUMIF(PnL_Speadsheet!$B$3:$BI$3,I$10,PnL_Speadsheet!$B23:$BI23)/1000 -> 0 | J26: =SUMIF(PnL_Speadsheet!$B$3:$BI$3,J$10,PnL_Speadsheet!$B23:$BI23)/1000 -> 0 | K26: =SUMIF(PnL_Speadsheet!$B$3:$BI$3,K$10,PnL_Speadsheet!$B23:$BI23)/1000 -> 0
C27: UW & Disbursal | E27: =SUM(F27:O27) -> -0.67653176 | F27: =SUMIF(PnL_Speadsheet!$B$3:$BI$3,F$10,PnL_Speadsheet!$B24:$BI24)/1000 -> -0.67653176 | G27: =SUMIF(PnL_Speadsheet!$B$3:$BI$3,G$10,PnL_Speadsheet!$B24:$BI24)/1000 -> 0 | H27: =SUMIF(PnL_Speadsheet!$B$3:$BI$3,H$10,PnL_Speadsheet!$B24:$BI24)/1000 -> 0 | I27: =SUMIF(PnL_Speadsheet!$B$3:$BI$3,I$10,PnL_Speadsheet!$B24:$BI24)/1000 -> 0 | J27: =SUMIF(PnL_Speadsheet!$B$3:$BI$3,J$10,PnL_Speadsheet!$B24:$BI24)/1000 -> 0 | K27: =SUMIF(PnL_Speadsheet!$B$3:$BI$3,K$10,PnL_Speadsheet!$B24:$BI24)/1000 -> 0
C28: Collection & AMC | E28: =SUM(F28:O28) -> -1.5706172 | F28: =SUMIF(PnL_Speadsheet!$B$3:$BI$3,F$10,PnL_Speadsheet!$B28:$BI28)/1000 -> -0.61796104 | G28: =SUMIF(PnL_Speadsheet!$B$3:$BI$3,G$10,PnL_Speadsheet!$B28:$BI28)/1000 -> -0.89496798 | H28: =SUMIF(PnL_Speadsheet!$B$3:$BI$3,H$10,PnL_Speadsheet!$B28:$BI28)/1000 -> -0.057688203 | I28: =SUMIF(PnL_Speadsheet!$B$3:$BI$3,I$10,PnL_Speadsheet!$B28:$BI28)/1000 -> 0 | J28: =SUMIF(PnL_Speadsheet!$B$3:$BI$3,J$10,PnL_Speadsheet!$B28:$BI28)/1000 -> 0 | K28: =SUMIF(PnL_Speadsheet!$B$3:$BI$3,K$10,PnL_Speadsheet!$B28:$BI28)/1000 -> 0
C29: After-sales services | E29: =SUM(F29:O29) -> -0.12093956 | F29: =SUMIF(PnL_Speadsheet!$B$3:$BI$3,F$10,PnL_Speadsheet!$B29:$BI29)/1000 -> -0.050966146 | G29: =SUMIF(PnL_Speadsheet!$B$3:$BI$3,G$10,PnL_Speadsheet!$B29:$BI29)/1000 -> -0.069973417 | H29: =SUMIF(PnL_Speadsheet!$B$3:$BI$3,H$10,PnL_Speadsheet!$B29:$BI29)/1000 -> 0 | I29: =SUMIF(PnL_Speadsheet!$B$3:$BI$3,I$10,PnL_Speadsheet!$B29:$BI29)/1000 -> 0 | J29: =SUMIF(PnL_Speadsheet!$B$3:$BI$3,J$10,PnL_Speadsheet!$B29:$BI29)/1000 -> 0 | K29: =SUMIF(PnL_Speadsheet!$B$3:$BI$3,K$10,PnL_Speadsheet!$B29:$BI29)/1000 -> 0
C30: Other support units | E30: =SUM(F30:O30) -> -8.8723692 | F30: =SUMIF(PnL_Speadsheet!$B$3:$BI$3,F$10,PnL_Speadsheet!$B30:$BI30)/1000 -> -3.7695787 | G30: =SUMIF(PnL_Speadsheet!$B$3:$BI$3,G$10,PnL_Speadsheet!$B30:$BI30)/1000 -> -5.1027905 | H30: =SUMIF(PnL_Speadsheet!$B$3:$BI$3,H$10,PnL_Speadsheet!$B30:$BI30)/1000 -> 0 | I30: =SUMIF(PnL_Speadsheet!$B$3:$BI$3,I$10,PnL_Speadsheet!$B30:$BI30)/1000 -> 0 | J30: =SUMIF(PnL_Speadsheet!$B$3:$BI$3,J$10,PnL_Speadsheet!$B30:$BI30)/1000 -> 0 | K30: =SUMIF(PnL_Speadsheet!$B$3:$BI$3,K$10,PnL_Speadsheet!$B30:$BI30)/1000 -> 0
C31: PBT | E31: =SUM(F31:O31) -> 11.834789 | F31: =SUMIF(PnL_Speadsheet!$B$3:$BI$3,F$10,PnL_Speadsheet!$B32:$BI32)/1000 -> 8.7561298 | G31: =SUMIF(PnL_Speadsheet!$B$3:$BI$3,G$10,PnL_Speadsheet!$B32:$BI32)/1000 -> 3.3566961 | H31: =SUMIF(PnL_Speadsheet!$B$3:$BI$3,H$10,PnL_Speadsheet!$B32:$BI32)/1000 -> -0.27803711 | I31: =SUMIF(PnL_Speadsheet!$B$3:$BI$3,I$10,PnL_Speadsheet!$B32:$BI32)/1000 -> 0 | J31: =SUMIF(PnL_Speadsheet!$B$3:$BI$3,J$10,PnL_Speadsheet!$B32:$BI32)/1000 -> 0 | K31: =SUMIF(PnL_Speadsheet!$B$3:$BI$3,K$10,PnL_Speadsheet!$B32:$BI32)/1000 -> 0
C32: In which: PROFIT BEFORE SU | E32: =E19+E23+SUM(E25:E29) -> 20.707158 | F32: =F19+F23+SUM(F25:F29) -> 12.525708 | G32: =G19+G23+SUM(G25:G29) -> 8.4594866 | H32: =H19+H23+SUM(H25:H29) -> -0.27803711 | I32: =I19+I23+SUM(I25:I29) -> 0 | J32: =J19+J23+SUM(J25:J29) -> 0 | K32: =K19+K23+SUM(K25:K29) -> 0

Sheet PnL_Speadsheet
A1: PL PROJECTION
A2: 60 months
B3: =YEAR(B4) -> 2025 | C3: =YEAR(C4) -> 2025 | D3: =YEAR(D4) -> 2025 | E3: =YEAR(E4) -> 2025 | F3: =YEAR(F4) -> 2025 | G3: =YEAR(G4) -> 2025 | H3: =YEAR(H4) -> 2025 | I3: =YEAR(I4) -> 2025 | ... BI3: =YEAR(BI4) -> 2029
A4: Business month | B4: ='Saleplan&PnL'!D4 -> 45658 | C4: ='Saleplan&PnL'!E4 -> 45716 | D4: ='Saleplan&PnL'!F4 -> 45747 | E4: ='Saleplan&PnL'!G4 -> 45777 | F4: ='Saleplan&PnL'!H4 -> 45808 | G4: ='Saleplan&PnL'!I4 -> 45838 | H4: ='Saleplan&PnL'!J4 -> 45869 | I4: ='Saleplan&PnL'!K4 -> 45900 | ... BI4: ='Saleplan&PnL'!BK4 -> 47483
A5: Month on board | B5: 1 | C5: 2 | D5: 3 | E5: 4 | F5: 5 | G5: 6 | H5: 7 | I5: 8 | J5: 9 | K5: 10 | L5: 11 | M5: 12 | N5: 13 | O5: 14 | P5: 15 | Q5: 16 | R5: 17 | S5: 18 | T5: 19 | U5: 20 | V5: 21 | W5: 22 | X5: 23 | Y5: 24 | Z5: 25 | AA5: 26 | AB5: 27 | AC5: 28 | AD5: 29 | AE5: 30 | AF5: 31 | AG5: 32 | AH5: 33 | AI5: 34 | AJ5: 35 | AK5: 36 | AL5: =AK5+1 -> 37 | AM5: =AL5+1 -> 38 | AN5: =AM5+1 -> 39 | AO5: =AN5+1 -> 40 | AP5: =AO5+1 -> 41 | AQ5: =AP5+1 -> 42 | AR5: =AQ5+1 -> 43 | AS5: =AR5+1 -> 44 | ... BI5: =BH5+1 -> 60
A6: Unit: mVND
A7: ENR | B7: {=SUMPRODUCT(B$55:B$114,TRANSPOSE(SAP_Speadsheet!$E$44:$BL$44))} -> 0 | C7: {=SUMPRODUCT(C$55:C$114,TRANSPOSE(SAP_Speadsheet!$E$44:$BL$44))} -> 0 | D7: {=SUMPRODUCT(D$55:D$114,TRANSPOSE(SAP_Speadsheet!$E$44:$BL$44))} -> 0 | E7: {=SUMPRODUCT(E$55:E$114,TRANSPOSE(SAP_Speadsheet!$E$44:$BL$44))} -> 0 | F7: {=SUMPRODUCT(F$55:F$114,TRANSPOSE(SAP_Speadsheet!$E$44:$BL$44))} -> 0 | G7: {=SUMPRODUCT(G$55:G$114,TRANSPOSE(SAP_Speadsheet!$E$44:$BL$44))} -> 0 | H7: {=SUMPRODUCT(H$55:H$114,TRANSPOSE(SAP_Speadsheet!$E$44:$BL$44))} -> 76405.55 | I7: {=SUMPRODUCT(I$55:I$114,TRANSPOSE(SAP_Speadsheet!$E$44:$BL$44))} -> 140217.45 | ... BI7: {=SUMPRODUCT(BI$55:BI$114,TRANSPOSE(SAP_Speadsheet!$E$44:$BL$44))} -> 0
A8: ANR | B8: {=SUMPRODUCT(B$55:B$114,TRANSPOSE(SAP_Speadsheet!$E$50:$BL$50))} -> 0 | C8: {=SUMPRODUCT(C$55:C$114,TRANSPOSE(SAP_Speadsheet!$E$50:$BL$50))} -> 0 | D8: {=SUMPRODUCT(D$55:D$114,TRANSPOSE(SAP_Speadsheet!$E$50:$BL$50))} -> 0 | E8: {=SUMPRODUCT(E$55:E$114,TRANSPOSE(SAP_Speadsheet!$E$50:$BL$50))} -> 0 | F8: {=SUMPRODUCT(F$55:F$114,TRANSPOSE(SAP_Speadsheet!$E$50:$BL$50))} -> 0 | G8: {=SUMPRODUCT(G$55:G$114,TRANSPOSE(SAP_Speadsheet!$E$50:$BL$50))} -> 0 | H8: {=SUMPRODUCT(H$55:H$114,TRANSPOSE(SAP_Speadsheet!$E$50:$BL$50))} -> 82198.197 | I8: {=SUMPRODUCT(I$55:I$114,TRANSPOSE(SAP_Speadsheet!$E$50:$BL$50))} -> 150220.47 | ... BI8: {=SUMPRODUCT(BI$55:BI$114,TRANSPOSE(SAP_Speadsheet!$E$50:$BL$50))} -> 0
A9: TOI | B9: {=SUMPRODUCT(B$55:B$114,TRANSPOSE(SAP_Speadsheet!$E$55:$BL$55))} -> 0 | C9: {=SUMPRODUCT(C$55:C$114,TRANSPOSE(SAP_Speadsheet!$E$55:$BL$55))} -> 0 | D9: {=SUMPRODUCT(D$55:D$114,TRANSPOSE(SAP_Speadsheet!$E$55:$BL$55))} -> 0 | E9: {=SUMPRODUCT(E$55:E$114,TRANSPOSE(SAP_Speadsheet!$E$55:$BL$55))} -> 0 | F9: {=SUMPRODUCT(F$55:F$114,TRANSPOSE(SAP_Speadsheet!$E$55:$BL$55))} -> 0 | G9: {=SUMPRODUCT(G$55:G$114,TRANSPOSE(SAP_Speadsheet!$E$55:$BL$55))} -> 0 | H9: {=SUMPRODUCT(H$55:H$114,TRANSPOSE(SAP_Speadsheet!$E$55:$BL$55))} -> 5874.9572 | I9: {=SUMPRODUCT(I$55:I$114,TRANSPOSE(SAP_Speadsheet!$E$55:$BL$55))} -> 8423.5092 | ... BI9: {=SUMPRODUCT(BI$55:BI$114,TRANSPOSE(SAP_Speadsheet!$E$55:$BL$55))} -> 0
A10: Checking | B10: =B9-B11-B14 -> 0 | C10: =C9-C11-C14 -> 0 | D10: =D9-D11-D14 -> 0 | E10: =E9-E11-E14 -> 0 | F10: =F9-F11-F14 -> 0 | G10: =G9-G11-G14 -> 0 | H10: =H9-H11-H14 -> 0 | I10: =I9-I11-I14 -> 0 | ... BI10: =BI9-BI11-BI14 -> 0
A11: Net interest income | B11: {=SUMPRODUCT(B$55:B$114,TRANSPOSE(SAP_Speadsheet!$E$57:$BL$57))} -> 0 | C11: {=SUMPRODUCT(C$55:C$114,TRANSPOSE(SAP_Speadsheet!$E$57:$BL$57))} -> 0 | D11: {=SUMPRODUCT(D$55:D$114,TRANSPOSE(SAP_Speadsheet!$E$57:$BL$57))} -> 0 | E11: {=SUMPRODUCT(E$55:E$114,TRANSPOSE(SAP_Speadsheet!$E$57:$BL$57))} -> 0 | F11: {=SUMPRODUCT(F$55:F$114,TRANSPOSE(SAP_Speadsheet!$E$57:$BL$57))} -> 0 | G11: {=SUMPRODUCT(G$55:G$114,TRANSPOSE(SAP_Speadsheet!$E$57:$BL$57))} -> 0 | H11: {=SUMPRODUCT(H$55:H$114,TRANSPOSE(SAP_Speadsheet!$E$57:$BL$57))} -> 3192.0742 | I11: {=SUMPRODUCT(I$55:I$114,TRANSPOSE(SAP_Speadsheet!$E$57:$BL$57))} -> 5724.1935 | ... BI11: {=SUMPRODUCT(BI$55:BI$114,TRANSPOSE(SAP_Speadsheet!$E$57:$BL$57))} -> 0
A12: Interest income | B12: {=SUMPRODUCT(B$55:B$114,TRANSPOSE(SAP_Speadsheet!$E$58:$BL$58))} -> 0 | C12: {=SUMPRODUCT(C$55:C$114,TRANSPOSE(SAP_Speadsheet!$E$58:$BL$58))} -> 0 | D12: {=SUMPRODUCT(D$55:D$114,TRANSPOSE(SAP_Speadsheet!$E$58:$BL$58))} -> 0 | E12: {=SUMPRODUCT(E$55:E$114,TRANSPOSE(SAP_Speadsheet!$E$58:$BL$58))} -> 0 | F12: {=SUMPRODUCT(F$55:F$114,TRANSPOSE(SAP_Speadsheet!$E$58:$BL$58))} -> 0 | G12: {=SUMPRODUCT(G$55:G$114,TRANSPOSE(SAP_Speadsheet!$E$58:$BL$58))} -> 0 | H12: {=SUMPRODUCT(H$55:H$114,TRANSPOSE(SAP_Speadsheet!$E$58:$BL$58))} -> 3674.1537 | I12: {=SUMPRODUCT(I$55:I$114,TRANSPOSE(SAP_Speadsheet!$E$58:$BL$58))} -> 6605.2128 | ... BI12: {=SUMPRODUCT(BI$55:BI$114,TRANSPOSE(SAP_Speadsheet!$E$58:$BL$58))} -> 0
A13: Cost of fund | B13: {=SUMPRODUCT(B$55:B$114,TRANSPOSE(SAP_Speadsheet!$E$59:$BL$59))} -> 0 | C13: {=SUMPRODUCT(C$55:C$114,TRANSPOSE(SAP_Speadsheet!$E$59:$BL$59))} -> 0 | D13: {=SUMPRODUCT(D$55:D$114,TRANSPOSE(SAP_Speadsheet!$E$59:$BL$59))} -> 0 | E13: {=SUMPRODUCT(E$55:E$114,TRANSPOSE(SAP_Speadsheet!$E$59:$BL$59))} -> 0 | F13: {=SUMPRODUCT(F$55:F$114,TRANSPOSE(SAP_Speadsheet!$E$59:$BL$59))} -> 0 | G13: {=SUMPRODUCT(G$55:G$114,TRANSPOSE(SAP_Speadsheet!$E$59:$BL$59))} -> 0 | H13: {=SUMPRODUCT(H$55:H$114,TRANSPOSE(SAP_Speadsheet!$E$59:$BL$59))} -> -482.07943 | I13: {=SUMPRODUCT(I$55:I$114,TRANSPOSE(SAP_Speadsheet!$E$59:$BL$59))} -> -881.01929 | ... BI13: {=SUMPRODUCT(BI$55:BI$114,TRANSPOSE(SAP_Speadsheet!$E$59:$BL$59))} -> 0
A14: Net fee income | B14: {=SUMPRODUCT(B$55:B$114,TRANSPOSE(SAP_Speadsheet!$E$61:$BL$61))} -> 0 | C14: {=SUMPRODUCT(C$55:C$114,TRANSPOSE(SAP_Speadsheet!$E$61:$BL$61))} -> 0 | D14: {=SUMPRODUCT(D$55:D$114,TRANSPOSE(SAP_Speadsheet!$E$61:$BL$61))} -> 0 | E14: {=SUMPRODUCT(E$55:E$114,TRANSPOSE(SAP_Speadsheet!$E$61:$BL$61))} -> 0 | F14: {=SUMPRODUCT(F$55:F$114,TRANSPOSE(SAP_Speadsheet!$E$61:$BL$61))} -> 0 | G14: {=SUMPRODUCT(G$55:G$114,TRANSPOSE(SAP_Speadsheet!$E$61:$BL$61))} -> 0 | H14: {=SUMPRODUCT(H$55:H$114,TRANSPOSE(SAP_Speadsheet!$E$61:$BL$61))} -> 2682.8829 | I14: {=SUMPRODUCT(I$55:I$114,TRANSPOSE(SAP_Speadsheet!$E$61:$BL$61))} -> 2699.3157 | ... BI14: {=SUMPRODUCT(BI$55:BI$114,TRANSPOSE(SAP_Speadsheet!$E$61:$BL$61))} -> 0
A15: Early termination income | B15: {=SUMPRODUCT(B$55:B$114,TRANSPOSE(SAP_Speadsheet!$E$62:$BL$62))} -> 0 | C15: {=SUMPRODUCT(C$55:C$114,TRANSPOSE(SAP_Speadsheet!$E$62:$BL$62))} -> 0 | D15: {=SUMPRODUCT(D$55:D$114,TRANSPOSE(SAP_Speadsheet!$E$62:$BL$62))} -> 0 | E15: {=SUMPRODUCT(E$55:E$114,TRANSPOSE(SAP_Speadsheet!$E$62:$BL$62))} -> 0 | F15: {=SUMPRODUCT(F$55:F$114,TRANSPOSE(SAP_Speadsheet!$E$62:$BL$62))} -> 0 | G15: {=SUMPRODUCT(G$55:G$114,TRANSPOSE(SAP_Speadsheet!$E$62:$BL$62))} -> 0 | H15: {=SUMPRODUCT(H$55:H$114,TRANSPOSE(SAP_Speadsheet!$E$62:$BL$62))} -> 211.17803 | I15: {=SUMPRODUCT(I$55:I$114,TRANSPOSE(SAP_Speadsheet!$E$62:$BL$62))} -> 344.82985 | ... BI15: {=SUMPRODUCT(BI$55:BI$114,TRANSPOSE(SAP_Speadsheet!$E$62:$BL$62))} -> 0
A16: Insurance fee | B16: {=SUMPRODUCT(B$55:B$114,TRANSPOSE(SAP_Speadsheet!$E$63:$BL$63))} -> 0 | C16: {=SUMPRODUCT(C$55:C$114,TRANSPOSE(SAP_Speadsheet!$E$63:$BL$63))} -> 0 | D16: {=SUMPRODUCT(D$55:D$114,TRANSPOSE(SAP_Speadsheet!$E$63:$BL$63))} -> 0 | E16: {=SUMPRODUCT(E$55:E$114,TRANSPOSE(SAP_Speadsheet!$E$63:$BL$63))} -> 0 | F16: {=SUMPRODUCT(F$55:F$114,TRANSPOSE(SAP_Speadsheet!$E$63:$BL$63))} -> 0 | G16: {=SUMPRODUCT(G$55:G$114,TRANSPOSE(SAP_Speadsheet!$E$63:$BL$63))} -> 0 | H16: {=SUMPRODUCT(H$55:H$114,TRANSPOSE(SAP_Speadsheet!$E$63:$BL$63))} -> 2471.7049 | I16: {=SUMPRODUCT(I$55:I$114,TRANSPOSE(SAP_Speadsheet!$E$63:$BL$63))} -> 2354.4859 | ... BI16: {=SUMPRODUCT(BI$55:BI$114,TRANSPOSE(SAP_Speadsheet!$E$63:$BL$63))} -> 0
A17: Support fee | B17: {=SUMPRODUCT(B$55:B$114,TRANSPOSE(SAP_Speadsheet!$E$64:$BL$64))} -> 0 | C17: {=SUMPRODUCT(C$55:C$114,TRANSPOSE(SAP_Speadsheet!$E$64:$BL$64))} -> 0 | D17: {=SUMPRODUCT(D$55:D$114,TRANSPOSE(SAP_Speadsheet!$E$64:$BL$64))} -> 0 | E17: {=SUMPRODUCT(E$55:E$114,TRANSPOSE(SAP_Speadsheet!$E$64:$BL$64))} -> 0 | F17: {=SUMPRODUCT(F$55:F$114,TRANSPOSE(SAP_Speadsheet!$E$64:$BL$64))} -> 0 | G17: {=SUMPRODUCT(G$55:G$114,TRANSPOSE(SAP_Speadsheet!$E$64:$BL$64))} -> 0 | H17: {=SUMPRODUCT(H$55:H$114,TRANSPOSE(SAP_Speadsheet!$E$64:$BL$64))} -> 0 | I17: {=SUMPRODUCT(I$55:I$114,TRANSPOSE(SAP_Speadsheet!$E$64:$BL$64))} -> 0 | ... BI17: {=SUMPRODUCT(BI$55:BI$114,TRANSPOSE(SAP_Speadsheet!$E$64:$BL$64))} -> 0
A18: Other income | B18: {=SUMPRODUCT(B$55:B$114,TRANSPOSE(SAP_Speadsheet!$E$68:$BL$68))} -> 0 | C18: {=SUMPRODUCT(C$55:C$114,TRANSPOSE(SAP_Speadsheet!$E$68:$BL$68))} -> 0 | D18: {=SUMPRODUCT(D$55:D$114,TRANSPOSE(SAP_Speadsheet!$E$68:$BL$68))} -> 0 | E18: {=SUMPRODUCT(E$55:E$114,TRANSPOSE(SAP_Speadsheet!$E$68:$BL$68))} -> 0 | F18: {=SUMPRODUCT(F$55:F$114,TRANSPOSE(SAP_Speadsheet!$E$68:$BL$68))} -> 0 | G18: {=SUMPRODUCT(G$55:G$114,TRANSPOSE(SAP_Speadsheet!$E$68:$BL$68))} -> 0 | H18: {=SUMPRODUCT(H$55:H$114,TRANSPOSE(SAP_Speadsheet!$E$68:$BL$68))} -> 0 | I18: {=SUMPRODUCT(I$55:I$114,TRANSPOSE(SAP_Speadsheet!$E$68:$BL$68))} -> 0 | ... BI18: {=SUMPRODUCT(BI$55:BI$114,TRANSPOSE(SAP_Speadsheet!$E$68:$BL$68))} -> 0
A19: OPEX | B19: =B20+B24+B28+B29+B30 -> 0 | C19: =C20+C24+C28+C29+C30 -> 0 | D19: =D20+D24+D28+D29+D30 -> 0 | E19: =E20+E24+E28+E29+E30 -> 0 | F19: =F20+F24+F28+F29+F30 -> 0 | G19: =G20+G24+G28+G29+G30 -> 0 | H19: =H20+H24+H28+H29+H30 -> -2784.6257 | I19: =I20+I24+I28+I29+I30 -> -2975.7944 | ... BI19: =BI20+BI24+BI28+BI29+BI30 -> 0
A20: Sale incentive&mkt | B20: =SUM(B21:B23) -> 0 | C20: =SUM(C21:C23) -> 0 | D20: =SUM(D21:D23) -> 0 | E20: =SUM(E21:E23) -> 0 | F20: =SUM(F21:F23) -> 0 | G20: =SUM(G21:G23) -> 0 | H20: =SUM(H21:H23) -> -2199.7711 | I20: =SUM(I21:I23) -> -2095.4484 | ... BI20: =SUM(BI21:BI23) -> 0
A21: Lead Acquisition | B21: {=SUMPRODUCT(B$55:B$114,TRANSPOSE(SAP_Speadsheet!$E$73:$BL$73))} -> 0 | C21: {=SUMPRODUCT(C$55:C$114,TRANSPOSE(SAP_Speadsheet!$E$73:$BL$73))} -> 0 | D21: {=SUMPRODUCT(D$55:D$114,TRANSPOSE(SAP_Speadsheet!$E$73:$BL$73))} -> 0 | E21: {=SUMPRODUCT(E$55:E$114,TRANSPOSE(SAP_Speadsheet!$E$73:$BL$73))} -> 0 | F21: {=SUMPRODUCT(F$55:F$114,TRANSPOSE(SAP_Speadsheet!$E$73:$BL$73))} -> 0 | G21: {=SUMPRODUCT(G$55:G$114,TRANSPOSE(SAP_Speadsheet!$E$73:$BL$73))} -> 0 | H21: {=SUMPRODUCT(H$55:H$114,TRANSPOSE(SAP_Speadsheet!$E$73:$BL$73))} -> -2199.7711 | I21: {=SUMPRODUCT(I$55:I$114,TRANSPOSE(SAP_Speadsheet!$E$73:$BL$73))} -> -2095.4484 | ... BI21: {=SUMPRODUCT(BI$55:BI$114,TRANSPOSE(SAP_Speadsheet!$E$73:$BL$73))} -> 0
A22: Sharing performance | B22: {=SUMPRODUCT(B$55:B$114,TRANSPOSE(SAP_Speadsheet!$E$74:$BL$74))} -> 0 | C22: {=SUMPRODUCT(C$55:C$114,TRANSPOSE(SAP_Speadsheet!$E$74:$BL$74))} -> 0 | D22: {=SUMPRODUCT(D$55:D$114,TRANSPOSE(SAP_Speadsheet!$E$74:$BL$74))} -> 0 | E22: {=SUMPRODUCT(E$55:E$114,TRANSPOSE(SAP_Speadsheet!$E$74:$BL$74))} -> 0 | F22: {=SUMPRODUCT(F$55:F$114,TRANSPOSE(SAP_Speadsheet!$E$74:$BL$74))} -> 0 | G22: {=SUMPRODUCT(G$55:G$114,TRANSPOSE(SAP_Speadsheet!$E$74:$BL$74))} -> 0 | H22: {=SUMPRODUCT(H$55:H$114,TRANSPOSE(SAP_Speadsheet!$E$74:$BL$74))} -> 0 | I22: {=SUMPRODUCT(I$55:I$114,TRANSPOSE(SAP_Speadsheet!$E$74:$BL$74))} -> 0 | ... BI22: {=SUMPRODUCT(BI$55:BI$114,TRANSPOSE(SAP_Speadsheet!$E$74:$BL$74))} -> 0
A23: Marketing | B23: {=SUMPRODUCT(B$55:B$114,TRANSPOSE(SAP_Speadsheet!$E$86:$BL$86))} -> 0 | C23: {=SUMPRODUCT(C$55:C$114,TRANSPOSE(SAP_Speadsheet!$E$86:$BL$86))} -> 0 | D23: {=SUMPRODUCT(D$55:D$114,TRANSPOSE(SAP_Speadsheet!$E$86:$BL$86))} -> 0 | E23: {=SUMPRODUCT(E$55:E$114,TRANSPOSE(SAP_Speadsheet!$E$86:$BL$86))} -> 0 | F23: {=SUMPRODUCT(F$55:F$114,TRANSPOSE(SAP_Speadsheet!$E$86:$BL$86))} -> 0 | G23: {=SUMPRODUCT(G$55:G$114,TRANSPOSE(SAP_Speadsheet!$E$86:$BL$86))} -> 0 | H23: {=SUMPRODUCT(H$55:H$114,TRANSPOSE(SAP_Speadsheet!$E$86:$BL$86))} -> 0 | I23: {=SUMPRODUCT(I$55:I$114,TRANSPOSE(SAP_Speadsheet!$E$86:$BL$86))} -> 0 | ... AV23: {=SUMPRODUCT(AV$55:AV$114,TRANSPOSE(SAP_Speadsheet!$E$86:$BL$86))} -> 0 | AW23: 0 | AX23: {=SUMPRODUCT(AX$55:AX$114,TRANSPOSE(SAP_Speadsheet!$E$86:$BL$86))} -> 0 | AY23: {=SUMPRODUCT(AY$55:AY$114,TRANSPOSE(SAP_Speadsheet!$E$86:$BL$86))} -> 0 | AZ23: {=SUMPRODUCT(AZ$55:AZ$114,TRANSPOSE(SAP_Speadsheet!$E$86:$BL$86))} -> 0 | BA23: {=SUMPRODUCT(BA$55:BA$114,TRANSPOSE(SAP_Speadsheet!$E$86:$BL$86))} -> 0 | BB23: {=SUMPRODUCT(BB$55:BB$114,TRANSPOSE(SAP_Speadsheet!$E$86:$BL$86))} -> 0 | BC23: {=SUMPRODUCT(BC$55:BC$114,TRANSPOSE(SAP_Speadsheet!$E$86:$BL$86))} -> 0 | BD23: {=SUMPRODUCT(BD$55:BD$114,TRANSPOSE(SAP_Speadsheet!$E$86:$BL$86))} -> 0 | BE23: {=SUMPRODUCT(BE$55:BE$114,TRANSPOSE(SAP_Speadsheet!$E$86:$BL$86))} -> 0 | ... BI23: {=SUMPRODUCT(BI$55:BI$114,TRANSPOSE(SAP_Speadsheet!$E$86:$BL$86))} -> 0
A24: UW & Disbursal | B24: {=SUMPRODUCT(B$55:B$114,TRANSPOSE(SAP_Speadsheet!$E$88:$BL$88))} -> 0 | C24: {=SUMPRODUCT(C$55:C$114,TRANSPOSE(SAP_Speadsheet!$E$88:$BL$88))} -> 0 | D24: {=SUMPRODUCT(D$55:D$114,TRANSPOSE(SAP_Speadsheet!$E$88:$BL$88))} -> 0 | E24: {=SUMPRODUCT(E$55:E$114,TRANSPOSE(SAP_Speadsheet!$E$88:$BL$88))} -> 0 | F24: {=SUMPRODUCT(F$55:F$114,TRANSPOSE(SAP_Speadsheet!$E$88:$BL$88))} -> 0 | G24: {=SUMPRODUCT(G$55:G$114,TRANSPOSE(SAP_Speadsheet!$E$88:$BL$88))} -> 0 | H24: {=SUMPRODUCT(H$55:H$114,TRANSPOSE(SAP_Speadsheet!$E$88:$BL$88))} -> -233.58318 | I24: {=SUMPRODUCT(I$55:I$114,TRANSPOSE(SAP_Speadsheet!$E$88:$BL$88))} -> -222.50565 | ... BI24: {=SUMPRODUCT(BI$55:BI$114,TRANSPOSE(SAP_Speadsheet!$E$88:$BL$88))} -> 0
A25: Underwriting | B25: {=SUMPRODUCT(B$55:B$114,TRANSPOSE(SAP_Speadsheet!$E$89:$BL$89))} -> 0 | C25: {=SUMPRODUCT(C$55:C$114,TRANSPOSE(SAP_Speadsheet!$E$89:$BL$89))} -> 0 | D25: {=SUMPRODUCT(D$55:D$114,TRANSPOSE(SAP_Speadsheet!$E$89:$BL$89))} -> 0 | E25: {=SUMPRODUCT(E$55:E$114,TRANSPOSE(SAP_Speadsheet!$E$89:$BL$89))} -> 0 | F25: {=SUMPRODUCT(F$55:F$114,TRANSPOSE(SAP_Speadsheet!$E$89:$BL$89))} -> 0 | G25: {=SUMPRODUCT(G$55:G$114,TRANSPOSE(SAP_Speadsheet!$E$89:$BL$89))} -> 0 | H25: {=SUMPRODUCT(H$55:H$114,TRANSPOSE(SAP_Speadsheet!$E$89:$BL$89))} -> -209.12318 | I25: {=SUMPRODUCT(I$55:I$114,TRANSPOSE(SAP_Speadsheet!$E$89:$BL$89))} -> -199.20565 | ... BI25: {=SUMPRODUCT(BI$55:BI$114,TRANSPOSE(SAP_Speadsheet!$E$89:$BL$89))} -> 0
A26: Disbursement | B26: {=SUMPRODUCT(B$55:B$114,TRANSPOSE(SAP_Speadsheet!$E$90:$BL$90))} -> 0 | C26: {=SUMPRODUCT(C$55:C$114,TRANSPOSE(SAP_Speadsheet!$E$90:$BL$90))} -> 0 | D26: {=SUMPRODUCT(D$55:D$114,TRANSPOSE(SAP_Speadsheet!$E$90:$BL$90))} -> 0 | E26: {=SUMPRODUCT(E$55:E$114,TRANSPOSE(SAP_Speadsheet!$E$90:$BL$90))} -> 0 | F26: {=SUMPRODUCT(F$55:F$114,TRANSPOSE(SAP_Speadsheet!$E$90:$BL$90))} -> 0 | G26: {=SUMPRODUCT(G$55:G$114,TRANSPOSE(SAP_Speadsheet!$E$90:$BL$90))} -> 0 | H26: {=SUMPRODUCT(H$55:H$114,TRANSPOSE(SAP_Speadsheet!$E$90:$BL$90))} -> -24.46 | I26: {=SUMPRODUCT(I$55:I$114,TRANSPOSE(SAP_Speadsheet!$E$90:$BL$90))} -> -23.3 | ... BI26: {=SUMPRODUCT(BI$55:BI$114,TRANSPOSE(SAP_Speadsheet!$E$90:$BL$90))} -> 0
A27: DOP | B27: {=SUMPRODUCT(B$55:B$114,TRANSPOSE(SAP_Speadsheet!$E$91:$BL$91))} -> 0 | C27: {=SUMPRODUCT(C$55:C$114,TRANSPOSE(SAP_Speadsheet!$E$91:$BL$91))} -> 0 | D27: {=SUMPRODUCT(D$55:D$114,TRANSPOSE(SAP_Speadsheet!$E$91:$BL$91))} -> 0 | E27: {=SUMPRODUCT(E$55:E$114,TRANSPOSE(SAP_Speadsheet!$E$91:$BL$91))} -> 0 | F27: {=SUMPRODUCT(F$55:F$114,TRANSPOSE(SAP_Speadsheet!$E$91:$BL$91))} -> 0 | G27: {=SUMPRODUCT(G$55:G$114,TRANSPOSE(SAP_Speadsheet!$E$91:$BL$91))} -> 0 | H27: {=SUMPRODUCT(H$55:H$114,TRANSPOSE(SAP_Speadsheet!$E$91:$BL$91))} -> 0 | I27: {=SUMPRODUCT(I$55:I$114,TRANSPOSE(SAP_Speadsheet!$E$91:$BL$91))} -> 0 | ... BI27: {=SUMPRODUCT(BI$55:BI$114,TRANSPOSE(SAP_Speadsheet!$E$91:$BL$91))} -> 0
A28: Collection | B28: {=SUMPRODUCT(B$55:B$114,TRANSPOSE(SAP_Speadsheet!$E$95:$BL$95))} -> 0 | C28: {=SUMPRODUCT(C$55:C$114,TRANSPOSE(SAP_Speadsheet!$E$95:$BL$95))} -> 0 | D28: {=SUMPRODUCT(D$55:D$114,TRANSPOSE(SAP_Speadsheet!$E$95:$BL$95))} -> 0 | E28: {=SUMPRODUCT(E$55:E$114,TRANSPOSE(SAP_Speadsheet!$E$95:$BL$95))} -> 0 | F28: {=SUMPRODUCT(F$55:F$114,TRANSPOSE(SAP_Speadsheet!$E$95:$BL$95))} -> 0 | G28: {=SUMPRODUCT(G$55:G$114,TRANSPOSE(SAP_Speadsheet!$E$95:$BL$95))} -> 0 | H28: {=SUMPRODUCT(H$55:H$114,TRANSPOSE(SAP_Speadsheet!$E$95:$BL$95))} -> -48.92 | I28: {=SUMPRODUCT(I$55:I$114,TRANSPOSE(SAP_Speadsheet!$E$95:$BL$95))} -> -91.6064 | ... BI28: {=SUMPRODUCT(BI$55:BI$114,TRANSPOSE(SAP_Speadsheet!$E$95:$BL$95))} -> 0
A29: After-sales services | B29: {=SUMPRODUCT(B$55:B$114,TRANSPOSE(SAP_Speadsheet!$E$99:$BL$99))} -> 0 | C29: {=SUMPRODUCT(C$55:C$114,TRANSPOSE(SAP_Speadsheet!$E$99:$BL$99))} -> 0 | D29: {=SUMPRODUCT(D$55:D$114,TRANSPOSE(SAP_Speadsheet!$E$99:$BL$99))} -> 0 | E29: {=SUMPRODUCT(E$55:E$114,TRANSPOSE(SAP_Speadsheet!$E$99:$BL$99))} -> 0 | F29: {=SUMPRODUCT(F$55:F$114,TRANSPOSE(SAP_Speadsheet!$E$99:$BL$99))} -> 0 | G29: {=SUMPRODUCT(G$55:G$114,TRANSPOSE(SAP_Speadsheet!$E$99:$BL$99))} -> 0 | H29: {=SUMPRODUCT(H$55:H$114,TRANSPOSE(SAP_Speadsheet!$E$99:$BL$99))} -> -3.93806 | I29: {=SUMPRODUCT(I$55:I$114,TRANSPOSE(SAP_Speadsheet!$E$99:$BL$99))} -> -7.43253 | ... BI29: {=SUMPRODUCT(BI$55:BI$114,TRANSPOSE(SAP_Speadsheet!$E$99:$BL$99))} -> 0
A30: Other support units | B30: {=SUMPRODUCT(B$55:B$114,TRANSPOSE(SAP_Speadsheet!$E$103:$BL$103))} -> 0 | C30: {=SUMPRODUCT(C$55:C$114,TRANSPOSE(SAP_Speadsheet!$E$103:$BL$103))} -> 0 | D30: {=SUMPRODUCT(D$55:D$114,TRANSPOSE(SAP_Speadsheet!$E$103:$BL$103))} -> 0 | E30: {=SUMPRODUCT(E$55:E$114,TRANSPOSE(SAP_Speadsheet!$E$103:$BL$103))} -> 0 | F30: {=SUMPRODUCT(F$55:F$114,TRANSPOSE(SAP_Speadsheet!$E$103:$BL$103))} -> 0 | G30: {=SUMPRODUCT(G$55:G$114,TRANSPOSE(SAP_Speadsheet!$E$103:$BL$103))} -> 0 | H30: {=SUMPRODUCT(H$55:H$114,TRANSPOSE(SAP_Speadsheet!$E$103:$BL$103))} -> -298.41329 | I30: {=SUMPRODUCT(I$55:I$114,TRANSPOSE(SAP_Speadsheet!$E$103:$BL$103))} -> -558.80146 | ... BI30: {=SUMPRODUCT(BI$55:BI$114,TRANSPOSE(SAP_Speadsheet!$E$103:$BL$103))} -> 0
A31: PROVISION | B31: {=SUMPRODUCT(B$55:B$114,TRANSPOSE(SAP_Speadsheet!$E$183:$BL$183))} -> 0 | C31: {=SUMPRODUCT(C$55:C$114,TRANSPOSE(SAP_Speadsheet!$E$183:$BL$183))} -> 0 | D31: {=SUMPRODUCT(D$55:D$114,TRANSPOSE(SAP_Speadsheet!$E$183:$BL$183))} -> 0 | E31: {=SUMPRODUCT(E$55:E$114,TRANSPOSE(SAP_Speadsheet!$E$183:$BL$183))} -> 0 | F31: {=SUMPRODUCT(F$55:F$114,TRANSPOSE(SAP_Speadsheet!$E$183:$BL$183))} -> 0 | G31: {=SUMPRODUCT(G$55:G$114,TRANSPOSE(SAP_Speadsheet!$E$183:$BL$183))} -> 0 | H31: {=SUMPRODUCT(H$55:H$114,TRANSPOSE(SAP_Speadsheet!$E$183:$BL$183))} -> -3451.3195 | I31: {=SUMPRODUCT(I$55:I$114,TRANSPOSE(SAP_Speadsheet!$E$183:$BL$183))} -> -4632.1263 | ... BI31: {=SUMPRODUCT(BI$55:BI$114,TRANSPOSE(SAP_Speadsheet!$E$183:$BL$183))} -> 0
A32: PBT | B32: {=SUMPRODUCT(B$55:B$114,TRANSPOSE(SAP_Speadsheet!$E$189:$BL$189))} -> 0 | C32: {=SUMPRODUCT(C$55:C$114,TRANSPOSE(SAP_Speadsheet!$E$189:$BL$189))} -> 0 | D32: {=SUMPRODUCT(D$55:D$114,TRANSPOSE(SAP_Speadsheet!$E$189:$BL$189))} -> 0 | E32: {=SUMPRODUCT(E$55:E$114,TRANSPOSE(SAP_Speadsheet!$E$189:$BL$189))} -> 0 | F32: {=SUMPRODUCT(F$55:F$114,TRANSPOSE(SAP_Speadsheet!$E$189:$BL$189))} -> 0 | G32: {=SUMPRODUCT(G$55:G$114,TRANSPOSE(SAP_Speadsheet!$E$189:$BL$189))} -> 0 | H32: {=SUMPRODUCT(H$55:H$114,TRANSPOSE(SAP_Speadsheet!$E$189:$BL$189))} -> -360.98796 | I32: {=SUMPRODUCT(I$55:I$114,TRANSPOSE(SAP_Speadsheet!$E$189:$BL$189))} -> 815.58856 | ... BI32: {=SUMPRODUCT(BI$55:BI$114,TRANSPOSE(SAP_Speadsheet!$E$189:$BL$189))} -> 0
A33: Checking | B33: =B9+B19+B31-B32 -> 0 | C33: =C9+C19+C31-C32 -> 0 | D33: =D9+D19+D31-D32 -> 0 | E33: =E9+E19+E31-E32 -> 0 | F33: =F9+F19+F31-F32 -> 0 | G33: =G9+G19+G31-G32 -> 0 | H33: =H9+H19+H31-H32 -> 0 | I33: =I9+I19+I31-I32 -> -1.3642421e-12 | ... BI33: =BI9+BI19+BI31-BI32 -> 0
A35: EOP BY BUCKET
A36: B0 | B36: {=SUMPRODUCT(B$55:B$114,TRANSPOSE(SAP_Speadsheet!$E$27:$BL$27))} -> 0 | C36: {=SUMPRODUCT(C$55:C$114,TRANSPOSE(SAP_Speadsheet!$E$27:$BL$27))} -> 0 | D36: {=SUMPRODUCT(D$55:D$114,TRANSPOSE(SAP_Speadsheet!$E$27:$BL$27))} -> 0 | E36: {=SUMPRODUCT(E$55:E$114,TRANSPOSE(SAP_Speadsheet!$E$27:$BL$27))} -> 0 | F36: {=SUMPRODUCT(F$55:F$114,TRANSPOSE(SAP_Speadsheet!$E$27:$BL$27))} -> 0 | G36: {=SUMPRODUCT(G$55:G$114,TRANSPOSE(SAP_Speadsheet!$E$27:$BL$27))} -> 0 | H36: {=SUMPRODUCT(H$55:H$114,TRANSPOSE(SAP_Speadsheet!$E$27:$BL$27))} -> 73429.7 | I36: {=SUMPRODUCT(I$55:I$114,TRANSPOSE(SAP_Speadsheet!$E$27:$BL$27))} -> 132829.74 | ... BI36: {=SUMPRODUCT(BI$55:BI$114,TRANSPOSE(SAP_Speadsheet!$E$27:$BL$27))} -> 0
A37: B1 | B37: {=SUMPRODUCT(B$55:B$114,TRANSPOSE(SAP_Speadsheet!$E$28:$BL$28))} -> 0 | C37: {=SUMPRODUCT(C$55:C$114,TRANSPOSE(SAP_Speadsheet!$E$28:$BL$28))} -> 0 | D37: {=SUMPRODUCT(D$55:D$114,TRANSPOSE(SAP_Speadsheet!$E$28:$BL$28))} -> 0 | E37: {=SUMPRODUCT(E$55:E$114,TRANSPOSE(SAP_Speadsheet!$E$28:$BL$28))} -> 0 | F37: {=SUMPRODUCT(F$55:F$114,TRANSPOSE(SAP_Speadsheet!$E$28:$BL$28))} -> 0 | G37: {=SUMPRODUCT(G$55:G$114,TRANSPOSE(SAP_Speadsheet!$E$28:$BL$28))} -> 0 | H37: {=SUMPRODUCT(H$55:H$114,TRANSPOSE(SAP_Speadsheet!$E$28:$BL$28))} -> 2975.8497 | I37: {=SUMPRODUCT(I$55:I$114,TRANSPOSE(SAP_Speadsheet!$E$28:$BL$28))} -> 5318.1137 | ... BI37: {=SUMPRODUCT(BI$55:BI$114,TRANSPOSE(SAP_Speadsheet!$E$28:$BL$28))} -> 0
A38: B2 | B38: {=SUMPRODUCT(B$55:B$114,TRANSPOSE(SAP_Speadsheet!$E$29:$BL$29))} -> 0 | C38: {=SUMPRODUCT(C$55:C$114,TRANSPOSE(SAP_Speadsheet!$E$29:$BL$29))} -> 0 | D38: {=SUMPRODUCT(D$55:D$114,TRANSPOSE(SAP_Speadsheet!$E$29:$BL$29))} -> 0 | E38: {=SUMPRODUCT(E$55:E$114,TRANSPOSE(SAP_Speadsheet!$E$29:$BL$29))} -> 0 | F38: {=SUMPRODUCT(F$55:F$114,TRANSPOSE(SAP_Speadsheet!$E$29:$BL$29))} -> 0 | G38: {=SUMPRODUCT(G$55:G$114,TRANSPOSE(SAP_Speadsheet!$E$29:$BL$29))} -> 0 | H38: {=SUMPRODUCT(H$55:H$114,TRANSPOSE(SAP_Speadsheet!$E$29:$BL$29))} -> 0 | I38: {=SUMPRODUCT(I$55:I$114,TRANSPOSE(SAP_Speadsheet!$E$29:$BL$29))} -> 2069.5923 | ... BI38: {=SUMPRODUCT(BI$55:BI$114,TRANSPOSE(SAP_Speadsheet!$E$29:$BL$29))} -> 0
A39: B3 | B39: {=SUMPRODUCT(B$55:B$114,TRANSPOSE(SAP_Speadsheet!$E$30:$BL$30))} -> 0 | C39: {=SUMPRODUCT(C$55:C$114,TRANSPOSE(SAP_Speadsheet!$E$30:$BL$30))} -> 0 | D39: {=SUMPRODUCT(D$55:D$114,TRANSPOSE(SAP_Speadsheet!$E$30:$BL$30))} -> 0 | E39: {=SUMPRODUCT(E$55:E$114,TRANSPOSE(SAP_Speadsheet!$E$30:$BL$30))} -> 0 | F39: {=SUMPRODUCT(F$55:F$114,TRANSPOSE(SAP_Speadsheet!$E$30:$BL$30))} -> 0 | G39: {=SUMPRODUCT(G$55:G$114,TRANSPOSE(SAP_Speadsheet!$E$30:$BL$30))} -> 0 | H39: {=SUMPRODUCT(H$55:H$114,TRANSPOSE(SAP_Speadsheet!$E$30:$BL$30))} -> 0 | I39: {=SUMPRODUCT(I$55:I$114,TRANSPOSE(SAP_Speadsheet!$E$30:$BL$30))} -> 0 | ... BI39: {=SUMPRODUCT(BI$55:BI$114,TRANSPOSE(SAP_Speadsheet!$E$30:$BL$30))} -> 0
A40: B4 | B40: {=SUMPRODUCT(B$55:B$114,TRANSPOSE(SAP_Speadsheet!$E$31:$BL$31))} -> 0 | C40: {=SUMPRODUCT(C$55:C$114,TRANSPOSE(SAP_Speadsheet!$E$31:$BL$31))} -> 0 | D40: {=SUMPRODUCT(D$55:D$114,TRANSPOSE(SAP_Speadsheet!$E$31:$BL$31))} -> 0 | E40: {=SUMPRODUCT(E$55:E$114,TRANSPOSE(SAP_Speadsheet!$E$31:$BL$31))} -> 0 | F40: {=SUMPRODUCT(F$55:F$114,TRANSPOSE(SAP_Speadsheet!$E$31:$BL$31))} -> 0 | G40: {=SUMPRODUCT(G$55:G$114,TRANSPOSE(SAP_Speadsheet!$E$31:$BL$31))} -> 0 | H40: {=SUMPRODUCT(H$55:H$114,TRANSPOSE(SAP_Speadsheet!$E$31:$BL$31))} -> 0 | I40: {=SUMPRODUCT(I$55:I$114,TRANSPOSE(SAP_Speadsheet!$E$31:$BL$31))} -> 0 | ... BI40: {=SUMPRODUCT(BI$55:BI$114,TRANSPOSE(SAP_Speadsheet!$E$31:$BL$31))} -> 0
A41: B5 | B41: {=SUMPRODUCT(B$55:B$114,TRANSPOSE(SAP_Speadsheet!$E$32:$BL$32))} -> 0 | C41: {=SUMPRODUCT(C$55:C$114,TRANSPOSE(SAP_Speadsheet!$E$32:$BL$32))} -> 0 | D41: {=SUMPRODUCT(D$55:D$114,TRANSPOSE(SAP_Speadsheet!$E$32:$BL$32))} -> 0 | E41: {=SUMPRODUCT(E$55:E$114,TRANSPOSE(SAP_Speadsheet!$E$32:$BL$32))} -> 0 | F41: {=SUMPRODUCT(F$55:F$114,TRANSPOSE(SAP_Speadsheet!$E$32:$BL$32))} -> 0 | G41: {=SUMPRODUCT(G$55:G$114,TRANSPOSE(SAP_Speadsheet!$E$32:$BL$32))} -> 0 | H41: {=SUMPRODUCT(H$55:H$114,TRANSPOSE(SAP_Speadsheet!$E$32:$BL$32))} -> 0 | I41: {=SUMPRODUCT(I$55:I$114,TRANSPOSE(SAP_Speadsheet!$E$32:$BL$32))} -> 0 | ... BI41: {=SUMPRODUCT(BI$55:BI$114,TRANSPOSE(SAP_Speadsheet!$E$32:$BL$32))} -> 0
A42: B6 | B42: {=SUMPRODUCT(B$55:B$114,TRANSPOSE(SAP_Speadsheet!$E$33:$BL$33))} -> 0 | C42: {=SUMPRODUCT(C$55:C$114,TRANSPOSE(SAP_Speadsheet!$E$33:$BL$33))} -> 0 | D42: {=SUMPRODUCT(D$55:D$114,TRANSPOSE(SAP_Speadsheet!$E$33:$BL$33))} -> 0 | E42: {=SUMPRODUCT(E$55:E$114,TRANSPOSE(SAP_Speadsheet!$E$33:$BL$33))} -> 0 | F42: {=SUMPRODUCT(F$55:F$114,TRANSPOSE(SAP_Speadsheet!$E$33:$BL$33))} -> 0 | G42: {=SUMPRODUCT(G$55:G$114,TRANSPOSE(SAP_Speadsheet!$E$33:$BL$33))} -> 0 | H42: {=SUMPRODUCT(H$55:H$114,TRANSPOSE(SAP_Speadsheet!$E$33:$BL$33))} -> 0 | I42: {=SUMPRODUCT(I$55:I$114,TRANSPOSE(SAP_Speadsheet!$E$33:$BL$33))} -> 0 | ... BI42: {=SUMPRODUCT(BI$55:BI$114,TRANSPOSE(SAP_Speadsheet!$E$33:$BL$33))} -> 0
A43: B7 | B43: {=SUMPRODUCT(B$55:B$114,TRANSPOSE(SAP_Speadsheet!$E$34:$BL$34))} -> 0 | C43: {=SUMPRODUCT(C$55:C$114,TRANSPOSE(SAP_Speadsheet!$E$34:$BL$34))} -> 0 | D43: {=SUMPRODUCT(D$55:D$114,TRANSPOSE(SAP_Speadsheet!$E$34:$BL$34))} -> 0 | E43: {=SUMPRODUCT(E$55:E$114,TRANSPOSE(SAP_Speadsheet!$E$34:$BL$34))} -> 0 | F43: {=SUMPRODUCT(F$55:F$114,TRANSPOSE(SAP_Speadsheet!$E$34:$BL$34))} -> 0 | G43: {=SUMPRODUCT(G$55:G$114,TRANSPOSE(SAP_Speadsheet!$E$34:$BL$34))} -> 0 | H43: {=SUMPRODUCT(H$55:H$114,TRANSPOSE(SAP_Speadsheet!$E$34:$BL$34))} -> 0 | I43: {=SUMPRODUCT(I$55:I$114,TRANSPOSE(SAP_Speadsheet!$E$34:$BL$34))} -> 0 | ... BI43: {=SUMPRODUCT(BI$55:BI$114,TRANSPOSE(SAP_Speadsheet!$E$34:$BL$34))} -> 0
A44: B8 | B44: {=SUMPRODUCT(B$55:B$114,TRANSPOSE(SAP_Speadsheet!$E$35:$BL$35))} -> 0 | C44: {=SUMPRODUCT(C$55:C$114,TRANSPOSE(SAP_Speadsheet!$E$35:$BL$35))} -> 0 | D44: {=SUMPRODUCT(D$55:D$114,TRANSPOSE(SAP_Speadsheet!$E$35:$BL$35))} -> 0 | E44: {=SUMPRODUCT(E$55:E$114,TRANSPOSE(SAP_Speadsheet!$E$35:$BL$35))} -> 0 | F44: {=SUMPRODUCT(F$55:F$114,TRANSPOSE(SAP_Speadsheet!$E$35:$BL$35))} -> 0 | G44: {=SUMPRODUCT(G$55:G$114,TRANSPOSE(SAP_Speadsheet!$E$35:$BL$35))} -> 0 | H44: {=SUMPRODUCT(H$55:H$114,TRANSPOSE(SAP_Speadsheet!$E$35:$BL$35))} -> 0 | I44: {=SUMPRODUCT(I$55:I$114,TRANSPOSE(SAP_Speadsheet!$E$35:$BL$35))} -> 0 | ... BI44: {=SUMPRODUCT(BI$55:BI$114,TRANSPOSE(SAP_Speadsheet!$E$35:$BL$35))} -> 0
A45: B9 | B45: {=SUMPRODUCT(B$55:B$114,TRANSPOSE(SAP_Speadsheet!$E$36:$BL$36))} -> 0 | C45: {=SUMPRODUCT(C$55:C$114,TRANSPOSE(SAP_Speadsheet!$E$36:$BL$36))} -> 0 | D45: {=SUMPRODUCT(D$55:D$114,TRANSPOSE(SAP_Speadsheet!$E$36:$BL$36))} -> 0 | E45: {=SUMPRODUCT(E$55:E$114,TRANSPOSE(SAP_Speadsheet!$E$36:$BL$36))} -> 0 | F45: {=SUMPRODUCT(F$55:F$114,TRANSPOSE(SAP_Speadsheet!$E$36:$BL$36))} -> 0 | G45: {=SUMPRODUCT(G$55:G$114,TRANSPOSE(SAP_Speadsheet!$E$36:$BL$36))} -> 0 | H45: {=SUMPRODUCT(H$55:H$114,TRANSPOSE(SAP_Speadsheet!$E$36:$BL$36))} -> 0 | I45: {=SUMPRODUCT(I$55:I$114,TRANSPOSE(SAP_Speadsheet!$E$36:$BL$36))} -> 0 | ... BI45: {=SUMPRODUCT(BI$55:BI$114,TRANSPOSE(SAP_Speadsheet!$E$36:$BL$36))} -> 0
A46: B10 | B46: {=SUMPRODUCT(B$55:B$114,TRANSPOSE(SAP_Speadsheet!$E$37:$BL$37))} -> 0 | C46: {=SUMPRODUCT(C$55:C$114,TRANSPOSE(SAP_Speadsheet!$E$37:$BL$37))} -> 0 | D46: {=SUMPRODUCT(D$55:D$114,TRANSPOSE(SAP_Speadsheet!$E$37:$BL$37))} -> 0 | E46: {=SUMPRODUCT(E$55:E$114,TRANSPOSE(SAP_Speadsheet!$E$37:$BL$37))} -> 0 | F46: {=SUMPRODUCT(F$55:F$114,TRANSPOSE(SAP_Speadsheet!$E$37:$BL$37))} -> 0 | G46: {=SUMPRODUCT(G$55:G$114,TRANSPOSE(SAP_Speadsheet!$E$37:$BL$37))} -> 0 | H46: {=SUMPRODUCT(H$55:H$114,TRANSPOSE(SAP_Speadsheet!$E$37:$BL$37))} -> 0 | I46: {=SUMPRODUCT(I$55:I$114,TRANSPOSE(SAP_Speadsheet!$E$37:$BL$37))} -> 0 | ... BI46: {=SUMPRODUCT(BI$55:BI$114,TRANSPOSE(SAP_Speadsheet!$E$37:$BL$37))} -> 0
A47: B11 | B47: {=SUMPRODUCT(B$55:B$114,TRANSPOSE(SAP_Speadsheet!$E$38:$BL$38))} -> 0 | C47: {=SUMPRODUCT(C$55:C$114,TRANSPOSE(SAP_Speadsheet!$E$38:$BL$38))} -> 0 | D47: {=SUMPRODUCT(D$55:D$114,TRANSPOSE(SAP_Speadsheet!$E$38:$BL$38))} -> 0 | E47: {=SUMPRODUCT(E$55:E$114,TRANSPOSE(SAP_Speadsheet!$E$38:$BL$38))} -> 0 | F47: {=SUMPRODUCT(F$55:F$114,TRANSPOSE(SAP_Speadsheet!$E$38:$BL$38))} -> 0 | G47: {=SUMPRODUCT(G$55:G$114,TRANSPOSE(SAP_Speadsheet!$E$38:$BL$38))} -> 0 | H47: {=SUMPRODUCT(H$55:H$114,TRANSPOSE(SAP_Speadsheet!$E$38:$BL$38))} -> 0 | I47: {=SUMPRODUCT(I$55:I$114,TRANSPOSE(SAP_Speadsheet!$E$38:$BL$38))} -> 0 | ... BI47: {=SUMPRODUCT(BI$55:BI$114,TRANSPOSE(SAP_Speadsheet!$E$38:$BL$38))} -> 0
A48: B12 | B48: {=SUMPRODUCT(B$55:B$114,TRANSPOSE(SAP_Speadsheet!$E$39:$BL$39))} -> 0 | C48: {=SUMPRODUCT(C$55:C$114,TRANSPOSE(SAP_Speadsheet!$E$39:$BL$39))} -> 0 | D48: {=SUMPRODUCT(D$55:D$114,TRANSPOSE(SAP_Speadsheet!$E$39:$BL$39))} -> 0 | E48: {=SUMPRODUCT(E$55:E$114,TRANSPOSE(SAP_Speadsheet!$E$39:$BL$39))} -> 0 | F48: {=SUMPRODUCT(F$55:F$114,TRANSPOSE(SAP_Speadsheet!$E$39:$BL$39))} -> 0 | G48: {=SUMPRODUCT(G$55:G$114,TRANSPOSE(SAP_Speadsheet!$E$39:$BL$39))} -> 0 | H48: {=SUMPRODUCT(H$55:H$114,TRANSPOSE(SAP_Speadsheet!$E$39:$BL$39))} -> 0 | I48: {=SUMPRODUCT(I$55:I$114,TRANSPOSE(SAP_Speadsheet!$E$39:$BL$39))} -> 0 | ... BI48: {=SUMPRODUCT(BI$55:BI$114,TRANSPOSE(SAP_Speadsheet!$E$39:$BL$39))} -> 0
A49: B13+ | B49: {=SUMPRODUCT(B$55:B$114,TRANSPOSE(SAP_Speadsheet!$E$40:$BL$40))} -> 0 | C49: {=SUMPRODUCT(C$55:C$114,TRANSPOSE(SAP_Speadsheet!$E$40:$BL$40))} -> 0 | D49: {=SUMPRODUCT(D$55:D$114,TRANSPOSE(SAP_Speadsheet!$E$40:$BL$40))} -> 0 | E49: {=SUMPRODUCT(E$55:E$114,TRANSPOSE(SAP_Speadsheet!$E$40:$BL$40))} -> 0 | F49: {=SUMPRODUCT(F$55:F$114,TRANSPOSE(SAP_Speadsheet!$E$40:$BL$40))} -> 0 | G49: {=SUMPRODUCT(G$55:G$114,TRANSPOSE(SAP_Speadsheet!$E$40:$BL$40))} -> 0 | H49: {=SUMPRODUCT(H$55:H$114,TRANSPOSE(SAP_Speadsheet!$E$40:$BL$40))} -> 0 | I49: {=SUMPRODUCT(I$55:I$114,TRANSPOSE(SAP_Speadsheet!$E$40:$BL$40))} -> 0 | ... BI49: {=SUMPRODUCT(BI$55:BI$114,TRANSPOSE(SAP_Speadsheet!$E$40:$BL$40))} -> 0
A50: B14+ | B50: {=SUMPRODUCT(B$55:B$114,TRANSPOSE(SAP_Speadsheet!$E$41:$BL$41))} -> 0 | C50: {=SUMPRODUCT(C$55:C$114,TRANSPOSE(SAP_Speadsheet!$E$41:$BL$41))} -> 0 | D50: {=SUMPRODUCT(D$55:D$114,TRANSPOSE(SAP_Speadsheet!$E$41:$BL$41))} -> 0 | E50: {=SUMPRODUCT(E$55:E$114,TRANSPOSE(SAP_Speadsheet!$E$41:$BL$41))} -> 0 | F50: {=SUMPRODUCT(F$55:F$114,TRANSPOSE(SAP_Speadsheet!$E$41:$BL$41))} -> 0 | G50: {=SUMPRODUCT(G$55:G$114,TRANSPOSE(SAP_Speadsheet!$E$41:$BL$41))} -> 0 | H50: {=SUMPRODUCT(H$55:H$114,TRANSPOSE(SAP_Speadsheet!$E$41:$BL$41))} -> 0 | I50: {=SUMPRODUCT(I$55:I$114,TRANSPOSE(SAP_Speadsheet!$E$41:$BL$41))} -> 0 | ... BI50: {=SUMPRODUCT(BI$55:BI$114,TRANSPOSE(SAP_Speadsheet!$E$41:$BL$41))} -> 0
A51: Checking | B51: =SUM(B36:B50)-B7 -> 0 | C51: =SUM(C36:C50)-C7 -> 0 | D51: =SUM(D36:D50)-D7 -> 0 | E51: =SUM(E36:E50)-E7 -> 0 | F51: =SUM(F36:F50)-F7 -> 0 | G51: =SUM(G36:G50)-G7 -> 0 | H51: =SUM(H36:H50)-H7 -> 0 | I51: =SUM(I36:I50)-I7 -> 0 | ... BI51: =SUM(BI36:BI50)-BI7 -> 0
A54: No. of account | B54: =ROUND('Saleplan&PnL'!D6*1000/Leadsheet!$E$10,0) -> 0 | C54: =ROUND('Saleplan&PnL'!E6*1000/Leadsheet!$E$10,0) -> 0 | D54: =ROUND('Saleplan&PnL'!F6*1000/Leadsheet!$E$10,0) -> 0 | E54: =ROUND('Saleplan&PnL'!G6*1000/Leadsheet!$E$10,0) -> 0 | F54: =ROUND('Saleplan&PnL'!H6*1000/Leadsheet!$E$10,0) -> 0 | G54: =ROUND('Saleplan&PnL'!I6*1000/Leadsheet!$E$10,0) -> 0 | H54: =ROUND('Saleplan&PnL'!J6*1000/Leadsheet!$E$10,0) -> 6115 | I54: =ROUND('Saleplan&PnL'!K6*1000/Leadsheet!$E$10,0) -> 5825 | ... BI54: =ROUND('Saleplan&PnL'!BK6*1000/Leadsheet!$E$10,0) -> 0
A55: 1 | B55: =IF($A55>B$5,"",OFFSET(B$54,0,-($A55-1))) -> 0 | C55: =IF($A55>C$5,"",OFFSET(C$54,0,-($A55-1))) -> 0 | D55: =IF($A55>D$5,"",OFFSET(D$54,0,-($A55-1))) -> 0 | E55: =IF($A55>E$5,"",OFFSET(E$54,0,-($A55-1))) -> 0 | F55: =IF($A55>F$5,"",OFFSET(F$54,0,-($A55-1))) -> 0 | G55: =IF($A55>G$5,"",OFFSET(G$54,0,-($A55-1))) -> 0 | H55: =IF($A55>H$5,"",OFFSET(H$54,0,-($A55-1))) -> 6115 | I55: =IF($A55>I$5,"",OFFSET(I$54,0,-($A55-1))) -> 5825 | ... BI55: =IF($A55>BI$5,"",OFFSET(BI$54,0,-($A55-1))) -> 0
A56: 2 | B56: =IF($A56>B$5,"",OFFSET(B$54,0,-($A56-1))) | C56: =IF($A56>C$5,"",OFFSET(C$54,0,-($A56-1))) -> 0 | D56: =IF($A56>D$5,"",OFFSET(D$54,0,-($A56-1))) -> 0 | E56: =IF($A56>E$5,"",OFFSET(E$54,0,-($A56-1))) -> 0 | F56: =IF($A56>F$5,"",OFFSET(F$54,0,-($A56-1))) -> 0 | G56: =IF($A56>G$5,"",OFFSET(G$54,0,-($A56-1))) -> 0 | H56: =IF($A56>H$5,"",OFFSET(H$54,0,-($A56-1))) -> 0 | I56: =IF($A56>I$5,"",OFFSET(I$54,0,-($A56-1))) -> 6115 | ... BI56: =IF($A56>BI$5,"",OFFSET(BI$54,0,-($A56-1))) -> 0
A57: 3 | B57: =IF($A57>B$5,"",OFFSET(B$54,0,-($A57-1))) | C57: =IF($A57>C$5,"",OFFSET(C$54,0,-($A57-1))) | D57: =IF($A57>D$5,"",OFFSET(D$54,0,-($A57-1))) -> 0 | E57: =IF($A57>E$5,"",OFFSET(E$54,0,-($A57-1))) -> 0 | F57: =IF($A57>F$5,"",OFFSET(F$54,0,-($A57-1))) -> 0 | G57: =IF($A57>G$5,"",OFFSET(G$54,0,-($A57-1))) -> 0 | H57: =IF($A57>H$5,"",OFFSET(H$54,0,-($A57-1))) -> 0 | I57: =IF($A57>I$5,"",OFFSET(I$54,0,-($A57-1))) -> 0 | ... BI57: =IF($A57>BI$5,"",OFFSET(BI$54,0,-($A57-1))) -> 0
A58: 4 | B58: =IF($A58>B$5,"",OFFSET(B$54,0,-($A58-1))) | C58: =IF($A58>C$5,"",OFFSET(C$54,0,-($A58-1))) | D58: =IF($A58>D$5,"",OFFSET(D$54,0,-($A58-1))) | E58: =IF($A58>E$5,"",OFFSET(E$54,0,-($A58-1))) -> 0 | F58: =IF($A58>F$5,"",OFFSET(F$54,0,-($A58-1))) -> 0 | G58: =IF($A58>G$5,"",OFFSET(G$54,0,-($A58-1))) -> 0 | H58: =IF($A58>H$5,"",OFFSET(H$54,0,-($A58-1))) -> 0 | I58: =IF($A58>I$5,"",OFFSET(I$54,0,-($A58-1))) -> 0 | ... BI58: =IF($A58>BI$5,"",OFFSET(BI$54,0,-($A58-1))) -> 0
A59: 5 | B59: =IF($A59>B$5,"",OFFSET(B$54,0,-($A59-1))) | C59: =IF($A59>C$5,"",OFFSET(C$54,0,-($A59-1))) | D59: =IF($A59>D$5,"",OFFSET(D$54,0,-($A59-1))) | E59: =IF($A59>E$5,"",OFFSET(E$54,0,-($A59-1))) | F59: =IF($A59>F$5,"",OFFSET(F$54,0,-($A59-1))) -> 0 | G59: =IF($A59>G$5,"",OFFSET(G$54,0,-($A59-1))) -> 0 | H59: =IF($A59>H$5,"",OFFSET(H$54,0,-($A59-1))) -> 0 | I59: =IF($A59>I$5,"",OFFSET(I$54,0,-($A59-1))) -> 0 | ... BI59: =IF($A59>BI$5,"",OFFSET(BI$54,0,-($A59-1))) -> 0
A60: 6 | B60: =IF($A60>B$5,"",OFFSET(B$54,0,-($A60-1))) | C60: =IF($A60>C$5,"",OFFSET(C$54,0,-($A60-1))) | D60: =IF($A60>D$5,"",OFFSET(D$54,0,-($A60-1))) | E60: =IF($A60>E$5,"",OFFSET(E$54,0,-($A60-1))) | F60: =IF($A60>F$5,"",OFFSET(F$54,0,-($A60-1))) | G60: =IF($A60>G$5,"",OFFSET(G$54,0,-($A60-1))) -> 0 | H60: =IF($A60>H$5,"",OFFSET(H$54,0,-($A60-1))) -> 0 | I60: =IF($A60>I$5,"",OFFSET(I$54,0,-($A60-1))) -> 0 | ... BI60: =IF($A60>BI$5,"",OFFSET(BI$54,0,-($A60-1))) -> 0
A61: 7 | B61: =IF($A61>B$5,"",OFFSET(B$54,0,-($A61-1))) | C61: =IF($A61>C$5,"",OFFSET(C$54,0,-($A61-1))) | D61: =IF($A61>D$5,"",OFFSET(D$54,0,-($A61-1))) | E61: =IF($A61>E$5,"",OFFSET(E$54,0,-($A61-1))) | F61: =IF($A61>F$5,"",OFFSET(F$54,0,-($A61-1))) | G61: =IF($A61>G$5,"",OFFSET(G$54,0,-($A61-1))) | H61: =IF($A61>H$5,"",OFFSET(H$54,0,-($A61-1))) -> 0 | I61: =IF($A61>I$5,"",OFFSET(I$54,0,-($A61-1))) -> 0 | ... BI61: =IF($A61>BI$5,"",OFFSET(BI$54,0,-($A61-1))) -> 0
A62: 8 | B62: =IF($A62>B$5,"",OFFSET(B$54,0,-($A62-1))) | C62: =IF($A62>C$5,"",OFFSET(C$54,0,-($A62-1))) | D62: =IF($A62>D$5,"",OFFSET(D$54,0,-($A62-1))) | E62: =IF($A62>E$5,"",OFFSET(E$54,0,-($A62-1))) | F62: =IF($A62>F$5,"",OFFSET(F$54,0,-($A62-1))) | G62: =IF($A62>G$5,"",OFFSET(G$54,0,-($A62-1))) | H62: =IF($A62>H$5,"",OFFSET(H$54,0,-($A62-1))) | I62: =IF($A62>I$5,"",OFFSET(I$54,0,-($A62-1))) -> 0 | ... BI62: =IF($A62>BI$5,"",OFFSET(BI$54,0,-($A62-1))) -> 0
A63: 9 | B63: =IF($A63>B$5,"",OFFSET(B$54,0,-($A63-1))) | C63: =IF($A63>C$5,"",OFFSET(C$54,0,-($A63-1))) | D63: =IF($A63>D$5,"",OFFSET(D$54,0,-($A63-1))) | E63: =IF($A63>E$5,"",OFFSET(E$54,0,-($A63-1))) | F63: =IF($A63>F$5,"",OFFSET(F$54,0,-($A63-1))) | G63: =IF($A63>G$5,"",OFFSET(G$54,0,-($A63-1))) | H63: =IF($A63>H$5,"",OFFSET(H$54,0,-($A63-1))) | I63: =IF($A63>I$5,"",OFFSET(I$54,0,-($A63-1))) | ... BI63: =IF($A63>BI$5,"",OFFSET(BI$54,0,-($A63-1))) -> 0
A64: 10 | B64: =IF($A64>B$5,"",OFFSET(B$54,0,-($A64-1))) | C64: =IF($A64>C$5,"",OFFSET(C$54,0,-($A64-1))) | D64: =IF($A64>D$5,"",OFFSET(D$54,0,-($A64-1))) | E64: =IF($A64>E$5,"",OFFSET(E$54,0,-($A64-1))) | F64: =IF($A64>F$5,"",OFFSET(F$54,0,-($A64-1))) | G64: =IF($A64>G$5,"",OFFSET(G$54,0,-($A64-1))) | H64: =IF($A64>H$5,"",OFFSET(H$54,0,-($A64-1))) | I64: =IF($A64>I$5,"",OFFSET(I$54,0,-($A64-1))) | ... BI64: =IF($A64>BI$5,"",OFFSET(BI$54,0,-($A64-1))) -> 0
A65: 11 | B65: =IF($A65>B$5,"",OFFSET(B$54,0,-($A65-1))) | C65: =IF($A65>C$5,"",OFFSET(C$54,0,-($A65-1))) | D65: =IF($A65>D$5,"",OFFSET(D$54,0,-($A65-1))) | E65: =IF($A65>E$5,"",OFFSET(E$54,0,-($A65-1))) | F65: =IF($A65>F$5,"",OFFSET(F$54,0,-($A65-1))) | G65: =IF($A65>G$5,"",OFFSET(G$54,0,-($A65-1))) | H65: =IF($A65>H$5,"",OFFSET(H$54,0,-($A65-1))) | I65: =IF($A65>I$5,"",OFFSET(I$54,0,-($A65-1))) | ... BI65: =IF($A65>BI$5,"",OFFSET(BI$54,0,-($A65-1))) -> 0
A66: 12 | B66: =IF($A66>B$5,"",OFFSET(B$54,0,-($A66-1))) | C66: =IF($A66>C$5,"",OFFSET(C$54,0,-($A66-1))) | D66: =IF($A66>D$5,"",OFFSET(D$54,0,-($A66-1))) | E66: =IF($A66>E$5,"",OFFSET(E$54,0,-($A66-1))) | F66: =IF($A66>F$5,"",OFFSET(F$54,0,-($A66-1))) | G66: =IF($A66>G$5,"",OFFSET(G$54,0,-($A66-1))) | H66: =IF($A66>H$5,"",OFFSET(H$54,0,-($A66-1))) | I66: =IF($A66>I$5,"",OFFSET(I$54,0,-($A66-1))) | ... BI66: =IF($A66>BI$5,"",OFFSET(BI$54,0,-($A66-1))) -> 0
... A114: 60 | B114: =IF($A114>B$5,"",OFFSET(B$54,0,-($A114-1))) | C114: =IF($A114>C$5,"",OFFSET(C$54,0,-($A114-1))) | D114: =IF($A114>D$5,"",OFFSET(D$54,0,-($A114-1))) | E114: =IF($A114>E$5,"",OFFSET(E$54,0,-($A114-1))) | F114: =IF($A114>F$5,"",OFFSET(F$54,0,-($A114-1))) | G114: =IF($A114>G$5,"",OFFSET(G$54,0,-($A114-1))) | H114: =IF($A114>H$5,"",OFFSET(H$54,0,-($A114-1))) | I114: =IF($A114>I$5,"",OFFSET(I$54,0,-($A114-1))) | ... BI114: =IF($A114>BI$5,"",OFFSET(BI$54,0,-($A114-1))) -> 0

Sheet Sheet1
