Workbook
Name __S1: {"Book1"}
Name __S1: {"Book1"}
Name __S1: {"Book1"}
Name _a1: {"'Sheet1'!$L$16"}
Name _a1: {"'Sheet1'!$L$16"}
Name _a1: {"'Sheet1'!$L$16"}
Name _S1: {"Book1"}
Name _S1: {"Book1"}
Name _S1: {"Book1"}
Name Ă: #REF!
Name Ạ196: #REF!
Name â259: #REF!
Name â259: #REF!
Name â312: #REF!
Name â312: #REF!
Name Acquisition_PlanA: #REF!
Name Acquisition_PlanB: #REF!
Name Actual: (PeriodInActual*(#REF!>0))*PeriodInPlan
Name Actual: (PeriodInActual*(#REF!>0))*PeriodInPlan
Name ActualBeyond: PeriodInActual*(#REF!>0)
Name ActualBeyond: PeriodInActual*(#REF!>0)
Name adf: #REF!
Name adf: #REF!
Name adf: #REF!
Name AdvIncQ12020: #REF!
Name AdvIncQ12020: #REF!
Name AdvIncQ12021: #REF!
Name AdvIncQ12021: #REF!
Name AdvIncQ12022: #REF!
Name AdvIncQ12022: #REF!
Name AdvIncQ12023: #REF!
Name AdvIncQ12023: #REF!
Name AdvIncQ12024: #REF!
Name AdvIncQ12024: #REF!
Name AdvIncQ22020: #REF!
Name AdvIncQ22020: #REF!
Name AdvIncQ22021: #REF!
Name AdvIncQ22021: #REF!
Name AdvIncQ22022: #REF!
Name AdvIncQ22022: #REF!
Name AdvIncQ22023: #REF!
Name AdvIncQ22023: #REF!
Name AdvIncQ22024: #REF!
Name AdvIncQ22024: #REF!
Name AdvIncQ32020: #REF!
Name AdvIncQ32020: #REF!
Name AdvIncQ32021: #REF!
Name AdvIncQ32021: #REF!
Name AdvIncQ32022: #REF!
Name AdvIncQ32022: #REF!
Name AdvIncQ32023: #REF!
Name AdvIncQ32023: #REF!
Name AdvIncQ32024: #REF!
Name AdvIncQ32024: #REF!
Name AdvIncQ42020: #REF!
Name AdvIncQ42020: #REF!
Name AdvIncQ42021: #REF!
Name AdvIncQ42021: #REF!
Name AdvIncQ42022: #REF!
Name AdvIncQ42022: #REF!

Sheet NOTE
A1: SAP MODEL - PAYLATER
N2: KHN | O2: v10 | P2: 20251201
B3: 1. Notes and disclaimer
C4: a. Giới thiệu về SAP
D5: - SAP: Single Account Profitability (Hiệu quả sản phẩm trên từng đơn vị sản phẩm)
D6: - Model SAP được sử dụng như 1 mô hình dự đoán hiệu quả vòng đời của sản phẩm.
D7: - Do sự phức tạp của sản phẩm, các hệ thống vận hành (hệ thống hạch kế toán, hệ thống quản trị rủi ro, hệ thống quản trị…), hành vi người sử dụng hành vi người sử dụng, model chỉ có thể mô phỏng tương đối trung bình vòng đời của sản phẩm.
D8: - Mô hình được tính toán dựa vào các yếu tố đầu vào xác định tại thời điểm, do đó kết quả của mô hình có thể có sự khác biệt so với thực tế vận hành sản phẩm.
D9: - Mô hình SAP Paylater tính hiệu quả của 1 thẻ mở và được cutoff tối đa tại thời điểm 5 năm ( 60 tháng) kể từ ngày bắt đầu sản phẩm
E10: - Trường hợp sử dụng phương pháp tính dự phòng VAS, cần ghi nhận thêm chi phí dự phòng năm thứ 6 liên quan tới hiệu quả sản phẩm thẻ 5 năm.
E11: - Trường hợp sử dụng phương pháp tính dự phòng VAS, cần ghi nhận thêm chi phí dự phòng năm thứ 4 liên quan tới hiệu quả sản phẩm thẻ 3 năm.
C13: b. Giới thiệu về PnL
D14: - Trong file tính này, Profit & Lost (PnL) được dự phóng từ trung bình cộng kết quả kinh doanh trên từng sản phẩm (SAP) với yếu tố "sale plan" (số thẻ mở mới) qua từng tháng, do đó có thể khác biệt so với kết quả thực tế vận hành.
D15: - Dòng tiền thực tế qua từng tháng có thể khác biệt với mô hình tính toán do nhiều yếu tố tác động bên ngoài thay đổi, do đó, vui lòng chỉ sử dụng mô hình cho mục đích tham khảo.
D16: - Cho mục đích tính dự phòng dòng tiền ngắn và trung hạn, mô hình PnL được cutoff tại thời điểm 5 năm (60 tháng) kể từ ngày bắt đầu khởi chạy sản phẩm đầu tiên.
B18: 2. Instruction
D19: - Dành cho người sử dụng
E20: - Chỉ chỉnh sửa vào các ô màu vàng
E21: - 2 sheets "SAP_Leadsheet" và "Sale plan&PL" cung cấp yếu tố đầu vào và đầu ra để tính toán mô hình SAP cũng như PnL.
F22: - Sheet SAP_Leadsheet được cấu trúc 2 phần, bên trái là các yếu tố đầu vào (input) và bên phải là kết quả dự đoán (output). Đơn vị sử dụng tại bảng tính là triệu VND (mVND) và phần trăm (%)
F23: - Sheet "Sale plan & PL" được cấu trúc 2 phần, bên trên là sale plan và bên dưới là kết quả PnL
E24: - 2 sheets "SAP_Spreadsheet" và "PL projection speadsheet" là các file tính toán cho 2 sheet "SAP_Leadsheet", "Sales plan & PL"
F25: - 2 sheets được cấu trúc từ trên xuống dưới theo thứ tự tính toán mô phỏng để đưa ra kết quả kinh doanh cuối cùng
F26: - 2 sheets đã được tạm khóa. Trường hợp cần mở khóa, điều chỉnh các yếu tố, vui lòng liên hệ với nhóm vận hành để được hỗ trợ.
D28: - Dành riêng cho người vận hành, hiệu chỉnh
E29: - Cần cẩn trọng khi điều chỉnh ở các file "speadsheet" vì 1 khi sai lệch rất khó tìm ra lỗi (VD: sửa nhầm ô, link nhầm vị trí,…)
B32: 3. Legend
C34: REVENUE INPUT
C36: Card Status
D37: Activate at beginning | E37: Tỉ lệ active thẻ tại thời điểm tháng 1 | G37: Tỉ lệ active được tính là khách hàng có spending và/hoặc có outstanding balance
D38: Average attrition rate | E38: Tỉ lệ giảm active qua từng thàng | G38: Lấy trung bình tỉ lệ giảm active thẻ của các tháng (tính theo cohort)
C40: Term of using
D41: Tenor | E41: Thời hạn tài khoản
D42: Due date | E42: Ngày tới thời hạn miễn lãi
D43: Free-interest period | E43: Thời gian được miễn lãi (VD 45-55 ngày)
C45: Usage Status
D46: Spd / active card | E46: Tổng chi tiêu tiêu tháng/số thẻ active
C48: Payment status
D49: Port Revolving rate | E49: Tỉ lệ chuyển đổi dư nợ (được tính là %/ANR tháng trước)
D50: Repayment rate | E50: Tỉ lệ thanh toán dư nợ (được tính %/ANR tháng trước)
C52: Pricing
D53: CII rate | E53: Chi phí lãi vay (annually) | G53: Lấy trung bình tỉ lãi của rút tiền và chi tiêu
D54: COF rate | E54: Chi phí vốn (annually) | G54: Lấy theo BRD
C56: Customer fee
D57: Annual fee | E57: Phí thường niên | G57: Lấy trung bình tỉ lệ các thẻ
D58: Annual Fee waiver | E58: Tỉ lệ miễn phí thường niên (trừ năm 1)
D59: Monthly fee | E59: Phí hàng tháng (subcription fee,…)
D60: Issuance fee | E60: Phí mở thẻ mới
D61: Termination fee | E61: Phí đóng thẻ
D62: Late payment rate | E62: Phí chậm trả
D63: %Latepayment collected | E63: Tỉ lệ thu hồi chậm trả
D64: Min due fee | E64: Phí nếu min< trả phí+gốc < phí gốc cần thu
C66: EMI
D67: EMI Penetration | E67: Tỉ lệ chuyển đổi trả góp/spending trong tháng
D68: Average tenor | E68: Thời hạn chuyển đổi trung bình
D69: Initial fee | E69: Phí chuyển đổi trung bình/tháng
C78: COST INPUT
C79: Inflation rate | E79: Tỉ lệ dự kiến tăng chi phí qua các năm
C80: Sales & Marketing
D81: Lead acquisition | E81: Chi phí leadgen trả cho đối tác
D82: Sharing TOI+RISKDPD90+ | E82: Chi phí chia sẻ doanh thu chi phí rủi ro cho đối tác | G82: Auto mode
D83: Sharing NII | E83: Chia sẻ thu nhập từ lãi cho đối tác | G83: Manual mode
D84: Sharing NFI | E84: Chia sẻ thu nhập từ phí cho đối tác | G84: Manual mode
D85: Sharing Risk DPD 90+ | E85: Chia sẻ thu nhập từ chi phí rủi ro | G85: Manual mode
D87: Marketing cost for acquisition | E87: Chi phí marketing cho thẻ mở
D88: Marketing cost for usage | E88: Chi phí promotion hàng tháng cho thẻ hoạt động
C90: UW & Disbursal cost
D91: Underwriting cost | E91: Chi phí underwriting cost/thẻ mở | G91: Chi phí bao gồm (PBC, KLP, CIC,…)
D92: DOP cost | E92: Chi phí luồng DOP | G92: Bao gồm SMS,…
D93: Approval rate | E93: Tỉ lệ chấp thuận mở thẻ | G93: Tỉ lệ số thẻ được chấp thuận/số thẻ vào luồng LOS
D94: Opening rate | E94: Tỉ lệ mở thẻ | G94: Tỉ lệ số thẻ mở /số thẻ được chấp thuận mở
D95: Opening cost | E95: Chi phí mở thẻ | G95: Bao gồm các chi phí hợp đồng, SMS khi mở thẻ
D96: Credit Support | E96: Chi phí khác( hiện tại chưa có)
C98: Collection & AMC | E98: Chi phí thu hồi nợ/số thẻ activated | G98: Hiện tại VPB đang chỉ phân bổ chi phí GB (B0-B3) cho CAKE, chưa bao gồm BB( B4+)
C100: After-sales services
D101: SMS | E101: Chi phí tin nhắn tháng
D102: x
C104: Overheads
D105: SU_HR direct | E105: Chi phí nhân sự trực tiếp phân bổ | G105: Lấy theo trung bình năm
D106: SU_HR indirect | E106: Chi phí nhân sự hỗ trợ phân bổ | G106: Lấy theo trung bình năm
D107: SU_IT | E107: Chi phí IT phân bổ | G107: Lấy theo trung bình năm
D108: SU_Others | E108: Các chi phí khác phân bổ | G108: Lấy theo trung bình năm
C110: RISK INPUT
C112: Recovery rate | E112: Tỉ lệ thu hồi nợ sau WO | G112: Hiện tại chưa đủ dữ liệu tính nên để =0
C114: Provision rate
D115: Avg NF | E115: Netflow- Tỉ lệ chuyển nợ
D116: PD | E116: Percentage of debt (tỉ lệ vỡ nợ)
D117: Pro. rate | E117: Tỉ lệ vỡ nợ đã điều chỉnh thu hồi nợ
B122: VAS | D122: DPD180+
B123: IFRS | D123: DPD360+
B147: DPD360+ | E147: IFRS | F147: EMI
B148: DPD180+ | E148: VAS | F148: non-EMI

Sheet DATA
B1: =C1&"_"&D1 -> All_Q1 | C1: =SAP_Leadsheet!C8 -> All | D1: =SAP_Leadsheet!C11 -> Q1
B2: Mapping | C2: Value | F2: All_Q1 | G2: MWG_Q1 | H2: VNPAY_Q1 | I2: BE_Q1 | J2: VDS_Q1
A3: Activate at beginning | B3: Active at beginning | C3: =INDEX($E$44:$AJ$53,MATCH($B$1,$E$44:$E$53,0),MATCH($B3,$E$44:$AJ$44,0)) -> 0.6392418 | E3: Spending | F3: =INDEX($E$44:$AJ$53,MATCH(F$2,$E$44:$E$53,0),MATCH($E3,$E$44:$AJ$44,0)) -> 1.0580627 | G3: =INDEX($E$44:$AJ$53,MATCH(G$2,$E$44:$E$53,0),MATCH($E3,$E$44:$AJ$44,0)) -> 1.6779288 | H3: =INDEX($E$44:$AJ$53,MATCH(H$2,$E$44:$E$53,0),MATCH($E3,$E$44:$AJ$44,0)) -> 0.9657573 | I3: =INDEX($E$44:$AJ$53,MATCH(I$2,$E$44:$E$53,0),MATCH($E3,$E$44:$AJ$44,0)) -> 0.43001421 | J3: =INDEX($E$44:$AJ$53,MATCH(J$2,$E$44:$E$53,0),MATCH($E3,$E$44:$AJ$44,0)) -> 0.52334755
A4: Spd / activate card | B4: Spending | C4: =INDEX($E$44:$AJ$53,MATCH($B$1,$E$44:$E$53,0),MATCH($B4,$E$44:$AJ$44,0)) -> 1.0580627 | E4: IR | F4: =INDEX($E$44:$AJ$53,MATCH(F$2,$E$44:$E$53,0),MATCH($E4,$E$44:$AJ$44,0)) -> 0.47795381 | G4: =INDEX($E$44:$AJ$53,MATCH(G$2,$E$44:$E$53,0),MATCH($E4,$E$44:$AJ$44,0)) -> 0.55 | H4: =INDEX($E$44:$AJ$53,MATCH(H$2,$E$44:$E$53,0),MATCH($E4,$E$44:$AJ$44,0)) -> 0.39 | I4: =INDEX($E$44:$AJ$53,MATCH(I$2,$E$44:$E$53,0),MATCH($E4,$E$44:$AJ$44,0)) -> 0.4 | J4: =INDEX($E$44:$AJ$53,MATCH(J$2,$E$44:$E$53,0),MATCH($E4,$E$44:$AJ$44,0)) -> 0.39
A5: Port Revolving rate | B5: % revolving | C5: =INDEX($E$44:$AJ$53,MATCH($B$1,$E$44:$E$53,0),MATCH($B5,$E$44:$AJ$44,0)) -> 0.69849829 | E5: COF | F5: =INDEX($E$44:$AJ$53,MATCH(F$2,$E$44:$E$53,0),MATCH($E5,$E$44:$AJ$44,0)) -> 0.069938802 | G5: =INDEX($E$44:$AJ$53,MATCH(G$2,$E$44:$E$53,0),MATCH($E5,$E$44:$AJ$44,0)) -> 0.069920144 | H5: =INDEX($E$44:$AJ$53,MATCH(H$2,$E$44:$E$53,0),MATCH($E5,$E$44:$AJ$44,0)) -> 0.069959036 | I5: =INDEX($E$44:$AJ$53,MATCH(I$2,$E$44:$E$53,0),MATCH($E5,$E$44:$AJ$44,0)) -> 0.06995507 | J5: =INDEX($E$44:$AJ$53,MATCH(J$2,$E$44:$E$53,0),MATCH($E5,$E$44:$AJ$44,0)) -> 0.069963269
A6: Payment rate | B6: % repayment | C6: =INDEX($E$44:$AJ$53,MATCH($B$1,$E$44:$E$53,0),MATCH($B6,$E$44:$AJ$44,0)) -> 0.36991535 | E6: Monthly fee (Subscription fee) | F6: =INDEX($E$44:$AJ$53,MATCH(F$2,$E$44:$E$53,0),MATCH($E6,$E$44:$AJ$44,0)) -> 0.0275 | G6: =INDEX($E$44:$AJ$53,MATCH(G$2,$E$44:$E$53,0),MATCH($E6,$E$44:$AJ$44,0)) -> 0.02 | H6: =INDEX($E$44:$AJ$53,MATCH(H$2,$E$44:$E$53,0),MATCH($E6,$E$44:$AJ$44,0)) -> 0.03 | I6: =INDEX($E$44:$AJ$53,MATCH(I$2,$E$44:$E$53,0),MATCH($E6,$E$44:$AJ$44,0)) -> 0.03 | J6: =INDEX($E$44:$AJ$53,MATCH(J$2,$E$44:$E$53,0),MATCH($E6,$E$44:$AJ$44,0)) -> 0.03
A7: IR | B7: IR | C7: =INDEX($E$44:$AJ$53,MATCH($B$1,$E$44:$E$53,0),MATCH($B7,$E$44:$AJ$44,0)) -> 0.47795381 | E7: % revolving | F7: =INDEX($E$44:$AJ$53,MATCH(F$2,$E$44:$E$53,0),MATCH($E7,$E$44:$AJ$44,0)) -> 0.69849829 | G7: =INDEX($E$44:$AJ$53,MATCH(G$2,$E$44:$E$53,0),MATCH($E7,$E$44:$AJ$44,0)) -> 0.77837592 | H7: =INDEX($E$44:$AJ$53,MATCH(H$2,$E$44:$E$53,0),MATCH($E7,$E$44:$AJ$44,0)) -> 0.68524609 | I7: =INDEX($E$44:$AJ$53,MATCH(I$2,$E$44:$E$53,0),MATCH($E7,$E$44:$AJ$44,0)) -> 0.71313914 | J7: =INDEX($E$44:$AJ$53,MATCH(J$2,$E$44:$E$53,0),MATCH($E7,$E$44:$AJ$44,0)) -> 0.7232694
A8: COF | B8: COF | C8: =INDEX($E$44:$AJ$53,MATCH($B$1,$E$44:$E$53,0),MATCH($B8,$E$44:$AJ$44,0)) -> 0.069938802 | E8: Active at beginning | F8: =INDEX($E$44:$AJ$53,MATCH(F$2,$E$44:$E$53,0),MATCH($E8,$E$44:$AJ$44,0)) -> 0.6392418 | G8: =INDEX($E$44:$AJ$53,MATCH(G$2,$E$44:$E$53,0),MATCH($E8,$E$44:$AJ$44,0)) -> 0.73403333 | H8: =INDEX($E$44:$AJ$53,MATCH(H$2,$E$44:$E$53,0),MATCH($E8,$E$44:$AJ$44,0)) -> 0.67973333 | I8: =INDEX($E$44:$AJ$53,MATCH(I$2,$E$44:$E$53,0),MATCH($E8,$E$44:$AJ$44,0)) -> 0.76776667 | J8: =INDEX($E$44:$AJ$53,MATCH(J$2,$E$44:$E$53,0),MATCH($E8,$E$44:$AJ$44,0)) -> 0.51063333
A9: Monthly fee (Subscription fee) | B9: Monthly fee (Subscription fee) | C9: =INDEX($E$44:$AJ$53,MATCH($B$1,$E$44:$E$53,0),MATCH($B9,$E$44:$AJ$44,0)) -> 0.0275 | E9: Active Month 4 | F9: =F8-F18*3 -> 0.60615117 | G9: =G8-G18*3 -> 0.68223167 | H9: =H8-H18*3 -> 0.64317708 | I9: =I8-I18*3 -> 0.715925 | J9: =J8-J18*3 -> 0.49795833
A10: Late payment penalty (fee) | B10: Late payment penalty (fee) | C10: =INDEX($E$44:$AJ$53,MATCH($B$1,$E$44:$E$53,0),MATCH($B10,$E$44:$AJ$44,0)) -> 0.072785593 | E10: %Installment | F10: =SUM(F11:F13) -> 0.34727685 | G10: =SUM(G11:G13) -> 0.59915944 | H10: =SUM(H11:H13) -> 0.017235754 | I10: =SUM(I11:I13) -> 0.062170492 | J10: =SUM(J11:J13) -> 0
A11: Spending promotion | B11: Promotion | C11: =INDEX($E$44:$AJ$53,MATCH($B$1,$E$44:$E$53,0),MATCH($B11,$E$44:$AJ$44,0)) -> 0.0045099003 | E11: Subvention | F11: =INDEX($E$44:$AJ$53,MATCH(F$2,$E$44:$E$53,0),MATCH($E11,$E$44:$AJ$44,0)) -> 0.29616921 | G11: =INDEX($E$44:$AJ$53,MATCH(G$2,$E$44:$E$53,0),MATCH($E11,$E$44:$AJ$44,0)) -> 0.52936116 | H11: =INDEX($E$44:$AJ$53,MATCH(H$2,$E$44:$E$53,0),MATCH($E11,$E$44:$AJ$44,0)) -> 0 | I11: =INDEX($E$44:$AJ$53,MATCH(I$2,$E$44:$E$53,0),MATCH($E11,$E$44:$AJ$44,0)) -> 0 | J11: =INDEX($E$44:$AJ$53,MATCH(J$2,$E$44:$E$53,0),MATCH($E11,$E$44:$AJ$44,0)) -> 0
A12: Marketing cost | B12: MKT | C12: =INDEX($E$44:$AJ$53,MATCH($B$1,$E$44:$E$53,0),MATCH($B12,$E$44:$AJ$44,0)) -> 0 | E12: Monthly fee | F12: =INDEX($E$44:$AJ$53,MATCH(F$2,$E$44:$E$53,0),MATCH($E12,$E$44:$AJ$44,0)) -> 0.04851372 | G12: =INDEX($E$44:$AJ$53,MATCH(G$2,$E$44:$E$53,0),MATCH($E12,$E$44:$AJ$44,0)) -> 0.06671633 | H12: =INDEX($E$44:$AJ$53,MATCH(H$2,$E$44:$E$53,0),MATCH($E12,$E$44:$AJ$44,0)) -> 0.012915199 | I12: =INDEX($E$44:$AJ$53,MATCH(I$2,$E$44:$E$53,0),MATCH($E12,$E$44:$AJ$44,0)) -> 0.062170492 | J12: =INDEX($E$44:$AJ$53,MATCH(J$2,$E$44:$E$53,0),MATCH($E12,$E$44:$AJ$44,0)) -> 0
A13: Underwriting cost & Score | B13: UW | C13: =INDEX($E$44:$AJ$53,MATCH($B$1,$E$44:$E$53,0),MATCH($B13,$E$44:$AJ$44,0)) -> 0.065146706 | E13: No fee | F13: =INDEX($E$44:$AJ$53,MATCH(F$2,$E$44:$E$53,0),MATCH($E13,$E$44:$AJ$44,0)) -> 0.0025939226 | G13: =INDEX($E$44:$AJ$53,MATCH(G$2,$E$44:$E$53,0),MATCH($E13,$E$44:$AJ$44,0)) -> 0.0030819445 | H13: =INDEX($E$44:$AJ$53,MATCH(H$2,$E$44:$E$53,0),MATCH($E13,$E$44:$AJ$44,0)) -> 0.0043205554 | I13: =INDEX($E$44:$AJ$53,MATCH(I$2,$E$44:$E$53,0),MATCH($E13,$E$44:$AJ$44,0)) -> 0 | J13: =INDEX($E$44:$AJ$53,MATCH(J$2,$E$44:$E$53,0),MATCH($E13,$E$44:$AJ$44,0)) -> 0
A14: Approval rate | B14: Approval rate | C14: =INDEX($E$44:$AJ$53,MATCH($B$1,$E$44:$E$53,0),MATCH($B14,$E$44:$AJ$44,0)) -> 0.267
A15: Disbursement rate | B15: Disbursement rate | C15: =INDEX($E$44:$AJ$53,MATCH($B$1,$E$44:$E$53,0),MATCH($B15,$E$44:$AJ$44,0)) -> 0.795
A16: Disbursement cost | B16: Disburse cost | C16: =INDEX($E$44:$AJ$53,MATCH($B$1,$E$44:$E$53,0),MATCH($B16,$E$44:$AJ$44,0)) -> 0.0026777105
A17: Collections_all | B17: Collection | C17: =INDEX($E$44:$AJ$53,MATCH($B$1,$E$44:$E$53,0),MATCH($B17,$E$44:$AJ$44,0)) -> 0.0049936505 | E17: Attrition rate | F17: All_Q1 | G17: MWG_Q1 | H17: VNPAY_Q1 | I17: BE_Q1 | J17: VDS_Q1
A18: Email & SMS | B18: SMS | C18: =INDEX($E$44:$AJ$53,MATCH($B$1,$E$44:$E$53,0),MATCH($B18,$E$44:$AJ$44,0)) -> 0.0037145494 | E18: Year 1 | F18: =INDEX($E$44:$L$49,MATCH(F$17,$E$44:$E$49,0),MATCH($E18,$E$44:$L$44,0)) -> 0.011030208 | G18: =INDEX($E$44:$L$49,MATCH(G$17,$E$44:$E$49,0),MATCH($E18,$E$44:$L$44,0)) -> 0.017267222 | H18: =INDEX($E$44:$L$49,MATCH(H$17,$E$44:$E$49,0),MATCH($E18,$E$44:$L$44,0)) -> 0.012185417 | I18: =INDEX($E$44:$L$49,MATCH(I$17,$E$44:$E$49,0),MATCH($E18,$E$44:$L$44,0)) -> 0.017280556 | J18: =INDEX($E$44:$L$49,MATCH(J$17,$E$44:$E$49,0),MATCH($E18,$E$44:$L$44,0)) -> 0.004225
A19: Direct HR | B19: Direct HR cost | C19: =INDEX($AR$44:$AV$48,MATCH($B19,$AR$44:$AR$48,0),MATCH($D$1,$AR$44:$AV$44,0)) -> 0.002
A20: Indirect HR | B20: Indirect HR cost | C20: =INDEX($AR$44:$AV$48,MATCH($B20,$AR$44:$AR$48,0),MATCH($D$1,$AR$44:$AV$44,0)) -> 0.00063414273 | F20: All_Q1 | G20: MWG_Q1 | H20: VNPAY_Q1 | I20: BE_Q1 | J20: VDS_Q1
A21: IT | B21: Indirect system cost | C21: =INDEX($AR$44:$AV$48,MATCH($B21,$AR$44:$AR$48,0),MATCH($D$1,$AR$44:$AV$44,0)) -> 0.0007468595 | E21: B00 | F21: =SUMIFS($BG:$BG,$BA:$BA,$E21,$AY:$AY,F$20) -> 0.047889979 | G21: =SUMIFS($BG:$BG,$BA:$BA,$E21,$AY:$AY,G$20) -> 0.035199152 | H21: =SUMIFS($BG:$BG,$BA:$BA,$E21,$AY:$AY,H$20) -> 0.0496 | I21: =SUMIFS($BG:$BG,$BA:$BA,$E21,$AY:$AY,I$20) -> 0.0608 | J21: =SUMIFS($BG:$BG,$BA:$BA,$E21,$AY:$AY,J$20) -> 0.074
A22: Other supports | B22: Other indirect supporting cost | C22: =INDEX($AR$44:$AV$48,MATCH($B22,$AR$44:$AR$48,0),MATCH($D$1,$AR$44:$AV$44,0)) -> 0.00098977289 | E22: B01 | F22: =SUMIFS($BG:$BG,$BA:$BA,$E22,$AY:$AY,F$20) -> 0.85717022 | G22: =SUMIFS($BG:$BG,$BA:$BA,$E22,$AY:$AY,G$20) -> 0.82375771 | H22: =SUMIFS($BG:$BG,$BA:$BA,$E22,$AY:$AY,H$20) -> 0.878 | I22: =SUMIFS($BG:$BG,$BA:$BA,$E22,$AY:$AY,I$20) -> 0.874 | J22: =SUMIFS($BG:$BG,$BA:$BA,$E22,$AY:$AY,J$20) -> 0.81892316
A23: Sharing NII | B23: Sharing NII | C23: =INDEX($E$44:$AO$53,MATCH($B$1,$E$44:$E$53,0),MATCH($B23,$E$44:$AO$44,0)) -> 0.33230275 | E23: B02 | F23: =SUMIFS($BG:$BG,$BA:$BA,$E23,$AY:$AY,F$20) -> 0.94435758 | G23: =SUMIFS($BG:$BG,$BA:$BA,$E23,$AY:$AY,G$20) -> 0.95445681 | H23: =SUMIFS($BG:$BG,$BA:$BA,$E23,$AY:$AY,H$20) -> 0.96281673 | I23: =SUMIFS($BG:$BG,$BA:$BA,$E23,$AY:$AY,I$20) -> 0.936 | J23: =SUMIFS($BG:$BG,$BA:$BA,$E23,$AY:$AY,J$20) -> 0.92415678
A24: Sharing NFI | B24: Sharing NFI | C24: =INDEX($E$44:$AO$53,MATCH($B$1,$E$44:$E$53,0),MATCH($B24,$E$44:$AO$44,0)) -> 0.33230275 | E24: B03 | F24: =SUMIFS($BG:$BG,$BA:$BA,$E24,$AY:$AY,F$20) -> 0.96426366 | G24: =SUMIFS($BG:$BG,$BA:$BA,$E24,$AY:$AY,G$20) -> 0.96662103 | H24: =SUMIFS($BG:$BG,$BA:$BA,$E24,$AY:$AY,H$20) -> 0.98180702 | I24: =SUMIFS($BG:$BG,$BA:$BA,$E24,$AY:$AY,I$20) -> 0.95463697 | J24: =SUMIFS($BG:$BG,$BA:$BA,$E24,$AY:$AY,J$20) -> 0.95398963
A25: Sharing Risk DPD 90+ | B25: Sharing Risk DPD 90+ | C25: =INDEX($E$44:$AO$53,MATCH($B$1,$E$44:$E$53,0),MATCH($B25,$E$44:$AO$44,0)) -> 0.33230275 | E25: B04 | F25: =SUMIFS($BG:$BG,$BA:$BA,$E25,$AY:$AY,F$20) -> 0.98262623 | G25: =SUMIFS($BG:$BG,$BA:$BA,$E25,$AY:$AY,G$20) -> 0.9883535 | H25: =SUMIFS($BG:$BG,$BA:$BA,$E25,$AY:$AY,H$20) -> 0.98896246 | I25: =SUMIFS($BG:$BG,$BA:$BA,$E25,$AY:$AY,I$20) -> 0.96453427 | J25: =SUMIFS($BG:$BG,$BA:$BA,$E25,$AY:$AY,J$20) -> 0.98865468
A26: Sharing TOI +Risk DPD90+ | B26: Sharing TOI +Risk DPD90+ | C26: =INDEX($E$44:$AO$53,MATCH($B$1,$E$44:$E$53,0),MATCH($B26,$E$44:$AO$44,0)) -> 0
A27: Initial fee | B27: Initial fee | C27: =INDEX($E$44:$AO$53,MATCH($B$1,$E$44:$E$53,0),MATCH($B27,$E$44:$AO$44,0)) -> 0.031770112
A29: Average attrition rate
A30: Year 1 | B30: Year 2 | C30: Year 3 | D30: Year 4 | E30: Year 5
A31: =INDEX($E$44:$L$49,MATCH($B$1,$E$44:$E$49,0),MATCH(A$30,$E$44:$L$44,0)) -> 0.011030208 | B31: =INDEX($E$44:$L$49,MATCH($B$1,$E$44:$E$49,0),MATCH(B$30,$E$44:$L$44,0)) -> 0.0068777618 | C31: =INDEX($E$44:$L$49,MATCH($B$1,$E$44:$E$49,0),MATCH(C$30,$E$44:$L$44,0)) -> 0.0054648835 | D31: =INDEX($E$44:$L$49,MATCH($B$1,$E$44:$E$49,0),MATCH(D$30,$E$44:$L$44,0)) -> 0.0042795518 | E31: =INDEX($E$44:$L$49,MATCH($B$1,$E$44:$E$49,0),MATCH(E$30,$E$44:$L$44,0)) -> 0.003317893
B33: EMI Penetration | C33: Tenor | D33: Subvention fee | F33: Bucket | G33: 1 | H33: 2 | I33: 3 | J33: 4 | K33: 5
A34: Retail 0% Installment | B34: {=TRANSPOSE(_xlfn.XLOOKUP($B$1,E44:$E$49,AD44:AF49))} -> 0.29616921 | C34: {=TRANSPOSE(_xlfn.XLOOKUP($B$1,$E$44:$E$49,$AG$44:$AI$49))} -> 5 | D34: =_xlfn.XLOOKUP($B$1,$E$44:$E$49,$AJ$44:$AJ$49) -> 0.07017491 | F34: B00 | G34: =SUMIFS(BB:BB,$AY:$AY,$B$1,$BA:$BA,$F34) -> 0.072699894 | H34: =SUMIFS(BC:BC,$AY:$AY,$B$1,$BA:$BA,$F34) -> 0.0535 | I34: =SUMIFS(BD:BD,$AY:$AY,$B$1,$BA:$BA,$F34) -> 0.0415 | J34: =SUMIFS(BE:BE,$AY:$AY,$B$1,$BA:$BA,$F34) -> 0.0375 | K34: =SUMIFS(BF:BF,$AY:$AY,$B$1,$BA:$BA,$F34) -> 0.03425
A35: Retail monthly installment | B35: 0.04851372 | C35: 6 | F35: B01 | G35: =SUMIFS(BB:BB,$AY:$AY,$B$1,$BA:$BA,$F35) -> 0.90027608 | H35: =SUMIFS(BC:BC,$AY:$AY,$B$1,$BA:$BA,$F35) -> 0.878075 | I35: =SUMIFS(BD:BD,$AY:$AY,$B$1,$BA:$BA,$F35) -> 0.845 | J35: =SUMIFS(BE:BE,$AY:$AY,$B$1,$BA:$BA,$F35) -> 0.8325 | K35: =SUMIFS(BF:BF,$AY:$AY,$B$1,$BA:$BA,$F35) -> 0.83
A36: Cash installment | B36: 0.0025939226 | C36: 3 | F36: B02 | G36: =SUMIFS(BB:BB,$AY:$AY,$B$1,$BA:$BA,$F36) -> 0.96147117 | H36: =SUMIFS(BC:BC,$AY:$AY,$B$1,$BA:$BA,$F36) -> 0.94570418 | I36: =SUMIFS(BD:BD,$AY:$AY,$B$1,$BA:$BA,$F36) -> 0.93820418 | J36: =SUMIFS(BE:BE,$AY:$AY,$B$1,$BA:$BA,$F36) -> 0.93820418 | K36: =SUMIFS(BF:BF,$AY:$AY,$B$1,$BA:$BA,$F36) -> 0.93820418
F37: B03 | G37: =SUMIFS(BB:BB,$AY:$AY,$B$1,$BA:$BA,$F37) -> 0.97863629 | H37: =SUMIFS(BC:BC,$AY:$AY,$B$1,$BA:$BA,$F37) -> 0.96132675 | I37: =SUMIFS(BD:BD,$AY:$AY,$B$1,$BA:$BA,$F37) -> 0.96045175 | J37: =SUMIFS(BE:BE,$AY:$AY,$B$1,$BA:$BA,$F37) -> 0.96045175 | K37: =SUMIFS(BF:BF,$AY:$AY,$B$1,$BA:$BA,$F37) -> 0.96045175
F38: B04 | G38: =SUMIFS(BB:BB,$AY:$AY,$B$1,$BA:$BA,$F38) -> 0.98774368 | H38: =SUMIFS(BC:BC,$AY:$AY,$B$1,$BA:$BA,$F38) -> 0.97616561 | I38: =SUMIFS(BD:BD,$AY:$AY,$B$1,$BA:$BA,$F38) -> 0.97974061 | J38: =SUMIFS(BE:BE,$AY:$AY,$B$1,$BA:$BA,$F38) -> 0.97974061 | K38: =SUMIFS(BF:BF,$AY:$AY,$B$1,$BA:$BA,$F38) -> 0.98974061
F39: B05 | G39: =SUMIFS(BB:BB,$AY:$AY,$B$1,$BA:$BA,$F39) -> 0.99170021 | H39: =SUMIFS(BC:BC,$AY:$AY,$B$1,$BA:$BA,$F39) -> 0.98827646 | I39: =SUMIFS(BD:BD,$AY:$AY,$B$1,$BA:$BA,$F39) -> 0.99110146 | J39: =SUMIFS(BE:BE,$AY:$AY,$B$1,$BA:$BA,$F39) -> 0.99110146 | K39: =SUMIFS(BF:BF,$AY:$AY,$B$1,$BA:$BA,$F39) -> 0.99110146
F40: B06 | G40: =SUMIFS(BB:BB,$AY:$AY,$B$1,$BA:$BA,$F40) -> 0.99493965 | H40: =SUMIFS(BC:BC,$AY:$AY,$B$1,$BA:$BA,$F40) -> 0.99378871 | I40: =SUMIFS(BD:BD,$AY:$AY,$B$1,$BA:$BA,$F40) -> 0.99378871 | J40: =SUMIFS(BE:BE,$AY:$AY,$B$1,$BA:$BA,$F40) -> 0.99378871 | K40: =SUMIFS(BF:BF,$AY:$AY,$B$1,$BA:$BA,$F40) -> 0.99378871
H43: Average attrition rate | AD43: EMI Penetration | AG43: Tenor | BK43: Original
A44: Group | B44: Partner | C44: Product | D44: Sub Product | E44: Index | F44: Period | G44: Active at beginning | H44: Year 1 | I44: Year 2 | J44: Year 3 | K44: Year 4 | L44: Year 5 | M44: Approval rate | N44: Disbursement rate | O44: IR | P44: COF | Q44: Spending | R44: Monthly fee (Subscription fee) | S44: Late payment penalty (fee) | T44: MKT | U44: UW | V44: Collection | W44: SMS | X44: Disburse cost | Y44: Leadgen | Z44: Promotion | AA44: Sharing | AB44: % repayment | AC44: % revolving | AD44: Subvention | AE44: Monthly fee | AF44: No fee | AG44: Subvention | AH44: Monthly fee | AI44: No fee | AJ44: Subvention fee | AK44: Initial fee | AL44: Sharing NII | AM44: Sharing NFI | AN44: Sharing Risk DPD 90+ | AO44: Sharing TOI +Risk DPD90+ | AR44: Phân bổ | AS44: Q1 | AT44: Q2 | AU44: Q3 | AV44: Q4 | AX44: Channel | AY44: Index | AZ44: Period | BA44: Bucket | BB44: 1 | BC44: 2 | BD44: 3 | BE44: 4 | BF44: 5 | BG44: AVG | BK44: Channel | BL44: Index | BM44: Period | BN44: Bucket | BO44: 1 | BP44: 2 | BQ44: 3 | BR44: 4 | BS44: 5 | BT44: AVG
A45: PL | B45: BE | C45: Paylater | D45: Paylater | E45: =B45&"_"&F45 -> BE_Q1 | F45: Q1 | G45: 0.76776667 | H45: 0.017280556 | I45: 0.012 | J45: 0.01 | K45: 0.008 | L45: 0.005 | M45: 0.289 | N45: 0.798 | O45: 0.4 | P45: 0.06995507 | Q45: 0.43001421 | R45: 0.03 | S45: 0.05 | T45: 0 | U45: 0.031587183 | V45: 0.0035566425 | W45: 0.0047158861 | X45: 0.0027329979 | Y45: 0 | Z45: 0.021209464 | AA45: 0.5 | AB45: 0.32408372 | AC45: 0.71313914 | AD45: 0 | AE45: 0.062170492 | AF45: 0 | AH45: 2 | AK45: 0.04 | AL45: 0.5 | AM45: 0.5 | AN45: 0.5 | AR45: Direct HR cost | AS45: 0.002 | AX45: BE | AY45: =AX45&"_"&AZ45 -> BE_Q1 | AZ45: Q1 | BA45: B00 | BB45: 0.082 | BC45: 0.06 | BD45: 0.057 | BE45: 0.055 | BF45: 0.05 | BG45: =AVERAGE(BB45:BF45) -> 0.0608 | BK45: BE | BL45: =BK45&"_"&BM45 -> BE_Q1 | BM45: Q1 | BN45: B00 | BO45: 0.082 | BP45: 0.06 | BQ45: 0.057 | BR45: 0.055 | BS45: 0.05 | BT45: =AVERAGE(BO45:BS45) -> 0.0608
A46: PL | B46: MWG | C46: Paylater | D46: Paylater | E46: =B46&"_"&F46 -> MWG_Q1 | F46: Q1 | G46: 0.73403333 | H46: 0.017267222 | I46: 0.007 | J46: 0.005 | K46: 0.004 | L46: 0.003 | M46: 0.646 | N46: 0.802 | O46: 0.55 | P46: 0.069920144 | Q46: 1.6779288 | R46: 0.02 | S46: 0.1 | T46: 0 | U46: 0.072742931 | V46: 0.0056310126 | W46: 0.0020504448 | X46: 0.002639991 | Y46: 0 | Z46: 0.0028245387 | AA46: 0.35 | AB46: 0.57514072 | AC46: 0.77837592 | AD46: 0.52936116 | AE46: 0.06671633 | AF46: 0.0030819445 | AG46: 5 | AH46: 7 | AI46: 3 | AJ46: 0.07017491 | AK46: 0.0299 | AL46: 0.35 | AM46: 0.35 | AN46: 0.35 | AR46: Indirect HR cost | AS46: 0.00063414273 | AX46: BE | AY46: =AX46&"_"&AZ46 -> BE_Q1 | AZ46: Q1 | BA46: B01 | BB46: 0.92 | BC46: 0.9 | BD46: 0.85 | BE46: 0.85 | BF46: 0.85 | BG46: =AVERAGE(BB46:BF46) -> 0.874 | BK46: BE | BL46: =BK46&"_"&BM46 -> BE_Q1 | BM46: Q1 | BN46: B01 | BO46: 0.92 | BP46: 0.9 | BQ46: 0.85 | BR46: 0.85 | BS46: 0.85 | BT46: =AVERAGE(BO46:BS46) -> 0.874
A47: PL | B47: VDS | C47: Paylater | D47: Paylater | E47: =B47&"_"&F47 -> VDS_Q1 | F47: Q1 | G47: 0.51063333 | H47: 0.004225 | I47: 0.004 | J47: 0.003 | K47: 0.002 | L47: 0.002 | M47: 0.112 | N47: 0.675 | O47: 0.39 | P47: 0.069963269 | Q47: 0.52334755 | R47: 0.03 | S47: 0.05 | T47: 0 | U47: 0.1030759 | V47: 0.0060295903 | W47: 0.0026744216 | X47: 0.0027329061 | Y47: 0 | Z47: 0 | AA47: 0.5 | AB47: 0.29129734 | AC47: 0.7232694 | AL47: 0.5 | AM47: 0.5 | AN47: 0.5 | AR47: Indirect system cost | AS47: 0.0007468595 | AX47: BE | AY47: =AX47&"_"&AZ47 -> BE_Q1 | AZ47: Q1 | BA47: B02 | BB47: 0.97 | BC47: 0.95 | BD47: 0.92 | BE47: 0.92 | BF47: 0.92 | BG47: =AVERAGE(BB47:BF47) -> 0.936 | BK47: BE | BL47: =BK47&"_"&BM47 -> BE_Q1 | BM47: Q1 | BN47: B02 | BO47: 0.97 | BP47: 0.95 | BQ47: 0.92 | BR47: 0.92 | BS47: 0.92 | BT47: =AVERAGE(BO47:BS47) -> 0.936
A48: PL | B48: VNPAY | C48: Paylater | D48: Paylater | E48: =B48&"_"&F48 -> VNPAY_Q1 | F48: Q1 | G48: 0.67973333 | H48: 0.012185417 | I48: 0.008 | J48: 0.007 | K48: 0.006 | L48: 0.005 | M48: 0.137 | N48: 0.887 | O48: 0.39 | P48: 0.069959036 | Q48: 0.9657573 | R48: 0.03 | S48: 0.1 | T48: 0 | U48: 0.060273246 | V48: 0.0055755729 | W48: 0.0049103804 | X48: 0.0026710866 | Y48: 0 | Z48: 0 | AA48: 0.1 | AB48: 0.29339861 | AC48: 0.68524609 | AD48: 0 | AE48: 0.012915199 | AF48: 0.0043205554 | AG48: 0 | AH48: 8 | AI48: 3 | AK48: 0.03 | AL48: 0.1 | AM48: 0.1 | AN48: 0.1 | AR48: Other indirect supporting cost | AS48: 0.00098977289 | AX48: BE | AY48: =AX48&"_"&AZ48 -> BE_Q1 | AZ48: Q1 | BA48: B03 | BB48: 0.97318484 | BC48: 0.95 | BD48: 0.95 | BE48: 0.95 | BF48: 0.95 | BG48: =AVERAGE(BB48:BF48) -> 0.95463697 | BK48: BE | BL48: =BK48&"_"&BM48 -> BE_Q1 | BM48: Q1 | BN48: B03 | BO48: 0.97318484 | BP48: 0.95 | BQ48: 0.95 | BR48: 0.95 | BS48: 0.95 | BT48: =AVERAGE(BO48:BS48) -> 0.95463697
A49: PL | B49: All | C49: Paylater | D49: Paylater | E49: =B49&"_"&F49 -> All_Q1 | F49: Q1 | G49: 0.6392418 | H49: 0.011030208 | I49: 0.0068777618 | J49: 0.0054648835 | K49: 0.0042795518 | L49: 0.003317893 | M49: 0.267 | N49: 0.795 | O49: 0.47795381 | P49: 0.069938802 | Q49: 1.0580627 | R49: 0.0275 | S49: 0.072785593 | T49: 0 | U49: 0.065146706 | V49: 0.0049936505 | W49: 0.0037145494 | X49: 0.0026777105 | Y49: 0 | Z49: 0.0045099003 | AA49: 0.33230275 | AB49: 0.36991535 | AC49: 0.69849829 | AD49: 0.29616921 | AE49: 0.04851372 | AF49: 0.0025939226 | AG49: 5 | AH49: 6 | AI49: 3 | AJ49: 0.07017491 | AK49: 0.031770112 | AL49: 0.33230275 | AM49: 0.33230275 | AN49: 0.33230275 | AX49: BE | AY49: =AX49&"_"&AZ49 -> BE_Q1 | AZ49: Q1 | BA49: B04 | BB49: 0.98267137 | BC49: 0.95 | BD49: 0.95 | BE49: 0.95 | BF49: 0.99 | BG49: =AVERAGE(BB49:BF49) -> 0.96453427 | BK49: BE | BL49: =BK49&"_"&BM49 -> BE_Q1 | BM49: Q1 | BN49: B04 | BO49: 0.98267137 | BP49: 0.95 | BQ49: 0.95 | BR49: 0.95 | BS49: 0.99 | BT49: =AVERAGE(BO49:BS49) -> 0.96453427
AX50: BE | AY50: =AX50&"_"&AZ50 -> BE_Q1 | AZ50: Q1 | BA50: B05 | BB50: 0.9898464 | BC50: 0.9853 | BD50: 0.99 | BE50: 0.99 | BF50: 0.99 | BG50: =AVERAGE(BB50:BF50) -> 0.98902928 | BK50: BE | BL50: =BK50&"_"&BM50 -> BE_Q1 | BM50: Q1 | BN50: B05 | BO50: 0.9898464 | BP50: 0.9853 | BQ50: 0.99 | BR50: 0.99 | BS50: 0.99 | BT50: =AVERAGE(BO50:BS50) -> 0.98902928
AX51: BE | AY51: =AX51&"_"&AZ51 -> BE_Q1 | AZ51: Q1 | BA51: B06 | BB51: 0.9999 | BC51: 0.9999 | BD51: 0.9999 | BE51: 0.9999 | BF51: 0.9999 | BG51: =AVERAGE(BB51:BF51) -> 0.9999 | BK51: BE | BL51: =BK51&"_"&BM51 -> BE_Q1 | BM51: Q1 | BN51: B06 | BO51: 0.9999 | BP51: 0.9999 | BQ51: 0.9999 | BR51: 0.9999 | BS51: 0.9999 | BT51: =AVERAGE(BO51:BS51) -> 0.9999
AX52: MWG | AY52: =AX52&"_"&AZ52 -> MWG_Q1 | AZ52: Q1 | BA52: B00 | BB52: 0.050995762 | BC52: 0.036 | BD52: 0.032 | BE52: 0.03 | BF52: 0.027 | BG52: =AVERAGE(BB52:BF52) -> 0.035199152 | BK52: MWG | BL52: =BK52&"_"&BM52 -> MWG_Q1 | BM52: Q1 | BN52: B00 | BO52: 0.054799576 | BP52: 0.048 | BQ52: 0.042 | BR52: 0.037 | BS52: 0.034 | BT52: =AVERAGE(BO52:BS52) -> 0.043159915
AX53: MWG | AY53: =AX53&"_"&AZ53 -> MWG_Q1 | AZ53: Q1 | BA53: B01 | BB53: 0.90878854 | BC53: 0.88 | BD53: 0.8 | BE53: 0.78 | BF53: 0.75 | BG53: =AVERAGE(BB53:BF53) -> 0.82375771 | BK53: MWG | BL53: =BK53&"_"&BM53 -> MWG_Q1 | BM53: Q1 | BN53: B01 | BO53: 0.90878854 | BP53: 0.88 | BQ53: 0.85 | BR53: 0.83 | BS53: 0.82 | BT53: =AVERAGE(BO53:BS53) -> 0.85775771
AX54: MWG | AY54: =AX54&"_"&AZ54 -> MWG_Q1 | AZ54: Q1 | BA54: B02 | BB54: 0.97228405 | BC54: 0.95 | BD54: 0.95 | BE54: 0.95 | BF54: 0.95 | BG54: =AVERAGE(BB54:BF54) -> 0.95445681 | BK54: MWG | BL54: =BK54&"_"&BM54 -> MWG_Q1 | BM54: Q1 | BN54: B02 | BO54: 0.97228405 | BP54: 0.95 | BQ54: 0.95 | BR54: 0.95 | BS54: 0.95 | BT54: =AVERAGE(BO54:BS54) -> 0.95445681
AX55: MWG | AY55: =AX55&"_"&AZ55 -> MWG_Q1 | AZ55: Q1 | BA55: B03 | BB55: 0.98960514 | BC55: 0.9635 | BD55: 0.96 | BE55: 0.96 | BF55: 0.96 | BG55: =AVERAGE(BB55:BF55) -> 0.96662103 | BK55: MWG | BL55: =BK55&"_"&BM55 -> MWG_Q1 | BM55: Q1 | BN55: B03 | BO55: 0.98960514 | BP55: 0.9635 | BQ55: 0.96 | BR55: 0.96 | BS55: 0.96 | BT55: =AVERAGE(BO55:BS55) -> 0.96662103
AX56: MWG | AY56: =AX56&"_"&AZ56 -> MWG_Q1 | AZ56: Q1 | BA56: B04 | BB56: 0.99606748 | BC56: 0.9757 | BD56: 0.99 | BE56: 0.99 | BF56: 0.99 | BG56: =AVERAGE(BB56:BF56) -> 0.9883535 | BK56: MWG | BL56: =BK56&"_"&BM56 -> MWG_Q1 | BM56: Q1 | BN56: B04 | BO56: 0.99606748 | BP56: 0.9757 | BQ56: 0.99 | BR56: 0.99 | BS56: 0.99 | BT56: =AVERAGE(BO56:BS56) -> 0.9883535
AX57: MWG | AY57: =AX57&"_"&AZ57 -> MWG_Q1 | AZ57: Q1 | BA57: B05 | BB57: 0.99281529 | BC57: 0.9834 | BD57: 0.99 | BE57: 0.99 | BF57: 0.99 | BG57: =AVERAGE(BB57:BF57) -> 0.98924306 | BK57: MWG | BL57: =BK57&"_"&BM57 -> MWG_Q1 | BM57: Q1 | BN57: B05 | BO57: 0.99281529 | BP57: 0.9834 | BQ57: 0.99 | BR57: 0.99 | BS57: 0.99 | BT57: =AVERAGE(BO57:BS57) -> 0.98924306
AX58: MWG | AY58: =AX58&"_"&AZ58 -> MWG_Q1 | AZ58: Q1 | BA58: B06 | BB58: 0.99 | BC58: 0.99 | BD58: 0.99 | BE58: 0.99 | BF58: 0.99 | BG58: =AVERAGE(BB58:BF58) -> 0.99 | BK58: MWG | BL58: =BK58&"_"&BM58 -> MWG_Q1 | BM58: Q1 | BN58: B06 | BO58: 0.99 | BP58: 0.99 | BQ58: 0.99 | BR58: 0.99 | BS58: 0.99 | BT58: =AVERAGE(BO58:BS58) -> 0.99
AX59: VDS | AY59: =AX59&"_"&AZ59 -> VDS_Q1 | AZ59: Q1 | BA59: B00 | BB59: 0.089 | BC59: 0.076 | BD59: 0.072 | BE59: 0.068 | BF59: 0.065 | BG59: =AVERAGE(BB59:BF59) -> 0.074 | BK59: VDS | BL59: =BK59&"_"&BM59 -> VDS_Q1 | BM59: Q1 | BN59: B00 | BO59: 0.089 | BP59: 0.076 | BQ59: 0.072 | BR59: 0.068 | BS59: 0.065 | BT59: =AVERAGE(BO59:BS59) -> 0.074
AX60: VDS | AY60: =AX60&"_"&AZ60 -> VDS_Q1 | AZ60: Q1 | BA60: B01 | BB60: 0.85231579 | BC60: 0.8323 | BD60: 0.81 | BE60: 0.8 | BF60: 0.8 | BG60: =AVERAGE(BB60:BF60) -> 0.81892316 | BK60: VDS | BL60: =BK60&"_"&BM60 -> VDS_Q1 | BM60: Q1 | BN60: B01 | BO60: 0.85231579 | BP60: 0.8323 | BQ60: 0.81 | BR60: 0.8 | BS60: 0.8 | BT60: =AVERAGE(BO60:BS60) -> 0.81892316
AX61: VDS | AY61: =AX61&"_"&AZ61 -> VDS_Q1 | AZ61: Q1 | BA61: B02 | BB61: 0.94078388 | BC61: 0.92 | BD61: 0.92 | BE61: 0.92 | BF61: 0.92 | BG61: =AVERAGE(BB61:BF61) -> 0.92415678 | BK61: VDS | BL61: =BK61&"_"&BM61 -> VDS_Q1 | BM61: Q1 | BN61: B02 | BO61: 0.94078388 | BP61: 0.92 | BQ61: 0.92 | BR61: 0.92 | BS61: 0.92 | BT61: =AVERAGE(BO61:BS61) -> 0.92415678
... AX79: All | AY79: =AX79&"_"&AZ79 -> All_Q1 | AZ79: Q1 | BA79: B06 | BB79: 0.99493965 | BC79: 0.99378871 | BD79: 0.99378871 | BE79: 0.99378871 | BF79: 0.99378871 | BG79: =AVERAGE(BB79:BF79) -> 0.9940189 | BK79: All | BL79: =BK79&"_"&BM79 -> All_Q1 | BM79: Q1 | BN79: B06 | BO79: 0.99493965 | BP79: 0.99378871 | BQ79: 0.99378871 | BR79: 0.99378871 | BS79: 0.99378871 | BT79: =AVERAGE(BO79:BS79) -> 0.9940189

Sheet SAP_Leadsheet
B1: SAP MODEL - PAYLATER CARD
B2: Leadsheet
B3: HKN | C3: =NOTE!P2 -> 20251201 | D3: =NOTE!O2 -> v10
B5: Select model type
B6: Write off | C6: DPD180+
B7: Provision | C7: IFRS
B8: Chanel | C8: All
B9: EMI mode | C9: EMI
B10: Customer type
B11: Quarter | C11: Q1
B13: REVENUE INPUT | I13: Cur: mVND, % | L13: SUMMARY OUTPUT | V13: Cur: mVND, %
E15: Year 1 | F15: Year 2 | G15: Year 3 | H15: Year 4 | I15: Year 5 | N15: Lifetime | O15: Year 1 | P15: Year 2 | Q15: Year 3 | R15: Year 4 | S15: Year 5 | T15: Year 6 | U15: % of ANR | V15: % of Spending
B17: Card Status | C17: Activate at beginning | E17: =DATA!C3 -> 0.6392418 | F17: Account having spending at month 1 | L17: Spending | N17: =N48 -> 26.542458 | O17: =O48 -> 7.3460319 | P17: =P48 -> 6.0081549 | Q17: =Q48 -> 5.0768553 | R17: =R48 -> 4.3420441 | S17: =S48 -> 3.7693718 | T17: =T48 -> 0
C18: Average attrition rate | E18: =DATA!A31 -> 0.011030208 | F18: =DATA!B31 -> 0.0068777618 | G18: =DATA!C31 -> 0.0054648835 | H18: =DATA!D31 -> 0.0042795518 | I18: =DATA!E31 -> 0.003317893 | J18: =IF(E17-E18*11-(F18+G18+H18+I18)*12<0,"check","OK") -> OK | L18: ANR | N18: =N49 -> 1.3704774 | O18: =O49 -> 1.6955335 | P18: =P49 -> 1.5692588 | Q18: =Q49 -> 1.3739191 | R18: =R49 -> 1.1886385 | S18: =S49 -> 1.0250369 | T18: =T49 -> 0
C19: per cohort | E19: including account have spending & balance | L19: TOI | N19: =N50 -> 2.0433936 | O19: =O50 -> 0.50288459 | P19: =P50 -> 0.43975111 | Q19: =Q50 -> 0.41715861 | R19: =R50 -> 0.37418294 | S19: =S50 -> 0.30941638 | T19: =T50 -> 0 | U19: =U50 -> 0.29820173 | V19: =V50 -> 0.076985848
L20: Net interest income | N20: =N51 -> 0.68910667 | O20: =O51 -> 0.12270156 | P20: =P51 -> 0.13217939 | Q20: =Q51 -> 0.15081336 | R20: =R51 -> 0.14375553 | S20: =S51 -> 0.13965683 | T20: =T51 -> 0 | U20: =U51 -> 0.10056447 | V20: =V51 -> 0.025962429
B21: Term of using | C21: Tenor | E21: 60 | F21: month | L21: Net fee income | N21: =N54 -> 1.354287 | O21: =O54 -> 0.38018303 | P21: =P54 -> 0.30757172 | Q21: =Q54 -> 0.26634524 | R21: =R54 -> 0.23042741 | S21: =S54 -> 0.16975955 | T21: =T54 -> 0 | U21: =U54 -> 0.19763726 | V21: =V54 -> 0.051023419
C22: Due date | E22: 5 | F22: Date of month | L22: Other income | N22: =N65 -> 0 | O22: =O65 -> 0 | P22: =P65 -> 0 | Q22: =Q65 -> 0 | R22: =R65 -> 0 | S22: =S65 -> 0 | T22: =T65 -> 0 | U22: =N22/$N$49/60*12 -> 0 | V22: =N22/$N$48/60*12 -> 0
C23: Free-interest period | E23: 45 | F23: days | L23: Provision cost | N23: =N66 -> -2.4358372 | O23: =O66 -> -0.90924204 | P23: =P66 -> -0.55696735 | Q23: =Q66 -> -0.39672309 | R23: =R66 -> -0.3172374 | S23: =S66 -> -0.25566734 | T23: =T66 -> 0 | U23: =U66 -> -0.35547281 | V23: =V66 -> -0.091771351
L24: Operation expenses | N24: =N67 -> -0.61325013 | O24: =O67 -> -0.24788521 | P24: =P67 -> -0.10309891 | Q24: =Q67 -> -0.09212599 | R24: =R67 -> -0.08912664 | S24: =S67 -> -0.081013382 | T24: =T67 -> 0 | U24: =U67 -> -0.089494382 | V24: =V67 -> -0.023104497
B25: Usage Status | C25: Spd / activate card | E25: =DATA!C4 -> 1.0580627 | F25: =E25 -> 1.0580627 | G25: =F25 -> 1.0580627 | H25: =G25 -> 1.0580627 | I25: =H25 -> 1.0580627 | L25: Variable Cost | N25: =N67-N81 -> -0.49676331 | O25: =O67-O81 -> -0.21753932 | P25: =P67-P81 -> -0.077342081 | Q25: =Q67-Q81 -> -0.069599557 | R25: =R67-R81 -> -0.069185947 | S25: =S67-S81 -> -0.063096409 | T25: =T67-T81 -> 0 | U25: =N25/$N$49/60*12 -> -0.072494931 | V25: =N25/$N$48/60*12 -> -0.0037431598
L26: Sales & Marketing | N26: =N68 -> -0.084967274 | O26: =O68 -> -0.056124799 | P26: =P68 -> 0 | Q26: =Q68 -> -0.0035983073 | R26: =R68 -> -0.012164168 | S26: =S68 -> -0.013079999 | T26: =T68 -> 0 | U26: =U68 -> -0.012399661 | V26: =V68 -> -0.0032011833
B27: Payment status | C27: Port Revolving rate | E27: =DATA!C5 -> 0.69849829 | L27: Promotion | N27: =N73 -> -0.11970384 | O27: =O73 -> -0.033129871 | P27: =P73 -> -0.027096179 | Q27: =Q73 -> -0.022896111 | R27: =R73 -> -0.019582186 | S27: =S73 -> -0.016999491 | T27: =T73 -> 0 | U27: =U73 -> -0.017468926 | V27: =V73 -> -0.0045099003
C28: Payment rate | E28: =DATA!C6 -> 0.36991535 | F28: =E28 -> 0.36991535 | G28: =F28 -> 0.36991535 | H28: =G28 -> 0.36991535 | I28: =H28 -> 0.36991535 | L28: UW & Disbursal cost | N28: =N74 -> -0.067824417 | O28: =O74 -> -0.067824417 | P28: =P74 -> 0 | Q28: =Q74 -> 0 | R28: =R74 -> 0 | S28: =S74 -> 0 | T28: =T74 -> 0 | U28: =U74 -> -0.0098979259 | V28: =V74 -> -0.0025553179
E29: payment T/ non-EMI ANR T-1 (excl WO) | L29: Collection | N29: =N77 -> -0.12527023 | O29: =O77 -> -0.034670455 | P29: =P77 -> -0.028356189 | Q29: =Q77 -> -0.023960811 | R29: =R77 -> -0.020492784 | S29: =S77 -> -0.01778999 | T29: =T77 -> 0 | U29: =U77 -> -0.018281255 | V29: =V77 -> -0.0047196168
L30: After sale service | N30: =N80 -> -0.098997552 | O30: =O80 -> -0.025789774 | P30: =P80 -> -0.021889713 | Q30: =Q80 -> -0.019144327 | R30: =R80 -> -0.016946808 | S30: =S80 -> -0.015226929 | T30: =T80 -> 0 | U30: =U80 -> -0.014447163 | V30: =V80 -> -0.0037297809
B31: Pricing | C31: CII rate | E31: =DATA!C7 -> 0.47795381 | F31: annually | L31: Overhead cost | N31: =N81 -> -0.11648682 | O31: =O81 -> -0.030345889 | P31: =P81 -> -0.025756829 | Q31: =Q81 -> -0.022526433 | R31: =R81 -> -0.019940693 | S31: =S81 -> -0.017916973 | T31: =T81 -> 0 | U31: =N31/$N$49/60*12 -> -0.016999451 | V31: =N31/$N$48/60*12 -> -0.00087773949
C32: COF rate | E32: =DATA!C8 -> 0.069938802 | F32: annually | L32: PBT | N32: =N82 -> -1.0056937 | O32: =O82 -> -0.65424266 | P32: =P82 -> -0.22031515 | Q32: =Q82 -> -0.071690469 | R32: =R82 -> -0.032181101 | S32: =S82 -> -0.027264335 | T32: =T82 -> 0 | U32: =U82 -> -0.14676546 | V32: =V82 -> -0.037889999
L33: Profit before sup.cost | N33: =N83 -> -0.8892069 | O33: =O83 -> -0.62389677 | P33: =P83 -> -0.19455832 | Q33: =Q83 -> -0.049164036 | R33: =R83 -> -0.012240409 | S33: =S83 -> -0.0093473619 | T33: =T83 -> 0 | U33: =U83 -> -0.12976601 | V33: =V83 -> -0.033501302
B34: Fee/charge | C34: Annual fee | F34: per card/year
C35: Annual Fee waiver | F35: % accard port
C36: Monthly fee (Subscription fee) | E36: =DATA!C9 -> 0.0275 | F36: per card having spending/month
C37: Transaction fee | F37: per spend/month
C38: Late payment interest | E38: 0 | F38: annually | G38: %Late payment collected | I38: 1
C39: Late payment penalty (fee) | E39: =DATA!C10 -> 0.072785593 | F39: per account | G39: %Late payment collected | I39: 1
C40: Min due fee | F40: per revolving balance/month
B43: Other fee(no share) | C43: Issuance fee | F43: per issued account
C44: Termination fee | F44: per terminated account
L45: PERFORMANCE OUTPUT | V45: Cur: mVND, %
B46: EMI
C47: Cash installment | N47: Lifetime | O47: Year 1 | P47: Year 2 | Q47: Year 3 | R47: Year 4 | S47: Year 5 | T47: Year 6 | U47: % of ANR | V47: % of Spending
C48: EMI Penetration | E48: =DATA!B36 -> 0.0025939226 | F48: per spending per month | L48: Spending | N48: =SUM(O48:S48) -> 26.542458 | O48: =SUM(SAP_Spreadsheet!G21:R21) -> 7.3460319 | P48: =SUM(SAP_Spreadsheet!S21:AD21) -> 6.0081549 | Q48: =SUM(SAP_Spreadsheet!AE21:AP21) -> 5.0768553 | R48: =SUM(SAP_Spreadsheet!AQ21:BB21) -> 4.3420441 | S48: =SUM(SAP_Spreadsheet!BC21:BN21) -> 3.7693718
C49: Average tenor | E49: =DATA!C36 -> 3 | F49: per transaction | L49: ANR | N49: =AVERAGEIF(SAP_Spreadsheet!G631:BN631,"<>0") -> 1.3704774 | O49: =IFERROR(AVERAGEIF(SAP_Spreadsheet!G631:R631,"<>0"),0) -> 1.6955335 | P49: =IFERROR(AVERAGEIF(SAP_Spreadsheet!S631:AD631,"<>0"),0) -> 1.5692588 | Q49: =IFERROR(AVERAGEIF(SAP_Spreadsheet!AE631:AP631,"<>0"),0) -> 1.3739191 | R49: =IFERROR(AVERAGEIF(SAP_Spreadsheet!AQ631:BB631,"<>0"),0) -> 1.1886385 | S49: =IFERROR(AVERAGEIF(SAP_Spreadsheet!BC631:BN631,"<>0"),0) -> 1.0250369
C50: Subvention fee (onetime) | F50: per installment | L50: TOI | N50: =N51+N54+N65 -> 2.0433936 | O50: =O51+O54+O65 -> 0.50288459 | P50: =P51+P54+P65 -> 0.43975111 | Q50: =Q51+Q54+Q65 -> 0.41715861 | R50: =R51+R54+R65 -> 0.37418294 | S50: =S51+S54+S65 -> 0.30941638 | U50: =N50/$N$49/60*12 -> 0.29820173 | V50: =N50/$N$48 -> 0.076985848
C51: Initial fee | F51: per month | L51: Net interest income | N51: =SUM(N52:N53) -> 0.68910667 | O51: =SUM(O52:O53) -> 0.12270156 | P51: =SUM(P52:P53) -> 0.13217939 | Q51: =SUM(Q52:Q53) -> 0.15081336 | R51: =SUM(R52:R53) -> 0.14375553 | S51: =SUM(S52:S53) -> 0.13965683 | U51: =N51/$N$49/60*12 -> 0.10056447 | V51: =N51/$N$48 -> 0.025962429
C52: Early repayment fee | F52: Outstanding balance | L52: CII | N52: =SUM( SAP_Spreadsheet!G646:BN646) -> 1.1683544 | O52: =SUM(SAP_Spreadsheet!G646:R646) -> 0.24128514 | P52: =SUM(SAP_Spreadsheet!S646:AD646) -> 0.24193147 | Q52: =SUM( SAP_Spreadsheet!AE646:AP646) -> 0.24690362 | R52: =SUM( SAP_Spreadsheet!AQ646:BB646) -> 0.22688748 | S52: =SUM(SAP_Spreadsheet!BC646:BN646) -> 0.21134668 | U52: =N52/$N$49/60*12 -> 0.17050327 | V52: =N52/$N$48 -> 0.04401832
C53: % Early rate | F53: Outstanding balance | L53: COF | N53: =SUM( SAP_Spreadsheet!G649:BN649) -> -0.47924773 | O53: =SUM(SAP_Spreadsheet!G649:R649) -> -0.11858358 | P53: =SUM(SAP_Spreadsheet!S649:AD649) -> -0.10975208 | Q53: =SUM( SAP_Spreadsheet!AE649:AP649) -> -0.096090257 | R53: =SUM( SAP_Spreadsheet!AQ649:BB649) -> -0.083131954 | S53: =SUM(SAP_Spreadsheet!BC649:BN649) -> -0.07168985 | U53: =N53/$N$49/60*12 -> -0.069938802 | V53: =N53/$N$48 -> -0.018055891
L54: Net fee income | N54: =SUM(N55:N64) -> 1.354287 | O54: =SUM(O55:O64) -> 0.38018303 | P54: =SUM(P55:P64) -> 0.30757172 | Q54: =SUM(Q55:Q64) -> 0.26634524 | R54: =SUM(R55:R64) -> 0.23042741 | S54: =SUM(S55:S64) -> 0.16975955 | U54: =N54/$N$49/60*12 -> 0.19763726 | V54: =N54/$N$48 -> 0.051023419
C55: Retail monthly installment | L55: Annual fee | N55: =SUM( SAP_Spreadsheet!G652:BN652) -> 0 | O55: =SUM(SAP_Spreadsheet!G652:R652) -> 0 | P55: =SUM(SAP_Spreadsheet!S652:AD652) -> 0 | Q55: =SUM( SAP_Spreadsheet!AE652:AP652) -> 0 | R55: =SUM( SAP_Spreadsheet!AQ652:BB652) -> 0 | S55: =SUM( SAP_Spreadsheet!BC652:BN652) -> 0 | U55: =N55/$N$49/60*12 -> 0 | V55: =N55/$N$48 -> 0
C56: EMI Penetration | E56: =DATA!B35 -> 0.04851372 | F56: per spending per month | L56: Monthly fee | N56: =SUM( SAP_Spreadsheet!G653:BN653) -> 0.57015787 | O56: =SUM(SAP_Spreadsheet!G653:R653) -> 0.15971908 | P56: =SUM(SAP_Spreadsheet!S653:AD653) -> 0.12152419 | Q56: =SUM( SAP_Spreadsheet!AE653:AP653) -> 0.10907272 | R56: =SUM( SAP_Spreadsheet!AQ653:BB653) -> 0.095759232 | S56: =SUM( SAP_Spreadsheet!BC653:BN653) -> 0.084082654 | U56: =N56/$N$49/60*12 -> 0.083205734 | V56: =N56/$N$48 -> 0.021480975
C57: Average tenor | E57: =DATA!C35 -> 6 | F57: per transaction | L57: Transaction fee | N57: =SUM( SAP_Spreadsheet!G654:BN654) -> 0 | O57: =SUM(SAP_Spreadsheet!G654:R654) -> 0 | P57: =SUM(SAP_Spreadsheet!S654:AD654) -> 0 | Q57: =SUM( SAP_Spreadsheet!AE654:AP654) -> 0 | R57: =SUM( SAP_Spreadsheet!AQ654:BB654) -> 0 | S57: =SUM( SAP_Spreadsheet!BC654:BN654) -> 0 | U57: =N57/$N$49/60*12 -> 0 | V57: =N57/$N$48 -> 0
C58: Initial fee | E58: =DATA!C27 -> 0.031770112 | F58: per month | L58: Issuance fee | N58: =SUM( SAP_Spreadsheet!G671:BN671) -> 0 | O58: =SUM(SAP_Spreadsheet!G671:R671) -> 0 | P58: =SUM(SAP_Spreadsheet!S671:AD671) -> 0 | Q58: =SUM( SAP_Spreadsheet!AE671:AP671) -> 0 | R58: =SUM( SAP_Spreadsheet!AQ671:BB671) -> 0 | S58: =SUM( SAP_Spreadsheet!BC671:BN671) -> 0 | U58: =N58/$N$49/60*12 -> 0 | V58: =N58/$N$48 -> 0
C59: Subvention fee (onetime) | F59: per installment | L59: Subvention fee | N59: =SUM( SAP_Spreadsheet!G655:BN655) -> 0.52670271 | O59: =SUM(SAP_Spreadsheet!G655:R655) -> 0.15267734 | P59: =SUM(SAP_Spreadsheet!S655:AD655) -> 0.12487137 | Q59: =SUM( SAP_Spreadsheet!AE655:AP655) -> 0.10551557 | R59: =SUM( SAP_Spreadsheet!AQ655:BB655) -> 0.090243513 | S59: =SUM( SAP_Spreadsheet!BC655:BN655) -> 0.053394918 | U59: =N59/$N$49/60*12 -> 0.076864124 | V59: =N59/$N$48 -> 0.019843781
C60: Early repayment fee | F60: Outstanding balance | L60: Late payment | N60: =SUM( SAP_Spreadsheet!G659:BN659) -> 0.06883298 | O60: =SUM(SAP_Spreadsheet!G659:R659) -> 0.024208393 | P60: =SUM(SAP_Spreadsheet!S659:AD659) -> 0.016266637 | Q60: =SUM( SAP_Spreadsheet!AE659:AP659) -> 0.011584249 | R60: =SUM( SAP_Spreadsheet!AQ659:BB659) -> 0.0092542963 | S60: =SUM( SAP_Spreadsheet!BC659:BN659) -> 0.0075194043 | U60: =N60/$N$49/60*12 -> 0.01004511 | V60: =N60/$N$48 -> 0.002593316
C61: % Early rate | F61: Outstanding balance | L61: Min due fee | N61: =SUM( SAP_Spreadsheet!G662:BN662) -> 0 | O61: =SUM(SAP_Spreadsheet!G662:R662) -> 0 | P61: =SUM(SAP_Spreadsheet!S662:AD662) -> 0 | Q61: =SUM( SAP_Spreadsheet!AE662:AP662) -> 0 | R61: =SUM( SAP_Spreadsheet!AQ662:BB662) -> 0 | S61: =SUM( SAP_Spreadsheet!BC662:BN662) -> 0 | U61: =N61/$N$49/60*12 -> 0 | V61: =N61/$N$48 -> 0
L62: EMI initial fee | N62: =SUM( SAP_Spreadsheet!G663:BN663) -> 0.1885934 | O62: =SUM(SAP_Spreadsheet!G663:R663) -> 0.043578226 | P62: =SUM(SAP_Spreadsheet!S663:AD663) -> 0.044909518 | Q62: =SUM( SAP_Spreadsheet!AE663:AP663) -> 0.040172708 | R62: =SUM( SAP_Spreadsheet!AQ663:BB663) -> 0.035170372 | S62: =SUM( SAP_Spreadsheet!BC663:BN663) -> 0.024762577 | U62: =N62/$N$49/60*12 -> 0.027522293 | V62: =N62/$N$48 -> 0.007105348
C63: Retail 0% Installment | L63: EMI- early termination | N63: =SUM( SAP_Spreadsheet!G667:BN667) -> 0 | O63: =SUM(SAP_Spreadsheet!G667:R667) -> 0 | P63: =SUM(SAP_Spreadsheet!S667:AD667) -> 0 | Q63: =SUM( SAP_Spreadsheet!AE667:AP667) -> 0 | R63: =SUM( SAP_Spreadsheet!AQ667:BB667) -> 0 | S63: =SUM( SAP_Spreadsheet!BC667:BN667) -> 0 | U63: =N63/$N$49/60*12 -> 0 | V63: =N63/$N$48 -> 0
C64: EMI Penetration | E64: =DATA!B34 -> 0.29616921 | F64: per spending per month | L64: x | N64: =SUM( SAP_Spreadsheet!G672:BN672) -> 0 | O64: =SUM(SAP_Spreadsheet!G672:R672) -> 0 | P64: =SUM(SAP_Spreadsheet!S672:AD672) -> 0 | Q64: =SUM( SAP_Spreadsheet!AE672:AP672) -> 0 | R64: =SUM( SAP_Spreadsheet!AQ672:BB672) -> 0 | S64: =SUM( SAP_Spreadsheet!BC672:BN672) -> 0 | U64: =N64/$N$49/60*12 -> 0 | V64: =N64/$N$48 -> 0
C65: Tenor | E65: =DATA!C34 -> 5 | F65: month | L65: Other income | N65: =SUM( SAP_Spreadsheet!G675:BN675) -> 0 | O65: =SUM(SAP_Spreadsheet!G675:R675) -> 0 | P65: =SUM(SAP_Spreadsheet!S675:AD675) -> 0 | Q65: =SUM( SAP_Spreadsheet!AE675:AP675) -> 0 | R65: =SUM( SAP_Spreadsheet!AQ675:BB675) -> 0 | S65: =SUM( SAP_Spreadsheet!BC675:BN675) -> 0 | U65: =N65/$N$49/60*12 -> 0 | V65: =N65/$N$48 -> 0
C66: Initial fee | F66: per month | L66: PROVISION | N66: =SUM(O66:T66) -> -2.4358372 | O66: =SUM(SAP_Spreadsheet!G775:R775) -> -0.90924204 | P66: =SUM(SAP_Spreadsheet!S775:AD775) -> -0.55696735 | Q66: =SUM(SAP_Spreadsheet!AE775:AP775) -> -0.39672309 | R66: =SUM(SAP_Spreadsheet!AQ775:BB775) -> -0.3172374 | S66: =SUM(SAP_Spreadsheet!BC775:BN775) -> -0.25566734 | T66: =SUM(SAP_Spreadsheet!BO775:BZ775) -> 0 | U66: =N66/$N$49/60*12 -> -0.35547281 | V66: =N66/$N$48 -> -0.091771351
C67: Subvention fee (onetime) | E67: =DATA!D34 -> 0.07017491 | F67: per installment | L67: OPEX | N67: =N68+N73+N74+N80+N77+N81 -> -0.61325013 | O67: =O68+O73+O74+O80+O77+O81 -> -0.24788521 | P67: =P68+P73+P74+P80+P77+P81 -> -0.10309891 | Q67: =Q68+Q73+Q74+Q80+Q77+Q81 -> -0.09212599 | R67: =R68+R73+R74+R80+R77+R81 -> -0.08912664 | S67: =S68+S73+S74+S80+S77+S81 -> -0.081013382 | U67: =N67/$N$49/60*12 -> -0.089494382 | V67: =N67/$N$48 -> -0.023104497
C68: Early repayment fee | F68: Outstanding balance | L68: Sales & Marketing | N68: =N69+N72 -> -0.084967274 | O68: =O69+O72 -> -0.056124799 | P68: =P69+P72 -> 0 | Q68: =Q69+Q72 -> -0.0035983073 | R68: =R69+R72 -> -0.012164168 | S68: =S69+S72 -> -0.013079999 | U68: =N68/$N$49/60*12 -> -0.012399661 | V68: =N68/$N$48 -> -0.0032011833
C69: % Early rate | F69: Outstanding balance | L69: Partner acquisition | N69: =SUM( SAP_Spreadsheet!G681:BN681) -> -0.084967274 | O69: =SUM(SAP_Spreadsheet!G681:R681) -> -0.056124799 | P69: =SUM(SAP_Spreadsheet!S681:AD681) -> 0 | Q69: =SUM( SAP_Spreadsheet!AE681:AP681) -> -0.0035983073 | R69: =SUM( SAP_Spreadsheet!AQ681:BB681) -> -0.012164168 | S69: =SUM( SAP_Spreadsheet!BC681:BN681) -> -0.013079999 | U69: =N69/$N$49/60*12 -> -0.012399661 | V69: =N69/$N$48 -> -0.0032011833
B70: COST INPUT | I70: Cur: mVND, % | L70: Leadgen | N70: =SUM( SAP_Spreadsheet!G682:BN682) -> 0 | O70: =SUM(SAP_Spreadsheet!G682:R682) -> 0 | P70: =SUM(SAP_Spreadsheet!S682:AD682) -> 0 | Q70: =SUM( SAP_Spreadsheet!AE682:AP682) -> 0 | R70: =SUM( SAP_Spreadsheet!AQ682:BB682) -> 0 | S70: =SUM( SAP_Spreadsheet!BC682:BN682) -> 0 | U70: =N70/$N$49/60*12 -> 0 | V70: =N70/$N$48 -> 0
B71: Inflation rate | L71: Sharing performance | N71: =SUM( SAP_Spreadsheet!G683:BN683) -> -0.084967274 | O71: =SUM(SAP_Spreadsheet!G683:R683) -> -0.056124799 | P71: =SUM(SAP_Spreadsheet!S683:AD683) -> 0 | Q71: =SUM( SAP_Spreadsheet!AE683:AP683) -> -0.0035983073 | R71: =SUM( SAP_Spreadsheet!AQ683:BB683) -> -0.012164168 | S71: =SUM( SAP_Spreadsheet!BC683:BN683) -> -0.013079999 | U71: =N71/$N$49/60*12 -> -0.012399661 | V71: =N71/$N$48 -> -0.0032011833
E72: =IF(SAP_Spreadsheet!$C$5="yes",0,3.5%) -> 0.035 | F72: annual rate | L72: Marketing acquisition | N72: =SUM( SAP_Spreadsheet!G689:BN689) -> 0 | O72: =SUM(SAP_Spreadsheet!G689:R689) -> 0 | P72: =SUM(SAP_Spreadsheet!S689:AD689) -> 0 | Q72: =SUM( SAP_Spreadsheet!AE689:AP689) -> 0 | R72: =SUM( SAP_Spreadsheet!AQ689:BB689) -> 0 | S72: =SUM( SAP_Spreadsheet!BC689:BN689) -> 0 | U72: =N72/$N$49/60*12 -> 0 | V72: =N72/$N$48 -> 0
B73: Sales & Marketing | L73: Promotion cost | N73: =SUM( SAP_Spreadsheet!G692:BN692) -> -0.11970384 | O73: =SUM(SAP_Spreadsheet!G692:R692) -> -0.033129871 | P73: =SUM(SAP_Spreadsheet!S692:AD692) -> -0.027096179 | Q73: =SUM( SAP_Spreadsheet!AE692:AP692) -> -0.022896111 | R73: =SUM( SAP_Spreadsheet!AQ692:BB692) -> -0.019582186 | S73: =SUM( SAP_Spreadsheet!BC692:BN692) -> -0.016999491 | U73: =N73/$N$49/60*12 -> -0.017468926 | V73: =N73/$N$48 -> -0.0045099003
B74: Partner acquisition | L74: UW & Disbursal cost | N74: =SUM(N75:N76) -> -0.067824417 | O74: =SUM(O75:O76) -> -0.067824417 | P74: =SUM(P75:P76) -> 0 | Q74: =SUM(Q75:Q76) -> 0 | R74: =SUM(R75:R76) -> 0 | S74: =SUM(S75:S76) -> 0 | U74: =N74/$N$49/60*12 -> -0.0098979259 | V74: =N74/$N$48 -> -0.0025553179
C75: Lead acquisition | F75: per issued account | L75: Underwriting cost | N75: =SUM(SAP_Spreadsheet!G694:BN694) -> -0.065146706 | O75: =SUM(SAP_Spreadsheet!G694:R694) -> -0.065146706 | P75: =SUM(SAP_Spreadsheet!S694:AD694) -> 0 | Q75: =SUM(SAP_Spreadsheet!AE694:AP694) -> 0 | R75: =SUM(SAP_Spreadsheet!AQ694:BB694) -> 0 | S75: =SUM(SAP_Spreadsheet!BC694:BN694) -> 0 | U75: =N75/$N$49/60*12 -> -0.0095071554 | V75: =N75/$N$48 -> -0.0024544338
C76: Sharing TOI +Risk DPD90+ | E76: =DATA!C26 -> 0 | F76: per month | G76: Auto mode | L76: Disbursement cost | N76: =SUM(SAP_Spreadsheet!G695:BN695) -> -0.0026777105 | O76: =SUM(SAP_Spreadsheet!G695:R695) -> -0.0026777105 | P76: =SUM(SAP_Spreadsheet!S695:AD695) -> 0 | Q76: =SUM(SAP_Spreadsheet!AE695:AP695) -> 0 | R76: =SUM(SAP_Spreadsheet!AQ695:BB695) -> 0 | S76: =SUM(SAP_Spreadsheet!BC695:BN695) -> 0 | U76: =N76/$N$49/60*12 -> -0.00039077049 | V76: =N76/$N$48 -> -0.00010088405
C77: Sharing NII | E77: =DATA!C23 -> 0.33230275 | F77: per month | G77: Manual mode | L77: Collection | N77: =SUM(N78:N79) -> -0.12527023 | O77: =SUM(O78:O79) -> -0.034670455 | P77: =SUM(P78:P79) -> -0.028356189 | Q77: =SUM(Q78:Q79) -> -0.023960811 | R77: =SUM(R78:R79) -> -0.020492784 | S77: =SUM(S78:S79) -> -0.01778999 | U77: =N77/$N$49/60*12 -> -0.018281255 | V77: =N77/$N$48 -> -0.0047196168
C78: Sharing NFI | E78: =DATA!C24 -> 0.33230275 | F78: per month | G78: Manual mode | L78: Early collection | N78: =SUM( SAP_Spreadsheet!G705:BN705) -> -0.12527023 | O78: =SUM(SAP_Spreadsheet!G705:R705) -> -0.034670455 | P78: =SUM(SAP_Spreadsheet!S705:AD705) -> -0.028356189 | Q78: =SUM( SAP_Spreadsheet!AE705:AP705) -> -0.023960811 | R78: =SUM( SAP_Spreadsheet!AQ705:BB705) -> -0.020492784 | S78: =SUM( SAP_Spreadsheet!BC705:BN705) -> -0.01778999 | U78: =N78/$N$49/60*12 -> -0.018281255 | V78: =N78/$N$48 -> -0.0047196168
C79: Sharing Risk DPD 90+ | E79: =DATA!C25 -> 0.33230275 | F79: per month | G79: Manual mode | L79: AMC | N79: =SUM( SAP_Spreadsheet!G706:BN706) -> 0 | O79: =SUM(SAP_Spreadsheet!G706:R706) -> 0 | P79: =SUM(SAP_Spreadsheet!S706:AD706) -> 0 | Q79: =SUM( SAP_Spreadsheet!AE706:AP706) -> 0 | R79: =SUM( SAP_Spreadsheet!AQ706:BB706) -> 0 | S79: =SUM( SAP_Spreadsheet!BC706:BN706) -> 0 | U79: =N79/$N$49/60*12 -> 0 | V79: =N79/$N$48 -> 0
B80: Marketing acquisition | L80: After sale service | N80: =SUM(SAP_Spreadsheet!G703:BN703) -> -0.098997552 | O80: =SUM(SAP_Spreadsheet!G703:R703) -> -0.025789774 | P80: =SUM(SAP_Spreadsheet!S703:AD703) -> -0.021889713 | Q80: =SUM( SAP_Spreadsheet!AE703:AP703) -> -0.019144327 | R80: =SUM( SAP_Spreadsheet!AQ703:BB703) -> -0.016946808 | S80: =SUM( SAP_Spreadsheet!BC703:BN703) -> -0.015226929 | U80: =N80/$N$49/60*12 -> -0.014447163 | V80: =N80/$N$48 -> -0.0037297809
C81: MKT cost for acquisition | F81: per issued account | L81: Other support units | N81: =SUM( SAP_Spreadsheet!G709:BN712) -> -0.11648682 | O81: =SUM(SAP_Spreadsheet!G709:R712) -> -0.030345889 | P81: =SUM(SAP_Spreadsheet!S709:AD712) -> -0.025756829 | Q81: =SUM( SAP_Spreadsheet!AE709:AP712) -> -0.022526433 | R81: =SUM( SAP_Spreadsheet!AQ709:BB712) -> -0.019940693 | S81: =SUM( SAP_Spreadsheet!BC709:BN712) -> -0.017916973 | U81: =N81/$N$49/60*12 -> -0.016999451 | V81: =N81/$N$48 -> -0.0043886974
L82: PBT | N82: =N50+N66+N67 -> -1.0056937 | O82: =O50+O66+O67 -> -0.65424266 | P82: =P50+P66+P67 -> -0.22031515 | Q82: =Q50+Q66+Q67 -> -0.071690469 | R82: =R50+R66+R67 -> -0.032181101 | S82: =S50+S66+S67 -> -0.027264335 | T82: =T50+T66+T67 -> 0 | U82: =N82/$N$49/60*12 -> -0.14676546 | V82: =N82/$N$48 -> -0.037889999
L83: PROFIT BEFORE SU | N83: =N50+N66+N67-N81 -> -0.8892069 | O83: =O50+O66+O67-O81 -> -0.62389677 | P83: =P50+P66+P67-P81 -> -0.19455832 | Q83: =Q50+Q66+Q67-Q81 -> -0.049164036 | R83: =R50+R66+R67-R81 -> -0.012240409 | S83: =S50+S66+S67-S81 -> -0.0093473619 | T83: =T50+T66+T67-T81 -> 0 | U83: =N83/$N$49/60*12 -> -0.12976601 | V83: =N83/$N$48 -> -0.033501302
B84: Promotion cost
C85: Spending promotion | E85: =DATA!C11 -> 0.0045099003 | F85: per spending
C86: Promotion yearly | F86: per active account | N86: =N83/N49 -> -0.64883005 | O86: =O83/O49 -> -0.36796487 | P86: =P83/P49 -> -0.12398103 | Q86: =Q83/Q49 -> -0.035783792 | R86: =R83/R49 -> -0.010297839 | S86: =S83/S49 -> -0.0091190496
N87: =N60/N49/60*12 -> 0.01004511 | O87: =O60/O49/60*12 -> 0.0028555488 | P87: =P60/P49/60*12 -> 0.0020731618 | Q87: =Q60/Q49/60*12 -> 0.0016863073 | R87: =R60/R49/60*12 -> 0.0015571254 | S87: =S60/S49/60*12 -> 0.0014671481
B88: UW & Disbursal cost
C89: Underwriting cost | E89: =DATA!C13*E90*E91 -> 0.013828366 | F89: per application
C90: Approval rate | E90: =DATA!C14 -> 0.267 | F90: of applications submitted
C91: Disbursement rate | E91: =DATA!C15 -> 0.795 | F91: of applications approved
C92: Disbursement cost | E92: =DATA!C16 -> 0.0026777105 | F92: per new issued account
B93: Collection
C94: Early collection | E94: =DATA!C17 -> 0.0049936505 | F94: per account / month
C95: x
C96: x
B98: Other after-sale cost
C99: SMS & Email | E99: =DATA!C18 -> 0.0037145494 | F99: per active card / month
C100: x
C101: x
B104: Overheads
C105: SU_Direct HR | E105: =DATA!C19 -> 0.002 | F105: per existing card / month
C106: SU_Indirect HR | E106: =DATA!C20 -> 0.00063414273 | F106: per existing card / month
C107: SU_IT | E107: =DATA!C21 -> 0.0007468595 | F107: per existing card / month
C108: SU_Others | E108: =DATA!C22 -> 0.00098977289 | F108: per existing card / month
B110: RISK INPUT
...

Sheet SAP_Spreadsheet
A1: Index!A1 | B1: SAP Model Paylater
B2: Spreadsheet
B4: Calendar | C4: =(30*4+31*7+28)/12 -> 30.416667 | AE4: =IF(AE$7<13,SAP_Leadsheet!$E$18,IF(SAP_Leadsheet!AF$6<25,SAP_Leadsheet!$F$18,IF(AE$7<37,SAP_Leadsheet!$G$18,IF(AE$7<49,SAP_Leadsheet!$H$18,SAP_Leadsheet!$I$18)))) -> 0.0068777618
B5: Validation | C5: No | D5: COF (*) | E5: =SAP_Leadsheet!E32 -> 0.069938802
E6: Year | G6: =ROUNDUP(G7/12,0) -> 1 | H6: =ROUNDUP(H7/12,0) -> 1 | I6: =ROUNDUP(I7/12,0) -> 1 | J6: =ROUNDUP(J7/12,0) -> 1 | K6: =ROUNDUP(K7/12,0) -> 1 | L6: =ROUNDUP(L7/12,0) -> 1 | M6: =ROUNDUP(M7/12,0) -> 1 | N6: =ROUNDUP(N7/12,0) -> 1 | ... BZ6: =ROUNDUP(BZ7/12,0) -> 6
E7: Month | G7: 1 | H7: =G7+1 -> 2 | I7: =H7+1 -> 3 | J7: =I7+1 -> 4 | K7: =J7+1 -> 5 | L7: =K7+1 -> 6 | M7: =L7+1 -> 7 | N7: =M7+1 -> 8 | O7: =N7+1 -> 9 | ... BZ7: =BY7+1 -> 72
A8: 1 | B8: CARD OPERATION | AE8: =IF(AE$7<37,SAP_Leadsheet!$G$18,IF(AE$7<49,SAP_Leadsheet!$H$18,SAP_Leadsheet!$I$18)) -> 0.0054648835
C10: Card Status | D10: Issued card | F10: # Card | G10: 1 | H10: =G10 -> 1 | I10: =H10 -> 1 | J10: =I10 -> 1 | K10: =J10 -> 1 | L10: =K10 -> 1 | M10: =L10 -> 1 | N10: =M10 -> 1 | O10: =N10 -> 1 | ... BN10: =BM10 -> 1
D11: Activate card | F11: # Card | G11: =G10*SAP_Leadsheet!E17 -> 0.6392418 | H11: =G11-H12 -> 0.62821159 | I11: =H11-I12 -> 0.61718138 | J11: =I11-J12 -> 0.60615117 | K11: =J11-K12 -> 0.59512097 | L11: =K11-L12 -> 0.58409076 | M11: =L11-M12 -> 0.57306055 | N11: =M11-N12 -> 0.56203034 | O11: =N11-O12 -> 0.55100014 | ... BN11: =BM11-BN12 -> 0.27862843
D12: Attrition rate | F12: % | G12: =OFFSET(SAP_Leadsheet!$D$18,0,SAP_Spreadsheet!G6) -> 0.011030208 | H12: =OFFSET(SAP_Leadsheet!$D$18,0,SAP_Spreadsheet!H6) -> 0.011030208 | I12: =OFFSET(SAP_Leadsheet!$D$18,0,SAP_Spreadsheet!I6) -> 0.011030208 | J12: =OFFSET(SAP_Leadsheet!$D$18,0,SAP_Spreadsheet!J6) -> 0.011030208 | K12: =OFFSET(SAP_Leadsheet!$D$18,0,SAP_Spreadsheet!K6) -> 0.011030208 | L12: =OFFSET(SAP_Leadsheet!$D$18,0,SAP_Spreadsheet!L6) -> 0.011030208 | M12: =OFFSET(SAP_Leadsheet!$D$18,0,SAP_Spreadsheet!M6) -> 0.011030208 | N12: =OFFSET(SAP_Leadsheet!$D$18,0,SAP_Spreadsheet!N6) -> 0.011030208 | ... BN12: =OFFSET(SAP_Leadsheet!$D$18,0,SAP_Spreadsheet!BN6) -> 0.003317893
C15: Spending status | D15: Spd per activate card (Port) | F15: mVND | G15: =OFFSET(SAP_Leadsheet!$E$25,0,SAP_Spreadsheet!G6-1) -> 1.0580627 | H15: =OFFSET(SAP_Leadsheet!$E$25,0,SAP_Spreadsheet!H6-1) -> 1.0580627 | I15: =OFFSET(SAP_Leadsheet!$E$25,0,SAP_Spreadsheet!I6-1) -> 1.0580627 | J15: =OFFSET(SAP_Leadsheet!$E$25,0,SAP_Spreadsheet!J6-1) -> 1.0580627 | K15: =OFFSET(SAP_Leadsheet!$E$25,0,SAP_Spreadsheet!K6-1) -> 1.0580627 | L15: =OFFSET(SAP_Leadsheet!$E$25,0,SAP_Spreadsheet!L6-1) -> 1.0580627 | M15: =OFFSET(SAP_Leadsheet!$E$25,0,SAP_Spreadsheet!M6-1) -> 1.0580627 | N15: =OFFSET(SAP_Leadsheet!$E$25,0,SAP_Spreadsheet!N6-1) -> 1.0580627 | ... BN15: =OFFSET(SAP_Leadsheet!$E$25,0,SAP_Spreadsheet!BN6-1) -> 1.0580627
A18: 3 | B18: BS by bucket
B20: CORE | C20: Core statement | D20: Beginning Bal | F20: mVND | G20: 0 | H20: =IF(H7>SAP_Leadsheet!$E$21,0,G25) -> 0.48759132 | I20: =IF(I7>SAP_Leadsheet!$E$21,0,H25) -> 0.95111634 | J20: =IF(J7>SAP_Leadsheet!$E$21,0,I25) -> 1.2742303 | K20: =IF(K7>SAP_Leadsheet!$E$21,0,J25) -> 1.4791941 | L20: =IF(L7>SAP_Leadsheet!$E$21,0,K25) -> 1.6143421 | M20: =IF(M7>SAP_Leadsheet!$E$21,0,L25) -> 1.6764079 | N20: =IF(N7>SAP_Leadsheet!$E$21,0,M25) -> 1.686068 | O20: =IF(O7>SAP_Leadsheet!$E$21,0,N25) -> 1.6677372 | ... BN20: =IF(BN7>SAP_Leadsheet!$E$21,0,BM25) -> 3.1736266
D21: New spending | F21: mVND | G21: =IF(G7>SAP_Leadsheet!$E$21,0,G15*G11) -> 0.67635791 | H21: =IF(H7>SAP_Leadsheet!$E$21,0,H15*H11) -> 0.66468725 | I21: =IF(I7>SAP_Leadsheet!$E$21,0,I15*I11) -> 0.6530166 | J21: =IF(J7>SAP_Leadsheet!$E$21,0,J15*J11) -> 0.64134595 | K21: =IF(K7>SAP_Leadsheet!$E$21,0,K15*K11) -> 0.6296753 | L21: =IF(L7>SAP_Leadsheet!$E$21,0,L15*L11) -> 0.61800465 | M21: =IF(M7>SAP_Leadsheet!$E$21,0,M15*M11) -> 0.606334 | N21: =IF(N7>SAP_Leadsheet!$E$21,0,N15*N11) -> 0.59466335 | ... BN21: =IF(BN7>SAP_Leadsheet!$E$21,0,BN15*BN11) -> 0.29480635
D22: EMI Capitalized | F22: mVND | G22: =-G29 -> 0.046116857 | H22: =-H29 -> 0.09143796 | I22: =-I29 -> 0.13596331 | J22: =-J29 -> 0.1791081 | K22: =-K29 -> 0.22146723 | L22: =-L29 -> 0.22297742 | M22: =-M29 -> 0.21892448 | N22: =-N29 -> 0.21487153 | ... BN22: =-BN29 -> 0.021080872
D23: Move to EMI | F23: mVND | G23: =-G28 -> -0.23488344 | H23: =-H28 -> -0.2308305 | I23: =-I28 -> -0.22677755 | J23: =-J28 -> -0.2227246 | K23: =-K28 -> -0.21867165 | L23: =-L28 -> -0.21461871 | M23: =-M28 -> -0.21056576 | N23: =-N28 -> -0.20651281 | ... BN23: =-BN28 -> 0
D24: Paid off | F24: mVND | H24: {=IF(H7>SAP_Leadsheet!$E$21,0,-G632*INDEX(SAP_Leadsheet!$E$28:$I$28,1,G6))} -> -0.061769696 | I24: {=IF(I7>SAP_Leadsheet!$E$21,0,-H632*INDEX(SAP_Leadsheet!$E$28:$I$28,1,H6))} -> -0.23908841 | J24: {=IF(J7>SAP_Leadsheet!$E$21,0,-I632*INDEX(SAP_Leadsheet!$E$28:$I$28,1,I6))} -> -0.39276569 | K24: {=IF(K7>SAP_Leadsheet!$E$21,0,-J632*INDEX(SAP_Leadsheet!$E$28:$I$28,1,J6))} -> -0.49732284 | L24: {=IF(L7>SAP_Leadsheet!$E$21,0,-K632*INDEX(SAP_Leadsheet!$E$28:$I$28,1,K6))} -> -0.56429759 | M24: {=IF(M7>SAP_Leadsheet!$E$21,0,-L632*INDEX(SAP_Leadsheet!$E$28:$I$28,1,L6))} -> -0.60503262 | N24: {=IF(N7>SAP_Leadsheet!$E$21,0,-M632*INDEX(SAP_Leadsheet!$E$28:$I$28,1,M6))} -> -0.62135278 | O24: {=IF(O7>SAP_Leadsheet!$E$21,0,-N632*INDEX(SAP_Leadsheet!$E$28:$I$28,1,N6))} -> -0.62138022 | ... BN24: {=IF(BN7>SAP_Leadsheet!$E$21,0,-BM632*INDEX(SAP_Leadsheet!$E$28:$I$28,1,BM6))} -> -0.33560137
D25: Ending Bal | F25: mVND | G25: =IF(SAP_Leadsheet!$E$21<G7,0,SUM(G20:G24)) -> 0.48759132 | H25: =IF(SAP_Leadsheet!$E$21<H7,0,SUM(H20:H24)) -> 0.95111634 | I25: =IF(SAP_Leadsheet!$E$21<I7,0,SUM(I20:I24)) -> 1.2742303 | J25: =IF(SAP_Leadsheet!$E$21<J7,0,SUM(J20:J24)) -> 1.4791941 | K25: =IF(SAP_Leadsheet!$E$21<K7,0,SUM(K20:K24)) -> 1.6143421 | L25: =IF(SAP_Leadsheet!$E$21<L7,0,SUM(L20:L24)) -> 1.6764079 | M25: =IF(SAP_Leadsheet!$E$21<M7,0,SUM(M20:M24)) -> 1.686068 | N25: =IF(SAP_Leadsheet!$E$21<N7,0,SUM(N20:N24)) -> 1.6677372 | ... BN25: =IF(SAP_Leadsheet!$E$21<BN7,0,SUM(BN20:BN24)) -> 3.1539125
B27: Installment | C27: Total EMI | D27: Beginning Bal | F27: mVND | G27: 0 | H27: =G30 -> 0.18876659 | I27: =H30 -> 0.32815912 | J27: =I30 -> 0.41897336 | K27: =J30 -> 0.46258986 | L27: =K30 -> 0.45979428 | M27: =L30 -> 0.45143557 | N27: =M30 -> 0.44307685 | O27: =N30 -> 0.43471814 | ... BN27: =BM30 -> 0.021080872
D28: New Billing | F28: mVND | G28: =G34+G224+G413 -> 0.23488344 | H28: =H34+H224+H413 -> 0.2308305 | I28: =I34+I224+I413 -> 0.22677755 | J28: =J34+J224+J413 -> 0.2227246 | K28: =K34+K224+K413 -> 0.21867165 | L28: =L34+L224+L413 -> 0.21461871 | M28: =M34+M224+M413 -> 0.21056576 | N28: =N34+N224+N413 -> 0.20651281 | ... BN28: =BN34+BN224+BN413 -> 0
D29: Paid off | F29: mVND | G29: =G35+G225+G414 -> -0.046116857 | H29: =H35+H225+H414 -> -0.09143796 | I29: =I35+I225+I414 -> -0.13596331 | J29: =J35+J225+J414 -> -0.1791081 | K29: =K35+K225+K414 -> -0.22146723 | L29: =L35+L225+L414 -> -0.22297742 | M29: =M35+M225+M414 -> -0.21892448 | N29: =N35+N225+N414 -> -0.21487153 | ... BN29: =BN35+BN225+BN414 -> -0.021080872
D30: Ending Bal | F30: mVND | G30: =G27+G28+G29 -> 0.18876659 | H30: =H27+H28+H29 -> 0.32815912 | I30: =I27+I28+I29 -> 0.41897336 | J30: =J27+J28+J29 -> 0.46258986 | K30: =K27+K28+K29 -> 0.45979428 | L30: =L27+L28+L29 -> 0.45143557 | M30: =M27+M28+M29 -> 0.44307685 | N30: =N27+N28+N29 -> 0.43471814 | ... BN30: =BN27+BN28+BN29 -> -3.3653635e-16
A32: 2.4
C33: Cash installment | D33: Beginning Bal | F33: mVND | G33: 0 | H33: =G158 -> 0.0011696133 | I33: =H158 -> 0.0017342382 | J33: =I158 -> 0.0017039654 | K33: =J158 -> 0.0016736926 | L33: =K158 -> 0.0016434199 | M33: =L158 -> 0.0016131471 | N33: =M158 -> 0.0015828744 | O33: =N158 -> 0.0015526016 | ... BN33: =BM158 -> 0.00026097233
D34: New Billing | F34: mVND | G34: =IF(SAP_Leadsheet!$C$9="non-EMI",0,IF(G7+SAP_Leadsheet!$E$49-1>SAP_Leadsheet!$E$21,0,SAP_Leadsheet!$E$48*G21)) -> 0.00175442 | H34: =IF(SAP_Leadsheet!$C$9="non-EMI",0,IF(H7+SAP_Leadsheet!$E$49-1>SAP_Leadsheet!$E$21,0,SAP_Leadsheet!$E$48*H21)) -> 0.0017241473 | I34: =IF(SAP_Leadsheet!$C$9="non-EMI",0,IF(I7+SAP_Leadsheet!$E$49-1>SAP_Leadsheet!$E$21,0,SAP_Leadsheet!$E$48*I21)) -> 0.0016938745 | J34: =IF(SAP_Leadsheet!$C$9="non-EMI",0,IF(J7+SAP_Leadsheet!$E$49-1>SAP_Leadsheet!$E$21,0,SAP_Leadsheet!$E$48*J21)) -> 0.0016636017 | K34: =IF(SAP_Leadsheet!$C$9="non-EMI",0,IF(K7+SAP_Leadsheet!$E$49-1>SAP_Leadsheet!$E$21,0,SAP_Leadsheet!$E$48*K21)) -> 0.001633329 | L34: =IF(SAP_Leadsheet!$C$9="non-EMI",0,IF(L7+SAP_Leadsheet!$E$49-1>SAP_Leadsheet!$E$21,0,SAP_Leadsheet!$E$48*L21)) -> 0.0016030562 | M34: =IF(SAP_Leadsheet!$C$9="non-EMI",0,IF(M7+SAP_Leadsheet!$E$49-1>SAP_Leadsheet!$E$21,0,SAP_Leadsheet!$E$48*M21)) -> 0.0015727834 | N34: =IF(SAP_Leadsheet!$C$9="non-EMI",0,IF(N7+SAP_Leadsheet!$E$49-1>SAP_Leadsheet!$E$21,0,SAP_Leadsheet!$E$48*N21)) -> 0.0015425107 | ... BN34: =IF(SAP_Leadsheet!$C$9="non-EMI",0,IF(BN7+SAP_Leadsheet!$E$49-1>SAP_Leadsheet!$E$21,0,SAP_Leadsheet!$E$48*BN21)) -> 0
D35: Paid off | F35: mVND | G35: =G36+G97 -> -0.00058480667 | H35: =H36+H97 -> -0.0011595224 | I35: =I36+I97 -> -0.0017241473 | J35: =J36+J97 -> -0.0016938745 | K35: =K36+K97 -> -0.0016636017 | L35: =L36+L97 -> -0.001633329 | M35: =M36+M97 -> -0.0016030562 | N35: =N36+N97 -> -0.0015727834 | ... BN35: =BN36+BN97 -> -0.00026097233
D36: Early payment | G36: =-SUM(G37:G96) -> 0 | H36: =-SUM(H37:H96) -> 0 | I36: =-SUM(I37:I96) -> 0 | J36: =-SUM(J37:J96) -> 0 | K36: =-SUM(K37:K96) -> 0 | L36: =-SUM(L37:L96) -> 0 | M36: =-SUM(M37:M96) -> 0 | N36: =-SUM(N37:N96) -> 0 | ... BN36: =-SUM(BN37:BN96) -> 0
C37: {=TRANSPOSE(G7:BN7)} -> 1 | G37: =IF(OR($C98>G$7,$C98+$E98-2<G$7),0,($D98-SUM($F98:F98)-SUM($F37:F37))*SAP_Leadsheet!$E$53) -> 0 | H37: =IF(OR($C98>H$7,$C98+$E98-2<H$7),0,($D98-SUM($F98:G98)-SUM($F37:G37))*SAP_Leadsheet!$E$53) -> 0 | I37: =IF(OR($C98>I$7,$C98+$E98-2<I$7),0,($D98-SUM($F98:H98)-SUM($F37:H37))*SAP_Leadsheet!$E$53) -> 0 | J37: =IF(OR($C98>J$7,$C98+$E98-2<J$7),0,($D98-SUM($F98:I98)-SUM($F37:I37))*SAP_Leadsheet!$E$53) -> 0 | K37: =IF(OR($C98>K$7,$C98+$E98-2<K$7),0,($D98-SUM($F98:J98)-SUM($F37:J37))*SAP_Leadsheet!$E$53) -> 0 | L37: =IF(OR($C98>L$7,$C98+$E98-2<L$7),0,($D98-SUM($F98:K98)-SUM($F37:K37))*SAP_Leadsheet!$E$53) -> 0 | M37: =IF(OR($C98>M$7,$C98+$E98-2<M$7),0,($D98-SUM($F98:L98)-SUM($F37:L37))*SAP_Leadsheet!$E$53) -> 0 | N37: =IF(OR($C98>N$7,$C98+$E98-2<N$7),0,($D98-SUM($F98:M98)-SUM($F37:M37))*SAP_Leadsheet!$E$53) -> 0 | ... BN37: =IF(OR($C98>BN$7,$C98+$E98-2<BN$7),0,($D98-SUM($F98:BM98)-SUM($F37:BM37))*SAP_Leadsheet!$E$53) -> 0
C38: 2 | G38: =IF(OR($C99>G$7,$C99+$E99-2<G$7),0,($D99-SUM($F99:F99)-SUM($F38:F38))*SAP_Leadsheet!$E$53) -> 0 | H38: =IF(OR($C99>H$7,$C99+$E99-2<H$7),0,($D99-SUM($F99:G99)-SUM($F38:G38))*SAP_Leadsheet!$E$53) -> 0 | I38: =IF(OR($C99>I$7,$C99+$E99-2<I$7),0,($D99-SUM($F99:H99)-SUM($F38:H38))*SAP_Leadsheet!$E$53) -> 0 | J38: =IF(OR($C99>J$7,$C99+$E99-2<J$7),0,($D99-SUM($F99:I99)-SUM($F38:I38))*SAP_Leadsheet!$E$53) -> 0 | K38: =IF(OR($C99>K$7,$C99+$E99-2<K$7),0,($D99-SUM($F99:J99)-SUM($F38:J38))*SAP_Leadsheet!$E$53) -> 0 | L38: =IF(OR($C99>L$7,$C99+$E99-2<L$7),0,($D99-SUM($F99:K99)-SUM($F38:K38))*SAP_Leadsheet!$E$53) -> 0 | M38: =IF(OR($C99>M$7,$C99+$E99-2<M$7),0,($D99-SUM($F99:L99)-SUM($F38:L38))*SAP_Leadsheet!$E$53) -> 0 | N38: =IF(OR($C99>N$7,$C99+$E99-2<N$7),0,($D99-SUM($F99:M99)-SUM($F38:M38))*SAP_Leadsheet!$E$53) -> 0 | ... BN38: =IF(OR($C99>BN$7,$C99+$E99-2<BN$7),0,($D99-SUM($F99:BM99)-SUM($F38:BM38))*SAP_Leadsheet!$E$53) -> 0
C39: 3 | G39: =IF(OR($C100>G$7,$C100+$E100-2<G$7),0,($D100-SUM($F100:F100)-SUM($F39:F39))*SAP_Leadsheet!$E$53) -> 0 | H39: =IF(OR($C100>H$7,$C100+$E100-2<H$7),0,($D100-SUM($F100:G100)-SUM($F39:G39))*SAP_Leadsheet!$E$53) -> 0 | I39: =IF(OR($C100>I$7,$C100+$E100-2<I$7),0,($D100-SUM($F100:H100)-SUM($F39:H39))*SAP_Leadsheet!$E$53) -> 0 | J39: =IF(OR($C100>J$7,$C100+$E100-2<J$7),0,($D100-SUM($F100:I100)-SUM($F39:I39))*SAP_Leadsheet!$E$53) -> 0 | K39: =IF(OR($C100>K$7,$C100+$E100-2<K$7),0,($D100-SUM($F100:J100)-SUM($F39:J39))*SAP_Leadsheet!$E$53) -> 0 | L39: =IF(OR($C100>L$7,$C100+$E100-2<L$7),0,($D100-SUM($F100:K100)-SUM($F39:K39))*SAP_Leadsheet!$E$53) -> 0 | M39: =IF(OR($C100>M$7,$C100+$E100-2<M$7),0,($D100-SUM($F100:L100)-SUM($F39:L39))*SAP_Leadsheet!$E$53) -> 0 | N39: =IF(OR($C100>N$7,$C100+$E100-2<N$7),0,($D100-SUM($F100:M100)-SUM($F39:M39))*SAP_Leadsheet!$E$53) -> 0 | ... BN39: =IF(OR($C100>BN$7,$C100+$E100-2<BN$7),0,($D100-SUM($F100:BM100)-SUM($F39:BM39))*SAP_Leadsheet!$E$53) -> 0
C40: 4 | G40: =IF(OR($C101>G$7,$C101+$E101-2<G$7),0,($D101-SUM($F101:F101)-SUM($F40:F40))*SAP_Leadsheet!$E$53) -> 0 | H40: =IF(OR($C101>H$7,$C101+$E101-2<H$7),0,($D101-SUM($F101:G101)-SUM($F40:G40))*SAP_Leadsheet!$E$53) -> 0 | I40: =IF(OR($C101>I$7,$C101+$E101-2<I$7),0,($D101-SUM($F101:H101)-SUM($F40:H40))*SAP_Leadsheet!$E$53) -> 0 | J40: =IF(OR($C101>J$7,$C101+$E101-2<J$7),0,($D101-SUM($F101:I101)-SUM($F40:I40))*SAP_Leadsheet!$E$53) -> 0 | K40: =IF(OR($C101>K$7,$C101+$E101-2<K$7),0,($D101-SUM($F101:J101)-SUM($F40:J40))*SAP_Leadsheet!$E$53) -> 0 | L40: =IF(OR($C101>L$7,$C101+$E101-2<L$7),0,($D101-SUM($F101:K101)-SUM($F40:K40))*SAP_Leadsheet!$E$53) -> 0 | M40: =IF(OR($C101>M$7,$C101+$E101-2<M$7),0,($D101-SUM($F101:L101)-SUM($F40:L40))*SAP_Leadsheet!$E$53) -> 0 | N40: =IF(OR($C101>N$7,$C101+$E101-2<N$7),0,($D101-SUM($F101:M101)-SUM($F40:M40))*SAP_Leadsheet!$E$53) -> 0 | ... BN40: =IF(OR($C101>BN$7,$C101+$E101-2<BN$7),0,($D101-SUM($F101:BM101)-SUM($F40:BM40))*SAP_Leadsheet!$E$53) -> 0
C41: 5 | G41: =IF(OR($C102>G$7,$C102+$E102-2<G$7),0,($D102-SUM($F102:F102)-SUM($F41:F41))*SAP_Leadsheet!$E$53) -> 0 | H41: =IF(OR($C102>H$7,$C102+$E102-2<H$7),0,($D102-SUM($F102:G102)-SUM($F41:G41))*SAP_Leadsheet!$E$53) -> 0 | I41: =IF(OR($C102>I$7,$C102+$E102-2<I$7),0,($D102-SUM($F102:H102)-SUM($F41:H41))*SAP_Leadsheet!$E$53) -> 0 | J41: =IF(OR($C102>J$7,$C102+$E102-2<J$7),0,($D102-SUM($F102:I102)-SUM($F41:I41))*SAP_Leadsheet!$E$53) -> 0 | K41: =IF(OR($C102>K$7,$C102+$E102-2<K$7),0,($D102-SUM($F102:J102)-SUM($F41:J41))*SAP_Leadsheet!$E$53) -> 0 | L41: =IF(OR($C102>L$7,$C102+$E102-2<L$7),0,($D102-SUM($F102:K102)-SUM($F41:K41))*SAP_Leadsheet!$E$53) -> 0 | M41: =IF(OR($C102>M$7,$C102+$E102-2<M$7),0,($D102-SUM($F102:L102)-SUM($F41:L41))*SAP_Leadsheet!$E$53) -> 0 | N41: =IF(OR($C102>N$7,$C102+$E102-2<N$7),0,($D102-SUM($F102:M102)-SUM($F41:M41))*SAP_Leadsheet!$E$53) -> 0 | ... BN41: =IF(OR($C102>BN$7,$C102+$E102-2<BN$7),0,($D102-SUM($F102:BM102)-SUM($F41:BM41))*SAP_Leadsheet!$E$53) -> 0
C42: 6 | G42: =IF(OR($C103>G$7,$C103+$E103-2<G$7),0,($D103-SUM($F103:F103)-SUM($F42:F42))*SAP_Leadsheet!$E$53) -> 0 | H42: =IF(OR($C103>H$7,$C103+$E103-2<H$7),0,($D103-SUM($F103:G103)-SUM($F42:G42))*SAP_Leadsheet!$E$53) -> 0 | I42: =IF(OR($C103>I$7,$C103+$E103-2<I$7),0,($D103-SUM($F103:H103)-SUM($F42:H42))*SAP_Leadsheet!$E$53) -> 0 | J42: =IF(OR($C103>J$7,$C103+$E103-2<J$7),0,($D103-SUM($F103:I103)-SUM($F42:I42))*SAP_Leadsheet!$E$53) -> 0 | K42: =IF(OR($C103>K$7,$C103+$E103-2<K$7),0,($D103-SUM($F103:J103)-SUM($F42:J42))*SAP_Leadsheet!$E$53) -> 0 | L42: =IF(OR($C103>L$7,$C103+$E103-2<L$7),0,($D103-SUM($F103:K103)-SUM($F42:K42))*SAP_Leadsheet!$E$53) -> 0 | M42: =IF(OR($C103>M$7,$C103+$E103-2<M$7),0,($D103-SUM($F103:L103)-SUM($F42:L42))*SAP_Leadsheet!$E$53) -> 0 | N42: =IF(OR($C103>N$7,$C103+$E103-2<N$7),0,($D103-SUM($F103:M103)-SUM($F42:M42))*SAP_Leadsheet!$E$53) -> 0 | ... BN42: =IF(OR($C103>BN$7,$C103+$E103-2<BN$7),0,($D103-SUM($F103:BM103)-SUM($F42:BM42))*SAP_Leadsheet!$E$53) -> 0
C43: 7 | G43: =IF(OR($C104>G$7,$C104+$E104-2<G$7),0,($D104-SUM($F104:F104)-SUM($F43:F43))*SAP_Leadsheet!$E$53) -> 0 | H43: =IF(OR($C104>H$7,$C104+$E104-2<H$7),0,($D104-SUM($F104:G104)-SUM($F43:G43))*SAP_Leadsheet!$E$53) -> 0 | I43: =IF(OR($C104>I$7,$C104+$E104-2<I$7),0,($D104-SUM($F104:H104)-SUM($F43:H43))*SAP_Leadsheet!$E$53) -> 0 | J43: =IF(OR($C104>J$7,$C104+$E104-2<J$7),0,($D104-SUM($F104:I104)-SUM($F43:I43))*SAP_Leadsheet!$E$53) -> 0 | K43: =IF(OR($C104>K$7,$C104+$E104-2<K$7),0,($D104-SUM($F104:J104)-SUM($F43:J43))*SAP_Leadsheet!$E$53) -> 0 | L43: =IF(OR($C104>L$7,$C104+$E104-2<L$7),0,($D104-SUM($F104:K104)-SUM($F43:K43))*SAP_Leadsheet!$E$53) -> 0 | M43: =IF(OR($C104>M$7,$C104+$E104-2<M$7),0,($D104-SUM($F104:L104)-SUM($F43:L43))*SAP_Leadsheet!$E$53) -> 0 | N43: =IF(OR($C104>N$7,$C104+$E104-2<N$7),0,($D104-SUM($F104:M104)-SUM($F43:M43))*SAP_Leadsheet!$E$53) -> 0 | ... BN43: =IF(OR($C104>BN$7,$C104+$E104-2<BN$7),0,($D104-SUM($F104:BM104)-SUM($F43:BM43))*SAP_Leadsheet!$E$53) -> 0
C44: 8 | G44: =IF(OR($C105>G$7,$C105+$E105-2<G$7),0,($D105-SUM($F105:F105)-SUM($F44:F44))*SAP_Leadsheet!$E$53) -> 0 | H44: =IF(OR($C105>H$7,$C105+$E105-2<H$7),0,($D105-SUM($F105:G105)-SUM($F44:G44))*SAP_Leadsheet!$E$53) -> 0 | I44: =IF(OR($C105>I$7,$C105+$E105-2<I$7),0,($D105-SUM($F105:H105)-SUM($F44:H44))*SAP_Leadsheet!$E$53) -> 0 | J44: =IF(OR($C105>J$7,$C105+$E105-2<J$7),0,($D105-SUM($F105:I105)-SUM($F44:I44))*SAP_Leadsheet!$E$53) -> 0 | K44: =IF(OR($C105>K$7,$C105+$E105-2<K$7),0,($D105-SUM($F105:J105)-SUM($F44:J44))*SAP_Leadsheet!$E$53) -> 0 | L44: =IF(OR($C105>L$7,$C105+$E105-2<L$7),0,($D105-SUM($F105:K105)-SUM($F44:K44))*SAP_Leadsheet!$E$53) -> 0 | M44: =IF(OR($C105>M$7,$C105+$E105-2<M$7),0,($D105-SUM($F105:L105)-SUM($F44:L44))*SAP_Leadsheet!$E$53) -> 0 | N44: =IF(OR($C105>N$7,$C105+$E105-2<N$7),0,($D105-SUM($F105:M105)-SUM($F44:M44))*SAP_Leadsheet!$E$53) -> 0 | ... BN44: =IF(OR($C105>BN$7,$C105+$E105-2<BN$7),0,($D105-SUM($F105:BM105)-SUM($F44:BM44))*SAP_Leadsheet!$E$53) -> 0
C45: 9 | G45: =IF(OR($C106>G$7,$C106+$E106-2<G$7),0,($D106-SUM($F106:F106)-SUM($F45:F45))*SAP_Leadsheet!$E$53) -> 0 | H45: =IF(OR($C106>H$7,$C106+$E106-2<H$7),0,($D106-SUM($F106:G106)-SUM($F45:G45))*SAP_Leadsheet!$E$53) -> 0 | I45: =IF(OR($C106>I$7,$C106+$E106-2<I$7),0,($D106-SUM($F106:H106)-SUM($F45:H45))*SAP_Leadsheet!$E$53) -> 0 | J45: =IF(OR($C106>J$7,$C106+$E106-2<J$7),0,($D106-SUM($F106:I106)-SUM($F45:I45))*SAP_Leadsheet!$E$53) -> 0 | K45: =IF(OR($C106>K$7,$C106+$E106-2<K$7),0,($D106-SUM($F106:J106)-SUM($F45:J45))*SAP_Leadsheet!$E$53) -> 0 | L45: =IF(OR($C106>L$7,$C106+$E106-2<L$7),0,($D106-SUM($F106:K106)-SUM($F45:K45))*SAP_Leadsheet!$E$53) -> 0 | M45: =IF(OR($C106>M$7,$C106+$E106-2<M$7),0,($D106-SUM($F106:L106)-SUM($F45:L45))*SAP_Leadsheet!$E$53) -> 0 | N45: =IF(OR($C106>N$7,$C106+$E106-2<N$7),0,($D106-SUM($F106:M106)-SUM($F45:M45))*SAP_Leadsheet!$E$53) -> 0 | ... BN45: =IF(OR($C106>BN$7,$C106+$E106-2<BN$7),0,($D106-SUM($F106:BM106)-SUM($F45:BM45))*SAP_Leadsheet!$E$53) -> 0
C46: 10 | G46: =IF(OR($C107>G$7,$C107+$E107-2<G$7),0,($D107-SUM($F107:F107)-SUM($F46:F46))*SAP_Leadsheet!$E$53) -> 0 | H46: =IF(OR($C107>H$7,$C107+$E107-2<H$7),0,($D107-SUM($F107:G107)-SUM($F46:G46))*SAP_Leadsheet!$E$53) -> 0 | I46: =IF(OR($C107>I$7,$C107+$E107-2<I$7),0,($D107-SUM($F107:H107)-SUM($F46:H46))*SAP_Leadsheet!$E$53) -> 0 | J46: =IF(OR($C107>J$7,$C107+$E107-2<J$7),0,($D107-SUM($F107:I107)-SUM($F46:I46))*SAP_Leadsheet!$E$53) -> 0 | K46: =IF(OR($C107>K$7,$C107+$E107-2<K$7),0,($D107-SUM($F107:J107)-SUM($F46:J46))*SAP_Leadsheet!$E$53) -> 0 | L46: =IF(OR($C107>L$7,$C107+$E107-2<L$7),0,($D107-SUM($F107:K107)-SUM($F46:K46))*SAP_Leadsheet!$E$53) -> 0 | M46: =IF(OR($C107>M$7,$C107+$E107-2<M$7),0,($D107-SUM($F107:L107)-SUM($F46:L46))*SAP_Leadsheet!$E$53) -> 0 | N46: =IF(OR($C107>N$7,$C107+$E107-2<N$7),0,($D107-SUM($F107:M107)-SUM($F46:M46))*SAP_Leadsheet!$E$53) -> 0 | ... BN46: =IF(OR($C107>BN$7,$C107+$E107-2<BN$7),0,($D107-SUM($F107:BM107)-SUM($F46:BM46))*SAP_Leadsheet!$E$53) -> 0
C47: 11 | G47: =IF(OR($C108>G$7,$C108+$E108-2<G$7),0,($D108-SUM($F108:F108)-SUM($F47:F47))*SAP_Leadsheet!$E$53) -> 0 | H47: =IF(OR($C108>H$7,$C108+$E108-2<H$7),0,($D108-SUM($F108:G108)-SUM($F47:G47))*SAP_Leadsheet!$E$53) -> 0 | I47: =IF(OR($C108>I$7,$C108+$E108-2<I$7),0,($D108-SUM($F108:H108)-SUM($F47:H47))*SAP_Leadsheet!$E$53) -> 0 | J47: =IF(OR($C108>J$7,$C108+$E108-2<J$7),0,($D108-SUM($F108:I108)-SUM($F47:I47))*SAP_Leadsheet!$E$53) -> 0 | K47: =IF(OR($C108>K$7,$C108+$E108-2<K$7),0,($D108-SUM($F108:J108)-SUM($F47:J47))*SAP_Leadsheet!$E$53) -> 0 | L47: =IF(OR($C108>L$7,$C108+$E108-2<L$7),0,($D108-SUM($F108:K108)-SUM($F47:K47))*SAP_Leadsheet!$E$53) -> 0 | M47: =IF(OR($C108>M$7,$C108+$E108-2<M$7),0,($D108-SUM($F108:L108)-SUM($F47:L47))*SAP_Leadsheet!$E$53) -> 0 | N47: =IF(OR($C108>N$7,$C108+$E108-2<N$7),0,($D108-SUM($F108:M108)-SUM($F47:M47))*SAP_Leadsheet!$E$53) -> 0 | ... BN47: =IF(OR($C108>BN$7,$C108+$E108-2<BN$7),0,($D108-SUM($F108:BM108)-SUM($F47:BM47))*SAP_Leadsheet!$E$53) -> 0
C48: 12 | G48: =IF(OR($C109>G$7,$C109+$E109-2<G$7),0,($D109-SUM($F109:F109)-SUM($F48:F48))*SAP_Leadsheet!$E$53) -> 0 | H48: =IF(OR($C109>H$7,$C109+$E109-2<H$7),0,($D109-SUM($F109:G109)-SUM($F48:G48))*SAP_Leadsheet!$E$53) -> 0 | I48: =IF(OR($C109>I$7,$C109+$E109-2<I$7),0,($D109-SUM($F109:H109)-SUM($F48:H48))*SAP_Leadsheet!$E$53) -> 0 | J48: =IF(OR($C109>J$7,$C109+$E109-2<J$7),0,($D109-SUM($F109:I109)-SUM($F48:I48))*SAP_Leadsheet!$E$53) -> 0 | K48: =IF(OR($C109>K$7,$C109+$E109-2<K$7),0,($D109-SUM($F109:J109)-SUM($F48:J48))*SAP_Leadsheet!$E$53) -> 0 | L48: =IF(OR($C109>L$7,$C109+$E109-2<L$7),0,($D109-SUM($F109:K109)-SUM($F48:K48))*SAP_Leadsheet!$E$53) -> 0 | M48: =IF(OR($C109>M$7,$C109+$E109-2<M$7),0,($D109-SUM($F109:L109)-SUM($F48:L48))*SAP_Leadsheet!$E$53) -> 0 | N48: =IF(OR($C109>N$7,$C109+$E109-2<N$7),0,($D109-SUM($F109:M109)-SUM($F48:M48))*SAP_Leadsheet!$E$53) -> 0 | ... BN48: =IF(OR($C109>BN$7,$C109+$E109-2<BN$7),0,($D109-SUM($F109:BM109)-SUM($F48:BM48))*SAP_Leadsheet!$E$53) -> 0
C49: 13 | G49: =IF(OR($C110>G$7,$C110+$E110-2<G$7),0,($D110-SUM($F110:F110)-SUM($F49:F49))*SAP_Leadsheet!$E$53) -> 0 | H49: =IF(OR($C110>H$7,$C110+$E110-2<H$7),0,($D110-SUM($F110:G110)-SUM($F49:G49))*SAP_Leadsheet!$E$53) -> 0 | I49: =IF(OR($C110>I$7,$C110+$E110-2<I$7),0,($D110-SUM($F110:H110)-SUM($F49:H49))*SAP_Leadsheet!$E$53) -> 0 | J49: =IF(OR($C110>J$7,$C110+$E110-2<J$7),0,($D110-SUM($F110:I110)-SUM($F49:I49))*SAP_Leadsheet!$E$53) -> 0 | K49: =IF(OR($C110>K$7,$C110+$E110-2<K$7),0,($D110-SUM($F110:J110)-SUM($F49:J49))*SAP_Leadsheet!$E$53) -> 0 | L49: =IF(OR($C110>L$7,$C110+$E110-2<L$7),0,($D110-SUM($F110:K110)-SUM($F49:K49))*SAP_Leadsheet!$E$53) -> 0 | M49: =IF(OR($C110>M$7,$C110+$E110-2<M$7),0,($D110-SUM($F110:L110)-SUM($F49:L49))*SAP_Leadsheet!$E$53) -> 0 | N49: =IF(OR($C110>N$7,$C110+$E110-2<N$7),0,($D110-SUM($F110:M110)-SUM($F49:M49))*SAP_Leadsheet!$E$53) -> 0 | ... BN49: =IF(OR($C110>BN$7,$C110+$E110-2<BN$7),0,($D110-SUM($F110:BM110)-SUM($F49:BM49))*SAP_Leadsheet!$E$53) -> 0
... C96: 60 | G96: =IF(OR($C157>G$7,$C157+$E157-2<G$7),0,($D157-SUM($F157:F157)-SUM($F96:F96))*SAP_Leadsheet!$E$53) -> 0 | H96: =IF(OR($C157>H$7,$C157+$E157-2<H$7),0,($D157-SUM($F157:G157)-SUM($F96:G96))*SAP_Leadsheet!$E$53) -> 0 | I96: =IF(OR($C157>I$7,$C157+$E157-2<I$7),0,($D157-SUM($F157:H157)-SUM($F96:H96))*SAP_Leadsheet!$E$53) -> 0 | J96: =IF(OR($C157>J$7,$C157+$E157-2<J$7),0,($D157-SUM($F157:I157)-SUM($F96:I96))*SAP_Leadsheet!$E$53) -> 0 | K96: =IF(OR($C157>K$7,$C157+$E157-2<K$7),0,($D157-SUM($F157:J157)-SUM($F96:J96))*SAP_Leadsheet!$E$53) -> 0 | L96: =IF(OR($C157>L$7,$C157+$E157-2<L$7),0,($D157-SUM($F157:K157)-SUM($F96:K96))*SAP_Leadsheet!$E$53) -> 0 | M96: =IF(OR($C157>M$7,$C157+$E157-2<M$7),0,($D157-SUM($F157:L157)-SUM($F96:L96))*SAP_Leadsheet!$E$53) -> 0 | N96: =IF(OR($C157>N$7,$C157+$E157-2<N$7),0,($D157-SUM($F157:M157)-SUM($F96:M96))*SAP_Leadsheet!$E$53) -> 0 | ... BN96: =IF(OR($C157>BN$7,$C157+$E157-2<BN$7),0,($D157-SUM($F157:BM157)-SUM($F96:BM96))*SAP_Leadsheet!$E$53) -> 0
D97: Normal payment | G97: =-SUM(G98:G157) -> -0.00058480667 | H97: =-SUM(H98:H157) -> -0.0011595224 | I97: =-SUM(I98:I157) -> -0.0017241473 | J97: =-SUM(J98:J157) -> -0.0016938745 | K97: =-SUM(K98:K157) -> -0.0016636017 | L97: =-SUM(L98:L157) -> -0.001633329 | M97: =-SUM(M98:M157) -> -0.0016030562 | N97: =-SUM(N98:N157) -> -0.0015727834 | ... BN97: =-SUM(BN98:BN157) -> -0.00026097233
C98: {=TRANSPOSE(G7:BN7)} -> 1 | D98: {=TRANSPOSE(G34:BN34)} -> 0.00175442 | E98: =SAP_Leadsheet!$E$49 -> 3 | G98: =IF(OR($C98>G$7,$C98+$E98-1<G$7),0,($D98-SUM($F98:F98)-SUM($F37:F37))/($E98+$C98-G$7)) -> 0.00058480667 | H98: =IF(OR($C98>H$7,$C98+$E98-1<H$7),0,($D98-SUM($F98:G98)-SUM($F37:G37))/($E98+$C98-H$7)) -> 0.00058480667 | I98: =IF(OR($C98>I$7,$C98+$E98-1<I$7),0,($D98-SUM($F98:H98)-SUM($F37:H37))/($E98+$C98-I$7)) -> 0.00058480667 | J98: =IF(OR($C98>J$7,$C98+$E98-1<J$7),0,($D98-SUM($F98:I98)-SUM($F37:I37))/($E98+$C98-J$7)) -> 0 | K98: =IF(OR($C98>K$7,$C98+$E98-1<K$7),0,($D98-SUM($F98:J98)-SUM($F37:J37))/($E98+$C98-K$7)) -> 0 | L98: =IF(OR($C98>L$7,$C98+$E98-1<L$7),0,($D98-SUM($F98:K98)-SUM($F37:K37))/($E98+$C98-L$7)) -> 0 | M98: =IF(OR($C98>M$7,$C98+$E98-1<M$7),0,($D98-SUM($F98:L98)-SUM($F37:L37))/($E98+$C98-M$7)) -> 0 | N98: =IF(OR($C98>N$7,$C98+$E98-1<N$7),0,($D98-SUM($F98:M98)-SUM($F37:M37))/($E98+$C98-N$7)) -> 0 | ... BN98: =IF(OR($C98>BN$7,$C98+$E98-1<BN$7),0,($D98-SUM($F98:BM98)-SUM($F37:BM37))/($E98+$C98-BN$7)) -> 0
C99: 2 | D99: 0.0017241473 | E99: =SAP_Leadsheet!$E$49 -> 3 | G99: =IF(OR($C99>G$7,$C99+$E99-1<G$7),0,($D99-SUM($F99:F99)-SUM($F38:F38))/($E99+$C99-G$7)) -> 0 | H99: =IF(OR($C99>H$7,$C99+$E99-1<H$7),0,($D99-SUM($F99:G99)-SUM($F38:G38))/($E99+$C99-H$7)) -> 0.00057471575 | I99: =IF(OR($C99>I$7,$C99+$E99-1<I$7),0,($D99-SUM($F99:H99)-SUM($F38:H38))/($E99+$C99-I$7)) -> 0.00057471575 | J99: =IF(OR($C99>J$7,$C99+$E99-1<J$7),0,($D99-SUM($F99:I99)-SUM($F38:I38))/($E99+$C99-J$7)) -> 0.00057471575 | K99: =IF(OR($C99>K$7,$C99+$E99-1<K$7),0,($D99-SUM($F99:J99)-SUM($F38:J38))/($E99+$C99-K$7)) -> 0 | L99: =IF(OR($C99>L$7,$C99+$E99-1<L$7),0,($D99-SUM($F99:K99)-SUM($F38:K38))/($E99+$C99-L$7)) -> 0 | M99: =IF(OR($C99>M$7,$C99+$E99-1<M$7),0,($D99-SUM($F99:L99)-SUM($F38:L38))/($E99+$C99-M$7)) -> 0 | N99: =IF(OR($C99>N$7,$C99+$E99-1<N$7),0,($D99-SUM($F99:M99)-SUM($F38:M38))/($E99+$C99-N$7)) -> 0 | ... BN99: =IF(OR($C99>BN$7,$C99+$E99-1<BN$7),0,($D99-SUM($F99:BM99)-SUM($F38:BM38))/($E99+$C99-BN$7)) -> 0
C100: 3 | D100: 0.0016938745 | E100: =SAP_Leadsheet!$E$49 -> 3 | G100: =IF(OR($C100>G$7,$C100+$E100-1<G$7),0,($D100-SUM($F100:F100)-SUM($F39:F39))/($E100+$C100-G$7)) -> 0 | H100: =IF(OR($C100>H$7,$C100+$E100-1<H$7),0,($D100-SUM($F100:G100)-SUM($F39:G39))/($E100+$C100-H$7)) -> 0 | I100: =IF(OR($C100>I$7,$C100+$E100-1<I$7),0,($D100-SUM($F100:H100)-SUM($F39:H39))/($E100+$C100-I$7)) -> 0.00056462483 | J100: =IF(OR($C100>J$7,$C100+$E100-1<J$7),0,($D100-SUM($F100:I100)-SUM($F39:I39))/($E100+$C100-J$7)) -> 0.00056462483 | K100: =IF(OR($C100>K$7,$C100+$E100-1<K$7),0,($D100-SUM($F100:J100)-SUM($F39:J39))/($E100+$C100-K$7)) -> 0.00056462483 | L100: =IF(OR($C100>L$7,$C100+$E100-1<L$7),0,($D100-SUM($F100:K100)-SUM($F39:K39))/($E100+$C100-L$7)) -> 0 | M100: =IF(OR($C100>M$7,$C100+$E100-1<M$7),0,($D100-SUM($F100:L100)-SUM($F39:L39))/($E100+$C100-M$7)) -> 0 | N100: =IF(OR($C100>N$7,$C100+$E100-1<N$7),0,($D100-SUM($F100:M100)-SUM($F39:M39))/($E100+$C100-N$7)) -> 0 | ... BN100: =IF(OR($C100>BN$7,$C100+$E100-1<BN$7),0,($D100-SUM($F100:BM100)-SUM($F39:BM39))/($E100+$C100-BN$7)) -> 0
C101: 4 | D101: 0.0016636017 | E101: =SAP_Leadsheet!$E$49 -> 3 | G101: =IF(OR($C101>G$7,$C101+$E101-1<G$7),0,($D101-SUM($F101:F101)-SUM($F40:F40))/($E101+$C101-G$7)) -> 0 | H101: =IF(OR($C101>H$7,$C101+$E101-1<H$7),0,($D101-SUM($F101:G101)-SUM($F40:G40))/($E101+$C101-H$7)) -> 0 | I101: =IF(OR($C101>I$7,$C101+$E101-1<I$7),0,($D101-SUM($F101:H101)-SUM($F40:H40))/($E101+$C101-I$7)) -> 0 | J101: =IF(OR($C101>J$7,$C101+$E101-1<J$7),0,($D101-SUM($F101:I101)-SUM($F40:I40))/($E101+$C101-J$7)) -> 0.00055453391 | K101: =IF(OR($C101>K$7,$C101+$E101-1<K$7),0,($D101-SUM($F101:J101)-SUM($F40:J40))/($E101+$C101-K$7)) -> 0.00055453391 | L101: =IF(OR($C101>L$7,$C101+$E101-1<L$7),0,($D101-SUM($F101:K101)-SUM($F40:K40))/($E101+$C101-L$7)) -> 0.00055453391 | M101: =IF(OR($C101>M$7,$C101+$E101-1<M$7),0,($D101-SUM($F101:L101)-SUM($F40:L40))/($E101+$C101-M$7)) -> 0 | N101: =IF(OR($C101>N$7,$C101+$E101-1<N$7),0,($D101-SUM($F101:M101)-SUM($F40:M40))/($E101+$C101-N$7)) -> 0 | ... BN101: =IF(OR($C101>BN$7,$C101+$E101-1<BN$7),0,($D101-SUM($F101:BM101)-SUM($F40:BM40))/($E101+$C101-BN$7)) -> 0
C102: 5 | D102: 0.001633329 | E102: =SAP_Leadsheet!$E$49 -> 3 | G102: =IF(OR($C102>G$7,$C102+$E102-1<G$7),0,($D102-SUM($F102:F102)-SUM($F41:F41))/($E102+$C102-G$7)) -> 0 | H102: =IF(OR($C102>H$7,$C102+$E102-1<H$7),0,($D102-SUM($F102:G102)-SUM($F41:G41))/($E102+$C102-H$7)) -> 0 | I102: =IF(OR($C102>I$7,$C102+$E102-1<I$7),0,($D102-SUM($F102:H102)-SUM($F41:H41))/($E102+$C102-I$7)) -> 0 | J102: =IF(OR($C102>J$7,$C102+$E102-1<J$7),0,($D102-SUM($F102:I102)-SUM($F41:I41))/($E102+$C102-J$7)) -> 0 | K102: =IF(OR($C102>K$7,$C102+$E102-1<K$7),0,($D102-SUM($F102:J102)-SUM($F41:J41))/($E102+$C102-K$7)) -> 0.00054444299 | L102: =IF(OR($C102>L$7,$C102+$E102-1<L$7),0,($D102-SUM($F102:K102)-SUM($F41:K41))/($E102+$C102-L$7)) -> 0.00054444299 | M102: =IF(OR($C102>M$7,$C102+$E102-1<M$7),0,($D102-SUM($F102:L102)-SUM($F41:L41))/($E102+$C102-M$7)) -> 0.00054444299 | N102: =IF(OR($C102>N$7,$C102+$E102-1<N$7),0,($D102-SUM($F102:M102)-SUM($F41:M41))/($E102+$C102-N$7)) -> 0 | ... BN102: =IF(OR($C102>BN$7,$C102+$E102-1<BN$7),0,($D102-SUM($F102:BM102)-SUM($F41:BM41))/($E102+$C102-BN$7)) -> 0
C103: 6 | D103: 0.0016030562 | E103: =SAP_Leadsheet!$E$49 -> 3 | G103: =IF(OR($C103>G$7,$C103+$E103-1<G$7),0,($D103-SUM($F103:F103)-SUM($F42:F42))/($E103+$C103-G$7)) -> 0 | H103: =IF(OR($C103>H$7,$C103+$E103-1<H$7),0,($D103-SUM($F103:G103)-SUM($F42:G42))/($E103+$C103-H$7)) -> 0 | I103: =IF(OR($C103>I$7,$C103+$E103-1<I$7),0,($D103-SUM($F103:H103)-SUM($F42:H42))/($E103+$C103-I$7)) -> 0 | J103: =IF(OR($C103>J$7,$C103+$E103-1<J$7),0,($D103-SUM($F103:I103)-SUM($F42:I42))/($E103+$C103-J$7)) -> 0 | K103: =IF(OR($C103>K$7,$C103+$E103-1<K$7),0,($D103-SUM($F103:J103)-SUM($F42:J42))/($E103+$C103-K$7)) -> 0 | L103: =IF(OR($C103>L$7,$C103+$E103-1<L$7),0,($D103-SUM($F103:K103)-SUM($F42:K42))/($E103+$C103-L$7)) -> 0.00053435207 | M103: =IF(OR($C103>M$7,$C103+$E103-1<M$7),0,($D103-SUM($F103:L103)-SUM($F42:L42))/($E103+$C103-M$7)) -> 0.00053435207 | N103: =IF(OR($C103>N$7,$C103+$E103-1<N$7),0,($D103-SUM($F103:M103)-SUM($F42:M42))/($E103+$C103-N$7)) -> 0.00053435207 | ... BN103: =IF(OR($C103>BN$7,$C103+$E103-1<BN$7),0,($D103-SUM($F103:BM103)-SUM($F42:BM42))/($E103+$C103-BN$7)) -> 0
C104: 7 | D104: 0.0015727834 | E104: =SAP_Leadsheet!$E$49 -> 3 | G104: =IF(OR($C104>G$7,$C104+$E104-1<G$7),0,($D104-SUM($F104:F104)-SUM($F43:F43))/($E104+$C104-G$7)) -> 0 | H104: =IF(OR($C104>H$7,$C104+$E104-1<H$7),0,($D104-SUM($F104:G104)-SUM($F43:G43))/($E104+$C104-H$7)) -> 0 | I104: =IF(OR($C104>I$7,$C104+$E104-1<I$7),0,($D104-SUM($F104:H104)-SUM($F43:H43))/($E104+$C104-I$7)) -> 0 | J104: =IF(OR($C104>J$7,$C104+$E104-1<J$7),0,($D104-SUM($F104:I104)-SUM($F43:I43))/($E104+$C104-J$7)) -> 0 | K104: =IF(OR($C104>K$7,$C104+$E104-1<K$7),0,($D104-SUM($F104:J104)-SUM($F43:J43))/($E104+$C104-K$7)) -> 0 | L104: =IF(OR($C104>L$7,$C104+$E104-1<L$7),0,($D104-SUM($F104:K104)-SUM($F43:K43))/($E104+$C104-L$7)) -> 0 | M104: =IF(OR($C104>M$7,$C104+$E104-1<M$7),0,($D104-SUM($F104:L104)-SUM($F43:L43))/($E104+$C104-M$7)) -> 0.00052426114 | N104: =IF(OR($C104>N$7,$C104+$E104-1<N$7),0,($D104-SUM($F104:M104)-SUM($F43:M43))/($E104+$C104-N$7)) -> 0.00052426114 | ... BN104: =IF(OR($C104>BN$7,$C104+$E104-1<BN$7),0,($D104-SUM($F104:BM104)-SUM($F43:BM43))/($E104+$C104-BN$7)) -> 0
C105: 8 | D105: 0.0015425107 | E105: =SAP_Leadsheet!$E$49 -> 3 | G105: =IF(OR($C105>G$7,$C105+$E105-1<G$7),0,($D105-SUM($F105:F105)-SUM($F44:F44))/($E105+$C105-G$7)) -> 0 | H105: =IF(OR($C105>H$7,$C105+$E105-1<H$7),0,($D105-SUM($F105:G105)-SUM($F44:G44))/($E105+$C105-H$7)) -> 0 | I105: =IF(OR($C105>I$7,$C105+$E105-1<I$7),0,($D105-SUM($F105:H105)-SUM($F44:H44))/($E105+$C105-I$7)) -> 0 | J105: =IF(OR($C105>J$7,$C105+$E105-1<J$7),0,($D105-SUM($F105:I105)-SUM($F44:I44))/($E105+$C105-J$7)) -> 0 | K105: =IF(OR($C105>K$7,$C105+$E105-1<K$7),0,($D105-SUM($F105:J105)-SUM($F44:J44))/($E105+$C105-K$7)) -> 0 | L105: =IF(OR($C105>L$7,$C105+$E105-1<L$7),0,($D105-SUM($F105:K105)-SUM($F44:K44))/($E105+$C105-L$7)) -> 0 | M105: =IF(OR($C105>M$7,$C105+$E105-1<M$7),0,($D105-SUM($F105:L105)-SUM($F44:L44))/($E105+$C105-M$7)) -> 0 | N105: =IF(OR($C105>N$7,$C105+$E105-1<N$7),0,($D105-SUM($F105:M105)-SUM($F44:M44))/($E105+$C105-N$7)) -> 0.00051417022 | ... BN105: =IF(OR($C105>BN$7,$C105+$E105-1<BN$7),0,($D105-SUM($F105:BM105)-SUM($F44:BM44))/($E105+$C105-BN$7)) -> 0
C106: 9 | D106: 0.0015122379 | E106: =SAP_Leadsheet!$E$49 -> 3 | G106: =IF(OR($C106>G$7,$C106+$E106-1<G$7),0,($D106-SUM($F106:F106)-SUM($F45:F45))/($E106+$C106-G$7)) -> 0 | H106: =IF(OR($C106>H$7,$C106+$E106-1<H$7),0,($D106-SUM($F106:G106)-SUM($F45:G45))/($E106+$C106-H$7)) -> 0 | I106: =IF(OR($C106>I$7,$C106+$E106-1<I$7),0,($D106-SUM($F106:H106)-SUM($F45:H45))/($E106+$C106-I$7)) -> 0 | J106: =IF(OR($C106>J$7,$C106+$E106-1<J$7),0,($D106-SUM($F106:I106)-SUM($F45:I45))/($E106+$C106-J$7)) -> 0 | K106: =IF(OR($C106>K$7,$C106+$E106-1<K$7),0,($D106-SUM($F106:J106)-SUM($F45:J45))/($E106+$C106-K$7)) -> 0 | L106: =IF(OR($C106>L$7,$C106+$E106-1<L$7),0,($D106-SUM($F106:K106)-SUM($F45:K45))/($E106+$C106-L$7)) -> 0 | M106: =IF(OR($C106>M$7,$C106+$E106-1<M$7),0,($D106-SUM($F106:L106)-SUM($F45:L45))/($E106+$C106-M$7)) -> 0 | N106: =IF(OR($C106>N$7,$C106+$E106-1<N$7),0,($D106-SUM($F106:M106)-SUM($F45:M45))/($E106+$C106-N$7)) -> 0 | ... BN106: =IF(OR($C106>BN$7,$C106+$E106-1<BN$7),0,($D106-SUM($F106:BM106)-SUM($F45:BM45))/($E106+$C106-BN$7)) -> 0
C107: 10 | D107: 0.0014819651 | E107: =SAP_Leadsheet!$E$49 -> 3 | G107: =IF(OR($C107>G$7,$C107+$E107-1<G$7),0,($D107-SUM($F107:F107)-SUM($F46:F46))/($E107+$C107-G$7)) -> 0 | H107: =IF(OR($C107>H$7,$C107+$E107-1<H$7),0,($D107-SUM($F107:G107)-SUM($F46:G46))/($E107+$C107-H$7)) -> 0 | I107: =IF(OR($C107>I$7,$C107+$E107-1<I$7),0,($D107-SUM($F107:H107)-SUM($F46:H46))/($E107+$C107-I$7)) -> 0 | J107: =IF(OR($C107>J$7,$C107+$E107-1<J$7),0,($D107-SUM($F107:I107)-SUM($F46:I46))/($E107+$C107-J$7)) -> 0 | K107: =IF(OR($C107>K$7,$C107+$E107-1<K$7),0,($D107-SUM($F107:J107)-SUM($F46:J46))/($E107+$C107-K$7)) -> 0 | L107: =IF(OR($C107>L$7,$C107+$E107-1<L$7),0,($D107-SUM($F107:K107)-SUM($F46:K46))/($E107+$C107-L$7)) -> 0 | M107: =IF(OR($C107>M$7,$C107+$E107-1<M$7),0,($D107-SUM($F107:L107)-SUM($F46:L46))/($E107+$C107-M$7)) -> 0 | N107: =IF(OR($C107>N$7,$C107+$E107-1<N$7),0,($D107-SUM($F107:M107)-SUM($F46:M46))/($E107+$C107-N$7)) -> 0 | ... BN107: =IF(OR($C107>BN$7,$C107+$E107-1<BN$7),0,($D107-SUM($F107:BM107)-SUM($F46:BM46))/($E107+$C107-BN$7)) -> 0
C108: 11 | D108: 0.0014516924 | E108: =SAP_Leadsheet!$E$49 -> 3 | G108: =IF(OR($C108>G$7,$C108+$E108-1<G$7),0,($D108-SUM($F108:F108)-SUM($F47:F47))/($E108+$C108-G$7)) -> 0 | H108: =IF(OR($C108>H$7,$C108+$E108-1<H$7),0,($D108-SUM($F108:G108)-SUM($F47:G47))/($E108+$C108-H$7)) -> 0 | I108: =IF(OR($C108>I$7,$C108+$E108-1<I$7),0,($D108-SUM($F108:H108)-SUM($F47:H47))/($E108+$C108-I$7)) -> 0 | J108: =IF(OR($C108>J$7,$C108+$E108-1<J$7),0,($D108-SUM($F108:I108)-SUM($F47:I47))/($E108+$C108-J$7)) -> 0 | K108: =IF(OR($C108>K$7,$C108+$E108-1<K$7),0,($D108-SUM($F108:J108)-SUM($F47:J47))/($E108+$C108-K$7)) -> 0 | L108: =IF(OR($C108>L$7,$C108+$E108-1<L$7),0,($D108-SUM($F108:K108)-SUM($F47:K47))/($E108+$C108-L$7)) -> 0 | M108: =IF(OR($C108>M$7,$C108+$E108-1<M$7),0,($D108-SUM($F108:L108)-SUM($F47:L47))/($E108+$C108-M$7)) -> 0 | N108: =IF(OR($C108>N$7,$C108+$E108-1<N$7),0,($D108-SUM($F108:M108)-SUM($F47:M47))/($E108+$C108-N$7)) -> 0 | ... BN108: =IF(OR($C108>BN$7,$C108+$E108-1<BN$7),0,($D108-SUM($F108:BM108)-SUM($F47:BM47))/($E108+$C108-BN$7)) -> 0
C109: 12 | D109: 0.0014214196 | E109: =SAP_Leadsheet!$E$49 -> 3 | G109: =IF(OR($C109>G$7,$C109+$E109-1<G$7),0,($D109-SUM($F109:F109)-SUM($F48:F48))/($E109+$C109-G$7)) -> 0 | H109: =IF(OR($C109>H$7,$C109+$E109-1<H$7),0,($D109-SUM($F109:G109)-SUM($F48:G48))/($E109+$C109-H$7)) -> 0 | I109: =IF(OR($C109>I$7,$C109+$E109-1<I$7),0,($D109-SUM($F109:H109)-SUM($F48:H48))/($E109+$C109-I$7)) -> 0 | J109: =IF(OR($C109>J$7,$C109+$E109-1<J$7),0,($D109-SUM($F109:I109)-SUM($F48:I48))/($E109+$C109-J$7)) -> 0 | K109: =IF(OR($C109>K$7,$C109+$E109-1<K$7),0,($D109-SUM($F109:J109)-SUM($F48:J48))/($E109+$C109-K$7)) -> 0 | L109: =IF(OR($C109>L$7,$C109+$E109-1<L$7),0,($D109-SUM($F109:K109)-SUM($F48:K48))/($E109+$C109-L$7)) -> 0 | M109: =IF(OR($C109>M$7,$C109+$E109-1<M$7),0,($D109-SUM($F109:L109)-SUM($F48:L48))/($E109+$C109-M$7)) -> 0 | N109: =IF(OR($C109>N$7,$C109+$E109-1<N$7),0,($D109-SUM($F109:M109)-SUM($F48:M48))/($E109+$C109-N$7)) -> 0 | ... BN109: =IF(OR($C109>BN$7,$C109+$E109-1<BN$7),0,($D109-SUM($F109:BM109)-SUM($F48:BM48))/($E109+$C109-BN$7)) -> 0
C110: 13 | D110: 0.0014025434 | E110: =SAP_Leadsheet!$E$49 -> 3 | G110: =IF(OR($C110>G$7,$C110+$E110-1<G$7),0,($D110-SUM($F110:F110)-SUM($F49:F49))/($E110+$C110-G$7)) -> 0 | H110: =IF(OR($C110>H$7,$C110+$E110-1<H$7),0,($D110-SUM($F110:G110)-SUM($F49:G49))/($E110+$C110-H$7)) -> 0 | I110: =IF(OR($C110>I$7,$C110+$E110-1<I$7),0,($D110-SUM($F110:H110)-SUM($F49:H49))/($E110+$C110-I$7)) -> 0 | J110: =IF(OR($C110>J$7,$C110+$E110-1<J$7),0,($D110-SUM($F110:I110)-SUM($F49:I49))/($E110+$C110-J$7)) -> 0 | K110: =IF(OR($C110>K$7,$C110+$E110-1<K$7),0,($D110-SUM($F110:J110)-SUM($F49:J49))/($E110+$C110-K$7)) -> 0 | L110: =IF(OR($C110>L$7,$C110+$E110-1<L$7),0,($D110-SUM($F110:K110)-SUM($F49:K49))/($E110+$C110-L$7)) -> 0 | M110: =IF(OR($C110>M$7,$C110+$E110-1<M$7),0,($D110-SUM($F110:L110)-SUM($F49:L49))/($E110+$C110-M$7)) -> 0 | N110: =IF(OR($C110>N$7,$C110+$E110-1<N$7),0,($D110-SUM($F110:M110)-SUM($F49:M49))/($E110+$C110-N$7)) -> 0 | ... BN110: =IF(OR($C110>BN$7,$C110+$E110-1<BN$7),0,($D110-SUM($F110:BM110)-SUM($F49:BM49))/($E110+$C110-BN$7)) -> 0
... C157: 60 | D157: 0 | E157: =SAP_Leadsheet!$E$49 -> 3 | G157: =IF(OR($C157>G$7,$C157+$E157-1<G$7),0,($D157-SUM($F157:F157)-SUM($F96:F96))/($E157+$C157-G$7)) -> 0 | H157: =IF(OR($C157>H$7,$C157+$E157-1<H$7),0,($D157-SUM($F157:G157)-SUM($F96:G96))/($E157+$C157-H$7)) -> 0 | I157: =IF(OR($C157>I$7,$C157+$E157-1<I$7),0,($D157-SUM($F157:H157)-SUM($F96:H96))/($E157+$C157-I$7)) -> 0 | J157: =IF(OR($C157>J$7,$C157+$E157-1<J$7),0,($D157-SUM($F157:I157)-SUM($F96:I96))/($E157+$C157-J$7)) -> 0 | K157: =IF(OR($C157>K$7,$C157+$E157-1<K$7),0,($D157-SUM($F157:J157)-SUM($F96:J96))/($E157+$C157-K$7)) -> 0 | L157: =IF(OR($C157>L$7,$C157+$E157-1<L$7),0,($D157-SUM($F157:K157)-SUM($F96:K96))/($E157+$C157-L$7)) -> 0 | M157: =IF(OR($C157>M$7,$C157+$E157-1<M$7),0,($D157-SUM($F157:L157)-SUM($F96:L96))/($E157+$C157-M$7)) -> 0 | N157: =IF(OR($C157>N$7,$C157+$E157-1<N$7),0,($D157-SUM($F157:M157)-SUM($F96:M96))/($E157+$C157-N$7)) -> 0 | ... BN157: =IF(OR($C157>BN$7,$C157+$E157-1<BN$7),0,($D157-SUM($F157:BM157)-SUM($F96:BM96))/($E157+$C157-BN$7)) -> 0
D158: Ending Bal | F158: mVND | G158: =G33+G34+G35 -> 0.0011696133 | H158: =H33+H34+H35 -> 0.0017342382 | I158: =I33+I34+I35 -> 0.0017039654 | J158: =J33+J34+J35 -> 0.0016736926 | K158: =K33+K34+K35 -> 0.0016434199 | L158: =L33+L34+L35 -> 0.0016131471 | M158: =M33+M34+M35 -> 0.0015828744 | N158: =N33+N34+N35 -> 0.0015526016 | ... BN158: =BN33+BN34+BN35 -> 4.3368087e-19
D160: EMI balance to fee | G160: =SUM(G161:G220) -> 0.00175442 | H160: =SUM(H161:H220) -> 0.0034785673 | I160: =SUM(I161:I220) -> 0.0051724418 | J160: =SUM(J161:J220) -> 0.0050816235 | K160: =SUM(K161:K220) -> 0.0049908052 | L160: =SUM(L161:L220) -> 0.0048999869 | M160: =SUM(M161:M220) -> 0.0048091686 | N160: =SUM(N161:N220) -> 0.0047183503 | ... BN160: =SUM(BN161:BN220) -> 0.00078291698
C161: =C98 -> 1 | D161: =D98 -> 0.00175442 | E161: =E98 -> 3 | G161: =IF(OR($C161>G$7,$C161+$E161-1<G$7),0,$D161) -> 0.00175442 | H161: =IF(OR($C161>H$7,$C161+$E161-1<H$7),0,$D161) -> 0.00175442 | I161: =IF(OR($C161>I$7,$C161+$E161-1<I$7),0,$D161) -> 0.00175442 | J161: =IF(OR($C161>J$7,$C161+$E161-1<J$7),0,$D161) -> 0 | K161: =IF(OR($C161>K$7,$C161+$E161-1<K$7),0,$D161) -> 0 | L161: =IF(OR($C161>L$7,$C161+$E161-1<L$7),0,$D161) -> 0 | M161: =IF(OR($C161>M$7,$C161+$E161-1<M$7),0,$D161) -> 0 | N161: =IF(OR($C161>N$7,$C161+$E161-1<N$7),0,$D161) -> 0 | ... BN161: =IF(OR($C161>BN$7,$C161+$E161-1<BN$7),0,$D161) -> 0
C162: =C99 -> 2 | D162: =D99 -> 0.0017241473 | E162: =E99 -> 3 | G162: =IF(OR($C162>G$7,$C162+$E162-1<G$7),0,$D162) -> 0 | H162: =IF(OR($C162>H$7,$C162+$E162-1<H$7),0,$D162) -> 0.0017241473 | I162: =IF(OR($C162>I$7,$C162+$E162-1<I$7),0,$D162) -> 0.0017241473 | J162: =IF(OR($C162>J$7,$C162+$E162-1<J$7),0,$D162) -> 0.0017241473 | K162: =IF(OR($C162>K$7,$C162+$E162-1<K$7),0,$D162) -> 0 | L162: =IF(OR($C162>L$7,$C162+$E162-1<L$7),0,$D162) -> 0 | M162: =IF(OR($C162>M$7,$C162+$E162-1<M$7),0,$D162) -> 0 | N162: =IF(OR($C162>N$7,$C162+$E162-1<N$7),0,$D162) -> 0 | ... BN162: =IF(OR($C162>BN$7,$C162+$E162-1<BN$7),0,$D162) -> 0
C163: =C100 -> 3 | D163: =D100 -> 0.0016938745 | E163: =E100 -> 3 | G163: =IF(OR($C163>G$7,$C163+$E163-1<G$7),0,$D163) -> 0 | H163: =IF(OR($C163>H$7,$C163+$E163-1<H$7),0,$D163) -> 0 | I163: =IF(OR($C163>I$7,$C163+$E163-1<I$7),0,$D163) -> 0.0016938745 | J163: =IF(OR($C163>J$7,$C163+$E163-1<J$7),0,$D163) -> 0.0016938745 | K163: =IF(OR($C163>K$7,$C163+$E163-1<K$7),0,$D163) -> 0.0016938745 | L163: =IF(OR($C163>L$7,$C163+$E163-1<L$7),0,$D163) -> 0 | M163: =IF(OR($C163>M$7,$C163+$E163-1<M$7),0,$D163) -> 0 | N163: =IF(OR($C163>N$7,$C163+$E163-1<N$7),0,$D163) -> 0 | ... BN163: =IF(OR($C163>BN$7,$C163+$E163-1<BN$7),0,$D163) -> 0
C164: =C101 -> 4 | D164: =D101 -> 0.0016636017 | E164: =E101 -> 3 | G164: =IF(OR($C164>G$7,$C164+$E164-1<G$7),0,$D164) -> 0 | H164: =IF(OR($C164>H$7,$C164+$E164-1<H$7),0,$D164) -> 0 | I164: =IF(OR($C164>I$7,$C164+$E164-1<I$7),0,$D164) -> 0 | J164: =IF(OR($C164>J$7,$C164+$E164-1<J$7),0,$D164) -> 0.0016636017 | K164: =IF(OR($C164>K$7,$C164+$E164-1<K$7),0,$D164) -> 0.0016636017 | L164: =IF(OR($C164>L$7,$C164+$E164-1<L$7),0,$D164) -> 0.0016636017 | M164: =IF(OR($C164>M$7,$C164+$E164-1<M$7),0,$D164) -> 0 | N164: =IF(OR($C164>N$7,$C164+$E164-1<N$7),0,$D164) -> 0 | ... BN164: =IF(OR($C164>BN$7,$C164+$E164-1<BN$7),0,$D164) -> 0
C165: =C102 -> 5 | D165: =D102 -> 0.001633329 | E165: =E102 -> 3 | G165: =IF(OR($C165>G$7,$C165+$E165-1<G$7),0,$D165) -> 0 | H165: =IF(OR($C165>H$7,$C165+$E165-1<H$7),0,$D165) -> 0 | I165: =IF(OR($C165>I$7,$C165+$E165-1<I$7),0,$D165) -> 0 | J165: =IF(OR($C165>J$7,$C165+$E165-1<J$7),0,$D165) -> 0 | K165: =IF(OR($C165>K$7,$C165+$E165-1<K$7),0,$D165) -> 0.001633329 | L165: =IF(OR($C165>L$7,$C165+$E165-1<L$7),0,$D165) -> 0.001633329 | M165: =IF(OR($C165>M$7,$C165+$E165-1<M$7),0,$D165) -> 0.001633329 | N165: =IF(OR($C165>N$7,$C165+$E165-1<N$7),0,$D165) -> 0 | ... BN165: =IF(OR($C165>BN$7,$C165+$E165-1<BN$7),0,$D165) -> 0
C166: =C103 -> 6 | D166: =D103 -> 0.0016030562 | E166: =E103 -> 3 | G166: =IF(OR($C166>G$7,$C166+$E166-1<G$7),0,$D166) -> 0 | H166: =IF(OR($C166>H$7,$C166+$E166-1<H$7),0,$D166) -> 0 | I166: =IF(OR($C166>I$7,$C166+$E166-1<I$7),0,$D166) -> 0 | J166: =IF(OR($C166>J$7,$C166+$E166-1<J$7),0,$D166) -> 0 | K166: =IF(OR($C166>K$7,$C166+$E166-1<K$7),0,$D166) -> 0 | L166: =IF(OR($C166>L$7,$C166+$E166-1<L$7),0,$D166) -> 0.0016030562 | M166: =IF(OR($C166>M$7,$C166+$E166-1<M$7),0,$D166) -> 0.0016030562 | N166: =IF(OR($C166>N$7,$C166+$E166-1<N$7),0,$D166) -> 0.0016030562 | ... BN166: =IF(OR($C166>BN$7,$C166+$E166-1<BN$7),0,$D166) -> 0
C167: =C104 -> 7 | D167: =D104 -> 0.0015727834 | E167: =E104 -> 3 | G167: =IF(OR($C167>G$7,$C167+$E167-1<G$7),0,$D167) -> 0 | H167: =IF(OR($C167>H$7,$C167+$E167-1<H$7),0,$D167) -> 0 | I167: =IF(OR($C167>I$7,$C167+$E167-1<I$7),0,$D167) -> 0 | J167: =IF(OR($C167>J$7,$C167+$E167-1<J$7),0,$D167) -> 0 | K167: =IF(OR($C167>K$7,$C167+$E167-1<K$7),0,$D167) -> 0 | L167: =IF(OR($C167>L$7,$C167+$E167-1<L$7),0,$D167) -> 0 | M167: =IF(OR($C167>M$7,$C167+$E167-1<M$7),0,$D167) -> 0.0015727834 | N167: =IF(OR($C167>N$7,$C167+$E167-1<N$7),0,$D167) -> 0.0015727834 | ... BN167: =IF(OR($C167>BN$7,$C167+$E167-1<BN$7),0,$D167) -> 0
C168: =C105 -> 8 | D168: =D105 -> 0.0015425107 | E168: =E105 -> 3 | G168: =IF(OR($C168>G$7,$C168+$E168-1<G$7),0,$D168) -> 0 | H168: =IF(OR($C168>H$7,$C168+$E168-1<H$7),0,$D168) -> 0 | I168: =IF(OR($C168>I$7,$C168+$E168-1<I$7),0,$D168) -> 0 | J168: =IF(OR($C168>J$7,$C168+$E168-1<J$7),0,$D168) -> 0 | K168: =IF(OR($C168>K$7,$C168+$E168-1<K$7),0,$D168) -> 0 | L168: =IF(OR($C168>L$7,$C168+$E168-1<L$7),0,$D168) -> 0 | M168: =IF(OR($C168>M$7,$C168+$E168-1<M$7),0,$D168) -> 0 | N168: =IF(OR($C168>N$7,$C168+$E168-1<N$7),0,$D168) -> 0.0015425107 | ... BN168: =IF(OR($C168>BN$7,$C168+$E168-1<BN$7),0,$D168) -> 0
C169: =C106 -> 9 | D169: =D106 -> 0.0015122379 | E169: =E106 -> 3 | G169: =IF(OR($C169>G$7,$C169+$E169-1<G$7),0,$D169) -> 0 | H169: =IF(OR($C169>H$7,$C169+$E169-1<H$7),0,$D169) -> 0 | I169: =IF(OR($C169>I$7,$C169+$E169-1<I$7),0,$D169) -> 0 | J169: =IF(OR($C169>J$7,$C169+$E169-1<J$7),0,$D169) -> 0 | K169: =IF(OR($C169>K$7,$C169+$E169-1<K$7),0,$D169) -> 0 | L169: =IF(OR($C169>L$7,$C169+$E169-1<L$7),0,$D169) -> 0 | M169: =IF(OR($C169>M$7,$C169+$E169-1<M$7),0,$D169) -> 0 | N169: =IF(OR($C169>N$7,$C169+$E169-1<N$7),0,$D169) -> 0 | ... BN169: =IF(OR($C169>BN$7,$C169+$E169-1<BN$7),0,$D169) -> 0
C170: =C107 -> 10 | D170: =D107 -> 0.0014819651 | E170: =E107 -> 3 | G170: =IF(OR($C170>G$7,$C170+$E170-1<G$7),0,$D170) -> 0 | H170: =IF(OR($C170>H$7,$C170+$E170-1<H$7),0,$D170) -> 0 | I170: =IF(OR($C170>I$7,$C170+$E170-1<I$7),0,$D170) -> 0 | J170: =IF(OR($C170>J$7,$C170+$E170-1<J$7),0,$D170) -> 0 | K170: =IF(OR($C170>K$7,$C170+$E170-1<K$7),0,$D170) -> 0 | L170: =IF(OR($C170>L$7,$C170+$E170-1<L$7),0,$D170) -> 0 | M170: =IF(OR($C170>M$7,$C170+$E170-1<M$7),0,$D170) -> 0 | N170: =IF(OR($C170>N$7,$C170+$E170-1<N$7),0,$D170) -> 0 | ... BN170: =IF(OR($C170>BN$7,$C170+$E170-1<BN$7),0,$D170) -> 0
C171: =C108 -> 11 | D171: =D108 -> 0.0014516924 | E171: =E108 -> 3 | G171: =IF(OR($C171>G$7,$C171+$E171-1<G$7),0,$D171) -> 0 | H171: =IF(OR($C171>H$7,$C171+$E171-1<H$7),0,$D171) -> 0 | I171: =IF(OR($C171>I$7,$C171+$E171-1<I$7),0,$D171) -> 0 | J171: =IF(OR($C171>J$7,$C171+$E171-1<J$7),0,$D171) -> 0 | K171: =IF(OR($C171>K$7,$C171+$E171-1<K$7),0,$D171) -> 0 | L171: =IF(OR($C171>L$7,$C171+$E171-1<L$7),0,$D171) -> 0 | M171: =IF(OR($C171>M$7,$C171+$E171-1<M$7),0,$D171) -> 0 | N171: =IF(OR($C171>N$7,$C171+$E171-1<N$7),0,$D171) -> 0 | ... BN171: =IF(OR($C171>BN$7,$C171+$E171-1<BN$7),0,$D171) -> 0
C172: =C109 -> 12 | D172: =D109 -> 0.0014214196 | E172: =E109 -> 3 | G172: =IF(OR($C172>G$7,$C172+$E172-1<G$7),0,$D172) -> 0 | H172: =IF(OR($C172>H$7,$C172+$E172-1<H$7),0,$D172) -> 0 | I172: =IF(OR($C172>I$7,$C172+$E172-1<I$7),0,$D172) -> 0 | J172: =IF(OR($C172>J$7,$C172+$E172-1<J$7),0,$D172) -> 0 | K172: =IF(OR($C172>K$7,$C172+$E172-1<K$7),0,$D172) -> 0 | L172: =IF(OR($C172>L$7,$C172+$E172-1<L$7),0,$D172) -> 0 | M172: =IF(OR($C172>M$7,$C172+$E172-1<M$7),0,$D172) -> 0 | N172: =IF(OR($C172>N$7,$C172+$E172-1<N$7),0,$D172) -> 0 | ... BN172: =IF(OR($C172>BN$7,$C172+$E172-1<BN$7),0,$D172) -> 0
... C220: =C157 -> 60 | D220: =D157 -> 0 | E220: =E157 -> 3 | G220: =IF(OR($C220>G$7,$C220+$E220-1<G$7),0,$D220) -> 0 | H220: =IF(OR($C220>H$7,$C220+$E220-1<H$7),0,$D220) -> 0 | I220: =IF(OR($C220>I$7,$C220+$E220-1<I$7),0,$D220) -> 0 | J220: =IF(OR($C220>J$7,$C220+$E220-1<J$7),0,$D220) -> 0 | K220: =IF(OR($C220>K$7,$C220+$E220-1<K$7),0,$D220) -> 0 | L220: =IF(OR($C220>L$7,$C220+$E220-1<L$7),0,$D220) -> 0 | M220: =IF(OR($C220>M$7,$C220+$E220-1<M$7),0,$D220) -> 0 | N220: =IF(OR($C220>N$7,$C220+$E220-1<N$7),0,$D220) -> 0 | ... BN220: =IF(OR($C220>BN$7,$C220+$E220-1<BN$7),0,$D220) -> 0
C223: Retail installment | D223: Beginning Bal | F223: mVND | G223: 0 | H223: =G348 -> 0.027343865 | I223: =H348 -> 0.048747134 | J223: =I348 -> 0.064304173 | K223: =J348 -> 0.074109346 | L223: =K348 -> 0.078257016 | M223: =L348 -> 0.07684155 | N223: =M348 -> 0.075426083 | O223: =N348 -> 0.074010616 | ... BN223: =BM348 -> 0.0025256165
D224: New Billing | F224: mVND | G224: =IF(SAP_Leadsheet!$C$9="non-EMI",0,IF(G$7+SAP_Leadsheet!$E$57-1>SAP_Leadsheet!$E$21,0,SAP_Leadsheet!$E$56*G21)) -> 0.032812638 | H224: =IF(SAP_Leadsheet!$C$9="non-EMI",0,IF(H$7+SAP_Leadsheet!$E$57-1>SAP_Leadsheet!$E$21,0,SAP_Leadsheet!$E$56*H21)) -> 0.032246451 | I224: =IF(SAP_Leadsheet!$C$9="non-EMI",0,IF(I$7+SAP_Leadsheet!$E$57-1>SAP_Leadsheet!$E$21,0,SAP_Leadsheet!$E$56*I21)) -> 0.031680264 | J224: =IF(SAP_Leadsheet!$C$9="non-EMI",0,IF(J$7+SAP_Leadsheet!$E$57-1>SAP_Leadsheet!$E$21,0,SAP_Leadsheet!$E$56*J21)) -> 0.031114078 | K224: =IF(SAP_Leadsheet!$C$9="non-EMI",0,IF(K$7+SAP_Leadsheet!$E$57-1>SAP_Leadsheet!$E$21,0,SAP_Leadsheet!$E$56*K21)) -> 0.030547891 | L224: =IF(SAP_Leadsheet!$C$9="non-EMI",0,IF(L$7+SAP_Leadsheet!$E$57-1>SAP_Leadsheet!$E$21,0,SAP_Leadsheet!$E$56*L21)) -> 0.029981704 | M224: =IF(SAP_Leadsheet!$C$9="non-EMI",0,IF(M$7+SAP_Leadsheet!$E$57-1>SAP_Leadsheet!$E$21,0,SAP_Leadsheet!$E$56*M21)) -> 0.029415518 | N224: =IF(SAP_Leadsheet!$C$9="non-EMI",0,IF(N$7+SAP_Leadsheet!$E$57-1>SAP_Leadsheet!$E$21,0,SAP_Leadsheet!$E$56*N21)) -> 0.028849331 | ... BN224: =IF(SAP_Leadsheet!$C$9="non-EMI",0,IF(BN$7+SAP_Leadsheet!$E$57-1>SAP_Leadsheet!$E$21,0,SAP_Leadsheet!$E$56*BN21)) -> 0
D225: Paid off | F225: mVND | G225: =G226+G287 -> -0.005468773 | H225: =H226+H287 -> -0.010843181 | I225: =I226+I287 -> -0.016123226 | J225: =J226+J287 -> -0.021308905 | K225: =K226+K287 -> -0.02640022 | L225: =L226+L287 -> -0.031397171 | M225: =M226+M287 -> -0.030830984 | N225: =N226+N287 -> -0.030264798 | ... BN225: =BN226+BN287 -> -0.0025256165
D226: Early payment | G226: =-SUM(G227:G286) -> 0 | H226: =-SUM(H227:H286) -> 0 | I226: =-SUM(I227:I286) -> 0 | J226: =-SUM(J227:J286) -> 0 | K226: =-SUM(K227:K286) -> 0 | L226: =-SUM(L227:L286) -> 0 | M226: =-SUM(M227:M286) -> 0 | N226: =-SUM(N227:N286) -> 0 | ... BN226: =-SUM(BN227:BN286) -> 0
C227: {=TRANSPOSE($G$7:$BN$7)} -> 1 | G227: =IF(OR($C288>G$7,$C288+$E288-2<G$7),0,($D288-SUM($F288:F288)-SUM($F227:F227))*SAP_Leadsheet!$E$61) -> 0 | H227: =IF(OR($C288>H$7,$C288+$E288-2<H$7),0,($D288-SUM($F288:G288)-SUM($F227:G227))*SAP_Leadsheet!$E$61) -> 0 | I227: =IF(OR($C288>I$7,$C288+$E288-2<I$7),0,($D288-SUM($F288:H288)-SUM($F227:H227))*SAP_Leadsheet!$E$61) -> 0 | J227: =IF(OR($C288>J$7,$C288+$E288-2<J$7),0,($D288-SUM($F288:I288)-SUM($F227:I227))*SAP_Leadsheet!$E$61) -> 0 | K227: =IF(OR($C288>K$7,$C288+$E288-2<K$7),0,($D288-SUM($F288:J288)-SUM($F227:J227))*SAP_Leadsheet!$E$61) -> 0 | L227: =IF(OR($C288>L$7,$C288+$E288-2<L$7),0,($D288-SUM($F288:K288)-SUM($F227:K227))*SAP_Leadsheet!$E$61) -> 0 | M227: =IF(OR($C288>M$7,$C288+$E288-2<M$7),0,($D288-SUM($F288:L288)-SUM($F227:L227))*SAP_Leadsheet!$E$61) -> 0 | N227: =IF(OR($C288>N$7,$C288+$E288-2<N$7),0,($D288-SUM($F288:M288)-SUM($F227:M227))*SAP_Leadsheet!$E$61) -> 0 | ... BN227: =IF(OR($C288>BN$7,$C288+$E288-2<BN$7),0,($D288-SUM($F288:BM288)-SUM($F227:BM227))*SAP_Leadsheet!$E$61) -> 0
C228: 2 | G228: =IF(OR($C289>G$7,$C289+$E289-2<G$7),0,($D289-SUM($F289:F289)-SUM($F228:F228))*SAP_Leadsheet!$E$61) -> 0 | H228: =IF(OR($C289>H$7,$C289+$E289-2<H$7),0,($D289-SUM($F289:G289)-SUM($F228:G228))*SAP_Leadsheet!$E$61) -> 0 | I228: =IF(OR($C289>I$7,$C289+$E289-2<I$7),0,($D289-SUM($F289:H289)-SUM($F228:H228))*SAP_Leadsheet!$E$61) -> 0 | J228: =IF(OR($C289>J$7,$C289+$E289-2<J$7),0,($D289-SUM($F289:I289)-SUM($F228:I228))*SAP_Leadsheet!$E$61) -> 0 | K228: =IF(OR($C289>K$7,$C289+$E289-2<K$7),0,($D289-SUM($F289:J289)-SUM($F228:J228))*SAP_Leadsheet!$E$61) -> 0 | L228: =IF(OR($C289>L$7,$C289+$E289-2<L$7),0,($D289-SUM($F289:K289)-SUM($F228:K228))*SAP_Leadsheet!$E$61) -> 0 | M228: =IF(OR($C289>M$7,$C289+$E289-2<M$7),0,($D289-SUM($F289:L289)-SUM($F228:L228))*SAP_Leadsheet!$E$61) -> 0 | N228: =IF(OR($C289>N$7,$C289+$E289-2<N$7),0,($D289-SUM($F289:M289)-SUM($F228:M228))*SAP_Leadsheet!$E$61) -> 0 | ... BN228: =IF(OR($C289>BN$7,$C289+$E289-2<BN$7),0,($D289-SUM($F289:BM289)-SUM($F228:BM228))*SAP_Leadsheet!$E$61) -> 0
C229: 3 | G229: =IF(OR($C290>G$7,$C290+$E290-2<G$7),0,($D290-SUM($F290:F290)-SUM($F229:F229))*SAP_Leadsheet!$E$61) -> 0 | H229: =IF(OR($C290>H$7,$C290+$E290-2<H$7),0,($D290-SUM($F290:G290)-SUM($F229:G229))*SAP_Leadsheet!$E$61) -> 0 | I229: =IF(OR($C290>I$7,$C290+$E290-2<I$7),0,($D290-SUM($F290:H290)-SUM($F229:H229))*SAP_Leadsheet!$E$61) -> 0 | J229: =IF(OR($C290>J$7,$C290+$E290-2<J$7),0,($D290-SUM($F290:I290)-SUM($F229:I229))*SAP_Leadsheet!$E$61) -> 0 | K229: =IF(OR($C290>K$7,$C290+$E290-2<K$7),0,($D290-SUM($F290:J290)-SUM($F229:J229))*SAP_Leadsheet!$E$61) -> 0 | L229: =IF(OR($C290>L$7,$C290+$E290-2<L$7),0,($D290-SUM($F290:K290)-SUM($F229:K229))*SAP_Leadsheet!$E$61) -> 0 | M229: =IF(OR($C290>M$7,$C290+$E290-2<M$7),0,($D290-SUM($F290:L290)-SUM($F229:L229))*SAP_Leadsheet!$E$61) -> 0 | N229: =IF(OR($C290>N$7,$C290+$E290-2<N$7),0,($D290-SUM($F290:M290)-SUM($F229:M229))*SAP_Leadsheet!$E$61) -> 0 | ... BN229: =IF(OR($C290>BN$7,$C290+$E290-2<BN$7),0,($D290-SUM($F290:BM290)-SUM($F229:BM229))*SAP_Leadsheet!$E$61) -> 0
C230: 4 | G230: =IF(OR($C291>G$7,$C291+$E291-2<G$7),0,($D291-SUM($F291:F291)-SUM($F230:F230))*SAP_Leadsheet!$E$61) -> 0 | H230: =IF(OR($C291>H$7,$C291+$E291-2<H$7),0,($D291-SUM($F291:G291)-SUM($F230:G230))*SAP_Leadsheet!$E$61) -> 0 | I230: =IF(OR($C291>I$7,$C291+$E291-2<I$7),0,($D291-SUM($F291:H291)-SUM($F230:H230))*SAP_Leadsheet!$E$61) -> 0 | J230: =IF(OR($C291>J$7,$C291+$E291-2<J$7),0,($D291-SUM($F291:I291)-SUM($F230:I230))*SAP_Leadsheet!$E$61) -> 0 | K230: =IF(OR($C291>K$7,$C291+$E291-2<K$7),0,($D291-SUM($F291:J291)-SUM($F230:J230))*SAP_Leadsheet!$E$61) -> 0 | L230: =IF(OR($C291>L$7,$C291+$E291-2<L$7),0,($D291-SUM($F291:K291)-SUM($F230:K230))*SAP_Leadsheet!$E$61) -> 0 | M230: =IF(OR($C291>M$7,$C291+$E291-2<M$7),0,($D291-SUM($F291:L291)-SUM($F230:L230))*SAP_Leadsheet!$E$61) -> 0 | N230: =IF(OR($C291>N$7,$C291+$E291-2<N$7),0,($D291-SUM($F291:M291)-SUM($F230:M230))*SAP_Leadsheet!$E$61) -> 0 | ... BN230: =IF(OR($C291>BN$7,$C291+$E291-2<BN$7),0,($D291-SUM($F291:BM291)-SUM($F230:BM230))*SAP_Leadsheet!$E$61) -> 0
C231: 5 | G231: =IF(OR($C292>G$7,$C292+$E292-2<G$7),0,($D292-SUM($F292:F292)-SUM($F231:F231))*SAP_Leadsheet!$E$61) -> 0 | H231: =IF(OR($C292>H$7,$C292+$E292-2<H$7),0,($D292-SUM($F292:G292)-SUM($F231:G231))*SAP_Leadsheet!$E$61) -> 0 | I231: =IF(OR($C292>I$7,$C292+$E292-2<I$7),0,($D292-SUM($F292:H292)-SUM($F231:H231))*SAP_Leadsheet!$E$61) -> 0 | J231: =IF(OR($C292>J$7,$C292+$E292-2<J$7),0,($D292-SUM($F292:I292)-SUM($F231:I231))*SAP_Leadsheet!$E$61) -> 0 | K231: =IF(OR($C292>K$7,$C292+$E292-2<K$7),0,($D292-SUM($F292:J292)-SUM($F231:J231))*SAP_Leadsheet!$E$61) -> 0 | L231: =IF(OR($C292>L$7,$C292+$E292-2<L$7),0,($D292-SUM($F292:K292)-SUM($F231:K231))*SAP_Leadsheet!$E$61) -> 0 | M231: =IF(OR($C292>M$7,$C292+$E292-2<M$7),0,($D292-SUM($F292:L292)-SUM($F231:L231))*SAP_Leadsheet!$E$61) -> 0 | N231: =IF(OR($C292>N$7,$C292+$E292-2<N$7),0,($D292-SUM($F292:M292)-SUM($F231:M231))*SAP_Leadsheet!$E$61) -> 0 | ... BN231: =IF(OR($C292>BN$7,$C292+$E292-2<BN$7),0,($D292-SUM($F292:BM292)-SUM($F231:BM231))*SAP_Leadsheet!$E$61) -> 0
C232: 6 | G232: =IF(OR($C293>G$7,$C293+$E293-2<G$7),0,($D293-SUM($F293:F293)-SUM($F232:F232))*SAP_Leadsheet!$E$61) -> 0 | H232: =IF(OR($C293>H$7,$C293+$E293-2<H$7),0,($D293-SUM($F293:G293)-SUM($F232:G232))*SAP_Leadsheet!$E$61) -> 0 | I232: =IF(OR($C293>I$7,$C293+$E293-2<I$7),0,($D293-SUM($F293:H293)-SUM($F232:H232))*SAP_Leadsheet!$E$61) -> 0 | J232: =IF(OR($C293>J$7,$C293+$E293-2<J$7),0,($D293-SUM($F293:I293)-SUM($F232:I232))*SAP_Leadsheet!$E$61) -> 0 | K232: =IF(OR($C293>K$7,$C293+$E293-2<K$7),0,($D293-SUM($F293:J293)-SUM($F232:J232))*SAP_Leadsheet!$E$61) -> 0 | L232: =IF(OR($C293>L$7,$C293+$E293-2<L$7),0,($D293-SUM($F293:K293)-SUM($F232:K232))*SAP_Leadsheet!$E$61) -> 0 | M232: =IF(OR($C293>M$7,$C293+$E293-2<M$7),0,($D293-SUM($F293:L293)-SUM($F232:L232))*SAP_Leadsheet!$E$61) -> 0 | N232: =IF(OR($C293>N$7,$C293+$E293-2<N$7),0,($D293-SUM($F293:M293)-SUM($F232:M232))*SAP_Leadsheet!$E$61) -> 0 | ... BN232: =IF(OR($C293>BN$7,$C293+$E293-2<BN$7),0,($D293-SUM($F293:BM293)-SUM($F232:BM232))*SAP_Leadsheet!$E$61) -> 0
C233: 7 | G233: =IF(OR($C294>G$7,$C294+$E294-2<G$7),0,($D294-SUM($F294:F294)-SUM($F233:F233))*SAP_Leadsheet!$E$61) -> 0 | H233: =IF(OR($C294>H$7,$C294+$E294-2<H$7),0,($D294-SUM($F294:G294)-SUM($F233:G233))*SAP_Leadsheet!$E$61) -> 0 | I233: =IF(OR($C294>I$7,$C294+$E294-2<I$7),0,($D294-SUM($F294:H294)-SUM($F233:H233))*SAP_Leadsheet!$E$61) -> 0 | J233: =IF(OR($C294>J$7,$C294+$E294-2<J$7),0,($D294-SUM($F294:I294)-SUM($F233:I233))*SAP_Leadsheet!$E$61) -> 0 | K233: =IF(OR($C294>K$7,$C294+$E294-2<K$7),0,($D294-SUM($F294:J294)-SUM($F233:J233))*SAP_Leadsheet!$E$61) -> 0 | L233: =IF(OR($C294>L$7,$C294+$E294-2<L$7),0,($D294-SUM($F294:K294)-SUM($F233:K233))*SAP_Leadsheet!$E$61) -> 0 | M233: =IF(OR($C294>M$7,$C294+$E294-2<M$7),0,($D294-SUM($F294:L294)-SUM($F233:L233))*SAP_Leadsheet!$E$61) -> 0 | N233: =IF(OR($C294>N$7,$C294+$E294-2<N$7),0,($D294-SUM($F294:M294)-SUM($F233:M233))*SAP_Leadsheet!$E$61) -> 0 | ... BN233: =IF(OR($C294>BN$7,$C294+$E294-2<BN$7),0,($D294-SUM($F294:BM294)-SUM($F233:BM233))*SAP_Leadsheet!$E$61) -> 0
C234: 8 | G234: =IF(OR($C295>G$7,$C295+$E295-2<G$7),0,($D295-SUM($F295:F295)-SUM($F234:F234))*SAP_Leadsheet!$E$61) -> 0 | H234: =IF(OR($C295>H$7,$C295+$E295-2<H$7),0,($D295-SUM($F295:G295)-SUM($F234:G234))*SAP_Leadsheet!$E$61) -> 0 | I234: =IF(OR($C295>I$7,$C295+$E295-2<I$7),0,($D295-SUM($F295:H295)-SUM($F234:H234))*SAP_Leadsheet!$E$61) -> 0 | J234: =IF(OR($C295>J$7,$C295+$E295-2<J$7),0,($D295-SUM($F295:I295)-SUM($F234:I234))*SAP_Leadsheet!$E$61) -> 0 | K234: =IF(OR($C295>K$7,$C295+$E295-2<K$7),0,($D295-SUM($F295:J295)-SUM($F234:J234))*SAP_Leadsheet!$E$61) -> 0 | L234: =IF(OR($C295>L$7,$C295+$E295-2<L$7),0,($D295-SUM($F295:K295)-SUM($F234:K234))*SAP_Leadsheet!$E$61) -> 0 | M234: =IF(OR($C295>M$7,$C295+$E295-2<M$7),0,($D295-SUM($F295:L295)-SUM($F234:L234))*SAP_Leadsheet!$E$61) -> 0 | N234: =IF(OR($C295>N$7,$C295+$E295-2<N$7),0,($D295-SUM($F295:M295)-SUM($F234:M234))*SAP_Leadsheet!$E$61) -> 0 | ... BN234: =IF(OR($C295>BN$7,$C295+$E295-2<BN$7),0,($D295-SUM($F295:BM295)-SUM($F234:BM234))*SAP_Leadsheet!$E$61) -> 0
C235: 9 | G235: =IF(OR($C296>G$7,$C296+$E296-2<G$7),0,($D296-SUM($F296:F296)-SUM($F235:F235))*SAP_Leadsheet!$E$61) -> 0 | H235: =IF(OR($C296>H$7,$C296+$E296-2<H$7),0,($D296-SUM($F296:G296)-SUM($F235:G235))*SAP_Leadsheet!$E$61) -> 0 | I235: =IF(OR($C296>I$7,$C296+$E296-2<I$7),0,($D296-SUM($F296:H296)-SUM($F235:H235))*SAP_Leadsheet!$E$61) -> 0 | J235: =IF(OR($C296>J$7,$C296+$E296-2<J$7),0,($D296-SUM($F296:I296)-SUM($F235:I235))*SAP_Leadsheet!$E$61) -> 0 | K235: =IF(OR($C296>K$7,$C296+$E296-2<K$7),0,($D296-SUM($F296:J296)-SUM($F235:J235))*SAP_Leadsheet!$E$61) -> 0 | L235: =IF(OR($C296>L$7,$C296+$E296-2<L$7),0,($D296-SUM($F296:K296)-SUM($F235:K235))*SAP_Leadsheet!$E$61) -> 0 | M235: =IF(OR($C296>M$7,$C296+$E296-2<M$7),0,($D296-SUM($F296:L296)-SUM($F235:L235))*SAP_Leadsheet!$E$61) -> 0 | N235: =IF(OR($C296>N$7,$C296+$E296-2<N$7),0,($D296-SUM($F296:M296)-SUM($F235:M235))*SAP_Leadsheet!$E$61) -> 0 | ... BN235: =IF(OR($C296>BN$7,$C296+$E296-2<BN$7),0,($D296-SUM($F296:BM296)-SUM($F235:BM235))*SAP_Leadsheet!$E$61) -> 0
C236: 10 | G236: =IF(OR($C297>G$7,$C297+$E297-2<G$7),0,($D297-SUM($F297:F297)-SUM($F236:F236))*SAP_Leadsheet!$E$61) -> 0 | H236: =IF(OR($C297>H$7,$C297+$E297-2<H$7),0,($D297-SUM($F297:G297)-SUM($F236:G236))*SAP_Leadsheet!$E$61) -> 0 | I236: =IF(OR($C297>I$7,$C297+$E297-2<I$7),0,($D297-SUM($F297:H297)-SUM($F236:H236))*SAP_Leadsheet!$E$61) -> 0 | J236: =IF(OR($C297>J$7,$C297+$E297-2<J$7),0,($D297-SUM($F297:I297)-SUM($F236:I236))*SAP_Leadsheet!$E$61) -> 0 | K236: =IF(OR($C297>K$7,$C297+$E297-2<K$7),0,($D297-SUM($F297:J297)-SUM($F236:J236))*SAP_Leadsheet!$E$61) -> 0 | L236: =IF(OR($C297>L$7,$C297+$E297-2<L$7),0,($D297-SUM($F297:K297)-SUM($F236:K236))*SAP_Leadsheet!$E$61) -> 0 | M236: =IF(OR($C297>M$7,$C297+$E297-2<M$7),0,($D297-SUM($F297:L297)-SUM($F236:L236))*SAP_Leadsheet!$E$61) -> 0 | N236: =IF(OR($C297>N$7,$C297+$E297-2<N$7),0,($D297-SUM($F297:M297)-SUM($F236:M236))*SAP_Leadsheet!$E$61) -> 0 | ... BN236: =IF(OR($C297>BN$7,$C297+$E297-2<BN$7),0,($D297-SUM($F297:BM297)-SUM($F236:BM236))*SAP_Leadsheet!$E$61) -> 0
C237: 11 | G237: =IF(OR($C298>G$7,$C298+$E298-2<G$7),0,($D298-SUM($F298:F298)-SUM($F237:F237))*SAP_Leadsheet!$E$61) -> 0 | H237: =IF(OR($C298>H$7,$C298+$E298-2<H$7),0,($D298-SUM($F298:G298)-SUM($F237:G237))*SAP_Leadsheet!$E$61) -> 0 | I237: =IF(OR($C298>I$7,$C298+$E298-2<I$7),0,($D298-SUM($F298:H298)-SUM($F237:H237))*SAP_Leadsheet!$E$61) -> 0 | J237: =IF(OR($C298>J$7,$C298+$E298-2<J$7),0,($D298-SUM($F298:I298)-SUM($F237:I237))*SAP_Leadsheet!$E$61) -> 0 | K237: =IF(OR($C298>K$7,$C298+$E298-2<K$7),0,($D298-SUM($F298:J298)-SUM($F237:J237))*SAP_Leadsheet!$E$61) -> 0 | L237: =IF(OR($C298>L$7,$C298+$E298-2<L$7),0,($D298-SUM($F298:K298)-SUM($F237:K237))*SAP_Leadsheet!$E$61) -> 0 | M237: =IF(OR($C298>M$7,$C298+$E298-2<M$7),0,($D298-SUM($F298:L298)-SUM($F237:L237))*SAP_Leadsheet!$E$61) -> 0 | N237: =IF(OR($C298>N$7,$C298+$E298-2<N$7),0,($D298-SUM($F298:M298)-SUM($F237:M237))*SAP_Leadsheet!$E$61) -> 0 | ... BN237: =IF(OR($C298>BN$7,$C298+$E298-2<BN$7),0,($D298-SUM($F298:BM298)-SUM($F237:BM237))*SAP_Leadsheet!$E$61) -> 0
C238: 12 | G238: =IF(OR($C299>G$7,$C299+$E299-2<G$7),0,($D299-SUM($F299:F299)-SUM($F238:F238))*SAP_Leadsheet!$E$61) -> 0 | H238: =IF(OR($C299>H$7,$C299+$E299-2<H$7),0,($D299-SUM($F299:G299)-SUM($F238:G238))*SAP_Leadsheet!$E$61) -> 0 | I238: =IF(OR($C299>I$7,$C299+$E299-2<I$7),0,($D299-SUM($F299:H299)-SUM($F238:H238))*SAP_Leadsheet!$E$61) -> 0 | J238: =IF(OR($C299>J$7,$C299+$E299-2<J$7),0,($D299-SUM($F299:I299)-SUM($F238:I238))*SAP_Leadsheet!$E$61) -> 0 | K238: =IF(OR($C299>K$7,$C299+$E299-2<K$7),0,($D299-SUM($F299:J299)-SUM($F238:J238))*SAP_Leadsheet!$E$61) -> 0 | L238: =IF(OR($C299>L$7,$C299+$E299-2<L$7),0,($D299-SUM($F299:K299)-SUM($F238:K238))*SAP_Leadsheet!$E$61) -> 0 | M238: =IF(OR($C299>M$7,$C299+$E299-2<M$7),0,($D299-SUM($F299:L299)-SUM($F238:L238))*SAP_Leadsheet!$E$61) -> 0 | N238: =IF(OR($C299>N$7,$C299+$E299-2<N$7),0,($D299-SUM($F299:M299)-SUM($F238:M238))*SAP_Leadsheet!$E$61) -> 0 | ... BN238: =IF(OR($C299>BN$7,$C299+$E299-2<BN$7),0,($D299-SUM($F299:BM299)-SUM($F238:BM238))*SAP_Leadsheet!$E$61) -> 0
C239: 13 | G239: =IF(OR($C300>G$7,$C300+$E300-2<G$7),0,($D300-SUM($F300:F300)-SUM($F239:F239))*SAP_Leadsheet!$E$61) -> 0 | H239: =IF(OR($C300>H$7,$C300+$E300-2<H$7),0,($D300-SUM($F300:G300)-SUM($F239:G239))*SAP_Leadsheet!$E$61) -> 0 | I239: =IF(OR($C300>I$7,$C300+$E300-2<I$7),0,($D300-SUM($F300:H300)-SUM($F239:H239))*SAP_Leadsheet!$E$61) -> 0 | J239: =IF(OR($C300>J$7,$C300+$E300-2<J$7),0,($D300-SUM($F300:I300)-SUM($F239:I239))*SAP_Leadsheet!$E$61) -> 0 | K239: =IF(OR($C300>K$7,$C300+$E300-2<K$7),0,($D300-SUM($F300:J300)-SUM($F239:J239))*SAP_Leadsheet!$E$61) -> 0 | L239: =IF(OR($C300>L$7,$C300+$E300-2<L$7),0,($D300-SUM($F300:K300)-SUM($F239:K239))*SAP_Leadsheet!$E$61) -> 0 | M239: =IF(OR($C300>M$7,$C300+$E300-2<M$7),0,($D300-SUM($F300:L300)-SUM($F239:L239))*SAP_Leadsheet!$E$61) -> 0 | N239: =IF(OR($C300>N$7,$C300+$E300-2<N$7),0,($D300-SUM($F300:M300)-SUM($F239:M239))*SAP_Leadsheet!$E$61) -> 0 | ... BN239: =IF(OR($C300>BN$7,$C300+$E300-2<BN$7),0,($D300-SUM($F300:BM300)-SUM($F239:BM239))*SAP_Leadsheet!$E$61) -> 0
... C286: 60 | G286: =IF(OR($C347>G$7,$C347+$E347-2<G$7),0,($D347-SUM($F347:F347)-SUM($F286:F286))*SAP_Leadsheet!$E$61) -> 0 | H286: =IF(OR($C347>H$7,$C347+$E347-2<H$7),0,($D347-SUM($F347:G347)-SUM($F286:G286))*SAP_Leadsheet!$E$61) -> 0 | I286: =IF(OR($C347>I$7,$C347+$E347-2<I$7),0,($D347-SUM($F347:H347)-SUM($F286:H286))*SAP_Leadsheet!$E$61) -> 0 | J286: =IF(OR($C347>J$7,$C347+$E347-2<J$7),0,($D347-SUM($F347:I347)-SUM($F286:I286))*SAP_Leadsheet!$E$61) -> 0 | K286: =IF(OR($C347>K$7,$C347+$E347-2<K$7),0,($D347-SUM($F347:J347)-SUM($F286:J286))*SAP_Leadsheet!$E$61) -> 0 | L286: =IF(OR($C347>L$7,$C347+$E347-2<L$7),0,($D347-SUM($F347:K347)-SUM($F286:K286))*SAP_Leadsheet!$E$61) -> 0 | M286: =IF(OR($C347>M$7,$C347+$E347-2<M$7),0,($D347-SUM($F347:L347)-SUM($F286:L286))*SAP_Leadsheet!$E$61) -> 0 | N286: =IF(OR($C347>N$7,$C347+$E347-2<N$7),0,($D347-SUM($F347:M347)-SUM($F286:M286))*SAP_Leadsheet!$E$61) -> 0 | ... BN286: =IF(OR($C347>BN$7,$C347+$E347-2<BN$7),0,($D347-SUM($F347:BM347)-SUM($F286:BM286))*SAP_Leadsheet!$E$61) -> 0
D287: Normal payment | G287: =-SUM(G288:G347) -> -0.005468773 | H287: =-SUM(H288:H347) -> -0.010843181 | I287: =-SUM(I288:I347) -> -0.016123226 | J287: =-SUM(J288:J347) -> -0.021308905 | K287: =-SUM(K288:K347) -> -0.02640022 | L287: =-SUM(L288:L347) -> -0.031397171 | M287: =-SUM(M288:M347) -> -0.030830984 | N287: =-SUM(N288:N347) -> -0.030264798 | ... BN287: =-SUM(BN288:BN347) -> -0.0025256165
C288: {=TRANSPOSE($G$7:$BN$7)} -> 1 | D288: {=TRANSPOSE(G224:BN224)} -> 0.032812638 | E288: =SAP_Leadsheet!$E$57 -> 6 | G288: =IF(OR($C288>G$7,$C288+$E288-1<G$7),0,($D288-SUM($F288:F288)-SUM($F227:F227))/($E288+$C288-G$7)) -> 0.005468773 | H288: =IF(OR($C288>H$7,$C288+$E288-1<H$7),0,($D288-SUM($F288:G288)-SUM($F227:G227))/($E288+$C288-H$7)) -> 0.005468773 | I288: =IF(OR($C288>I$7,$C288+$E288-1<I$7),0,($D288-SUM($F288:H288)-SUM($F227:H227))/($E288+$C288-I$7)) -> 0.005468773 | J288: =IF(OR($C288>J$7,$C288+$E288-1<J$7),0,($D288-SUM($F288:I288)-SUM($F227:I227))/($E288+$C288-J$7)) -> 0.005468773 | K288: =IF(OR($C288>K$7,$C288+$E288-1<K$7),0,($D288-SUM($F288:J288)-SUM($F227:J227))/($E288+$C288-K$7)) -> 0.005468773 | L288: =IF(OR($C288>L$7,$C288+$E288-1<L$7),0,($D288-SUM($F288:K288)-SUM($F227:K227))/($E288+$C288-L$7)) -> 0.005468773 | M288: =IF(OR($C288>M$7,$C288+$E288-1<M$7),0,($D288-SUM($F288:L288)-SUM($F227:L227))/($E288+$C288-M$7)) -> 0 | N288: =IF(OR($C288>N$7,$C288+$E288-1<N$7),0,($D288-SUM($F288:M288)-SUM($F227:M227))/($E288+$C288-N$7)) -> 0 | ... BN288: =IF(OR($C288>BN$7,$C288+$E288-1<BN$7),0,($D288-SUM($F288:BM288)-SUM($F227:BM227))/($E288+$C288-BN$7)) -> 0
C289: 2 | D289: 0.032246451 | E289: =SAP_Leadsheet!$E$57 -> 6 | G289: =IF(OR($C289>G$7,$C289+$E289-1<G$7),0,($D289-SUM($F289:F289)-SUM($F228:F228))/($E289+$C289-G$7)) -> 0 | H289: =IF(OR($C289>H$7,$C289+$E289-1<H$7),0,($D289-SUM($F289:G289)-SUM($F228:G228))/($E289+$C289-H$7)) -> 0.0053744085 | I289: =IF(OR($C289>I$7,$C289+$E289-1<I$7),0,($D289-SUM($F289:H289)-SUM($F228:H228))/($E289+$C289-I$7)) -> 0.0053744085 | J289: =IF(OR($C289>J$7,$C289+$E289-1<J$7),0,($D289-SUM($F289:I289)-SUM($F228:I228))/($E289+$C289-J$7)) -> 0.0053744085 | K289: =IF(OR($C289>K$7,$C289+$E289-1<K$7),0,($D289-SUM($F289:J289)-SUM($F228:J228))/($E289+$C289-K$7)) -> 0.0053744085 | L289: =IF(OR($C289>L$7,$C289+$E289-1<L$7),0,($D289-SUM($F289:K289)-SUM($F228:K228))/($E289+$C289-L$7)) -> 0.0053744085 | M289: =IF(OR($C289>M$7,$C289+$E289-1<M$7),0,($D289-SUM($F289:L289)-SUM($F228:L228))/($E289+$C289-M$7)) -> 0.0053744085 | N289: =IF(OR($C289>N$7,$C289+$E289-1<N$7),0,($D289-SUM($F289:M289)-SUM($F228:M228))/($E289+$C289-N$7)) -> 0 | ... BN289: =IF(OR($C289>BN$7,$C289+$E289-1<BN$7),0,($D289-SUM($F289:BM289)-SUM($F228:BM228))/($E289+$C289-BN$7)) -> 0
C290: 3 | D290: 0.031680264 | E290: =SAP_Leadsheet!$E$57 -> 6 | G290: =IF(OR($C290>G$7,$C290+$E290-1<G$7),0,($D290-SUM($F290:F290)-SUM($F229:F229))/($E290+$C290-G$7)) -> 0 | H290: =IF(OR($C290>H$7,$C290+$E290-1<H$7),0,($D290-SUM($F290:G290)-SUM($F229:G229))/($E290+$C290-H$7)) -> 0 | I290: =IF(OR($C290>I$7,$C290+$E290-1<I$7),0,($D290-SUM($F290:H290)-SUM($F229:H229))/($E290+$C290-I$7)) -> 0.0052800441 | J290: =IF(OR($C290>J$7,$C290+$E290-1<J$7),0,($D290-SUM($F290:I290)-SUM($F229:I229))/($E290+$C290-J$7)) -> 0.0052800441 | K290: =IF(OR($C290>K$7,$C290+$E290-1<K$7),0,($D290-SUM($F290:J290)-SUM($F229:J229))/($E290+$C290-K$7)) -> 0.0052800441 | L290: =IF(OR($C290>L$7,$C290+$E290-1<L$7),0,($D290-SUM($F290:K290)-SUM($F229:K229))/($E290+$C290-L$7)) -> 0.0052800441 | M290: =IF(OR($C290>M$7,$C290+$E290-1<M$7),0,($D290-SUM($F290:L290)-SUM($F229:L229))/($E290+$C290-M$7)) -> 0.0052800441 | N290: =IF(OR($C290>N$7,$C290+$E290-1<N$7),0,($D290-SUM($F290:M290)-SUM($F229:M229))/($E290+$C290-N$7)) -> 0.0052800441 | ... BN290: =IF(OR($C290>BN$7,$C290+$E290-1<BN$7),0,($D290-SUM($F290:BM290)-SUM($F229:BM229))/($E290+$C290-BN$7)) -> 0
C291: 4 | D291: 0.031114078 | E291: =SAP_Leadsheet!$E$57 -> 6 | G291: =IF(OR($C291>G$7,$C291+$E291-1<G$7),0,($D291-SUM($F291:F291)-SUM($F230:F230))/($E291+$C291-G$7)) -> 0 | H291: =IF(OR($C291>H$7,$C291+$E291-1<H$7),0,($D291-SUM($F291:G291)-SUM($F230:G230))/($E291+$C291-H$7)) -> 0 | I291: =IF(OR($C291>I$7,$C291+$E291-1<I$7),0,($D291-SUM($F291:H291)-SUM($F230:H230))/($E291+$C291-I$7)) -> 0 | J291: =IF(OR($C291>J$7,$C291+$E291-1<J$7),0,($D291-SUM($F291:I291)-SUM($F230:I230))/($E291+$C291-J$7)) -> 0.0051856796 | K291: =IF(OR($C291>K$7,$C291+$E291-1<K$7),0,($D291-SUM($F291:J291)-SUM($F230:J230))/($E291+$C291-K$7)) -> 0.0051856796 | L291: =IF(OR($C291>L$7,$C291+$E291-1<L$7),0,($D291-SUM($F291:K291)-SUM($F230:K230))/($E291+$C291-L$7)) -> 0.0051856796 | M291: =IF(OR($C291>M$7,$C291+$E291-1<M$7),0,($D291-SUM($F291:L291)-SUM($F230:L230))/($E291+$C291-M$7)) -> 0.0051856796 | N291: =IF(OR($C291>N$7,$C291+$E291-1<N$7),0,($D291-SUM($F291:M291)-SUM($F230:M230))/($E291+$C291-N$7)) -> 0.0051856796 | ... BN291: =IF(OR($C291>BN$7,$C291+$E291-1<BN$7),0,($D291-SUM($F291:BM291)-SUM($F230:BM230))/($E291+$C291-BN$7)) -> 0
C292: 5 | D292: 0.030547891 | E292: =SAP_Leadsheet!$E$57 -> 6 | G292: =IF(OR($C292>G$7,$C292+$E292-1<G$7),0,($D292-SUM($F292:F292)-SUM($F231:F231))/($E292+$C292-G$7)) -> 0 | H292: =IF(OR($C292>H$7,$C292+$E292-1<H$7),0,($D292-SUM($F292:G292)-SUM($F231:G231))/($E292+$C292-H$7)) -> 0 | I292: =IF(OR($C292>I$7,$C292+$E292-1<I$7),0,($D292-SUM($F292:H292)-SUM($F231:H231))/($E292+$C292-I$7)) -> 0 | J292: =IF(OR($C292>J$7,$C292+$E292-1<J$7),0,($D292-SUM($F292:I292)-SUM($F231:I231))/($E292+$C292-J$7)) -> 0 | K292: =IF(OR($C292>K$7,$C292+$E292-1<K$7),0,($D292-SUM($F292:J292)-SUM($F231:J231))/($E292+$C292-K$7)) -> 0.0050913152 | L292: =IF(OR($C292>L$7,$C292+$E292-1<L$7),0,($D292-SUM($F292:K292)-SUM($F231:K231))/($E292+$C292-L$7)) -> 0.0050913152 | M292: =IF(OR($C292>M$7,$C292+$E292-1<M$7),0,($D292-SUM($F292:L292)-SUM($F231:L231))/($E292+$C292-M$7)) -> 0.0050913152 | N292: =IF(OR($C292>N$7,$C292+$E292-1<N$7),0,($D292-SUM($F292:M292)-SUM($F231:M231))/($E292+$C292-N$7)) -> 0.0050913152 | ... BN292: =IF(OR($C292>BN$7,$C292+$E292-1<BN$7),0,($D292-SUM($F292:BM292)-SUM($F231:BM231))/($E292+$C292-BN$7)) -> 0
C293: 6 | D293: 0.029981704 | E293: =SAP_Leadsheet!$E$57 -> 6 | G293: =IF(OR($C293>G$7,$C293+$E293-1<G$7),0,($D293-SUM($F293:F293)-SUM($F232:F232))/($E293+$C293-G$7)) -> 0 | H293: =IF(OR($C293>H$7,$C293+$E293-1<H$7),0,($D293-SUM($F293:G293)-SUM($F232:G232))/($E293+$C293-H$7)) -> 0 | I293: =IF(OR($C293>I$7,$C293+$E293-1<I$7),0,($D293-SUM($F293:H293)-SUM($F232:H232))/($E293+$C293-I$7)) -> 0 | J293: =IF(OR($C293>J$7,$C293+$E293-1<J$7),0,($D293-SUM($F293:I293)-SUM($F232:I232))/($E293+$C293-J$7)) -> 0 | K293: =IF(OR($C293>K$7,$C293+$E293-1<K$7),0,($D293-SUM($F293:J293)-SUM($F232:J232))/($E293+$C293-K$7)) -> 0 | L293: =IF(OR($C293>L$7,$C293+$E293-1<L$7),0,($D293-SUM($F293:K293)-SUM($F232:K232))/($E293+$C293-L$7)) -> 0.0049969507 | M293: =IF(OR($C293>M$7,$C293+$E293-1<M$7),0,($D293-SUM($F293:L293)-SUM($F232:L232))/($E293+$C293-M$7)) -> 0.0049969507 | N293: =IF(OR($C293>N$7,$C293+$E293-1<N$7),0,($D293-SUM($F293:M293)-SUM($F232:M232))/($E293+$C293-N$7)) -> 0.0049969507 | ... BN293: =IF(OR($C293>BN$7,$C293+$E293-1<BN$7),0,($D293-SUM($F293:BM293)-SUM($F232:BM232))/($E293+$C293-BN$7)) -> 0
C294: 7 | D294: 0.029415518 | E294: =SAP_Leadsheet!$E$57 -> 6 | G294: =IF(OR($C294>G$7,$C294+$E294-1<G$7),0,($D294-SUM($F294:F294)-SUM($F233:F233))/($E294+$C294-G$7)) -> 0 | H294: =IF(OR($C294>H$7,$C294+$E294-1<H$7),0,($D294-SUM($F294:G294)-SUM($F233:G233))/($E294+$C294-H$7)) -> 0 | I294: =IF(OR($C294>I$7,$C294+$E294-1<I$7),0,($D294-SUM($F294:H294)-SUM($F233:H233))/($E294+$C294-I$7)) -> 0 | J294: =IF(OR($C294>J$7,$C294+$E294-1<J$7),0,($D294-SUM($F294:I294)-SUM($F233:I233))/($E294+$C294-J$7)) -> 0 | K294: =IF(OR($C294>K$7,$C294+$E294-1<K$7),0,($D294-SUM($F294:J294)-SUM($F233:J233))/($E294+$C294-K$7)) -> 0 | L294: =IF(OR($C294>L$7,$C294+$E294-1<L$7),0,($D294-SUM($F294:K294)-SUM($F233:K233))/($E294+$C294-L$7)) -> 0 | M294: =IF(OR($C294>M$7,$C294+$E294-1<M$7),0,($D294-SUM($F294:L294)-SUM($F233:L233))/($E294+$C294-M$7)) -> 0.0049025863 | N294: =IF(OR($C294>N$7,$C294+$E294-1<N$7),0,($D294-SUM($F294:M294)-SUM($F233:M233))/($E294+$C294-N$7)) -> 0.0049025863 | ... BN294: =IF(OR($C294>BN$7,$C294+$E294-1<BN$7),0,($D294-SUM($F294:BM294)-SUM($F233:BM233))/($E294+$C294-BN$7)) -> 0
C295: 8 | D295: 0.028849331 | E295: =SAP_Leadsheet!$E$57 -> 6 | G295: =IF(OR($C295>G$7,$C295+$E295-1<G$7),0,($D295-SUM($F295:F295)-SUM($F234:F234))/($E295+$C295-G$7)) -> 0 | H295: =IF(OR($C295>H$7,$C295+$E295-1<H$7),0,($D295-SUM($F295:G295)-SUM($F234:G234))/($E295+$C295-H$7)) -> 0 | I295: =IF(OR($C295>I$7,$C295+$E295-1<I$7),0,($D295-SUM($F295:H295)-SUM($F234:H234))/($E295+$C295-I$7)) -> 0 | J295: =IF(OR($C295>J$7,$C295+$E295-1<J$7),0,($D295-SUM($F295:I295)-SUM($F234:I234))/($E295+$C295-J$7)) -> 0 | K295: =IF(OR($C295>K$7,$C295+$E295-1<K$7),0,($D295-SUM($F295:J295)-SUM($F234:J234))/($E295+$C295-K$7)) -> 0 | L295: =IF(OR($C295>L$7,$C295+$E295-1<L$7),0,($D295-SUM($F295:K295)-SUM($F234:K234))/($E295+$C295-L$7)) -> 0 | M295: =IF(OR($C295>M$7,$C295+$E295-1<M$7),0,($D295-SUM($F295:L295)-SUM($F234:L234))/($E295+$C295-M$7)) -> 0 | N295: =IF(OR($C295>N$7,$C295+$E295-1<N$7),0,($D295-SUM($F295:M295)-SUM($F234:M234))/($E295+$C295-N$7)) -> 0.0048082218 | ... BN295: =IF(OR($C295>BN$7,$C295+$E295-1<BN$7),0,($D295-SUM($F295:BM295)-SUM($F234:BM234))/($E295+$C295-BN$7)) -> 0
C296: 9 | D296: 0.028283144 | E296: =SAP_Leadsheet!$E$57 -> 6 | G296: =IF(OR($C296>G$7,$C296+$E296-1<G$7),0,($D296-SUM($F296:F296)-SUM($F235:F235))/($E296+$C296-G$7)) -> 0 | H296: =IF(OR($C296>H$7,$C296+$E296-1<H$7),0,($D296-SUM($F296:G296)-SUM($F235:G235))/($E296+$C296-H$7)) -> 0 | I296: =IF(OR($C296>I$7,$C296+$E296-1<I$7),0,($D296-SUM($F296:H296)-SUM($F235:H235))/($E296+$C296-I$7)) -> 0 | J296: =IF(OR($C296>J$7,$C296+$E296-1<J$7),0,($D296-SUM($F296:I296)-SUM($F235:I235))/($E296+$C296-J$7)) -> 0 | K296: =IF(OR($C296>K$7,$C296+$E296-1<K$7),0,($D296-SUM($F296:J296)-SUM($F235:J235))/($E296+$C296-K$7)) -> 0 | L296: =IF(OR($C296>L$7,$C296+$E296-1<L$7),0,($D296-SUM($F296:K296)-SUM($F235:K235))/($E296+$C296-L$7)) -> 0 | M296: =IF(OR($C296>M$7,$C296+$E296-1<M$7),0,($D296-SUM($F296:L296)-SUM($F235:L235))/($E296+$C296-M$7)) -> 0 | N296: =IF(OR($C296>N$7,$C296+$E296-1<N$7),0,($D296-SUM($F296:M296)-SUM($F235:M235))/($E296+$C296-N$7)) -> 0 | ... BN296: =IF(OR($C296>BN$7,$C296+$E296-1<BN$7),0,($D296-SUM($F296:BM296)-SUM($F235:BM235))/($E296+$C296-BN$7)) -> 0
C297: 10 | D297: 0.027716957 | E297: =SAP_Leadsheet!$E$57 -> 6 | G297: =IF(OR($C297>G$7,$C297+$E297-1<G$7),0,($D297-SUM($F297:F297)-SUM($F236:F236))/($E297+$C297-G$7)) -> 0 | H297: =IF(OR($C297>H$7,$C297+$E297-1<H$7),0,($D297-SUM($F297:G297)-SUM($F236:G236))/($E297+$C297-H$7)) -> 0 | I297: =IF(OR($C297>I$7,$C297+$E297-1<I$7),0,($D297-SUM($F297:H297)-SUM($F236:H236))/($E297+$C297-I$7)) -> 0 | J297: =IF(OR($C297>J$7,$C297+$E297-1<J$7),0,($D297-SUM($F297:I297)-SUM($F236:I236))/($E297+$C297-J$7)) -> 0 | K297: =IF(OR($C297>K$7,$C297+$E297-1<K$7),0,($D297-SUM($F297:J297)-SUM($F236:J236))/($E297+$C297-K$7)) -> 0 | L297: =IF(OR($C297>L$7,$C297+$E297-1<L$7),0,($D297-SUM($F297:K297)-SUM($F236:K236))/($E297+$C297-L$7)) -> 0 | M297: =IF(OR($C297>M$7,$C297+$E297-1<M$7),0,($D297-SUM($F297:L297)-SUM($F236:L236))/($E297+$C297-M$7)) -> 0 | N297: =IF(OR($C297>N$7,$C297+$E297-1<N$7),0,($D297-SUM($F297:M297)-SUM($F236:M236))/($E297+$C297-N$7)) -> 0 | ... BN297: =IF(OR($C297>BN$7,$C297+$E297-1<BN$7),0,($D297-SUM($F297:BM297)-SUM($F236:BM236))/($E297+$C297-BN$7)) -> 0
...

Sheet Sales plan& PnL
E1: PROFIT & LOSS 60M | H1: =SAP_Leadsheet!C6 -> DPD180+
A3: Code | B3: Product | C3: Old/new | D3: Item | F3: I. | G3: SALES PLAN
A4: =B4&D4&C4 -> Auto loan | B4: Auto loan
H5: If you want to estimate the mix price & promotion tenor for your product package, please input here & link to Leadsheet properly in term of pricing
A6: =B6&D6&C6 -> Auto loan | B6: Auto loan | H6: Please input your expected disbursement volume with date of lauching out product if you would like to project 60M profit and loss.
A8: =B8&D8&C8 -> Auto loan | B8: Auto loan | H8: Business month | J8: 45658 | K8: =EOMONTH(J8,1) -> 45716 | L8: =EOMONTH(K8,1) -> 45747 | M8: =EOMONTH(L8,1) -> 45777 | N8: =EOMONTH(M8,1) -> 45808 | O8: =EOMONTH(N8,1) -> 45838 | P8: =EOMONTH(O8,1) -> 45869 | Q8: =EOMONTH(P8,1) -> 45900 | R8: =EOMONTH(Q8,1) -> 45930 | ... BR8: =EOMONTH(BQ8,1) -> 47514
H9: Don't delete | J9: =YEAR(J8) -> 2025 | K9: =YEAR(K8) -> 2025 | L9: =YEAR(L8) -> 2025 | M9: =YEAR(M8) -> 2025 | N9: =YEAR(N8) -> 2025 | O9: =YEAR(O8) -> 2025 | P9: =YEAR(P8) -> 2025 | Q9: =YEAR(Q8) -> 2025 | ... BR9: =YEAR(BR8) -> 2030
A10: =B10&D10&C10 -> Auto loan | B10: Auto loan | H10: New issued (Card)
F12: II. | G12: PROFIT & LOSS
H14: FISCAL YEAR | J14: Total | K14: =J9 -> 2025 | L14: =K14+1 -> 2026 | M14: =L14+1 -> 2027 | N14: =M14+1 -> 2028 | O14: =N14+1 -> 2029 | P14: =O14+1 -> 2030
J15: bVND | K15: bVND | L15: bVND | M15: bVND | N15: bVND | O15: bVND | P15: bVND
H17: New Issued Paylater | J17: =SUM(K17:U17) -> 0 | K17: =SUMIF($J$9:$BQ$9,K$14,$J$10:$BQ$10) -> 0 | L17: =SUMIF($J$9:$BQ$9,L$14,$J$10:$BQ$10) -> 0 | M17: =SUMIF($J$9:$BQ$9,M$14,$J$10:$BQ$10) -> 0 | N17: =SUMIF($J$9:$BQ$9,N$14,$J$10:$BQ$10) -> 0 | O17: =SUMIF($J$9:$BQ$9,O$14,$J$10:$BQ$10) -> 0 | P17: =SUMIF($J$9:$BQ$9,P$14,$J$10:$BQ$10) -> 0
H18: Average monthly issued Paylater | J18: =AVERAGE(J10:AS10) -> #DIV/0! | K18: =K17/COUNTIF($J$9:$AS$9,K14) -> 0 | L18: =L17/COUNTIF($J$9:$AS$9,L14) -> 0 | M18: =M17/COUNTIF($J$9:$AS$9,M14) -> 0 | N18: =N17/COUNTIF($J$9:$BQ$9,N14) -> 0 | O18: =O17/COUNTIF($J$9:$BQ$9,O14) -> 0 | P18: =IFERROR(P17/COUNTIF($J$9:$BQ$9,P14),0) -> 0
H20: EOP | K20: =OFFSET(PnL_Speadsheet!$D$7,0,MATCH(DATE('Sales plan& PnL'!K$14,12,31),PnL_Speadsheet!$E$4:$BL$4,0))/1000 -> 0 | L20: =OFFSET(PnL_Speadsheet!$D$7,0,MATCH(DATE('Sales plan& PnL'!L$14,12,31),PnL_Speadsheet!$E$4:$BL$4,0))/1000 -> 0 | M20: =OFFSET(PnL_Speadsheet!$D$7,0,MATCH(DATE('Sales plan& PnL'!M$14,12,31),PnL_Speadsheet!$E$4:$BL$4,0))/1000 -> 0 | N20: =OFFSET(PnL_Speadsheet!$D$7,0,MATCH(DATE('Sales plan& PnL'!N$14,12,31),PnL_Speadsheet!$E$4:$BL$4,0))/1000 -> 0 | O20: =PnL_Speadsheet!BL7/1000 -> 0 | P20: =PnL_Speadsheet!BN7/1000 -> 0
H21: ADB | J21: =SUM(PnL_Speadsheet!E8:BK8)/1000/COUNT(PnL_Speadsheet!E3:BK3) -> 0 | K21: =SUMIF(PnL_Speadsheet!$E$3:$BL$3,K$14,PnL_Speadsheet!$E8:$BL8)/1000/COUNTIF(PnL_Speadsheet!$E$3:$BL$3,'Sales plan& PnL'!K$14) -> 0 | L21: =SUMIF(PnL_Speadsheet!$E$3:$BL$3,L$14,PnL_Speadsheet!$E8:$BL8)/1000/COUNTIF(PnL_Speadsheet!$E$3:$BL$3,'Sales plan& PnL'!L$14) -> 0 | M21: =SUMIF(PnL_Speadsheet!$E$3:$BL$3,M$14,PnL_Speadsheet!$E8:$BL8)/1000/COUNTIF(PnL_Speadsheet!$E$3:$BL$3,'Sales plan& PnL'!M$14) -> 0 | N21: =SUMIF(PnL_Speadsheet!$E$3:$BL$3,N$14,PnL_Speadsheet!$E8:$BL8)/1000/COUNTIF(PnL_Speadsheet!$E$3:$BL$3,'Sales plan& PnL'!N$14) -> 0 | O21: =SUMIF(PnL_Speadsheet!$E$3:$BL$3,O$14,PnL_Speadsheet!$E8:$BL8)/1000/COUNTIF(PnL_Speadsheet!$E$3:$BL$3,'Sales plan& PnL'!O$14) -> 0 | P21: =IFERROR(SUMIF(PnL_Speadsheet!$E$3:$BL$3,P$14,PnL_Speadsheet!$E8:$BL8)/1000/COUNTIF(PnL_Speadsheet!$E$3:$BL$3,'Sales plan& PnL'!P$14),0) -> 0
H23: TOI | J23: =SUM(K23:U23) -> 0 | K23: =SUMIF(PnL_Speadsheet!$E$3:$BL$3,K$14,PnL_Speadsheet!$E9:$BL9)/1000 -> 0 | L23: =SUMIF(PnL_Speadsheet!$E$3:$BL$3,L$14,PnL_Speadsheet!$E9:$BL9)/1000 -> 0 | M23: =SUMIF(PnL_Speadsheet!$E$3:$BL$3,M$14,PnL_Speadsheet!$E9:$BL9)/1000 -> 0 | N23: =SUMIF(PnL_Speadsheet!$E$3:$BL$3,N$14,PnL_Speadsheet!$E9:$BL9)/1000 -> 0 | O23: =SUMIF(PnL_Speadsheet!$E$3:$BL$3,O$14,PnL_Speadsheet!$E9:$BL9)/1000 -> 0 | P23: =SUMIF(PnL_Speadsheet!$E$3:$BL$3,P$14,PnL_Speadsheet!$E9:$BL9)/1000 -> 0
H24: NII | J24: =SUM(K24:U24) -> 0 | K24: =SUMIF(PnL_Speadsheet!$E$3:$BL$3,K$14,PnL_Speadsheet!$E10:$BL10)/1000 -> 0 | L24: =SUMIF(PnL_Speadsheet!$E$3:$BL$3,L$14,PnL_Speadsheet!$E10:$BL10)/1000 -> 0 | M24: =SUMIF(PnL_Speadsheet!$E$3:$BL$3,M$14,PnL_Speadsheet!$E10:$BL10)/1000 -> 0 | N24: =SUMIF(PnL_Speadsheet!$E$3:$BL$3,N$14,PnL_Speadsheet!$E10:$BL10)/1000 -> 0 | O24: =SUMIF(PnL_Speadsheet!$E$3:$BL$3,O$14,PnL_Speadsheet!$E10:$BL10)/1000 -> 0 | P24: =SUMIF(PnL_Speadsheet!$E$3:$BL$3,P$14,PnL_Speadsheet!$E10:$BL10)/1000 -> 0
H25: CII | J25: =SUM(K25:U25) -> 0 | K25: =SUMIF(PnL_Speadsheet!$E$3:$BL$3,K$14,PnL_Speadsheet!$E11:$BL11)/1000 -> 0 | L25: =SUMIF(PnL_Speadsheet!$E$3:$BL$3,L$14,PnL_Speadsheet!$E11:$BL11)/1000 -> 0 | M25: =SUMIF(PnL_Speadsheet!$E$3:$BL$3,M$14,PnL_Speadsheet!$E11:$BL11)/1000 -> 0 | N25: =SUMIF(PnL_Speadsheet!$E$3:$BL$3,N$14,PnL_Speadsheet!$E11:$BL11)/1000 -> 0 | O25: =SUMIF(PnL_Speadsheet!$E$3:$BL$3,O$14,PnL_Speadsheet!$E11:$BL11)/1000 -> 0 | P25: =SUMIF(PnL_Speadsheet!$E$3:$BL$3,P$14,PnL_Speadsheet!$E11:$BL11)/1000 -> 0
H26: COF | J26: =SUM(K26:U26) -> 0 | K26: =SUMIF(PnL_Speadsheet!$E$3:$BL$3,K$14,PnL_Speadsheet!$E12:$BL12)/1000 -> 0 | L26: =SUMIF(PnL_Speadsheet!$E$3:$BL$3,L$14,PnL_Speadsheet!$E12:$BL12)/1000 -> 0 | M26: =SUMIF(PnL_Speadsheet!$E$3:$BL$3,M$14,PnL_Speadsheet!$E12:$BL12)/1000 -> 0 | N26: =SUMIF(PnL_Speadsheet!$E$3:$BL$3,N$14,PnL_Speadsheet!$E12:$BL12)/1000 -> 0 | O26: =SUMIF(PnL_Speadsheet!$E$3:$BL$3,O$14,PnL_Speadsheet!$E12:$BL12)/1000 -> 0 | P26: =SUMIF(PnL_Speadsheet!$E$3:$BL$3,P$14,PnL_Speadsheet!$E12:$BL12)/1000 -> 0
H27: NFI | J27: =SUM(K27:U27) -> 0 | K27: =SUMIF(PnL_Speadsheet!$E$3:$BL$3,K$14,PnL_Speadsheet!$E13:$BL13)/1000 -> 0 | L27: =SUMIF(PnL_Speadsheet!$E$3:$BL$3,L$14,PnL_Speadsheet!$E13:$BL13)/1000 -> 0 | M27: =SUMIF(PnL_Speadsheet!$E$3:$BL$3,M$14,PnL_Speadsheet!$E13:$BL13)/1000 -> 0 | N27: =SUMIF(PnL_Speadsheet!$E$3:$BL$3,N$14,PnL_Speadsheet!$E13:$BL13)/1000 -> 0 | O27: =SUMIF(PnL_Speadsheet!$E$3:$BL$3,O$14,PnL_Speadsheet!$E13:$BL13)/1000 -> 0 | P27: =SUMIF(PnL_Speadsheet!$E$3:$BL$3,P$14,PnL_Speadsheet!$E13:$BL13)/1000 -> 0
H28: Annual fee | J28: =SUM(K28:U28) -> 0 | K28: =SUMIF(PnL_Speadsheet!$E$3:$BL$3,K$14,PnL_Speadsheet!$E14:$BL14)/1000 -> 0 | L28: =SUMIF(PnL_Speadsheet!$E$3:$BL$3,L$14,PnL_Speadsheet!$E14:$BL14)/1000 -> 0 | M28: =SUMIF(PnL_Speadsheet!$E$3:$BL$3,M$14,PnL_Speadsheet!$E14:$BL14)/1000 -> 0 | N28: =SUMIF(PnL_Speadsheet!$E$3:$BL$3,N$14,PnL_Speadsheet!$E14:$BL14)/1000 -> 0 | O28: =SUMIF(PnL_Speadsheet!$E$3:$BL$3,O$14,PnL_Speadsheet!$E14:$BL14)/1000 -> 0 | P28: =SUMIF(PnL_Speadsheet!$E$3:$BL$3,P$14,PnL_Speadsheet!$E14:$BL14)/1000 -> 0
H29: Monthly fee | J29: =SUM(K29:U29) -> 0 | K29: =SUMIF(PnL_Speadsheet!$E$3:$BL$3,K$14,PnL_Speadsheet!$E15:$BL15)/1000 -> 0 | L29: =SUMIF(PnL_Speadsheet!$E$3:$BL$3,L$14,PnL_Speadsheet!$E15:$BL15)/1000 -> 0 | M29: =SUMIF(PnL_Speadsheet!$E$3:$BL$3,M$14,PnL_Speadsheet!$E15:$BL15)/1000 -> 0 | N29: =SUMIF(PnL_Speadsheet!$E$3:$BL$3,N$14,PnL_Speadsheet!$E15:$BL15)/1000 -> 0 | O29: =SUMIF(PnL_Speadsheet!$E$3:$BL$3,O$14,PnL_Speadsheet!$E15:$BL15)/1000 -> 0 | P29: =SUMIF(PnL_Speadsheet!$E$3:$BL$3,P$14,PnL_Speadsheet!$E15:$BL15)/1000 -> 0
H30: Transaction fee | J30: =SUM(K30:U30) -> 0 | K30: =SUMIF(PnL_Speadsheet!$E$3:$BL$3,K$14,PnL_Speadsheet!$E16:$BL16)/1000 -> 0 | L30: =SUMIF(PnL_Speadsheet!$E$3:$BL$3,L$14,PnL_Speadsheet!$E16:$BL16)/1000 -> 0 | M30: =SUMIF(PnL_Speadsheet!$E$3:$BL$3,M$14,PnL_Speadsheet!$E16:$BL16)/1000 -> 0 | N30: =SUMIF(PnL_Speadsheet!$E$3:$BL$3,N$14,PnL_Speadsheet!$E16:$BL16)/1000 -> 0 | O30: =SUMIF(PnL_Speadsheet!$E$3:$BL$3,O$14,PnL_Speadsheet!$E16:$BL16)/1000 -> 0 | P30: =SUMIF(PnL_Speadsheet!$E$3:$BL$3,P$14,PnL_Speadsheet!$E16:$BL16)/1000 -> 0
H31: Issuance fee | J31: =SUM(K31:U31) -> 0 | K31: =SUMIF(PnL_Speadsheet!$E$3:$BL$3,K$14,PnL_Speadsheet!$E17:$BL17)/1000 -> 0 | L31: =SUMIF(PnL_Speadsheet!$E$3:$BL$3,L$14,PnL_Speadsheet!$E17:$BL17)/1000 -> 0 | M31: =SUMIF(PnL_Speadsheet!$E$3:$BL$3,M$14,PnL_Speadsheet!$E17:$BL17)/1000 -> 0 | N31: =SUMIF(PnL_Speadsheet!$E$3:$BL$3,N$14,PnL_Speadsheet!$E17:$BL17)/1000 -> 0 | O31: =SUMIF(PnL_Speadsheet!$E$3:$BL$3,O$14,PnL_Speadsheet!$E17:$BL17)/1000 -> 0 | P31: =SUMIF(PnL_Speadsheet!$E$3:$BL$3,P$14,PnL_Speadsheet!$E17:$BL17)/1000 -> 0
H32: Subvention fee | J32: =SUM(K32:U32) -> 0 | K32: =SUMIF(PnL_Speadsheet!$E$3:$BL$3,K$14,PnL_Speadsheet!$E18:$BL18)/1000 -> 0 | L32: =SUMIF(PnL_Speadsheet!$E$3:$BL$3,L$14,PnL_Speadsheet!$E18:$BL18)/1000 -> 0 | M32: =SUMIF(PnL_Speadsheet!$E$3:$BL$3,M$14,PnL_Speadsheet!$E18:$BL18)/1000 -> 0 | N32: =SUMIF(PnL_Speadsheet!$E$3:$BL$3,N$14,PnL_Speadsheet!$E18:$BL18)/1000 -> 0 | O32: =SUMIF(PnL_Speadsheet!$E$3:$BL$3,O$14,PnL_Speadsheet!$E18:$BL18)/1000 -> 0 | P32: =SUMIF(PnL_Speadsheet!$E$3:$BL$3,P$14,PnL_Speadsheet!$E18:$BL18)/1000 -> 0
H33: Late payment | J33: =SUM(K33:U33) -> 0 | K33: =SUMIF(PnL_Speadsheet!$E$3:$BL$3,K$14,PnL_Speadsheet!$E19:$BL19)/1000 -> 0 | L33: =SUMIF(PnL_Speadsheet!$E$3:$BL$3,L$14,PnL_Speadsheet!$E19:$BL19)/1000 -> 0 | M33: =SUMIF(PnL_Speadsheet!$E$3:$BL$3,M$14,PnL_Speadsheet!$E19:$BL19)/1000 -> 0 | N33: =SUMIF(PnL_Speadsheet!$E$3:$BL$3,N$14,PnL_Speadsheet!$E19:$BL19)/1000 -> 0 | O33: =SUMIF(PnL_Speadsheet!$E$3:$BL$3,O$14,PnL_Speadsheet!$E19:$BL19)/1000 -> 0 | P33: =SUMIF(PnL_Speadsheet!$E$3:$BL$3,P$14,PnL_Speadsheet!$E19:$BL19)/1000 -> 0
H34: Min due fee | J34: =SUM(K34:U34) -> 0 | K34: =SUMIF(PnL_Speadsheet!$E$3:$BL$3,K$14,PnL_Speadsheet!$E20:$BL20)/1000 -> 0 | L34: =SUMIF(PnL_Speadsheet!$E$3:$BL$3,L$14,PnL_Speadsheet!$E20:$BL20)/1000 -> 0 | M34: =SUMIF(PnL_Speadsheet!$E$3:$BL$3,M$14,PnL_Speadsheet!$E20:$BL20)/1000 -> 0 | N34: =SUMIF(PnL_Speadsheet!$E$3:$BL$3,N$14,PnL_Speadsheet!$E20:$BL20)/1000 -> 0 | O34: =SUMIF(PnL_Speadsheet!$E$3:$BL$3,O$14,PnL_Speadsheet!$E20:$BL20)/1000 -> 0 | P34: =SUMIF(PnL_Speadsheet!$E$3:$BL$3,P$14,PnL_Speadsheet!$E20:$BL20)/1000 -> 0
... H38: Other income | J38: =SUM(K38:U38) -> 0 | K38: =SUMIF(PnL_Speadsheet!$E$3:$BL$3,K$14,PnL_Speadsheet!$E24:$BL24)/1000 -> 0 | L38: =SUMIF(PnL_Speadsheet!$E$3:$BL$3,L$14,PnL_Speadsheet!$E24:$BL24)/1000 -> 0 | M38: =SUMIF(PnL_Speadsheet!$E$3:$BL$3,M$14,PnL_Speadsheet!$E24:$BL24)/1000 -> 0 | N38: =SUMIF(PnL_Speadsheet!$E$3:$BL$3,N$14,PnL_Speadsheet!$E24:$BL24)/1000 -> 0 | O38: =SUMIF(PnL_Speadsheet!$E$3:$BL$3,O$14,PnL_Speadsheet!$E24:$BL24)/1000 -> 0 | P38: =SUMIF(PnL_Speadsheet!$E$3:$BL$3,P$14,PnL_Speadsheet!$E24:$BL24)/1000 -> 0
H39: OPEX | J39: =SUM(K39:U39) -> 0 | K39: =(SUMIF(PnL_Speadsheet!$E$3:$BL$3,K$14,PnL_Speadsheet!$E26:$BL26)/1000) -> 0 | L39: =(SUMIF(PnL_Speadsheet!$E$3:$BL$3,L$14,PnL_Speadsheet!$E26:$BL26)/1000) -> 0 | M39: =(SUMIF(PnL_Speadsheet!$E$3:$BL$3,M$14,PnL_Speadsheet!$E26:$BL26)/1000) -> 0 | N39: =(SUMIF(PnL_Speadsheet!$E$3:$BL$3,N$14,PnL_Speadsheet!$E26:$BL26)/1000) -> 0 | O39: =(SUMIF(PnL_Speadsheet!$E$3:$BL$3,O$14,PnL_Speadsheet!$E26:$BL26)/1000) -> 0 | P39: =(SUMIF(PnL_Speadsheet!$E$3:$BL$3,P$14,PnL_Speadsheet!$E26:$BL26)/1000) -> 0
H40: Variable expenses | J40: =J41+J44+J45+J46+J47 -> 0 | K40: =K41+K44+K45+K46+K47 -> 0 | L40: =L41+L44+L45+L46+L47 -> 0 | M40: =M41+M44+M45+M46+M47 -> 0 | N40: =N41+N44+N45+N46+N47 -> 0 | O40: =O41+O44+O45+O46+O47 -> 0 | P40: =P41+P44+P45+P46+P47 -> 0
H41: Sales & Marketing | J41: =SUM(K41:U41) -> 0 | K41: =(SUMIF(PnL_Speadsheet!$E$3:$BL$3,K$14,PnL_Speadsheet!$E27:$BL27)/1000)-K43 -> 0 | L41: =(SUMIF(PnL_Speadsheet!$E$3:$BL$3,L$14,PnL_Speadsheet!$E27:$BL27)/1000)-L43 -> 0 | M41: =(SUMIF(PnL_Speadsheet!$E$3:$BL$3,M$14,PnL_Speadsheet!$E27:$BL27)/1000)-M43 -> 0 | N41: =(SUMIF(PnL_Speadsheet!$E$3:$BL$3,N$14,PnL_Speadsheet!$E27:$BL27)/1000)-N43 -> 0 | O41: =(SUMIF(PnL_Speadsheet!$E$3:$BL$3,O$14,PnL_Speadsheet!$E27:$BL27)/1000)-O43 -> 0 | P41: =(SUMIF(PnL_Speadsheet!$E$3:$BL$3,P$14,PnL_Speadsheet!$E27:$BL27)/1000)-P43 -> 0
H42: Partner acquisition | J42: =SUM(K42:U42) -> 0 | K42: =(SUMIF(PnL_Speadsheet!$E$3:$BL$3,K$14,PnL_Speadsheet!$E28:$BL28)/1000) -> 0 | L42: =(SUMIF(PnL_Speadsheet!$E$3:$BL$3,L$14,PnL_Speadsheet!$E28:$BL28)/1000) -> 0 | M42: =(SUMIF(PnL_Speadsheet!$E$3:$BL$3,M$14,PnL_Speadsheet!$E28:$BL28)/1000) -> 0 | N42: =(SUMIF(PnL_Speadsheet!$E$3:$BL$3,N$14,PnL_Speadsheet!$E28:$BL28)/1000) -> 0 | O42: =(SUMIF(PnL_Speadsheet!$E$3:$BL$3,O$14,PnL_Speadsheet!$E28:$BL28)/1000) -> 0 | P42: =(SUMIF(PnL_Speadsheet!$E$3:$BL$3,P$14,PnL_Speadsheet!$E28:$BL28)/1000) -> 0
H43: Marketing acquisition | J43: =SUM(K43:U43) -> 0 | K43: =SUMIF(PnL_Speadsheet!$E$3:$BL$3,K$14,PnL_Speadsheet!$E31:$BL31)/1000 -> 0 | L43: =SUMIF(PnL_Speadsheet!$E$3:$BL$3,L$14,PnL_Speadsheet!$E31:$BL31)/1000 -> 0 | M43: =SUMIF(PnL_Speadsheet!$E$3:$BL$3,M$14,PnL_Speadsheet!$E31:$BL31)/1000 -> 0 | N43: =SUMIF(PnL_Speadsheet!$E$3:$BL$3,N$14,PnL_Speadsheet!$E31:$BL31)/1000 -> 0 | O43: =SUMIF(PnL_Speadsheet!$E$3:$BL$3,O$14,PnL_Speadsheet!$E31:$BL31)/1000 -> 0 | P43: =SUMIF(PnL_Speadsheet!$E$3:$BL$3,P$14,PnL_Speadsheet!$E31:$BL31)/1000 -> 0
H44: Marketing promotion | J44: =SUM(K44:U44) -> 0 | K44: =(SUMIF(PnL_Speadsheet!$E$3:$BL$3,K$14,PnL_Speadsheet!$E32:$BL32)/1000) -> 0 | L44: =(SUMIF(PnL_Speadsheet!$E$3:$BL$3,L$14,PnL_Speadsheet!$E32:$BL32)/1000) -> 0 | M44: =(SUMIF(PnL_Speadsheet!$E$3:$BL$3,M$14,PnL_Speadsheet!$E32:$BL32)/1000) -> 0 | N44: =(SUMIF(PnL_Speadsheet!$E$3:$BL$3,N$14,PnL_Speadsheet!$E32:$BL32)/1000) -> 0 | O44: =(SUMIF(PnL_Speadsheet!$E$3:$BL$3,O$14,PnL_Speadsheet!$E32:$BL32)/1000) -> 0 | P44: =(SUMIF(PnL_Speadsheet!$E$3:$BL$3,P$14,PnL_Speadsheet!$E32:$BL32)/1000) -> 0
H45: UW & Disbursal | J45: =SUM(K45:U45) -> 0 | K45: =SUMIF(PnL_Speadsheet!$E$3:$BL$3,K$14,PnL_Speadsheet!$E33:$BL33)/1000 -> 0 | L45: =SUMIF(PnL_Speadsheet!$E$3:$BL$3,L$14,PnL_Speadsheet!$E33:$BL33)/1000 -> 0 | M45: =SUMIF(PnL_Speadsheet!$E$3:$BL$3,M$14,PnL_Speadsheet!$E33:$BL33)/1000 -> 0 | N45: =SUMIF(PnL_Speadsheet!$E$3:$BL$3,N$14,PnL_Speadsheet!$E33:$BL33)/1000 -> 0 | O45: =SUMIF(PnL_Speadsheet!$E$3:$BL$3,O$14,PnL_Speadsheet!$E33:$BL33)/1000 -> 0 | P45: =SUMIF(PnL_Speadsheet!$E$3:$BL$3,P$14,PnL_Speadsheet!$E33:$BL33)/1000 -> 0
H46: Collection | J46: =SUM(K46:U46) -> 0 | K46: =SUMIF(PnL_Speadsheet!$E$3:$BL$3,K$14,PnL_Speadsheet!$E34:$BL34)/1000 -> 0 | L46: =SUMIF(PnL_Speadsheet!$E$3:$BL$3,L$14,PnL_Speadsheet!$E34:$BL34)/1000 -> 0 | M46: =SUMIF(PnL_Speadsheet!$E$3:$BL$3,M$14,PnL_Speadsheet!$E34:$BL34)/1000 -> 0 | N46: =SUMIF(PnL_Speadsheet!$E$3:$BL$3,N$14,PnL_Speadsheet!$E34:$BL34)/1000 -> 0 | O46: =SUMIF(PnL_Speadsheet!$E$3:$BL$3,O$14,PnL_Speadsheet!$E34:$BL34)/1000 -> 0 | P46: =SUMIF(PnL_Speadsheet!$E$3:$BL$3,P$14,PnL_Speadsheet!$E34:$BL34)/1000 -> 0
H47: After-sales services | J47: =SUM(K47:U47) -> 0 | K47: =SUMIF(PnL_Speadsheet!$E$3:$BL$3,K$14,PnL_Speadsheet!$E37:$BL37)/1000 -> 0 | L47: =SUMIF(PnL_Speadsheet!$E$3:$BL$3,L$14,PnL_Speadsheet!$E37:$BL37)/1000 -> 0 | M47: =SUMIF(PnL_Speadsheet!$E$3:$BL$3,M$14,PnL_Speadsheet!$E37:$BL37)/1000 -> 0 | N47: =SUMIF(PnL_Speadsheet!$E$3:$BL$3,N$14,PnL_Speadsheet!$E37:$BL37)/1000 -> 0 | O47: =SUMIF(PnL_Speadsheet!$E$3:$BL$3,O$14,PnL_Speadsheet!$E37:$BL37)/1000 -> 0 | P47: =SUMIF(PnL_Speadsheet!$E$3:$BL$3,P$14,PnL_Speadsheet!$E37:$BL37)/1000 -> 0
H48: Overhead expenses | J48: =SUM(K48:U48) -> 0 | K48: =SUMIF(PnL_Speadsheet!$E$3:$BL$3,K$14,PnL_Speadsheet!$E38:$BL38)/1000 -> 0 | L48: =SUMIF(PnL_Speadsheet!$E$3:$BL$3,L$14,PnL_Speadsheet!$E38:$BL38)/1000 -> 0 | M48: =SUMIF(PnL_Speadsheet!$E$3:$BL$3,M$14,PnL_Speadsheet!$E38:$BL38)/1000 -> 0 | N48: =SUMIF(PnL_Speadsheet!$E$3:$BL$3,N$14,PnL_Speadsheet!$E38:$BL38)/1000 -> 0 | O48: =SUMIF(PnL_Speadsheet!$E$3:$BL$3,O$14,PnL_Speadsheet!$E38:$BL38)/1000 -> 0 | P48: =SUMIF(PnL_Speadsheet!$E$3:$BL$3,P$14,PnL_Speadsheet!$E38:$BL38)/1000 -> 0
H49: PROVISION | J49: =SUM(K49:U49) -> 0 | K49: =SUMIF(PnL_Speadsheet!$E$3:$BL$3,K$14,PnL_Speadsheet!$E25:$BL25)/1000 -> 0 | L49: =SUMIF(PnL_Speadsheet!$E$3:$BL$3,L$14,PnL_Speadsheet!$E25:$BL25)/1000 -> 0 | M49: =SUMIF(PnL_Speadsheet!$E$3:$BL$3,M$14,PnL_Speadsheet!$E25:$BL25)/1000 -> 0 | N49: =SUMIF(PnL_Speadsheet!$E$3:$BL$3,N$14,PnL_Speadsheet!$E25:$BL25)/1000 -> 0 | O49: =SUMIF(PnL_Speadsheet!$E$3:$BL$3,O$14,PnL_Speadsheet!$E25:$BL25)/1000 -> 0 | P49: =SUMIF(PnL_Speadsheet!$E$3:$BL$3,P$14,PnL_Speadsheet!$E25:$BL25)/1000 -> 0
H50: PBT | J50: =SUM(K50:U50) -> 0 | K50: =SUMIF(PnL_Speadsheet!$E$3:$BL$3,K$14,PnL_Speadsheet!$E39:$BL39)/1000 -> 0 | L50: =SUMIF(PnL_Speadsheet!$E$3:$BL$3,L$14,PnL_Speadsheet!$E39:$BL39)/1000 -> 0 | M50: =SUMIF(PnL_Speadsheet!$E$3:$BL$3,M$14,PnL_Speadsheet!$E39:$BL39)/1000 -> 0 | N50: =SUMIF(PnL_Speadsheet!$E$3:$BL$3,N$14,PnL_Speadsheet!$E39:$BL39)/1000 -> 0 | O50: =SUMIF(PnL_Speadsheet!$E$3:$BL$3,O$14,PnL_Speadsheet!$E39:$BL39)/1000 -> 0 | P50: =SUMIF(PnL_Speadsheet!$E$3:$BL$3,P$14,PnL_Speadsheet!$E39:$BL39)/1000 -> 0
H51: In which: PROFIT BEFORE SUPPORT COST | J51: =SUM(K51:U51) -> 0 | K51: =K23+K49+SUM(K44:K47) -> 0 | L51: =L23+L49+SUM(L44:L47) -> 0 | M51: =M23+M49+SUM(M44:M47) -> 0 | N51: =N23+N49+SUM(N44:N47) -> 0 | O51: =O23+O49+SUM(O44:O47) -> 0 | P51: =P23+P49+SUM(P44:P47) -> 0

Sheet PnL_Speadsheet
C1: ='Sales plan& PnL'!H1 -> DPD180+ | D1: PL PROJECTION
D2: 60 months
E3: =YEAR(E4) -> 2025 | F3: =YEAR(F4) -> 2025 | G3: =YEAR(G4) -> 2025 | H3: =YEAR(H4) -> 2025 | I3: =YEAR(I4) -> 2025 | J3: =YEAR(J4) -> 2025 | K3: =YEAR(K4) -> 2025 | L3: =YEAR(L4) -> 2025 | ... BL3: =YEAR(BL4) -> 2029
D4: Business month | E4: ='Sales plan& PnL'!J8 -> 45658 | F4: ='Sales plan& PnL'!K8 -> 45716 | G4: ='Sales plan& PnL'!L8 -> 45747 | H4: ='Sales plan& PnL'!M8 -> 45777 | I4: ='Sales plan& PnL'!N8 -> 45808 | J4: ='Sales plan& PnL'!O8 -> 45838 | K4: ='Sales plan& PnL'!P8 -> 45869 | L4: ='Sales plan& PnL'!Q8 -> 45900 | ... BL4: ='Sales plan& PnL'!BQ8 -> 47483
D5: Month on board | E5: =1 -> 1 | F5: =E5+1 -> 2 | G5: =F5+1 -> 3 | H5: =G5+1 -> 4 | I5: =H5+1 -> 5 | J5: =I5+1 -> 6 | K5: =J5+1 -> 7 | L5: =K5+1 -> 8 | M5: =L5+1 -> 9 | ... BL5: =BK5+1 -> 60
D6: Unit: mVND
D7: ENR | E7: {=SUMPRODUCT(E$63:E$122,TRANSPOSE(SAP_Spreadsheet!$G$603:$BN$603))} -> 0 | F7: {=SUMPRODUCT(F$63:F$122,TRANSPOSE(SAP_Spreadsheet!$G$603:$BN$603))} -> 0 | G7: {=SUMPRODUCT(G$63:G$122,TRANSPOSE(SAP_Spreadsheet!$G$603:$BN$603))} -> 0 | H7: {=SUMPRODUCT(H$63:H$122,TRANSPOSE(SAP_Spreadsheet!$G$603:$BN$603))} -> 0 | I7: {=SUMPRODUCT(I$63:I$122,TRANSPOSE(SAP_Spreadsheet!$G$603:$BN$603))} -> 0 | J7: {=SUMPRODUCT(J$63:J$122,TRANSPOSE(SAP_Spreadsheet!$G$603:$BN$603))} -> 0 | K7: {=SUMPRODUCT(K$63:K$122,TRANSPOSE(SAP_Spreadsheet!$G$603:$BN$603))} -> 0 | L7: {=SUMPRODUCT(L$63:L$122,TRANSPOSE(SAP_Spreadsheet!$G$603:$BN$603))} -> 0 | ... BL7: {=SUMPRODUCT(BL$63:BL$122,TRANSPOSE(SAP_Spreadsheet!$G$603:$BN$603))} -> 0
D8: ANR | E8: {=SUMPRODUCT(E$63:E$122,TRANSPOSE(SAP_Spreadsheet!$G$631:$BN$631))} -> 0 | F8: {=SUMPRODUCT(F$63:F$122,TRANSPOSE(SAP_Spreadsheet!$G$631:$BN$631))} -> 0 | G8: {=SUMPRODUCT(G$63:G$122,TRANSPOSE(SAP_Spreadsheet!$G$631:$BN$631))} -> 0 | H8: {=SUMPRODUCT(H$63:H$122,TRANSPOSE(SAP_Spreadsheet!$G$631:$BN$631))} -> 0 | I8: {=SUMPRODUCT(I$63:I$122,TRANSPOSE(SAP_Spreadsheet!$G$631:$BN$631))} -> 0 | J8: {=SUMPRODUCT(J$63:J$122,TRANSPOSE(SAP_Spreadsheet!$G$631:$BN$631))} -> 0 | K8: {=SUMPRODUCT(K$63:K$122,TRANSPOSE(SAP_Spreadsheet!$G$631:$BN$631))} -> 0 | L8: {=SUMPRODUCT(L$63:L$122,TRANSPOSE(SAP_Spreadsheet!$G$631:$BN$631))} -> 0 | ... BL8: {=SUMPRODUCT(BL$63:BL$122,TRANSPOSE(SAP_Spreadsheet!$G$631:$BN$631))} -> 0
D9: TOI | E9: {=SUMPRODUCT(E$63:E$122,TRANSPOSE(SAP_Spreadsheet!$G$677:$BN$677))} -> 0 | F9: {=SUMPRODUCT(F$63:F$122,TRANSPOSE(SAP_Spreadsheet!$G$677:$BN$677))} -> 0 | G9: {=SUMPRODUCT(G$63:G$122,TRANSPOSE(SAP_Spreadsheet!$G$677:$BN$677))} -> 0 | H9: {=SUMPRODUCT(H$63:H$122,TRANSPOSE(SAP_Spreadsheet!$G$677:$BN$677))} -> 0 | I9: {=SUMPRODUCT(I$63:I$122,TRANSPOSE(SAP_Spreadsheet!$G$677:$BN$677))} -> 0 | J9: {=SUMPRODUCT(J$63:J$122,TRANSPOSE(SAP_Spreadsheet!$G$677:$BN$677))} -> 0 | K9: {=SUMPRODUCT(K$63:K$122,TRANSPOSE(SAP_Spreadsheet!$G$677:$BN$677))} -> 0 | L9: {=SUMPRODUCT(L$63:L$122,TRANSPOSE(SAP_Spreadsheet!$G$677:$BN$677))} -> 0 | ... BL9: {=SUMPRODUCT(BL$63:BL$122,TRANSPOSE(SAP_Spreadsheet!$G$677:$BN$677))} -> 0
D10: Net interest income | E10: {=SUMPRODUCT(E$63:E$122,TRANSPOSE(SAP_Spreadsheet!$G$650:$BN$650))} -> 0 | F10: {=SUMPRODUCT(F$63:F$122,TRANSPOSE(SAP_Spreadsheet!$G$650:$BN$650))} -> 0 | G10: {=SUMPRODUCT(G$63:G$122,TRANSPOSE(SAP_Spreadsheet!$G$650:$BN$650))} -> 0 | H10: {=SUMPRODUCT(H$63:H$122,TRANSPOSE(SAP_Spreadsheet!$G$650:$BN$650))} -> 0 | I10: {=SUMPRODUCT(I$63:I$122,TRANSPOSE(SAP_Spreadsheet!$G$650:$BN$650))} -> 0 | J10: {=SUMPRODUCT(J$63:J$122,TRANSPOSE(SAP_Spreadsheet!$G$650:$BN$650))} -> 0 | K10: {=SUMPRODUCT(K$63:K$122,TRANSPOSE(SAP_Spreadsheet!$G$650:$BN$650))} -> 0 | L10: {=SUMPRODUCT(L$63:L$122,TRANSPOSE(SAP_Spreadsheet!$G$650:$BN$650))} -> 0 | ... BL10: {=SUMPRODUCT(BL$63:BL$122,TRANSPOSE(SAP_Spreadsheet!$G$650:$BN$650))} -> 0
D11: CII | E11: {=SUMPRODUCT(E$63:E$122,TRANSPOSE(SAP_Spreadsheet!$G$646:$BN$646))} -> 0 | F11: {=SUMPRODUCT(F$63:F$122,TRANSPOSE(SAP_Spreadsheet!$G$646:$BN$646))} -> 0 | G11: {=SUMPRODUCT(G$63:G$122,TRANSPOSE(SAP_Spreadsheet!$G$646:$BN$646))} -> 0 | H11: {=SUMPRODUCT(H$63:H$122,TRANSPOSE(SAP_Spreadsheet!$G$646:$BN$646))} -> 0 | I11: {=SUMPRODUCT(I$63:I$122,TRANSPOSE(SAP_Spreadsheet!$G$646:$BN$646))} -> 0 | J11: {=SUMPRODUCT(J$63:J$122,TRANSPOSE(SAP_Spreadsheet!$G$646:$BN$646))} -> 0 | K11: {=SUMPRODUCT(K$63:K$122,TRANSPOSE(SAP_Spreadsheet!$G$646:$BN$646))} -> 0 | L11: {=SUMPRODUCT(L$63:L$122,TRANSPOSE(SAP_Spreadsheet!$G$646:$BN$646))} -> 0 | ... BL11: {=SUMPRODUCT(BL$63:BL$122,TRANSPOSE(SAP_Spreadsheet!$G$646:$BN$646))} -> 0
D12: COF | E12: {=SUMPRODUCT(E$63:E$122,TRANSPOSE(SAP_Spreadsheet!$G$649:$BN$649))} -> 0 | F12: {=SUMPRODUCT(F$63:F$122,TRANSPOSE(SAP_Spreadsheet!$G$649:$BN$649))} -> 0 | G12: {=SUMPRODUCT(G$63:G$122,TRANSPOSE(SAP_Spreadsheet!$G$649:$BN$649))} -> 0 | H12: {=SUMPRODUCT(H$63:H$122,TRANSPOSE(SAP_Spreadsheet!$G$649:$BN$649))} -> 0 | I12: {=SUMPRODUCT(I$63:I$122,TRANSPOSE(SAP_Spreadsheet!$G$649:$BN$649))} -> 0 | J12: {=SUMPRODUCT(J$63:J$122,TRANSPOSE(SAP_Spreadsheet!$G$649:$BN$649))} -> 0 | K12: {=SUMPRODUCT(K$63:K$122,TRANSPOSE(SAP_Spreadsheet!$G$649:$BN$649))} -> 0 | L12: {=SUMPRODUCT(L$63:L$122,TRANSPOSE(SAP_Spreadsheet!$G$649:$BN$649))} -> 0 | ... BL12: {=SUMPRODUCT(BL$63:BL$122,TRANSPOSE(SAP_Spreadsheet!$G$649:$BN$649))} -> 0
D13: Net fee income | E13: {=SUMPRODUCT(E$63:E$122,TRANSPOSE(SAP_Spreadsheet!$G$673:$BN$673))} -> 0 | F13: {=SUMPRODUCT(F$63:F$122,TRANSPOSE(SAP_Spreadsheet!$G$673:$BN$673))} -> 0 | G13: {=SUMPRODUCT(G$63:G$122,TRANSPOSE(SAP_Spreadsheet!$G$673:$BN$673))} -> 0 | H13: {=SUMPRODUCT(H$63:H$122,TRANSPOSE(SAP_Spreadsheet!$G$673:$BN$673))} -> 0 | I13: {=SUMPRODUCT(I$63:I$122,TRANSPOSE(SAP_Spreadsheet!$G$673:$BN$673))} -> 0 | J13: {=SUMPRODUCT(J$63:J$122,TRANSPOSE(SAP_Spreadsheet!$G$673:$BN$673))} -> 0 | K13: {=SUMPRODUCT(K$63:K$122,TRANSPOSE(SAP_Spreadsheet!$G$673:$BN$673))} -> 0 | L13: {=SUMPRODUCT(L$63:L$122,TRANSPOSE(SAP_Spreadsheet!$G$673:$BN$673))} -> 0 | ... BL13: {=SUMPRODUCT(BL$63:BL$122,TRANSPOSE(SAP_Spreadsheet!$G$673:$BN$673))} -> 0
D14: Annual fee | E14: {=SUMPRODUCT(E$63:E$122,TRANSPOSE(SAP_Spreadsheet!$G$652:$BN$652))} -> 0 | F14: {=SUMPRODUCT(F$63:F$122,TRANSPOSE(SAP_Spreadsheet!$G$652:$BN$652))} -> 0 | G14: {=SUMPRODUCT(G$63:G$122,TRANSPOSE(SAP_Spreadsheet!$G$652:$BN$652))} -> 0 | H14: {=SUMPRODUCT(H$63:H$122,TRANSPOSE(SAP_Spreadsheet!$G$652:$BN$652))} -> 0 | I14: {=SUMPRODUCT(I$63:I$122,TRANSPOSE(SAP_Spreadsheet!$G$652:$BN$652))} -> 0 | J14: {=SUMPRODUCT(J$63:J$122,TRANSPOSE(SAP_Spreadsheet!$G$652:$BN$652))} -> 0 | K14: {=SUMPRODUCT(K$63:K$122,TRANSPOSE(SAP_Spreadsheet!$G$652:$BN$652))} -> 0 | L14: {=SUMPRODUCT(L$63:L$122,TRANSPOSE(SAP_Spreadsheet!$G$652:$BN$652))} -> 0 | ... BL14: {=SUMPRODUCT(BL$63:BL$122,TRANSPOSE(SAP_Spreadsheet!$G$652:$BN$652))} -> 0
D15: Monthly fee | E15: {=SUMPRODUCT(E$63:E$122,TRANSPOSE(SAP_Spreadsheet!$G$653:$BN$653))} -> 0 | F15: {=SUMPRODUCT(F$63:F$122,TRANSPOSE(SAP_Spreadsheet!$G$653:$BN$653))} -> 0 | G15: {=SUMPRODUCT(G$63:G$122,TRANSPOSE(SAP_Spreadsheet!$G$653:$BN$653))} -> 0 | H15: {=SUMPRODUCT(H$63:H$122,TRANSPOSE(SAP_Spreadsheet!$G$653:$BN$653))} -> 0 | I15: {=SUMPRODUCT(I$63:I$122,TRANSPOSE(SAP_Spreadsheet!$G$653:$BN$653))} -> 0 | J15: {=SUMPRODUCT(J$63:J$122,TRANSPOSE(SAP_Spreadsheet!$G$653:$BN$653))} -> 0 | K15: {=SUMPRODUCT(K$63:K$122,TRANSPOSE(SAP_Spreadsheet!$G$653:$BN$653))} -> 0 | L15: {=SUMPRODUCT(L$63:L$122,TRANSPOSE(SAP_Spreadsheet!$G$653:$BN$653))} -> 0 | ... BL15: {=SUMPRODUCT(BL$63:BL$122,TRANSPOSE(SAP_Spreadsheet!$G$653:$BN$653))} -> 0
D16: Transaction fee | E16: {=SUMPRODUCT(E$63:E$122,TRANSPOSE(SAP_Spreadsheet!$G$654:$BN$654))} -> 0 | F16: {=SUMPRODUCT(F$63:F$122,TRANSPOSE(SAP_Spreadsheet!$G$654:$BN$654))} -> 0 | G16: {=SUMPRODUCT(G$63:G$122,TRANSPOSE(SAP_Spreadsheet!$G$654:$BN$654))} -> 0 | H16: {=SUMPRODUCT(H$63:H$122,TRANSPOSE(SAP_Spreadsheet!$G$654:$BN$654))} -> 0 | I16: {=SUMPRODUCT(I$63:I$122,TRANSPOSE(SAP_Spreadsheet!$G$654:$BN$654))} -> 0 | J16: {=SUMPRODUCT(J$63:J$122,TRANSPOSE(SAP_Spreadsheet!$G$654:$BN$654))} -> 0 | K16: {=SUMPRODUCT(K$63:K$122,TRANSPOSE(SAP_Spreadsheet!$G$654:$BN$654))} -> 0 | L16: {=SUMPRODUCT(L$63:L$122,TRANSPOSE(SAP_Spreadsheet!$G$654:$BN$654))} -> 0 | ... BL16: {=SUMPRODUCT(BL$63:BL$122,TRANSPOSE(SAP_Spreadsheet!$G$654:$BN$654))} -> 0
D17: Issuance fee | E17: {=SUMPRODUCT(E$63:E$122,TRANSPOSE(SAP_Spreadsheet!$G$671:$BN$671))} -> 0 | F17: {=SUMPRODUCT(F$63:F$122,TRANSPOSE(SAP_Spreadsheet!$G$671:$BN$671))} -> 0 | G17: {=SUMPRODUCT(G$63:G$122,TRANSPOSE(SAP_Spreadsheet!$G$671:$BN$671))} -> 0 | H17: {=SUMPRODUCT(H$63:H$122,TRANSPOSE(SAP_Spreadsheet!$G$671:$BN$671))} -> 0 | I17: {=SUMPRODUCT(I$63:I$122,TRANSPOSE(SAP_Spreadsheet!$G$671:$BN$671))} -> 0 | J17: {=SUMPRODUCT(J$63:J$122,TRANSPOSE(SAP_Spreadsheet!$G$671:$BN$671))} -> 0 | K17: {=SUMPRODUCT(K$63:K$122,TRANSPOSE(SAP_Spreadsheet!$G$671:$BN$671))} -> 0 | L17: {=SUMPRODUCT(L$63:L$122,TRANSPOSE(SAP_Spreadsheet!$G$671:$BN$671))} -> 0 | ... BL17: {=SUMPRODUCT(BL$63:BL$122,TRANSPOSE(SAP_Spreadsheet!$G$671:$BN$671))} -> 0
D18: Subvention | E18: {=SUMPRODUCT(E$63:E$122,TRANSPOSE(SAP_Spreadsheet!$G$655:$BN$655))} -> 0 | F18: {=SUMPRODUCT(F$63:F$122,TRANSPOSE(SAP_Spreadsheet!$G$655:$BN$655))} -> 0 | G18: {=SUMPRODUCT(G$63:G$122,TRANSPOSE(SAP_Spreadsheet!$G$655:$BN$655))} -> 0 | H18: {=SUMPRODUCT(H$63:H$122,TRANSPOSE(SAP_Spreadsheet!$G$655:$BN$655))} -> 0 | I18: {=SUMPRODUCT(I$63:I$122,TRANSPOSE(SAP_Spreadsheet!$G$655:$BN$655))} -> 0 | J18: {=SUMPRODUCT(J$63:J$122,TRANSPOSE(SAP_Spreadsheet!$G$655:$BN$655))} -> 0 | K18: {=SUMPRODUCT(K$63:K$122,TRANSPOSE(SAP_Spreadsheet!$G$655:$BN$655))} -> 0 | L18: {=SUMPRODUCT(L$63:L$122,TRANSPOSE(SAP_Spreadsheet!$G$655:$BN$655))} -> 0 | ... BL18: {=SUMPRODUCT(BL$63:BL$122,TRANSPOSE(SAP_Spreadsheet!$G$655:$BN$655))} -> 0
D19: Late payment | E19: {=SUMPRODUCT(E$63:E$122,TRANSPOSE(SAP_Spreadsheet!$G$659:$BN$659))} -> 0 | F19: {=SUMPRODUCT(F$63:F$122,TRANSPOSE(SAP_Spreadsheet!$G$659:$BN$659))} -> 0 | G19: {=SUMPRODUCT(G$63:G$122,TRANSPOSE(SAP_Spreadsheet!$G$659:$BN$659))} -> 0 | H19: {=SUMPRODUCT(H$63:H$122,TRANSPOSE(SAP_Spreadsheet!$G$659:$BN$659))} -> 0 | I19: {=SUMPRODUCT(I$63:I$122,TRANSPOSE(SAP_Spreadsheet!$G$659:$BN$659))} -> 0 | J19: {=SUMPRODUCT(J$63:J$122,TRANSPOSE(SAP_Spreadsheet!$G$659:$BN$659))} -> 0 | K19: {=SUMPRODUCT(K$63:K$122,TRANSPOSE(SAP_Spreadsheet!$G$659:$BN$659))} -> 0 | L19: {=SUMPRODUCT(L$63:L$122,TRANSPOSE(SAP_Spreadsheet!$G$659:$BN$659))} -> 0 | ... BL19: {=SUMPRODUCT(BL$63:BL$122,TRANSPOSE(SAP_Spreadsheet!$G$659:$BN$659))} -> 0
D20: Min due fee | E20: {=SUMPRODUCT(E$63:E$122,TRANSPOSE(SAP_Spreadsheet!$G$662:$BN$662))} -> 0 | F20: {=SUMPRODUCT(F$63:F$122,TRANSPOSE(SAP_Spreadsheet!$G$662:$BN$662))} -> 0 | G20: {=SUMPRODUCT(G$63:G$122,TRANSPOSE(SAP_Spreadsheet!$G$662:$BN$662))} -> 0 | H20: {=SUMPRODUCT(H$63:H$122,TRANSPOSE(SAP_Spreadsheet!$G$662:$BN$662))} -> 0 | I20: {=SUMPRODUCT(I$63:I$122,TRANSPOSE(SAP_Spreadsheet!$G$662:$BN$662))} -> 0 | J20: {=SUMPRODUCT(J$63:J$122,TRANSPOSE(SAP_Spreadsheet!$G$662:$BN$662))} -> 0 | K20: {=SUMPRODUCT(K$63:K$122,TRANSPOSE(SAP_Spreadsheet!$G$662:$BN$662))} -> 0 | L20: {=SUMPRODUCT(L$63:L$122,TRANSPOSE(SAP_Spreadsheet!$G$662:$BN$662))} -> 0 | ... BL20: {=SUMPRODUCT(BL$63:BL$122,TRANSPOSE(SAP_Spreadsheet!$G$662:$BN$662))} -> 0
D21: EMI fee | E21: {=SUMPRODUCT(E$63:E$122,TRANSPOSE(SAP_Spreadsheet!$G$663:$BN$663))} -> 0 | F21: {=SUMPRODUCT(F$63:F$122,TRANSPOSE(SAP_Spreadsheet!$G$663:$BN$663))} -> 0 | G21: {=SUMPRODUCT(G$63:G$122,TRANSPOSE(SAP_Spreadsheet!$G$663:$BN$663))} -> 0 | H21: {=SUMPRODUCT(H$63:H$122,TRANSPOSE(SAP_Spreadsheet!$G$663:$BN$663))} -> 0 | I21: {=SUMPRODUCT(I$63:I$122,TRANSPOSE(SAP_Spreadsheet!$G$663:$BN$663))} -> 0 | J21: {=SUMPRODUCT(J$63:J$122,TRANSPOSE(SAP_Spreadsheet!$G$663:$BN$663))} -> 0 | K21: {=SUMPRODUCT(K$63:K$122,TRANSPOSE(SAP_Spreadsheet!$G$663:$BN$663))} -> 0 | L21: {=SUMPRODUCT(L$63:L$122,TRANSPOSE(SAP_Spreadsheet!$G$663:$BN$663))} -> 0 | ... BL21: {=SUMPRODUCT(BL$63:BL$122,TRANSPOSE(SAP_Spreadsheet!$G$663:$BN$663))} -> 0
D22: EMI- Early termination fee | E22: {=SUMPRODUCT(E$63:E$122,TRANSPOSE(SAP_Spreadsheet!$G$667:$BN$667))} -> 0 | F22: {=SUMPRODUCT(F$63:F$122,TRANSPOSE(SAP_Spreadsheet!$G$667:$BN$667))} -> 0 | G22: {=SUMPRODUCT(G$63:G$122,TRANSPOSE(SAP_Spreadsheet!$G$667:$BN$667))} -> 0 | H22: {=SUMPRODUCT(H$63:H$122,TRANSPOSE(SAP_Spreadsheet!$G$667:$BN$667))} -> 0 | I22: {=SUMPRODUCT(I$63:I$122,TRANSPOSE(SAP_Spreadsheet!$G$667:$BN$667))} -> 0 | J22: {=SUMPRODUCT(J$63:J$122,TRANSPOSE(SAP_Spreadsheet!$G$667:$BN$667))} -> 0 | K22: {=SUMPRODUCT(K$63:K$122,TRANSPOSE(SAP_Spreadsheet!$G$667:$BN$667))} -> 0 | L22: {=SUMPRODUCT(L$63:L$122,TRANSPOSE(SAP_Spreadsheet!$G$667:$BN$667))} -> 0 | ... BL22: {=SUMPRODUCT(BL$63:BL$122,TRANSPOSE(SAP_Spreadsheet!$G$667:$BN$667))} -> 0
D23: Fee suspended due to CIC | E23: {=SUMPRODUCT(E$63:E$122,TRANSPOSE(SAP_Spreadsheet!$G$672:$BN$672))} -> 0 | F23: {=SUMPRODUCT(F$63:F$122,TRANSPOSE(SAP_Spreadsheet!$G$672:$BN$672))} -> 0 | G23: {=SUMPRODUCT(G$63:G$122,TRANSPOSE(SAP_Spreadsheet!$G$672:$BN$672))} -> 0 | H23: {=SUMPRODUCT(H$63:H$122,TRANSPOSE(SAP_Spreadsheet!$G$672:$BN$672))} -> 0 | I23: {=SUMPRODUCT(I$63:I$122,TRANSPOSE(SAP_Spreadsheet!$G$672:$BN$672))} -> 0 | J23: {=SUMPRODUCT(J$63:J$122,TRANSPOSE(SAP_Spreadsheet!$G$672:$BN$672))} -> 0 | K23: {=SUMPRODUCT(K$63:K$122,TRANSPOSE(SAP_Spreadsheet!$G$672:$BN$672))} -> 0 | L23: {=SUMPRODUCT(L$63:L$122,TRANSPOSE(SAP_Spreadsheet!$G$672:$BN$672))} -> 0 | ... BL23: {=SUMPRODUCT(BL$63:BL$122,TRANSPOSE(SAP_Spreadsheet!$G$672:$BN$672))} -> 0
D24: Other Income | E24: {=SUMPRODUCT(E$63:E$122,TRANSPOSE(SAP_Spreadsheet!$G$675:$BN$675))} -> 0 | F24: {=SUMPRODUCT(F$63:F$122,TRANSPOSE(SAP_Spreadsheet!$G$675:$BN$675))} -> 0 | G24: {=SUMPRODUCT(G$63:G$122,TRANSPOSE(SAP_Spreadsheet!$G$675:$BN$675))} -> 0 | H24: {=SUMPRODUCT(H$63:H$122,TRANSPOSE(SAP_Spreadsheet!$G$675:$BN$675))} -> 0 | I24: {=SUMPRODUCT(I$63:I$122,TRANSPOSE(SAP_Spreadsheet!$G$675:$BN$675))} -> 0 | J24: {=SUMPRODUCT(J$63:J$122,TRANSPOSE(SAP_Spreadsheet!$G$675:$BN$675))} -> 0 | K24: {=SUMPRODUCT(K$63:K$122,TRANSPOSE(SAP_Spreadsheet!$G$675:$BN$675))} -> 0 | L24: {=SUMPRODUCT(L$63:L$122,TRANSPOSE(SAP_Spreadsheet!$G$675:$BN$675))} -> 0 | ... BL24: {=SUMPRODUCT(BL$63:BL$122,TRANSPOSE(SAP_Spreadsheet!$G$675:$BN$675))} -> 0
D25: PROVISION | E25: {=SUMPRODUCT(E$63:E$122,TRANSPOSE(SAP_Spreadsheet!$G$775:$BN$775))} -> 0 | F25: {=SUMPRODUCT(F$63:F$122,TRANSPOSE(SAP_Spreadsheet!$G$775:$BN$775))} -> 0 | G25: {=SUMPRODUCT(G$63:G$122,TRANSPOSE(SAP_Spreadsheet!$G$775:$BN$775))} -> 0 | H25: {=SUMPRODUCT(H$63:H$122,TRANSPOSE(SAP_Spreadsheet!$G$775:$BN$775))} -> 0 | I25: {=SUMPRODUCT(I$63:I$122,TRANSPOSE(SAP_Spreadsheet!$G$775:$BN$775))} -> 0 | J25: {=SUMPRODUCT(J$63:J$122,TRANSPOSE(SAP_Spreadsheet!$G$775:$BN$775))} -> 0 | K25: {=SUMPRODUCT(K$63:K$122,TRANSPOSE(SAP_Spreadsheet!$G$775:$BN$775))} -> 0 | L25: {=SUMPRODUCT(L$63:L$122,TRANSPOSE(SAP_Spreadsheet!$G$775:$BN$775))} -> 0 | ... BL25: {=SUMPRODUCT(BL$63:BL$122,TRANSPOSE(SAP_Spreadsheet!$G$775:$BN$775))} -> 0
D26: OPEX | E26: {=SUMPRODUCT(E$63:E$122,TRANSPOSE(SAP_Spreadsheet!$G$715:$BN$715))} -> 0 | F26: {=SUMPRODUCT(F$63:F$122,TRANSPOSE(SAP_Spreadsheet!$G$715:$BN$715))} -> 0 | G26: {=SUMPRODUCT(G$63:G$122,TRANSPOSE(SAP_Spreadsheet!$G$715:$BN$715))} -> 0 | H26: {=SUMPRODUCT(H$63:H$122,TRANSPOSE(SAP_Spreadsheet!$G$715:$BN$715))} -> 0 | I26: {=SUMPRODUCT(I$63:I$122,TRANSPOSE(SAP_Spreadsheet!$G$715:$BN$715))} -> 0 | J26: {=SUMPRODUCT(J$63:J$122,TRANSPOSE(SAP_Spreadsheet!$G$715:$BN$715))} -> 0 | K26: {=SUMPRODUCT(K$63:K$122,TRANSPOSE(SAP_Spreadsheet!$G$715:$BN$715))} -> 0 | L26: {=SUMPRODUCT(L$63:L$122,TRANSPOSE(SAP_Spreadsheet!$G$715:$BN$715))} -> 0 | ... BL26: {=SUMPRODUCT(BL$63:BL$122,TRANSPOSE(SAP_Spreadsheet!$G$715:$BN$715))} -> 0
D27: Sales team & mgt | E27: {=SUMPRODUCT(E$63:E$122,TRANSPOSE(SAP_Spreadsheet!$G$690:$BN$690))} -> 0 | F27: {=SUMPRODUCT(F$63:F$122,TRANSPOSE(SAP_Spreadsheet!$G$690:$BN$690))} -> 0 | G27: {=SUMPRODUCT(G$63:G$122,TRANSPOSE(SAP_Spreadsheet!$G$690:$BN$690))} -> 0 | H27: {=SUMPRODUCT(H$63:H$122,TRANSPOSE(SAP_Spreadsheet!$G$690:$BN$690))} -> 0 | I27: {=SUMPRODUCT(I$63:I$122,TRANSPOSE(SAP_Spreadsheet!$G$690:$BN$690))} -> 0 | J27: {=SUMPRODUCT(J$63:J$122,TRANSPOSE(SAP_Spreadsheet!$G$690:$BN$690))} -> 0 | K27: {=SUMPRODUCT(K$63:K$122,TRANSPOSE(SAP_Spreadsheet!$G$690:$BN$690))} -> 0 | L27: {=SUMPRODUCT(L$63:L$122,TRANSPOSE(SAP_Spreadsheet!$G$690:$BN$690))} -> 0 | ... BL27: {=SUMPRODUCT(BL$63:BL$122,TRANSPOSE(SAP_Spreadsheet!$G$690:$BN$690))} -> 0
D28: Partner acquisition | E28: {=SUMPRODUCT(E$63:E$122,TRANSPOSE(SAP_Spreadsheet!$G$681:$BN$681))} -> 0 | F28: {=SUMPRODUCT(F$63:F$122,TRANSPOSE(SAP_Spreadsheet!$G$681:$BN$681))} -> 0 | G28: {=SUMPRODUCT(G$63:G$122,TRANSPOSE(SAP_Spreadsheet!$G$681:$BN$681))} -> 0 | H28: {=SUMPRODUCT(H$63:H$122,TRANSPOSE(SAP_Spreadsheet!$G$681:$BN$681))} -> 0 | I28: {=SUMPRODUCT(I$63:I$122,TRANSPOSE(SAP_Spreadsheet!$G$681:$BN$681))} -> 0 | J28: {=SUMPRODUCT(J$63:J$122,TRANSPOSE(SAP_Spreadsheet!$G$681:$BN$681))} -> 0 | K28: {=SUMPRODUCT(K$63:K$122,TRANSPOSE(SAP_Spreadsheet!$G$681:$BN$681))} -> 0 | L28: {=SUMPRODUCT(L$63:L$122,TRANSPOSE(SAP_Spreadsheet!$G$681:$BN$681))} -> 0 | ... BL28: {=SUMPRODUCT(BL$63:BL$122,TRANSPOSE(SAP_Spreadsheet!$G$681:$BN$681))} -> 0
D29: Leadgen | E29: {=SUMPRODUCT(E$63:E$122,TRANSPOSE(SAP_Spreadsheet!$G$682:$BN$682))} -> 0 | F29: {=SUMPRODUCT(F$63:F$122,TRANSPOSE(SAP_Spreadsheet!$G$682:$BN$682))} -> 0 | G29: {=SUMPRODUCT(G$63:G$122,TRANSPOSE(SAP_Spreadsheet!$G$682:$BN$682))} -> 0 | H29: {=SUMPRODUCT(H$63:H$122,TRANSPOSE(SAP_Spreadsheet!$G$682:$BN$682))} -> 0 | I29: {=SUMPRODUCT(I$63:I$122,TRANSPOSE(SAP_Spreadsheet!$G$682:$BN$682))} -> 0 | J29: {=SUMPRODUCT(J$63:J$122,TRANSPOSE(SAP_Spreadsheet!$G$682:$BN$682))} -> 0 | K29: {=SUMPRODUCT(K$63:K$122,TRANSPOSE(SAP_Spreadsheet!$G$682:$BN$682))} -> 0 | L29: {=SUMPRODUCT(L$63:L$122,TRANSPOSE(SAP_Spreadsheet!$G$682:$BN$682))} -> 0 | ... BL29: {=SUMPRODUCT(BL$63:BL$122,TRANSPOSE(SAP_Spreadsheet!$G$682:$BN$682))} -> 0
D30: Sharing performance | E30: {=SUMPRODUCT(E$63:E$122,TRANSPOSE(SAP_Spreadsheet!$G$683:$BN$683))} -> 0 | F30: {=SUMPRODUCT(F$63:F$122,TRANSPOSE(SAP_Spreadsheet!$G$683:$BN$683))} -> 0 | G30: {=SUMPRODUCT(G$63:G$122,TRANSPOSE(SAP_Spreadsheet!$G$683:$BN$683))} -> 0 | H30: {=SUMPRODUCT(H$63:H$122,TRANSPOSE(SAP_Spreadsheet!$G$683:$BN$683))} -> 0 | I30: {=SUMPRODUCT(I$63:I$122,TRANSPOSE(SAP_Spreadsheet!$G$683:$BN$683))} -> 0 | J30: {=SUMPRODUCT(J$63:J$122,TRANSPOSE(SAP_Spreadsheet!$G$683:$BN$683))} -> 0 | K30: {=SUMPRODUCT(K$63:K$122,TRANSPOSE(SAP_Spreadsheet!$G$683:$BN$683))} -> 0 | L30: {=SUMPRODUCT(L$63:L$122,TRANSPOSE(SAP_Spreadsheet!$G$683:$BN$683))} -> 0 | ... BL30: {=SUMPRODUCT(BL$63:BL$122,TRANSPOSE(SAP_Spreadsheet!$G$683:$BN$683))} -> 0
D31: Marketing acquisition | E31: {=SUMPRODUCT(E$63:E$122,TRANSPOSE(SAP_Spreadsheet!$G$689:$BN$689))} -> 0 | F31: {=SUMPRODUCT(F$63:F$122,TRANSPOSE(SAP_Spreadsheet!$G$689:$BN$689))} -> 0 | G31: {=SUMPRODUCT(G$63:G$122,TRANSPOSE(SAP_Spreadsheet!$G$689:$BN$689))} -> 0 | H31: {=SUMPRODUCT(H$63:H$122,TRANSPOSE(SAP_Spreadsheet!$G$689:$BN$689))} -> 0 | I31: {=SUMPRODUCT(I$63:I$122,TRANSPOSE(SAP_Spreadsheet!$G$689:$BN$689))} -> 0 | J31: {=SUMPRODUCT(J$63:J$122,TRANSPOSE(SAP_Spreadsheet!$G$689:$BN$689))} -> 0 | K31: {=SUMPRODUCT(K$63:K$122,TRANSPOSE(SAP_Spreadsheet!$G$689:$BN$689))} -> 0 | L31: {=SUMPRODUCT(L$63:L$122,TRANSPOSE(SAP_Spreadsheet!$G$689:$BN$689))} -> 0 | ... BL31: {=SUMPRODUCT(BL$63:BL$122,TRANSPOSE(SAP_Spreadsheet!$G$689:$BN$689))} -> 0
D32: Marketing cost for promotion | E32: {=SUMPRODUCT(E$63:E$122,TRANSPOSE(SAP_Spreadsheet!$G$692:$BN$692))} -> 0 | F32: {=SUMPRODUCT(F$63:F$122,TRANSPOSE(SAP_Spreadsheet!$G$692:$BN$692))} -> 0 | G32: {=SUMPRODUCT(G$63:G$122,TRANSPOSE(SAP_Spreadsheet!$G$692:$BN$692))} -> 0 | H32: {=SUMPRODUCT(H$63:H$122,TRANSPOSE(SAP_Spreadsheet!$G$692:$BN$692))} -> 0 | I32: {=SUMPRODUCT(I$63:I$122,TRANSPOSE(SAP_Spreadsheet!$G$692:$BN$692))} -> 0 | J32: {=SUMPRODUCT(J$63:J$122,TRANSPOSE(SAP_Spreadsheet!$G$692:$BN$692))} -> 0 | K32: {=SUMPRODUCT(K$63:K$122,TRANSPOSE(SAP_Spreadsheet!$G$692:$BN$692))} -> 0 | L32: {=SUMPRODUCT(L$63:L$122,TRANSPOSE(SAP_Spreadsheet!$G$692:$BN$692))} -> 0 | ... BL32: {=SUMPRODUCT(BL$63:BL$122,TRANSPOSE(SAP_Spreadsheet!$G$692:$BN$692))} -> 0
D33: UW & Disbursal | E33: {=SUMPRODUCT(E$63:E$122,TRANSPOSE(SAP_Spreadsheet!$G$696:$BN$696))} -> 0 | F33: {=SUMPRODUCT(F$63:F$122,TRANSPOSE(SAP_Spreadsheet!$G$696:$BN$696))} -> 0 | G33: {=SUMPRODUCT(G$63:G$122,TRANSPOSE(SAP_Spreadsheet!$G$696:$BN$696))} -> 0 | H33: {=SUMPRODUCT(H$63:H$122,TRANSPOSE(SAP_Spreadsheet!$G$696:$BN$696))} -> 0 | I33: {=SUMPRODUCT(I$63:I$122,TRANSPOSE(SAP_Spreadsheet!$G$696:$BN$696))} -> 0 | J33: {=SUMPRODUCT(J$63:J$122,TRANSPOSE(SAP_Spreadsheet!$G$696:$BN$696))} -> 0 | K33: {=SUMPRODUCT(K$63:K$122,TRANSPOSE(SAP_Spreadsheet!$G$696:$BN$696))} -> 0 | L33: {=SUMPRODUCT(L$63:L$122,TRANSPOSE(SAP_Spreadsheet!$G$696:$BN$696))} -> 0 | ... BL33: {=SUMPRODUCT(BL$63:BL$122,TRANSPOSE(SAP_Spreadsheet!$G$696:$BN$696))} -> 0
D34: Collection | E34: =E35+E36 -> 0 | F34: =F35+F36 -> 0 | G34: =G35+G36 -> 0 | H34: =H35+H36 -> 0 | I34: =I35+I36 -> 0 | J34: =J35+J36 -> 0 | K34: =K35+K36 -> 0 | L34: =L35+L36 -> 0 | ... BL34: =BL35+BL36 -> 0
D35: Early collections | E35: {=SUMPRODUCT(E$63:E$122,TRANSPOSE(SAP_Spreadsheet!$G$705:$BN$705))} -> 0 | F35: {=SUMPRODUCT(F$63:F$122,TRANSPOSE(SAP_Spreadsheet!$G$705:$BN$705))} -> 0 | G35: {=SUMPRODUCT(G$63:G$122,TRANSPOSE(SAP_Spreadsheet!$G$705:$BN$705))} -> 0 | H35: {=SUMPRODUCT(H$63:H$122,TRANSPOSE(SAP_Spreadsheet!$G$705:$BN$705))} -> 0 | I35: {=SUMPRODUCT(I$63:I$122,TRANSPOSE(SAP_Spreadsheet!$G$705:$BN$705))} -> 0 | J35: {=SUMPRODUCT(J$63:J$122,TRANSPOSE(SAP_Spreadsheet!$G$705:$BN$705))} -> 0 | K35: {=SUMPRODUCT(K$63:K$122,TRANSPOSE(SAP_Spreadsheet!$G$705:$BN$705))} -> 0 | L35: {=SUMPRODUCT(L$63:L$122,TRANSPOSE(SAP_Spreadsheet!$G$705:$BN$705))} -> 0 | ... BL35: {=SUMPRODUCT(BL$63:BL$122,TRANSPOSE(SAP_Spreadsheet!$G$705:$BN$705))} -> 0
D36: AMC | E36: {=SUMPRODUCT(E$63:E$122,TRANSPOSE(SAP_Spreadsheet!$G$706:$BN$706))} -> 0 | F36: {=SUMPRODUCT(F$63:F$122,TRANSPOSE(SAP_Spreadsheet!$G$706:$BN$706))} -> 0 | G36: {=SUMPRODUCT(G$63:G$122,TRANSPOSE(SAP_Spreadsheet!$G$706:$BN$706))} -> 0 | H36: {=SUMPRODUCT(H$63:H$122,TRANSPOSE(SAP_Spreadsheet!$G$706:$BN$706))} -> 0 | I36: {=SUMPRODUCT(I$63:I$122,TRANSPOSE(SAP_Spreadsheet!$G$706:$BN$706))} -> 0 | J36: {=SUMPRODUCT(J$63:J$122,TRANSPOSE(SAP_Spreadsheet!$G$706:$BN$706))} -> 0 | K36: {=SUMPRODUCT(K$63:K$122,TRANSPOSE(SAP_Spreadsheet!$G$706:$BN$706))} -> 0 | L36: {=SUMPRODUCT(L$63:L$122,TRANSPOSE(SAP_Spreadsheet!$G$706:$BN$706))} -> 0 | ... BL36: {=SUMPRODUCT(BL$63:BL$122,TRANSPOSE(SAP_Spreadsheet!$G$706:$BN$706))} -> 0
D37: After-sales services | E37: {=SUMPRODUCT(E$63:E$122,TRANSPOSE(SAP_Spreadsheet!$G$703:$BN$703))} -> 0 | F37: {=SUMPRODUCT(F$63:F$122,TRANSPOSE(SAP_Spreadsheet!$G$703:$BN$703))} -> 0 | G37: {=SUMPRODUCT(G$63:G$122,TRANSPOSE(SAP_Spreadsheet!$G$703:$BN$703))} -> 0 | H37: {=SUMPRODUCT(H$63:H$122,TRANSPOSE(SAP_Spreadsheet!$G$703:$BN$703))} -> 0 | I37: {=SUMPRODUCT(I$63:I$122,TRANSPOSE(SAP_Spreadsheet!$G$703:$BN$703))} -> 0 | J37: {=SUMPRODUCT(J$63:J$122,TRANSPOSE(SAP_Spreadsheet!$G$703:$BN$703))} -> 0 | K37: {=SUMPRODUCT(K$63:K$122,TRANSPOSE(SAP_Spreadsheet!$G$703:$BN$703))} -> 0 | L37: {=SUMPRODUCT(L$63:L$122,TRANSPOSE(SAP_Spreadsheet!$G$703:$BN$703))} -> 0 | ... BL37: {=SUMPRODUCT(BL$63:BL$122,TRANSPOSE(SAP_Spreadsheet!$G$703:$BN$703))} -> 0
D38: Other support units | E38: {=SUMPRODUCT(E$63:E$122,TRANSPOSE(SAP_Spreadsheet!$G$713:$BN$713))} -> 0 | F38: {=SUMPRODUCT(F$63:F$122,TRANSPOSE(SAP_Spreadsheet!$G$713:$BN$713))} -> 0 | G38: {=SUMPRODUCT(G$63:G$122,TRANSPOSE(SAP_Spreadsheet!$G$713:$BN$713))} -> 0 | H38: {=SUMPRODUCT(H$63:H$122,TRANSPOSE(SAP_Spreadsheet!$G$713:$BN$713))} -> 0 | I38: {=SUMPRODUCT(I$63:I$122,TRANSPOSE(SAP_Spreadsheet!$G$713:$BN$713))} -> 0 | J38: {=SUMPRODUCT(J$63:J$122,TRANSPOSE(SAP_Spreadsheet!$G$713:$BN$713))} -> 0 | K38: {=SUMPRODUCT(K$63:K$122,TRANSPOSE(SAP_Spreadsheet!$G$713:$BN$713))} -> 0 | L38: {=SUMPRODUCT(L$63:L$122,TRANSPOSE(SAP_Spreadsheet!$G$713:$BN$713))} -> 0 | ... BL38: {=SUMPRODUCT(BL$63:BL$122,TRANSPOSE(SAP_Spreadsheet!$G$713:$BN$713))} -> 0
D39: PBT | E39: =E9+E26+E25 -> 0 | F39: =F9+F26+F25 -> 0 | G39: =G9+G26+G25 -> 0 | H39: =H9+H26+H25 -> 0 | I39: =I9+I26+I25 -> 0 | J39: =J9+J26+J25 -> 0 | K39: =K9+K26+K25 -> 0 | L39: =L9+L26+L25 -> 0 | ... BL39: =BL9+BL26+BL25 -> 0
D41: Checking | E41: =E9+E26+E25-E39 -> 0 | F41: =F9+F26+F25-F39 -> 0 | G41: =G9+G26+G25-G39 -> 0 | H41: =H9+H26+H25-H39 -> 0 | I41: =I9+I26+I25-I39 -> 0 | J41: =J9+J26+J25-J39 -> 0 | K41: =K9+K26+K25-K39 -> 0 | L41: =L9+L26+L25-L39 -> 0 | ... BL41: =BL9+BL26+BL25-BL39 -> 0
D42: EOP BY BUCKET
D43: B0 | E43: {=SUMPRODUCT(E$63:E$122,TRANSPOSE(SAP_Spreadsheet!$G$610:$BN$610))} -> 0 | F43: {=SUMPRODUCT(F$63:F$122,TRANSPOSE(SAP_Spreadsheet!$G$610:$BN$610))} -> 0 | G43: {=SUMPRODUCT(G$63:G$122,TRANSPOSE(SAP_Spreadsheet!$G$610:$BN$610))} -> 0 | H43: {=SUMPRODUCT(H$63:H$122,TRANSPOSE(SAP_Spreadsheet!$G$610:$BN$610))} -> 0 | I43: {=SUMPRODUCT(I$63:I$122,TRANSPOSE(SAP_Spreadsheet!$G$610:$BN$610))} -> 0 | J43: {=SUMPRODUCT(J$63:J$122,TRANSPOSE(SAP_Spreadsheet!$G$610:$BN$610))} -> 0 | K43: {=SUMPRODUCT(K$63:K$122,TRANSPOSE(SAP_Spreadsheet!$G$610:$BN$610))} -> 0 | L43: {=SUMPRODUCT(L$63:L$122,TRANSPOSE(SAP_Spreadsheet!$G$610:$BN$610))} -> 0 | ... BL43: {=SUMPRODUCT(BL$63:BL$122,TRANSPOSE(SAP_Spreadsheet!$G$610:$BN$610))} -> 0
D44: B1 | E44: {=SUMPRODUCT(E$63:E$122,TRANSPOSE(SAP_Spreadsheet!$G$611:$BN$611))} -> 0 | F44: {=SUMPRODUCT(F$63:F$122,TRANSPOSE(SAP_Spreadsheet!$G$611:$BN$611))} -> 0 | G44: {=SUMPRODUCT(G$63:G$122,TRANSPOSE(SAP_Spreadsheet!$G$611:$BN$611))} -> 0 | H44: {=SUMPRODUCT(H$63:H$122,TRANSPOSE(SAP_Spreadsheet!$G$611:$BN$611))} -> 0 | I44: {=SUMPRODUCT(I$63:I$122,TRANSPOSE(SAP_Spreadsheet!$G$611:$BN$611))} -> 0 | J44: {=SUMPRODUCT(J$63:J$122,TRANSPOSE(SAP_Spreadsheet!$G$611:$BN$611))} -> 0 | K44: {=SUMPRODUCT(K$63:K$122,TRANSPOSE(SAP_Spreadsheet!$G$611:$BN$611))} -> 0 | L44: {=SUMPRODUCT(L$63:L$122,TRANSPOSE(SAP_Spreadsheet!$G$611:$BN$611))} -> 0 | ... BL44: {=SUMPRODUCT(BL$63:BL$122,TRANSPOSE(SAP_Spreadsheet!$G$611:$BN$611))} -> 0
D45: B2 | E45: {=SUMPRODUCT(E$63:E$122,TRANSPOSE(SAP_Spreadsheet!$G$612:$BN$612))} -> 0 | F45: {=SUMPRODUCT(F$63:F$122,TRANSPOSE(SAP_Spreadsheet!$G$612:$BN$612))} -> 0 | G45: {=SUMPRODUCT(G$63:G$122,TRANSPOSE(SAP_Spreadsheet!$G$612:$BN$612))} -> 0 | H45: {=SUMPRODUCT(H$63:H$122,TRANSPOSE(SAP_Spreadsheet!$G$612:$BN$612))} -> 0 | I45: {=SUMPRODUCT(I$63:I$122,TRANSPOSE(SAP_Spreadsheet!$G$612:$BN$612))} -> 0 | J45: {=SUMPRODUCT(J$63:J$122,TRANSPOSE(SAP_Spreadsheet!$G$612:$BN$612))} -> 0 | K45: {=SUMPRODUCT(K$63:K$122,TRANSPOSE(SAP_Spreadsheet!$G$612:$BN$612))} -> 0 | L45: {=SUMPRODUCT(L$63:L$122,TRANSPOSE(SAP_Spreadsheet!$G$612:$BN$612))} -> 0 | ... BL45: {=SUMPRODUCT(BL$63:BL$122,TRANSPOSE(SAP_Spreadsheet!$G$612:$BN$612))} -> 0
D46: B3 | E46: {=SUMPRODUCT(E$63:E$122,TRANSPOSE(SAP_Spreadsheet!$G$613:$BN$613))} -> 0 | F46: {=SUMPRODUCT(F$63:F$122,TRANSPOSE(SAP_Spreadsheet!$G$613:$BN$613))} -> 0 | G46: {=SUMPRODUCT(G$63:G$122,TRANSPOSE(SAP_Spreadsheet!$G$613:$BN$613))} -> 0 | H46: {=SUMPRODUCT(H$63:H$122,TRANSPOSE(SAP_Spreadsheet!$G$613:$BN$613))} -> 0 | I46: {=SUMPRODUCT(I$63:I$122,TRANSPOSE(SAP_Spreadsheet!$G$613:$BN$613))} -> 0 | J46: {=SUMPRODUCT(J$63:J$122,TRANSPOSE(SAP_Spreadsheet!$G$613:$BN$613))} -> 0 | K46: {=SUMPRODUCT(K$63:K$122,TRANSPOSE(SAP_Spreadsheet!$G$613:$BN$613))} -> 0 | L46: {=SUMPRODUCT(L$63:L$122,TRANSPOSE(SAP_Spreadsheet!$G$613:$BN$613))} -> 0 | ... BL46: {=SUMPRODUCT(BL$63:BL$122,TRANSPOSE(SAP_Spreadsheet!$G$613:$BN$613))} -> 0
D47: B4 | E47: {=SUMPRODUCT(E$63:E$122,TRANSPOSE(SAP_Spreadsheet!$G$614:$BN$614))} -> 0 | F47: {=SUMPRODUCT(F$63:F$122,TRANSPOSE(SAP_Spreadsheet!$G$614:$BN$614))} -> 0 | G47: {=SUMPRODUCT(G$63:G$122,TRANSPOSE(SAP_Spreadsheet!$G$614:$BN$614))} -> 0 | H47: {=SUMPRODUCT(H$63:H$122,TRANSPOSE(SAP_Spreadsheet!$G$614:$BN$614))} -> 0 | I47: {=SUMPRODUCT(I$63:I$122,TRANSPOSE(SAP_Spreadsheet!$G$614:$BN$614))} -> 0 | J47: {=SUMPRODUCT(J$63:J$122,TRANSPOSE(SAP_Spreadsheet!$G$614:$BN$614))} -> 0 | K47: {=SUMPRODUCT(K$63:K$122,TRANSPOSE(SAP_Spreadsheet!$G$614:$BN$614))} -> 0 | L47: {=SUMPRODUCT(L$63:L$122,TRANSPOSE(SAP_Spreadsheet!$G$614:$BN$614))} -> 0 | ... BL47: {=SUMPRODUCT(BL$63:BL$122,TRANSPOSE(SAP_Spreadsheet!$G$614:$BN$614))} -> 0
D48: B5 | E48: {=SUMPRODUCT(E$63:E$122,TRANSPOSE(SAP_Spreadsheet!$G$615:$BN$615))} -> 0 | F48: {=SUMPRODUCT(F$63:F$122,TRANSPOSE(SAP_Spreadsheet!$G$615:$BN$615))} -> 0 | G48: {=SUMPRODUCT(G$63:G$122,TRANSPOSE(SAP_Spreadsheet!$G$615:$BN$615))} -> 0 | H48: {=SUMPRODUCT(H$63:H$122,TRANSPOSE(SAP_Spreadsheet!$G$615:$BN$615))} -> 0 | I48: {=SUMPRODUCT(I$63:I$122,TRANSPOSE(SAP_Spreadsheet!$G$615:$BN$615))} -> 0 | J48: {=SUMPRODUCT(J$63:J$122,TRANSPOSE(SAP_Spreadsheet!$G$615:$BN$615))} -> 0 | K48: {=SUMPRODUCT(K$63:K$122,TRANSPOSE(SAP_Spreadsheet!$G$615:$BN$615))} -> 0 | L48: {=SUMPRODUCT(L$63:L$122,TRANSPOSE(SAP_Spreadsheet!$G$615:$BN$615))} -> 0 | ... BL48: {=SUMPRODUCT(BL$63:BL$122,TRANSPOSE(SAP_Spreadsheet!$G$615:$BN$615))} -> 0
D49: B6 | E49: {=SUMPRODUCT(E$63:E$122,TRANSPOSE(SAP_Spreadsheet!$G$616:$BN$616))} -> 0 | F49: {=SUMPRODUCT(F$63:F$122,TRANSPOSE(SAP_Spreadsheet!$G$616:$BN$616))} -> 0 | G49: {=SUMPRODUCT(G$63:G$122,TRANSPOSE(SAP_Spreadsheet!$G$616:$BN$616))} -> 0 | H49: {=SUMPRODUCT(H$63:H$122,TRANSPOSE(SAP_Spreadsheet!$G$616:$BN$616))} -> 0 | I49: {=SUMPRODUCT(I$63:I$122,TRANSPOSE(SAP_Spreadsheet!$G$616:$BN$616))} -> 0 | J49: {=SUMPRODUCT(J$63:J$122,TRANSPOSE(SAP_Spreadsheet!$G$616:$BN$616))} -> 0 | K49: {=SUMPRODUCT(K$63:K$122,TRANSPOSE(SAP_Spreadsheet!$G$616:$BN$616))} -> 0 | L49: {=SUMPRODUCT(L$63:L$122,TRANSPOSE(SAP_Spreadsheet!$G$616:$BN$616))} -> 0 | ... BL49: {=SUMPRODUCT(BL$63:BL$122,TRANSPOSE(SAP_Spreadsheet!$G$616:$BN$616))} -> 0
D50: B7 | E50: {=SUMPRODUCT(E$63:E$122,TRANSPOSE(SAP_Spreadsheet!$G$617:$BN$617))} -> 0 | F50: {=SUMPRODUCT(F$63:F$122,TRANSPOSE(SAP_Spreadsheet!$G$617:$BN$617))} -> 0 | G50: {=SUMPRODUCT(G$63:G$122,TRANSPOSE(SAP_Spreadsheet!$G$617:$BN$617))} -> 0 | H50: {=SUMPRODUCT(H$63:H$122,TRANSPOSE(SAP_Spreadsheet!$G$617:$BN$617))} -> 0 | I50: {=SUMPRODUCT(I$63:I$122,TRANSPOSE(SAP_Spreadsheet!$G$617:$BN$617))} -> 0 | J50: {=SUMPRODUCT(J$63:J$122,TRANSPOSE(SAP_Spreadsheet!$G$617:$BN$617))} -> 0 | K50: {=SUMPRODUCT(K$63:K$122,TRANSPOSE(SAP_Spreadsheet!$G$617:$BN$617))} -> 0 | L50: {=SUMPRODUCT(L$63:L$122,TRANSPOSE(SAP_Spreadsheet!$G$617:$BN$617))} -> 0 | ... BL50: {=SUMPRODUCT(BL$63:BL$122,TRANSPOSE(SAP_Spreadsheet!$G$617:$BN$617))} -> 0
D51: B8 | E51: {=SUMPRODUCT(E$63:E$122,TRANSPOSE(SAP_Spreadsheet!$G$618:$BN$618))} -> 0 | F51: {=SUMPRODUCT(F$63:F$122,TRANSPOSE(SAP_Spreadsheet!$G$618:$BN$618))} -> 0 | G51: {=SUMPRODUCT(G$63:G$122,TRANSPOSE(SAP_Spreadsheet!$G$618:$BN$618))} -> 0 | H51: {=SUMPRODUCT(H$63:H$122,TRANSPOSE(SAP_Spreadsheet!$G$618:$BN$618))} -> 0 | I51: {=SUMPRODUCT(I$63:I$122,TRANSPOSE(SAP_Spreadsheet!$G$618:$BN$618))} -> 0 | J51: {=SUMPRODUCT(J$63:J$122,TRANSPOSE(SAP_Spreadsheet!$G$618:$BN$618))} -> 0 | K51: {=SUMPRODUCT(K$63:K$122,TRANSPOSE(SAP_Spreadsheet!$G$618:$BN$618))} -> 0 | L51: {=SUMPRODUCT(L$63:L$122,TRANSPOSE(SAP_Spreadsheet!$G$618:$BN$618))} -> 0 | ... BL51: {=SUMPRODUCT(BL$63:BL$122,TRANSPOSE(SAP_Spreadsheet!$G$618:$BN$618))} -> 0
D52: B9 | E52: {=SUMPRODUCT(E$63:E$122,TRANSPOSE(SAP_Spreadsheet!$G$619:$BN$619))} -> 0 | F52: {=SUMPRODUCT(F$63:F$122,TRANSPOSE(SAP_Spreadsheet!$G$619:$BN$619))} -> 0 | G52: {=SUMPRODUCT(G$63:G$122,TRANSPOSE(SAP_Spreadsheet!$G$619:$BN$619))} -> 0 | H52: {=SUMPRODUCT(H$63:H$122,TRANSPOSE(SAP_Spreadsheet!$G$619:$BN$619))} -> 0 | I52: {=SUMPRODUCT(I$63:I$122,TRANSPOSE(SAP_Spreadsheet!$G$619:$BN$619))} -> 0 | J52: {=SUMPRODUCT(J$63:J$122,TRANSPOSE(SAP_Spreadsheet!$G$619:$BN$619))} -> 0 | K52: {=SUMPRODUCT(K$63:K$122,TRANSPOSE(SAP_Spreadsheet!$G$619:$BN$619))} -> 0 | L52: {=SUMPRODUCT(L$63:L$122,TRANSPOSE(SAP_Spreadsheet!$G$619:$BN$619))} -> 0 | ... BL52: {=SUMPRODUCT(BL$63:BL$122,TRANSPOSE(SAP_Spreadsheet!$G$619:$BN$619))} -> 0
D53: B10 | E53: {=SUMPRODUCT(E$63:E$122,TRANSPOSE(SAP_Spreadsheet!$G$620:$BN$620))} -> 0 | F53: {=SUMPRODUCT(F$63:F$122,TRANSPOSE(SAP_Spreadsheet!$G$620:$BN$620))} -> 0 | G53: {=SUMPRODUCT(G$63:G$122,TRANSPOSE(SAP_Spreadsheet!$G$620:$BN$620))} -> 0 | H53: {=SUMPRODUCT(H$63:H$122,TRANSPOSE(SAP_Spreadsheet!$G$620:$BN$620))} -> 0 | I53: {=SUMPRODUCT(I$63:I$122,TRANSPOSE(SAP_Spreadsheet!$G$620:$BN$620))} -> 0 | J53: {=SUMPRODUCT(J$63:J$122,TRANSPOSE(SAP_Spreadsheet!$G$620:$BN$620))} -> 0 | K53: {=SUMPRODUCT(K$63:K$122,TRANSPOSE(SAP_Spreadsheet!$G$620:$BN$620))} -> 0 | L53: {=SUMPRODUCT(L$63:L$122,TRANSPOSE(SAP_Spreadsheet!$G$620:$BN$620))} -> 0 | ... BL53: {=SUMPRODUCT(BL$63:BL$122,TRANSPOSE(SAP_Spreadsheet!$G$620:$BN$620))} -> 0
D54: B11 | E54: {=SUMPRODUCT(E$63:E$122,TRANSPOSE(SAP_Spreadsheet!$G$621:$BN$621))} -> 0 | F54: {=SUMPRODUCT(F$63:F$122,TRANSPOSE(SAP_Spreadsheet!$G$621:$BN$621))} -> 0 | G54: {=SUMPRODUCT(G$63:G$122,TRANSPOSE(SAP_Spreadsheet!$G$621:$BN$621))} -> 0 | H54: {=SUMPRODUCT(H$63:H$122,TRANSPOSE(SAP_Spreadsheet!$G$621:$BN$621))} -> 0 | I54: {=SUMPRODUCT(I$63:I$122,TRANSPOSE(SAP_Spreadsheet!$G$621:$BN$621))} -> 0 | J54: {=SUMPRODUCT(J$63:J$122,TRANSPOSE(SAP_Spreadsheet!$G$621:$BN$621))} -> 0 | K54: {=SUMPRODUCT(K$63:K$122,TRANSPOSE(SAP_Spreadsheet!$G$621:$BN$621))} -> 0 | L54: {=SUMPRODUCT(L$63:L$122,TRANSPOSE(SAP_Spreadsheet!$G$621:$BN$621))} -> 0 | ... BL54: {=SUMPRODUCT(BL$63:BL$122,TRANSPOSE(SAP_Spreadsheet!$G$621:$BN$621))} -> 0
D55: B12 | E55: {=SUMPRODUCT(E$63:E$122,TRANSPOSE(SAP_Spreadsheet!$G$622:$BN$622))} -> 0 | F55: {=SUMPRODUCT(F$63:F$122,TRANSPOSE(SAP_Spreadsheet!$G$622:$BN$622))} -> 0 | G55: {=SUMPRODUCT(G$63:G$122,TRANSPOSE(SAP_Spreadsheet!$G$622:$BN$622))} -> 0 | H55: {=SUMPRODUCT(H$63:H$122,TRANSPOSE(SAP_Spreadsheet!$G$622:$BN$622))} -> 0 | I55: {=SUMPRODUCT(I$63:I$122,TRANSPOSE(SAP_Spreadsheet!$G$622:$BN$622))} -> 0 | J55: {=SUMPRODUCT(J$63:J$122,TRANSPOSE(SAP_Spreadsheet!$G$622:$BN$622))} -> 0 | K55: {=SUMPRODUCT(K$63:K$122,TRANSPOSE(SAP_Spreadsheet!$G$622:$BN$622))} -> 0 | L55: {=SUMPRODUCT(L$63:L$122,TRANSPOSE(SAP_Spreadsheet!$G$622:$BN$622))} -> 0 | ... BL55: {=SUMPRODUCT(BL$63:BL$122,TRANSPOSE(SAP_Spreadsheet!$G$622:$BN$622))} -> 0
D57: Accumulated Card | E57: =SUMPRODUCT(E63:E122,$C$63:$C$122) -> 0 | F57: =SUMPRODUCT(F63:F122,$C$63:$C$122) -> 0 | G57: =SUMPRODUCT(G63:G122,$C$63:$C$122) -> 0 | H57: =SUMPRODUCT(H63:H122,$C$63:$C$122) -> 0 | I57: =SUMPRODUCT(I63:I122,$C$63:$C$122) -> 0 | J57: =SUMPRODUCT(J63:J122,$C$63:$C$122) -> 0 | K57: =SUMPRODUCT(K63:K122,$C$63:$C$122) -> 0 | L57: =SUMPRODUCT(L63:L122,$C$63:$C$122) -> 0 | ... BL57: =SUMPRODUCT(BL63:BL122,$C$63:$C$122) -> 0
D58: Activated card | E58: =SUMPRODUCT(E63:E122,$B$63:$B$122) -> 0 | F58: =SUMPRODUCT(F63:F122,$B$63:$B$122) -> 0 | G58: =SUMPRODUCT(G63:G122,$B$63:$B$122) -> 0 | H58: =SUMPRODUCT(H63:H122,$B$63:$B$122) -> 0 | I58: =SUMPRODUCT(I63:I122,$B$63:$B$122) -> 0 | J58: =SUMPRODUCT(J63:J122,$B$63:$B$122) -> 0 | K58: =SUMPRODUCT(K63:K122,$B$63:$B$122) -> 0 | L58: =SUMPRODUCT(L63:L122,$B$63:$B$122) -> 0 | ... BL58: =SUMPRODUCT(BL63:BL122,$B$63:$B$122) -> 0
D59: Total Usage | E59: =PnL_Speadsheet!E58*SAP_Spreadsheet!G15 -> 0 | F59: =PnL_Speadsheet!F58*SAP_Spreadsheet!H15 -> 0 | G59: =PnL_Speadsheet!G58*SAP_Spreadsheet!I15 -> 0 | H59: =PnL_Speadsheet!H58*SAP_Spreadsheet!J15 -> 0 | I59: =PnL_Speadsheet!I58*SAP_Spreadsheet!K15 -> 0 | J59: =PnL_Speadsheet!J58*SAP_Spreadsheet!L15 -> 0 | K59: =PnL_Speadsheet!K58*SAP_Spreadsheet!M15 -> 0 | L59: =PnL_Speadsheet!L58*SAP_Spreadsheet!N15 -> 0 | ... BL59: =PnL_Speadsheet!BL58*SAP_Spreadsheet!BN15 -> 0
B61: Term card | C61: =SAP_Leadsheet!E21 -> 60
B62: Activated card | C62: Iss @attrition | D62: No. of account | E62: =ROUND('Sales plan& PnL'!J10,0) -> 0 | F62: =ROUND('Sales plan& PnL'!K10,0) -> 0 | G62: =ROUND('Sales plan& PnL'!L10,0) -> 0 | H62: =ROUND('Sales plan& PnL'!M10,0) -> 0 | I62: =ROUND('Sales plan& PnL'!N10,0) -> 0 | J62: =ROUND('Sales plan& PnL'!O10,0) -> 0 | K62: =ROUND('Sales plan& PnL'!P10,0) -> 0 | L62: =ROUND('Sales plan& PnL'!Q10,0) -> 0 | ... BL62: =ROUND('Sales plan& PnL'!BQ10,0) -> 0
B63: =SUMIFS(SAP_Spreadsheet!$G$11:$BN$11,SAP_Spreadsheet!$G$7:$BN$7,PnL_Speadsheet!$D63) -> 0.6392418 | C63: =SUMIFS(SAP_Spreadsheet!$G$10:$BN$10,SAP_Spreadsheet!$G$7:$BN$7,PnL_Speadsheet!$D63) -> 1 | D63: 1 | E63: =IF($D63>$C$61,0,IF($D63>E$5,"",OFFSET(E$62,0,-($D63-1)))) -> 0 | F63: =IF($D63>$C$61,0,IF($D63>F$5,"",OFFSET(F$62,0,-($D63-1)))) -> 0 | G63: =IF($D63>$C$61,0,IF($D63>G$5,"",OFFSET(G$62,0,-($D63-1)))) -> 0 | H63: =IF($D63>$C$61,0,IF($D63>H$5,"",OFFSET(H$62,0,-($D63-1)))) -> 0 | I63: =IF($D63>$C$61,0,IF($D63>I$5,"",OFFSET(I$62,0,-($D63-1)))) -> 0 | J63: =IF($D63>$C$61,0,IF($D63>J$5,"",OFFSET(J$62,0,-($D63-1)))) -> 0 | K63: =IF($D63>$C$61,0,IF($D63>K$5,"",OFFSET(K$62,0,-($D63-1)))) -> 0 | L63: =IF($D63>$C$61,0,IF($D63>L$5,"",OFFSET(L$62,0,-($D63-1)))) -> 0 | ... BL63: =IF($D63>$C$61,0,IF($D63>BL$5,"",OFFSET(BL$62,0,-($D63-1)))) -> 0
B64: =SUMIFS(SAP_Spreadsheet!$G$11:$BN$11,SAP_Spreadsheet!$G$7:$BN$7,PnL_Speadsheet!$D64) -> 0.62821159 | C64: =SUMIFS(SAP_Spreadsheet!$G$10:$BN$10,SAP_Spreadsheet!$G$7:$BN$7,PnL_Speadsheet!$D64) -> 1 | D64: =D63+1 -> 2 | E64: =IF($D64>$C$61,0,IF($D64>E$5,"",OFFSET(E$62,0,-($D64-1)))) | F64: =IF($D64>$C$61,0,IF($D64>F$5,"",OFFSET(F$62,0,-($D64-1)))) -> 0 | G64: =IF($D64>$C$61,0,IF($D64>G$5,"",OFFSET(G$62,0,-($D64-1)))) -> 0 | H64: =IF($D64>$C$61,0,IF($D64>H$5,"",OFFSET(H$62,0,-($D64-1)))) -> 0 | I64: =IF($D64>$C$61,0,IF($D64>I$5,"",OFFSET(I$62,0,-($D64-1)))) -> 0 | J64: =IF($D64>$C$61,0,IF($D64>J$5,"",OFFSET(J$62,0,-($D64-1)))) -> 0 | K64: =IF($D64>$C$61,0,IF($D64>K$5,"",OFFSET(K$62,0,-($D64-1)))) -> 0 | L64: =IF($D64>$C$61,0,IF($D64>L$5,"",OFFSET(L$62,0,-($D64-1)))) -> 0 | ... BL64: =IF($D64>$C$61,0,IF($D64>BL$5,"",OFFSET(BL$62,0,-($D64-1)))) -> 0
B65: =SUMIFS(SAP_Spreadsheet!$G$11:$BN$11,SAP_Spreadsheet!$G$7:$BN$7,PnL_Speadsheet!$D65) -> 0.61718138 | C65: =SUMIFS(SAP_Spreadsheet!$G$10:$BN$10,SAP_Spreadsheet!$G$7:$BN$7,PnL_Speadsheet!$D65) -> 1 | D65: =D64+1 -> 3 | E65: =IF($D65>$C$61,0,IF($D65>E$5,"",OFFSET(E$62,0,-($D65-1)))) | F65: =IF($D65>$C$61,0,IF($D65>F$5,"",OFFSET(F$62,0,-($D65-1)))) | G65: =IF($D65>$C$61,0,IF($D65>G$5,"",OFFSET(G$62,0,-($D65-1)))) -> 0 | H65: =IF($D65>$C$61,0,IF($D65>H$5,"",OFFSET(H$62,0,-($D65-1)))) -> 0 | I65: =IF($D65>$C$61,0,IF($D65>I$5,"",OFFSET(I$62,0,-($D65-1)))) -> 0 | J65: =IF($D65>$C$61,0,IF($D65>J$5,"",OFFSET(J$62,0,-($D65-1)))) -> 0 | K65: =IF($D65>$C$61,0,IF($D65>K$5,"",OFFSET(K$62,0,-($D65-1)))) -> 0 | L65: =IF($D65>$C$61,0,IF($D65>L$5,"",OFFSET(L$62,0,-($D65-1)))) -> 0 | ... BL65: =IF($D65>$C$61,0,IF($D65>BL$5,"",OFFSET(BL$62,0,-($D65-1)))) -> 0
B66: =SUMIFS(SAP_Spreadsheet!$G$11:$BN$11,SAP_Spreadsheet!$G$7:$BN$7,PnL_Speadsheet!$D66) -> 0.60615117 | C66: =SUMIFS(SAP_Spreadsheet!$G$10:$BN$10,SAP_Spreadsheet!$G$7:$BN$7,PnL_Speadsheet!$D66) -> 1 | D66: =D65+1 -> 4 | E66: =IF($D66>$C$61,0,IF($D66>E$5,"",OFFSET(E$62,0,-($D66-1)))) | F66: =IF($D66>$C$61,0,IF($D66>F$5,"",OFFSET(F$62,0,-($D66-1)))) | G66: =IF($D66>$C$61,0,IF($D66>G$5,"",OFFSET(G$62,0,-($D66-1)))) | H66: =IF($D66>$C$61,0,IF($D66>H$5,"",OFFSET(H$62,0,-($D66-1)))) -> 0 | I66: =IF($D66>$C$61,0,IF($D66>I$5,"",OFFSET(I$62,0,-($D66-1)))) -> 0 | J66: =IF($D66>$C$61,0,IF($D66>J$5,"",OFFSET(J$62,0,-($D66-1)))) -> 0 | K66: =IF($D66>$C$61,0,IF($D66>K$5,"",OFFSET(K$62,0,-($D66-1)))) -> 0 | L66: =IF($D66>$C$61,0,IF($D66>L$5,"",OFFSET(L$62,0,-($D66-1)))) -> 0 | ... BL66: =IF($D66>$C$61,0,IF($D66>BL$5,"",OFFSET(BL$62,0,-($D66-1)))) -> 0
B67: =SUMIFS(SAP_Spreadsheet!$G$11:$BN$11,SAP_Spreadsheet!$G$7:$BN$7,PnL_Speadsheet!$D67) -> 0.59512097 | C67: =SUMIFS(SAP_Spreadsheet!$G$10:$BN$10,SAP_Spreadsheet!$G$7:$BN$7,PnL_Speadsheet!$D67) -> 1 | D67: =D66+1 -> 5 | E67: =IF($D67>$C$61,0,IF($D67>E$5,"",OFFSET(E$62,0,-($D67-1)))) | F67: =IF($D67>$C$61,0,IF($D67>F$5,"",OFFSET(F$62,0,-($D67-1)))) | G67: =IF($D67>$C$61,0,IF($D67>G$5,"",OFFSET(G$62,0,-($D67-1)))) | H67: =IF($D67>$C$61,0,IF($D67>H$5,"",OFFSET(H$62,0,-($D67-1)))) | I67: =IF($D67>$C$61,0,IF($D67>I$5,"",OFFSET(I$62,0,-($D67-1)))) -> 0 | J67: =IF($D67>$C$61,0,IF($D67>J$5,"",OFFSET(J$62,0,-($D67-1)))) -> 0 | K67: =IF($D67>$C$61,0,IF($D67>K$5,"",OFFSET(K$62,0,-($D67-1)))) -> 0 | L67: =IF($D67>$C$61,0,IF($D67>L$5,"",OFFSET(L$62,0,-($D67-1)))) -> 0 | ... BL67: =IF($D67>$C$61,0,IF($D67>BL$5,"",OFFSET(BL$62,0,-($D67-1)))) -> 0
B68: =SUMIFS(SAP_Spreadsheet!$G$11:$BN$11,SAP_Spreadsheet!$G$7:$BN$7,PnL_Speadsheet!$D68) -> 0.58409076 | C68: =SUMIFS(SAP_Spreadsheet!$G$10:$BN$10,SAP_Spreadsheet!$G$7:$BN$7,PnL_Speadsheet!$D68) -> 1 | D68: =D67+1 -> 6 | E68: =IF($D68>$C$61,0,IF($D68>E$5,"",OFFSET(E$62,0,-($D68-1)))) | F68: =IF($D68>$C$61,0,IF($D68>F$5,"",OFFSET(F$62,0,-($D68-1)))) | G68: =IF($D68>$C$61,0,IF($D68>G$5,"",OFFSET(G$62,0,-($D68-1)))) | H68: =IF($D68>$C$61,0,IF($D68>H$5,"",OFFSET(H$62,0,-($D68-1)))) | I68: =IF($D68>$C$61,0,IF($D68>I$5,"",OFFSET(I$62,0,-($D68-1)))) | J68: =IF($D68>$C$61,0,IF($D68>J$5,"",OFFSET(J$62,0,-($D68-1)))) -> 0 | K68: =IF($D68>$C$61,0,IF($D68>K$5,"",OFFSET(K$62,0,-($D68-1)))) -> 0 | L68: =IF($D68>$C$61,0,IF($D68>L$5,"",OFFSET(L$62,0,-($D68-1)))) -> 0 | ... BL68: =IF($D68>$C$61,0,IF($D68>BL$5,"",OFFSET(BL$62,0,-($D68-1)))) -> 0
B69: =SUMIFS(SAP_Spreadsheet!$G$11:$BN$11,SAP_Spreadsheet!$G$7:$BN$7,PnL_Speadsheet!$D69) -> 0.57306055 | C69: =SUMIFS(SAP_Spreadsheet!$G$10:$BN$10,SAP_Spreadsheet!$G$7:$BN$7,PnL_Speadsheet!$D69) -> 1 | D69: =D68+1 -> 7 | E69: =IF($D69>$C$61,0,IF($D69>E$5,"",OFFSET(E$62,0,-($D69-1)))) | F69: =IF($D69>$C$61,0,IF($D69>F$5,"",OFFSET(F$62,0,-($D69-1)))) | G69: =IF($D69>$C$61,0,IF($D69>G$5,"",OFFSET(G$62,0,-($D69-1)))) | H69: =IF($D69>$C$61,0,IF($D69>H$5,"",OFFSET(H$62,0,-($D69-1)))) | I69: =IF($D69>$C$61,0,IF($D69>I$5,"",OFFSET(I$62,0,-($D69-1)))) | J69: =IF($D69>$C$61,0,IF($D69>J$5,"",OFFSET(J$62,0,-($D69-1)))) | K69: =IF($D69>$C$61,0,IF($D69>K$5,"",OFFSET(K$62,0,-($D69-1)))) -> 0 | L69: =IF($D69>$C$61,0,IF($D69>L$5,"",OFFSET(L$62,0,-($D69-1)))) -> 0 | ... BL69: =IF($D69>$C$61,0,IF($D69>BL$5,"",OFFSET(BL$62,0,-($D69-1)))) -> 0
B70: =SUMIFS(SAP_Spreadsheet!$G$11:$BN$11,SAP_Spreadsheet!$G$7:$BN$7,PnL_Speadsheet!$D70) -> 0.56203034 | C70: =SUMIFS(SAP_Spreadsheet!$G$10:$BN$10,SAP_Spreadsheet!$G$7:$BN$7,PnL_Speadsheet!$D70) -> 1 | D70: =D69+1 -> 8 | E70: =IF($D70>$C$61,0,IF($D70>E$5,"",OFFSET(E$62,0,-($D70-1)))) | F70: =IF($D70>$C$61,0,IF($D70>F$5,"",OFFSET(F$62,0,-($D70-1)))) | G70: =IF($D70>$C$61,0,IF($D70>G$5,"",OFFSET(G$62,0,-($D70-1)))) | H70: =IF($D70>$C$61,0,IF($D70>H$5,"",OFFSET(H$62,0,-($D70-1)))) | I70: =IF($D70>$C$61,0,IF($D70>I$5,"",OFFSET(I$62,0,-($D70-1)))) | J70: =IF($D70>$C$61,0,IF($D70>J$5,"",OFFSET(J$62,0,-($D70-1)))) | K70: =IF($D70>$C$61,0,IF($D70>K$5,"",OFFSET(K$62,0,-($D70-1)))) | L70: =IF($D70>$C$61,0,IF($D70>L$5,"",OFFSET(L$62,0,-($D70-1)))) -> 0 | ... BL70: =IF($D70>$C$61,0,IF($D70>BL$5,"",OFFSET(BL$62,0,-($D70-1)))) -> 0
B71: =SUMIFS(SAP_Spreadsheet!$G$11:$BN$11,SAP_Spreadsheet!$G$7:$BN$7,PnL_Speadsheet!$D71) -> 0.55100014 | C71: =SUMIFS(SAP_Spreadsheet!$G$10:$BN$10,SAP_Spreadsheet!$G$7:$BN$7,PnL_Speadsheet!$D71) -> 1 | D71: =D70+1 -> 9 | E71: =IF($D71>$C$61,0,IF($D71>E$5,"",OFFSET(E$62,0,-($D71-1)))) | F71: =IF($D71>$C$61,0,IF($D71>F$5,"",OFFSET(F$62,0,-($D71-1)))) | G71: =IF($D71>$C$61,0,IF($D71>G$5,"",OFFSET(G$62,0,-($D71-1)))) | H71: =IF($D71>$C$61,0,IF($D71>H$5,"",OFFSET(H$62,0,-($D71-1)))) | I71: =IF($D71>$C$61,0,IF($D71>I$5,"",OFFSET(I$62,0,-($D71-1)))) | J71: =IF($D71>$C$61,0,IF($D71>J$5,"",OFFSET(J$62,0,-($D71-1)))) | K71: =IF($D71>$C$61,0,IF($D71>K$5,"",OFFSET(K$62,0,-($D71-1)))) | L71: =IF($D71>$C$61,0,IF($D71>L$5,"",OFFSET(L$62,0,-($D71-1)))) | ... BL71: =IF($D71>$C$61,0,IF($D71>BL$5,"",OFFSET(BL$62,0,-($D71-1)))) -> 0
B72: =SUMIFS(SAP_Spreadsheet!$G$11:$BN$11,SAP_Spreadsheet!$G$7:$BN$7,PnL_Speadsheet!$D72) -> 0.53996993 | C72: =SUMIFS(SAP_Spreadsheet!$G$10:$BN$10,SAP_Spreadsheet!$G$7:$BN$7,PnL_Speadsheet!$D72) -> 1 | D72: =D71+1 -> 10 | E72: =IF($D72>$C$61,0,IF($D72>E$5,"",OFFSET(E$62,0,-($D72-1)))) | F72: =IF($D72>$C$61,0,IF($D72>F$5,"",OFFSET(F$62,0,-($D72-1)))) | G72: =IF($D72>$C$61,0,IF($D72>G$5,"",OFFSET(G$62,0,-($D72-1)))) | H72: =IF($D72>$C$61,0,IF($D72>H$5,"",OFFSET(H$62,0,-($D72-1)))) | I72: =IF($D72>$C$61,0,IF($D72>I$5,"",OFFSET(I$62,0,-($D72-1)))) | J72: =IF($D72>$C$61,0,IF($D72>J$5,"",OFFSET(J$62,0,-($D72-1)))) | K72: =IF($D72>$C$61,0,IF($D72>K$5,"",OFFSET(K$62,0,-($D72-1)))) | L72: =IF($D72>$C$61,0,IF($D72>L$5,"",OFFSET(L$62,0,-($D72-1)))) | ... BL72: =IF($D72>$C$61,0,IF($D72>BL$5,"",OFFSET(BL$62,0,-($D72-1)))) -> 0
B73: =SUMIFS(SAP_Spreadsheet!$G$11:$BN$11,SAP_Spreadsheet!$G$7:$BN$7,PnL_Speadsheet!$D73) -> 0.52893972 | C73: =SUMIFS(SAP_Spreadsheet!$G$10:$BN$10,SAP_Spreadsheet!$G$7:$BN$7,PnL_Speadsheet!$D73) -> 1 | D73: =D72+1 -> 11 | E73: =IF($D73>$C$61,0,IF($D73>E$5,"",OFFSET(E$62,0,-($D73-1)))) | F73: =IF($D73>$C$61,0,IF($D73>F$5,"",OFFSET(F$62,0,-($D73-1)))) | G73: =IF($D73>$C$61,0,IF($D73>G$5,"",OFFSET(G$62,0,-($D73-1)))) | H73: =IF($D73>$C$61,0,IF($D73>H$5,"",OFFSET(H$62,0,-($D73-1)))) | I73: =IF($D73>$C$61,0,IF($D73>I$5,"",OFFSET(I$62,0,-($D73-1)))) | J73: =IF($D73>$C$61,0,IF($D73>J$5,"",OFFSET(J$62,0,-($D73-1)))) | K73: =IF($D73>$C$61,0,IF($D73>K$5,"",OFFSET(K$62,0,-($D73-1)))) | L73: =IF($D73>$C$61,0,IF($D73>L$5,"",OFFSET(L$62,0,-($D73-1)))) | ... BL73: =IF($D73>$C$61,0,IF($D73>BL$5,"",OFFSET(BL$62,0,-($D73-1)))) -> 0
B74: =SUMIFS(SAP_Spreadsheet!$G$11:$BN$11,SAP_Spreadsheet!$G$7:$BN$7,PnL_Speadsheet!$D74) -> 0.51790951 | C74: =SUMIFS(SAP_Spreadsheet!$G$10:$BN$10,SAP_Spreadsheet!$G$7:$BN$7,PnL_Speadsheet!$D74) -> 1 | D74: =D73+1 -> 12 | E74: =IF($D74>$C$61,0,IF($D74>E$5,"",OFFSET(E$62,0,-($D74-1)))) | F74: =IF($D74>$C$61,0,IF($D74>F$5,"",OFFSET(F$62,0,-($D74-1)))) | G74: =IF($D74>$C$61,0,IF($D74>G$5,"",OFFSET(G$62,0,-($D74-1)))) | H74: =IF($D74>$C$61,0,IF($D74>H$5,"",OFFSET(H$62,0,-($D74-1)))) | I74: =IF($D74>$C$61,0,IF($D74>I$5,"",OFFSET(I$62,0,-($D74-1)))) | J74: =IF($D74>$C$61,0,IF($D74>J$5,"",OFFSET(J$62,0,-($D74-1)))) | K74: =IF($D74>$C$61,0,IF($D74>K$5,"",OFFSET(K$62,0,-($D74-1)))) | L74: =IF($D74>$C$61,0,IF($D74>L$5,"",OFFSET(L$62,0,-($D74-1)))) | ... BL74: =IF($D74>$C$61,0,IF($D74>BL$5,"",OFFSET(BL$62,0,-($D74-1)))) -> 0
B75: =SUMIFS(SAP_Spreadsheet!$G$11:$BN$11,SAP_Spreadsheet!$G$7:$BN$7,PnL_Speadsheet!$D75) -> 0.51103175 | C75: =SUMIFS(SAP_Spreadsheet!$G$10:$BN$10,SAP_Spreadsheet!$G$7:$BN$7,PnL_Speadsheet!$D75) -> 1 | D75: =D74+1 -> 13 | E75: =IF($D75>$C$61,0,IF($D75>E$5,"",OFFSET(E$62,0,-($D75-1)))) | F75: =IF($D75>$C$61,0,IF($D75>F$5,"",OFFSET(F$62,0,-($D75-1)))) | G75: =IF($D75>$C$61,0,IF($D75>G$5,"",OFFSET(G$62,0,-($D75-1)))) | H75: =IF($D75>$C$61,0,IF($D75>H$5,"",OFFSET(H$62,0,-($D75-1)))) | I75: =IF($D75>$C$61,0,IF($D75>I$5,"",OFFSET(I$62,0,-($D75-1)))) | J75: =IF($D75>$C$61,0,IF($D75>J$5,"",OFFSET(J$62,0,-($D75-1)))) | K75: =IF($D75>$C$61,0,IF($D75>K$5,"",OFFSET(K$62,0,-($D75-1)))) | L75: =IF($D75>$C$61,0,IF($D75>L$5,"",OFFSET(L$62,0,-($D75-1)))) | ... BL75: =IF($D75>$C$61,0,IF($D75>BL$5,"",OFFSET(BL$62,0,-($D75-1)))) -> 0
... B122: =SUMIFS(SAP_Spreadsheet!$G$11:$BN$11,SAP_Spreadsheet!$G$7:$BN$7,PnL_Speadsheet!$D122) -> 0.27862843 | C122: =SUMIFS(SAP_Spreadsheet!$G$10:$BN$10,SAP_Spreadsheet!$G$7:$BN$7,PnL_Speadsheet!$D122) -> 1 | D122: =D121+1 -> 60 | E122: =IF($D122>$C$61,0,IF($D122>E$5,"",OFFSET(E$62,0,-($D122-1)))) | F122: =IF($D122>$C$61,0,IF($D122>F$5,"",OFFSET(F$62,0,-($D122-1)))) | G122: =IF($D122>$C$61,0,IF($D122>G$5,"",OFFSET(G$62,0,-($D122-1)))) | H122: =IF($D122>$C$61,0,IF($D122>H$5,"",OFFSET(H$62,0,-($D122-1)))) | I122: =IF($D122>$C$61,0,IF($D122>I$5,"",OFFSET(I$62,0,-($D122-1)))) | J122: =IF($D122>$C$61,0,IF($D122>J$5,"",OFFSET(J$62,0,-($D122-1)))) | K122: =IF($D122>$C$61,0,IF($D122>K$5,"",OFFSET(K$62,0,-($D122-1)))) | L122: =IF($D122>$C$61,0,IF($D122>L$5,"",OFFSET(L$62,0,-($D122-1)))) | ... BL122: =IF($D122>$C$61,0,IF($D122>BL$5,"",OFFSET(BL$62,0,-($D122-1)))) -> 0

Sheet Sheet1
