Workbook
Name __S1: {"Book1"}
Name __S1: {"Book1"}
Name _a1: {"'Sheet1'!$L$16"}
Name _a1: {"'Sheet1'!$L$16"}
Name _S1: {"Book1"}
Name _S1: {"Book1"}
Name Ă: #REF!
Name Ạ196: #REF!
Name â259: #REF!
Name â259: #REF!
Name â312: #REF!
Name â312: #REF!
Name Acquisition_PlanA: #REF!
Name Acquisition_PlanB: #REF!
Name Actual: (PeriodInActual*(#REF!>0))*PeriodInPlan
Name ActualBeyond: PeriodInActual*(#REF!>0)
Name adf: #REF!
Name adf: #REF!
Name AdvIncQ12020: #REF!
Name AdvIncQ12021: #REF!
Name AdvIncQ12022: #REF!
Name AdvIncQ12023: #REF!
Name AdvIncQ12024: #REF!
Name AdvIncQ22020: #REF!
Name AdvIncQ22021: #REF!
Name AdvIncQ22022: #REF!
Name AdvIncQ22023: #REF!
Name AdvIncQ22024: #REF!
Name AdvIncQ32020: #REF!
Name AdvIncQ32021: #REF!
Name AdvIncQ32022: #REF!
Name AdvIncQ32023: #REF!
Name AdvIncQ32024: #REF!
Name AdvIncQ42020: #REF!
Name AdvIncQ42021: #REF!
Name AdvIncQ42022: #REF!
Name AdvIncQ42023: #REF!
Name AdvIncQ42024: #REF!
Name AdvPenRate2020: #REF!
Name AdvPenRate2021: #REF!
Name AdvPenRate2022: #REF!
Name AdvPenRate2023: #REF!
Name AdvPenRate2024: #REF!
Name AllReportList: #REF!
Name Amount_act: #REF!
Name Amount_CF: #REF!
Name Amount_F: #REF!
Name Amount_KPI_act: #REF!
Name approval: #REF!
Name approval: #REF!
Name Attribute_F: #REF!
Name B: #REF!
Name b2bSpr: #REF!
Name BaoHanhSuaChua: #REF!
Name be_KPI_bud: #REF!
Name be2B: #REF!
Name bf: #REF!
Name bf: #REF!
Name BieuPhi: #REF!
Name BrMarQ12020: #REF!

Sheet NOTE
A1: SAP MODEL - PAYLATER
N2: KHN | O2: v8 | P2: 20250401
B3: 1. Notes and disclaimer
C4: a. Giới thiệu về SAP
D5: - SAP: Single Account Profitability (Hiệu quả sản phẩm trên từng đơn vị sản phẩm)
D6: - Model SAP được sử dụng như 1 mô hình dự đoán hiệu quả vòng đời của sản phẩm.
D7: - Do sự phức tạp của sản phẩm, các hệ thống vận hành (hệ thống hạch kế toán, hệ thống quản trị rủi ro, hệ thống quản trị…), hành vi người sử dụng hành vi người sử dụng, model chỉ có thể mô phỏng tương đối trung bình vòng đời của sản phẩm.
D8: - Mô hình được tính toán dựa vào các yếu tố đầu vào xác định tại thời điểm, do đó kết quả của mô hình có thể có sự khác biệt so với thực tế vận hành sản phẩm.
D9: - Mô hình SAP Paylater tính hiệu quả của 1 thẻ mở và được cutoff tối đa tại thời điểm 5 năm ( 60 tháng) kể từ ngày bắt đầu sản phẩm
E10: - Trường hợp sử dụng phương pháp tính dự phòng VAS, cần ghi nhận thêm chi phí dự phòng năm thứ 6 liên quan tới hiệu quả sản phẩm thẻ 5 năm.
E11: - Trường hợp sử dụng phương pháp tính dự phòng VAS, cần ghi nhận thêm chi phí dự phòng năm thứ 4 liên quan tới hiệu quả sản phẩm thẻ 3 năm.
C13: b. Giới thiệu về PnL
D14: - Trong file tính này, Profit & Lost (PnL) được dự phóng từ trung bình cộng kết quả kinh doanh trên từng sản phẩm (SAP) với yếu tố "sale plan" (số thẻ mở mới) qua từng tháng, do đó có thể khác biệt so với kết quả thực tế vận hành.
D15: - Dòng tiền thực tế qua từng tháng có thể khác biệt với mô hình tính toán do nhiều yếu tố tác động bên ngoài thay đổi, do đó, vui lòng chỉ sử dụng mô hình cho mục đích tham khảo.
D16: - Cho mục đích tính dự phòng dòng tiền ngắn và trung hạn, mô hình PnL được cutoff tại thời điểm 5 năm (60 tháng) kể từ ngày bắt đầu khởi chạy sản phẩm đầu tiên.
B18: 2. Instruction
D19: - Dành cho người sử dụng
E20: - Chỉ chỉnh sửa vào các ô màu vàng
E21: - 2 sheets "SAP_Leadsheet" và "Sale plan&PL" cung cấp yếu tố đầu vào và đầu ra để tính toán mô hình SAP cũng như PnL.
F22: - Sheet SAP_Leadsheet được cấu trúc 2 phần, bên trái là các yếu tố đầu vào (input) và bên phải là kết quả dự đoán (output). Đơn vị sử dụng tại bảng tính là triệu VND (mVND) và phần trăm (%)
F23: - Sheet "Sale plan & PL" được cấu trúc 2 phần, bên trên là sale plan và bên dưới là kết quả PnL
E24: - 2 sheets "SAP_Spreadsheet" và "PL projection speadsheet" là các file tính toán cho 2 sheet "SAP_Leadsheet", "Sales plan & PL"
F25: - 2 sheets được cấu trúc từ trên xuống dưới theo thứ tự tính toán mô phỏng để đưa ra kết quả kinh doanh cuối cùng
F26: - 2 sheets đã được tạm khóa. Trường hợp cần mở khóa, điều chỉnh các yếu tố, vui lòng liên hệ với nhóm vận hành để được hỗ trợ.
D28: - Dành riêng cho người vận hành, hiệu chỉnh
E29: - Cần cẩn trọng khi điều chỉnh ở các file "speadsheet" vì 1 khi sai lệch rất khó tìm ra lỗi (VD: sửa nhầm ô, link nhầm vị trí,…)
B32: 3. Legend
C34: REVENUE INPUT
C36: Card Status
D37: Activate at beginning | E37: Tỉ lệ active thẻ tại thời điểm tháng 1 | G37: Tỉ lệ active được tính là khách hàng có spending và/hoặc có outstanding balance
D38: Average attrition rate | E38: Tỉ lệ giảm active qua từng thàng | G38: Lấy trung bình tỉ lệ giảm active thẻ của các tháng (tính theo cohort)
C40: Term of using
D41: Tenor | E41: Thời hạn tài khoản
D42: Due date | E42: Ngày tới thời hạn miễn lãi
D43: Free-interest period | E43: Thời gian được miễn lãi (VD 45-55 ngày)
C45: Usage Status
D46: Spd / active card | E46: Tổng chi tiêu tiêu tháng/số thẻ active
C48: Payment status
D49: Port Revolving rate | E49: Tỉ lệ chuyển đổi dư nợ (được tính là %/ANR tháng trước)
D50: Repayment rate | E50: Tỉ lệ thanh toán dư nợ (được tính %/ANR tháng trước)
C52: Pricing
D53: CII rate | E53: Chi phí lãi vay (annually) | G53: Lấy trung bình tỉ lãi của rút tiền và chi tiêu
D54: COF rate | E54: Chi phí vốn (annually) | G54: Lấy theo BRD
C56: Customer fee
D57: Annual fee | E57: Phí thường niên | G57: Lấy trung bình tỉ lệ các thẻ
D58: Annual Fee waiver | E58: Tỉ lệ miễn phí thường niên (trừ năm 1)
D59: Monthly fee | E59: Phí hàng tháng (subcription fee,…)
D60: Issuance fee | E60: Phí mở thẻ mới
D61: Termination fee | E61: Phí đóng thẻ
D62: Late payment rate | E62: Phí chậm trả
D63: %Latepayment collected | E63: Tỉ lệ thu hồi chậm trả
D64: Min due fee | E64: Phí nếu min< trả phí+gốc < phí gốc cần thu
C66: EMI
D67: EMI Penetration | E67: Tỉ lệ chuyển đổi trả góp/spending trong tháng
D68: Average tenor | E68: Thời hạn chuyển đổi trung bình
D69: Initial fee | E69: Phí chuyển đổi trung bình/tháng
C71: COST INPUT
C72: Inflation rate | E72: Tỉ lệ dự kiến tăng chi phí qua các năm
C73: Sales & Marketing
D74: Lead acquisition | E74: Chi phí leadgen trả cho đối tác
D75: Sharing TOI+RISKDPD90+ | E75: Chi phí chia sẻ doanh thu chi phí rủi ro cho đối tác | G75: Auto mode
D76: Sharing NII | E76: Chia sẻ thu nhập từ lãi cho đối tác | G76: Manual mode
D77: Sharing NFI | E77: Chia sẻ thu nhập từ phí cho đối tác | G77: Manual mode
D78: Sharing Risk DPD 90+ | E78: Chia sẻ thu nhập từ chi phí rủi ro | G78: Manual mode
D80: Marketing cost for acquisition | E80: Chi phí marketing cho thẻ mở
D81: Marketing cost for usage | E81: Chi phí promotion hàng tháng cho thẻ hoạt động
C83: UW & Disbursal cost
D84: Underwriting cost | E84: Chi phí underwriting cost/thẻ mở | G84: Chi phí bao gồm (PBC, KLP, CIC,…)
D85: DOP cost | E85: Chi phí luồng DOP | G85: Bao gồm SMS,…
D86: Approval rate | E86: Tỉ lệ chấp thuận mở thẻ | G86: Tỉ lệ số thẻ được chấp thuận/số thẻ vào luồng LOS
D87: Opening rate | E87: Tỉ lệ mở thẻ | G87: Tỉ lệ số thẻ mở /số thẻ được chấp thuận mở
D88: Opening cost | E88: Chi phí mở thẻ | G88: Bao gồm các chi phí hợp đồng, SMS khi mở thẻ
D89: Credit Support | E89: Chi phí khác( hiện tại chưa có)
C91: Collection & AMC | E91: Chi phí thu hồi nợ/số thẻ activated | G91: Hiện tại VPB đang chỉ phân bổ chi phí GB (B0-B3) cho CAKE, chưa bao gồm BB( B4+)
C93: After-sales services
D94: SMS | E94: Chi phí tin nhắn tháng
D95: x
C97: Overheads
D98: SU_HR direct | E98: Chi phí nhân sự trực tiếp phân bổ | G98: Lấy theo trung bình năm
D99: SU_HR indirect | E99: Chi phí nhân sự hỗ trợ phân bổ | G99: Lấy theo trung bình năm
D100: SU_IT | E100: Chi phí IT phân bổ | G100: Lấy theo trung bình năm
D101: SU_Others | E101: Các chi phí khác phân bổ | G101: Lấy theo trung bình năm
C103: RISK INPUT
C105: Recovery rate | E105: Tỉ lệ thu hồi nợ sau WO | G105: Hiện tại chưa đủ dữ liệu tính nên để =0
C107: Provision rate
D108: Avg NF | E108: Netflow- Tỉ lệ chuyển nợ
D109: PD | E109: Percentage of debt (tỉ lệ vỡ nợ)
D110: Pro. rate | E110: Tỉ lệ vỡ nợ đã điều chỉnh thu hồi nợ
B140: DPD360+ | E140: IFRS | F140: EMI
B141: DPD180+ | E141: VAS | F141: non-EMI

Sheet SAP_Leadsheet
B1: SAP MODEL - PAYLATER CARD
B2: Leadsheet | Y2: OUTPUT
B3: HKN | C3: =NOTE!P2 -> 20250401 | D3: =NOTE!O2 -> v8 | Y3: ANR
Y4: TOI
B5: Select model type | Y5: Net interest income
B6: Write off | C6: DPD180+
B7: Provision | C7: VAS | Y7: PROVISION
B8: Chanel | C8: ALL | Y8: OPEX
B9: EMI mode | C9: EMI | Y9: Acq
B10: Customer type | Y10: Alter-sale mgt
B11: Quarter | C11: Q3.2025
E12: 0.98 | H12: %
B13: REVENUE INPUT | I13: Cur: mVND, % | L13: PERFORMANCE OUTPUT | V13: Cur: mVND, %
E15: Year 1 | F15: Year 2 | G15: Year 3 | H15: Year 4 | I15: Year 5 | N15: Lifetime | O15: Year 1 | P15: Year 2 | Q15: Year 3 | R15: Year 4 | S15: Year 5 | T15: Year 6 | U15: % of ANR | V15: % of Spending
L16: Spending | N16: =SUM(O16:S16) -> 12.727565 | O16: =SUM(SAP_Spreadsheet!G24:R24) -> 4.375036 | P16: =SUM(SAP_Spreadsheet!S24:AD24) -> 2.746214 | Q16: =SUM(SAP_Spreadsheet!AE24:AP24) -> 2.4523703 | R16: =SUM(SAP_Spreadsheet!AQ24:BB24) -> 1.8369478 | S16: =SUM(SAP_Spreadsheet!BC24:BN24) -> 1.3169969 | W16: Avg card sau attrition * spending/card
B17: Card Status | C17: Activate at beginning | E17: =DATA!B5 -> 0.66492241 | F17: Account having spending at month 1 | L17: ANR | N17: =AVERAGEIF(SAP_Spreadsheet!G202:BN202,"<>0") -> 0.50119744 | O17: =IFERROR(AVERAGEIF(SAP_Spreadsheet!G202:R202,"<>0"),0) -> 0.80495309 | P17: =IFERROR(AVERAGEIF(SAP_Spreadsheet!S202:AD202,"<>0"),0) -> 0.54304049 | Q17: =IFERROR(AVERAGEIF(SAP_Spreadsheet!AE202:AP202,"<>0"),0) -> 0.49769693 | R17: =IFERROR(AVERAGEIF(SAP_Spreadsheet!AQ202:BB202,"<>0"),0) -> 0.38169086 | S17: =IFERROR(AVERAGEIF(SAP_Spreadsheet!BC202:BN202,"<>0"),0) -> 0.27860583
C18: Average attrition rate | E18: =DATA!B6 -> 0.024514721 | F18: =DATA!C6 -> 0.0096187086 | G18: =DATA!D6 -> 0.0058085881 | H18: =DATA!E6 -> 0.0044311984 | I18: =DATA!F6 -> 0.0041467977 | J18: =IF(E17-E18*11-(F18+G18+H18+I18)*12<0,"check","OK") -> OK | L18: TOI | N18: =N19+N22 -> 0.76624159 | O18: =O19+O22 -> 0.30433161 | P18: =P19+P22 -> 0.28020682 | Q18: =Q19+Q22 -> 0.085345069 | R18: =R19+R22 -> 0.058305771 | S18: =S19+S22 -> 0.038052318 | U18: =N18/$N$17/60*12 -> 0.30576437 | V18: =N18/$N$16 -> 0.060203314
C19: per cohort | E19: including account have spending & balance | L19: Net interest income | N19: =SUM(N20:N21) -> 0.045832731 | O19: =SUM(O20:O21) -> 0.048879927 | P19: =SUM(P20:P21) -> 0.0068769217 | Q19: =SUM(Q20:Q21) -> 0.0023911483 | R19: =SUM(R20:R21) -> -0.004659294 | S19: =SUM(S20:S21) -> -0.0076559717 | U19: =N19/$N$17/60*12 -> 0.018289292 | V19: =N19/$N$16 -> 0.0036010605
L20: CII | N20: =SUM( SAP_Spreadsheet!G216:BN216) -> 0.17865005 | O20: =SUM(SAP_Spreadsheet!G216:R216) -> 0.091542441 | P20: =SUM(SAP_Spreadsheet!S216:AD216) -> 0.035658067 | Q20: =SUM( SAP_Spreadsheet!AE216:AP216) -> 0.028769086 | R20: =SUM( SAP_Spreadsheet!AQ216:BB216) -> 0.015570321 | S20: =SUM(SAP_Spreadsheet!BC216:BN216) -> 0.0071101374 | U20: =N20/$N$17/60*12 -> 0.071289292 | V20: =N20/$N$16 -> 0.014036467 | W20: ANR*%B0&1 thu được*%IR
B21: Term of using | C21: Tenor | E21: 60 | F21: month | L21: COF | N21: =SUM( SAP_Spreadsheet!G219:BN219) -> -0.13281732 | O21: =SUM(SAP_Spreadsheet!G219:R219) -> -0.042662514 | P21: =SUM(SAP_Spreadsheet!S219:AD219) -> -0.028781146 | Q21: =SUM( SAP_Spreadsheet!AE219:AP219) -> -0.026377937 | R21: =SUM( SAP_Spreadsheet!AQ219:BB219) -> -0.020229615 | S21: =SUM(SAP_Spreadsheet!BC219:BN219) -> -0.014766109 | U21: =N21/$N$17/60*12 -> -0.053 | V21: =N21/$N$16 -> -0.010435407 | W21: ANR*%COF
C22: Due date | E22: 5 | F22: Date of month | L22: Net fee income | N22: =SUM(N23:N32) -> 0.72040886 | O22: =SUM(O23:O32) -> 0.25545168 | P22: =SUM(P23:P32) -> 0.2733299 | Q22: =SUM(Q23:Q32) -> 0.082953921 | R22: =SUM(R23:R32) -> 0.062965065 | S22: =SUM(S23:S32) -> 0.04570829 | U22: =N22/$N$17/60*12 -> 0.28747508 | V22: =N22/$N$16 -> 0.056602253
C23: Free-interest period | E23: 45 | F23: days | L23: Annual fee | N23: =SUM( SAP_Spreadsheet!G222:BN222) -> 0 | O23: =SUM(SAP_Spreadsheet!G222:R222) -> 0 | P23: =SUM(SAP_Spreadsheet!S222:AD222) -> 0 | Q23: =SUM( SAP_Spreadsheet!AE222:AP222) -> 0 | R23: =SUM( SAP_Spreadsheet!AQ222:BB222) -> 0 | S23: =SUM( SAP_Spreadsheet!BC222:BN222) -> 0 | U23: =N23/$N$17/60*12 -> 0 | V23: =N23/$N$16 -> 0 | W23: Avg card sau waiver * annual fee
L24: Monthly fee | N24: =SUM( SAP_Spreadsheet!G223:BN223) -> 0.46565712 | O24: =SUM(SAP_Spreadsheet!G223:R223) -> 0.16955432 | P24: =SUM(SAP_Spreadsheet!S223:AD223) -> 0.10601758 | Q24: =SUM( SAP_Spreadsheet!AE223:AP223) -> 0.082206687 | R24: =SUM( SAP_Spreadsheet!AQ223:BB223) -> 0.062482458 | S24: =SUM( SAP_Spreadsheet!BC223:BN223) -> 0.045396071 | U24: =N24/$N$17/60*12 -> 0.18581784 | V24: =N24/$N$16 -> 0.036586505 | W24: Avg card*%B0&1 thu được*monthly fee
B25: Usage Status | C25: Spd / activate card | E25: =DATA!B13 -> 0.68778008 | F25: =DATA!C13 -> 0.68778008 | G25: =DATA!D13 -> 0.84420051 | H25: =DATA!E13 -> 0.84420051 | I25: =DATA!F13 -> 0.84420051 | L25: Transaction fee | N25: =SUM( SAP_Spreadsheet!G224:BN224) -> 0 | O25: =SUM(SAP_Spreadsheet!G224:R224) -> 0 | P25: =SUM(SAP_Spreadsheet!S224:AD224) -> 0 | Q25: =SUM( SAP_Spreadsheet!AE224:AP224) -> 0 | R25: =SUM( SAP_Spreadsheet!AQ224:BB224) -> 0 | S25: =SUM( SAP_Spreadsheet!BC224:BN224) -> 0 | U25: =N25/$N$17/60*12 -> 0 | V25: =N25/$N$16 -> 0 | W25: Newspending * %transaction fee * (1-%RRB0-1)
L26: Issuance fee | N26: =SUM( SAP_Spreadsheet!G225:BN225) -> 0 | O26: =SUM(SAP_Spreadsheet!G225:R225) -> 0 | P26: =SUM(SAP_Spreadsheet!S225:AD225) -> 0 | Q26: =SUM( SAP_Spreadsheet!AE225:AP225) -> 0 | R26: =SUM( SAP_Spreadsheet!AQ225:BB225) -> 0 | S26: =SUM( SAP_Spreadsheet!BC225:BN225) -> 0 | U26: =N26/$N$17/60*12 -> 0 | V26: =N26/$N$16 -> 0 | AB26: New spending = spending/active * avg active card sau attrition
B27: Payment status | C27: Port Revolving rate | E27: =DATA!D20 -> 0.5115999 | L27: Termination fee | N27: =SUM( SAP_Spreadsheet!G226:BN226) -> 0 | O27: =SUM(SAP_Spreadsheet!G226:R226) -> 0 | P27: =SUM(SAP_Spreadsheet!S226:AD226) -> 0 | Q27: =SUM( SAP_Spreadsheet!AE226:AP226) -> 0 | R27: =SUM( SAP_Spreadsheet!AQ226:BB226) -> 0 | S27: =SUM( SAP_Spreadsheet!BC226:BN226) -> 0 | U27: =N27/$N$17/60*12 -> 0 | V27: =N27/$N$16 -> 0
C28: Payment rate | E28: =DATA!D21 -> 0.39533386 | F28: =E28 -> 0.39533386 | G28: =F28 -> 0.39533386 | H28: =G28 -> 0.39533386 | I28: =H28 -> 0.39533386 | L28: Late payment | N28: =SUM( SAP_Spreadsheet!G227:BN227) -> 0.0054397423 | O28: =SUM(SAP_Spreadsheet!G227:R227) -> 0.0027933642 | P28: =SUM(SAP_Spreadsheet!S227:AD227) -> 0.0011043173 | Q28: =SUM( SAP_Spreadsheet!AE227:AP227) -> 0.00074723412 | R28: =SUM( SAP_Spreadsheet!AQ227:BB227) -> 0.00048260761 | S28: =SUM( SAP_Spreadsheet!BC227:BN227) -> 0.0003122191 | U28: =N28/$N$17/60*12 -> 0.0021706984 | V28: =N28/$N$16 -> 0.00042739851 | W28: Late pmt fee * [B1 * (1-%RRB1-2)/total balacne] * avg card
E29: payment T/ANR T-1 (excl WO) | L29: Min due fee | N29: =SUM( SAP_Spreadsheet!G230:BN230) -> 0 | O29: =SUM(SAP_Spreadsheet!G230:R230) -> 0 | P29: =SUM(SAP_Spreadsheet!S230:AD230) -> 0 | Q29: =SUM( SAP_Spreadsheet!AE230:AP230) -> 0 | R29: =SUM( SAP_Spreadsheet!AQ230:BB230) -> 0 | S29: =SUM( SAP_Spreadsheet!BC230:BN230) -> 0 | U29: =N29/$N$17/60*12 -> 0 | V29: =N29/$N$16 -> 0 | W29: ANR*%B0&1 thu được*%Mindue | AB29: [B1 * (1-%RRB1-2)/total balacne] -> tính ra số thẻ late
L30: EMI initial fee | N30: =SUM( SAP_Spreadsheet!G231:BN231) -> 0.249312 | O30: =SUM(SAP_Spreadsheet!G231:R231) -> 0.083104 | P30: =SUM(SAP_Spreadsheet!S231:AD231) -> 0.166208 | Q30: =SUM( SAP_Spreadsheet!AE231:AP231) -> 0 | R30: =SUM( SAP_Spreadsheet!AQ231:BB231) -> 0 | S30: =SUM( SAP_Spreadsheet!BC231:BN231) -> 0 | U30: =N30/$N$17/60*12 -> 0.099486542 | V30: =N30/$N$16 -> 0.01958835 | W30: EMI amt * tenor * 3%
B31: Pricing | C31: CII rate | E31: =DATA!D22 -> 0.41540864 | F31: annually | L31: EMI- early termination | N31: =SUM( SAP_Spreadsheet!G235:BN235) -> 0 | O31: =SUM(SAP_Spreadsheet!G235:R235) -> 0 | P31: =SUM(SAP_Spreadsheet!S235:AD235) -> 0 | Q31: =SUM( SAP_Spreadsheet!AE235:AP235) -> 0 | R31: =SUM( SAP_Spreadsheet!AQ235:BB235) -> 0 | S31: =SUM( SAP_Spreadsheet!BC235:BN235) -> 0 | U31: =N31/$N$17/60*12 -> 0 | V31: =N31/$N$16 -> 0
C32: COF rate | E32: 0.053 | F32: annually | L32: Fee suspended due to CIC | N32: =SUM( SAP_Spreadsheet!G236:BN236) -> 0 | O32: =SUM(SAP_Spreadsheet!G236:R236) -> 0 | P32: =SUM(SAP_Spreadsheet!S236:AD236) -> 0 | Q32: =SUM( SAP_Spreadsheet!AE236:AP236) -> 0 | R32: =SUM( SAP_Spreadsheet!AQ236:BB236) -> 0 | S32: =SUM( SAP_Spreadsheet!BC236:BN236) -> 0 | U32: =N32/$N$17/60*12 -> 0 | V32: =N32/$N$16 -> 0
L33: Other income | N33: =SUM( SAP_Spreadsheet!G240:BN240) -> 0 | O33: =SUM(SAP_Spreadsheet!G240:R240) -> 0 | P33: =SUM(SAP_Spreadsheet!S240:AD240) -> 0 | Q33: =SUM( SAP_Spreadsheet!AE240:AP240) -> 0 | R33: =SUM( SAP_Spreadsheet!AQ240:BB240) -> 0 | S33: =SUM( SAP_Spreadsheet!BC240:BN240) -> 0 | U33: =N33/$N$17/60*12 -> 0 | V33: =N33/$N$16 -> 0
B34: Fee/charge | C34: Annual fee | F34: per card/year | L34: PROVISION | N34: =SUM(O34:T34) -> -0.73067779 | O34: =SUM(SAP_Spreadsheet!G335:R335) -> -0.22082755 | P34: =SUM(SAP_Spreadsheet!S335:AD335) -> -0.23313954 | Q34: =SUM(SAP_Spreadsheet!AE335:AP335) -> -0.11835593 | R34: =SUM(SAP_Spreadsheet!AQ335:BB335) -> -0.084536149 | S34: =SUM(SAP_Spreadsheet!BC335:BN335) -> -0.053594948 | T34: =SUM(SAP_Spreadsheet!BO335:BZ335) -> -0.020223678 | U34: =N34/$N$17/60*12 -> -0.29157284 | V34: =N34/$N$16 -> -0.05740908
C35: Annual Fee waiver | F35: % accard port | L35: OPEX | N35: =N36+N41+N42+N48+N45+N49 -> -0.38866078 | O35: =O36+O41+O42+O48+O45+O49 -> -0.19668238 | P35: =P36+P41+P42+P48+P45+P49 -> -0.10842667 | Q35: =Q36+Q41+Q42+Q48+Q45+Q49 -> -0.036183467 | R35: =R36+R41+R42+R48+R45+R49 -> -0.027442497 | S35: =S36+S41+S42+S48+S45+S49 -> -0.019925772 | U35: =N35/$N$17/60*12 -> -0.15509288 | V35: =N35/$N$16 -> -0.030536932
C36: Monthtly fee (Subcription fee) | E36: =DATA!D26 -> 0.03222005 | F36: per card having spending/month | L36: Sales & Marketing | N36: =SUM(N38:N41) -> -0.11800728 | O36: =SUM(O38:O41) -> -0.058711755 | P36: =SUM(P38:P41) -> -0.05929552 | Q36: =SUM(Q38:Q41) -> 0 | R36: =SUM(R38:R41) -> 0 | S36: =SUM(S38:S41) -> 0 | U36: =N36/$N$17/60*12 -> -0.047090135 | V36: =N36/$N$16 -> -0.0092717873
C37: Transaction fee | F37: per spend/month | L37: Lead acquisition | N37: =SUM( SAP_Spreadsheet!G244:BN244) -> 0 | O37: =SUM(SAP_Spreadsheet!G244:R244) -> 0 | P37: =SUM(SAP_Spreadsheet!S244:AD244) -> 0 | Q37: =SUM( SAP_Spreadsheet!AE244:AP244) -> 0 | R37: =SUM( SAP_Spreadsheet!AQ244:BB244) -> 0 | S37: =SUM( SAP_Spreadsheet!BC244:BN244) -> 0 | U37: =N37/$N$17/60*12 -> 0 | V37: =N37/$N$16 -> 0
C38: Issuance fee | F38: per issued account | L38: Sharing TOI +Risk DPD90+ | N38: =SUM( SAP_Spreadsheet!G245:BN245) -> -0.11800728 | O38: =SUM(SAP_Spreadsheet!G245:R245) -> -0.058711755 | P38: =SUM(SAP_Spreadsheet!S245:AD245) -> -0.05929552 | Q38: =SUM( SAP_Spreadsheet!AE245:AP245) -> 0 | R38: =SUM( SAP_Spreadsheet!AQ245:BB245) -> 0 | S38: =SUM( SAP_Spreadsheet!BC245:BN245) -> 0 | U38: =N38/$N$17/60*12 -> -0.047090135 | V38: =N38/$N$16 -> -0.0092717873
C39: Termination fee | F39: per terminated account | L39: Sharing adjusted | N39: =SUM( SAP_Spreadsheet!G246:BN246) -> 0 | O39: =SUM(SAP_Spreadsheet!G246:R246) -> 0 | P39: =SUM(SAP_Spreadsheet!S246:AD246) -> 0 | Q39: =SUM( SAP_Spreadsheet!AE246:AP246) -> 0 | R39: =SUM( SAP_Spreadsheet!AQ246:BB246) -> 0 | S39: =SUM( SAP_Spreadsheet!BC246:BN246) -> 0 | U39: =N39/$N$17/60*12 -> 0 | V39: =N39/$N$16 -> 0
L40: Marketing cost for acquistion | N40: =SUM( SAP_Spreadsheet!G250:BN250) -> 0 | O40: =SUM(SAP_Spreadsheet!G250:R250) -> 0 | P40: =SUM(SAP_Spreadsheet!S250:AD250) -> 0 | Q40: =SUM( SAP_Spreadsheet!AE250:AP250) -> 0 | R40: =SUM( SAP_Spreadsheet!AQ250:BB250) -> 0 | S40: =SUM( SAP_Spreadsheet!BC250:BN250) -> 0 | U40: =N40/$N$17/60*12 -> 0 | V40: =N40/$N$16 -> 0
C41: Late payment interest | E41: 0 | F41: annually | L41: Promotion cost | N41: =-SUM( SAP_Spreadsheet!G251:BN251) -> 0 | O41: =-SUM(SAP_Spreadsheet!G251:R251) -> 0 | P41: =-SUM(SAP_Spreadsheet!S251:AD251) -> 0 | Q41: =-SUM( SAP_Spreadsheet!AE251:AP251) -> 0 | R41: =-SUM( SAP_Spreadsheet!AQ251:BB251) -> 0 | S41: =-SUM( SAP_Spreadsheet!BC251:BN251) -> 0 | U41: =N41/$N$17/60*12 -> 0 | V41: =N41/$N$16 -> 0
C42: Late payment penalty (fee) | E42: 0.1 | F42: per account | L42: UW & Disbursal cost | N42: =SUM(N43:N44) -> -0.060689763 | O42: =SUM(O43:O44) -> -0.060689763 | P42: =SUM(P43:P44) -> 0 | Q42: =SUM(Q43:Q44) -> 0 | R42: =SUM(R43:R44) -> 0 | S42: =SUM(S43:S44) -> 0 | U42: =N42/$N$17/60*12 -> -0.024217906 | V42: =N42/$N$16 -> -0.0047683719
L43: Underwriting cost | N43: =SUM(SAP_Spreadsheet!G254:BN254) -> -0.056689763 | O43: =SUM(SAP_Spreadsheet!G254:R254) -> -0.056689763 | P43: =SUM(SAP_Spreadsheet!S254:AD254) -> 0 | Q43: =SUM(SAP_Spreadsheet!AE254:AP254) -> 0 | R43: =SUM(SAP_Spreadsheet!AQ254:BB254) -> 0 | S43: =SUM(SAP_Spreadsheet!BC254:BN254) -> 0 | U43: =N43/$N$17/60*12 -> -0.022621729 | V43: =N43/$N$16 -> -0.0044540934
L44: Disbursement cost | N44: =SUM(SAP_Spreadsheet!G255:BN255) -> -0.004 | O44: =SUM(SAP_Spreadsheet!G255:R255) -> -0.004 | P44: =SUM(SAP_Spreadsheet!S255:AD255) -> 0 | Q44: =SUM(SAP_Spreadsheet!AE255:AP255) -> 0 | R44: =SUM(SAP_Spreadsheet!AQ255:BB255) -> 0 | S44: =SUM(SAP_Spreadsheet!BC255:BN255) -> 0 | U44: =N44/$N$17/60*12 -> -0.0015961773 | V44: =N44/$N$16 -> -0.0003142785
C45: Min due fee | F45: per revolving balance/month | L45: Collection | N45: =SUM(N46:N47) -> -0.13595951 | O45: =SUM(O46:O47) -> -0.050888779 | P45: =SUM(P46:P47) -> -0.031942932 | Q45: =SUM(Q46:Q47) -> -0.023239695 | R45: =SUM(R46:R47) -> -0.017407692 | S45: =SUM(S46:S47) -> -0.012480418 | U45: =N45/$N$17/60*12 -> -0.054253874 | V45: =N45/$N$16 -> -0.010682288
L46: Early collection | N46: =SUM( SAP_Spreadsheet!G265:BN265) -> -0.13595951 | O46: =SUM(SAP_Spreadsheet!G265:R265) -> -0.050888779 | P46: =SUM(SAP_Spreadsheet!S265:AD265) -> -0.031942932 | Q46: =SUM( SAP_Spreadsheet!AE265:AP265) -> -0.023239695 | R46: =SUM( SAP_Spreadsheet!AQ265:BB265) -> -0.017407692 | S46: =SUM( SAP_Spreadsheet!BC265:BN265) -> -0.012480418 | U46: =N46/$N$17/60*12 -> -0.054253874 | V46: =N46/$N$16 -> -0.010682288
B47: EMI | L47: AMC | N47: =SUM( SAP_Spreadsheet!G266:BN266) -> 0 | O47: =SUM(SAP_Spreadsheet!G266:R266) -> 0 | P47: =SUM(SAP_Spreadsheet!S266:AD266) -> 0 | Q47: =SUM( SAP_Spreadsheet!AE266:AP266) -> 0 | R47: =SUM( SAP_Spreadsheet!AQ266:BB266) -> 0 | S47: =SUM( SAP_Spreadsheet!BC266:BN266) -> 0 | U47: =N47/$N$17/60*12 -> 0 | V47: =N47/$N$16 -> 0
C48: Payment by months | L48: After sale service | N48: =SUM(SAP_Spreadsheet!G263:BN263) -> -0.012485702 | O48: =SUM(SAP_Spreadsheet!G263:R263) -> -0.0044527681 | P48: =SUM(SAP_Spreadsheet!S263:AD263) -> -0.0028999277 | Q48: =SUM( SAP_Spreadsheet!AE263:AP263) -> -0.0021838223 | R48: =SUM( SAP_Spreadsheet!AQ263:BB263) -> -0.0016930328 | S48: =SUM( SAP_Spreadsheet!BC263:BN263) -> -0.0012561508 | U48: =N48/$N$17/60*12 -> -0.0049823486 | V48: =N48/$N$16 -> -0.00098099689
C49: EMI Penetration | F49: per spending per month | L49: Other support units | N49: =SUM( SAP_Spreadsheet!G269:BN272) -> -0.061518527 | O49: =SUM(SAP_Spreadsheet!G269:R272) -> -0.021939315 | P49: =SUM(SAP_Spreadsheet!S269:AD272) -> -0.014288286 | Q49: =SUM( SAP_Spreadsheet!AE269:AP272) -> -0.010759951 | R49: =SUM( SAP_Spreadsheet!AQ269:BB272) -> -0.0083417724 | S49: =SUM( SAP_Spreadsheet!BC269:BN272) -> -0.0061892035 | U49: =N49/$N$17/60*12 -> -0.02454862 | V49: =N49/$N$16 -> -0.0048334876
C50: Average tenor | F50: per transaction | L50: PROFIT BEFORE SU | N50: =N18+N34+N35-N49+N33 -> -0.29157846 | O50: =O18+O34+O35-O49+O33 -> -0.091239007 | P50: =P18+P34+P35-P49+P33 -> -0.047071094 | Q50: =Q18+Q34+Q35-Q49+Q33 -> -0.05843438 | R50: =R18+R34+R35-R49+R33 -> -0.045331103 | S50: =S18+S34+S35-S49+S33 -> -0.029279198 | U50: =N50/$N$17/60*12 -> -0.11635273 | V50: =N50/$N$16 -> -0.02290921
C51: Initial fee | F51: per month | L51: PBT | N51: =N18+N33+N34+N35 -> -0.35309699 | O51: =O18+O33+O34+O35 -> -0.11317832 | P51: =P18+P33+P34+P35 -> -0.06135938 | Q51: =Q18+Q33+Q34+Q35 -> -0.06919433 | R51: =R18+R33+R34+R35 -> -0.053672875 | S51: =S18+S33+S34+S35 -> -0.035468402 | T51: =T18+T33+T34+T35 -> -0.020223678 | U51: =N51/$N$17/60*12 -> -0.14090135 | V51: =N51/$N$16 -> -0.027742698
C52: Early repayment | F52: transaction
C53: % early
C55: Retail 0% Installment
C56: #start month | E56: 6
C57: EMI Penetration | E57: 0.1 | F57: Account having installments
C58: # EMI tnx | E58: 3 | F58: # times (max 5)
C59: Ticket size | E59: 7 | F59: per installment transaction
C60: Prepayment | F60: per installment transaction
C61: Tenor | E61: 7 | F61: per transaction (max 10m)
C62: Initial fee | E62: =7%*0.5+0.4*2.99%*E61 -> 0.11872 | F62: per installment product price
B64: COST INPUT | I64: Cur: mVND, % | L64: SUMMARY OUTPUT | V64: Cur: mVND, %
B65: Inflation rate
E66: =IF(SAP_Spreadsheet!$C$5="yes",0,3.5%) -> 0.035 | F66: annual rate | N66: Lifetime | O66: Year 1 | P66: Year 2 | Q66: Year 3 | R66: Year 4 | S66: Year 5 | T66: Year 6 | U66: % of ANR | V66: % of Spending
B67: Sales & Marketing
C68: Lead acquisition | F68: per issued account | L68: ANR | N68: =N17 -> 0.50119744 | O68: =O17 -> 0.80495309 | P68: =P17 -> 0.54304049 | Q68: =Q17 -> 0.49769693 | R68: =R17 -> 0.38169086 | S68: =S17 -> 0.27860583 | T68: =T17 -> 0
C69: Sharing TOI +Risk DPD90+ | E69: =DATA!D36 -> 0.37546996 | F69: per month | G69: Auto mode | L69: TOI | N69: =N18 -> 0.76624159 | O69: =O18 -> 0.30433161 | P69: =P18 -> 0.28020682 | Q69: =Q18 -> 0.085345069 | R69: =R18 -> 0.058305771 | S69: =S18 -> 0.038052318 | T69: =T18 -> 0 | U69: =N69/$N$17/60*12 -> 0.30576437 | V69: =N69/$N$16/60*12 -> 0.012040663
C70: Sharing NII | F70: per month | G70: Manual mode | L70: Other income | N70: =N33 -> 0 | O70: =O33 -> 0 | P70: =P33 -> 0 | Q70: =Q33 -> 0 | R70: =R33 -> 0 | S70: =S33 -> 0 | T70: =T33 -> 0 | U70: =N70/$N$17/60*12 -> 0 | V70: =N70/$N$16/60*12 -> 0
C71: Sharing NFI | F71: per month | G71: Manual mode | L71: Variable Cost | N71: =N35-N49 -> -0.32714226 | O71: =O35-O49 -> -0.17474307 | P71: =P35-P49 -> -0.09413838 | Q71: =Q35-Q49 -> -0.025423517 | R71: =R35-R49 -> -0.019100725 | S71: =S35-S49 -> -0.013736568 | T71: =T35-T49 -> 0 | U71: =N71/$N$17/60*12 -> -0.13054426 | V71: =N71/$N$16/60*12 -> -0.0051406888
C72: Sharing Risk DPD 90+ | F72: per month | G72: Manual mode | L72: Provision cost | N72: =N34 -> -0.73067779 | O72: =O34 -> -0.22082755 | P72: =P34 -> -0.23313954 | Q72: =Q34 -> -0.11835593 | R72: =R34 -> -0.084536149 | S72: =S34 -> -0.053594948 | T72: =T34 -> -0.020223678 | U72: =N72/$N$17/60*12 -> -0.29157284 | V72: =N72/$N$16/60*12 -> -0.011481816
C73: Marketing cost for acquisition | F73: per issued account | L73: Profit before fixed cost | N73: =SUM(N69:N72) -> -0.29157846 | O73: =SUM(O69:O72) -> -0.091239007 | P73: =SUM(P69:P72) -> -0.047071094 | Q73: =SUM(Q69:Q72) -> -0.05843438 | R73: =SUM(R69:R72) -> -0.045331103 | S73: =SUM(S69:S72) -> -0.029279198 | T73: =SUM(T69:T72) -> -0.020223678 | U73: =N73/$N$17/60*12 -> -0.11635273 | V73: =N73/$N$16/60*12 -> -0.004581842
L74: Fixed cost | N74: =N49 -> -0.061518527 | O74: =O49 -> -0.021939315 | P74: =P49 -> -0.014288286 | Q74: =Q49 -> -0.010759951 | R74: =R49 -> -0.0083417724 | S74: =S49 -> -0.0061892035 | T74: =T49 -> 0 | U74: =N74/$N$17/60*12 -> -0.02454862 | V74: =N74/$N$16/60*12 -> -0.00096669751
B75: Promotion cost | L75: PBT | N75: =SUM(N73:N74) -> -0.35309699 | O75: =SUM(O73:O74) -> -0.11317832 | P75: =SUM(P73:P74) -> -0.06135938 | Q75: =SUM(Q73:Q74) -> -0.06919433 | R75: =SUM(R73:R74) -> -0.053672875 | S75: =SUM(S73:S74) -> -0.035468402 | T75: =SUM(T73:T74) -> -0.020223678 | U75: =N75/$N$17/60*12 -> -0.14090135 | V75: =N75/$N$16/60*12 -> -0.0055485395
C76: Marketing cost for usage
B78: UW & Disbursal cost
C79: Underwriting cost | E79: =DATA!D33*SAP_Leadsheet!E81*SAP_Leadsheet!E80 -> 0.0090857817 | F79: per application
C80: Approval rate | E80: 0.216 | F80: of applications submitted
C81: Disbursement rate | E81: 0.742 | F81: of applications approved
C82: Disbursement cost | E82: 0.004 | F82: per new issued account
B84: Collection & AMC
C85: Early collection of B0 | E85: 0.008 | F85: per account / month
C86: Early collection > B0 | D86: of B1 | F86: per account / month
C87: AMC | D87: B4-B12 | F87: per mVND (>= 90D) / month
B89: Other after-sale cost
C90: SMS & Email | E90: 0.0007 | F90: per active card / month
C91: x
C92: x
B94: Overheads
C95: SU_Direct HR | E95: 0.0010782076 | F95: per existing card / month
C96: SU_Indirect HR | E96: 0.00063414273 | F96: per existing card / month
C97: SU_IT | E97: 0.0007468595 | F97: per existing card / month
C98: SU_Others | E98: 0.00098977289 | F98: per existing card / month
B99: RISK INPUT
B101: Provision rate | E101: Avg NF | L101: PD | S101: Pro. rate
C102: Bucket | E102: 1 | F102: 2 | G102: 3 | H102: 4 | I102: 5 | K102: Bucket | L102: 1 | M102: 2 | N102: 3 | O102: 4 | P102: 5 | R102: Bucket | S102: 1 | T102: 2 | U102: 3 | V102: 4 | W102: 5
C103: B00 | E103: 0.065 | F103: 0.035 | G103: 0.03 | H103: 0.025 | I103: 0.022 | K103: B00 | L103: =PRODUCT(E103:E$116) -> 0.053159843 | M103: =PRODUCT(F103:F$116) -> 0.025235332 | N103: =PRODUCT(G103:G$116) -> 0.020657181 | O103: =PRODUCT(H103:H$116) -> 0.016592113 | P103: =PRODUCT(I103:I$116) -> 0.014601059 | R103: B00 | S103: =L103*(1-SAP_Leadsheet!$E$122)*(1-SAP_Leadsheet!$E$123)*(1-SAP_Leadsheet!$E$124) -> 0.053159843 | T103: =M103*(1-SAP_Leadsheet!$E$122)*(1-SAP_Leadsheet!$E$123)*(1-SAP_Leadsheet!$E$124) -> 0.025235332 | U103: =N103*(1-SAP_Leadsheet!$E$122)*(1-SAP_Leadsheet!$E$123)*(1-SAP_Leadsheet!$E$124) -> 0.020657181 | V103: =O103*(1-SAP_Leadsheet!$E$122)*(1-SAP_Leadsheet!$E$123)*(1-SAP_Leadsheet!$E$124) -> 0.016592113 | W103: =P103*(1-SAP_Leadsheet!$E$122)*(1-SAP_Leadsheet!$E$123)*(1-SAP_Leadsheet!$E$124) -> 0.014601059
C104: B01 | E104: 0.9 | F104: 0.85268498 | G104: 0.83 | H104: 0.8 | I104: 0.8 | K104: B01 | L104: =PRODUCT(E104:E$116) -> 0.81784373 | M104: =PRODUCT(F104:F$116) -> 0.72100948 | N104: =PRODUCT(G104:G$116) -> 0.68857269 | O104: =PRODUCT(H104:H$116) -> 0.66368452 | P104: =PRODUCT(I104:I$116) -> 0.66368452 | R104: B01 | S104: =L104*(1-SAP_Leadsheet!$E$122)*(1-SAP_Leadsheet!$E$123)*(1-SAP_Leadsheet!$E$124) -> 0.81784373 | T104: =M104*(1-SAP_Leadsheet!$E$122)*(1-SAP_Leadsheet!$E$123)*(1-SAP_Leadsheet!$E$124) -> 0.72100948 | U104: =N104*(1-SAP_Leadsheet!$E$122)*(1-SAP_Leadsheet!$E$123)*(1-SAP_Leadsheet!$E$124) -> 0.68857269 | V104: =O104*(1-SAP_Leadsheet!$E$122)*(1-SAP_Leadsheet!$E$123)*(1-SAP_Leadsheet!$E$124) -> 0.66368452 | W104: =P104*(1-SAP_Leadsheet!$E$122)*(1-SAP_Leadsheet!$E$123)*(1-SAP_Leadsheet!$E$124) -> 0.66368452
C105: B02 | E105: 0.96 | F105: 0.92697715 | G105: 0.9 | H105: 0.9 | I105: 0.9 | K105: B02 | L105: =PRODUCT(E105:E$116) -> 0.90871526 | M105: =PRODUCT(F105:F$116) -> 0.84557544 | N105: =PRODUCT(G105:G$116) -> 0.82960564 | O105: =PRODUCT(H105:H$116) -> 0.82960564 | P105: =PRODUCT(I105:I$116) -> 0.82960564 | R105: B02 | S105: =L105*(1-SAP_Leadsheet!$E$122)*(1-SAP_Leadsheet!$E$123)*(1-SAP_Leadsheet!$E$124) -> 0.90871526 | T105: =M105*(1-SAP_Leadsheet!$E$122)*(1-SAP_Leadsheet!$E$123)*(1-SAP_Leadsheet!$E$124) -> 0.84557544 | U105: =N105*(1-SAP_Leadsheet!$E$122)*(1-SAP_Leadsheet!$E$123)*(1-SAP_Leadsheet!$E$124) -> 0.82960564 | V105: =O105*(1-SAP_Leadsheet!$E$122)*(1-SAP_Leadsheet!$E$123)*(1-SAP_Leadsheet!$E$124) -> 0.82960564 | W105: =P105*(1-SAP_Leadsheet!$E$122)*(1-SAP_Leadsheet!$E$123)*(1-SAP_Leadsheet!$E$124) -> 0.82960564
C106: B03 | E106: 0.98201991 | F106: 0.9634852 | G106: 0.95 | H106: 0.95 | I106: 0.95 | K106: B03 | L106: =PRODUCT(E106:E$116) -> 0.9465784 | M106: =PRODUCT(F106:F$116) -> 0.91218586 | N106: =PRODUCT(G106:G$116) -> 0.92178405 | O106: =PRODUCT(H106:H$116) -> 0.92178405 | P106: =PRODUCT(I106:I$116) -> 0.92178405 | R106: B03 | S106: =L106*(1-SAP_Leadsheet!$E$122)*(1-SAP_Leadsheet!$E$123)*(1-SAP_Leadsheet!$E$124) -> 0.9465784 | T106: =M106*(1-SAP_Leadsheet!$E$122)*(1-SAP_Leadsheet!$E$123)*(1-SAP_Leadsheet!$E$124) -> 0.91218586 | U106: =N106*(1-SAP_Leadsheet!$E$122)*(1-SAP_Leadsheet!$E$123)*(1-SAP_Leadsheet!$E$124) -> 0.92178405 | V106: =O106*(1-SAP_Leadsheet!$E$122)*(1-SAP_Leadsheet!$E$123)*(1-SAP_Leadsheet!$E$124) -> 0.92178405 | W106: =P106*(1-SAP_Leadsheet!$E$122)*(1-SAP_Leadsheet!$E$123)*(1-SAP_Leadsheet!$E$124) -> 0.92178405
C107: B04 | E107: 0.98498153 | F107: 0.97571401 | G107: 0.99 | H107: 0.99 | I107: 0.99 | K107: B04 | L107: =PRODUCT(E107:E$116) -> 0.96390958 | M107: =PRODUCT(F107:F$116) -> 0.94675648 | N107: =PRODUCT(G107:G$116) -> 0.970299 | O107: =PRODUCT(H107:H$116) -> 0.970299 | P107: =PRODUCT(I107:I$116) -> 0.970299 | R107: B04 | S107: =L107*(1-SAP_Leadsheet!$E$122)*(1-SAP_Leadsheet!$E$123)*(1-SAP_Leadsheet!$E$124) -> 0.96390958 | T107: =M107*(1-SAP_Leadsheet!$E$122)*(1-SAP_Leadsheet!$E$123)*(1-SAP_Leadsheet!$E$124) -> 0.94675648 | U107: =N107*(1-SAP_Leadsheet!$E$122)*(1-SAP_Leadsheet!$E$123)*(1-SAP_Leadsheet!$E$124) -> 0.970299 | V107: =O107*(1-SAP_Leadsheet!$E$122)*(1-SAP_Leadsheet!$E$123)*(1-SAP_Leadsheet!$E$124) -> 0.970299 | W107: =P107*(1-SAP_Leadsheet!$E$122)*(1-SAP_Leadsheet!$E$123)*(1-SAP_Leadsheet!$E$124) -> 0.970299
C108: B05 | E108: 0.9852836 | F108: 0.98344467 | G108: 0.99 | H108: 0.99 | I108: 0.99 | K108: B05 | L108: =PRODUCT(E108:E$116) -> 0.97860675 | M108: =PRODUCT(F108:F$116) -> 0.97032171 | N108: =PRODUCT(G108:G$116) -> 0.9801 | O108: =PRODUCT(H108:H$116) -> 0.9801 | P108: =PRODUCT(I108:I$116) -> 0.9801 | R108: B05 | S108: =L108*(1-SAP_Leadsheet!$E$122)*(1-SAP_Leadsheet!$E$123)*(1-SAP_Leadsheet!$E$124) -> 0.97860675 | T108: =M108*(1-SAP_Leadsheet!$E$122)*(1-SAP_Leadsheet!$E$123)*(1-SAP_Leadsheet!$E$124) -> 0.97032171 | U108: =N108*(1-SAP_Leadsheet!$E$122)*(1-SAP_Leadsheet!$E$123)*(1-SAP_Leadsheet!$E$124) -> 0.9801 | V108: =O108*(1-SAP_Leadsheet!$E$122)*(1-SAP_Leadsheet!$E$123)*(1-SAP_Leadsheet!$E$124) -> 0.9801 | W108: =P108*(1-SAP_Leadsheet!$E$122)*(1-SAP_Leadsheet!$E$123)*(1-SAP_Leadsheet!$E$124) -> 0.9801
...

Sheet DATA
B3: 1. Attrition
B5: =SUMPRODUCT(I5:I8,$H$46:$H$49)/SUM($H$46:$H$49) -> 0.66492241 | C5: Account having spending at month 1 | H5: VDS | I5: 0.54 | J5: 0.012 | K5: 0.01 | L5: 0.005 | M5: 0.005 | N5: 0.005
B6: =SUMPRODUCT(J5:J8,$H$46:$H$49)/SUM($H$46:$H$49) -> 0.024514721 | C6: =SUMPRODUCT(K5:K8,$H$46:$H$49)/SUM($H$46:$H$49) -> 0.0096187086 | D6: =SUMPRODUCT(L5:L8,$H$46:$H$49)/SUM($H$46:$H$49) -> 0.0058085881 | E6: =SUMPRODUCT(M5:M8,$H$46:$H$49)/SUM($H$46:$H$49) -> 0.0044311984 | F6: =SUMPRODUCT(N5:N8,$H$46:$H$49)/SUM($H$46:$H$49) -> 0.0041467977 | H6: BE | I6: 0.8 | J6: 0.05 | K6: 0.007 | L6: 0.003 | M6: 0.003 | N6: 0.002
H7: VNPAY | I7: 0.72247981 | J7: 0.02 | K7: 0.013 | L7: 0.01 | M7: 0.005 | N7: 0.005
H8: MWG | I8: 0.55 | J8: 0.005 | K8: 0.005 | L8: 0.005 | M8: 0.005 | N8: 0.005
B10: 2. Spending
B13: =SUMPRODUCT(I13:I16,$H$46:$H$49)/SUM($H$46:$H$49) -> 0.68778008 | C13: =SUMPRODUCT(J13:J16,$H$46:$H$49)/SUM($H$46:$H$49) -> 0.68778008 | D13: =SUMPRODUCT(K13:K16,$H$46:$H$49)/SUM($H$46:$H$49) -> 0.84420051 | E13: =SUMPRODUCT(L13:L16,$H$46:$H$49)/SUM($H$46:$H$49) -> 0.84420051 | F13: =SUMPRODUCT(M13:M16,$H$46:$H$49)/SUM($H$46:$H$49) -> 0.84420051 | H13: VDS | I13: 0.45 | J13: =I13 -> 0.45 | K13: =J13 -> 0.45 | L13: =K13 -> 0.45 | M13: =L13 -> 0.45
H14: BE | I14: 0.45 | J14: =I14 -> 0.45 | K14: 1 | L14: 1 | M14: 1
H15: VNPAY | I15: 1 | J15: 1 | K15: 1 | L15: 1 | M15: 1
H16: MWG | I16: =5/3 -> 1.6666667 | J16: =I16 -> 1.6666667 | K16: =J16 -> 1.6666667 | L16: =K16 -> 1.6666667 | M16: =L16 -> 1.6666667
B18: 3. Revolving, repayment | I18: Revolving | J18: Repayment | K18: IR
H19: VDS | I19: 0.6212039 | J19: 0.3760479 | K19: 0.39
B20: Revolving | D20: =SUMPRODUCT(I19:I22,$M$56:$M$59)/SUM($M$56:$M$59) -> 0.5115999 | H20: BE | I20: 0.56195721 | J20: 0.44620293 | K20: 0.39
B21: Repayment | D21: =SUMPRODUCT(J19:J22,$M$56:$M$59)/SUM($M$56:$M$59) -> 0.39533386 | H21: VNPAY | I21: 0.56195721 | J21: 0.44620293 | K21: 0.39
B22: IR | D22: =SUMPRODUCT(K19:K22,$M$61:$M$64)/SUM($M$61:$M$64) -> 0.41540864 | H22: MWG | I22: 0.3 | J22: 0.3 | K22: 0.55
B25: 4. FEE
B26: Monthly fee | D26: =SUMPRODUCT(I27:I30,$H$46:$H$49)/SUM($H$46:$H$49) -> 0.03222005 | I26: monthly fee
H27: VDS | I27: 0.033
H28: BE | I28: 0.033
H29: VNPAY | I29: 0.033
H30: MWG | I30: 0.022
B32: 5. UW
B33: UW | D33: =SUM(E33:G33)/SUM(E34:G34)/10^6 -> 0.056689763 | E33: 518864882 | F33: 491421302 | G33: 477366582
B34: new account | E34: 9371 | F34: 8431 | G34: 8440
H35: VDS | I35: 0.5
B36: Sharing | D36: =SUMPRODUCT(I35:I38,$M$56:$M$59)/SUM($M$56:$M$59) -> 0.37546996 | H36: BE | I36: 0.5
H37: VNPAY | I37: 0.1
H38: MWG | I38: 0.35
D39: 45809 | E39: 45839 | F39: 45870 | G39: 45901
B40: New account
C41: VDS | D41: 3055 | E41: 1904 | F41: 1887 | G41: 2031
C42: BEG | D42: 1914 | E42: 1866 | F42: 1741 | G42: 1832
C43: VNPAY | D43: 2503 | E43: 2589 | F43: 2029 | G43: 2239
C44: MWG | D44: 1974 | E44: 2919 | F44: 2689 | G44: 2261
B45: Active account
C46: VDS | D46: 12498 | E46: 12437 | F46: 11083 | G46: 10452 | H46: =SUM(E46:G46) -> 33972
C47: BEG | D47: 7542 | E47: 8354 | F47: 8582 | G47: 9232 | H47: =SUM(E47:G47) -> 26168
C48: VNPAY | D48: 8022 | E48: 9017 | F48: 8214 | G48: 8116 | H48: =SUM(E48:G48) -> 25347
C49: MWG | D49: 733 | E49: 1762 | F49: 2527 | G49: 2235 | H49: =SUM(E49:G49) -> 6524
B50: Spending | I50: Repayment | J50: Installment spending | K50: =SUM(J54:L54)/SUM(E51:G54) -> 0.11722891
C51: VDS | D51: 12929240094 | E51: 12474809632 | F51: 9445336586 | G51: 9125003063 | H51: =SUM(E51:G51) -> 31045149281
C52: BEG | D52: 7745288700 | E52: 8142216513 | F52: 7801255169 | G52: 7926201248 | H52: =SUM(E52:G52) -> 23869672930
C53: VNPAY | D53: 17622441300 | E53: 17881303472 | F53: 16244324841 | G53: 15275927270 | H53: =SUM(E53:G53) -> 49401555583
C54: MWG | D54: 4.1176304e+09 | E54: 8932559708 | F54: 12586882650 | G54: 12824214914 | H54: =SUM(E54:G54) -> 34343657272 | J54: 5100227209 | K54: 5070914850 | L54: 6083822775
B55: ENR | I55: ENR exclude WO180
C56: VDS | D56: 26040511140 | E56: 27730732486 | F56: 28744359931 | G56: 30178361985 | I56: 22148871140 | J56: 22693234757 | K56: 22507599931 | L56: 22942521985 | M56: =SUM(J56:L56) -> 68143356673
C57: BEG | D57: 13217594611 | E57: 15461800031 | F57: 17508750374 | G57: 19473181026 | I57: 25457141269 | J57: 29352371776 | K57: 32677251042 | L57: 35866402954 | M57: =SUM(J57:L57) -> 97896025772
C58: VNPAY | D58: 25457141269 | E58: 29352371776 | F58: 32857251042 | G58: 36526402954 | I58: 22148871140 | J58: 22693234757 | K58: 22507599931 | L58: 22942521985 | M58: =SUM(J58:L58) -> 68143356673
C59: MWG | D59: 8462495252 | E59: 16239237866 | F59: 25467548263 | G59: 33104607622 | I59: 8462495252 | J59: 16239237866 | K59: 25467548263 | L59: 33104607622 | M59: =SUM(J59:L59) -> 74811393751
B60: EMI | I60: ENR exclude EMI
C61: VDS | I61: =I56-D61 -> 22148871140 | J61: =J56-E61 -> 22693234757 | K61: =K56-F61 -> 22507599931 | L61: =L56-G61 -> 22942521985 | M61: =SUM(J61:L61) -> 68143356673
C62: BEG | I62: =I57-D62 -> 25457141269 | J62: =J57-E62 -> 29352371776 | K62: =K57-F62 -> 32677251042 | L62: =L57-G62 -> 35866402954 | M62: =SUM(J62:L62) -> 97896025772
C63: VNPAY | I63: =I58-D63 -> 22148871140 | J63: =J58-E63 -> 22693234757 | K63: =K58-F63 -> 22507599931 | L63: =L58-G63 -> 22942521985 | M63: =SUM(J63:L63) -> 68143356673
C64: MWG | D64: 2402781546 | E64: 6822970698 | F64: 10095884056 | G64: 13682670940 | I64: =I59-D64 -> 6059713706 | J64: =J59-E64 -> 9416267168 | K64: =K59-F64 -> 15371664207 | L64: =L59-G64 -> 19421936682 | M64: =SUM(J64:L64) -> 44209868057
B65: Revolving | I65: Revolving exclude WO180
C66: VDS | D66: 15087266335 | E66: 17380177451 | F66: 20452614720 | G66: 22543365551 | I66: 11189853973 | J66: 12338497463 | K66: 14215854722 | L66: 15307525551
C67: BEG | D67: 5656858758 | E67: 7759192645 | F67: 10531083260 | G67: 12502625335 | I67: 8248829038 | J67: 12261732849 | K67: 17144605013 | L67: 20263612803
C68: VNPAY | D68: 8253816353 | E68: 12266675272 | F68: 17324605010 | G68: 20923612803 | I68: 25457141269 | J68: 29352371776 | K68: 32677251042 | L68: 35866402954
C69: MWG | D69: 4511359745 | E69: 4420584123 | F69: 6692794577 | G69: 11786886990 | I69: 4511359745 | J69: 4420584123 | K69: 6692794577 | L69: 11786886990

Sheet SAP_Spreadsheet
A1: Index!A1 | B1: SAP Model Paylater
B2: Spreadsheet
B4: Calendar | C4: =(30*4+31*7+28)/12 -> 30.416667 | AE4: =IF(AE$7<13,SAP_Leadsheet!$E$18,IF(SAP_Leadsheet!AF$6<25,SAP_Leadsheet!$F$18,IF(AE$7<37,SAP_Leadsheet!$G$18,IF(AE$7<49,SAP_Leadsheet!$H$18,SAP_Leadsheet!$I$18)))) -> 0.0096187086
B5: Validation | C5: No | D5: COF (*) | E5: =SAP_Leadsheet!E32 -> 0.053
E6: Year | G6: =ROUNDUP(G7/12,0) -> 1 | H6: =ROUNDUP(H7/12,0) -> 1 | I6: =ROUNDUP(I7/12,0) -> 1 | J6: =ROUNDUP(J7/12,0) -> 1 | K6: =ROUNDUP(K7/12,0) -> 1 | L6: =ROUNDUP(L7/12,0) -> 1 | M6: =ROUNDUP(M7/12,0) -> 1 | N6: =ROUNDUP(N7/12,0) -> 1 | ... BZ6: =ROUNDUP(BZ7/12,0) -> 6
E7: Month | G7: 1 | H7: =G7+1 -> 2 | I7: =H7+1 -> 3 | J7: =I7+1 -> 4 | K7: =J7+1 -> 5 | L7: =K7+1 -> 6 | M7: =L7+1 -> 7 | N7: =M7+1 -> 8 | O7: =N7+1 -> 9 | ... BZ7: =BY7+1 -> 72
A8: 1 | B8: CARD OPERATION | AE8: =IF(AE$7<37,SAP_Leadsheet!$G$18,IF(AE$7<49,SAP_Leadsheet!$H$18,SAP_Leadsheet!$I$18)) -> 0.0058085881
C10: Card Status | D10: Issued card | F10: # Card | G10: 1 | H10: =G10 -> 1 | I10: =H10 -> 1 | J10: =I10 -> 1 | K10: =J10 -> 1 | L10: =K10 -> 1 | M10: =L10 -> 1 | N10: =M10 -> 1 | O10: =N10 -> 1 | ... BN10: =BM10 -> 1
D11: Activate card | F11: # Card | G11: =G10*SAP_Leadsheet!E17 -> 0.66492241 | H11: =G11-H12 -> 0.64040769 | I11: =H11-I12 -> 0.61589297 | J11: =I11-J12 -> 0.59137825 | K11: =J11-K12 -> 0.56686352 | L11: =K11-L12 -> 0.5423488 | M11: =L11-M12 -> 0.51783408 | N11: =M11-N12 -> 0.49331936 | O11: =N11-O12 -> 0.46880464 | ... BN11: =BM11-BN12 -> 0.10719696
D12: Attrition rate | F12: % | G12: =OFFSET(SAP_Leadsheet!$D$18,0,SAP_Spreadsheet!G6) -> 0.024514721 | H12: =OFFSET(SAP_Leadsheet!$D$18,0,SAP_Spreadsheet!H6) -> 0.024514721 | I12: =OFFSET(SAP_Leadsheet!$D$18,0,SAP_Spreadsheet!I6) -> 0.024514721 | J12: =OFFSET(SAP_Leadsheet!$D$18,0,SAP_Spreadsheet!J6) -> 0.024514721 | K12: =OFFSET(SAP_Leadsheet!$D$18,0,SAP_Spreadsheet!K6) -> 0.024514721 | L12: =OFFSET(SAP_Leadsheet!$D$18,0,SAP_Spreadsheet!L6) -> 0.024514721 | M12: =OFFSET(SAP_Leadsheet!$D$18,0,SAP_Spreadsheet!M6) -> 0.024514721 | N12: =OFFSET(SAP_Leadsheet!$D$18,0,SAP_Spreadsheet!N6) -> 0.024514721 | ... BN12: =OFFSET(SAP_Leadsheet!$D$18,0,SAP_Spreadsheet!BN6) -> 0.0041467977
C15: Spending status | D15: Spd per activate card (Port) | F15: mVND | G15: =OFFSET(SAP_Leadsheet!$E$25,0,SAP_Spreadsheet!G6-1) -> 0.68778008 | H15: =OFFSET(SAP_Leadsheet!$E$25,0,SAP_Spreadsheet!H6-1) -> 0.68778008 | I15: =OFFSET(SAP_Leadsheet!$E$25,0,SAP_Spreadsheet!I6-1) -> 0.68778008 | J15: =OFFSET(SAP_Leadsheet!$E$25,0,SAP_Spreadsheet!J6-1) -> 0.68778008 | K15: =OFFSET(SAP_Leadsheet!$E$25,0,SAP_Spreadsheet!K6-1) -> 0.68778008 | L15: =OFFSET(SAP_Leadsheet!$E$25,0,SAP_Spreadsheet!L6-1) -> 0.68778008 | M15: =OFFSET(SAP_Leadsheet!$E$25,0,SAP_Spreadsheet!M6-1) -> 0.68778008 | N15: =OFFSET(SAP_Leadsheet!$E$25,0,SAP_Spreadsheet!N6-1) -> 0.68778008 | ... BN15: =OFFSET(SAP_Leadsheet!$E$25,0,SAP_Spreadsheet!BN6-1) -> 0.84420051
D17: Card Port | F17: % | G17: 1 | H17: 1 | I17: 1 | J17: 1 | K17: 1 | L17: 1 | M17: 1 | N17: 1 | O17: 1 | P17: 1 | Q17: 1 | R17: 1 | S17: 1 | T17: 1 | U17: 1 | V17: 1 | W17: 1 | X17: 1 | Y17: 1 | Z17: 1 | AA17: 1 | AB17: 1 | AC17: 1 | AD17: 1 | AE17: 1 | AF17: 1 | AG17: 1 | AH17: 1 | AI17: 1 | AJ17: 1 | AK17: 1 | AL17: 1 | AM17: 1 | AN17: 1 | AO17: 1 | AP17: 1 | AQ17: 1 | AR17: 1 | AS17: 1 | AT17: 1 | AU17: 1 | AV17: 1 | AW17: 1 | AX17: 1 | AY17: 1 | AZ17: 1 | BA17: 1 | BB17: 1 | BC17: 1 | BD17: 1 | BE17: 1 | BF17: 1 | BG17: 1 | BH17: 1 | BI17: 1 | BJ17: 1 | BK17: 1 | BL17: 1 | BM17: 1 | BN17: 1
D18: Transactor | F18: % | G18: =1-G19 -> 0.4884001 | H18: =1-H19 -> 0.4884001 | I18: =1-I19 -> 0.4884001 | J18: =1-J19 -> 0.4884001 | K18: =1-K19 -> 0.4884001 | L18: =1-L19 -> 0.4884001 | M18: =1-M19 -> 0.4884001 | N18: =1-N19 -> 0.4884001 | ... BN18: =1-BN19 -> 0.4884001
D19: Revolver | F19: % | G19: =SAP_Leadsheet!$E$27 -> 0.5115999 | H19: =SAP_Leadsheet!$E$27 -> 0.5115999 | I19: =SAP_Leadsheet!$E$27 -> 0.5115999 | J19: =SAP_Leadsheet!$E$27 -> 0.5115999 | K19: =SAP_Leadsheet!$E$27 -> 0.5115999 | L19: =SAP_Leadsheet!$E$27 -> 0.5115999 | M19: =SAP_Leadsheet!$E$27 -> 0.5115999 | N19: =SAP_Leadsheet!$E$27 -> 0.5115999 | ... BN19: =SAP_Leadsheet!$E$27 -> 0.5115999
A21: 3 | B21: BS by bucket
B23: CORE | C23: Core statement | D23: Beginning Bal | F23: mVND | G23: 0 | H23: =IF(H7>SAP_Leadsheet!$E$21,0,G28) -> 0.45732039 | I23: =IF(I7>SAP_Leadsheet!$E$21,0,H28) -> 0.83586421 | J23: =IF(J7>SAP_Leadsheet!$E$21,0,I28) -> 1.0274185 | K23: =IF(K7>SAP_Leadsheet!$E$21,0,J28) -> 1.077777 | L23: =IF(L7>SAP_Leadsheet!$E$21,0,K28) -> 1.0546632 | M23: =IF(M7>SAP_Leadsheet!$E$21,0,L28) -> 0.30472749 | N23: =IF(N7>SAP_Leadsheet!$E$21,0,M28) -> 0.3273984 | O23: =IF(O7>SAP_Leadsheet!$E$21,0,N28) -> 0.37367686 | ... BN23: =IF(BN7>SAP_Leadsheet!$E$21,0,BM28) -> 0.9358462
D24: New spending | F24: mVND | G24: =IF(G7>SAP_Leadsheet!$E$21,0,G15*G11) -> 0.45732039 | H24: =IF(H7>SAP_Leadsheet!$E$21,0,H15*H11) -> 0.44045965 | I24: =IF(I7>SAP_Leadsheet!$E$21,0,I15*I11) -> 0.42359892 | J24: =IF(J7>SAP_Leadsheet!$E$21,0,J15*J11) -> 0.40673818 | K24: =IF(K7>SAP_Leadsheet!$E$21,0,K15*K11) -> 0.38987744 | L24: =IF(L7>SAP_Leadsheet!$E$21,0,L15*L11) -> 0.37301671 | M24: =IF(M7>SAP_Leadsheet!$E$21,0,M15*M11) -> 0.35615597 | N24: =IF(N7>SAP_Leadsheet!$E$21,0,N15*N11) -> 0.33929523 | ... BN24: =IF(BN7>SAP_Leadsheet!$E$21,0,BN15*BN11) -> 0.090495731
D25: EMI Capitalized | F25: mVND | H25: =-G34 -> 0 | I25: =-H34 -> 0 | J25: =-I34 -> 0 | K25: =-J34 -> 0 | L25: =-K34 -> 0 | M25: =-L34 -> 0 | N25: =-M34 -> 0.0233017 | O25: =-N34 -> 0.029585133 | ... BN25: =-BM34 -> 0
D26: Move to EMI | F26: mVND | G26: =-G31 -> 0 | H26: =-H31 -> 0 | I26: =-I31 -> 0 | J26: =-J31 -> 0 | K26: =-K31 -> 0 | L26: =-L31 -> -0.7 | M26: =-M31 -> 0 | N26: =-N31 -> 0 | ... BN26: =-BN31 -> 0
D27: Paid off | F27: mVND | H27: {=IF(G7>SAP_Leadsheet!$E$21,0,-G202*INDEX(SAP_Leadsheet!$E$28:$I$28,1,SAP_Spreadsheet!G6)-H33)} -> -0.061915834 | I27: {=IF(H7>SAP_Leadsheet!$E$21,0,-H202*INDEX(SAP_Leadsheet!$E$28:$I$28,1,SAP_Spreadsheet!H6)-I33)} -> -0.23204464 | J27: {=IF(I7>SAP_Leadsheet!$E$21,0,-I202*INDEX(SAP_Leadsheet!$E$28:$I$28,1,SAP_Spreadsheet!I6)-J33)} -> -0.35637963 | K27: {=IF(J7>SAP_Leadsheet!$E$21,0,-J202*INDEX(SAP_Leadsheet!$E$28:$I$28,1,SAP_Spreadsheet!J6)-K33)} -> -0.41299127 | L27: {=IF(K7>SAP_Leadsheet!$E$21,0,-K202*INDEX(SAP_Leadsheet!$E$28:$I$28,1,SAP_Spreadsheet!K6)-L33)} -> -0.42295241 | M27: {=IF(L7>SAP_Leadsheet!$E$21,0,-L202*INDEX(SAP_Leadsheet!$E$28:$I$28,1,SAP_Spreadsheet!L6)-M33)} -> -0.33348506 | N27: {=IF(M7>SAP_Leadsheet!$E$21,0,-M202*INDEX(SAP_Leadsheet!$E$28:$I$28,1,SAP_Spreadsheet!M6)-N33)} -> -0.31631848 | O27: {=IF(N7>SAP_Leadsheet!$E$21,0,-N202*INDEX(SAP_Leadsheet!$E$28:$I$28,1,SAP_Spreadsheet!N6)-O33)} -> -0.29452411 | ... BN27: {=IF(BM7>SAP_Leadsheet!$E$21,0,-BM202*INDEX(SAP_Leadsheet!$E$28:$I$28,1,SAP_Spreadsheet!BM6)-BN33)} -> -0.095278857
D28: Ending Bal | F28: mVND | G28: =IF(SAP_Leadsheet!$E$21<G7,0,SUM(G23:G27)) -> 0.45732039 | H28: =IF(SAP_Leadsheet!$E$21<H7,0,SUM(H23:H27)) -> 0.83586421 | I28: =IF(SAP_Leadsheet!$E$21<I7,0,SUM(I23:I27)) -> 1.0274185 | J28: =IF(SAP_Leadsheet!$E$21<J7,0,SUM(J23:J27)) -> 1.077777 | K28: =IF(SAP_Leadsheet!$E$21<K7,0,SUM(K23:K27)) -> 1.0546632 | L28: =IF(SAP_Leadsheet!$E$21<L7,0,SUM(L23:L27)) -> 0.30472749 | M28: =IF(SAP_Leadsheet!$E$21<M7,0,SUM(M23:M27)) -> 0.3273984 | N28: =IF(SAP_Leadsheet!$E$21<N7,0,SUM(N23:N27)) -> 0.37367686 | ... BN28: =IF(SAP_Leadsheet!$E$21<BN7,0,SUM(BN23:BN27)) -> 0.93106307
B30: Installment | C30: Total EMI | D30: Beginning Bal | F30: mVND | G30: =G38+G106 -> 0 | H30: =H38+H106 -> 0 | I30: =I38+I106 -> 0 | J30: =J38+J106 -> 0 | K30: =K38+K106 -> 0 | L30: =L38+L106 -> 0 | M30: =M38+M106 -> 0.7 | N30: =N38+N106 -> 0.6 | ... BN30: =BN38+BN106 -> 3.6082248e-16
D31: New Billing | F31: mVND | G31: =IF(SAP_Leadsheet!$C$9="non-EMI",0,G39+G107) -> 0 | H31: =IF(SAP_Leadsheet!$C$9="non-EMI",0,H39+H107) -> 0 | I31: =IF(SAP_Leadsheet!$C$9="non-EMI",0,I39+I107) -> 0 | J31: =IF(SAP_Leadsheet!$C$9="non-EMI",0,J39+J107) -> 0 | K31: =IF(SAP_Leadsheet!$C$9="non-EMI",0,K39+K107) -> 0 | L31: =IF(SAP_Leadsheet!$C$9="non-EMI",0,L39+L107) -> 0.7 | M31: =IF(SAP_Leadsheet!$C$9="non-EMI",0,M39+M107) -> 0 | N31: =IF(SAP_Leadsheet!$C$9="non-EMI",0,N39+N107) -> 0 | ... BN31: =IF(SAP_Leadsheet!$C$9="non-EMI",0,BN39+BN107) -> 0
D32: Paid off | F32: mVND | G32: =G40+G108 -> 0 | H32: =H40+H108 -> 0 | I32: =I40+I108 -> 0 | J32: =J40+J108 -> 0 | K32: =K40+K108 -> 0 | L32: =L40+L108 -> 0 | M32: =M40+M108 -> -0.1 | N32: =N40+N108 -> -0.1 | ... BN32: =BN40+BN108 -> 0
D33: Paid off | F33: mVND | H33: =H32*G181/G172 -> 0 | I33: =I32*H181/H172 -> 0 | J33: =J32*I181/I172 -> 0 | K33: =K32*J181/J172 -> 0 | L33: =L32*K181/K172 -> 0 | M33: =M32*L181/L172 -> -0.0766983 | N33: =N32*M181/M172 -> -0.070414867 | O33: =O32*N181/N172 -> -0.064834608 | ... BN33: =BN32*BM181/BM172 -> 0
D34: Move to Core statement | F34: mVND | H34: =H32-H33 -> 0 | I34: =I32-I33 -> 0 | J34: =J32-J33 -> 0 | K34: =K32-K33 -> 0 | L34: =L32-L33 -> 0 | M34: =M32-M33 -> -0.0233017 | N34: =N32-N33 -> -0.029585133 | O34: =O32-O33 -> -0.035165392 | ... BN34: =BN32-BN33 -> 0
D35: Ending Bal | F35: mVND | G35: =G101+G169 -> 0 | H35: =H101+H169 -> 0 | I35: =I101+I169 -> 0 | J35: =J101+J169 -> 0 | K35: =K101+K169 -> 0 | L35: =L101+L169 -> 0.7 | M35: =M101+M169 -> 0.6 | N35: =N101+N169 -> 0.5 | ... BN35: =BN101+BN169 -> 3.6082248e-16
A37: 2.4 | B37: Loại 1 | C37: EMI penetration | G37: =SAP_Leadsheet!$E$49 -> 0 | H37: =SAP_Leadsheet!$E$49 -> 0 | I37: =SAP_Leadsheet!$E$49 -> 0 | J37: =SAP_Leadsheet!$E$49 -> 0 | K37: =SAP_Leadsheet!$E$49 -> 0 | L37: =SAP_Leadsheet!$E$49 -> 0 | M37: =SAP_Leadsheet!$E$49 -> 0 | N37: =SAP_Leadsheet!$E$49 -> 0 | ... BN37: =SAP_Leadsheet!$E$49 -> 0
B38: Sửa sau | C38: EMI statement | D38: Beginning Bal | G38: 0 | H38: =IF(H7>SAP_Leadsheet!$E$21,0,G101) -> 0 | I38: =IF(I7>SAP_Leadsheet!$E$21,0,H101) -> 0 | J38: =IF(J7>SAP_Leadsheet!$E$21,0,I101) -> 0 | K38: =IF(K7>SAP_Leadsheet!$E$21,0,J101) -> 0 | L38: =IF(L7>SAP_Leadsheet!$E$21,0,K101) -> 0 | M38: =IF(M7>SAP_Leadsheet!$E$21,0,L101) -> 0 | N38: =IF(N7>SAP_Leadsheet!$E$21,0,M101) -> 0 | O38: =IF(O7>SAP_Leadsheet!$E$21,0,N101) -> 0 | ... BN38: =IF(BN7>SAP_Leadsheet!$E$21,0,BM101) -> 0
D39: New Billing | G39: =IF(SAP_Leadsheet!$C$9="non-EMI",0,IF(G7>SAP_Leadsheet!$E$21,0,G37*G24)) -> 0 | H39: =IF(SAP_Leadsheet!$C$9="non-EMI",0,IF(H7>SAP_Leadsheet!$E$21,0,H37*H24)) -> 0 | I39: =IF(SAP_Leadsheet!$C$9="non-EMI",0,IF(I7>SAP_Leadsheet!$E$21,0,I37*I24)) -> 0 | J39: =IF(SAP_Leadsheet!$C$9="non-EMI",0,IF(J7>SAP_Leadsheet!$E$21,0,J37*J24)) -> 0 | K39: =IF(SAP_Leadsheet!$C$9="non-EMI",0,IF(K7>SAP_Leadsheet!$E$21,0,K37*K24)) -> 0 | L39: =IF(SAP_Leadsheet!$C$9="non-EMI",0,IF(L7>SAP_Leadsheet!$E$21,0,L37*L24)) -> 0 | M39: =IF(SAP_Leadsheet!$C$9="non-EMI",0,IF(M7>SAP_Leadsheet!$E$21,0,M37*M24)) -> 0 | N39: =IF(SAP_Leadsheet!$C$9="non-EMI",0,IF(N7>SAP_Leadsheet!$E$21,0,N37*N24)) -> 0 | ... BN39: =IF(SAP_Leadsheet!$C$9="non-EMI",0,IF(BN7>SAP_Leadsheet!$E$21,0,BN37*BN24)) -> 0
D40: Paid off | G40: 0 | H40: =IF(H7>SAP_Leadsheet!$E$21,0,-SUM(H41:H100)*G208) -> 0 | I40: =IF(I7>SAP_Leadsheet!$E$21,0,-SUM(I41:I100)*H208) -> 0 | J40: =IF(J7>SAP_Leadsheet!$E$21,0,-SUM(J41:J100)*I208) -> 0 | K40: =IF(K7>SAP_Leadsheet!$E$21,0,-SUM(K41:K100)*J208) -> 0 | L40: =IF(L7>SAP_Leadsheet!$E$21,0,-SUM(L41:L100)*K208) -> 0 | M40: =IF(M7>SAP_Leadsheet!$E$21,0,-SUM(M41:M100)*L208) -> 0 | N40: =IF(N7>SAP_Leadsheet!$E$21,0,-SUM(N41:N100)*M208) -> 0 | O40: =IF(O7>SAP_Leadsheet!$E$21,0,-SUM(O41:O100)*N208) -> 0 | ... BN40: =IF(BN7>SAP_Leadsheet!$E$21,0,-SUM(BN41:BN100)*BM208) -> 0
C41: {=TRANSPOSE(G7:BN7)} -> 1 | D41: {=TRANSPOSE(G39:BN39)} -> 0 | E41: =SAP_Leadsheet!$E$50 -> 0 | G41: =IF($C41+1>G$7,0,IF($D41>SUM(#REF!),$D41/$E41,0)) -> 0 | H41: =IF($C41+1>H$7,0,IF($D41>SUM($G41:G41),$D41/$E41,0)) -> 0 | I41: =IF($C41+1>I$7,0,IF($D41>SUM($G41:H41),$D41/$E41,0)) -> 0 | J41: =IF($C41+1>J$7,0,IF($D41>SUM($G41:I41),$D41/$E41,0)) -> 0 | K41: =IF($C41+1>K$7,0,IF($D41>SUM($G41:J41),$D41/$E41,0)) -> 0 | L41: =IF($C41+1>L$7,0,IF($D41>SUM($G41:K41),$D41/$E41,0)) -> 0 | M41: =IF($C41+1>M$7,0,IF($D41>SUM($G41:L41),$D41/$E41,0)) -> 0 | N41: =IF($C41+1>N$7,0,IF($D41>SUM($G41:M41),$D41/$E41,0)) -> 0 | O41: =IF($C41+1>O$7,0,IF($D41>SUM($G41:N41),$D41/$E41,0)) -> 0 | ... BN41: =IF($C41+1>BN$7,0,IF($D41>SUM($G41:BM41),$D41/$E41,0)) -> 0
C42: 2 | D42: 0 | E42: =SAP_Leadsheet!$E$50 -> 0 | G42: =IF($C42+1>G$7,0,IF($D42>SUM(#REF!),$D42/$E42,0)) -> 0 | H42: =IF($C42+1>H$7,0,IF($D42>SUM($G42:G42),$D42/$E42,0)) -> 0 | I42: =IF($C42+1>I$7,0,IF($D42>SUM($G42:H42),$D42/$E42,0)) -> 0 | J42: =IF($C42+1>J$7,0,IF($D42>SUM($G42:I42),$D42/$E42,0)) -> 0 | K42: =IF($C42+1>K$7,0,IF($D42>SUM($G42:J42),$D42/$E42,0)) -> 0 | L42: =IF($C42+1>L$7,0,IF($D42>SUM($G42:K42),$D42/$E42,0)) -> 0 | M42: =IF($C42+1>M$7,0,IF($D42>SUM($G42:L42),$D42/$E42,0)) -> 0 | N42: =IF($C42+1>N$7,0,IF($D42>SUM($G42:M42),$D42/$E42,0)) -> 0 | O42: =IF($C42+1>O$7,0,IF($D42>SUM($G42:N42),$D42/$E42,0)) -> 0 | ... BN42: =IF($C42+1>BN$7,0,IF($D42>SUM($G42:BM42),$D42/$E42,0)) -> 0
C43: 3 | D43: 0 | E43: =SAP_Leadsheet!$E$50 -> 0 | G43: =IF($C43+1>G$7,0,IF($D43>SUM(#REF!),$D43/$E43,0)) -> 0 | H43: =IF($C43+1>H$7,0,IF($D43>SUM($G43:G43),$D43/$E43,0)) -> 0 | I43: =IF($C43+1>I$7,0,IF($D43>SUM($G43:H43),$D43/$E43,0)) -> 0 | J43: =IF($C43+1>J$7,0,IF($D43>SUM($G43:I43),$D43/$E43,0)) -> 0 | K43: =IF($C43+1>K$7,0,IF($D43>SUM($G43:J43),$D43/$E43,0)) -> 0 | L43: =IF($C43+1>L$7,0,IF($D43>SUM($G43:K43),$D43/$E43,0)) -> 0 | M43: =IF($C43+1>M$7,0,IF($D43>SUM($G43:L43),$D43/$E43,0)) -> 0 | N43: =IF($C43+1>N$7,0,IF($D43>SUM($G43:M43),$D43/$E43,0)) -> 0 | O43: =IF($C43+1>O$7,0,IF($D43>SUM($G43:N43),$D43/$E43,0)) -> 0 | ... BN43: =IF($C43+1>BN$7,0,IF($D43>SUM($G43:BM43),$D43/$E43,0)) -> 0
C44: 4 | D44: 0 | E44: =SAP_Leadsheet!$E$50 -> 0 | G44: =IF($C44+1>G$7,0,IF($D44>SUM(#REF!),$D44/$E44,0)) -> 0 | H44: =IF($C44+1>H$7,0,IF($D44>SUM($G44:G44),$D44/$E44,0)) -> 0 | I44: =IF($C44+1>I$7,0,IF($D44>SUM($G44:H44),$D44/$E44,0)) -> 0 | J44: =IF($C44+1>J$7,0,IF($D44>SUM($G44:I44),$D44/$E44,0)) -> 0 | K44: =IF($C44+1>K$7,0,IF($D44>SUM($G44:J44),$D44/$E44,0)) -> 0 | L44: =IF($C44+1>L$7,0,IF($D44>SUM($G44:K44),$D44/$E44,0)) -> 0 | M44: =IF($C44+1>M$7,0,IF($D44>SUM($G44:L44),$D44/$E44,0)) -> 0 | N44: =IF($C44+1>N$7,0,IF($D44>SUM($G44:M44),$D44/$E44,0)) -> 0 | O44: =IF($C44+1>O$7,0,IF($D44>SUM($G44:N44),$D44/$E44,0)) -> 0 | ... BN44: =IF($C44+1>BN$7,0,IF($D44>SUM($G44:BM44),$D44/$E44,0)) -> 0
C45: 5 | D45: 0 | E45: =SAP_Leadsheet!$E$50 -> 0 | G45: =IF($C45+1>G$7,0,IF($D45>SUM(#REF!),$D45/$E45,0)) -> 0 | H45: =IF($C45+1>H$7,0,IF($D45>SUM($G45:G45),$D45/$E45,0)) -> 0 | I45: =IF($C45+1>I$7,0,IF($D45>SUM($G45:H45),$D45/$E45,0)) -> 0 | J45: =IF($C45+1>J$7,0,IF($D45>SUM($G45:I45),$D45/$E45,0)) -> 0 | K45: =IF($C45+1>K$7,0,IF($D45>SUM($G45:J45),$D45/$E45,0)) -> 0 | L45: =IF($C45+1>L$7,0,IF($D45>SUM($G45:K45),$D45/$E45,0)) -> 0 | M45: =IF($C45+1>M$7,0,IF($D45>SUM($G45:L45),$D45/$E45,0)) -> 0 | N45: =IF($C45+1>N$7,0,IF($D45>SUM($G45:M45),$D45/$E45,0)) -> 0 | O45: =IF($C45+1>O$7,0,IF($D45>SUM($G45:N45),$D45/$E45,0)) -> 0 | ... BN45: =IF($C45+1>BN$7,0,IF($D45>SUM($G45:BM45),$D45/$E45,0)) -> 0
C46: 6 | D46: 0 | E46: =SAP_Leadsheet!$E$50 -> 0 | G46: =IF($C46+1>G$7,0,IF($D46>SUM(#REF!),$D46/$E46,0)) -> 0 | H46: =IF($C46+1>H$7,0,IF($D46>SUM($G46:G46),$D46/$E46,0)) -> 0 | I46: =IF($C46+1>I$7,0,IF($D46>SUM($G46:H46),$D46/$E46,0)) -> 0 | J46: =IF($C46+1>J$7,0,IF($D46>SUM($G46:I46),$D46/$E46,0)) -> 0 | K46: =IF($C46+1>K$7,0,IF($D46>SUM($G46:J46),$D46/$E46,0)) -> 0 | L46: =IF($C46+1>L$7,0,IF($D46>SUM($G46:K46),$D46/$E46,0)) -> 0 | M46: =IF($C46+1>M$7,0,IF($D46>SUM($G46:L46),$D46/$E46,0)) -> 0 | N46: =IF($C46+1>N$7,0,IF($D46>SUM($G46:M46),$D46/$E46,0)) -> 0 | O46: =IF($C46+1>O$7,0,IF($D46>SUM($G46:N46),$D46/$E46,0)) -> 0 | ... BN46: =IF($C46+1>BN$7,0,IF($D46>SUM($G46:BM46),$D46/$E46,0)) -> 0
C47: 7 | D47: 0 | E47: =SAP_Leadsheet!$E$50 -> 0 | G47: =IF($C47+1>G$7,0,IF($D47>SUM(#REF!),$D47/$E47,0)) -> 0 | H47: =IF($C47+1>H$7,0,IF($D47>SUM($G47:G47),$D47/$E47,0)) -> 0 | I47: =IF($C47+1>I$7,0,IF($D47>SUM($G47:H47),$D47/$E47,0)) -> 0 | J47: =IF($C47+1>J$7,0,IF($D47>SUM($G47:I47),$D47/$E47,0)) -> 0 | K47: =IF($C47+1>K$7,0,IF($D47>SUM($G47:J47),$D47/$E47,0)) -> 0 | L47: =IF($C47+1>L$7,0,IF($D47>SUM($G47:K47),$D47/$E47,0)) -> 0 | M47: =IF($C47+1>M$7,0,IF($D47>SUM($G47:L47),$D47/$E47,0)) -> 0 | N47: =IF($C47+1>N$7,0,IF($D47>SUM($G47:M47),$D47/$E47,0)) -> 0 | O47: =IF($C47+1>O$7,0,IF($D47>SUM($G47:N47),$D47/$E47,0)) -> 0 | ... BN47: =IF($C47+1>BN$7,0,IF($D47>SUM($G47:BM47),$D47/$E47,0)) -> 0
C48: 8 | D48: 0 | E48: =SAP_Leadsheet!$E$50 -> 0 | G48: =IF($C48+1>G$7,0,IF($D48>SUM(#REF!),$D48/$E48,0)) -> 0 | H48: =IF($C48+1>H$7,0,IF($D48>SUM($G48:G48),$D48/$E48,0)) -> 0 | I48: =IF($C48+1>I$7,0,IF($D48>SUM($G48:H48),$D48/$E48,0)) -> 0 | J48: =IF($C48+1>J$7,0,IF($D48>SUM($G48:I48),$D48/$E48,0)) -> 0 | K48: =IF($C48+1>K$7,0,IF($D48>SUM($G48:J48),$D48/$E48,0)) -> 0 | L48: =IF($C48+1>L$7,0,IF($D48>SUM($G48:K48),$D48/$E48,0)) -> 0 | M48: =IF($C48+1>M$7,0,IF($D48>SUM($G48:L48),$D48/$E48,0)) -> 0 | N48: =IF($C48+1>N$7,0,IF($D48>SUM($G48:M48),$D48/$E48,0)) -> 0 | O48: =IF($C48+1>O$7,0,IF($D48>SUM($G48:N48),$D48/$E48,0)) -> 0 | ... BN48: =IF($C48+1>BN$7,0,IF($D48>SUM($G48:BM48),$D48/$E48,0)) -> 0
C49: 9 | D49: 0 | E49: =SAP_Leadsheet!$E$50 -> 0 | G49: =IF($C49+1>G$7,0,IF($D49>SUM(#REF!),$D49/$E49,0)) -> 0 | H49: =IF($C49+1>H$7,0,IF($D49>SUM($G49:G49),$D49/$E49,0)) -> 0 | I49: =IF($C49+1>I$7,0,IF($D49>SUM($G49:H49),$D49/$E49,0)) -> 0 | J49: =IF($C49+1>J$7,0,IF($D49>SUM($G49:I49),$D49/$E49,0)) -> 0 | K49: =IF($C49+1>K$7,0,IF($D49>SUM($G49:J49),$D49/$E49,0)) -> 0 | L49: =IF($C49+1>L$7,0,IF($D49>SUM($G49:K49),$D49/$E49,0)) -> 0 | M49: =IF($C49+1>M$7,0,IF($D49>SUM($G49:L49),$D49/$E49,0)) -> 0 | N49: =IF($C49+1>N$7,0,IF($D49>SUM($G49:M49),$D49/$E49,0)) -> 0 | O49: =IF($C49+1>O$7,0,IF($D49>SUM($G49:N49),$D49/$E49,0)) -> 0 | ... BN49: =IF($C49+1>BN$7,0,IF($D49>SUM($G49:BM49),$D49/$E49,0)) -> 0
C50: 10 | D50: 0 | E50: =SAP_Leadsheet!$E$50 -> 0 | G50: =IF($C50+1>G$7,0,IF($D50>SUM(#REF!),$D50/$E50,0)) -> 0 | H50: =IF($C50+1>H$7,0,IF($D50>SUM($G50:G50),$D50/$E50,0)) -> 0 | I50: =IF($C50+1>I$7,0,IF($D50>SUM($G50:H50),$D50/$E50,0)) -> 0 | J50: =IF($C50+1>J$7,0,IF($D50>SUM($G50:I50),$D50/$E50,0)) -> 0 | K50: =IF($C50+1>K$7,0,IF($D50>SUM($G50:J50),$D50/$E50,0)) -> 0 | L50: =IF($C50+1>L$7,0,IF($D50>SUM($G50:K50),$D50/$E50,0)) -> 0 | M50: =IF($C50+1>M$7,0,IF($D50>SUM($G50:L50),$D50/$E50,0)) -> 0 | N50: =IF($C50+1>N$7,0,IF($D50>SUM($G50:M50),$D50/$E50,0)) -> 0 | O50: =IF($C50+1>O$7,0,IF($D50>SUM($G50:N50),$D50/$E50,0)) -> 0 | ... BN50: =IF($C50+1>BN$7,0,IF($D50>SUM($G50:BM50),$D50/$E50,0)) -> 0
C51: 11 | D51: 0 | E51: =SAP_Leadsheet!$E$50 -> 0 | G51: =IF($C51+1>G$7,0,IF($D51>SUM(#REF!),$D51/$E51,0)) -> 0 | H51: =IF($C51+1>H$7,0,IF($D51>SUM($G51:G51),$D51/$E51,0)) -> 0 | I51: =IF($C51+1>I$7,0,IF($D51>SUM($G51:H51),$D51/$E51,0)) -> 0 | J51: =IF($C51+1>J$7,0,IF($D51>SUM($G51:I51),$D51/$E51,0)) -> 0 | K51: =IF($C51+1>K$7,0,IF($D51>SUM($G51:J51),$D51/$E51,0)) -> 0 | L51: =IF($C51+1>L$7,0,IF($D51>SUM($G51:K51),$D51/$E51,0)) -> 0 | M51: =IF($C51+1>M$7,0,IF($D51>SUM($G51:L51),$D51/$E51,0)) -> 0 | N51: =IF($C51+1>N$7,0,IF($D51>SUM($G51:M51),$D51/$E51,0)) -> 0 | O51: =IF($C51+1>O$7,0,IF($D51>SUM($G51:N51),$D51/$E51,0)) -> 0 | ... BN51: =IF($C51+1>BN$7,0,IF($D51>SUM($G51:BM51),$D51/$E51,0)) -> 0
C52: 12 | D52: 0 | E52: =SAP_Leadsheet!$E$50 -> 0 | G52: =IF($C52+1>G$7,0,IF($D52>SUM(#REF!),$D52/$E52,0)) -> 0 | H52: =IF($C52+1>H$7,0,IF($D52>SUM($G52:G52),$D52/$E52,0)) -> 0 | I52: =IF($C52+1>I$7,0,IF($D52>SUM($G52:H52),$D52/$E52,0)) -> 0 | J52: =IF($C52+1>J$7,0,IF($D52>SUM($G52:I52),$D52/$E52,0)) -> 0 | K52: =IF($C52+1>K$7,0,IF($D52>SUM($G52:J52),$D52/$E52,0)) -> 0 | L52: =IF($C52+1>L$7,0,IF($D52>SUM($G52:K52),$D52/$E52,0)) -> 0 | M52: =IF($C52+1>M$7,0,IF($D52>SUM($G52:L52),$D52/$E52,0)) -> 0 | N52: =IF($C52+1>N$7,0,IF($D52>SUM($G52:M52),$D52/$E52,0)) -> 0 | O52: =IF($C52+1>O$7,0,IF($D52>SUM($G52:N52),$D52/$E52,0)) -> 0 | ... BN52: =IF($C52+1>BN$7,0,IF($D52>SUM($G52:BM52),$D52/$E52,0)) -> 0
C53: 13 | D53: 0 | E53: =SAP_Leadsheet!$E$50 -> 0 | G53: =IF($C53+1>G$7,0,IF($D53>SUM(#REF!),$D53/$E53,0)) -> 0 | H53: =IF($C53+1>H$7,0,IF($D53>SUM($G53:G53),$D53/$E53,0)) -> 0 | I53: =IF($C53+1>I$7,0,IF($D53>SUM($G53:H53),$D53/$E53,0)) -> 0 | J53: =IF($C53+1>J$7,0,IF($D53>SUM($G53:I53),$D53/$E53,0)) -> 0 | K53: =IF($C53+1>K$7,0,IF($D53>SUM($G53:J53),$D53/$E53,0)) -> 0 | L53: =IF($C53+1>L$7,0,IF($D53>SUM($G53:K53),$D53/$E53,0)) -> 0 | M53: =IF($C53+1>M$7,0,IF($D53>SUM($G53:L53),$D53/$E53,0)) -> 0 | N53: =IF($C53+1>N$7,0,IF($D53>SUM($G53:M53),$D53/$E53,0)) -> 0 | O53: =IF($C53+1>O$7,0,IF($D53>SUM($G53:N53),$D53/$E53,0)) -> 0 | ... BN53: =IF($C53+1>BN$7,0,IF($D53>SUM($G53:BM53),$D53/$E53,0)) -> 0
... C100: 60 | D100: 0 | E100: =SAP_Leadsheet!$E$50 -> 0 | G100: =IF($C100+1>G$7,0,IF($D100>SUM(#REF!),$D100/$E100,0)) -> 0 | H100: =IF($C100+1>H$7,0,IF($D100>SUM($G100:G100),$D100/$E100,0)) -> 0 | I100: =IF($C100+1>I$7,0,IF($D100>SUM($G100:H100),$D100/$E100,0)) -> 0 | J100: =IF($C100+1>J$7,0,IF($D100>SUM($G100:I100),$D100/$E100,0)) -> 0 | K100: =IF($C100+1>K$7,0,IF($D100>SUM($G100:J100),$D100/$E100,0)) -> 0 | L100: =IF($C100+1>L$7,0,IF($D100>SUM($G100:K100),$D100/$E100,0)) -> 0 | M100: =IF($C100+1>M$7,0,IF($D100>SUM($G100:L100),$D100/$E100,0)) -> 0 | N100: =IF($C100+1>N$7,0,IF($D100>SUM($G100:M100),$D100/$E100,0)) -> 0 | O100: =IF($C100+1>O$7,0,IF($D100>SUM($G100:N100),$D100/$E100,0)) -> 0 | ... BN100: =IF($C100+1>BN$7,0,IF($D100>SUM($G100:BM100),$D100/$E100,0)) -> 0
D101: Ending Bal | G101: =SUM(G38:G40) -> 0 | H101: =SUM(H38:H40) -> 0 | I101: =SUM(I38:I40) -> 0 | J101: =SUM(J38:J40) -> 0 | K101: =SUM(K38:K40) -> 0 | L101: =SUM(L38:L40) -> 0 | M101: =SUM(M38:M40) -> 0 | N101: =SUM(N38:N40) -> 0 | ... BN101: =SUM(BN38:BN40) -> 0
C103: EMI Retail 0%
D104: # EMI | F104: # | G104: =IF(G7=SAP_Leadsheet!$E$56,1,IF(G7=SAP_Leadsheet!$E$56+SAP_Leadsheet!$E$61+2,2,IF(G7=SAP_Leadsheet!$E$56+SAP_Leadsheet!$E$61*2+4,3,IF(G7=SAP_Leadsheet!$E$56+SAP_Leadsheet!$E$61*3+6,4,IF(G7=SAP_Leadsheet!$E$56+SAP_Leadsheet!$E$61*4+8,5,0))))) -> 0 | H104: =IF(H7=SAP_Leadsheet!$E$56,1,IF(H7=SAP_Leadsheet!$E$56+SAP_Leadsheet!$E$61+2,2,IF(H7=SAP_Leadsheet!$E$56+SAP_Leadsheet!$E$61*2+4,3,IF(H7=SAP_Leadsheet!$E$56+SAP_Leadsheet!$E$61*3+6,4,IF(H7=SAP_Leadsheet!$E$56+SAP_Leadsheet!$E$61*4+8,5,0))))) -> 0 | I104: =IF(I7=SAP_Leadsheet!$E$56,1,IF(I7=SAP_Leadsheet!$E$56+SAP_Leadsheet!$E$61+2,2,IF(I7=SAP_Leadsheet!$E$56+SAP_Leadsheet!$E$61*2+4,3,IF(I7=SAP_Leadsheet!$E$56+SAP_Leadsheet!$E$61*3+6,4,IF(I7=SAP_Leadsheet!$E$56+SAP_Leadsheet!$E$61*4+8,5,0))))) -> 0 | J104: =IF(J7=SAP_Leadsheet!$E$56,1,IF(J7=SAP_Leadsheet!$E$56+SAP_Leadsheet!$E$61+2,2,IF(J7=SAP_Leadsheet!$E$56+SAP_Leadsheet!$E$61*2+4,3,IF(J7=SAP_Leadsheet!$E$56+SAP_Leadsheet!$E$61*3+6,4,IF(J7=SAP_Leadsheet!$E$56+SAP_Leadsheet!$E$61*4+8,5,0))))) -> 0 | K104: =IF(K7=SAP_Leadsheet!$E$56,1,IF(K7=SAP_Leadsheet!$E$56+SAP_Leadsheet!$E$61+2,2,IF(K7=SAP_Leadsheet!$E$56+SAP_Leadsheet!$E$61*2+4,3,IF(K7=SAP_Leadsheet!$E$56+SAP_Leadsheet!$E$61*3+6,4,IF(K7=SAP_Leadsheet!$E$56+SAP_Leadsheet!$E$61*4+8,5,0))))) -> 0 | L104: =IF(L7=SAP_Leadsheet!$E$56,1,IF(L7=SAP_Leadsheet!$E$56+SAP_Leadsheet!$E$61+2,2,IF(L7=SAP_Leadsheet!$E$56+SAP_Leadsheet!$E$61*2+4,3,IF(L7=SAP_Leadsheet!$E$56+SAP_Leadsheet!$E$61*3+6,4,IF(L7=SAP_Leadsheet!$E$56+SAP_Leadsheet!$E$61*4+8,5,0))))) -> 1 | M104: =IF(M7=SAP_Leadsheet!$E$56,1,IF(M7=SAP_Leadsheet!$E$56+SAP_Leadsheet!$E$61+2,2,IF(M7=SAP_Leadsheet!$E$56+SAP_Leadsheet!$E$61*2+4,3,IF(M7=SAP_Leadsheet!$E$56+SAP_Leadsheet!$E$61*3+6,4,IF(M7=SAP_Leadsheet!$E$56+SAP_Leadsheet!$E$61*4+8,5,0))))) -> 0 | N104: =IF(N7=SAP_Leadsheet!$E$56,1,IF(N7=SAP_Leadsheet!$E$56+SAP_Leadsheet!$E$61+2,2,IF(N7=SAP_Leadsheet!$E$56+SAP_Leadsheet!$E$61*2+4,3,IF(N7=SAP_Leadsheet!$E$56+SAP_Leadsheet!$E$61*3+6,4,IF(N7=SAP_Leadsheet!$E$56+SAP_Leadsheet!$E$61*4+8,5,0))))) -> 0 | ... BN104: =IF(BN7=SAP_Leadsheet!$E$56,1,IF(BN7=SAP_Leadsheet!$E$56+SAP_Leadsheet!$E$61+2,2,IF(BN7=SAP_Leadsheet!$E$56+SAP_Leadsheet!$E$61*2+4,3,IF(BN7=SAP_Leadsheet!$E$56+SAP_Leadsheet!$E$61*3+6,4,IF(BN7=SAP_Leadsheet!$E$56+SAP_Leadsheet!$E$61*4+8,5,0))))) -> 0
D105: Penetration | F105: % | G105: =IF(G104=0,0,SAP_Leadsheet!$E$57) -> 0 | H105: =IF(H104=0,0,SAP_Leadsheet!$E$57) -> 0 | I105: =IF(I104=0,0,SAP_Leadsheet!$E$57) -> 0 | J105: =IF(J104=0,0,SAP_Leadsheet!$E$57) -> 0 | K105: =IF(K104=0,0,SAP_Leadsheet!$E$57) -> 0 | L105: =IF(L104=0,0,SAP_Leadsheet!$E$57) -> 0.1 | M105: =IF(M104=0,0,SAP_Leadsheet!$E$57) -> 0 | N105: =IF(N104=0,0,SAP_Leadsheet!$E$57) -> 0 | ... BN105: =IF(BN104=0,0,SAP_Leadsheet!$E$57) -> 0
D106: Beginning Bal | G106: 0 | H106: =G169 -> 0 | I106: =H169 -> 0 | J106: =I169 -> 0 | K106: =J169 -> 0 | L106: =K169 -> 0 | M106: =L169 -> 0.7 | N106: =M169 -> 0.6 | O106: =N169 -> 0.5 | ... BN106: =BM169 -> 3.6082248e-16
D107: New Billing | G107: =IF(AND(SAP_Leadsheet!$C$9="EMI",G104<=SAP_Leadsheet!$E$58),G105*SAP_Leadsheet!$E$59,0) -> 0 | H107: =IF(AND(SAP_Leadsheet!$C$9="EMI",H104<=SAP_Leadsheet!$E$58),H105*SAP_Leadsheet!$E$59,0) -> 0 | I107: =IF(AND(SAP_Leadsheet!$C$9="EMI",I104<=SAP_Leadsheet!$E$58),I105*SAP_Leadsheet!$E$59,0) -> 0 | J107: =IF(AND(SAP_Leadsheet!$C$9="EMI",J104<=SAP_Leadsheet!$E$58),J105*SAP_Leadsheet!$E$59,0) -> 0 | K107: =IF(AND(SAP_Leadsheet!$C$9="EMI",K104<=SAP_Leadsheet!$E$58),K105*SAP_Leadsheet!$E$59,0) -> 0 | L107: =IF(AND(SAP_Leadsheet!$C$9="EMI",L104<=SAP_Leadsheet!$E$58),L105*SAP_Leadsheet!$E$59,0) -> 0.7 | M107: =IF(AND(SAP_Leadsheet!$C$9="EMI",M104<=SAP_Leadsheet!$E$58),M105*SAP_Leadsheet!$E$59,0) -> 0 | N107: =IF(AND(SAP_Leadsheet!$C$9="EMI",N104<=SAP_Leadsheet!$E$58),N105*SAP_Leadsheet!$E$59,0) -> 0 | ... BN107: =IF(AND(SAP_Leadsheet!$C$9="EMI",BN104<=SAP_Leadsheet!$E$58),BN105*SAP_Leadsheet!$E$59,0) -> 0
D108: Paid off | G108: =-SUM(G109:G168) -> 0 | H108: =-SUM(H109:H168) -> 0 | I108: =-SUM(I109:I168) -> 0 | J108: =-SUM(J109:J168) -> 0 | K108: =-SUM(K109:K168) -> 0 | L108: =-SUM(L109:L168) -> 0 | M108: =-SUM(M109:M168) -> -0.1 | N108: =-SUM(N109:N168) -> -0.1 | ... BN108: =-SUM(BN109:BN168) -> 0
C109: {=TRANSPOSE(G7:BN7)} -> 1 | D109: {=TRANSPOSE(G107:BN107)} -> 0 | E109: =SAP_Leadsheet!$E$61 -> 7 | G109: =IF($C109+1>G$7,0,IF($D109>SUM(#REF!),$D109/$E109,0)) -> 0 | H109: =IF($C109+1>H$7,0,IF($D109>SUM($G109:G109),$D109/$E109,0)) -> 0 | I109: =IF($C109+1>I$7,0,IF($D109>SUM($G109:H109),$D109/$E109,0)) -> 0 | J109: =IF($C109+1>J$7,0,IF($D109>SUM($G109:I109),$D109/$E109,0)) -> 0 | K109: =IF($C109+1>K$7,0,IF($D109>SUM($G109:J109),$D109/$E109,0)) -> 0 | L109: =IF($C109+1>L$7,0,IF($D109>SUM($G109:K109),$D109/$E109,0)) -> 0 | M109: =IF($C109+1>M$7,0,IF($D109>SUM($G109:L109),$D109/$E109,0)) -> 0 | N109: =IF($C109+1>N$7,0,IF($D109>SUM($G109:M109),$D109/$E109,0)) -> 0 | O109: =IF($C109+1>O$7,0,IF($D109>SUM($G109:N109),$D109/$E109,0)) -> 0 | ... BN109: =IF($C109+1>BN$7,0,IF($D109>SUM($G109:BM109),$D109/$E109,0)) -> 0
C110: 2 | D110: 0 | E110: =SAP_Leadsheet!$E$61 -> 7 | G110: =IF($C110+1>G$7,0,IF($D110>SUM(#REF!),$D110/$E110,0)) -> 0 | H110: =IF($C110+1>H$7,0,IF($D110>SUM($G110:G110),$D110/$E110,0)) -> 0 | I110: =IF($C110+1>I$7,0,IF($D110>SUM($G110:H110),$D110/$E110,0)) -> 0 | J110: =IF($C110+1>J$7,0,IF($D110>SUM($G110:I110),$D110/$E110,0)) -> 0 | K110: =IF($C110+1>K$7,0,IF($D110>SUM($G110:J110),$D110/$E110,0)) -> 0 | L110: =IF($C110+1>L$7,0,IF($D110>SUM($G110:K110),$D110/$E110,0)) -> 0 | M110: =IF($C110+1>M$7,0,IF($D110>SUM($G110:L110),$D110/$E110,0)) -> 0 | N110: =IF($C110+1>N$7,0,IF($D110>SUM($G110:M110),$D110/$E110,0)) -> 0 | O110: =IF($C110+1>O$7,0,IF($D110>SUM($G110:N110),$D110/$E110,0)) -> 0 | ... BN110: =IF($C110+1>BN$7,0,IF($D110>SUM($G110:BM110),$D110/$E110,0)) -> 0
C111: 3 | D111: 0 | E111: =SAP_Leadsheet!$E$61 -> 7 | G111: =IF($C111+1>G$7,0,IF($D111>SUM(#REF!),$D111/$E111,0)) -> 0 | H111: =IF($C111+1>H$7,0,IF($D111>SUM($G111:G111),$D111/$E111,0)) -> 0 | I111: =IF($C111+1>I$7,0,IF($D111>SUM($G111:H111),$D111/$E111,0)) -> 0 | J111: =IF($C111+1>J$7,0,IF($D111>SUM($G111:I111),$D111/$E111,0)) -> 0 | K111: =IF($C111+1>K$7,0,IF($D111>SUM($G111:J111),$D111/$E111,0)) -> 0 | L111: =IF($C111+1>L$7,0,IF($D111>SUM($G111:K111),$D111/$E111,0)) -> 0 | M111: =IF($C111+1>M$7,0,IF($D111>SUM($G111:L111),$D111/$E111,0)) -> 0 | N111: =IF($C111+1>N$7,0,IF($D111>SUM($G111:M111),$D111/$E111,0)) -> 0 | O111: =IF($C111+1>O$7,0,IF($D111>SUM($G111:N111),$D111/$E111,0)) -> 0 | ... BN111: =IF($C111+1>BN$7,0,IF($D111>SUM($G111:BM111),$D111/$E111,0)) -> 0
C112: 4 | D112: 0 | E112: =SAP_Leadsheet!$E$61 -> 7 | G112: =IF($C112+1>G$7,0,IF($D112>SUM(#REF!),$D112/$E112,0)) -> 0 | H112: =IF($C112+1>H$7,0,IF($D112>SUM($G112:G112),$D112/$E112,0)) -> 0 | I112: =IF($C112+1>I$7,0,IF($D112>SUM($G112:H112),$D112/$E112,0)) -> 0 | J112: =IF($C112+1>J$7,0,IF($D112>SUM($G112:I112),$D112/$E112,0)) -> 0 | K112: =IF($C112+1>K$7,0,IF($D112>SUM($G112:J112),$D112/$E112,0)) -> 0 | L112: =IF($C112+1>L$7,0,IF($D112>SUM($G112:K112),$D112/$E112,0)) -> 0 | M112: =IF($C112+1>M$7,0,IF($D112>SUM($G112:L112),$D112/$E112,0)) -> 0 | N112: =IF($C112+1>N$7,0,IF($D112>SUM($G112:M112),$D112/$E112,0)) -> 0 | O112: =IF($C112+1>O$7,0,IF($D112>SUM($G112:N112),$D112/$E112,0)) -> 0 | ... BN112: =IF($C112+1>BN$7,0,IF($D112>SUM($G112:BM112),$D112/$E112,0)) -> 0
C113: 5 | D113: 0 | E113: =SAP_Leadsheet!$E$61 -> 7 | G113: =IF($C113+1>G$7,0,IF($D113>SUM(#REF!),$D113/$E113,0)) -> 0 | H113: =IF($C113+1>H$7,0,IF($D113>SUM($G113:G113),$D113/$E113,0)) -> 0 | I113: =IF($C113+1>I$7,0,IF($D113>SUM($G113:H113),$D113/$E113,0)) -> 0 | J113: =IF($C113+1>J$7,0,IF($D113>SUM($G113:I113),$D113/$E113,0)) -> 0 | K113: =IF($C113+1>K$7,0,IF($D113>SUM($G113:J113),$D113/$E113,0)) -> 0 | L113: =IF($C113+1>L$7,0,IF($D113>SUM($G113:K113),$D113/$E113,0)) -> 0 | M113: =IF($C113+1>M$7,0,IF($D113>SUM($G113:L113),$D113/$E113,0)) -> 0 | N113: =IF($C113+1>N$7,0,IF($D113>SUM($G113:M113),$D113/$E113,0)) -> 0 | O113: =IF($C113+1>O$7,0,IF($D113>SUM($G113:N113),$D113/$E113,0)) -> 0 | ... BN113: =IF($C113+1>BN$7,0,IF($D113>SUM($G113:BM113),$D113/$E113,0)) -> 0
C114: 6 | D114: 0.7 | E114: =SAP_Leadsheet!$E$61 -> 7 | G114: =IF($C114+1>G$7,0,IF($D114>SUM(#REF!),$D114/$E114,0)) -> 0 | H114: =IF($C114+1>H$7,0,IF($D114>SUM($G114:G114),$D114/$E114,0)) -> 0 | I114: =IF($C114+1>I$7,0,IF($D114>SUM($G114:H114),$D114/$E114,0)) -> 0 | J114: =IF($C114+1>J$7,0,IF($D114>SUM($G114:I114),$D114/$E114,0)) -> 0 | K114: =IF($C114+1>K$7,0,IF($D114>SUM($G114:J114),$D114/$E114,0)) -> 0 | L114: =IF($C114+1>L$7,0,IF($D114>SUM($G114:K114),$D114/$E114,0)) -> 0 | M114: =IF($C114+1>M$7,0,IF($D114>SUM($G114:L114),$D114/$E114,0)) -> 0.1 | N114: =IF($C114+1>N$7,0,IF($D114>SUM($G114:M114),$D114/$E114,0)) -> 0.1 | O114: =IF($C114+1>O$7,0,IF($D114>SUM($G114:N114),$D114/$E114,0)) -> 0.1 | ... BN114: =IF($C114+1>BN$7,0,IF($D114>SUM($G114:BM114),$D114/$E114,0)) -> 0
C115: 7 | D115: 0 | E115: =SAP_Leadsheet!$E$61 -> 7 | G115: =IF($C115+1>G$7,0,IF($D115>SUM(#REF!),$D115/$E115,0)) -> 0 | H115: =IF($C115+1>H$7,0,IF($D115>SUM($G115:G115),$D115/$E115,0)) -> 0 | I115: =IF($C115+1>I$7,0,IF($D115>SUM($G115:H115),$D115/$E115,0)) -> 0 | J115: =IF($C115+1>J$7,0,IF($D115>SUM($G115:I115),$D115/$E115,0)) -> 0 | K115: =IF($C115+1>K$7,0,IF($D115>SUM($G115:J115),$D115/$E115,0)) -> 0 | L115: =IF($C115+1>L$7,0,IF($D115>SUM($G115:K115),$D115/$E115,0)) -> 0 | M115: =IF($C115+1>M$7,0,IF($D115>SUM($G115:L115),$D115/$E115,0)) -> 0 | N115: =IF($C115+1>N$7,0,IF($D115>SUM($G115:M115),$D115/$E115,0)) -> 0 | O115: =IF($C115+1>O$7,0,IF($D115>SUM($G115:N115),$D115/$E115,0)) -> 0 | ... BN115: =IF($C115+1>BN$7,0,IF($D115>SUM($G115:BM115),$D115/$E115,0)) -> 0
C116: 8 | D116: 0 | E116: =SAP_Leadsheet!$E$61 -> 7 | G116: =IF($C116+1>G$7,0,IF($D116>SUM(#REF!),$D116/$E116,0)) -> 0 | H116: =IF($C116+1>H$7,0,IF($D116>SUM($G116:G116),$D116/$E116,0)) -> 0 | I116: =IF($C116+1>I$7,0,IF($D116>SUM($G116:H116),$D116/$E116,0)) -> 0 | J116: =IF($C116+1>J$7,0,IF($D116>SUM($G116:I116),$D116/$E116,0)) -> 0 | K116: =IF($C116+1>K$7,0,IF($D116>SUM($G116:J116),$D116/$E116,0)) -> 0 | L116: =IF($C116+1>L$7,0,IF($D116>SUM($G116:K116),$D116/$E116,0)) -> 0 | M116: =IF($C116+1>M$7,0,IF($D116>SUM($G116:L116),$D116/$E116,0)) -> 0 | N116: =IF($C116+1>N$7,0,IF($D116>SUM($G116:M116),$D116/$E116,0)) -> 0 | O116: =IF($C116+1>O$7,0,IF($D116>SUM($G116:N116),$D116/$E116,0)) -> 0 | ... BN116: =IF($C116+1>BN$7,0,IF($D116>SUM($G116:BM116),$D116/$E116,0)) -> 0
C117: 9 | D117: 0 | E117: =SAP_Leadsheet!$E$61 -> 7 | G117: =IF($C117+1>G$7,0,IF($D117>SUM(#REF!),$D117/$E117,0)) -> 0 | H117: =IF($C117+1>H$7,0,IF($D117>SUM($G117:G117),$D117/$E117,0)) -> 0 | I117: =IF($C117+1>I$7,0,IF($D117>SUM($G117:H117),$D117/$E117,0)) -> 0 | J117: =IF($C117+1>J$7,0,IF($D117>SUM($G117:I117),$D117/$E117,0)) -> 0 | K117: =IF($C117+1>K$7,0,IF($D117>SUM($G117:J117),$D117/$E117,0)) -> 0 | L117: =IF($C117+1>L$7,0,IF($D117>SUM($G117:K117),$D117/$E117,0)) -> 0 | M117: =IF($C117+1>M$7,0,IF($D117>SUM($G117:L117),$D117/$E117,0)) -> 0 | N117: =IF($C117+1>N$7,0,IF($D117>SUM($G117:M117),$D117/$E117,0)) -> 0 | O117: =IF($C117+1>O$7,0,IF($D117>SUM($G117:N117),$D117/$E117,0)) -> 0 | ... BN117: =IF($C117+1>BN$7,0,IF($D117>SUM($G117:BM117),$D117/$E117,0)) -> 0
C118: 10 | D118: 0 | E118: =SAP_Leadsheet!$E$61 -> 7 | G118: =IF($C118+1>G$7,0,IF($D118>SUM(#REF!),$D118/$E118,0)) -> 0 | H118: =IF($C118+1>H$7,0,IF($D118>SUM($G118:G118),$D118/$E118,0)) -> 0 | I118: =IF($C118+1>I$7,0,IF($D118>SUM($G118:H118),$D118/$E118,0)) -> 0 | J118: =IF($C118+1>J$7,0,IF($D118>SUM($G118:I118),$D118/$E118,0)) -> 0 | K118: =IF($C118+1>K$7,0,IF($D118>SUM($G118:J118),$D118/$E118,0)) -> 0 | L118: =IF($C118+1>L$7,0,IF($D118>SUM($G118:K118),$D118/$E118,0)) -> 0 | M118: =IF($C118+1>M$7,0,IF($D118>SUM($G118:L118),$D118/$E118,0)) -> 0 | N118: =IF($C118+1>N$7,0,IF($D118>SUM($G118:M118),$D118/$E118,0)) -> 0 | O118: =IF($C118+1>O$7,0,IF($D118>SUM($G118:N118),$D118/$E118,0)) -> 0 | ... BN118: =IF($C118+1>BN$7,0,IF($D118>SUM($G118:BM118),$D118/$E118,0)) -> 0
C119: 11 | D119: 0 | E119: =SAP_Leadsheet!$E$61 -> 7 | G119: =IF($C119+1>G$7,0,IF($D119>SUM(#REF!),$D119/$E119,0)) -> 0 | H119: =IF($C119+1>H$7,0,IF($D119>SUM($G119:G119),$D119/$E119,0)) -> 0 | I119: =IF($C119+1>I$7,0,IF($D119>SUM($G119:H119),$D119/$E119,0)) -> 0 | J119: =IF($C119+1>J$7,0,IF($D119>SUM($G119:I119),$D119/$E119,0)) -> 0 | K119: =IF($C119+1>K$7,0,IF($D119>SUM($G119:J119),$D119/$E119,0)) -> 0 | L119: =IF($C119+1>L$7,0,IF($D119>SUM($G119:K119),$D119/$E119,0)) -> 0 | M119: =IF($C119+1>M$7,0,IF($D119>SUM($G119:L119),$D119/$E119,0)) -> 0 | N119: =IF($C119+1>N$7,0,IF($D119>SUM($G119:M119),$D119/$E119,0)) -> 0 | O119: =IF($C119+1>O$7,0,IF($D119>SUM($G119:N119),$D119/$E119,0)) -> 0 | ... BN119: =IF($C119+1>BN$7,0,IF($D119>SUM($G119:BM119),$D119/$E119,0)) -> 0
C120: 12 | D120: 0 | E120: =SAP_Leadsheet!$E$61 -> 7 | G120: =IF($C120+1>G$7,0,IF($D120>SUM(#REF!),$D120/$E120,0)) -> 0 | H120: =IF($C120+1>H$7,0,IF($D120>SUM($G120:G120),$D120/$E120,0)) -> 0 | I120: =IF($C120+1>I$7,0,IF($D120>SUM($G120:H120),$D120/$E120,0)) -> 0 | J120: =IF($C120+1>J$7,0,IF($D120>SUM($G120:I120),$D120/$E120,0)) -> 0 | K120: =IF($C120+1>K$7,0,IF($D120>SUM($G120:J120),$D120/$E120,0)) -> 0 | L120: =IF($C120+1>L$7,0,IF($D120>SUM($G120:K120),$D120/$E120,0)) -> 0 | M120: =IF($C120+1>M$7,0,IF($D120>SUM($G120:L120),$D120/$E120,0)) -> 0 | N120: =IF($C120+1>N$7,0,IF($D120>SUM($G120:M120),$D120/$E120,0)) -> 0 | O120: =IF($C120+1>O$7,0,IF($D120>SUM($G120:N120),$D120/$E120,0)) -> 0 | ... BN120: =IF($C120+1>BN$7,0,IF($D120>SUM($G120:BM120),$D120/$E120,0)) -> 0
C121: 13 | D121: 0 | E121: =SAP_Leadsheet!$E$61 -> 7 | G121: =IF($C121+1>G$7,0,IF($D121>SUM(#REF!),$D121/$E121,0)) -> 0 | H121: =IF($C121+1>H$7,0,IF($D121>SUM($G121:G121),$D121/$E121,0)) -> 0 | I121: =IF($C121+1>I$7,0,IF($D121>SUM($G121:H121),$D121/$E121,0)) -> 0 | J121: =IF($C121+1>J$7,0,IF($D121>SUM($G121:I121),$D121/$E121,0)) -> 0 | K121: =IF($C121+1>K$7,0,IF($D121>SUM($G121:J121),$D121/$E121,0)) -> 0 | L121: =IF($C121+1>L$7,0,IF($D121>SUM($G121:K121),$D121/$E121,0)) -> 0 | M121: =IF($C121+1>M$7,0,IF($D121>SUM($G121:L121),$D121/$E121,0)) -> 0 | N121: =IF($C121+1>N$7,0,IF($D121>SUM($G121:M121),$D121/$E121,0)) -> 0 | O121: =IF($C121+1>O$7,0,IF($D121>SUM($G121:N121),$D121/$E121,0)) -> 0 | ... BN121: =IF($C121+1>BN$7,0,IF($D121>SUM($G121:BM121),$D121/$E121,0)) -> 0
... C168: 60 | D168: 0 | E168: =SAP_Leadsheet!$E$61 -> 7 | G168: =IF($C168+1>G$7,0,IF($D168>SUM(#REF!),$D168/$E168,0)) -> 0 | H168: =IF($C168+1>H$7,0,IF($D168>SUM($G168:G168),$D168/$E168,0)) -> 0 | I168: =IF($C168+1>I$7,0,IF($D168>SUM($G168:H168),$D168/$E168,0)) -> 0 | J168: =IF($C168+1>J$7,0,IF($D168>SUM($G168:I168),$D168/$E168,0)) -> 0 | K168: =IF($C168+1>K$7,0,IF($D168>SUM($G168:J168),$D168/$E168,0)) -> 0 | L168: =IF($C168+1>L$7,0,IF($D168>SUM($G168:K168),$D168/$E168,0)) -> 0 | M168: =IF($C168+1>M$7,0,IF($D168>SUM($G168:L168),$D168/$E168,0)) -> 0 | N168: =IF($C168+1>N$7,0,IF($D168>SUM($G168:M168),$D168/$E168,0)) -> 0 | O168: =IF($C168+1>O$7,0,IF($D168>SUM($G168:N168),$D168/$E168,0)) -> 0 | ... BN168: =IF($C168+1>BN$7,0,IF($D168>SUM($G168:BM168),$D168/$E168,0)) -> 0
D169: Ending Bal | G169: =G106+G107+G108 -> 0 | H169: =H106+H107+H108 -> 0 | I169: =I106+I107+I108 -> 0 | J169: =J106+J107+J108 -> 0 | K169: =K106+K107+K108 -> 0 | L169: =L106+L107+L108 -> 0.7 | M169: =M106+M107+M108 -> 0.6 | N169: =N106+N107+N108 -> 0.5 | ... BN169: =BN106+BN107+BN108 -> 3.6082248e-16
B171: ENR | D171: Total bank | F171: mVND | G171: =G28+G35 -> 0.45732039 | H171: =H28+H35 -> 0.83586421 | I171: =I28+I35 -> 1.0274185 | J171: =J28+J35 -> 1.077777 | K171: =K28+K35 -> 1.0546632 | L171: =L28+L35 -> 1.0047275 | M171: =M28+M35 -> 0.9273984 | N171: =N28+N35 -> 0.87367686 | ... BN171: =BN28+BN35 -> 0.93106307
D172: Outstanding balance | F172: mVND | G172: {=IF(G7>SAP_Leadsheet!$E$21,0,_xlfn.IFS(SAP_Leadsheet!$C$6="DPD360+",SUM(SAP_Spreadsheet!G181:G194),SAP_Leadsheet!$C$6="DPD180+",SUM(SAP_Spreadsheet!G181:G188)))} -> 0.45732039 | H172: {=IF(H7>SAP_Leadsheet!$E$21,0,_xlfn.IFS(SAP_Leadsheet!$C$6="DPD360+",SUM(SAP_Spreadsheet!H181:H194),SAP_Leadsheet!$C$6="DPD180+",SUM(SAP_Spreadsheet!H181:H188)))} -> 0.83586421 | I172: {=IF(I7>SAP_Leadsheet!$E$21,0,_xlfn.IFS(SAP_Leadsheet!$C$6="DPD360+",SUM(SAP_Spreadsheet!I181:I194),SAP_Leadsheet!$C$6="DPD180+",SUM(SAP_Spreadsheet!I181:I188)))} -> 1.0274185 | J172: {=IF(J7>SAP_Leadsheet!$E$21,0,_xlfn.IFS(SAP_Leadsheet!$C$6="DPD360+",SUM(SAP_Spreadsheet!J181:J194),SAP_Leadsheet!$C$6="DPD180+",SUM(SAP_Spreadsheet!J181:J188)))} -> 1.077777 | K172: {=IF(K7>SAP_Leadsheet!$E$21,0,_xlfn.IFS(SAP_Leadsheet!$C$6="DPD360+",SUM(SAP_Spreadsheet!K181:K194),SAP_Leadsheet!$C$6="DPD180+",SUM(SAP_Spreadsheet!K181:K188)))} -> 1.0546632 | L172: {=IF(L7>SAP_Leadsheet!$E$21,0,_xlfn.IFS(SAP_Leadsheet!$C$6="DPD360+",SUM(SAP_Spreadsheet!L181:L194),SAP_Leadsheet!$C$6="DPD180+",SUM(SAP_Spreadsheet!L181:L188)))} -> 1.0047275 | M172: {=IF(M7>SAP_Leadsheet!$E$21,0,_xlfn.IFS(SAP_Leadsheet!$C$6="DPD360+",SUM(SAP_Spreadsheet!M181:M194),SAP_Leadsheet!$C$6="DPD180+",SUM(SAP_Spreadsheet!M181:M188)))} -> 0.9273984 | N172: {=IF(N7>SAP_Leadsheet!$E$21,0,_xlfn.IFS(SAP_Leadsheet!$C$6="DPD360+",SUM(SAP_Spreadsheet!N181:N194),SAP_Leadsheet!$C$6="DPD180+",SUM(SAP_Spreadsheet!N181:N188)))} -> 0.87367686 | ... BN172: {=IF(BN7>SAP_Leadsheet!$E$21,0,_xlfn.IFS(SAP_Leadsheet!$C$6="DPD360+",SUM(SAP_Spreadsheet!BN181:BN194),SAP_Leadsheet!$C$6="DPD180+",SUM(SAP_Spreadsheet!BN181:BN188)))} -> 0.22687234
D173: Writeoff balance | F173: mVND | G173: =G171-G172 -> 0 | H173: =H171-H172 -> 0 | I173: =I171-I172 -> 0 | J173: =J171-J172 -> 0 | K173: =K171-K172 -> 0 | L173: =L171-L172 -> 0 | M173: =M171-M172 -> 0 | N173: =N171-N172 -> 0 | ... BN173: =BN171-BN172 -> 0.70419073
D174: Outstanding Bal/TB | F174: mVND | G174: =IFERROR(G172/G171,0) -> 1 | H174: =IFERROR(H172/H171,0) -> 1 | I174: =IFERROR(I172/I171,0) -> 1 | J174: =IFERROR(J172/J171,0) -> 1 | K174: =IFERROR(K172/K171,0) -> 1 | L174: =IFERROR(L172/L171,0) -> 1 | M174: =IFERROR(M172/M171,0) -> 1 | N174: =IFERROR(N172/N171,0) -> 1 | ... BN174: =IFERROR(BN172/BN171,0) -> 0.24367021
D176: ENR TB | F176: mVND | G176: =G171 -> 0.45732039 | H176: =H171 -> 0.83586421 | I176: =I171 -> 1.0274185 | J176: =J171 -> 1.077777 | K176: =K171 -> 1.0546632 | L176: =L171 -> 1.0047275 | M176: =M171 -> 0.9273984 | N176: =N171 -> 0.87367686 | ... BN176: =BN171 -> 0.93106307
D177: ENR GB | F177: mVND | G177: =IF(G7>SAP_Leadsheet!$E$21,0,SUM(G181:G184)) -> 0.45732039 | H177: =IF(H7>SAP_Leadsheet!$E$21,0,SUM(H181:H184)) -> 0.83586421 | I177: =IF(I7>SAP_Leadsheet!$E$21,0,SUM(I181:I184)) -> 1.0274185 | J177: =IF(J7>SAP_Leadsheet!$E$21,0,SUM(J181:J184)) -> 1.077777 | K177: =IF(K7>SAP_Leadsheet!$E$21,0,SUM(K181:K184)) -> 1.0294419 | L177: =IF(L7>SAP_Leadsheet!$E$21,0,SUM(L181:L184)) -> 0.93542623 | M177: =IF(M7>SAP_Leadsheet!$E$21,0,SUM(M181:M184)) -> 0.80683332 | N177: =IF(N7>SAP_Leadsheet!$E$21,0,SUM(N181:N184)) -> 0.70268443 | ... BN177: =IF(BN7>SAP_Leadsheet!$E$21,0,SUM(BN181:BN184)) -> 0.21256466
D178: ENR BB | F178: mVND | G178: =IF(G7>SAP_Leadsheet!$E$21,0,G176-G177) -> 0 | H178: =IF(H7>SAP_Leadsheet!$E$21,0,H176-H177) -> 0 | I178: =IF(I7>SAP_Leadsheet!$E$21,0,I176-I177) -> 0 | J178: =IF(J7>SAP_Leadsheet!$E$21,0,J176-J177) -> 0 | K178: =IF(K7>SAP_Leadsheet!$E$21,0,K176-K177) -> 0.025221328 | L178: =IF(L7>SAP_Leadsheet!$E$21,0,L176-L177) -> 0.069301266 | M178: =IF(M7>SAP_Leadsheet!$E$21,0,M176-M177) -> 0.12056508 | N178: =IF(N7>SAP_Leadsheet!$E$21,0,N176-N177) -> 0.17099243 | ... BN178: =IF(BN7>SAP_Leadsheet!$E$21,0,BN176-BN177) -> 0.71849842
C181: Bucket | D181: B00 | F181: mVND | G181: =IF(G7>SAP_Leadsheet!$E$21,0,MAX(G171-SUM(G182:G195),0)) -> 0.45732039 | H181: =IF(H7>SAP_Leadsheet!$E$21,0,MAX(H171-SUM(H182:H195),0)) -> 0.80613838 | I181: =IF(I7>SAP_Leadsheet!$E$21,0,MAX(I171-SUM(I182:I195),0)) -> 0.94826625 | J181: =IF(J7>SAP_Leadsheet!$E$21,0,MAX(J171-SUM(J182:J195),0)) -> 0.94329752 | K181: =IF(K7>SAP_Leadsheet!$E$21,0,MAX(K171-SUM(K182:K195),0)) -> 0.86738123 | L181: =IF(L7>SAP_Leadsheet!$E$21,0,MAX(L171-SUM(L182:L195),0)) -> 0.77060891 | M181: =IF(M7>SAP_Leadsheet!$E$21,0,MAX(M171-SUM(M182:M195),0)) -> 0.65302635 | N181: =IF(N7>SAP_Leadsheet!$E$21,0,MAX(N171-SUM(N182:N195),0)) -> 0.56644497 | ... BZ181: =IF(BZ7>SAP_Leadsheet!$E$21,0,MAX(BZ171-SUM(BZ182:BZ195),0)) -> 0
D182: B01 | E182: 1 | F182: mVND | H182: =G181*OFFSET(SAP_Leadsheet!$D$102,SAP_Spreadsheet!$E182,SAP_Spreadsheet!H$6) -> 0.029725825 | I182: =H181*OFFSET(SAP_Leadsheet!$D$102,SAP_Spreadsheet!$E182,SAP_Spreadsheet!I$6) -> 0.052398995 | J182: =I181*OFFSET(SAP_Leadsheet!$D$102,SAP_Spreadsheet!$E182,SAP_Spreadsheet!J$6) -> 0.061637306 | K182: =J181*OFFSET(SAP_Leadsheet!$D$102,SAP_Spreadsheet!$E182,SAP_Spreadsheet!K$6) -> 0.061314339 | L182: =K181*OFFSET(SAP_Leadsheet!$D$102,SAP_Spreadsheet!$E182,SAP_Spreadsheet!L$6) -> 0.05637978 | M182: =L181*OFFSET(SAP_Leadsheet!$D$102,SAP_Spreadsheet!$E182,SAP_Spreadsheet!M$6) -> 0.050089579 | N182: =M181*OFFSET(SAP_Leadsheet!$D$102,SAP_Spreadsheet!$E182,SAP_Spreadsheet!N$6) -> 0.042446713 | O182: =N181*OFFSET(SAP_Leadsheet!$D$102,SAP_Spreadsheet!$E182,SAP_Spreadsheet!O$6) -> 0.036818923 | ... BN182: =BM181*OFFSET(SAP_Leadsheet!$D$102,SAP_Spreadsheet!$E182,SAP_Spreadsheet!BN$6) -> 0.0045841384 | BO182: =BN181*OFFSET(SAP_Leadsheet!$D$102,SAP_Spreadsheet!$E182,SAP_Spreadsheet!BC$6) -> 0.0044140502 | BP182: =BO181*OFFSET(SAP_Leadsheet!$D$102,SAP_Spreadsheet!$E182,SAP_Spreadsheet!BD$6) -> 0 | BQ182: =BP181*OFFSET(SAP_Leadsheet!$D$102,SAP_Spreadsheet!$E182,SAP_Spreadsheet!BE$6) -> 0 | BR182: =BQ181*OFFSET(SAP_Leadsheet!$D$102,SAP_Spreadsheet!$E182,SAP_Spreadsheet!BF$6) -> 0 | BS182: =BR181*OFFSET(SAP_Leadsheet!$D$102,SAP_Spreadsheet!$E182,SAP_Spreadsheet!BG$6) -> 0 | BT182: =BS181*OFFSET(SAP_Leadsheet!$D$102,SAP_Spreadsheet!$E182,SAP_Spreadsheet!BH$6) -> 0 | BU182: =BT181*OFFSET(SAP_Leadsheet!$D$102,SAP_Spreadsheet!$E182,SAP_Spreadsheet!BI$6) -> 0 | BV182: =BU181*OFFSET(SAP_Leadsheet!$D$102,SAP_Spreadsheet!$E182,SAP_Spreadsheet!BJ$6) -> 0 | ... BZ182: =BY181*OFFSET(SAP_Leadsheet!$D$102,SAP_Spreadsheet!$E182,SAP_Spreadsheet!BN$6) -> 0
D183: B02 | E183: 2 | F183: mVND | H183: =G182*OFFSET(SAP_Leadsheet!$D$102,SAP_Spreadsheet!$E183,SAP_Spreadsheet!H$6) -> 0 | I183: =H182*OFFSET(SAP_Leadsheet!$D$102,SAP_Spreadsheet!$E183,SAP_Spreadsheet!I$6) -> 0.026753243 | J183: =I182*OFFSET(SAP_Leadsheet!$D$102,SAP_Spreadsheet!$E183,SAP_Spreadsheet!J$6) -> 0.047159096 | K183: =J182*OFFSET(SAP_Leadsheet!$D$102,SAP_Spreadsheet!$E183,SAP_Spreadsheet!K$6) -> 0.055473575 | L183: =K182*OFFSET(SAP_Leadsheet!$D$102,SAP_Spreadsheet!$E183,SAP_Spreadsheet!L$6) -> 0.055182905 | M183: =L182*OFFSET(SAP_Leadsheet!$D$102,SAP_Spreadsheet!$E183,SAP_Spreadsheet!M$6) -> 0.050741802 | N183: =M182*OFFSET(SAP_Leadsheet!$D$102,SAP_Spreadsheet!$E183,SAP_Spreadsheet!N$6) -> 0.045080621 | O183: =N182*OFFSET(SAP_Leadsheet!$D$102,SAP_Spreadsheet!$E183,SAP_Spreadsheet!O$6) -> 0.038202041 | ... BN183: =BM182*OFFSET(SAP_Leadsheet!$D$102,SAP_Spreadsheet!$E183,SAP_Spreadsheet!BN$6) -> 0.0038018719 | BO183: =BN182*OFFSET(SAP_Leadsheet!$D$102,SAP_Spreadsheet!$E183,SAP_Spreadsheet!BC$6) -> 0.0036673107 | BP183: =BO182*OFFSET(SAP_Leadsheet!$D$102,SAP_Spreadsheet!$E183,SAP_Spreadsheet!BD$6) -> 0.0035312401 | BQ183: =BP182*OFFSET(SAP_Leadsheet!$D$102,SAP_Spreadsheet!$E183,SAP_Spreadsheet!BE$6) -> 0 | BR183: =BQ182*OFFSET(SAP_Leadsheet!$D$102,SAP_Spreadsheet!$E183,SAP_Spreadsheet!BF$6) -> 0 | BS183: =BR182*OFFSET(SAP_Leadsheet!$D$102,SAP_Spreadsheet!$E183,SAP_Spreadsheet!BG$6) -> 0 | BT183: =BS182*OFFSET(SAP_Leadsheet!$D$102,SAP_Spreadsheet!$E183,SAP_Spreadsheet!BH$6) -> 0 | BU183: =BT182*OFFSET(SAP_Leadsheet!$D$102,SAP_Spreadsheet!$E183,SAP_Spreadsheet!BI$6) -> 0 | BV183: =BU182*OFFSET(SAP_Leadsheet!$D$102,SAP_Spreadsheet!$E183,SAP_Spreadsheet!BJ$6) -> 0 | ... BZ183: =BY182*OFFSET(SAP_Leadsheet!$D$102,SAP_Spreadsheet!$E183,SAP_Spreadsheet!BN$6) -> 0
D184: B03 | E184: 3 | F184: mVND | H184: =G183*OFFSET(SAP_Leadsheet!$D$102,SAP_Spreadsheet!$E184,SAP_Spreadsheet!H$6) -> 0 | I184: =H183*OFFSET(SAP_Leadsheet!$D$102,SAP_Spreadsheet!$E184,SAP_Spreadsheet!I$6) -> 0 | J184: =I183*OFFSET(SAP_Leadsheet!$D$102,SAP_Spreadsheet!$E184,SAP_Spreadsheet!J$6) -> 0.025683113 | K184: =J183*OFFSET(SAP_Leadsheet!$D$102,SAP_Spreadsheet!$E184,SAP_Spreadsheet!K$6) -> 0.045272732 | L184: =K183*OFFSET(SAP_Leadsheet!$D$102,SAP_Spreadsheet!$E184,SAP_Spreadsheet!L$6) -> 0.053254632 | M184: =L183*OFFSET(SAP_Leadsheet!$D$102,SAP_Spreadsheet!$E184,SAP_Spreadsheet!M$6) -> 0.052975588 | N184: =M183*OFFSET(SAP_Leadsheet!$D$102,SAP_Spreadsheet!$E184,SAP_Spreadsheet!N$6) -> 0.04871213 | O184: =N183*OFFSET(SAP_Leadsheet!$D$102,SAP_Spreadsheet!$E184,SAP_Spreadsheet!O$6) -> 0.043277396 | ... BN184: =BM183*OFFSET(SAP_Leadsheet!$D$102,SAP_Spreadsheet!$E184,SAP_Spreadsheet!BN$6) -> 0.0035400042 | BO184: =BN183*OFFSET(SAP_Leadsheet!$D$102,SAP_Spreadsheet!$E184,SAP_Spreadsheet!BC$6) -> 0.0034216847 | BP184: =BO183*OFFSET(SAP_Leadsheet!$D$102,SAP_Spreadsheet!$E184,SAP_Spreadsheet!BD$6) -> 0.0033005796 | BQ184: =BP183*OFFSET(SAP_Leadsheet!$D$102,SAP_Spreadsheet!$E184,SAP_Spreadsheet!BE$6) -> 0.0031781161 | BR184: =BQ183*OFFSET(SAP_Leadsheet!$D$102,SAP_Spreadsheet!$E184,SAP_Spreadsheet!BF$6) -> 0 | BS184: =BR183*OFFSET(SAP_Leadsheet!$D$102,SAP_Spreadsheet!$E184,SAP_Spreadsheet!BG$6) -> 0 | BT184: =BS183*OFFSET(SAP_Leadsheet!$D$102,SAP_Spreadsheet!$E184,SAP_Spreadsheet!BH$6) -> 0 | BU184: =BT183*OFFSET(SAP_Leadsheet!$D$102,SAP_Spreadsheet!$E184,SAP_Spreadsheet!BI$6) -> 0 | BV184: =BU183*OFFSET(SAP_Leadsheet!$D$102,SAP_Spreadsheet!$E184,SAP_Spreadsheet!BJ$6) -> 0 | ... BZ184: =BY183*OFFSET(SAP_Leadsheet!$D$102,SAP_Spreadsheet!$E184,SAP_Spreadsheet!BN$6) -> 0
D185: B04 | E185: 4 | F185: mVND | H185: =G184*OFFSET(SAP_Leadsheet!$D$102,SAP_Spreadsheet!$E185,SAP_Spreadsheet!H$6) -> 0 | I185: =H184*OFFSET(SAP_Leadsheet!$D$102,SAP_Spreadsheet!$E185,SAP_Spreadsheet!I$6) -> 0 | J185: =I184*OFFSET(SAP_Leadsheet!$D$102,SAP_Spreadsheet!$E185,SAP_Spreadsheet!J$6) -> 0 | K185: =J184*OFFSET(SAP_Leadsheet!$D$102,SAP_Spreadsheet!$E185,SAP_Spreadsheet!K$6) -> 0.025221328 | L185: =K184*OFFSET(SAP_Leadsheet!$D$102,SAP_Spreadsheet!$E185,SAP_Spreadsheet!L$6) -> 0.044458724 | M185: =L184*OFFSET(SAP_Leadsheet!$D$102,SAP_Spreadsheet!$E185,SAP_Spreadsheet!M$6) -> 0.052297109 | N185: =M184*OFFSET(SAP_Leadsheet!$D$102,SAP_Spreadsheet!$E185,SAP_Spreadsheet!N$6) -> 0.052023082 | O185: =N184*OFFSET(SAP_Leadsheet!$D$102,SAP_Spreadsheet!$E185,SAP_Spreadsheet!O$6) -> 0.047836281 | ... BN185: =BM184*OFFSET(SAP_Leadsheet!$D$102,SAP_Spreadsheet!$E185,SAP_Spreadsheet!BN$6) -> 0.0034717976 | BO185: =BN184*OFFSET(SAP_Leadsheet!$D$102,SAP_Spreadsheet!$E185,SAP_Spreadsheet!BC$6) -> 0.003363004 | BP185: =BO184*OFFSET(SAP_Leadsheet!$D$102,SAP_Spreadsheet!$E185,SAP_Spreadsheet!BD$6) -> 0.0032506004 | BQ185: =BP184*OFFSET(SAP_Leadsheet!$D$102,SAP_Spreadsheet!$E185,SAP_Spreadsheet!BE$6) -> 0.0031355507 | BR185: =BQ184*OFFSET(SAP_Leadsheet!$D$102,SAP_Spreadsheet!$E185,SAP_Spreadsheet!BF$6) -> 0.0030192103 | BS185: =BR184*OFFSET(SAP_Leadsheet!$D$102,SAP_Spreadsheet!$E185,SAP_Spreadsheet!BG$6) -> 0 | BT185: =BS184*OFFSET(SAP_Leadsheet!$D$102,SAP_Spreadsheet!$E185,SAP_Spreadsheet!BH$6) -> 0 | BU185: =BT184*OFFSET(SAP_Leadsheet!$D$102,SAP_Spreadsheet!$E185,SAP_Spreadsheet!BI$6) -> 0 | BV185: =BU184*OFFSET(SAP_Leadsheet!$D$102,SAP_Spreadsheet!$E185,SAP_Spreadsheet!BJ$6) -> 0 | ... BZ185: =BY184*OFFSET(SAP_Leadsheet!$D$102,SAP_Spreadsheet!$E185,SAP_Spreadsheet!BN$6) -> 0
D186: B05 | E186: 5 | F186: mVND | H186: =G185*OFFSET(SAP_Leadsheet!$D$102,SAP_Spreadsheet!$E186,SAP_Spreadsheet!H$6) -> 0 | I186: =H185*OFFSET(SAP_Leadsheet!$D$102,SAP_Spreadsheet!$E186,SAP_Spreadsheet!I$6) -> 0 | J186: =I185*OFFSET(SAP_Leadsheet!$D$102,SAP_Spreadsheet!$E186,SAP_Spreadsheet!J$6) -> 0 | K186: =J185*OFFSET(SAP_Leadsheet!$D$102,SAP_Spreadsheet!$E186,SAP_Spreadsheet!K$6) -> 0 | L186: =K185*OFFSET(SAP_Leadsheet!$D$102,SAP_Spreadsheet!$E186,SAP_Spreadsheet!L$6) -> 0.024842543 | M186: =L185*OFFSET(SAP_Leadsheet!$D$102,SAP_Spreadsheet!$E186,SAP_Spreadsheet!M$6) -> 0.043791022 | N186: =M185*OFFSET(SAP_Leadsheet!$D$102,SAP_Spreadsheet!$E186,SAP_Spreadsheet!N$6) -> 0.051511687 | O186: =N185*OFFSET(SAP_Leadsheet!$D$102,SAP_Spreadsheet!$E186,SAP_Spreadsheet!O$6) -> 0.051241776 | ... BN186: =BM185*OFFSET(SAP_Leadsheet!$D$102,SAP_Spreadsheet!$E186,SAP_Spreadsheet!BN$6) -> 0.0035432451 | BO186: =BN185*OFFSET(SAP_Leadsheet!$D$102,SAP_Spreadsheet!$E186,SAP_Spreadsheet!BC$6) -> 0.0034370796 | BP186: =BO185*OFFSET(SAP_Leadsheet!$D$102,SAP_Spreadsheet!$E186,SAP_Spreadsheet!BD$6) -> 0.0033293739 | BQ186: =BP185*OFFSET(SAP_Leadsheet!$D$102,SAP_Spreadsheet!$E186,SAP_Spreadsheet!BE$6) -> 0.0032180944 | BR186: =BQ185*OFFSET(SAP_Leadsheet!$D$102,SAP_Spreadsheet!$E186,SAP_Spreadsheet!BF$6) -> 0.0031041952 | BS186: =BR185*OFFSET(SAP_Leadsheet!$D$102,SAP_Spreadsheet!$E186,SAP_Spreadsheet!BG$6) -> 0.0029890182 | BT186: =BS185*OFFSET(SAP_Leadsheet!$D$102,SAP_Spreadsheet!$E186,SAP_Spreadsheet!BH$6) -> 0 | BU186: =BT185*OFFSET(SAP_Leadsheet!$D$102,SAP_Spreadsheet!$E186,SAP_Spreadsheet!BI$6) -> 0 | BV186: =BU185*OFFSET(SAP_Leadsheet!$D$102,SAP_Spreadsheet!$E186,SAP_Spreadsheet!BJ$6) -> 0 | ... BZ186: =BY185*OFFSET(SAP_Leadsheet!$D$102,SAP_Spreadsheet!$E186,SAP_Spreadsheet!BN$6) -> 0
D187: B06 | E187: 6 | F187: mVND | H187: =G186*OFFSET(SAP_Leadsheet!$D$102,SAP_Spreadsheet!$E187,SAP_Spreadsheet!H$6) -> 0 | I187: =H186*OFFSET(SAP_Leadsheet!$D$102,SAP_Spreadsheet!$E187,SAP_Spreadsheet!I$6) -> 0 | J187: =I186*OFFSET(SAP_Leadsheet!$D$102,SAP_Spreadsheet!$E187,SAP_Spreadsheet!J$6) -> 0 | K187: =J186*OFFSET(SAP_Leadsheet!$D$102,SAP_Spreadsheet!$E187,SAP_Spreadsheet!K$6) -> 0 | L187: =K186*OFFSET(SAP_Leadsheet!$D$102,SAP_Spreadsheet!$E187,SAP_Spreadsheet!L$6) -> 0 | M187: =L186*OFFSET(SAP_Leadsheet!$D$102,SAP_Spreadsheet!$E187,SAP_Spreadsheet!M$6) -> 0.02447695 | N187: =M186*OFFSET(SAP_Leadsheet!$D$102,SAP_Spreadsheet!$E187,SAP_Spreadsheet!N$6) -> 0.043146576 | O187: =N186*OFFSET(SAP_Leadsheet!$D$102,SAP_Spreadsheet!$E187,SAP_Spreadsheet!O$6) -> 0.05075362 | ... BN187: =BM186*OFFSET(SAP_Leadsheet!$D$102,SAP_Spreadsheet!$E187,SAP_Spreadsheet!BN$6) -> 0.0036126285 | BO187: =BN186*OFFSET(SAP_Leadsheet!$D$102,SAP_Spreadsheet!$E187,SAP_Spreadsheet!BC$6) -> 0.0035078126 | BP187: =BO186*OFFSET(SAP_Leadsheet!$D$102,SAP_Spreadsheet!$E187,SAP_Spreadsheet!BD$6) -> 0.0034027088 | BQ187: =BP186*OFFSET(SAP_Leadsheet!$D$102,SAP_Spreadsheet!$E187,SAP_Spreadsheet!BE$6) -> 0.0032960802 | BR187: =BQ186*OFFSET(SAP_Leadsheet!$D$102,SAP_Spreadsheet!$E187,SAP_Spreadsheet!BF$6) -> 0.0031859135 | BS187: =BR186*OFFSET(SAP_Leadsheet!$D$102,SAP_Spreadsheet!$E187,SAP_Spreadsheet!BG$6) -> 0.0030731532 | BT187: =BS186*OFFSET(SAP_Leadsheet!$D$102,SAP_Spreadsheet!$E187,SAP_Spreadsheet!BH$6) -> 0.002959128 | BU187: =BT186*OFFSET(SAP_Leadsheet!$D$102,SAP_Spreadsheet!$E187,SAP_Spreadsheet!BI$6) -> 0 | BV187: =BU186*OFFSET(SAP_Leadsheet!$D$102,SAP_Spreadsheet!$E187,SAP_Spreadsheet!BJ$6) -> 0 | ... BZ187: =BY186*OFFSET(SAP_Leadsheet!$D$102,SAP_Spreadsheet!$E187,SAP_Spreadsheet!BN$6) -> 0
D188: B07 | E188: 7 | F188: mVND | H188: =G187*OFFSET(SAP_Leadsheet!$D$102,SAP_Spreadsheet!$E188,SAP_Spreadsheet!H$6) -> 0 | I188: =H187*OFFSET(SAP_Leadsheet!$D$102,SAP_Spreadsheet!$E188,SAP_Spreadsheet!I$6) -> 0 | J188: =I187*OFFSET(SAP_Leadsheet!$D$102,SAP_Spreadsheet!$E188,SAP_Spreadsheet!J$6) -> 0 | K188: =J187*OFFSET(SAP_Leadsheet!$D$102,SAP_Spreadsheet!$E188,SAP_Spreadsheet!K$6) -> 0 | L188: =K187*OFFSET(SAP_Leadsheet!$D$102,SAP_Spreadsheet!$E188,SAP_Spreadsheet!L$6) -> 0 | M188: =L187*OFFSET(SAP_Leadsheet!$D$102,SAP_Spreadsheet!$E188,SAP_Spreadsheet!M$6) -> 0 | N188: =M187*OFFSET(SAP_Leadsheet!$D$102,SAP_Spreadsheet!$E188,SAP_Spreadsheet!N$6) -> 0.02431108 | O188: =N187*OFFSET(SAP_Leadsheet!$D$102,SAP_Spreadsheet!$E188,SAP_Spreadsheet!O$6) -> 0.04285419 | ... BN188: =BM187*OFFSET(SAP_Leadsheet!$D$102,SAP_Spreadsheet!$E188,SAP_Spreadsheet!BN$6) -> 0.0036800095 | BO188: =BN187*OFFSET(SAP_Leadsheet!$D$102,SAP_Spreadsheet!$E188,SAP_Spreadsheet!BC$6) -> 0.0035765022 | BP188: =BO187*OFFSET(SAP_Leadsheet!$D$102,SAP_Spreadsheet!$E188,SAP_Spreadsheet!BD$6) -> 0.0034727345 | BQ188: =BP187*OFFSET(SAP_Leadsheet!$D$102,SAP_Spreadsheet!$E188,SAP_Spreadsheet!BE$6) -> 0.0033686817 | BR188: =BQ187*OFFSET(SAP_Leadsheet!$D$102,SAP_Spreadsheet!$E188,SAP_Spreadsheet!BF$6) -> 0.0032631194 | BS188: =BR187*OFFSET(SAP_Leadsheet!$D$102,SAP_Spreadsheet!$E188,SAP_Spreadsheet!BG$6) -> 0.0031540544 | BT188: =BS187*OFFSET(SAP_Leadsheet!$D$102,SAP_Spreadsheet!$E188,SAP_Spreadsheet!BH$6) -> 0.0030424217 | BU188: =BT187*OFFSET(SAP_Leadsheet!$D$102,SAP_Spreadsheet!$E188,SAP_Spreadsheet!BI$6) -> 0.0029295368 | BV188: =BU187*OFFSET(SAP_Leadsheet!$D$102,SAP_Spreadsheet!$E188,SAP_Spreadsheet!BJ$6) -> 0 | ... BZ188: =BY187*OFFSET(SAP_Leadsheet!$D$102,SAP_Spreadsheet!$E188,SAP_Spreadsheet!BN$6) -> 0
D189: B08 | E189: 8 | F189: mVND | H189: =G188*OFFSET(SAP_Leadsheet!$D$102,SAP_Spreadsheet!$E189,SAP_Spreadsheet!H$6) -> 0 | I189: =H188*OFFSET(SAP_Leadsheet!$D$102,SAP_Spreadsheet!$E189,SAP_Spreadsheet!I$6) -> 0 | J189: =I188*OFFSET(SAP_Leadsheet!$D$102,SAP_Spreadsheet!$E189,SAP_Spreadsheet!J$6) -> 0 | K189: =J188*OFFSET(SAP_Leadsheet!$D$102,SAP_Spreadsheet!$E189,SAP_Spreadsheet!K$6) -> 0 | L189: =K188*OFFSET(SAP_Leadsheet!$D$102,SAP_Spreadsheet!$E189,SAP_Spreadsheet!L$6) -> 0 | M189: =L188*OFFSET(SAP_Leadsheet!$D$102,SAP_Spreadsheet!$E189,SAP_Spreadsheet!M$6) -> 0 | N189: =M188*OFFSET(SAP_Leadsheet!$D$102,SAP_Spreadsheet!$E189,SAP_Spreadsheet!N$6) -> 0 | O189: =N188*OFFSET(SAP_Leadsheet!$D$102,SAP_Spreadsheet!$E189,SAP_Spreadsheet!O$6) -> 0.02431108 | ... BN189: =BM188*OFFSET(SAP_Leadsheet!$D$102,SAP_Spreadsheet!$E189,SAP_Spreadsheet!BN$6) -> 0.0037834138 | BO189: =BN188*OFFSET(SAP_Leadsheet!$D$102,SAP_Spreadsheet!$E189,SAP_Spreadsheet!BC$6) -> 0.0036800095 | BP189: =BO188*OFFSET(SAP_Leadsheet!$D$102,SAP_Spreadsheet!$E189,SAP_Spreadsheet!BD$6) -> 0.0035765022 | BQ189: =BP188*OFFSET(SAP_Leadsheet!$D$102,SAP_Spreadsheet!$E189,SAP_Spreadsheet!BE$6) -> 0.0034727345 | BR189: =BQ188*OFFSET(SAP_Leadsheet!$D$102,SAP_Spreadsheet!$E189,SAP_Spreadsheet!BF$6) -> 0.0033686817 | BS189: =BR188*OFFSET(SAP_Leadsheet!$D$102,SAP_Spreadsheet!$E189,SAP_Spreadsheet!BG$6) -> 0.0032631194 | BT189: =BS188*OFFSET(SAP_Leadsheet!$D$102,SAP_Spreadsheet!$E189,SAP_Spreadsheet!BH$6) -> 0.0031540544 | BU189: =BT188*OFFSET(SAP_Leadsheet!$D$102,SAP_Spreadsheet!$E189,SAP_Spreadsheet!BI$6) -> 0.0030424217 | BV189: =BU188*OFFSET(SAP_Leadsheet!$D$102,SAP_Spreadsheet!$E189,SAP_Spreadsheet!BJ$6) -> 0.0029295368 | ... BZ189: =BY188*OFFSET(SAP_Leadsheet!$D$102,SAP_Spreadsheet!$E189,SAP_Spreadsheet!BN$6) -> 0
D190: B09 | E190: 9 | F190: mVND | H190: =G189*OFFSET(SAP_Leadsheet!$D$102,SAP_Spreadsheet!$E190,SAP_Spreadsheet!H$6) -> 0 | I190: =H189*OFFSET(SAP_Leadsheet!$D$102,SAP_Spreadsheet!$E190,SAP_Spreadsheet!I$6) -> 0 | J190: =I189*OFFSET(SAP_Leadsheet!$D$102,SAP_Spreadsheet!$E190,SAP_Spreadsheet!J$6) -> 0 | K190: =J189*OFFSET(SAP_Leadsheet!$D$102,SAP_Spreadsheet!$E190,SAP_Spreadsheet!K$6) -> 0 | L190: =K189*OFFSET(SAP_Leadsheet!$D$102,SAP_Spreadsheet!$E190,SAP_Spreadsheet!L$6) -> 0 | M190: =L189*OFFSET(SAP_Leadsheet!$D$102,SAP_Spreadsheet!$E190,SAP_Spreadsheet!M$6) -> 0 | N190: =M189*OFFSET(SAP_Leadsheet!$D$102,SAP_Spreadsheet!$E190,SAP_Spreadsheet!N$6) -> 0 | O190: =N189*OFFSET(SAP_Leadsheet!$D$102,SAP_Spreadsheet!$E190,SAP_Spreadsheet!O$6) -> 0 | ... BN190: =BM189*OFFSET(SAP_Leadsheet!$D$102,SAP_Spreadsheet!$E190,SAP_Spreadsheet!BN$6) -> 0.0038870403 | BO190: =BN189*OFFSET(SAP_Leadsheet!$D$102,SAP_Spreadsheet!$E190,SAP_Spreadsheet!BC$6) -> 0.0037834138 | BP190: =BO189*OFFSET(SAP_Leadsheet!$D$102,SAP_Spreadsheet!$E190,SAP_Spreadsheet!BD$6) -> 0.0036800095 | BQ190: =BP189*OFFSET(SAP_Leadsheet!$D$102,SAP_Spreadsheet!$E190,SAP_Spreadsheet!BE$6) -> 0.0035765022 | BR190: =BQ189*OFFSET(SAP_Leadsheet!$D$102,SAP_Spreadsheet!$E190,SAP_Spreadsheet!BF$6) -> 0.0034727345 | BS190: =BR189*OFFSET(SAP_Leadsheet!$D$102,SAP_Spreadsheet!$E190,SAP_Spreadsheet!BG$6) -> 0.0033686817 | BT190: =BS189*OFFSET(SAP_Leadsheet!$D$102,SAP_Spreadsheet!$E190,SAP_Spreadsheet!BH$6) -> 0.0032631194 | BU190: =BT189*OFFSET(SAP_Leadsheet!$D$102,SAP_Spreadsheet!$E190,SAP_Spreadsheet!BI$6) -> 0.0031540544 | BV190: =BU189*OFFSET(SAP_Leadsheet!$D$102,SAP_Spreadsheet!$E190,SAP_Spreadsheet!BJ$6) -> 0.0030424217 | ... BZ190: =BY189*OFFSET(SAP_Leadsheet!$D$102,SAP_Spreadsheet!$E190,SAP_Spreadsheet!BN$6) -> 0
D191: B10 | E191: 10 | F191: mVND | H191: =G190*OFFSET(SAP_Leadsheet!$D$102,SAP_Spreadsheet!$E191,SAP_Spreadsheet!H$6) -> 0 | I191: =H190*OFFSET(SAP_Leadsheet!$D$102,SAP_Spreadsheet!$E191,SAP_Spreadsheet!I$6) -> 0 | J191: =I190*OFFSET(SAP_Leadsheet!$D$102,SAP_Spreadsheet!$E191,SAP_Spreadsheet!J$6) -> 0 | K191: =J190*OFFSET(SAP_Leadsheet!$D$102,SAP_Spreadsheet!$E191,SAP_Spreadsheet!K$6) -> 0 | L191: =K190*OFFSET(SAP_Leadsheet!$D$102,SAP_Spreadsheet!$E191,SAP_Spreadsheet!L$6) -> 0 | M191: =L190*OFFSET(SAP_Leadsheet!$D$102,SAP_Spreadsheet!$E191,SAP_Spreadsheet!M$6) -> 0 | N191: =M190*OFFSET(SAP_Leadsheet!$D$102,SAP_Spreadsheet!$E191,SAP_Spreadsheet!N$6) -> 0 | O191: =N190*OFFSET(SAP_Leadsheet!$D$102,SAP_Spreadsheet!$E191,SAP_Spreadsheet!O$6) -> 0 | ... BN191: =BM190*OFFSET(SAP_Leadsheet!$D$102,SAP_Spreadsheet!$E191,SAP_Spreadsheet!BN$6) -> 0.003991158 | BO191: =BN190*OFFSET(SAP_Leadsheet!$D$102,SAP_Spreadsheet!$E191,SAP_Spreadsheet!BC$6) -> 0.0038870403 | BP191: =BO190*OFFSET(SAP_Leadsheet!$D$102,SAP_Spreadsheet!$E191,SAP_Spreadsheet!BD$6) -> 0.0037834138 | BQ191: =BP190*OFFSET(SAP_Leadsheet!$D$102,SAP_Spreadsheet!$E191,SAP_Spreadsheet!BE$6) -> 0.0036800095 | BR191: =BQ190*OFFSET(SAP_Leadsheet!$D$102,SAP_Spreadsheet!$E191,SAP_Spreadsheet!BF$6) -> 0.0035765022 | BS191: =BR190*OFFSET(SAP_Leadsheet!$D$102,SAP_Spreadsheet!$E191,SAP_Spreadsheet!BG$6) -> 0.0034727345 | BT191: =BS190*OFFSET(SAP_Leadsheet!$D$102,SAP_Spreadsheet!$E191,SAP_Spreadsheet!BH$6) -> 0.0033686817 | BU191: =BT190*OFFSET(SAP_Leadsheet!$D$102,SAP_Spreadsheet!$E191,SAP_Spreadsheet!BI$6) -> 0.0032631194 | BV191: =BU190*OFFSET(SAP_Leadsheet!$D$102,SAP_Spreadsheet!$E191,SAP_Spreadsheet!BJ$6) -> 0.0031540544 | ... BZ191: =BY190*OFFSET(SAP_Leadsheet!$D$102,SAP_Spreadsheet!$E191,SAP_Spreadsheet!BN$6) -> 0
D192: B11 | E192: 11 | F192: mVND | H192: =G191*OFFSET(SAP_Leadsheet!$D$102,SAP_Spreadsheet!$E192,SAP_Spreadsheet!H$6) -> 0 | I192: =H191*OFFSET(SAP_Leadsheet!$D$102,SAP_Spreadsheet!$E192,SAP_Spreadsheet!I$6) -> 0 | J192: =I191*OFFSET(SAP_Leadsheet!$D$102,SAP_Spreadsheet!$E192,SAP_Spreadsheet!J$6) -> 0 | K192: =J191*OFFSET(SAP_Leadsheet!$D$102,SAP_Spreadsheet!$E192,SAP_Spreadsheet!K$6) -> 0 | L192: =K191*OFFSET(SAP_Leadsheet!$D$102,SAP_Spreadsheet!$E192,SAP_Spreadsheet!L$6) -> 0 | M192: =L191*OFFSET(SAP_Leadsheet!$D$102,SAP_Spreadsheet!$E192,SAP_Spreadsheet!M$6) -> 0 | N192: =M191*OFFSET(SAP_Leadsheet!$D$102,SAP_Spreadsheet!$E192,SAP_Spreadsheet!N$6) -> 0 | O192: =N191*OFFSET(SAP_Leadsheet!$D$102,SAP_Spreadsheet!$E192,SAP_Spreadsheet!O$6) -> 0 | ... BN192: =BM191*OFFSET(SAP_Leadsheet!$D$102,SAP_Spreadsheet!$E192,SAP_Spreadsheet!BN$6) -> 0.0040962056 | BO192: =BN191*OFFSET(SAP_Leadsheet!$D$102,SAP_Spreadsheet!$E192,SAP_Spreadsheet!BC$6) -> 0.003991158 | BP192: =BO191*OFFSET(SAP_Leadsheet!$D$102,SAP_Spreadsheet!$E192,SAP_Spreadsheet!BD$6) -> 0.0038870403 | BQ192: =BP191*OFFSET(SAP_Leadsheet!$D$102,SAP_Spreadsheet!$E192,SAP_Spreadsheet!BE$6) -> 0.0037834138 | BR192: =BQ191*OFFSET(SAP_Leadsheet!$D$102,SAP_Spreadsheet!$E192,SAP_Spreadsheet!BF$6) -> 0.0036800095 | BS192: =BR191*OFFSET(SAP_Leadsheet!$D$102,SAP_Spreadsheet!$E192,SAP_Spreadsheet!BG$6) -> 0.0035765022 | BT192: =BS191*OFFSET(SAP_Leadsheet!$D$102,SAP_Spreadsheet!$E192,SAP_Spreadsheet!BH$6) -> 0.0034727345 | BU192: =BT191*OFFSET(SAP_Leadsheet!$D$102,SAP_Spreadsheet!$E192,SAP_Spreadsheet!BI$6) -> 0.0033686817 | BV192: =BU191*OFFSET(SAP_Leadsheet!$D$102,SAP_Spreadsheet!$E192,SAP_Spreadsheet!BJ$6) -> 0.0032631194 | ... BZ192: =BY191*OFFSET(SAP_Leadsheet!$D$102,SAP_Spreadsheet!$E192,SAP_Spreadsheet!BN$6) -> 0
D193: B12 | E193: 12 | F193: mVND | H193: =G192*OFFSET(SAP_Leadsheet!$D$102,SAP_Spreadsheet!$E193,SAP_Spreadsheet!H$6) -> 0 | I193: =H192*OFFSET(SAP_Leadsheet!$D$102,SAP_Spreadsheet!$E193,SAP_Spreadsheet!I$6) -> 0 | J193: =I192*OFFSET(SAP_Leadsheet!$D$102,SAP_Spreadsheet!$E193,SAP_Spreadsheet!J$6) -> 0 | K193: =J192*OFFSET(SAP_Leadsheet!$D$102,SAP_Spreadsheet!$E193,SAP_Spreadsheet!K$6) -> 0 | L193: =K192*OFFSET(SAP_Leadsheet!$D$102,SAP_Spreadsheet!$E193,SAP_Spreadsheet!L$6) -> 0 | M193: =L192*OFFSET(SAP_Leadsheet!$D$102,SAP_Spreadsheet!$E193,SAP_Spreadsheet!M$6) -> 0 | N193: =M192*OFFSET(SAP_Leadsheet!$D$102,SAP_Spreadsheet!$E193,SAP_Spreadsheet!N$6) -> 0 | O193: =N192*OFFSET(SAP_Leadsheet!$D$102,SAP_Spreadsheet!$E193,SAP_Spreadsheet!O$6) -> 0 | ... BN193: =BM192*OFFSET(SAP_Leadsheet!$D$102,SAP_Spreadsheet!$E193,SAP_Spreadsheet!BN$6) -> 0.0042015134 | BO193: =BN192*OFFSET(SAP_Leadsheet!$D$102,SAP_Spreadsheet!$E193,SAP_Spreadsheet!BC$6) -> 0.0040962056 | BP193: =BO192*OFFSET(SAP_Leadsheet!$D$102,SAP_Spreadsheet!$E193,SAP_Spreadsheet!BD$6) -> 0.003991158 | BQ193: =BP192*OFFSET(SAP_Leadsheet!$D$102,SAP_Spreadsheet!$E193,SAP_Spreadsheet!BE$6) -> 0.0038870403 | BR193: =BQ192*OFFSET(SAP_Leadsheet!$D$102,SAP_Spreadsheet!$E193,SAP_Spreadsheet!BF$6) -> 0.0037834138 | BS193: =BR192*OFFSET(SAP_Leadsheet!$D$102,SAP_Spreadsheet!$E193,SAP_Spreadsheet!BG$6) -> 0.0036800095 | BT193: =BS192*OFFSET(SAP_Leadsheet!$D$102,SAP_Spreadsheet!$E193,SAP_Spreadsheet!BH$6) -> 0.0035765022 | BU193: =BT192*OFFSET(SAP_Leadsheet!$D$102,SAP_Spreadsheet!$E193,SAP_Spreadsheet!BI$6) -> 0.0034727345 | BV193: =BU192*OFFSET(SAP_Leadsheet!$D$102,SAP_Spreadsheet!$E193,SAP_Spreadsheet!BJ$6) -> 0.0033686817 | ... BZ193: =BY192*OFFSET(SAP_Leadsheet!$D$102,SAP_Spreadsheet!$E193,SAP_Spreadsheet!BN$6) -> 0.0029295368
D194: B13 | E194: 13 | F194: mVND | H194: =G193*OFFSET(SAP_Leadsheet!$D$102,SAP_Spreadsheet!$E194,SAP_Spreadsheet!H$6) -> 0 | I194: =H193*OFFSET(SAP_Leadsheet!$D$102,SAP_Spreadsheet!$E194,SAP_Spreadsheet!I$6) -> 0 | J194: =I193*OFFSET(SAP_Leadsheet!$D$102,SAP_Spreadsheet!$E194,SAP_Spreadsheet!J$6) -> 0 | K194: =J193*OFFSET(SAP_Leadsheet!$D$102,SAP_Spreadsheet!$E194,SAP_Spreadsheet!K$6) -> 0 | L194: =K193*OFFSET(SAP_Leadsheet!$D$102,SAP_Spreadsheet!$E194,SAP_Spreadsheet!L$6) -> 0 | M194: =L193*OFFSET(SAP_Leadsheet!$D$102,SAP_Spreadsheet!$E194,SAP_Spreadsheet!M$6) -> 0 | N194: =M193*OFFSET(SAP_Leadsheet!$D$102,SAP_Spreadsheet!$E194,SAP_Spreadsheet!N$6) -> 0 | O194: =N193*OFFSET(SAP_Leadsheet!$D$102,SAP_Spreadsheet!$E194,SAP_Spreadsheet!O$6) -> 0 | ... BN194: =BM193*OFFSET(SAP_Leadsheet!$D$102,SAP_Spreadsheet!$E194,SAP_Spreadsheet!BN$6) -> 0.0049116556 | BO194: =BN193*OFFSET(SAP_Leadsheet!$D$102,SAP_Spreadsheet!$E194,SAP_Spreadsheet!BC$6) -> 0.0042015134 | BP194: =BO193*OFFSET(SAP_Leadsheet!$D$102,SAP_Spreadsheet!$E194,SAP_Spreadsheet!BD$6) -> 0.0040962056 | BQ194: =BP193*OFFSET(SAP_Leadsheet!$D$102,SAP_Spreadsheet!$E194,SAP_Spreadsheet!BE$6) -> 0.003991158 | BR194: =BQ193*OFFSET(SAP_Leadsheet!$D$102,SAP_Spreadsheet!$E194,SAP_Spreadsheet!BF$6) -> 0.0038870403 | BS194: =BR193*OFFSET(SAP_Leadsheet!$D$102,SAP_Spreadsheet!$E194,SAP_Spreadsheet!BG$6) -> 0.0037834138 | BT194: =BS193*OFFSET(SAP_Leadsheet!$D$102,SAP_Spreadsheet!$E194,SAP_Spreadsheet!BH$6) -> 0.0036800095 | BU194: =BT193*OFFSET(SAP_Leadsheet!$D$102,SAP_Spreadsheet!$E194,SAP_Spreadsheet!BI$6) -> 0.0035765022 | BV194: =BU193*OFFSET(SAP_Leadsheet!$D$102,SAP_Spreadsheet!$E194,SAP_Spreadsheet!BJ$6) -> 0.0034727345 | ... BZ194: =BY193*OFFSET(SAP_Leadsheet!$D$102,SAP_Spreadsheet!$E194,SAP_Spreadsheet!BN$6) -> 0.0030424217
D195: B14+ | F195: mVND | H195: =G195+G194 -> 0 | I195: =H195+H194 -> 0 | J195: =I195+I194 -> 0 | K195: =J195+J194 -> 0 | L195: =K195+K194 -> 0 | M195: =L195+L194 -> 0 | N195: =M195+M194 -> 0 | O195: =N195+N194 -> 0 | ... BZ195: =BY195+BY194 -> 0.72470584
C198: ANR | D198: Due date | F198: of month | G198: =IF(G7>SAP_Leadsheet!$E$21,0,SAP_Leadsheet!$E$22) -> 5 | H198: =IF(H7>SAP_Leadsheet!$E$21,0,SAP_Leadsheet!$E$22) -> 5 | I198: =IF(I7>SAP_Leadsheet!$E$21,0,SAP_Leadsheet!$E$22) -> 5 | J198: =IF(J7>SAP_Leadsheet!$E$21,0,SAP_Leadsheet!$E$22) -> 5 | K198: =IF(K7>SAP_Leadsheet!$E$21,0,SAP_Leadsheet!$E$22) -> 5 | L198: =IF(L7>SAP_Leadsheet!$E$21,0,SAP_Leadsheet!$E$22) -> 5 | M198: =IF(M7>SAP_Leadsheet!$E$21,0,SAP_Leadsheet!$E$22) -> 5 | N198: =IF(N7>SAP_Leadsheet!$E$21,0,SAP_Leadsheet!$E$22) -> 5 | ... BZ198: =IF(BZ7>SAP_Leadsheet!$E$21,0,SAP_Leadsheet!$E$22) -> 0
D199: Statement date | F199: date of month | G199: =IF(SAP_Spreadsheet!G7>SAP_Leadsheet!$E$21,0,ROUNDDOWN(IF(G198-(SAP_Leadsheet!$E$23-$C$4)>0,G198-(SAP_Leadsheet!$E$23-$C$4),$C$4+G198-(SAP_Leadsheet!$E$23-$C$4)),0)) -> 20 | H199: =IF(SAP_Spreadsheet!H7>SAP_Leadsheet!$E$21,0,ROUNDDOWN(IF(H198-(SAP_Leadsheet!$E$23-$C$4)>0,H198-(SAP_Leadsheet!$E$23-$C$4),$C$4+H198-(SAP_Leadsheet!$E$23-$C$4)),0)) -> 20 | I199: =IF(SAP_Spreadsheet!I7>SAP_Leadsheet!$E$21,0,ROUNDDOWN(IF(I198-(SAP_Leadsheet!$E$23-$C$4)>0,I198-(SAP_Leadsheet!$E$23-$C$4),$C$4+I198-(SAP_Leadsheet!$E$23-$C$4)),0)) -> 20 | J199: =IF(SAP_Spreadsheet!J7>SAP_Leadsheet!$E$21,0,ROUNDDOWN(IF(J198-(SAP_Leadsheet!$E$23-$C$4)>0,J198-(SAP_Leadsheet!$E$23-$C$4),$C$4+J198-(SAP_Leadsheet!$E$23-$C$4)),0)) -> 20 | K199: =IF(SAP_Spreadsheet!K7>SAP_Leadsheet!$E$21,0,ROUNDDOWN(IF(K198-(SAP_Leadsheet!$E$23-$C$4)>0,K198-(SAP_Leadsheet!$E$23-$C$4),$C$4+K198-(SAP_Leadsheet!$E$23-$C$4)),0)) -> 20 | L199: =IF(SAP_Spreadsheet!L7>SAP_Leadsheet!$E$21,0,ROUNDDOWN(IF(L198-(SAP_Leadsheet!$E$23-$C$4)>0,L198-(SAP_Leadsheet!$E$23-$C$4),$C$4+L198-(SAP_Leadsheet!$E$23-$C$4)),0)) -> 20 | M199: =IF(SAP_Spreadsheet!M7>SAP_Leadsheet!$E$21,0,ROUNDDOWN(IF(M198-(SAP_Leadsheet!$E$23-$C$4)>0,M198-(SAP_Leadsheet!$E$23-$C$4),$C$4+M198-(SAP_Leadsheet!$E$23-$C$4)),0)) -> 20 | N199: =IF(SAP_Spreadsheet!N7>SAP_Leadsheet!$E$21,0,ROUNDDOWN(IF(N198-(SAP_Leadsheet!$E$23-$C$4)>0,N198-(SAP_Leadsheet!$E$23-$C$4),$C$4+N198-(SAP_Leadsheet!$E$23-$C$4)),0)) -> 20 | ... BN199: =IF(SAP_Spreadsheet!BN7>SAP_Leadsheet!$E$21,0,ROUNDDOWN(IF(BN198-(SAP_Leadsheet!$E$23-$C$4)>0,BN198-(SAP_Leadsheet!$E$23-$C$4),$C$4+BN198-(SAP_Leadsheet!$E$23-$C$4)),0)) -> 20
D200: ANR TB | F200: mVND | G200: =(0*G199+G171*($C$4-G199))/$C$4 -> 0.15661657 | H200: =(G171*H199+H171*($C$4-H199))/$C$4 -> 0.58695868 | I200: =(H171*I199+I171*($C$4-I199))/$C$4 -> 0.90146499 | J200: =(I171*J199+J171*($C$4-J199))/$C$4 -> 1.0446646 | K200: =(J171*K199+K171*($C$4-K199))/$C$4 -> 1.0698613 | L200: =(K171*L199+L171*($C$4-L199))/$C$4 -> 1.0375619 | M200: =(L171*M199+M171*($C$4-M199))/$C$4 -> 0.97824493 | N200: =(M171*N199+N171*($C$4-N199))/$C$4 -> 0.90900061 | O200: =(N171*O199+O171*($C$4-O199))/$C$4 -> 0.85912053 | ... BN200: =(BM171*BN199+BN171*($C$4-BN199))/$C$4 -> 0.93420814
D202: ANR outstanding (excl WO) | F202: mVND | G202: =(0*G199+G172*($C$4-G199))/$C$4 -> 0.15661657 | H202: =(G172*H199+H172*($C$4-H199))/$C$4 -> 0.58695868 | I202: =(H172*I199+I172*($C$4-I199))/$C$4 -> 0.90146499 | J202: =(I172*J199+J172*($C$4-J199))/$C$4 -> 1.0446646 | K202: =(J172*K199+K172*($C$4-K199))/$C$4 -> 1.0698613 | L202: =(K172*L199+L172*($C$4-L199))/$C$4 -> 1.0375619 | M202: =(L172*M199+M172*($C$4-M199))/$C$4 -> 0.97824493 | N202: =(M172*N199+N172*($C$4-N199))/$C$4 -> 0.90900061 | O202: =(N172*O199+O172*($C$4-O199))/$C$4 -> 0.85079481 | ... BN202: =(BM172*BN199+BN172*($C$4-BN199))/$C$4 -> 0.23250513
D204: ANR/ENR | F204: % | G204: =IFERROR(G200/G171,0) -> 0.34246575 | H204: =IFERROR(H200/H171,0) -> 0.70221775 | I204: =IFERROR(I200/I171,0) -> 0.8774078 | J204: =IFERROR(J200/J171,0) -> 0.96927707 | K204: =IFERROR(K200/K171,0) -> 1.0144104 | L204: =IFERROR(L200/L171,0) -> 1.0326799 | M204: =IFERROR(M200/M171,0) -> 1.0548271 | N204: =IFERROR(N200/N171,0) -> 1.0404311 | ... BN204: =IFERROR(BN200/BN171,0) -> 1.0033779
C206: Revolving status
D207: Revol Port | F207: % | G207: =IF(G7>SAP_Leadsheet!$E$21,0,SAP_Leadsheet!$E$27) -> 0.5115999 | H207: =IF(H7>SAP_Leadsheet!$E$21,0,SAP_Leadsheet!$E$27) -> 0.5115999 | I207: =IF(I7>SAP_Leadsheet!$E$21,0,SAP_Leadsheet!$E$27) -> 0.5115999 | J207: =IF(J7>SAP_Leadsheet!$E$21,0,SAP_Leadsheet!$E$27) -> 0.5115999 | K207: =IF(K7>SAP_Leadsheet!$E$21,0,SAP_Leadsheet!$E$27) -> 0.5115999 | L207: =IF(L7>SAP_Leadsheet!$E$21,0,SAP_Leadsheet!$E$27) -> 0.5115999 | M207: =IF(M7>SAP_Leadsheet!$E$21,0,SAP_Leadsheet!$E$27) -> 0.5115999 | N207: =IF(N7>SAP_Leadsheet!$E$21,0,SAP_Leadsheet!$E$27) -> 0.5115999 | ... BN207: =IF(BN7>SAP_Leadsheet!$E$21,0,SAP_Leadsheet!$E$27) -> 0.5115999
D208: B0&B1/total balance (inclWO) | F208: % | G208: =IF(SAP_Spreadsheet!G6>SAP_Leadsheet!$E$21,0,(G182+G181)/SAP_Spreadsheet!G171) -> 1 | H208: =IF(SAP_Spreadsheet!H6>SAP_Leadsheet!$E$21,0,(H182+H181)/SAP_Spreadsheet!H171) -> 1 | I208: =IF(SAP_Spreadsheet!I6>SAP_Leadsheet!$E$21,0,(I182+I181)/SAP_Spreadsheet!I171) -> 0.97396071 | J208: =IF(SAP_Spreadsheet!J6>SAP_Leadsheet!$E$21,0,(J182+J181)/SAP_Spreadsheet!J171) -> 0.9324144 | K208: =IF(SAP_Spreadsheet!K6>SAP_Leadsheet!$E$21,0,(K182+K181)/SAP_Spreadsheet!K171) -> 0.88056127 | L208: =IF(SAP_Spreadsheet!L6>SAP_Leadsheet!$E$21,0,(L182+L181)/SAP_Spreadsheet!L171) -> 0.8230975 | M208: =IF(SAP_Spreadsheet!M6>SAP_Leadsheet!$E$21,0,(M182+M181)/SAP_Spreadsheet!M171) -> 0.75815952 | N208: =IF(SAP_Spreadsheet!N6>SAP_Leadsheet!$E$21,0,(N182+N181)/SAP_Spreadsheet!N171) -> 0.69693008 | ... BN208: =IF(SAP_Spreadsheet!BN6>SAP_Leadsheet!$E$21,0,(BN182+BN181)/SAP_Spreadsheet!BN171) -> 0.2204177
D209: B0&B1/balance (tỉ lệ thu phí) | F209: % | G209: =IF(SAP_Spreadsheet!G7>SAP_Leadsheet!$E$21,0,(G181+G182)/SAP_Spreadsheet!G172) -> 1 | H209: =IF(SAP_Spreadsheet!H7>SAP_Leadsheet!$E$21,0,(H181+H182)/SAP_Spreadsheet!H172) -> 1 | I209: =IF(SAP_Spreadsheet!I7>SAP_Leadsheet!$E$21,0,(I181+I182)/SAP_Spreadsheet!I172) -> 0.97396071 | J209: =IF(SAP_Spreadsheet!J7>SAP_Leadsheet!$E$21,0,(J181+J182)/SAP_Spreadsheet!J172) -> 0.9324144 | K209: =IF(SAP_Spreadsheet!K7>SAP_Leadsheet!$E$21,0,(K181+K182)/SAP_Spreadsheet!K172) -> 0.88056127 | L209: =IF(SAP_Spreadsheet!L7>SAP_Leadsheet!$E$21,0,(L181+L182)/SAP_Spreadsheet!L172) -> 0.8230975 | M209: =IF(SAP_Spreadsheet!M7>SAP_Leadsheet!$E$21,0,(M181+M182)/SAP_Spreadsheet!M172) -> 0.75815952 | N209: =IF(SAP_Spreadsheet!N7>SAP_Leadsheet!$E$21,0,(N181+N182)/SAP_Spreadsheet!N172) -> 0.69693008 | ... BN209: =IF(SAP_Spreadsheet!BN7>SAP_Leadsheet!$E$21,0,(BN181+BN182)/SAP_Spreadsheet!BN172) -> 0.90457384
D210: B0&B1/balance (tỉ lệ thu lãi) | F210: % | H210: =IF(SAP_Spreadsheet!H8>SAP_Leadsheet!$E$21,0,1-(H172-H182-H181)/H211) -> 1 | I210: =IF(SAP_Spreadsheet!I8>SAP_Leadsheet!$E$21,0,1-(I172-I182-I181)/I211) -> 0.91090805 | J210: =IF(SAP_Spreadsheet!J8>SAP_Leadsheet!$E$21,0,1-(J172-J182-J181)/J211) -> 0.84205576 | K210: =IF(SAP_Spreadsheet!K8>SAP_Leadsheet!$E$21,0,1-(K172-K182-K181)/K211) -> 0.7643043 | L210: =IF(SAP_Spreadsheet!L8>SAP_Leadsheet!$E$21,0,1-(L172-L182-L181)/L211) -> 0.67526858 | M210: =IF(SAP_Spreadsheet!M8>SAP_Leadsheet!$E$21,0,1-(M172-M182-M181)/M211) -> 0.57747651 | N210: =IF(SAP_Spreadsheet!N8>SAP_Leadsheet!$E$21,0,1-(N172-N182-N181)/N211) -> 0.47092698 | O210: =IF(SAP_Spreadsheet!O8>SAP_Leadsheet!$E$21,0,1-(O172-O182-O181)/O211) -> 0.41045376 | ... BN210: =IF(SAP_Spreadsheet!BN8>SAP_Leadsheet!$E$21,0,1-(BN172-BN182-BN181)/BN211) -> 0.30206925
D211: Revolving balance Non EMI | F211: mVND | G211: 0 | H211: =IF(H7>SAP_Leadsheet!$E$21,0,G207*G174*G202) -> 0.080125022 | I211: =IF(I7>SAP_Leadsheet!$E$21,0,H207*H174*H202) -> 0.300288 | J211: =IF(J7>SAP_Leadsheet!$E$21,0,I207*I174*I202) -> 0.46118939 | K211: =IF(K7>SAP_Leadsheet!$E$21,0,J207*J174*J202) -> 0.53445028 | L211: =IF(L7>SAP_Leadsheet!$E$21,0,K207*K174*K202) -> 0.54734095 | M211: =IF(M7>SAP_Leadsheet!$E$21,0,L207*L174*L202) -> 0.53081657 | N211: =IF(N7>SAP_Leadsheet!$E$21,0,M207*M174*M202) -> 0.50047 | O211: =IF(O7>SAP_Leadsheet!$E$21,0,N207*N174*N202) -> 0.46504462 | ... BN211: =IF(BN7>SAP_Leadsheet!$E$21,0,BM207*BM174*BM202) -> 0.031019634
...

Sheet Sales plan& PnL
E1: PROFIT & LOSS 60M | H1: =SAP_Leadsheet!C6 -> DPD180+
A3: Code | B3: Product | C3: Old/new | D3: Item | F3: I. | G3: SALES PLAN
A4: =B4&D4&C4 -> Auto loan | B4: Auto loan
H5: If you want to estimate the mix price & promotion tenor for your product package, please input here & link to Leadsheet properly in term of pricing
A6: =B6&D6&C6 -> Auto loan | B6: Auto loan | H6: Please input your expected disbursement volume with date of lauching out product if you would like to project 60M profit and loss.
A8: =B8&D8&C8 -> Auto loan | B8: Auto loan | H8: Business month | J8: 45658 | K8: =EOMONTH(J8,1) -> 45716 | L8: =EOMONTH(K8,1) -> 45747 | M8: =EOMONTH(L8,1) -> 45777 | N8: =EOMONTH(M8,1) -> 45808 | O8: =EOMONTH(N8,1) -> 45838 | P8: =EOMONTH(O8,1) -> 45869 | Q8: =EOMONTH(P8,1) -> 45900 | R8: =EOMONTH(Q8,1) -> 45930 | ... BR8: =EOMONTH(BQ8,1) -> 47514
H9: Don't delete | J9: =YEAR(J8) -> 2025 | K9: =YEAR(K8) -> 2025 | L9: =YEAR(L8) -> 2025 | M9: =YEAR(M8) -> 2025 | N9: =YEAR(N8) -> 2025 | O9: =YEAR(O8) -> 2025 | P9: =YEAR(P8) -> 2025 | Q9: =YEAR(Q8) -> 2025 | ... BR9: =YEAR(BR8) -> 2030
A10: =B10&D10&C10 -> Auto loan | B10: Auto loan | H10: New issued (Card)
F12: II. | G12: PROFIT & LOSS
H14: FISCAL YEAR | J14: Total | K14: =J9 -> 2025 | L14: =K14+1 -> 2026 | M14: =L14+1 -> 2027 | N14: =M14+1 -> 2028 | O14: =N14+1 -> 2029 | P14: =O14+1 -> 2030
J15: bVND | K15: bVND | L15: bVND | M15: bVND | N15: bVND | O15: bVND | P15: bVND
H17: New Issued Paylater | J17: =SUM(K17:U17) -> 0 | K17: =SUMIF($J$9:$BQ$9,K$14,$J$10:$BQ$10) -> 0 | L17: =SUMIF($J$9:$BQ$9,L$14,$J$10:$BQ$10) -> 0 | M17: =SUMIF($J$9:$BQ$9,M$14,$J$10:$BQ$10) -> 0 | N17: =SUMIF($J$9:$BQ$9,N$14,$J$10:$BQ$10) -> 0 | O17: =SUMIF($J$9:$BQ$9,O$14,$J$10:$BQ$10) -> 0 | P17: =SUMIF($J$9:$BQ$9,P$14,$J$10:$BQ$10) -> 0
H18: Average monthly issued Paylater | J18: =AVERAGE(J10:AS10) -> #DIV/0! | K18: =K17/COUNTIF($J$9:$AS$9,K14) -> 0 | L18: =L17/COUNTIF($J$9:$AS$9,L14) -> 0 | M18: =M17/COUNTIF($J$9:$AS$9,M14) -> 0 | N18: =N17/COUNTIF($J$9:$BQ$9,N14) -> 0 | O18: =O17/COUNTIF($J$9:$BQ$9,O14) -> 0 | P18: =IFERROR(P17/COUNTIF($J$9:$BQ$9,P14),0) -> 0
H20: EOP | K20: =OFFSET(PnL_Speadsheet!$D$7,0,MATCH(DATE('Sales plan& PnL'!K$14,12,31),PnL_Speadsheet!$E$4:$BL$4,0))/1000 -> 0 | L20: =OFFSET(PnL_Speadsheet!$D$7,0,MATCH(DATE('Sales plan& PnL'!L$14,12,31),PnL_Speadsheet!$E$4:$BL$4,0))/1000 -> 0 | M20: =OFFSET(PnL_Speadsheet!$D$7,0,MATCH(DATE('Sales plan& PnL'!M$14,12,31),PnL_Speadsheet!$E$4:$BL$4,0))/1000 -> 0 | N20: =OFFSET(PnL_Speadsheet!$D$7,0,MATCH(DATE('Sales plan& PnL'!N$14,12,31),PnL_Speadsheet!$E$4:$BL$4,0))/1000 -> 0 | O20: =PnL_Speadsheet!BL7/1000 -> 0 | P20: =PnL_Speadsheet!BN7/1000 -> 0
H21: ADB | J21: =SUM(PnL_Speadsheet!E8:BK8)/1000/COUNT(PnL_Speadsheet!E3:BK3) -> 0 | K21: =SUMIF(PnL_Speadsheet!$E$3:$BL$3,K$14,PnL_Speadsheet!$E8:$BL8)/1000/COUNTIF(PnL_Speadsheet!$E$3:$BL$3,'Sales plan& PnL'!K$14) -> 0 | L21: =SUMIF(PnL_Speadsheet!$E$3:$BL$3,L$14,PnL_Speadsheet!$E8:$BL8)/1000/COUNTIF(PnL_Speadsheet!$E$3:$BL$3,'Sales plan& PnL'!L$14) -> 0 | M21: =SUMIF(PnL_Speadsheet!$E$3:$BL$3,M$14,PnL_Speadsheet!$E8:$BL8)/1000/COUNTIF(PnL_Speadsheet!$E$3:$BL$3,'Sales plan& PnL'!M$14) -> 0 | N21: =SUMIF(PnL_Speadsheet!$E$3:$BL$3,N$14,PnL_Speadsheet!$E8:$BL8)/1000/COUNTIF(PnL_Speadsheet!$E$3:$BL$3,'Sales plan& PnL'!N$14) -> 0 | O21: =SUMIF(PnL_Speadsheet!$E$3:$BL$3,O$14,PnL_Speadsheet!$E8:$BL8)/1000/COUNTIF(PnL_Speadsheet!$E$3:$BL$3,'Sales plan& PnL'!O$14) -> 0 | P21: =IFERROR(SUMIF(PnL_Speadsheet!$E$3:$BL$3,P$14,PnL_Speadsheet!$E8:$BL8)/1000/COUNTIF(PnL_Speadsheet!$E$3:$BL$3,'Sales plan& PnL'!P$14),0) -> 0
H23: TOI | J23: =SUM(K23:U23) -> 0 | K23: =SUMIF(PnL_Speadsheet!$E$3:$BL$3,K$14,PnL_Speadsheet!$E9:$BL9)/1000 -> 0 | L23: =SUMIF(PnL_Speadsheet!$E$3:$BL$3,L$14,PnL_Speadsheet!$E9:$BL9)/1000 -> 0 | M23: =SUMIF(PnL_Speadsheet!$E$3:$BL$3,M$14,PnL_Speadsheet!$E9:$BL9)/1000 -> 0 | N23: =SUMIF(PnL_Speadsheet!$E$3:$BL$3,N$14,PnL_Speadsheet!$E9:$BL9)/1000 -> 0 | O23: =SUMIF(PnL_Speadsheet!$E$3:$BL$3,O$14,PnL_Speadsheet!$E9:$BL9)/1000 -> 0 | P23: =SUMIF(PnL_Speadsheet!$E$3:$BL$3,P$14,PnL_Speadsheet!$E9:$BL9)/1000 -> 0
H24: NII | J24: =SUM(K24:U24) -> 0 | K24: =SUMIF(PnL_Speadsheet!$E$3:$BL$3,K$14,PnL_Speadsheet!$E10:$BL10)/1000 -> 0 | L24: =SUMIF(PnL_Speadsheet!$E$3:$BL$3,L$14,PnL_Speadsheet!$E10:$BL10)/1000 -> 0 | M24: =SUMIF(PnL_Speadsheet!$E$3:$BL$3,M$14,PnL_Speadsheet!$E10:$BL10)/1000 -> 0 | N24: =SUMIF(PnL_Speadsheet!$E$3:$BL$3,N$14,PnL_Speadsheet!$E10:$BL10)/1000 -> 0 | O24: =SUMIF(PnL_Speadsheet!$E$3:$BL$3,O$14,PnL_Speadsheet!$E10:$BL10)/1000 -> 0 | P24: =SUMIF(PnL_Speadsheet!$E$3:$BL$3,P$14,PnL_Speadsheet!$E10:$BL10)/1000 -> 0
H25: CII | J25: =SUM(K25:U25) -> 0 | K25: =SUMIF(PnL_Speadsheet!$E$3:$BL$3,K$14,PnL_Speadsheet!$E11:$BL11)/1000 -> 0 | L25: =SUMIF(PnL_Speadsheet!$E$3:$BL$3,L$14,PnL_Speadsheet!$E11:$BL11)/1000 -> 0 | M25: =SUMIF(PnL_Speadsheet!$E$3:$BL$3,M$14,PnL_Speadsheet!$E11:$BL11)/1000 -> 0 | N25: =SUMIF(PnL_Speadsheet!$E$3:$BL$3,N$14,PnL_Speadsheet!$E11:$BL11)/1000 -> 0 | O25: =SUMIF(PnL_Speadsheet!$E$3:$BL$3,O$14,PnL_Speadsheet!$E11:$BL11)/1000 -> 0 | P25: =SUMIF(PnL_Speadsheet!$E$3:$BL$3,P$14,PnL_Speadsheet!$E11:$BL11)/1000 -> 0
H26: COF | J26: =SUM(K26:U26) -> 0 | K26: =SUMIF(PnL_Speadsheet!$E$3:$BL$3,K$14,PnL_Speadsheet!$E12:$BL12)/1000 -> 0 | L26: =SUMIF(PnL_Speadsheet!$E$3:$BL$3,L$14,PnL_Speadsheet!$E12:$BL12)/1000 -> 0 | M26: =SUMIF(PnL_Speadsheet!$E$3:$BL$3,M$14,PnL_Speadsheet!$E12:$BL12)/1000 -> 0 | N26: =SUMIF(PnL_Speadsheet!$E$3:$BL$3,N$14,PnL_Speadsheet!$E12:$BL12)/1000 -> 0 | O26: =SUMIF(PnL_Speadsheet!$E$3:$BL$3,O$14,PnL_Speadsheet!$E12:$BL12)/1000 -> 0 | P26: =SUMIF(PnL_Speadsheet!$E$3:$BL$3,P$14,PnL_Speadsheet!$E12:$BL12)/1000 -> 0
H27: NFI | J27: =SUM(K27:U27) -> 0 | K27: =SUMIF(PnL_Speadsheet!$E$3:$BL$3,K$14,PnL_Speadsheet!$E13:$BL13)/1000 -> 0 | L27: =SUMIF(PnL_Speadsheet!$E$3:$BL$3,L$14,PnL_Speadsheet!$E13:$BL13)/1000 -> 0 | M27: =SUMIF(PnL_Speadsheet!$E$3:$BL$3,M$14,PnL_Speadsheet!$E13:$BL13)/1000 -> 0 | N27: =SUMIF(PnL_Speadsheet!$E$3:$BL$3,N$14,PnL_Speadsheet!$E13:$BL13)/1000 -> 0 | O27: =SUMIF(PnL_Speadsheet!$E$3:$BL$3,O$14,PnL_Speadsheet!$E13:$BL13)/1000 -> 0 | P27: =SUMIF(PnL_Speadsheet!$E$3:$BL$3,P$14,PnL_Speadsheet!$E13:$BL13)/1000 -> 0
H28: Annual fee | J28: =SUM(K28:U28) -> 0 | K28: =SUMIF(PnL_Speadsheet!$E$3:$BL$3,K$14,PnL_Speadsheet!$E14:$BL14)/1000 -> 0 | L28: =SUMIF(PnL_Speadsheet!$E$3:$BL$3,L$14,PnL_Speadsheet!$E14:$BL14)/1000 -> 0 | M28: =SUMIF(PnL_Speadsheet!$E$3:$BL$3,M$14,PnL_Speadsheet!$E14:$BL14)/1000 -> 0 | N28: =SUMIF(PnL_Speadsheet!$E$3:$BL$3,N$14,PnL_Speadsheet!$E14:$BL14)/1000 -> 0 | O28: =SUMIF(PnL_Speadsheet!$E$3:$BL$3,O$14,PnL_Speadsheet!$E14:$BL14)/1000 -> 0 | P28: =SUMIF(PnL_Speadsheet!$E$3:$BL$3,P$14,PnL_Speadsheet!$E14:$BL14)/1000 -> 0
H29: Monthly fee | J29: =SUM(K29:U29) -> 0 | K29: =SUMIF(PnL_Speadsheet!$E$3:$BL$3,K$14,PnL_Speadsheet!$E15:$BL15)/1000 -> 0 | L29: =SUMIF(PnL_Speadsheet!$E$3:$BL$3,L$14,PnL_Speadsheet!$E15:$BL15)/1000 -> 0 | M29: =SUMIF(PnL_Speadsheet!$E$3:$BL$3,M$14,PnL_Speadsheet!$E15:$BL15)/1000 -> 0 | N29: =SUMIF(PnL_Speadsheet!$E$3:$BL$3,N$14,PnL_Speadsheet!$E15:$BL15)/1000 -> 0 | O29: =SUMIF(PnL_Speadsheet!$E$3:$BL$3,O$14,PnL_Speadsheet!$E15:$BL15)/1000 -> 0 | P29: =SUMIF(PnL_Speadsheet!$E$3:$BL$3,P$14,PnL_Speadsheet!$E15:$BL15)/1000 -> 0
H30: Transaction fee | J30: =SUM(K30:U30) -> 0 | K30: =SUMIF(PnL_Speadsheet!$E$3:$BL$3,K$14,PnL_Speadsheet!$E16:$BL16)/1000 -> 0 | L30: =SUMIF(PnL_Speadsheet!$E$3:$BL$3,L$14,PnL_Speadsheet!$E16:$BL16)/1000 -> 0 | M30: =SUMIF(PnL_Speadsheet!$E$3:$BL$3,M$14,PnL_Speadsheet!$E16:$BL16)/1000 -> 0 | N30: =SUMIF(PnL_Speadsheet!$E$3:$BL$3,N$14,PnL_Speadsheet!$E16:$BL16)/1000 -> 0 | O30: =SUMIF(PnL_Speadsheet!$E$3:$BL$3,O$14,PnL_Speadsheet!$E16:$BL16)/1000 -> 0 | P30: =SUMIF(PnL_Speadsheet!$E$3:$BL$3,P$14,PnL_Speadsheet!$E16:$BL16)/1000 -> 0
H31: Issuance fee | J31: =SUM(K31:U31) -> 0 | K31: =SUMIF(PnL_Speadsheet!$E$3:$BL$3,K$14,PnL_Speadsheet!$E17:$BL17)/1000 -> 0 | L31: =SUMIF(PnL_Speadsheet!$E$3:$BL$3,L$14,PnL_Speadsheet!$E17:$BL17)/1000 -> 0 | M31: =SUMIF(PnL_Speadsheet!$E$3:$BL$3,M$14,PnL_Speadsheet!$E17:$BL17)/1000 -> 0 | N31: =SUMIF(PnL_Speadsheet!$E$3:$BL$3,N$14,PnL_Speadsheet!$E17:$BL17)/1000 -> 0 | O31: =SUMIF(PnL_Speadsheet!$E$3:$BL$3,O$14,PnL_Speadsheet!$E17:$BL17)/1000 -> 0 | P31: =SUMIF(PnL_Speadsheet!$E$3:$BL$3,P$14,PnL_Speadsheet!$E17:$BL17)/1000 -> 0
H32: Termination fee | J32: =SUM(K32:U32) -> 0 | K32: =SUMIF(PnL_Speadsheet!$E$3:$BL$3,K$14,PnL_Speadsheet!$E18:$BL18)/1000 -> 0 | L32: =SUMIF(PnL_Speadsheet!$E$3:$BL$3,L$14,PnL_Speadsheet!$E18:$BL18)/1000 -> 0 | M32: =SUMIF(PnL_Speadsheet!$E$3:$BL$3,M$14,PnL_Speadsheet!$E18:$BL18)/1000 -> 0 | N32: =SUMIF(PnL_Speadsheet!$E$3:$BL$3,N$14,PnL_Speadsheet!$E18:$BL18)/1000 -> 0 | O32: =SUMIF(PnL_Speadsheet!$E$3:$BL$3,O$14,PnL_Speadsheet!$E18:$BL18)/1000 -> 0 | P32: =SUMIF(PnL_Speadsheet!$E$3:$BL$3,P$14,PnL_Speadsheet!$E18:$BL18)/1000 -> 0
H33: Late payment | J33: =SUM(K33:U33) -> 0 | K33: =SUMIF(PnL_Speadsheet!$E$3:$BL$3,K$14,PnL_Speadsheet!$E19:$BL19)/1000 -> 0 | L33: =SUMIF(PnL_Speadsheet!$E$3:$BL$3,L$14,PnL_Speadsheet!$E19:$BL19)/1000 -> 0 | M33: =SUMIF(PnL_Speadsheet!$E$3:$BL$3,M$14,PnL_Speadsheet!$E19:$BL19)/1000 -> 0 | N33: =SUMIF(PnL_Speadsheet!$E$3:$BL$3,N$14,PnL_Speadsheet!$E19:$BL19)/1000 -> 0 | O33: =SUMIF(PnL_Speadsheet!$E$3:$BL$3,O$14,PnL_Speadsheet!$E19:$BL19)/1000 -> 0 | P33: =SUMIF(PnL_Speadsheet!$E$3:$BL$3,P$14,PnL_Speadsheet!$E19:$BL19)/1000 -> 0
H34: Min due fee | J34: =SUM(K34:U34) -> 0 | K34: =SUMIF(PnL_Speadsheet!$E$3:$BL$3,K$14,PnL_Speadsheet!$E20:$BL20)/1000 -> 0 | L34: =SUMIF(PnL_Speadsheet!$E$3:$BL$3,L$14,PnL_Speadsheet!$E20:$BL20)/1000 -> 0 | M34: =SUMIF(PnL_Speadsheet!$E$3:$BL$3,M$14,PnL_Speadsheet!$E20:$BL20)/1000 -> 0 | N34: =SUMIF(PnL_Speadsheet!$E$3:$BL$3,N$14,PnL_Speadsheet!$E20:$BL20)/1000 -> 0 | O34: =SUMIF(PnL_Speadsheet!$E$3:$BL$3,O$14,PnL_Speadsheet!$E20:$BL20)/1000 -> 0 | P34: =SUMIF(PnL_Speadsheet!$E$3:$BL$3,P$14,PnL_Speadsheet!$E20:$BL20)/1000 -> 0
... H37: Fee suspended due to CIC | J37: =SUM(K37:U37) -> 0 | K37: =SUMIF(PnL_Speadsheet!$E$3:$BL$3,K$14,PnL_Speadsheet!$E23:$BL23)/1000 -> 0 | L37: =SUMIF(PnL_Speadsheet!$E$3:$BL$3,L$14,PnL_Speadsheet!$E23:$BL23)/1000 -> 0 | M37: =SUMIF(PnL_Speadsheet!$E$3:$BL$3,M$14,PnL_Speadsheet!$E23:$BL23)/1000 -> 0 | N37: =SUMIF(PnL_Speadsheet!$E$3:$BL$3,N$14,PnL_Speadsheet!$E23:$BL23)/1000 -> 0 | O37: =SUMIF(PnL_Speadsheet!$E$3:$BL$3,O$14,PnL_Speadsheet!$E23:$BL23)/1000 -> 0 | P37: =SUMIF(PnL_Speadsheet!$E$3:$BL$3,P$14,PnL_Speadsheet!$E23:$BL23)/1000 -> 0
H38: OPEX | J38: =SUM(K38:U38) -> 0 | K38: =(SUMIF(PnL_Speadsheet!$E$3:$BL$3,K$14,PnL_Speadsheet!$E24:$BL24)/1000) -> 0 | L38: =(SUMIF(PnL_Speadsheet!$E$3:$BL$3,L$14,PnL_Speadsheet!$E24:$BL24)/1000) -> 0 | M38: =(SUMIF(PnL_Speadsheet!$E$3:$BL$3,M$14,PnL_Speadsheet!$E24:$BL24)/1000) -> 0 | N38: =(SUMIF(PnL_Speadsheet!$E$3:$BL$3,N$14,PnL_Speadsheet!$E24:$BL24)/1000) -> 0 | O38: =(SUMIF(PnL_Speadsheet!$E$3:$BL$3,O$14,PnL_Speadsheet!$E24:$BL24)/1000) -> 0 | P38: =(SUMIF(PnL_Speadsheet!$E$3:$BL$3,P$14,PnL_Speadsheet!$E24:$BL24)/1000) -> 0
H39: Sharing to partner | J39: =SUM(K39:U39) -> 0 | K39: =(SUMIF(PnL_Speadsheet!$E$3:$BL$3,K$14,PnL_Speadsheet!$E25:$BL25)/1000)-K40 -> 0 | L39: =(SUMIF(PnL_Speadsheet!$E$3:$BL$3,L$14,PnL_Speadsheet!$E25:$BL25)/1000)-L40 -> 0 | M39: =(SUMIF(PnL_Speadsheet!$E$3:$BL$3,M$14,PnL_Speadsheet!$E25:$BL25)/1000)-M40 -> 0 | N39: =(SUMIF(PnL_Speadsheet!$E$3:$BL$3,N$14,PnL_Speadsheet!$E25:$BL25)/1000)-N40 -> 0 | O39: =(SUMIF(PnL_Speadsheet!$E$3:$BL$3,O$14,PnL_Speadsheet!$E25:$BL25)/1000)-O40 -> 0 | P39: =(SUMIF(PnL_Speadsheet!$E$3:$BL$3,P$14,PnL_Speadsheet!$E25:$BL25)/1000)-P40 -> 0
H40: Marketing acquisition | J40: =SUM(K40:U40) -> 0 | K40: =SUMIF(PnL_Speadsheet!$E$3:$BL$3,K$14,PnL_Speadsheet!$E29:$BL29)/1000 -> 0 | L40: =SUMIF(PnL_Speadsheet!$E$3:$BL$3,L$14,PnL_Speadsheet!$E29:$BL29)/1000 -> 0 | M40: =SUMIF(PnL_Speadsheet!$E$3:$BL$3,M$14,PnL_Speadsheet!$E29:$BL29)/1000 -> 0 | N40: =SUMIF(PnL_Speadsheet!$E$3:$BL$3,N$14,PnL_Speadsheet!$E29:$BL29)/1000 -> 0 | O40: =SUMIF(PnL_Speadsheet!$E$3:$BL$3,O$14,PnL_Speadsheet!$E29:$BL29)/1000 -> 0 | P40: =SUMIF(PnL_Speadsheet!$E$3:$BL$3,P$14,PnL_Speadsheet!$E29:$BL29)/1000 -> 0
H41: Marketing promotion | J41: =SUM(K41:U41) -> 0 | K41: =(SUMIF(PnL_Speadsheet!$E$3:$BL$3,K$14,PnL_Speadsheet!$E30:$BL30)/1000) -> 0 | L41: =(SUMIF(PnL_Speadsheet!$E$3:$BL$3,L$14,PnL_Speadsheet!$E30:$BL30)/1000) -> 0 | M41: =(SUMIF(PnL_Speadsheet!$E$3:$BL$3,M$14,PnL_Speadsheet!$E30:$BL30)/1000) -> 0 | N41: =(SUMIF(PnL_Speadsheet!$E$3:$BL$3,N$14,PnL_Speadsheet!$E30:$BL30)/1000) -> 0 | O41: =(SUMIF(PnL_Speadsheet!$E$3:$BL$3,O$14,PnL_Speadsheet!$E30:$BL30)/1000) -> 0 | P41: =(SUMIF(PnL_Speadsheet!$E$3:$BL$3,P$14,PnL_Speadsheet!$E30:$BL30)/1000) -> 0
H42: UW & Disbursal | J42: =SUM(K42:U42) -> 0 | K42: =SUMIF(PnL_Speadsheet!$E$3:$BL$3,K$14,PnL_Speadsheet!$E31:$BL31)/1000 -> 0 | L42: =SUMIF(PnL_Speadsheet!$E$3:$BL$3,L$14,PnL_Speadsheet!$E31:$BL31)/1000 -> 0 | M42: =SUMIF(PnL_Speadsheet!$E$3:$BL$3,M$14,PnL_Speadsheet!$E31:$BL31)/1000 -> 0 | N42: =SUMIF(PnL_Speadsheet!$E$3:$BL$3,N$14,PnL_Speadsheet!$E31:$BL31)/1000 -> 0 | O42: =SUMIF(PnL_Speadsheet!$E$3:$BL$3,O$14,PnL_Speadsheet!$E31:$BL31)/1000 -> 0 | P42: =SUMIF(PnL_Speadsheet!$E$3:$BL$3,P$14,PnL_Speadsheet!$E31:$BL31)/1000 -> 0
H43: Collection & AMC | J43: =SUM(K43:U43) -> 0 | K43: =SUMIF(PnL_Speadsheet!$E$3:$BL$3,K$14,PnL_Speadsheet!$E32:$BL32)/1000 -> 0 | L43: =SUMIF(PnL_Speadsheet!$E$3:$BL$3,L$14,PnL_Speadsheet!$E32:$BL32)/1000 -> 0 | M43: =SUMIF(PnL_Speadsheet!$E$3:$BL$3,M$14,PnL_Speadsheet!$E32:$BL32)/1000 -> 0 | N43: =SUMIF(PnL_Speadsheet!$E$3:$BL$3,N$14,PnL_Speadsheet!$E32:$BL32)/1000 -> 0 | O43: =SUMIF(PnL_Speadsheet!$E$3:$BL$3,O$14,PnL_Speadsheet!$E32:$BL32)/1000 -> 0 | P43: =SUMIF(PnL_Speadsheet!$E$3:$BL$3,P$14,PnL_Speadsheet!$E32:$BL32)/1000 -> 0
H44: After-sales services | J44: =SUM(K44:U44) -> 0 | K44: =SUMIF(PnL_Speadsheet!$E$3:$BL$3,K$14,PnL_Speadsheet!$E35:$BL35)/1000 -> 0 | L44: =SUMIF(PnL_Speadsheet!$E$3:$BL$3,L$14,PnL_Speadsheet!$E35:$BL35)/1000 -> 0 | M44: =SUMIF(PnL_Speadsheet!$E$3:$BL$3,M$14,PnL_Speadsheet!$E35:$BL35)/1000 -> 0 | N44: =SUMIF(PnL_Speadsheet!$E$3:$BL$3,N$14,PnL_Speadsheet!$E35:$BL35)/1000 -> 0 | O44: =SUMIF(PnL_Speadsheet!$E$3:$BL$3,O$14,PnL_Speadsheet!$E35:$BL35)/1000 -> 0 | P44: =SUMIF(PnL_Speadsheet!$E$3:$BL$3,P$14,PnL_Speadsheet!$E35:$BL35)/1000 -> 0
H45: Other support units | J45: =SUM(K45:U45) -> 0 | K45: =SUMIF(PnL_Speadsheet!$E$3:$BL$3,K$14,PnL_Speadsheet!$E36:$BL36)/1000 -> 0 | L45: =SUMIF(PnL_Speadsheet!$E$3:$BL$3,L$14,PnL_Speadsheet!$E36:$BL36)/1000 -> 0 | M45: =SUMIF(PnL_Speadsheet!$E$3:$BL$3,M$14,PnL_Speadsheet!$E36:$BL36)/1000 -> 0 | N45: =SUMIF(PnL_Speadsheet!$E$3:$BL$3,N$14,PnL_Speadsheet!$E36:$BL36)/1000 -> 0 | O45: =SUMIF(PnL_Speadsheet!$E$3:$BL$3,O$14,PnL_Speadsheet!$E36:$BL36)/1000 -> 0 | P45: =SUMIF(PnL_Speadsheet!$E$3:$BL$3,P$14,PnL_Speadsheet!$E36:$BL36)/1000 -> 0
H46: PROVISION | J46: =SUM(K46:U46) -> 0 | K46: =SUMIF(PnL_Speadsheet!$E$3:$BL$3,K$14,PnL_Speadsheet!$E37:$BL37)/1000 -> 0 | L46: =SUMIF(PnL_Speadsheet!$E$3:$BL$3,L$14,PnL_Speadsheet!$E37:$BL37)/1000 -> 0 | M46: =SUMIF(PnL_Speadsheet!$E$3:$BL$3,M$14,PnL_Speadsheet!$E37:$BL37)/1000 -> 0 | N46: =SUMIF(PnL_Speadsheet!$E$3:$BL$3,N$14,PnL_Speadsheet!$E37:$BL37)/1000 -> 0 | O46: =SUMIF(PnL_Speadsheet!$E$3:$BL$3,O$14,PnL_Speadsheet!$E37:$BL37)/1000 -> 0 | P46: =SUMIF(PnL_Speadsheet!$E$3:$BL$3,P$14,PnL_Speadsheet!$E37:$BL37)/1000 -> 0
H47: Other income | J47: =SUM(K47:U47) -> 0 | K47: =SUMIF(PnL_Speadsheet!$E$3:$BL$3,K$14,PnL_Speadsheet!$E38:$BL38)/1000 -> 0 | L47: =SUMIF(PnL_Speadsheet!$E$3:$BL$3,L$14,PnL_Speadsheet!$E38:$BL38)/1000 -> 0 | M47: =SUMIF(PnL_Speadsheet!$E$3:$BL$3,M$14,PnL_Speadsheet!$E38:$BL38)/1000 -> 0 | N47: =SUMIF(PnL_Speadsheet!$E$3:$BL$3,N$14,PnL_Speadsheet!$E38:$BL38)/1000 -> 0 | O47: =SUMIF(PnL_Speadsheet!$E$3:$BL$3,O$14,PnL_Speadsheet!$E38:$BL38)/1000 -> 0 | P47: =SUMIF(PnL_Speadsheet!$E$3:$BL$3,P$14,PnL_Speadsheet!$E38:$BL38)/1000 -> 0
H48: PBT | J48: =SUM(K48:U48) -> 0 | K48: =SUMIF(PnL_Speadsheet!$E$3:$BL$3,K$14,PnL_Speadsheet!$E39:$BL39)/1000 -> 0 | L48: =SUMIF(PnL_Speadsheet!$E$3:$BL$3,L$14,PnL_Speadsheet!$E39:$BL39)/1000 -> 0 | M48: =SUMIF(PnL_Speadsheet!$E$3:$BL$3,M$14,PnL_Speadsheet!$E39:$BL39)/1000 -> 0 | N48: =SUMIF(PnL_Speadsheet!$E$3:$BL$3,N$14,PnL_Speadsheet!$E39:$BL39)/1000 -> 0 | O48: =SUMIF(PnL_Speadsheet!$E$3:$BL$3,O$14,PnL_Speadsheet!$E39:$BL39)/1000 -> 0 | P48: =SUMIF(PnL_Speadsheet!$E$3:$BL$3,P$14,PnL_Speadsheet!$E39:$BL39)/1000 -> 0
H49: In which: PROFIT BEFORE SUPPORT COST | J49: =SUM(K49:U49) -> 0 | K49: =K23+K46+SUM(K41:K44) -> 0 | L49: =L23+L46+SUM(L41:L44) -> 0 | M49: =M23+M46+SUM(M41:M44) -> 0 | N49: =N23+N46+SUM(N41:N44) -> 0 | O49: =O23+O46+SUM(O41:O44) -> 0 | P49: =P23+P46+SUM(P41:P44) -> 0

Sheet PnL_Speadsheet
C1: ='Sales plan& PnL'!H1 -> DPD180+ | D1: PL PROJECTION
D2: 60 months
E3: =YEAR(E4) -> 2025 | F3: =YEAR(F4) -> 2025 | G3: =YEAR(G4) -> 2025 | H3: =YEAR(H4) -> 2025 | I3: =YEAR(I4) -> 2025 | J3: =YEAR(J4) -> 2025 | K3: =YEAR(K4) -> 2025 | L3: =YEAR(L4) -> 2025 | ... BL3: =YEAR(BL4) -> 2029
D4: Business month | E4: ='Sales plan& PnL'!J8 -> 45658 | F4: ='Sales plan& PnL'!K8 -> 45716 | G4: ='Sales plan& PnL'!L8 -> 45747 | H4: ='Sales plan& PnL'!M8 -> 45777 | I4: ='Sales plan& PnL'!N8 -> 45808 | J4: ='Sales plan& PnL'!O8 -> 45838 | K4: ='Sales plan& PnL'!P8 -> 45869 | L4: ='Sales plan& PnL'!Q8 -> 45900 | ... BL4: ='Sales plan& PnL'!BQ8 -> 47483
D5: Month on board | E5: =1 -> 1 | F5: =E5+1 -> 2 | G5: =F5+1 -> 3 | H5: =G5+1 -> 4 | I5: =H5+1 -> 5 | J5: =I5+1 -> 6 | K5: =J5+1 -> 7 | L5: =K5+1 -> 8 | M5: =L5+1 -> 9 | ... BL5: =BK5+1 -> 60
D6: Unit: mVND
D7: ENR | E7: {=SUMPRODUCT(E$63:E$122,TRANSPOSE(SAP_Spreadsheet!$G$172:$BN$172))} -> 0 | F7: {=SUMPRODUCT(F$63:F$122,TRANSPOSE(SAP_Spreadsheet!$G$172:$BN$172))} -> 0 | G7: {=SUMPRODUCT(G$63:G$122,TRANSPOSE(SAP_Spreadsheet!$G$172:$BN$172))} -> 0 | H7: {=SUMPRODUCT(H$63:H$122,TRANSPOSE(SAP_Spreadsheet!$G$172:$BN$172))} -> 0 | I7: {=SUMPRODUCT(I$63:I$122,TRANSPOSE(SAP_Spreadsheet!$G$172:$BN$172))} -> 0 | J7: {=SUMPRODUCT(J$63:J$122,TRANSPOSE(SAP_Spreadsheet!$G$172:$BN$172))} -> 0 | K7: {=SUMPRODUCT(K$63:K$122,TRANSPOSE(SAP_Spreadsheet!$G$172:$BN$172))} -> 0 | L7: {=SUMPRODUCT(L$63:L$122,TRANSPOSE(SAP_Spreadsheet!$G$172:$BN$172))} -> 0 | ... BL7: {=SUMPRODUCT(BL$63:BL$122,TRANSPOSE(SAP_Spreadsheet!$G$172:$BN$172))} -> 0
D8: ANR | E8: {=SUMPRODUCT(E$63:E$122,TRANSPOSE(SAP_Spreadsheet!$G$202:$BN$202))} -> 0 | F8: {=SUMPRODUCT(F$63:F$122,TRANSPOSE(SAP_Spreadsheet!$G$202:$BN$202))} -> 0 | G8: {=SUMPRODUCT(G$63:G$122,TRANSPOSE(SAP_Spreadsheet!$G$202:$BN$202))} -> 0 | H8: {=SUMPRODUCT(H$63:H$122,TRANSPOSE(SAP_Spreadsheet!$G$202:$BN$202))} -> 0 | I8: {=SUMPRODUCT(I$63:I$122,TRANSPOSE(SAP_Spreadsheet!$G$202:$BN$202))} -> 0 | J8: {=SUMPRODUCT(J$63:J$122,TRANSPOSE(SAP_Spreadsheet!$G$202:$BN$202))} -> 0 | K8: {=SUMPRODUCT(K$63:K$122,TRANSPOSE(SAP_Spreadsheet!$G$202:$BN$202))} -> 0 | L8: {=SUMPRODUCT(L$63:L$122,TRANSPOSE(SAP_Spreadsheet!$G$202:$BN$202))} -> 0 | ... BL8: {=SUMPRODUCT(BL$63:BL$122,TRANSPOSE(SAP_Spreadsheet!$G$202:$BN$202))} -> 0
D9: TOI | E9: {=SUMPRODUCT(E$63:E$122,TRANSPOSE(SAP_Spreadsheet!$G$239:$BN$239))} -> 0 | F9: {=SUMPRODUCT(F$63:F$122,TRANSPOSE(SAP_Spreadsheet!$G$239:$BN$239))} -> 0 | G9: {=SUMPRODUCT(G$63:G$122,TRANSPOSE(SAP_Spreadsheet!$G$239:$BN$239))} -> 0 | H9: {=SUMPRODUCT(H$63:H$122,TRANSPOSE(SAP_Spreadsheet!$G$239:$BN$239))} -> 0 | I9: {=SUMPRODUCT(I$63:I$122,TRANSPOSE(SAP_Spreadsheet!$G$239:$BN$239))} -> 0 | J9: {=SUMPRODUCT(J$63:J$122,TRANSPOSE(SAP_Spreadsheet!$G$239:$BN$239))} -> 0 | K9: {=SUMPRODUCT(K$63:K$122,TRANSPOSE(SAP_Spreadsheet!$G$239:$BN$239))} -> 0 | L9: {=SUMPRODUCT(L$63:L$122,TRANSPOSE(SAP_Spreadsheet!$G$239:$BN$239))} -> 0 | ... BL9: {=SUMPRODUCT(BL$63:BL$122,TRANSPOSE(SAP_Spreadsheet!$G$239:$BN$239))} -> 0
D10: Net interest income | E10: {=SUMPRODUCT(E$63:E$122,TRANSPOSE(SAP_Spreadsheet!$G$220:$BN$220))} -> 0 | F10: {=SUMPRODUCT(F$63:F$122,TRANSPOSE(SAP_Spreadsheet!$G$220:$BN$220))} -> 0 | G10: {=SUMPRODUCT(G$63:G$122,TRANSPOSE(SAP_Spreadsheet!$G$220:$BN$220))} -> 0 | H10: {=SUMPRODUCT(H$63:H$122,TRANSPOSE(SAP_Spreadsheet!$G$220:$BN$220))} -> 0 | I10: {=SUMPRODUCT(I$63:I$122,TRANSPOSE(SAP_Spreadsheet!$G$220:$BN$220))} -> 0 | J10: {=SUMPRODUCT(J$63:J$122,TRANSPOSE(SAP_Spreadsheet!$G$220:$BN$220))} -> 0 | K10: {=SUMPRODUCT(K$63:K$122,TRANSPOSE(SAP_Spreadsheet!$G$220:$BN$220))} -> 0 | L10: {=SUMPRODUCT(L$63:L$122,TRANSPOSE(SAP_Spreadsheet!$G$220:$BN$220))} -> 0 | ... BL10: {=SUMPRODUCT(BL$63:BL$122,TRANSPOSE(SAP_Spreadsheet!$G$220:$BN$220))} -> 0
D11: CII | E11: {=SUMPRODUCT(E$63:E$122,TRANSPOSE(SAP_Spreadsheet!$G$216:$BN$216))} -> 0 | F11: {=SUMPRODUCT(F$63:F$122,TRANSPOSE(SAP_Spreadsheet!$G$216:$BN$216))} -> 0 | G11: {=SUMPRODUCT(G$63:G$122,TRANSPOSE(SAP_Spreadsheet!$G$216:$BN$216))} -> 0 | H11: {=SUMPRODUCT(H$63:H$122,TRANSPOSE(SAP_Spreadsheet!$G$216:$BN$216))} -> 0 | I11: {=SUMPRODUCT(I$63:I$122,TRANSPOSE(SAP_Spreadsheet!$G$216:$BN$216))} -> 0 | J11: {=SUMPRODUCT(J$63:J$122,TRANSPOSE(SAP_Spreadsheet!$G$216:$BN$216))} -> 0 | K11: {=SUMPRODUCT(K$63:K$122,TRANSPOSE(SAP_Spreadsheet!$G$216:$BN$216))} -> 0 | L11: {=SUMPRODUCT(L$63:L$122,TRANSPOSE(SAP_Spreadsheet!$G$216:$BN$216))} -> 0 | ... BL11: {=SUMPRODUCT(BL$63:BL$122,TRANSPOSE(SAP_Spreadsheet!$G$216:$BN$216))} -> 0
D12: COF | E12: {=SUMPRODUCT(E$63:E$122,TRANSPOSE(SAP_Spreadsheet!$G$219:$BN$219))} -> 0 | F12: {=SUMPRODUCT(F$63:F$122,TRANSPOSE(SAP_Spreadsheet!$G$219:$BN$219))} -> 0 | G12: {=SUMPRODUCT(G$63:G$122,TRANSPOSE(SAP_Spreadsheet!$G$219:$BN$219))} -> 0 | H12: {=SUMPRODUCT(H$63:H$122,TRANSPOSE(SAP_Spreadsheet!$G$219:$BN$219))} -> 0 | I12: {=SUMPRODUCT(I$63:I$122,TRANSPOSE(SAP_Spreadsheet!$G$219:$BN$219))} -> 0 | J12: {=SUMPRODUCT(J$63:J$122,TRANSPOSE(SAP_Spreadsheet!$G$219:$BN$219))} -> 0 | K12: {=SUMPRODUCT(K$63:K$122,TRANSPOSE(SAP_Spreadsheet!$G$219:$BN$219))} -> 0 | L12: {=SUMPRODUCT(L$63:L$122,TRANSPOSE(SAP_Spreadsheet!$G$219:$BN$219))} -> 0 | ... BL12: {=SUMPRODUCT(BL$63:BL$122,TRANSPOSE(SAP_Spreadsheet!$G$219:$BN$219))} -> 0
D13: Net fee income | E13: {=SUMPRODUCT(E$63:E$122,TRANSPOSE(SAP_Spreadsheet!$G$237:$BN$237))} -> 0 | F13: {=SUMPRODUCT(F$63:F$122,TRANSPOSE(SAP_Spreadsheet!$G$237:$BN$237))} -> 0 | G13: {=SUMPRODUCT(G$63:G$122,TRANSPOSE(SAP_Spreadsheet!$G$237:$BN$237))} -> 0 | H13: {=SUMPRODUCT(H$63:H$122,TRANSPOSE(SAP_Spreadsheet!$G$237:$BN$237))} -> 0 | I13: {=SUMPRODUCT(I$63:I$122,TRANSPOSE(SAP_Spreadsheet!$G$237:$BN$237))} -> 0 | J13: {=SUMPRODUCT(J$63:J$122,TRANSPOSE(SAP_Spreadsheet!$G$237:$BN$237))} -> 0 | K13: {=SUMPRODUCT(K$63:K$122,TRANSPOSE(SAP_Spreadsheet!$G$237:$BN$237))} -> 0 | L13: {=SUMPRODUCT(L$63:L$122,TRANSPOSE(SAP_Spreadsheet!$G$237:$BN$237))} -> 0 | ... BL13: {=SUMPRODUCT(BL$63:BL$122,TRANSPOSE(SAP_Spreadsheet!$G$237:$BN$237))} -> 0
D14: Annual fee | E14: {=SUMPRODUCT(E$63:E$122,TRANSPOSE(SAP_Spreadsheet!$G$222:$BN$222))} -> 0 | F14: {=SUMPRODUCT(F$63:F$122,TRANSPOSE(SAP_Spreadsheet!$G$222:$BN$222))} -> 0 | G14: {=SUMPRODUCT(G$63:G$122,TRANSPOSE(SAP_Spreadsheet!$G$222:$BN$222))} -> 0 | H14: {=SUMPRODUCT(H$63:H$122,TRANSPOSE(SAP_Spreadsheet!$G$222:$BN$222))} -> 0 | I14: {=SUMPRODUCT(I$63:I$122,TRANSPOSE(SAP_Spreadsheet!$G$222:$BN$222))} -> 0 | J14: {=SUMPRODUCT(J$63:J$122,TRANSPOSE(SAP_Spreadsheet!$G$222:$BN$222))} -> 0 | K14: {=SUMPRODUCT(K$63:K$122,TRANSPOSE(SAP_Spreadsheet!$G$222:$BN$222))} -> 0 | L14: {=SUMPRODUCT(L$63:L$122,TRANSPOSE(SAP_Spreadsheet!$G$222:$BN$222))} -> 0 | ... BL14: {=SUMPRODUCT(BL$63:BL$122,TRANSPOSE(SAP_Spreadsheet!$G$222:$BN$222))} -> 0
D15: Monthly fee | E15: {=SUMPRODUCT(E$63:E$122,TRANSPOSE(SAP_Spreadsheet!$G$223:$BN$223))} -> 0 | F15: {=SUMPRODUCT(F$63:F$122,TRANSPOSE(SAP_Spreadsheet!$G$223:$BN$223))} -> 0 | G15: {=SUMPRODUCT(G$63:G$122,TRANSPOSE(SAP_Spreadsheet!$G$223:$BN$223))} -> 0 | H15: {=SUMPRODUCT(H$63:H$122,TRANSPOSE(SAP_Spreadsheet!$G$223:$BN$223))} -> 0 | I15: {=SUMPRODUCT(I$63:I$122,TRANSPOSE(SAP_Spreadsheet!$G$223:$BN$223))} -> 0 | J15: {=SUMPRODUCT(J$63:J$122,TRANSPOSE(SAP_Spreadsheet!$G$223:$BN$223))} -> 0 | K15: {=SUMPRODUCT(K$63:K$122,TRANSPOSE(SAP_Spreadsheet!$G$223:$BN$223))} -> 0 | L15: {=SUMPRODUCT(L$63:L$122,TRANSPOSE(SAP_Spreadsheet!$G$223:$BN$223))} -> 0 | ... BL15: {=SUMPRODUCT(BL$63:BL$122,TRANSPOSE(SAP_Spreadsheet!$G$223:$BN$223))} -> 0
D16: Transaction fee | E16: {=SUMPRODUCT(E$63:E$122,TRANSPOSE(SAP_Spreadsheet!$G$224:$BN$224))} -> 0 | F16: {=SUMPRODUCT(F$63:F$122,TRANSPOSE(SAP_Spreadsheet!$G$224:$BN$224))} -> 0 | G16: {=SUMPRODUCT(G$63:G$122,TRANSPOSE(SAP_Spreadsheet!$G$224:$BN$224))} -> 0 | H16: {=SUMPRODUCT(H$63:H$122,TRANSPOSE(SAP_Spreadsheet!$G$224:$BN$224))} -> 0 | I16: {=SUMPRODUCT(I$63:I$122,TRANSPOSE(SAP_Spreadsheet!$G$224:$BN$224))} -> 0 | J16: {=SUMPRODUCT(J$63:J$122,TRANSPOSE(SAP_Spreadsheet!$G$224:$BN$224))} -> 0 | K16: {=SUMPRODUCT(K$63:K$122,TRANSPOSE(SAP_Spreadsheet!$G$224:$BN$224))} -> 0 | L16: {=SUMPRODUCT(L$63:L$122,TRANSPOSE(SAP_Spreadsheet!$G$224:$BN$224))} -> 0 | ... BL16: {=SUMPRODUCT(BL$63:BL$122,TRANSPOSE(SAP_Spreadsheet!$G$224:$BN$224))} -> 0
D17: Issuance fee | E17: {=SUMPRODUCT(E$63:E$122,TRANSPOSE(SAP_Spreadsheet!$G$225:$BN$225))} -> 0 | F17: {=SUMPRODUCT(F$63:F$122,TRANSPOSE(SAP_Spreadsheet!$G$225:$BN$225))} -> 0 | G17: {=SUMPRODUCT(G$63:G$122,TRANSPOSE(SAP_Spreadsheet!$G$225:$BN$225))} -> 0 | H17: {=SUMPRODUCT(H$63:H$122,TRANSPOSE(SAP_Spreadsheet!$G$225:$BN$225))} -> 0 | I17: {=SUMPRODUCT(I$63:I$122,TRANSPOSE(SAP_Spreadsheet!$G$225:$BN$225))} -> 0 | J17: {=SUMPRODUCT(J$63:J$122,TRANSPOSE(SAP_Spreadsheet!$G$225:$BN$225))} -> 0 | K17: {=SUMPRODUCT(K$63:K$122,TRANSPOSE(SAP_Spreadsheet!$G$225:$BN$225))} -> 0 | L17: {=SUMPRODUCT(L$63:L$122,TRANSPOSE(SAP_Spreadsheet!$G$225:$BN$225))} -> 0 | ... BL17: {=SUMPRODUCT(BL$63:BL$122,TRANSPOSE(SAP_Spreadsheet!$G$225:$BN$225))} -> 0
D18: Termination fee | E18: {=SUMPRODUCT(E$63:E$122,TRANSPOSE(SAP_Spreadsheet!$G$226:$BN$226))} -> 0 | F18: {=SUMPRODUCT(F$63:F$122,TRANSPOSE(SAP_Spreadsheet!$G$226:$BN$226))} -> 0 | G18: {=SUMPRODUCT(G$63:G$122,TRANSPOSE(SAP_Spreadsheet!$G$226:$BN$226))} -> 0 | H18: {=SUMPRODUCT(H$63:H$122,TRANSPOSE(SAP_Spreadsheet!$G$226:$BN$226))} -> 0 | I18: {=SUMPRODUCT(I$63:I$122,TRANSPOSE(SAP_Spreadsheet!$G$226:$BN$226))} -> 0 | J18: {=SUMPRODUCT(J$63:J$122,TRANSPOSE(SAP_Spreadsheet!$G$226:$BN$226))} -> 0 | K18: {=SUMPRODUCT(K$63:K$122,TRANSPOSE(SAP_Spreadsheet!$G$226:$BN$226))} -> 0 | L18: {=SUMPRODUCT(L$63:L$122,TRANSPOSE(SAP_Spreadsheet!$G$226:$BN$226))} -> 0 | ... BL18: {=SUMPRODUCT(BL$63:BL$122,TRANSPOSE(SAP_Spreadsheet!$G$226:$BN$226))} -> 0
D19: Late payment | E19: {=SUMPRODUCT(E$63:E$122,TRANSPOSE(SAP_Spreadsheet!$G$227:$BN$227))} -> 0 | F19: {=SUMPRODUCT(F$63:F$122,TRANSPOSE(SAP_Spreadsheet!$G$227:$BN$227))} -> 0 | G19: {=SUMPRODUCT(G$63:G$122,TRANSPOSE(SAP_Spreadsheet!$G$227:$BN$227))} -> 0 | H19: {=SUMPRODUCT(H$63:H$122,TRANSPOSE(SAP_Spreadsheet!$G$227:$BN$227))} -> 0 | I19: {=SUMPRODUCT(I$63:I$122,TRANSPOSE(SAP_Spreadsheet!$G$227:$BN$227))} -> 0 | J19: {=SUMPRODUCT(J$63:J$122,TRANSPOSE(SAP_Spreadsheet!$G$227:$BN$227))} -> 0 | K19: {=SUMPRODUCT(K$63:K$122,TRANSPOSE(SAP_Spreadsheet!$G$227:$BN$227))} -> 0 | L19: {=SUMPRODUCT(L$63:L$122,TRANSPOSE(SAP_Spreadsheet!$G$227:$BN$227))} -> 0 | ... BL19: {=SUMPRODUCT(BL$63:BL$122,TRANSPOSE(SAP_Spreadsheet!$G$227:$BN$227))} -> 0
D20: Min due fee | E20: {=SUMPRODUCT(E$63:E$122,TRANSPOSE(SAP_Spreadsheet!$G$230:$BN$230))} -> 0 | F20: {=SUMPRODUCT(F$63:F$122,TRANSPOSE(SAP_Spreadsheet!$G$230:$BN$230))} -> 0 | G20: {=SUMPRODUCT(G$63:G$122,TRANSPOSE(SAP_Spreadsheet!$G$230:$BN$230))} -> 0 | H20: {=SUMPRODUCT(H$63:H$122,TRANSPOSE(SAP_Spreadsheet!$G$230:$BN$230))} -> 0 | I20: {=SUMPRODUCT(I$63:I$122,TRANSPOSE(SAP_Spreadsheet!$G$230:$BN$230))} -> 0 | J20: {=SUMPRODUCT(J$63:J$122,TRANSPOSE(SAP_Spreadsheet!$G$230:$BN$230))} -> 0 | K20: {=SUMPRODUCT(K$63:K$122,TRANSPOSE(SAP_Spreadsheet!$G$230:$BN$230))} -> 0 | L20: {=SUMPRODUCT(L$63:L$122,TRANSPOSE(SAP_Spreadsheet!$G$230:$BN$230))} -> 0 | ... BL20: {=SUMPRODUCT(BL$63:BL$122,TRANSPOSE(SAP_Spreadsheet!$G$230:$BN$230))} -> 0
D21: EMI fee | E21: {=SUMPRODUCT(E$63:E$122,TRANSPOSE(SAP_Spreadsheet!$G$231:$BN$231))} -> 0 | F21: {=SUMPRODUCT(F$63:F$122,TRANSPOSE(SAP_Spreadsheet!$G$231:$BN$231))} -> 0 | G21: {=SUMPRODUCT(G$63:G$122,TRANSPOSE(SAP_Spreadsheet!$G$231:$BN$231))} -> 0 | H21: {=SUMPRODUCT(H$63:H$122,TRANSPOSE(SAP_Spreadsheet!$G$231:$BN$231))} -> 0 | I21: {=SUMPRODUCT(I$63:I$122,TRANSPOSE(SAP_Spreadsheet!$G$231:$BN$231))} -> 0 | J21: {=SUMPRODUCT(J$63:J$122,TRANSPOSE(SAP_Spreadsheet!$G$231:$BN$231))} -> 0 | K21: {=SUMPRODUCT(K$63:K$122,TRANSPOSE(SAP_Spreadsheet!$G$231:$BN$231))} -> 0 | L21: {=SUMPRODUCT(L$63:L$122,TRANSPOSE(SAP_Spreadsheet!$G$231:$BN$231))} -> 0 | ... BL21: {=SUMPRODUCT(BL$63:BL$122,TRANSPOSE(SAP_Spreadsheet!$G$231:$BN$231))} -> 0
D22: EMI- Early termination fee | E22: {=SUMPRODUCT(E$63:E$122,TRANSPOSE(SAP_Spreadsheet!$G$235:$BN$235))} -> 0 | F22: {=SUMPRODUCT(F$63:F$122,TRANSPOSE(SAP_Spreadsheet!$G$235:$BN$235))} -> 0 | G22: {=SUMPRODUCT(G$63:G$122,TRANSPOSE(SAP_Spreadsheet!$G$235:$BN$235))} -> 0 | H22: {=SUMPRODUCT(H$63:H$122,TRANSPOSE(SAP_Spreadsheet!$G$235:$BN$235))} -> 0 | I22: {=SUMPRODUCT(I$63:I$122,TRANSPOSE(SAP_Spreadsheet!$G$235:$BN$235))} -> 0 | J22: {=SUMPRODUCT(J$63:J$122,TRANSPOSE(SAP_Spreadsheet!$G$235:$BN$235))} -> 0 | K22: {=SUMPRODUCT(K$63:K$122,TRANSPOSE(SAP_Spreadsheet!$G$235:$BN$235))} -> 0 | L22: {=SUMPRODUCT(L$63:L$122,TRANSPOSE(SAP_Spreadsheet!$G$235:$BN$235))} -> 0 | ... BL22: {=SUMPRODUCT(BL$63:BL$122,TRANSPOSE(SAP_Spreadsheet!$G$235:$BN$235))} -> 0
D23: Fee suspended due to CIC | E23: {=SUMPRODUCT(E$63:E$122,TRANSPOSE(SAP_Spreadsheet!$G$236:$BN$236))} -> 0 | F23: {=SUMPRODUCT(F$63:F$122,TRANSPOSE(SAP_Spreadsheet!$G$236:$BN$236))} -> 0 | G23: {=SUMPRODUCT(G$63:G$122,TRANSPOSE(SAP_Spreadsheet!$G$236:$BN$236))} -> 0 | H23: {=SUMPRODUCT(H$63:H$122,TRANSPOSE(SAP_Spreadsheet!$G$236:$BN$236))} -> 0 | I23: {=SUMPRODUCT(I$63:I$122,TRANSPOSE(SAP_Spreadsheet!$G$236:$BN$236))} -> 0 | J23: {=SUMPRODUCT(J$63:J$122,TRANSPOSE(SAP_Spreadsheet!$G$236:$BN$236))} -> 0 | K23: {=SUMPRODUCT(K$63:K$122,TRANSPOSE(SAP_Spreadsheet!$G$236:$BN$236))} -> 0 | L23: {=SUMPRODUCT(L$63:L$122,TRANSPOSE(SAP_Spreadsheet!$G$236:$BN$236))} -> 0 | ... BL23: {=SUMPRODUCT(BL$63:BL$122,TRANSPOSE(SAP_Spreadsheet!$G$236:$BN$236))} -> 0
D24: OPEX | E24: {=SUMPRODUCT(E$63:E$122,TRANSPOSE(SAP_Spreadsheet!$G$275:$BN$275))} -> 0 | F24: {=SUMPRODUCT(F$63:F$122,TRANSPOSE(SAP_Spreadsheet!$G$275:$BN$275))} -> 0 | G24: {=SUMPRODUCT(G$63:G$122,TRANSPOSE(SAP_Spreadsheet!$G$275:$BN$275))} -> 0 | H24: {=SUMPRODUCT(H$63:H$122,TRANSPOSE(SAP_Spreadsheet!$G$275:$BN$275))} -> 0 | I24: {=SUMPRODUCT(I$63:I$122,TRANSPOSE(SAP_Spreadsheet!$G$275:$BN$275))} -> 0 | J24: {=SUMPRODUCT(J$63:J$122,TRANSPOSE(SAP_Spreadsheet!$G$275:$BN$275))} -> 0 | K24: {=SUMPRODUCT(K$63:K$122,TRANSPOSE(SAP_Spreadsheet!$G$275:$BN$275))} -> 0 | L24: {=SUMPRODUCT(L$63:L$122,TRANSPOSE(SAP_Spreadsheet!$G$275:$BN$275))} -> 0 | ... BL24: {=SUMPRODUCT(BL$63:BL$122,TRANSPOSE(SAP_Spreadsheet!$G$275:$BN$275))} -> 0
D25: Sales team & mgt | E25: =SUM(E27:E29) -> 0 | F25: =SUM(F27:F29) -> 0 | G25: =SUM(G27:G29) -> 0 | H25: =SUM(H27:H29) -> 0 | I25: =SUM(I27:I29) -> 0 | J25: =SUM(J27:J29) -> 0 | K25: =SUM(K27:K29) -> 0 | L25: =SUM(L27:L29) -> 0 | ... BL25: =SUM(BL27:BL29) -> 0
D26: Lead acquisition | E26: {=SUMPRODUCT(E$63:E$122,TRANSPOSE(SAP_Spreadsheet!$G$244:$BN$244))} -> 0 | F26: {=SUMPRODUCT(F$63:F$122,TRANSPOSE(SAP_Spreadsheet!$G$244:$BN$244))} -> 0 | G26: {=SUMPRODUCT(G$63:G$122,TRANSPOSE(SAP_Spreadsheet!$G$244:$BN$244))} -> 0 | H26: {=SUMPRODUCT(H$63:H$122,TRANSPOSE(SAP_Spreadsheet!$G$244:$BN$244))} -> 0 | I26: {=SUMPRODUCT(I$63:I$122,TRANSPOSE(SAP_Spreadsheet!$G$244:$BN$244))} -> 0 | J26: {=SUMPRODUCT(J$63:J$122,TRANSPOSE(SAP_Spreadsheet!$G$244:$BN$244))} -> 0 | K26: {=SUMPRODUCT(K$63:K$122,TRANSPOSE(SAP_Spreadsheet!$G$244:$BN$244))} -> 0 | L26: {=SUMPRODUCT(L$63:L$122,TRANSPOSE(SAP_Spreadsheet!$G$244:$BN$244))} -> 0 | ... BL26: {=SUMPRODUCT(BL$63:BL$122,TRANSPOSE(SAP_Spreadsheet!$G$244:$BN$244))} -> 0
D27: Sharing TOI+RISKDPD90+ | E27: {=SUMPRODUCT(E$63:E$122,TRANSPOSE(SAP_Spreadsheet!$G$245:$BN$245))} -> 0 | F27: {=SUMPRODUCT(F$63:F$122,TRANSPOSE(SAP_Spreadsheet!$G$245:$BN$245))} -> 0 | G27: {=SUMPRODUCT(G$63:G$122,TRANSPOSE(SAP_Spreadsheet!$G$245:$BN$245))} -> 0 | H27: {=SUMPRODUCT(H$63:H$122,TRANSPOSE(SAP_Spreadsheet!$G$245:$BN$245))} -> 0 | I27: {=SUMPRODUCT(I$63:I$122,TRANSPOSE(SAP_Spreadsheet!$G$245:$BN$245))} -> 0 | J27: {=SUMPRODUCT(J$63:J$122,TRANSPOSE(SAP_Spreadsheet!$G$245:$BN$245))} -> 0 | K27: {=SUMPRODUCT(K$63:K$122,TRANSPOSE(SAP_Spreadsheet!$G$245:$BN$245))} -> 0 | L27: {=SUMPRODUCT(L$63:L$122,TRANSPOSE(SAP_Spreadsheet!$G$245:$BN$245))} -> 0 | ... BL27: {=SUMPRODUCT(BL$63:BL$122,TRANSPOSE(SAP_Spreadsheet!$G$245:$BN$245))} -> 0
D28: Sharing adjust | E28: {=SUMPRODUCT(E$63:E$122,TRANSPOSE(SAP_Spreadsheet!$G$245:$BN$245))} -> 0 | F28: {=SUMPRODUCT(F$63:F$122,TRANSPOSE(SAP_Spreadsheet!$G$245:$BN$245))} -> 0 | G28: {=SUMPRODUCT(G$63:G$122,TRANSPOSE(SAP_Spreadsheet!$G$245:$BN$245))} -> 0 | H28: {=SUMPRODUCT(H$63:H$122,TRANSPOSE(SAP_Spreadsheet!$G$245:$BN$245))} -> 0 | I28: {=SUMPRODUCT(I$63:I$122,TRANSPOSE(SAP_Spreadsheet!$G$245:$BN$245))} -> 0 | J28: {=SUMPRODUCT(J$63:J$122,TRANSPOSE(SAP_Spreadsheet!$G$245:$BN$245))} -> 0 | K28: {=SUMPRODUCT(K$63:K$122,TRANSPOSE(SAP_Spreadsheet!$G$245:$BN$245))} -> 0 | L28: {=SUMPRODUCT(L$63:L$122,TRANSPOSE(SAP_Spreadsheet!$G$245:$BN$245))} -> 0 | ... BL28: {=SUMPRODUCT(BL$63:BL$122,TRANSPOSE(SAP_Spreadsheet!$G$245:$BN$245))} -> 0
D29: Marketing cost for acquisition | E29: {=SUMPRODUCT(E$63:E$122,TRANSPOSE(SAP_Spreadsheet!$G$250:$BN$250))} -> 0 | F29: {=SUMPRODUCT(F$63:F$122,TRANSPOSE(SAP_Spreadsheet!$G$250:$BN$250))} -> 0 | G29: {=SUMPRODUCT(G$63:G$122,TRANSPOSE(SAP_Spreadsheet!$G$250:$BN$250))} -> 0 | H29: {=SUMPRODUCT(H$63:H$122,TRANSPOSE(SAP_Spreadsheet!$G$250:$BN$250))} -> 0 | I29: {=SUMPRODUCT(I$63:I$122,TRANSPOSE(SAP_Spreadsheet!$G$250:$BN$250))} -> 0 | J29: {=SUMPRODUCT(J$63:J$122,TRANSPOSE(SAP_Spreadsheet!$G$250:$BN$250))} -> 0 | K29: {=SUMPRODUCT(K$63:K$122,TRANSPOSE(SAP_Spreadsheet!$G$250:$BN$250))} -> 0 | L29: {=SUMPRODUCT(L$63:L$122,TRANSPOSE(SAP_Spreadsheet!$G$250:$BN$250))} -> 0 | ... BL29: {=SUMPRODUCT(BL$63:BL$122,TRANSPOSE(SAP_Spreadsheet!$G$250:$BN$250))} -> 0
D30: Marketing cost for promotion | E30: {=SUMPRODUCT(E$63:E$122,TRANSPOSE(SAP_Spreadsheet!$G$251:$BN$251))} -> 0 | F30: {=SUMPRODUCT(F$63:F$122,TRANSPOSE(SAP_Spreadsheet!$G$251:$BN$251))} -> 0 | G30: {=SUMPRODUCT(G$63:G$122,TRANSPOSE(SAP_Spreadsheet!$G$251:$BN$251))} -> 0 | H30: {=SUMPRODUCT(H$63:H$122,TRANSPOSE(SAP_Spreadsheet!$G$251:$BN$251))} -> 0 | I30: {=SUMPRODUCT(I$63:I$122,TRANSPOSE(SAP_Spreadsheet!$G$251:$BN$251))} -> 0 | J30: {=SUMPRODUCT(J$63:J$122,TRANSPOSE(SAP_Spreadsheet!$G$251:$BN$251))} -> 0 | K30: {=SUMPRODUCT(K$63:K$122,TRANSPOSE(SAP_Spreadsheet!$G$251:$BN$251))} -> 0 | L30: {=SUMPRODUCT(L$63:L$122,TRANSPOSE(SAP_Spreadsheet!$G$251:$BN$251))} -> 0 | ... BL30: {=SUMPRODUCT(BL$63:BL$122,TRANSPOSE(SAP_Spreadsheet!$G$251:$BN$251))} -> 0
D31: UW & Disbursal | E31: {=SUMPRODUCT(E$63:E$122,TRANSPOSE(SAP_Spreadsheet!$G$256:$BN$256))} -> 0 | F31: {=SUMPRODUCT(F$63:F$122,TRANSPOSE(SAP_Spreadsheet!$G$256:$BN$256))} -> 0 | G31: {=SUMPRODUCT(G$63:G$122,TRANSPOSE(SAP_Spreadsheet!$G$256:$BN$256))} -> 0 | H31: {=SUMPRODUCT(H$63:H$122,TRANSPOSE(SAP_Spreadsheet!$G$256:$BN$256))} -> 0 | I31: {=SUMPRODUCT(I$63:I$122,TRANSPOSE(SAP_Spreadsheet!$G$256:$BN$256))} -> 0 | J31: {=SUMPRODUCT(J$63:J$122,TRANSPOSE(SAP_Spreadsheet!$G$256:$BN$256))} -> 0 | K31: {=SUMPRODUCT(K$63:K$122,TRANSPOSE(SAP_Spreadsheet!$G$256:$BN$256))} -> 0 | L31: {=SUMPRODUCT(L$63:L$122,TRANSPOSE(SAP_Spreadsheet!$G$256:$BN$256))} -> 0 | ... BL31: {=SUMPRODUCT(BL$63:BL$122,TRANSPOSE(SAP_Spreadsheet!$G$256:$BN$256))} -> 0
D32: Collection | E32: =E33+E34 -> 0 | F32: =F33+F34 -> 0 | G32: =G33+G34 -> 0 | H32: =H33+H34 -> 0 | I32: =I33+I34 -> 0 | J32: =J33+J34 -> 0 | K32: =K33+K34 -> 0 | L32: =L33+L34 -> 0 | ... BL32: =BL33+BL34 -> 0
D33: Early collections | E33: {=SUMPRODUCT(E$63:E$122,TRANSPOSE(SAP_Spreadsheet!$G$265:$BN$265))} -> 0 | F33: {=SUMPRODUCT(F$63:F$122,TRANSPOSE(SAP_Spreadsheet!$G$265:$BN$265))} -> 0 | G33: {=SUMPRODUCT(G$63:G$122,TRANSPOSE(SAP_Spreadsheet!$G$265:$BN$265))} -> 0 | H33: {=SUMPRODUCT(H$63:H$122,TRANSPOSE(SAP_Spreadsheet!$G$265:$BN$265))} -> 0 | I33: {=SUMPRODUCT(I$63:I$122,TRANSPOSE(SAP_Spreadsheet!$G$265:$BN$265))} -> 0 | J33: {=SUMPRODUCT(J$63:J$122,TRANSPOSE(SAP_Spreadsheet!$G$265:$BN$265))} -> 0 | K33: {=SUMPRODUCT(K$63:K$122,TRANSPOSE(SAP_Spreadsheet!$G$265:$BN$265))} -> 0 | L33: {=SUMPRODUCT(L$63:L$122,TRANSPOSE(SAP_Spreadsheet!$G$265:$BN$265))} -> 0 | ... BL33: {=SUMPRODUCT(BL$63:BL$122,TRANSPOSE(SAP_Spreadsheet!$G$265:$BN$265))} -> 0
D34: AMC | E34: {=SUMPRODUCT(E$63:E$122,TRANSPOSE(SAP_Spreadsheet!$G$266:$BN$266))} -> 0 | F34: {=SUMPRODUCT(F$63:F$122,TRANSPOSE(SAP_Spreadsheet!$G$266:$BN$266))} -> 0 | G34: {=SUMPRODUCT(G$63:G$122,TRANSPOSE(SAP_Spreadsheet!$G$266:$BN$266))} -> 0 | H34: {=SUMPRODUCT(H$63:H$122,TRANSPOSE(SAP_Spreadsheet!$G$266:$BN$266))} -> 0 | I34: {=SUMPRODUCT(I$63:I$122,TRANSPOSE(SAP_Spreadsheet!$G$266:$BN$266))} -> 0 | J34: {=SUMPRODUCT(J$63:J$122,TRANSPOSE(SAP_Spreadsheet!$G$266:$BN$266))} -> 0 | K34: {=SUMPRODUCT(K$63:K$122,TRANSPOSE(SAP_Spreadsheet!$G$266:$BN$266))} -> 0 | L34: {=SUMPRODUCT(L$63:L$122,TRANSPOSE(SAP_Spreadsheet!$G$266:$BN$266))} -> 0 | ... BL34: {=SUMPRODUCT(BL$63:BL$122,TRANSPOSE(SAP_Spreadsheet!$G$266:$BN$266))} -> 0
D35: After-sales services | E35: {=SUMPRODUCT(E$63:E$122,TRANSPOSE(SAP_Spreadsheet!$G$263:$BN$263))} -> 0 | F35: {=SUMPRODUCT(F$63:F$122,TRANSPOSE(SAP_Spreadsheet!$G$263:$BN$263))} -> 0 | G35: {=SUMPRODUCT(G$63:G$122,TRANSPOSE(SAP_Spreadsheet!$G$263:$BN$263))} -> 0 | H35: {=SUMPRODUCT(H$63:H$122,TRANSPOSE(SAP_Spreadsheet!$G$263:$BN$263))} -> 0 | I35: {=SUMPRODUCT(I$63:I$122,TRANSPOSE(SAP_Spreadsheet!$G$263:$BN$263))} -> 0 | J35: {=SUMPRODUCT(J$63:J$122,TRANSPOSE(SAP_Spreadsheet!$G$263:$BN$263))} -> 0 | K35: {=SUMPRODUCT(K$63:K$122,TRANSPOSE(SAP_Spreadsheet!$G$263:$BN$263))} -> 0 | L35: {=SUMPRODUCT(L$63:L$122,TRANSPOSE(SAP_Spreadsheet!$G$263:$BN$263))} -> 0 | ... BL35: {=SUMPRODUCT(BL$63:BL$122,TRANSPOSE(SAP_Spreadsheet!$G$263:$BN$263))} -> 0
D36: Other support units | E36: {=SUMPRODUCT(E$63:E$122,TRANSPOSE(SAP_Spreadsheet!$G$273:$BN$273))} -> 0 | F36: {=SUMPRODUCT(F$63:F$122,TRANSPOSE(SAP_Spreadsheet!$G$273:$BN$273))} -> 0 | G36: {=SUMPRODUCT(G$63:G$122,TRANSPOSE(SAP_Spreadsheet!$G$273:$BN$273))} -> 0 | H36: {=SUMPRODUCT(H$63:H$122,TRANSPOSE(SAP_Spreadsheet!$G$273:$BN$273))} -> 0 | I36: {=SUMPRODUCT(I$63:I$122,TRANSPOSE(SAP_Spreadsheet!$G$273:$BN$273))} -> 0 | J36: {=SUMPRODUCT(J$63:J$122,TRANSPOSE(SAP_Spreadsheet!$G$273:$BN$273))} -> 0 | K36: {=SUMPRODUCT(K$63:K$122,TRANSPOSE(SAP_Spreadsheet!$G$273:$BN$273))} -> 0 | L36: {=SUMPRODUCT(L$63:L$122,TRANSPOSE(SAP_Spreadsheet!$G$273:$BN$273))} -> 0 | ... BL36: {=SUMPRODUCT(BL$63:BL$122,TRANSPOSE(SAP_Spreadsheet!$G$273:$BN$273))} -> 0
D37: PROVISION | E37: {=SUMPRODUCT(E$63:E$122,TRANSPOSE(SAP_Spreadsheet!$G$335:$BN$335))} -> 0 | F37: {=SUMPRODUCT(F$63:F$122,TRANSPOSE(SAP_Spreadsheet!$G$335:$BN$335))} -> 0 | G37: {=SUMPRODUCT(G$63:G$122,TRANSPOSE(SAP_Spreadsheet!$G$335:$BN$335))} -> 0 | H37: {=SUMPRODUCT(H$63:H$122,TRANSPOSE(SAP_Spreadsheet!$G$335:$BN$335))} -> 0 | I37: {=SUMPRODUCT(I$63:I$122,TRANSPOSE(SAP_Spreadsheet!$G$335:$BN$335))} -> 0 | J37: {=SUMPRODUCT(J$63:J$122,TRANSPOSE(SAP_Spreadsheet!$G$335:$BN$335))} -> 0 | K37: {=SUMPRODUCT(K$63:K$122,TRANSPOSE(SAP_Spreadsheet!$G$335:$BN$335))} -> 0 | L37: {=SUMPRODUCT(L$63:L$122,TRANSPOSE(SAP_Spreadsheet!$G$335:$BN$335))} -> 0 | ... BL37: {=SUMPRODUCT(BL$63:BL$122,TRANSPOSE(SAP_Spreadsheet!$G$335:$BN$335))} -> 0
D38: Other Income | E38: {=SUMPRODUCT(E$63:E$122,TRANSPOSE(SAP_Spreadsheet!$G$240:$BN$240))} -> 0 | F38: {=SUMPRODUCT(F$63:F$122,TRANSPOSE(SAP_Spreadsheet!$G$240:$BN$240))} -> 0 | G38: {=SUMPRODUCT(G$63:G$122,TRANSPOSE(SAP_Spreadsheet!$G$240:$BN$240))} -> 0 | H38: {=SUMPRODUCT(H$63:H$122,TRANSPOSE(SAP_Spreadsheet!$G$240:$BN$240))} -> 0 | I38: {=SUMPRODUCT(I$63:I$122,TRANSPOSE(SAP_Spreadsheet!$G$240:$BN$240))} -> 0 | J38: {=SUMPRODUCT(J$63:J$122,TRANSPOSE(SAP_Spreadsheet!$G$240:$BN$240))} -> 0 | K38: {=SUMPRODUCT(K$63:K$122,TRANSPOSE(SAP_Spreadsheet!$G$240:$BN$240))} -> 0 | L38: {=SUMPRODUCT(L$63:L$122,TRANSPOSE(SAP_Spreadsheet!$G$240:$BN$240))} -> 0 | ... BL38: {=SUMPRODUCT(BL$63:BL$122,TRANSPOSE(SAP_Spreadsheet!$G$240:$BN$240))} -> 0
D39: PBT | E39: =E9+E24+E37+E38 -> 0 | F39: =F9+F24+F37+F38 -> 0 | G39: =G9+G24+G37+G38 -> 0 | H39: =H9+H24+H37+H38 -> 0 | I39: =I9+I24+I37+I38 -> 0 | J39: =J9+J24+J37+J38 -> 0 | K39: =K9+K24+K37+K38 -> 0 | L39: =L9+L24+L37+L38 -> 0 | ... BL39: =BL9+BL24+BL37+BL38 -> 0
D41: Checking | E41: =E9+E24+E37-E39 -> 0 | F41: =F9+F24+F37-F39 -> 0 | G41: =G9+G24+G37-G39 -> 0 | H41: =H9+H24+H37-H39 -> 0 | I41: =I9+I24+I37-I39 -> 0 | J41: =J9+J24+J37-J39 -> 0 | K41: =K9+K24+K37-K39 -> 0 | L41: =L9+L24+L37-L39 -> 0 | ... BL41: =BL9+BL24+BL37-BL39 -> 0
D42: EOP BY BUCKET
D43: B0 | E43: {=SUMPRODUCT(E$63:E$122,TRANSPOSE(SAP_Spreadsheet!$G$181:$BN$181))} -> 0 | F43: {=SUMPRODUCT(F$63:F$122,TRANSPOSE(SAP_Spreadsheet!$G$181:$BN$181))} -> 0 | G43: {=SUMPRODUCT(G$63:G$122,TRANSPOSE(SAP_Spreadsheet!$G$181:$BN$181))} -> 0 | H43: {=SUMPRODUCT(H$63:H$122,TRANSPOSE(SAP_Spreadsheet!$G$181:$BN$181))} -> 0 | I43: {=SUMPRODUCT(I$63:I$122,TRANSPOSE(SAP_Spreadsheet!$G$181:$BN$181))} -> 0 | J43: {=SUMPRODUCT(J$63:J$122,TRANSPOSE(SAP_Spreadsheet!$G$181:$BN$181))} -> 0 | K43: {=SUMPRODUCT(K$63:K$122,TRANSPOSE(SAP_Spreadsheet!$G$181:$BN$181))} -> 0 | L43: {=SUMPRODUCT(L$63:L$122,TRANSPOSE(SAP_Spreadsheet!$G$181:$BN$181))} -> 0 | ... BL43: {=SUMPRODUCT(BL$63:BL$122,TRANSPOSE(SAP_Spreadsheet!$G$181:$BN$181))} -> 0
D44: B1 | E44: {=SUMPRODUCT(E$63:E$122,TRANSPOSE(SAP_Spreadsheet!$G$182:$BN$182))} -> 0 | F44: {=SUMPRODUCT(F$63:F$122,TRANSPOSE(SAP_Spreadsheet!$G$182:$BN$182))} -> 0 | G44: {=SUMPRODUCT(G$63:G$122,TRANSPOSE(SAP_Spreadsheet!$G$182:$BN$182))} -> 0 | H44: {=SUMPRODUCT(H$63:H$122,TRANSPOSE(SAP_Spreadsheet!$G$182:$BN$182))} -> 0 | I44: {=SUMPRODUCT(I$63:I$122,TRANSPOSE(SAP_Spreadsheet!$G$182:$BN$182))} -> 0 | J44: {=SUMPRODUCT(J$63:J$122,TRANSPOSE(SAP_Spreadsheet!$G$182:$BN$182))} -> 0 | K44: {=SUMPRODUCT(K$63:K$122,TRANSPOSE(SAP_Spreadsheet!$G$182:$BN$182))} -> 0 | L44: {=SUMPRODUCT(L$63:L$122,TRANSPOSE(SAP_Spreadsheet!$G$182:$BN$182))} -> 0 | ... BL44: {=SUMPRODUCT(BL$63:BL$122,TRANSPOSE(SAP_Spreadsheet!$G$182:$BN$182))} -> 0
D45: B2 | E45: {=SUMPRODUCT(E$63:E$122,TRANSPOSE(SAP_Spreadsheet!$G$183:$BN$183))} -> 0 | F45: {=SUMPRODUCT(F$63:F$122,TRANSPOSE(SAP_Spreadsheet!$G$183:$BN$183))} -> 0 | G45: {=SUMPRODUCT(G$63:G$122,TRANSPOSE(SAP_Spreadsheet!$G$183:$BN$183))} -> 0 | H45: {=SUMPRODUCT(H$63:H$122,TRANSPOSE(SAP_Spreadsheet!$G$183:$BN$183))} -> 0 | I45: {=SUMPRODUCT(I$63:I$122,TRANSPOSE(SAP_Spreadsheet!$G$183:$BN$183))} -> 0 | J45: {=SUMPRODUCT(J$63:J$122,TRANSPOSE(SAP_Spreadsheet!$G$183:$BN$183))} -> 0 | K45: {=SUMPRODUCT(K$63:K$122,TRANSPOSE(SAP_Spreadsheet!$G$183:$BN$183))} -> 0 | L45: {=SUMPRODUCT(L$63:L$122,TRANSPOSE(SAP_Spreadsheet!$G$183:$BN$183))} -> 0 | ... BL45: {=SUMPRODUCT(BL$63:BL$122,TRANSPOSE(SAP_Spreadsheet!$G$183:$BN$183))} -> 0
D46: B3 | E46: {=SUMPRODUCT(E$63:E$122,TRANSPOSE(SAP_Spreadsheet!$G$184:$BN$184))} -> 0 | F46: {=SUMPRODUCT(F$63:F$122,TRANSPOSE(SAP_Spreadsheet!$G$184:$BN$184))} -> 0 | G46: {=SUMPRODUCT(G$63:G$122,TRANSPOSE(SAP_Spreadsheet!$G$184:$BN$184))} -> 0 | H46: {=SUMPRODUCT(H$63:H$122,TRANSPOSE(SAP_Spreadsheet!$G$184:$BN$184))} -> 0 | I46: {=SUMPRODUCT(I$63:I$122,TRANSPOSE(SAP_Spreadsheet!$G$184:$BN$184))} -> 0 | J46: {=SUMPRODUCT(J$63:J$122,TRANSPOSE(SAP_Spreadsheet!$G$184:$BN$184))} -> 0 | K46: {=SUMPRODUCT(K$63:K$122,TRANSPOSE(SAP_Spreadsheet!$G$184:$BN$184))} -> 0 | L46: {=SUMPRODUCT(L$63:L$122,TRANSPOSE(SAP_Spreadsheet!$G$184:$BN$184))} -> 0 | ... BL46: {=SUMPRODUCT(BL$63:BL$122,TRANSPOSE(SAP_Spreadsheet!$G$184:$BN$184))} -> 0
D47: B4 | E47: {=SUMPRODUCT(E$63:E$122,TRANSPOSE(SAP_Spreadsheet!$G$185:$BN$185))} -> 0 | F47: {=SUMPRODUCT(F$63:F$122,TRANSPOSE(SAP_Spreadsheet!$G$185:$BN$185))} -> 0 | G47: {=SUMPRODUCT(G$63:G$122,TRANSPOSE(SAP_Spreadsheet!$G$185:$BN$185))} -> 0 | H47: {=SUMPRODUCT(H$63:H$122,TRANSPOSE(SAP_Spreadsheet!$G$185:$BN$185))} -> 0 | I47: {=SUMPRODUCT(I$63:I$122,TRANSPOSE(SAP_Spreadsheet!$G$185:$BN$185))} -> 0 | J47: {=SUMPRODUCT(J$63:J$122,TRANSPOSE(SAP_Spreadsheet!$G$185:$BN$185))} -> 0 | K47: {=SUMPRODUCT(K$63:K$122,TRANSPOSE(SAP_Spreadsheet!$G$185:$BN$185))} -> 0 | L47: {=SUMPRODUCT(L$63:L$122,TRANSPOSE(SAP_Spreadsheet!$G$185:$BN$185))} -> 0 | ... BL47: {=SUMPRODUCT(BL$63:BL$122,TRANSPOSE(SAP_Spreadsheet!$G$185:$BN$185))} -> 0
D48: B5 | E48: {=SUMPRODUCT(E$63:E$122,TRANSPOSE(SAP_Spreadsheet!$G$186:$BN$186))} -> 0 | F48: {=SUMPRODUCT(F$63:F$122,TRANSPOSE(SAP_Spreadsheet!$G$186:$BN$186))} -> 0 | G48: {=SUMPRODUCT(G$63:G$122,TRANSPOSE(SAP_Spreadsheet!$G$186:$BN$186))} -> 0 | H48: {=SUMPRODUCT(H$63:H$122,TRANSPOSE(SAP_Spreadsheet!$G$186:$BN$186))} -> 0 | I48: {=SUMPRODUCT(I$63:I$122,TRANSPOSE(SAP_Spreadsheet!$G$186:$BN$186))} -> 0 | J48: {=SUMPRODUCT(J$63:J$122,TRANSPOSE(SAP_Spreadsheet!$G$186:$BN$186))} -> 0 | K48: {=SUMPRODUCT(K$63:K$122,TRANSPOSE(SAP_Spreadsheet!$G$186:$BN$186))} -> 0 | L48: {=SUMPRODUCT(L$63:L$122,TRANSPOSE(SAP_Spreadsheet!$G$186:$BN$186))} -> 0 | ... BL48: {=SUMPRODUCT(BL$63:BL$122,TRANSPOSE(SAP_Spreadsheet!$G$186:$BN$186))} -> 0
D49: B6 | E49: {=SUMPRODUCT(E$63:E$122,TRANSPOSE(SAP_Spreadsheet!$G$187:$BN$187))} -> 0 | F49: {=SUMPRODUCT(F$63:F$122,TRANSPOSE(SAP_Spreadsheet!$G$187:$BN$187))} -> 0 | G49: {=SUMPRODUCT(G$63:G$122,TRANSPOSE(SAP_Spreadsheet!$G$187:$BN$187))} -> 0 | H49: {=SUMPRODUCT(H$63:H$122,TRANSPOSE(SAP_Spreadsheet!$G$187:$BN$187))} -> 0 | I49: {=SUMPRODUCT(I$63:I$122,TRANSPOSE(SAP_Spreadsheet!$G$187:$BN$187))} -> 0 | J49: {=SUMPRODUCT(J$63:J$122,TRANSPOSE(SAP_Spreadsheet!$G$187:$BN$187))} -> 0 | K49: {=SUMPRODUCT(K$63:K$122,TRANSPOSE(SAP_Spreadsheet!$G$187:$BN$187))} -> 0 | L49: {=SUMPRODUCT(L$63:L$122,TRANSPOSE(SAP_Spreadsheet!$G$187:$BN$187))} -> 0 | ... BL49: {=SUMPRODUCT(BL$63:BL$122,TRANSPOSE(SAP_Spreadsheet!$G$187:$BN$187))} -> 0
D50: B7 | E50: {=SUMPRODUCT(E$63:E$122,TRANSPOSE(SAP_Spreadsheet!$G$188:$BN$188))} -> 0 | F50: {=SUMPRODUCT(F$63:F$122,TRANSPOSE(SAP_Spreadsheet!$G$188:$BN$188))} -> 0 | G50: {=SUMPRODUCT(G$63:G$122,TRANSPOSE(SAP_Spreadsheet!$G$188:$BN$188))} -> 0 | H50: {=SUMPRODUCT(H$63:H$122,TRANSPOSE(SAP_Spreadsheet!$G$188:$BN$188))} -> 0 | I50: {=SUMPRODUCT(I$63:I$122,TRANSPOSE(SAP_Spreadsheet!$G$188:$BN$188))} -> 0 | J50: {=SUMPRODUCT(J$63:J$122,TRANSPOSE(SAP_Spreadsheet!$G$188:$BN$188))} -> 0 | K50: {=SUMPRODUCT(K$63:K$122,TRANSPOSE(SAP_Spreadsheet!$G$188:$BN$188))} -> 0 | L50: {=SUMPRODUCT(L$63:L$122,TRANSPOSE(SAP_Spreadsheet!$G$188:$BN$188))} -> 0 | ... BL50: {=SUMPRODUCT(BL$63:BL$122,TRANSPOSE(SAP_Spreadsheet!$G$188:$BN$188))} -> 0
D51: B8 | E51: {=SUMPRODUCT(E$63:E$122,TRANSPOSE(SAP_Spreadsheet!$G$189:$BN$189))} -> 0 | F51: {=SUMPRODUCT(F$63:F$122,TRANSPOSE(SAP_Spreadsheet!$G$189:$BN$189))} -> 0 | G51: {=SUMPRODUCT(G$63:G$122,TRANSPOSE(SAP_Spreadsheet!$G$189:$BN$189))} -> 0 | H51: {=SUMPRODUCT(H$63:H$122,TRANSPOSE(SAP_Spreadsheet!$G$189:$BN$189))} -> 0 | I51: {=SUMPRODUCT(I$63:I$122,TRANSPOSE(SAP_Spreadsheet!$G$189:$BN$189))} -> 0 | J51: {=SUMPRODUCT(J$63:J$122,TRANSPOSE(SAP_Spreadsheet!$G$189:$BN$189))} -> 0 | K51: {=SUMPRODUCT(K$63:K$122,TRANSPOSE(SAP_Spreadsheet!$G$189:$BN$189))} -> 0 | L51: {=SUMPRODUCT(L$63:L$122,TRANSPOSE(SAP_Spreadsheet!$G$189:$BN$189))} -> 0 | ... BL51: {=SUMPRODUCT(BL$63:BL$122,TRANSPOSE(SAP_Spreadsheet!$G$189:$BN$189))} -> 0
D52: B9 | E52: {=SUMPRODUCT(E$63:E$122,TRANSPOSE(SAP_Spreadsheet!$G$190:$BN$190))} -> 0 | F52: {=SUMPRODUCT(F$63:F$122,TRANSPOSE(SAP_Spreadsheet!$G$190:$BN$190))} -> 0 | G52: {=SUMPRODUCT(G$63:G$122,TRANSPOSE(SAP_Spreadsheet!$G$190:$BN$190))} -> 0 | H52: {=SUMPRODUCT(H$63:H$122,TRANSPOSE(SAP_Spreadsheet!$G$190:$BN$190))} -> 0 | I52: {=SUMPRODUCT(I$63:I$122,TRANSPOSE(SAP_Spreadsheet!$G$190:$BN$190))} -> 0 | J52: {=SUMPRODUCT(J$63:J$122,TRANSPOSE(SAP_Spreadsheet!$G$190:$BN$190))} -> 0 | K52: {=SUMPRODUCT(K$63:K$122,TRANSPOSE(SAP_Spreadsheet!$G$190:$BN$190))} -> 0 | L52: {=SUMPRODUCT(L$63:L$122,TRANSPOSE(SAP_Spreadsheet!$G$190:$BN$190))} -> 0 | ... BL52: {=SUMPRODUCT(BL$63:BL$122,TRANSPOSE(SAP_Spreadsheet!$G$190:$BN$190))} -> 0
D53: B10 | E53: {=SUMPRODUCT(E$63:E$122,TRANSPOSE(SAP_Spreadsheet!$G$191:$BN$191))} -> 0 | F53: {=SUMPRODUCT(F$63:F$122,TRANSPOSE(SAP_Spreadsheet!$G$191:$BN$191))} -> 0 | G53: {=SUMPRODUCT(G$63:G$122,TRANSPOSE(SAP_Spreadsheet!$G$191:$BN$191))} -> 0 | H53: {=SUMPRODUCT(H$63:H$122,TRANSPOSE(SAP_Spreadsheet!$G$191:$BN$191))} -> 0 | I53: {=SUMPRODUCT(I$63:I$122,TRANSPOSE(SAP_Spreadsheet!$G$191:$BN$191))} -> 0 | J53: {=SUMPRODUCT(J$63:J$122,TRANSPOSE(SAP_Spreadsheet!$G$191:$BN$191))} -> 0 | K53: {=SUMPRODUCT(K$63:K$122,TRANSPOSE(SAP_Spreadsheet!$G$191:$BN$191))} -> 0 | L53: {=SUMPRODUCT(L$63:L$122,TRANSPOSE(SAP_Spreadsheet!$G$191:$BN$191))} -> 0 | ... BL53: {=SUMPRODUCT(BL$63:BL$122,TRANSPOSE(SAP_Spreadsheet!$G$191:$BN$191))} -> 0
D54: B11 | E54: {=SUMPRODUCT(E$63:E$122,TRANSPOSE(SAP_Spreadsheet!$G$192:$BN$192))} -> 0 | F54: {=SUMPRODUCT(F$63:F$122,TRANSPOSE(SAP_Spreadsheet!$G$192:$BN$192))} -> 0 | G54: {=SUMPRODUCT(G$63:G$122,TRANSPOSE(SAP_Spreadsheet!$G$192:$BN$192))} -> 0 | H54: {=SUMPRODUCT(H$63:H$122,TRANSPOSE(SAP_Spreadsheet!$G$192:$BN$192))} -> 0 | I54: {=SUMPRODUCT(I$63:I$122,TRANSPOSE(SAP_Spreadsheet!$G$192:$BN$192))} -> 0 | J54: {=SUMPRODUCT(J$63:J$122,TRANSPOSE(SAP_Spreadsheet!$G$192:$BN$192))} -> 0 | K54: {=SUMPRODUCT(K$63:K$122,TRANSPOSE(SAP_Spreadsheet!$G$192:$BN$192))} -> 0 | L54: {=SUMPRODUCT(L$63:L$122,TRANSPOSE(SAP_Spreadsheet!$G$192:$BN$192))} -> 0 | ... BL54: {=SUMPRODUCT(BL$63:BL$122,TRANSPOSE(SAP_Spreadsheet!$G$192:$BN$192))} -> 0
D55: B12 | E55: {=SUMPRODUCT(E$63:E$122,TRANSPOSE(SAP_Spreadsheet!$G$193:$BN$193))} -> 0 | F55: {=SUMPRODUCT(F$63:F$122,TRANSPOSE(SAP_Spreadsheet!$G$193:$BN$193))} -> 0 | G55: {=SUMPRODUCT(G$63:G$122,TRANSPOSE(SAP_Spreadsheet!$G$193:$BN$193))} -> 0 | H55: {=SUMPRODUCT(H$63:H$122,TRANSPOSE(SAP_Spreadsheet!$G$193:$BN$193))} -> 0 | I55: {=SUMPRODUCT(I$63:I$122,TRANSPOSE(SAP_Spreadsheet!$G$193:$BN$193))} -> 0 | J55: {=SUMPRODUCT(J$63:J$122,TRANSPOSE(SAP_Spreadsheet!$G$193:$BN$193))} -> 0 | K55: {=SUMPRODUCT(K$63:K$122,TRANSPOSE(SAP_Spreadsheet!$G$193:$BN$193))} -> 0 | L55: {=SUMPRODUCT(L$63:L$122,TRANSPOSE(SAP_Spreadsheet!$G$193:$BN$193))} -> 0 | ... BL55: {=SUMPRODUCT(BL$63:BL$122,TRANSPOSE(SAP_Spreadsheet!$G$193:$BN$193))} -> 0
D57: Accumulated Card | E57: =SUMPRODUCT(E63:E122,$C$63:$C$122) -> 0 | F57: =SUMPRODUCT(F63:F122,$C$63:$C$122) -> 0 | G57: =SUMPRODUCT(G63:G122,$C$63:$C$122) -> 0 | H57: =SUMPRODUCT(H63:H122,$C$63:$C$122) -> 0 | I57: =SUMPRODUCT(I63:I122,$C$63:$C$122) -> 0 | J57: =SUMPRODUCT(J63:J122,$C$63:$C$122) -> 0 | K57: =SUMPRODUCT(K63:K122,$C$63:$C$122) -> 0 | L57: =SUMPRODUCT(L63:L122,$C$63:$C$122) -> 0 | ... BL57: =SUMPRODUCT(BL63:BL122,$C$63:$C$122) -> 0
D58: Activated card | E58: =SUMPRODUCT(E63:E122,$B$63:$B$122) -> 0 | F58: =SUMPRODUCT(F63:F122,$B$63:$B$122) -> 0 | G58: =SUMPRODUCT(G63:G122,$B$63:$B$122) -> 0 | H58: =SUMPRODUCT(H63:H122,$B$63:$B$122) -> 0 | I58: =SUMPRODUCT(I63:I122,$B$63:$B$122) -> 0 | J58: =SUMPRODUCT(J63:J122,$B$63:$B$122) -> 0 | K58: =SUMPRODUCT(K63:K122,$B$63:$B$122) -> 0 | L58: =SUMPRODUCT(L63:L122,$B$63:$B$122) -> 0 | ... BL58: =SUMPRODUCT(BL63:BL122,$B$63:$B$122) -> 0
D59: Total Usage | E59: =PnL_Speadsheet!E58*SAP_Spreadsheet!G15 -> 0 | F59: =PnL_Speadsheet!F58*SAP_Spreadsheet!H15 -> 0 | G59: =PnL_Speadsheet!G58*SAP_Spreadsheet!I15 -> 0 | H59: =PnL_Speadsheet!H58*SAP_Spreadsheet!J15 -> 0 | I59: =PnL_Speadsheet!I58*SAP_Spreadsheet!K15 -> 0 | J59: =PnL_Speadsheet!J58*SAP_Spreadsheet!L15 -> 0 | K59: =PnL_Speadsheet!K58*SAP_Spreadsheet!M15 -> 0 | L59: =PnL_Speadsheet!L58*SAP_Spreadsheet!N15 -> 0 | ... BL59: =PnL_Speadsheet!BL58*SAP_Spreadsheet!BN15 -> 0
B61: Term card | C61: =SAP_Leadsheet!E21 -> 60
B62: Activated card | C62: Iss @attrition | D62: No. of account | E62: =ROUND('Sales plan& PnL'!J10,0) -> 0 | F62: =ROUND('Sales plan& PnL'!K10,0) -> 0 | G62: =ROUND('Sales plan& PnL'!L10,0) -> 0 | H62: =ROUND('Sales plan& PnL'!M10,0) -> 0 | I62: =ROUND('Sales plan& PnL'!N10,0) -> 0 | J62: =ROUND('Sales plan& PnL'!O10,0) -> 0 | K62: =ROUND('Sales plan& PnL'!P10,0) -> 0 | L62: =ROUND('Sales plan& PnL'!Q10,0) -> 0 | ... BL62: =ROUND('Sales plan& PnL'!BQ10,0) -> 0
B63: =SUMIFS(SAP_Spreadsheet!$G$11:$BN$11,SAP_Spreadsheet!$G$7:$BN$7,PnL_Speadsheet!$D63) -> 0.66492241 | C63: =SUMIFS(SAP_Spreadsheet!$G$10:$BN$10,SAP_Spreadsheet!$G$7:$BN$7,PnL_Speadsheet!$D63) -> 1 | D63: 1 | E63: =IF($D63>$C$61,0,IF($D63>E$5,"",OFFSET(E$62,0,-($D63-1)))) -> 0 | F63: =IF($D63>$C$61,0,IF($D63>F$5,"",OFFSET(F$62,0,-($D63-1)))) -> 0 | G63: =IF($D63>$C$61,0,IF($D63>G$5,"",OFFSET(G$62,0,-($D63-1)))) -> 0 | H63: =IF($D63>$C$61,0,IF($D63>H$5,"",OFFSET(H$62,0,-($D63-1)))) -> 0 | I63: =IF($D63>$C$61,0,IF($D63>I$5,"",OFFSET(I$62,0,-($D63-1)))) -> 0 | J63: =IF($D63>$C$61,0,IF($D63>J$5,"",OFFSET(J$62,0,-($D63-1)))) -> 0 | K63: =IF($D63>$C$61,0,IF($D63>K$5,"",OFFSET(K$62,0,-($D63-1)))) -> 0 | L63: =IF($D63>$C$61,0,IF($D63>L$5,"",OFFSET(L$62,0,-($D63-1)))) -> 0 | ... BL63: =IF($D63>$C$61,0,IF($D63>BL$5,"",OFFSET(BL$62,0,-($D63-1)))) -> 0
B64: =SUMIFS(SAP_Spreadsheet!$G$11:$BN$11,SAP_Spreadsheet!$G$7:$BN$7,PnL_Speadsheet!$D64) -> 0.64040769 | C64: =SUMIFS(SAP_Spreadsheet!$G$10:$BN$10,SAP_Spreadsheet!$G$7:$BN$7,PnL_Speadsheet!$D64) -> 1 | D64: =D63+1 -> 2 | E64: =IF($D64>$C$61,0,IF($D64>E$5,"",OFFSET(E$62,0,-($D64-1)))) | F64: =IF($D64>$C$61,0,IF($D64>F$5,"",OFFSET(F$62,0,-($D64-1)))) -> 0 | G64: =IF($D64>$C$61,0,IF($D64>G$5,"",OFFSET(G$62,0,-($D64-1)))) -> 0 | H64: =IF($D64>$C$61,0,IF($D64>H$5,"",OFFSET(H$62,0,-($D64-1)))) -> 0 | I64: =IF($D64>$C$61,0,IF($D64>I$5,"",OFFSET(I$62,0,-($D64-1)))) -> 0 | J64: =IF($D64>$C$61,0,IF($D64>J$5,"",OFFSET(J$62,0,-($D64-1)))) -> 0 | K64: =IF($D64>$C$61,0,IF($D64>K$5,"",OFFSET(K$62,0,-($D64-1)))) -> 0 | L64: =IF($D64>$C$61,0,IF($D64>L$5,"",OFFSET(L$62,0,-($D64-1)))) -> 0 | ... BL64: =IF($D64>$C$61,0,IF($D64>BL$5,"",OFFSET(BL$62,0,-($D64-1)))) -> 0
B65: =SUMIFS(SAP_Spreadsheet!$G$11:$BN$11,SAP_Spreadsheet!$G$7:$BN$7,PnL_Speadsheet!$D65) -> 0.61589297 | C65: =SUMIFS(SAP_Spreadsheet!$G$10:$BN$10,SAP_Spreadsheet!$G$7:$BN$7,PnL_Speadsheet!$D65) -> 1 | D65: =D64+1 -> 3 | E65: =IF($D65>$C$61,0,IF($D65>E$5,"",OFFSET(E$62,0,-($D65-1)))) | F65: =IF($D65>$C$61,0,IF($D65>F$5,"",OFFSET(F$62,0,-($D65-1)))) | G65: =IF($D65>$C$61,0,IF($D65>G$5,"",OFFSET(G$62,0,-($D65-1)))) -> 0 | H65: =IF($D65>$C$61,0,IF($D65>H$5,"",OFFSET(H$62,0,-($D65-1)))) -> 0 | I65: =IF($D65>$C$61,0,IF($D65>I$5,"",OFFSET(I$62,0,-($D65-1)))) -> 0 | J65: =IF($D65>$C$61,0,IF($D65>J$5,"",OFFSET(J$62,0,-($D65-1)))) -> 0 | K65: =IF($D65>$C$61,0,IF($D65>K$5,"",OFFSET(K$62,0,-($D65-1)))) -> 0 | L65: =IF($D65>$C$61,0,IF($D65>L$5,"",OFFSET(L$62,0,-($D65-1)))) -> 0 | ... BL65: =IF($D65>$C$61,0,IF($D65>BL$5,"",OFFSET(BL$62,0,-($D65-1)))) -> 0
B66: =SUMIFS(SAP_Spreadsheet!$G$11:$BN$11,SAP_Spreadsheet!$G$7:$BN$7,PnL_Speadsheet!$D66) -> 0.59137825 | C66: =SUMIFS(SAP_Spreadsheet!$G$10:$BN$10,SAP_Spreadsheet!$G$7:$BN$7,PnL_Speadsheet!$D66) -> 1 | D66: =D65+1 -> 4 | E66: =IF($D66>$C$61,0,IF($D66>E$5,"",OFFSET(E$62,0,-($D66-1)))) | F66: =IF($D66>$C$61,0,IF($D66>F$5,"",OFFSET(F$62,0,-($D66-1)))) | G66: =IF($D66>$C$61,0,IF($D66>G$5,"",OFFSET(G$62,0,-($D66-1)))) | H66: =IF($D66>$C$61,0,IF($D66>H$5,"",OFFSET(H$62,0,-($D66-1)))) -> 0 | I66: =IF($D66>$C$61,0,IF($D66>I$5,"",OFFSET(I$62,0,-($D66-1)))) -> 0 | J66: =IF($D66>$C$61,0,IF($D66>J$5,"",OFFSET(J$62,0,-($D66-1)))) -> 0 | K66: =IF($D66>$C$61,0,IF($D66>K$5,"",OFFSET(K$62,0,-($D66-1)))) -> 0 | L66: =IF($D66>$C$61,0,IF($D66>L$5,"",OFFSET(L$62,0,-($D66-1)))) -> 0 | ... BL66: =IF($D66>$C$61,0,IF($D66>BL$5,"",OFFSET(BL$62,0,-($D66-1)))) -> 0
B67: =SUMIFS(SAP_Spreadsheet!$G$11:$BN$11,SAP_Spreadsheet!$G$7:$BN$7,PnL_Speadsheet!$D67) -> 0.56686352 | C67: =SUMIFS(SAP_Spreadsheet!$G$10:$BN$10,SAP_Spreadsheet!$G$7:$BN$7,PnL_Speadsheet!$D67) -> 1 | D67: =D66+1 -> 5 | E67: =IF($D67>$C$61,0,IF($D67>E$5,"",OFFSET(E$62,0,-($D67-1)))) | F67: =IF($D67>$C$61,0,IF($D67>F$5,"",OFFSET(F$62,0,-($D67-1)))) | G67: =IF($D67>$C$61,0,IF($D67>G$5,"",OFFSET(G$62,0,-($D67-1)))) | H67: =IF($D67>$C$61,0,IF($D67>H$5,"",OFFSET(H$62,0,-($D67-1)))) | I67: =IF($D67>$C$61,0,IF($D67>I$5,"",OFFSET(I$62,0,-($D67-1)))) -> 0 | J67: =IF($D67>$C$61,0,IF($D67>J$5,"",OFFSET(J$62,0,-($D67-1)))) -> 0 | K67: =IF($D67>$C$61,0,IF($D67>K$5,"",OFFSET(K$62,0,-($D67-1)))) -> 0 | L67: =IF($D67>$C$61,0,IF($D67>L$5,"",OFFSET(L$62,0,-($D67-1)))) -> 0 | ... BL67: =IF($D67>$C$61,0,IF($D67>BL$5,"",OFFSET(BL$62,0,-($D67-1)))) -> 0
B68: =SUMIFS(SAP_Spreadsheet!$G$11:$BN$11,SAP_Spreadsheet!$G$7:$BN$7,PnL_Speadsheet!$D68) -> 0.5423488 | C68: =SUMIFS(SAP_Spreadsheet!$G$10:$BN$10,SAP_Spreadsheet!$G$7:$BN$7,PnL_Speadsheet!$D68) -> 1 | D68: =D67+1 -> 6 | E68: =IF($D68>$C$61,0,IF($D68>E$5,"",OFFSET(E$62,0,-($D68-1)))) | F68: =IF($D68>$C$61,0,IF($D68>F$5,"",OFFSET(F$62,0,-($D68-1)))) | G68: =IF($D68>$C$61,0,IF($D68>G$5,"",OFFSET(G$62,0,-($D68-1)))) | H68: =IF($D68>$C$61,0,IF($D68>H$5,"",OFFSET(H$62,0,-($D68-1)))) | I68: =IF($D68>$C$61,0,IF($D68>I$5,"",OFFSET(I$62,0,-($D68-1)))) | J68: =IF($D68>$C$61,0,IF($D68>J$5,"",OFFSET(J$62,0,-($D68-1)))) -> 0 | K68: =IF($D68>$C$61,0,IF($D68>K$5,"",OFFSET(K$62,0,-($D68-1)))) -> 0 | L68: =IF($D68>$C$61,0,IF($D68>L$5,"",OFFSET(L$62,0,-($D68-1)))) -> 0 | ... BL68: =IF($D68>$C$61,0,IF($D68>BL$5,"",OFFSET(BL$62,0,-($D68-1)))) -> 0
B69: =SUMIFS(SAP_Spreadsheet!$G$11:$BN$11,SAP_Spreadsheet!$G$7:$BN$7,PnL_Speadsheet!$D69) -> 0.51783408 | C69: =SUMIFS(SAP_Spreadsheet!$G$10:$BN$10,SAP_Spreadsheet!$G$7:$BN$7,PnL_Speadsheet!$D69) -> 1 | D69: =D68+1 -> 7 | E69: =IF($D69>$C$61,0,IF($D69>E$5,"",OFFSET(E$62,0,-($D69-1)))) | F69: =IF($D69>$C$61,0,IF($D69>F$5,"",OFFSET(F$62,0,-($D69-1)))) | G69: =IF($D69>$C$61,0,IF($D69>G$5,"",OFFSET(G$62,0,-($D69-1)))) | H69: =IF($D69>$C$61,0,IF($D69>H$5,"",OFFSET(H$62,0,-($D69-1)))) | I69: =IF($D69>$C$61,0,IF($D69>I$5,"",OFFSET(I$62,0,-($D69-1)))) | J69: =IF($D69>$C$61,0,IF($D69>J$5,"",OFFSET(J$62,0,-($D69-1)))) | K69: =IF($D69>$C$61,0,IF($D69>K$5,"",OFFSET(K$62,0,-($D69-1)))) -> 0 | L69: =IF($D69>$C$61,0,IF($D69>L$5,"",OFFSET(L$62,0,-($D69-1)))) -> 0 | ... BL69: =IF($D69>$C$61,0,IF($D69>BL$5,"",OFFSET(BL$62,0,-($D69-1)))) -> 0
B70: =SUMIFS(SAP_Spreadsheet!$G$11:$BN$11,SAP_Spreadsheet!$G$7:$BN$7,PnL_Speadsheet!$D70) -> 0.49331936 | C70: =SUMIFS(SAP_Spreadsheet!$G$10:$BN$10,SAP_Spreadsheet!$G$7:$BN$7,PnL_Speadsheet!$D70) -> 1 | D70: =D69+1 -> 8 | E70: =IF($D70>$C$61,0,IF($D70>E$5,"",OFFSET(E$62,0,-($D70-1)))) | F70: =IF($D70>$C$61,0,IF($D70>F$5,"",OFFSET(F$62,0,-($D70-1)))) | G70: =IF($D70>$C$61,0,IF($D70>G$5,"",OFFSET(G$62,0,-($D70-1)))) | H70: =IF($D70>$C$61,0,IF($D70>H$5,"",OFFSET(H$62,0,-($D70-1)))) | I70: =IF($D70>$C$61,0,IF($D70>I$5,"",OFFSET(I$62,0,-($D70-1)))) | J70: =IF($D70>$C$61,0,IF($D70>J$5,"",OFFSET(J$62,0,-($D70-1)))) | K70: =IF($D70>$C$61,0,IF($D70>K$5,"",OFFSET(K$62,0,-($D70-1)))) | L70: =IF($D70>$C$61,0,IF($D70>L$5,"",OFFSET(L$62,0,-($D70-1)))) -> 0 | ... BL70: =IF($D70>$C$61,0,IF($D70>BL$5,"",OFFSET(BL$62,0,-($D70-1)))) -> 0
B71: =SUMIFS(SAP_Spreadsheet!$G$11:$BN$11,SAP_Spreadsheet!$G$7:$BN$7,PnL_Speadsheet!$D71) -> 0.46880464 | C71: =SUMIFS(SAP_Spreadsheet!$G$10:$BN$10,SAP_Spreadsheet!$G$7:$BN$7,PnL_Speadsheet!$D71) -> 1 | D71: =D70+1 -> 9 | E71: =IF($D71>$C$61,0,IF($D71>E$5,"",OFFSET(E$62,0,-($D71-1)))) | F71: =IF($D71>$C$61,0,IF($D71>F$5,"",OFFSET(F$62,0,-($D71-1)))) | G71: =IF($D71>$C$61,0,IF($D71>G$5,"",OFFSET(G$62,0,-($D71-1)))) | H71: =IF($D71>$C$61,0,IF($D71>H$5,"",OFFSET(H$62,0,-($D71-1)))) | I71: =IF($D71>$C$61,0,IF($D71>I$5,"",OFFSET(I$62,0,-($D71-1)))) | J71: =IF($D71>$C$61,0,IF($D71>J$5,"",OFFSET(J$62,0,-($D71-1)))) | K71: =IF($D71>$C$61,0,IF($D71>K$5,"",OFFSET(K$62,0,-($D71-1)))) | L71: =IF($D71>$C$61,0,IF($D71>L$5,"",OFFSET(L$62,0,-($D71-1)))) | ... BL71: =IF($D71>$C$61,0,IF($D71>BL$5,"",OFFSET(BL$62,0,-($D71-1)))) -> 0
B72: =SUMIFS(SAP_Spreadsheet!$G$11:$BN$11,SAP_Spreadsheet!$G$7:$BN$7,PnL_Speadsheet!$D72) -> 0.44428992 | C72: =SUMIFS(SAP_Spreadsheet!$G$10:$BN$10,SAP_Spreadsheet!$G$7:$BN$7,PnL_Speadsheet!$D72) -> 1 | D72: =D71+1 -> 10 | E72: =IF($D72>$C$61,0,IF($D72>E$5,"",OFFSET(E$62,0,-($D72-1)))) | F72: =IF($D72>$C$61,0,IF($D72>F$5,"",OFFSET(F$62,0,-($D72-1)))) | G72: =IF($D72>$C$61,0,IF($D72>G$5,"",OFFSET(G$62,0,-($D72-1)))) | H72: =IF($D72>$C$61,0,IF($D72>H$5,"",OFFSET(H$62,0,-($D72-1)))) | I72: =IF($D72>$C$61,0,IF($D72>I$5,"",OFFSET(I$62,0,-($D72-1)))) | J72: =IF($D72>$C$61,0,IF($D72>J$5,"",OFFSET(J$62,0,-($D72-1)))) | K72: =IF($D72>$C$61,0,IF($D72>K$5,"",OFFSET(K$62,0,-($D72-1)))) | L72: =IF($D72>$C$61,0,IF($D72>L$5,"",OFFSET(L$62,0,-($D72-1)))) | ... BL72: =IF($D72>$C$61,0,IF($D72>BL$5,"",OFFSET(BL$62,0,-($D72-1)))) -> 0
B73: =SUMIFS(SAP_Spreadsheet!$G$11:$BN$11,SAP_Spreadsheet!$G$7:$BN$7,PnL_Speadsheet!$D73) -> 0.4197752 | C73: =SUMIFS(SAP_Spreadsheet!$G$10:$BN$10,SAP_Spreadsheet!$G$7:$BN$7,PnL_Speadsheet!$D73) -> 1 | D73: =D72+1 -> 11 | E73: =IF($D73>$C$61,0,IF($D73>E$5,"",OFFSET(E$62,0,-($D73-1)))) | F73: =IF($D73>$C$61,0,IF($D73>F$5,"",OFFSET(F$62,0,-($D73-1)))) | G73: =IF($D73>$C$61,0,IF($D73>G$5,"",OFFSET(G$62,0,-($D73-1)))) | H73: =IF($D73>$C$61,0,IF($D73>H$5,"",OFFSET(H$62,0,-($D73-1)))) | I73: =IF($D73>$C$61,0,IF($D73>I$5,"",OFFSET(I$62,0,-($D73-1)))) | J73: =IF($D73>$C$61,0,IF($D73>J$5,"",OFFSET(J$62,0,-($D73-1)))) | K73: =IF($D73>$C$61,0,IF($D73>K$5,"",OFFSET(K$62,0,-($D73-1)))) | L73: =IF($D73>$C$61,0,IF($D73>L$5,"",OFFSET(L$62,0,-($D73-1)))) | ... BL73: =IF($D73>$C$61,0,IF($D73>BL$5,"",OFFSET(BL$62,0,-($D73-1)))) -> 0
B74: =SUMIFS(SAP_Spreadsheet!$G$11:$BN$11,SAP_Spreadsheet!$G$7:$BN$7,PnL_Speadsheet!$D74) -> 0.39526048 | C74: =SUMIFS(SAP_Spreadsheet!$G$10:$BN$10,SAP_Spreadsheet!$G$7:$BN$7,PnL_Speadsheet!$D74) -> 1 | D74: =D73+1 -> 12 | E74: =IF($D74>$C$61,0,IF($D74>E$5,"",OFFSET(E$62,0,-($D74-1)))) | F74: =IF($D74>$C$61,0,IF($D74>F$5,"",OFFSET(F$62,0,-($D74-1)))) | G74: =IF($D74>$C$61,0,IF($D74>G$5,"",OFFSET(G$62,0,-($D74-1)))) | H74: =IF($D74>$C$61,0,IF($D74>H$5,"",OFFSET(H$62,0,-($D74-1)))) | I74: =IF($D74>$C$61,0,IF($D74>I$5,"",OFFSET(I$62,0,-($D74-1)))) | J74: =IF($D74>$C$61,0,IF($D74>J$5,"",OFFSET(J$62,0,-($D74-1)))) | K74: =IF($D74>$C$61,0,IF($D74>K$5,"",OFFSET(K$62,0,-($D74-1)))) | L74: =IF($D74>$C$61,0,IF($D74>L$5,"",OFFSET(L$62,0,-($D74-1)))) | ... BL74: =IF($D74>$C$61,0,IF($D74>BL$5,"",OFFSET(BL$62,0,-($D74-1)))) -> 0
B75: =SUMIFS(SAP_Spreadsheet!$G$11:$BN$11,SAP_Spreadsheet!$G$7:$BN$7,PnL_Speadsheet!$D75) -> 0.38564177 | C75: =SUMIFS(SAP_Spreadsheet!$G$10:$BN$10,SAP_Spreadsheet!$G$7:$BN$7,PnL_Speadsheet!$D75) -> 1 | D75: =D74+1 -> 13 | E75: =IF($D75>$C$61,0,IF($D75>E$5,"",OFFSET(E$62,0,-($D75-1)))) | F75: =IF($D75>$C$61,0,IF($D75>F$5,"",OFFSET(F$62,0,-($D75-1)))) | G75: =IF($D75>$C$61,0,IF($D75>G$5,"",OFFSET(G$62,0,-($D75-1)))) | H75: =IF($D75>$C$61,0,IF($D75>H$5,"",OFFSET(H$62,0,-($D75-1)))) | I75: =IF($D75>$C$61,0,IF($D75>I$5,"",OFFSET(I$62,0,-($D75-1)))) | J75: =IF($D75>$C$61,0,IF($D75>J$5,"",OFFSET(J$62,0,-($D75-1)))) | K75: =IF($D75>$C$61,0,IF($D75>K$5,"",OFFSET(K$62,0,-($D75-1)))) | L75: =IF($D75>$C$61,0,IF($D75>L$5,"",OFFSET(L$62,0,-($D75-1)))) | ... BL75: =IF($D75>$C$61,0,IF($D75>BL$5,"",OFFSET(BL$62,0,-($D75-1)))) -> 0
... B122: =SUMIFS(SAP_Spreadsheet!$G$11:$BN$11,SAP_Spreadsheet!$G$7:$BN$7,PnL_Speadsheet!$D122) -> 0.10719696 | C122: =SUMIFS(SAP_Spreadsheet!$G$10:$BN$10,SAP_Spreadsheet!$G$7:$BN$7,PnL_Speadsheet!$D122) -> 1 | D122: =D121+1 -> 60 | E122: =IF($D122>$C$61,0,IF($D122>E$5,"",OFFSET(E$62,0,-($D122-1)))) | F122: =IF($D122>$C$61,0,IF($D122>F$5,"",OFFSET(F$62,0,-($D122-1)))) | G122: =IF($D122>$C$61,0,IF($D122>G$5,"",OFFSET(G$62,0,-($D122-1)))) | H122: =IF($D122>$C$61,0,IF($D122>H$5,"",OFFSET(H$62,0,-($D122-1)))) | I122: =IF($D122>$C$61,0,IF($D122>I$5,"",OFFSET(I$62,0,-($D122-1)))) | J122: =IF($D122>$C$61,0,IF($D122>J$5,"",OFFSET(J$62,0,-($D122-1)))) | K122: =IF($D122>$C$61,0,IF($D122>K$5,"",OFFSET(K$62,0,-($D122-1)))) | L122: =IF($D122>$C$61,0,IF($D122>L$5,"",OFFSET(L$62,0,-($D122-1)))) | ... BL122: =IF($D122>$C$61,0,IF($D122>BL$5,"",OFFSET(BL$62,0,-($D122-1)))) -> 0

Sheet Sheet1
