Workbook
Name __S1: {"Book1"}
Name __S1: {"Book1"}
Name __S1: {"Book1"}
Name _a1: {"'Sheet1'!$L$16"}
Name _a1: {"'Sheet1'!$L$16"}
Name _a1: {"'Sheet1'!$L$16"}
Name _S1: {"Book1"}
Name _S1: {"Book1"}
Name _S1: {"Book1"}
Name Ă: #REF!
Name Ạ196: #REF!
Name â259: #REF!
Name â259: #REF!
Name â312: #REF!
Name â312: #REF!
Name Acquisition_PlanA: #REF!
Name Acquisition_PlanB: #REF!
Name Actual: (PeriodInActual*(#REF!>0))*PeriodInPlan
Name Actual: (PeriodInActual*(#REF!>0))*PeriodInPlan
Name Actual: (PeriodInActual*(#REF!>0))*PeriodInPlan
Name ActualBeyond: PeriodInActual*(#REF!>0)
Name ActualBeyond: PeriodInActual*(#REF!>0)
Name ActualBeyond: PeriodInActual*(#REF!>0)
Name adf: #REF!
Name adf: #REF!
Name adf: #REF!
Name AdvIncQ12020: #REF!
Name AdvIncQ12020: #REF!
Name AdvIncQ12021: #REF!
Name AdvIncQ12021: #REF!
Name AdvIncQ12022: #REF!
Name AdvIncQ12022: #REF!
Name AdvIncQ12023: #REF!
Name AdvIncQ12023: #REF!
Name AdvIncQ12024: #REF!
Name AdvIncQ12024: #REF!
Name AdvIncQ22020: #REF!
Name AdvIncQ22020: #REF!
Name AdvIncQ22021: #REF!
Name AdvIncQ22021: #REF!
Name AdvIncQ22022: #REF!
Name AdvIncQ22022: #REF!
Name AdvIncQ22023: #REF!
Name AdvIncQ22023: #REF!
Name AdvIncQ22024: #REF!
Name AdvIncQ22024: #REF!
Name AdvIncQ32020: #REF!
Name AdvIncQ32020: #REF!
Name AdvIncQ32021: #REF!
Name AdvIncQ32021: #REF!
Name AdvIncQ32022: #REF!
Name AdvIncQ32022: #REF!
Name AdvIncQ32023: #REF!
Name AdvIncQ32023: #REF!
Name AdvIncQ32024: #REF!
Name AdvIncQ32024: #REF!
Name AdvIncQ42020: #REF!
Name AdvIncQ42020: #REF!
Name AdvIncQ42021: #REF!
Name AdvIncQ42021: #REF!

Sheet NOTE
A1: SAP MODEL - CASHLOAN
B2: OFFICIAL | N2: HKN | O2: v9 | P2: 20251001
B3: 1. Notes and disclaimer
C4: a. Giới thiệu về SAP
D5: - SAP: Single Account Profitability (Hiệu quả sản phẩm trên từng đơn vị sản phẩm)
D6: - Model SAP được sử dụng như một (01) trong các mô hình dự đoán hiệu quả vòng đời của sản phẩm.
D7: - Do sự phức tạp của sản phẩm, các hệ thống vận hành (hệ thống hạch kế toán, hệ thống quản trị rủi ro, hệ thống quản trị…), hành vi người sử dụng hành vi người sử dụng, model chỉ có thể mô phỏng tương đối trung bình vòng đời của sản phẩm.
D8: - Do tính chất thời điểm, mô hình được xây dựng mô phỏng theo cách vận hành sản phẩm tại thời điểm phát hành. Trường hợp hệ thống thay đổi, sản phẩm thay đổi, mô hình sẽ không thể phản ánh đúng bản chất vận hành sản phẩm.
D9: - Mô hình được tính toán dựa vào các yếu tố đầu vào xác định tại một thời điểm xác định, do đó kết quả của mô hình có thể có sự khác biệt so với thực tế vận hành sản phẩm.
D10: - Mô hình SAP Cashloan tính hiệu quả của khoản vay giải ngân và thời hạn tối đa được áp dụng là 5 năm ( 60 tháng) kể từ ngày bắt đầu sản phẩm đối với sử dụng phương pháp dự phòng IFRS
E11: - Lưu ý rằng trường hợp áp dụng cho khoản vay 5 năm, thì các chi phí sẽ không được tính toán đầy đủ do chi phí COF cho thời gian từ lúc khoản vay kết thúc tới lúc được xóa trên sổ kế toán.
E12: - Chỉ nên sử dụng với khoản vay dưới 4 năm (48 tháng) để được tính toán đầy đủ chi phí
E13: - Đối với phương pháp tính rủi ro VAS, thời hạn khoản vay tối đa sử dụng là 4 năm (48 tháng)
C15: b. Giới thiệu về PnL
D16: - Trong file tính này, Profit & Lost (PnL) được dự phóng từ trung bình cộng kết quả kinh doanh trên từng sản phẩm (SAP) với yếu tố "sale plan" (số giải ngân) qua từng tháng, do đó có thể khác biệt so với kết quả thực tế vận hành.
D17: - Dòng tiền thực tế qua từng tháng có thể khác biệt với mô hình tính toán do nhiều yếu tố tác động bên ngoài thay đổi, do đó, vui lòng chỉ sử dụng mô hình cho mục đích tham khảo.
D18: - Cho mục đích tính dự phòng dòng tiền ngắn và trung hạn, mô hình PnL được cutoff tại thời điểm 5 năm (60 tháng) kể từ ngày bắt đầu khởi chạy sản phẩm đầu tiên.
B20: 2. Instruction
D21: - Dành cho người sử dụng
E22: - Chỉ chỉnh sửa vào các ô màu vàng
E23: - 2 sheets "SAP_Leadsheet" và "Sale plan&PnL" cung cấp yếu tố đầu vào và đầu ra để tính toán mô hình SAP cũng như PnL.
F24: - Sheet SAP_Leadsheet được cấu trúc 2 phần, bên trái là các yếu tố đầu vào (input) và bên phải là kết quả dự đoán (output). Đơn vị sử dụng tại bảng tính là triệu VND (mVND) và phần trăm (%)
F25: - Sheet "Sale plan & PL" được cấu trúc 2 phần, bên trên là sale plan và bên dưới là kết quả PnL
E26: - 2 sheets "SAP_Spreadsheet" và "PL projection speadsheet" là các file tính toán cho 2 sheet "SAP_Leadsheet", "Sales plan & PL"
F27: - 2 sheets được cấu trúc từ trên xuống dưới theo thứ tự tính toán mô phỏng để đưa ra kết quả kinh doanh cuối cùng
F28: - 2 sheets đã được tạm khóa. Trường hợp cần mở khóa, điều chỉnh các yếu tố, vui lòng liên hệ với nhóm vận hành để được hỗ trợ.
D30: - Dành riêng cho người vận hành, hiệu chỉnh
E31: - Cần cẩn trọng khi điều chỉnh ở các file "speadsheet" vì 1 khi sai lệch rất khó tìm ra lỗi (VD: sửa nhầm ô, link nhầm vị trí,…)
B34: 3. Legend
C35: GENERAL INPUT
G37: Diễn giải | L37: Chú thích
D38: Risk input | G38: Loại phương pháp tính rủi ro | L38: Lựa chon phương pháp tính rủi ro VAS và IFRS
D39: Write off | G39: Thời điểm WO | L39: Lựa chọn thời điểm ghi nhận WO là 360 hoặc 180
C40: REVENUE INPUT
G42: Diễn giải | L42: Chú thích
C43: Amount & Tenor
D44: Loan amount | G44: Số tiền vay giải ngân (có thể bao gồm bảo hiểm hoặc không) | L44: Trường hợp số tiền giải ngân > giá trị hàng hóa, chỉ ghi = số thực tế giải ngân
D45: Payment Method | G45: Phương pháp tính lãi | L45: EMI (Equated monthly Installment)- số tiền thanh toán cố định hàng tháng
D46: Nominal Tenor | G46: Thời hạn vay | L46: Thời hạn ghi nhận trên khoản vay ( VD: 1 tháng, 3 tháng, 12 tháng,…)
D47: Maturity to Termination | G47: Thời hạn từ lúc đáo hạn tới lúc tới khi ra ngoại bảng | L47: Nên để 6 tháng để khớp với hệ thống kế toán, rủi ro đang ghi nhận WO180+
D48: Month on book | G48: Thời gian ghi nhận trên sổ sách | L48: = Nominal tenor + Maturity to termination
C50: Pricing
D51: From- To | G51: Từ tháng… tới tháng
D52: IR | G52: Interest rate- lãi suất khoản vay
D53: COF | G53: Cost of fund - Giá vốn | L53: Sử dụng matrix mua vốn của VPB
D54: NIM | G54: Net interest margin - Biên lãi ròng
C56: Early prepayment
D57: From- To | G57: Từ tháng… tới tháng
D58: Penalty fee | G58: Phí phạt
D59: Penalty IR | G59: Lãi phạt
D60: %Attrition | G60: Tỉ lệ trả trước hạn | L60: Tỉ lệ trả trước tính theo cohort, thông thường quan sát trung bình 6 tháng
C61: Credit insurrance
D62: Banca Premium (excl. in loan) | G62: Tỉ lệ bảo hiểm khoản vay (dư nợ không bao gồm bảo hiểm khoản vay) | L62: VD: 7% khoản vay, 8% khoản vay
D63: Banca Premium (incl. in loan) | G63: Tỉ lệ bảo hiểm khoản vay (dư nợ có bao gồm bảo hiểm khoản vay)
D64: Penetration | G64: Tỉ lệ khoản vay có bảo hiểm/tổng khoản vay giải ngân
D65: Commission to CAKE | G65: Tỉ lệ nhận được từ số tiền bảo hiểm | L65: Hiện tai, số này là khoàng 85% tổng số tiền thu từ bảo hiểm
C66: Support fee
D67: Các khoản thu khác | L67: Hiện tại chưa có
C72: COST INPUT
G74: Diễn giải | L74: Chú thích
C75: Inflation rate | G75: Tỉ lệ tăng giá chi phí qua các năm
C77: Acquisition cost | G77: Chi phí mở rộng khách hàng
D78: Sale incentive | G78: Chi phí sales, trả đối tác kinh doanh
D79: Sharing TOI and Risk DPD90+ | G79: Chia sẻ doanh thu, rủi ro(DPD90+) | L79: xem giải thích DPD+ tại đây
D80: Sharing TOI and Risk DPD180+ | G80: Chia sẻ doanh thu, rủi ro(DPD180+) | L80: xem giải thích DPD+ tại đây
D82: Sharing CII (only) | G82: Chỉ chia sẻ doanh thu từ lãi
D83: Sharing COF (only) | G83: Chỉ chia sẻ chi phí vốn
D84: Sharing NFI (only) | G84: Chỉ chia sẻ doanh thu từ vốn
D85: Sharing Risk DPD90+ (Only) | G85: Chỉ chia sẻ rủi ro (DPD90+) | L85: xem giải thích DPD+ tại đây
D86: Sharing Risk DPD180+ (only) | G86: Chỉ chia sẻ rủi ro (DPD180+) | L86: xem giải thích DPD+ tại đây
D88: Partner Lead Acquistion | G88: Chi phí leadgen đối tác
C90: * Chú thích
C91: Chia sẻ rủi ro DPD90/ (DPD180+) là phương pháp tính rủi ro = 100% duy nhất 1 lần tại thời điểm dư nợ DPD90 +(tức quá hạn >90 ngày, chuyển nợ nhóm 3)/ DPD180+(tức qua hạn >180 ngày, chuyển nợ nhóm 4) mà ko tính tại các bucket khác.
C92: Phương pháp này chỉ sử dụng đối với các đối tác chia sẻ doanh thu chi phí.
D94: Marketing cost | G94: Chi phí marketing để mở khoản vay
D96: UW & Disbursal
E97: Underwriting cost & Score | G97: Chi phí kiểm tra điều kiện mở khoản vay
E98: DOP cost | G98: Chi phí luồng DOP (nếu có) (SMS,…)
E99: Disbursement cost | G99: Chi phí mở khoản vay (chi phí esign, sms,…)
E100: Approval rate | G100: Tỉ lệ phê duyệt | L100: Tỉ lệ khách hàng được phê duyệt/khách hàng vào luồng LOS
E101: Disbursement rate | G101: Tỉ lệ giải ngân | L101: Tỉ lệ khách hàng giải ngân/khách hàng được phê duyệt
D103: Collection & AMC
E104: Collections_all | G104: Đơn giá thu nợ tính trung bình cho các khoản vay
D106: Aftersale service
E107: Email & SMS | G107: Chi phí Email, SMS hàng tháng
D109: Supporting units | G109: Chi phí phân bổ
E110: Direct HR | G110: Chi phí nhân sự trực tiếp
E111: Indirect HR | G111: Chi phí nhân sự hỗ trợ
E112: IT | G112: Chi phí IT
E113: Other supports | G113: Chi phí khác (Chi phí thuê VP, CS, khác…)
C115: RISK INPUT
D117: NF | G117: Netflow- Tỉ lệ chuyển nợ
D118: PD | G118: Percentage of debt (tỉ lệ vỡ nợ)
D119: Pro. Rate | G119: Tỉ lệ vỡ nợ đã điều chỉnh thu hồi nợ
D121: Recovery rate | G121: Tỉ lệ thu hồi nợ sau WO
D122: Collect after WO
D123: Fee and others | G123: Tỉ lệ thu được phí, phạt, khác
B128: Write-off mode | E128: Provision mode
B129: DPD360+ | E129: IFRS
B130: DPD180+ | E130: VAS

Sheet DATA
C1: HKN
C2: Export source: 20260122
B4: 1 | C4: Aproval rate, signed rate
C6: aprroval rate | E6: =D10/D9 -> 0.38146326
C7: Signed rate | E7: =D11/D10 -> 0.93733228
C9: Application | D9: 2947196
C10: Approval | D10: 1124247
C11: Signed | D11: 1053793
B19: 2 | C19: Disburse, Tenor, Insurance, IR
C21: Disburse date | D21: # Disburse | E21: Disburse amount (VND) | G21: Ticket size (VND) | H21: Avg tenor (Month) | I21: Avg IR (%) | J21: Insurance fee (VND) | K21: % Insurance penetration by date
B22: PD | C22: 45992 | D22: 188031 | E22: 699210716000 | F22: 190721187321 | G22: 3718592.8 | H22: 1 | I22: 0.56689296 | J22: 51741676000 | K22: 0.99998936 | L22: =E22-J22 -> 647469040000
B23: PD | C23: 45962 | D23: 168520 | E23: 573628436000 | F23: 34260992528 | G23: 3403919 | H23: 1 | I23: 0.56788096 | J23: 42439206000 | K23: 1 | L23: =E23-J23 -> 531189230000
B24: PD | C24: 45931 | D24: 170703 | E24: 591442880000 | F24: 36240388319 | G24: 3464748 | H24: 1 | I24: 0.56997153 | J24: 43760590000 | K24: 1 | L24: =E24-J24 -> 547682290000
B25: PD | C25: 45901 | D25: 137891 | E25: 468373996000 | F25: 31047611939 | G25: 3396697.4 | H25: 1 | I25: 0.57105322 | J25: 34644786000 | K25: 1 | L25: =E25-J25 -> 433729210000
B26: PD | C26: 45870 | D26: 92113 | E26: 314000196000 | F26: 15439379324 | G26: 3408858.6 | H26: 1 | I26: 0.57115065 | J26: 23212896000 | K26: 1 | L26: =E26-J26 -> 290787300000
B27: PD | C27: 45839 | D27: 63333 | E27: 236663940000 | F27: 12296965387 | G27: 3736818.7 | H27: 1 | I27: 0.58071937 | J27: 17494140000 | K27: 1 | L27: =E27-J27 -> 219169800000
B28: PD | C28: 45809 | D28: 37045 | E28: 164604632000 | F28: 5584537745 | G28: 4443369.7 | H28: 1 | I28: 0.59810501 | J28: 12170632000 | K28: 0.99997301 | L28: =E28-J28 -> 152434000000
B29: PD | C29: 45778 | D29: 40652 | E29: 167858172000 | F29: 6206674079 | G29: 4129149.2 | H29: 1 | I29: 0.59718095 | J29: 12395692000 | K29: 1 | L29: =E29-J29 -> 155462480000
B30: PD | C30: 45748 | D30: 40388 | E30: 163797828000 | F30: 5553237320 | G30: 4055606.3 | H30: 1 | I30: 0.59601862 | J30: 12087558000 | K30: 1 | L30: =E30-J30 -> 151710270000
B31: PD | C31: 45717 | D31: 42319 | E31: 158845500000 | F31: 5459971468 | G31: 3753526.8 | H31: 1 | I31: 0.59481084 | J31: 12610100000 | K31: 0.99981096 | L31: =E31-J31 -> 146235400000
B32: PD | C32: 45689 | D32: 35363 | E32: 133485000000 | F32: 4749141919 | G32: 3774708 | H32: 1 | I32: 0.59569041 | J32: 10618710000 | K32: 1 | L32: =E32-J32 -> 122866290000
B33: PD | C33: 45658 | D33: 37562 | E33: 141375000000 | F33: 5354592901 | G33: 3763777.2 | H33: 1 | I33: 0.59706086 | J33: 11270440000 | K33: 1 | L33: =E33-J33 -> 130104560000
H35: =SUMPRODUCT(H22:H33,D22:D33)/SUM(D22:D33) -> 1
F36: Adj ticket size | G36: Ticketsize | H36: Tenor | J36: % Insurance rate | K36: Penetration
C37: AVG | F37: =G37 -> 3.5358329 | G37: =SUM(E22:E24)/SUM(D22:D24)/10^6 -> 3.5358329 | H37: =ROUND(SUMPRODUCT(H22:H24,E22:E24)/SUM(E22:E24),0) -> 1 | I37: =AVERAGE(I22:I24) -> 0.56824848 | J37: 0.08 | K37: =SUMPRODUCT(K22:K24,E22:E24)/SUM(E22:E24) -> 0.99999601
D39: 1 | E39: =D39+1 -> 2 | F39: =E39+1 -> 3 | G39: =F39+1 -> 4 | H39: =G39+1 -> 5 | I39: =H39+1 -> 6 | J39: =I39+1 -> 7 | K39: =J39+1 -> 8 | L39: =K39+1 -> 9 | M39: =L39+1 -> 10 | N39: 11 | O39: 12
C40: Limit OD | D40: 581050000 | E40: 427800000 | F40: 512350000 | G40: 514550000 | H40: 517850000 | I40: 527000000 | J40: 425350000 | K40: 78350000 | L40: 86800000 | M40: 104300000 | N40: 85100000 | O40: 69950000
C42: Limit fee | D42: =SUM(M40:O40)/SUM(D22:D24)/10^6 -> 0.00049188816
B47: 3 | C47: UW, collection, MKT
D49: 1 | E49: =D49+1 -> 2 | F49: =E49+1 -> 3 | G49: =F49+1 -> 4 | H49: =G49+1 -> 5 | I49: =H49+1 -> 6 | J49: =I49+1 -> 7 | K49: =J49+1 -> 8 | L49: =K49+1 -> 9 | M49: =L49+1 -> 10 | N49: 11 | O49: 12
C50: New ACC | D50: =PNL!M517+PNL!M556+PNL!M595+PNL!M634+PNL!M672 -> 37557 | E50: =PNL!N517+PNL!N556+PNL!N595+PNL!N634+PNL!N672 -> 35357 | F50: =PNL!O517+PNL!O556+PNL!O595+PNL!O634+PNL!O672 -> 42315 | G50: =PNL!P517+PNL!P556+PNL!P595+PNL!P634+PNL!P672 -> 40433 | H50: =PNL!Q517+PNL!Q556+PNL!Q595+PNL!Q634+PNL!Q672 -> 40883 | I50: =PNL!R517+PNL!R556+PNL!R595+PNL!R634+PNL!R672 -> 37045 | J50: =PNL!S517+PNL!S556+PNL!S595+PNL!S634+PNL!S672 -> 63333 | K50: =PNL!T517+PNL!T556+PNL!T595+PNL!T634+PNL!T672 -> 92113 | ... O50: =PNL!X517+PNL!X556+PNL!X595+PNL!X634+PNL!X672 -> 188031
C51: Accum | D51: =PNL!M519+PNL!M558+PNL!M597+PNL!M636+PNL!M674 -> 48569 | E51: =PNL!N519+PNL!N558+PNL!N597+PNL!N636+PNL!N674 -> 43818 | F51: =PNL!O519+PNL!O558+PNL!O597+PNL!O636+PNL!O674 -> 45385 | G51: =PNL!P519+PNL!P558+PNL!P597+PNL!P636+PNL!P674 -> 44806 | H51: =PNL!Q519+PNL!Q558+PNL!Q597+PNL!Q636+PNL!Q674 -> 44647 | I51: =PNL!R519+PNL!R558+PNL!R597+PNL!R636+PNL!R674 -> 42621 | J51: =PNL!S519+PNL!S558+PNL!S597+PNL!S636+PNL!S674 -> 45925 | K51: =PNL!T519+PNL!T558+PNL!T597+PNL!T636+PNL!T674 -> 83734 | ... O51: =PNL!X519+PNL!X558+PNL!X597+PNL!X636+PNL!X674 -> 184132
C52: Disbursement | D52: =PNL!M520+PNL!M559+PNL!M598+PNL!M637+PNL!M675 -> 141375000000 | E52: =PNL!N520+PNL!N559+PNL!N598+PNL!N637+PNL!N675 -> 133485000000 | F52: =PNL!O520+PNL!O559+PNL!O598+PNL!O637+PNL!O675 -> 158817500000 | G52: =PNL!P520+PNL!P559+PNL!P598+PNL!P637+PNL!P675 -> 163797828000 | H52: =PNL!Q520+PNL!Q559+PNL!Q598+PNL!Q637+PNL!Q675 -> 167858172000 | I52: =PNL!R520+PNL!R559+PNL!R598+PNL!R637+PNL!R675 -> 164604632000 | J52: =PNL!S520+PNL!S559+PNL!S598+PNL!S637+PNL!S675 -> 236641260000 | K52: =PNL!T520+PNL!T559+PNL!T598+PNL!T637+PNL!T675 -> 314000196000 | ... O52: =PNL!X520+PNL!X559+PNL!X598+PNL!X637+PNL!X675 -> 699210716000
C54: UW | D54: =PNL!M547+PNL!M586+PNL!M625+PNL!M664+PNL!M702 -> 294708631 | E54: =PNL!N547+PNL!N586+PNL!N625+PNL!N664+PNL!N702 -> 241456911 | F54: =PNL!O547+PNL!O586+PNL!O625+PNL!O664+PNL!O702 -> 274430890 | G54: =PNL!P547+PNL!P586+PNL!P625+PNL!P664+PNL!P702 -> 2.5677811e+08 | H54: =PNL!Q547+PNL!Q586+PNL!Q625+PNL!Q664+PNL!Q702 -> 230726390 | I54: =PNL!R547+PNL!R586+PNL!R625+PNL!R664+PNL!R702 -> 2.6131897e+08 | J54: =PNL!S547+PNL!S586+PNL!S625+PNL!S664+PNL!S702 -> 774554348 | K54: =PNL!T547+PNL!T586+PNL!T625+PNL!T664+PNL!T702 -> 1088847457 | ... O54: =PNL!X547+PNL!X586+PNL!X625+PNL!X664+PNL!X702 -> 1567243148
C55: MKT acquisition | D55: =PNL!M545+PNL!M584+PNL!M623+PNL!M662+PNL!M700 -> 0 | E55: =PNL!N545+PNL!N584+PNL!N623+PNL!N662+PNL!N700 -> 0 | F55: =PNL!O545+PNL!O584+PNL!O623+PNL!O662+PNL!O700 -> 0 | G55: =PNL!P545+PNL!P584+PNL!P623+PNL!P662+PNL!P700 -> 0 | H55: =PNL!Q545+PNL!Q584+PNL!Q623+PNL!Q662+PNL!Q700 -> 0 | I55: =PNL!R545+PNL!R584+PNL!R623+PNL!R662+PNL!R700 -> 0 | J55: =PNL!S545+PNL!S584+PNL!S623+PNL!S662+PNL!S700 -> 40000000 | K55: =PNL!T545+PNL!T584+PNL!T623+PNL!T662+PNL!T700 -> 38824927 | ... O55: =PNL!X545+PNL!X584+PNL!X623+PNL!X662+PNL!X700 -> 24403980
C56: Partner acquisition | D56: =PNL!M546+PNL!M585+PNL!M624+PNL!M663+PNL!M701 -> 5613597335 | E56: =PNL!N546+PNL!N585+PNL!N624+PNL!N663+PNL!N701 -> 5090892820 | F56: =PNL!O546+PNL!O585+PNL!O624+PNL!O663+PNL!O701 -> 5481907837 | G56: =PNL!P546+PNL!P585+PNL!P624+PNL!P663+PNL!P701 -> 3923265598 | H56: =PNL!Q546+PNL!Q585+PNL!Q624+PNL!Q663+PNL!Q701 -> 4564628668 | I56: =PNL!R546+PNL!R585+PNL!R624+PNL!R663+PNL!R701 -> 5017928237 | J56: =PNL!S546+PNL!S585+PNL!S624+PNL!S663+PNL!S701 -> 5519565810 | K56: =PNL!T546+PNL!T585+PNL!T624+PNL!T663+PNL!T701 -> 5578703708 | ... O56: =PNL!X546+PNL!X585+PNL!X624+PNL!X663+PNL!X701 -> 9293871690
C57: Open cost (Esign, NFC) | D57: =PNL!M548+PNL!M549+PNL!M587+PNL!M588+PNL!M626+PNL!M627+PNL!M665+PNL!M666+PNL!M703+PNL!M704 -> 74545065 | E57: =PNL!N548+PNL!N549+PNL!N587+PNL!N588+PNL!N626+PNL!N627+PNL!N665+PNL!N666+PNL!N703+PNL!N704 -> 56131305 | F57: =PNL!O548+PNL!O549+PNL!O587+PNL!O588+PNL!O626+PNL!O627+PNL!O665+PNL!O666+PNL!O703+PNL!O704 -> 75152614 | G57: =PNL!P548+PNL!P549+PNL!P587+PNL!P588+PNL!P626+PNL!P627+PNL!P665+PNL!P666+PNL!P703+PNL!P704 -> 119315953 | H57: =PNL!Q548+PNL!Q549+PNL!Q587+PNL!Q588+PNL!Q626+PNL!Q627+PNL!Q665+PNL!Q666+PNL!Q703+PNL!Q704 -> 66792605 | I57: =PNL!R548+PNL!R549+PNL!R587+PNL!R588+PNL!R626+PNL!R627+PNL!R665+PNL!R666+PNL!R703+PNL!R704 -> 68376864 | J57: =PNL!S548+PNL!S549+PNL!S587+PNL!S588+PNL!S626+PNL!S627+PNL!S665+PNL!S666+PNL!S703+PNL!S704 -> 91851795 | K57: =PNL!T548+PNL!T549+PNL!T587+PNL!T588+PNL!T626+PNL!T627+PNL!T665+PNL!T666+PNL!T703+PNL!T704 -> 111126840 | ... O57: =PNL!X548+PNL!X549+PNL!X587+PNL!X588+PNL!X626+PNL!X627+PNL!X665+PNL!X666+PNL!X703+PNL!X704 -> 2.0607168e+08
C58: Collection | D58: =PNL!M550+PNL!M589+PNL!M628+PNL!M667+PNL!M705 -> 3.8013328e+08 | E58: =PNL!N550+PNL!N589+PNL!N628+PNL!N667+PNL!N705 -> 4.5412169e+08 | F58: =PNL!O550+PNL!O589+PNL!O628+PNL!O667+PNL!O705 -> 2.0636976e+08 | G58: =PNL!P550+PNL!P589+PNL!P628+PNL!P667+PNL!P705 -> 1.9828551e+08 | H58: =PNL!Q550+PNL!Q589+PNL!Q628+PNL!Q667+PNL!Q705 -> 2.3158827e+08 | I58: =PNL!R550+PNL!R589+PNL!R628+PNL!R667+PNL!R705 -> 80922783 | J58: =PNL!S550+PNL!S589+PNL!S628+PNL!S667+PNL!S705 -> 121000549 | K58: =PNL!T550+PNL!T589+PNL!T628+PNL!T667+PNL!T705 -> 1.2149155e+08 | ... O58: =PNL!X550+PNL!X589+PNL!X628+PNL!X667+PNL!X705 -> 5.9461648e+08
C59: SMS | D59: =PNL!M552+PNL!M591+PNL!M630+PNL!M669+PNL!M707 -> 29016624 | E59: =PNL!N552+PNL!N591+PNL!N630+PNL!N669+PNL!N707 -> 14547401 | F59: =PNL!O552+PNL!O591+PNL!O630+PNL!O669+PNL!O707 -> 19220055 | G59: =PNL!P552+PNL!P591+PNL!P630+PNL!P669+PNL!P707 -> 26683398 | H59: =PNL!Q552+PNL!Q591+PNL!Q630+PNL!Q669+PNL!Q707 -> 20358234 | I59: =PNL!R552+PNL!R591+PNL!R630+PNL!R669+PNL!R707 -> 17135613 | J59: =PNL!S552+PNL!S591+PNL!S630+PNL!S669+PNL!S707 -> 23219446 | K59: =PNL!T552+PNL!T591+PNL!T630+PNL!T669+PNL!T707 -> 16912920 | ... O59: =PNL!X552+PNL!X591+PNL!X630+PNL!X669+PNL!X707 -> 67674083
C64: =SUM(M55:O55)/SUM(M50:O50)/10^6 -> 0.00046334764 | D64: marketing_acquisition_cost
C65: =SUM(M54:O54)/SUM(M50:O50)/10^6 -> 0.0079689063 | D65: Underwriting
C66: 0.005 | D66: Collection | G66: (Chi phi Q3 không đầy đủ do chuyển đổi hệ thống)
C67: =SUM(M57:O57)/SUM(M50:O50)/10^6 -> 0.0010561588 | D67: Opening
C68: =SUM(M59:O59)/SUM(M51:O51)/10^6 -> 0.00042219527 | D68: SMS
B70: 4 | C70: Partner acquisition cost | D70: (tính theo tỉ lệ giải ngân)
D71: Sharing TOI | E71: Leadgen | I71: Disbursement | L71: Total Q4 | M71: 45658 | N71: 45689 | O71: 45717 | P71: 45748 | Q71: 45778 | R71: 45809 | S71: 45839 | T71: 45870 | U71: 45901 | V71: 45931 | W71: 45962 | X71: 45992
B72: PD | C72: VDS | D72: 0.5 | I72: Payday | J72: payday | K72: VDS | L72: =SUM(V72:X72)/10^9 -> 916.25407 | M72: 140501000000 | N72: 132184000000 | O72: 156783500000 | P72: 162270828000 | Q72: 166904172000 | R72: 164068632000 | S72: 181103580000 | T72: 188150580000 | U72: 269540028000 | V72: 322185708000 | W72: 289807632000 | X72: 304260732000
B73: PD | C73: VDS | D73: 0.5 | I73: Payday | J73: payroll | K73: VDS | L73: =SUM(V73:X73)/10^9 -> 3.471 | M73: 874000000 | N73: 1301000000 | O73: 2034000000 | P73: 1527000000 | Q73: 954000000 | R73: 536000000 | S73: 894000000 | T73: 1104000000 | U73: 1189000000 | V73: 942000000 | W73: 1259000000 | X73: 1270000000
B74: PD | C74: CAKE | I74: Payday | J74: payday | K74: CAKE | L74: =SUM(V74:X74)/10^9 -> 922.28393 | S74: 54643680000 | T74: 124745616000 | U74: 196882488000 | V74: 261600732000 | W74: 276096276000 | X74: 384586924000
B75: PD | C75: VNPAY | E75: 0.01 | I75: Payday | J75: payday | K75: VNPAY | L75: =SUM(V75:X75)/10^9 -> 21.993228 | S75: 0 | T75: 0 | U75: 756000000 | V75: 6445440000 | W75: 6465528000 | X75: 9082260000
B76: PD | C76: ZALOPAY | E76: 0.025 | I76: Payday | J76: payday | K76: ZALOPAY | L76: =SUM(V76:X76)/10^9 -> 0.0108 | S76: 0 | T76: 0 | X76: 10800000
C77: AVERAGE | D77: =SUMPRODUCT(D72:D76,$L$72:$L$76)/SUM($L$72:$L$76) -> 0.24670564 | E77: =SUMPRODUCT(E72:E76,$L$72:$L$76)/SUM($L$72:$L$76) -> 0.00011813344
B78: 5
C79: CAKE
C80: From | D80: To | E80: Penalty fee | F80: Penalty IR | G80: %Attrition | J80: From | K80: To | L80: Penalty fee | M80: Penalty IR | N80: %Attrition | Q80: From | R80: To | S80: Penalty fee | T80: Penalty IR | U80: %Attrition
A81: CL | B81: VDS | C81: 1 | D81: 1 | E81: ='Early repayment'!E179 -> 0.08 | G81: 0.12 | I81: VDS | J81: 2 | K81: 3 | L81: ='Early repayment'!E179 -> 0.08 | N81: 0.06 | P81: VDS | Q81: 4 | R81: 14 | S81: ='Early repayment'!F179 -> 0.05 | U81: 0.02
A82: CL | B82: VDS | C82: 1 | D82: 1 | E82: ='Early repayment'!E180 -> 0.08 | G82: 0.12 | I82: VDS | J82: 2 | K82: 3 | L82: ='Early repayment'!E180 -> 0.08 | N82: 0.06 | P82: VDS | Q82: 4 | R82: 14 | S82: ='Early repayment'!F180 -> 0.05 | U82: 0.02
A83: CL | B83: CAKE | C83: 1 | D83: 1 | E83: ='Early repayment'!E181 -> 0.08 | G83: 0.11 | I83: CAKE | J83: 2 | K83: 3 | L83: ='Early repayment'!E181 -> 0.08 | N83: 0.045 | P83: CAKE | Q83: 4 | R83: 14 | S83: ='Early repayment'!F181 -> 0.05 | U83: 0.018
A84: CL | B84: MWG | C84: 1 | D84: 1 | E84: ='Early repayment'!E182 -> 0.08 | G84: 0.01 | I84: MWG | J84: 2 | K84: 3 | L84: ='Early repayment'!E182 -> 0.08 | N84: 0.02 | P84: MWG | Q84: 4 | R84: 14 | S84: ='Early repayment'!F182 -> 0.08 | U84: 0.01
A85: CL | B85: VNPAY | C85: 1 | D85: 1 | E85: ='Early repayment'!E183 -> 0.08 | G85: 0.04 | I85: VNPAY | J85: 2 | K85: 3 | L85: ='Early repayment'!E183 -> 0.08 | N85: 0.025 | P85: VNPAY | Q85: 4 | R85: 14 | S85: ='Early repayment'!F183 -> 0.08 | U85: 0.025
A86: CL | B86: ZaloPAY | C86: 1 | D86: 1 | E86: ='Early repayment'!E184 -> 0.03 | G86: 0.06 | I86: ZaloPAY | J86: 2 | K86: 3 | L86: ='Early repayment'!E184 -> 0.03 | N86: 0.04 | P86: ZaloPAY | Q86: 4 | R86: 14 | S86: ='Early repayment'!F184 -> 0.03 | U86: 0.013
A87: CL | B87: VNPOST | C87: 1 | D87: 1 | E87: ='Early repayment'!E185 -> 0.03 | G87: 0.01 | I87: VNPOST | J87: 2 | K87: 3 | L87: ='Early repayment'!E185 -> 0.03 | N87: 0.01 | P87: VNPOST | Q87: 4 | R87: 14 | S87: ='Early repayment'!F185 -> 0.03 | U87: 0.01
A88: OD | C88: 1 | D88: 1 | E88: 0 | G88: 0 | J88: 2 | K88: 3 | L88: 0 | N88: 0 | Q88: 4 | R88: 14 | S88: 0 | U88: 0
A89: PD | B89: VDS | C89: 1 | D89: 1 | E89: 0 | G89: 0.95 | I89: VDS | J89: 2 | K89: 3 | L89: 0 | N89: 0 | P89: VDS | Q89: 4 | R89: 14 | S89: 0 | U89: 0
A90: PD | B90: VDS | C90: 1 | D90: 1 | E90: 0 | G90: 0.95 | I90: VDS | J90: 2 | K90: 3 | L90: 0 | N90: 0 | P90: VDS | Q90: 4 | R90: 14 | S90: 0 | U90: 0
A91: PD | B91: CAKE | C91: 1 | D91: 1 | E91: 0 | G91: 0.95 | I91: CAKE | J91: 2 | K91: 3 | L91: 0 | N91: 0 | P91: CAKE | Q91: 4 | R91: 14 | S91: 0 | U91: 0
A92: PD | B92: VNPAY | C92: 1 | D92: 1 | E92: 0 | G92: 0.95 | I92: VNPAY | J92: 2 | K92: 3 | P92: VNPAY | Q92: 4 | R92: 14
E95: Penalty fee | F95: Penalty IR | G95: %Attrition
A96: PD | B96: VDS | C96: =SUM(PNL!V523:X523) -> 892697006794 | D96: 1 | E96: =SUMPRODUCT($C$96:$C$99,$E$89:$E$92)/SUM($C$96:$C$99) -> 0 | G96: =SUMPRODUCT(G89:G92,$C$96:$C$99)/SUM($C$96:$C$99) -> 0.95
A97: PD | B97: VDS | C97: =SUM(PNL!V524:X524) -> 687117693555 | D97: 2-3 | E97: =SUMPRODUCT($C$96:$C$99,$L$89:$L$92)/SUM($C$96:$C$99) -> 0 | G97: =SUMPRODUCT(N89:N92,$C$96:$C$99)/SUM($C$96:$C$99) -> 0
A98: PD | B98: CAKE | C98: =SUM(PNL!V525:X525) -> 205579313239 | D98: other | E98: =SUMPRODUCT($C$96:$C$99,$S$89:$S$92)/SUM($C$96:$C$99) -> 0 | G98: =SUMPRODUCT($C$96:$C$99,$U$89:$U$92)/SUM($C$96:$C$99) -> 0
A99: PD | B99: VNPAY | C99: =SUM(PNL!V526:X526) -> 56415276705
B102: 6 | C102: Risk cost
B104: Row Labels | C104: ADJ | D104: AVG q4 | F104: 1 | G104: =F104+1 -> 2 | H104: =G104+1 -> 3 | I104: =H104+1 -> 4 | J104: =I104+1 -> 5 | K104: =J104+1 -> 6 | L104: =K104+1 -> 7 | M104: =L104+1 -> 8 | N104: =M104+1 -> 9 | O104: =N104+1 -> 10 | P104: 11 | Q104: 12
B105: 0 | C105: 0.074 | D105: =AVERAGE(O105:Q105) -> 0.099107559 | F105: =F124/E123 -> 0.074020724 | G105: =G124/F123 -> 0.076948372 | H105: =H124/G123 -> 0.066673858 | I105: =I124/H123 -> 0.059315377 | J105: =J124/I123 -> 0.063818607 | K105: =K124/J123 -> 0.064568755 | L105: =L124/K123 -> 0.063092421 | M105: =M124/L123 -> 0.089941045 | ... Q105: =Q124/P123 -> 0.087419174
B106: 1 | C106: 0.795 | D106: =AVERAGE(O106:Q106) -> 0.80649936 | F106: =F125/E124 -> 0.60834874 | G106: =G125/F124 -> 0.82410865 | H106: =H125/G124 -> 0.79653038 | I106: =I125/H124 -> 0.71866993 | J106: =J125/I124 -> 0.76386289 | K106: =K125/J124 -> 0.78817891 | L106: =L125/K124 -> 0.79071196 | M106: =M125/L124 -> 0.77963879 | ... Q106: =Q125/P124 -> 0.81718058
B107: 2 | C107: =D107 -> 0.95128048 | D107: =AVERAGE(O107:Q107) -> 0.95128048 | F107: 1 | G107: 1 | H107: =H126/G125 -> 0.90175172 | I107: =I126/H125 -> 0.95122497 | J107: 1 | K107: =K126/J125 -> 0.94460603 | L107: =L126/K125 -> 0.87981423 | M107: =M126/L125 -> 0.91386455 | N107: =N126/M125 -> 0.94733836 | O107: =O126/N125 -> 0.93200414 | P107: =P126/O125 -> 0.9530382 | Q107: =Q126/P125 -> 0.96879911
B108: 3 | C108: =D108 -> 0.97622305 | D108: =AVERAGE(O108:Q108) -> 0.97622305 | F108: =F127/E126 -> 0.95885304 | G108: =G127/F126 -> 0.96646117 | H108: =H127/G126 -> 1.0096081 | I108: =I127/H126 -> 0.96704879 | J108: =J127/I126 -> 0.97310308 | K108: =K127/J126 -> 0.9751925 | L108: 1 | M108: 1 | N108: =N127/M126 -> 0.96748633 | O108: =O127/N126 -> 0.96730891 | P108: =P127/O126 -> 0.97146979 | Q108: =Q127/P126 -> 0.98989045
B109: 4 | C109: =D109 -> 0.9894391 | D109: =AVERAGE(O109:Q109) -> 0.9894391 | F109: =F128/E127 -> 1.0302131 | G109: =G128/F127 -> 0.97733402 | H109: =H128/G127 -> 0.94164258 | I109: =I128/H127 -> 0.97967675 | J109: =J128/I127 -> 0.97689932 | K109: =K128/J127 -> 0.98127835 | L109: =L128/K127 -> 0.95811099 | M109: =M128/L127 -> 0.97644065 | ... Q109: =Q128/P127 -> 0.98356929
B110: 5 | C110: 0.999 | D110: =AVERAGE(O110:Q110) -> 0.9809784 | F110: =F129/E128 -> 0.99097788 | G110: =G129/F128 -> 0.91221805 | H110: =H129/G128 -> 0.9880409 | I110: =I129/H128 -> 0.98688127 | J110: =J129/I128 -> 0.92469534 | K110: =K129/J128 -> 0.98587184 | L110: 1 | M110: =M129/L128 -> 0.99542935 | N110: =N129/M128 -> 0.98651315 | O110: 1 | P110: =P129/O128 -> 0.99208829 | Q110: =Q129/P128 -> 0.9508469
B111: 6 | C111: 0.99 | D111: =AVERAGE(O111:Q111) -> 0.97462268 | F111: =F130/E129 -> 0.95742438 | G111: =G130/F129 -> 1.0244017 | H111: =H130/G129 -> 1.021361 | I111: =I130/H129 -> 0.9872606 | J111: 1 | K111: =K130/J129 -> 0.98696448 | L111: =L130/K129 -> 0.91777621 | M111: =M130/L129 -> 1.0087037 | N111: =N130/M129 -> 0.98218842 | O111: =O130/N129 -> 0.94452934 | P111: =P130/O129 -> 0.9836383 | Q111: =Q130/P129 -> 0.9957004
B112: 7 | C112: =D112 -> 0.98683542 | D112: =AVERAGE(O112:Q112) -> 0.98683542 | F112: =F131/E130 -> 0.99206204 | G112: =G131/F130 -> 0.97305851 | H112: =H131/G130 -> 0.92602683 | I112: =I131/H130 -> 0.96408864 | J112: =J131/I130 -> 0.96692409 | K112: =K131/J130 -> 0.98159444 | L112: 1 | M112: =M131/L130 -> 0.93070317 | N112: =N131/M130 -> 0.98052255 | O112: =O131/N130 -> 1.0015937 | P112: =P131/O130 -> 0.98944786 | Q112: =Q131/P130 -> 0.96946472
B113: 8 | C113: =D113 -> 0.91508468 | D113: =AVERAGE(O113:Q113) -> 0.91508468 | F113: =F132/E131 -> 0.98370329 | G113: =G132/F131 -> 0.94349863 | H113: =H132/G131 -> 1.0100234 | I113: =I132/H131 -> 0.9948871 | J113: =J132/I131 -> 1.041549 | K113: =K132/J131 -> 0.99044598 | L113: 1 | M113: =M132/L131 -> 1.0227446 | N113: =N132/M131 -> 1 | O113: =O132/N131 -> 0.70946888 | P113: =P132/O131 -> 1 | Q113: =Q132/P131 -> 1.0357852
B114: 9
B115: 10
B116: 11
B117: 12
B118: 13
B119: 14
B120: 15
F122: 1 | G122: =F122+1 -> 2 | H122: =G122+1 -> 3 | I122: =H122+1 -> 4 | J122: =I122+1 -> 5 | K122: =J122+1 -> 6 | L122: =K122+1 -> 7 | M122: =L122+1 -> 8 | N122: =M122+1 -> 9 | O122: =N122+1 -> 10 | P122: 11 | Q122: 12
D123: 0 | E123: =RISK!P8 -> 140907432312 | F123: =RISK!Q8 -> 125733474174 | G123: =RISK!R8 -> 120452958029 | H123: =RISK!S8 -> 124792371704 | I123: =RISK!T8 -> 130856706527 | J123: =RISK!U8 -> 132564696356 | K123: =RISK!V8 -> 131668433529 | L123: =RISK!W8 -> 187034559967 | ... Q123: =RISK!AB8 -> 518502880178
D124: 1 | E124: =RISK!P9 -> 8049379348 | F124: =RISK!Q9 -> 10430070154 | G124: =RISK!R9 -> 9674986086 | H124: =RISK!S9 -> 8031063372 | I124: =RISK!T9 -> 7402106547 | J124: =RISK!U9 -> 8351092769 | K124: =RISK!V9 -> 8559537399 | L124: =RISK!W9 -> 8307280207 | ... Q124: =RISK!AB9 -> 38818570296
D125: 2 | E125: =RISK!P10 -> 4435792144 | F125: =RISK!Q10 -> 4896829780 | G125: =RISK!R10 -> 8595511000 | H125: =RISK!S10 -> 7706420334 | I125: =RISK!T10 -> 5771683753 | J125: =RISK!U10 -> 5654194523 | K125: =RISK!V10 -> 6582155229 | L125: =RISK!W10 -> 6768128609 | ... Q125: =RISK!AB10 -> 34029191778
D126: 3 | E126: =RISK!P11 -> 5098774496 | F126: =RISK!Q11 -> 4313905587 | G126: =RISK!R11 -> 4713700431 | H126: =RISK!S11 -> 7751016797 | I126: =RISK!T11 -> 7330539438 | J126: =RISK!U11 -> 5690338454 | K126: =RISK!V11 -> 5340986249 | L126: =RISK!W11 -> 5791073866 | ... Q126: =RISK!AB11 -> 31842681047
D127: 4 | E127: =RISK!P12 -> 4790023788 | F127: =RISK!Q12 -> 4888975408 | G127: =RISK!R12 -> 4169222252 | H127: =RISK!S12 -> 4758990057 | I127: =RISK!T12 -> 7495611443 | J127: =RISK!U12 -> 7133370522 | K127: =RISK!V12 -> 5549175405 | L127: =RISK!W12 -> 5489579313 | ... Q127: =RISK!AB12 -> 14406280932
D128: 5 | E128: =RISK!P13 -> 4124645905 | F128: =RISK!Q13 -> 4934745342 | G128: =RISK!R13 -> 4778161995 | H128: =RISK!S13 -> 3925917203 | I128: =RISK!T13 -> 4662271901 | J128: =RISK!U13 -> 7322457696 | K128: =RISK!V13 -> 6999822052 | L128: =RISK!W13 -> 5316725948 | ... Q128: =RISK!AB13 -> 11465822103
D129: 6 | E129: =RISK!P14 -> 3444566681 | F129: =RISK!Q14 -> 4087432848 | G129: =RISK!R14 -> 4501563793 | H129: =RISK!S14 -> 4721019466 | I129: =RISK!T14 -> 3874414147 | J129: =RISK!U14 -> 4311181112 | K129: =RISK!V14 -> 7219004819 | L129: =RISK!W14 -> 7209935596 | ... Q129: =RISK!AB14 -> 5566562267
D130: 7 | E130: =RISK!P15 -> 3056608221 | F130: =RISK!Q15 -> 3297912124 | G130: =RISK!R15 -> 4187173007 | H130: =RISK!S15 -> 4597721703 | I130: =RISK!T15 -> 4660876514 | J130: =RISK!U15 -> 3968094669 | K130: =RISK!V15 -> 4254982638 | L130: =RISK!W15 -> 6625430860 | ... Q130: =RISK!AB15 -> 5901405147
D131: 8 | E131: =RISK!P16 -> 2403947249 | F131: =RISK!Q16 -> 3032344975 | G131: =RISK!R16 -> 3209061450 | H131: =RISK!S16 -> 3877434529 | I131: =RISK!T16 -> 4432611255 | J131: =RISK!U16 -> 4506713760 | K131: =RISK!V16 -> 3895059680 | L131: =RISK!W16 -> 4514742412 | ... Q131: =RISK!AB16 -> 5596138320
...

Sheet PNL
J1: 6.9400224e+11
B2: Group | C2: Product | D2: Subproduct | E2: Chanel | F2: Catergory | G2: Index | I2: Product PnL | K2: 45597 | L2: 45627 | M2: 45658 | N2: 45689 | O2: 45717 | P2: 45748 | Q2: 45778 | R2: 45809 | S2: 45839 | T2: 45870 | U2: 45901 | V2: 45931 | W2: 45962 | X2: 45992
I3: LENDING
B4: lending | D4: all | G4: =B4&"_"&C4&"_"&D4&"_"&E4&"_"&F4 -> lending__all__ | I4: New account | J4: =SUM(M4:X4) -> 1710749 | K4: =SUMIFS(K$48:K$3038,$I$48:$I$3038,"New account") -> 69275 | L4: =SUMIFS(L$48:L$3038,$I$48:$I$3038,"New account") -> 83163 | M4: =SUMIFS(M$48:M$3038,$I$48:$I$3038,"New account") -> 72675 | N4: =SUMIFS(N$48:N$3038,$I$48:$I$3038,"New account") -> 62148 | O4: =SUMIFS(O$48:O$3038,$I$48:$I$3038,"New account") -> 83436 | P4: =SUMIFS(P$48:P$3038,$I$48:$I$3038,"New account") -> 82811 | Q4: =SUMIFS(Q$48:Q$3038,$I$48:$I$3038,"New account") -> 83424 | R4: =SUMIFS(R$48:R$3038,$I$48:$I$3038,"New account") -> 86016 | ... V4: =SUMIFS(V$48:V$3038,$I$48:$I$3038,"New account") -> 242972 | W4: =SUMIFS($W$48:$W$3038,$I$48:$I$3038,"New account") -> 248246 | X4: =SUMIFS(X$48:X$3038,$I$48:$I$3038,"New account") -> 271168 | Y4: =X4-W4 -> 22922 | Z4: 248246
B5: lending | D5: all | G5: =B5&"_"&C5&"_"&D5&"_"&E5&"_"&F5 -> lending__all__ | I5: Repeat account | J5: =SUM(M5:X5) -> 977652 | K5: =SUMIFS(K$48:K$3038,$I$48:$I$3038,"Repeat account") -> 31467 | L5: =SUMIFS(L$48:L$3038,$I$48:$I$3038,"Repeat account") -> 41624 | M5: =SUMIFS(M$48:M$3038,$I$48:$I$3038,"Repeat account") -> 36793 | N5: =SUMIFS(N$48:N$3038,$I$48:$I$3038,"Repeat account") -> 35375 | O5: =SUMIFS(O$48:O$3038,$I$48:$I$3038,"Repeat account") -> 45120 | P5: =SUMIFS(P$48:P$3038,$I$48:$I$3038,"Repeat account") -> 44837 | Q5: =SUMIFS(Q$48:Q$3038,$I$48:$I$3038,"Repeat account") -> 44599 | R5: =SUMIFS(R$48:R$3038,$I$48:$I$3038,"Repeat account") -> 45859 | ... X5: =SUMIFS(X$48:X$3038,$I$48:$I$3038,"Repeat account") -> 176457 | Y5: =X5-W5 -> 18648
B6: lending | D6: all | G6: =B6&"_"&C6&"_"&D6&"_"&E6&"_"&F6 -> lending__all__ | I6: Accumulated account | J6: =W6 -> 596972 | K6: =SUMIFS(K$48:K$3038,$I$48:$I$3038,"Accumulated account") -> 263026 | L6: =SUMIFS(L$48:L$3038,$I$48:$I$3038,"Accumulated account") -> 289241 | M6: =SUMIFS(M$48:M$3038,$I$48:$I$3038,"Accumulated account") -> 293226 | N6: =SUMIFS(N$48:N$3038,$I$48:$I$3038,"Accumulated account") -> 286953 | O6: =SUMIFS(O$48:O$3038,$I$48:$I$3038,"Accumulated account") -> 302253 | P6: =SUMIFS(P$48:P$3038,$I$48:$I$3038,"Accumulated account") -> 315835 | Q6: =SUMIFS(Q$48:Q$3038,$I$48:$I$3038,"Accumulated account") -> 335201 | R6: =SUMIFS(R$48:R$3038,$I$48:$I$3038,"Accumulated account") -> 346940 | ... X6: =SUMIFS(X$48:X$3038,$I$48:$I$3038,"Accumulated account") -> 641252 | Y6: =X6-W6 -> 44280
B7: lending | D7: all | G7: =B7&"_"&C7&"_"&D7&"_"&E7&"_"&F7 -> lending__all__ | I7: Disbursement | J7: =SUM(M7:X7) -> 14621515936862 | K7: =SUMIFS(K$48:K$3038,$I$48:$I$3038,"Disbursement") -> 565385177155 | L7: =SUMIFS(L$48:L$3038,$I$48:$I$3038,"Disbursement") -> 648539970448 | M7: =SUMIFS(M$48:M$3038,$I$48:$I$3038,"Disbursement") -> 607486373275 | N7: =SUMIFS(N$48:N$3038,$I$48:$I$3038,"Disbursement") -> 495446382206 | O7: =SUMIFS(O$48:O$3038,$I$48:$I$3038,"Disbursement") -> 683532749818 | P7: =SUMIFS(P$48:P$3038,$I$48:$I$3038,"Disbursement") -> 798190174129 | Q7: =SUMIFS(Q$48:Q$3038,$I$48:$I$3038,"Disbursement") -> 840951063659 | R7: =SUMIFS(R$48:R$3038,$I$48:$I$3038,"Disbursement") -> 923959113319 | ... X7: =SUMIFS(X$48:X$3038,$I$48:$I$3038,"Disbursement") -> 2134949493401 | Y7: =X7-W7 -> 155850768634
B8: lending | D8: all | G8: =B8&"_"&C8&"_"&D8&"_"&E8&"_"&F8 -> lending__all__ | I8: Disbursement w insurance | K8: =SUMIFS(K$48:K$3038,$I$48:$I$3038,"Disbursement w insurance") -> 415183060000 | L8: =SUMIFS(L$48:L$3038,$I$48:$I$3038,"Disbursement w insurance") -> 482160430000 | M8: =SUMIFS(M$48:M$3038,$I$48:$I$3038,"Disbursement w insurance") -> 444116950000 | N8: =SUMIFS(N$48:N$3038,$I$48:$I$3038,"Disbursement w insurance") -> 350181210000 | O8: =SUMIFS(O$48:O$3038,$I$48:$I$3038,"Disbursement w insurance") -> 496968420000 | P8: =SUMIFS(P$48:P$3038,$I$48:$I$3038,"Disbursement w insurance") -> 588092938000 | Q8: =SUMIFS(Q$48:Q$3038,$I$48:$I$3038,"Disbursement w insurance") -> 593910462000 | R8: =SUMIFS(R$48:R$3038,$I$48:$I$3038,"Disbursement w insurance") -> 669560212000 | ... X8: =SUMIFS(X$48:X$3038,$I$48:$I$3038,"Disbursement w insurance") -> 1785933196000 | Y8: =X8-W8 -> 130786320000
B9: lending | D9: all | G9: =B9&"_"&C9&"_"&D9&"_"&E9&"_"&F9 -> lending__all__ | I9: Disbursement w/o insurance | K9: =SUMIFS(K$48:K$3038,$I$48:$I$3038,"Disbursement w/o insurance") -> 44524560000 | L9: =SUMIFS(L$48:L$3038,$I$48:$I$3038,"Disbursement w/o insurance") -> 52877400000 | M9: =SUMIFS(M$48:M$3038,$I$48:$I$3038,"Disbursement w/o insurance") -> 54308000000 | N9: =SUMIFS(N$48:N$3038,$I$48:$I$3038,"Disbursement w/o insurance") -> 50012000000 | O9: =SUMIFS(O$48:O$3038,$I$48:$I$3038,"Disbursement w/o insurance") -> 74491000000 | P9: =SUMIFS(P$48:P$3038,$I$48:$I$3038,"Disbursement w/o insurance") -> 95609900000 | Q9: =SUMIFS(Q$48:Q$3038,$I$48:$I$3038,"Disbursement w/o insurance") -> 127503000000 | R9: =SUMIFS(R$48:R$3038,$I$48:$I$3038,"Disbursement w/o insurance") -> 135639400000 | ... X9: =SUMIFS(X$48:X$3038,$I$48:$I$3038,"Disbursement w/o insurance") -> 278008000000 | Y9: =X9-W9 -> 27131000000
B10: lending | D10: all | G10: =B10&"_"&C10&"_"&D10&"_"&E10&"_"&F10 -> lending__all__ | I10: Balance ENR | J10: =V10 -> 5341105587162 | K10: =SUMIFS(K$48:K$3038,$I$48:$I$3038,"Balance ENR") -> 2052438476066 | L10: =SUMIFS(L$48:L$3038,$I$48:$I$3038,"Balance ENR") -> 2208691233824 | M10: =SUMIFS(M$48:M$3038,$I$48:$I$3038,"Balance ENR") -> 2353465097862 | N10: =SUMIFS(N$48:N$3038,$I$48:$I$3038,"Balance ENR") -> 2269348501981 | O10: =SUMIFS(O$48:O$3038,$I$48:$I$3038,"Balance ENR") -> 2381914281455 | P10: =SUMIFS(P$48:P$3038,$I$48:$I$3038,"Balance ENR") -> 2586626572528 | Q10: =SUMIFS(Q$48:Q$3038,$I$48:$I$3038,"Balance ENR") -> 2809564235670 | R10: =SUMIFS(R$48:R$3038,$I$48:$I$3038,"Balance ENR") -> 3047094181089 | ... X10: =SUMIFS(X$48:X$3038,$I$48:$I$3038,"Balance ENR") -> 6617059046336 | Y10: =X10-W10 -> 627698525984
B11: lending | D11: all | G11: =B11&"_"&C11&"_"&D11&"_"&E11&"_"&F11 -> lending__all__ | I11: Indue balance | K11: =SUMIFS(K$48:K$3038,$I$48:$I$3038,"Indue balance") -> 1861677245641 | L11: =SUMIFS(L$48:L$3038,$I$48:$I$3038,"Indue balance") -> 2017439375775 | M11: =SUMIFS(M$48:M$3038,$I$48:$I$3038,"Indue balance") -> 2146462749230 | N11: =SUMIFS(N$48:N$3038,$I$48:$I$3038,"Indue balance") -> 2109310363676 | O11: =SUMIFS(O$48:O$3038,$I$48:$I$3038,"Indue balance") -> 2212171474295 | P11: =SUMIFS(P$48:P$3038,$I$48:$I$3038,"Indue balance") -> 2407668341994 | Q11: =SUMIFS(Q$48:Q$3038,$I$48:$I$3038,"Indue balance") -> 2623647731424 | R11: =SUMIFS(R$48:R$3038,$I$48:$I$3038,"Indue balance") -> 2862461599102 | ... X11: =SUMIFS(X$48:X$3038,$I$48:$I$3038,"Indue balance") -> 6319462955843 | Y11: =X11-W11 -> 607432583519
B12: lending | D12: all | G12: =B12&"_"&C12&"_"&D12&"_"&E12&"_"&F12 -> lending__all__ | I12: Overdue balance (dpd >0) | K12: =SUMIFS(K$48:K$3038,$I$48:$I$3038,"Overdue balance (dpd >0)") -> 190761230425 | L12: =SUMIFS(L$48:L$3038,$I$48:$I$3038,"Overdue balance (dpd >0)") -> 191251858049 | M12: =SUMIFS(M$48:M$3038,$I$48:$I$3038,"Overdue balance (dpd >0)") -> 207002348632 | N12: =SUMIFS(N$48:N$3038,$I$48:$I$3038,"Overdue balance (dpd >0)") -> 160038138305 | O12: =SUMIFS(O$48:O$3038,$I$48:$I$3038,"Overdue balance (dpd >0)") -> 169742807160 | P12: =SUMIFS(P$48:P$3038,$I$48:$I$3038,"Overdue balance (dpd >0)") -> 178958230534 | Q12: =SUMIFS(Q$48:Q$3038,$I$48:$I$3038,"Overdue balance (dpd >0)") -> 185916504246 | R12: =SUMIFS(R$48:R$3038,$I$48:$I$3038,"Overdue balance (dpd >0)") -> 184632581987 | ... X12: =SUMIFS(X$48:X$3038,$I$48:$I$3038,"Overdue balance (dpd >0)") -> 297596090493 | Y12: =X12-W12 -> 20265942465
B13: lending | D13: all | G13: =B13&"_"&C13&"_"&D13&"_"&E13&"_"&F13 -> lending__all__ | I13: Overdue balance (90d+)- CAKE | K13: =SUMIFS(K$48:K$3038,$I$48:$I$3038,"Overdue balance (90d+)- CAKE") -> 209084219244 | L13: =SUMIFS(L$48:L$3038,$I$48:$I$3038,"Overdue balance (90d+)- CAKE") -> 218890134025 | M13: =SUMIFS(M$48:M$3038,$I$48:$I$3038,"Overdue balance (90d+)- CAKE") -> 251298767400 | N13: =SUMIFS(N$48:N$3038,$I$48:$I$3038,"Overdue balance (90d+)- CAKE") -> 189681407635 | O13: =SUMIFS(O$48:O$3038,$I$48:$I$3038,"Overdue balance (90d+)- CAKE") -> 197886173133 | P13: =SUMIFS(P$48:P$3038,$I$48:$I$3038,"Overdue balance (90d+)- CAKE") -> 205873544624 | Q13: =SUMIFS(Q$48:Q$3038,$I$48:$I$3038,"Overdue balance (90d+)- CAKE") -> 223901043135 | R13: =SUMIFS(R$48:R$3038,$I$48:$I$3038,"Overdue balance (90d+)- CAKE") -> 210075662340 | ... X13: =SUMIFS(X$48:X$3038,$I$48:$I$3038,"Overdue balance (90d+)- CAKE") -> 246201433440 | Y13: =X13-W13 -> 10263474907
B14: lending | D14: all | G14: =B14&"_"&C14&"_"&D14&"_"&E14&"_"&F14 -> lending__all__ | I14: Overdue balance (10d+) | K14: =SUMIFS(K$48:K$3038,$I$48:$I$3038,"Overdue balance (10d+)") -> 425943553591 | L14: =SUMIFS(L$48:L$3038,$I$48:$I$3038,"Overdue balance (10d+)") -> 470976426376 | M14: =SUMIFS(M$48:M$3038,$I$48:$I$3038,"Overdue balance (10d+)") -> 495636150490 | N14: =SUMIFS(N$48:N$3038,$I$48:$I$3038,"Overdue balance (10d+)") -> 446334022206 | O14: =SUMIFS(O$48:O$3038,$I$48:$I$3038,"Overdue balance (10d+)") -> 482513889165 | P14: =SUMIFS(P$48:P$3038,$I$48:$I$3038,"Overdue balance (10d+)") -> 467190144812 | Q14: =SUMIFS(Q$48:Q$3038,$I$48:$I$3038,"Overdue balance (10d+)") -> 488876105575 | R14: =SUMIFS(R$48:R$3038,$I$48:$I$3038,"Overdue balance (10d+)") -> 535617603799 | ... X14: =SUMIFS(X$48:X$3038,$I$48:$I$3038,"Overdue balance (10d+)") -> 0 | Y14: =X14-W14 -> -882816124425
B15: lending | D15: all | G15: =B15&"_"&C15&"_"&D15&"_"&E15&"_"&F15 -> lending__all__ | I15: Overdue balance (90+) | K15: =SUMIFS(K$48:K$3038,$I$48:$I$3038,"Overdue balance (90+)") -> 229333356425 | L15: =SUMIFS(L$48:L$3038,$I$48:$I$3038,"Overdue balance (90+)") -> 246335530146 | M15: =SUMIFS(M$48:M$3038,$I$48:$I$3038,"Overdue balance (90+)") -> 273128559163 | N15: =SUMIFS(N$48:N$3038,$I$48:$I$3038,"Overdue balance (90+)") -> 216556182793 | O15: =SUMIFS(O$48:O$3038,$I$48:$I$3038,"Overdue balance (90+)") -> 241525121033 | P15: =SUMIFS(P$48:P$3038,$I$48:$I$3038,"Overdue balance (90+)") -> 239203735205 | Q15: =SUMIFS(Q$48:Q$3038,$I$48:$I$3038,"Overdue balance (90+)") -> 257266404757 | R15: =SUMIFS(R$48:R$3038,$I$48:$I$3038,"Overdue balance (90+)") -> 264987269863 | ... X15: =SUMIFS(X$48:X$3038,$I$48:$I$3038,"Overdue balance (90+)") -> 0 | Y15: =X15-W15 -> -288216101887
B16: lending | D16: all | G16: =B16&"_"&C16&"_"&D16&"_"&E16&"_"&F16 -> lending__all__ | I16: Overdue balance (11-90d) | K16: =SUMIFS(K$48:K$3038,$I$48:$I$3038,"Overdue balance (11-90d)") -> 196610197166 | L16: =SUMIFS(L$48:L$3038,$I$48:$I$3038,"Overdue balance (11-90d)") -> 224392444824 | M16: =SUMIFS(M$48:M$3038,$I$48:$I$3038,"Overdue balance (11-90d)") -> 222507591327 | N16: =SUMIFS(N$48:N$3038,$I$48:$I$3038,"Overdue balance (11-90d)") -> 229777839413 | O16: =SUMIFS(O$48:O$3038,$I$48:$I$3038,"Overdue balance (11-90d)") -> 240988768132 | P16: =SUMIFS(P$48:P$3038,$I$48:$I$3038,"Overdue balance (11-90d)") -> 227986409607 | Q16: =SUMIFS(Q$48:Q$3038,$I$48:$I$3038,"Overdue balance (11-90d)") -> 231609700818 | R16: =SUMIFS(R$48:R$3038,$I$48:$I$3038,"Overdue balance (11-90d)") -> 270630333936 | ... X16: =SUMIFS(X$48:X$3038,$I$48:$I$3038,"Overdue balance (11-90d)") -> 0 | Y16: =X16-W16 -> -593736182398
B17: lending | D17: all | G17: =B17&"_"&C17&"_"&D17&"_"&E17&"_"&F17 -> lending__all__ | I17: %NPL CAKE | K17: =K13/K10 -> 0.10187113 | L17: =L13/L10 -> 0.099103999 | M17: =M13/M10 -> 0.1067782 | N17: =N13/N10 -> 0.08358408 | O17: =O13/O10 -> 0.083078629 | P17: =P13/P10 -> 0.079591522 | Q17: =Q13/Q10 -> 0.079692445 | R17: =R13/R10 -> 0.06894295 | ... X17: =X13/X10 -> 0.037207078 | Y17: =X17-W17 -> -0.0021857681
B18: lending | D18: all | F18: npl | G18: =B18&"_"&C18&"_"&D18&"_"&E18&"_"&F18 -> lending__all__npl | I18: %NPL CIC | K18: =K15/K10 -> 0.11173702 | L18: =L15/L10 -> 0.11153009 | M18: =M15/M10 -> 0.1160538 | N18: =N15/N10 -> 0.095426587 | O18: =O15/O10 -> 0.10139959 | P18: =P15/P10 -> 0.092477104 | Q18: =Q15/Q10 -> 0.091568081 | R18: =R15/R10 -> 0.086963925 | ... X18: =X15/X10 -> 0 | Y18: =X18-W18 -> -0.048121348
B19: lending | D19: all | G19: =B19&"_"&C19&"_"&D19&"_"&E19&"_"&F19 -> lending__all__ | I19: TOI | J19: =J20+J25+J29 -> 2.1042215e+12 | K19: =K20+K25+K29 -> 79814464956 | L19: =L20+L25+L29 -> 9.0589203e+10 | M19: =M20+M25+M29 -> 93976364502 | N19: =N20+N25+N29 -> 83352868197 | O19: =O20+O25+O29 -> 1.0271915e+11 | P19: =P20+P25+P29 -> 111585837773 | Q19: =Q20+Q25+Q29 -> 120805173410 | ... X19: =X20+X25+X29 -> 320447530496 | Y19: =X19-W19 -> 36422964193
B20: lending | D20: all | G20: =B20&"_"&C20&"_"&D20&"_"&E20&"_"&F20 -> lending__all__ | I20: Net interest income | J20: =J21-J24 -> 1.2814118e+12 | K20: =K21-K24 -> 52213603901 | L20: =L21-L24 -> 58117593045 | M20: =M21-M24 -> 64177638510 | N20: =N21-N24 -> 58823369739 | O20: =O21-O24 -> 6.7391301e+10 | P20: =P21-P24 -> 71053250087 | Q20: =Q21-Q24 -> 79740766095 | ... X20: =X21-X24 -> 190414952434 | Y20: =X20-W20 -> 25163690176
B21: lending | D21: all | G21: =B21&"_"&C21&"_"&D21&"_"&E21&"_"&F21 -> lending__all__ | I21: Interest Income | J21: =SUM(M21:X21) -> 1525705629347 | K21: 62223552804 | L21: =L22+K23-L23 -> 69272878417 | M21: =M22+L23-M23 -> 76219395758 | N21: =N22+M23-N23 -> 69975903294 | O21: =O22+N23-O23 -> 79648572501 | P21: =P22+O23-P23 -> 83805884795 | Q21: =Q22+P23-Q23 -> 94103072191 | R21: =R22+Q23-R23 -> 100381074810 | S21: =S22+R23-S23 -> 118193939617 | ... X21: =X22+W23-X23 -> 229979382831 | Y21: =X21-W21 -> 31622681111
B22: lending | D22: all | G22: =B22&"_"&C22&"_"&D22&"_"&E22&"_"&F22 -> lending__all__ | I22: Thu lãi vay | J22: =SUM(M22:X22) -> 1539717162560 | K22: =SUMIFS(K$48:K$3038,$I$48:$I$3038,"Thu lãi vay") -> 63214223471 | L22: =SUMIFS(L$48:L$3038,$I$48:$I$3038,"Thu lãi vay") -> 70990475112 | M22: =SUMIFS(M$48:M$3038,$I$48:$I$3038,"Thu lãi vay") -> 76707556347 | N22: =SUMIFS(N$48:N$3038,$I$48:$I$3038,"Thu lãi vay") -> 69254610169 | O22: =SUMIFS(O$48:O$3038,$I$48:$I$3038,"Thu lãi vay") -> 79789204964 | P22: =SUMIFS(P$48:P$3038,$I$48:$I$3038,"Thu lãi vay") -> 84276037008 | Q22: =SUMIFS(Q$48:Q$3038,$I$48:$I$3038,"Thu lãi vay") -> 94567752275 | R22: =SUMIFS(R$48:R$3038,$I$48:$I$3038,"Thu lãi vay") -> 100878684667 | ... X22: =SUMIFS(X$48:X$3038,$I$48:$I$3038,"Thu lãi vay") -> 232297213106 | Y22: =X22-W22 -> 31297405614 | AA22: =W22-W23+V23 -> 198356701720
B23: lending | D23: all | G23: =B23&"_"&C23&"_"&D23&"_"&E23&"_"&F23 -> lending__all__ | I23: Thoái lãi | K23: =SUMIFS(K$48:K$3038,$I$48:$I$3038,"Thoái lãi") -> 7999287750 | L23: =SUMIFS(L$48:L$3038,$I$48:$I$3038,"Thoái lãi") -> 9716884445 | M23: =SUMIFS(M$48:M$3038,$I$48:$I$3038,"Thoái lãi") -> 10205045034 | N23: =SUMIFS(N$48:N$3038,$I$48:$I$3038,"Thoái lãi") -> 9483751909 | O23: =SUMIFS(O$48:O$3038,$I$48:$I$3038,"Thoái lãi") -> 9624384372 | P23: =SUMIFS(P$48:P$3038,$I$48:$I$3038,"Thoái lãi") -> 10094536585 | Q23: =SUMIFS(Q$48:Q$3038,$I$48:$I$3038,"Thoái lãi") -> 10559216669 | R23: =SUMIFS(R$48:R$3038,$I$48:$I$3038,"Thoái lãi") -> 11056826526 | ... X23: =SUMIFS(X$48:X$3038,$I$48:$I$3038,"Thoái lãi") -> 23728417658 | Y23: =X23-W23 -> 2317830275
B24: lending | D24: all | G24: =B24&"_"&C24&"_"&D24&"_"&E24&"_"&F24 -> lending__all__ | I24: COF | J24: =SUM(M24:X24) -> 2.4429386e+11 | K24: =SUMIFS(K$48:K$3038,$I$48:$I$3038,"COF") -> 10009948903 | L24: =SUMIFS(L$48:L$3038,$I$48:$I$3038,"COF") -> 11155285372 | M24: =SUMIFS(M$48:M$3038,$I$48:$I$3038,"COF") -> 12041757248 | N24: =SUMIFS(N$48:N$3038,$I$48:$I$3038,"COF") -> 11152533555 | O24: =SUMIFS(O$48:O$3038,$I$48:$I$3038,"COF") -> 1.2257271e+10 | P24: =SUMIFS(P$48:P$3038,$I$48:$I$3038,"COF") -> 12752634708 | Q24: =SUMIFS(Q$48:Q$3038,$I$48:$I$3038,"COF") -> 14362306096 | R24: =SUMIFS(R$48:R$3038,$I$48:$I$3038,"COF") -> 15239240769 | ... X24: =SUMIFS(X$48:X$3038,$I$48:$I$3038,"COF") -> 39564430397 | Y24: =X24-W24 -> 6458990935 | AA24: 1562245635
B25: lending | D25: all | G25: =B25&"_"&C25&"_"&D25&"_"&E25&"_"&F25 -> lending__all__ | I25: Net fee income | J25: =SUM(J26:J28) -> 803908966781 | K25: =SUM(K26:K28) -> 27583083979 | L25: =SUM(L26:L28) -> 3.2434754e+10 | M25: =SUM(M26:M28) -> 29756782715 | N25: =SUM(N26:N28) -> 24284197615 | O25: =SUM(O26:O28) -> 34259497297 | P25: =SUM(P26:P28) -> 39687689775 | Q25: =SUM(Q26:Q28) -> 39889216104 | ... X25: =SUM(X26:X28) -> 126910887822 | Y25: =X25-W25 -> 10509921230 | AA25: =AA24+W20 -> 166813507893
B26: lending | D26: all | G26: =B26&"_"&C26&"_"&D26&"_"&E26&"_"&F26 -> lending__all__ | I26: Insurance fee | J26: =SUM(M26:X26) -> 656687659991 | K26: =SUMIFS(K$48:K$3038,$I$48:$I$3038,"Insurance fee") -> 24710450873 | L26: =SUMIFS(L$48:L$3038,$I$48:$I$3038,"Insurance fee") -> 2.9076808e+10 | M26: =SUMIFS(M$48:M$3038,$I$48:$I$3038,"Insurance fee") -> 26590524165 | N26: =SUMIFS(N$48:N$3038,$I$48:$I$3038,"Insurance fee") -> 21215572578 | O26: =SUMIFS(O$48:O$3038,$I$48:$I$3038,"Insurance fee") -> 29713730593 | P26: =SUMIFS(P$48:P$3038,$I$48:$I$3038,"Insurance fee") -> 33878604810 | Q26: =SUMIFS(Q$48:Q$3038,$I$48:$I$3038,"Insurance fee") -> 34268836103 | R26: =SUMIFS(R$48:R$3038,$I$48:$I$3038,"Insurance fee") -> 38448492066 | ... X26: =SUMIFS(X$48:X$3038,$I$48:$I$3038,"Insurance fee") -> 100963671223 | Y26: =X26-W26 -> 7965801966
B27: lending | D27: all | G27: =B27&"_"&C27&"_"&D27&"_"&E27&"_"&F27 -> lending__all__ | I27: Early repayment fee | J27: =SUM(M27:X27) -> 143290856790 | K27: =SUMIFS(K$48:K$3038,$I$48:$I$3038,"Early repayment fee") -> 2422383106 | L27: =SUMIFS(L$48:L$3038,$I$48:$I$3038,"Early repayment fee") -> 2633346724 | M27: =SUMIFS(M$48:M$3038,$I$48:$I$3038,"Early repayment fee") -> 2585208550 | N27: =SUMIFS(N$48:N$3038,$I$48:$I$3038,"Early repayment fee") -> 2640825037 | O27: =SUMIFS(O$48:O$3038,$I$48:$I$3038,"Early repayment fee") -> 4033416704 | P27: =SUMIFS(P$48:P$3038,$I$48:$I$3038,"Early repayment fee") -> 5294534965 | Q27: =SUMIFS(Q$48:Q$3038,$I$48:$I$3038,"Early repayment fee") -> 5102530001 | R27: =SUMIFS(R$48:R$3038,$I$48:$I$3038,"Early repayment fee") -> 8503845964 | ... X27: =SUMIFS(X$48:X$3038,$I$48:$I$3038,"Early repayment fee") -> 25877266599 | Y27: =X27-W27 -> 2559269264
B28: lending | D28: all | G28: =B28&"_"&C28&"_"&D28&"_"&E28&"_"&F28 -> lending__all__ | I28: Limit fee | J28: =SUM(M28:X28) -> 3930450000 | K28: =SUMIFS(K$48:K$3038,$I$48:$I$3038,"Limit fee") -> 450250000 | L28: =SUMIFS(L$48:L$3038,$I$48:$I$3038,"Limit fee") -> 724600000 | M28: =SUMIFS(M$48:M$3038,$I$48:$I$3038,"Limit fee") -> 581050000 | N28: =SUMIFS(N$48:N$3038,$I$48:$I$3038,"Limit fee") -> 427800000 | O28: =SUMIFS(O$48:O$3038,$I$48:$I$3038,"Limit fee") -> 512350000 | P28: =SUMIFS(P$48:P$3038,$I$48:$I$3038,"Limit fee") -> 514550000 | Q28: =SUMIFS(Q$48:Q$3038,$I$48:$I$3038,"Limit fee") -> 517850000 | R28: =SUMIFS(R$48:R$3038,$I$48:$I$3038,"Limit fee") -> 527000000 | ... X28: =SUMIFS(X$48:X$3038,$I$48:$I$3038,"Limit fee") -> 69950000 | Y28: =X28-W28 -> -15150000 | AE28: T3 | AF28: 4 | AG28: 5 | AH28: 6
B29: lending | D29: all | G29: =B29&"_"&C29&"_"&D29&"_"&E29&"_"&F29 -> lending__all__ | I29: Other TOI | J29: =SUM(M29:X29) -> 18900766405 | K29: =SUMIFS(K$48:K$3038,$I$48:$I$3038,"Other TOI") -> 17777076 | L29: =SUMIFS(L$48:L$3038,$I$48:$I$3038,"Other TOI") -> 36855729 | M29: =SUMIFS(M$48:M$3038,$I$48:$I$3038,"Other TOI") -> 41943277 | N29: =SUMIFS(N$48:N$3038,$I$48:$I$3038,"Other TOI") -> 245300843 | O29: =SUMIFS(O$48:O$3038,$I$48:$I$3038,"Other TOI") -> 1068351047 | P29: =SUMIFS(P$48:P$3038,$I$48:$I$3038,"Other TOI") -> 844897911 | Q29: =SUMIFS(Q$48:Q$3038,$I$48:$I$3038,"Other TOI") -> 1175191211 | R29: =SUMIFS(R$48:R$3038,$I$48:$I$3038,"Other TOI") -> 1380588199 | ... X29: =SUMIFS(X$48:X$3038,$I$48:$I$3038,"Other TOI") -> 3121690240 | Y29: =X29-W29 -> 749352787
B30: lending | D30: all | G30: =B30&"_"&C30&"_"&D30&"_"&E30&"_"&F30 -> lending__all__ | I30: Provision expenses | J30: =SUM(M30:X30) -> 910112574484 | K30: =SUMIFS(K$48:K$3038,$I$48:$I$3038,"Provision expenses") -> 21518247295 | L30: =SUMIFS(L$48:L$3038,$I$48:$I$3038,"Provision expenses") -> 31138146416 | M30: =SUMIFS(M$48:M$3038,$I$48:$I$3038,"Provision expenses") -> 73619871731 | N30: =SUMIFS(N$48:N$3038,$I$48:$I$3038,"Provision expenses") -> 45681275021 | O30: =SUMIFS(O$48:O$3038,$I$48:$I$3038,"Provision expenses") -> 55722136445 | P30: =SUMIFS(P$48:P$3038,$I$48:$I$3038,"Provision expenses") -> 39812626019 | Q30: =SUMIFS(Q$48:Q$3038,$I$48:$I$3038,"Provision expenses") -> 62627976854 | R30: =SUMIFS(R$48:R$3038,$I$48:$I$3038,"Provision expenses") -> 62111404665 | ... X30: =SUMIFS(X$48:X$3038,$I$48:$I$3038,"Provision expenses") -> 139120336347 | Y30: =X30-W30 -> 22876470286 | AE30: =O33/(O19-PNL!$R30) -> 0.34888206 | AF30: =P33/(P19-PNL!$R30) -> 0.45399467 | AG30: =Q33/(Q19-PNL!$R30) -> 0.30569865 | AH30: =R33/(R19-PNL!$R30) -> 0.33858353
B31: lending | D31: all | G31: =B31&"_"&C31&"_"&D31&"_"&E31&"_"&F31 -> lending__all__ | I31: Variable expenses | J31: =SUM(J32:J39) -> 4.7548279e+11 | K31: =SUM(K32:K39) -> 2.0090911e+10 | L31: =SUM(L32:L39) -> 2.0567001e+10 | M31: =SUM(M32:M39) -> 1.9830158e+10 | N31: =SUM(N32:N39) -> 1.9592649e+10 | O31: =SUM(O32:O39) -> 2.0036374e+10 | P31: =SUM(P32:P39) -> 2.9249124e+10 | Q31: =SUM(Q32:Q39) -> 2.4248721e+10 | ... X31: =SUM(X32:X39) -> 6.7714843e+10 | Y31: =X31-W31 -> 4.2236889e+09
B32: lending | D32: all | G32: =B32&"_"&C32&"_"&D32&"_"&E32&"_"&F32 -> lending__all__ | I32: Marketing acquisition cost | J32: =SUM(M32:X32) -> 33561348302 | K32: =SUMIFS(K$48:K$3038,$I$48:$I$3038,"Marketing acquisition cost") -> 1057341055 | L32: =SUMIFS(L$48:L$3038,$I$48:$I$3038,"Marketing acquisition cost") -> 1358095141 | M32: =SUMIFS(M$48:M$3038,$I$48:$I$3038,"Marketing acquisition cost") -> 1181479170 | N32: =SUMIFS(N$48:N$3038,$I$48:$I$3038,"Marketing acquisition cost") -> 885757119 | O32: =SUMIFS(O$48:O$3038,$I$48:$I$3038,"Marketing acquisition cost") -> 1503077794 | P32: =SUMIFS(P$48:P$3038,$I$48:$I$3038,"Marketing acquisition cost") -> 2078254342 | Q32: =SUMIFS(Q$48:Q$3038,$I$48:$I$3038,"Marketing acquisition cost") -> 1414197238 | R32: =SUMIFS(R$48:R$3038,$I$48:$I$3038,"Marketing acquisition cost") -> 2978507515 | ... X32: =SUMIFS(X$48:X$3038,$I$48:$I$3038,"Marketing acquisition cost") -> 4458472607 | Y32: =X32-W32 -> 760056426 | AF32: =SUM(P33:R33)/(SUM(P19:R19)-SUM(P30:R30)) -> 0.32077081
B33: lending | D33: all | G33: =B33&"_"&C33&"_"&D33&"_"&E33&"_"&F33 -> lending__all__ | I33: Partner acquisition cost | J33: =SUM(M33:X33) -> 365824861719 | K33: =SUMIFS(K$48:K$3038,$I$48:$I$3038,"Partner acquisition cost") -> 15057180956 | L33: =SUMIFS(L$48:L$3038,$I$48:$I$3038,"Partner acquisition cost") -> 14005998385 | M33: =SUMIFS(M$48:M$3038,$I$48:$I$3038,"Partner acquisition cost") -> 13808398735 | N33: =SUMIFS(N$48:N$3038,$I$48:$I$3038,"Partner acquisition cost") -> 13830372027 | O33: =SUMIFS(O$48:O$3038,$I$48:$I$3038,"Partner acquisition cost") -> 14167313884 | P33: =SUMIFS(P$48:P$3038,$I$48:$I$3038,"Partner acquisition cost") -> 22461128822 | Q33: =SUMIFS(Q$48:Q$3038,$I$48:$I$3038,"Partner acquisition cost") -> 17942605735 | R33: =SUMIFS(R$48:R$3038,$I$48:$I$3038,"Partner acquisition cost") -> 24340890312 | ... X33: =SUMIFS(X$48:X$3038,$I$48:$I$3038,"Partner acquisition cost") -> 53410055880 | Y33: =X33-W33 -> 2731194887
B34: lending | D34: all | G34: =B34&"_"&C34&"_"&D34&"_"&E34&"_"&F34 -> lending__all__ | I34: Underwritting | J34: =SUM(M34:X34) -> 48625010811 | K34: =SUMIFS(K$48:K$3038,$I$48:$I$3038,"Underwritting") -> 2.3518551e+09 | L34: =SUMIFS(L$48:L$3038,$I$48:$I$3038,"Underwritting") -> 3.0051226e+09 | M34: =SUMIFS(M$48:M$3038,$I$48:$I$3038,"Underwritting") -> 2481935995 | N34: =SUMIFS(N$48:N$3038,$I$48:$I$3038,"Underwritting") -> 1864713205 | O34: =SUMIFS(O$48:O$3038,$I$48:$I$3038,"Underwritting") -> 2200530610 | P34: =SUMIFS(P$48:P$3038,$I$48:$I$3038,"Underwritting") -> 2327024294 | Q34: =SUMIFS(Q$48:Q$3038,$I$48:$I$3038,"Underwritting") -> 2381411929 | R34: =SUMIFS(R$48:R$3038,$I$48:$I$3038,"Underwritting") -> 2.7435755e+09 | ... X34: =SUMIFS(X$48:X$3038,$I$48:$I$3038,"Underwritting") -> 6.9355259e+09 | Y34: =X34-W34 -> 7.6363578e+08 | AE34: =SUM(M33:Q33)/(SUM(M19:Q19)-SUM(M30:Q30)) -> 0.34986548
B35: lending | D35: all | G35: =B35&"_"&C35&"_"&D35&"_"&E35&"_"&F35 -> lending__all__ | I35: E Contract | J35: =SUM(M35:X35) -> 1519628255 | K35: =SUMIFS(K$48:K$3038,$I$48:$I$3038,"E Contract") -> 53857518 | L35: =SUMIFS(L$48:L$3038,$I$48:$I$3038,"E Contract") -> 65273472 | M35: =SUMIFS(M$48:M$3038,$I$48:$I$3038,"E Contract") -> 56495896 | N35: =SUMIFS(N$48:N$3038,$I$48:$I$3038,"E Contract") -> 49048615 | O35: =SUMIFS(O$48:O$3038,$I$48:$I$3038,"E Contract") -> 67832022 | P35: =SUMIFS(P$48:P$3038,$I$48:$I$3038,"E Contract") -> 175886615 | Q35: =SUMIFS(Q$48:Q$3038,$I$48:$I$3038,"E Contract") -> 68122992 | R35: =SUMIFS(R$48:R$3038,$I$48:$I$3038,"E Contract") -> 72317391 | ... X35: =SUMIFS(X$48:X$3038,$I$48:$I$3038,"E Contract") -> 213824235 | Y35: =X35-W35 -> 24215944 | AE35: =SUM(O33:Q33)/(SUM(O19:Q19)-SUM(O30:Q30)) -> 0.30840262
B36: lending | D36: all | G36: =B36&"_"&C36&"_"&D36&"_"&E36&"_"&F36 -> lending__all__ | I36: NFC | J36: =SUM(M36:X36) -> 1.8790432e+09 | K36: =SUMIFS(K$48:K$3038,$I$48:$I$3038,"NFC") -> 0 | L36: =SUMIFS(L$48:L$3038,$I$48:$I$3038,"NFC") -> 0 | M36: =SUMIFS(M$48:M$3038,$I$48:$I$3038,"NFC") -> 169563600 | N36: =SUMIFS(N$48:N$3038,$I$48:$I$3038,"NFC") -> 106067025 | O36: =SUMIFS(O$48:O$3038,$I$48:$I$3038,"NFC") -> 1.5749527e+08 | P36: =SUMIFS(P$48:P$3038,$I$48:$I$3038,"NFC") -> 130956075 | Q36: =SUMIFS(Q$48:Q$3038,$I$48:$I$3038,"NFC") -> 1.311741e+08 | R36: =SUMIFS(R$48:R$3038,$I$48:$I$3038,"NFC") -> 142207875 | ... X36: =SUMIFS(X$48:X$3038,$I$48:$I$3038,"NFC") -> 2.2355044e+08 | Y36: =X36-W36 -> 48698663
B37: lending | D37: all | G37: =B37&"_"&C37&"_"&D37&"_"&E37&"_"&F37 -> lending__all__ | I37: Collection | J37: =SUM(M37:X37) -> 2.1745285e+10 | K37: =SUMIFS(K$48:K$3038,$I$48:$I$3038,"Collection") -> 1.519396e+09 | L37: =SUMIFS(L$48:L$3038,$I$48:$I$3038,"Collection") -> 2.0116083e+09 | M37: =SUMIFS(M$48:M$3038,$I$48:$I$3038,"Collection") -> 1.9697249e+09 | N37: =SUMIFS(N$48:N$3038,$I$48:$I$3038,"Collection") -> 2.7642571e+09 | O37: =SUMIFS(O$48:O$3038,$I$48:$I$3038,"Collection") -> 1.8174388e+09 | P37: =SUMIFS(P$48:P$3038,$I$48:$I$3038,"Collection") -> 1.8878663e+09 | Q37: =SUMIFS(Q$48:Q$3038,$I$48:$I$3038,"Collection") -> 2.1552092e+09 | R37: =SUMIFS(R$48:R$3038,$I$48:$I$3038,"Collection") -> 7.98981e+08 | ... X37: =SUMIFS(X$48:X$3038,$I$48:$I$3038,"Collection") -> 2.1716428e+09 | Y37: =X37-W37 -> -1.1192268e+08
B38: lending | D38: all | G38: =B38&"_"&C38&"_"&D38&"_"&E38&"_"&F38 -> lending__all__ | I38: Promotion | K38: =SUMIFS(K$48:K$3038,$I$48:$I$3038,"Promotion") -> 0 | L38: =SUMIFS(L$48:L$3038,$I$48:$I$3038,"Promotion") -> 0 | M38: =SUMIFS(M$48:M$3038,$I$48:$I$3038,"Promotion") -> 0 | N38: =SUMIFS(N$48:N$3038,$I$48:$I$3038,"Promotion") -> 0 | O38: =SUMIFS(O$48:O$3038,$I$48:$I$3038,"Promotion") -> 0 | P38: =SUMIFS(P$48:P$3038,$I$48:$I$3038,"Promotion") -> 0 | Q38: =SUMIFS(Q$48:Q$3038,$I$48:$I$3038,"Promotion") -> 0 | R38: =SUMIFS(R$48:R$3038,$I$48:$I$3038,"Promotion") -> 0 | ... X38: =SUMIFS(X$48:X$3038,$I$48:$I$3038,"Promotion") -> 0 | Y38: =X38-W38 -> 0
B39: lending | D39: all | G39: =B39&"_"&C39&"_"&D39&"_"&E39&"_"&F39 -> lending__all__ | I39: SMS | J39: =SUM(M39:X39) -> 2.3276164e+09 | K39: =SUMIFS(K$48:K$3038,$I$48:$I$3038,"SMS") -> 51280493 | L39: =SUMIFS(L$48:L$3038,$I$48:$I$3038,"SMS") -> 1.2090274e+08 | M39: =SUMIFS(M$48:M$3038,$I$48:$I$3038,"SMS") -> 1.6255954e+08 | N39: =SUMIFS(N$48:N$3038,$I$48:$I$3038,"SMS") -> 92434059 | O39: =SUMIFS(O$48:O$3038,$I$48:$I$3038,"SMS") -> 1.2268585e+08 | P39: =SUMIFS(P$48:P$3038,$I$48:$I$3038,"SMS") -> 1.8800768e+08 | Q39: =SUMIFS(Q$48:Q$3038,$I$48:$I$3038,"SMS") -> 1.5599935e+08 | R39: =SUMIFS(R$48:R$3038,$I$48:$I$3038,"SMS") -> 1.4185615e+08 | ... X39: =SUMIFS(X$48:X$3038,$I$48:$I$3038,"SMS") -> 3.0177097e+08 | Y39: =X39-W39 -> 7809869.7
B40: lending | D40: all | F40: overhead_cost | G40: =B40&"_"&C40&"_"&D40&"_"&E40&"_"&F40 -> lending__all__overhead_cost | I40: Overhead expenses | J40: =J41+J42+J43+J44 -> 2.5119714e+11 | K40: =SUM(K41:K44) -> 13411705149 | L40: =SUM(L41:L44) -> 3.4364414e+10 | M40: =SUM(M41:M44) -> 1.6575132e+10 | N40: =SUM(N41:N44) -> 1.6692886e+10 | O40: =SUM(O41:O44) -> 1.5924716e+10 | P40: =SUM(P41:P44) -> 1.8131155e+10 | Q40: =SUM(Q41:Q44) -> 1.6327544e+10 | R40: =SUM(R41:R44) -> 1.8135932e+10 | ... X40: =SUM(X41:X44) -> 5.555639e+09 | Y40: =X40-W40 -> -1.5682497e+10
B41: lending | D41: all | F41: direct_HR | G41: =B41&"_"&C41&"_"&D41&"_"&E41&"_"&F41 -> lending__all__direct_HR | I41: Direct HR cost | J41: =SUM(M41:X41) -> 5.2992316e+10 | K41: 3773682025 | L41: 3992626360 | M41: 3.9685506e+09 | N41: 4.0859711e+09 | O41: 4.2642751e+09 | P41: 4.171865e+09 | Q41: 4.1524613e+09 | R41: 4.1415548e+09 | S41: 4102129822 | T41: 4.9579724e+09 | U41: 4.7033021e+09 | V41: 4.6965227e+09 | W41: 4.870546e+09 | X41: 4.8771647e+09 | Y41: =X41-W41 -> 6618717.2
B42: lending | D42: all | F42: indirect_HR | G42: =B42&"_"&C42&"_"&D42&"_"&E42&"_"&F42 -> lending__all__indirect_HR | I42: Indirect HR cost | J42: =SUM(M42:X42) -> 8.4030951e+10 | K42: 3138024865 | L42: 3148726854 | M42: 4.1123033e+09 | N42: 3.8659797e+09 | O42: 3.7812967e+09 | P42: 3.7540052e+09 | Q42: 3.853413e+09 | R42: 3.9692345e+09 | S42: =4087561962.53592+11450450192.1994 -> 1.5538012e+10 | T42: 8.5528422e+09 | U42: =4504719087.22856+1791388162 -> 6.2961072e+09 | V42: =4483394213.06167+ 18673900000 -> 2.3157294e+10 | W42: =4610179776.01231+ 1861808833 -> 6.4719886e+09 | X42: 6.7847425e+08 | Y42: =X42-W42 -> -5.7935144e+09
B43: lending | D43: all | F43: system_cost | G43: =B43&"_"&C43&"_"&D43&"_"&E43&"_"&F43 -> lending__all__system_cost | I43: Indirect system cost | J43: =SUM(M43:X43) -> 5.603845e+10 | K43: 3267200000 | L43: 5.7172092e+09 | M43: 4.3643831e+09 | N43: 4.746293e+09 | O43: 4.1445754e+09 | P43: 5.1406923e+09 | Q43: 5.0611001e+09 | R43: 5.4753529e+09 | S43: 5.1091676e+09 | T43: 5.3105345e+09 | U43: 5.729459e+09 | V43: 5.9682653e+09 | W43: 4.9886269e+09 | Y43: =X43-W43 -> -4.9886269e+09
B44: lending | D44: all | F44: other_support_cost | G44: =B44&"_"&C44&"_"&D44&"_"&E44&"_"&F44 -> lending__all__other_support_cost | I44: Other indirect supporting cost | J44: =SUM(M44:X44) -> 5.8135426e+10 | K44: 3232798259 | L44: 2.1505851e+10 | M44: 4.1298955e+09 | N44: 3.9946427e+09 | O44: 3.7345692e+09 | P44: 5.0645925e+09 | Q44: 3.2605699e+09 | R44: 4.5497895e+09 | S44: 5.0711071e+09 | T44: 5.3659947e+09 | U44: 7.0166703e+09 | V44: 1.104062e+10 | W44: 4.9069741e+09 | Y44: =X44-W44 -> -4.9069741e+09
B45: lending | D45: all | F45: profit_after_overhead | G45: =B45&"_"&C45&"_"&D45&"_"&E45&"_"&F45 -> lending__all__profit_after_overhead | I45: Profit after allocation cost | J45: =J19-J30-J31-J40 -> 4.6742899e+11 | K45: =K19-K30-K31-K40 -> 2.4793601e+10 | L45: =L19-L30-L31-L40 -> 4.5196421e+09 | M45: =M19-M30-M31-M40 -> -1.6048798e+10 | N45: =N19-N30-N31-N40 -> 1.3860575e+09 | O45: =O19-O30-O31-O40 -> 1.1035923e+10 | P45: =P19-P30-P31-P40 -> 2.4392933e+10 | Q45: =Q19-Q30-Q31-Q40 -> 1.7600932e+10 | ... X45: =X19-X30-X31-X40 -> 1.0805671e+11 | Y45: =X45-W45 -> 2.5005302e+10
I46: Profit before allocation cost | J46: =J19-J30-J31 -> 7.1862613e+11 | K46: =K19-K30-K31 -> 3.8205307e+10 | L46: =L19-L30-L31 -> 3.8884056e+10 | M46: =M19-M30-M31 -> 5.2633493e+08 | N46: =N19-N30-N31 -> 1.8078944e+10 | O46: =O19-O30-O31 -> 2.6960639e+10 | P46: =P19-P30-P31 -> 4.2524088e+10 | Q46: =Q19-Q30-Q31 -> 3.3928476e+10 | ... S46: =S19-S30-S31 -> 6.4546717e+10 | T46: =T45+T40 -> 7.478261e+10 | U46: =U45+U40 -> 7.9216638e+10 | V46: =V45+V40 -> 1.1948777e+11 | W46: =W45+W40 -> 1.0428955e+11 | X46: =X45+X40 -> 1.1361235e+11 | Y46: =X46-W46 -> 9.322805e+09
Y47: =X47-W47 -> 0
B48: lending | G48: =B48&"_"&C48&"_"&D48&"_"&E48&"_"&F48 -> lending____ | I48: Cashloan with Viettel | Y48: =X48-W48 -> 0
B49: lending | C49: cashloan | D49: cashloan | E49: VDS | F49: new_account | G49: =B49&"_"&C49&"_"&D49&"_"&E49&"_"&F49 -> lending_cashloan_cashloan_VDS_new_account | I49: New account | K49: 17956 | L49: 15750 | M49: 15082 | N49: 11820 | O49: 18786 | P49: 19997 | Q49: 16661 | R49: 17951 | S49: 25713 | T49: 23272 | U49: 26446 | V49: 27305 | W49: 29191 | X49: 32735 | Y49: =X49-W49 -> 3544
B50: lending | C50: cashloan | D50: cashloan | E50: VDS | F50: Repeat account | G50: =B50&"_"&C50&"_"&D50&"_"&E50&"_"&F50 -> lending_cashloan_cashloan_VDS_Repeat account | I50: Repeat account | K50: 4682 | L50: 5020 | M50: 5125 | N50: 4599 | O50: 7455 | P50: 7849 | Q50: 6407 | R50: 6743 | S50: 9386 | T50: 8830 | U50: 12587 | V50: 14893 | W50: 15478 | X50: 16505 | Y50: =X50-W50 -> 1027
B51: lending | C51: cashloan | D51: cashloan | E51: VDS | F51: active_account | G51: =B51&"_"&C51&"_"&D51&"_"&E51&"_"&F51 -> lending_cashloan_cashloan_VDS_active_account | I51: Accumulated account | J51: =W51 -> 163592 | K51: 129097 | L51: 132635 | M51: =136327-4782 -> 131545 | N51: =136829-12268 -> 124561 | O51: =141237-14332 -> 126905 | P51: =146432-16309 -> 130123 | Q51: 131023 | R51: 130324 | S51: 138380 | T51: 143825 | U51: 150208 | V51: 155368 | W51: 163592 | X51: 173179 | Y51: =X51-W51 -> 9587
B52: lending | C52: cashloan | D52: cashloan | E52: VDS | F52: disburse/spend | G52: =B52&"_"&C52&"_"&D52&"_"&E52&"_"&F52 -> lending_cashloan_cashloan_VDS_disburse/spend | I52: Disbursement | J52: =SUM(M52:X52) -> 4004483580000 | K52: 189961290000 | L52: =182857630000+465120000+405530000+1832240000 -> 185560520000 | M52: =180511400000+74900000+173890000+237950000 -> 180998140000 | N52: 131780450000 | O52: 199492410000 | P52: 249365790000 | Q52: 237678410000 | R52: 261376050000 | S52: 380965670000 | T52: 346289200000 | U52: 465278440000 | V52: 489924960000 | W52: 513252480000 | X52: 548081580000 | Y52: =X52-W52 -> 34829100000
B53: lending | C53: cashloan | D53: cashloan | E53: VDS | G53: =B53&"_"&C53&"_"&D53&"_"&E53&"_"&F53 -> lending_cashloan_cashloan_VDS_ | I53: Disbursement w insurance | J53: =SUM(M53:X53) -> 3354301180000 | K53: 176386290000 | L53: 171559520000 | M53: 166922140000 | N53: 111638450000 | O53: 167308410000 | P53: 207148790000 | Q53: 196198410000 | R53: 219451650000 | S53: 322370670000 | T53: 290750200000 | U53: 388527440000 | V53: 407913960000 | W53: 422825480000 | X53: 453245580000 | Y53: =X53-W53 -> 30420100000 | Z53: =N53/N52 -> 0.84715487 | AA53: =O53/O52 -> 0.83867055 | AB53: =P53/P52 -> 0.83070252 | AC53: =Q53/Q52 -> 0.82547847
B54: lending | C54: cashloan | D54: cashloan | E54: VDS | G54: =B54&"_"&C54&"_"&D54&"_"&E54&"_"&F54 -> lending_cashloan_cashloan_VDS_ | I54: Disbursement w/o insurance | J54: =SUM(M54:X54) -> 650182400000 | K54: =K52-K53 -> 13575000000 | L54: =L52-L53 -> 14001000000 | M54: =M52-M53 -> 14076000000 | N54: =N52-N53 -> 20142000000 | O54: =O52-O53 -> 32184000000 | P54: =P52-P53 -> 42217000000 | Q54: =Q52-Q53 -> 41480000000 | R54: =R52-R53 -> 41924400000 | ... X54: =X52-X53 -> 94836000000 | Y54: =X54-W54 -> 4409000000
B55: lending | C55: cashloan | D55: cashloan | E55: VDS | F55: ENR | G55: =B55&"_"&C55&"_"&D55&"_"&E55&"_"&F55 -> lending_cashloan_cashloan_VDS_ENR | I55: Balance ENR | J55: =W55 -> 2072466106173 | K55: 1096760883557 | L55: 1105565326487 | M55: 1147479030231 | N55: 1059836524693 | O55: 1075941072798 | P55: 1136717782140 | Q55: 1178814582203 | R55: 1219457237377 | S55: 1378305772338 | T55: 1490245196812 | U55: 1689128717794 | V55: 1873560534525 | W55: 2072466106173 | X55: 2269684868394 | Y55: =X55-W55 -> 197218762221 | AI55: lending_cashloan_cashloan_CAKE_CII
B56: lending | C56: cashloan | D56: cashloan | E56: VDS | G56: =B56&"_"&C56&"_"&D56&"_"&E56&"_"&F56 -> lending_cashloan_cashloan_VDS_ | I56: Indue balance | J56: =V55 -> 1873560534525 | K56: =K55-K57 -> 1003932482028 | L56: =L55-L57 -> 1022463924093 | M56: =M55-M57 -> 1061249950213 | N56: =N55-N57 -> 1003227370358 | O56: =O55-O57 -> 1013650376772 | P56: =P55-P57 -> 1070490754302 | Q56: =Q55-Q57 -> 1112040908577 | R56: =R55-R57 -> 1160661668614 | ... X56: =X55-X57 -> 2214371972305 | Y56: =X56-W56 -> 197794560591 | AI56: lending_cashloan_cashloan_VDS_CII
B57: lending | C57: cashloan | D57: cashloan | E57: VDS | G57: =B57&"_"&C57&"_"&D57&"_"&E57&"_"&F57 -> lending_cashloan_cashloan_VDS_ | I57: Overdue balance (dpd >0) | J57: =X57 -> 55312896089 | K57: 92828401529 | L57: 83101402394 | M57: 86229080018 | N57: 56609154335 | O57: 62290696026 | P57: 66227027838 | Q57: 66773673626 | R57: 58795568763 | S57: 60003198592 | T57: 58296956930 | U57: 57653830020 | V57: 56159961677 | W57: 55888694459 | X57: 55312896089 | Y57: =X57-W57 -> -575798370
B58: lending | C58: cashloan | D58: cashloan | E58: VDS | G58: =B58&"_"&C58&"_"&D58&"_"&E58&"_"&F58 -> lending_cashloan_cashloan_VDS_ | I58: Overdue balance (90d+)- CAKE | K58: 128266006630 | L58: 115945446021 | M58: 132900321522 | N58: 96174898054 | O58: 104563918691 | P58: 108253009276 | Q58: 113013683395 | R58: 96321001040 | S58: 97930342031 | T58: 94382038235 | U58: 90846402382 | V58: 87120064487 | W58: 87195482343 | X58: 87477919039 | Y58: =X58-W58 -> 282436696
B59: lending | C59: cashloan | D59: cashloan | E59: VDS | F59: overdue_balance_10d | G59: =B59&"_"&C59&"_"&D59&"_"&E59&"_"&F59 -> lending_cashloan_cashloan_VDS_overdue_balance_10d | I59: Overdue balance (10d+) | K59: 242335512813 | L59: 253215307338 | M59: 257387831112 | N59: 216211035603 | O59: 228003295831 | P59: 219589836982 | Q59: 222121862595 | R59: 222657233390 | S59: 231139715652 | T59: 240339626322 | U59: 270521140060 | V59: 276093953608 | W59: 299632744083 | Y59: =X59-W59 -> -299632744083
B60: lending | C60: cashloan | D60: cashloan | E60: VDS | F60: overdue_balance_90d | G60: =B60&"_"&C60&"_"&D60&"_"&E60&"_"&F60 -> lending_cashloan_cashloan_VDS_overdue_balance_90d | I60: Overdue balance (90+) | K60: 137654955413 | L60: 132330092600 | M60: 144274036407 | N60: 108007211794 | O60: 123200234353 | P60: 121834681774 | Q60: 125809078154 | R60: 117132587105 | S60: 112198077246 | T60: 109518480538 | U60: 114038507340 | V60: 102390446994 | W60: 103829795891 | Y60: =X60-W60 -> -103829795891
B61: lending | C61: cashloan | D61: cashloan | E61: VDS | G61: =B61&"_"&C61&"_"&D61&"_"&E61&"_"&F61 -> lending_cashloan_cashloan_VDS_ | I61: Overdue balance (11-90d) | K61: =K59-K60 -> 104680557400 | L61: =L59-L60 -> 120885214738 | M61: =M59-M60 -> 113113794705 | N61: =N59-N60 -> 108203823809 | O61: =O59-O60 -> 104803061478 | P61: =P59-P60 -> 97755155208 | Q61: =Q59-Q60 -> 96312784441 | R61: =R59-R60 -> 105524646285 | ... X61: =X59-X60 -> 0 | Y61: =X61-W61 -> -195802948192
B62: lending | C62: cashloan | D62: cashloan | E62: VDS | G62: =B62&"_"&C62&"_"&D62&"_"&E62&"_"&F62 -> lending_cashloan_cashloan_VDS_ | I62: %NPL CAKE | K62: =K58/K55 -> 0.11694984 | L62: =L58/L55 -> 0.10487435 | M62: =M58/M55 -> 0.11581939 | N62: =N58/N55 -> 0.090745031 | O62: =O58/O55 -> 0.097183685 | P62: =P58/P55 -> 0.095232969 | Q62: =Q58/Q55 -> 0.095870619 | R62: =R58/R55 -> 0.07898678 | ... X62: =X58/X55 -> 0.038541879 | Y62: =X62-W62 -> -0.0035314184
B63: lending | C63: cashloan | D63: cashloan | E63: VDS | F63: npl | G63: =B63&"_"&C63&"_"&D63&"_"&E63&"_"&F63 -> lending_cashloan_cashloan_VDS_npl | I63: %NPL CIC | K63: =K60/K55 -> 0.12551045 | L63: =L60/L55 -> 0.1196945 | M63: =M60/M55 -> 0.12573131 | N63: =N60/N55 -> 0.10190931 | O63: =O60/O55 -> 0.11450463 | P63: =P60/P55 -> 0.10718112 | Q63: =Q60/Q55 -> 0.10672508 | R63: =R60/R55 -> 0.09605305 | ... X63: =X60/X55 -> 0 | Y63: =X63-W63 -> -0.050099635
B64: lending | C64: cashloan | D64: cashloan | E64: VDS | F64: TOI | G64: =B64&"_"&C64&"_"&D64&"_"&E64&"_"&F64 -> lending_cashloan_cashloan_VDS_TOI | I64: TOI | J64: =J65+J70+J74 -> 7.7818999e+11 | K64: =K65+K70+K74 -> 39678475231 | L64: =L65+L70+L74 -> 40794534742 | M64: =M65+M70+M74 -> 42417349530 | N64: =N65+N70+N74 -> 36081236115 | O64: =O65+O70+O74 -> 4.3326725e+10 | P64: =P65+P70+P74 -> 46412665489 | Q64: =Q65+Q70+Q74 -> 48948107995 | ... X64: =X65+X70+X74 -> 108562437639 | Y64: =X64-W64 -> 12719745647
B65: lending | C65: cashloan | D65: cashloan | E65: VDS | F65: NII | G65: =B65&"_"&C65&"_"&D65&"_"&E65&"_"&F65 -> lending_cashloan_cashloan_VDS_NII | I65: Net interest income | J65: =J66-J69 -> 5.1056124e+11 | K65: =K66-K69 -> 28096935555 | L65: =L66-L69 -> 29477909200 | M65: =M66-M69 -> 31408352679 | N65: =N66-N69 -> 28082686231 | O65: =O66-O69 -> 3.1161138e+10 | P65: =P66-P69 -> 31800150847 | Q65: =Q66-Q69 -> 34650462975 | ... X65: =X66-X69 -> 69103432092 | Y65: =X65-W65 -> 9033539037
B66: lending | C66: cashloan | D66: cashloan | E66: VDS | F66: CII | G66: =B66&"_"&C66&"_"&D66&"_"&E66&"_"&F66 -> lending_cashloan_cashloan_VDS_CII | I66: Interest Income | J66: =SUM(M66:X66) -> 609986674726 | K66: =K67+4129655067-K68 -> 33954168405 | L66: =L67+K68-L68 -> 35757060039 | M66: =M67+L68-M68 -> 37783907263 | N66: =N67+M68-N68 -> 33812818355 | O66: =O67+N68-O68 -> 37182247404 | P66: =P67+O68-P68 -> 37849380586 | Q66: =Q67+P68-Q68 -> 41245909958 | R66: =R67+Q68-R68 -> 42103351990 | S66: =S67+R68-S68 -> 47626846642 | ... X66: =X67+W68-X68 -> 83038946867 | Y66: =X66-W66 -> 10988344966
B67: lending | C67: cashloan | D67: cashloan | E67: VDS | G67: =B67&"_"&C67&"_"&D67&"_"&E67&"_"&F67 -> lending_cashloan_cashloan_VDS_ | I67: Thu lãi vay | J67: =SUM(M67:X67) -> 613885530839 | K67: 34594747983 | L67: 36499809681 | M67: 38002137672 | N67: 33265599220 | O67: 37097394365 | P67: 38016634897 | Q67: 41300148104 | R67: 42069348583 | S67: 48463084122 | T67: 53272770215 | U67: 57987623749 | V67: 67607734919 | W67: 72936674388 | X67: 83866380605 | Y67: =X67-W67 -> 10929706217
B68: lending | C68: cashloan | D68: cashloan | E68: VDS | G68: =B68&"_"&C68&"_"&D68&"_"&E68&"_"&F68 -> lending_cashloan_cashloan_VDS_ | I68: Thoái lãi | K68: 4770234645 | L68: =5174464805+338519482 -> 5512984287 | M68: 5731214696 | N68: 5183995561 | O68: 5099142522 | P68: 5266396833 | Q68: 5320634979 | R68: 5286631572 | S68: 6122869052 | T68: 6343120731 | U68: 6873616956 | V68: 7698334175 | W68: 8584406662 | X68: 9411840400 | Y68: =X68-W68 -> 827433738
B69: lending | C69: cashloan | D69: cashloan | E69: VDS | F69: COF | G69: =B69&"_"&C69&"_"&D69&"_"&E69&"_"&F69 -> lending_cashloan_cashloan_VDS_COF | I69: COF | J69: =SUM(M69:X69) -> 9.9425439e+10 | K69: 5857232850 | L69: 6279150839 | M69: 6375554584 | N69: 5730132124 | O69: 6.0211096e+09 | P69: 6049229739 | Q69: 6595446983 | R69: 6655068859 | S69: 7483310232 | T69: 8431017077 | U69: 9199477519 | V69: 10968868255 | W69: 11980708846 | X69: 13935514775 | Y69: =X69-W69 -> 1954805929
B70: lending | C70: cashloan | D70: cashloan | E70: VDS | F70: NFI | G70: =B70&"_"&C70&"_"&D70&"_"&E70&"_"&F70 -> lending_cashloan_cashloan_VDS_NFI | I70: Net fee income | J70: =SUM(J71:J73) -> 258847063309 | K70: =SUM(K71:K73) -> 11581539676 | L70: =SUM(L71:L73) -> 11310385070 | M70: =SUM(M71:M73) -> 10991696913 | N70: =SUM(N71:N73) -> 7892325195 | O70: =SUM(O71:O73) -> 11621648139 | P70: =SUM(P71:P73) -> 14200870683 | Q70: =SUM(Q71:Q73) -> 13650928899 | ... X70: =SUM(X71:X73) -> 38039477442 | Y70: =X70-W70 -> 3123495600
B71: lending | C71: cashloan | D71: cashloan | E71: VDS | F71: insurance_fee | G71: =B71&"_"&C71&"_"&D71&"_"&E71&"_"&F71 -> lending_cashloan_cashloan_VDS_insurance_fee | I71: Insurance fee | J71: =SUM(M71:X71) -> 185509077376 | K71: 9880274232 | L71: 9609902815 | M71: 9350140074 | N71: 6253425370 | O71: 9371776980 | P71: 11603056744 | Q71: 10990049707 | R71: 12292579444 | S71: 17614586890 | T71: 15879842307 | U71: 21235065395 | V71: 22360422125 | W71: 23434158916 | X71: 25123973424 | Y71: =X71-W71 -> 1689814508
B72: lending | C72: cashloan | D72: cashloan | E72: VDS | F72: early_terminate_fee | G72: =B72&"_"&C72&"_"&D72&"_"&E72&"_"&F72 -> lending_cashloan_cashloan_VDS_early_terminate_fee | I72: Early repayment fee | J72: =SUM(M72:X72) -> 73337985933 | K72: 1701265444 | L72: 1700482255 | M72: 1641556839 | N72: 1638899825 | O72: 2249871159 | P72: 2597813939 | Q72: 2660879192 | R72: 4670199524 | S72: 5523134361 | T72: 7479660750 | U72: 9308611570 | V72: 11170031830 | W72: 11481822926 | X72: 12915504018 | Y72: =X72-W72 -> 1433681092
B73: lending | C73: cashloan | D73: cashloan | E73: VDS | F73: loan_grant_fee | G73: =B73&"_"&C73&"_"&D73&"_"&E73&"_"&F73 -> lending_cashloan_cashloan_VDS_loan_grant_fee | I73: Limit fee | J73: =SUM(M73:X73) -> 0 | Y73: =X73-W73 -> 0
B74: lending | C74: cashloan | D74: cashloan | E74: VDS | F74: other_TOI | G74: =B74&"_"&C74&"_"&D74&"_"&E74&"_"&F74 -> lending_cashloan_cashloan_VDS_other_TOI | I74: Other TOI | J74: =SUM(M74:X74) -> 8781688694 | L74: 6240472 | M74: 17299938 | N74: 106224689 | O74: 543939386 | P74: 411643959 | Q74: 646716121 | R74: 809494479 | S74: 1044337501 | T74: 1059351007 | U74: 881953182 | V74: 984383232 | W74: 856817095 | X74: 1419528105 | Y74: =X74-W74 -> 562711010
B75: lending | C75: cashloan | D75: cashloan | E75: VDS | F75: provision | G75: =B75&"_"&C75&"_"&D75&"_"&E75&"_"&F75 -> lending_cashloan_cashloan_VDS_provision | I75: Provision expenses | J75: =SUM(M75:X75) -> 384508940425 | K75: 11931346505 | L75: 17026123186 | M75: 41826219082 | N75: 19959148404 | O75: =21225687782+3947986996 -> 25173674778 | P75: 19593311130 | Q75: 33241125666 | R75: =24968728875+3743543011 -> 28712271886 | S75: 22993577846 | T75: 29817195991 | U75: =34107002222+3560569609 -> 37667571831 | V75: 35542834791 | W75: 41845997466 | X75: 48136011554 | Y75: =X75-W75 -> 6290014088
B76: lending | C76: cashloan | D76: cashloan | E76: VDS | F76: variable_cost | G76: =B76&"_"&C76&"_"&D76&"_"&E76&"_"&F76 -> lending_cashloan_cashloan_VDS_variable_cost | I76: Variable expenses | J76: =SUM(J77:J84) -> 2.5814778e+11 | K76: =SUM(K77:K84) -> 1.2035103e+10 | L76: =SUM(L77:L84) -> 1.0389226e+10 | M76: =SUM(M77:M84) -> 8.9735752e+09 | N76: =SUM(N77:N84) -> 9.4990983e+09 | O76: =SUM(O77:O84) -> 9.1017108e+09 | P76: =SUM(P77:P84) -> 1.8195644e+10 | Q76: =SUM(Q77:Q84) -> 1.2636588e+10 | ... X76: =SUM(X77:X84) -> 3.8137243e+10 | Y76: =X76-W76 -> 2.7984547e+09
B77: lending | C77: cashloan | D77: cashloan | E77: VDS | F77: marketing_acquisition_cost | G77: =B77&"_"&C77&"_"&D77&"_"&E77&"_"&F77 -> lending_cashloan_cashloan_VDS_marketing_acquisition_cost | I77: Marketing acquisition cost | J77: =SUM(M77:X77) -> 0 | Y77: =X77-W77 -> 0
B78: lending | C78: cashloan | D78: cashloan | E78: VDS | F78: partner_acquisition_cost | G78: =B78&"_"&C78&"_"&D78&"_"&E78&"_"&F78 -> lending_cashloan_cashloan_VDS_partner_acquisition_cost | I78: Partner acquisition cost | J78: =SUM(M78:X78) -> 239769284291 | K78: =10711164687+14400000 -> 10725564687 | L78: =8776603791+8880000 -> 8785483791 | M78: =7469010968+1380000 -> 7470390968 | N78: 7820321397 | O78: =7710727408+2520000 -> 7713247408 | P78: =16791179734+60000 -> 16791239734 | Q78: =7260122763+4000000000 -> 11260122763 | R78: =13137790945 +3000000000 -> 16137790945 | S78: 27658468626 | T78: 18036041466 | U78: 27652613134 | V78: 29699438610 | W78: 33440423242 | X78: 36089185998 | Y78: =X78-W78 -> 2648762756
B79: lending | C79: cashloan | D79: cashloan | E79: VDS | F79: underwritting | G79: =B79&"_"&C79&"_"&D79&"_"&E79&"_"&F79 -> lending_cashloan_cashloan_VDS_underwritting | I79: Underwritting | J79: =SUM(M79:X79) -> 8.6198621e+09 | K79: 4.4043894e+08 | L79: 4.4329095e+08 | M79: 3.9917418e+08 | N79: 3.1302639e+08 | O79: 5.051819e+08 | P79: 4.6889049e+08 | Q79: 4.0615919e+08 | R79: 4.2155351e+08 | S79: 5.5936268e+08 | T79: 9.5530429e+08 | U79: 1.1051968e+09 | V79: 1.0838683e+09 | W79: 1.0973286e+09 | X79: 1.3048158e+09 | Y79: =X79-W79 -> 2.0748718e+08
B80: lending | C80: cashloan | D80: cashloan | E80: VDS | F80: e_contract | G80: =B80&"_"&C80&"_"&D80&"_"&E80&"_"&F80 -> lending_cashloan_cashloan_VDS_e_contract | I80: E Contract | J80: =SUM(M80:X80) -> 240282623 | K80: 14335502 | L80: 12561591 | M80: 11966337 | N80: 9677426 | O80: 15041279 | P80: 41754120 | Q80: 13256531 | R80: 14710483 | S80: 20382708 | T80: 19382271 | U80: 21102642 | V80: 21960093 | W80: 23428833 | X80: 27619900 | Y80: =X80-W80 -> 4191067
B81: lending | C81: cashloan | D81: cashloan | E81: VDS | F81: nfc | G81: =B81&"_"&C81&"_"&D81&"_"&E81&"_"&F81 -> lending_cashloan_cashloan_VDS_nfc | I81: NFC | J81: =SUM(M81:X81) -> 5.1008941e+08 | M81: 51653337 | N81: 33091702 | O81: 49670832 | P81: 42424743 | Q81: 35311091 | R81: 35545616 | S81: 43025475 | T81: 41031841 | U81: 39560833 | V81: 42140309 | W81: 40721047 | X81: 55912589 | Y81: =X81-W81 -> 15191543
B82: lending | C82: cashloan | D82: cashloan | E82: VDS | F82: collection | G82: =B82&"_"&C82&"_"&D82&"_"&E82&"_"&F82 -> lending_cashloan_cashloan_VDS_collection | I82: Collection | J82: =SUM(M82:X82) -> 8.2461864e+09 | K82: 8.312179e+08 | L82: 1.0905324e+09 | M82: 9.6826744e+08 | N82: 1.2832666e+09 | O82: 7.675066e+08 | P82: 7.7487494e+08 | Q82: 8.6048709e+08 | R82: 3.3669705e+08 | S82: 482732506 | T82: 4.877469e+08 | U82: 5.8367932e+08 | V82: 4.4825287e+08 | W82: 6.6098012e+08 | X82: 5.9169499e+08 | Y82: =X82-W82 -> -69285130
F83: promotion | I83: Promotion | Y83: =X83-W83 -> 0
B84: lending | C84: cashloan | D84: cashloan | E84: VDS | F84: sms | G84: =B84&"_"&C84&"_"&D84&"_"&E84&"_"&F84 -> lending_cashloan_cashloan_VDS_sms | I84: SMS | J84: =SUM(M84:X84) -> 7.6207568e+08 | K84: 23546297 | L84: 57357222 | M84: 72122983 | N84: 39714767 | O84: 51062828 | P84: 76460183 | Q84: 61251508 | R84: 52513201 | S84: 72596706 | T84: 34002631 | U84: 75962331 | V84: 82468427 | W84: 75906435 | X84: 68013675 | Y84: =X84-W84 -> -7892760.2
B85: lending | C85: cashloan | D85: cashloan | E85: VDS | F85: profit_before_overhead | G85: =B85&"_"&C85&"_"&D85&"_"&E85&"_"&F85 -> lending_cashloan_cashloan_VDS_profit_before_overhead | I85: Profit before allocation cost | J85: =J64-J75-J76 -> 1.3553327e+11 | K85: =K64-K75-K76 -> 1.5712025e+10 | L85: =L64-L75-L76 -> 1.3379186e+10 | M85: =M64-M75-M76 -> -8.3824448e+09 | N85: =N64-N75-N76 -> 6.6229894e+09 | O85: =O64-O75-O76 -> 9.0513397e+09 | P85: =P64-P75-P76 -> 8.6237101e+09 | Q85: =Q64-Q75-Q76 -> 3.0703942e+09 | ... X85: =X64-X75-X76 -> 2.2289183e+10 | Y85: =X85-W85 -> 3.6312769e+09
Y86: =X86-W86 -> 0
B87: lending | C87: cashloan | D87: payroll | E87: VDS | G87: =B87&"_"&C87&"_"&D87&"_"&E87&"_"&F87 -> lending_cashloan_payroll_VDS_ | I87: Cashloan Payroll with VDS | Y87: =X87-W87 -> 0
B88: lending | C88: cashloan | D88: payroll | E88: VDS | F88: new_account | G88: =B88&"_"&C88&"_"&D88&"_"&E88&"_"&F88 -> lending_cashloan_payroll_VDS_new_account | I88: New account | K88: 90 | L88: 56 | M88: 60 | N88: 70 | O88: 108 | P88: 75 | Q88: 71 | R88: 24 | S88: 52 | T88: 63 | U88: 59 | V88: 63 | W88: 54 | X88: 37 | Y88: =X88-W88 -> -17
B89: lending | C89: cashloan | D89: payroll | E89: VDS | F89: Repeat account | G89: =B89&"_"&C89&"_"&D89&"_"&E89&"_"&F89 -> lending_cashloan_payroll_VDS_Repeat account | I89: Repeat account | K89: 9 | L89: 7 | M89: 14 | N89: 17 | O89: 21 | P89: 18 | Q89: 21 | R89: 146 | S89: 18 | T89: 22 | U89: 33 | V89: 46 | W89: 36 | X89: 31 | Y89: =X89-W89 -> -5
B90: lending | C90: cashloan | D90: payroll | E90: VDS | F90: active_account | G90: =B90&"_"&C90&"_"&D90&"_"&E90&"_"&F90 -> lending_cashloan_payroll_VDS_active_account | I90: Accumulated account | K90: 892 | L90: 902 | M90: =879-2 -> 877 | N90: =874-21 -> 853 | O90: =879-30 -> 849 | P90: =862-32 -> 830 | Q90: =851-43 -> 808 | R90: 777 | S90: 769 | T90: 762 | U90: 743 | V90: 731 | W90: 707 | X90: 685 | Y90: =X90-W90 -> -22
B91: lending | C91: cashloan | D91: payroll | E91: VDS | F91: disburse/spend | G91: =B91&"_"&C91&"_"&D91&"_"&E91&"_"&F91 -> lending_cashloan_payroll_VDS_disburse/spend | I91: Disbursement | J91: =SUM(M91:X91) -> 11871000000 | K91: 1487350000 | L91: 846550000 | M91: 1011950000 | N91: 1109450000 | O91: 1798700000 | P91: 1227200000 | Q91: 1149700000 | R91: 374000000 | S91: 809800000 | T91: 1040200000 | U91: 953500000 | V91: 1056500000 | W91: 746250000 | X91: 593750000 | Y91: =X91-W91 -> -152500000
B92: lending | C92: cashloan | D92: payroll | E92: VDS | G92: =B92&"_"&C92&"_"&D92&"_"&E92&"_"&F92 -> lending_cashloan_payroll_VDS_ | I92: Disbursement w insurance | K92: 1267350000 | L92: 830550000 | M92: 922950000 | N92: 933450000 | O92: 1526700000 | P92: 1012200000 | Q92: 959700000 | R92: 294000000 | S92: 709800000 | T92: 865200000 | U92: 703500000 | V92: 871500000 | W92: 572250000 | X92: 498750000 | Y92: =X92-W92 -> -73500000
B93: lending | C93: cashloan | D93: payroll | E93: VDS | G93: =B93&"_"&C93&"_"&D93&"_"&E93&"_"&F93 -> lending_cashloan_payroll_VDS_ | I93: Disbursement w/o insurance | K93: =K91-K92 -> 220000000 | L93: =L91-L92 -> 16000000 | M93: =M91-M92 -> 89000000 | N93: =N91-N92 -> 176000000 | O93: =O91-O92 -> 272000000 | P93: =P91-P92 -> 215000000 | Q93: =Q91-Q92 -> 190000000 | R93: =R91-R92 -> 80000000 | ... X93: =X91-X92 -> 95000000 | Y93: =X93-W93 -> -79000000
B94: lending | C94: cashloan | D94: payroll | E94: VDS | F94: ENR | G94: =B94&"_"&C94&"_"&D94&"_"&E94&"_"&F94 -> lending_cashloan_payroll_VDS_ENR | I94: Balance ENR | J94: =W94 -> 6974057806 | K94: 10497997193 | L94: 10143873242 | M94: 9787251521 | N94: 9283199996 | O94: 9564466715 | P94: 9405286904 | Q94: 9191757861 | R94: 8337120782 | S94: 7983124244 | T94: 7828795755 | U94: 7633800771 | V94: 7459775694 | W94: 6974057806 | X94: 6432786980 | Y94: =X94-W94 -> -541270826
B95: lending | C95: cashloan | D95: payroll | E95: VDS | G95: =B95&"_"&C95&"_"&D95&"_"&E95&"_"&F95 -> lending_cashloan_payroll_VDS_ | I95: Indue balance | K95: =K94-K96 -> 10225974298 | L95: =L94-L96 -> 9830283011 | M95: =M94-M96 -> 9467640305 | N95: =N94-N96 -> 9059508037 | O95: =O94-O96 -> 9332494963 | P95: =P94-P96 -> 9152619023 | Q95: =Q94-Q96 -> 8970521915 | R95: =R94-R96 -> 8139455189 | ... X95: =X94-X96 -> 6366020104 | Y95: =X95-W95 -> -538657251
B96: lending | C96: cashloan | D96: payroll | E96: VDS | G96: =B96&"_"&C96&"_"&D96&"_"&E96&"_"&F96 -> lending_cashloan_payroll_VDS_ | I96: Overdue balance (dpd >0) | K96: 272022895 | L96: 313590231 | M96: 319611216 | N96: 223691959 | O96: 231971752 | P96: 252667881 | Q96: 221235946 | R96: 197665593 | S96: 168230763 | T96: 135516021 | U96: 163031884 | V96: 128507791 | W96: 69380451 | X96: 66766876 | Y96: =X96-W96 -> -2613575
B97: lending | C97: cashloan | D97: payroll | E97: VDS | G97: =B97&"_"&C97&"_"&D97&"_"&E97&"_"&F97 -> lending_cashloan_payroll_VDS_ | I97: Overdue balance (90d+)- CAKE | K97: 403780031 | L97: 438309084 | M97: 544105569 | N97: 373436279 | O97: 347952498 | P97: 375187979 | Q97: 310092447 | R97: 255093337 | S97: 227620612 | T97: 272098888 | U97: 267107696 | V97: 191374126 | W97: 76778488 | X97: 99551208 | Y97: =X97-W97 -> 22772720
B98: lending | C98: cashloan | D98: payroll | E98: VDS | F98: overdue_balance_10d | G98: =B98&"_"&C98&"_"&D98&"_"&E98&"_"&F98 -> lending_cashloan_payroll_VDS_overdue_balance_10d | I98: Overdue balance (10d+) | K98: 1175510891 | L98: 1306880160 | M98: 1235086144 | N98: 1065957703 | O98: 1014278041 | P98: 976837749 | Q98: 1014713162 | R98: 1026921137 | S98: 1039008206 | T98: 967552758 | U98: 929048526 | V98: 855300264 | W98: 647959961 | Y98: =X98-W98 -> -647959961
B99: lending | C99: cashloan | D99: payroll | E99: VDS | F99: overdue_balance_90d | G99: =B99&"_"&C99&"_"&D99&"_"&E99&"_"&F99 -> lending_cashloan_payroll_VDS_overdue_balance_90d | I99: Overdue balance (90+) | K99: 553108322 | L99: 631753544 | M99: 663967253 | N99: 506368733 | O99: 444849247 | P99: 433580872 | Q99: 434134510 | R99: 428886401 | S99: 385074813 | T99: 460032671 | U99: 474785513 | V99: 385117696 | W99: 262439208 | Y99: =X99-W99 -> -262439208
B100: lending | C100: cashloan | D100: payroll | E100: VDS | G100: =B100&"_"&C100&"_"&D100&"_"&E100&"_"&F100 -> lending_cashloan_payroll_VDS_ | I100: Overdue balance (11-90d) | K100: =K98-K99 -> 622402569 | L100: =L98-L99 -> 675126616 | M100: =M98-M99 -> 571118891 | N100: =N98-N99 -> 559588970 | O100: =O98-O99 -> 569428794 | P100: =P98-P99 -> 543256877 | Q100: =Q98-Q99 -> 580578652 | R100: =R98-R99 -> 598034736 | ... X100: =X98-X99 -> 0 | Y100: =X100-W100 -> -385520753
...

Sheet Early repayment
M6: VNPOST
M29: CAKE
M51: VDS
L73: MWG
L95: Zalopay
L117: VNPAY
D144: MOB1-3 | R144: MOB4-end
B145: RATE
D146: 1 | E146: 2 | F146: =E146+1 -> 3 | G146: =F146+1 -> 4 | H146: =G146+1 -> 5 | I146: =H146+1 -> 6 | J146: =I146+1 -> 7 | K146: =J146+1 -> 8 | L146: =K146+1 -> 9 | M146: =L146+1 -> 10 | ... O146: =N146+1 -> 12 | T146: 1 | U146: 2 | V146: =U146+1 -> 3 | W146: =V146+1 -> 4 | X146: =W146+1 -> 5 | Y146: =X146+1 -> 6 | Z146: =Y146+1 -> 7 | AA146: =Z146+1 -> 8 | AB146: =AA146+1 -> 9 | AC146: =AB146+1 -> 10 | ... AE146: =AD146+1 -> 12
B147: CL | C147: VDS | D147: 0.03 | E147: 0.03 | F147: 0.03 | G147: 0.03 | H147: 0.03 | I147: 0.03 | J147: 0.03 | K147: 0.08 | L147: 0.08 | M147: 0.08 | N147: 0.08 | O147: 0.08 | R147: CL | S147: VDS | T147: 0.03 | U147: 0.03 | V147: 0.03 | W147: 0.03 | X147: 0.03 | Y147: 0.03 | Z147: 0.03 | AA147: 0.05 | AB147: 0.05 | AC147: 0.05 | AD147: 0.05 | AE147: 0.05
B148: CL | C148: VDS | D148: 0.03 | E148: 0.03 | F148: 0.03 | G148: 0.03 | H148: 0.03 | I148: 0.03 | J148: 0.03 | K148: 0.08 | L148: 0.08 | M148: 0.08 | N148: 0.08 | O148: 0.08 | R148: CL | S148: VDS | T148: 0.03 | U148: 0.03 | V148: 0.03 | W148: 0.03 | X148: 0.03 | Y148: 0.03 | Z148: 0.03 | AA148: 0.05 | AB148: 0.05 | AC148: 0.05 | AD148: 0.05 | AE148: 0.05
B149: CL | C149: CAKE | D149: 0.03 | E149: 0.03 | F149: 0.03 | G149: 0.05 | H149: 0.05 | I149: 0.05 | J149: 0.05 | K149: 0.08 | L149: 0.08 | M149: 0.08 | N149: 0.08 | O149: 0.08 | R149: CL | S149: CAKE | T149: 0.03 | U149: 0.03 | V149: 0.03 | W149: 0.05 | X149: 0.05 | Y149: 0.05 | Z149: 0.05 | AA149: 0.05 | AB149: 0.05 | AC149: 0.05 | AD149: 0.05 | AE149: 0.05
B150: CL | C150: MWG | D150: 0.03 | E150: 0.03 | F150: 0.03 | G150: 0.03 | H150: 0.03 | I150: 0.03 | J150: 0.03 | K150: 0.08 | L150: 0.08 | M150: 0.08 | N150: 0.08 | O150: 0.08 | R150: CL | S150: MWG | T150: 0.03 | U150: 0.03 | V150: 0.03 | W150: 0.03 | X150: 0.03 | Y150: 0.03 | Z150: 0.03 | AA150: 0.08 | AB150: 0.08 | AC150: 0.08 | AD150: 0.08 | AE150: 0.08
B151: CL | C151: VNPAY | D151: 0.03 | E151: 0.03 | F151: 0.03 | G151: 0.03 | H151: 0.03 | I151: 0.03 | J151: 0.03 | K151: 0.08 | L151: 0.08 | M151: 0.08 | N151: 0.08 | O151: 0.08 | R151: CL | S151: VNPAY | T151: 0.03 | U151: 0.03 | V151: 0.03 | W151: 0.03 | X151: 0.03 | Y151: 0.03 | Z151: 0.03 | AA151: 0.08 | AB151: 0.08 | AC151: 0.08 | AD151: 0.08 | AE151: 0.08
B152: CL | C152: ZaloPAY | D152: 0.03 | E152: 0.03 | F152: 0.03 | G152: 0.03 | H152: 0.03 | I152: 0.03 | J152: 0.03 | K152: 0.03 | L152: 0.03 | M152: 0.03 | N152: 0.03 | O152: 0.03 | R152: CL | S152: ZaloPAY | T152: 0.03 | U152: 0.03 | V152: 0.03 | W152: 0.03 | X152: 0.03 | Y152: 0.03 | Z152: 0.03 | AA152: 0.03 | AB152: 0.03 | AC152: 0.03 | AD152: 0.03 | AE152: 0.03
B153: CL | C153: VNPOST | D153: 0.03 | E153: 0.03 | F153: 0.03 | G153: 0.03 | H153: 0.03 | I153: 0.03 | J153: 0.03 | K153: 0.03 | L153: 0.03 | M153: 0.03 | N153: 0.03 | O153: 0.03 | R153: CL | S153: VNPOST | T153: 0.03 | U153: 0.03 | V153: 0.03 | W153: 0.03 | X153: 0.03 | Y153: 0.03 | Z153: 0.03 | AA153: 0.03 | AB153: 0.03 | AC153: 0.03 | AD153: 0.03 | AE153: 0.03
C157: Disburse | D157: 1 | E157: 2 | F157: =E157+1 -> 3 | G157: =F157+1 -> 4 | H157: =G157+1 -> 5 | I157: =H157+1 -> 6 | J157: =I157+1 -> 7 | K157: =J157+1 -> 8 | L157: =K157+1 -> 9 | M157: =L157+1 -> 10 | N157: 11 | O157: 12
B158: CL | C158: VDS | D158: =DATA!#REF! -> #REF! | E158: =DATA!#REF! -> #REF! | F158: =DATA!#REF! -> #REF! | G158: =DATA!#REF! -> #REF! | H158: =DATA!#REF! -> #REF! | I158: =DATA!#REF! -> #REF! | J158: =DATA!#REF! -> #REF! | K158: =DATA!#REF! -> #REF! | ... M158: =DATA!#REF! -> #REF! | N158: 513252480000 | O158: 548081580000
B159: CL | C159: VDS | D159: =DATA!#REF! -> #REF! | E159: =DATA!#REF! -> #REF! | F159: =DATA!#REF! -> #REF! | G159: =DATA!#REF! -> #REF! | H159: =DATA!#REF! -> #REF! | I159: =DATA!#REF! -> #REF! | J159: =DATA!#REF! -> #REF! | K159: =DATA!#REF! -> #REF! | ... M159: =DATA!#REF! -> #REF! | N159: 746250000 | O159: 593750000
B160: CL | C160: CAKE | D160: =DATA!#REF! -> #REF! | E160: =DATA!#REF! -> #REF! | F160: =DATA!#REF! -> #REF! | G160: =DATA!#REF! -> #REF! | H160: =DATA!#REF! -> #REF! | I160: =DATA!#REF! -> #REF! | J160: =DATA!#REF! -> #REF! | K160: =DATA!#REF! -> #REF! | ... M160: =DATA!#REF! -> #REF! | N160: 587879520000 | O160: 522091590000
B161: CL | C161: MWG | D161: =DATA!#REF! -> #REF! | E161: =DATA!#REF! -> #REF! | F161: =DATA!#REF! -> #REF! | G161: =DATA!#REF! -> #REF! | H161: =DATA!#REF! -> #REF! | I161: =DATA!#REF! -> #REF! | J161: =DATA!#REF! -> #REF! | K161: =DATA!#REF! -> #REF! | ... M161: =DATA!#REF! -> #REF! | N161: 100217490000 | O161: 126953670000
B162: CL | C162: VNPAY | D162: =DATA!#REF! -> #REF! | E162: =DATA!#REF! -> #REF! | F162: =DATA!#REF! -> #REF! | G162: =DATA!#REF! -> #REF! | H162: =DATA!#REF! -> #REF! | I162: =DATA!#REF! -> #REF! | J162: =DATA!#REF! -> #REF! | K162: =DATA!#REF! -> #REF! | ... M162: =DATA!#REF! -> #REF! | N162: 19620350000 | O162: 21697550000
B163: CL | C163: ZaloPAY | D163: =DATA!#REF! -> #REF! | E163: =DATA!#REF! -> #REF! | F163: =DATA!#REF! -> #REF! | G163: =DATA!#REF! -> #REF! | H163: =DATA!#REF! -> #REF! | I163: =DATA!#REF! -> #REF! | J163: =DATA!#REF! -> #REF! | K163: =DATA!#REF! -> #REF! | ... M163: =DATA!#REF! -> #REF! | N163: 98531400000 | O163: 117580890000
B164: CL | C164: VNPOST | D164: =DATA!#REF! -> #REF! | E164: =DATA!#REF! -> #REF! | F164: =DATA!#REF! -> #REF! | G164: =DATA!#REF! -> #REF! | H164: =DATA!#REF! -> #REF! | I164: =DATA!#REF! -> #REF! | J164: =DATA!#REF! -> #REF! | K164: =DATA!#REF! -> #REF! | ... M164: =DATA!#REF! -> #REF! | N164: 10022250000 | O164: 17538450000
C167: Balance
C168: VDS | D168: 1147479030231 | E168: 1059836524693 | F168: 1075941072798 | G168: 1136717782140 | H168: 1178814582203 | I168: 1219457237377 | J168: 1378305772338 | K168: 1490245196812 | L168: 1689128717794 | M168: 1873560534525 | N168: 2072466106173 | O168: 2269684868394
C169: VDS | D169: 9787251521 | E169: 9283199996 | F169: 9564466715 | G169: 9405286904 | H169: 9191757861 | I169: 8337120782 | J169: 7983124244 | K169: 7828795755 | L169: 7633800771 | M169: 7459775694 | N169: 6974057806 | O169: 6432786980
C170: CAKE | D170: 617388935208 | E170: 641355826984 | F170: 714122331087 | G170: 828149405266 | H170: 942281111056 | I170: 1061749655584 | J170: 1263411463377 | K170: 1408151899248 | L170: 1661204287348 | M170: 1884077906690 | N170: 2174765666320 | O170: 2357795195257
C171: MWG | D171: 36367269639 | E171: 46067112309 | F171: 65390137765 | G171: 87363644373 | H171: 113146946702 | I171: 143342303049 | J171: 182312198583 | K171: 229400437441 | L171: 310005556768 | M171: 375444603055 | N171: 442698671892 | O171: 529319867060
C172: VNPAY | D172: 13469430921 | E172: 21779092016 | F172: 31958511524 | G172: 42799955655 | H172: 57933433924 | I172: 69056405609 | J172: 76005949782 | K172: 80667491327 | L172: 91494491443 | M172: 101068876374 | N172: 107157807951 | O172: 114324863034
C173: ZaloPAY | F173: 9630000 | G173: 8294394 | H173: 28358115388 | I173: 70729974420 | J173: 147333061236 | K173: 210389493640 | L173: 265187908930 | M173: 354053782593 | N173: 405762171754 | O173: 466276829515
C174: VNPOST | G174: 31810609 | H174: 107196374 | I174: 692239123 | J174: 1249560912 | K174: 1781017598 | L174: 4151089766 | M174: 9760122310 | N174: 18483847677 | O174: 34203552680
E178: MOB1-3 | F178: MOB4-end
C179: CL | D179: VDS | E179: =SUMPRODUCT(M168:O168,M147:O147)/SUM(M168:O168) -> 0.08 | F179: =SUMPRODUCT(M168:O168,AC147:AE147)/SUM(M168:O168) -> 0.05
C180: CL | D180: VDS | E180: =SUMPRODUCT(M169:O169,M148:O148)/SUM(M169:O169) -> 0.08 | F180: =SUMPRODUCT(M169:O169,AC148:AE148)/SUM(M169:O169) -> 0.05
C181: CL | D181: CAKE | E181: =SUMPRODUCT(M170:O170,M149:O149)/SUM(M170:O170) -> 0.08 | F181: =SUMPRODUCT(M170:O170,AC149:AE149)/SUM(M170:O170) -> 0.05
C182: CL | D182: MWG | E182: =SUMPRODUCT(M171:O171,M150:O150)/SUM(M171:O171) -> 0.08 | F182: =SUMPRODUCT(M171:O171,AC150:AE150)/SUM(M171:O171) -> 0.08
C183: CL | D183: VNPAY | E183: =SUMPRODUCT(M172:O172,M151:O151)/SUM(M172:O172) -> 0.08 | F183: =SUMPRODUCT(M172:O172,AC151:AE151)/SUM(M172:O172) -> 0.08
C184: CL | D184: ZaloPAY | E184: =SUMPRODUCT(M173:O173,M152:O152)/SUM(M173:O173) -> 0.03 | F184: =SUMPRODUCT(M173:O173,AC152:AE152)/SUM(M173:O173) -> 0.03
C185: CL | D185: VNPOST | E185: =SUMPRODUCT(M174:O174,M153:O153)/SUM(M174:O174) -> 0.03 | F185: =SUMPRODUCT(M174:O174,AC153:AE153)/SUM(M174:O174) -> 0.03

Sheet RISK
B4: PD
B6: Sum of principal balance | C6: Column Labels
B7: Row Labels | C7: 202412 | D7: 202501 | E7: 202502 | F7: 202503 | G7: 202504 | H7: 202505 | I7: 202506 | J7: 202507 | K7: 202508 | L7: 202509 | M7: 202510 | O7: Row Labels | P7: 202412 | Q7: 202501 | R7: 202502 | S7: 202503 | T7: 202504 | U7: 202505 | V7: 202506 | W7: 202507 | X7: 202508 | Y7: 202509 | Z7: 202510 | AA7: 202511 | AB7: 202512
B8: B00 | C8: 140907432312 | D8: 125733474174 | E8: 120452958029 | F8: 124792371704 | G8: 130856706527 | H8: 132564696356 | I8: 131668433529 | J8: 187034559967 | K8: 234570648779 | L8: 361167057609 | M8: 427073147362 | O8: B00 | P8: 140907432312 | Q8: 125733474174 | R8: 120452958029 | S8: 124792371704 | T8: 130856706527 | U8: 132564696356 | V8: 131668433529 | W8: 187034559967 | X8: 234570648779 | Y8: 361167057609 | Z8: 427073147362 | AA8: 444050983683 | AB8: 518502880178
B9: B01 | C9: 8049379348 | D9: 10430070154 | E9: 9674986086 | F9: 8031063372 | G9: 7402106547 | H9: 8351092769 | I9: 8559537399 | J9: 8307280207 | K9: 16822083715 | L9: 19265374663 | M9: 40594276097 | O9: B01 | P9: 8049379348 | Q9: 10430070154 | R9: 9674986086 | S9: 8031063372 | T9: 7402106547 | U9: 8351092769 | V9: 8559537399 | W9: 8307280207 | X9: 16822083715 | Y9: 19265374663 | Z9: 40594276097 | AA9: 41642193407 | AB9: 38818570296
B10: B02 | C10: 4435792144 | D10: 4896829780 | E10: 8595511000 | F10: 7706420334 | G10: 5771683753 | H10: 5654194523 | I10: 6582155229 | J10: 6768128609 | K10: 6476677859 | L10: 12875173819 | M10: 15270541419 | O10: B02 | P10: 4435792144 | Q10: 4896829780 | R10: 8595511000 | S10: 7706420334 | T10: 5771683753 | U10: 5654194523 | V10: 6582155229 | W10: 6768128609 | X10: 6476677859 | Y10: 12875173819 | Z10: 15270541419 | AA10: 32868197980 | AB10: 34029191778
B11: B03 | C11: 5098774496 | D11: 4313905587 | E11: 4713700431 | F11: 7751016797 | G11: 7330539438 | H11: 5690338454 | I11: 5340986249 | J11: 5791073866 | K11: 6185152797 | L11: 6135605392 | M11: 11999715261 | O11: B03 | P11: 5098774496 | Q11: 4313905587 | R11: 4713700431 | S11: 7751016797 | T11: 7330539438 | U11: 5690338454 | V11: 5340986249 | W11: 5791073866 | X11: 6185152797 | Y11: 6135605392 | Z11: 11999715261 | AA11: 14553409292 | AB11: 31842681047
B12: B04 | C12: 4790023788 | D12: 4888975408 | E12: 4169222252 | F12: 4758990057 | G12: 7495611443 | H12: 7133370522 | I12: 5549175405 | J12: 5489579313 | K12: 5883465410 | L12: 5984050756 | M12: 5935025762 | O12: B04 | P12: 4790023788 | Q12: 4888975408 | R12: 4169222252 | S12: 4758990057 | T12: 7495611443 | U12: 7133370522 | V12: 5549175405 | W12: 5489579313 | X12: 5883465410 | Y12: 5984050756 | Z12: 5935025762 | AA12: 11657360869 | AB12: 14406280932
B13: B05 | C13: 4124645905 | D13: 4934745342 | E13: 4778161995 | F13: 3925917203 | G13: 4662271901 | H13: 7322457696 | I13: 6999822052 | J13: 5316725948 | K13: 5360248366 | L13: 5783462054 | M13: 5974154178 | O13: B05 | P13: 4124645905 | Q13: 4934745342 | R13: 4778161995 | S13: 3925917203 | T13: 4662271901 | U13: 7322457696 | V13: 6999822052 | W13: 5316725948 | X13: 5360248366 | Y13: 5783462054 | Z13: 5974154178 | AA13: 5854320253 | AB13: 11465822103
B14: B06 | C14: 3444566681 | D14: 4087432848 | E14: 4501563793 | F14: 4721019466 | G14: 3874414147 | H14: 4311181112 | I14: 7219004819 | J14: 7209935596 | K14: 5292425080 | L14: 5287955522 | M14: 5868477448 | O14: B06 | P14: 3444566681 | Q14: 4087432848 | R14: 4501563793 | S14: 4721019466 | T14: 3874414147 | U14: 4311181112 | V14: 7219004819 | W14: 7209935596 | X14: 5292425080 | Y14: 5287955522 | Z14: 5868417448 | AA14: 5926888411 | AB14: 5566562267
B15: B07 | C15: 3056608221 | D15: 3297912124 | E15: 4187173007 | F15: 4597721703 | G15: 4660876514 | H15: 3968094669 | I15: 4256572638 | J15: 6625430860 | K15: 7277688767 | L15: 5205196152 | M15: 5018131138 | O15: B07 | P15: 3056608221 | Q15: 3297912124 | R15: 4187173007 | S15: 4597721703 | T15: 4660876514 | U15: 3968094669 | V15: 4254982638 | W15: 6625430860 | X15: 7272688767 | Y15: 5198158627 | Z15: 4994629138 | AA15: 5772400183 | AB15: 5901405147
B16: B08 | C16: 2403947249 | D16: 3032344975 | E16: 3231259504 | F16: 3883092064 | G16: 4455085951 | H16: 4509113367 | I16: 3907179760 | J16: 4539312832 | K16: 6203958337 | L16: 7170503915 | M16: 5245986074 | O16: B08 | P16: 2403947249 | Q16: 3032344975 | R16: 3209061450 | S16: 3877434529 | T16: 4432611255 | U16: 4506713760 | V16: 3895059680 | W16: 4514742412 | X16: 6166309473 | Y16: 7131035354 | Z16: 5206442770 | AA16: 4941925114 | AB16: 5596138320
B17: B09 | C17: 1992845181 | D17: 2364770807 | E17: 2875111337 | F17: 3263425245 | G17: 3870803181 | H17: 4639256336 | I17: 4472172151 | J17: 4042746905 | K17: 4652678695 | L17: 6203958337 | M17: 5088884000 | O17: B09 | P17: 1992845181 | Q17: 2364770807 | R17: 2861013337 | S17: 3241227191 | T17: 3857609577 | U17: 4616781640 | V17: 4463656517 | W17: 4019506825 | X17: 4617428275 | Y17: 6166309473 | Z17: 5059247637 | AA17: 5206442770 | AB17: 5118772716
B18: B10 | C18: 1893505610 | D18: 2029094278 | E18: 2193788847 | F18: 2889791733 | G18: 3263425245 | H18: 3870803181 | I18: 4639256336 | J18: 4272667881 | K18: 3904006251 | L18: 4652678695 | M18: 8160105786 | O18: B10+ | P18: =SUM(P19:P41) -> 19100946411 | Q18: =SUM(Q19:Q41) -> 21071369888 | R18: =SUM(R19:R41) -> 22848159753 | S18: =SUM(S19:S41) -> 25814153486 | T18: =SUM(T19:T41) -> 29055380677 | U18: =SUM(U19:U41) -> 32912990254 | V18: =SUM(V19:V41) -> 37529771894 | W18: =SUM(W19:W41) -> 41986480470 | ... AB18: =SUM(AB19:AB41) -> 69549237551
B19: B11 | C19: 2615970631 | D19: 1853047905 | E19: 2016002111 | F19: 2284088847 | G19: 2889791733 | H19: 3150177356 | I19: 3870803181 | J19: 4264827550 | K19: 4383122556 | L19: 3904006251 | M19: 4755861069 | O19: B10 | P19: 1893505610 | Q19: 2029094278 | R19: 2188788847 | S19: 2875693733 | T19: 3241227191 | U19: 3857609577 | V19: 4616781640 | W19: 4264152247 | X19: 3880766171 | Y19: 4617428275 | Z19: 8109160127 | AA19: 5059247637 | AB19: 5240922659
B20: B12 | C20: 2699806684 | D20: 2660589206 | E20: 1815945991 | F20: 1936569111 | G20: 2284088847 | H20: 2883667643 | I20: 3150177356 | J20: 4095272285 | K20: 4222269485 | L20: 4383122556 | M20: 3918360283 | O20: B11 | P20: 2615970631 | Q20: 1853047905 | R20: 2013000076 | S20: 2279088847 | T20: 2875693733 | U20: 3127979302 | V20: 3857609577 | W20: 4245501387 | X20: 4374606922 | Y20: 3880766171 | Z20: 4721110655 | AA20: 8109160127 | AB20: 4948026348
B21: B13 | C21: 2678111331 | D21: 2736513609 | E21: 2627512020 | F21: 1803850991 | G21: 1936569111 | H21: 2278417771 | I21: 2883667643 | J21: 3374565195 | K21: 4168191840 | L21: 4222269485 | M21: 4527018767 | O21: B12 | P21: 2699806684 | Q21: 2660589206 | R21: 1812573991 | S21: 1933567076 | T21: 2279088847 | U21: 2869569643 | V21: 3127979302 | W21: 4078930148 | X21: 4202943322 | Y21: 4370606922 | Z21: 3894620197 | AA21: 4721110655 | AB21: 8367352555
B22: B14 | C22: 2335415793 | D22: 2496616461 | E22: 2530657107 | F22: 2539397243 | G22: 1803850991 | H22: 1986969275 | I22: 2278417771 | J22: 2899343075 | K22: 3484577486 | L22: 4168191840 | M22: 4016515924 | O22: B13 | P22: 2678111331 | Q22: 2736513609 | R22: 2623856020 | S22: 1800478991 | T22: 1933567076 | U22: 2273417771 | V22: 2869569643 | W22: 3352367141 | X22: 4151849703 | Y22: 4202943322 | Z22: 4514503133 | AA22: 3894620197 | AB22: 4569750243
B23: B15 | C23: 2034681390 | D23: 2351385795 | E23: 2572269731 | F23: 2606203706 | G23: 2539397243 | H23: 1784540286 | I23: 1986969275 | J23: 2300520511 | K23: 2806893075 | L23: 3484577486 | M23: 4210313522 | O23: B14 | P23: 2329202793 | Q23: 2490515735 | R23: 2521912107 | S23: 2535741243 | T23: 1800478991 | U23: 1983967240 | V23: 2273417771 | W23: 2885245075 | X23: 3462379432 | Y23: 4151849703 | Z23: 3997189761 | AA23: 4514503133 | AB23: 3921997196
B24: B16 | C24: 1231619486 | D24: 2041768388 | E24: 2311864598 | F24: 2587616461 | G24: 2606203706 | H24: 2581964319 | I24: 1784540286 | J24: 2067319275 | K24: 2339170511 | L24: 2806893075 | M24: 3444515187 | O24: B15 | P24: 2025336392 | Q24: 2348362795 | R24: 2566169005 | S24: 2597458706 | T24: 2535741243 | U24: 1781168286 | V24: 1983967240 | W24: 2295520511 | X24: 2795795075 | Y24: 3462379432 | Z24: 4195254125 | AA24: 3997189761 | AB24: 4341992226
B25: B17 | C25: 1296828243 | D25: 1238496061 | E25: 1966540137 | F25: 2332472793 | G25: 2587616461 | H25: 2657590226 | I25: 2581964319 | J25: 1698336998 | K25: 1992327072 | L25: 2339170511 | M25: 2928432253 | O25: B16 | P25: 1231619486 | Q25: 2029233390 | R25: 2305651598 | S25: 2581515735 | T25: 2597458706 | U25: 2578308319 | V25: 1781168286 | W25: 2064317240 | X25: 2331170511 | Y25: 2795795075 | Z25: 3423034393 | AA25: 4195254125 | AB25: 4168314369
B26: B18 | C26: 1337512243 | D26: 1303001668 | E26: 1261042486 | F26: 2034681390 | G26: 2332472793 | H26: 2496616461 | I26: 2657590226 | J26: 2581240264 | K26: 1760129201 | L26: 1992327072 | M26: 2345861385 | O26: B17 | P26: 1294828243 | Q26: 1238496061 | R26: 1957195139 | S26: 2326259793 | T26: 2581515735 | U26: 2648845226 | V26: 2578308319 | W26: 1694964998 | X26: 1989325072 | Y26: 2331170511 | Z26: 2915334253 | AA26: 3423034393 | AB26: 4151853369
B27: B19 | C27: 900285502 | D27: 1362472248 | E27: 1324296196 | F27: 1231619486 | G27: 2034681390 | H27: 2351385795 | I27: 2496616461 | J27: 2513176585 | K27: 2648240264 | L27: 1760129201 | M27: 2008091198 | O27: B18 | P27: 1333022243 | Q27: 1301001668 | R27: 1261042486 | S27: 2025336392 | T27: 2326259793 | U27: 2490515735 | V27: 2648845226 | W27: 2577584264 | X27: 1756757166 | Y27: 1989325072 | Z27: 2337861385 | AA27: 2915334253 | AB27: 3524206847
B28: B20 | C28: 99257496 | D28: 927275497 | E28: 1361722436 | F28: 1296828243 | G28: 1231619486 | H28: 2041768388 | I28: 2351385795 | J28: 2607421630 | K28: 2453136727 | L28: 2648240264 | M28: 1819829201 | O28: B19 | P28: 900285502 | Q28: 1357982248 | R28: 1322296196 | S28: 1231619486 | T28: 2025336392 | U28: 2348362795 | V28: 2490515735 | W28: 2504431585 | X28: 2644584264 | Y28: 1756757166 | Z28: 2005089198 | AA28: 2337861385 | AB28: 2982932267
B29: B21 | D29: 99257496 | E29: 833984356 | F29: 1337512243 | G29: 1296828243 | H29: 1238496061 | I29: 2041768388 | J29: 2360712598 | K29: 2667461488 | L29: 2453136727 | M29: 2648240264 | O29: B20 | P29: 99257496 | Q29: 927275497 | R29: 1357232436 | S29: 1294828243 | T29: 1231619486 | U29: 2029233390 | V29: 2348362795 | W29: 2601320904 | X29: 2444391727 | Y29: 2644584264 | Z29: 1816457166 | AA29: 2005089198 | AB29: 2299361385
B30: B22 | E30: 84457496 | F30: 900285502 | G30: 1337512243 | H30: 1303001668 | I30: 1238496061 | J30: 2111931387 | K30: 2294962598 | L30: 2667461488 | M30: 2398091218 | O30: B21 | Q30: 99257496 | R30: 833984356 | S30: 1333022243 | T30: 1294828243 | U30: 1238496061 | V30: 2029233390 | W30: 2357689598 | X30: 2661360762 | Y30: 2444391727 | Z30: 2644584264 | AA30: 1816457166 | AB30: 1997439402
B31: B23 | F31: 99257496 | G31: 900285502 | H31: 1362472248 | I31: 1303001668 | J31: 1279542074 | K31: 2132681387 | L31: 2294962598 | M31: 2547500942 | O31: B22 | R31: 84457496 | S31: 900285502 | T31: 1333022243 | U31: 1301001668 | V31: 1238496061 | W31: 2099396389 | X31: 2291939598 | Y31: 2661360762 | Z31: 2389346218 | AA31: 2644584264 | AB31: 1790077234
B32: B24 | G32: 99257496 | H32: 927275497 | I32: 1362472248 | J32: 1256417668 | K32: 1227920064 | L32: 2132681387 | M32: 2391409653 | O32: B23 | S32: 99257496 | T32: 900285502 | U32: 1357982248 | V32: 1301001668 | W32: 1279542074 | X32: 2120146389 | Y32: 2291939598 | Z32: 2541400216 | AA32: 2389346218 | AB32: 2717113992
B33: B25 | H33: 99257496 | I33: 927275497 | J33: 1379185248 | K33: 1315039678 | L33: 1227920064 | M33: 2158170455 | O33: B24 | T33: 99257496 | U33: 927275497 | V33: 1357982248 | W33: 1254417668 | X33: 1227920064 | Y33: 2120146389 | Z33: 2391386653 | AA33: 2541400216 | AB33: 2296046220
B34: B26 | I34: 99257496 | J34: 905598807 | K34: 1366935303 | L34: 1315039678 | M34: 1253827736 | O34: B25 | U34: 99257496 | V34: 927275497 | W34: 1375085248 | X34: 1313039678 | Y34: 1227920064 | Z34: 2142635457 | AA34: 2391386653 | AB34: 2546427728
B35: B27 | J35: 150805186 | K35: 910864752 | L35: 1366935303 | M35: 1342201938 | O35: B26 | V35: 99257496 | W35: 905208807 | X35: 1362835303 | Y35: 1313039678 | Z35: 1253827736 | AA35: 2142635457 | AB35: 2479659139
B36: B28 | K36: 195789186 | L36: 910864752 | M36: 1310940303 | O36: B27 | W36: 150805186 | X36: 910474752 | Y36: 1362835303 | Z36: 1340201938 | AA36: 1253827736 | AB36: 2108665457
B37: B29 | L37: 195789186 | M37: 921909752 | O37: B28 | X37: 195789186 | Y37: 910474752 | Z37: 1306840303 | AA37: 1340201938 | AB37: 1258153078
B38: B30 | M38: 240739186 | O38: B29 | Y38: 195789186 | Z38: 921519752 | AA38: 1306840303 | AB38: 1287778963
O39: B30 | Z39: 240739186 | AA39: 921519752 | AB39: 1340907936
O40: B31 | AA40: 240739186 | AB40: 945619752
B41: OD | O41: B32 | AB41: 264639186

Sheet Leadsheet
B1: SAP PAYDAY MODEL | D1: 1
B2: HKN | C2: =[1]NOTE!P2 -> 20251001 | D2: =[1]NOTE!O2 -> v5 | K2: NOTE
K3: Please read carefully about before using model
B4: Product | C4: Unsecured loan | D4: UPL | E4: Risk input | G4: IFRS | H4: =G4 -> IFRS | L4: Disclaimer
B5: Sub-Product | C5: Payday | D5: ALL | E5: Write off | G5: DPD180+ | H5: =G5 -> DPD180+ | L5: Instruction
B6: Sub-Segments | C6: CAKE | D6: ALL | E6: Quarter | G6: Q3.2025 | H6: =G6 -> Q3.2025 | L6: Legend
B8: REVENUE INPUT | H8: Cur: mVND | K8: GENERAL OUTPUT | U8: Cur: mVND
B10: Amount & Tenor | C10: Loan amount | E10: =DATA!G37 -> 3.5358329 | N10: Life time | O10: Year 1 | P10: Year 2 | Q10: Year 3 | R10: Year 4 | S10: Year 5 | T10: % ANR | U10: % Disbursement
C11: Payment Method | E11: EMI | K11: ANR | N11: =N29 -> 0.42985568 | O11: =O29 -> 0.42985568 | P11: =P29 -> 0 | Q11: =Q29 -> 0 | R11: =R29 -> 0 | S11: =S29 -> 0 | U11: =N11/$E$10 -> 0.12157127
C12: Nominal Tenor | E12: =DATA!H37 -> 1 | K12: TOI | N12: =SUM(N13:N15) -> 0.36675528 | O12: =SUM(O13:O15) -> 0.36675528 | P12: =SUM(P13:P15) -> 0 | Q12: =SUM(Q13:Q15) -> 0 | R12: =SUM(R13:R15) -> 0 | S12: =SUM(S13:S15) -> 0 | T12: =N12/$E$14*12/$N$11 -> 1.4626382 | U12: =N12/$E$10 -> 0.10372529
C13: Maturity to Termination | E13: 6 | K13: Net interest income | N13: =N31 -> 0.14255811 | O13: =O31 -> 0.14255811 | P13: =P31 -> 0 | Q13: =Q31 -> 0 | R13: =R31 -> 0 | S13: =S31 -> 0 | T13: =N13/$E$14*12/$N$11 -> 0.56852881 | U13: =N13/$E$10 -> 0.040318114
C14: Month on book | E14: =E12+E13 -> 7 | K14: Net fee income | N14: =N34 -> 0.22419717 | O14: =O34 -> 0.22419717 | P14: =P34 -> 0 | Q14: =Q34 -> 0 | R14: =R34 -> 0 | S14: =S34 -> 0 | T14: =N14/$E$14*12/$N$11 -> 0.8941094 | U14: =N14/$E$10 -> 0.063407173
K15: Other income | N15: =N37 -> 0 | O15: =O37 -> 0 | P15: =P37 -> 0 | Q15: =Q37 -> 0 | R15: =R37 -> 0 | S15: =S37 -> 0 | T15: =N15/$E$14*12/$N$11 -> 0 | U15: =N15/$E$10 -> 0
K16: PROVISION | N16: =N38 -> -0.17376626 | O16: =O38 -> -0.17376626 | P16: =P38 -> 0 | Q16: =Q38 -> 0 | R16: =R38 -> 0 | S16: =S38 -> 0 | T16: =N16/$E$14*12/$N$11 -> -0.69298843 | U16: =N16/$E$10 -> -0.049144364
B17: Pricing | C17: From | D17: To | E17: IR | F17: COF | G17: NIM | K17: OPEX | N17: =SUM(N18:N21) -> -0.11811444 | O17: =SUM(O18:O21) -> -0.11811444 | P17: =SUM(P18:P21) -> 0 | Q17: =SUM(Q18:Q21) -> 0 | R17: =SUM(R18:R21) -> 0 | S17: =SUM(S18:S21) -> 0 | T17: =N17/$E$14*12/$N$11 -> -0.47104625 | U17: =N17/$E$10 -> -0.033404985
A18: 1 | B18: In due | C18: 1 | D18: 1 | E18: =DATA!I37 -> 0.56824848 | F18: =DATA!D162 -> 0.059930813 | G18: =E18-F18 -> 0.50831767 | K18: Acquisition cost | N18: =SUM(N40) -> -0.04522502 | O18: =SUM(O40) -> -0.04522502 | P18: =SUM(P40) -> 0 | Q18: =SUM(Q40) -> 0 | R18: =SUM(R40) -> 0 | S18: =SUM(S40) -> 0 | T18: =N18/$E$14*12/$N$11 -> -0.18035962 | U18: =N18/$E$10 -> -0.012790486
A19: 2 | B19: Overdue | C19: =D18+1 -> 2 | D19: =E14 -> 7 | E19: =E18 -> 0.56824848 | F19: =F18 -> 0.059930813 | G19: =E19-F19 -> 0.50831767 | K19: UW & Disbursal | N19: =N44 -> -0.0090250651 | O19: =O44 -> -0.0090250651 | P19: =P44 -> 0 | Q19: =Q44 -> 0 | R19: =R44 -> 0 | S19: =S44 -> 0 | T19: =N19/$E$14*12/$N$11 -> -0.035992406 | U19: =N19/$E$10 -> -0.0025524581
A20: 3 | K20: Collection & aftersale service | N20: =N47 -> -0.0070726272 | O20: =O47 -> -0.0070726272 | P20: =P47 -> 0 | Q20: =Q47 -> 0 | R20: =R47 -> 0 | S20: =S47 -> 0 | T20: =N20/$E$14*12/$N$11 -> -0.028205987 | U20: =N20/$E$10 -> -0.0020002719
A21: 4 | B21: Credit insurrance | C21: Banca Premium (excl. in loan) | F21: per disbursement amount | K21: Support unit | N21: =N51 -> -0.056791732 | O21: =O51 -> -0.056791732 | P21: =P51 -> 0 | Q21: =Q51 -> 0 | R21: =R51 -> 0 | S21: =S51 -> 0 | T21: =N21/$E$14*12/$N$11 -> -0.22648824 | U21: =N21/$E$10 -> -0.016061769
C22: Banca Premium (incl. in loan) | E22: =DATA!J37 -> 0.08 | F22: per disbursement amount | K22: PBT | N22: =N12+N16+N17 -> 0.07487458 | O22: =O12+O16+O17 -> 0.07487458 | P22: =P12+P16+P17 -> 0 | Q22: =Q12+Q16+Q17 -> 0 | R22: =R12+R16+R17 -> 0 | S22: =S12+S16+S17 -> 0 | T22: =N22/$E$14*12/$N$11 -> 0.29860353 | U22: =N22/$E$10 -> 0.021175938
A23: 5 | C23: Penetration | E23: =DATA!K37 -> 0.99999601 | F23: per disbursement amount | K23: In which: PROFIT BEFORE SU | N23: =N22-N21 -> 0.13166631 | O23: =O22-O21 -> 0.13166631 | P23: =P22-P21 -> 0 | Q23: =Q22-Q21 -> 0 | R23: =R22-R21 -> 0 | S23: =S22-S21 -> 0 | T23: =N23/$E$14*12/$N$11 -> 0.52509176 | U23: =N23/$E$10 -> 0.037237708
C24: Commission to CAKE | E24: 0.856 | F24: per disbursement amount | H24: done
H25: done
B26: Support fee | F26: per account | K26: PERFORMANCE OUTPUT | U26: Cur: mVND
F27: per ticketsize
N28: Life time | O28: Year 1 | P28: Year 2 | Q28: Year 3 | R28: Year 4 | S28: Year 5 | T28: % ANR | U28: % Disbursement
B29: COST INPUT | H29: Cur: mVND | K29: ANR | N29: =SUM(SAP_Speadsheet!$D$48:$BF$48)/COUNTIF(SAP_Speadsheet!$D$48:$BF$48,">0") -> 0.42985568 | O29: =IFERROR(SUM(SAP_Speadsheet!$D$48:$P$48)/COUNTIF(SAP_Speadsheet!$D$48:$P$48,">0"),0) -> 0.42985568 | P29: =IFERROR(SUM(SAP_Speadsheet!$Q$48:$AB$48)/COUNTIF(SAP_Speadsheet!$Q$48:$AB$48,">0"),0) -> 0 | Q29: =IFERROR(SUM(SAP_Speadsheet!$AC$48:$AN$48)/COUNTIF(SAP_Speadsheet!$AC$48:$AN$48,">0"),0) -> 0 | R29: =IFERROR(SUM(SAP_Speadsheet!$AO$48:$AZ$48)/COUNTIF(SAP_Speadsheet!$AO$48:$AZ$48,">0"),0) -> 0 | S29: =IFERROR(SUM(SAP_Speadsheet!$BA$48:$BF$48)/COUNTIF(SAP_Speadsheet!$BA$48:$BF$48,">0"),0) -> 0 | U29: =N29/$E$10 -> 0.12157127
K30: TOI | N30: =SUM(O30:S30) -> 0.36675528 | O30: =SUM(SAP_Speadsheet!$E$53:$P$53) -> 0.36675528 | P30: =SUM(SAP_Speadsheet!$Q$53:$AB$53) -> 0 | Q30: =SUM(SAP_Speadsheet!$AC$53:$AN$53) -> 0 | R30: =SUM(SAP_Speadsheet!$AO$53:$AZ$53) -> 0 | S30: =SUM(SAP_Speadsheet!$BA$53:$BF$53) -> 0 | T30: =N30/$E$14*12/$N$29 -> 1.4626382 | U30: =N30/$E$10 -> 0.10372529
B31: Inflation rate | E31: 0.035 | F31: % per year | K31: Net interest income | N31: =SUM(O31:S31) -> 0.14255811 | O31: =SUM(SAP_Speadsheet!$E$55:$P$55) -> 0.14255811 | P31: =SUM(SAP_Speadsheet!$Q$55:$AB$55) -> 0 | Q31: =SUM(SAP_Speadsheet!$AC$55:$AN$55) -> 0 | R31: =SUM(SAP_Speadsheet!$AO$55:$AZ$55) -> 0 | S31: =SUM(SAP_Speadsheet!$BA$55:$BF$55) -> 0 | T31: =N31/$E$14*12/$N$29 -> 0.56852881 | U31: =N31/$E$10 -> 0.040318114
K32: Interest income | N32: =SUM(O32:S32) -> 0.15758571 | O32: =SUM(SAP_Speadsheet!$E$56:$P$56) -> 0.15758571 | P32: =SUM(SAP_Speadsheet!$Q$56:$AB$56) -> 0 | Q32: =SUM(SAP_Speadsheet!$AC$56:$AN$56) -> 0 | R32: =SUM(SAP_Speadsheet!$AO$56:$AZ$56) -> 0 | S32: =SUM(SAP_Speadsheet!$BA$56:$BF$56) -> 0 | T32: =N32/$E$14*12/$N$29 -> 0.62845962 | U32: =N32/$E$10 -> 0.044568202
B33: Acquisition cost | K33: Cost of fund | N33: =SUM(O33:S33) -> -0.0150276 | O33: =SUM(SAP_Speadsheet!$E$57:$P$57) -> -0.0150276 | P33: =SUM(SAP_Speadsheet!$Q$57:$AB$57) -> 0 | Q33: =SUM(SAP_Speadsheet!$AC$57:$AN$57) -> 0 | R33: =SUM(SAP_Speadsheet!$AO$57:$AZ$57) -> 0 | S33: =SUM(SAP_Speadsheet!$BA$57:$BF$57) -> 0 | T33: =N33/$E$14*12/$N$29 -> -0.059930813 | U33: =N33/$E$10 -> -0.0042500878
C34: Sale incentive | E34: Auto MODE | K34: Net fee income | N34: =SUM(O34:S34) -> 0.22419717 | O34: =SUM(SAP_Speadsheet!$E$59:$P$59) -> 0.22419717 | P34: =SUM(SAP_Speadsheet!$Q$59:$AB$59) -> 0 | Q34: =SUM(SAP_Speadsheet!$AC$59:$AN$59) -> 0 | R34: =SUM(SAP_Speadsheet!$AO$59:$AZ$59) -> 0 | S34: =SUM(SAP_Speadsheet!$BA$59:$BF$59) -> 0 | T34: =N34/$E$14*12/$N$29 -> 0.8941094 | U34: =N34/$E$10 -> 0.063407173
C35: Sharing TOI and Risk DPD90+ | E35: 0.25 | F35: % per month | K35: Insurance commission | N35: =SUM(O35:S35) -> 0.22419717 | O35: =SUM(SAP_Speadsheet!$E$60:$P$60) -> 0.22419717 | P35: =SUM(SAP_Speadsheet!$Q$60:$AB$60) -> 0 | Q35: =SUM(SAP_Speadsheet!$AC$60:$AN$60) -> 0 | R35: =SUM(SAP_Speadsheet!$AO$60:$AZ$60) -> 0 | S35: =SUM(SAP_Speadsheet!$BA$60:$BF$60) -> 0 | T35: =N35/$E$14*12/$N$29 -> 0.8941094 | U35: =N35/$E$10 -> 0.063407173
C36: Sharing TOI and Risk DPD180+ | F36: % per month | K36: Support fee | N36: =SUM(O36:S36) -> 0 | O36: =SUM(SAP_Speadsheet!$E$61:$P$61) -> 0 | P36: =SUM(SAP_Speadsheet!$Q$61:$AB$61) -> 0 | Q36: =SUM(SAP_Speadsheet!$AC$61:$AN$61) -> 0 | R36: =SUM(SAP_Speadsheet!$AO$61:$AZ$61) -> 0 | S36: =SUM(SAP_Speadsheet!$BA$61:$BF$61) -> 0 | T36: =N36/$E$14*12/$N$29 -> 0 | U36: =N36/$E$10 -> 0
E37: Adjust MODE | K37: Other income | N37: =SUM(O37:S37) -> 0 | O37: =SUM(SAP_Speadsheet!$E$63:$P$63) -> 0 | P37: =SUM(SAP_Speadsheet!$Q$63:$AB$63) -> 0 | Q37: =SUM(SAP_Speadsheet!$AC$63:$AN$63) -> 0 | R37: =SUM(SAP_Speadsheet!$AO$63:$AZ$63) -> 0 | S37: =SUM(SAP_Speadsheet!$BA$63:$BF$63) -> 0 | T37: =N37/$E$14*12/$N$29 -> 0 | U37: =N37/$E$10 -> 0
C38: Sharing CII (only) | F38: % per month | K38: PROVISION | N38: =SUM(O38:S38) -> -0.17376626 | O38: =SUM(SAP_Speadsheet!$E$175:$P$175) -> -0.17376626 | P38: =SUM(SAP_Speadsheet!$Q$175:$AB$175) -> 0 | Q38: =SUM(SAP_Speadsheet!$AC$175:$AN$175) -> 0 | R38: =SUM(SAP_Speadsheet!$AO$175:$AZ$175) -> 0 | S38: =SUM(SAP_Speadsheet!$BA$175:$BF$175) -> 0 | T38: =N38/$E$14*12/$N$29 -> -0.69298843 | U38: =N38/$E$10 -> -0.049144364
C39: Sharing COF (only) | F39: % per month | K39: OPEX | N39: =SUM(O39:S39) -> -0.11811444 | O39: =+SUM(O40,O44,O47,O51) -> -0.11811444 | P39: =+SUM(P40,P44,P47,P51) -> 0 | Q39: =+SUM(Q40,Q44,Q47,Q51) -> 0 | R39: =+SUM(R40,R44,R47,R51) -> 0 | S39: =+SUM(S40,S44,S47,S51) -> 0 | T39: =N39/$E$14*12/$N$29 -> -0.47104625 | U39: =N39/$E$10 -> -0.033404985
C40: Sharing NFI (only) | F40: % per month | K40: Acquisition cost | N40: =SUM(O40:S40) -> -0.04522502 | O40: =SUM(O41:O43) -> -0.04522502 | P40: =SUM(P41:P43) -> 0 | Q40: =SUM(Q41:Q43) -> 0 | R40: =SUM(R41:R43) -> 0 | S40: =SUM(S41:S43) -> 0 | T40: =N40/$E$14*12/$N$29 -> -0.18035962 | U40: =N40/$E$10 -> -0.012790486
C41: Sharing Risk DPD90+ (Only) | F41: % per month | K41: Lead Acquisition | N41: =SUM(O41:S41) -> 0 | O41: =SUM(SAP_Speadsheet!$E$68:$P$68) -> 0 | P41: =SUM(SAP_Speadsheet!$Q$68:$AB$68) -> 0 | Q41: =SUM(SAP_Speadsheet!$AC$68:$AN$68) -> 0 | R41: =SUM(SAP_Speadsheet!$AO$68:$AZ$68) -> 0 | S41: =SUM(SAP_Speadsheet!$BA$68:$BF$68) -> 0 | T41: =N41/$E$14*12/$N$29 -> 0 | U41: =N41/$E$10 -> 0
C42: Sharing Risk DPD180+ (only) | F42: % per month | K42: Sharing performance | N42: =SUM(O42:S42) -> -0.044761672 | O42: =SUM(SAP_Speadsheet!$E$69:$P$69) -> -0.044761672 | P42: =SUM(SAP_Speadsheet!$Q$69:$AB$69) -> 0 | Q42: =SUM(SAP_Speadsheet!$AC$69:$AN$69) -> 0 | R42: =SUM(SAP_Speadsheet!$AO$69:$AZ$69) -> 0 | S42: =SUM(SAP_Speadsheet!$BA$69:$BF$69) -> 0 | T42: =N42/$E$14*12/$N$29 -> -0.17851176 | U42: =N42/$E$10 -> -0.012659442
K43: Marketing | N43: =SUM(O43:S43) -> -0.00046334764 | O43: =SUM(SAP_Speadsheet!$E$78:$P$78) -> -0.00046334764 | P43: =SUM(SAP_Speadsheet!$Q$78:$AB$78) -> 0 | Q43: =SUM(SAP_Speadsheet!$AC$78:$AN$78) -> 0 | R43: =SUM(SAP_Speadsheet!$AO$78:$AZ$78) -> 0 | S43: =SUM(SAP_Speadsheet!$BA$78:$BF$78) -> 0 | T43: =N43/$E$14*12/$N$29 -> -0.0018478533 | U43: =N43/$E$10 -> -0.00013104342
C44: Partner Lead Acquistion | F44: per account | K44: UW & Disbursal | N44: =SUM(O44:S44) -> -0.0090250651 | O44: =SUM(O45:O46) -> -0.0090250651 | P44: =SUM(P45:P46) -> 0 | Q44: =SUM(Q45:Q46) -> 0 | R44: =SUM(R45:R46) -> 0 | S44: =SUM(S45:S46) -> 0 | T44: =N44/$E$14*12/$N$29 -> -0.035992406 | U44: =N44/$E$10 -> -0.0025524581
F45: per ticketsize | K45: Underwriting | N45: =SUM(O45:S45) -> -0.0079689063 | O45: =SUM(SAP_Speadsheet!$E$81:$P$81) -> -0.0079689063 | P45: =SUM(SAP_Speadsheet!$Q$81:$AB$81) -> 0 | Q45: =SUM(SAP_Speadsheet!$AC$81:$AN$81) -> 0 | R45: =SUM(SAP_Speadsheet!$AO$81:$AZ$81) -> 0 | S45: =SUM(SAP_Speadsheet!$BA$81:$BF$81) -> 0 | T45: =N45/$E$14*12/$N$29 -> -0.031780392 | U45: =N45/$E$10 -> -0.0022537565
K46: Disbursement | N46: =SUM(O46:S46) -> -0.0010561588 | O46: =SUM(SAP_Speadsheet!$E$82:$P$82) -> -0.0010561588 | P46: =SUM(SAP_Speadsheet!$Q$82:$AB$82) -> 0 | Q46: =SUM(SAP_Speadsheet!$AC$82:$AN$82) -> 0 | R46: =SUM(SAP_Speadsheet!$AO$82:$AZ$82) -> 0 | S46: =SUM(SAP_Speadsheet!$BA$82:$BF$82) -> 0 | T46: =N46/$E$14*12/$N$29 -> -0.0042120137 | U46: =N46/$E$10 -> -0.00029870157
C47: Marketing cost | K47: Collection & after sale service | N47: =SUM(O47:S47) -> -0.0070726272 | O47: =SUM(O48:O50) -> -0.0070726272 | P47: =SUM(P48:P50) -> 0 | Q47: =SUM(Q48:Q50) -> 0 | R47: =SUM(R48:R50) -> 0 | S47: =SUM(S48:S50) -> 0 | T47: =N47/$E$14*12/$N$29 -> -0.028205987 | U47: =N47/$E$10 -> -0.0020002719
K48: Early collections | N48: =SUM(O48:S48) -> -0.0066504319 | O48: =SUM(SAP_Speadsheet!$E$88:$P$88) -> -0.0066504319 | P48: =SUM(SAP_Speadsheet!$Q$88:$AB$88) -> 0 | Q48: =SUM(SAP_Speadsheet!$AC$88:$AN$88) -> 0 | R48: =SUM(SAP_Speadsheet!$AO$88:$AZ$88) -> 0 | S48: =SUM(SAP_Speadsheet!$BA$88:$BF$88) -> 0 | T48: =N48/$E$14*12/$N$29 -> -0.026522251 | U48: =N48/$E$10 -> -0.0018808671
C49: Marketing cost | E49: =DATA!C64 -> 0.00046334764 | F49: per account | K49: AMC | N49: =SUM(O49:S49) -> 0 | O49: =SUM(SAP_Speadsheet!$E$89:$P$89) -> 0 | P49: =SUM(SAP_Speadsheet!$Q$89:$AB$89) -> 0 | Q49: =SUM(SAP_Speadsheet!$AC$89:$AN$89) -> 0 | R49: =SUM(SAP_Speadsheet!$AO$89:$AZ$89) -> 0 | S49: =SUM(SAP_Speadsheet!$BA$89:$BF$89) -> 0 | T49: =N49/$E$14*12/$N$29 -> 0 | U49: =N49/$E$10 -> 0
K50: Aftersale service | N50: =SUM(O50:S50) -> -0.00042219527 | O50: =SUM(SAP_Speadsheet!$E$91:$P$91) -> -0.00042219527 | P50: =SUM(SAP_Speadsheet!$Q$91:$AB$91) -> 0 | Q50: =SUM(SAP_Speadsheet!$AC$91:$AN$91) -> 0 | R50: =SUM(SAP_Speadsheet!$AO$91:$AZ$91) -> 0 | S50: =SUM(SAP_Speadsheet!$BA$91:$BF$91) -> 0 | T50: =N50/$E$14*12/$N$29 -> -0.0016837356 | U50: =N50/$E$10 -> -0.00011940476
B51: UW & Disbursal | C51: Underwriting cost & Score | E51: =DATA!C65*Leadsheet!E54*Leadsheet!E55 -> 0.0028493448 | F51: of application | K51: Supporting Units | N51: =SUM(O51:S51) -> -0.056791732 | O51: =SUM(O52:O55) -> -0.056791732 | P51: =SUM(P52:P55) -> 0 | Q51: =SUM(Q52:Q55) -> 0 | R51: =SUM(R52:R55) -> 0 | S51: =SUM(S52:S55) -> 0 | T51: =N51/$E$14*12/$N$29 -> -0.22648824 | U51: =N51/$E$10 -> -0.016061769
C52: DOP cost | F52: of account | K52: Direct HR | N52: =SUM(O52:S52) -> -0.0090772826 | O52: =SUM(SAP_Speadsheet!$E$96:$P$96) -> -0.0090772826 | P52: =SUM(SAP_Speadsheet!$Q$96:$AB$96) -> 0 | Q52: =SUM(SAP_Speadsheet!$AC$96:$AN$96) -> 0 | R52: =SUM(SAP_Speadsheet!$AO$96:$AZ$96) -> 0 | S52: =SUM(SAP_Speadsheet!$BA$96:$BF$96) -> 0 | T52: =N52/$E$14*12/$N$29 -> -0.036200652 | U52: =N52/$E$10 -> -0.0025672261
C53: Disbursement cost | E53: =DATA!C67 -> 0.0010561588 | F53: of account | K53: Indiect HR | N53: =SUM(O53:S53) -> -0.02431866 | O53: =SUM(SAP_Speadsheet!$E$97:$P$97) -> -0.02431866 | P53: =SUM(SAP_Speadsheet!$Q$97:$AB$97) -> 0 | Q53: =SUM(SAP_Speadsheet!$AC$97:$AN$97) -> 0 | R53: =SUM(SAP_Speadsheet!$AO$97:$AZ$97) -> 0 | S53: =SUM(SAP_Speadsheet!$BA$97:$BF$97) -> 0 | T53: =N53/$E$14*12/$N$29 -> -0.09698402 | U53: =N53/$E$10 -> -0.0068777742
C54: Approval rate | E54: =DATA!E6 -> 0.38146326 | F54: of submitted application | K54: IT | N54: =SUM(O54:S54) -> -0.011666441 | O54: =SUM(SAP_Speadsheet!$E$98:$P$98) -> -0.011666441 | P54: =SUM(SAP_Speadsheet!$Q$98:$AB$98) -> 0 | Q54: =SUM(SAP_Speadsheet!$AC$98:$AN$98) -> 0 | R54: =SUM(SAP_Speadsheet!$AO$98:$AZ$98) -> 0 | S54: =SUM(SAP_Speadsheet!$BA$98:$BF$98) -> 0 | T54: =N54/$E$14*12/$N$29 -> -0.046526344 | U54: =N54/$E$10 -> -0.0032994888
C55: Disbursement rate | E55: =DATA!E7 -> 0.93733228 | F55: of aproved application | K55: Other support units | N55: =SUM(O55:S55) -> -0.011729348 | O55: =SUM(SAP_Speadsheet!$E$99:$P$99) -> -0.011729348 | P55: =SUM(SAP_Speadsheet!$Q$99:$AB$99) -> 0 | Q55: =SUM(SAP_Speadsheet!$AC$99:$AN$99) -> 0 | R55: =SUM(SAP_Speadsheet!$AO$99:$AZ$99) -> 0 | S55: =SUM(SAP_Speadsheet!$BA$99:$BF$99) -> 0 | T55: =N55/$E$14*12/$N$29 -> -0.046777221 | U55: =N55/$E$10 -> -0.0033172802
K56: PBT | N56: =SUM(O56:S56) -> 0.07487458 | O56: =SUM(SAP_Speadsheet!$E$181:$P$181) -> 0.07487458 | P56: =SUM(SAP_Speadsheet!$Q$181:$AB$181) -> 0 | Q56: =SUM(SAP_Speadsheet!$AC$181:$AN$181) -> 0 | R56: =SUM(SAP_Speadsheet!$AO$181:$AZ$181) -> 0 | S56: =SUM(SAP_Speadsheet!$BA$181:$BF$181) -> 0 | T56: =N56/$E$14*12/$N$29 -> 0.29860353 | U56: =N56/$E$10 -> 0.021175938
A57: Inflation | B57: Collection & AMC | C57: Collections_all | E57: =DATA!C66 -> 0.005 | F57: per account/month
C58: Collections_B1+ | F58: per account/month
A59: Incentive | C59: AMC_principal collected | F59: per 1mVND collected amount
A60: Sale team | C60: AMC_interest collected | F60: per 1mVND collected amount
A61: Sale Mgt | C61: AMC_penalty collected | F61: per 1mVND collected amount
A62: MA
B63: Aftersale service
C64: Email & SMS | E64: =DATA!C68 -> 0.00042219527 | F64: per account/month
B67: Supporting units | C67: Direct HR | E67: =DATA!D153 -> 0.0090772826 | F67: per account/month
C68: Indirect HR | E68: =DATA!D154 -> 0.02431866 | F68: per account/month
C69: IT | E69: =DATA!D155 -> 0.011666441 | F69: per account/month
C70: Other supports | E70: =DATA!D156 -> 0.011729348 | F70: per account/month
A72: CPCUW
B73: RISK INPUT
B75: Net flow | D75: NF | E75: PD | F75: Pro. Rate
C76: B0 - B1 | D76: =DATA!C105 -> 0.074 | E76: =PRODUCT(D76:$D$89) -> 0.05274245 | F76: =E76*(1-$E$95)*(1-$E$96)*(1-$E$97)*(1-$E$98) -> 0.049144364
C77: B1 - B2 | D77: =DATA!C106 -> 0.795 | E77: =PRODUCT(D77:$D$89) -> 0.71273581 | F77: =E77*(1-$E$95)*(1-$E$96)*(1-$E$97)*(1-$E$98) -> 0.66411303
C78: B2 - B3 | D78: =DATA!C107 -> 0.95128048 | E78: =PRODUCT(D78:$D$89) -> 0.89652303 | F78: =E78*(1-$E$95)*(1-$E$96)*(1-$E$97)*(1-$E$98) -> 0.8353623
C79: B3 - B4 | D79: =DATA!C108 -> 0.97622305 | E79: =PRODUCT(D79:$D$89) -> 0.94243816 | F79: =E79*(1-$E$95)*(1-$E$96)*(1-$E$97)*(1-$E$98) -> 0.8781451
C80: B4 - B5 | D80: =DATA!C109 -> 0.9894391 | E80: =PRODUCT(D80:$D$89) -> 0.96539224 | F80: =E80*(1-$E$95)*(1-$E$96)*(1-$E$97)*(1-$E$98) -> 0.89953326
C81: B5 - B6 | D81: 0.99 | E81: =PRODUCT(D81:$D$89) -> 0.97569648 | F81: =E81*(1-$E$95)*(1-$E$96)*(1-$E$97)*(1-$E$98) -> 0.90913454
C82: B6 - B7 | D82: 0.992 | E82: =PRODUCT(D82:$D$89) -> 0.985552 | F82: =E82*(1-$E$95)*(1-$E$96)*(1-$E$97)*(1-$E$98) -> 0.91831772
C83: B7 - B8 | D83: 0.9935 | E83: =PRODUCT(D83:$D$89) -> 0.9935 | F83: =E83*(1-$E$95)*(1-$E$96)*(1-$E$97)*(1-$E$98) -> 0.92572351
C84: B8 - B9 | D84: 1 | E84: =PRODUCT(D84:$D$89) -> 1 | F84: =E84*(1-$E$96)*(1-$E$97)*(1-$E$98) -> 0.950796
C85: B9 - B10 | D85: 1 | E85: =PRODUCT(D85:$D$89) -> 1 | F85: =E85*(1-$E$96)*(1-$E$97)*(1-$E$98) -> 0.950796
C86: B10 - B11 | D86: 1 | E86: =PRODUCT(D86:$D$89) -> 1 | F86: =E86*(1-$E$96)*(1-$E$97)*(1-$E$98) -> 0.950796
C87: B11 - B12 | D87: 1 | E87: =PRODUCT(D87:$D$89) -> 1 | F87: =E87*(1-$E$96)*(1-$E$97)*(1-$E$98) -> 0.950796
C88: B12 - B13 | D88: 1 | E88: =PRODUCT(D88:$D$89) -> 1 | F88: =E88*(1-$E$96)*(1-$E$97)*(1-$E$98) -> 0.950796
C89: B13-B24 | F89: =(1-$E$96)*(1-$E$97)*(1-$E$98) -> 0.950796
C90: B25-B36 | F90: =(1-$E$97)*(1-$E$98) -> 0.9702
C91: B36+ | F91: =(1-$E$98) -> 0.99
A92: Recovery rate B13-B24 | C92: Risk cost/ Disburse | D92: =N38/E10 -> -0.049144364
A93: Recovery rate B24-B36 | C93: Riskcost/ANR | D93: =T38 -> -0.69298843
A94: Recovery rate B36+
B95: Recovery rate | C95: B8-B12 | E95: 0.02
C96: B13-B24 | D96: Recovery rate B13-B24 | E96: 0.02
C97: B24-B36 | D97: Recovery rate B24-B36 | E97: 0.02
C98: B36+ | D98: Recovery rate B36+ | E98: 0.01
B100: %B1A/B1 | E100: =1-D77 -> 0.205
B102: Collected after WO | C102: Fee and Penalty | F102: per principle

Sheet SAP_Speadsheet
B1: SAP Speadsheet
C4: Method
C5: Month on book | D5: 0 | E5: =D5+1 -> 1 | F5: =E5+1 -> 2 | G5: =F5+1 -> 3 | H5: =G5+1 -> 4 | I5: =H5+1 -> 5 | J5: =I5+1 -> 6 | K5: =J5+1 -> 7 | L5: =K5+1 -> 8 | ... BL5: =BK5+1 -> 60
C6: Oustanding tenor | D6: =IF(Leadsheet!$E$12-SAP_Speadsheet!D5<0,0,Leadsheet!$E$12-SAP_Speadsheet!D5) -> 1 | E6: =IF(Leadsheet!$E$12-SAP_Speadsheet!E5<0,0,Leadsheet!$E$12-SAP_Speadsheet!E5) -> 0 | F6: =IF(Leadsheet!$E$12-SAP_Speadsheet!F5<0,0,Leadsheet!$E$12-SAP_Speadsheet!F5) -> 0 | G6: =IF(Leadsheet!$E$12-SAP_Speadsheet!G5<0,0,Leadsheet!$E$12-SAP_Speadsheet!G5) -> 0 | H6: =IF(Leadsheet!$E$12-SAP_Speadsheet!H5<0,0,Leadsheet!$E$12-SAP_Speadsheet!H5) -> 0 | I6: =IF(Leadsheet!$E$12-SAP_Speadsheet!I5<0,0,Leadsheet!$E$12-SAP_Speadsheet!I5) -> 0 | J6: =IF(Leadsheet!$E$12-SAP_Speadsheet!J5<0,0,Leadsheet!$E$12-SAP_Speadsheet!J5) -> 0 | K6: =IF(Leadsheet!$E$12-SAP_Speadsheet!K5<0,0,Leadsheet!$E$12-SAP_Speadsheet!K5) -> 0 | ... BL6: =IF(Leadsheet!$E$12-SAP_Speadsheet!BL5<0,0,Leadsheet!$E$12-SAP_Speadsheet!BL5) -> 0
C7: Last month on book | D7: =Leadsheet!E13+Leadsheet!E12 -> 7
B9: Balance
B10: Interest rate
C11: INR rate | D11: =Leadsheet!E18 -> 0.56824848 | E11: =IF(E$5>$D$7,0,VLOOKUP(SAP_Speadsheet!E$5,Leadsheet!$C$18:$F$19,3,1)) -> 0.56824848 | F11: =IF(F$5>$D$7,0,VLOOKUP(SAP_Speadsheet!F$5,Leadsheet!$C$18:$F$19,3,1)) -> 0.56824848 | G11: =IF(G$5>$D$7,0,VLOOKUP(SAP_Speadsheet!G$5,Leadsheet!$C$18:$F$19,3,1)) -> 0.56824848 | H11: =IF(H$5>$D$7,0,VLOOKUP(SAP_Speadsheet!H$5,Leadsheet!$C$18:$F$19,3,1)) -> 0.56824848 | I11: =IF(I$5>$D$7,0,VLOOKUP(SAP_Speadsheet!I$5,Leadsheet!$C$18:$F$19,3,1)) -> 0.56824848 | J11: =IF(J$5>$D$7,0,VLOOKUP(SAP_Speadsheet!J$5,Leadsheet!$C$18:$F$19,3,1)) -> 0.56824848 | K11: =IF(K$5>$D$7,0,VLOOKUP(SAP_Speadsheet!K$5,Leadsheet!$C$18:$F$19,3,1)) -> 0.56824848 | L11: =IF(L$5>$D$7,0,VLOOKUP(SAP_Speadsheet!L$5,Leadsheet!$C$18:$F$19,3,1)) -> 0 | ... BL11: =IF(BL$5>$D$7,0,VLOOKUP(SAP_Speadsheet!BL$5,Leadsheet!$C$18:$F$19,3,1)) -> 0
C12: COF rate | D12: =Leadsheet!F18 -> 0.059930813 | E12: =IF(E$5>$D$7,0,VLOOKUP(SAP_Speadsheet!E$5,Leadsheet!$C$18:$F$19,4,1)) -> 0.059930813 | F12: =IF(F$5>$D$7,0,VLOOKUP(SAP_Speadsheet!F$5,Leadsheet!$C$18:$F$19,4,1)) -> 0.059930813 | G12: =IF(G$5>$D$7,0,VLOOKUP(SAP_Speadsheet!G$5,Leadsheet!$C$18:$F$19,4,1)) -> 0.059930813 | H12: =IF(H$5>$D$7,0,VLOOKUP(SAP_Speadsheet!H$5,Leadsheet!$C$18:$F$19,4,1)) -> 0.059930813 | I12: =IF(I$5>$D$7,0,VLOOKUP(SAP_Speadsheet!I$5,Leadsheet!$C$18:$F$19,4,1)) -> 0.059930813 | J12: =IF(J$5>$D$7,0,VLOOKUP(SAP_Speadsheet!J$5,Leadsheet!$C$18:$F$19,4,1)) -> 0.059930813 | K12: =IF(K$5>$D$7,0,VLOOKUP(SAP_Speadsheet!K$5,Leadsheet!$C$18:$F$19,4,1)) -> 0.059930813 | L12: =IF(L$5>$D$7,0,VLOOKUP(SAP_Speadsheet!L$5,Leadsheet!$C$18:$F$19,4,1)) -> 0 | ... BL12: =IF(BL$5>$D$7,0,VLOOKUP(SAP_Speadsheet!BL$5,Leadsheet!$C$18:$F$19,4,1)) -> 0
C13: Prepayment Penalty | E13: =IF(E$5<Leadsheet!$E$12,VLOOKUP(SAP_Speadsheet!E$5,Leadsheet!#REF!,3,1),0) -> 0 | F13: =IF(F$5<Leadsheet!$E$12,VLOOKUP(SAP_Speadsheet!F$5,Leadsheet!#REF!,3,1),0) -> 0 | G13: =IF(G$5<Leadsheet!$E$12,VLOOKUP(SAP_Speadsheet!G$5,Leadsheet!#REF!,3,1),0) -> 0 | H13: =IF(H$5<Leadsheet!$E$12,VLOOKUP(SAP_Speadsheet!H$5,Leadsheet!#REF!,3,1),0) -> 0 | I13: =IF(I$5<Leadsheet!$E$12,VLOOKUP(SAP_Speadsheet!I$5,Leadsheet!#REF!,3,1),0) -> 0 | J13: =IF(J$5<Leadsheet!$E$12,VLOOKUP(SAP_Speadsheet!J$5,Leadsheet!#REF!,3,1),0) -> 0 | K13: =IF(K$5<Leadsheet!$E$12,VLOOKUP(SAP_Speadsheet!K$5,Leadsheet!#REF!,3,1),0) -> 0 | L13: =IF(L$5<Leadsheet!$E$12,VLOOKUP(SAP_Speadsheet!L$5,Leadsheet!#REF!,3,1),0) -> 0 | ... BL13: =IF(BL$5<Leadsheet!$E$12,VLOOKUP(SAP_Speadsheet!BL$5,Leadsheet!#REF!,3,1),0) -> 0
B15: EMI | C15: Account accumulated | D15: 1 | E15: =IF(E5>$D$7,0,D15) -> 1 | F15: =IF(F5>$D$7,0,E15) -> 1 | G15: =IF(G5>$D$7,0,F15) -> 1 | H15: =IF(H5>$D$7,0,G15) -> 1 | I15: =IF(I5>$D$7,0,H15) -> 1 | J15: =IF(J5>$D$7,0,I15) -> 1 | K15: =IF(K5>$D$7,0,J15) -> 1 | L15: =IF(L5>$D$7,0,K15) -> 0 | ... BL15: =IF(BL5>$D$7,0,BK15) -> 0
C16: Nominal ENR | D16: =Leadsheet!E10 -> 3.5358329 | E16: =IF(E$5>Leadsheet!$E$12,0,D16+E19) -> -4.4408921e-16 | F16: =IF(F$5>Leadsheet!$E$12,0,E16+F19) -> 0 | G16: =IF(G$5>Leadsheet!$E$12,0,F16+G19) -> 0 | H16: =IF(H$5>Leadsheet!$E$12,0,G16+H19) -> 0 | I16: =IF(I$5>Leadsheet!$E$12,0,H16+I19) -> 0 | J16: =IF(J$5>Leadsheet!$E$12,0,I16+J19) -> 0 | K16: =IF(K$5>Leadsheet!$E$12,0,J16+K19) -> 0 | L16: =IF(L$5>Leadsheet!$E$12,0,K16+L19) -> 0 | ... BL16: =IF(BL$5>Leadsheet!$E$12,0,BK16+BL19) -> 0
C17: EMI payment | E17: =-IFERROR(PMT(D11/12,D6,-D16),0) -> -3.7032689 | F17: =-IFERROR(PMT(E11/12,E6,-E16),0) -> 0 | G17: =-IFERROR(PMT(F11/12,F6,-F16),0) -> 0 | H17: =-IFERROR(PMT(G11/12,G6,-G16),0) -> 0 | I17: =-IFERROR(PMT(H11/12,H6,-H16),0) -> 0 | J17: =-IFERROR(PMT(I11/12,I6,-I16),0) -> 0 | K17: =-IFERROR(PMT(J11/12,J6,-J16),0) -> 0 | L17: =-IFERROR(PMT(K11/12,K6,-K16),0) -> 0 | ... BL17: =-IFERROR(PMT(BK11/12,BK6,-BK16),0) -> 0
C18: Nominal Interest | E18: =-IF(E5>$D$6,0,D16*D11/12) -> -0.16743597 | F18: =-IF(F5>$D$6,0,E16*E11/12) -> 0 | G18: =-IF(G5>$D$6,0,F16*F11/12) -> 0 | H18: =-IF(H5>$D$6,0,G16*G11/12) -> 0 | I18: =-IF(I5>$D$6,0,H16*H11/12) -> 0 | J18: =-IF(J5>$D$6,0,I16*I11/12) -> 0 | K18: =-IF(K5>$D$6,0,J16*J11/12) -> 0 | L18: =-IF(L5>$D$6,0,K16*K11/12) -> 0 | ... BL18: =-IF(BL5>$D$6,0,BK16*BK11/12) -> 0
C19: Nominal Payment | E19: =E17-E18 -> -3.5358329 | F19: =F17-F18 -> 0 | G19: =G17-G18 -> 0 | H19: =H17-H18 -> 0 | I19: =I17-I18 -> 0 | J19: =J17-J18 -> 0 | K19: =K17-K18 -> 0 | L19: =L17-L18 -> 0 | ... BL19: =BL17-BL18 -> 0
C22: Schedule Payment | E22: =IF(E5>Leadsheet!$E$12,0,IFERROR(E19/D16*D25*(1-Leadsheet!$D$76),0)) -> -3.2741813 | F22: =IF(F5>Leadsheet!$E$12,0,IFERROR(F19/E16*E25*(1-Leadsheet!$D$76),0)) -> 0 | G22: =IF(G5>Leadsheet!$E$12,0,IFERROR(G19/F16*F25*(1-Leadsheet!$D$76),0)) -> 0 | H22: =IF(H5>Leadsheet!$E$12,0,IFERROR(H19/G16*G25*(1-Leadsheet!$D$76),0)) -> 0 | I22: =IF(I5>Leadsheet!$E$12,0,IFERROR(I19/H16*H25*(1-Leadsheet!$D$76),0)) -> 0 | J22: =IF(J5>Leadsheet!$E$12,0,IFERROR(J19/I16*I25*(1-Leadsheet!$D$76),0)) -> 0 | K22: =IF(K5>Leadsheet!$E$12,0,IFERROR(K19/J16*J25*(1-Leadsheet!$D$76),0)) -> 0 | L22: =IF(L5>Leadsheet!$E$12,0,IFERROR(L19/K16*K25*(1-Leadsheet!$D$76),0)) -> 0 | ... BL22: =IF(BL5>Leadsheet!$E$12,0,IFERROR(BL19/BK16*BK25*(1-Leadsheet!$D$76),0)) -> 0
A24: SBV | B24: Overdue | C24: Balance by Bucket/Group
A25: G1 | B25: 0 | C25: B0 | D25: =Leadsheet!E10 -> 3.5358329 | E25: =IF(E5>=Leadsheet!$E$12,0,D42+E22-SUM(E26:E39)) -> 0 | F25: =IF(F5>=Leadsheet!$E$12,0,E42+F22-SUM(F26:F39)) -> 0 | G25: =IF(G5>=Leadsheet!$E$12,0,F42+G22-SUM(G26:G39)) -> 0 | H25: =IF(H5>=Leadsheet!$E$12,0,G42+H22-SUM(H26:H39)) -> 0 | I25: =IF(I5>=Leadsheet!$E$12,0,H42+I22-SUM(I26:I39)) -> 0 | J25: =IF(J5>=Leadsheet!$E$12,0,I42+J22-SUM(J26:J39)) -> 0 | K25: =IF(K5>=Leadsheet!$E$12,0,J42+K22-SUM(K26:K39)) -> 0 | L25: =IF(L5>=Leadsheet!$E$12,0,K42+L22-SUM(L26:L39)) -> 0 | ... BL25: =IF(BL5>=Leadsheet!$E$12,0,BK42+BL22-SUM(BL26:BL39)) -> 0
A26: G2 | B26: 30 | C26: B1 | E26: =IF(E$5>$D$7,0,D25*Leadsheet!$D76) -> 0.26165163 | F26: =IF(F$5>$D$7,0,E25*Leadsheet!$D76) -> 0 | G26: =IF(G$5>$D$7,0,F25*Leadsheet!$D76) -> 0 | H26: =IF(H$5>$D$7,0,G25*Leadsheet!$D76) -> 0 | I26: =IF(I$5>$D$7,0,H25*Leadsheet!$D76) -> 0 | J26: =IF(J$5>$D$7,0,I25*Leadsheet!$D76) -> 0 | K26: =IF(K$5>$D$7,0,J25*Leadsheet!$D76) -> 0 | L26: =IF(L$5>$D$7,0,K25*Leadsheet!$D76) -> 0 | ... BL26: =IF(BL$5>$D$7,0,BK25*Leadsheet!$D76) -> 0
A27: G2 | B27: 60 | C27: B2 | E27: =IF(E$5>$D$7,0,D26*Leadsheet!$D77) -> 0 | F27: =IF(F$5>$D$7,0,E26*Leadsheet!$D77) -> 0.20801305 | G27: =IF(G$5>$D$7,0,F26*Leadsheet!$D77) -> 0 | H27: =IF(H$5>$D$7,0,G26*Leadsheet!$D77) -> 0 | I27: =IF(I$5>$D$7,0,H26*Leadsheet!$D77) -> 0 | J27: =IF(J$5>$D$7,0,I26*Leadsheet!$D77) -> 0 | K27: =IF(K$5>$D$7,0,J26*Leadsheet!$D77) -> 0 | L27: =IF(L$5>$D$7,0,K26*Leadsheet!$D77) -> 0 | ... BL27: =IF(BL$5>$D$7,0,BK26*Leadsheet!$D77) -> 0
A28: G2 | B28: 90 | C28: B3 | E28: =IF(E$5>$D$7,0,D27*Leadsheet!$D78) -> 0 | F28: =IF(F$5>$D$7,0,E27*Leadsheet!$D78) -> 0 | G28: =IF(G$5>$D$7,0,F27*Leadsheet!$D78) -> 0.19787875 | H28: =IF(H$5>$D$7,0,G27*Leadsheet!$D78) -> 0 | I28: =IF(I$5>$D$7,0,H27*Leadsheet!$D78) -> 0 | J28: =IF(J$5>$D$7,0,I27*Leadsheet!$D78) -> 0 | K28: =IF(K$5>$D$7,0,J27*Leadsheet!$D78) -> 0 | L28: =IF(L$5>$D$7,0,K27*Leadsheet!$D78) -> 0 | ... AU28: =IF(AU$5>$D$7,0,AT27*Leadsheet!$D78) -> 0 | AV28: 0 | AW28: =IF(AW$5>$D$7,0,AV27*Leadsheet!$D78) -> 0 | AX28: =IF(AX$5>$D$7,0,AW27*Leadsheet!$D78) -> 0 | AY28: =IF(AY$5>$D$7,0,AX27*Leadsheet!$D78) -> 0 | AZ28: =IF(AZ$5>$D$7,0,AY27*Leadsheet!$D78) -> 0 | BA28: =IF(BA$5>$D$7,0,AZ27*Leadsheet!$D78) -> 0 | BB28: =IF(BB$5>$D$7,0,BA27*Leadsheet!$D78) -> 0 | BC28: =IF(BC$5>$D$7,0,BB27*Leadsheet!$D78) -> 0 | BD28: =IF(BD$5>$D$7,0,BC27*Leadsheet!$D78) -> 0 | ... BL28: =IF(BL$5>$D$7,0,BK27*Leadsheet!$D78) -> 0
A29: G3 | B29: 120 | C29: B4 | E29: =IF(E$5>$D$7,0,D28*Leadsheet!$D79) -> 0 | F29: =IF(F$5>$D$7,0,E28*Leadsheet!$D79) -> 0 | G29: =IF(G$5>$D$7,0,F28*Leadsheet!$D79) -> 0 | H29: =IF(H$5>$D$7,0,G28*Leadsheet!$D79) -> 0.1931738 | I29: =IF(I$5>$D$7,0,H28*Leadsheet!$D79) -> 0 | J29: =IF(J$5>$D$7,0,I28*Leadsheet!$D79) -> 0 | K29: =IF(K$5>$D$7,0,J28*Leadsheet!$D79) -> 0 | L29: =IF(L$5>$D$7,0,K28*Leadsheet!$D79) -> 0 | ... BL29: =IF(BL$5>$D$7,0,BK28*Leadsheet!$D79) -> 0
A30: G3 | B30: 150 | C30: B5 | E30: =IF(E$5>$D$7,0,D29*Leadsheet!$D80) -> 0 | F30: =IF(F$5>$D$7,0,E29*Leadsheet!$D80) -> 0 | G30: =IF(G$5>$D$7,0,F29*Leadsheet!$D80) -> 0 | H30: =IF(H$5>$D$7,0,G29*Leadsheet!$D80) -> 0 | I30: =IF(I$5>$D$7,0,H29*Leadsheet!$D80) -> 0.19113371 | J30: =IF(J$5>$D$7,0,I29*Leadsheet!$D80) -> 0 | K30: =IF(K$5>$D$7,0,J29*Leadsheet!$D80) -> 0 | L30: =IF(L$5>$D$7,0,K29*Leadsheet!$D80) -> 0 | ... BL30: =IF(BL$5>$D$7,0,BK29*Leadsheet!$D80) -> 0
A31: G3 | B31: 180 | C31: B6 | E31: =IF(E$5>$D$7,0,D30*Leadsheet!$D81) -> 0 | F31: =IF(F$5>$D$7,0,E30*Leadsheet!$D81) -> 0 | G31: =IF(G$5>$D$7,0,F30*Leadsheet!$D81) -> 0 | H31: =IF(H$5>$D$7,0,G30*Leadsheet!$D81) -> 0 | I31: =IF(I$5>$D$7,0,H30*Leadsheet!$D81) -> 0 | J31: =IF(J$5>$D$7,0,I30*Leadsheet!$D81) -> 0.18922237 | K31: =IF(K$5>$D$7,0,J30*Leadsheet!$D81) -> 0 | L31: =IF(L$5>$D$7,0,K30*Leadsheet!$D81) -> 0 | ... BL31: =IF(BL$5>$D$7,0,BK30*Leadsheet!$D81) -> 0
A32: G4 | B32: 210 | C32: B7 | E32: =IF(E$5>$D$7,0,D31*Leadsheet!$D82) -> 0 | F32: =IF(F$5>$D$7,0,E31*Leadsheet!$D82) -> 0 | G32: =IF(G$5>$D$7,0,F31*Leadsheet!$D82) -> 0 | H32: =IF(H$5>$D$7,0,G31*Leadsheet!$D82) -> 0 | I32: =IF(I$5>$D$7,0,H31*Leadsheet!$D82) -> 0 | J32: =IF(J$5>$D$7,0,I31*Leadsheet!$D82) -> 0 | K32: =IF(K$5>$D$7,0,J31*Leadsheet!$D82) -> 0.18770859 | L32: =IF(L$5>$D$7,0,K31*Leadsheet!$D82) -> 0 | ... BL32: =IF(BL$5>$D$7,0,BK31*Leadsheet!$D82) -> 0
A33: G4 | B33: 240 | C33: B8 | E33: =IF(E$5>$D$7,0,D32*Leadsheet!$D83) -> 0 | F33: =IF(F$5>$D$7,0,E32*Leadsheet!$D83) -> 0 | G33: =IF(G$5>$D$7,0,F32*Leadsheet!$D83) -> 0 | H33: =IF(H$5>$D$7,0,G32*Leadsheet!$D83) -> 0 | I33: =IF(I$5>$D$7,0,H32*Leadsheet!$D83) -> 0 | J33: =IF(J$5>$D$7,0,I32*Leadsheet!$D83) -> 0 | K33: =IF(K$5>$D$7,0,J32*Leadsheet!$D83) -> 0 | L33: =IF(L$5>$D$7,0,K32*Leadsheet!$D83) -> 0 | ... BL33: =IF(BL$5>$D$7,0,BK32*Leadsheet!$D83) -> 0
A34: G4 | B34: 270 | C34: B9 | E34: =IF(E$5>$D$7,0,D33*Leadsheet!$D84) -> 0 | F34: =IF(F$5>$D$7,0,E33*Leadsheet!$D84) -> 0 | G34: =IF(G$5>$D$7,0,F33*Leadsheet!$D84) -> 0 | H34: =IF(H$5>$D$7,0,G33*Leadsheet!$D84) -> 0 | I34: =IF(I$5>$D$7,0,H33*Leadsheet!$D84) -> 0 | J34: =IF(J$5>$D$7,0,I33*Leadsheet!$D84) -> 0 | K34: =IF(K$5>$D$7,0,J33*Leadsheet!$D84) -> 0 | L34: =IF(L$5>$D$7,0,K33*Leadsheet!$D84) -> 0 | ... BL34: =IF(BL$5>$D$7,0,BK33*Leadsheet!$D84) -> 0
A35: G4 | B35: 300 | C35: B10 | E35: =IF(E$5>$D$7,0,D34*Leadsheet!$D85) -> 0 | F35: =IF(F$5>$D$7,0,E34*Leadsheet!$D85) -> 0 | G35: =IF(G$5>$D$7,0,F34*Leadsheet!$D85) -> 0 | H35: =IF(H$5>$D$7,0,G34*Leadsheet!$D85) -> 0 | I35: =IF(I$5>$D$7,0,H34*Leadsheet!$D85) -> 0 | J35: =IF(J$5>$D$7,0,I34*Leadsheet!$D85) -> 0 | K35: =IF(K$5>$D$7,0,J34*Leadsheet!$D85) -> 0 | L35: =IF(L$5>$D$7,0,K34*Leadsheet!$D85) -> 0 | ... BL35: =IF(BL$5>$D$7,0,BK34*Leadsheet!$D85) -> 0
A36: G4 | B36: 330 | C36: B11 | E36: =IF(E$5>$D$7,0,D35*Leadsheet!$D86) -> 0 | F36: =IF(F$5>$D$7,0,E35*Leadsheet!$D86) -> 0 | G36: =IF(G$5>$D$7,0,F35*Leadsheet!$D86) -> 0 | H36: =IF(H$5>$D$7,0,G35*Leadsheet!$D86) -> 0 | I36: =IF(I$5>$D$7,0,H35*Leadsheet!$D86) -> 0 | J36: =IF(J$5>$D$7,0,I35*Leadsheet!$D86) -> 0 | K36: =IF(K$5>$D$7,0,J35*Leadsheet!$D86) -> 0 | L36: =IF(L$5>$D$7,0,K35*Leadsheet!$D86) -> 0 | ... BL36: =IF(BL$5>$D$7,0,BK35*Leadsheet!$D86) -> 0
A37: G4 | B37: 360 | C37: B12 | E37: =IF(E$5>$D$7,0,D36*Leadsheet!$D87) -> 0 | F37: =IF(F$5>$D$7,0,E36*Leadsheet!$D87) -> 0 | G37: =IF(G$5>$D$7,0,F36*Leadsheet!$D87) -> 0 | H37: =IF(H$5>$D$7,0,G36*Leadsheet!$D87) -> 0 | I37: =IF(I$5>$D$7,0,H36*Leadsheet!$D87) -> 0 | J37: =IF(J$5>$D$7,0,I36*Leadsheet!$D87) -> 0 | K37: =IF(K$5>$D$7,0,J36*Leadsheet!$D87) -> 0 | L37: =IF(L$5>$D$7,0,K36*Leadsheet!$D87) -> 0 | ... BL37: =IF(BL$5>$D$7,0,BK36*Leadsheet!$D87) -> 0
A38: G5 | B38: 390 | C38: B13 | E38: =IF(E$5>$D$7,0,D37*Leadsheet!$D88) -> 0 | F38: =IF(F$5>$D$7,0,E37*Leadsheet!$D88) -> 0 | G38: =IF(G$5>$D$7,0,F37*Leadsheet!$D88) -> 0 | H38: =IF(H$5>$D$7,0,G37*Leadsheet!$D88) -> 0 | I38: =IF(I$5>$D$7,0,H37*Leadsheet!$D88) -> 0 | J38: =IF(J$5>$D$7,0,I37*Leadsheet!$D88) -> 0 | K38: =IF(K$5>$D$7,0,J37*Leadsheet!$D88) -> 0 | L38: =IF(L$5>$D$7,0,K37*Leadsheet!$D88) -> 0 | ... BL38: =IF(BL$5>$D$7,0,BK37*Leadsheet!$D88) -> 0
A39: G5 | B39: 420+ | C39: B14+ | E39: =IF(E5>$D$7,0,D38+D39) -> 0 | F39: =IF(F5>$D$7,0,E38+E39) -> 0 | G39: =IF(G5>$D$7,0,F38+F39) -> 0 | H39: =IF(H5>$D$7,0,G38+G39) -> 0 | I39: =IF(I5>$D$7,0,H38+H39) -> 0 | J39: =IF(J5>$D$7,0,I38+I39) -> 0 | K39: =IF(K5>$D$7,0,J38+J39) -> 0 | L39: =IF(L5>$D$7,0,K38+K39) -> 0 | ... BL39: =IF(BL5>$D$7,0,BK38+BK39) -> 0
B41: ENR
C42: Total bank | D42: =SUM(D25:D39) -> 3.5358329 | E42: =SUM(E25:E39) -> 0.26165163 | F42: =SUM(F25:F39) -> 0.20801305 | G42: =SUM(G25:G39) -> 0.19787875 | H42: =SUM(H25:H39) -> 0.1931738 | I42: =SUM(I25:I39) -> 0.19113371 | J42: =SUM(J25:J39) -> 0.18922237 | K42: =SUM(K25:K39) -> 0.18770859 | ... BL42: =SUM(BL25:BL39) -> 0
C43: Outstanding balance | D43: {=IF(D5=$D$7,0,_xlfn.IFS(Leadsheet!$G$5="DPD360+",SUM(SAP_Speadsheet!D25:D38),Leadsheet!$G$5="DPD180+",SUM(SAP_Speadsheet!D25:D32)))} -> 3.5358329 | E43: {=IF(E5=$D$7,0,_xlfn.IFS(Leadsheet!$G$5="DPD360+",SUM(SAP_Speadsheet!E25:E38),Leadsheet!$G$5="DPD180+",SUM(SAP_Speadsheet!E25:E32)))} -> 0.26165163 | F43: {=IF(F5=$D$7,0,_xlfn.IFS(Leadsheet!$G$5="DPD360+",SUM(SAP_Speadsheet!F25:F38),Leadsheet!$G$5="DPD180+",SUM(SAP_Speadsheet!F25:F32)))} -> 0.20801305 | G43: {=IF(G5=$D$7,0,_xlfn.IFS(Leadsheet!$G$5="DPD360+",SUM(SAP_Speadsheet!G25:G38),Leadsheet!$G$5="DPD180+",SUM(SAP_Speadsheet!G25:G32)))} -> 0.19787875 | H43: {=IF(H5=$D$7,0,_xlfn.IFS(Leadsheet!$G$5="DPD360+",SUM(SAP_Speadsheet!H25:H38),Leadsheet!$G$5="DPD180+",SUM(SAP_Speadsheet!H25:H32)))} -> 0.1931738 | I43: {=IF(I5=$D$7,0,_xlfn.IFS(Leadsheet!$G$5="DPD360+",SUM(SAP_Speadsheet!I25:I38),Leadsheet!$G$5="DPD180+",SUM(SAP_Speadsheet!I25:I32)))} -> 0.19113371 | J43: {=IF(J5=$D$7,0,_xlfn.IFS(Leadsheet!$G$5="DPD360+",SUM(SAP_Speadsheet!J25:J38),Leadsheet!$G$5="DPD180+",SUM(SAP_Speadsheet!J25:J32)))} -> 0.18922237 | K43: {=IF(K5=$D$7,0,_xlfn.IFS(Leadsheet!$G$5="DPD360+",SUM(SAP_Speadsheet!K25:K38),Leadsheet!$G$5="DPD180+",SUM(SAP_Speadsheet!K25:K32)))} -> 0 | ... BL43: {=IF(BL5=$D$7,0,_xlfn.IFS(Leadsheet!$G$5="DPD360+",SUM(SAP_Speadsheet!BL25:BL38),Leadsheet!$G$5="DPD180+",SUM(SAP_Speadsheet!BL25:BL32)))} -> 0
C44: Writeoff balance | D44: =D42-D43 -> 0 | E44: =E42-E43 -> 0 | F44: =F42-F43 -> 0 | G44: =G42-G43 -> 0 | H44: =H42-H43 -> 0 | I44: =I42-I43 -> 0 | J44: =J42-J43 -> 0 | K44: =K42-K43 -> 0.18770859 | ... BL44: =BL42-BL43 -> 0
C45: Outstanding Bal/TB | D45: =IFERROR(D43/D42,"") -> 1 | E45: =IFERROR(E43/E42,"") -> 1 | F45: =IFERROR(F43/F42,"") -> 1 | G45: =IFERROR(G43/G42,"") -> 1 | H45: =IFERROR(H43/H42,"") -> 1 | I45: =IFERROR(I43/I42,"") -> 1 | J45: =IFERROR(J43/J42,"") -> 1 | K45: =IFERROR(K43/K42,"") -> 0 | ... BL45: =IFERROR(BL43/BL42,"")
B47: ANR
C48: Outstanding balance | E48: =IF(E5>$D$7,0,AVERAGE(D43:E43)) -> 1.8987423 | F48: =IF(F5>$D$7,0,AVERAGE(E43:F43)) -> 0.23483234 | G48: =IF(G5>$D$7,0,AVERAGE(F43:G43)) -> 0.2029459 | H48: =IF(H5>$D$7,0,AVERAGE(G43:H43)) -> 0.19552628 | I48: =IF(I5>$D$7,0,AVERAGE(H43:I43)) -> 0.19215376 | J48: =IF(J5>$D$7,0,AVERAGE(I43:J43)) -> 0.19017804 | K48: =IF(K5>$D$7,0,AVERAGE(J43:K43)) -> 0.094611187 | L48: =IF(L5>$D$7,0,AVERAGE(K43:L43)) -> 0 | ... BL48: =IF(BL5>$D$7,0,AVERAGE(BK43:BL43)) -> 0
C49: ANR for CII (B0+B1A) | E49: =D25*(1-Leadsheet!$D$76)+D26*Leadsheet!$E$100 -> 3.2741813 | F49: =E25*(1-Leadsheet!$D$76)+E26*Leadsheet!$E$100 -> 0.053638585 | G49: =F25*(1-Leadsheet!$D$76)+F26*Leadsheet!$E$100 -> 0 | H49: =G25*(1-Leadsheet!$D$76)+G26*Leadsheet!$E$100 -> 0 | I49: =H25*(1-Leadsheet!$D$76)+H26*Leadsheet!$E$100 -> 0 | J49: =I25*(1-Leadsheet!$D$76)+I26*Leadsheet!$E$100 -> 0 | K49: =J25*(1-Leadsheet!$D$76)+J26*Leadsheet!$E$100 -> 0 | L49: =K25*(1-Leadsheet!$D$76)+K26*Leadsheet!$E$100 -> 0 | ... BL49: =BK25*(1-Leadsheet!$D$76)+BK26*Leadsheet!$E$100 -> 0
B51: Performance
B53: TOI | E53: =E55+E59+E63 -> 0.36976012 | F53: =F55+F59+F63 -> 0.0013671959 | G53: =G55+G59+G63 -> -0.0010135594 | H53: =H55+H59+H63 -> -0.00097650407 | I53: =I55+I59+I63 -> -0.0009596609 | J53: =J55+J59+J63 -> -0.00094979373 | K53: =K55+K59+K63 -> -0.00047251045 | L53: =L55+L59+L63 -> 0 | ... BL53: =BL55+BL59+BL63 -> 0
C55: Net interest income | E55: =E56+E57 -> 0.14556295 | F55: =F56+F57 -> 0.0013671959 | G55: =G56+G57 -> -0.0010135594 | H55: =H56+H57 -> -0.00097650407 | I55: =I56+I57 -> -0.0009596609 | J55: =J56+J57 -> -0.00094979373 | K55: =K56+K57 -> -0.00047251045 | L55: =L56+L57 -> 0 | ... BL55: =BL56+BL57 -> 0
C56: Interest income | E56: =IFERROR(E$49*D$11/12,0) -> 0.15504571 | F56: =IFERROR(F$49*E$11/12,0) -> 0.0025400037 | G56: =IFERROR(G$49*F$11/12,0) -> 0 | H56: =IFERROR(H$49*G$11/12,0) -> 0 | I56: =IFERROR(I$49*H$11/12,0) -> 0 | J56: =IFERROR(J$49*I$11/12,0) -> 0 | K56: =IFERROR(K$49*J$11/12,0) -> 0 | L56: =IFERROR(L$49*K$11/12,0) -> 0 | ... BL56: =IFERROR(BL$49*BK$11/12,0) -> 0
C57: Cost of fund | E57: =-IFERROR(E48*D12/12,0) -> -0.009482764 | F57: =-IFERROR(F48*E12/12,0) -> -0.0011728078 | G57: =-IFERROR(G48*F12/12,0) -> -0.0010135594 | H57: =-IFERROR(H48*G12/12,0) -> -0.00097650407 | I57: =-IFERROR(I48*H12/12,0) -> -0.0009596609 | J57: =-IFERROR(J48*I12/12,0) -> -0.00094979373 | K57: =-IFERROR(K48*J12/12,0) -> -0.00047251045 | L57: =-IFERROR(L48*K12/12,0) -> 0 | ... BL57: =-IFERROR(BL48*BK12/12,0) -> 0
C59: Net fee income | E59: =SUM(E60:E61) -> 0.22419717 | F59: =SUM(F60:F62) -> 0 | G59: =SUM(G60:G62) -> 0 | H59: =SUM(H60:H62) -> 0 | I59: =SUM(I60:I62) -> 0 | J59: =SUM(J60:J62) -> 0 | K59: =SUM(K60:K62) -> 0 | L59: =SUM(L60:L62) -> 0 | M59: =SUM(M60:M62) -> 0 | ... BL59: =SUM(BL60:BL62) -> 0
C60: Insurrance fee | E60: =Leadsheet!E10*Leadsheet!E21*Leadsheet!E23*Leadsheet!E24+Leadsheet!E10/(1+Leadsheet!E22*Leadsheet!E23)*Leadsheet!E22*Leadsheet!E23*Leadsheet!E24 -> 0.22419717
C61: Support fee | E61: =Leadsheet!E10*Leadsheet!E27+Leadsheet!E26 -> 0
B63: Other Income | E63: {=IF(E5=$D$7,_xlfn.IFS(Leadsheet!$G$4="IFRS",0,Leadsheet!$G$5="DPD180+",(E172-E137)*(1+Leadsheet!$E$102),Leadsheet!$G$5="DPD360+",(E157-E137)*(1+Leadsheet!$E$102)),0)} -> 0 | F63: {=IF(F5=$D$7,_xlfn.IFS(Leadsheet!$G$4="IFRS",0,Leadsheet!$G$5="DPD180+",(F172-F137)*(1+Leadsheet!$E$102),Leadsheet!$G$5="DPD360+",(F157-F137)*(1+Leadsheet!$E$102)),0)} -> 0 | G63: {=IF(G5=$D$7,_xlfn.IFS(Leadsheet!$G$4="IFRS",0,Leadsheet!$G$5="DPD180+",(G172-G137)*(1+Leadsheet!$E$102),Leadsheet!$G$5="DPD360+",(G157-G137)*(1+Leadsheet!$E$102)),0)} -> 0 | H63: {=IF(H5=$D$7,_xlfn.IFS(Leadsheet!$G$4="IFRS",0,Leadsheet!$G$5="DPD180+",(H172-H137)*(1+Leadsheet!$E$102),Leadsheet!$G$5="DPD360+",(H157-H137)*(1+Leadsheet!$E$102)),0)} -> 0 | I63: {=IF(I5=$D$7,_xlfn.IFS(Leadsheet!$G$4="IFRS",0,Leadsheet!$G$5="DPD180+",(I172-I137)*(1+Leadsheet!$E$102),Leadsheet!$G$5="DPD360+",(I157-I137)*(1+Leadsheet!$E$102)),0)} -> 0 | J63: {=IF(J5=$D$7,_xlfn.IFS(Leadsheet!$G$4="IFRS",0,Leadsheet!$G$5="DPD180+",(J172-J137)*(1+Leadsheet!$E$102),Leadsheet!$G$5="DPD360+",(J157-J137)*(1+Leadsheet!$E$102)),0)} -> 0 | K63: {=IF(K5=$D$7,_xlfn.IFS(Leadsheet!$G$4="IFRS",0,Leadsheet!$G$5="DPD180+",(K172-K137)*(1+Leadsheet!$E$102),Leadsheet!$G$5="DPD360+",(K157-K137)*(1+Leadsheet!$E$102)),0)} -> 0 | L63: {=IF(L5=$D$7,_xlfn.IFS(Leadsheet!$G$4="IFRS",0,Leadsheet!$G$5="DPD180+",(L172-L137)*(1+Leadsheet!$E$102),Leadsheet!$G$5="DPD360+",(L157-L137)*(1+Leadsheet!$E$102)),0)} -> 0 | ... AB63: {=IF(AB5=$D$7,_xlfn.IFS(Leadsheet!$G$4="IFRS",0,Leadsheet!$G$5="DPD180+",(AB172-AB137)*(1+Leadsheet!$E$102),Leadsheet!$G$5="DPD360+",(AB157-AB137)*(1+Leadsheet!$E$102)),0)} -> 0 | AC63: =IF(AC5>$D$7,0,IF(Leadsheet!$G$5="DPD180+",SUM(SAP_Speadsheet!AB33:AB37)-SUM(SAP_Speadsheet!AC34:AC38),0)) -> 0 | AD63: =IF(AD5>$D$7,0,IF(Leadsheet!$G$5="DPD180+",SUM(SAP_Speadsheet!AC33:AC37)-SUM(SAP_Speadsheet!AD34:AD38),0)) -> 0 | AE63: =IF(AE5>$D$7,0,IF(Leadsheet!$G$5="DPD180+",SUM(SAP_Speadsheet!AD33:AD37)-SUM(SAP_Speadsheet!AE34:AE38),0)) -> 0 | AF63: =IF(AF5>$D$7,0,IF(Leadsheet!$G$5="DPD180+",SUM(SAP_Speadsheet!AE33:AE37)-SUM(SAP_Speadsheet!AF34:AF38),0)) -> 0 | AG63: =IF(AG5>$D$7,0,IF(Leadsheet!$G$5="DPD180+",SUM(SAP_Speadsheet!AF33:AF37)-SUM(SAP_Speadsheet!AG34:AG38),0)) -> 0 | AH63: =IF(AH5>$D$7,0,IF(Leadsheet!$G$5="DPD180+",SUM(SAP_Speadsheet!AG33:AG37)-SUM(SAP_Speadsheet!AH34:AH38),0)) -> 0 | AI63: =IF(AI5>$D$7,0,IF(Leadsheet!$G$5="DPD180+",SUM(SAP_Speadsheet!AH33:AH37)-SUM(SAP_Speadsheet!AI34:AI38),0)) -> 0 | AJ63: =IF(AJ5>$D$7,0,IF(Leadsheet!$G$5="DPD180+",SUM(SAP_Speadsheet!AI33:AI37)-SUM(SAP_Speadsheet!AJ34:AJ38),0)) -> 0 | ... BL63: =IF(BL5>$D$7,0,IF(Leadsheet!$G$5="DPD180+",SUM(SAP_Speadsheet!BK33:BK37)-SUM(SAP_Speadsheet!BL34:BL38),0)) -> 0
B66: VARIABLE EXPENSES | E66: =E67+E77+E80+E87+E91 -> -0.10735064 | F66: =F67+F77+F80+F87+F91 -> -0.00063594899 | G66: =G67+G77+G80+G87+G91 -> -2.6429302e-05 | H66: =H67+H77+H80+H87+H91 -> 0.04826441 | I66: =I67+I77+I80+I87+I91 -> -0.00054038832 | J66: =J67+J77+J80+J87+J91 -> -0.00050796406 | K66: =K67+K77+K80+K87+K91 -> -0.00052575473 | L66: =L67+L77+L80+L87+L91 -> 0 | ... BL66: =BL67+BL77+BL80+BL87+BL91 -> 0
B67: Sale incentive | E67: =E68+E69 -> -0.092440029 | F67: =F68+F69 -> -0.00034179899 | G67: =G68+G69 -> 0.00025338985 | H67: =H68+H69 -> 0.048537576 | I67: =I68+I69 -> -0.00027010729 | J67: =J68+J69 -> -0.00024038584 | K67: =K68+K69 -> -0.00026031713 | L67: =L68+L69 -> 0 | ... BL67: =BL68+BL69 -> 0
C68: Lead Acquistion | E68: =-Leadsheet!E44-Leadsheet!E45*Leadsheet!E10 -> 0
C69: Sharing Performance | E69: =SUM(E70:E76) -> -0.092440029 | F69: =SUM(F70:F76) -> -0.00034179899 | G69: =SUM(G70:G76) -> 0.00025338985 | H69: =SUM(H70:H76) -> 0.048537576 | I69: =SUM(I70:I76) -> -0.00027010729 | J69: =SUM(J70:J76) -> -0.00024038584 | K69: =SUM(K70:K76) -> -0.00026031713 | L69: =SUM(L70:L76) -> 0 | ... BL69: =SUM(BL70:BL76) -> 0
C70: Sharing CII (only) | E70: =-SUM(E56:E56)*Leadsheet!$E$38 -> 0 | F70: =-SUM(F56:F56)*Leadsheet!$E$38 -> 0 | G70: =-SUM(G56:G56)*Leadsheet!$E$38 -> 0 | H70: =-SUM(H56:H56)*Leadsheet!$E$38 -> 0 | I70: =-SUM(I56:I56)*Leadsheet!$E$38 -> 0 | J70: =-SUM(J56:J56)*Leadsheet!$E$38 -> 0 | K70: =-SUM(K56:K56)*Leadsheet!$E$38 -> 0 | L70: =-SUM(L56:L56)*Leadsheet!$E$38 -> 0 | ... BL70: =-SUM(BL56:BL56)*Leadsheet!$E$38 -> 0
C71: Sharing COF (only) | E71: =-E57*Leadsheet!$E$39 -> 0 | F71: =-F57*Leadsheet!$E$39 -> 0 | G71: =-G57*Leadsheet!$E$39 -> 0 | H71: =-H57*Leadsheet!$E$39 -> 0 | I71: =-I57*Leadsheet!$E$39 -> 0 | J71: =-J57*Leadsheet!$E$39 -> 0 | K71: =-K57*Leadsheet!$E$39 -> 0 | L71: =-L57*Leadsheet!$E$39 -> 0 | ... BL71: =-BL57*Leadsheet!$E$39 -> 0
C72: Sharing NFI (only) | E72: =-E59*Leadsheet!$E$40 -> 0 | F72: =-F59*Leadsheet!$E$40 -> 0 | G72: =-G59*Leadsheet!$E$40 -> 0 | H72: =-H59*Leadsheet!$E$40 -> 0 | I72: =-I59*Leadsheet!$E$40 -> 0 | J72: =-J59*Leadsheet!$E$40 -> 0 | K72: =-K59*Leadsheet!$E$40 -> 0 | L72: =-L59*Leadsheet!$E$40 -> 0 | ... BL72: =-BL59*Leadsheet!$E$40 -> 0
C73: Sharing Risk DPD90+ (Only) | E73: =IF(E5>$D$7,0,Leadsheet!$E$41*(E29-SUM(D29:D37)+SUM(E30:E38))) -> 0 | F73: =IF(F5>$D$7,0,Leadsheet!$E$41*(F29-SUM(E29:E37)+SUM(F30:F38))) -> 0 | G73: =IF(G5>$D$7,0,Leadsheet!$E$41*(G29-SUM(F29:F37)+SUM(G30:G38))) -> 0 | H73: =IF(H5>$D$7,0,Leadsheet!$E$41*(H29-SUM(G29:G37)+SUM(H30:H38))) -> 0 | I73: =IF(I5>$D$7,0,Leadsheet!$E$41*(I29-SUM(H29:H37)+SUM(I30:I38))) -> 0 | J73: =IF(J5>$D$7,0,Leadsheet!$E$41*(J29-SUM(I29:I37)+SUM(J30:J38))) -> 0 | K73: =IF(K5>$D$7,0,Leadsheet!$E$41*(K29-SUM(J29:J37)+SUM(K30:K38))) -> 0 | L73: =IF(L5>$D$7,0,Leadsheet!$E$41*(L29-SUM(K29:K37)+SUM(L30:L38))) -> 0 | ... BL73: =IF(BL5>$D$7,0,Leadsheet!$E$41*(BL29-SUM(BK29:BK37)+SUM(BL30:BL38))) -> 0
C74: Sharing Risk DPD180+ (only) | E74: =IF(E5>$D$7,0,Leadsheet!$E$42*(E32+SUM(D32:D37)-SUM(E33:E38))) -> 0 | F74: =IF(F5>$D$7,0,Leadsheet!$E$42*(F32+SUM(E32:E37)-SUM(F33:F38))) -> 0 | G74: =IF(G5>$D$7,0,Leadsheet!$E$42*(G32+SUM(F32:F37)-SUM(G33:G38))) -> 0 | H74: =IF(H5>$D$7,0,Leadsheet!$E$42*(H32+SUM(G32:G37)-SUM(H33:H38))) -> 0 | I74: =IF(I5>$D$7,0,Leadsheet!$E$42*(I32+SUM(H32:H37)-SUM(I33:I38))) -> 0 | J74: =IF(J5>$D$7,0,Leadsheet!$E$42*(J32+SUM(I32:I37)-SUM(J33:J38))) -> 0 | K74: =IF(K5>$D$7,0,Leadsheet!$E$42*(K32+SUM(J32:J37)-SUM(K33:K38))) -> 0 | L74: =IF(L5>$D$7,0,Leadsheet!$E$42*(L32+SUM(K32:K37)-SUM(L33:L38))) -> 0 | ... BL74: =IF(BL5>$D$7,0,Leadsheet!$E$42*(BL32+SUM(BK32:BK37)-SUM(BL33:BL38))) -> 0
C75: Sharing TOI+ Risk DPD90+ | E75: =IF(E5>$D$7,0,Leadsheet!$E$35*(-(E55+E59)+E29-SUM(D29:D37)+SUM(E30:E38))) -> -0.092440029 | F75: =IF(F5>$D$7,0,Leadsheet!$E$35*(-(F55+F59)+F29-SUM(E29:E37)+SUM(F30:F38))) -> -0.00034179899 | G75: =IF(G5>$D$7,0,Leadsheet!$E$35*(-(G55+G59)+G29-SUM(F29:F37)+SUM(G30:G38))) -> 0.00025338985 | H75: =IF(H5>$D$7,0,Leadsheet!$E$35*(-(H55+H59)+H29-SUM(G29:G37)+SUM(H30:H38))) -> 0.048537576 | I75: =IF(I5>$D$7,0,Leadsheet!$E$35*(-(I55+I59)+I29-SUM(H29:H37)+SUM(I30:I38))) -> -0.00027010729 | J75: =IF(J5>$D$7,0,Leadsheet!$E$35*(-(J55+J59)+J29-SUM(I29:I37)+SUM(J30:J38))) -> -0.00024038584 | K75: =IF(K5>$D$7,0,Leadsheet!$E$35*(-(K55+K59)+K29-SUM(J29:J37)+SUM(K30:K38))) -> -0.00026031713 | L75: =IF(L5>$D$7,0,Leadsheet!$E$35*(-(L55+L59)+L29-SUM(K29:K37)+SUM(L30:L38))) -> 0 | ... AB75: =IF(AB5>$D$7,0,Leadsheet!$E$35*(-(AB55+AB59)+AB29-SUM(AA29:AA37)+SUM(AB30:AB38))) -> 0 | AC75: =IF(AC5>$D$7,0,Leadsheet!$E$35*(-AC53+AC29-SUM(AB29:AB37)+SUM(AC30:AC38))) -> 0 | AD75: =IF(AD5>$D$7,0,Leadsheet!$E$35*(-AD53+AD29-SUM(AC29:AC37)+SUM(AD30:AD38))) -> 0 | AE75: =IF(AE5>$D$7,0,Leadsheet!$E$35*(-AE53+AE29-SUM(AD29:AD37)+SUM(AE30:AE38))) -> 0 | AF75: =IF(AF5>$D$7,0,Leadsheet!$E$35*(-AF53+AF29-SUM(AE29:AE37)+SUM(AF30:AF38))) -> 0 | AG75: =IF(AG5>$D$7,0,Leadsheet!$E$35*(-AG53+AG29-SUM(AF29:AF37)+SUM(AG30:AG38))) -> 0 | AH75: =IF(AH5>$D$7,0,Leadsheet!$E$35*(-AH53+AH29-SUM(AG29:AG37)+SUM(AH30:AH38))) -> 0 | AI75: =IF(AI5>$D$7,0,Leadsheet!$E$35*(-AI53+AI29-SUM(AH29:AH37)+SUM(AI30:AI38))) -> 0 | AJ75: =IF(AJ5>$D$7,0,Leadsheet!$E$35*(-AJ53+AJ29-SUM(AI29:AI37)+SUM(AJ30:AJ38))) -> 0 | ... BL75: =IF(BL5>$D$7,0,Leadsheet!$E$35*(-BL53+BL29-SUM(BK29:BK37)+SUM(BL30:BL38))) -> 0
C76: Sharing TOI+ Risk DPD180+ | E76: =IF(E5>$D$7,0,Leadsheet!$E$42*(-(E55+E59)+E32+SUM(D32:D37)-SUM(E33:E38))) -> 0 | F76: =IF(F5>$D$7,0,Leadsheet!$E$42*(-(F55+F59)+F32+SUM(E32:E37)-SUM(F33:F38))) -> 0 | G76: =IF(G5>$D$7,0,Leadsheet!$E$42*(-(G55+G59)+G32+SUM(F32:F37)-SUM(G33:G38))) -> 0 | H76: =IF(H5>$D$7,0,Leadsheet!$E$42*(-(H55+H59)+H32+SUM(G32:G37)-SUM(H33:H38))) -> 0 | I76: =IF(I5>$D$7,0,Leadsheet!$E$42*(-(I55+I59)+I32+SUM(H32:H37)-SUM(I33:I38))) -> 0 | J76: =IF(J5>$D$7,0,Leadsheet!$E$42*(-(J55+J59)+J32+SUM(I32:I37)-SUM(J33:J38))) -> 0 | K76: =IF(K5>$D$7,0,Leadsheet!$E$42*(-(K55+K59)+K32+SUM(J32:J37)-SUM(K33:K38))) -> 0 | L76: =IF(L5>$D$7,0,Leadsheet!$E$42*(-(L55+L59)+L32+SUM(K32:K37)-SUM(L33:L38))) -> 0 | ... AB76: =IF(AB5>$D$7,0,Leadsheet!$E$42*(-(AB55+AB59)+AB32+SUM(AA32:AA37)-SUM(AB33:AB38))) -> 0 | AC76: =IF(AC5>$D$7,0,Leadsheet!$E$42*(-AC53+AC32+SUM(AB32:AB37)-SUM(AC33:AC38))) -> 0 | AD76: =IF(AD5>$D$7,0,Leadsheet!$E$42*(-AD53+AD32+SUM(AC32:AC37)-SUM(AD33:AD38))) -> 0 | AE76: =IF(AE5>$D$7,0,Leadsheet!$E$42*(-AE53+AE32+SUM(AD32:AD37)-SUM(AE33:AE38))) -> 0 | AF76: =IF(AF5>$D$7,0,Leadsheet!$E$42*(-AF53+AF32+SUM(AE32:AE37)-SUM(AF33:AF38))) -> 0 | AG76: =IF(AG5>$D$7,0,Leadsheet!$E$42*(-AG53+AG32+SUM(AF32:AF37)-SUM(AG33:AG38))) -> 0 | AH76: =IF(AH5>$D$7,0,Leadsheet!$E$42*(-AH53+AH32+SUM(AG32:AG37)-SUM(AH33:AH38))) -> 0 | AI76: =IF(AI5>$D$7,0,Leadsheet!$E$42*(-AI53+AI32+SUM(AH32:AH37)-SUM(AI33:AI38))) -> 0 | AJ76: =IF(AJ5>$D$7,0,Leadsheet!$E$42*(-AJ53+AJ32+SUM(AI32:AI37)-SUM(AJ33:AJ38))) -> 0 | ... BL76: =IF(BL5>$D$7,0,Leadsheet!$E$42*(-BL53+BL32+SUM(BK32:BK37)-SUM(BL33:BL38))) -> 0
B77: Marketing | E77: =E78+E62 -> -0.00046334764
C78: Marketing_acquisition | E78: =-Leadsheet!E49 -> -0.00046334764
B80: UW & Disbursal | E80: =E81+E82+E83 -> -0.0090250651
C81: Underwriting Cost | E81: =-Leadsheet!E51/Leadsheet!E54/Leadsheet!E55-Leadsheet!E52 -> -0.0079689063
C82: Disbursement cost | E82: =-Leadsheet!E53 -> -0.0010561588
C83: DOP cost | E83: =-Leadsheet!E52 -> 0
C85: Expense Increase | E85: 1 | F85: =IF(F$5>$D$7,0,IF(F$5<12,1,(1+Leadsheet!$E$31)^(ROUNDDOWN(F$5/12,0)))) -> 1 | G85: =IF(G$5>$D$7,0,IF(G$5<12,1,(1+Leadsheet!$E$31)^(ROUNDDOWN(G$5/12,0)))) -> 1 | H85: =IF(H$5>$D$7,0,IF(H$5<12,1,(1+Leadsheet!$E$31)^(ROUNDDOWN(H$5/12,0)))) -> 1 | I85: =IF(I$5>$D$7,0,IF(I$5<12,1,(1+Leadsheet!$E$31)^(ROUNDDOWN(I$5/12,0)))) -> 1 | J85: =IF(J$5>$D$7,0,IF(J$5<12,1,(1+Leadsheet!$E$31)^(ROUNDDOWN(J$5/12,0)))) -> 1 | K85: =IF(K$5>$D$7,0,IF(K$5<12,1,(1+Leadsheet!$E$31)^(ROUNDDOWN(K$5/12,0)))) -> 1 | L85: =IF(L$5>$D$7,0,IF(L$5<12,1,(1+Leadsheet!$E$31)^(ROUNDDOWN(L$5/12,0)))) -> 0 | M85: =IF(M$5>$D$7,0,IF(M$5<12,1,(1+Leadsheet!$E$31)^(ROUNDDOWN(M$5/12,0)))) -> 0 | ... BL85: =IF(BL$5>$D$7,0,IF(BL$5<12,1,(1+Leadsheet!$E$31)^(ROUNDDOWN(BL$5/12,0)))) -> 0
B87: Collection & AMC | E87: =SUM(E88:E89) -> -0.005 | F87: =SUM(F88:F89) -> -0.00029415 | G87: =SUM(G88:G89) -> -0.00027981915 | H87: =SUM(H88:H89) -> -0.00027316591 | I87: =SUM(I88:I89) -> -0.00027028103 | J87: =SUM(J88:J89) -> -0.00026757822 | K87: =SUM(K88:K89) -> -0.00026543759 | L87: =SUM(L88:L89) -> 0 | ... BL87: =SUM(BL88:BL89) -> 0
C88: Early collections | E88: =-IF(E5>Leadsheet!$E$12,Leadsheet!$E$57*E$85*E42/$D$42,Leadsheet!$E$57*E$85*D15) -> -0.005 | F88: =-IF(F5>Leadsheet!$E$12,Leadsheet!$E$57*F$85*F42/$D$42,Leadsheet!$E$57*F$85*E15) -> -0.00029415 | G88: =-IF(G5>Leadsheet!$E$12,Leadsheet!$E$57*G$85*G42/$D$42,Leadsheet!$E$57*G$85*F15) -> -0.00027981915 | H88: =-IF(H5>Leadsheet!$E$12,Leadsheet!$E$57*H$85*H42/$D$42,Leadsheet!$E$57*H$85*G15) -> -0.00027316591 | I88: =-IF(I5>Leadsheet!$E$12,Leadsheet!$E$57*I$85*I42/$D$42,Leadsheet!$E$57*I$85*H15) -> -0.00027028103 | J88: =-IF(J5>Leadsheet!$E$12,Leadsheet!$E$57*J$85*J42/$D$42,Leadsheet!$E$57*J$85*I15) -> -0.00026757822 | K88: =-IF(K5>Leadsheet!$E$12,Leadsheet!$E$57*K$85*K42/$D$42,Leadsheet!$E$57*K$85*J15) -> -0.00026543759 | L88: =-IF(L5>Leadsheet!$E$12,Leadsheet!$E$57*L$85*L42/$D$42,Leadsheet!$E$57*L$85*K15) -> 0 | ... BL88: =-IF(BL5>Leadsheet!$E$12,Leadsheet!$E$57*BL$85*BL42/$D$42,Leadsheet!$E$57*BL$85*BK15) -> 0
C89: AMC
B91: After sale service | E91: =SUM(E92:E93) -> -0.00042219527 | F91: =SUM(F92:F93) -> 0 | G91: =SUM(G92:G93) -> 0 | H91: =SUM(H92:H93) -> 0 | I91: =SUM(I92:I93) -> 0 | J91: =SUM(J92:J93) -> 0 | K91: =SUM(K92:K93) -> 0 | L91: =SUM(L92:L93) -> 0 | ... BL91: =SUM(BL92:BL93) -> 0
C92: SMS & Email | E92: =IF(E5>Leadsheet!$E$12,0,-E15*Leadsheet!$E$64) -> -0.00042219527 | F92: =IF(F5>Leadsheet!$E$12,0,-F15*Leadsheet!$E$64) -> 0 | G92: =IF(G5>Leadsheet!$E$12,0,-G15*Leadsheet!$E$64) -> 0 | H92: =IF(H5>Leadsheet!$E$12,0,-H15*Leadsheet!$E$64) -> 0 | I92: =IF(I5>Leadsheet!$E$12,0,-I15*Leadsheet!$E$64) -> 0 | J92: =IF(J5>Leadsheet!$E$12,0,-J15*Leadsheet!$E$64) -> 0 | K92: =IF(K5>Leadsheet!$E$12,0,-K15*Leadsheet!$E$64) -> 0 | L92: =IF(L5>Leadsheet!$E$12,0,-L15*Leadsheet!$E$64) -> 0 | ... BL92: =IF(BL5>Leadsheet!$E$12,0,-BL15*Leadsheet!$E$64) -> 0
B95: OVERHEAD EXPENSES | E95: =SUM(E96:E99) -> -0.056791732 | F95: =SUM(F96:F99) -> 0 | G95: =SUM(G96:G99) -> 0 | H95: =SUM(H96:H99) -> 0 | I95: =SUM(I96:I99) -> 0 | J95: =SUM(J96:J99) -> 0 | K95: =SUM(K96:K99) -> 0 | L95: =SUM(L96:L99) -> 0 | ... BL95: =SUM(BL96:BL99) -> 0
C96: Direct HR | E96: =-IF(E$5>Leadsheet!$E$12,0,Leadsheet!$E67*SAP_Speadsheet!E$85*D$15) -> -0.0090772826 | F96: =-IF(F$5>Leadsheet!$E$12,0,Leadsheet!$E67*SAP_Speadsheet!F$85*E$15) -> 0 | G96: =-IF(G$5>Leadsheet!$E$12,0,Leadsheet!$E67*SAP_Speadsheet!G$85*F$15) -> 0 | H96: =-IF(H$5>Leadsheet!$E$12,0,Leadsheet!$E67*SAP_Speadsheet!H$85*G$15) -> 0 | I96: =-IF(I$5>Leadsheet!$E$12,0,Leadsheet!$E67*SAP_Speadsheet!I$85*H$15) -> 0 | J96: =-IF(J$5>Leadsheet!$E$12,0,Leadsheet!$E67*SAP_Speadsheet!J$85*I$15) -> 0 | K96: =-IF(K$5>Leadsheet!$E$12,0,Leadsheet!$E67*SAP_Speadsheet!K$85*J$15) -> 0 | L96: =-IF(L$5>Leadsheet!$E$12,0,Leadsheet!$E67*SAP_Speadsheet!L$85*K$15) -> 0 | ... BL96: =-IF(BL$5>Leadsheet!$E$12,0,Leadsheet!$E67*SAP_Speadsheet!BL$85*BK$15) -> 0
C97: Indirect HR | E97: =-IF(E$5>Leadsheet!$E$12,0,Leadsheet!$E68*SAP_Speadsheet!E$85*D$15) -> -0.02431866 | F97: =-IF(F$5>Leadsheet!$E$12,0,Leadsheet!$E68*SAP_Speadsheet!F$85*E$15) -> 0 | G97: =-IF(G$5>Leadsheet!$E$12,0,Leadsheet!$E68*SAP_Speadsheet!G$85*F$15) -> 0 | H97: =-IF(H$5>Leadsheet!$E$12,0,Leadsheet!$E68*SAP_Speadsheet!H$85*G$15) -> 0 | I97: =-IF(I$5>Leadsheet!$E$12,0,Leadsheet!$E68*SAP_Speadsheet!I$85*H$15) -> 0 | J97: =-IF(J$5>Leadsheet!$E$12,0,Leadsheet!$E68*SAP_Speadsheet!J$85*I$15) -> 0 | K97: =-IF(K$5>Leadsheet!$E$12,0,Leadsheet!$E68*SAP_Speadsheet!K$85*J$15) -> 0 | L97: =-IF(L$5>Leadsheet!$E$12,0,Leadsheet!$E68*SAP_Speadsheet!L$85*K$15) -> 0 | ... BL97: =-IF(BL$5>Leadsheet!$E$12,0,Leadsheet!$E68*SAP_Speadsheet!BL$85*BK$15) -> 0
C98: IT | E98: =-IF(E$5>Leadsheet!$E$12,0,Leadsheet!$E69*SAP_Speadsheet!E$85*D$15) -> -0.011666441 | F98: =-IF(F$5>Leadsheet!$E$12,0,Leadsheet!$E69*SAP_Speadsheet!F$85*E$15) -> 0 | G98: =-IF(G$5>Leadsheet!$E$12,0,Leadsheet!$E69*SAP_Speadsheet!G$85*F$15) -> 0 | H98: =-IF(H$5>Leadsheet!$E$12,0,Leadsheet!$E69*SAP_Speadsheet!H$85*G$15) -> 0 | I98: =-IF(I$5>Leadsheet!$E$12,0,Leadsheet!$E69*SAP_Speadsheet!I$85*H$15) -> 0 | J98: =-IF(J$5>Leadsheet!$E$12,0,Leadsheet!$E69*SAP_Speadsheet!J$85*I$15) -> 0 | K98: =-IF(K$5>Leadsheet!$E$12,0,Leadsheet!$E69*SAP_Speadsheet!K$85*J$15) -> 0 | L98: =-IF(L$5>Leadsheet!$E$12,0,Leadsheet!$E69*SAP_Speadsheet!L$85*K$15) -> 0 | ... BL98: =-IF(BL$5>Leadsheet!$E$12,0,Leadsheet!$E69*SAP_Speadsheet!BL$85*BK$15) -> 0
C99: Other support units | E99: =-IF(E$5>Leadsheet!$E$12,0,Leadsheet!$E70*SAP_Speadsheet!E$85*D$15) -> -0.011729348 | F99: =-IF(F$5>Leadsheet!$E$12,0,Leadsheet!$E70*SAP_Speadsheet!F$85*E$15) -> 0 | G99: =-IF(G$5>Leadsheet!$E$12,0,Leadsheet!$E70*SAP_Speadsheet!G$85*F$15) -> 0 | H99: =-IF(H$5>Leadsheet!$E$12,0,Leadsheet!$E70*SAP_Speadsheet!H$85*G$15) -> 0 | I99: =-IF(I$5>Leadsheet!$E$12,0,Leadsheet!$E70*SAP_Speadsheet!I$85*H$15) -> 0 | J99: =-IF(J$5>Leadsheet!$E$12,0,Leadsheet!$E70*SAP_Speadsheet!J$85*I$15) -> 0 | K99: =-IF(K$5>Leadsheet!$E$12,0,Leadsheet!$E70*SAP_Speadsheet!K$85*J$15) -> 0 | L99: =-IF(L$5>Leadsheet!$E$12,0,Leadsheet!$E70*SAP_Speadsheet!L$85*K$15) -> 0 | ... BL99: =-IF(BL$5>Leadsheet!$E$12,0,Leadsheet!$E70*SAP_Speadsheet!BL$85*BK$15) -> 0
B102: Provision
C103: Provision Rate | E103: IFRS | F103: VAS360 | G103: VAS180
C104: B0 | E104: =Leadsheet!F76 -> 0.049144364 | F104: 0.0075 | G104: 0.0075
C105: B1 | E105: =Leadsheet!F77 -> 0.66411303 | F105: 0.0575 | G105: 0.0575
C106: B2 | E106: =Leadsheet!F78 -> 0.8353623 | F106: 0.0575 | G106: 0.0575
C107: B3 | E107: =Leadsheet!F79 -> 0.8781451 | F107: 0.0575 | G107: 0.0575
C108: B4 | E108: =Leadsheet!F80 -> 0.89953326 | F108: 0.2075 | G108: 0.2075
C109: B5 | E109: =Leadsheet!F81 -> 0.90913454 | F109: 0.2075 | G109: 0.2075
C110: B6 | E110: =Leadsheet!F82 -> 0.91831772 | F110: 0.2075 | G110: 0.2075
C111: B7 | E111: =Leadsheet!F83 -> 0.92572351 | F111: 0.5075 | G111: 0.5075
C112: B8 | E112: =Leadsheet!F84 -> 0.950796 | F112: 0.5075 | G112: 1
C113: B9 | E113: =Leadsheet!F85 -> 0.950796 | F113: 0.5075
C114: B10 | E114: =Leadsheet!F86 -> 0.950796 | F114: 0.5075
C115: B11 | E115: =Leadsheet!F87 -> 0.950796 | F115: 0.5075
C116: B12 | E116: =Leadsheet!F88 -> 0.950796 | F116: 0.5075
C117: B13 | E117: =Leadsheet!F89 -> 0.950796 | F117: 1
C118: B14+ | E118: =Leadsheet!F90 -> 0.9702 | F118: 1
B120: IFRS
C121: Provision cost
C122: B0 | E122: =IF(E$5>$D$7,0,E25*$E104) -> 0 | F122: =IF(F$5>$D$7,0,F25*$E104) -> 0 | G122: =IF(G$5>$D$7,0,G25*$E104) -> 0 | H122: =IF(H$5>$D$7,0,H25*$E104) -> 0 | I122: =IF(I$5>$D$7,0,I25*$E104) -> 0 | J122: =IF(J$5>$D$7,0,J25*$E104) -> 0 | K122: =IF(K$5>$D$7,0,K25*$E104) -> 0 | L122: =IF(L$5>$D$7,0,L25*$E104) -> 0 | ... BL122: =IF(BL$5>$D$7,0,BL25*$E104) -> 0
C123: B1 | E123: =IF(E$5>$D$7,0,E26*$E105) -> 0.17376626 | F123: =IF(F$5>$D$7,0,F26*$E105) -> 0 | G123: =IF(G$5>$D$7,0,G26*$E105) -> 0 | H123: =IF(H$5>$D$7,0,H26*$E105) -> 0 | I123: =IF(I$5>$D$7,0,I26*$E105) -> 0 | J123: =IF(J$5>$D$7,0,J26*$E105) -> 0 | K123: =IF(K$5>$D$7,0,K26*$E105) -> 0 | L123: =IF(L$5>$D$7,0,L26*$E105) -> 0 | ... BL123: =IF(BL$5>$D$7,0,BL26*$E105) -> 0
C124: B2 | E124: =IF(E$5>$D$7,0,E27*$E106) -> 0 | F124: =IF(F$5>$D$7,0,F27*$E106) -> 0.17376626 | G124: =IF(G$5>$D$7,0,G27*$E106) -> 0 | H124: =IF(H$5>$D$7,0,H27*$E106) -> 0 | I124: =IF(I$5>$D$7,0,I27*$E106) -> 0 | J124: =IF(J$5>$D$7,0,J27*$E106) -> 0 | K124: =IF(K$5>$D$7,0,K27*$E106) -> 0 | L124: =IF(L$5>$D$7,0,L27*$E106) -> 0 | ... BL124: =IF(BL$5>$D$7,0,BL27*$E106) -> 0
C125: B3 | E125: =IF(E$5>$D$7,0,E28*$E107) -> 0 | F125: =IF(F$5>$D$7,0,F28*$E107) -> 0 | G125: =IF(G$5>$D$7,0,G28*$E107) -> 0.17376626 | H125: =IF(H$5>$D$7,0,H28*$E107) -> 0 | I125: =IF(I$5>$D$7,0,I28*$E107) -> 0 | J125: =IF(J$5>$D$7,0,J28*$E107) -> 0 | K125: =IF(K$5>$D$7,0,K28*$E107) -> 0 | L125: =IF(L$5>$D$7,0,L28*$E107) -> 0 | ... BL125: =IF(BL$5>$D$7,0,BL28*$E107) -> 0
...

Sheet Saleplan&PnL
C1: PROFIT & LOSS 60M
C2: I. | D2: SALES PLAN
C4: Business month | D4: 45658 | E4: =EOMONTH(D4,1) -> 45716 | F4: =EOMONTH(E4,1) -> 45747 | G4: =EOMONTH(F4,1) -> 45777 | H4: =EOMONTH(G4,1) -> 45808 | I4: =EOMONTH(H4,1) -> 45838 | J4: =EOMONTH(I4,1) -> 45869 | K4: =EOMONTH(J4,1) -> 45900 | L4: =EOMONTH(K4,1) -> 45930 | ... BL4: =EOMONTH(BK4,1) -> 47514
C5: Don't delete | D5: =YEAR(D4) -> 2025 | E5: =YEAR(E4) -> 2025 | F5: =YEAR(F4) -> 2025 | G5: =YEAR(G4) -> 2025 | H5: =YEAR(H4) -> 2025 | I5: =YEAR(I4) -> 2025 | J5: =YEAR(J4) -> 2025 | K5: =YEAR(K4) -> 2025 | ... BL5: =YEAR(BL4) -> 2030
C6: New disbursement (bVND)
C8: II. | D8: PROFIT & LOSS
C10: FISCAL YEAR | E10: Total | F10: =YEAR(D4) -> 2025 | G10: =F10+1 -> 2026 | H10: =G10+1 -> 2027 | I10: =H10+1 -> 2028 | J10: =I10+1 -> 2029 | K10: =J10+1 -> 2030
E11: bVND | F11: bVND | G11: bVND | H11: bVND | I11: bVND | J11: bVND | K11: bVND
C13: NEW DISBURSAL | E13: =SUM(F13:O13) -> 0 | F13: =SUMIF($D$5:$BL$5,F$10,$D$6:$BL$6) -> 0 | G13: =SUMIF($D$5:$BL$5,G$10,$D$6:$BL$6) -> 0 | H13: =SUMIF($D$5:$BL$5,H$10,$D$6:$BL$6) -> 0 | I13: =SUMIF($D$5:$BL$5,I$10,$D$6:$BL$6) -> 0 | J13: =SUMIF($D$5:$BL$5,J$10,$D$6:$BL$6) -> 0 | K13: =SUMIF($D$5:$BL$5,K$10,$D$6:$BL$6) -> 0
C14: Monthly disbursement | E14: =IFERROR(AVERAGE(D6:AM6),0) -> 0 | F14: =IFERROR(F13/COUNTIFS($D$5:$BL$5,F10,$D$6:$BL$6,"<>"&""),0) -> 0 | G14: =IFERROR(G13/COUNTIFS($D$5:$BL$5,G10,$D$6:$BL$6,"<>"&""),0) -> 0 | H14: =IFERROR(H13/COUNTIFS($D$5:$BL$5,H10,$D$6:$BL$6,"<>"&""),0) -> 0 | I14: =IFERROR(I13/COUNTIFS($D$5:$BL$5,I10,$D$6:$BL$6,"<>"&""),0) -> 0 | J14: =IFERROR(J13/COUNTIFS($D$5:$BL$5,J10,$D$6:$BL$6,"<>"&""),0) -> 0 | K14: =IFERROR(K13/COUNTIFS($D$5:$BL$5,K10,$D$6:$BL$6,"<>"&""),0) -> 0
C16: EOP | F16: =OFFSET(PnL_Speadsheet!$A$7,0,MATCH(DATE('Saleplan&PnL'!F$10,12,31),PnL_Speadsheet!$B$4:$BI$4,0))/1000 -> 0 | G16: =OFFSET(PnL_Speadsheet!$A$7,0,MATCH(DATE('Saleplan&PnL'!G$10,12,31),PnL_Speadsheet!$B$4:$BI$4,0))/1000 -> 0 | H16: =OFFSET(PnL_Speadsheet!$A$7,0,MATCH(DATE('Saleplan&PnL'!H$10,12,31),PnL_Speadsheet!$B$4:$BI$4,0))/1000 -> 0 | I16: =OFFSET(PnL_Speadsheet!$A$7,0,MATCH(DATE('Saleplan&PnL'!I$10,12,31),PnL_Speadsheet!$B$4:$BI$4,0))/1000 -> 0 | J16: =OFFSET(PnL_Speadsheet!$A$7,0,MATCH(DATE('Saleplan&PnL'!J$10,12,31),PnL_Speadsheet!$B$4:$BI$4,0))/1000 -> 0 | K16: =IFERROR(OFFSET(PnL_Speadsheet!$A$7,0,MATCH(DATE('Saleplan&PnL'!K$10,12,31),PnL_Speadsheet!$B$4:$BI$4,0))/1000,0) -> 0
C17: ADB | E17: =IFERROR(SUM(PnL_Speadsheet!B8:AK8)/1000/COUNTIFS(PnL_Speadsheet!B8:BI8,"<>0"&""),0) -> 0 | F17: =IFERROR(SUMIF(PnL_Speadsheet!$B$3:$BI$3,F$10,PnL_Speadsheet!$B8:$BI8)/1000/COUNTIFS(PnL_Speadsheet!$B$3:$BI$3,'Saleplan&PnL'!F$10,PnL_Speadsheet!$B$8:$BI$8,"<>0"),0) -> 0 | G17: =IFERROR(SUMIF(PnL_Speadsheet!$B$3:$BI$3,G$10,PnL_Speadsheet!$B8:$BI8)/1000/COUNTIFS(PnL_Speadsheet!$B$3:$BI$3,'Saleplan&PnL'!G$10,PnL_Speadsheet!$B$8:$BI$8,"<>0"),0) -> 0 | H17: =IFERROR(SUMIF(PnL_Speadsheet!$B$3:$BI$3,H$10,PnL_Speadsheet!$B8:$BI8)/1000/COUNTIFS(PnL_Speadsheet!$B$3:$BI$3,'Saleplan&PnL'!H$10,PnL_Speadsheet!$B$8:$BI$8,"<>0"),0) -> 0 | I17: =IFERROR(SUMIF(PnL_Speadsheet!$B$3:$BI$3,I$10,PnL_Speadsheet!$B8:$BI8)/1000/COUNTIFS(PnL_Speadsheet!$B$3:$BI$3,'Saleplan&PnL'!I$10,PnL_Speadsheet!$B$8:$BI$8,"<>0"),0) -> 0 | J17: =IFERROR(SUMIF(PnL_Speadsheet!$B$3:$BI$3,J$10,PnL_Speadsheet!$B8:$BI8)/1000/COUNTIFS(PnL_Speadsheet!$B$3:$BI$3,'Saleplan&PnL'!J$10,PnL_Speadsheet!$B$8:$BI$8,"<>0"),0) -> 0 | K17: =IFERROR(SUMIF(PnL_Speadsheet!$B$3:$BI$3,K$10,PnL_Speadsheet!$B8:$BI8)/1000/COUNTIFS(PnL_Speadsheet!$B$3:$BI$3,'Saleplan&PnL'!K$10,PnL_Speadsheet!$B$8:$BI$8,"<>0"),0) -> 0
C19: TOI | E19: =SUM(F19:O19) -> 0 | F19: =SUMIF(PnL_Speadsheet!$B$3:$BI$3,F$10,PnL_Speadsheet!$B9:$BI9)/1000 -> 0 | G19: =SUMIF(PnL_Speadsheet!$B$3:$BI$3,G$10,PnL_Speadsheet!$B9:$BI9)/1000 -> 0 | H19: =SUMIF(PnL_Speadsheet!$B$3:$BI$3,H$10,PnL_Speadsheet!$B9:$BI9)/1000 -> 0 | I19: =SUMIF(PnL_Speadsheet!$B$3:$BI$3,I$10,PnL_Speadsheet!$B9:$BI9)/1000 -> 0 | J19: =SUMIF(PnL_Speadsheet!$B$3:$BI$3,J$10,PnL_Speadsheet!$B9:$BI9)/1000 -> 0 | K19: =SUMIF(PnL_Speadsheet!$B$3:$BI$3,K$10,PnL_Speadsheet!$B9:$BI9)/1000 -> 0
C20: NII | E20: =SUM(F20:O20) -> 0 | F20: =SUMIF(PnL_Speadsheet!$B$3:$BI$3,F$10,PnL_Speadsheet!$B11:$BI11)/1000 -> 0 | G20: =SUMIF(PnL_Speadsheet!$B$3:$BI$3,G$10,PnL_Speadsheet!$B11:$BI11)/1000 -> 0 | H20: =SUMIF(PnL_Speadsheet!$B$3:$BI$3,H$10,PnL_Speadsheet!$B11:$BI11)/1000 -> 0 | I20: =SUMIF(PnL_Speadsheet!$B$3:$BI$3,I$10,PnL_Speadsheet!$B11:$BI11)/1000 -> 0 | J20: =SUMIF(PnL_Speadsheet!$B$3:$BI$3,J$10,PnL_Speadsheet!$B11:$BI11)/1000 -> 0 | K20: =SUMIF(PnL_Speadsheet!$B$3:$BI$3,K$10,PnL_Speadsheet!$B11:$BI11)/1000 -> 0
C21: NFI | E21: =SUM(F21:O21) -> 0 | F21: =SUMIF(PnL_Speadsheet!$B$3:$BI$3,F$10,PnL_Speadsheet!$B14:$BI14)/1000 -> 0 | G21: =SUMIF(PnL_Speadsheet!$B$3:$BI$3,G$10,PnL_Speadsheet!$B14:$BI14)/1000 -> 0 | H21: =SUMIF(PnL_Speadsheet!$B$3:$BI$3,H$10,PnL_Speadsheet!$B14:$BI14)/1000 -> 0 | I21: =SUMIF(PnL_Speadsheet!$B$3:$BI$3,I$10,PnL_Speadsheet!$B14:$BI14)/1000 -> 0 | J21: =SUMIF(PnL_Speadsheet!$B$3:$BI$3,J$10,PnL_Speadsheet!$B14:$BI14)/1000 -> 0 | K21: =SUMIF(PnL_Speadsheet!$B$3:$BI$3,K$10,PnL_Speadsheet!$B14:$BI14)/1000 -> 0
C22: Other TOI | E22: =SUM(F22:O22) -> 0 | F22: =SUMIF(PnL_Speadsheet!$B$3:$BI$3,F$10,PnL_Speadsheet!$B17:$BI17)/1000 -> 0 | G22: =SUMIF(PnL_Speadsheet!$B$3:$BI$3,G$10,PnL_Speadsheet!$B17:$BI17)/1000 -> 0 | H22: =SUMIF(PnL_Speadsheet!$B$3:$BI$3,H$10,PnL_Speadsheet!$B17:$BI17)/1000 -> 0 | I22: =SUMIF(PnL_Speadsheet!$B$3:$BI$3,I$10,PnL_Speadsheet!$B17:$BI17)/1000 -> 0 | J22: =SUMIF(PnL_Speadsheet!$B$3:$BI$3,J$10,PnL_Speadsheet!$B17:$BI17)/1000 -> 0 | K22: =SUMIF(PnL_Speadsheet!$B$3:$BI$3,K$10,PnL_Speadsheet!$B17:$BI17)/1000 -> 0
C23: PROVISION | E23: =SUM(F23:O23) -> 0 | F23: =SUMIF(PnL_Speadsheet!$B$3:$BI$3,F$10,PnL_Speadsheet!$B30:$BI30)/1000 -> 0 | G23: =SUMIF(PnL_Speadsheet!$B$3:$BI$3,G$10,PnL_Speadsheet!$B30:$BI30)/1000 -> 0 | H23: =SUMIF(PnL_Speadsheet!$B$3:$BI$3,H$10,PnL_Speadsheet!$B30:$BI30)/1000 -> 0 | I23: =SUMIF(PnL_Speadsheet!$B$3:$BI$3,I$10,PnL_Speadsheet!$B30:$BI30)/1000 -> 0 | J23: =SUMIF(PnL_Speadsheet!$B$3:$BI$3,J$10,PnL_Speadsheet!$B30:$BI30)/1000 -> 0 | K23: =SUMIF(PnL_Speadsheet!$B$3:$BI$3,K$10,PnL_Speadsheet!$B30:$BI30)/1000 -> 0
C24: OPEX | E24: =SUM(F24:O24) -> 0 | F24: =SUMIF(PnL_Speadsheet!$B$3:$BI$3,F$10,PnL_Speadsheet!$B18:$BI18)/1000 -> 0 | G24: =SUMIF(PnL_Speadsheet!$B$3:$BI$3,G$10,PnL_Speadsheet!$B18:$BI18)/1000 -> 0 | H24: =SUMIF(PnL_Speadsheet!$B$3:$BI$3,H$10,PnL_Speadsheet!$B18:$BI18)/1000 -> 0 | I24: =SUMIF(PnL_Speadsheet!$B$3:$BI$3,I$10,PnL_Speadsheet!$B18:$BI18)/1000 -> 0 | J24: =SUMIF(PnL_Speadsheet!$B$3:$BI$3,J$10,PnL_Speadsheet!$B18:$BI18)/1000 -> 0 | K24: =SUMIF(PnL_Speadsheet!$B$3:$BI$3,K$10,PnL_Speadsheet!$B18:$BI18)/1000 -> 0
C25: Sales incentives | E25: =SUM(F25:O25) -> 0 | F25: =SUMIF(PnL_Speadsheet!$B$3:$BI$3,F$10,PnL_Speadsheet!$B20:$BI21)/1000 -> 0 | G25: =SUMIF(PnL_Speadsheet!$B$3:$BI$3,G$10,PnL_Speadsheet!$B20:$BI21)/1000 -> 0 | H25: =SUMIF(PnL_Speadsheet!$B$3:$BI$3,H$10,PnL_Speadsheet!$B20:$BI21)/1000 -> 0 | I25: =SUMIF(PnL_Speadsheet!$B$3:$BI$3,I$10,PnL_Speadsheet!$B20:$BI21)/1000 -> 0 | J25: =SUMIF(PnL_Speadsheet!$B$3:$BI$3,J$10,PnL_Speadsheet!$B20:$BI21)/1000 -> 0 | K25: =SUMIF(PnL_Speadsheet!$B$3:$BI$3,K$10,PnL_Speadsheet!$B20:$BI21)/1000 -> 0
C26: Marketing | E26: =SUM(F26:O26) -> 0 | F26: =SUMIF(PnL_Speadsheet!$B$3:$BI$3,F$10,PnL_Speadsheet!$B21:$BI21)/1000 -> 0 | G26: =SUMIF(PnL_Speadsheet!$B$3:$BI$3,G$10,PnL_Speadsheet!$B21:$BI21)/1000 -> 0 | H26: =SUMIF(PnL_Speadsheet!$B$3:$BI$3,H$10,PnL_Speadsheet!$B21:$BI21)/1000 -> 0 | I26: =SUMIF(PnL_Speadsheet!$B$3:$BI$3,I$10,PnL_Speadsheet!$B21:$BI21)/1000 -> 0 | J26: =SUMIF(PnL_Speadsheet!$B$3:$BI$3,J$10,PnL_Speadsheet!$B21:$BI21)/1000 -> 0 | K26: =SUMIF(PnL_Speadsheet!$B$3:$BI$3,K$10,PnL_Speadsheet!$B21:$BI21)/1000 -> 0
C27: UW & Disbursal | E27: =SUM(F27:O27) -> 0 | F27: =SUMIF(PnL_Speadsheet!$B$3:$BI$3,F$10,PnL_Speadsheet!$B23:$BI23)/1000 -> 0 | G27: =SUMIF(PnL_Speadsheet!$B$3:$BI$3,G$10,PnL_Speadsheet!$B23:$BI23)/1000 -> 0 | H27: =SUMIF(PnL_Speadsheet!$B$3:$BI$3,H$10,PnL_Speadsheet!$B23:$BI23)/1000 -> 0 | I27: =SUMIF(PnL_Speadsheet!$B$3:$BI$3,I$10,PnL_Speadsheet!$B23:$BI23)/1000 -> 0 | J27: =SUMIF(PnL_Speadsheet!$B$3:$BI$3,J$10,PnL_Speadsheet!$B23:$BI23)/1000 -> 0 | K27: =SUMIF(PnL_Speadsheet!$B$3:$BI$3,K$10,PnL_Speadsheet!$B23:$BI23)/1000 -> 0
C28: Collection & AMC | E28: =SUM(F28:O28) -> 0 | F28: =SUMIF(PnL_Speadsheet!$B$3:$BI$3,F$10,PnL_Speadsheet!$B27:$BI27)/1000 -> 0 | G28: =SUMIF(PnL_Speadsheet!$B$3:$BI$3,G$10,PnL_Speadsheet!$B27:$BI27)/1000 -> 0 | H28: =SUMIF(PnL_Speadsheet!$B$3:$BI$3,H$10,PnL_Speadsheet!$B27:$BI27)/1000 -> 0 | I28: =SUMIF(PnL_Speadsheet!$B$3:$BI$3,I$10,PnL_Speadsheet!$B27:$BI27)/1000 -> 0 | J28: =SUMIF(PnL_Speadsheet!$B$3:$BI$3,J$10,PnL_Speadsheet!$B27:$BI27)/1000 -> 0 | K28: =SUMIF(PnL_Speadsheet!$B$3:$BI$3,K$10,PnL_Speadsheet!$B27:$BI27)/1000 -> 0
C29: After-sales services | E29: =SUM(F29:O29) -> 0 | F29: =SUMIF(PnL_Speadsheet!$B$3:$BI$3,F$10,PnL_Speadsheet!$B28:$BI28)/1000 -> 0 | G29: =SUMIF(PnL_Speadsheet!$B$3:$BI$3,G$10,PnL_Speadsheet!$B28:$BI28)/1000 -> 0 | H29: =SUMIF(PnL_Speadsheet!$B$3:$BI$3,H$10,PnL_Speadsheet!$B28:$BI28)/1000 -> 0 | I29: =SUMIF(PnL_Speadsheet!$B$3:$BI$3,I$10,PnL_Speadsheet!$B28:$BI28)/1000 -> 0 | J29: =SUMIF(PnL_Speadsheet!$B$3:$BI$3,J$10,PnL_Speadsheet!$B28:$BI28)/1000 -> 0 | K29: =SUMIF(PnL_Speadsheet!$B$3:$BI$3,K$10,PnL_Speadsheet!$B28:$BI28)/1000 -> 0
C30: Other support units | E30: =SUM(F30:O30) -> 0 | F30: =SUMIF(PnL_Speadsheet!$B$3:$BI$3,F$10,PnL_Speadsheet!$B29:$BI29)/1000 -> 0 | G30: =SUMIF(PnL_Speadsheet!$B$3:$BI$3,G$10,PnL_Speadsheet!$B29:$BI29)/1000 -> 0 | H30: =SUMIF(PnL_Speadsheet!$B$3:$BI$3,H$10,PnL_Speadsheet!$B29:$BI29)/1000 -> 0 | I30: =SUMIF(PnL_Speadsheet!$B$3:$BI$3,I$10,PnL_Speadsheet!$B29:$BI29)/1000 -> 0 | J30: =SUMIF(PnL_Speadsheet!$B$3:$BI$3,J$10,PnL_Speadsheet!$B29:$BI29)/1000 -> 0 | K30: =SUMIF(PnL_Speadsheet!$B$3:$BI$3,K$10,PnL_Speadsheet!$B29:$BI29)/1000 -> 0
C31: PBT | E31: =SUM(F31:O31) -> 0 | F31: =SUMIF(PnL_Speadsheet!$B$3:$BI$3,F$10,PnL_Speadsheet!$B31:$BI31)/1000 -> 0 | G31: =SUMIF(PnL_Speadsheet!$B$3:$BI$3,G$10,PnL_Speadsheet!$B31:$BI31)/1000 -> 0 | H31: =SUMIF(PnL_Speadsheet!$B$3:$BI$3,H$10,PnL_Speadsheet!$B31:$BI31)/1000 -> 0 | I31: =SUMIF(PnL_Speadsheet!$B$3:$BI$3,I$10,PnL_Speadsheet!$B31:$BI31)/1000 -> 0 | J31: =SUMIF(PnL_Speadsheet!$B$3:$BI$3,J$10,PnL_Speadsheet!$B31:$BI31)/1000 -> 0 | K31: =SUMIF(PnL_Speadsheet!$B$3:$BI$3,K$10,PnL_Speadsheet!$B31:$BI31)/1000 -> 0
C32: In which: PROFIT BEFORE SU | E32: =E19+E23+SUM(E25:E29) -> 0 | F32: =F19+F23+SUM(F25:F29) -> 0 | G32: =G19+G23+SUM(G25:G29) -> 0 | H32: =H19+H23+SUM(H25:H29) -> 0 | I32: =I19+I23+SUM(I25:I29) -> 0 | J32: =J19+J23+SUM(J25:J29) -> 0 | K32: =K19+K23+SUM(K25:K29) -> 0

Sheet PnL_Speadsheet
A1: PL PROJECTION
A2: 60 months
B3: =YEAR(B4) -> 2025 | C3: =YEAR(C4) -> 2025 | D3: =YEAR(D4) -> 2025 | E3: =YEAR(E4) -> 2025 | F3: =YEAR(F4) -> 2025 | G3: =YEAR(G4) -> 2025 | H3: =YEAR(H4) -> 2025 | I3: =YEAR(I4) -> 2025 | ... BI3: =YEAR(BI4) -> 2029
A4: Business month | B4: ='Saleplan&PnL'!D4 -> 45658 | C4: ='Saleplan&PnL'!E4 -> 45716 | D4: ='Saleplan&PnL'!F4 -> 45747 | E4: ='Saleplan&PnL'!G4 -> 45777 | F4: ='Saleplan&PnL'!H4 -> 45808 | G4: ='Saleplan&PnL'!I4 -> 45838 | H4: ='Saleplan&PnL'!J4 -> 45869 | I4: ='Saleplan&PnL'!K4 -> 45900 | ... BI4: ='Saleplan&PnL'!BK4 -> 47483
A5: Month on board | B5: 1 | C5: 2 | D5: 3 | E5: 4 | F5: 5 | G5: 6 | H5: 7 | I5: 8 | J5: 9 | K5: 10 | L5: 11 | M5: 12 | N5: 13 | O5: 14 | P5: 15 | Q5: 16 | R5: 17 | S5: 18 | T5: 19 | U5: 20 | V5: 21 | W5: 22 | X5: 23 | Y5: 24 | Z5: 25 | AA5: 26 | AB5: 27 | AC5: 28 | AD5: 29 | AE5: 30 | AF5: 31 | AG5: 32 | AH5: 33 | AI5: 34 | AJ5: 35 | AK5: 36 | AL5: =AK5+1 -> 37 | AM5: =AL5+1 -> 38 | AN5: =AM5+1 -> 39 | AO5: =AN5+1 -> 40 | AP5: =AO5+1 -> 41 | AQ5: =AP5+1 -> 42 | AR5: =AQ5+1 -> 43 | AS5: =AR5+1 -> 44 | ... BI5: =BH5+1 -> 60
A6: Unit: mVND
A7: ENR | B7: {=SUMPRODUCT(B$54:B$113,TRANSPOSE(SAP_Speadsheet!$E$42:$BL$42))} -> 0 | C7: {=SUMPRODUCT(C$54:C$113,TRANSPOSE(SAP_Speadsheet!$E$42:$BL$42))} -> 0 | D7: {=SUMPRODUCT(D$54:D$113,TRANSPOSE(SAP_Speadsheet!$E$42:$BL$42))} -> 0 | E7: {=SUMPRODUCT(E$54:E$113,TRANSPOSE(SAP_Speadsheet!$E$42:$BL$42))} -> 0 | F7: {=SUMPRODUCT(F$54:F$113,TRANSPOSE(SAP_Speadsheet!$E$42:$BL$42))} -> 0 | G7: {=SUMPRODUCT(G$54:G$113,TRANSPOSE(SAP_Speadsheet!$E$42:$BL$42))} -> 0 | H7: {=SUMPRODUCT(H$54:H$113,TRANSPOSE(SAP_Speadsheet!$E$42:$BL$42))} -> 0 | I7: {=SUMPRODUCT(I$54:I$113,TRANSPOSE(SAP_Speadsheet!$E$42:$BL$42))} -> 0 | ... BI7: {=SUMPRODUCT(BI$54:BI$113,TRANSPOSE(SAP_Speadsheet!$E$42:$BL$42))} -> 0
A8: ANR | B8: {=SUMPRODUCT(B$54:B$113,TRANSPOSE(SAP_Speadsheet!$E$48:$BL$48))} -> 0 | C8: {=SUMPRODUCT(C$54:C$113,TRANSPOSE(SAP_Speadsheet!$E$48:$BL$48))} -> 0 | D8: {=SUMPRODUCT(D$54:D$113,TRANSPOSE(SAP_Speadsheet!$E$48:$BL$48))} -> 0 | E8: {=SUMPRODUCT(E$54:E$113,TRANSPOSE(SAP_Speadsheet!$E$48:$BL$48))} -> 0 | F8: {=SUMPRODUCT(F$54:F$113,TRANSPOSE(SAP_Speadsheet!$E$48:$BL$48))} -> 0 | G8: {=SUMPRODUCT(G$54:G$113,TRANSPOSE(SAP_Speadsheet!$E$48:$BL$48))} -> 0 | H8: {=SUMPRODUCT(H$54:H$113,TRANSPOSE(SAP_Speadsheet!$E$48:$BL$48))} -> 0 | I8: {=SUMPRODUCT(I$54:I$113,TRANSPOSE(SAP_Speadsheet!$E$48:$BL$48))} -> 0 | ... BI8: {=SUMPRODUCT(BI$54:BI$113,TRANSPOSE(SAP_Speadsheet!$E$48:$BL$48))} -> 0
A9: TOI | B9: {=SUMPRODUCT(B$54:B$113,TRANSPOSE(SAP_Speadsheet!$E$53:$BL$53))} -> 0 | C9: {=SUMPRODUCT(C$54:C$113,TRANSPOSE(SAP_Speadsheet!$E$53:$BL$53))} -> 0 | D9: {=SUMPRODUCT(D$54:D$113,TRANSPOSE(SAP_Speadsheet!$E$53:$BL$53))} -> 0 | E9: {=SUMPRODUCT(E$54:E$113,TRANSPOSE(SAP_Speadsheet!$E$53:$BL$53))} -> 0 | F9: {=SUMPRODUCT(F$54:F$113,TRANSPOSE(SAP_Speadsheet!$E$53:$BL$53))} -> 0 | G9: {=SUMPRODUCT(G$54:G$113,TRANSPOSE(SAP_Speadsheet!$E$53:$BL$53))} -> 0 | H9: {=SUMPRODUCT(H$54:H$113,TRANSPOSE(SAP_Speadsheet!$E$53:$BL$53))} -> 0 | I9: {=SUMPRODUCT(I$54:I$113,TRANSPOSE(SAP_Speadsheet!$E$53:$BL$53))} -> 0 | ... BI9: {=SUMPRODUCT(BI$54:BI$113,TRANSPOSE(SAP_Speadsheet!$E$53:$BL$53))} -> 0
A10: Checking | B10: =B9-B11-B14 -> 0 | C10: =C9-C11-C14 -> 0 | D10: =D9-D11-D14 -> 0 | E10: =E9-E11-E14 -> 0 | F10: =F9-F11-F14 -> 0 | G10: =G9-G11-G14 -> 0 | H10: =H9-H11-H14 -> 0 | I10: =I9-I11-I14 -> 0 | ... BI10: =BI9-BI11-BI14 -> 0
A11: Net interest income | B11: {=SUMPRODUCT(B$54:B$113,TRANSPOSE(SAP_Speadsheet!$E$55:$BL$55))} -> 0 | C11: {=SUMPRODUCT(C$54:C$113,TRANSPOSE(SAP_Speadsheet!$E$55:$BL$55))} -> 0 | D11: {=SUMPRODUCT(D$54:D$113,TRANSPOSE(SAP_Speadsheet!$E$55:$BL$55))} -> 0 | E11: {=SUMPRODUCT(E$54:E$113,TRANSPOSE(SAP_Speadsheet!$E$55:$BL$55))} -> 0 | F11: {=SUMPRODUCT(F$54:F$113,TRANSPOSE(SAP_Speadsheet!$E$55:$BL$55))} -> 0 | G11: {=SUMPRODUCT(G$54:G$113,TRANSPOSE(SAP_Speadsheet!$E$55:$BL$55))} -> 0 | H11: {=SUMPRODUCT(H$54:H$113,TRANSPOSE(SAP_Speadsheet!$E$55:$BL$55))} -> 0 | I11: {=SUMPRODUCT(I$54:I$113,TRANSPOSE(SAP_Speadsheet!$E$55:$BL$55))} -> 0 | ... BI11: {=SUMPRODUCT(BI$54:BI$113,TRANSPOSE(SAP_Speadsheet!$E$55:$BL$55))} -> 0
A12: Interest income | B12: {=SUMPRODUCT(B$54:B$113,TRANSPOSE(SAP_Speadsheet!$E$56:$BL$56))} -> 0 | C12: {=SUMPRODUCT(C$54:C$113,TRANSPOSE(SAP_Speadsheet!$E$56:$BL$56))} -> 0 | D12: {=SUMPRODUCT(D$54:D$113,TRANSPOSE(SAP_Speadsheet!$E$56:$BL$56))} -> 0 | E12: {=SUMPRODUCT(E$54:E$113,TRANSPOSE(SAP_Speadsheet!$E$56:$BL$56))} -> 0 | F12: {=SUMPRODUCT(F$54:F$113,TRANSPOSE(SAP_Speadsheet!$E$56:$BL$56))} -> 0 | G12: {=SUMPRODUCT(G$54:G$113,TRANSPOSE(SAP_Speadsheet!$E$56:$BL$56))} -> 0 | H12: {=SUMPRODUCT(H$54:H$113,TRANSPOSE(SAP_Speadsheet!$E$56:$BL$56))} -> 0 | I12: {=SUMPRODUCT(I$54:I$113,TRANSPOSE(SAP_Speadsheet!$E$56:$BL$56))} -> 0 | ... BI12: {=SUMPRODUCT(BI$54:BI$113,TRANSPOSE(SAP_Speadsheet!$E$56:$BL$56))} -> 0
A13: Cost of fund | B13: {=SUMPRODUCT(B$54:B$113,TRANSPOSE(SAP_Speadsheet!$E$57:$BL$57))} -> 0 | C13: {=SUMPRODUCT(C$54:C$113,TRANSPOSE(SAP_Speadsheet!$E$57:$BL$57))} -> 0 | D13: {=SUMPRODUCT(D$54:D$113,TRANSPOSE(SAP_Speadsheet!$E$57:$BL$57))} -> 0 | E13: {=SUMPRODUCT(E$54:E$113,TRANSPOSE(SAP_Speadsheet!$E$57:$BL$57))} -> 0 | F13: {=SUMPRODUCT(F$54:F$113,TRANSPOSE(SAP_Speadsheet!$E$57:$BL$57))} -> 0 | G13: {=SUMPRODUCT(G$54:G$113,TRANSPOSE(SAP_Speadsheet!$E$57:$BL$57))} -> 0 | H13: {=SUMPRODUCT(H$54:H$113,TRANSPOSE(SAP_Speadsheet!$E$57:$BL$57))} -> 0 | I13: {=SUMPRODUCT(I$54:I$113,TRANSPOSE(SAP_Speadsheet!$E$57:$BL$57))} -> 0 | ... BI13: {=SUMPRODUCT(BI$54:BI$113,TRANSPOSE(SAP_Speadsheet!$E$57:$BL$57))} -> 0
A14: Net fee income | B14: {=SUMPRODUCT(B$54:B$113,TRANSPOSE(SAP_Speadsheet!$E$59:$BL$59))} -> 0 | C14: {=SUMPRODUCT(C$54:C$113,TRANSPOSE(SAP_Speadsheet!$E$59:$BL$59))} -> 0 | D14: {=SUMPRODUCT(D$54:D$113,TRANSPOSE(SAP_Speadsheet!$E$59:$BL$59))} -> 0 | E14: {=SUMPRODUCT(E$54:E$113,TRANSPOSE(SAP_Speadsheet!$E$59:$BL$59))} -> 0 | F14: {=SUMPRODUCT(F$54:F$113,TRANSPOSE(SAP_Speadsheet!$E$59:$BL$59))} -> 0 | G14: {=SUMPRODUCT(G$54:G$113,TRANSPOSE(SAP_Speadsheet!$E$59:$BL$59))} -> 0 | H14: {=SUMPRODUCT(H$54:H$113,TRANSPOSE(SAP_Speadsheet!$E$59:$BL$59))} -> 0 | I14: {=SUMPRODUCT(I$54:I$113,TRANSPOSE(SAP_Speadsheet!$E$59:$BL$59))} -> 0 | ... BI14: {=SUMPRODUCT(BI$54:BI$113,TRANSPOSE(SAP_Speadsheet!$E$59:$BL$59))} -> 0
A15: Insurance fee | B15: {=SUMPRODUCT(B$54:B$113,TRANSPOSE(SAP_Speadsheet!$E$60:$BL$60))} -> 0 | C15: {=SUMPRODUCT(C$54:C$113,TRANSPOSE(SAP_Speadsheet!$E$60:$BL$60))} -> 0 | D15: {=SUMPRODUCT(D$54:D$113,TRANSPOSE(SAP_Speadsheet!$E$60:$BL$60))} -> 0 | E15: {=SUMPRODUCT(E$54:E$113,TRANSPOSE(SAP_Speadsheet!$E$60:$BL$60))} -> 0 | F15: {=SUMPRODUCT(F$54:F$113,TRANSPOSE(SAP_Speadsheet!$E$60:$BL$60))} -> 0 | G15: {=SUMPRODUCT(G$54:G$113,TRANSPOSE(SAP_Speadsheet!$E$60:$BL$60))} -> 0 | H15: {=SUMPRODUCT(H$54:H$113,TRANSPOSE(SAP_Speadsheet!$E$60:$BL$60))} -> 0 | I15: {=SUMPRODUCT(I$54:I$113,TRANSPOSE(SAP_Speadsheet!$E$60:$BL$60))} -> 0 | ... BI15: {=SUMPRODUCT(BI$54:BI$113,TRANSPOSE(SAP_Speadsheet!$E$60:$BL$60))} -> 0
A16: Support fee | B16: {=SUMPRODUCT(B$54:B$113,TRANSPOSE(SAP_Speadsheet!$E$61:$BL$61))} -> 0 | C16: {=SUMPRODUCT(C$54:C$113,TRANSPOSE(SAP_Speadsheet!$E$61:$BL$61))} -> 0 | D16: {=SUMPRODUCT(D$54:D$113,TRANSPOSE(SAP_Speadsheet!$E$61:$BL$61))} -> 0 | E16: {=SUMPRODUCT(E$54:E$113,TRANSPOSE(SAP_Speadsheet!$E$61:$BL$61))} -> 0 | F16: {=SUMPRODUCT(F$54:F$113,TRANSPOSE(SAP_Speadsheet!$E$61:$BL$61))} -> 0 | G16: {=SUMPRODUCT(G$54:G$113,TRANSPOSE(SAP_Speadsheet!$E$61:$BL$61))} -> 0 | H16: {=SUMPRODUCT(H$54:H$113,TRANSPOSE(SAP_Speadsheet!$E$61:$BL$61))} -> 0 | I16: {=SUMPRODUCT(I$54:I$113,TRANSPOSE(SAP_Speadsheet!$E$61:$BL$61))} -> 0 | ... BI16: {=SUMPRODUCT(BI$54:BI$113,TRANSPOSE(SAP_Speadsheet!$E$61:$BL$61))} -> 0
A17: Other income | B17: {=SUMPRODUCT(B$54:B$113,TRANSPOSE(SAP_Speadsheet!$E$63:$BL$63))} -> 0 | C17: {=SUMPRODUCT(C$54:C$113,TRANSPOSE(SAP_Speadsheet!$E$63:$BL$63))} -> 0 | D17: {=SUMPRODUCT(D$54:D$113,TRANSPOSE(SAP_Speadsheet!$E$63:$BL$63))} -> 0 | E17: {=SUMPRODUCT(E$54:E$113,TRANSPOSE(SAP_Speadsheet!$E$63:$BL$63))} -> 0 | F17: {=SUMPRODUCT(F$54:F$113,TRANSPOSE(SAP_Speadsheet!$E$63:$BL$63))} -> 0 | G17: {=SUMPRODUCT(G$54:G$113,TRANSPOSE(SAP_Speadsheet!$E$63:$BL$63))} -> 0 | H17: {=SUMPRODUCT(H$54:H$113,TRANSPOSE(SAP_Speadsheet!$E$63:$BL$63))} -> 0 | I17: {=SUMPRODUCT(I$54:I$113,TRANSPOSE(SAP_Speadsheet!$E$63:$BL$63))} -> 0 | ... BI17: {=SUMPRODUCT(BI$54:BI$113,TRANSPOSE(SAP_Speadsheet!$E$63:$BL$63))} -> 0
A18: OPEX | B18: =B19+B23+B27+B28+B29 -> 0 | C18: =C19+C23+C27+C28+C29 -> 0 | D18: =D19+D23+D27+D28+D29 -> 0 | E18: =E19+E23+E27+E28+E29 -> 0 | F18: =F19+F23+F27+F28+F29 -> 0 | G18: =G19+G23+G27+G28+G29 -> 0 | H18: =H19+H23+H27+H28+H29 -> 0 | I18: =I19+I23+I27+I28+I29 -> 0 | ... BI18: =BI19+BI23+BI27+BI28+BI29 -> 0
A19: Sale incentive&mkt | B19: =SUM(B20:B22) -> 0 | C19: =SUM(C20:C22) -> 0 | D19: =SUM(D20:D22) -> 0 | E19: =SUM(E20:E22) -> 0 | F19: =SUM(F20:F22) -> 0 | G19: =SUM(G20:G22) -> 0 | H19: =SUM(H20:H22) -> 0 | I19: =SUM(I20:I22) -> 0 | ... BI19: =SUM(BI20:BI22) -> 0
A20: Lead Acquisition | B20: {=SUMPRODUCT(B$54:B$113,TRANSPOSE(SAP_Speadsheet!$E$68:$BL$68))} -> 0 | C20: {=SUMPRODUCT(C$54:C$113,TRANSPOSE(SAP_Speadsheet!$E$68:$BL$68))} -> 0 | D20: {=SUMPRODUCT(D$54:D$113,TRANSPOSE(SAP_Speadsheet!$E$68:$BL$68))} -> 0 | E20: {=SUMPRODUCT(E$54:E$113,TRANSPOSE(SAP_Speadsheet!$E$68:$BL$68))} -> 0 | F20: {=SUMPRODUCT(F$54:F$113,TRANSPOSE(SAP_Speadsheet!$E$68:$BL$68))} -> 0 | G20: {=SUMPRODUCT(G$54:G$113,TRANSPOSE(SAP_Speadsheet!$E$68:$BL$68))} -> 0 | H20: {=SUMPRODUCT(H$54:H$113,TRANSPOSE(SAP_Speadsheet!$E$68:$BL$68))} -> 0 | I20: {=SUMPRODUCT(I$54:I$113,TRANSPOSE(SAP_Speadsheet!$E$68:$BL$68))} -> 0 | ... BI20: {=SUMPRODUCT(BI$54:BI$113,TRANSPOSE(SAP_Speadsheet!$E$68:$BL$68))} -> 0
A21: Sharing performance | B21: {=SUMPRODUCT(B$54:B$113,TRANSPOSE(SAP_Speadsheet!$E$69:$BL$69))} -> 0 | C21: {=SUMPRODUCT(C$54:C$113,TRANSPOSE(SAP_Speadsheet!$E$69:$BL$69))} -> 0 | D21: {=SUMPRODUCT(D$54:D$113,TRANSPOSE(SAP_Speadsheet!$E$69:$BL$69))} -> 0 | E21: {=SUMPRODUCT(E$54:E$113,TRANSPOSE(SAP_Speadsheet!$E$69:$BL$69))} -> 0 | F21: {=SUMPRODUCT(F$54:F$113,TRANSPOSE(SAP_Speadsheet!$E$69:$BL$69))} -> 0 | G21: {=SUMPRODUCT(G$54:G$113,TRANSPOSE(SAP_Speadsheet!$E$69:$BL$69))} -> 0 | H21: {=SUMPRODUCT(H$54:H$113,TRANSPOSE(SAP_Speadsheet!$E$69:$BL$69))} -> 0 | I21: {=SUMPRODUCT(I$54:I$113,TRANSPOSE(SAP_Speadsheet!$E$69:$BL$69))} -> 0 | ... BI21: {=SUMPRODUCT(BI$54:BI$113,TRANSPOSE(SAP_Speadsheet!$E$69:$BL$69))} -> 0
A22: Marketing | B22: {=SUMPRODUCT(B$54:B$113,TRANSPOSE(SAP_Speadsheet!$E$78:$BL$78))} -> 0 | C22: {=SUMPRODUCT(C$54:C$113,TRANSPOSE(SAP_Speadsheet!$E$78:$BL$78))} -> 0 | D22: {=SUMPRODUCT(D$54:D$113,TRANSPOSE(SAP_Speadsheet!$E$78:$BL$78))} -> 0 | E22: {=SUMPRODUCT(E$54:E$113,TRANSPOSE(SAP_Speadsheet!$E$78:$BL$78))} -> 0 | F22: {=SUMPRODUCT(F$54:F$113,TRANSPOSE(SAP_Speadsheet!$E$78:$BL$78))} -> 0 | G22: {=SUMPRODUCT(G$54:G$113,TRANSPOSE(SAP_Speadsheet!$E$78:$BL$78))} -> 0 | H22: {=SUMPRODUCT(H$54:H$113,TRANSPOSE(SAP_Speadsheet!$E$78:$BL$78))} -> 0 | I22: {=SUMPRODUCT(I$54:I$113,TRANSPOSE(SAP_Speadsheet!$E$78:$BL$78))} -> 0 | ... AV22: {=SUMPRODUCT(AV$54:AV$113,TRANSPOSE(SAP_Speadsheet!$E$78:$BL$78))} -> 0 | AW22: 0 | AX22: {=SUMPRODUCT(AX$54:AX$113,TRANSPOSE(SAP_Speadsheet!$E$78:$BL$78))} -> 0 | AY22: {=SUMPRODUCT(AY$54:AY$113,TRANSPOSE(SAP_Speadsheet!$E$78:$BL$78))} -> 0 | AZ22: {=SUMPRODUCT(AZ$54:AZ$113,TRANSPOSE(SAP_Speadsheet!$E$78:$BL$78))} -> 0 | BA22: {=SUMPRODUCT(BA$54:BA$113,TRANSPOSE(SAP_Speadsheet!$E$78:$BL$78))} -> 0 | BB22: {=SUMPRODUCT(BB$54:BB$113,TRANSPOSE(SAP_Speadsheet!$E$78:$BL$78))} -> 0 | BC22: {=SUMPRODUCT(BC$54:BC$113,TRANSPOSE(SAP_Speadsheet!$E$78:$BL$78))} -> 0 | BD22: {=SUMPRODUCT(BD$54:BD$113,TRANSPOSE(SAP_Speadsheet!$E$78:$BL$78))} -> 0 | BE22: {=SUMPRODUCT(BE$54:BE$113,TRANSPOSE(SAP_Speadsheet!$E$78:$BL$78))} -> 0 | ... BI22: {=SUMPRODUCT(BI$54:BI$113,TRANSPOSE(SAP_Speadsheet!$E$78:$BL$78))} -> 0
A23: UW & Disbursal | B23: {=SUMPRODUCT(B$54:B$113,TRANSPOSE(SAP_Speadsheet!$E$80:$BL$80))} -> 0 | C23: {=SUMPRODUCT(C$54:C$113,TRANSPOSE(SAP_Speadsheet!$E$80:$BL$80))} -> 0 | D23: {=SUMPRODUCT(D$54:D$113,TRANSPOSE(SAP_Speadsheet!$E$80:$BL$80))} -> 0 | E23: {=SUMPRODUCT(E$54:E$113,TRANSPOSE(SAP_Speadsheet!$E$80:$BL$80))} -> 0 | F23: {=SUMPRODUCT(F$54:F$113,TRANSPOSE(SAP_Speadsheet!$E$80:$BL$80))} -> 0 | G23: {=SUMPRODUCT(G$54:G$113,TRANSPOSE(SAP_Speadsheet!$E$80:$BL$80))} -> 0 | H23: {=SUMPRODUCT(H$54:H$113,TRANSPOSE(SAP_Speadsheet!$E$80:$BL$80))} -> 0 | I23: {=SUMPRODUCT(I$54:I$113,TRANSPOSE(SAP_Speadsheet!$E$80:$BL$80))} -> 0 | ... BI23: {=SUMPRODUCT(BI$54:BI$113,TRANSPOSE(SAP_Speadsheet!$E$80:$BL$80))} -> 0
A24: Underwriting | B24: {=SUMPRODUCT(B$54:B$113,TRANSPOSE(SAP_Speadsheet!$E$81:$BL$81))} -> 0 | C24: {=SUMPRODUCT(C$54:C$113,TRANSPOSE(SAP_Speadsheet!$E$81:$BL$81))} -> 0 | D24: {=SUMPRODUCT(D$54:D$113,TRANSPOSE(SAP_Speadsheet!$E$81:$BL$81))} -> 0 | E24: {=SUMPRODUCT(E$54:E$113,TRANSPOSE(SAP_Speadsheet!$E$81:$BL$81))} -> 0 | F24: {=SUMPRODUCT(F$54:F$113,TRANSPOSE(SAP_Speadsheet!$E$81:$BL$81))} -> 0 | G24: {=SUMPRODUCT(G$54:G$113,TRANSPOSE(SAP_Speadsheet!$E$81:$BL$81))} -> 0 | H24: {=SUMPRODUCT(H$54:H$113,TRANSPOSE(SAP_Speadsheet!$E$81:$BL$81))} -> 0 | I24: {=SUMPRODUCT(I$54:I$113,TRANSPOSE(SAP_Speadsheet!$E$81:$BL$81))} -> 0 | ... BI24: {=SUMPRODUCT(BI$54:BI$113,TRANSPOSE(SAP_Speadsheet!$E$81:$BL$81))} -> 0
A25: Disbursement | B25: {=SUMPRODUCT(B$54:B$113,TRANSPOSE(SAP_Speadsheet!$E$82:$BL$82))} -> 0 | C25: {=SUMPRODUCT(C$54:C$113,TRANSPOSE(SAP_Speadsheet!$E$82:$BL$82))} -> 0 | D25: {=SUMPRODUCT(D$54:D$113,TRANSPOSE(SAP_Speadsheet!$E$82:$BL$82))} -> 0 | E25: {=SUMPRODUCT(E$54:E$113,TRANSPOSE(SAP_Speadsheet!$E$82:$BL$82))} -> 0 | F25: {=SUMPRODUCT(F$54:F$113,TRANSPOSE(SAP_Speadsheet!$E$82:$BL$82))} -> 0 | G25: {=SUMPRODUCT(G$54:G$113,TRANSPOSE(SAP_Speadsheet!$E$82:$BL$82))} -> 0 | H25: {=SUMPRODUCT(H$54:H$113,TRANSPOSE(SAP_Speadsheet!$E$82:$BL$82))} -> 0 | I25: {=SUMPRODUCT(I$54:I$113,TRANSPOSE(SAP_Speadsheet!$E$82:$BL$82))} -> 0 | ... BI25: {=SUMPRODUCT(BI$54:BI$113,TRANSPOSE(SAP_Speadsheet!$E$82:$BL$82))} -> 0
A26: DOP | B26: {=SUMPRODUCT(B$54:B$113,TRANSPOSE(SAP_Speadsheet!$E$83:$BL$83))} -> 0 | C26: {=SUMPRODUCT(C$54:C$113,TRANSPOSE(SAP_Speadsheet!$E$83:$BL$83))} -> 0 | D26: {=SUMPRODUCT(D$54:D$113,TRANSPOSE(SAP_Speadsheet!$E$83:$BL$83))} -> 0 | E26: {=SUMPRODUCT(E$54:E$113,TRANSPOSE(SAP_Speadsheet!$E$83:$BL$83))} -> 0 | F26: {=SUMPRODUCT(F$54:F$113,TRANSPOSE(SAP_Speadsheet!$E$83:$BL$83))} -> 0 | G26: {=SUMPRODUCT(G$54:G$113,TRANSPOSE(SAP_Speadsheet!$E$83:$BL$83))} -> 0 | H26: {=SUMPRODUCT(H$54:H$113,TRANSPOSE(SAP_Speadsheet!$E$83:$BL$83))} -> 0 | I26: {=SUMPRODUCT(I$54:I$113,TRANSPOSE(SAP_Speadsheet!$E$83:$BL$83))} -> 0 | ... BI26: {=SUMPRODUCT(BI$54:BI$113,TRANSPOSE(SAP_Speadsheet!$E$83:$BL$83))} -> 0
A27: Collection | B27: {=SUMPRODUCT(B$54:B$113,TRANSPOSE(SAP_Speadsheet!$E$87:$BL$87))} -> 0 | C27: {=SUMPRODUCT(C$54:C$113,TRANSPOSE(SAP_Speadsheet!$E$87:$BL$87))} -> 0 | D27: {=SUMPRODUCT(D$54:D$113,TRANSPOSE(SAP_Speadsheet!$E$87:$BL$87))} -> 0 | E27: {=SUMPRODUCT(E$54:E$113,TRANSPOSE(SAP_Speadsheet!$E$87:$BL$87))} -> 0 | F27: {=SUMPRODUCT(F$54:F$113,TRANSPOSE(SAP_Speadsheet!$E$87:$BL$87))} -> 0 | G27: {=SUMPRODUCT(G$54:G$113,TRANSPOSE(SAP_Speadsheet!$E$87:$BL$87))} -> 0 | H27: {=SUMPRODUCT(H$54:H$113,TRANSPOSE(SAP_Speadsheet!$E$87:$BL$87))} -> 0 | I27: {=SUMPRODUCT(I$54:I$113,TRANSPOSE(SAP_Speadsheet!$E$87:$BL$87))} -> 0 | ... BI27: {=SUMPRODUCT(BI$54:BI$113,TRANSPOSE(SAP_Speadsheet!$E$87:$BL$87))} -> 0
A28: After-sales services | B28: {=SUMPRODUCT(B$54:B$113,TRANSPOSE(SAP_Speadsheet!$E$91:$BL$91))} -> 0 | C28: {=SUMPRODUCT(C$54:C$113,TRANSPOSE(SAP_Speadsheet!$E$91:$BL$91))} -> 0 | D28: {=SUMPRODUCT(D$54:D$113,TRANSPOSE(SAP_Speadsheet!$E$91:$BL$91))} -> 0 | E28: {=SUMPRODUCT(E$54:E$113,TRANSPOSE(SAP_Speadsheet!$E$91:$BL$91))} -> 0 | F28: {=SUMPRODUCT(F$54:F$113,TRANSPOSE(SAP_Speadsheet!$E$91:$BL$91))} -> 0 | G28: {=SUMPRODUCT(G$54:G$113,TRANSPOSE(SAP_Speadsheet!$E$91:$BL$91))} -> 0 | H28: {=SUMPRODUCT(H$54:H$113,TRANSPOSE(SAP_Speadsheet!$E$91:$BL$91))} -> 0 | I28: {=SUMPRODUCT(I$54:I$113,TRANSPOSE(SAP_Speadsheet!$E$91:$BL$91))} -> 0 | ... BI28: {=SUMPRODUCT(BI$54:BI$113,TRANSPOSE(SAP_Speadsheet!$E$91:$BL$91))} -> 0
A29: Other support units | B29: {=SUMPRODUCT(B$54:B$113,TRANSPOSE(SAP_Speadsheet!$E$95:$BL$95))} -> 0 | C29: {=SUMPRODUCT(C$54:C$113,TRANSPOSE(SAP_Speadsheet!$E$95:$BL$95))} -> 0 | D29: {=SUMPRODUCT(D$54:D$113,TRANSPOSE(SAP_Speadsheet!$E$95:$BL$95))} -> 0 | E29: {=SUMPRODUCT(E$54:E$113,TRANSPOSE(SAP_Speadsheet!$E$95:$BL$95))} -> 0 | F29: {=SUMPRODUCT(F$54:F$113,TRANSPOSE(SAP_Speadsheet!$E$95:$BL$95))} -> 0 | G29: {=SUMPRODUCT(G$54:G$113,TRANSPOSE(SAP_Speadsheet!$E$95:$BL$95))} -> 0 | H29: {=SUMPRODUCT(H$54:H$113,TRANSPOSE(SAP_Speadsheet!$E$95:$BL$95))} -> 0 | I29: {=SUMPRODUCT(I$54:I$113,TRANSPOSE(SAP_Speadsheet!$E$95:$BL$95))} -> 0 | ... BI29: {=SUMPRODUCT(BI$54:BI$113,TRANSPOSE(SAP_Speadsheet!$E$95:$BL$95))} -> 0
A30: PROVISION | B30: {=SUMPRODUCT(B$54:B$113,TRANSPOSE(SAP_Speadsheet!$E$175:$BL$175))} -> 0 | C30: {=SUMPRODUCT(C$54:C$113,TRANSPOSE(SAP_Speadsheet!$E$175:$BL$175))} -> 0 | D30: {=SUMPRODUCT(D$54:D$113,TRANSPOSE(SAP_Speadsheet!$E$175:$BL$175))} -> 0 | E30: {=SUMPRODUCT(E$54:E$113,TRANSPOSE(SAP_Speadsheet!$E$175:$BL$175))} -> 0 | F30: {=SUMPRODUCT(F$54:F$113,TRANSPOSE(SAP_Speadsheet!$E$175:$BL$175))} -> 0 | G30: {=SUMPRODUCT(G$54:G$113,TRANSPOSE(SAP_Speadsheet!$E$175:$BL$175))} -> 0 | H30: {=SUMPRODUCT(H$54:H$113,TRANSPOSE(SAP_Speadsheet!$E$175:$BL$175))} -> 0 | I30: {=SUMPRODUCT(I$54:I$113,TRANSPOSE(SAP_Speadsheet!$E$175:$BL$175))} -> 0 | ... BI30: {=SUMPRODUCT(BI$54:BI$113,TRANSPOSE(SAP_Speadsheet!$E$175:$BL$175))} -> 0
A31: PBT | B31: {=SUMPRODUCT(B$54:B$113,TRANSPOSE(SAP_Speadsheet!$E$181:$BL$181))} -> 0 | C31: {=SUMPRODUCT(C$54:C$113,TRANSPOSE(SAP_Speadsheet!$E$181:$BL$181))} -> 0 | D31: {=SUMPRODUCT(D$54:D$113,TRANSPOSE(SAP_Speadsheet!$E$181:$BL$181))} -> 0 | E31: {=SUMPRODUCT(E$54:E$113,TRANSPOSE(SAP_Speadsheet!$E$181:$BL$181))} -> 0 | F31: {=SUMPRODUCT(F$54:F$113,TRANSPOSE(SAP_Speadsheet!$E$181:$BL$181))} -> 0 | G31: {=SUMPRODUCT(G$54:G$113,TRANSPOSE(SAP_Speadsheet!$E$181:$BL$181))} -> 0 | H31: {=SUMPRODUCT(H$54:H$113,TRANSPOSE(SAP_Speadsheet!$E$181:$BL$181))} -> 0 | I31: {=SUMPRODUCT(I$54:I$113,TRANSPOSE(SAP_Speadsheet!$E$181:$BL$181))} -> 0 | ... BI31: {=SUMPRODUCT(BI$54:BI$113,TRANSPOSE(SAP_Speadsheet!$E$181:$BL$181))} -> 0
A32: Checking | B32: =B9+B18+B30-B31 -> 0 | C32: =C9+C18+C30-C31 -> 0 | D32: =D9+D18+D30-D31 -> 0 | E32: =E9+E18+E30-E31 -> 0 | F32: =F9+F18+F30-F31 -> 0 | G32: =G9+G18+G30-G31 -> 0 | H32: =H9+H18+H30-H31 -> 0 | I32: =I9+I18+I30-I31 -> 0 | ... BI32: =BI9+BI18+BI30-BI31 -> 0
A34: EOP BY BUCKET
A35: B0 | B35: {=SUMPRODUCT(B$54:B$113,TRANSPOSE(SAP_Speadsheet!$E$25:$BL$25))} -> 0 | C35: {=SUMPRODUCT(C$54:C$113,TRANSPOSE(SAP_Speadsheet!$E$25:$BL$25))} -> 0 | D35: {=SUMPRODUCT(D$54:D$113,TRANSPOSE(SAP_Speadsheet!$E$25:$BL$25))} -> 0 | E35: {=SUMPRODUCT(E$54:E$113,TRANSPOSE(SAP_Speadsheet!$E$25:$BL$25))} -> 0 | F35: {=SUMPRODUCT(F$54:F$113,TRANSPOSE(SAP_Speadsheet!$E$25:$BL$25))} -> 0 | G35: {=SUMPRODUCT(G$54:G$113,TRANSPOSE(SAP_Speadsheet!$E$25:$BL$25))} -> 0 | H35: {=SUMPRODUCT(H$54:H$113,TRANSPOSE(SAP_Speadsheet!$E$25:$BL$25))} -> 0 | I35: {=SUMPRODUCT(I$54:I$113,TRANSPOSE(SAP_Speadsheet!$E$25:$BL$25))} -> 0 | ... BI35: {=SUMPRODUCT(BI$54:BI$113,TRANSPOSE(SAP_Speadsheet!$E$25:$BL$25))} -> 0
A36: B1 | B36: {=SUMPRODUCT(B$54:B$113,TRANSPOSE(SAP_Speadsheet!$E$26:$BL$26))} -> 0 | C36: {=SUMPRODUCT(C$54:C$113,TRANSPOSE(SAP_Speadsheet!$E$26:$BL$26))} -> 0 | D36: {=SUMPRODUCT(D$54:D$113,TRANSPOSE(SAP_Speadsheet!$E$26:$BL$26))} -> 0 | E36: {=SUMPRODUCT(E$54:E$113,TRANSPOSE(SAP_Speadsheet!$E$26:$BL$26))} -> 0 | F36: {=SUMPRODUCT(F$54:F$113,TRANSPOSE(SAP_Speadsheet!$E$26:$BL$26))} -> 0 | G36: {=SUMPRODUCT(G$54:G$113,TRANSPOSE(SAP_Speadsheet!$E$26:$BL$26))} -> 0 | H36: {=SUMPRODUCT(H$54:H$113,TRANSPOSE(SAP_Speadsheet!$E$26:$BL$26))} -> 0 | I36: {=SUMPRODUCT(I$54:I$113,TRANSPOSE(SAP_Speadsheet!$E$26:$BL$26))} -> 0 | ... BI36: {=SUMPRODUCT(BI$54:BI$113,TRANSPOSE(SAP_Speadsheet!$E$26:$BL$26))} -> 0
A37: B2 | B37: {=SUMPRODUCT(B$54:B$113,TRANSPOSE(SAP_Speadsheet!$E$27:$BL$27))} -> 0 | C37: {=SUMPRODUCT(C$54:C$113,TRANSPOSE(SAP_Speadsheet!$E$27:$BL$27))} -> 0 | D37: {=SUMPRODUCT(D$54:D$113,TRANSPOSE(SAP_Speadsheet!$E$27:$BL$27))} -> 0 | E37: {=SUMPRODUCT(E$54:E$113,TRANSPOSE(SAP_Speadsheet!$E$27:$BL$27))} -> 0 | F37: {=SUMPRODUCT(F$54:F$113,TRANSPOSE(SAP_Speadsheet!$E$27:$BL$27))} -> 0 | G37: {=SUMPRODUCT(G$54:G$113,TRANSPOSE(SAP_Speadsheet!$E$27:$BL$27))} -> 0 | H37: {=SUMPRODUCT(H$54:H$113,TRANSPOSE(SAP_Speadsheet!$E$27:$BL$27))} -> 0 | I37: {=SUMPRODUCT(I$54:I$113,TRANSPOSE(SAP_Speadsheet!$E$27:$BL$27))} -> 0 | ... BI37: {=SUMPRODUCT(BI$54:BI$113,TRANSPOSE(SAP_Speadsheet!$E$27:$BL$27))} -> 0
A38: B3 | B38: {=SUMPRODUCT(B$54:B$113,TRANSPOSE(SAP_Speadsheet!$E$28:$BL$28))} -> 0 | C38: {=SUMPRODUCT(C$54:C$113,TRANSPOSE(SAP_Speadsheet!$E$28:$BL$28))} -> 0 | D38: {=SUMPRODUCT(D$54:D$113,TRANSPOSE(SAP_Speadsheet!$E$28:$BL$28))} -> 0 | E38: {=SUMPRODUCT(E$54:E$113,TRANSPOSE(SAP_Speadsheet!$E$28:$BL$28))} -> 0 | F38: {=SUMPRODUCT(F$54:F$113,TRANSPOSE(SAP_Speadsheet!$E$28:$BL$28))} -> 0 | G38: {=SUMPRODUCT(G$54:G$113,TRANSPOSE(SAP_Speadsheet!$E$28:$BL$28))} -> 0 | H38: {=SUMPRODUCT(H$54:H$113,TRANSPOSE(SAP_Speadsheet!$E$28:$BL$28))} -> 0 | I38: {=SUMPRODUCT(I$54:I$113,TRANSPOSE(SAP_Speadsheet!$E$28:$BL$28))} -> 0 | ... BI38: {=SUMPRODUCT(BI$54:BI$113,TRANSPOSE(SAP_Speadsheet!$E$28:$BL$28))} -> 0
A39: B4 | B39: {=SUMPRODUCT(B$54:B$113,TRANSPOSE(SAP_Speadsheet!$E$29:$BL$29))} -> 0 | C39: {=SUMPRODUCT(C$54:C$113,TRANSPOSE(SAP_Speadsheet!$E$29:$BL$29))} -> 0 | D39: {=SUMPRODUCT(D$54:D$113,TRANSPOSE(SAP_Speadsheet!$E$29:$BL$29))} -> 0 | E39: {=SUMPRODUCT(E$54:E$113,TRANSPOSE(SAP_Speadsheet!$E$29:$BL$29))} -> 0 | F39: {=SUMPRODUCT(F$54:F$113,TRANSPOSE(SAP_Speadsheet!$E$29:$BL$29))} -> 0 | G39: {=SUMPRODUCT(G$54:G$113,TRANSPOSE(SAP_Speadsheet!$E$29:$BL$29))} -> 0 | H39: {=SUMPRODUCT(H$54:H$113,TRANSPOSE(SAP_Speadsheet!$E$29:$BL$29))} -> 0 | I39: {=SUMPRODUCT(I$54:I$113,TRANSPOSE(SAP_Speadsheet!$E$29:$BL$29))} -> 0 | ... BI39: {=SUMPRODUCT(BI$54:BI$113,TRANSPOSE(SAP_Speadsheet!$E$29:$BL$29))} -> 0
