Workbook
Name IQ_CH: 110000
Name IQ_CQ: 5000
Name IQ_CY: 10000
Name IQ_DAILY: 500000
Name IQ_FH: 100000
Name IQ_FQ: 500
Name IQ_FY: 1000
Name IQ_LTM: 2000
Name IQ_MONTH: 15000
Name IQ_NTM: 6000
Name IQ_WEEK: 50000
Name IQ_YTD: 3000
Name SWITCH_EXPENSES: 1
Name SWITCH_LIABILITIES: 1
Name valuevx: 42.314159

Sheet Revenue
A1: Đơn vị: vnd | E1: 1 | F1: 2 | G1: 3 | H1: 4 | I1: 5 | J1: 6 | K1: 7 | L1: 8 | M1: 9 | N1: 10 | O1: 11 | P1: 12
A2: BeFinancial - CAKE | AH2: BeFinancial - CAKE
A3: Actual | F3: =F29/E29 -> 0.80888653 | G3: =G37/F37 -> 1.2604584 | H3: =H5/G5 -> 0.92674828 | I3: =I5/H5 -> 1.0281138 | J3: =J5/I5 -> 1.0013925 | M3: =L5-M5 -> 3.4969101e+08 | N3: =N5/N59 -> 0.2541237 | Q3: all figures in VND | AG3: 2638255471 | AH3: Budget | AI3: =AI13-AI12 -> 3.6442301e+09 | AJ3: =AJ13-AJ12 -> 3.2475356e+09 | AK3: =AK13-AK12 -> 3.4913905e+09 | AL3: =AL13-AL12 -> 2.9044626e+09 | AM3: =AM13-AM12 -> 3.5440335e+09 | AN3: =AN13-AN12 -> 3.8886047e+09 | AO3: =AO13-AO12 -> 4.1684033e+09 | AP3: =AP13-AP12 -> 4.14009e+09 | ... AT3: =AT13-AT12 -> 4.502786e+09 | AU3: all figures in VNĐ
A4: P&L summary after allocation | B4: % KPI | C4: % KPI | D4: YTD | E4: 45292 | F4: 45323 | G4: 45352 | H4: 45383 | I4: 45413 | J4: 45444 | K4: 45474 | L4: 45505 | M4: 45536 | N4: 45566 | O4: 45597 | P4: 45627 | Q4: 2024 Actual | R4: 2025 YTD | S4: 45658 | T4: 45689 | U4: 45717 | V4: 45748 | W4: 45778 | X4: 45809 | Y4: 45839 | Z4: 45870 | AA4: 45901 | AB4: 45931 | AC4: 45962 | AD4: 45992 | AE4: 2025 Actual | AG4: check | AH4: P&L summary after allocation | AI4: 45658 | AJ4: 45689 | AK4: 45717 | AL4: 45748 | AM4: 45778 | AN4: 45809 | AO4: 45839 | AP4: 45870 | AQ4: 45901 | AR4: 45931 | AS4: 45962 | AT4: 45992 | AU4: 2025 YTD | AV4: 2024 Actual
A5: Income from deposit products | B5: =(R5/1)/AU5 -> 0.59621368 | C5: =IFERROR(B5,0) -> 0.59621368 | D5: =SUM(E5:P5) -> 4.420101e+11 | E5: =SUM(E6:E8) -> 3.540048e+10 | F5: =SUM(F6:F8) -> 33999675821 | G5: =SUM(G6:G8) -> 3.6048406e+10 | H5: =SUM(H6:H8) -> 3.3407799e+10 | I5: =SUM(I6:I8) -> 3.434702e+10 | J5: =SUM(J6:J8) -> 3.4394848e+10 | K5: =SUM(K6:K8) -> 3.6437059e+10 | L5: =SUM(L6:L8) -> 3.740933e+10 | ... P5: =SUM(P6:P8) -> 42362236475 | Q5: =SUM(E5:P5) -> 4.420101e+11 | R5: =SUM(S5:AD5) -> 5.3169539e+11 | S5: =SUM(S6:S8) -> 45837772985 | T5: =SUM(T6:T8) -> 4.5941552e+10 | U5: =SUM(U6:U8) -> 5.4181546e+10 | V5: =SUM(V6:V8) -> 5.5214507e+10 | W5: =SUM(W6:W8) -> 6.1489923e+10 | X5: =SUM(X6:X8) -> 6.2476762e+10 | Y5: =SUM(Y6:Y8) -> 6.7156183e+10 | Z5: =SUM(Z6:Z8) -> 6.9629497e+10 | ... AD5: =SUM(AD6:AD8) -> 0 | AE5: =SUM(S5:AD5) -> 5.3169539e+11 | AH5: Income from deposit products | AI5: =SUM(AI6:AI8) -> 4.4992075e+10 | AJ5: =SUM(AJ6:AJ8) -> 5.0754935e+10 | AK5: =SUM(AK6:AK8) -> 56703006875 | AL5: =SUM(AL6:AL8) -> 6.2629412e+10 | AM5: =SUM(AM6:AM8) -> 6.8012059e+10 | AN5: =SUM(AN6:AN8) -> 7.2850948e+10 | AO5: =SUM(AO6:AO8) -> 77689836875 | AP5: =SUM(AP6:AP8) -> 8.2485392e+10 | ... AT5: =SUM(AT6:AT8) -> 9.969946e+10 | AU5: =SUM(AI5:AT5) -> 8.9178664e+11
A6: CASA | B6: =(R6/1)/AU6 -> 0.47082873 | C6: =IFERROR(B6,0) -> 0.47082873 | D6: =SUM(E6:P6) -> 1.9654287e+10 | E6: 1.4422921e+09 | F6: 1.3553569e+09 | G6: 1.4063825e+09 | H6: 1.3311403e+09 | I6: 1.3718093e+09 | J6: 1.4916783e+09 | K6: 1.7021247e+09 | L6: 1.7710066e+09 | M6: 1.80151e+09 | N6: 2006103524 | O6: 1956116410 | P6: 2018766820 | Q6: =SUM(E6:P6) -> 1.9654287e+10 | R6: =SUM(S6:AD6) -> 2.2585654e+10 | S6: 2223092407 | T6: 1.9887908e+09 | U6: 2.2054323e+09 | V6: 2.2492915e+09 | W6: 2.4533783e+09 | X6: 2.5923384e+09 | Y6: 3.0265847e+09 | Z6: 3.0418351e+09 | AA6: 2.8049108e+09 | AE6: =SUM(S6:AD6) -> 2.2585654e+10 | AH6: CASA | AI6: 2.3183333e+09 | AJ6: 2.7516667e+09 | AK6: 3.12e+09 | AL6: 3.4666667e+09 | AM6: 3.77e+09 | AN6: 4.03e+09 | AO6: 4290000000 | AP6: 4.5066667e+09 | AQ6: 4680000000 | AR6: 4.8533333e+09 | AS6: 5.0266667e+09 | AT6: 5.1566667e+09 | AU6: =SUM(AI6:AT6) -> 47970000000
A7: SS | B7: =(R7/1)/AU7 -> #DIV/0! | C7: =IFERROR(B7,0) -> 0 | D7: =SUM(E7:P7) -> 0 | Q7: =SUM(E7:P7) -> 0 | AE7: =SUM(S7:AD7) -> 0 | AH7: SS | AU7: =SUM(AI7:AT7) -> 0
A8: Term Deposits | B8: =(R8/1)/AU8 -> 0.60334167 | C8: =IFERROR(B8,0) -> 0.60334167 | D8: =SUM(E8:P8) -> 4.2235581e+11 | E8: 3.3958188e+10 | F8: 3.2644319e+10 | G8: 3.4642024e+10 | H8: 3.2076658e+10 | I8: 3.2975211e+10 | J8: 3.2903169e+10 | K8: 3.4734934e+10 | L8: 3.5638324e+10 | M8: 3.5258129e+10 | N8: 38870929658 | O8: 38310454706 | P8: 40343469655 | Q8: =SUM(E8:P8) -> 4.2235581e+11 | R8: =SUM(S8:AD8) -> 5.0910974e+11 | S8: 43614680578 | T8: 4.3952762e+10 | U8: 5.1976113e+10 | V8: 5.2965216e+10 | W8: 5.9036545e+10 | X8: 5.9884423e+10 | Y8: 6.4129598e+10 | Z8: 6.6587662e+10 | AA8: 6.6962735e+10 | AE8: =SUM(S8:AD8) -> 5.0910974e+11 | AH8: Term Deposits | AI8: 4.2673742e+10 | AJ8: 4.8003268e+10 | AK8: 53583006875 | AL8: 5.9162746e+10 | AM8: 6.4242059e+10 | AN8: 6.8820948e+10 | AO8: 73399836875 | AP8: 7.7978726e+10 | AQ8: 8.2557614e+10 | AR8: 87136503125 | AS8: 9.1715392e+10 | AT8: 94542793125 | AU8: =SUM(AI8:AT8) -> 8.4381664e+11
A9: Income from credit products | B9: =(R9/1)/AU9 -> 0.57790099 | C9: =IFERROR(B9,0) -> 0.57790099 | D9: =SUM(E9:P9) -> 8.2857719e+11 | E9: =E10+E14+E17+E20+E23 -> 28828668892 | F9: =F10+F14+F17+F20+F23 -> 30233023471 | G9: =G10+G14+G17+G20+G23 -> 3.1369122e+10 | H9: =H10+H14+H17+H20+H23 -> 3.9956004e+10 | I9: =I10+I14+I17+I20+I23 -> 4.7766964e+10 | J9: =J10+J14+J17+J20+J23 -> 5.5055892e+10 | K9: =K10+K14+K17+K20+K23 -> 75896454114 | L9: =L10+L14+L17+L20+L23 -> 85039924776 | ... P9: =P10+P14+P17+P20+P23 -> 121786257839 | Q9: =SUM(E9:P9) -> 8.2857719e+11 | R9: =SUM(S9:AD9) -> 1.4295451e+12 | S9: =S10+S14+S17+S20+S23 -> 1.2863271e+11 | T9: =T10+T14+T17+T20+T23 -> 1.169575e+11 | U9: =U10+U14+U17+U20+U23 -> 138096338246 | V9: =V10+V14+V17+V20+V23 -> 151078947518 | W9: =W10+W14+W17+W20+W23 -> 168215147029 | X9: =X10+X14+X17+X20+X23 -> 147554709449 | Y9: =Y10+Y14+Y17+Y20+Y23 -> 163239518794 | Z9: =Z10+Z14+Z17+Z20+Z23 -> 197622157190 | ... AD9: =AD10+AD14+AD17+AD20+AD23 -> 0 | AE9: =SUM(S9:AD9) -> 1.4295451e+12 | AH9: Income from credit products | AI9: =AI10+AI14+AI17+AI20+AI23+AI26 -> 1.4329723e+11 | AJ9: =AJ10+AJ14+AJ17+AJ20+AJ23+AJ26 -> 1.5227363e+11 | AK9: =AK10+AK14+AK17+AK20+AK23+AK26 -> 1.6341581e+11 | AL9: =AL10+AL14+AL17+AL20+AL23+AL26 -> 1.7408811e+11 | AM9: =AM10+AM14+AM17+AM20+AM23+AM26 -> 1.8608698e+11 | AN9: =AN10+AN14+AN17+AN20+AN23+AN26 -> 1.9791885e+11 | AO9: =AO10+AO14+AO17+AO20+AO23+AO26 -> 2.1013907e+11 | AP9: =AP10+AP14+AP17+AP20+AP23+AP26 -> 2.2275186e+11 | ... AT9: =AT10+AT14+AT17+AT20+AT23+AT26 -> 2.7604713e+11 | AU9: =SUM(AI9:AT9) -> 2.4736852e+12
A10: Credit card | B10: =(R10/1)/AU10 -> 0.72896863 | C10: =IFERROR(B10,0) -> 0.72896863 | D10: =SUM(E10:P10) -> 167388599156 | E10: =SUM(E11:E13) -> 7623886493 | F10: =SUM(F11:F13) -> 10147956150 | G10: =SUM(G11:G13) -> 7544483878 | H10: =SUM(H11:H13) -> 11676043557 | I10: =SUM(I11:I13) -> 11725540784 | J10: =SUM(J11:J13) -> 12851233295 | K10: =SUM(K11:K13) -> 13232162394 | L10: =SUM(L11:L13) -> 14698185849 | ... P10: =SUM(P11:P13) -> 18530470576 | Q10: =SUM(E10:P10) -> 167388599156 | R10: =SUM(S10:AD10) -> 2.6971099e+11 | S10: =SUM(S11:S13) -> 2.1711338e+10 | T10: =SUM(T11:T13) -> 2.1382921e+10 | U10: =SUM(U11:U13) -> 21692524249 | V10: =SUM(V11:V13) -> 25388538271 | W10: =SUM(W11:W13) -> 31392916810 | X10: =SUM(X11:X13) -> 34885977665 | Y10: =SUM(Y11:Y13) -> 30192067366 | Z10: =SUM(Z11:Z13) -> 40646648749 | ... AD10: =SUM(AD11:AD13) -> 0 | AE10: =SUM(S10:AD10) -> 2.6971099e+11 | AH10: Credit card | AI10: =AI11+AI13+AI12 -> 2.4491782e+10 | AJ10: =AJ11+AJ13+AJ12 -> 2.4660503e+10 | AK10: =AK11+AK13+AK12 -> 2.5711474e+10 | AL10: =AL11+AL13+AL12 -> 2.6474627e+10 | AM10: =AM11+AM13+AM12 -> 2.8400958e+10 | AN10: =AN11+AN13+AN12 -> 2.9979383e+10 | AO10: =AO11+AO13+AO12 -> 3.1526726e+10 | AP10: =AP11+AP13+AP12 -> 3.2796978e+10 | ... AT10: =AT11+AT13+AT12 -> 3.8559833e+10 | AU10: =SUM(AI10:AT10) -> 3.6998984e+11
A11: Interest Income | B11: =(R11/1)/AU11 -> 0.63888265 | C11: =IFERROR(B11,0) -> 0.63888265 | D11: =SUM(E11:P11) -> 95902899947 | E11: =4472730286-2321927855+2335699134 -> 4486501565 | F11: =4580516789+2321927855-1010518810 -> 5891925834 | G11: =5926713484+1010518810+3043745-2819491515 -> 4120784524 | H11: =7180956467+2819491515-2808491427+4091729 -> 7196048284 | I11: =7197889399+2808491427-3154407914 -> 6851972912 | J11: =8279181293+3154407914-3533621420 -> 7899967787 | K11: =7970752555+3533621420-3733269308 -> 7771104667 | L11: =9429096125+3733269308-4206787379 -> 8955578054 | M11: =10110875323+4206787379-4407951982 -> 9909710720 | N11: =10184346142+4407951982-4548658214 -> 10043639910 | O11: =11747409847+4548658214-5034040644 -> 11262027417 | P11: =11718103524+5034040644-5238505895 -> 11513638273 | Q11: =SUM(E11:P11) -> 95902899947 | R11: =SUM(S11:AD11) -> 1.4624591e+11 | S11: =12736.3252655556*10^6 -> 1.2736325e+10 | T11: =12711.793072*10^6 -> 12711793072 | U11: =18302210300-6396782252 -> 11905428048 | V11: 15048779990 | W11: =20038520765-4475367874 -> 15563152891 | X11: 17460193644 | Y11: 17669830163 | Z11: 21451679111 | AA11: 21698728050 | AE11: =SUM(S11:AD11) -> 1.4624591e+11 | AH11: Interest Income | AI11: 1.4715022e+10 | AJ11: 1.500064e+10 | AK11: 1.5518774e+10 | AL11: 1.6570558e+10 | AM11: 1.7549574e+10 | AN11: 1.8466109e+10 | AO11: 1.9406628e+10 | AP11: 2.0368332e+10 | AQ11: 2.1333337e+10 | AR11: 2.2318701e+10 | AS11: 2.3341118e+10 | AT11: 2.4320087e+10 | AU11: =SUM(AI11:AT11) -> 2.2890888e+11
A12: Interchange | B12: =(R12/1)/AU12 -> 0.62553037 | C12: =IFERROR(B12,0) -> 0.62553037 | D12: =SUM(E12:P12) -> 24576789128 | E12: 1179443896 | F12: 1032636916 | G12: 1883604576 | H12: 1578834209 | I12: 2075789609 | J12: =1823578547 -> 1823578547 | K12: 2210803421 | L12: 2137698801 | M12: 2380438413 | N12: 2682994684 | O12: 2609854914 | P12: 2981111142 | Q12: =SUM(E12:P12) -> 24576789128 | R12: =SUM(S12:AD12) -> 2.9444387e+10 | S12: 2326092651 | T12: 3294432114 | U12: 3200762702 | V12: 2818191674 | W12: 3413548040 | X12: 3274779830 | Y12: 3811177050 | Z12: 3483623072 | AA12: 3.8217798e+09 | AE12: =SUM(S12:AD12) -> 2.9444387e+10 | AH12: Interchange | AI12: 3.066265e+09 | AJ12: 3.2061634e+09 | AK12: 3.3506546e+09 | AL12: 3.4998036e+09 | AM12: 3.6536754e+09 | AN12: 3.812335e+09 | AO12: 3.9758476e+09 | AP12: 4.1442781e+09 | AQ12: 4.3176915e+09 | AR12: 4.496153e+09 | AS12: 4.6797275e+09 | AT12: 4.8684801e+09 | AU12: =SUM(AI12:AT12) -> 4.7071075e+10
A13: Fee income | B13: =(R13/1)/AU13 -> 1.0001149 | C13: =IFERROR(B13,0) -> 1.0001149 | D13: =SUM(E13:P13) -> 46908910081 | E13: =2078100221-1777041072+1656881883 -> 1957941032 | F13: =2240721485+1777041072-794369157 -> 3223393400 | G13: =2881710239+794369157-2135984618 -> 1540094778 | H13: =2744496517+2135984618-1979320071 -> 2901161064 | I13: =3016665362+1979320071-2198207170 -> 2797778263 | J13: =3509253994+2198207170-2579774203 -> 3127686961 | K13: =3081788559+2579774203-2552674298+141365842 -> 3250254306 | L13: =4024643118+2552674298-2972408422 -> 3604908994 | M13: =4576228503+2972408422-3177240607 -> 4371396318 | N13: =4497390199+3177240607-3217295228 -> 4457335578 | O13: =12793137531+3217295228-4369194533 -> 11641238226 | P13: =3794145294+4369194533-4127618666 -> 4035721161 | Q13: =SUM(E13:P13) -> 46908910081 | R13: =SUM(S13:AD13) -> 9.4020691e+10 | S13: =8975.01312666667*10^6-S12 -> 6.6489205e+09 | T13: =8671.12787144445*10^6-T12 -> 5.3766958e+09 | U13: =11625545500-5039212001 -> 6586333499 | V13: 7521566607 | W13: =15959900985-5887321470+2343636364 -> 12416215879 | X13: 14151004191 | Y13: 8711060153 | Z13: 15711346566 | AA13: 16897547442 | AE13: =SUM(S13:AD13) -> 9.4020691e+10 | AH13: Fee income | AI13: 6.7104951e+09 | AJ13: 6.453699e+09 | AK13: 6.8420451e+09 | AL13: 6.4042662e+09 | AM13: 7.1977088e+09 | AN13: 7.7009398e+09 | AO13: 8.1442509e+09 | AP13: 8.2843681e+09 | AQ13: =8415426063.98329+1443000000 -> 9.8584261e+09 | AR13: 8.4357429e+09 | AS13: 8.6066813e+09 | AT13: 9.3712661e+09 | AU13: =SUM(AI13:AT13) -> 9.4009889e+10
A14: Cash loan | B14: =(R14/1)/AU14 -> 0.58067341 | C14: =IFERROR(B14,0) -> 0.58067341 | D14: =SUM(E14:P14) -> 4.7718835e+11 | E14: =10130937223-1253000493-10154+1011910704+8044520+3605537323 -> 13503419123 | F14: =10454533267+1253000493+3480522-1545241177-68489+2164718047 -> 12330422663 | G14: =13224508357-1781009381+2721694059 -> 14165193035 | H14: =12480657889+1781009381-3262357-1929235088+5231264000.18855 -> 1.7560434e+10 | I14: =17340858209.331+5852182828 -> 2.3193041e+10 | J14: =18601155077+94707+10677923598+1228568678.77941-2284902288 -> 2.822284e+10 | K14: =30199814953+2284902288-2735072822+15952581491 -> 45702225910 | L14: =38164890166+2735072822-3902972065+14766644848 -> 51763635771 | M14: =40636567084+982792501+3902972065-5064275848+15057642423 -> 55515698225 | N14: =56723522005-6459362775+17219877407 -> 67484036637 | O14: =61334925217-7432024033+16282957435 -> 70185858619 | P14: =60932617104+7432024033-8216161374+17413068347 -> 77561548110 | Q14: =SUM(E14:P14) -> 4.7718835e+11 | R14: =SUM(S14:AD14) -> 9.5993088e+11 | S14: =S15+S16 -> 8.2877028e+10 | T14: =T15+T16 -> 7.3536218e+10 | U14: =U15+U16 -> 90806987870 | V14: =V15+V16 -> 100311182969 | W14: =W15+W16 -> 110191364925 | X14: =X15+X16 -> 96646485412 | Y14: =Y15+Y16 -> 115799565506 | Z14: =Z15+Z16 -> 136486258184 | AA14: =AA15+AA16 -> 153275790568 | AE14: =SUM(S14:AD14) -> 9.5993088e+11 | AH14: Cash loan | AI14: =AI15+AI16 -> 9.2364422e+10 | AJ14: =AJ15+AJ16 -> 9.9649496e+10 | AK14: =AK15+AK16 -> 1.0782682e+11 | AL14: =AL15+AL16 -> 1.1591693e+11 | AM14: =AM15+AM16 -> 1.2402256e+11 | AN14: =AN15+AN16 -> 1.3224206e+11 | AO14: =AO15+AO16 -> 1.4070221e+11 | AP14: =AP15+AP16 -> 1.4971643e+11 | ... AT14: =AT15+AT16 -> 1.8653539e+11 | AU14: =SUM(AI14:AT14) -> 1.6531339e+12
A15: Interest Income | E15: 9822684664 | F15: 10060580608 | G15: 11255014335 | H15: 12126013651 | I15: 17109986037 | J15: 16046492631 | K15: 29242392962 | L15: 35636664319 | M15: 39472033518 | N15: 48402415531 | O15: 51497992410 | P15: 56912007079 | Q15: =SUM(E15:P15) -> 337584277745 | R15: =SUM(S15:AD15) -> 7.9276186e+11 | S15: =63352.4307067778*10^6 -> 6.3352431e+10 | T15: 58657425818 | U15: =76344334175-8811641235 -> 67532692940 | V15: 71488136425 | W15: =91069031847-9633540635 -> 81435491212 | X15: 88142639448 | Y15: 105404205925 | Z15: 121870162370 | AA15: 134878672388 | AI15: 7.0792641e+10 | AJ15: 7.6628826e+10 | AK15: 8.3343191e+10 | AL15: 8.9959762e+10 | AM15: 9.6579176e+10 | AN15: 1.0330576e+11 | AO15: 1.1026494e+11 | AP15: 1.1775678e+11 | AQ15: 1.2546836e+11 | AR15: 1.3303144e+11 | AS15: 1.4060935e+11 | AT15: 1.4846144e+11 | AU15: =SUM(AI15:AT15) -> 1.2962017e+12
A16: Fee income | E16: 3680734459 | F16: 2269842055 | G16: 2910178700 | H16: 5.4344202e+09 | I16: 6.083055e+09 | J16: 1.2176347e+10 | K16: 16459832948 | L16: 16126971452 | M16: 16043664707 | N16: 19081621106 | O16: 18687866209 | P16: 20649541031 | Q16: =SUM(E16:P16) -> 1.3960407e+11 | R16: =SUM(S16:AD16) -> 1.6716902e+11 | S16: =2585208550+16939388929 -> 19524597479 | T16: 1.4878793e+10 | U16: =4357697099+18916597831 -> 23274294930 | V16: =5294534965+23528511579 -> 28823046544 | W16: =5102530001+23653343712 -> 28755873713 | X16: 8503845964 | Y16: 10395359581 | Z16: 14616095814 | AA16: 18397118180 | AI16: 2.1571781e+10 | AJ16: 2.3020671e+10 | AK16: 2.4483624e+10 | AL16: 2.5957168e+10 | AM16: 2.7443381e+10 | AN16: 2.8936294e+10 | AO16: 3.043727e+10 | AP16: 3.195965e+10 | AQ16: 3.3486892e+10 | AR16: 3.5017182e+10 | AS16: 3.6544326e+10 | AT16: 3.8073949e+10 | AU16: =SUM(AI16:AT16) -> 3.5693219e+11
A17: Pay day loan | B17: =(R17/1)/AU17 -> 0.51726684 | C17: =IFERROR(B17,0) -> 0.51726684 | D17: =SUM(E17:P17) -> 1.2836178e+11 | E17: =1731837685-27551638+74763964+3024414731 -> 4803464742 | F17: =1893405606+27551638-58249898+3016914165 -> 4879621511 | G17: =2433097916-43185351+3959227879.2 -> 6.3491404e+09 | H17: =2738252099+43185351-41105355+4667859999.7037 -> 7.4081921e+09 | I17: =3395471237+5796804892 -> 9192276129 | J17: =3609434923+6424397168-56271600 -> 9977560491 | K17: =4540246107+56271600-47851261+7851414034 -> 12400080480 | L17: =4985545722+47851261-77340097+8520985077 -> 13477041963 | M17: =5060551048+77340097-75500112+8309967451 -> 13372358484 | N17: =5558900401-96699988+9087046603 -> 14549247016 | O17: =5321181281-77091089+8427493438 -> 13671583630 | P17: =6675824625+77091089-135438883+11663739212 -> 18281216043 | Q17: =SUM(E17:P17) -> 1.2836178e+11 | R17: =SUM(S17:AD17) -> 1.2069203e+11 | S17: =S18+S19 -> 1.6267745e+10 | T17: =T18+T19 -> 14704552067 | U17: =U18+U19 -> 17050685748 | V17: =V18+V19 -> 16823379156 | W17: =W18+W19 -> 17302527583 | X17: =X18+X19 -> 6648549132 | Y17: =Y18+Y19 -> 7509366443 | Z17: =Z18+Z19 -> 10664313763 | AA17: =AA18+AA19 -> 13720914092 | AE17: =SUM(S17:AD17) -> 1.2069203e+11 | AH17: Pay day loan | AI17: =AI18+AI19 -> 1.667638e+10 | AJ17: =AJ18+AJ19 -> 1.7204842e+10 | AK17: =AK18+AK19 -> 1.7898854e+10 | AL17: =AL18+AL19 -> 1.834654e+10 | AM17: =AM18+AM19 -> 1.8802133e+10 | AN17: =AN18+AN19 -> 1.9259966e+10 | AO17: =AO18+AO19 -> 1.9714454e+10 | AP17: =AP18+AP19 -> 2.016686e+10 | ... AT17: =AT18+AT19 -> 2.2005117e+10 | AU17: =SUM(AI17:AT17) -> 2.3332644e+11
A18: Interest Income | E18: 1779050011 | F18: 1862707346 | G18: 2389912565 | H18: 2740332095 | I18: 3395471237 | J18: 3553163323 | K18: 4548666446 | L18: 4956056886 | M18: 5062391033 | N18: 5462200413 | O18: 5244090192 | P18: 6508988960 | Q18: =SUM(E18:P18) -> 47503030507 | R18: =SUM(S18:AD18) -> 7.0085585e+10 | S18: =6617.74465811111*10^6 -> 6.6177447e+09 | T18: =5508.505087*10^6 -> 5508505087 | U18: =6359746765-106193778 -> 6253552987 | V18: 6473661986 | W18: =6794376825-105399665 -> 6688977160 | X18: 6648549132 | Y18: 7509366443 | Z18: 10664313763 | AA18: 13720914092 | AI18: 6.1097463e+09 | AJ18: 6.339575e+09 | AK18: 6.7349535e+09 | AL18: 6.8840063e+09 | AM18: 7.0409663e+09 | AN18: 7.2001661e+09 | AO18: 7.3560206e+09 | AP18: 7.5097937e+09 | AQ18: 7.6606517e+09 | AR18: 7.8267751e+09 | AS18: 8.0008724e+09 | AT18: 8.1535168e+09 | AU18: =SUM(AI18:AT18) -> 8.6817044e+10
A19: Fee income | E19: 3024414731 | F19: 3016914165 | G19: 3.9592279e+09 | H19: 4.66786e+09 | I19: 5796804892 | J19: 6424397168 | K19: 7851414034 | L19: 8520985077 | M19: 8309967451 | N19: 9087046603 | O19: 8427493438 | P19: 11772227083 | Q19: =SUM(E19:P19) -> 8.0858753e+10 | R19: =SUM(S19:AD19) -> 50606447334 | S19: =9650*10^6 -> 9650000000 | T19: =9196.04698*10^6 -> 9196046980 | U19: 10797132761 | V19: 10349717170 | W19: 10613550423 | AI19: 1.0566633e+10 | AJ19: 1.0865267e+10 | AK19: 11163900000 | AL19: 1.1462533e+10 | AM19: 1.1761167e+10 | AN19: 1.20598e+10 | AO19: 1.2358433e+10 | AP19: 1.2657067e+10 | AQ19: 1.29557e+10 | AR19: 1.3254333e+10 | AS19: 1.3552967e+10 | AT19: 1.38516e+10 | AU19: =SUM(AI19:AT19) -> 1.465094e+11
A20: Paylater | B20: =(R20/1)/AU20 -> 0.59310015 | C20: =IFERROR(B20,0) -> 0.59310015 | D20: =SUM(E20:P20) -> 3124798247 | I20: 51061059 | J20: 125496366 | K20: =220940096+7973965-16167166 -> 212746895 | L20: =332748242+16167166-28944690 -> 319970718 | M20: =398037448+28944690-35276697 -> 391705441 | N20: =631534237-47352518 -> 584181719 | O20: =778169229-76040535 -> 702128694 | P20: =742339674+76040535-80872854 -> 737507355 | Q20: =SUM(E20:P20) -> 3124798247 | R20: =SUM(S20:AD20) -> 1.5923103e+10 | S20: =S21+S22 -> 8.8099864e+08 | T20: =T21+T22 -> 1069140221 | U20: =U21+U22 -> 1292789944 | V20: =V21+V22 -> 1351132922 | W20: =W21+W22 -> 1656385562 | X20: =X21+X22 -> 1875945039 | Y20: =Y21+Y22 -> 2091044528 | Z20: =Z21+Z22 -> 2673230298 | AA20: =AA21+AA22 -> 3032435697 | AE20: =SUM(S20:AD20) -> 1.5923103e+10 | AH20: BNPL | AI20: =AI21+AI22 -> 9.0247627e+08 | AJ20: =AJ21+AJ22 -> 1.1216932e+09 | AK20: =AK21+AK22 -> 1.4016528e+09 | AL20: =AL21+AL22 -> 1.6370788e+09 | AM20: =AM21+AM22 -> 1.86424e+09 | AN20: =AN21+AN22 -> 2.0893812e+09 | AO20: =AO21+AO22 -> 2.3259799e+09 | AP20: =AP21+AP22 -> 2.5601171e+09 | ... AT20: =AT21+AT22 -> 3.6888245e+09 | AU20: =SUM(AI20:AT20) -> 2.6847241e+10
A21: Interest Income | Q21: =SUM(E21:P21) -> 0 | R21: =SUM(S21:AD21) -> 5328377346 | T21: 189915753 | U21: =370785283-92711511 -> 278073772 | V21: 426213283 | W21: =520699092-30445764 -> 490253328 | X21: 569261256 | Y21: 689302043 | Z21: 1147845494 | AA21: 1537512417 | AI21: 1.401837e+08 | AJ21: 2.3568613e+08 | AK21: 3.4890238e+08 | AL21: 4.2448901e+08 | AM21: 4.9248507e+08 | AN21: 5.6492392e+08 | AO21: 6.3333331e+08 | AP21: 7.0170999e+08 | AQ21: 7.7858062e+08 | AR21: 8.6046062e+08 | AS21: 9.4546277e+08 | AT21: 1.0339184e+09 | AU21: =SUM(AI21:AT21) -> 7.1601359e+09
A22: Fee income | I22: 51061059 | J22: 125496366 | K22: =220940096+7973965-16167166 -> 212746895 | L22: =332748242+16167166-28944690 -> 319970718 | M22: =398037448+28944690-35276697 -> 391705441 | N22: =631534237-47352518 -> 584181719 | O22: =778169229-76040535 -> 702128694 | P22: =742339674+76040535-80872854 -> 737507355 | Q22: =SUM(E22:P22) -> 3124798247 | R22: =SUM(S22:AD22) -> 1.0594726e+10 | S22: =880.998637777778*10^6 -> 8.8099864e+08 | T22: 879224468 | U22: =1047083553-32367381 -> 1014716172 | V22: 924919639 | W22: =1278245610-112113376 -> 1166132234 | X22: 1306683783 | Y22: 1401742485 | Z22: 1525384804 | AA22: 1494923280 | AI22: 7.6229257e+08 | AJ22: 8.8600709e+08 | AK22: 1.0527505e+09 | AL22: 1.2125898e+09 | AM22: 1.3717549e+09 | AN22: 1.5244573e+09 | AO22: 1.6926466e+09 | AP22: 1.8584071e+09 | AQ22: 2.0283575e+09 | AR22: 2.216563e+09 | AS22: 2.4263729e+09 | AT22: 2.6549061e+09 | AU22: =SUM(AI22:AT22) -> 1.9687105e+10
A23: OD | B23: =(R23/1)/AU23 -> 0.41685544 | C23: =IFERROR(B23,0) -> 0.41685544 | D23: =SUM(E23:P23) -> 52513659020 | E23: =2916044602-230672955+212526887 -> 2897898534 | F23: =2898187184+230672955-253836992 -> 2875023147 | G23: =3601198061-290893363 -> 3310304698 | H23: =3292565159+290893363-272123540 -> 3311334982 | I23: =3895474182-290429443 -> 3605044739 | J23: =4152301850-273539921 -> 3878761929 | K23: =4382422078+273539921-306723564 -> 4349238435 | L23: =4840554142+306723564-366187231 -> 4781090475 | M23: =4794154299+412500000+366187231-421958623 -> 5150882907 | N23: =6199397537-452554320 -> 5746843217 | O23: =6421892830-490172628 -> 5931720202 | P23: =6756112570+490172628-570769443 -> 6675515755 | Q23: =SUM(E23:P23) -> 52513659020 | R23: =SUM(S23:AD23) -> 63288131261 | S23: =S24+S25 -> 6895598820 | T23: =T24+T25 -> 6264667900 | U23: =U24+U25 -> 7253350435 | V23: =V24+V25 -> 7204714200 | W23: =W24+W25 -> 7671952149 | X23: =X24+X25 -> 7497752201 | Y23: =Y24+Y25 -> 7647474951 | Z23: =Z24+Z25 -> 7151706196 | AA23: =AA24+AA25 -> 5700914409 | AE23: =SUM(S23:AD23) -> 63288131261 | AH23: OD | AI23: =AI24+AI25 -> 8.5282818e+09 | AJ23: =AJ24+AJ25 -> 8.973108e+09 | AK23: =AK24+AK25 -> 9.4903448e+09 | AL23: =AL24+AL25 -> 1.0150084e+10 | AM23: =AM24+AM25 -> 1.0908966e+10 | AN23: =AN24+AN25 -> 1.1689184e+10 | AO23: =AO24+AO25 -> 1.2596839e+10 | AP23: =AP24+AP25 -> 1.3584069e+10 | ... AT23: =AT24+AT25 -> 1.8363632e+10 | AU23: =SUM(AI23:AT23) -> 1.5182273e+11
A24: Interest Income | E24: 2676498534 | F24: 2741523147 | G24: 3160104698 | H24: 3180434982 | I24: 3437444739 | J24: 3575578015 | K24: 4036838435 | L24: 4433490475 | M24: 4738382907 | N24: 5294443217 | O24: 5481470202 | P24: 5950915755 | Q24: =SUM(E24:P24) -> 48707125106 | R24: =SUM(S24:AD24) -> 59625711261 | S24: =6314.54882*10^6 -> 6314548820 | T24: =5836.8679*10^6 -> 5836867900 | U24: =7447549794-706549359 -> 6741000435 | V24: 6690164200 | W24: =7974378518-820276369 -> 7154102149 | X24: 6970752201 | Y24: 7222124951 | Z24: 7073356196 | AA24: 5622794409 | AI24: 7.5903136e+09 | AJ24: 7.9896194e+09 | AK24: 8.4584409e+09 | AL24: 9.0669944e+09 | AM24: 9.772028e+09 | AN24: 1.0495827e+10 | AO24: 1.1344574e+10 | AP24: 1.2270478e+10 | AQ24: 1.3283406e+10 | AR24: 1.4374695e+10 | AS24: 1.55481e+10 | AT24: 1.6781696e+10 | AU24: =SUM(AI24:AT24) -> 1.3697617e+11
A25: Fee income | E25: 221400000 | F25: 133500000 | G25: 150200000 | H25: 130900000 | I25: 167600000 | J25: 303183914 | K25: 312400000 | L25: 347600000 | M25: 412500000 | N25: 452400000 | O25: 450250000 | P25: 724600000 | Q25: =SUM(E25:P25) -> 3806533914 | R25: =SUM(S25:AD25) -> 3662420000 | S25: 581050000 | T25: 427800000 | U25: 512350000 | V25: 514550000 | W25: 517850000 | X25: 527000000 | Y25: 425350000 | Z25: 78350000 | AA25: 78120000 | AI25: 9.3796813e+08 | AJ25: 9.8348858e+08 | AK25: 1.0319038e+09 | AL25: 1.0830894e+09 | AM25: 1.136938e+09 | AN25: 1.1933568e+09 | AO25: 1.2522646e+09 | AP25: 1.3135907e+09 | AQ25: 1.3772728e+09 | AR25: 1.443256e+09 | AS25: 1.5114915e+09 | AT25: 1.5819362e+09 | AU25: =SUM(AI25:AT25) -> 1.4846557e+10
A26: TW | B26: =(R26/1)/AU26 -> 0 | R26: =SUM(S26:AD26) -> 0 | S26: =S27+S28 -> 0 | AE26: =SUM(S26:AD26) -> 0 | AH26: TW | AI26: =AI27+AI28 -> 3.3388889e+08 | AJ26: =AJ27+AJ28 -> 6.6399239e+08 | AK26: =AK27+AK28 -> 1.0866648e+09 | AL26: =AL27+AL28 -> 1.5628474e+09 | AM26: =AM27+AM28 -> 2.088128e+09 | AN26: =AN27+AN28 -> 2.6588783e+09 | AO26: =AO27+AO28 -> 3.2728626e+09 | AP26: =AP27+AP28 -> 3.927407e+09 | ... AT26: =AT27+AT28 -> 6.894333e+09 | AU26: =SUM(AI26:AT26) -> 3.8565123e+10
A27: Interest Income | R27: =SUM(S27:AD27) -> 0 | AI27: 68055556 | AJ27: 1.3232572e+08 | AK27: 2.891648e+08 | AL27: 4.9951409e+08 | AM27: 7.5896129e+08 | AN27: 1.0638783e+09 | AO27: 1.4120292e+09 | AP27: 1.8007404e+09 | AQ27: 2.2273985e+09 | AR27: 2.6897924e+09 | AS27: 3.1837866e+09 | AT27: 3.7041304e+09 | AU27: =SUM(AI27:AT27) -> 1.7829777e+10
A28: Fee income | R28: =SUM(S28:AD28) -> 0 | AI28: 2.6583333e+08 | AJ28: 5.3166667e+08 | AK28: 7.975e+08 | AL28: 1.0633333e+09 | AM28: 1.3291667e+09 | AN28: 1.595e+09 | AO28: 1.8608333e+09 | AP28: 2.1266667e+09 | AQ28: 2392500000 | AR28: 2.6583698e+09 | AS28: 2.9242732e+09 | AT28: 3.1902026e+09 | AU28: =SUM(AI28:AT28) -> 2.0735346e+10
A29: Fee Income | B29: =(R29/1)/AU29 -> 0.20063723 | C29: =IFERROR(B29,0) -> 0.20063723 | D29: =SUM(E29:P29) -> 9.7215869e+10 | E29: =E30+E37+E43+E47+E50+E51+E34+E33 -> 823965395 | F29: =F30+F37+F43+F47+F50+F51+F34+F33 -> 6.6649451e+08 | G29: =G30+G37+G43+G47+G50+G51+G34+G33 -> 3738401916 | H29: =H30+H37+H43+H47+H50+H51+H34+H33 -> 1650605437 | I29: =I30+I37+I43+I47+I50+I51+I34+I33 -> 3.2030179e+09 | J29: =J30+J37+J43+J47+J50+J33+J34 -> 793890764 | K29: =K30+K37+K43+K47+K50+K51+K34+K33 -> 5.7604825e+09 | L29: =L30+L37+L43+L47+L50+L51+L34+L33 -> 17789506696 | M29: =M30+M37+M43+M47+M50+M51+M34+M33 -> 892636698 | N29: =N30+N37+N43+N47+N50+N51+N34+N33 -> 14429550885 | O29: =O30+O37+O43+O47+O50+O51+O34+O33 -> 6150919522 | P29: =P30+P37+P43+P47+P50+P51+P34+P33 -> 41316396324 | Q29: =SUM(E29:P29) -> 9.7215869e+10 | R29: =SUM(S29:AD29) -> 1.8741163e+10 | S29: =S30+S37+S43+S47+S50+S51+S34+S33+S46 -> 1419604308 | T29: =T30+T37+T43+T47+T50+T51+T34+T33+T46 -> 1.5423438e+09 | U29: =U30+U37+U43+U47+U50+U51+U34+U33+U46 -> 1.0729186e+09 | V29: =V30+V37+V43+V47+V50+V51+V34+V33+V46 -> 1443861435 | W29: =W30+W37+W43+W47+W50+W51+W34+W33+W46 -> 6288457136 | X29: =X30+X37+X43+X47+X50+X51+X34+X33+X46 -> 1.1170783e+09 | Y29: =Y30+Y37+Y43+Y47+Y50+Y51+Y34+Y33+Y46 -> 2751844521 | Z29: =Z30+Z37+Z43+Z47+Z50+Z51+Z34+Z33+Z46 -> 1559497946 | ... AD29: =AD30+AD37+AD43+AD47+AD50+AD51+AD34+AD33+AD46 -> 0 | AE29: =SUM(S29:AD29) -> 1.8741163e+10 | AH29: Fee Income | AI29: =AI30+AI37+AI43+AI47+AI50+AI51+AI33+AI34+AI35+AI36+AI46 -> 4.0589908e+09 | AJ29: =AJ30+AJ37+AJ43+AJ47+AJ50+AJ51+AJ33+AJ34+AJ35+AJ36+AJ46 -> 3.7314255e+09 | AK29: =AK30+AK37+AK43+AK47+AK50+AK51+AK33+AK34+AK35+AK36+AK46 -> 3.8067205e+09 | AL29: =AL30+AL37+AL43+AL47+AL50+AL51+AL33+AL34+AL35+AL36+AL46 -> 3.8873523e+09 | AM29: =AM30+AM37+AM43+AM47+AM50+AM51+AM33+AM34+AM35+AM36+AM46 -> 3.9657127e+09 | AN29: =AN30+AN37+AN43+AN47+AN50+AN51+AN33+AN34+AN35+AN36+AN46 -> 4.0480827e+09 | AO29: =AO30+AO37+AO43+AO47+AO50+AO51+AO33+AO34+AO35+AO36+AO46 -> 4.4344645e+09 | AP29: =AP30+AP37+AP43+AP47+AP50+AP51+AP33+AP34+AP35+AP36+AP46 -> 4.2152485e+09 | ... AT29: =AT30+AT37+AT43+AT47+AT50+AT51+AT33+AT34+AT35+AT36+AT46 -> 4.2822934e+10 | AU29: =SUM(AI29:AT29) -> 9.3408206e+10
A30: Commission from Payoo | B30: =(R30/1)/AU30 -> 0.45867847 | C30: =IFERROR(B30,0) -> 0.45867847 | D30: =SUM(E30:P30) -> 9.7412922e+08 | E30: =SUM(E31:E32) -> 114156931 | F30: =SUM(F31:F32) -> 60407573 | G30: =SUM(G31:G32) -> 69962901 | H30: =SUM(H31:H32) -> 67952746 | I30: =SUM(I31:I32) -> 76903891 | J30: =SUM(J31:J32) -> 75315209 | K30: =SUM(K31:K32) -> 79216437 | L30: =SUM(L31:L32) -> 78941409 | ... P30: =SUM(P31:P32) -> 83485307 | Q30: =SUM(E30:P30) -> 9.7412922e+08 | R30: =SUM(S30:AD30) -> 6.2326612e+08 | S30: =SUM(S31:S32) -> 77716977 | T30: =SUM(T31:T32) -> 67309473 | U30: =SUM(U31:U32) -> 76734210 | V30: =SUM(V31:V32) -> 74361945 | W30: =SUM(W31:W32) -> 71059507 | X30: =SUM(X31:X32) -> 6169630.1 | Y30: =SUM(Y31:Y32) -> 80344691 | Z30: =SUM(Z31:Z32) -> 84933690 | ... AD30: =SUM(AD31:AD32) -> 0 | AE30: =SUM(S30:AD30) -> 6.2326612e+08 | AH30: Commission from Payoo | AI30: =AI31+AI32 -> 64662170 | AJ30: =AJ31+AJ32 -> 75517869 | AK30: =AK31+AK32 -> 85520079 | AL30: =AL31+AL32 -> 95767673 | AM30: =AM31+AM32 -> 1.0395349e+08 | AN30: =AN31+AN32 -> 1.1233027e+08 | AO30: =AO31+AO32 -> 1.2090022e+08 | AP30: =AP31+AP32 -> 1.2726437e+08 | ... AT30: =AT31+AT32 -> 1.5156919e+08 | AU30: =SUM(AI30:AT30) -> 1.3588301e+09
A31: Bill Payment | B31: =(R31/1)/AU31 -> 0.010757861 | C31: =IFERROR(B31,0) -> 0.010757861 | D31: =SUM(E31:P31) -> 14983636 | E31: 1573636.4 | F31: 1421818.2 | G31: =1379000/1.1 -> 1253636.4 | H31: 1391818.2 | I31: =1422500/1.1 -> 1293181.8 | J31: 1375909.1 | K31: 841818.18 | L31: 993636.36 | M31: 885000 | N31: 1115909.1 | O31: 1439545.5 | P31: 1397727.3 | Q31: =SUM(E31:P31) -> 14983636 | R31: =SUM(S31:AD31) -> 13921273 | S31: 1378181.8 | T31: 1378181.8 | U31: 2486090.9 | V31: 2486090.9 | W31: 1249090.9 | X31: 1235909.1 | Y31: 1235909.1 | Z31: 1235909.1 | AA31: 1235909.1 | AE31: =SUM(S31:AD31) -> 13921273 | AH31: Bill Payment | AI31: 61872230 | AJ31: 72201736 | AK31: 81700561 | AL31: 91420037 | AM31: 99159286 | AN31: 1.0707034e+08 | AO31: 1.1515523e+08 | AP31: 1.2113051e+08 | AQ31: 1.2722819e+08 | AR31: 1.3344967e+08 | AS31: 1.3979634e+08 | AT31: 1.4387174e+08 | AU31: =SUM(AI31:AT31) -> 1.2940559e+09
A32: Mobile top-up | B32: =(R32/1)/AU32 -> 9.4072064 | C32: =IFERROR(B32,0) -> 9.4072064 | D32: =SUM(E32:P32) -> 9.5914559e+08 | E32: 1.1258329e+08 | F32: =60407573-1421818 -> 58985755 | G32: =69962901-G31 -> 68709265 | H32: 66560928 | I32: 75610709 | J32: 73939300 | K32: 78374619 | L32: =78941409-L31 -> 77947773 | M32: 90847836 | N32: 86677646 | O32: =88260427-O31 -> 86820882 | P32: =83485307-P31 -> 82087580 | Q32: =SUM(E32:P32) -> 9.5914559e+08 | R32: =SUM(S32:AD32) -> 6.0934485e+08 | S32: =77716977-S31 -> 76338795 | T32: =67309473-T31 -> 65931291 | U32: 74248119 | V32: 71875854 | W32: 69810416 | X32: =76541703-X33 -> 4933721 | Y32: 79108782 | Z32: 83697781 | AA32: 83400089 | AE32: =SUM(S32:AD32) -> 6.0934485e+08 | AH32: Mobile top-up | AI32: 2789940.2 | AJ32: 3316133.3 | AK32: 3819518.2 | AL32: 4347636.4 | AM32: 4794204.5 | AN32: 5259927.3 | AO32: 5744995.5 | AP32: 6133866.7 | AQ32: 6536250 | AR32: 6952272.7 | AS32: 7382062.1 | AT32: 7697454.5 | AU32: =SUM(AI32:AT32) -> 64774261
A33: Napas fee income | B33: =(R33/1)/AU33 -> 0.53168549 | C33: =IFERROR(B33,0) -> 0.53168549 | D33: =SUM(E33:P33) -> 528350355 | F33: 61642364 | G33: 33262203 | H33: 58847346 | I33: 30940911 | J33: 46558669 | K33: 46783626 | L33: 47703750 | M33: 48341777 | N33: 55670830 | O33: 49765206 | P33: 48833673 | Q33: =SUM(E33:P33) -> 528350355 | R33: =SUM(S33:AD33) -> 483946610 | S33: 52295822 | T33: 50487578 | U33: 44293151 | V33: 43798961 | W33: 48940205 | X33: 71607982 | Y33: 50937668 | Z33: 54885138 | AA33: 66700105 | AE33: =SUM(S33:AD33) -> 483946610 | AH33: Napas fee income | AI33: 45807801 | AJ33: 53014500 | AK33: 59496341 | AL33: 66029727 | AM33: 71036080 | AN33: 76081091 | AO33: 81164761 | AP33: 84689182 | AQ33: 88239375 | AR33: 91815341 | AS33: 95417080 | AT33: 97420909 | AU33: =SUM(AI33:AT33) -> 9.1021219e+08
A34: VNpay | B34: =(R34/1)/AU34 -> #DIV/0! | C34: =IFERROR(B34,0) -> 0 | D34: =SUM(E34:P34) -> 74604660 | F34: 8369568 | G34: 15938225 | I34: 16558020 | N34: 10545568 | O34: 10742450 | P34: 12450829 | R34: =SUM(S34:AD34) -> 106428124 | S34: 9620432 | T34: 12192592 | U34: 13700326 | W34: 20341309 | X34: 29331878 | Z34: 14921132 | AA34: 6320455 | AE34: =SUM(S34:AD34) -> 106428124 | AH34: VNpay | AI34: 0 | AJ34: 0 | AK34: 0 | AL34: 0 | AM34: 0 | AN34: 0 | AO34: 0 | AP34: 0 | AQ34: 0 | AR34: 0 | AS34: 0 | AT34: 0 | AU34: =SUM(AI34:AT34) -> 0
A35: Vietlot | B35: =(R35/1)/AU35 -> 0 | R35: =SUM(S35:AD35) -> 0 | AE35: =SUM(S35:AD35) -> 0 | AH35: Vietlot | AI35: 1689545.5 | AJ35: 3894545.5 | AK35: 6529090.9 | AL35: 9621818.2 | AM35: 12886364 | AN35: 16494545 | AO35: 20446364 | AP35: 24283636 | AQ35: 28350000 | AR35: 32645455 | AS35: 37170000 | AT35: 41236364 | AU35: =SUM(AI35:AT35) -> 2.3524773e+08
A36: Traveloka | B36: =(R36/1)/AU36 -> 0 | R36: =SUM(S36:AD36) -> 0 | AE36: =SUM(S36:AD36) -> 0 | AH36: Traveloka | AI36: 14079545 | AJ36: 32454545 | AK36: 54409091 | AL36: 80181818 | AM36: 1.0738636e+08 | AN36: 1.3745455e+08 | AO36: 1.7038636e+08 | AP36: 2.0236364e+08 | AQ36: 2.3625e+08 | AR36: 2.7204545e+08 | AS36: 3.0975e+08 | AT36: 3.4363636e+08 | AU36: =SUM(AI36:AT36) -> 1.9603977e+09
A37: Fee from Mastercard | B37: =(R37/1)/AU37 -> 0.24457789 | C37: =IFERROR(B37,0) -> 0.24457789 | D37: =SUM(E37:P37) -> 7.5885395e+09 | E37: =SUM(E38:E42) -> 642152995 | F37: =SUM(F38:F42) -> 491270025 | G37: =SUM(G38:G42) -> 619225414 | H37: =SUM(H38:H42) -> 547410709 | I37: =SUM(I38:I42) -> 712714978 | J37: =SUM(J38:J42) -> 649861962 | K37: =SUM(K38:K42) -> 7.5052302e+08 | L37: =SUM(L38:L42) -> 732763491 | ... P37: =SUM(P38:P42) -> 552194063 | Q37: =SUM(E37:P37) -> 7.5885395e+09 | R37: =SUM(S37:AD37) -> 3.5879882e+09 | S37: =SUM(S38:S42) -> 435886294 | T37: =SUM(T38:T42) -> 5.4851277e+08 | U37: =SUM(U38:U42) -> 281741112 | V37: =SUM(V38:V42) -> 261531231 | W37: =SUM(W38:W42) -> 375170209 | X37: =SUM(X38:X42) -> 408463753 | Y37: =SUM(Y38:Y42) -> 415417975 | Z37: =SUM(Z38:Z42) -> 443390529 | ... AD37: =SUM(AD38:AD42) -> 0 | AE37: =SUM(S37:AD37) -> 3.5879882e+09 | AH37: Fee from Mastercard | AI37: =AI38+AI39+AI42+AI40+AI41 -> 6.310404e+08 | AJ37: =AJ38+AJ39+AJ42+AJ40+AJ41 -> 658580400 | AK37: =AK38+AK39+AK42+AK40+AK41 -> 686120400 | AL37: =AL38+AL39+AL42+AL40+AL41 -> 713660400 | AM37: =AM38+AM39+AM42+AM40+AM41 -> 741200400 | AN37: =AN38+AN39+AN42+AN40+AN41 -> 768740400 | AO37: =AO38+AO39+AO42+AO40+AO41 -> 796280400 | AP37: =AP38+AP39+AP42+AP40+AP41 -> 823820400 | ... AT37: =AT38+AT39+AT42+AT40+AT41 -> 933980400 | AU37: =SUM(AI37:AT37) -> 14670124800
A38: Interchange fee from MasterCard | B38: =(R38/1)/AU38 -> #DIV/0! | C38: =IFERROR(B38,0) -> 0 | E38: 367451124 | F38: =252272418+97007 -> 252369425 | G38: 322171949 | H38: 284943281 | I38: 374396772 | J38: =287.919075*10^6 -> 287919075 | K38: 297599228 | L38: 212819314 | M38: 76198938 | Q38: =SUM(E38:P38) -> 2475869106 | R38: =SUM(S38:AD38) -> 0 | AE38: =SUM(S38:AD38) -> 0 | AU38: =SUM(AI38:AT38) -> 0
A39: FX fee from MasterCard | B39: =(R39/1)/AU39 -> #DIV/0! | C39: =IFERROR(B39,0) -> 0 | E39: 246601871 | F39: 218450600 | G39: 271803465 | H39: 240067428 | I39: 312968206 | J39: =233.29254*10^6 -> 233292540 | K39: 217382455 | L39: 167449444 | M39: 59723887 | Q39: =SUM(E39:P39) -> 1967739896 | R39: =SUM(S39:AD39) -> 0 | AE39: =SUM(S39:AD39) -> 0 | AU39: =SUM(AI39:AT39) -> 0
A40: Interchange fee from Visa | J40: 123150347 | K40: 2.3554134e+08 | L40: =296749175+55745558 -> 352494733 | M40: =562948852 -> 562948852 | N40: 608148561 | O40: 583402642 | P40: 552194063 | R40: =SUM(S40:AD40) -> 3.5879882e+09 | S40: 435886294 | T40: =548.512773333333*10^6 -> 5.4851277e+08 | U40: 281741112 | V40: 261531231 | W40: 375170209 | X40: 408463753 | Y40: 415417975 | Z40: 443390529 | AA40: 417874297 | AI40: 1.158864e+08 | AJ40: 123026400 | AK40: 1.301664e+08 | AL40: 137306400 | AM40: 1.444464e+08 | AN40: 1.515864e+08 | AO40: 158726400 | AP40: 1.658664e+08 | AQ40: =173006400+5280000000 -> 5453006400 | AR40: 1.801464e+08 | AS40: 187286400 | AT40: 194426400 | AU40: =SUM(AI40:AT40) -> 7141876800
A41: Fx mark up | AI41: 3.31104e+08 | AJ41: 351504000 | AK41: 3.71904e+08 | AL41: 392304000 | AM41: 4.12704e+08 | AN41: 4.33104e+08 | AO41: 4.53504e+08 | AP41: 4.73904e+08 | AQ41: 4.94304e+08 | AR41: 5.14704e+08 | AS41: 535104000 | AT41: 555504000 | AU41: =SUM(AI41:AT41) -> 5319648000
A42: Reissue Card | B42: =(R42/1)/AU42 -> 0 | C42: =IFERROR(B42,0) -> 0 | E42: 28100000 | F42: 20450000 | G42: 25250000 | H42: 22400000 | I42: 25350000 | J42: 5500000 | Q42: =SUM(E42:P42) -> 127050000 | R42: =SUM(S42:AD42) -> 0 | AE42: =SUM(S42:AD42) -> 0 | AI42: 184050000 | AJ42: 184050000 | AK42: 184050000 | AL42: 184050000 | AM42: 184050000 | AN42: 184050000 | AO42: 184050000 | AP42: 184050000 | AQ42: 184050000 | AR42: 184050000 | AS42: 184050000 | AT42: 184050000 | AU42: =SUM(AI42:AT42) -> 2208600000
A43: Micro investment | B43: =(R43/1)/AU43 -> 0.40928881 | C43: =IFERROR(B43,0) -> 0.40928881 | D43: =SUM(E43:P43) -> 3.2282676e+08 | E43: =E44+E45 -> 24704248 | F43: =F44+F45 -> 14067065 | G43: =G44+G45 -> 18238324 | H43: =H44+H45 -> 19897209 | I43: =I44+I45 -> 22154924 | J43: =J44+J45 -> 22154924 | K43: =K44+K45 -> 32141265 | L43: =L44+L45 -> 29692629 | ... P43: =P44+P45 -> 35246295 | Q43: =SUM(E43:P43) -> 3.2282676e+08 | R43: =SUM(S43:AD43) -> 294439578 | S43: =S44+S45 -> 33657088 | T43: =T44+T45 -> 30406692 | U43: =U44+U45 -> 32744379 | V43: =V44+V45 -> 31163899 | W43: =W44+W45 -> 34677614 | X43: =X44+X45 -> 33978281 | Y43: =Y44+Y45 -> 36796055 | Z43: =Z44+Z45 -> 30507785 | ... AD43: =AD44+AD45 -> 0 | AE43: =SUM(S43:AD43) -> 294439578 | AH43: Micro investment | AI43: =AI44+AI45 -> 19711364 | AJ43: =AJ44+AJ45 -> 25963636 | AK43: =AK44+AK45 -> 32645455 | AL43: =AL44+AL45 -> 40090909 | AM43: =AM44+AM45 -> 47250000 | AN43: =AN44+AN45 -> 54981818 | AO43: =AO44+AO45 -> 63286364 | AP43: =AP44+AP45 -> 70827273 | ... AT43: =AT44+AT45 -> 1.0309091e+08 | AU43: =SUM(AI43:AT43) -> 7.1939318e+08
A44: Interest Income | B44: =(R44/1)/AU44 -> 0 | C44: =IFERROR(B44,0) -> 0 | D44: =SUM(E44:P44) -> 0 | Q44: =SUM(E44:P44) -> 0 | R44: =SUM(S44:AD44) -> 0 | AE44: =SUM(S44:AD44) -> 0 | AH44: Interest Income | AI44: 19711364 | AJ44: 25963636 | AK44: 32645455 | AL44: 40090909 | AM44: 47250000 | AN44: 54981818 | AO44: 63286364 | AP44: 70827273 | AQ44: 78750000 | AR44: 87054545 | AS44: 95740909 | AT44: 1.0309091e+08 | AU44: =SUM(AI44:AT44) -> 7.1939318e+08
A45: Bonus + support fee | B45: =(R45/1)/AU45 -> #DIV/0! | C45: =IFERROR(B45,0) -> 0 | D45: =SUM(E45:P45) -> 3.2282676e+08 | E45: 24704248 | F45: 14067065 | G45: 18238324 | H45: 19897209 | I45: =22.154924*10^6 -> 22154924 | J45: =22.154924*10^6 -> 22154924 | K45: 32141265 | L45: =29.692629*10^6 -> 29692629 | M45: 35579935 | N45: 34671406 | O45: 34278538 | P45: 35246295 | Q45: =SUM(E45:P45) -> 3.2282676e+08 | R45: =SUM(S45:AD45) -> 294439578 | S45: =33.657088*10^6 -> 33657088 | T45: =30.406692*10^6 -> 30406692 | U45: 32744379 | V45: 31163899 | W45: 34677614 | X45: 33978281 | Y45: 36796055 | Z45: 30507785 | AA45: 30507785 | AE45: =SUM(S45:AD45) -> 294439578 | AH45: Bonus + support fee | AU45: =SUM(AI45:AT45) -> 0
A46: Other incomes | R46: =SUM(S46:AD46) -> 867167655 | S46: 267038014 | U46: 134707885 | V46: 68913930 | W46: 117350035 | X46: 82271760 | Y46: 80848132 | Z46: 60519231 | AA46: 55518668 | AI46: 1750000000 | AJ46: 1750000000 | AK46: 1750000000 | AL46: 1750000000 | AM46: 1750000000 | AN46: 1750000000 | AO46: 1750000000 | AP46: 1750000000 | AQ46: 1750000000 | AR46: 1750000000 | AS46: 1750000000 | AT46: 1750000000 | AU46: =SUM(AI46:AT46) -> 21000000000
A47: Insurance | B47: =(R47/1)/AU47 -> #DIV/0! | C47: =IFERROR(B47,0) -> 0 | D47: =SUM(E47:P47) -> 0 | Q47: =SUM(E47:P47) -> 0 | R47: =SUM(S47:AD47) -> 0 | AE47: =SUM(S47:AD47) -> 0 | AH47: Insurance | AU47: =SUM(AI47:AT47) -> 0
A48: Loan insurance | B48: =(R48/1)/AU48 -> #DIV/0! | C48: =IFERROR(B48,0) -> 0 | D48: =SUM(E48:P48) -> 0 | Q48: =SUM(E48:P48) -> 0 | R48: =SUM(S48:AD48) -> 0 | AE48: =SUM(S48:AD48) -> 0 | AH48: Loan insurance | AI48: 0 | AJ48: 0 | AK48: 0 | AL48: 0 | AM48: 0 | AN48: 0 | AO48: 0 | AP48: 0 | AQ48: 0 | AR48: 0 | AS48: 0 | AT48: 0 | AU48: =SUM(AI48:AT48) -> 0
A49: Personal accident insurance | B49: =(R49/1)/AU49 -> #DIV/0! | C49: =IFERROR(B49,0) -> 0 | D49: =SUM(E49:P49) -> 0 | Q49: =SUM(E49:P49) -> 0 | R49: =SUM(S49:AD49) -> 0 | AE49: =SUM(S49:AD49) -> 0 | AH49: Personal accident insurance | AI49: 0 | AJ49: 0 | AK49: 0 | AL49: 0 | AM49: 0 | AN49: 0 | AO49: 0 | AP49: 0 | AQ49: 0 | AR49: 0 | AS49: 0 | AT49: 0 | AU49: =SUM(AI49:AT49) -> 0
A50: Fractional share | B50: =(R50/1)/AU50 -> #DIV/0! | C50: =IFERROR(B50,0) -> 0 | D50: =SUM(E50:P50) -> 20082884657 | P50: 20082884657 | Q50: =SUM(E50:P50) -> 20082884657 | R50: =SUM(S50:AD50) -> 0 | AE50: =SUM(S50:AD50) -> 0 | AH50: Fractional share | AI50: 0 | AJ50: 0 | AK50: 0 | AL50: 0 | AM50: 0 | AN50: 0 | AO50: 0 | AP50: 0 | AQ50: 0 | AR50: 0 | AS50: 0 | AT50: 0 | AU50: =SUM(AI50:AT50) -> 0
A51: Other | B51: =(R51/1)/AU51 -> 0.243139 | C51: =IFERROR(B51,0) -> 0.243139 | D51: =SUM(E51:P51) -> 81401978888 | E51: =42.951221*10^6 -> 42951221 | F51: =30.737917*10^6 -> 30737917 | G51: 2981774849 | H51: 956497427 | I51: =231186024+1817659011+294900128 -> 2343745163 | J51: =3333660846+9664163366-10860591+770.481894*10^6 -> 13757445515 | K51: =1850000000+3001818182 -> 4851818182 | L51: =16844.423638*10^6+55981779 -> 16900405417 | M51: 18110473 | N51: 13632720965 | O51: =933048178+4451422081 -> 5384470259 | P51: =418416843+20082884657 -> 20501301500 | Q51: =SUM(E51:P51) -> 81401978888 | R51: =SUM(S51:AD51) -> 1.2777927e+10 | S51: =SUM(S52:S58) -> 543389681 | T51: =SUM(T52:T58) -> 833434644 | U51: =SUM(U52:U58) -> 4.8899754e+08 | V51: =SUM(V52:V58) -> 964091469 | W51: =SUM(W52:W58) -> 5620918257 | X51: =SUM(X52:X58) -> 485255000 | Y51: =SUM(Y52:Y58) -> 2087500000 | Z51: =SUM(Z52:Z58) -> 870340441 | AA51: =SUM(AA52:AA58) -> 884000000 | AE51: =SUM(S51:AD51) -> 1.2777927e+10 | AH51: Others | AI51: =SUM(AI52:AI58) -> 1532000000 | AJ51: =SUM(AJ52:AJ58) -> 1132000000 | AK51: =SUM(AK52:AK58) -> 1132000000 | AL51: =SUM(AL52:AL58) -> 1132000000 | AM51: =SUM(AM52:AM58) -> 1132000000 | AN51: =SUM(AN52:AN58) -> 1132000000 | AO51: =SUM(AO52:AO58) -> 1432000000 | AP51: =SUM(AP52:AP58) -> 1132000000 | ... AT51: =SUM(AT52:AT58) -> 39402000000 | AU51: =SUM(AI51:AT51) -> 52554000000
A52: Smart OTP | R52: =SUM(S52:AD52) -> 1127748000 | S52: 20000000 | T52: 20000000 | U52: 20000000 | V52: 20000000 | W52: 937748000 | X52: 20000000 | Y52: 30000000 | Z52: 30000000 | AA52: 30000000 | AI52: 30000000 | AJ52: 30000000 | AK52: 30000000 | AL52: 30000000 | AM52: 30000000 | AN52: 30000000 | AO52: 30000000 | AP52: 30000000 | AQ52: 30000000 | AR52: 30000000 | AS52: 30000000 | AT52: 14000000000 | AU52: =SUM(AI52:AT52) -> 14330000000
A53: EKYC | R53: =SUM(S53:AD53) -> 3600000000 | S53: 400000000 | T53: 400000000 | U53: 400000000 | V53: 400000000 | W53: 400000000 | X53: 400000000 | Y53: 400000000 | Z53: 400000000 | AA53: 400000000 | AI53: 0 | AJ53: 0 | AK53: 0 | AL53: 0 | AM53: 0 | AN53: 0 | AO53: 0 | AP53: 0 | AQ53: 0 | AR53: 0 | AS53: 0 | AT53: 24000000000 | AU53: =SUM(AI53:AT53) -> 24000000000
A54: Check RAR | R54: =SUM(S54:AD54) -> 0 | AI54: 850000000 | AJ54: 450000000 | AK54: 450000000 | AL54: 450000000 | AM54: 450000000 | AN54: 450000000 | AO54: 450000000 | AP54: 450000000 | AQ54: 450000000 | AR54: 450000000 | AS54: 450000000 | AT54: 450000000 | AU54: =SUM(AI54:AT54) -> 5800000000
A55: Face Authen | R55: =SUM(S55:AD55) -> 0 | AI55: 0 | AJ55: 0 | AK55: 0 | AL55: 0 | AM55: 0 | AN55: 0 | AO55: 300000000 | AP55: 0 | AQ55: 0 | AR55: 0 | AS55: 0 | AT55: 300000000 | AU55: =SUM(AI55:AT55) -> 600000000
A56: Data Score | R56: =SUM(S56:AD56) -> 0 | AI56: 83333333 | AJ56: 83333333 | AK56: 83333333 | AL56: 83333333 | AM56: 83333333 | AN56: 83333333 | AO56: 83333333 | AP56: 83333333 | AQ56: 83333333 | AR56: 83333333 | AS56: 83333333 | AT56: 83333333 | AU56: =SUM(AI56:AT56) -> 1e+09
A57: C-ticket | R57: =SUM(S57:AD57) -> 7.4466206e+09 | S57: 49937736 | T57: 339982699 | U57: 5997539.6 | V57: 497005399 | W57: 4208156786 | Y57: 1588000000 | Z57: 3.7304044e+08 | AA57: 384500000 | AI57: 5.0666667e+08 | AJ57: 5.0666667e+08 | AK57: 5.0666667e+08 | AL57: 5.0666667e+08 | AM57: 5.0666667e+08 | AN57: 5.0666667e+08 | AO57: 5.0666667e+08 | AP57: 5.0666667e+08 | AQ57: 5.0666667e+08 | AR57: 5.0666667e+08 | AS57: 5.0666667e+08 | AT57: 5.0666667e+08 | AU57: =SUM(AI57:AT57) -> 6.08e+09
A58: Others (1900 FPT) | R58: =SUM(S58:AD58) -> 603558431 | S58: 73451945 | T58: 73451945 | U58: 63000000 | V58: =116000000-V46 -> 47086070 | W58: 75013471 | X58: 65255000 | Y58: 69500000 | Z58: 67300000 | AA58: 69500000 | AI58: 62000000 | AJ58: 62000000 | AK58: 62000000 | AL58: 62000000 | AM58: 62000000 | AN58: 62000000 | AO58: 62000000 | AP58: 62000000 | AQ58: 62000000 | AR58: 62000000 | AS58: 62000000 | AT58: 62000000 | AU58: =SUM(AI58:AT58) -> 744000000
A59: Total | B59: =(R59/1)/AU59 -> 0.57243433 | C59: =IFERROR(B59,0) -> 0.57243433 | D59: =SUM(E59:P59) -> 1.3815606e+12 | E59: =E5+E9+E29 -> 6.5053115e+10 | F59: =F5+F9+F29 -> 6.4899194e+10 | G59: =G5+G9+G29 -> 7.115593e+10 | H59: =H5+H9+H29 -> 7.5014409e+10 | I59: =I5+I9+I29 -> 8.5317002e+10 | J59: =J5+J9+J29+J51 -> 1.0400208e+11 | K59: =K5+K9+K29 -> 1.18094e+11 | L59: =L5+L9+L29 -> 1.4023876e+11 | M59: =M5+M9+M29 -> 1.2904447e+11 | N59: =N5+N9+N29 -> 160854862828 | O59: =O5+O9+O29 -> 162421902340 | P59: =P5+P9+P29 -> 205464890638 | Q59: =SUM(E59:P59) -> 1.3815606e+12 | R59: =SUM(S59:AD59) -> 1.9799817e+12 | S59: =S5+S9+S29 -> 1.7589009e+11 | T59: =T5+T9+T29 -> 1.644414e+11 | U59: =U5+U9+U29 -> 1.933508e+11 | V59: =V5+V9+V29 -> 2.0773732e+11 | W59: =W5+W9+W29 -> 2.3599353e+11 | X59: =X5+X9+X29 -> 2.1114855e+11 | Y59: =Y5+Y9+Y29 -> 2.3314755e+11 | Z59: =Z5+Z9+Z29 -> 2.6881115e+11 | ... AD59: =AD5+AD9+AD29 -> 0 | AE59: =SUM(S59:AD59) -> 1.9799817e+12 | AH59: Total | AI59: =AI5+AI9+AI29 -> 1.923483e+11 | AJ59: =AJ5+AJ9+AJ29 -> 2.0675999e+11 | AK59: =AK5+AK9+AK29 -> 2.2392553e+11 | AL59: =AL5+AL9+AL29 -> 2.4060487e+11 | AM59: =AM5+AM9+AM29 -> 2.5806475e+11 | AN59: =AN5+AN9+AN29 -> 2.7481788e+11 | AO59: =AO5+AO9+AO29 -> 2.9226338e+11 | AP59: =AP5+AP9+AP29 -> 3.094525e+11 | ... AT59: =AT5+AT9+AT29 -> 4.1856953e+11 | AU59: =SUM(AI59:AT59) -> 3.4588801e+12
A60: Growth MoM | C60: =IFERROR(B60,0) -> 0 | AX60: =AI60*10^9 -> 0 | AY60: =AJ60*10^9 -> 0 | AZ60: =AK60*10^9 -> 0 | BA60: =AL60*10^9 -> 0 | BB60: =AM60*10^9 -> 0 | BC60: =AN60*10^9 -> 0 | BD60: =AO60*10^9 -> 0 | BE60: =AP60*10^9 -> 0 | ... BI60: =AT60*10^9 -> 0
C61: =IFERROR(B61,0) -> 0 | D61: =D5/D59 -> 0.31993537 | AX61: =AI61*10^9 -> 0 | AY61: =AJ61*10^9 -> 0 | AZ61: =AK61*10^9 -> 0 | BA61: =AL61*10^9 -> 0 | BB61: =AM61*10^9 -> 0 | BC61: =AN61*10^9 -> 0 | BD61: =AO61*10^9 -> 0 | BE61: =AP61*10^9 -> 0 | ... BI61: =AT61*10^9 -> 0
A62: Check | AI62: =AI59/10^9 -> 192.3483 | AJ62: =AJ59/10^9 -> 206.75999 | AK62: =AK59/10^9 -> 223.92553 | AL62: =AL59/10^9 -> 240.60487 | AM62: =AM59/10^9 -> 258.06475 | AN62: =AN59/10^9 -> 274.81788 | AO62: =AO59/10^9 -> 292.26338 | AP62: =AP59/10^9 -> 309.4525 | ... AT62: =AT59/10^9 -> 418.56953 | AX62: =AI62*10^9 -> 1.923483e+11 | AY62: =AJ62*10^9 -> 2.0675999e+11 | AZ62: =AK62*10^9 -> 2.2392553e+11 | BA62: =AL62*10^9 -> 2.4060487e+11 | BB62: =AM62*10^9 -> 2.5806475e+11 | BC62: =AN62*10^9 -> 2.7481788e+11 | BD62: =AO62*10^9 -> 2.9226338e+11 | BE62: =AP62*10^9 -> 3.094525e+11 | ... BI62: =AT62*10^9 -> 4.1856953e+11
AC64: =AC59+AC62+AC63 -> 0 | AU64: 3523000000000
C65: Target 2023 | D65: Actual 2023 | E65: Gap | F65: %Actual/Target | AU65: =AU64-AU59 -> 6.4119922e+10
A66: Deposit | C66: =C67+C68 -> 8.9178664e+11 | D66: =D67+D68 -> 4.420101e+11 | E66: =D66-C66 -> -4.4977654e+11 | F66: =D66/C66 -> 0.49564557
A67: Casa | C67: =AU6 -> 47970000000 | D67: =D6 -> 1.9654287e+10 | E67: =D67-C67 -> -2.8315713e+10 | F67: =D67/C67 -> 0.4097204 | P67: 5.88521e+10
A68: TD | C68: =AU7+AU8 -> 8.4381664e+11 | D68: =D8 -> 4.2235581e+11 | E68: =D68-C68 -> -4.2146082e+11 | F68: =D68/C68 -> 0.50053032 | P68: =P59-P67 -> 1.4661279e+11
A69: Fee income | C69: =AU29 -> 9.3408206e+10 | D69: =D29 -> 9.7215869e+10 | E69: =D69-C69 -> 3.8076628e+09 | F69: =D69/C69 -> 1.0407637 | AI69: 0.18405 | AJ69: 0.18405 | AK69: 0.18405 | AL69: 0.18405 | AM69: 0.18405 | AN69: 0.18405 | AO69: 0.18405 | AP69: 0.18405 | AQ69: 0.18405 | AR69: 0.18405 | AS69: 0.18405 | AT69: 0.18405
A70: Other (Smart OTP) | C70: =AU51 -> 52554000000 | E70: =D70-C70 -> -52554000000 | F70: =D70/C70 -> 0
A71: Lending | C71: =SUM(C72:C75) -> 2.4082729e+12 | D71: =SUM(D72:D75) -> 8.2545239e+11 | E71: =D71-C71 -> -1.5828205e+12 | F71: =D71/C71 -> 0.342757
A72: Credit card | C72: =AU10 -> 3.6998984e+11 | D72: =D10 -> 167388599156 | E72: =D72-C72 -> -2.0260124e+11 | F72: =D72/C72 -> 0.45241404
A73: Payday | C73: =AU17 -> 2.3332644e+11 | D73: =D17 -> 1.2836178e+11 | E73: =D73-C73 -> -1.0496466e+11 | F73: =D73/C73 -> 0.55013817 | AX73: =AI73*10^9 -> 0 | AY73: =AJ73*10^9 -> 0 | AZ73: =AK73*10^9 -> 0 | BA73: =AL73*10^9 -> 0 | BB73: =AM73*10^9 -> 0 | BC73: =AN73*10^9 -> 0 | BD73: =AO73*10^9 -> 0 | BE73: =AP73*10^9 -> 0 | ... BI73: =AT73*10^9 -> 0
A74: Cash loan | C74: =AU14 -> 1.6531339e+12 | D74: =D14 -> 4.7718835e+11 | E74: =D74-C74 -> -1.1759455e+12 | F74: =D74/C74 -> 0.28865681 | AX74: =AI74*10^9 -> 0 | AY74: =AJ74*10^9 -> 0 | AZ74: =AK74*10^9 -> 0 | BA74: =AL74*10^9 -> 0 | BB74: =AM74*10^9 -> 0 | BC74: =AN74*10^9 -> 0 | BD74: =AO74*10^9 -> 0 | BE74: =AP74*10^9 -> 0 | ... BI74: =AT74*10^9 -> 0
A75: OD | C75: =AU23 -> 1.5182273e+11 | D75: =D23 -> 52513659020 | E75: =D75-C75 -> -9.9309071e+10 | F75: =D75/C75 -> 0.34588799 | AX75: =AI75*10^9 -> 0 | AY75: =AJ75*10^9 -> 0 | AZ75: =AK75*10^9 -> 0 | BA75: =AL75*10^9 -> 0 | BB75: =AM75*10^9 -> 0 | BC75: =AN75*10^9 -> 0 | BD75: =AO75*10^9 -> 0 | BE75: =AP75*10^9 -> 0 | ... BI75: =AT75*10^9 -> 0
A76: Total revenue | C76: =C66+C69+C70+C71 -> 3.4460217e+12 | D76: =D66+D69+D71 -> 1.3646784e+12 | E76: =D76-C76 -> -2.0813434e+12 | F76: =D76/C76 -> 0.3960156 | AX76: =AI76*10^9 -> 0 | AY76: =AJ76*10^9 -> 0 | AZ76: =AK76*10^9 -> 0 | BA76: =AL76*10^9 -> 0 | BB76: =AM76*10^9 -> 0 | BC76: =AN76*10^9 -> 0 | BD76: =AO76*10^9 -> 0 | BE76: =AP76*10^9 -> 0 | ... BI76: =AT76*10^9 -> 0
K118: 22898373

Sheet EBITDA
A1: Đơn vị: Tỷ VNĐ
A2: BeFinancial - CAKE | B2: 11 | AF2: BeFinancial - CAKE
A3: Actual | B3: 1 | O3: =O16-O59 -> 118.0348 | S3: =Q30+R30+S30+Q77+R77+S77 -> 176.63408 | AF3: Budget
A5: CHỈ TIÊU | B5: % KPI | C5: YTD 2024 | D5: 45292 | E5: 45323 | F5: 45352 | G5: 45383 | H5: 45413 | I5: 45444 | J5: 45474 | K5: 45505 | L5: 45536 | M5: 45566 | N5: 45597 | O5: 45627 | P5: YTD 2025 | Q5: 45658 | R5: 45689 | S5: 45717 | T5: 45748 | U5: 45778 | V5: 45809 | W5: 45839 | X5: 45870 | Y5: 45901 | Z5: 45931 | AA5: 45962 | AB5: 45992 | AE5: CHỈ TIÊU | AF5: 45292 | AG5: 45323 | AH5: 45352 | AI5: 45383 | AJ5: 45413 | AK5: 45444 | AL5: 45474 | AM5: 45505 | AN5: 45536 | AO5: 45566 | AP5: 45597 | AQ5: 45627 | AR5: 2024 YTD | AS5: 2024 FY Budget | AT5: 45658 | AU5: 45689 | AV5: 45717 | AW5: 45748 | AX5: 45778 | AY5: 45809 | AZ5: 45839 | BA5: 45870 | BB5: 45901 | BC5: 45931 | BD5: 45962 | BE5: 45992 | BF5: 2025 YTD | BG5: 2025 FY Budget
A6: Disbursement | C6: =SUM(C7:C9) -> 223.13779 | D6: 201.39047 | E6: 152.77505 | F6: 181.82287 | G6: 229.69441 | H6: 256.22206 | I6: 320.05572 | J6: 363.26119 | K6: 395.4963 | L6: 434.77299 | M6: 473.80811 | N6: 420.42575 | O6: 470.23176 | P6: =SUM(OFFSET(Q6,0,$B$2-1):OFFSET(Q6,0,$B$3-1)) -> 0 | Q6: =SUM(Q7:Q9) -> 0 | R6: =SUM(R7:R9) -> 0 | S6: =SUM(S7:S9) -> 0 | T6: =SUM(T7:T9) -> 0 | U6: =SUM(U7:U9) -> 0 | V6: =SUM(V7:V9) -> 0 | W6: =SUM(W7:W9) -> 0 | X6: =SUM(X7:X9) -> 0 | ... AB6: =SUM(AB7:AB9) -> 0
A7: Cashloan | C7: =104585050000/10^9+4.263 -> 108.84805 | D7: 91.98835 | E7: 55.1652 | F7: 57.30889 | G7: 99.39909 | H7: 112.69616 | I7: 155.31388 | J7: 167.74406 | K7: 187.16389 | L7: 223.05886 | M7: 236.45691 | N7: 192.34919 | O7: 186.92712 | P7: =SUM(OFFSET(Q7,0,$B$2-1):OFFSET(Q7,0,$B$3-1)) -> 0
A8: Payday | C8: =38479500000/10^9 -> 38.4795 | D8: 43.961 | E8: 43.7385 | F8: 59.82 | G8: 67.741 | H8: 79.375 | I8: 93.3155 | J8: 114.003 | K8: 123.6105 | L8: 120.6545 | M8: 132.0375 | N8: 122.399 | O8: 169.8025 | P8: =SUM(OFFSET(Q8,0,$B$2-1):OFFSET(Q8,0,$B$3-1)) -> 0
A9: OD | C9: =75810236516/10^9 -> 75.810237 | D9: 65.441115 | E9: 53.871348 | F9: 64.693978 | G9: 62.554322 | H9: 64.150902 | I9: 71.426344 | J9: 81.514133 | K9: 84.72191 | L9: 91.059627 | M9: 105.3137 | N9: 105.67756 | O9: 113.50214 | P9: =SUM(OFFSET(Q9,0,$B$2-1):OFFSET(Q9,0,$B$3-1)) -> 0
A10: Balance | C10: =SUM(C11:C13) -> 6568.6498 | D10: 6990.6146 | E10: 7769.8141 | F10: 7841.8873 | G10: 8007.8578 | H10: 8577.2974 | I10: 8933.6391 | J10: 9389.6329 | K10: 9888.5933 | L10: 10496.431 | M10: 11015.993 | N10: 11280.538 | O10: 11653.887 | P10: =SUM(OFFSET(Q10,0,$B$2-1):OFFSET(Q10,0,$B$3-1)) -> 0 | Q10: =SUM(Q11:Q13) -> 0 | R10: =SUM(R11:R13) -> 0 | S10: =SUM(S11:S13) -> 0 | T10: =SUM(T11:T13) -> 0 | U10: =SUM(U11:U13) -> 0 | V10: =SUM(V11:V13) -> 0 | W10: =SUM(W11:W13) -> 0 | X10: =SUM(X11:X13) -> 0 | ... AB10: =SUM(AB11:AB13) -> 0
A11: Deposit | C11: =5673632553487/10^9 -> 5673.6326 | D11: 5985.4749 | E11: 6648.7962 | F11: 6605.514 | G11: 6625.9513 | H11: 7043.2664 | I11: 7299.9562 | J11: 7420.9175 | K11: 7660.9151 | L11: 7995.1687 | M11: 8274.0444 | N11: 8302.5022 | O11: 8480.7301 | P11: =SUM(OFFSET(Q11,0,$B$2-1):OFFSET(Q11,0,$B$3-1)) -> 0
A12: Lending | C12: =464182732087/10^9 -> 464.18273 | D12: 548.28836 | E12: 586.4096 | F12: 627.47499 | G12: 707.96482 | H12: 797.51277 | I12: 1017.9536 | J12: 1304.91 | K12: 1493.3742 | L12: 1695.5337 | M12: 1900.5866 | N12: 2052.4385 | O12: 2208.6912 | P12: =SUM(OFFSET(Q12,0,$B$2-1):OFFSET(Q12,0,$B$3-1)) -> 0
A13: Credit card | C13: =430834551930/10^9 -> 430.83455 | D13: 456.85133 | E13: 534.60833 | F13: 608.89833 | G13: 673.94167 | H13: 736.51824 | I13: 615.72933 | J13: 663.80537 | K13: 734.30399 | L13: 805.72849 | M13: 841.3621 | N13: 925.5971 | O13: 964.46527 | P13: =SUM(OFFSET(Q13,0,$B$2-1):OFFSET(Q13,0,$B$3-1)) -> 0
A14: REVENUE | B14: =P14/BG14 -> 0.64021911 | C14: =SUM(OFFSET(D14,0,$B$2-1):OFFSET(D14,0,$B$3-1)) -> 1268.0859 | D14: 65.089663 | E14: 64.885127 | F14: 71.156486 | G14: 75.007954 | H14: 85.291264 | I14: 103.96575 | J14: 136.4 | K14: 158.66772 | L14: 147.60043 | M14: 179.22531 | N14: 180.79622 | O14: 201.77328 | P14: =SUM(OFFSET(Q14,0,$B$2-1):OFFSET(Q14,0,$B$3-1)) -> 2214.4411 | Q14: 175.89947 | R14: 164.43364 | S14: 193.3508 | T14: 207.73738 | U14: 233.49353 | V14: 249.8301 | W14: 288.30868 | X14: 323.17577 | Y14: 378.21176 | AE14: REVENUE | AF14: 76.361358 | AG14: 75.639602 | AH14: 89.144128 | AI14: 103.58462 | AJ14: 119.25741 | AK14: 133.78752 | AL14: 147.33206 | AM14: 159.45381 | AN14: 172.66297 | AO14: 188.54409 | AP14: 202.67058 | AQ14: 224.48205 | AR14: =SUM(OFFSET(AF14,0,$B$2-1):OFFSET(AF14,0,$B$3-1)) -> 1468.4381 | AS14: =SUM(AF14:AQ14) -> 1692.9202 | AT14: 192.3483 | AU14: 206.75999 | AV14: 223.92553 | AW14: 240.60487 | AX14: 258.06475 | AY14: 274.81788 | AZ14: 292.26338 | BA14: 309.4525 | BB14: 333.9849 | BC14: 344.99816 | BD14: 363.09028 | BE14: 418.56953 | BF14: =SUM(OFFSET(AT14,0,$B$2-1):OFFSET(AT14,0,$B$3-1)) -> 3040.3106 | BG14: =SUM(AT14:BE14) -> 3458.8801
A15: EXPENSE | B15: =P15/BG15 -> 0.59071707 | C15: =SUM(OFFSET(D15,0,$B$2-1):OFFSET(D15,0,$B$3-1)) -> 569.91307 | D15: 38.990543 | E15: 38.557637 | F15: 40.01737 | G15: 37.6 | H15: 41.080038 | I15: 41.844071 | J15: 63.091627 | K15: 66.073304 | L15: 64.281654 | M15: 69.767832 | N15: 68.608996 | O15: 73.830938 | P15: =SUM(OFFSET(Q15,0,$B$2-1):OFFSET(Q15,0,$B$3-1)) -> 665.79169 | Q15: 60.596165 | R15: 58.535619 | S15: 66.146837 | T15: 67.024054 | U15: 74.810398 | V15: 72.353886 | W15: 83.685087 | X15: 89.812774 | Y15: 92.826868 | AE15: EXPENSE | AF15: 34.261358 | AG15: 36.739602 | AH15: 37.844128 | AI15: 43.084616 | AJ15: 46.657413 | AK15: 49.387519 | AL15: 51.332059 | AM15: 54.853814 | AN15: 58.062968 | AO15: 61.844089 | AP15: 65.670581 | AQ15: 33.082046 | AR15: =SUM(OFFSET(AF15,0,$B$2-1):OFFSET(AF15,0,$B$3-1)) -> 539.73815 | AS15: =SUM(AF15:AQ15) -> 572.82019 | AT15: =AT14-AT16 -> 59.663763 | AU15: =AU14-AU16 -> 65.941375 | AV15: =AV14-AV16 -> 72.724618 | AW15: =AW14-AW16 -> 79.441977 | AX15: =AX14-AX16 -> 85.68105 | AY15: =AY14-AY16 -> 91.509141 | AZ15: =AZ14-AZ16 -> 97.355548 | BA15: =BA14-BA16 -> 103.21068 | ... BE15: =BE14-BE16 -> 125.63807 | BF15: =SUM(OFFSET(AT15,0,$B$2-1):OFFSET(AT15,0,$B$3-1)) -> 1001.4526 | BG15: =SUM(AT15:BE15) -> 1127.0906
A16: Total TOI | B16: =P16/BG16 -> 0.66414635 | C16: =SUM(OFFSET(D16,0,$B$2-1):OFFSET(D16,0,$B$3-1)) -> 698.17286 | D16: 26.09912 | E16: 26.327489 | F16: 31.139116 | G16: 37.407954 | H16: 44.211226 | I16: 62.121678 | J16: 73.308373 | K16: 92.594417 | L16: 83.318778 | M16: 109.45748 | N16: 112.18722 | O16: 127.94235 | P16: =SUM(OFFSET(Q16,0,$B$2-1):OFFSET(Q16,0,$B$3-1)) -> 1548.6494 | Q16: =Q14-Q15 -> 115.30331 | R16: =R14-R15 -> 105.89802 | S16: =S14-S15 -> 127.20397 | T16: =T14-T15 -> 140.71332 | U16: =U14-U15 -> 158.68313 | V16: =V14-V15 -> 177.47622 | W16: =W14-W15 -> 204.62359 | X16: =X14-X15 -> 233.363 | ... AB16: =AB14-AB15 -> 0 | AE16: Total TOI | AF16: =AF17+AF21+AF24 -> 42.1 | AG16: =AG17+AG21+AG24 -> 38.9 | AH16: =AH17+AH21+AH24 -> 51.3 | AI16: =AI17+AI21+AI24 -> 60.5 | AJ16: =AJ17+AJ21+AJ24 -> 72.6 | AK16: =AK17+AK21+AK24 -> 84.4 | AL16: =AL17+AL21+AL24 -> 96 | AM16: =AM17+AM21+AM24 -> 104.6 | ... AQ16: =AQ17+AQ21+AQ24 -> 191.4 | AR16: =SUM(OFFSET(AF16,0,$B$2-1):OFFSET(AF16,0,$B$3-1)) -> 928.7 | AS16: =SUM(AF16:AQ16) -> 1120.1 | AT16: =AT17+AT21+AT24 -> 132.68453 | AU16: =AU17+AU21+AU24 -> 140.81862 | AV16: =AV17+AV21+AV24 -> 151.20091 | AW16: =AW17+AW21+AW24 -> 161.1629 | AX16: =AX17+AX21+AX24 -> 172.3837 | AY16: =AY17+AY21+AY24 -> 183.30874 | AZ16: =AZ17+AZ21+AZ24 -> 194.90783 | BA16: =BA17+BA21+BA24 -> 206.24182 | ... BE16: =BE17+BE21+BE24 -> 292.93145 | BF16: =SUM(OFFSET(AT16,0,$B$2-1):OFFSET(AT16,0,$B$3-1)) -> 2038.858 | BG16: =SUM(AT16:BE16) -> 2331.7894
A17: TOI of Liabilities | B17: =P17/BG17 -> 0.46070863 | C17: =SUM(D17:O17) -> 131.51851 | D17: 5.4542925 | E17: 4.383529 | F17: 9.1201571 | G17: 7 | H17: 5.4949001 | I17: 9.2604819 | J17: 7.801 | K17: 23.244424 | L17: 5.98 | M17: 19.32959 | N17: 11.9 | O17: 22.550141 | P17: =SUM(OFFSET(Q17,0,$B$2-1):OFFSET(Q17,0,$B$3-1)) -> 101.23719 | Q17: =Q18+Q19+Q20 -> 7.0133013 | R17: =R18+R19+R20 -> 7.5874353 | S17: =S18+S19+S20 -> 9.6820502 | T17: =T18+T19+T20 -> 11.360376 | U17: =U18+U19+U20 -> 13.075268 | V17: =V18+V19+V20 -> 12.200694 | W17: =W18+W19+W20 -> 13.701581 | X17: =X18+X19+X20 -> 13.051334 | ... AB17: =AB18+AB19+AB20 -> 0 | AE17: TOI of Liabilities | AF17: =SUM(AF18:AF20) -> 4.7 | AG17: =SUM(AG18:AG20) -> 5 | AH17: =SUM(AH18:AH20) -> 5.3 | AI17: =SUM(AI18:AI20) -> 5.7 | AJ17: =SUM(AJ18:AJ20) -> 6 | AK17: =SUM(AK18:AK20) -> 6.3 | AL17: =SUM(AL18:AL20) -> 6.5 | AM17: =SUM(AM18:AM20) -> 6.9 | ... AQ17: =SUM(AQ18:AQ20) -> 53.2 | AR17: =SUM(OFFSET(AF17,0,$B$2-1):OFFSET(AF17,0,$B$3-1)) -> 69 | AS17: =SUM(AF17:AQ17) -> 122.2 | AT17: =SUM(AT18:AT20) -> 10.022243 | AU17: =SUM(AU18:AU20) -> 10.68841 | AV17: =SUM(AV18:AV20) -> 11.760151 | AW17: =SUM(AW18:AW20) -> 12.829728 | AX17: =SUM(AX18:AX20) -> 13.844686 | AY17: =SUM(AY18:AY20) -> 14.74943 | AZ17: =SUM(AZ18:AZ20) -> 15.969795 | BA17: =SUM(BA18:BA20) -> 16.576801 | ... BE17: =SUM(BE18:BE20) -> 58.238777 | BF17: =SUM(OFFSET(AT17,0,$B$2-1):OFFSET(AT17,0,$B$3-1)) -> 161.50355 | BG17: =SUM(AT17:BE17) -> 219.74233
A18: TOI of Deposit | B18: =P18/BG18 -> 0.6084021 | C18: =SUM(D18:O18) -> 71.212918 | D18: 5.337681 | E18: 4.3534391 | F18: 6.3877329 | G18: 6.4 | H18: 5.3 | I18: 5.55 | J18: 6.266 | K18: 6.7 | L18: 6.22 | M18: 6.047924 | N18: 7 | O18: 5.650141 | P18: =SUM(OFFSET(Q18,0,$B$2-1):OFFSET(Q18,0,$B$3-1)) -> 93.820369 | Q18: 6.4134101 | R18: 7.0545337 | S18: 9.3597592 | T18: 10.705649 | U18: 10.2 | V18: 12.108847 | W18: 12.103127 | X18: 12.643311 | Y18: 13.231732 | AE18: TOI of Deposit | AF18: 4.6 | AG18: 4.9 | AH18: 5.2 | AI18: 5.5 | AJ18: 5.8 | AK18: 6.1 | AL18: 6.3 | AM18: 6.6 | AN18: 6.9 | AO18: 7.2 | AP18: 7.5 | AQ18: 7.8 | AR18: =SUM(OFFSET(AF18,0,$B$2-1):OFFSET(AF18,0,$B$3-1)) -> 66.6 | AS18: =SUM(AF18:AQ18) -> 74.4 | AT18: 7.2718333 | AU18: 8.3918333 | AV18: 9.5046167 | AW18: 10.611017 | AX18: 11.647783 | AY18: 12.570917 | AZ18: 13.50625 | BA18: 14.411283 | BB18: 15.286017 | BC18: 16.17295 | BD18: 17.072083 | BE18: 17.76125 | BF18: =SUM(OFFSET(AT18,0,$B$2-1):OFFSET(AT18,0,$B$3-1)) -> 136.44658 | BG18: =SUM(AT18:BE18) -> 154.20783
A19: TOI of Fee income | B19: =P19/BG19 -> -0.25557913 | C19: =SUM(D19:O19) -> 19.70284 | D19: 0.073660276 | E19: 0.030089906 | F19: 2.7324241 | G19: 0.4 | H19: -0.1 | I19: 2.94 | J19: -0.265 | K19: -0.3 | L19: -0.34 | M19: 13.181666 | N19: 0.35 | O19: 1 | P19: =SUM(OFFSET(Q19,0,$B$2-1):OFFSET(Q19,0,$B$3-1)) -> -3.3175444 | Q19: -0.21010883 | R19: =-293.09842/1000 -> -0.29309842 | S19: -0.17770902 | T19: -0.37827312 | U19: =-0.363 -> -0.363 | V19: -0.39340749 | W19: -0.48904613 | X19: -0.46231739 | Y19: -0.55058396 | AE19: TOI of Fee income | AF19: 0.1 | AG19: 0.1 | AH19: 0.1 | AI19: 0.2 | AJ19: 0.2 | AK19: 0.2 | AL19: 0.2 | AM19: 0.3 | AN19: 0.3 | AO19: 0.3 | AP19: 0.4 | AQ19: 0.4 | AR19: =SUM(OFFSET(AF19,0,$B$2-1):OFFSET(AF19,0,$B$3-1)) -> 2.4 | AS19: =SUM(AF19:AQ19) -> 2.8 | AT19: 1.2184095 | AU19: 1.1645765 | AV19: 1.1235339 | AW19: 1.0867112 | AX19: 1.0649029 | AY19: 1.0465136 | AZ19: 1.0315451 | BA19: 1.0335177 | BB19: 1.0377768 | BC19: 1.0443237 | BD19: 1.0531597 | BE19: 1.0755271 | BF19: =SUM(OFFSET(AT19,0,$B$2-1):OFFSET(AT19,0,$B$3-1)) -> 11.904971 | BG19: =SUM(AT19:BE19) -> 12.980498
A20: Other TOI | B20: =P20/BG20 -> 0.20425398 | C20: =SUM(D20:O20) -> 40.602757 | D20: 0.042951221 | E20: 3.0737917e-08 | G20: 0.2 | H20: 0.29490013 | I20: 0.77048189 | J20: 1.8 | K20: 16.844424 | L20: 0.1 | M20: 0.1 | N20: 4.55 | O20: 15.9 | P20: =SUM(OFFSET(Q20,0,$B$2-1):OFFSET(Q20,0,$B$3-1)) -> 10.734364 | Q20: 0.81 | R20: =826/1000 -> 0.826 | S20: 0.5 | T20: 1.033 | U20: 3.2382683 | V20: 0.485255 | W20: 2.0875 | X20: 0.87034044 | Y20: 0.884 | AE20: Other TOI | AQ20: 45 | AR20: =SUM(OFFSET(AF20,0,$B$2-1):OFFSET(AF20,0,$B$3-1)) -> 0 | AS20: =SUM(AF20:AQ20) -> 45 | AT20: 1.532 | AU20: 1.132 | AV20: 1.132 | AW20: 1.132 | AX20: 1.132 | AY20: 1.132 | AZ20: 1.432 | BA20: 1.132 | BB20: 1.132 | BC20: 1.132 | BD20: 1.132 | BE20: 39.402 | BF20: =SUM(OFFSET(AT20,0,$B$2-1):OFFSET(AT20,0,$B$3-1)) -> 13.152 | BG20: =SUM(AT20:BE20) -> 52.554
A21: TOI of Card | B21: =P21/BG21 -> 0.72797991 | C21: =SUM(D21:O21) -> 112.75678 | D21: 2.408777 | E21: 4.8955014 | F21: 1.3635527 | G21: 5.3614223 | H21: 6.8461201 | I21: 18.429695 | J21: 9.1618877 | K21: 6.8158602 | L21: 11.137047 | M21: 11.247661 | N21: 19.889255 | O21: 15.2 | P21: =SUM(OFFSET(Q21,0,$B$2-1):OFFSET(Q21,0,$B$3-1)) -> 203.3852 | Q21: =Q22+Q23 -> 13.767405 | R21: =R22+R23 -> 13.733703 | S21: =S22+S23 -> 13.579927 | T21: =T22+T23 -> 16.675694 | U21: =U22+U23 -> 23.434286 | V21: =V22+V23 -> 29.632297 | W21: =W22+W23 -> 21.186228 | X21: =X22+X23 -> 30.85078 | ... AB21: =AB22+AB23 -> 0 | AE21: TOI of Card | AF21: =SUM(AF22:AF23) -> 3.7 | AG21: =SUM(AG22:AG23) -> 4.6 | AH21: =SUM(AH22:AH23) -> 7.8 | AI21: =SUM(AI22:AI23) -> 8.7 | AJ21: =SUM(AJ22:AJ23) -> 9.5 | AK21: =SUM(AK22:AK23) -> 11.9 | AL21: =SUM(AL22:AL23) -> 12.9 | AM21: =SUM(AM22:AM23) -> 13.5 | ... AQ21: =SUM(AQ22:AQ23) -> 17.1 | AR21: =SUM(OFFSET(AF21,0,$B$2-1):OFFSET(AF21,0,$B$3-1)) -> 118.4 | AS21: =SUM(AF21:AQ21) -> 135.5 | AT21: =SUM(AT22:AT23) -> 18.257635 | AU21: =SUM(AU22:AU23) -> 18.226989 | AV21: =SUM(AV22:AV23) -> 18.950269 | AW21: =SUM(AW22:AW23) -> 19.409674 | AX21: =SUM(AX22:AX23) -> 21.04076 | AY21: =SUM(AY22:AY23) -> 22.319454 | AZ21: =SUM(AZ22:AZ23) -> 23.55813 | BA21: =SUM(BA22:BA23) -> 24.510296 | ... BE21: =SUM(BE22:BE23) -> 28.37985 | BF21: =SUM(OFFSET(AT21,0,$B$2-1):OFFSET(AT21,0,$B$3-1)) -> 251.00313 | BG21: =SUM(AT21:BE21) -> 279.38298
A22: TOI of Debit card | B22: =P22/BG22 -> 0.52160384 | C22: =SUM(D22:O22) -> 0.52089552 | D22: -2.0004205 | E22: -1.9212874 | F22: -2.7634134 | G22: -2.0568142 | H22: -2.0329462 | I22: 11.141066 | J22: 1.4348877 | K22: -1.6401398 | L22: -0.46295269 | M22: -0.29833919 | N22: 0.02125491 | O22: 1.1 | P22: =SUM(OFFSET(Q22,0,$B$2-1):OFFSET(Q22,0,$B$3-1)) -> 4.1939893 | Q22: -0.36985688 | S22: -0.10360138 | T22: -0.42228429 | U22: 0.11797397 | V22: -0.13616028 | W22: -0.057598087 | X22: 0.1991644 | Y22: 4.9663518 | AE22: TOI of Debit card | AF22: -2.4 | AG22: -2.4 | AH22: -0.4 | AI22: -0.4 | AJ22: -0.4 | AK22: 1 | AL22: 1 | AM22: 1 | AN22: 1 | AO22: 1 | AP22: 1 | AQ22: 1 | AR22: =SUM(OFFSET(AF22,0,$B$2-1):OFFSET(AF22,0,$B$3-1)) -> 0 | AS22: =SUM(AF22:AQ22) -> 1 | AT22: 0.076910362 | AU22: 0.10445036 | AV22: 0.13199036 | AW22: 0.15953036 | AX22: 0.18707036 | AY22: 0.21461036 | AZ22: 0.24215036 | BA22: 0.26969036 | BB22: =0.297230362+5.3 -> 5.5972304 | BC22: 0.32477036 | BD22: 0.35231036 | BE22: 0.37985036 | BF22: =SUM(OFFSET(AT22,0,$B$2-1):OFFSET(AT22,0,$B$3-1)) -> 7.660714 | BG22: =SUM(AT22:BE22) -> 8.0405643
A23: TOI of Credit card | B23: =P23/BG23 -> 0.73409536 | C23: =SUM(D23:O23) -> 112.23588 | D23: 4.4091975 | E23: 6.8167888 | F23: 4.1269661 | G23: 7.4182365 | H23: 8.8790663 | I23: 7.2886289 | J23: 7.727 | K23: 8.456 | L23: 11.6 | M23: 11.546 | N23: 19.868 | O23: 14.1 | P23: =SUM(OFFSET(Q23,0,$B$2-1):OFFSET(Q23,0,$B$3-1)) -> 199.19121 | Q23: 14.137262 | R23: =13733.7025684444/1000 -> 13.733703 | S23: 13.683529 | T23: 17.097979 | U23: 23.316312 | V23: 29.768457 | W23: 21.243826 | X23: 30.651616 | Y23: 35.558528 | AE23: TOI of Credit card | AF23: 6.1 | AG23: 7 | AH23: 8.2 | AI23: 9.1 | AJ23: 9.9 | AK23: 10.9 | AL23: 11.9 | AM23: 12.5 | AN23: 13.3 | AO23: 14.3 | AP23: 15.2 | AQ23: 16.1 | AR23: =SUM(OFFSET(AF23,0,$B$2-1):OFFSET(AF23,0,$B$3-1)) -> 118.4 | AS23: =SUM(AF23:AQ23) -> 134.5 | AT23: 18.180725 | AU23: 18.122539 | AV23: 18.818278 | AW23: 19.250144 | AX23: 20.85369 | AY23: 22.104844 | AZ23: 23.31598 | BA23: 24.240605 | BB23: =25.1512319990545+1.4 -> 26.551232 | BC23: 25.460843 | BD23: 26.443538 | BE23: 28 | BF23: =SUM(OFFSET(AT23,0,$B$2-1):OFFSET(AT23,0,$B$3-1)) -> 243.34242 | BG23: =SUM(AT23:BE23) -> 271.34242
A24: TOI of Lending products | B24: =P24/BG24 -> 0.67883517 | C24: =SUM(D24:O24) -> 583.02632 | D24: 18.257274 | E24: 17.003229 | F24: 20.569212 | G24: 24.99622 | H24: 31.967651 | I24: 37.734202 | J24: 52.320522 | K24: 62.543391 | L24: 66.231432 | M24: 78.884186 | N24: 80.419 | O24: 92.1 | P24: =SUM(OFFSET(Q24,0,$B$2-1):OFFSET(Q24,0,$B$3-1)) -> 1244.0769 | Q24: =SUM(Q25:Q29) -> 94.769915 | R24: =SUM(R25:R29) -> 84.284106 | S24: =SUM(S25:S29) -> 103.95841 | T24: =SUM(T25:T29) -> 112.74795 | U24: =SUM(U25:U29) -> 122.2 | V24: =SUM(V25:V29) -> 135.62717 | W24: =SUM(W25:W29) -> 169.73407 | X24: =SUM(X25:X29) -> 189.46095 | ... AB24: =SUM(AB25:AB29) -> 0 | AE24: TOI of Lending products | AF24: =SUM(AF25:AF29) -> 33.7 | AG24: =SUM(AG25:AG29) -> 29.3 | AH24: =SUM(AH25:AH29) -> 38.2 | AI24: =SUM(AI25:AI29) -> 46.1 | AJ24: =SUM(AJ25:AJ29) -> 57.1 | AK24: =SUM(AK25:AK29) -> 66.2 | AL24: =SUM(AL25:AL29) -> 76.6 | AM24: =SUM(AM25:AM29) -> 84.2 | ... AQ24: =SUM(AQ25:AQ29) -> 121.1 | AR24: =SUM(OFFSET(AF24,0,$B$2-1):OFFSET(AF24,0,$B$3-1)) -> 741.3 | AS24: =SUM(AF24:AQ24) -> 862.4 | AT24: =SUM(AT25:AT29) -> 104.40465 | AU24: =SUM(AU25:AU29) -> 111.90322 | AV24: =SUM(AV25:AV29) -> 120.4905 | AW24: =SUM(AW25:AW29) -> 128.92349 | AX24: =SUM(AX25:AX29) -> 137.49826 | AY24: =SUM(AY25:AY29) -> 146.23986 | AZ24: =SUM(AZ25:AZ29) -> 155.3799 | BA24: =SUM(BA25:BA29) -> 165.15473 | ... BE24: =SUM(BE25:BE29) -> 206.31283 | BF24: =SUM(OFFSET(AT24,0,$B$2-1):OFFSET(AT24,0,$B$3-1)) -> 1626.3513 | BG24: =SUM(AT24:BE24) -> 1832.6641
A25: TOI Vay kỳ hạn | B25: =P25/BG25 -> 0.70171083 | C25: =SUM(D25:O25) -> 416.72574 | D25: 11.314543 | E25: 10.03958 | F25: 11.664783 | G25: 15.035967 | H25: 20.488776 | I25: 24.78855 | J25: 40.697373 | K25: 45.272138 | L25: 48.583965 | M25: 59.440069 | N25: 61.5 | O25: 67.9 | P25: =SUM(OFFSET(Q25,0,$B$2-1):OFFSET(Q25,0,$B$3-1)) -> 996.00471 | Q25: 72.488775 | R25: =63843.9932084444/1000 -> 63.843993 | S25: 79.661951 | T25: ='Slide 2025'!H141 -> 89.130891 | U25: 97.5 | V25: 111.4093 | W25: 140.25025 | X25: 155.61405 | Y25: 186.1055 | AE25: TOI Vay kỳ hạn | AF25: 22.8 | AG25: 20.4 | AH25: 27.4 | AI25: 33.5 | AJ25: 41.5 | AK25: 47.5 | AL25: 52.8 | AM25: 55.9 | AN25: 60.4 | AO25: 66.2 | AP25: 70.9 | AQ25: 74.8 | AR25: =SUM(OFFSET(AF25,0,$B$2-1):OFFSET(AF25,0,$B$3-1)) -> 499.3 | AS25: =SUM(AF25:AQ25) -> 574.1 | AT25: 79.909379 | AU25: 86.021582 | AV25: 92.886533 | AW25: 99.681596 | AX25: 106.49004 | AY25: 113.41831 | AZ25: 120.58744 | BA25: 128.29637 | BB25: 136.2201 | BC25: 144.03172 | BD25: 151.87882 | BE25: 159.97291 | BF25: =SUM(OFFSET(AT25,0,$B$2-1):OFFSET(AT25,0,$B$3-1)) -> 1259.4219 | BG25: =SUM(AT25:BE25) -> 1419.3948
A26: TOI Vay ngắn ngày | B26: =P26/BG26 -> 0.80071949 | C26: =SUM(D26:O26) -> 119.45184 | D26: 4.5584224 | E26: 4.6202345 | F26: 6.0534337 | G26: 7.1014075 | H26: 8.4765154 | I26: 9.5441906 | J26: 8.7413173 | K26: 12.894384 | L26: 12.829769 | M26: 13.946168 | N26: 13.086 | O26: 17.6 | P26: =SUM(OFFSET(Q26,0,$B$2-1):OFFSET(Q26,0,$B$3-1)) -> 179.25145 | Q26: 15.505887 | R26: =14034.8572681111/1000 -> 14.034857 | S26: 16.682503 | T26: ='Slide 2025'!H202 -> 16.120455 | U26: 16.6 | V26: 16.107793 | W26: 21.318024 | X26: 25.749059 | Y26: 37.132869 | AE26: TOI Vay ngắn ngày | AF26: 7 | AG26: 4.9 | AH26: 6.4 | AI26: 7.1 | AJ26: 7.2 | AK26: 7.1 | AL26: 8.7 | AM26: 9 | AN26: 9.1 | AO26: 10 | AP26: 10.1 | AQ26: 10 | AR26: =SUM(OFFSET(AF26,0,$B$2-1):OFFSET(AF26,0,$B$3-1)) -> 86.6 | AS26: =SUM(AF26:AQ26) -> 96.6 | AT26: 16.012009 | AU26: 16.526957 | AV26: 17.173725 | AW26: 17.602274 | AX26: 18.038841 | AY26: 18.477187 | AZ26: 18.911118 | BA26: 19.343552 | BB26: 19.773786 | BC26: 20.220229 | BD26: 20.674673 | BE26: 21.108626 | BF26: =SUM(OFFSET(AT26,0,$B$2-1):OFFSET(AT26,0,$B$3-1)) -> 202.75435 | BG26: =SUM(AT26:BE26) -> 223.86298
A27: TOI Overdraft | B27: =P27/BG27 -> 0.41556808 | C27: =SUM(D27:O27) -> 44.023575 | D27: 2.3843083 | E27: 2.3434152 | F27: 2.8509951 | G27: 2.8588454 | H27: 2.9523596 | I27: 3.2905094 | J27: 2.6855987 | K27: 4.0848969 | L27: 4.4626971 | M27: 4.9979495 | N27: 5.212 | O27: 5.9 | P27: =SUM(OFFSET(Q27,0,$B$2-1):OFFSET(Q27,0,$B$3-1)) -> 54.473487 | Q27: 6.0033602 | R27: =5473.89711111111/1000 -> 5.4738971 | S27: 6.3746954 | T27: ='Slide 2025'!H172 -> 6.3344924 | U27: 6.7 | V27: 6.4882581 | W27: 6.4087893 | X27: 5.7167435 | Y27: 4.9732508 | AE27: TOI Overdraft | AF27: 2.8 | AG27: 2.9 | AH27: 2.8 | AI27: 2.7 | AJ27: 2.7 | AK27: 2.6 | AL27: 2.7 | AM27: 2.9 | AN27: 3 | AO27: 3.1 | AP27: 3.2 | AQ27: 3.1 | AR27: =SUM(OFFSET(AF27,0,$B$2-1):OFFSET(AF27,0,$B$3-1)) -> 31.4 | AS27: =SUM(AF27:AQ27) -> 34.5 | AT27: 7.3786114 | AU27: 7.7509983 | AV27: 8.1869764 | AW27: 8.7561859 | AX27: 9.4148165 | AY27: 10.084609 | AZ27: 10.871214 | BA27: 11.726317 | BB27: 12.659272 | BC27: 13.660911 | BD27: 14.734488 | BE27: 15.857581 | BF27: =SUM(OFFSET(AT27,0,$B$2-1):OFFSET(AT27,0,$B$3-1)) -> 115.2244 | BG27: =SUM(AT27:BE27) -> 131.08198
A28: TOI TW | B28: =P28/BG28 -> 0 | C28: =SUM(D28:O28) -> 0 | P28: =SUM(OFFSET(Q28,0,$B$2-1):OFFSET(Q28,0,$B$3-1)) -> 0 | AE28: TOI TW | AF28: 0.2 | AG28: 0.2 | AH28: 0.3 | AI28: -0.2 | AJ28: 0.6 | AK28: 1.5 | AL28: 2.6 | AM28: 4 | AN28: 5.6 | AO28: 7 | AP28: 8.4 | AQ28: 10.2 | AR28: =SUM(OFFSET(AF28,0,$B$2-1):OFFSET(AF28,0,$B$3-1)) -> 30.2 | AS28: =SUM(AF28:AQ28) -> 40.4 | AT28: 0.32277778 | AU28: 0.64200165 | AV28: 1.0378222 | AW28: 1.4771993 | AX28: 1.9561835 | AY28: 2.4716098 | AZ28: 3.0217052 | BA28: 3.6042589 | BB28: 4.2172429 | BC28: 4.8591794 | BD28: 5.5265922 | BE28: 6.2147711 | BF28: =SUM(OFFSET(AT28,0,$B$2-1):OFFSET(AT28,0,$B$3-1)) -> 29.136573 | BG28: =SUM(AT28:BE28) -> 35.351344
A29: TOI Paylater | B29: =P29/BG29 -> 0.62452487 | C29: =SUM(D29:O29) -> 2.8251561 | H29: 0.05 | I29: 0.11095187 | J29: 0.19623293 | K29: 0.29197129 | L29: 0.355 | M29: 0.5 | N29: 0.621 | O29: 0.7 | P29: =SUM(OFFSET(Q29,0,$B$2-1):OFFSET(Q29,0,$B$3-1)) -> 14.347212 | Q29: 0.77189184 | R29: =931.357997666667/1000 -> 0.931358 | S29: 1.2392599 | T29: 1.1621162 | U29: 1.4 | V29: 1.6218176 | W29: 1.7570116 | X29: 2.3811003 | Y29: 3.0826563 | AE29: TOI Paylater | AF29: 0.9 | AG29: 0.9 | AH29: 1.3 | AI29: 3 | AJ29: 5.1 | AK29: 7.5 | AL29: 9.8 | AM29: 12.4 | AN29: 15 | AO29: 17.6 | AP29: 20.3 | AQ29: 23 | AR29: =SUM(OFFSET(AF29,0,$B$2-1):OFFSET(AF29,0,$B$3-1)) -> 93.8 | AS29: =SUM(AF29:AQ29) -> 116.8 | AT29: 0.78187777 | AU29: 0.96168121 | AV29: 1.2054396 | AW29: 1.4062376 | AX29: 1.5983722 | AY29: 1.7881455 | AZ29: 1.9884248 | BA29: 2.1842275 | BB29: 2.3927852 | BC29: 2.6252157 | BD29: 2.8816603 | BE29: 3.1589355 | BF29: =SUM(OFFSET(AT29,0,$B$2-1):OFFSET(AT29,0,$B$3-1)) -> 19.814067 | BG29: =SUM(AT29:BE29) -> 22.973003
A30: Expenses | B30: =P30/BG30 -> 0.58843401 | C30: =SUM(D30:O30) -> 193.35862 | D30: 7.8384613 | E30: 6.8558063 | F30: 5.4708682 | G30: 12.650517 | H30: 14.054304 | I30: 14.439599 | J30: 16.684509 | K30: 16.620597 | L30: 23.132 | M30: 25.577412 | N30: 29.555 | O30: 20.479543 | P30: =SUM(OFFSET(Q30,0,$B$2-1):OFFSET(Q30,0,$B$3-1)) -> 314.48842 | Q30: =Q31+Q38+Q45+Q59 -> 22.524556 | R30: =R31+R38+R45+R59 -> 25.508704 | S30: =S31+S38+S45+S59 -> 21.928473 | T30: =T31+T38+T45+T59 -> 33.111 | U30: =U31+U38+U45+U59 -> 28.869711 | V30: =V31+V38+V45+V59 -> 31.443454 | W30: =W31+W38+W45+W59 -> 50.373115 | X30: =X31+X38+X45+X59 -> 45.372824 | ... AB30: =AB31+AB38+AB45+AB59 -> 0 | AE30: Expenses | AF30: =AF31+AF38+AF45+AF59 -> 21.238787 | AG30: =AG31+AG38+AG45+AG59 -> 17.02612 | AH30: =AH31+AH38+AH45+AH59 -> 23.879348 | AI30: =AI31+AI38+AI45+AI59 -> 28.704657 | AJ30: =AJ31+AJ38+AJ45+AJ59 -> 30.358248 | AK30: =AK31+AK38+AK45+AK59 -> 34.032942 | AL30: =AL31+AL38+AL45+AL59 -> 38.213848 | AM30: =AM31+AM38+AM45+AM59 -> 38.568832 | ... AQ30: =AQ31+AQ38+AQ45+AQ59 -> 50.018142 | AR30: =SUM(OFFSET(AF30,0,$B$2-1):OFFSET(AF30,0,$B$3-1)) -> 368.2246 | AS30: =SUM(AF30:AQ30) -> 418.24275 | AT30: =AT31+AT38+AT45+AT59 -> 39.911847 | AU30: =AU31+AU38+AU45+AU59 -> 40.233331 | AV30: =AV31+AV38+AV45+AV59 -> 41.854616 | AW30: =AW31+AW38+AW45+AW59 -> 42.545697 | AX30: =AX31+AX38+AX45+AX59 -> 43.663803 | AY30: =AY31+AY38+AY45+AY59 -> 44.289103 | AZ30: =AZ31+AZ38+AZ45+AZ59 -> 42.878515 | BA30: =BA31+BA38+BA45+BA59 -> 43.9976 | ... BE30: =BE31+BE38+BE45+BE59 -> 52.138301 | BF30: =SUM(OFFSET(AT30,0,$B$2-1):OFFSET(AT30,0,$B$3-1)) -> 482.31146 | BG30: =SUM(AT30:BE30) -> 534.44976
A31: Underwritting cost | B31: =P31/BG31 -> 0.6225854 | C31: =SUM(D31:O31) -> 23.385349 | D31: 1.3027835 | E31: 1.0747668 | F31: 1.6039279 | G31: 1.3027034 | H31: 1.3140798 | I31: 2.1078519 | J31: 2.034 | K31: 1.951 | L31: 2.2 | M31: 2.474943 | N31: 2.793 | O31: 3.2262925 | P31: =SUM(OFFSET(Q31,0,$B$2-1):OFFSET(Q31,0,$B$3-1)) -> 31.322758 | Q31: =SUM(Q32:Q37) -> 3.6550947 | R31: =SUM(R32:R37) -> 3.2898456 | S31: =1070.51640555557/1000 -> 1.0705164 | T31: 3.04 | U31: 3.0110239 | V31: 2.0718308 | W31: 4.392667 | X31: 4.7119908 | Y31: 6.0797884 | Z31: =SUM(Z32:Z37) -> 0 | AA31: =SUM(AA32:AA37) -> 0 | AB31: =SUM(AB32:AB37) -> 0 | AE31: Underwritting cost | AF31: =SUM(AF32:AF37) -> 2.1814874 | AG31: =SUM(AG32:AG37) -> 1.6679371 | AH31: =SUM(AH32:AH37) -> 2.1060349 | AI31: =SUM(AI32:AI37) -> 2.6347134 | AJ31: =SUM(AJ32:AJ37) -> 2.5450795 | AK31: =SUM(AK32:AK37) -> 2.1841463 | AL31: =SUM(AL32:AL37) -> 2.3745211 | AM31: =SUM(AM32:AM37) -> 2.5168892 | ... AQ31: =SUM(AQ32:AQ37) -> 2.9212437 | AR31: =SUM(OFFSET(AF31,0,$B$2-1):OFFSET(AF31,0,$B$3-1)) -> 26.785343 | AS31: =SUM(AF31:AQ31) -> 29.706587 | AT31: =SUM(AT32:AT37) -> 3.644275 | AU31: =SUM(AU32:AU37) -> 3.7531099 | AV31: =SUM(AV32:AV37) -> 3.8619449 | AW31: =SUM(AW32:AW37) -> 3.9707798 | AX31: =SUM(AX32:AX37) -> 4.0796148 | AY31: =SUM(AY32:AY37) -> 4.1834497 | AZ31: =SUM(AZ32:AZ37) -> 4.2210763 | BA31: =SUM(BA32:BA37) -> 4.3272029 | ... BE31: =SUM(BE32:BE37) -> 4.6519594 | BF31: =SUM(OFFSET(AT31,0,$B$2-1):OFFSET(AT31,0,$B$3-1)) -> 45.658822 | BG31: =SUM(AT31:BE31) -> 50.310781
A32: U_Vay kỳ hạn | B32: =P32/BG32 -> 0.14812922 | C32: =SUM(D32:O32) -> 9.4922255 | D32: 0.27379295 | E32: 0.15161438 | F32: 0.23992795 | G32: 0.4 | H32: 0.24245347 | I32: 0.65814423 | J32: 1 | K32: 0.7 | L32: 1 | M32: 1.4 | N32: 1.7 | O32: 1.7262925 | P32: =SUM(OFFSET(Q32,0,$B$2-1):OFFSET(Q32,0,$B$3-1)) -> 3.5176197 | Q32: 2.1787741 | R32: =1338.8455888889/1000 -> 1.3388456 | AE32: U_Vay kỳ hạn | AF32: 0.77158742 | AG32: 0.43677314 | AH32: 0.68095988 | AI32: 0.84999546 | AJ32: 0.97723614 | AK32: 1.0749358 | AL32: 1.0265093 | AM32: 0.98816392 | AN32: 1.0679635 | AO32: 1.1288 | AP32: 0.5865 | AQ32: 0.6035 | AR32: =SUM(OFFSET(AF32,0,$B$2-1):OFFSET(AF32,0,$B$3-1)) -> 9.5894245 | AS32: =SUM(AF32:AQ32) -> 10.192924 | AT32: 1.8260987 | AU32: 1.8619307 | AV32: 1.8977626 | AW32: 1.9335945 | AX32: 1.9694265 | AY32: 2.0052584 | AZ32: 1.9707153 | BA32: 2.0046723 | BB32: 2.0386292 | BC32: 2.0725861 | BD32: 2.1055431 | BE32: 2.06075 | BF32: =SUM(OFFSET(AT32,0,$B$2-1):OFFSET(AT32,0,$B$3-1)) -> 21.686217 | BG32: =SUM(AT32:BE32) -> 23.746967
A33: U_Vay ngắn ngày | B33: =P33/BG33 -> 0.097928658 | C33: =SUM(D33:O33) -> 3.6324027 | D33: 0.2602931 | E33: 0.24607065 | F33: 0.39086261 | G33: 0.3 | H33: 0.31 | I33: 0.42539948 | J33: 0.3 | K33: 0.301 | L33: 0.2 | M33: 0.24877691 | N33: 0.25 | O33: 0.4 | P33: =SUM(OFFSET(Q33,0,$B$2-1):OFFSET(Q33,0,$B$3-1)) -> 0.63829573 | Q33: 0.35329573 | R33: =285/1000 -> 0.285 | AE33: U_Vay ngắn ngày | AF33: 0.3969 | AG33: 0.25578 | AH33: 0.3822 | AI33: 0.41748 | AJ33: 0.41748 | AK33: 0.21168 | AL33: 0.2352 | AM33: 0.2352 | AN33: 0.24 | AO33: 0.26786667 | AP33: 0.26786667 | AQ33: 0.268 | AR33: =SUM(OFFSET(AF33,0,$B$2-1):OFFSET(AF33,0,$B$3-1)) -> 3.3276533 | AS33: =SUM(AF33:AQ33) -> 3.5956533 | AT33: 0.42521111 | AU33: 0.44775556 | AV33: 0.4703 | AW33: 0.49284444 | AX33: 0.51538889 | AY33: 0.53293333 | AZ33: 0.55464444 | BA33: 0.57635556 | BB33: 0.59806667 | BC33: 0.61977778 | BD33: 0.64148889 | BE33: 0.6432 | BF33: =SUM(OFFSET(AT33,0,$B$2-1):OFFSET(AT33,0,$B$3-1)) -> 5.8747667 | BG33: =SUM(AT33:BE33) -> 6.5179667
A34: U_Overdraft | B34: =P34/BG34 -> 0.086914139 | C34: =SUM(D34:O34) -> 2.3707503 | D34: 0.22597708 | E34: 0.17848743 | F34: 0.29679293 | G34: 0.20270341 | H34: 0.3 | I34: 0.31434078 | J34: 0.134 | K34: 0.14 | L34: 0.1 | M34: 0.14144871 | N34: 0.167 | O34: 0.17 | P34: =SUM(OFFSET(Q34,0,$B$2-1):OFFSET(Q34,0,$B$3-1)) -> 0.29789821 | Q34: 0.15789821 | R34: =140/1000 -> 0.14 | AE34: U_Overdraft | AF34: 0.2 | AG34: 0.2 | AH34: 0.2 | AI34: 0.2 | AJ34: 0.066666667 | AK34: 0.066666667 | AL34: 0.066666667 | AM34: 0.066666667 | AN34: 0.066666667 | AO34: 0.066666667 | AP34: 0.066666667 | AQ34: 0.066666667 | AR34: =SUM(OFFSET(AF34,0,$B$2-1):OFFSET(AF34,0,$B$3-1)) -> 1.2666667 | AS34: =SUM(AF34:AQ34) -> 1.3333333 | AT34: 0.19625 | AU34: 0.2125 | AV34: 0.22875 | AW34: 0.245 | AX34: 0.26125 | AY34: 0.2775 | AZ34: 0.29375 | BA34: 0.31 | BB34: 0.32625 | BC34: 0.3425 | BD34: 0.35875 | BE34: 0.375 | BF34: =SUM(OFFSET(AT34,0,$B$2-1):OFFSET(AT34,0,$B$3-1)) -> 3.0525 | BG34: =SUM(AT34:BE34) -> 3.4275
A35: U_TW | B35: =P35/BG35 -> 0 | C35: =SUM(D35:O35) -> 0.003187925 | D35: 0.003187925 | P35: =SUM(OFFSET(Q35,0,$B$2-1):OFFSET(Q35,0,$B$3-1)) -> 0 | AE35: U_TW | AF35: 0.008 | AG35: 0.010384 | AH35: 0.017875 | AI35: 0.06152851 | AJ35: 0.078023022 | AK35: 0.047384074 | AL35: 0.053448297 | AM35: 0.057020669 | AN35: 0.060024576 | AO35: 0.066089282 | AP35: 0.074332413 | AQ35: 0.076708507 | AR35: =SUM(OFFSET(AF35,0,$B$2-1):OFFSET(AF35,0,$B$3-1)) -> 0.53410984 | AS35: =SUM(AF35:AQ35) -> 0.61081835 | AT35: 0.0083333333 | AU35: 0.016666667 | AV35: 0.025 | AW35: 0.033333333 | AX35: 0.041666667 | AY35: 0.05 | AZ35: 0.058333333 | BA35: 0.066666667 | BB35: 0.075 | BC35: 0.083333333 | BD35: 0.091666667 | BE35: 0.1 | BF35: =SUM(OFFSET(AT35,0,$B$2-1):OFFSET(AT35,0,$B$3-1)) -> 0.55 | BG35: =SUM(AT35:BE35) -> 0.65
A36: U_Paylater | B36: =P36/BG36 -> 0.10392291 | C36: =SUM(D36:O36) -> 0.85595775 | J36: 0.1 | K36: 0.17 | L36: 0.1 | M36: 0.13895775 | N36: 0.167 | O36: 0.18 | P36: =SUM(OFFSET(Q36,0,$B$2-1):OFFSET(Q36,0,$B$3-1)) -> 1.0442434 | Q36: 0.19724335 | R36: =847/1000 -> 0.847 | AE36: U_Paylater | AF36: 0.18 | AG36: 0.14 | AH36: 0.2 | AI36: 0.48070948 | AJ36: 0.7973403 | AK36: 0.56264645 | AL36: 0.72603019 | AM36: 0.90317128 | AN36: 1.0792873 | AO36: 1.2583688 | AP36: 1.4399348 | AQ36: 1.6272019 | AR36: =SUM(OFFSET(AF36,0,$B$2-1):OFFSET(AF36,0,$B$3-1)) -> 7.7674885 | AS36: =SUM(AF36:AQ36) -> 9.3946904 | AT36: 0.73170833 | AU36: 0.75091667 | AV36: 0.770125 | AW36: 0.78933333 | AX36: 0.80854167 | AY36: 0.82775 | AZ36: 0.84695833 | BA36: 0.86616667 | BB36: 0.885375 | BC36: 0.90458333 | BD36: 0.92379167 | BE36: 0.943 | BF36: =SUM(OFFSET(AT36,0,$B$2-1):OFFSET(AT36,0,$B$3-1)) -> 9.10525 | BG36: =SUM(AT36:BE36) -> 10.04825
A37: U_Credit card | B37: =P37/BG37 -> 0.24440196 | C37: =SUM(D37:O37) -> 7.0618247 | D37: 0.53953246 | E37: 0.49859436 | F37: 0.67634445 | G37: 0.4 | H37: 0.46162635 | I37: 0.70996741 | J37: 0.5 | K37: 0.64 | L37: 0.8 | M37: 0.54575965 | N37: 0.54 | O37: 0.75 | P37: =SUM(OFFSET(Q37,0,$B$2-1):OFFSET(Q37,0,$B$3-1)) -> 1.4468833 | Q37: 0.76788331 | R37: =679/1000 -> 0.679 | AE37: U_Credit card | AF37: 0.625 | AG37: 0.625 | AH37: 0.625 | AI37: 0.625 | AJ37: 0.20833333 | AK37: 0.22083333 | AL37: 0.26666667 | AM37: 0.26666667 | AN37: 0.27916667 | AO37: 0.27916667 | AP37: 0.27916667 | AQ37: 0.27916667 | AR37: =SUM(OFFSET(AF37,0,$B$2-1):OFFSET(AF37,0,$B$3-1)) -> 4.3 | AS37: =SUM(AF37:AQ37) -> 4.5791667 | AT37: 0.45667346 | AU37: 0.46334036 | AV37: 0.47000727 | AW37: 0.47667417 | AX37: 0.48334107 | AY37: 0.49000797 | AZ37: 0.49667487 | BA37: 0.50334177 | BB37: 0.51000867 | BC37: 0.51667557 | BD37: 0.52334247 | BE37: 0.53000938 | BF37: =SUM(OFFSET(AT37,0,$B$2-1):OFFSET(AT37,0,$B$3-1)) -> 5.3900877 | BG37: =SUM(AT37:BE37) -> 5.920097
A38: Collection cost | B38: =P38/BG38 -> 0.43883174 | C38: =SUM(D38:O38) -> 16.710402 | D38: 0.68510334 | E38: 0.94645772 | F38: 0.61938523 | G38: 0.72008395 | H38: 1.0852278 | I38: 1.4515888 | J38: 1.7002769 | K38: 1.131 | L38: 1.688 | M38: 1.5242783 | N38: 2.159 | O38: 3 | P38: =SUM(OFFSET(Q38,0,$B$2-1):OFFSET(Q38,0,$B$3-1)) -> 24.115376 | Q38: =SUM(Q39:Q44) -> 2.9009268 | R38: =SUM(R39:R44) -> 4.025 | S38: =SUM(S39:S44) -> 2.908 | T38: 3.026 | U38: 3.2895894 | V38: 1.2558601 | W38: 2.215 | X38: 2.091 | Y38: 2.404 | Z38: =SUM(Z39:Z44) -> 0 | AA38: =SUM(AA39:AA44) -> 0 | AB38: =SUM(AB39:AB44) -> 0 | AE38: Collection cost | AF38: =SUM(AF39:AF44) -> 0.99067893 | AG38: =SUM(AG39:AG44) -> 1.038893 | AH38: =SUM(AH39:AH44) -> 1.3627256 | AI38: =SUM(AI39:AI44) -> 1.8770163 | AJ38: =SUM(AJ39:AJ44) -> 1.6780869 | AK38: =SUM(AK39:AK44) -> 1.1860733 | AL38: =SUM(AL39:AL44) -> 1.4027395 | AM38: =SUM(AM39:AM44) -> 1.6816327 | ... AQ38: =SUM(AQ39:AQ44) -> 2.9738626 | AR38: =SUM(OFFSET(AF38,0,$B$2-1):OFFSET(AF38,0,$B$3-1)) -> 18.16682 | AS38: =SUM(AF38:AQ38) -> 21.140683 | AT38: =SUM(AT39:AT44) -> 3.1453695 | AU38: =SUM(AU39:AU44) -> 3.4212995 | AV38: =SUM(AV39:AV44) -> 3.7376505 | AW38: =SUM(AW39:AW44) -> 4.0628269 | AX38: =SUM(AX39:AX44) -> 4.3579039 | AY38: =SUM(AY39:AY44) -> 4.6481853 | AZ38: =SUM(AZ39:AZ44) -> 4.8631072 | BA38: =SUM(BA39:BA44) -> 5.0443166 | ... BE38: =SUM(BE39:BE44) -> 5.6261914 | BF38: =SUM(OFFSET(AT38,0,$B$2-1):OFFSET(AT38,0,$B$3-1)) -> 49.327391 | BG38: =SUM(AT38:BE38) -> 54.953583
A39: C_Vay kỳ hạn | B39: =P39/BG39 -> 0.12991148 | C39: =SUM(D39:O39) -> 8.3969884 | D39: 0.29460998 | E39: 0.47708614 | F39: 0.26919553 | G39: 0.26555742 | H39: 0.46876775 | I39: 0.76670897 | J39: 0.89806257 | K39: 0.568 | L39: 0.824 | M39: 0.8 | N39: 1.164 | O39: 1.601 | P39: =SUM(OFFSET(Q39,0,$B$2-1):OFFSET(Q39,0,$B$3-1)) -> 4.782732 | Q39: 1.508732 | R39: =1942/1000 -> 1.942 | S39: 1.332 | AE39: C_Vay kỳ hạn | AF39: 0.24110741 | AG39: 0.29570405 | AH39: 0.38082404 | AI39: 0.48707347 | AJ39: 0.30461399 | AK39: 0.37179748 | AL39: 0.43508285 | AM39: 0.49410534 | AN39: 0.55826947 | AO39: 0.62876947 | AP39: 0.69941856 | AQ39: 0.77153998 | AR39: =SUM(OFFSET(AF39,0,$B$2-1):OFFSET(AF39,0,$B$3-1)) -> 4.8967661 | AS39: =SUM(AF39:AQ39) -> 5.6683061 | AT39: 1.9824685 | AU39: 2.2078905 | AV39: 2.4684605 | AW39: 2.7343585 | AX39: 2.966722 | AY39: 3.1909086 | AZ39: 3.3364006 | BA39: 3.4448856 | BB39: 3.5489161 | BC39: 3.5977296 | BD39: 3.6330086 | BE39: 3.703566 | BF39: =SUM(OFFSET(AT39,0,$B$2-1):OFFSET(AT39,0,$B$3-1)) -> 33.111749 | BG39: =SUM(AT39:BE39) -> 36.815315
A40: C_Vay ngắn ngày | B40: =P40/BG40 -> 0.33421934 | C40: =SUM(D40:O40) -> 1.9896565 | D40: 0.10801703 | E40: 0.11051804 | F40: 0.060343175 | G40: 0.069001624 | H40: 0.13314976 | I40: 0.23719077 | J40: 0.2778266 | K40: 0.131 | L40: 0.184 | M40: 0.16160945 | N40: 0.228 | O40: 0.289 | P40: =SUM(OFFSET(Q40,0,$B$2-1):OFFSET(Q40,0,$B$3-1)) -> 1.0401333 | Q40: 0.38013328 | R40: =454/1000 -> 0.454 | S40: 0.206 | AE40: C_Vay ngắn ngày | AF40: 0.31752 | AG40: 0.204624 | AH40: 0.30576 | AI40: 0.333984 | AJ40: 0.333984 | AK40: 0.10584 | AL40: 0.1176 | AM40: 0.1176 | AN40: 0.12 | AO40: 0.13393333 | AP40: 0.13393333 | AQ40: 0.134 | AR40: =SUM(OFFSET(AF40,0,$B$2-1):OFFSET(AF40,0,$B$3-1)) -> 2.2247787 | AS40: =SUM(AF40:AQ40) -> 2.3587787 | AT40: 0.22445463 | AU40: 0.23079815 | AV40: 0.23714167 | AW40: 0.24348519 | AX40: 0.2498287 | AY40: 0.25617222 | AZ40: 0.26251574 | BA40: 0.26885926 | BB40: 0.27520278 | BC40: 0.2815463 | BD40: 0.28788981 | BE40: 0.29423333 | BF40: =SUM(OFFSET(AT40,0,$B$2-1):OFFSET(AT40,0,$B$3-1)) -> 2.8178944 | BG40: =SUM(AT40:BE40) -> 3.1121278
A41: C_Overdraft | B41: =P41/BG41 -> 0.18891669 | C41: =SUM(D41:O41) -> 1.0946801 | D41: 0.01306603 | E41: 0.069890319 | F41: 0.059738313 | G41: 0.077581479 | H41: 0.1003966 | I41: 0.10532818 | J41: 0.12337314 | K41: 0.081 | L41: 0.116 | M41: 0.12830606 | N41: 0.1 | O41: 0.12 | P41: =SUM(OFFSET(Q41,0,$B$2-1):OFFSET(Q41,0,$B$3-1)) -> 0.72686716 | Q41: 0.080867163 | R41: =368/1000 -> 0.368 | S41: 0.278 | AE41: C_Overdraft | AF41: 0.00864 | AG41: 0.0083291315 | AH41: 0.0092417149 | AI41: 0.10215439 | AJ41: 0.035125693 | AK41: 0.038462645 | AL41: 0.052452708 | AM41: 0.057032294 | AN41: 0.061818815 | AO41: 0.080178122 | AP41: 0.086423362 | AQ41: 0.092918162 | AR41: =SUM(OFFSET(AF41,0,$B$2-1):OFFSET(AF41,0,$B$3-1)) -> 0.53985888 | AS41: =SUM(AF41:AQ41) -> 0.63277704 | AT41: 0.26774382 | AU41: 0.27273406 | AV41: 0.27924429 | AW41: 0.28720191 | AX41: 0.2965447 | AY41: 0.30721902 | AZ41: 0.31917839 | BA41: 0.33238231 | BB41: 0.34679536 | BC41: 0.36238641 | BD41: 0.37912799 | BE41: 0.39699576 | BF41: =SUM(OFFSET(AT41,0,$B$2-1):OFFSET(AT41,0,$B$3-1)) -> 3.4505583 | BG41: =SUM(AT41:BE41) -> 3.847554
A42: C_TW | B42: =P42/BG42 -> 0 | C42: =SUM(D42:O42) -> 0 | P42: =SUM(OFFSET(Q42,0,$B$2-1):OFFSET(Q42,0,$B$3-1)) -> 0 | AE42: C_TW | AF42: 0.004608 | AG42: 0.00959232 | AH42: 0.01817232 | AI42: 0.047706005 | AJ42: 0.085157056 | AK42: 0.13064577 | AL42: 0.056861291 | AM42: 0.061639577 | AN42: 0.076645721 | AO42: 0.093168041 | AP42: 0.11175114 | AQ42: 0.13092827 | AR42: =SUM(OFFSET(AF42,0,$B$2-1):OFFSET(AF42,0,$B$3-1)) -> 0.69594724 | AS42: =SUM(AF42:AQ42) -> 0.82687551 | AT42: 0 | AU42: 0.00125 | AV42: 0.00375 | AW42: 0.0075 | AX42: 0.0125 | AY42: 0.01875 | AZ42: 0.02625 | BA42: 0.035 | BB42: 0.045 | BC42: 0.05625 | BD42: 0.06875 | BE42: 0.0825 | BF42: =SUM(OFFSET(AT42,0,$B$2-1):OFFSET(AT42,0,$B$3-1)) -> 0.275 | BG42: =SUM(AT42:BE42) -> 0.3575
A43: C_Paylater | B43: =P43/BG43 -> 0.20896238 | C43: =SUM(D43:O43) -> 0.285 | N43: 0.096 | O43: 0.189 | P43: =SUM(OFFSET(Q43,0,$B$2-1):OFFSET(Q43,0,$B$3-1)) -> 0.572 | R43: =304/1000 -> 0.304 | S43: 0.268 | AE43: C_Paylater | AF43: 0.0864 | AG43: 0.1536 | AH43: 0.2496 | AI43: 0.48034055 | AJ43: 0.77666389 | AK43: 0.3905014 | AL43: 0.57831046 | AM43: 0.77715542 | AN43: 0.98134056 | AO43: 1.1900573 | AP43: 1.4042286 | AQ43: 1.6214378 | AR43: =SUM(OFFSET(AF43,0,$B$2-1):OFFSET(AF43,0,$B$3-1)) -> 7.0681982 | AS43: =SUM(AF43:AQ43) -> 8.689636 | AT43: 0.11016595 | AU43: 0.12869812 | AV43: 0.14938145 | AW43: 0.1705127 | AX43: 0.19209187 | AY43: 0.21411895 | AZ43: 0.23659395 | BA43: 0.25951687 | BB43: 0.2828877 | BC43: 0.30670645 | BD43: 0.33097312 | BE43: 0.3556877 | BF43: =SUM(OFFSET(AT43,0,$B$2-1):OFFSET(AT43,0,$B$3-1)) -> 2.3816471 | BG43: =SUM(AT43:BE43) -> 2.7373348
A44: C_Credit card | B44: =P44/BG44 -> 0.33551186 | C44: =SUM(D44:O44) -> 4.8940771 | D44: 0.2694103 | E44: 0.28896322 | F44: 0.23010821 | G44: 0.30794342 | H44: 0.38291371 | I44: 0.34236086 | J44: 0.40101457 | K44: 0.351 | L44: 0.564 | M44: 0.43436283 | N44: 0.571 | O44: 0.751 | P44: =SUM(OFFSET(Q44,0,$B$2-1):OFFSET(Q44,0,$B$3-1)) -> 2.7121943 | Q44: 0.93119433 | R44: =957/1000 -> 0.957 | S44: 0.824 | AE44: C_Credit card | AF44: 0.33240352 | AG44: 0.36704352 | AH44: 0.39912752 | AI44: 0.42575787 | AJ44: 0.14254225 | AK44: 0.148826 | AL44: 0.16243215 | AM44: 0.17410007 | AN44: 0.18658465 | AO44: 0.19890257 | AP44: 0.2035509 | AQ44: 0.2230384 | AR44: =SUM(OFFSET(AF44,0,$B$2-1):OFFSET(AF44,0,$B$3-1)) -> 2.741271 | AS44: =SUM(AF44:AQ44) -> 2.9643094 | AT44: 0.56053659 | AU44: 0.57992859 | AV44: 0.59967259 | AW44: 0.61976859 | AX44: 0.64021659 | AY44: 0.66101659 | AZ44: 0.68216859 | BA44: 0.70367259 | BB44: 0.72552859 | BC44: 0.74773659 | BD44: 0.77029659 | BE44: 0.79320859 | BF44: =SUM(OFFSET(AT44,0,$B$2-1):OFFSET(AT44,0,$B$3-1)) -> 7.2905425 | BG44: =SUM(AT44:BE44) -> 8.083751
A45: Growth Cost | B45: =P45/BG45 -> 0.5836886 | C45: =SUM(D45:O45) -> 22.086451 | D45: 1.6204707 | E45: 1.3257268 | F45: 1.7904455 | G45: 0.79130439 | H45: 1.2115977 | I45: 1.1760761 | J45: 1.84539 | K45: 0.55998393 | L45: 1.065 | M45: 2.25475 | N45: 4.1 | O45: 4.3457056 | P45: =SUM(OFFSET(Q45,0,$B$2-1):OFFSET(Q45,0,$B$3-1)) -> 34.834377 | Q45: =Q46+Q55 -> 2.631621 | R45: =R46+R55 -> 1.5153659 | S45: =S46+S55 -> 2.0671417 | T45: =T46+T55 -> 3.876 | U45: =U46+U55 -> 3.198932 | V45: =V46+V55 -> 4.1625204 | W45: =W46+W55 -> 6.6706166 | X45: =X46+X55 -> 6.757406 | ... AB45: =AB46+AB55 -> 0 | AE45: Growth Cost | AF45: =AF46+AF55 -> 3.1081269 | AG45: =AG46+AG55 -> 2.9671978 | AH45: =AH46+AH55 -> 3.2957391 | AI45: =AI46+AI55 -> 3.7871585 | AJ45: =AJ46+AJ55 -> 4.1571859 | AK45: =AK46+AK55 -> 4.4914171 | AL45: =AL46+AL55 -> 4.8828646 | AM45: =AM46+AM55 -> 5.1641633 | ... AQ45: =AQ46+AQ55 -> 6.6740163 | AR45: =SUM(OFFSET(AF45,0,$B$2-1):OFFSET(AF45,0,$B$3-1)) -> 49.600463 | AS45: =SUM(AF45:AQ45) -> 56.27448 | AT45: =AT46+AT55 -> 5.2281608 | AU45: =AU46+AU55 -> 4.5971754 | AV45: =AV46+AV55 -> 4.7105257 | AW45: =AW46+AW55 -> 4.8247926 | AX45: =AX46+AX55 -> 4.8060254 | AY45: =AY46+AY55 -> 4.9161748 | AZ45: =AZ46+AZ55 -> 4.9162409 | BA45: =BA46+BA55 -> 5.0206782 | ... BE45: =BE46+BE55 -> 4.9621297 | BF45: =SUM(OFFSET(AT45,0,$B$2-1):OFFSET(AT45,0,$B$3-1)) -> 54.717599 | BG45: =SUM(AT45:BE45) -> 59.679728
A46: Variable cost - Acquire customer | B46: =P46/BG46 -> 0.74026662 | C46: =SUM(D46:O46) -> 16.697116 | D46: 1.5194707 | E46: 0.93499966 | F46: 1.640623 | G46: 0.58746257 | H46: 0.61862184 | I46: 0.5438675 | J46: 1.2507503 | K46: 0.34304252 | L46: 1.01 | M46: 1.15475 | N46: 3.9 | O46: 3.1935283 | P46: =SUM(OFFSET(Q46,0,$B$2-1):OFFSET(Q46,0,$B$3-1)) -> 32.816834 | Q46: 2.5519197 | R46: =1327.942642/1000 -> 1.3279426 | S46: =1567.257847/1000 -> 1.5672578 | T46: 3.244 | U46: 3.0376885 | V46: 3.9890682 | W46: 6.4735809 | X46: 6.6716615 | Y46: 3.9537145 | Z46: =SUM(Z48:Z54) -> 0 | AA46: =SUM(AA48:AA54) -> 0 | AB46: =SUM(AB48:AB54) -> 0 | AE46: Variable cost - Acquire customer | AF46: =SUM(AF48:AF54) -> 2.1016132 | AG46: =SUM(AG48:AG54) -> 1.858346 | AH46: =SUM(AH48:AH54) -> 2.0912056 | AI46: =SUM(AI48:AI54) -> 2.4944788 | AJ46: =SUM(AJ48:AJ54) -> 2.778269 | AK46: =SUM(AK48:AK54) -> 3.0563393 | AL46: =SUM(AL48:AL54) -> 3.3176198 | AM46: =SUM(AM48:AM54) -> 3.5002507 | ... AQ46: =SUM(AQ48:AQ54) -> 4.5602935 | AR46: =SUM(OFFSET(AF46,0,$B$2-1):OFFSET(AF46,0,$B$3-1)) -> 33.346151 | AS46: =SUM(AF46:AQ46) -> 37.906445 | AT46: =SUM(AT47:AT54) -> 3.4397333 | AU46: =SUM(AU47:AU54) -> 3.6938667 | AV46: =SUM(AV47:AV54) -> 3.7359 | AW46: =SUM(AW47:AW54) -> 3.7779333 | AX46: =SUM(AX47:AX54) -> 3.6959667 | AY46: =SUM(AY47:AY54) -> 3.742 | AZ46: =SUM(AZ47:AZ54) -> 3.6770333 | BA46: =SUM(BA47:BA54) -> 3.7200667 | ... BE46: =SUM(BE47:BE54) -> 3.4302 | BF46: =SUM(OFFSET(AT46,0,$B$2-1):OFFSET(AT46,0,$B$3-1)) -> 40.9009 | BG46: =SUM(AT46:BE46) -> 44.3311
A47: CASA | AT47: 0.425 | AU47: 0.425 | AV47: 0.425 | AW47: 0.425 | AX47: 0.425 | AY47: 0.425 | AZ47: 0.425 | BA47: 0.425 | BB47: 0.425 | BC47: 0.425 | BD47: 0.425 | BE47: 0.425 | BF47: =SUM(OFFSET(AT47,0,$B$2-1):OFFSET(AT47,0,$B$3-1)) -> 4.675 | BG47: =SUM(AT47:BE47) -> 5.1
A48: Acquire TD | B48: =P48/BG48 -> 0 | C48: =SUM(D48:O48) -> 2.8181757 | D48: 0.0703825 | E48: 0.1253475 | F48: 0.923 | G48: 0.066580072 | H48: 0.065245308 | I48: 0.04375 | J48: 0.15537031 | K48: 0.215 | L48: 0.21 | M48: 0.2435 | N48: 0.7 | P48: =SUM(OFFSET(Q48,0,$B$2-1):OFFSET(Q48,0,$B$3-1)) -> 0 | AE48: Acquire TD | AF48: 0.44444444 | AG48: 0.44444444 | AH48: 0.44444444 | AI48: 0.44444444 | AJ48: 0.44444444 | AK48: 0.44444444 | AL48: 0.44444444 | AM48: 0.44444444 | AN48: 0.44444444 | AO48: 0.44444444 | AP48: 0.44444444 | AQ48: 0.44444444 | AR48: =SUM(OFFSET(AF48,0,$B$2-1):OFFSET(AF48,0,$B$3-1)) -> 4.8888889 | AS48: =SUM(AF48:AQ48) -> 5.3333333 | AT48: 0.5684 | AU48: 0.7582 | AV48: 0.7359 | AW48: 0.7136 | AX48: 0.5673 | AY48: 0.549 | AZ48: 0.5307 | BA48: 0.5124 | BB48: 0.4941 | BC48: 0.4758 | BD48: 0.4575 | BE48: 0.1032 | BF48: =SUM(OFFSET(AT48,0,$B$2-1):OFFSET(AT48,0,$B$3-1)) -> 6.3629 | BG48: =SUM(AT48:BE48) -> 6.4661
A49: Acquire Vay kỳ hạn | B49: =P49/BG49 -> 0 | C49: =SUM(D49:O49) -> 0 | P49: =SUM(OFFSET(Q49,0,$B$2-1):OFFSET(Q49,0,$B$3-1)) -> 0 | AE49: Acquire Vay kỳ hạn | AF49: 0.38579371 | AG49: 0.21838657 | AH49: 0.34047994 | AI49: 0.42499773 | AJ49: 0.48861807 | AK49: 0.53746789 | AL49: 0.57028293 | AM49: 0.54897996 | AN49: 0.59331304 | AO49: 0.664 | AP49: 0.69 | AQ49: 0.71 | AR49: =SUM(OFFSET(AF49,0,$B$2-1):OFFSET(AF49,0,$B$3-1)) -> 5.4623198 | AS49: =SUM(AF49:AQ49) -> 6.1723198 | AT49: 1.767 | AU49: 1.824 | AV49: 1.881 | AW49: 1.938 | AX49: 1.995 | AY49: 2.052 | AZ49: 1.998 | BA49: 2.052 | BB49: 2.106 | BC49: 2.16 | BD49: 2.214 | BE49: 2.142 | BF49: =SUM(OFFSET(AT49,0,$B$2-1):OFFSET(AT49,0,$B$3-1)) -> 21.987 | BG49: =SUM(AT49:BE49) -> 24.129
A50: Acquire Vay ngắn ngày | B50: =P50/BG50 -> 0 | C50: =SUM(D50:O50) -> 0 | P50: =SUM(OFFSET(Q50,0,$B$2-1):OFFSET(Q50,0,$B$3-1)) -> 0 | AE50: Acquire Vay ngắn ngày | AF50: 0.165375 | AG50: 0.106575 | AH50: 0.15925 | AI50: 0.17395 | AJ50: 0.17395 | AK50: 0.1764 | AL50: 0.196 | AM50: 0.196 | AN50: 0.2 | AO50: 0.22322222 | AP50: 0.22322222 | AQ50: 0.22333333 | AR50: =SUM(OFFSET(AF50,0,$B$2-1):OFFSET(AF50,0,$B$3-1)) -> 1.9939444 | AS50: =SUM(AF50:AQ50) -> 2.2172778 | AT50: 0.00083333333 | AU50: 0.0016666667 | AV50: 0.0025 | AW50: 0.0033333333 | AX50: 0.0041666667 | AY50: 0.005 | AZ50: 0.0058333333 | BA50: 0.0066666667 | BB50: 0.0075 | BC50: 0.0083333333 | BD50: 0.0091666667 | BE50: 0.01 | BF50: =SUM(OFFSET(AT50,0,$B$2-1):OFFSET(AT50,0,$B$3-1)) -> 0.055 | BG50: =SUM(AT50:BE50) -> 0.065
A51: Acquire Overdraft | B51: =P51/BG51 -> 0 | C51: =SUM(D51:O51) -> 0 | P51: =SUM(OFFSET(Q51,0,$B$2-1):OFFSET(Q51,0,$B$3-1)) -> 0 | AE51: Acquire Overdraft | AF51: 0.08 | AG51: 0.08 | AH51: 0.08 | AI51: 0.08 | AJ51: 0.08 | AK51: 0.08 | AL51: 0.08 | AM51: 0.08 | AN51: 0.08 | AO51: 0.08 | AP51: 0.08 | AQ51: 0.08 | AR51: =SUM(OFFSET(AF51,0,$B$2-1):OFFSET(AF51,0,$B$3-1)) -> 0.88 | AS51: =SUM(AF51:AQ51) -> 0.96 | AT51: 0.0785 | AU51: 0.085 | AV51: 0.0915 | AW51: 0.098 | AX51: 0.1045 | AY51: 0.111 | AZ51: 0.1175 | BA51: 0.124 | BB51: 0.1305 | BC51: 0.137 | BD51: 0.1435 | BE51: 0.15 | BF51: =SUM(OFFSET(AT51,0,$B$2-1):OFFSET(AT51,0,$B$3-1)) -> 1.221 | BG51: =SUM(AT51:BE51) -> 1.371
A52: Acquire TW | B52: =P52/BG52 -> #DIV/0! | C52: =SUM(D52:O52) -> 0 | P52: =SUM(OFFSET(Q52,0,$B$2-1):OFFSET(Q52,0,$B$3-1)) -> 0 | AE52: Acquire TW | AF52: 0.036 | AG52: 0.03894 | AH52: 0.06703125 | AI52: 0.23073191 | AJ52: 0.29258633 | AK52: 0.35538056 | AL52: 0.40086223 | AM52: 0.42765501 | AN52: 0.45018432 | AO52: 0.49566961 | AP52: 0.5574931 | AQ52: 0.5753138 | AR52: =SUM(OFFSET(AF52,0,$B$2-1):OFFSET(AF52,0,$B$3-1)) -> 3.3525343 | AS52: =SUM(AF52:AQ52) -> 3.9278481 | BF52: =SUM(OFFSET(AT52,0,$B$2-1):OFFSET(AT52,0,$B$3-1)) -> 0 | BG52: =SUM(AT52:BE52) -> 0
A53: Acquire Paylater | B53: =P53/BG53 -> #DIV/0! | C53: =SUM(D53:O53) -> 0 | P53: =SUM(OFFSET(Q53,0,$B$2-1):OFFSET(Q53,0,$B$3-1)) -> 0 | AE53: Acquire Paylater | AF53: 0.09 | AG53: 0.07 | AH53: 0.1 | AI53: 0.24035474 | AJ53: 0.39867015 | AK53: 0.56264645 | AL53: 0.72603019 | AM53: 0.90317128 | AN53: 1.0792873 | AO53: 1.2583688 | AP53: 1.4399348 | AQ53: 1.6272019 | AR53: =SUM(OFFSET(AF53,0,$B$2-1):OFFSET(AF53,0,$B$3-1)) -> 6.8684636 | AS53: =SUM(AF53:AQ53) -> 8.4956655 | BF53: =SUM(OFFSET(AT53,0,$B$2-1):OFFSET(AT53,0,$B$3-1)) -> 0 | BG53: =SUM(AT53:BE53) -> 0
A54: Acquire Credit card | B54: =P54/BG54 -> 0 | C54: =SUM(D54:O54) -> 10.657677 | D54: 1.4490882 | E54: 0.80965216 | F54: 0.6898875 | G54: 0.5208825 | H54: 0.55337653 | I54: 0.5001175 | J54: 1.09538 | K54: 0.12804252 | L54: 0.8 | M54: 0.91125 | N54: 3.2 | P54: =SUM(OFFSET(Q54,0,$B$2-1):OFFSET(Q54,0,$B$3-1)) -> 0 | AE54: Acquire Credit card | AF54: 0.9 | AG54: 0.9 | AH54: 0.9 | AI54: 0.9 | AJ54: 0.9 | AK54: 0.9 | AL54: 0.9 | AM54: 0.9 | AN54: 0.9 | AO54: 0.9 | AP54: 0.9 | AQ54: 0.9 | AR54: =SUM(OFFSET(AF54,0,$B$2-1):OFFSET(AF54,0,$B$3-1)) -> 9.9 | AS54: =SUM(AF54:AQ54) -> 10.8 | AT54: 0.6 | AU54: 0.6 | AV54: 0.6 | AW54: 0.6 | AX54: 0.6 | AY54: 0.6 | AZ54: 0.6 | BA54: 0.6 | BB54: 0.6 | BC54: 0.6 | BD54: 0.6 | BE54: 0.6 | BF54: =SUM(OFFSET(AT54,0,$B$2-1):OFFSET(AT54,0,$B$3-1)) -> 6.6 | BG54: =SUM(AT54:BE54) -> 7.2
A55: Variable cost - Promotion | B55: =P55/BG55 -> 0.1314478 | C55: =SUM(D55:O55) -> 5.3893342 | D55: 0.101 | E55: 0.39072714 | F55: 0.14982257 | G55: 0.20384182 | H55: 0.59297584 | I55: 0.63220856 | J55: 0.59463964 | K55: 0.2169414 | L55: 0.055 | M55: 1.1 | N55: 0.2 | O55: 1.1521772 | P55: =SUM(OFFSET(Q55,0,$B$2-1):OFFSET(Q55,0,$B$3-1)) -> 2.0175434 | Q55: 0.079701329 | R55: =187.423233888889/1000 -> 0.18742323 | S55: =499.883868888889/1000 -> 0.49988387 | T55: 0.632 | U55: 0.16124353 | V55: 0.17345222 | W55: 0.19703575 | X55: 0.08574449 | Y55: 0.001058991 | Z55: =SUM(Z57:Z58) -> 0 | AA55: =SUM(AA57:AA58) -> 0 | AB55: =SUM(AB57:AB58) -> 0 | AE55: Variable cost - Promotion | AF55: =AF57+AF58 -> 1.0065138 | AG55: =AG57+AG58 -> 1.1088518 | AH55: =AH57+AH58 -> 1.2045335 | AI55: =AI57+AI58 -> 1.2926796 | AJ55: =AJ57+AJ58 -> 1.3789169 | AK55: =AK57+AK58 -> 1.4350778 | AL55: =AL57+AL58 -> 1.5652448 | AM55: =AM57+AM58 -> 1.6639126 | ... AQ55: =AQ57+AQ58 -> 2.1137228 | AR55: =SUM(OFFSET(AF55,0,$B$2-1):OFFSET(AF55,0,$B$3-1)) -> 16.254312 | AS55: =SUM(AF55:AQ55) -> 18.368035 | AT55: =SUM(AT56:AT58) -> 1.7884275 | AU55: =SUM(AU56:AU58) -> 0.9033087 | AV55: =SUM(AV56:AV58) -> 0.97462566 | AW55: =SUM(AW56:AW58) -> 1.0468593 | AX55: =SUM(AX56:AX58) -> 1.1100587 | AY55: =SUM(AY56:AY58) -> 1.1741748 | AZ55: =SUM(AZ56:AZ58) -> 1.2392076 | BA55: =SUM(BA56:BA58) -> 1.3006115 | ... BE55: =SUM(BE56:BE58) -> 1.5319297 | BF55: =SUM(OFFSET(AT55,0,$B$2-1):OFFSET(AT55,0,$B$3-1)) -> 13.816699 | BG55: =SUM(AT55:BE55) -> 15.348628
A56: CASA | AT56: 0.13409091 | AU56: 0.15454545 | AV56: 0.17272727 | AW56: 0.19090909 | AX56: 0.20454545 | AY56: 0.21818182 | AZ56: 0.23181818 | BA56: 0.24090909 | BB56: 0.25 | BC56: 0.25909091 | BD56: 0.26818182 | BE56: 0.27272727 | BF56: =SUM(OFFSET(AT56,0,$B$2-1):OFFSET(AT56,0,$B$3-1)) -> 2.325 | BG56: =SUM(AT56:BE56) -> 2.5977273
A57: TD | B57: =P57/BG57 -> 0 | C57: =SUM(D57:O57) -> 1.5725366 | D57: 0.101 | E57: 0.04344 | F57: 0.05275 | G57: 0.15 | H57: 0.20557284 | I57: 0.51752773 | J57: 0.502246 | P57: =SUM(OFFSET(Q57,0,$B$2-1):OFFSET(Q57,0,$B$3-1)) -> 0 | AE57: Promotion Deposit products | AF57: 0.19560185 | AG57: 0.20717593 | AH57: 0.21875 | AI57: 0.23032407 | AJ57: 0.24189815 | AK57: 0.25347222 | AL57: 0.2650463 | AM57: 0.27662037 | AN57: 0.28819444 | AO57: 0.29976852 | AP57: 0.31134259 | AQ57: 0.32291667 | AR57: =SUM(OFFSET(AF57,0,$B$2-1):OFFSET(AF57,0,$B$3-1)) -> 2.7881944 | AS57: =SUM(AF57:AQ57) -> 3.1111111 | AT57: 0.24418919 | AU57: 0.27432432 | AV57: 0.30445946 | AW57: 0.33459459 | AX57: 0.35932432 | AY57: 0.38405405 | AZ57: 0.40878378 | BA57: 0.43351351 | BB57: 0.45824324 | BC57: 0.48297297 | BD57: 0.5077027 | BE57: 0.51351351 | BF57: =SUM(OFFSET(AT57,0,$B$2-1):OFFSET(AT57,0,$B$3-1)) -> 4.1921622 | BG57: =SUM(AT57:BE57) -> 4.7056757
A58: Credit card usage | B58: =P58/BG58 -> 0 | C58: =SUM(D58:O58) -> 2.4026443 | E58: 0.34728714 | F58: 0.097072567 | G58: 0.053841817 | H58: 0.387403 | I58: 0.11468083 | J58: 0.092393647 | K58: 0.2169414 | M58: 1.0930239 | P58: =SUM(OFFSET(Q58,0,$B$2-1):OFFSET(Q58,0,$B$3-1)) -> 0 | AE58: Promotion Credit card usage | AF58: 0.81091194 | AG58: 0.90167583 | AH58: 0.98578347 | AI58: 1.0623556 | AJ58: 1.1370187 | AK58: 1.1816056 | AL58: 1.3001985 | AM58: 1.3872922 | AN58: 1.4841082 | AO58: 1.5877297 | AP58: 1.6274381 | AQ58: 1.7908061 | AR58: =SUM(OFFSET(AF58,0,$B$2-1):OFFSET(AF58,0,$B$3-1)) -> 13.466118 | AS58: =SUM(AF58:AQ58) -> 15.256924 | AT58: 1.4101474 | AU58: 0.47443892 | AV58: 0.49743892 | AW58: 0.52135559 | AX58: 0.54618892 | AY58: 0.57193892 | AZ58: 0.59860559 | BA58: 0.62618892 | BB58: 0.65468892 | BC58: 0.68410559 | BD58: 0.71443892 | BE58: 0.74568892 | BF58: =SUM(OFFSET(AT58,0,$B$2-1):OFFSET(AT58,0,$B$3-1)) -> 7.2995366 | BG58: =SUM(AT58:BE58) -> 8.0452255
A59: Sharing expenses for partner | B59: =P59/BG59 -> 0.60679964 | C59: =SUM(D59:O59) -> 131.17642 | D59: 4.2301037 | E59: 3.508855 | F59: 1.4571096 | G59: 9.8364255 | H59: 10.443399 | I59: 9.7040827 | J59: 11.104842 | K59: 12.978613 | L59: 18.179 | M59: 19.323441 | N59: 20.503 | O59: 9.9075449 | P59: =SUM(OFFSET(Q59,0,$B$2-1):OFFSET(Q59,0,$B$3-1)) -> 224.21591 | Q59: =SUM(Q60:Q65) -> 13.336914 | R59: =SUM(R60:R65) -> 16.678493 | S59: =SUM(S60:S65) -> 15.882814 | T59: 23.169 | U59: 19.370166 | V59: 23.953242 | W59: 37.094831 | X59: 31.812427 | Y59: 42.918019 | Z59: =SUM(Z60:Z65) -> 0 | AA59: =SUM(AA60:AA65) -> 0 | AB59: =SUM(AB60:AB65) -> 0 | AE59: Sharing expenses for partner | AF59: =SUM(AF60:AF65) -> 14.958493 | AG59: =SUM(AG60:AG65) -> 11.352092 | AH59: =SUM(AH60:AH65) -> 17.114848 | AI59: =SUM(AI60:AI65) -> 20.405769 | AJ59: =SUM(AJ60:AJ65) -> 21.977896 | AK59: =SUM(AK60:AK65) -> 26.171306 | AL59: =SUM(AL60:AL65) -> 29.553722 | AM59: =SUM(AM60:AM65) -> 29.206147 | ... AQ59: =SUM(AQ60:AQ65) -> 37.449019 | AR59: =SUM(OFFSET(AF59,0,$B$2-1):OFFSET(AF59,0,$B$3-1)) -> 273.67198 | AS59: =SUM(AF59:AQ59) -> 311.121 | AT59: =SUM(AT60:AT65) -> 27.894042 | AU59: =SUM(AU60:AU65) -> 28.461746 | AV59: =SUM(AV60:AV65) -> 29.544495 | AW59: =SUM(AW60:AW65) -> 29.687298 | AX59: =SUM(AX60:AX65) -> 30.420259 | AY59: =SUM(AY60:AY65) -> 30.541293 | AZ59: =SUM(AZ60:AZ65) -> 28.87809 | BA59: =SUM(BA60:BA65) -> 29.605402 | ... BE59: =SUM(BE60:BE65) -> 36.898021 | BF59: =SUM(OFFSET(AT59,0,$B$2-1):OFFSET(AT59,0,$B$3-1)) -> 332.60765 | BG59: =SUM(AT59:BE59) -> 369.50567
A60: Sharing expense Huy động | B60: =P60/BG60 -> 0.097195828 | C60: =SUM(D60:O60) -> 9.2054036 | D60: 0.66279853 | E60: 0.66596756 | F60: 0.71455004 | G60: 0.70298953 | H60: 0.74445641 | I60: 0.74059144 | J60: 0.77735481 | K60: 0.79620982 | L60: 0.8 | M60: 0.85894055 | N60: 0.853 | O60: 0.88854493 | P60: =SUM(OFFSET(Q60,0,$B$2-1):OFFSET(Q60,0,$B$3-1)) -> 3.0191535 | Q60: 0.92989478 | R60: =969.053328/1000 -> 0.96905333 | S60: 1.1202054 | AE60: Sharing expense Huy động | AF60: 0.70416667 | AG60: 0.74583333 | AH60: 0.7875 | AI60: 0.82916667 | AJ60: 0.87083333 | AK60: 0.9125 | AL60: 1.1131944 | AM60: 1.1618056 | AN60: 1.2104167 | AO60: 1.2590278 | AP60: 1.3076389 | AQ60: 1.35625 | AR60: =SUM(OFFSET(AF60,0,$B$2-1):OFFSET(AF60,0,$B$3-1)) -> 10.902083 | AS60: =SUM(AF60:AQ60) -> 12.258333 | AT60: 1.0641875 | AU60: 1.2893542 | AV60: 1.5409375 | AW60: 1.8134375 | AX60: 2.0900208 | AY60: 2.3686875 | AZ60: 2.6646042 | BA60: 2.9759375 | BB60: 3.3023542 | BC60: 3.6453542 | BD60: 4.0049375 | BE60: 4.3027708 | BF60: =SUM(OFFSET(AT60,0,$B$2-1):OFFSET(AT60,0,$B$3-1)) -> 26.759813 | BG60: =SUM(AT60:BE60) -> 31.062583
A61: Sharing expense Vay kỳ hạn | B61: =P61/BG61 -> 0.10502671 | C61: =SUM(D61:O61) -> 83.703453 | D61: 1.969461 | E61: 1.171049 | F61: 0.17451087 | G61: 7.589826 | H61: 7.319936 | I61: 5.1820234 | J61: 5.3944862 | K61: 8.6991602 | L61: 12.913 | M61: 13.722 | N61: 15.85 | O61: 3.718 | P61: =SUM(OFFSET(Q61,0,$B$2-1):OFFSET(Q61,0,$B$3-1)) -> 26.693457 | Q61: 6.7934214 | R61: =10618.5465435/1000 -> 10.618547 | S61: 9.2814889 | AE61: Sharing expense Vay kỳ hạn | AF61: 10.279927 | AG61: 7.8788806 | AH61: 12.254349 | AI61: 14.435488 | AJ61: 14.919249 | AK61: 17.932502 | AL61: 20.071765 | AM61: 18.951884 | AN61: 20.466533 | AO61: 21.482879 | AP61: 17.859071 | AQ61: 19.564695 | AR61: =SUM(OFFSET(AF61,0,$B$2-1):OFFSET(AF61,0,$B$3-1)) -> 176.53253 | AS61: =SUM(AF61:AQ61) -> 196.09722 | AT61: 21.42071 | AU61: 21.551415 | AV61: 21.680693 | AW61: 21.301292 | AX61: 21.625875 | AY61: 21.608731 | AZ61: 19.347271 | BA61: 19.369287 | BB61: 19.61963 | BC61: 20.815143 | BD61: 22.147864 | BE61: 23.670828 | BF61: =SUM(OFFSET(AT61,0,$B$2-1):OFFSET(AT61,0,$B$3-1)) -> 230.48791 | BG61: =SUM(AT61:BE61) -> 254.15874
A62: Sharing expense Vay ngắn ngày | B62: =P62/BG62 -> 0.21740895 | C62: =SUM(D62:O62) -> 38.267559 | D62: 1.5978442 | E62: 1.6718384 | F62: 0.56804865 | G62: 1.54361 | H62: 2.3790062 | I62: 3.7814679 | J62: 4.9330013 | K62: 3.4832428 | L62: 4.466 | M62: 4.7425 | N62: 3.8 | O62: 5.301 | P62: =SUM(OFFSET(Q62,0,$B$2-1):OFFSET(Q62,0,$B$3-1)) -> 16.18561 | Q62: 5.6135973 | R62: =5090.8928195/1000 -> 5.0908928 | S62: 5.4811202 | AE62: Sharing expense Vay ngắn ngày | AF62: 3.2397 | AG62: 1.8859592 | AH62: 2.7381343 | AI62: 2.9982662 | AJ62: 2.8875929 | AK62: 2.7606431 | AL62: 3.2241728 | AM62: 2.76005 | AN62: 2.6667232 | AO62: 3.3694333 | AP62: 3.2347445 | AQ62: 2.9966164 | AR62: =SUM(OFFSET(AF62,0,$B$2-1):OFFSET(AF62,0,$B$3-1)) -> 31.765419 | AS62: =SUM(AF62:AQ62) -> 34.762036 | AT62: 5.4683474 | AU62: 5.6926401 | AV62: 6.0693636 | AW62: 6.0788226 | AX62: 6.2114018 | AY62: 6.0304161 | AZ62: 6.1693146 | BA62: 6.2929738 | BB62: 6.4144244 | BC62: 6.5406619 | BD62: 6.674059 | BE62: 6.8053388 | BF62: =SUM(OFFSET(AT62,0,$B$2-1):OFFSET(AT62,0,$B$3-1)) -> 67.642426 | BG62: =SUM(AT62:BE62) -> 74.447764
A63: Sharing expense TW | B63: =P63/BG63 -> 0 | C63: =SUM(D63:O63) -> 0 | P63: =SUM(OFFSET(Q63,0,$B$2-1):OFFSET(Q63,0,$B$3-1)) -> 0 | AE63: Sharing expense TW | AF63: 0.115 | AG63: 0.089070246 | AH63: 0.14095156 | AI63: 0.12684879 | AJ63: 0.16647493 | AK63: 0.18358314 | AL63: 0.1312484 | AM63: 0.12541736 | AN63: 0.14446115 | AO63: 0.15337004 | AP63: 0.17846621 | AQ63: 0.17752896 | AR63: =SUM(OFFSET(AF63,0,$B$2-1):OFFSET(AF63,0,$B$3-1)) -> 1.5548918 | AS63: =SUM(AF63:AQ63) -> 1.7324208 | AT63: 0.096833333 | AU63: 0.19260049 | AV63: 0.31134666 | AW63: 0.44315978 | AX63: 0.57415605 | AY63: 0.70543893 | AZ63: 0.83959543 | BA63: 0.98504928 | BB63: 1.1348763 | BC63: 1.2927761 | BD63: 1.4558564 | BE63: 1.6217448 | BF63: =SUM(OFFSET(AT63,0,$B$2-1):OFFSET(AT63,0,$B$3-1)) -> 8.0316888 | BG63: =SUM(AT63:BE63) -> 9.6534335
A64: Sharing expense Paylater | B64: =P64/BG64 -> 0 | C64: =SUM(D64:O64) -> 0 | P64: =SUM(OFFSET(Q64,0,$B$2-1):OFFSET(Q64,0,$B$3-1)) -> 0 | AE64: Sharing expense Paylater | AF64: 0.4685625 | AG64: 0.41931386 | AH64: 0.63193423 | AI64: 1.3039607 | AJ64: 2.2011598 | AK64: 3.2020059 | AL64: 3.7764627 | AM64: 4.7905103 | AN64: 5.7703564 | AO64: 8.4569871 | AP64: 9.6968108 | AQ64: 10.955532 | AR64: =SUM(OFFSET(AF64,0,$B$2-1):OFFSET(AF64,0,$B$3-1)) -> 40.718064 | AS64: =SUM(AF64:AQ64) -> 51.673596 | AT64: -0.19527119 | AU64: -0.30418873 | AV64: -0.11162971 | AW64: -0.021860048 | AX64: -0.14070082 | AY64: -0.22386288 | AZ64: -0.26102529 | BA64: -0.21778665 | BB64: -0.21834537 | BC64: -0.15323672 | BD64: -0.14572244 | BE64: -0.084395268 | BF64: =SUM(OFFSET(AT64,0,$B$2-1):OFFSET(AT64,0,$B$3-1)) -> -1.9936298 | BG64: =SUM(AT64:BE64) -> -2.0780251
A65: Sharing expense Credit card | B65: =P65/BG65 -> 0 | C65: =SUM(D65:O65) -> 0 | P65: =SUM(OFFSET(Q65,0,$B$2-1):OFFSET(Q65,0,$B$3-1)) -> 0 | AE65: Sharing expense Credit card | AF65: 0.15113672 | AG65: 0.3330344 | AH65: 0.56197911 | AI65: 0.71203862 | AJ65: 0.93258632 | AK65: 1.180071 | AL65: 1.2368788 | AM65: 1.4164792 | AN65: 1.6367692 | AO65: 1.8911068 | AP65: 2.1469108 | AQ65: 2.398397 | AR65: =SUM(OFFSET(AF65,0,$B$2-1):OFFSET(AF65,0,$B$3-1)) -> 12.198991 | AS65: =SUM(AF65:AQ65) -> 14.597388 | AT65: 0.03923529 | AU65: 0.039925196 | AV65: 0.053784304 | AW65: 0.072445843 | AX65: 0.059505589 | AY65: 0.051882415 | AZ65: 0.11832988 | BA65: 0.19994102 | BB65: 0.23748936 | BC65: 0.27949747 | BD65: 0.52740234 | BE65: 0.58173312 | BF65: =SUM(OFFSET(AT65,0,$B$2-1):OFFSET(AT65,0,$B$3-1)) -> 1.6794387 | BG65: =SUM(AT65:BE65) -> 2.2611718
A66: Profit before provision | B66: =P66/BG66 -> 0.68665987 | C66: =SUM(D66:O66) -> 632.75659 | D66: 18.260659 | E66: 19.471683 | F66: 25.668248 | G66: 24.757437 | H66: 30.156922 | I66: 47.682079 | J66: 56.623864 | K66: 75.97382 | L66: 60.186778 | M66: 83.880071 | N66: 82.632224 | O66: 107.4628 | P66: =SUM(OFFSET(Q66,0,$B$2-1):OFFSET(Q66,0,$B$3-1)) -> 1234.161 | Q66: =Q16-Q30 -> 92.778751 | R66: =R16-R30 -> 80.389314 | S66: =S16-S30 -> 105.27549 | T66: =T16-T30 -> 107.60232 | U66: =U16-U30 -> 129.81342 | V66: =V16-V30 -> 146.03276 | W66: =W16-W30 -> 154.25047 | X66: =X16-X30 -> 187.99018 | ... AB66: =AB16-AB30 -> 0 | AE66: Profit before provision | AF66: =AF16-AF30 -> 20.861213 | AG66: =AG16-AG30 -> 21.87388 | AH66: =AH16-AH30 -> 27.420652 | AI66: =AI16-AI30 -> 31.795343 | AJ66: =AJ16-AJ30 -> 42.241752 | AK66: =AK16-AK30 -> 50.367058 | AL66: =AL16-AL30 -> 57.786152 | AM66: =AM16-AM30 -> 66.031168 | ... AQ66: =AQ16-AQ30 -> 141.38186 | AR66: =SUM(OFFSET(AF66,0,$B$2-1):OFFSET(AF66,0,$B$3-1)) -> 560.4754 | AS66: =SUM(AF66:AQ66) -> 701.85725 | AT66: =AT16-AT30 -> 92.772685 | AU66: =AU16-AU30 -> 100.58529 | AV66: =AV16-AV30 -> 109.3463 | AW66: =AW16-AW30 -> 118.6172 | AX66: =AX16-AX30 -> 128.7199 | AY66: =AY16-AY30 -> 139.01964 | AZ66: =AZ16-AZ30 -> 152.02931 | BA66: =BA16-BA30 -> 162.24422 | ... BE66: =BE16-BE30 -> 240.79315 | BF66: =SUM(OFFSET(AT66,0,$B$2-1):OFFSET(AT66,0,$B$3-1)) -> 1556.5465 | BG66: =SUM(AT66:BE66) -> 1797.3397
A67: Provision expenses | B67: =P67/BG67 -> 0.63080652 | C67: =SUM(D67:O67) -> 266.77638 | D67: 9.1449659 | E67: 13.386717 | F67: 15.929969 | G67: 13.381908 | H67: 13.941157 | I67: 19.772303 | J67: 28.509015 | K67: 24.790119 | L67: 26.107888 | M67: 28.202336 | N67: 30.448 | O67: 43.162 | P67: =SUM(OFFSET(Q67,0,$B$2-1):OFFSET(Q67,0,$B$3-1)) -> 728.78854 | Q67: =SUM(Q68:Q73) -> 99.626458 | R67: =SUM(R68:R73) -> 59.83 | S67: =SUM(S68:S73) -> 73.835694 | T67: 51.889 | U67: 73.619902 | V67: 84.570489 | W67: 69.217 | X67: 104.307 | Y67: 111.893 | Z67: =SUM(Z68:Z73) -> 0 | AA67: =SUM(AA68:AA73) -> 0 | AB67: =SUM(AB68:AB73) -> 0 | AE67: Provision expenses | AF67: =SUM(AF68:AF73) -> 17.256413 | AG67: =SUM(AG68:AG73) -> 21.435962 | AH67: =SUM(AH68:AH73) -> 13.860857 | AI67: =SUM(AI68:AI73) -> 13.279422 | AJ67: =SUM(AJ68:AJ73) -> 17.327316 | AK67: =SUM(AK68:AK73) -> 17.130277 | AL67: =SUM(AL68:AL73) -> 18.603238 | AM67: =SUM(AM68:AM73) -> 19.910325 | ... AQ67: =SUM(AQ68:AQ73) -> 33.542685 | AR67: =SUM(OFFSET(AF67,0,$B$2-1):OFFSET(AF67,0,$B$3-1)) -> 218.93953 | AS67: =SUM(AF67:AQ67) -> 252.48222 | AT67: =SUM(AT68:AT73) -> 105.68636 | AU67: =SUM(AU68:AU73) -> 56.612029 | AV67: =SUM(AV68:AV73) -> 67.470802 | AW67: =SUM(AW68:AW73) -> 74.480451 | AX67: =SUM(AX68:AX73) -> 79.95488 | AY67: =SUM(AY68:AY73) -> 87.14543 | AZ67: =SUM(AZ68:AZ73) -> 97.005275 | BA67: =SUM(BA68:BA73) -> 106.16858 | ... BE67: =SUM(BE68:BE73) -> 126.8668 | BF67: =SUM(OFFSET(AT67,0,$B$2-1):OFFSET(AT67,0,$B$3-1)) -> 1028.4614 | BG67: =SUM(AT67:BE67) -> 1155.3282
A68: Vay kỳ hạn Provision | B68: =P68/BG68 -> 0.17913726 | C68: =SUM(D68:O68) -> 120.69941 | D68: 2.2453543 | E68: 2.9558034 | F68: 3.2753034 | G68: 5.0749657 | H68: 5.4767027 | I68: 6.4100901 | J68: 14.372958 | K68: 12.696 | L68: 13.621412 | M68: 14.305823 | N68: 16.514 | O68: 23.751 | P68: =SUM(OFFSET(Q68,0,$B$2-1):OFFSET(Q68,0,$B$3-1)) -> 138.0122 | Q68: 55.301742 | R68: =37431/1000 -> 37.431 | S68: 45.279458 | AE68: Vay kỳ hạn Provision | AF68: 2.240576 | AG68: 4.6746317 | AH68: 2.8582128 | AI68: 4.6437091 | AJ68: 8.3213588 | AK68: 7.6708064 | AL68: 8.2702096 | AM68: 8.5431316 | AN68: 9.2925866 | AO68: 12.483451 | AP68: 19.865459 | AQ68: 18.912467 | AR68: =SUM(OFFSET(AF68,0,$B$2-1):OFFSET(AF68,0,$B$3-1)) -> 88.864132 | AS68: =SUM(AF68:AQ68) -> 107.7766 | AT68: 54.601421 | AU68: 36.382062 | AV68: 43.719686 | AW68: 47.561054 | AX68: 51.696063 | AY68: 58.135638 | AZ68: 66.020446 | BA68: 74.401697 | BB68: 79.367475 | BC68: 83.427541 | BD68: 86.28238 | BE68: 88.83165 | BF68: =SUM(OFFSET(AT68,0,$B$2-1):OFFSET(AT68,0,$B$3-1)) -> 681.59546 | BG68: =SUM(AT68:BE68) -> 770.42711
A69: Vay ngắn ngày Provision | B69: =P69/BG69 -> 0.24614861 | C69: =SUM(D69:O69) -> 23.477354 | D69: 0.49081762 | E69: 0.87774278 | F69: 1.0729132 | G69: 1.0042476 | H69: 1.2661038 | I69: 1.9694995 | J69: 3.2554235 | K69: 2.22 | L69: 2.0109246 | M69: 2.5466813 | N69: 2.776 | O69: 3.987 | P69: =SUM(OFFSET(Q69,0,$B$2-1):OFFSET(Q69,0,$B$3-1)) -> 19.584432 | Q69: 10.026817 | R69: =4036/1000 -> 4.036 | S69: 5.521615 | AE69: Vay ngắn ngày Provision | AF69: 0.55802899 | AG69: 1.1283911 | AH69: 0.92819147 | AI69: 1.1767275 | AJ69: 1.4164643 | AK69: 1.6109992 | AL69: 1.5764889 | AM69: 2.8591755 | AN69: 3.1821245 | AO69: 2.5683029 | AP69: 2.9400897 | AQ69: 3.3824955 | AR69: =SUM(OFFSET(AF69,0,$B$2-1):OFFSET(AF69,0,$B$3-1)) -> 19.944984 | AS69: =SUM(AF69:AQ69) -> 23.32748 | AT69: 10.874215 | AU69: 4.8617077 | AV69: 5.3920268 | AW69: 5.6869508 | AX69: 5.9021244 | AY69: 5.9844686 | AZ69: 6.0158143 | BA69: 6.2739412 | BB69: 6.6472031 | BC69: 7.1508748 | BD69: 7.3123046 | BE69: 7.4618146 | BF69: =SUM(OFFSET(AT69,0,$B$2-1):OFFSET(AT69,0,$B$3-1)) -> 72.101631 | BG69: =SUM(AT69:BE69) -> 79.563446
A70: Overdraft Provision | B70: =P70/BG70 -> 0.21543914 | C70: =SUM(D70:O70) -> 19.281871 | D70: 0.89482664 | E70: 0.69609173 | F70: 0.73489177 | G70: 0.78806089 | H70: 0.85405015 | I70: 1.3854449 | J70: 2.1913334 | K70: 2.151 | L70: 1.9406706 | M70: 2.0185007 | N70: 2.229 | O70: 3.398 | P70: =SUM(OFFSET(Q70,0,$B$2-1):OFFSET(Q70,0,$B$3-1)) -> 17.426428 | Q70: 8.2913019 | R70: =4214/1000 -> 4.214 | S70: 4.9211263 | AE70: Overdraft Provision | AF70: 0.36808281 | AG70: 0.43198611 | AH70: 0.39203585 | AI70: 0.60669082 | AJ70: 0.71475647 | AK70: 0.81923759 | AL70: 1.2758981 | AM70: 1.5301904 | AN70: 1.5662177 | AO70: 2.2306204 | AP70: 2.2586275 | AQ70: 2.2771926 | AR70: =SUM(OFFSET(AF70,0,$B$2-1):OFFSET(AF70,0,$B$3-1)) -> 12.194344 | AS70: =SUM(AF70:AQ70) -> 14.471536 | AT70: 9.8811461 | AU70: 3.0763818 | AV70: 4.2292469 | AW70: 5.521755 | AX70: 5.367256 | AY70: 5.5453574 | AZ70: 6.7018989 | BA70: 7.1531918 | BB70: 7.7567032 | BC70: 8.2419745 | BD70: 8.5777589 | BE70: 8.8352685 | BF70: =SUM(OFFSET(AT70,0,$B$2-1):OFFSET(AT70,0,$B$3-1)) -> 72.05267 | BG70: =SUM(AT70:BE70) -> 80.887939
A71: TW Provision | B71: =P71/BG71 -> 0 | C71: =SUM(D71:O71) -> 0 | P71: =SUM(OFFSET(Q71,0,$B$2-1):OFFSET(Q71,0,$B$3-1)) -> 0 | AE71: TW Provision | AF71: 0 | AG71: 0.0433125 | AH71: 0.053796187 | AI71: 0.094686109 | AJ71: 0.32825611 | AK71: 0.4654389 | AL71: 0.60853923 | AM71: 0.74786822 | AN71: 0.99406769 | AO71: 1.2585604 | AP71: 1.6084437 | AQ71: 2.1838307 | AR71: =SUM(OFFSET(AF71,0,$B$2-1):OFFSET(AF71,0,$B$3-1)) -> 6.202969 | AS71: =SUM(AF71:AQ71) -> 8.3867998 | AT71: 0.015 | AU71: 0.033375 | AV71: 0.054118333 | AW71: 0.076501133 | AX71: 0.10746538 | AY71: 0.14487035 | AZ71: 0.18517587 | BA71: 0.23682556 | BB71: 0.32535607 | BC71: 0.44242081 | BD71: 0.57733206 | BE71: 0.72122099 | BF71: =SUM(OFFSET(AT71,0,$B$2-1):OFFSET(AT71,0,$B$3-1)) -> 2.1984406 | BG71: =SUM(AT71:BE71) -> 2.9196615
A72: Paylater Provision | B72: =P72/BG72 -> 0.13626162 | C72: =SUM(D72:O72) -> 1.2995205 | I72: 0.013023997 | J72: 0.084185873 | K72: 0.108 | L72: 0.12931066 | M72: 0.1 | N72: 0.305 | O72: 0.56 | P72: =SUM(OFFSET(Q72,0,$B$2-1):OFFSET(Q72,0,$B$3-1)) -> 3.3892931 | Q72: 0.7421681 | R72: =1084/1000 -> 1.084 | S72: 1.563125 | AE72: Paylater Provision | AF72: 0 | AG72: 0.07425 | AH72: 0.033 | AI72: 0.062528125 | AJ72: 0.20746329 | AK72: 0.31856525 | AL72: 0.39836048 | AM72: 0.45381303 | AN72: 0.60422459 | AO72: 0.74100126 | AP72: 0.91049052 | AQ72: 1.0995039 | AR72: =SUM(OFFSET(AF72,0,$B$2-1):OFFSET(AF72,0,$B$3-1)) -> 3.8036965 | AS72: =SUM(AF72:AQ72) -> 4.9032004 | AT72: 0.53040412 | AU72: 0.90612597 | AV72: 1.2465042 | AW72: 1.4415011 | AX72: 1.6873196 | AY72: 1.9332988 | AZ72: 1.9511893 | BA72: 2.1824113 | BB72: 2.7353015 | BC72: 3.1453963 | BD72: 3.4535198 | BE72: 3.6604531 | BF72: =SUM(OFFSET(AT72,0,$B$2-1):OFFSET(AT72,0,$B$3-1)) -> 21.212972 | BG72: =SUM(AT72:BE72) -> 24.873425
A73: Credit Card Provision | B73: =P73/BG73 -> 0.27906412 | C73: =SUM(D73:O73) -> 102.01822 | D73: 5.5139673 | E73: 8.8570792 | F73: 10.846861 | G73: 6.5146334 | H73: 6.3443005 | I73: 9.9942444 | J73: 8.605114 | K73: 7.6151194 | L73: 8.4055704 | M73: 9.2313308 | N73: 8.624 | O73: 11.466 | P73: =SUM(OFFSET(Q73,0,$B$2-1):OFFSET(Q73,0,$B$3-1)) -> 54.8798 | Q73: 25.26443 | R73: =13065/1000 -> 13.065 | S73: 16.55037 | AE73: Credit Card Provision | AF73: 14.089726 | AG73: 15.083391 | AH73: 9.5956211 | AI73: 6.6950801 | AJ73: 6.3390169 | AK73: 6.2452301 | AL73: 6.4737419 | AM73: 5.7761461 | AN73: 6.0254792 | AO73: 5.9213566 | AP73: 5.6846166 | AQ73: 5.6871956 | AR73: =SUM(OFFSET(AF73,0,$B$2-1):OFFSET(AF73,0,$B$3-1)) -> 87.929405 | AS73: =SUM(AF73:AQ73) -> 93.616601 | AT73: 29.784177 | AU73: 11.352377 | AV73: 12.82922 | AW73: 14.192689 | AX73: 15.194651 | AY73: 15.401797 | AZ73: 16.130751 | BA73: 15.920511 | BB73: 15.805561 | BC73: 16.026842 | BD73: 16.661631 | BE73: 17.35639 | BF73: =SUM(OFFSET(AT73,0,$B$2-1):OFFSET(AT73,0,$B$3-1)) -> 179.30021 | BG73: =SUM(AT73:BE73) -> 196.6566
A74: Profit after Provsion expenses | B74: =P74/BG74 -> 0.78717045 | C74: =SUM(D74:O74) -> 365.98021 | D74: 9.1156931 | E74: 6.084966 | F74: 9.7382784 | G74: 11.375529 | H74: 16.215765 | I74: 27.909776 | J74: 28.114849 | K74: 51.183701 | L74: 34.07889 | M74: 55.677734 | N74: 52.184224 | O74: 64.300803 | P74: =SUM(OFFSET(Q74,0,$B$2-1):OFFSET(Q74,0,$B$3-1)) -> 505.37247 | Q74: =Q66-Q67 -> -6.8477078 | R74: =R66-R67 -> 20.559314 | S74: =S66-S67 -> 31.439798 | T74: =T66-T67 -> 55.713323 | U74: =U66-U67 -> 56.193517 | V74: =V66-V67 -> 61.462272 | W74: =W66-W67 -> 85.033474 | X74: =X66-X67 -> 83.683175 | ... AB74: =AB66-AB67 -> 0 | AE74: Profit after Provsion expenses | AF74: =AF66-AF67 -> 3.6048 | AG74: =AG66-AG67 -> 0.43791796 | AH74: =AH66-AH67 -> 13.559795 | AI74: =AI66-AI67 -> 18.515921 | AJ74: =AJ66-AJ67 -> 24.914436 | AK74: =AK66-AK67 -> 33.23678 | AL74: =AL66-AL67 -> 39.182914 | AM74: =AM66-AM67 -> 46.120843 | ... AQ74: =AQ66-AQ67 -> 107.83917 | AR74: =SUM(OFFSET(AF74,0,$B$2-1):OFFSET(AF74,0,$B$3-1)) -> 341.53586 | AS74: =SUM(AF74:AQ74) -> 449.37504 | AT74: =AT66-AT67 -> -12.913677 | AU74: =AU66-AU67 -> 43.973259 | AV74: =AV66-AV67 -> 41.875497 | AW74: =AW66-AW67 -> 44.136746 | AX74: =AX66-AX67 -> 48.765021 | AY74: =AY66-AY67 -> 51.874209 | AZ74: =AZ66-AZ67 -> 55.024037 | BA74: =BA66-BA67 -> 56.075645 | ... BE74: =BE66-BE67 -> 113.92636 | BF74: =SUM(OFFSET(AT74,0,$B$2-1):OFFSET(AT74,0,$B$3-1)) -> 528.08513 | BG74: =SUM(AT74:BE74) -> 642.01149
A75: Partnership development cost | AT75: 3.3333333 | AU75: 3.3333333 | AV75: 3.3333333 | AW75: 3.3333333 | AX75: 3.3333333 | AY75: 3.3333333 | AZ75: 3.3333333 | BA75: 3.3333333 | BB75: 3.3333333 | BC75: 3.3333333 | BD75: 3.3333333 | BE75: 3.3333333 | BF75: =SUM(OFFSET(AT75,0,$B$2-1):OFFSET(AT75,0,$B$3-1)) -> 36.666667 | BG75: =SUM(AT75:BE75) -> 40
A77: OPEX | B77: =P77/BG77 -> 0.64737924 | C77: =SUM(D77:O77) -> 387.88187 | D77: 25.388071 | E77: 15.977401 | F77: 28.06661 | G77: 27.240486 | H77: 27.466909 | I77: 29.426299 | J77: 30.82283 | K77: 32.524791 | L77: 31.263 | M77: 41.61222 | N77: 33.132316 | O77: 64.960934 | P77: =SUM(OFFSET(Q77,0,$B$2-1):OFFSET(Q77,0,$B$3-1)) -> 356.31563 | Q77: =Q78+Q79+Q80+Q81+Q82+Q90+Q91+Q92+Q93+Q94 -> 41.583168 | R77: =R78+R79+R80+R81+R82+R90+R91+R92+R93+R94 -> 32.850327 | S77: =S78+S79+S80+S81+S82+S90+S91+S92+S93+S94 -> 32.238852 | T77: =T78+T79+T80+T81+T82+T90+T91+T92+T93+T94 -> 34.88 | U77: =U78+U79+U80+U81+U82+U90+U91+U92+U93+U94 -> 34.130738 | V77: =V78+V79+V80+V81+V82+V90+V91+V92+V93+V94 -> 36.728034 | W77: =W78+W79+W80+W81+W82+W90+W91+W92+W93+W94 -> 52.425 | X77: =X78+X79+X80+X81+X82+X90+X91+X92+X93+X94 -> 46.984986 | ... AB77: =AB78+AB79+AB80+AB81+AB82+AB90+AB91+AB92+AB93+AB94 -> 0 | AE77: OPEX | AF77: =AF78+AF79+AF80+AF81+AF82+AF90+AF91+AF92+AF93+AF94 -> 33.148632 | AG77: =AG78+AG79+AG80+AG81+AG82+AG90+AG91+AG92+AG93+AG94 -> 33.499897 | AH77: =AH78+AH79+AH80+AH81+AH82+AH90+AH91+AH92+AH93+AH94 -> 33.817192 | AI77: =AI78+AI79+AI80+AI81+AI82+AI90+AI91+AI92+AI93+AI94 -> 33.421668 | AJ77: =AJ78+AJ79+AJ80+AJ81+AJ82+AJ90+AJ91+AJ92+AJ93+AJ94 -> 33.661495 | AK77: =AK78+AK79+AK80+AK81+AK82+AK90+AK91+AK92+AK93+AK94 -> 33.969525 | AL77: =AL78+AL79+AL80+AL81+AL82+AL90+AL91+AL92+AL93+AL94 -> 34.160332 | AM77: =AM78+AM79+AM80+AM81+AM82+AM90+AM91+AM92+AM93+AM94 -> 34.381132 | ... AQ77: =AQ78+AQ79+AQ80+AQ81+AQ82+AQ90+AQ91+AQ92+AQ93+AQ94 -> 83.415058 | AR77: =SUM(OFFSET(AF77,0,$B$2-1):OFFSET(AF77,0,$B$3-1)) -> 375.5106 | AS77: =SUM(AF77:AQ77) -> 458.92566 | AT77: =AT78+AT79+AT80+AT81+AT82+AT90+AT91+AT92+AT93+AT94+AT98 -> 46.075839 | AU77: =AU78+AU79+AU80+AU81+AU82+AU90+AU91+AU92+AU93+AU94+AU98 -> 46.15565 | AV77: =AV78+AV79+AV80+AV81+AV82+AV90+AV91+AV92+AV93+AV94+AV98 -> 46.235365 | AW77: =AW78+AW79+AW80+AW81+AW82+AW90+AW91+AW92+AW93+AW94+AW98 -> 46.018775 | AX77: =AX78+AX79+AX80+AX81+AX82+AX90+AX91+AX92+AX93+AX94+AX98 -> 46.093707 | AY77: =AY78+AY79+AY80+AY81+AY82+AY90+AY91+AY92+AY93+AY94+AY98 -> 46.169211 | AZ77: =AZ78+AZ79+AZ80+AZ81+AZ82+AZ90+AZ91+AZ92+AZ93+AZ94+AZ98 -> 45.441797 | BA77: =BA78+BA79+BA80+BA81+BA82+BA90+BA91+BA92+BA93+BA94+BA98 -> 45.507995 | ... BE77: =BE78+BE79+BE80+BE81+BE82+BE90+BE91+BE92+BE93+BE94+BE98 -> 45.771486 | BF77: =SUM(OFFSET(AT77,0,$B$2-1):OFFSET(AT77,0,$B$3-1)) -> 504.62557 | BG77: =SUM(AT77:BE77) -> 550.39705
A78: Staff cost | B78: =P78/BG78 -> 0.64293588 | C78: =SUM(D78:O78) -> 201.38125 | D78: 12.521225 | E78: 7.0590288 | F78: 13.93925 | G78: 13.966114 | H78: 13.990877 | I78: 13.903596 | J78: 14.414315 | K78: 16.17296 | L78: 16 | M78: 20.623515 | N78: 17.145069 | O78: 41.645303 | P78: =SUM(OFFSET(Q78,0,$B$2-1):OFFSET(Q78,0,$B$3-1)) -> 191.97159 | Q78: 17.070031 | R78: =16063.2389963333/1000 -> 16.063239 | S78: 17.486041 | T78: 17.916 | U78: 18.456738 | V78: 18.507495 | W78: 33.438622 | X78: 27.592331 | Y78: 25.441091 | Z78: =Z79/1000 -> 0 | AE78: Staff cost | AF78: 15.946285 | AG78: 15.946285 | AH78: 15.946285 | AI78: 15.946285 | AJ78: 15.946285 | AK78: 15.946285 | AL78: 15.946285 | AM78: 15.946285 | AN78: 15.946285 | AO78: 15.946285 | AP78: 15.946285 | AQ78: 63.785142 | AR78: =SUM(OFFSET(AF78,0,$B$2-1):OFFSET(AF78,0,$B$3-1)) -> 175.40914 | AS78: =SUM(AF78:AQ78) -> 239.19428 | AT78: 24.882158 | AU78: 24.882158 | AV78: 24.882158 | AW78: 24.882158 | AX78: 24.882158 | AY78: 24.882158 | AZ78: 24.882158 | BA78: 24.882158 | BB78: 24.882158 | BC78: 24.882158 | BD78: 24.882158 | BE78: 24.882158 | BF78: =SUM(OFFSET(AT78,0,$B$2-1):OFFSET(AT78,0,$B$3-1)) -> 273.70374 | BG78: =SUM(AT78:BE78) -> 298.5859
A79: Marketing & Communication | B79: =P79/BG79 -> 0.42290547 | C79: =SUM(D79:O79) -> 13.192524 | D79: 1.3469666 | E79: 0.44142992 | F79: 0.84881937 | G79: 0.79359494 | H79: 0.78313415 | I79: 1.2253138 | J79: 0.95716811 | K79: 0.55468099 | L79: 0.934 | M79: 1.4397237 | N79: 0.51424728 | O79: 3.3534455 | P79: =SUM(OFFSET(Q79,0,$B$2-1):OFFSET(Q79,0,$B$3-1)) -> 10.424891 | Q79: 0.91361416 | R79: =470.222598/1000 -> 0.4702226 | S79: 0.23572911 | T79: 1.31 | U79: 0.541 | V79: 2.2329271 | W79: 0.74917818 | X79: 2.4936661 | Y79: 1.4785533 | AE79: Marketing & Communication | AF79: 1.4166667 | AG79: 1.4166667 | AH79: 1.4166667 | AI79: 1.4166667 | AJ79: 1.4166667 | AK79: 1.4166667 | AL79: 1.4166667 | AM79: 1.4166667 | AN79: 1.4166667 | AO79: 1.4166667 | AP79: 1.4166667 | AQ79: 1.4166667 | AR79: =SUM(OFFSET(AF79,0,$B$2-1):OFFSET(AF79,0,$B$3-1)) -> 15.583333 | AS79: =SUM(AF79:AQ79) -> 17 | AT79: 2.05422 | AU79: 2.05422 | AV79: 2.05422 | AW79: 2.05422 | AX79: 2.05422 | AY79: 2.05422 | AZ79: 2.05422 | BA79: 2.05422 | BB79: 2.05422 | BC79: 2.05422 | BD79: 2.05422 | BE79: 2.05422 | BF79: =SUM(OFFSET(AT79,0,$B$2-1):OFFSET(AT79,0,$B$3-1)) -> 22.59642 | BG79: =SUM(AT79:BE79) -> 24.65064
A80: PR - EAD | B80: =P80/BG80 -> #DIV/0! | C80: =SUM(D80:O80) -> 0 | P80: =SUM(OFFSET(Q80,0,$B$2-1):OFFSET(Q80,0,$B$3-1)) -> 0 | AE80: PR - EAD | AF80: 0.25 | AG80: 0.25 | AH80: 0.25 | AI80: 0.25 | AJ80: 0.25 | AK80: 0.25 | AL80: 0.25 | AM80: 0.25 | AN80: 0.25 | AO80: 0.25 | AP80: 0.25 | AQ80: 0.25 | AR80: =SUM(OFFSET(AF80,0,$B$2-1):OFFSET(AF80,0,$B$3-1)) -> 2.75 | AS80: =SUM(AF80:AQ80) -> 3 | BF80: =SUM(OFFSET(AT80,0,$B$2-1):OFFSET(AT80,0,$B$3-1)) -> 0 | BG80: =SUM(AT80:BE80) -> 0
A81: CI | B81: =P81/BG81 -> #DIV/0! | C81: =SUM(D81:O81) -> 0 | P81: =SUM(OFFSET(Q81,0,$B$2-1):OFFSET(Q81,0,$B$3-1)) -> 0 | AE81: CI | AF81: 0.16666667 | AG81: 0.16666667 | AH81: 0.16666667 | AI81: 0.16666667 | AJ81: 0.16666667 | AK81: 0.16666667 | AL81: 0.16666667 | AM81: 0.16666667 | AN81: 0.16666667 | AO81: 0.16666667 | AP81: 0.16666667 | AQ81: 0.16666667 | AR81: =SUM(OFFSET(AF81,0,$B$2-1):OFFSET(AF81,0,$B$3-1)) -> 1.8333333 | AS81: =SUM(AF81:AQ81) -> 2 | BF81: =SUM(OFFSET(AT81,0,$B$2-1):OFFSET(AT81,0,$B$3-1)) -> 0 | BG81: =SUM(AT81:BE81) -> 0
A82: Operation | B82: =P82/BG82 -> 0.65258842 | C82: =SUM(D82:O82) -> 44.661246 | D82: 3.8814329 | E82: 2.9369037 | F82: 4.6467188 | G82: 3.1339198 | H82: 3.6602792 | I82: 4.17619 | J82: 4.0508785 | K82: 3.2668206 | L82: 3.32 | M82: 3.5430565 | N82: 4.843 | O82: 3.2020464 | P82: =SUM(OFFSET(Q82,0,$B$2-1):OFFSET(Q82,0,$B$3-1)) -> 39.356722 | Q82: =SUM(Q83:Q89) -> 4.9751155 | R82: =SUM(R83:R89) -> 5.106727 | S82: =SUM(S83:S89) -> 4.23 | T82: =SUM(T83:T89) -> 3.826 | U82: =SUM(U83:U89) -> 2.518 | V82: =SUM(V83:V89) -> 3.8376466 | W82: =SUM(W83:W89) -> 6.1624197 | X82: =SUM(X83:X89) -> 4.0803234 | ... AB82: =SUM(AB83:AB89) -> 0 | AE82: Operation | AF82: =SUM(AF83:AF89) -> 3.5364 | AG82: =SUM(AG83:AG89) -> 3.5364 | AH82: =SUM(AH83:AH89) -> 3.5364 | AI82: =SUM(AI83:AI89) -> 2.9004 | AJ82: =SUM(AJ83:AJ89) -> 2.9004 | AK82: =SUM(AK83:AK89) -> 2.9654 | AL82: =SUM(AL83:AL89) -> 2.9134 | AM82: =SUM(AM83:AM89) -> 2.9134 | ... AQ82: =SUM(AQ83:AQ89) -> 2.9784 | AR82: =SUM(OFFSET(AF82,0,$B$2-1):OFFSET(AF82,0,$B$3-1)) -> 34.1374 | AS82: =SUM(AF82:AQ82) -> 37.1158 | AT82: =SUM(AT83:AT89) -> 5.6160743 | AU82: =SUM(AU83:AU89) -> 5.6220327 | AV82: =SUM(AV83:AV89) -> 5.627991 | AW82: =SUM(AW83:AW89) -> 5.3364493 | AX82: =SUM(AX83:AX89) -> 5.3424077 | AY82: =SUM(AY83:AY89) -> 5.348366 | AZ82: =SUM(AZ83:AZ89) -> 4.5543243 | BA82: =SUM(BA83:BA89) -> 4.5602827 | ... BE82: =SUM(BE83:BE89) -> 4.584116 | BF82: =SUM(OFFSET(AT82,0,$B$2-1):OFFSET(AT82,0,$B$3-1)) -> 55.724526 | BG82: =SUM(AT82:BE82) -> 60.308642
A83: KYC | B83: =P83/BG83 -> 1.6563216 | C83: =SUM(D83:O83) -> 13.392113 | D83: 1.7106728 | E83: 1.0251658 | F83: 1.4224581 | G83: 0.92102917 | H83: 1.0990655 | I83: 1.366803 | J83: 1.2805256 | K83: 0.59513087 | L83: 0.33 | M83: 0.65066295 | N83: 2.107 | O83: 0.88359898 | P83: =SUM(OFFSET(Q83,0,$B$2-1):OFFSET(Q83,0,$B$3-1)) -> 4.857163 | Q83: 0.83697604 | R83: =727.693860666667/1000 -> 0.72769386 | S83: 0.722 | T83: 0.763 | U83: 0.195 | V83: 0.40742554 | W83: 0.3763823 | X83: 0.40578638 | Y83: 0.42289889 | AE83: KYC | AF83: 1.418 | AG83: 1.418 | AH83: 1.418 | AI83: 0.782 | AJ83: 0.782 | AK83: 0.782 | AL83: 0.4 | AM83: 0.4 | AN83: 0.4 | AO83: 0.4 | AP83: 0.4 | AQ83: 0.4 | AR83: =SUM(OFFSET(AF83,0,$B$2-1):OFFSET(AF83,0,$B$3-1)) -> 8.6 | AS83: =SUM(AF83:AQ83) -> 9 | AT83: 0.4675 | AU83: 0.4675 | AV83: 0.4675 | AW83: 0.17 | AX83: 0.17 | AY83: 0.17 | AZ83: 0.17 | BA83: 0.17 | BB83: 0.17 | BC83: 0.17 | BD83: 0.17 | BE83: 0.17 | BF83: =SUM(OFFSET(AT83,0,$B$2-1):OFFSET(AT83,0,$B$3-1)) -> 2.7625 | BG83: =SUM(AT83:BE83) -> 2.9325
A84: NFC | Q84: 0.357 | R84: =223.299/1000 -> 0.223299 | S84: 0.332 | T84: 0.276 | U84: 0.276 | V84: 0.299385 | W84: 0.339 | X84: 0.325 | Y84: 0.321117 | AT84: 1.14 | AU84: 1.14 | AV84: 1.14 | AW84: 1.14 | AX84: 1.14 | AY84: 1.14 | AZ84: 0.34 | BA84: 0.34 | BB84: 0.34 | BC84: 0.34 | BD84: 0.34 | BE84: 0.34 | BF84: =SUM(OFFSET(AT84,0,$B$2-1):OFFSET(AT84,0,$B$3-1)) -> 8.54 | BG84: =SUM(AT84:BE84) -> 8.88
A85: CS | B85: =P85/BG85 -> 0.71840113 | C85: =SUM(D85:O85) -> 4.3849531 | D85: 0.28088942 | E85: 0.35 | F85: 0.45 | G85: 0.27253149 | H85: 0.41121363 | I85: 0.33556231 | J85: 0.46527196 | K85: 0.22354324 | L85: 0.5 | M85: 0.50193859 | N85: 0.273 | O85: 0.3210025 | P85: =SUM(OFFSET(Q85,0,$B$2-1):OFFSET(Q85,0,$B$3-1)) -> 5.5843019 | Q85: 0.40042078 | R85: =1448.734136/1000 -> 1.4487341 | S85: 0.59 | T85: 0.546 | U85: 0.468 | V85: 0.60137151 | W85: 0.43575384 | X85: 0.55360084 | Y85: 0.54042078 | AE85: CS | AF85: 0.6 | AG85: 0.6 | AH85: 0.6 | AI85: 0.6 | AJ85: 0.6 | AK85: 0.6 | AL85: 0.8 | AM85: 0.8 | AN85: 0.8 | AO85: 0.8 | AP85: 0.8 | AQ85: 0.8 | AR85: =SUM(OFFSET(AF85,0,$B$2-1):OFFSET(AF85,0,$B$3-1)) -> 7.6 | AS85: =SUM(AF85:AQ85) -> 8.4 | AT85: 0.64776971 | AU85: 0.64776971 | AV85: 0.64776971 | AW85: 0.64776971 | AX85: 0.64776971 | AY85: 0.64776971 | AZ85: 0.64776971 | BA85: 0.64776971 | BB85: 0.64776971 | BC85: 0.64776971 | BD85: 0.64776971 | BE85: 0.64776971 | BF85: =SUM(OFFSET(AT85,0,$B$2-1):OFFSET(AT85,0,$B$3-1)) -> 7.1254668 | BG85: =SUM(AT85:BE85) -> 7.7732365
A86: CX | B86: =P86/BG86 -> #DIV/0! | C86: =SUM(D86:O86) -> 0 | P86: =SUM(OFFSET(Q86,0,$B$2-1):OFFSET(Q86,0,$B$3-1)) -> 0 | AE86: CX | AF86: 0.0684 | AG86: 0.0684 | AH86: 0.0684 | AI86: 0.0684 | AJ86: 0.0684 | AK86: 0.0684 | AL86: 0.0684 | AM86: 0.0684 | AN86: 0.0684 | AO86: 0.0684 | AP86: 0.0684 | AQ86: 0.0684 | AR86: =SUM(OFFSET(AF86,0,$B$2-1):OFFSET(AF86,0,$B$3-1)) -> 0.7524 | AS86: =SUM(AF86:AQ86) -> 0.8208 | BF86: =SUM(OFFSET(AT86,0,$B$2-1):OFFSET(AT86,0,$B$3-1)) -> 0 | BG86: =SUM(AT86:BE86) -> 0
A87: Debit card issuance fee | B87: =P87/BG87 -> 0.075414781 | C87: =SUM(D87:O87) -> 4.4460115 | D87: 0.1601125 | E87: 0.133 | F87: 0.78552561 | G87: 0.3694061 | H87: 0.3 | I87: 0.266 | J87: 0.3697763 | K87: 0.28878597 | L87: 0.8 | M87: 0.47340501 | N87: 0.7 | O87: -0.2 | P87: =SUM(OFFSET(Q87,0,$B$2-1):OFFSET(Q87,0,$B$3-1)) -> 0.1 | S87: 0.1 | AE87: Debit card issuance fee | AF87: 0.4 | AG87: 0.4 | AH87: 0.4 | AI87: 0.4 | AJ87: 0.4 | AK87: 0.4 | AL87: 0.4 | AM87: 0.4 | AN87: 0.4 | AO87: 0.4 | AP87: 0.4 | AQ87: 0.4 | AR87: =SUM(OFFSET(AF87,0,$B$2-1):OFFSET(AF87,0,$B$3-1)) -> 4.4 | AS87: =SUM(AF87:AQ87) -> 4.8 | AT87: 0.1105 | AU87: 0.1105 | AV87: 0.1105 | AW87: 0.1105 | AX87: 0.1105 | AY87: 0.1105 | AZ87: 0.1105 | BA87: 0.1105 | BB87: 0.1105 | BC87: 0.1105 | BD87: 0.1105 | BE87: 0.1105 | BF87: =SUM(OFFSET(AT87,0,$B$2-1):OFFSET(AT87,0,$B$3-1)) -> 1.2155 | BG87: =SUM(AT87:BE87) -> 1.326
A88: Credit card (issuance) | B88: =P88/BG88 -> 0.6719976 | C88: =SUM(D88:O88) -> 3.1968544 | D88: 0.349931 | E88: 0.34 | F88: 0.3 | G88: 0.270953 | H88: 0.3 | I88: 0.77897036 | J88: 0.4 | K88: 0.457 | P88: =SUM(OFFSET(Q88,0,$B$2-1):OFFSET(Q88,0,$B$3-1)) -> 3.0379331 | Q88: 0.32271865 | R88: 0.207 | S88: 0.186 | T88: 0.311 | U88: 0.268 | V88: 0.38408414 | W88: 0.47701469 | X88: 0.43629716 | Y88: 0.44581849 | AE88: Credit card (issuance) | AF88: 0.65 | AG88: 0.65 | AH88: 0.65 | AI88: 0.65 | AJ88: 0.65 | AK88: 0.715 | AL88: 0.845 | AM88: 0.845 | AN88: 0.91 | AO88: 0.91 | AP88: 0.91 | AQ88: 0.91 | AR88: =SUM(OFFSET(AF88,0,$B$2-1):OFFSET(AF88,0,$B$3-1)) -> 8.385 | AS88: =SUM(AF88:AQ88) -> 9.295 | AT88: 0.34395833 | AU88: 0.34991667 | AV88: 0.355875 | AW88: 0.36183333 | AX88: 0.36779167 | AY88: 0.37375 | AZ88: 0.37970833 | BA88: 0.38566667 | BB88: 0.391625 | BC88: 0.39758333 | BD88: 0.40354167 | BE88: 0.4095 | BF88: =SUM(OFFSET(AT88,0,$B$2-1):OFFSET(AT88,0,$B$3-1)) -> 4.11125 | BG88: =SUM(AT88:BE88) -> 4.52075
A89: Others (office, anciliaries,) | B89: =P89/BG89 -> 0.66029418 | C89: =SUM(D89:O89) -> 19.241315 | D89: 1.3798271 | E89: 1.0887379 | F89: 1.6887351 | G89: 1.3 | H89: 1.55 | I89: 1.4288544 | J89: 1.5353046 | K89: 1.7023606 | L89: 1.69 | M89: 1.91705 | N89: 1.763 | O89: 2.1974449 | P89: =SUM(OFFSET(Q89,0,$B$2-1):OFFSET(Q89,0,$B$3-1)) -> 23.028523 | Q89: =4.3-Q90 -> 3.058 | R89: 2.5 | S89: 2.3 | T89: 1.93 | U89: 1.311 | V89: 2.1453805 | W89: 4.5342689 | X89: 2.359639 | Y89: 2.8902343 | AE89: Others (office, anciliaries,) | AF89: 0.4 | AG89: 0.4 | AH89: 0.4 | AI89: 0.4 | AJ89: 0.4 | AK89: 0.4 | AL89: 0.4 | AM89: 0.4 | AN89: 0.4 | AO89: 0.4 | AP89: 0.4 | AQ89: 0.4 | AR89: =SUM(OFFSET(AF89,0,$B$2-1):OFFSET(AF89,0,$B$3-1)) -> 4.4 | AS89: =SUM(AF89:AQ89) -> 4.8 | AT89: 2.9063463 | AU89: 2.9063463 | AV89: 2.9063463 | AW89: 2.9063463 | AX89: 2.9063463 | AY89: 2.9063463 | AZ89: 2.9063463 | BA89: 2.9063463 | BB89: 2.9063463 | BC89: 2.9063463 | BD89: 2.9063463 | BE89: 2.9063463 | BF89: =SUM(OFFSET(AT89,0,$B$2-1):OFFSET(AT89,0,$B$3-1)) -> 31.969809 | BG89: =SUM(AT89:BE89) -> 34.876156
A90: Allocated Expenses from VPBank | B90: =P90/BG90 -> 0.6273 | C90: =SUM(D90:O90) -> 17.021439 | D90: 0.70921685 | E90: 1.3112649 | F90: 1.3112649 | G90: 1.3331731 | H90: 1.4796994 | I90: 1.4068925 | J90: 1.414 | K90: 1.5 | L90: 1.433 | M90: 1.6089274 | N90: 1.514 | O90: 2 | P90: =SUM(OFFSET(Q90,0,$B$2-1):OFFSET(Q90,0,$B$3-1)) -> 12.546 | Q90: 1.242 | R90: 1.25 | S90: 1.454 | T90: 1.348 | U90: 1.418 | V90: 1.384 | W90: 1.525 | X90: 1.418 | Y90: 1.507 | AE90: Allocated Expenses from VPBank | AF90: 2.3333333 | AG90: 2.3333333 | AH90: 2.3333333 | AI90: 2.3333333 | AJ90: 2.3333333 | AK90: 2.3333333 | AL90: 2.3333333 | AM90: 2.3333333 | AN90: 2.3333333 | AO90: 2.3333333 | AP90: 2.3333333 | AQ90: 2.3333333 | AR90: =SUM(OFFSET(AF90,0,$B$2-1):OFFSET(AF90,0,$B$3-1)) -> 25.666667 | AS90: =SUM(AF90:AQ90) -> 28 | AT90: 1.6666667 | AU90: 1.6666667 | AV90: 1.6666667 | AW90: 1.6666667 | AX90: 1.6666667 | AY90: 1.6666667 | AZ90: 1.6666667 | BA90: 1.6666667 | BB90: 1.6666667 | BC90: 1.6666667 | BD90: 1.6666667 | BE90: 1.6666667 | BF90: =SUM(OFFSET(AT90,0,$B$2-1):OFFSET(AT90,0,$B$3-1)) -> 18.333333 | BG90: =SUM(AT90:BE90) -> 20
A91: Allocated Expenses from BEG (admin, office, system…) | B91: =P91/BG91 -> #DIV/0! | C91: =SUM(D91:O91) -> 0 | P91: =SUM(OFFSET(Q91,0,$B$2-1):OFFSET(Q91,0,$B$3-1)) -> 0 | AE91: Allocated Expenses from BEG (admin, office, system…) | AF91: 0.9895405 | AG91: 0.9895405 | AH91: 0.9895405 | AI91: 0.9895405 | AJ91: 0.9895405 | AK91: 0.9895405 | AL91: 0.9895405 | AM91: 0.9895405 | AN91: 0.9895405 | AO91: 0.9895405 | AP91: 0.9895405 | AQ91: 0.9895405 | AR91: =SUM(OFFSET(AF91,0,$B$2-1):OFFSET(AF91,0,$B$3-1)) -> 10.884945 | AS91: =SUM(AF91:AQ91) -> 11.874486 | BF91: =SUM(OFFSET(AT91,0,$B$2-1):OFFSET(AT91,0,$B$3-1)) -> 0 | BG91: =SUM(AT91:BE91) -> 0
A92: D&A | C92: =SUM(D92:O92) -> 3.3696834 | D92: 0.29886343 | E92: 0.27778915 | F92: 0.24756416 | G92: 0.52470336 | H92: 0.015470772 | I92: 0.31548057 | J92: 0.28964776 | K92: 0.2534352 | L92: 0.276 | M92: 0.296729 | N92: 0.287 | O92: 0.287 | P92: =SUM(OFFSET(Q92,0,$B$2-1):OFFSET(Q92,0,$B$3-1)) -> 2.7018702 | Q92: 0.28557699 | R92: 0.273 | S92: 0.274 | T92: 0.295 | U92: 0.276 | V92: 0.27998769 | W92: 0.35452244 | X92: 0.32124348 | Y92: 0.34253957 | AE92: D&A | AF92: 0 | AG92: 0 | AH92: 0 | AI92: 0 | AJ92: 0 | AK92: 0 | AL92: 0 | AM92: 0 | AN92: 0 | AO92: 0 | AP92: 0 | AQ92: 0 | AR92: =SUM(OFFSET(AF92,0,$B$2-1):OFFSET(AF92,0,$B$3-1)) -> 0 | AS92: =SUM(AF92:AQ92) -> 0 | AT92: 0 | AU92: 0 | AV92: 0 | AW92: 0 | AX92: 0 | AY92: 0 | AZ92: 0 | BA92: 0 | BB92: 0 | BC92: 0 | BD92: 0 | BE92: 0 | BF92: =SUM(OFFSET(AT92,0,$B$2-1):OFFSET(AT92,0,$B$3-1)) -> 0 | BG92: =SUM(AT92:BE92) -> 0
A93: Financial Expenses | B93: =P93/BG93 -> 0.66789987 | C93: =SUM(D93:O93) -> 28.762108 | D93: 0.56413763 | E93: 0.62203274 | F93: 0.74039199 | G93: 0.93380695 | H93: 1.2694484 | I93: 1.4041534 | J93: 2.7568237 | K93: 3.1325098 | L93: 2.1 | M93: 7.3668036 | N93: 3.032 | O93: 4.84 | P93: =SUM(OFFSET(Q93,0,$B$2-1):OFFSET(Q93,0,$B$3-1)) -> 25.380817 | Q93: =9945.830299/1000 -> 9.9458303 | R93: =1654.138388/1000 -> 1.6541384 | S93: =1828.259645/1000 -> 1.8282596 | T93: 1.791 | U93: 2.34 | V93: 1.9422923 | W93: 2.0364461 | X93: 2.0029439 | Y93: 1.8399063 | AE93: Financial Expenses | AF93: 1.1792276 | AG93: 1.4715115 | AH93: 1.7274673 | AI93: 1.9041503 | AJ93: 2.077632 | AK93: 2.2516636 | AL93: 2.4227113 | AM93: 2.5688818 | AN93: 3.0015618 | AO93: 3.1115857 | AP93: 3.2276017 | AQ93: 3.3693654 | AR93: =SUM(OFFSET(AF93,0,$B$2-1):OFFSET(AF93,0,$B$3-1)) -> 24.943995 | AS93: =SUM(AF93:AQ93) -> 28.31336 | AT93: 3.1667443 | AU93: 3.1667443 | AV93: 3.1667443 | AW93: 3.1667443 | AX93: 3.1667443 | AY93: 3.1667443 | AZ93: 3.1667443 | BA93: 3.1667443 | BB93: 3.1667443 | BC93: 3.1667443 | BD93: 3.1667443 | BE93: 3.1667443 | BF93: =SUM(OFFSET(AT93,0,$B$2-1):OFFSET(AT93,0,$B$3-1)) -> 34.834187 | BG93: =SUM(AT93:BE93) -> 38.000931
A94: Infrastructure & Software | B94: =P94/BG94 -> 0.67922001 | C94: =SUM(D94:O94) -> 79.493613 | D94: 6.0662288 | E94: 3.3289517 | F94: 6.3326013 | G94: 6.5551737 | H94: 6.268 | I94: 6.9946729 | J94: 6.9399962 | K94: 7.6443843 | L94: 7.2 | M94: 6.733465 | N94: 5.797 | O94: 9.6331394 | P94: =SUM(OFFSET(Q94,0,$B$2-1):OFFSET(Q94,0,$B$3-1)) -> 73.933737 | Q94: =6.368+Q95 -> 7.151 | R94: 8.033 | S94: =S95+S96 -> 6.7308219 | T94: =7.344+0.75+0.3 -> 8.394 | U94: =8.181+0.4 -> 8.581 | V94: 8.5436847 | W94: 8.1588109 | X94: 9.0764779 | Y94: 9.2649415 | AE94: Infrastructure & Software | AF94: 7.330512 | AG94: 7.3894925 | AH94: 7.4508322 | AI94: 7.5146255 | AJ94: 7.5809705 | AK94: 7.6499693 | AL94: 7.7217281 | AM94: 7.7963572 | AN94: 7.8739715 | AO94: 7.9546903 | AP94: 8.038638 | AQ94: 8.1259435 | AR94: =SUM(OFFSET(AF94,0,$B$2-1):OFFSET(AF94,0,$B$3-1)) -> 84.301787 | AS94: =SUM(AF94:AQ94) -> 92.42773 | AT94: =AT95+AT96+AT97 -> 8.6899754 | AU94: =AU95+AU96+AU97 -> 8.7638277 | AV94: =AV95+AV96+AV97 -> 8.8375847 | AW94: =AW95+AW96+AW97 -> 8.9125363 | AX94: =AX95+AX96+AX97 -> 8.9815099 | AY94: =AY95+AY96+AY97 -> 9.0510556 | AZ94: =AZ95+AZ96+AZ97 -> 9.1176835 | BA94: =BA95+BA96+BA97 -> 9.1779234 | ... BE94: =BE95+BE96+BE97 -> 9.4175807 | BF94: =SUM(OFFSET(AT94,0,$B$2-1):OFFSET(AT94,0,$B$3-1)) -> 99.43336 | BG94: =SUM(AT94:BE94) -> 108.85094
A95: SMS | B95: =P95/BG95 -> 0.57783092 | C95: =SUM(D95:O95) -> 8.4798232 | D95: 0.55009316 | E95: 0.572 | F95: 0.69573 | G95: 0.5 | H95: 0.7 | I95: 0.703 | J95: 0.946 | K95: 0.9 | L95: 0.753 | M95: 0.768 | N95: 0.692 | O95: 0.7 | P95: =SUM(OFFSET(Q95,0,$B$2-1):OFFSET(Q95,0,$B$3-1)) -> 8.264 | Q95: 0.783 | R95: 1.253 | S95: 0.81 | T95: 0.751 | U95: 0.951 | V95: 0.867 | W95: 0.86 | X95: 0.909 | Y95: 1.08 | AE95: SMS | AF95: 1.2 | AG95: 1.2 | AH95: 1.2 | AI95: 1.2 | AJ95: 1.2 | AK95: 1.2 | AL95: 1.2 | AM95: 1.2 | AN95: 1.2 | AO95: 1.2 | AP95: 1.2 | AQ95: 1.2 | AR95: =SUM(OFFSET(AF95,0,$B$2-1):OFFSET(AF95,0,$B$3-1)) -> 13.2 | AS95: =SUM(AF95:AQ95) -> 14.4 | AT95: 0.81087705 | AU95: 0.88472943 | AV95: 0.95848641 | AW95: 1.0334379 | AX95: 1.1024116 | AY95: 1.1719573 | AZ95: 1.2385851 | BA95: 1.2988251 | BB95: 1.3605001 | BC95: 1.4212348 | BD95: 1.4822342 | BE95: 1.5384824 | BF95: =SUM(OFFSET(AT95,0,$B$2-1):OFFSET(AT95,0,$B$3-1)) -> 12.763279 | BG95: =SUM(AT95:BE95) -> 14.301761
A96: IT expenses tại Cake | B96: =P96/BG96 -> 0.092996893 | C96: =SUM(D96:O96) -> 47.141418 | D96: 3.7507013 | E96: 1.2329414 | F96: 4.0483266 | G96: 4.3420197 | H96: 3.854846 | I96: 4.3565985 | J96: 4.2329962 | K96: 4.8233843 | L96: 4.505 | M96: 4.254465 | N96: 3.123 | O96: 4.6171394 | P96: =SUM(OFFSET(Q96,0,$B$2-1):OFFSET(Q96,0,$B$3-1)) -> 5.9208219 | S96: 5.9208219 | AE96: IT expenses tại Cake | AF96: 4.656 | AG96: 4.656 | AH96: 4.656 | AI96: 4.656 | AJ96: 4.656 | AK96: 4.656 | AL96: 4.656 | AM96: 4.656 | AN96: 4.656 | AO96: 4.656 | AP96: 4.656 | AQ96: 4.656 | AR96: =SUM(OFFSET(AF96,0,$B$2-1):OFFSET(AF96,0,$B$3-1)) -> 51.216 | AS96: =SUM(AF96:AQ96) -> 55.872 | AT96: 5.3055732 | AU96: 5.3055732 | AV96: 5.3055732 | AW96: 5.3055732 | AX96: 5.3055732 | AY96: 5.3055732 | AZ96: 5.3055732 | BA96: 5.3055732 | BB96: 5.3055732 | BC96: 5.3055732 | BD96: 5.3055732 | BE96: 5.3055732 | BF96: =SUM(OFFSET(AT96,0,$B$2-1):OFFSET(AT96,0,$B$3-1)) -> 58.361306 | BG96: =SUM(AT96:BE96) -> 63.666879
A97: IT expenses allocated from BE | B97: =P97/BG97 -> 0.04148007 | C97: =SUM(D97:O97) -> 23.872372 | D97: 1.7654344 | E97: 1.5240103 | F97: 1.5885447 | G97: 1.713154 | H97: 1.713154 | I97: 1.9350743 | J97: 1.761 | K97: 1.921 | L97: 1.942 | M97: 1.711 | N97: 1.982 | O97: 4.316 | P97: =SUM(OFFSET(Q97,0,$B$2-1):OFFSET(Q97,0,$B$3-1)) -> 1.281 | T97: 0.3 | U97: 0.4 | X97: 0.581 | AE97: IT expenses allocated from BE | AF97: 1.474512 | AG97: 1.5334925 | AH97: 1.5948322 | AI97: 1.6586255 | AJ97: 1.7249705 | AK97: 1.7939693 | AL97: 1.8657281 | AM97: 1.9403572 | AN97: 2.0179715 | AO97: 2.0986903 | AP97: 2.182638 | AQ97: 2.2699435 | AR97: =SUM(OFFSET(AF97,0,$B$2-1):OFFSET(AF97,0,$B$3-1)) -> 19.885787 | AS97: =SUM(AF97:AQ97) -> 22.15573 | AT97: 2.5735251 | AU97: 2.5735251 | AV97: 2.5735251 | AW97: 2.5735251 | AX97: 2.5735251 | AY97: 2.5735251 | AZ97: 2.5735251 | BA97: 2.5735251 | BB97: 2.5735251 | BC97: 2.5735251 | BD97: 2.5735251 | BE97: 2.5735251 | BF97: =SUM(OFFSET(AT97,0,$B$2-1):OFFSET(AT97,0,$B$3-1)) -> 28.308776 | BG97: =SUM(AT97:BE97) -> 30.882301
A98: Tax/Bank charges | B98: =P98/BG98 -> #DIV/0! | C98: =SUM(D98:O98) -> 0.033326235 | D98: 0.033326235 | P98: =SUM(OFFSET(Q98,0,$B$2-1):OFFSET(Q98,0,$B$3-1)) -> 0.018892455 | Q98: 0.018892455 | AE98: Tax/Bank charges | AF98: 0.049883218 | AG98: 0.049883218 | AH98: 0.049883218 | AI98: 0.049883218 | AJ98: 0.049883218 | AK98: 0.049883218 | AL98: 0.049883218 | AM98: 0.049883218 | AN98: 0.049883218 | AO98: 0.049883218 | AP98: 0.049883218 | AQ98: 0.049883218 | AR98: =SUM(OFFSET(AF98,0,$B$2-1):OFFSET(AF98,0,$B$3-1)) -> 0.54871539 | AS98: =SUM(AF98:AQ98) -> 0.59859861 | BF98: =SUM(OFFSET(AT98,0,$B$2-1):OFFSET(AT98,0,$B$3-1)) -> 0 | BG98: =SUM(AT98:BE98) -> 0
A99: Operating Income | B99: =P99/BG99 -> 2.8878908 | C99: =SUM(D99:O99) -> -21.792003 | D99: -16.272378 | E99: -9.892435 | F99: -18.328332 | G99: -15.864957 | H99: -11.251144 | I99: -1.4068661 | J99: -2.7079807 | K99: 18.65891 | L99: 2.8158896 | M99: 14.065514 | N99: 19.051907 | O99: -0.66013124 | P99: =SUM(OFFSET(Q99,0,$B$2-1):OFFSET(Q99,0,$B$3-1)) -> 149.05685 | Q99: =Q74-Q77 -> -48.430876 | R99: =R74-R77 -> -12.291013 | S99: =S74-S77 -> -0.79905371 | T99: =T74-T77 -> 20.833323 | U99: =U74-U77 -> 22.062779 | V99: =V74-V77 -> 24.734238 | W99: =W74-W77 -> 32.608474 | X99: =X74-X77 -> 36.69819 | ... AB99: =AB74-AB77 -> 0 | AE99: Operating Income | AF99: =AF74-AF77 -> -29.543832 | AG99: =AG74-AG77 -> -33.061979 | AH99: =AH74-AH77 -> -20.257397 | AI99: =AI74-AI77 -> -14.905747 | AJ99: =AJ74-AJ77 -> -8.7470593 | AK99: =AK74-AK77 -> -0.73274521 | AL99: =AL74-AL77 -> 5.0225822 | AM99: =AM74-AM77 -> 11.739712 | ... AQ99: =AQ74-AQ77 -> 24.424115 | AR99: =SUM(OFFSET(AF99,0,$B$2-1):OFFSET(AF99,0,$B$3-1)) -> -33.974736 | AS99: =SUM(AF99:AQ99) -> -9.5506203 | AT99: =AT74-AT77-AT75 -> -62.32285 | AU99: =AU74-AU77-AU75 -> -5.5157235 | AV99: =AV74-AV77-AV75 -> -7.6932017 | AW99: =AW74-AW77-AW75 -> -5.2153617 | AX99: =AX74-AX77-AX75 -> -0.6620187 | AY99: =AY74-AY77-AY75 -> 2.3716651 | AZ99: =AZ74-AZ77-AZ75 -> 6.2489066 | BA99: =BA74-BA77-BA75 -> 7.234316 | ... BE99: =BE74-BE77-BE75 -> 64.821536 | BF99: =SUM(OFFSET(AT99,0,$B$2-1):OFFSET(AT99,0,$B$3-1)) -> -13.207101 | BG99: =SUM(AT99:BE99) -> 51.614435
A100: EBITDA | B100: =P100/BG100 -> 1.9766648 | C100: =SUM(D100:O100) -> 10.339788 | D100: -15.409377 | E100: -8.9926131 | F100: -17.340376 | G100: -14.406447 | H100: -9.9662248 | I100: 0.31276784 | J100: 0.33849081 | K100: 22.044855 | L100: 5.1918896 | M100: 21.729047 | N100: 22.370907 | O100: 4.4668688 | P100: =SUM(OFFSET(Q100,0,$B$2-1):OFFSET(Q100,0,$B$3-1)) -> 177.13954 | Q100: =Q99+Q93+Q92 -> -38.199468 | R100: =R99+R93+R92 -> -10.363875 | S100: =S99+S93+S92 -> 1.3032059 | T100: =T99+T93+T92 -> 22.919323 | U100: =U99+U93+U92 -> 24.678779 | V100: =V99+V93+V92 -> 26.956519 | W100: =W99+W93+W92 -> 34.999443 | X100: =X99+X93+X92 -> 39.022377 | ... AB100: =AB99+AB93+AB92 -> 0 | AE100: EBITDA | AF100: =AF99+AF93 -> -28.364605 | AG100: =AG99+AG93 -> -31.590467 | AH100: =AH99+AH93 -> -18.52993 | AI100: =AI99+AI93 -> -13.001597 | AJ100: =AJ99+AJ93 -> -6.6694274 | AK100: =AK99+AK93 -> 1.5189184 | AL100: =AL99+AL93 -> 7.4452935 | AM100: =AM99+AM93 -> 14.308593 | ... AQ100: =AQ99+AQ93 -> 27.793481 | AR100: =SUM(OFFSET(AF100,0,$B$2-1):OFFSET(AF100,0,$B$3-1)) -> -9.030741 | AS100: =SUM(AF100:AQ100) -> 18.76274 | AT100: =AT99+AT93+AT92 -> -59.156105 | AU100: =AU99+AU93+AU92 -> -2.3489793 | AV100: =AV99+AV93+AV92 -> -4.5264575 | AW100: =AW99+AW93+AW92 -> -2.0486175 | AX100: =AX99+AX93+AX92 -> 2.5047256 | AY100: =AY99+AY93+AY92 -> 5.5384094 | AZ100: =AZ99+AZ93+AZ92 -> 9.4156509 | BA100: =BA99+BA93+BA92 -> 10.40106 | ... BE100: =BE99+BE93+BE92 -> 67.98828 | BF100: =SUM(OFFSET(AT100,0,$B$2-1):OFFSET(AT100,0,$B$3-1)) -> 21.627085 | BG100: =SUM(AT100:BE100) -> 89.615366
W106: =W77-W93 -> 50.388553

Sheet Tracking KPI
A1: BeFinancial - CAKE
A3: Chọn tháng hiện tại => | C3: 45901
A4: So sánh với tháng => | C4: 45870
A6: Đơn vị: Tỷ VNĐ | AF6: 45292
A7: CHỈ TIÊU | B7: =C4 -> 45870 | C7: =C3 -> 45901 | D7: MTD Plan | E7: +/-LM | F7: Growth MoM | G7: +/-BG | H7: YTD 2025 | I7: YTD 2025 Plan | J7: FY 2025 Plan | K7: +/-BG | L7: %FY KPI | AF7: 45323
A8: REVENUE | B8: =INDEX(EBITDA!$A$5:$AB$100,MATCH('Tracking KPI'!A8,EBITDA!$A$5:$A$100,0),MATCH('Tracking KPI'!$C$4,EBITDA!$A$5:$AB$5,0)) -> 323.17577 | C8: =INDEX(EBITDA!$A$5:$AB$100,MATCH('Tracking KPI'!A8,EBITDA!$A$5:$A$100,0),MATCH('Tracking KPI'!$C$3,EBITDA!$A$5:$AB$5,0)) -> 378.21176 | D8: =INDEX(EBITDA!$AE$5:$BG$100,MATCH(A8,EBITDA!$AE$5:$AE$100,0),MATCH('Tracking KPI'!$C$3,EBITDA!$AE$5:$BG$5,0)) -> 333.9849 | E8: =C8-INDEX(EBITDA!$A$5:$AB$100,MATCH('Tracking KPI'!A8,EBITDA!$A$5:$A$100,0),MATCH('Tracking KPI'!$C$4,EBITDA!$A$5:$AB$5,0)) -> 55.035984 | F8: =IFERROR(C8/(C8-E8),"") -> 1.1702974 | G8: =C8-D8 -> 44.22686 | H8: =EBITDA!P14 -> 2214.4411 | I8: =EBITDA!BF14 -> 3040.3106 | J8: =EBITDA!BG14 -> 3458.8801 | K8: =H8-I8 -> -825.86943 | L8: =IFERROR(H8/J8,"") -> 0.64021911 | AF8: 45352
A9: EXPENSE | B9: =INDEX(EBITDA!$A$5:$AB$100,MATCH('Tracking KPI'!A9,EBITDA!$A$5:$A$100,0),MATCH('Tracking KPI'!$C$4,EBITDA!$A$5:$AB$5,0)) -> 89.812774 | C9: =INDEX(EBITDA!$A$5:$AB$100,MATCH('Tracking KPI'!A9,EBITDA!$A$5:$A$100,0),MATCH('Tracking KPI'!$C$3,EBITDA!$A$5:$AB$5,0)) -> 92.826868 | D9: =INDEX(EBITDA!$AE$5:$BG$100,MATCH(A9,EBITDA!$AE$5:$AE$100,0),MATCH('Tracking KPI'!$C$3,EBITDA!$AE$5:$BG$5,0)) -> 109.11745 | E9: =C9-INDEX(EBITDA!$A$5:$AB$100,MATCH('Tracking KPI'!A9,EBITDA!$A$5:$A$100,0),MATCH('Tracking KPI'!$C$4,EBITDA!$A$5:$AB$5,0)) -> 3.0140942 | F9: =IFERROR(C9/(C9-E9),"") -> 1.0335598 | G9: =C9-D9 -> -16.290586 | H9: =EBITDA!P15 -> 665.79169 | I9: =EBITDA!BF15 -> 1001.4526 | J9: =EBITDA!BG15 -> 1127.0906 | K9: =H9-I9 -> -335.66089 | L9: =IFERROR(H9/J9,"") -> 0.59071707 | AF9: 45383
A10: Total TOI | B10: =INDEX(EBITDA!$A$5:$AB$100,MATCH('Tracking KPI'!A10,EBITDA!$A$5:$A$100,0),MATCH('Tracking KPI'!$C$4,EBITDA!$A$5:$AB$5,0)) -> 233.363 | C10: =INDEX(EBITDA!$A$5:$AB$100,MATCH('Tracking KPI'!A10,EBITDA!$A$5:$A$100,0),MATCH('Tracking KPI'!$C$3,EBITDA!$A$5:$AB$5,0)) -> 285.38489 | D10: =INDEX(EBITDA!$AE$5:$BG$100,MATCH(A10,EBITDA!$AE$5:$AE$100,0),MATCH('Tracking KPI'!$C$3,EBITDA!$AE$5:$BG$5,0)) -> 224.86744 | E10: =C10-INDEX(EBITDA!$A$5:$AB$100,MATCH('Tracking KPI'!A10,EBITDA!$A$5:$A$100,0),MATCH('Tracking KPI'!$C$4,EBITDA!$A$5:$AB$5,0)) -> 52.02189 | F10: =IFERROR(C10/(C10-E10),"") -> 1.2229226 | G10: =C10-D10 -> 60.517446 | H10: =EBITDA!P16 -> 1548.6494 | I10: =EBITDA!BF16 -> 2038.858 | J10: =EBITDA!BG16 -> 2331.7894 | K10: =H10-I10 -> -490.20854 | L10: =IFERROR(H10/J10,"") -> 0.66414635 | AF10: 45413
A11: TOI of Liabilities | B11: =INDEX(EBITDA!$A$5:$AB$100,MATCH('Tracking KPI'!A11,EBITDA!$A$5:$A$100,0),MATCH('Tracking KPI'!$C$4,EBITDA!$A$5:$AB$5,0)) -> 13.051334 | C11: =INDEX(EBITDA!$A$5:$AB$100,MATCH('Tracking KPI'!A11,EBITDA!$A$5:$A$100,0),MATCH('Tracking KPI'!$C$3,EBITDA!$A$5:$AB$5,0)) -> 13.565148 | D11: =INDEX(EBITDA!$AE$5:$BG$100,MATCH(A11,EBITDA!$AE$5:$AE$100,0),MATCH('Tracking KPI'!$C$3,EBITDA!$AE$5:$BG$5,0)) -> 17.455794 | E11: =C11-INDEX(EBITDA!$A$5:$AB$100,MATCH('Tracking KPI'!A11,EBITDA!$A$5:$A$100,0),MATCH('Tracking KPI'!$C$4,EBITDA!$A$5:$AB$5,0)) -> 0.51381445 | F11: =IFERROR(C11/(C11-E11),"") -> 1.0393687 | G11: =C11-D11 -> -3.8906455 | H11: =EBITDA!P17 -> 101.23719 | I11: =EBITDA!BF17 -> 161.50355 | J11: =EBITDA!BG17 -> 219.74233 | K11: =H11-I11 -> -60.266366 | L11: =IFERROR(H11/J11,"") -> 0.46070863 | AF11: 45444
A12: TOI of Deposit | B12: =INDEX(EBITDA!$A$5:$AB$100,MATCH('Tracking KPI'!A12,EBITDA!$A$5:$A$100,0),MATCH('Tracking KPI'!$C$4,EBITDA!$A$5:$AB$5,0)) -> 12.643311 | C12: =INDEX(EBITDA!$A$5:$AB$100,MATCH('Tracking KPI'!A12,EBITDA!$A$5:$A$100,0),MATCH('Tracking KPI'!$C$3,EBITDA!$A$5:$AB$5,0)) -> 13.231732 | D12: =INDEX(EBITDA!$AE$5:$BG$100,MATCH(A12,EBITDA!$AE$5:$AE$100,0),MATCH('Tracking KPI'!$C$3,EBITDA!$AE$5:$BG$5,0)) -> 15.286017 | E12: =C12-INDEX(EBITDA!$A$5:$AB$100,MATCH('Tracking KPI'!A12,EBITDA!$A$5:$A$100,0),MATCH('Tracking KPI'!$C$4,EBITDA!$A$5:$AB$5,0)) -> 0.58842146 | F12: =IFERROR(C12/(C12-E12),"") -> 1.0465401 | G12: =C12-D12 -> -2.0542847 | H12: =EBITDA!P18 -> 93.820369 | I12: =EBITDA!BF18 -> 136.44658 | J12: =EBITDA!BG18 -> 154.20783 | K12: =H12-I12 -> -42.626214 | L12: =IFERROR(H12/J12,"") -> 0.6084021 | AF12: 45474
A13: TOI of Fee income | B13: =INDEX(EBITDA!$A$5:$AB$100,MATCH('Tracking KPI'!A13,EBITDA!$A$5:$A$100,0),MATCH('Tracking KPI'!$C$4,EBITDA!$A$5:$AB$5,0)) -> -0.46231739 | C13: =INDEX(EBITDA!$A$5:$AB$100,MATCH('Tracking KPI'!A13,EBITDA!$A$5:$A$100,0),MATCH('Tracking KPI'!$C$3,EBITDA!$A$5:$AB$5,0)) -> -0.55058396 | D13: =INDEX(EBITDA!$AE$5:$BG$100,MATCH(A13,EBITDA!$AE$5:$AE$100,0),MATCH('Tracking KPI'!$C$3,EBITDA!$AE$5:$BG$5,0)) -> 1.0377768 | E13: =C13-INDEX(EBITDA!$A$5:$AB$100,MATCH('Tracking KPI'!A13,EBITDA!$A$5:$A$100,0),MATCH('Tracking KPI'!$C$4,EBITDA!$A$5:$AB$5,0)) -> -0.088266574 | F13: =IFERROR(C13/(C13-E13),"") -> 1.190922 | G13: =C13-D13 -> -1.5883608 | H13: =EBITDA!P19 -> -3.3175444 | I13: =EBITDA!BF19 -> 11.904971 | J13: =EBITDA!BG19 -> 12.980498 | K13: =H13-I13 -> -15.222515 | L13: =IFERROR(H13/J13,"") -> -0.25557913 | AF13: 45505
A14: Other TOI | B14: =INDEX(EBITDA!$A$5:$AB$100,MATCH('Tracking KPI'!A14,EBITDA!$A$5:$A$100,0),MATCH('Tracking KPI'!$C$4,EBITDA!$A$5:$AB$5,0)) -> 0.87034044 | C14: =INDEX(EBITDA!$A$5:$AB$100,MATCH('Tracking KPI'!A14,EBITDA!$A$5:$A$100,0),MATCH('Tracking KPI'!$C$3,EBITDA!$A$5:$AB$5,0)) -> 0.884 | D14: =INDEX(EBITDA!$AE$5:$BG$100,MATCH(A14,EBITDA!$AE$5:$AE$100,0),MATCH('Tracking KPI'!$C$3,EBITDA!$AE$5:$BG$5,0)) -> 1.132 | E14: =C14-INDEX(EBITDA!$A$5:$AB$100,MATCH('Tracking KPI'!A14,EBITDA!$A$5:$A$100,0),MATCH('Tracking KPI'!$C$4,EBITDA!$A$5:$AB$5,0)) -> 0.013659559 | F14: =IFERROR(C14/(C14-E14),"") -> 1.0156945 | G14: =C14-D14 -> -0.248 | H14: =EBITDA!P20 -> 10.734364 | I14: =EBITDA!BF20 -> 13.152 | J14: =EBITDA!BG20 -> 52.554 | K14: =H14-I14 -> -2.4176363 | L14: =IFERROR(H14/J14,"") -> 0.20425398 | AF14: 45536
A15: TOI of Card | B15: =INDEX(EBITDA!$A$5:$AB$100,MATCH('Tracking KPI'!A15,EBITDA!$A$5:$A$100,0),MATCH('Tracking KPI'!$C$4,EBITDA!$A$5:$AB$5,0)) -> 30.85078 | C15: =INDEX(EBITDA!$A$5:$AB$100,MATCH('Tracking KPI'!A15,EBITDA!$A$5:$A$100,0),MATCH('Tracking KPI'!$C$3,EBITDA!$A$5:$AB$5,0)) -> 40.52488 | D15: =INDEX(EBITDA!$AE$5:$BG$100,MATCH(A15,EBITDA!$AE$5:$AE$100,0),MATCH('Tracking KPI'!$C$3,EBITDA!$AE$5:$BG$5,0)) -> 32.148462 | E15: =C15-INDEX(EBITDA!$A$5:$AB$100,MATCH('Tracking KPI'!A15,EBITDA!$A$5:$A$100,0),MATCH('Tracking KPI'!$C$4,EBITDA!$A$5:$AB$5,0)) -> 9.6740995 | F15: =IFERROR(C15/(C15-E15),"") -> 1.3135771 | G15: =C15-D15 -> 8.3764172 | H15: =EBITDA!P21 -> 203.3852 | I15: =EBITDA!BF21 -> 251.00313 | J15: =EBITDA!BG21 -> 279.38298 | K15: =H15-I15 -> -47.617933 | L15: =IFERROR(H15/J15,"") -> 0.72797991 | AF15: 45566
A16: TOI of Debit card | B16: =INDEX(EBITDA!$A$5:$AB$100,MATCH('Tracking KPI'!A16,EBITDA!$A$5:$A$100,0),MATCH('Tracking KPI'!$C$4,EBITDA!$A$5:$AB$5,0)) -> 0.1991644 | C16: =INDEX(EBITDA!$A$5:$AB$100,MATCH('Tracking KPI'!A16,EBITDA!$A$5:$A$100,0),MATCH('Tracking KPI'!$C$3,EBITDA!$A$5:$AB$5,0)) -> 4.9663518 | D16: =INDEX(EBITDA!$AE$5:$BG$100,MATCH(A16,EBITDA!$AE$5:$AE$100,0),MATCH('Tracking KPI'!$C$3,EBITDA!$AE$5:$BG$5,0)) -> 5.5972304 | E16: =C16-INDEX(EBITDA!$A$5:$AB$100,MATCH('Tracking KPI'!A16,EBITDA!$A$5:$A$100,0),MATCH('Tracking KPI'!$C$4,EBITDA!$A$5:$AB$5,0)) -> 4.7671874 | F16: =IFERROR(C16/(C16-E16),"") -> 24.935941 | G16: =C16-D16 -> -0.63087855 | H16: =EBITDA!P22 -> 4.1939893 | I16: =EBITDA!BF22 -> 7.660714 | J16: =EBITDA!BG22 -> 8.0405643 | K16: =H16-I16 -> -3.4667247 | L16: =IFERROR(H16/J16,"") -> 0.52160384 | AF16: 45597
A17: TOI of Credit card | B17: =INDEX(EBITDA!$A$5:$AB$100,MATCH('Tracking KPI'!A17,EBITDA!$A$5:$A$100,0),MATCH('Tracking KPI'!$C$4,EBITDA!$A$5:$AB$5,0)) -> 30.651616 | C17: =INDEX(EBITDA!$A$5:$AB$100,MATCH('Tracking KPI'!A17,EBITDA!$A$5:$A$100,0),MATCH('Tracking KPI'!$C$3,EBITDA!$A$5:$AB$5,0)) -> 35.558528 | D17: =INDEX(EBITDA!$AE$5:$BG$100,MATCH(A17,EBITDA!$AE$5:$AE$100,0),MATCH('Tracking KPI'!$C$3,EBITDA!$AE$5:$BG$5,0)) -> 26.551232 | E17: =C17-INDEX(EBITDA!$A$5:$AB$100,MATCH('Tracking KPI'!A17,EBITDA!$A$5:$A$100,0),MATCH('Tracking KPI'!$C$4,EBITDA!$A$5:$AB$5,0)) -> 4.9069121 | F17: =IFERROR(C17/(C17-E17),"") -> 1.1600866 | G17: =C17-D17 -> 9.0072957 | H17: =EBITDA!P23 -> 199.19121 | I17: =EBITDA!BF23 -> 243.34242 | J17: =EBITDA!BG23 -> 271.34242 | K17: =H17-I17 -> -44.151208 | L17: =IFERROR(H17/J17,"") -> 0.73409536 | AF17: 45627
A18: TOI of Lending products | B18: =INDEX(EBITDA!$A$5:$AB$100,MATCH('Tracking KPI'!A18,EBITDA!$A$5:$A$100,0),MATCH('Tracking KPI'!$C$4,EBITDA!$A$5:$AB$5,0)) -> 189.46095 | C18: =INDEX(EBITDA!$A$5:$AB$100,MATCH('Tracking KPI'!A18,EBITDA!$A$5:$A$100,0),MATCH('Tracking KPI'!$C$3,EBITDA!$A$5:$AB$5,0)) -> 231.29427 | D18: =INDEX(EBITDA!$AE$5:$BG$100,MATCH(A18,EBITDA!$AE$5:$AE$100,0),MATCH('Tracking KPI'!$C$3,EBITDA!$AE$5:$BG$5,0)) -> 175.26319 | E18: =C18-INDEX(EBITDA!$A$5:$AB$100,MATCH('Tracking KPI'!A18,EBITDA!$A$5:$A$100,0),MATCH('Tracking KPI'!$C$4,EBITDA!$A$5:$AB$5,0)) -> 41.833325 | F18: =IFERROR(C18/(C18-E18),"") -> 1.2208018 | G18: =C18-D18 -> 56.031087 | H18: =EBITDA!P24 -> 1244.0769 | I18: =EBITDA!BF24 -> 1626.3513 | J18: =EBITDA!BG24 -> 1832.6641 | K18: =H18-I18 -> -382.27444 | L18: =IFERROR(H18/J18,"") -> 0.67883517 | AF18: 45658
A19: TOI Vay kỳ hạn | B19: =INDEX(EBITDA!$A$5:$AB$100,MATCH('Tracking KPI'!A19,EBITDA!$A$5:$A$100,0),MATCH('Tracking KPI'!$C$4,EBITDA!$A$5:$AB$5,0)) -> 155.61405 | C19: =INDEX(EBITDA!$A$5:$AB$100,MATCH('Tracking KPI'!A19,EBITDA!$A$5:$A$100,0),MATCH('Tracking KPI'!$C$3,EBITDA!$A$5:$AB$5,0)) -> 186.1055 | D19: =INDEX(EBITDA!$AE$5:$BG$100,MATCH(A19,EBITDA!$AE$5:$AE$100,0),MATCH('Tracking KPI'!$C$3,EBITDA!$AE$5:$BG$5,0)) -> 136.2201 | E19: =C19-INDEX(EBITDA!$A$5:$AB$100,MATCH('Tracking KPI'!A19,EBITDA!$A$5:$A$100,0),MATCH('Tracking KPI'!$C$4,EBITDA!$A$5:$AB$5,0)) -> 30.491452 | F19: =IFERROR(C19/(C19-E19),"") -> 1.1959428 | G19: =C19-D19 -> 49.885397 | H19: =EBITDA!P25 -> 996.00471 | I19: =EBITDA!BF25 -> 1259.4219 | J19: =EBITDA!BG25 -> 1419.3948 | K19: =H19-I19 -> -263.41719 | L19: =IFERROR(H19/J19,"") -> 0.70171083 | AF19: 45689
... A29: U_TW | B29: =INDEX(EBITDA!$A$5:$AB$100,MATCH('Tracking KPI'!A29,EBITDA!$A$5:$A$100,0),MATCH('Tracking KPI'!$C$4,EBITDA!$A$5:$AB$5,0)) -> 0 | C29: =INDEX(EBITDA!$A$5:$AB$100,MATCH('Tracking KPI'!A29,EBITDA!$A$5:$A$100,0),MATCH('Tracking KPI'!$C$3,EBITDA!$A$5:$AB$5,0)) -> 0 | D29: =INDEX(EBITDA!$AE$5:$BG$100,MATCH(A29,EBITDA!$AE$5:$AE$100,0),MATCH('Tracking KPI'!$C$3,EBITDA!$AE$5:$BG$5,0)) -> 0.075 | E29: =C29-INDEX(EBITDA!$A$5:$AB$100,MATCH('Tracking KPI'!A29,EBITDA!$A$5:$A$100,0),MATCH('Tracking KPI'!$C$4,EBITDA!$A$5:$AB$5,0)) -> 0 | F29: =IFERROR(C29/(C29-E29),"") | G29: =C29-D29 -> -0.075 | H29: =EBITDA!P35 -> 0 | I29: =EBITDA!BF35 -> 0.55 | J29: =EBITDA!BG35 -> 0.65 | K29: =H29-I29 -> -0.55 | L29: =IFERROR(H29/J29,"") -> 0 | AF29: 45992
A30: U_Paylater | B30: =INDEX(EBITDA!$A$5:$AB$100,MATCH('Tracking KPI'!A30,EBITDA!$A$5:$A$100,0),MATCH('Tracking KPI'!$C$4,EBITDA!$A$5:$AB$5,0)) -> 0 | C30: =INDEX(EBITDA!$A$5:$AB$100,MATCH('Tracking KPI'!A30,EBITDA!$A$5:$A$100,0),MATCH('Tracking KPI'!$C$3,EBITDA!$A$5:$AB$5,0)) -> 0 | D30: =INDEX(EBITDA!$AE$5:$BG$100,MATCH(A30,EBITDA!$AE$5:$AE$100,0),MATCH('Tracking KPI'!$C$3,EBITDA!$AE$5:$BG$5,0)) -> 0.885375 | E30: =C30-INDEX(EBITDA!$A$5:$AB$100,MATCH('Tracking KPI'!A30,EBITDA!$A$5:$A$100,0),MATCH('Tracking KPI'!$C$4,EBITDA!$A$5:$AB$5,0)) -> 0 | F30: =IFERROR(C30/(C30-E30),"") | G30: =C30-D30 -> -0.885375 | H30: =EBITDA!P36 -> 1.0442434 | I30: =EBITDA!BF36 -> 9.10525 | J30: =EBITDA!BG36 -> 10.04825 | K30: =H30-I30 -> -8.0610066 | L30: =IFERROR(H30/J30,"") -> 0.10392291
A31: U_Credit card | B31: =INDEX(EBITDA!$A$5:$AB$100,MATCH('Tracking KPI'!A31,EBITDA!$A$5:$A$100,0),MATCH('Tracking KPI'!$C$4,EBITDA!$A$5:$AB$5,0)) -> 0 | C31: =INDEX(EBITDA!$A$5:$AB$100,MATCH('Tracking KPI'!A31,EBITDA!$A$5:$A$100,0),MATCH('Tracking KPI'!$C$3,EBITDA!$A$5:$AB$5,0)) -> 0 | D31: =INDEX(EBITDA!$AE$5:$BG$100,MATCH(A31,EBITDA!$AE$5:$AE$100,0),MATCH('Tracking KPI'!$C$3,EBITDA!$AE$5:$BG$5,0)) -> 0.51000867 | E31: =C31-INDEX(EBITDA!$A$5:$AB$100,MATCH('Tracking KPI'!A31,EBITDA!$A$5:$A$100,0),MATCH('Tracking KPI'!$C$4,EBITDA!$A$5:$AB$5,0)) -> 0 | F31: =IFERROR(C31/(C31-E31),"") | G31: =C31-D31 -> -0.51000867 | H31: =EBITDA!P37 -> 1.4468833 | I31: =EBITDA!BF37 -> 5.3900877 | J31: =EBITDA!BG37 -> 5.920097 | K31: =H31-I31 -> -3.9432043 | L31: =IFERROR(H31/J31,"") -> 0.24440196
A32: Collection cost | B32: =INDEX(EBITDA!$A$5:$AB$100,MATCH('Tracking KPI'!A32,EBITDA!$A$5:$A$100,0),MATCH('Tracking KPI'!$C$4,EBITDA!$A$5:$AB$5,0)) -> 2.091 | C32: =INDEX(EBITDA!$A$5:$AB$100,MATCH('Tracking KPI'!A32,EBITDA!$A$5:$A$100,0),MATCH('Tracking KPI'!$C$3,EBITDA!$A$5:$AB$5,0)) -> 2.404 | D32: =INDEX(EBITDA!$AE$5:$BG$100,MATCH(A32,EBITDA!$AE$5:$AE$100,0),MATCH('Tracking KPI'!$C$3,EBITDA!$AE$5:$BG$5,0)) -> 5.2243305 | E32: =C32-INDEX(EBITDA!$A$5:$AB$100,MATCH('Tracking KPI'!A32,EBITDA!$A$5:$A$100,0),MATCH('Tracking KPI'!$C$4,EBITDA!$A$5:$AB$5,0)) -> 0.313 | F32: =IFERROR(C32/(C32-E32),"") -> 1.1496891 | G32: =C32-D32 -> -2.8203305 | H32: =EBITDA!P38 -> 24.115376 | I32: =EBITDA!BF38 -> 49.327391 | J32: =EBITDA!BG38 -> 54.953583 | K32: =H32-I32 -> -25.212015 | L32: =IFERROR(H32/J32,"") -> 0.43883174
A33: C_Vay kỳ hạn | B33: =INDEX(EBITDA!$A$5:$AB$100,MATCH('Tracking KPI'!A33,EBITDA!$A$5:$A$100,0),MATCH('Tracking KPI'!$C$4,EBITDA!$A$5:$AB$5,0)) -> 0 | C33: =INDEX(EBITDA!$A$5:$AB$100,MATCH('Tracking KPI'!A33,EBITDA!$A$5:$A$100,0),MATCH('Tracking KPI'!$C$3,EBITDA!$A$5:$AB$5,0)) -> 0 | D33: =INDEX(EBITDA!$AE$5:$BG$100,MATCH(A33,EBITDA!$AE$5:$AE$100,0),MATCH('Tracking KPI'!$C$3,EBITDA!$AE$5:$BG$5,0)) -> 3.5489161 | E33: =C33-INDEX(EBITDA!$A$5:$AB$100,MATCH('Tracking KPI'!A33,EBITDA!$A$5:$A$100,0),MATCH('Tracking KPI'!$C$4,EBITDA!$A$5:$AB$5,0)) -> 0 | F33: =IFERROR(C33/(C33-E33),"") | G33: =C33-D33 -> -3.5489161 | H33: =EBITDA!P39 -> 4.782732 | I33: =EBITDA!BF39 -> 33.111749 | J33: =EBITDA!BG39 -> 36.815315 | K33: =H33-I33 -> -28.329017 | L33: =IFERROR(H33/J33,"") -> 0.12991148
A34: C_Vay ngắn ngày | B34: =INDEX(EBITDA!$A$5:$AB$100,MATCH('Tracking KPI'!A34,EBITDA!$A$5:$A$100,0),MATCH('Tracking KPI'!$C$4,EBITDA!$A$5:$AB$5,0)) -> 0 | C34: =INDEX(EBITDA!$A$5:$AB$100,MATCH('Tracking KPI'!A34,EBITDA!$A$5:$A$100,0),MATCH('Tracking KPI'!$C$3,EBITDA!$A$5:$AB$5,0)) -> 0 | D34: =INDEX(EBITDA!$AE$5:$BG$100,MATCH(A34,EBITDA!$AE$5:$AE$100,0),MATCH('Tracking KPI'!$C$3,EBITDA!$AE$5:$BG$5,0)) -> 0.27520278 | E34: =C34-INDEX(EBITDA!$A$5:$AB$100,MATCH('Tracking KPI'!A34,EBITDA!$A$5:$A$100,0),MATCH('Tracking KPI'!$C$4,EBITDA!$A$5:$AB$5,0)) -> 0 | F34: =IFERROR(C34/(C34-E34),"") | G34: =C34-D34 -> -0.27520278 | H34: =EBITDA!P40 -> 1.0401333 | I34: =EBITDA!BF40 -> 2.8178944 | J34: =EBITDA!BG40 -> 3.1121278 | K34: =H34-I34 -> -1.7777612 | L34: =IFERROR(H34/J34,"") -> 0.33421934
A35: C_Overdraft | B35: =INDEX(EBITDA!$A$5:$AB$100,MATCH('Tracking KPI'!A35,EBITDA!$A$5:$A$100,0),MATCH('Tracking KPI'!$C$4,EBITDA!$A$5:$AB$5,0)) -> 0 | C35: =INDEX(EBITDA!$A$5:$AB$100,MATCH('Tracking KPI'!A35,EBITDA!$A$5:$A$100,0),MATCH('Tracking KPI'!$C$3,EBITDA!$A$5:$AB$5,0)) -> 0 | D35: =INDEX(EBITDA!$AE$5:$BG$100,MATCH(A35,EBITDA!$AE$5:$AE$100,0),MATCH('Tracking KPI'!$C$3,EBITDA!$AE$5:$BG$5,0)) -> 0.34679536 | E35: =C35-INDEX(EBITDA!$A$5:$AB$100,MATCH('Tracking KPI'!A35,EBITDA!$A$5:$A$100,0),MATCH('Tracking KPI'!$C$4,EBITDA!$A$5:$AB$5,0)) -> 0 | F35: =IFERROR(C35/(C35-E35),"") | G35: =C35-D35 -> -0.34679536 | H35: =EBITDA!P41 -> 0.72686716 | I35: =EBITDA!BF41 -> 3.4505583 | J35: =EBITDA!BG41 -> 3.847554 | K35: =H35-I35 -> -2.7236911 | L35: =IFERROR(H35/J35,"") -> 0.18891669
A36: C_TW | B36: =INDEX(EBITDA!$A$5:$AB$100,MATCH('Tracking KPI'!A36,EBITDA!$A$5:$A$100,0),MATCH('Tracking KPI'!$C$4,EBITDA!$A$5:$AB$5,0)) -> 0 | C36: =INDEX(EBITDA!$A$5:$AB$100,MATCH('Tracking KPI'!A36,EBITDA!$A$5:$A$100,0),MATCH('Tracking KPI'!$C$3,EBITDA!$A$5:$AB$5,0)) -> 0 | D36: =INDEX(EBITDA!$AE$5:$BG$100,MATCH(A36,EBITDA!$AE$5:$AE$100,0),MATCH('Tracking KPI'!$C$3,EBITDA!$AE$5:$BG$5,0)) -> 0.045 | E36: =C36-INDEX(EBITDA!$A$5:$AB$100,MATCH('Tracking KPI'!A36,EBITDA!$A$5:$A$100,0),MATCH('Tracking KPI'!$C$4,EBITDA!$A$5:$AB$5,0)) -> 0 | F36: =IFERROR(C36/(C36-E36),"") | G36: =C36-D36 -> -0.045 | H36: =EBITDA!P42 -> 0 | I36: =EBITDA!BF42 -> 0.275 | J36: =EBITDA!BG42 -> 0.3575 | K36: =H36-I36 -> -0.275 | L36: =IFERROR(H36/J36,"") -> 0
A37: C_Paylater | B37: =INDEX(EBITDA!$A$5:$AB$100,MATCH('Tracking KPI'!A37,EBITDA!$A$5:$A$100,0),MATCH('Tracking KPI'!$C$4,EBITDA!$A$5:$AB$5,0)) -> 0 | C37: =INDEX(EBITDA!$A$5:$AB$100,MATCH('Tracking KPI'!A37,EBITDA!$A$5:$A$100,0),MATCH('Tracking KPI'!$C$3,EBITDA!$A$5:$AB$5,0)) -> 0 | D37: =INDEX(EBITDA!$AE$5:$BG$100,MATCH(A37,EBITDA!$AE$5:$AE$100,0),MATCH('Tracking KPI'!$C$3,EBITDA!$AE$5:$BG$5,0)) -> 0.2828877 | E37: =C37-INDEX(EBITDA!$A$5:$AB$100,MATCH('Tracking KPI'!A37,EBITDA!$A$5:$A$100,0),MATCH('Tracking KPI'!$C$4,EBITDA!$A$5:$AB$5,0)) -> 0 | F37: =IFERROR(C37/(C37-E37),"") | G37: =C37-D37 -> -0.2828877 | H37: =EBITDA!P43 -> 0.572 | I37: =EBITDA!BF43 -> 2.3816471 | J37: =EBITDA!BG43 -> 2.7373348 | K37: =H37-I37 -> -1.8096471 | L37: =IFERROR(H37/J37,"") -> 0.20896238
A38: C_Credit card | B38: =INDEX(EBITDA!$A$5:$AB$100,MATCH('Tracking KPI'!A38,EBITDA!$A$5:$A$100,0),MATCH('Tracking KPI'!$C$4,EBITDA!$A$5:$AB$5,0)) -> 0 | C38: =INDEX(EBITDA!$A$5:$AB$100,MATCH('Tracking KPI'!A38,EBITDA!$A$5:$A$100,0),MATCH('Tracking KPI'!$C$3,EBITDA!$A$5:$AB$5,0)) -> 0 | D38: =INDEX(EBITDA!$AE$5:$BG$100,MATCH(A38,EBITDA!$AE$5:$AE$100,0),MATCH('Tracking KPI'!$C$3,EBITDA!$AE$5:$BG$5,0)) -> 0.72552859 | E38: =C38-INDEX(EBITDA!$A$5:$AB$100,MATCH('Tracking KPI'!A38,EBITDA!$A$5:$A$100,0),MATCH('Tracking KPI'!$C$4,EBITDA!$A$5:$AB$5,0)) -> 0 | F38: =IFERROR(C38/(C38-E38),"") | G38: =C38-D38 -> -0.72552859 | H38: =EBITDA!P44 -> 2.7121943 | I38: =EBITDA!BF44 -> 7.2905425 | J38: =EBITDA!BG44 -> 8.083751 | K38: =H38-I38 -> -4.5783481 | L38: =IFERROR(H38/J38,"") -> 0.33551186
A39: Growth Cost | B39: =INDEX(EBITDA!$A$5:$AB$100,MATCH('Tracking KPI'!A39,EBITDA!$A$5:$A$100,0),MATCH('Tracking KPI'!$C$4,EBITDA!$A$5:$AB$5,0)) -> 6.757406 | C39: =INDEX(EBITDA!$A$5:$AB$100,MATCH('Tracking KPI'!A39,EBITDA!$A$5:$A$100,0),MATCH('Tracking KPI'!$C$3,EBITDA!$A$5:$AB$5,0)) -> 3.9547735 | D39: =INDEX(EBITDA!$AE$5:$BG$100,MATCH(A39,EBITDA!$AE$5:$AE$100,0),MATCH('Tracking KPI'!$C$3,EBITDA!$AE$5:$BG$5,0)) -> 5.1260322 | E39: =C39-INDEX(EBITDA!$A$5:$AB$100,MATCH('Tracking KPI'!A39,EBITDA!$A$5:$A$100,0),MATCH('Tracking KPI'!$C$4,EBITDA!$A$5:$AB$5,0)) -> -2.8026325 | F39: =IFERROR(C39/(C39-E39),"") -> 0.58525024 | G39: =C39-D39 -> -1.1712587 | H39: =EBITDA!P45 -> 34.834377 | I39: =EBITDA!BF45 -> 54.717599 | J39: =EBITDA!BG45 -> 59.679728 | K39: =H39-I39 -> -19.883222 | L39: =IFERROR(H39/J39,"") -> 0.5836886
A40: Variable cost - Acquire customer | B40: =INDEX(EBITDA!$A$5:$AB$100,MATCH('Tracking KPI'!A40,EBITDA!$A$5:$A$100,0),MATCH('Tracking KPI'!$C$4,EBITDA!$A$5:$AB$5,0)) -> 6.6716615 | C40: =INDEX(EBITDA!$A$5:$AB$100,MATCH('Tracking KPI'!A40,EBITDA!$A$5:$A$100,0),MATCH('Tracking KPI'!$C$3,EBITDA!$A$5:$AB$5,0)) -> 3.9537145 | D40: =INDEX(EBITDA!$AE$5:$BG$100,MATCH(A40,EBITDA!$AE$5:$AE$100,0),MATCH('Tracking KPI'!$C$3,EBITDA!$AE$5:$BG$5,0)) -> 3.7631 | E40: =C40-INDEX(EBITDA!$A$5:$AB$100,MATCH('Tracking KPI'!A40,EBITDA!$A$5:$A$100,0),MATCH('Tracking KPI'!$C$4,EBITDA!$A$5:$AB$5,0)) -> -2.717947 | F40: =IFERROR(C40/(C40-E40),"") -> 0.59261317 | G40: =C40-D40 -> 0.19061449 | H40: =EBITDA!P46 -> 32.816834 | I40: =EBITDA!BF46 -> 40.9009 | J40: =EBITDA!BG46 -> 44.3311 | K40: =H40-I40 -> -8.0840663 | L40: =IFERROR(H40/J40,"") -> 0.74026662
A41: Acquire TD | B41: =INDEX(EBITDA!$A$5:$AB$100,MATCH('Tracking KPI'!A41,EBITDA!$A$5:$A$100,0),MATCH('Tracking KPI'!$C$4,EBITDA!$A$5:$AB$5,0)) -> 0 | C41: =INDEX(EBITDA!$A$5:$AB$100,MATCH('Tracking KPI'!A41,EBITDA!$A$5:$A$100,0),MATCH('Tracking KPI'!$C$3,EBITDA!$A$5:$AB$5,0)) -> 0 | D41: =INDEX(EBITDA!$AE$5:$BG$100,MATCH(A41,EBITDA!$AE$5:$AE$100,0),MATCH('Tracking KPI'!$C$3,EBITDA!$AE$5:$BG$5,0)) -> 0.4941 | E41: =C41-INDEX(EBITDA!$A$5:$AB$100,MATCH('Tracking KPI'!A41,EBITDA!$A$5:$A$100,0),MATCH('Tracking KPI'!$C$4,EBITDA!$A$5:$AB$5,0)) -> 0 | F41: =IFERROR(C41/(C41-E41),"") | G41: =C41-D41 -> -0.4941 | H41: =EBITDA!P48 -> 0 | I41: =EBITDA!BF48 -> 6.3629 | J41: =EBITDA!BG48 -> 6.4661 | K41: =H41-I41 -> -6.3629 | L41: =IFERROR(H41/J41,"") -> 0
A42: Acquire Vay kỳ hạn | B42: =INDEX(EBITDA!$A$5:$AB$100,MATCH('Tracking KPI'!A42,EBITDA!$A$5:$A$100,0),MATCH('Tracking KPI'!$C$4,EBITDA!$A$5:$AB$5,0)) -> 0 | C42: =INDEX(EBITDA!$A$5:$AB$100,MATCH('Tracking KPI'!A42,EBITDA!$A$5:$A$100,0),MATCH('Tracking KPI'!$C$3,EBITDA!$A$5:$AB$5,0)) -> 0 | D42: =INDEX(EBITDA!$AE$5:$BG$100,MATCH(A42,EBITDA!$AE$5:$AE$100,0),MATCH('Tracking KPI'!$C$3,EBITDA!$AE$5:$BG$5,0)) -> 2.106 | E42: =C42-INDEX(EBITDA!$A$5:$AB$100,MATCH('Tracking KPI'!A42,EBITDA!$A$5:$A$100,0),MATCH('Tracking KPI'!$C$4,EBITDA!$A$5:$AB$5,0)) -> 0 | F42: =IFERROR(C42/(C42-E42),"") | G42: =C42-D42 -> -2.106 | H42: =EBITDA!P49 -> 0 | I42: =EBITDA!BF49 -> 21.987 | J42: =EBITDA!BG49 -> 24.129 | K42: =H42-I42 -> -21.987 | L42: =IFERROR(H42/J42,"") -> 0
A43: Acquire Vay ngắn ngày | B43: =INDEX(EBITDA!$A$5:$AB$100,MATCH('Tracking KPI'!A43,EBITDA!$A$5:$A$100,0),MATCH('Tracking KPI'!$C$4,EBITDA!$A$5:$AB$5,0)) -> 0 | C43: =INDEX(EBITDA!$A$5:$AB$100,MATCH('Tracking KPI'!A43,EBITDA!$A$5:$A$100,0),MATCH('Tracking KPI'!$C$3,EBITDA!$A$5:$AB$5,0)) -> 0 | D43: =INDEX(EBITDA!$AE$5:$BG$100,MATCH(A43,EBITDA!$AE$5:$AE$100,0),MATCH('Tracking KPI'!$C$3,EBITDA!$AE$5:$BG$5,0)) -> 0.0075 | E43: =C43-INDEX(EBITDA!$A$5:$AB$100,MATCH('Tracking KPI'!A43,EBITDA!$A$5:$A$100,0),MATCH('Tracking KPI'!$C$4,EBITDA!$A$5:$AB$5,0)) -> 0 | F43: =IFERROR(C43/(C43-E43),"") | G43: =C43-D43 -> -0.0075 | H43: =EBITDA!P50 -> 0 | I43: =EBITDA!BF50 -> 0.055 | J43: =EBITDA!BG50 -> 0.065 | K43: =H43-I43 -> -0.055 | L43: =IFERROR(H43/J43,"") -> 0
A44: Acquire Overdraft | B44: =INDEX(EBITDA!$A$5:$AB$100,MATCH('Tracking KPI'!A44,EBITDA!$A$5:$A$100,0),MATCH('Tracking KPI'!$C$4,EBITDA!$A$5:$AB$5,0)) -> 0 | C44: =INDEX(EBITDA!$A$5:$AB$100,MATCH('Tracking KPI'!A44,EBITDA!$A$5:$A$100,0),MATCH('Tracking KPI'!$C$3,EBITDA!$A$5:$AB$5,0)) -> 0 | D44: =INDEX(EBITDA!$AE$5:$BG$100,MATCH(A44,EBITDA!$AE$5:$AE$100,0),MATCH('Tracking KPI'!$C$3,EBITDA!$AE$5:$BG$5,0)) -> 0.1305 | E44: =C44-INDEX(EBITDA!$A$5:$AB$100,MATCH('Tracking KPI'!A44,EBITDA!$A$5:$A$100,0),MATCH('Tracking KPI'!$C$4,EBITDA!$A$5:$AB$5,0)) -> 0 | F44: =IFERROR(C44/(C44-E44),"") | G44: =C44-D44 -> -0.1305 | H44: =EBITDA!P51 -> 0 | I44: =EBITDA!BF51 -> 1.221 | J44: =EBITDA!BG51 -> 1.371 | K44: =H44-I44 -> -1.221 | L44: =IFERROR(H44/J44,"") -> 0
A45: Acquire TW | B45: =INDEX(EBITDA!$A$5:$AB$100,MATCH('Tracking KPI'!A45,EBITDA!$A$5:$A$100,0),MATCH('Tracking KPI'!$C$4,EBITDA!$A$5:$AB$5,0)) -> 0 | C45: =INDEX(EBITDA!$A$5:$AB$100,MATCH('Tracking KPI'!A45,EBITDA!$A$5:$A$100,0),MATCH('Tracking KPI'!$C$3,EBITDA!$A$5:$AB$5,0)) -> 0 | D45: =INDEX(EBITDA!$AE$5:$BG$100,MATCH(A45,EBITDA!$AE$5:$AE$100,0),MATCH('Tracking KPI'!$C$3,EBITDA!$AE$5:$BG$5,0)) -> 0 | E45: =C45-INDEX(EBITDA!$A$5:$AB$100,MATCH('Tracking KPI'!A45,EBITDA!$A$5:$A$100,0),MATCH('Tracking KPI'!$C$4,EBITDA!$A$5:$AB$5,0)) -> 0 | F45: =IFERROR(C45/(C45-E45),"") | G45: =C45-D45 -> 0 | H45: =EBITDA!P52 -> 0 | I45: =EBITDA!BF52 -> 0 | J45: =EBITDA!BG52 -> 0 | K45: =H45-I45 -> 0 | L45: =IFERROR(H45/J45,"")
A46: Acquire Paylater | B46: =INDEX(EBITDA!$A$5:$AB$100,MATCH('Tracking KPI'!A46,EBITDA!$A$5:$A$100,0),MATCH('Tracking KPI'!$C$4,EBITDA!$A$5:$AB$5,0)) -> 0 | C46: =INDEX(EBITDA!$A$5:$AB$100,MATCH('Tracking KPI'!A46,EBITDA!$A$5:$A$100,0),MATCH('Tracking KPI'!$C$3,EBITDA!$A$5:$AB$5,0)) -> 0 | D46: =INDEX(EBITDA!$AE$5:$BG$100,MATCH(A46,EBITDA!$AE$5:$AE$100,0),MATCH('Tracking KPI'!$C$3,EBITDA!$AE$5:$BG$5,0)) -> 0 | E46: =C46-INDEX(EBITDA!$A$5:$AB$100,MATCH('Tracking KPI'!A46,EBITDA!$A$5:$A$100,0),MATCH('Tracking KPI'!$C$4,EBITDA!$A$5:$AB$5,0)) -> 0 | F46: =IFERROR(C46/(C46-E46),"") | G46: =C46-D46 -> 0 | H46: =EBITDA!P53 -> 0 | I46: =EBITDA!BF53 -> 0 | J46: =EBITDA!BG53 -> 0 | K46: =H46-I46 -> 0 | L46: =IFERROR(H46/J46,"")
A47: Acquire Credit card | B47: =INDEX(EBITDA!$A$5:$AB$100,MATCH('Tracking KPI'!A47,EBITDA!$A$5:$A$100,0),MATCH('Tracking KPI'!$C$4,EBITDA!$A$5:$AB$5,0)) -> 0 | C47: =INDEX(EBITDA!$A$5:$AB$100,MATCH('Tracking KPI'!A47,EBITDA!$A$5:$A$100,0),MATCH('Tracking KPI'!$C$3,EBITDA!$A$5:$AB$5,0)) -> 0 | D47: =INDEX(EBITDA!$AE$5:$BG$100,MATCH(A47,EBITDA!$AE$5:$AE$100,0),MATCH('Tracking KPI'!$C$3,EBITDA!$AE$5:$BG$5,0)) -> 0.6 | E47: =C47-INDEX(EBITDA!$A$5:$AB$100,MATCH('Tracking KPI'!A47,EBITDA!$A$5:$A$100,0),MATCH('Tracking KPI'!$C$4,EBITDA!$A$5:$AB$5,0)) -> 0 | F47: =IFERROR(C47/(C47-E47),"") | G47: =C47-D47 -> -0.6 | H47: =EBITDA!P54 -> 0 | I47: =EBITDA!BF54 -> 6.6 | J47: =EBITDA!BG54 -> 7.2 | K47: =H47-I47 -> -6.6 | L47: =IFERROR(H47/J47,"") -> 0
A48: Variable cost - Promotion | B48: =INDEX(EBITDA!$A$5:$AB$100,MATCH('Tracking KPI'!A48,EBITDA!$A$5:$A$100,0),MATCH('Tracking KPI'!$C$4,EBITDA!$A$5:$AB$5,0)) -> 0.08574449 | C48: =INDEX(EBITDA!$A$5:$AB$100,MATCH('Tracking KPI'!A48,EBITDA!$A$5:$A$100,0),MATCH('Tracking KPI'!$C$3,EBITDA!$A$5:$AB$5,0)) -> 0.001058991 | D48: =INDEX(EBITDA!$AE$5:$BG$100,MATCH(A48,EBITDA!$AE$5:$AE$100,0),MATCH('Tracking KPI'!$C$3,EBITDA!$AE$5:$BG$5,0)) -> 1.3629322 | E48: =C48-INDEX(EBITDA!$A$5:$AB$100,MATCH('Tracking KPI'!A48,EBITDA!$A$5:$A$100,0),MATCH('Tracking KPI'!$C$4,EBITDA!$A$5:$AB$5,0)) -> -0.084685499 | F48: =IFERROR(C48/(C48-E48),"") -> 0.012350543 | G48: =C48-D48 -> -1.3618732 | H48: =EBITDA!P55 -> 2.0175434 | I48: =EBITDA!BF55 -> 13.816699 | J48: =EBITDA!BG55 -> 15.348628 | K48: =H48-I48 -> -11.799155 | L48: =IFERROR(H48/J48,"") -> 0.1314478
A49: Promotion Deposit products | B49: =INDEX(EBITDA!$A$5:$AB$100,MATCH('Tracking KPI'!A49,EBITDA!$A$5:$A$100,0),MATCH('Tracking KPI'!$C$4,EBITDA!$A$5:$AB$5,0)) -> #N/A | C49: =INDEX(EBITDA!$A$5:$AB$100,MATCH('Tracking KPI'!A49,EBITDA!$A$5:$A$100,0),MATCH('Tracking KPI'!$C$3,EBITDA!$A$5:$AB$5,0)) -> #N/A | D49: =INDEX(EBITDA!$AE$5:$BG$100,MATCH(A49,EBITDA!$AE$5:$AE$100,0),MATCH('Tracking KPI'!$C$3,EBITDA!$AE$5:$BG$5,0)) -> 0.45824324 | E49: =C49-INDEX(EBITDA!$A$5:$AB$100,MATCH('Tracking KPI'!A49,EBITDA!$A$5:$A$100,0),MATCH('Tracking KPI'!$C$4,EBITDA!$A$5:$AB$5,0)) -> #N/A | F49: =IFERROR(C49/(C49-E49),"") | G49: =C49-D49 -> #N/A | H49: =EBITDA!P57 -> 0 | I49: =EBITDA!BF57 -> 4.1921622 | J49: =EBITDA!BG57 -> 4.7056757 | K49: =H49-I49 -> -4.1921622 | L49: =IFERROR(H49/J49,"") -> 0
A50: Promotion Credit card usage | B50: =INDEX(EBITDA!$A$5:$AB$100,MATCH('Tracking KPI'!A50,EBITDA!$A$5:$A$100,0),MATCH('Tracking KPI'!$C$4,EBITDA!$A$5:$AB$5,0)) -> #N/A | C50: =INDEX(EBITDA!$A$5:$AB$100,MATCH('Tracking KPI'!A50,EBITDA!$A$5:$A$100,0),MATCH('Tracking KPI'!$C$3,EBITDA!$A$5:$AB$5,0)) -> #N/A | D50: =INDEX(EBITDA!$AE$5:$BG$100,MATCH(A50,EBITDA!$AE$5:$AE$100,0),MATCH('Tracking KPI'!$C$3,EBITDA!$AE$5:$BG$5,0)) -> 0.65468892 | E50: =C50-INDEX(EBITDA!$A$5:$AB$100,MATCH('Tracking KPI'!A50,EBITDA!$A$5:$A$100,0),MATCH('Tracking KPI'!$C$4,EBITDA!$A$5:$AB$5,0)) -> #N/A | F50: =IFERROR(C50/(C50-E50),"") | G50: =C50-D50 -> #N/A | H50: =EBITDA!P58 -> 0 | I50: =EBITDA!BF58 -> 7.2995366 | J50: =EBITDA!BG58 -> 8.0452255 | K50: =H50-I50 -> -7.2995366 | L50: =IFERROR(H50/J50,"") -> 0
A51: Sharing expenses for partner | B51: =INDEX(EBITDA!$A$5:$AB$100,MATCH('Tracking KPI'!A51,EBITDA!$A$5:$A$100,0),MATCH('Tracking KPI'!$C$4,EBITDA!$A$5:$AB$5,0)) -> 31.812427 | C51: =INDEX(EBITDA!$A$5:$AB$100,MATCH('Tracking KPI'!A51,EBITDA!$A$5:$A$100,0),MATCH('Tracking KPI'!$C$3,EBITDA!$A$5:$AB$5,0)) -> 42.918019 | D51: =INDEX(EBITDA!$AE$5:$BG$100,MATCH(A51,EBITDA!$AE$5:$AE$100,0),MATCH('Tracking KPI'!$C$3,EBITDA!$AE$5:$BG$5,0)) -> 30.490429 | E51: =C51-INDEX(EBITDA!$A$5:$AB$100,MATCH('Tracking KPI'!A51,EBITDA!$A$5:$A$100,0),MATCH('Tracking KPI'!$C$4,EBITDA!$A$5:$AB$5,0)) -> 11.105592 | F51: =IFERROR(C51/(C51-E51),"") -> 1.349096 | G51: =C51-D51 -> 12.427591 | H51: =EBITDA!P59 -> 224.21591 | I51: =EBITDA!BF59 -> 332.60765 | J51: =EBITDA!BG59 -> 369.50567 | K51: =H51-I51 -> -108.39174 | L51: =IFERROR(H51/J51,"") -> 0.60679964
A52: Sharing expense Huy động | B52: =INDEX(EBITDA!$A$5:$AB$100,MATCH('Tracking KPI'!A52,EBITDA!$A$5:$A$100,0),MATCH('Tracking KPI'!$C$4,EBITDA!$A$5:$AB$5,0)) -> 0 | C52: =INDEX(EBITDA!$A$5:$AB$100,MATCH('Tracking KPI'!A52,EBITDA!$A$5:$A$100,0),MATCH('Tracking KPI'!$C$3,EBITDA!$A$5:$AB$5,0)) -> 0 | D52: =INDEX(EBITDA!$AE$5:$BG$100,MATCH(A52,EBITDA!$AE$5:$AE$100,0),MATCH('Tracking KPI'!$C$3,EBITDA!$AE$5:$BG$5,0)) -> 3.3023542 | E52: =C52-INDEX(EBITDA!$A$5:$AB$100,MATCH('Tracking KPI'!A52,EBITDA!$A$5:$A$100,0),MATCH('Tracking KPI'!$C$4,EBITDA!$A$5:$AB$5,0)) -> 0 | F52: =IFERROR(C52/(C52-E52),"") | G52: =C52-D52 -> -3.3023542 | H52: =EBITDA!P60 -> 3.0191535 | I52: =EBITDA!BF60 -> 26.759813 | J52: =EBITDA!BG60 -> 31.062583 | K52: =H52-I52 -> -23.740659 | L52: =IFERROR(H52/J52,"") -> 0.097195828
A53: Sharing expense Vay kỳ hạn | B53: =INDEX(EBITDA!$A$5:$AB$100,MATCH('Tracking KPI'!A53,EBITDA!$A$5:$A$100,0),MATCH('Tracking KPI'!$C$4,EBITDA!$A$5:$AB$5,0)) -> 0 | C53: =INDEX(EBITDA!$A$5:$AB$100,MATCH('Tracking KPI'!A53,EBITDA!$A$5:$A$100,0),MATCH('Tracking KPI'!$C$3,EBITDA!$A$5:$AB$5,0)) -> 0 | D53: =INDEX(EBITDA!$AE$5:$BG$100,MATCH(A53,EBITDA!$AE$5:$AE$100,0),MATCH('Tracking KPI'!$C$3,EBITDA!$AE$5:$BG$5,0)) -> 19.61963 | E53: =C53-INDEX(EBITDA!$A$5:$AB$100,MATCH('Tracking KPI'!A53,EBITDA!$A$5:$A$100,0),MATCH('Tracking KPI'!$C$4,EBITDA!$A$5:$AB$5,0)) -> 0 | F53: =IFERROR(C53/(C53-E53),"") | G53: =C53-D53 -> -19.61963 | H53: =EBITDA!P61 -> 26.693457 | I53: =EBITDA!BF61 -> 230.48791 | J53: =EBITDA!BG61 -> 254.15874 | K53: =H53-I53 -> -203.79445 | L53: =IFERROR(H53/J53,"") -> 0.10502671
A54: Sharing expense Vay ngắn ngày | B54: =INDEX(EBITDA!$A$5:$AB$100,MATCH('Tracking KPI'!A54,EBITDA!$A$5:$A$100,0),MATCH('Tracking KPI'!$C$4,EBITDA!$A$5:$AB$5,0)) -> 0 | C54: =INDEX(EBITDA!$A$5:$AB$100,MATCH('Tracking KPI'!A54,EBITDA!$A$5:$A$100,0),MATCH('Tracking KPI'!$C$3,EBITDA!$A$5:$AB$5,0)) -> 0 | D54: =INDEX(EBITDA!$AE$5:$BG$100,MATCH(A54,EBITDA!$AE$5:$AE$100,0),MATCH('Tracking KPI'!$C$3,EBITDA!$AE$5:$BG$5,0)) -> 6.4144244 | E54: =C54-INDEX(EBITDA!$A$5:$AB$100,MATCH('Tracking KPI'!A54,EBITDA!$A$5:$A$100,0),MATCH('Tracking KPI'!$C$4,EBITDA!$A$5:$AB$5,0)) -> 0 | F54: =IFERROR(C54/(C54-E54),"") | G54: =C54-D54 -> -6.4144244 | H54: =EBITDA!P62 -> 16.18561 | I54: =EBITDA!BF62 -> 67.642426 | J54: =EBITDA!BG62 -> 74.447764 | K54: =H54-I54 -> -51.456815 | L54: =IFERROR(H54/J54,"") -> 0.21740895
A55: Sharing expense TW | B55: =INDEX(EBITDA!$A$5:$AB$100,MATCH('Tracking KPI'!A55,EBITDA!$A$5:$A$100,0),MATCH('Tracking KPI'!$C$4,EBITDA!$A$5:$AB$5,0)) -> 0 | C55: =INDEX(EBITDA!$A$5:$AB$100,MATCH('Tracking KPI'!A55,EBITDA!$A$5:$A$100,0),MATCH('Tracking KPI'!$C$3,EBITDA!$A$5:$AB$5,0)) -> 0 | D55: =INDEX(EBITDA!$AE$5:$BG$100,MATCH(A55,EBITDA!$AE$5:$AE$100,0),MATCH('Tracking KPI'!$C$3,EBITDA!$AE$5:$BG$5,0)) -> 1.1348763 | E55: =C55-INDEX(EBITDA!$A$5:$AB$100,MATCH('Tracking KPI'!A55,EBITDA!$A$5:$A$100,0),MATCH('Tracking KPI'!$C$4,EBITDA!$A$5:$AB$5,0)) -> 0 | F55: =IFERROR(C55/(C55-E55),"") | G55: =C55-D55 -> -1.1348763 | H55: =EBITDA!P63 -> 0 | I55: =EBITDA!BF63 -> 8.0316888 | J55: =EBITDA!BG63 -> 9.6534335 | K55: =H55-I55 -> -8.0316888 | L55: =IFERROR(H55/J55,"") -> 0
A56: Sharing expense Paylater | B56: =INDEX(EBITDA!$A$5:$AB$100,MATCH('Tracking KPI'!A56,EBITDA!$A$5:$A$100,0),MATCH('Tracking KPI'!$C$4,EBITDA!$A$5:$AB$5,0)) -> 0 | C56: =INDEX(EBITDA!$A$5:$AB$100,MATCH('Tracking KPI'!A56,EBITDA!$A$5:$A$100,0),MATCH('Tracking KPI'!$C$3,EBITDA!$A$5:$AB$5,0)) -> 0 | D56: =INDEX(EBITDA!$AE$5:$BG$100,MATCH(A56,EBITDA!$AE$5:$AE$100,0),MATCH('Tracking KPI'!$C$3,EBITDA!$AE$5:$BG$5,0)) -> -0.21834537 | E56: =C56-INDEX(EBITDA!$A$5:$AB$100,MATCH('Tracking KPI'!A56,EBITDA!$A$5:$A$100,0),MATCH('Tracking KPI'!$C$4,EBITDA!$A$5:$AB$5,0)) -> 0 | F56: =IFERROR(C56/(C56-E56),"") | G56: =C56-D56 -> 0.21834537 | H56: =EBITDA!P64 -> 0 | I56: =EBITDA!BF64 -> -1.9936298 | J56: =EBITDA!BG64 -> -2.0780251 | K56: =H56-I56 -> 1.9936298 | L56: =IFERROR(H56/J56,"") -> 0
A57: Sharing expense Credit card | B57: =INDEX(EBITDA!$A$5:$AB$100,MATCH('Tracking KPI'!A57,EBITDA!$A$5:$A$100,0),MATCH('Tracking KPI'!$C$4,EBITDA!$A$5:$AB$5,0)) -> 0 | C57: =INDEX(EBITDA!$A$5:$AB$100,MATCH('Tracking KPI'!A57,EBITDA!$A$5:$A$100,0),MATCH('Tracking KPI'!$C$3,EBITDA!$A$5:$AB$5,0)) -> 0 | D57: =INDEX(EBITDA!$AE$5:$BG$100,MATCH(A57,EBITDA!$AE$5:$AE$100,0),MATCH('Tracking KPI'!$C$3,EBITDA!$AE$5:$BG$5,0)) -> 0.23748936 | E57: =C57-INDEX(EBITDA!$A$5:$AB$100,MATCH('Tracking KPI'!A57,EBITDA!$A$5:$A$100,0),MATCH('Tracking KPI'!$C$4,EBITDA!$A$5:$AB$5,0)) -> 0 | F57: =IFERROR(C57/(C57-E57),"") | G57: =C57-D57 -> -0.23748936 | H57: =EBITDA!P65 -> 0 | I57: =EBITDA!BF65 -> 1.6794387 | J57: =EBITDA!BG65 -> 2.2611718 | K57: =H57-I57 -> -1.6794387 | L57: =IFERROR(H57/J57,"") -> 0
A58: Profit before provision | B58: =INDEX(EBITDA!$A$5:$AB$100,MATCH('Tracking KPI'!A58,EBITDA!$A$5:$A$100,0),MATCH('Tracking KPI'!$C$4,EBITDA!$A$5:$AB$5,0)) -> 187.99018 | C58: =INDEX(EBITDA!$A$5:$AB$100,MATCH('Tracking KPI'!A58,EBITDA!$A$5:$A$100,0),MATCH('Tracking KPI'!$C$3,EBITDA!$A$5:$AB$5,0)) -> 230.02831 | D58: =INDEX(EBITDA!$AE$5:$BG$100,MATCH(A58,EBITDA!$AE$5:$AE$100,0),MATCH('Tracking KPI'!$C$3,EBITDA!$AE$5:$BG$5,0)) -> 179.59332 | E58: =C58-INDEX(EBITDA!$A$5:$AB$100,MATCH('Tracking KPI'!A58,EBITDA!$A$5:$A$100,0),MATCH('Tracking KPI'!$C$4,EBITDA!$A$5:$AB$5,0)) -> 42.038133 | F58: =IFERROR(C58/(C58-E58),"") -> 1.2236188 | G58: =C58-D58 -> 50.434986 | H58: =EBITDA!P66 -> 1234.161 | I58: =EBITDA!BF66 -> 1556.5465 | J58: =EBITDA!BG66 -> 1797.3397 | K58: =H58-I58 -> -322.3855 | L58: =IFERROR(H58/J58,"") -> 0.68665987
A59: Provision expenses | B59: =INDEX(EBITDA!$A$5:$AB$100,MATCH('Tracking KPI'!A59,EBITDA!$A$5:$A$100,0),MATCH('Tracking KPI'!$C$4,EBITDA!$A$5:$AB$5,0)) -> 104.307 | C59: =INDEX(EBITDA!$A$5:$AB$100,MATCH('Tracking KPI'!A59,EBITDA!$A$5:$A$100,0),MATCH('Tracking KPI'!$C$3,EBITDA!$A$5:$AB$5,0)) -> 111.893 | D59: =INDEX(EBITDA!$AE$5:$BG$100,MATCH(A59,EBITDA!$AE$5:$AE$100,0),MATCH('Tracking KPI'!$C$3,EBITDA!$AE$5:$BG$5,0)) -> 112.6376 | E59: =C59-INDEX(EBITDA!$A$5:$AB$100,MATCH('Tracking KPI'!A59,EBITDA!$A$5:$A$100,0),MATCH('Tracking KPI'!$C$4,EBITDA!$A$5:$AB$5,0)) -> 7.586 | F59: =IFERROR(C59/(C59-E59),"") -> 1.0727276 | G59: =C59-D59 -> -0.74459927 | H59: =EBITDA!P67 -> 728.78854 | I59: =EBITDA!BF67 -> 1028.4614 | J59: =EBITDA!BG67 -> 1155.3282 | K59: =H59-I59 -> -299.67284 | L59: =IFERROR(H59/J59,"") -> 0.63080652
A60: Vay kỳ hạn Provision | B60: =INDEX(EBITDA!$A$5:$AB$100,MATCH('Tracking KPI'!A60,EBITDA!$A$5:$A$100,0),MATCH('Tracking KPI'!$C$4,EBITDA!$A$5:$AB$5,0)) -> 0 | C60: =INDEX(EBITDA!$A$5:$AB$100,MATCH('Tracking KPI'!A60,EBITDA!$A$5:$A$100,0),MATCH('Tracking KPI'!$C$3,EBITDA!$A$5:$AB$5,0)) -> 0 | D60: =INDEX(EBITDA!$AE$5:$BG$100,MATCH(A60,EBITDA!$AE$5:$AE$100,0),MATCH('Tracking KPI'!$C$3,EBITDA!$AE$5:$BG$5,0)) -> 79.367475 | E60: =C60-INDEX(EBITDA!$A$5:$AB$100,MATCH('Tracking KPI'!A60,EBITDA!$A$5:$A$100,0),MATCH('Tracking KPI'!$C$4,EBITDA!$A$5:$AB$5,0)) -> 0 | F60: =IFERROR(C60/(C60-E60),"") | G60: =C60-D60 -> -79.367475 | H60: =EBITDA!P68 -> 138.0122 | I60: =EBITDA!BF68 -> 681.59546 | J60: =EBITDA!BG68 -> 770.42711 | K60: =H60-I60 -> -543.58326 | L60: =IFERROR(H60/J60,"") -> 0.17913726
... A66: Profit after Provsion expenses | B66: =INDEX(EBITDA!$A$5:$AB$100,MATCH('Tracking KPI'!A66,EBITDA!$A$5:$A$100,0),MATCH('Tracking KPI'!$C$4,EBITDA!$A$5:$AB$5,0)) -> 83.683175 | C66: =INDEX(EBITDA!$A$5:$AB$100,MATCH('Tracking KPI'!A66,EBITDA!$A$5:$A$100,0),MATCH('Tracking KPI'!$C$3,EBITDA!$A$5:$AB$5,0)) -> 118.13531 | D66: =INDEX(EBITDA!$AE$5:$BG$100,MATCH(A66,EBITDA!$AE$5:$AE$100,0),MATCH('Tracking KPI'!$C$3,EBITDA!$AE$5:$BG$5,0)) -> 66.955723 | E66: =C66-INDEX(EBITDA!$A$5:$AB$100,MATCH('Tracking KPI'!A66,EBITDA!$A$5:$A$100,0),MATCH('Tracking KPI'!$C$4,EBITDA!$A$5:$AB$5,0)) -> 34.452133 | F66: =IFERROR(C66/(C66-E66),"") -> 1.4116972 | G66: =C66-D66 -> 51.179585 | H66: =EBITDA!P74 -> 505.37247 | I66: =EBITDA!BF74 -> 528.08513 | J66: =EBITDA!BG74 -> 642.01149 | K66: =H66-I66 -> -22.71266 | L66: =IFERROR(H66/J66,"") -> 0.78717045
A67: OPEX | B67: =INDEX(EBITDA!$A$5:$AB$100,MATCH('Tracking KPI'!A67,EBITDA!$A$5:$A$100,0),MATCH('Tracking KPI'!$C$4,EBITDA!$A$5:$AB$5,0)) -> 46.984986 | C67: =INDEX(EBITDA!$A$5:$AB$100,MATCH('Tracking KPI'!A67,EBITDA!$A$5:$A$100,0),MATCH('Tracking KPI'!$C$3,EBITDA!$A$5:$AB$5,0)) -> 44.494521 | D67: =INDEX(EBITDA!$AE$5:$BG$100,MATCH(A67,EBITDA!$AE$5:$AE$100,0),MATCH('Tracking KPI'!$C$3,EBITDA!$AE$5:$BG$5,0)) -> 45.575629 | E67: =C67-INDEX(EBITDA!$A$5:$AB$100,MATCH('Tracking KPI'!A67,EBITDA!$A$5:$A$100,0),MATCH('Tracking KPI'!$C$4,EBITDA!$A$5:$AB$5,0)) -> -2.4904646 | F67: =IFERROR(C67/(C67-E67),"") -> 0.94699446 | G67: =C67-D67 -> -1.0811075 | H67: =EBITDA!P77 -> 356.31563 | I67: =EBITDA!BF77 -> 504.62557 | J67: =EBITDA!BG77 -> 550.39705 | K67: =H67-I67 -> -148.30994 | L67: =IFERROR(H67/J67,"") -> 0.64737924
A68: Staff cost | B68: =INDEX(EBITDA!$A$5:$AB$100,MATCH('Tracking KPI'!A68,EBITDA!$A$5:$A$100,0),MATCH('Tracking KPI'!$C$4,EBITDA!$A$5:$AB$5,0)) -> 27.592331 | C68: =INDEX(EBITDA!$A$5:$AB$100,MATCH('Tracking KPI'!A68,EBITDA!$A$5:$A$100,0),MATCH('Tracking KPI'!$C$3,EBITDA!$A$5:$AB$5,0)) -> 25.441091 | D68: =INDEX(EBITDA!$AE$5:$BG$100,MATCH(A68,EBITDA!$AE$5:$AE$100,0),MATCH('Tracking KPI'!$C$3,EBITDA!$AE$5:$BG$5,0)) -> 24.882158 | E68: =C68-INDEX(EBITDA!$A$5:$AB$100,MATCH('Tracking KPI'!A68,EBITDA!$A$5:$A$100,0),MATCH('Tracking KPI'!$C$4,EBITDA!$A$5:$AB$5,0)) -> -2.15124 | F68: =IFERROR(C68/(C68-E68),"") -> 0.92203486 | G68: =C68-D68 -> 0.55893278 | H68: =EBITDA!P78 -> 191.97159 | I68: =EBITDA!BF78 -> 273.70374 | J68: =EBITDA!BG78 -> 298.5859 | K68: =H68-I68 -> -81.732152 | L68: =IFERROR(H68/J68,"") -> 0.64293588
A69: Marketing & Communication | B69: =INDEX(EBITDA!$A$5:$AB$100,MATCH('Tracking KPI'!A69,EBITDA!$A$5:$A$100,0),MATCH('Tracking KPI'!$C$4,EBITDA!$A$5:$AB$5,0)) -> 2.4936661 | C69: =INDEX(EBITDA!$A$5:$AB$100,MATCH('Tracking KPI'!A69,EBITDA!$A$5:$A$100,0),MATCH('Tracking KPI'!$C$3,EBITDA!$A$5:$AB$5,0)) -> 1.4785533 | D69: =INDEX(EBITDA!$AE$5:$BG$100,MATCH(A69,EBITDA!$AE$5:$AE$100,0),MATCH('Tracking KPI'!$C$3,EBITDA!$AE$5:$BG$5,0)) -> 2.05422 | E69: =C69-INDEX(EBITDA!$A$5:$AB$100,MATCH('Tracking KPI'!A69,EBITDA!$A$5:$A$100,0),MATCH('Tracking KPI'!$C$4,EBITDA!$A$5:$AB$5,0)) -> -1.0151128 | F69: =IFERROR(C69/(C69-E69),"") -> 0.59292354 | G69: =C69-D69 -> -0.57566669 | H69: =EBITDA!P79 -> 10.424891 | I69: =EBITDA!BF79 -> 22.59642 | J69: =EBITDA!BG79 -> 24.65064 | K69: =H69-I69 -> -12.17153 | L69: =IFERROR(H69/J69,"") -> 0.42290547
A70: PR - EAD | B70: =INDEX(EBITDA!$A$5:$AB$100,MATCH('Tracking KPI'!A70,EBITDA!$A$5:$A$100,0),MATCH('Tracking KPI'!$C$4,EBITDA!$A$5:$AB$5,0)) -> 0 | C70: =INDEX(EBITDA!$A$5:$AB$100,MATCH('Tracking KPI'!A70,EBITDA!$A$5:$A$100,0),MATCH('Tracking KPI'!$C$3,EBITDA!$A$5:$AB$5,0)) -> 0 | D70: =INDEX(EBITDA!$AE$5:$BG$100,MATCH(A70,EBITDA!$AE$5:$AE$100,0),MATCH('Tracking KPI'!$C$3,EBITDA!$AE$5:$BG$5,0)) -> 0 | E70: =C70-INDEX(EBITDA!$A$5:$AB$100,MATCH('Tracking KPI'!A70,EBITDA!$A$5:$A$100,0),MATCH('Tracking KPI'!$C$4,EBITDA!$A$5:$AB$5,0)) -> 0 | F70: =IFERROR(C70/(C70-E70),"") | G70: =C70-D70 -> 0 | H70: =EBITDA!P80 -> 0 | I70: =EBITDA!BF80 -> 0 | J70: =EBITDA!BG80 -> 0 | K70: =H70-I70 -> 0 | L70: =IFERROR(H70/J70,"")
A71: CI | B71: =INDEX(EBITDA!$A$5:$AB$100,MATCH('Tracking KPI'!A71,EBITDA!$A$5:$A$100,0),MATCH('Tracking KPI'!$C$4,EBITDA!$A$5:$AB$5,0)) -> 0 | C71: =INDEX(EBITDA!$A$5:$AB$100,MATCH('Tracking KPI'!A71,EBITDA!$A$5:$A$100,0),MATCH('Tracking KPI'!$C$3,EBITDA!$A$5:$AB$5,0)) -> 0 | D71: =INDEX(EBITDA!$AE$5:$BG$100,MATCH(A71,EBITDA!$AE$5:$AE$100,0),MATCH('Tracking KPI'!$C$3,EBITDA!$AE$5:$BG$5,0)) -> 0 | E71: =C71-INDEX(EBITDA!$A$5:$AB$100,MATCH('Tracking KPI'!A71,EBITDA!$A$5:$A$100,0),MATCH('Tracking KPI'!$C$4,EBITDA!$A$5:$AB$5,0)) -> 0 | F71: =IFERROR(C71/(C71-E71),"") | G71: =C71-D71 -> 0 | H71: =EBITDA!P81 -> 0 | I71: =EBITDA!BF81 -> 0 | J71: =EBITDA!BG81 -> 0 | K71: =H71-I71 -> 0 | L71: =IFERROR(H71/J71,"")
A72: Operation | B72: =INDEX(EBITDA!$A$5:$AB$100,MATCH('Tracking KPI'!A72,EBITDA!$A$5:$A$100,0),MATCH('Tracking KPI'!$C$4,EBITDA!$A$5:$AB$5,0)) -> 4.0803234 | C72: =INDEX(EBITDA!$A$5:$AB$100,MATCH('Tracking KPI'!A72,EBITDA!$A$5:$A$100,0),MATCH('Tracking KPI'!$C$3,EBITDA!$A$5:$AB$5,0)) -> 4.6204894 | D72: =INDEX(EBITDA!$AE$5:$BG$100,MATCH(A72,EBITDA!$AE$5:$AE$100,0),MATCH('Tracking KPI'!$C$3,EBITDA!$AE$5:$BG$5,0)) -> 4.566241 | E72: =C72-INDEX(EBITDA!$A$5:$AB$100,MATCH('Tracking KPI'!A72,EBITDA!$A$5:$A$100,0),MATCH('Tracking KPI'!$C$4,EBITDA!$A$5:$AB$5,0)) -> 0.54016606 | F72: =IFERROR(C72/(C72-E72),"") -> 1.1323832 | G72: =C72-D72 -> 0.054248427 | H72: =EBITDA!P82 -> 39.356722 | I72: =EBITDA!BF82 -> 55.724526 | J72: =EBITDA!BG82 -> 60.308642 | K72: =H72-I72 -> -16.367805 | L72: =IFERROR(H72/J72,"") -> 0.65258842
A73: KYC | B73: =INDEX(EBITDA!$A$5:$AB$100,MATCH('Tracking KPI'!A73,EBITDA!$A$5:$A$100,0),MATCH('Tracking KPI'!$C$4,EBITDA!$A$5:$AB$5,0)) -> 0.40578638 | C73: =INDEX(EBITDA!$A$5:$AB$100,MATCH('Tracking KPI'!A73,EBITDA!$A$5:$A$100,0),MATCH('Tracking KPI'!$C$3,EBITDA!$A$5:$AB$5,0)) -> 0.42289889 | D73: =INDEX(EBITDA!$AE$5:$BG$100,MATCH(A73,EBITDA!$AE$5:$AE$100,0),MATCH('Tracking KPI'!$C$3,EBITDA!$AE$5:$BG$5,0)) -> 0.17 | E73: =C73-INDEX(EBITDA!$A$5:$AB$100,MATCH('Tracking KPI'!A73,EBITDA!$A$5:$A$100,0),MATCH('Tracking KPI'!$C$4,EBITDA!$A$5:$AB$5,0)) -> 0.01711251 | F73: =IFERROR(C73/(C73-E73),"") -> 1.0421712 | G73: =C73-D73 -> 0.25289889 | H73: =EBITDA!P83 -> 4.857163 | I73: =EBITDA!BF83 -> 2.7625 | J73: =EBITDA!BG83 -> 2.9325 | K73: =H73-I73 -> 2.094663 | L73: =IFERROR(H73/J73,"") -> 1.6563216
A74: CS | B74: =INDEX(EBITDA!$A$5:$AB$100,MATCH('Tracking KPI'!A74,EBITDA!$A$5:$A$100,0),MATCH('Tracking KPI'!$C$4,EBITDA!$A$5:$AB$5,0)) -> 0.55360084 | C74: =INDEX(EBITDA!$A$5:$AB$100,MATCH('Tracking KPI'!A74,EBITDA!$A$5:$A$100,0),MATCH('Tracking KPI'!$C$3,EBITDA!$A$5:$AB$5,0)) -> 0.54042078 | D74: =INDEX(EBITDA!$AE$5:$BG$100,MATCH(A74,EBITDA!$AE$5:$AE$100,0),MATCH('Tracking KPI'!$C$3,EBITDA!$AE$5:$BG$5,0)) -> 0.64776971 | E74: =C74-INDEX(EBITDA!$A$5:$AB$100,MATCH('Tracking KPI'!A74,EBITDA!$A$5:$A$100,0),MATCH('Tracking KPI'!$C$4,EBITDA!$A$5:$AB$5,0)) -> -0.013180062 | F74: =IFERROR(C74/(C74-E74),"") -> 0.97619212 | G74: =C74-D74 -> -0.10734893 | H74: =EBITDA!P85 -> 5.5843019 | I74: =EBITDA!BF85 -> 7.1254668 | J74: =EBITDA!BG85 -> 7.7732365 | K74: =H74-I74 -> -1.5411649 | L74: =IFERROR(H74/J74,"") -> 0.71840113
A75: CX | B75: =INDEX(EBITDA!$A$5:$AB$100,MATCH('Tracking KPI'!A75,EBITDA!$A$5:$A$100,0),MATCH('Tracking KPI'!$C$4,EBITDA!$A$5:$AB$5,0)) -> 0 | C75: =INDEX(EBITDA!$A$5:$AB$100,MATCH('Tracking KPI'!A75,EBITDA!$A$5:$A$100,0),MATCH('Tracking KPI'!$C$3,EBITDA!$A$5:$AB$5,0)) -> 0 | D75: =INDEX(EBITDA!$AE$5:$BG$100,MATCH(A75,EBITDA!$AE$5:$AE$100,0),MATCH('Tracking KPI'!$C$3,EBITDA!$AE$5:$BG$5,0)) -> 0 | E75: =C75-INDEX(EBITDA!$A$5:$AB$100,MATCH('Tracking KPI'!A75,EBITDA!$A$5:$A$100,0),MATCH('Tracking KPI'!$C$4,EBITDA!$A$5:$AB$5,0)) -> 0 | F75: =IFERROR(C75/(C75-E75),"") | G75: =C75-D75 -> 0 | H75: =EBITDA!P86 -> 0 | I75: =EBITDA!BF86 -> 0 | J75: =EBITDA!BG86 -> 0 | K75: =H75-I75 -> 0 | L75: =IFERROR(H75/J75,"")
A76: Debit card issuance fee | B76: =INDEX(EBITDA!$A$5:$AB$100,MATCH('Tracking KPI'!A76,EBITDA!$A$5:$A$100,0),MATCH('Tracking KPI'!$C$4,EBITDA!$A$5:$AB$5,0)) -> 0 | C76: =INDEX(EBITDA!$A$5:$AB$100,MATCH('Tracking KPI'!A76,EBITDA!$A$5:$A$100,0),MATCH('Tracking KPI'!$C$3,EBITDA!$A$5:$AB$5,0)) -> 0 | D76: =INDEX(EBITDA!$AE$5:$BG$100,MATCH(A76,EBITDA!$AE$5:$AE$100,0),MATCH('Tracking KPI'!$C$3,EBITDA!$AE$5:$BG$5,0)) -> 0.1105 | E76: =C76-INDEX(EBITDA!$A$5:$AB$100,MATCH('Tracking KPI'!A76,EBITDA!$A$5:$A$100,0),MATCH('Tracking KPI'!$C$4,EBITDA!$A$5:$AB$5,0)) -> 0 | F76: =IFERROR(C76/(C76-E76),"") | G76: =C76-D76 -> -0.1105 | H76: =EBITDA!P87 -> 0.1 | I76: =EBITDA!BF87 -> 1.2155 | J76: =EBITDA!BG87 -> 1.326 | K76: =H76-I76 -> -1.1155 | L76: =IFERROR(H76/J76,"") -> 0.075414781
A77: Credit card (issuance) | B77: =INDEX(EBITDA!$A$5:$AB$100,MATCH('Tracking KPI'!A77,EBITDA!$A$5:$A$100,0),MATCH('Tracking KPI'!$C$4,EBITDA!$A$5:$AB$5,0)) -> 0.43629716 | C77: =INDEX(EBITDA!$A$5:$AB$100,MATCH('Tracking KPI'!A77,EBITDA!$A$5:$A$100,0),MATCH('Tracking KPI'!$C$3,EBITDA!$A$5:$AB$5,0)) -> 0.44581849 | D77: =INDEX(EBITDA!$AE$5:$BG$100,MATCH(A77,EBITDA!$AE$5:$AE$100,0),MATCH('Tracking KPI'!$C$3,EBITDA!$AE$5:$BG$5,0)) -> 0.391625 | E77: =C77-INDEX(EBITDA!$A$5:$AB$100,MATCH('Tracking KPI'!A77,EBITDA!$A$5:$A$100,0),MATCH('Tracking KPI'!$C$4,EBITDA!$A$5:$AB$5,0)) -> 0.0095213309 | F77: =IFERROR(C77/(C77-E77),"") -> 1.021823 | G77: =C77-D77 -> 0.054193493 | H77: =EBITDA!P88 -> 3.0379331 | I77: =EBITDA!BF88 -> 4.11125 | J77: =EBITDA!BG88 -> 4.52075 | K77: =H77-I77 -> -1.0733169 | L77: =IFERROR(H77/J77,"") -> 0.6719976
A78: Others (office, anciliaries,) | B78: =INDEX(EBITDA!$A$5:$AB$100,MATCH('Tracking KPI'!A78,EBITDA!$A$5:$A$100,0),MATCH('Tracking KPI'!$C$4,EBITDA!$A$5:$AB$5,0)) -> 2.359639 | C78: =INDEX(EBITDA!$A$5:$AB$100,MATCH('Tracking KPI'!A78,EBITDA!$A$5:$A$100,0),MATCH('Tracking KPI'!$C$3,EBITDA!$A$5:$AB$5,0)) -> 2.8902343 | D78: =INDEX(EBITDA!$AE$5:$BG$100,MATCH(A78,EBITDA!$AE$5:$AE$100,0),MATCH('Tracking KPI'!$C$3,EBITDA!$AE$5:$BG$5,0)) -> 2.9063463 | E78: =C78-INDEX(EBITDA!$A$5:$AB$100,MATCH('Tracking KPI'!A78,EBITDA!$A$5:$A$100,0),MATCH('Tracking KPI'!$C$4,EBITDA!$A$5:$AB$5,0)) -> 0.53059529 | F78: =IFERROR(C78/(C78-E78),"") -> 1.2248629 | G78: =C78-D78 -> -0.016112029 | H78: =EBITDA!P89 -> 23.028523 | I78: =EBITDA!BF89 -> 31.969809 | J78: =EBITDA!BG89 -> 34.876156 | K78: =H78-I78 -> -8.9412868 | L78: =IFERROR(H78/J78,"") -> 0.66029418
A79: Allocated Expenses from VPBank | B79: =INDEX(EBITDA!$A$5:$AB$100,MATCH('Tracking KPI'!A79,EBITDA!$A$5:$A$100,0),MATCH('Tracking KPI'!$C$4,EBITDA!$A$5:$AB$5,0)) -> 1.418 | C79: =INDEX(EBITDA!$A$5:$AB$100,MATCH('Tracking KPI'!A79,EBITDA!$A$5:$A$100,0),MATCH('Tracking KPI'!$C$3,EBITDA!$A$5:$AB$5,0)) -> 1.507 | D79: =INDEX(EBITDA!$AE$5:$BG$100,MATCH(A79,EBITDA!$AE$5:$AE$100,0),MATCH('Tracking KPI'!$C$3,EBITDA!$AE$5:$BG$5,0)) -> 1.6666667 | E79: =C79-INDEX(EBITDA!$A$5:$AB$100,MATCH('Tracking KPI'!A79,EBITDA!$A$5:$A$100,0),MATCH('Tracking KPI'!$C$4,EBITDA!$A$5:$AB$5,0)) -> 0.089 | F79: =IFERROR(C79/(C79-E79),"") -> 1.0627645 | G79: =C79-D79 -> -0.15966667 | H79: =EBITDA!P90 -> 12.546 | I79: =EBITDA!BF90 -> 18.333333 | J79: =EBITDA!BG90 -> 20 | K79: =H79-I79 -> -5.7873333 | L79: =IFERROR(H79/J79,"") -> 0.6273
A80: Allocated Expenses from BEG (admin, office, system…) | B80: =INDEX(EBITDA!$A$5:$AB$100,MATCH('Tracking KPI'!A80,EBITDA!$A$5:$A$100,0),MATCH('Tracking KPI'!$C$4,EBITDA!$A$5:$AB$5,0)) -> 0 | C80: =INDEX(EBITDA!$A$5:$AB$100,MATCH('Tracking KPI'!A80,EBITDA!$A$5:$A$100,0),MATCH('Tracking KPI'!$C$3,EBITDA!$A$5:$AB$5,0)) -> 0 | D80: =INDEX(EBITDA!$AE$5:$BG$100,MATCH(A80,EBITDA!$AE$5:$AE$100,0),MATCH('Tracking KPI'!$C$3,EBITDA!$AE$5:$BG$5,0)) -> 0 | E80: =C80-INDEX(EBITDA!$A$5:$AB$100,MATCH('Tracking KPI'!A80,EBITDA!$A$5:$A$100,0),MATCH('Tracking KPI'!$C$4,EBITDA!$A$5:$AB$5,0)) -> 0 | F80: =IFERROR(C80/(C80-E80),"") | G80: =C80-D80 -> 0 | H80: =EBITDA!P91 -> 0 | I80: =EBITDA!BF91 -> 0 | J80: =EBITDA!BG91 -> 0 | K80: =H80-I80 -> 0 | L80: =IFERROR(H80/J80,"")
A81: D&A | B81: =INDEX(EBITDA!$A$5:$AB$100,MATCH('Tracking KPI'!A81,EBITDA!$A$5:$A$100,0),MATCH('Tracking KPI'!$C$4,EBITDA!$A$5:$AB$5,0)) -> 0.32124348 | C81: =INDEX(EBITDA!$A$5:$AB$100,MATCH('Tracking KPI'!A81,EBITDA!$A$5:$A$100,0),MATCH('Tracking KPI'!$C$3,EBITDA!$A$5:$AB$5,0)) -> 0.34253957 | D81: =INDEX(EBITDA!$AE$5:$BG$100,MATCH(A81,EBITDA!$AE$5:$AE$100,0),MATCH('Tracking KPI'!$C$3,EBITDA!$AE$5:$BG$5,0)) -> 0 | E81: =C81-INDEX(EBITDA!$A$5:$AB$100,MATCH('Tracking KPI'!A81,EBITDA!$A$5:$A$100,0),MATCH('Tracking KPI'!$C$4,EBITDA!$A$5:$AB$5,0)) -> 0.021296098 | F81: =IFERROR(C81/(C81-E81),"") -> 1.0662927 | G81: =C81-D81 -> 0.34253957 | H81: =EBITDA!P92 -> 2.7018702 | I81: =EBITDA!BF92 -> 0 | J81: =EBITDA!BG92 -> 0 | K81: =H81-I81 -> 2.7018702 | L81: =IFERROR(H81/J81,"")
A82: Financial Expenses | B82: =INDEX(EBITDA!$A$5:$AB$100,MATCH('Tracking KPI'!A82,EBITDA!$A$5:$A$100,0),MATCH('Tracking KPI'!$C$4,EBITDA!$A$5:$AB$5,0)) -> 2.0029439 | C82: =INDEX(EBITDA!$A$5:$AB$100,MATCH('Tracking KPI'!A82,EBITDA!$A$5:$A$100,0),MATCH('Tracking KPI'!$C$3,EBITDA!$A$5:$AB$5,0)) -> 1.8399063 | D82: =INDEX(EBITDA!$AE$5:$BG$100,MATCH(A82,EBITDA!$AE$5:$AE$100,0),MATCH('Tracking KPI'!$C$3,EBITDA!$AE$5:$BG$5,0)) -> 3.1667443 | E82: =C82-INDEX(EBITDA!$A$5:$AB$100,MATCH('Tracking KPI'!A82,EBITDA!$A$5:$A$100,0),MATCH('Tracking KPI'!$C$4,EBITDA!$A$5:$AB$5,0)) -> -0.16303762 | F82: =IFERROR(C82/(C82-E82),"") -> 0.91860101 | G82: =C82-D82 -> -1.326838 | H82: =EBITDA!P93 -> 25.380817 | I82: =EBITDA!BF93 -> 34.834187 | J82: =EBITDA!BG93 -> 38.000931 | K82: =H82-I82 -> -9.4533699 | L82: =IFERROR(H82/J82,"") -> 0.66789987
A83: Infrastructure & Software | B83: =INDEX(EBITDA!$A$5:$AB$100,MATCH('Tracking KPI'!A83,EBITDA!$A$5:$A$100,0),MATCH('Tracking KPI'!$C$4,EBITDA!$A$5:$AB$5,0)) -> 9.0764779 | C83: =INDEX(EBITDA!$A$5:$AB$100,MATCH('Tracking KPI'!A83,EBITDA!$A$5:$A$100,0),MATCH('Tracking KPI'!$C$3,EBITDA!$A$5:$AB$5,0)) -> 9.2649415 | D83: =INDEX(EBITDA!$AE$5:$BG$100,MATCH(A83,EBITDA!$AE$5:$AE$100,0),MATCH('Tracking KPI'!$C$3,EBITDA!$AE$5:$BG$5,0)) -> 9.2395985 | E83: =C83-INDEX(EBITDA!$A$5:$AB$100,MATCH('Tracking KPI'!A83,EBITDA!$A$5:$A$100,0),MATCH('Tracking KPI'!$C$4,EBITDA!$A$5:$AB$5,0)) -> 0.18846356 | F83: =IFERROR(C83/(C83-E83),"") -> 1.020764 | G83: =C83-D83 -> 0.02534301 | H83: =EBITDA!P94 -> 73.933737 | I83: =EBITDA!BF94 -> 99.43336 | J83: =EBITDA!BG94 -> 108.85094 | K83: =H83-I83 -> -25.499624 | L83: =IFERROR(H83/J83,"") -> 0.67922001
A84: SMS | B84: =INDEX(EBITDA!$A$5:$AB$100,MATCH('Tracking KPI'!A84,EBITDA!$A$5:$A$100,0),MATCH('Tracking KPI'!$C$4,EBITDA!$A$5:$AB$5,0)) -> 0.909 | C84: =INDEX(EBITDA!$A$5:$AB$100,MATCH('Tracking KPI'!A84,EBITDA!$A$5:$A$100,0),MATCH('Tracking KPI'!$C$3,EBITDA!$A$5:$AB$5,0)) -> 1.08 | D84: =INDEX(EBITDA!$AE$5:$BG$100,MATCH(A84,EBITDA!$AE$5:$AE$100,0),MATCH('Tracking KPI'!$C$3,EBITDA!$AE$5:$BG$5,0)) -> 1.3605001 | E84: =C84-INDEX(EBITDA!$A$5:$AB$100,MATCH('Tracking KPI'!A84,EBITDA!$A$5:$A$100,0),MATCH('Tracking KPI'!$C$4,EBITDA!$A$5:$AB$5,0)) -> 0.171 | F84: =IFERROR(C84/(C84-E84),"") -> 1.1881188 | G84: =C84-D84 -> -0.28050014 | H84: =EBITDA!P95 -> 8.264 | I84: =EBITDA!BF95 -> 12.763279 | J84: =EBITDA!BG95 -> 14.301761 | K84: =H84-I84 -> -4.4992791 | L84: =IFERROR(H84/J84,"") -> 0.57783092
A85: IT expenses tại Cake | B85: =INDEX(EBITDA!$A$5:$AB$100,MATCH('Tracking KPI'!A85,EBITDA!$A$5:$A$100,0),MATCH('Tracking KPI'!$C$4,EBITDA!$A$5:$AB$5,0)) -> 0 | C85: =INDEX(EBITDA!$A$5:$AB$100,MATCH('Tracking KPI'!A85,EBITDA!$A$5:$A$100,0),MATCH('Tracking KPI'!$C$3,EBITDA!$A$5:$AB$5,0)) -> 0 | D85: =INDEX(EBITDA!$AE$5:$BG$100,MATCH(A85,EBITDA!$AE$5:$AE$100,0),MATCH('Tracking KPI'!$C$3,EBITDA!$AE$5:$BG$5,0)) -> 5.3055732 | E85: =C85-INDEX(EBITDA!$A$5:$AB$100,MATCH('Tracking KPI'!A85,EBITDA!$A$5:$A$100,0),MATCH('Tracking KPI'!$C$4,EBITDA!$A$5:$AB$5,0)) -> 0 | F85: =IFERROR(C85/(C85-E85),"") | G85: =C85-D85 -> -5.3055732 | H85: =EBITDA!P96 -> 5.9208219 | I85: =EBITDA!BF96 -> 58.361306 | J85: =EBITDA!BG96 -> 63.666879 | K85: =H85-I85 -> -52.440484 | L85: =IFERROR(H85/J85,"") -> 0.092996893
... A89: EBITDA | B89: =INDEX(EBITDA!$A$5:$AB$100,MATCH('Tracking KPI'!A89,EBITDA!$A$5:$A$100,0),MATCH('Tracking KPI'!$C$4,EBITDA!$A$5:$AB$5,0)) -> 39.022377 | C89: =INDEX(EBITDA!$A$5:$AB$100,MATCH('Tracking KPI'!A89,EBITDA!$A$5:$A$100,0),MATCH('Tracking KPI'!$C$3,EBITDA!$A$5:$AB$5,0)) -> 75.823233 | D89: =INDEX(EBITDA!$AE$5:$BG$100,MATCH(A89,EBITDA!$AE$5:$AE$100,0),MATCH('Tracking KPI'!$C$3,EBITDA!$AE$5:$BG$5,0)) -> 21.213505 | E89: =C89-INDEX(EBITDA!$A$5:$AB$100,MATCH('Tracking KPI'!A89,EBITDA!$A$5:$A$100,0),MATCH('Tracking KPI'!$C$4,EBITDA!$A$5:$AB$5,0)) -> 36.800856 | F89: =IFERROR(C89/(C89-E89),"") -> 1.9430706 | G89: =C89-D89 -> 54.609728 | H89: =EBITDA!P100 -> 177.13954 | I89: =EBITDA!BF100 -> 21.627085 | J89: =EBITDA!BG100 -> 89.615366 | K89: =H89-I89 -> 155.51245 | L89: =IFERROR(H89/J89,"") -> 1.9766648

Sheet Paylater
B1: Group | C1: Product | D1: Type | E1: Channel | F1: Mapping Product | G1: Mapping Group KPIxProducts | I1: Category | J1: Index | L1: Product PnL | M1: YTD | N1: 45597 | O1: 45627 | P1: 45658 | Q1: 45689 | R1: 45717 | S1: 45748 | T1: 45778 | U1: 45809 | V1: 45839 | W1: 45870 | X1: 45901 | Y1: 45931 | Z1: 45962 | AA1: 45992 | AB1: FY2025 | AC1: Thoái lãi | AD1: =AA80+AA186+AA239+AA292+AA345 -> 374868547
L2: Paylater | AC2: Thoái phí | AD2: =AA90+AA196+AA249+AA302+AA355 -> 630277621
B3: lending | C3: paylater | D3: paylater | E3: all | K3: All | L3: New account | N3: =N53+N159+N212+N265 -> 6543 | O3: =O53+O159+O212+O265 -> 7080 | P3: =P53+P159+P212+P265 -> 6883 | Q3: =Q53+Q159+Q212+Q265+Q318 -> 15455 | R3: =R53+R159+R212+R265+R318 -> 7234 | S3: =S53+S159+S212+S265+S318 -> 7199 | T3: =T53+T159+T212+T265+T318 -> 7341 | U3: =U53+U159+U212+U265+U318 -> 9544 | V3: =V53+V159+V212+V265+V318 -> 9371 | W3: =W53+W159+W212+W265+W318 -> 8431 | X3: =X53+X159+X212+X265+X318 -> 8440 | ... AA3: =AA53+AA159+AA212+AA265+AA318 -> 11975
B4: lending | C4: paylater | D4: paylater | E4: all | J4: =B4&"_"&C4&"_"&D4&"_"&E4&"_"&I4 -> lending_paylater_paylater_all_ | K4: All | L4: Accumulated account | N4: =N54+N160+N213+N266 -> 46582 | O4: =O54+O160+O213+O266 -> 53662 | P4: =P54+P160+P213+P266 -> 60545 | Q4: =Q54+Q160+Q213+Q266+Q319 -> 76000 | R4: =R54+R160+R213+R266+R319 -> 83234 | S4: =S54+S160+S213+S266+S319 -> 90433 | T4: =T54+T160+T213+T266+T319 -> 97774 | U4: =U54+U160+U213+U266+U319 -> 107318 | V4: =V54+V160+V213+V266+V319 -> 116689 | W4: =W54+W160+W213+W266+W319 -> 125120 | X4: =X54+X160+X213+X266+X319 -> 133560 | ... AA4: =AA54+AA160+AA213+AA266+AA319 -> 164709
