Workbook
Name __S1: {"Book1"}
Name __S1: {"Book1"}
Name _a1: {"'Sheet1'!$L$16"}
Name _a1: {"'Sheet1'!$L$16"}
Name _S1: {"Book1"}
Name _S1: {"Book1"}
Name Ă: #REF!
Name Ạ196: #REF!
Name â259: #REF!
Name â259: #REF!
Name â312: #REF!
Name â312: #REF!
Name Acquisition_PlanA: #REF!
Name Acquisition_PlanB: #REF!
Name Actual: (PeriodInActual*(#REF!>0))*PeriodInPlan
Name Actual: (PeriodInActual*(#REF!>0))*PeriodInPlan
Name ActualBeyond: PeriodInActual*(#REF!>0)
Name ActualBeyond: PeriodInActual*(#REF!>0)
Name adf: #REF!
Name adf: #REF!
Name AdvIncQ12020: #REF!
Name AdvIncQ12021: #REF!
Name AdvIncQ12022: #REF!
Name AdvIncQ12023: #REF!
Name AdvIncQ12024: #REF!
Name AdvIncQ22020: #REF!
Name AdvIncQ22021: #REF!
Name AdvIncQ22022: #REF!
Name AdvIncQ22023: #REF!
Name AdvIncQ22024: #REF!
Name AdvIncQ32020: #REF!
Name AdvIncQ32021: #REF!
Name AdvIncQ32022: #REF!
Name AdvIncQ32023: #REF!
Name AdvIncQ32024: #REF!
Name AdvIncQ42020: #REF!
Name AdvIncQ42021: #REF!
Name AdvIncQ42022: #REF!
Name AdvIncQ42023: #REF!
Name AdvIncQ42024: #REF!
Name AdvPenRate2020: #REF!
Name AdvPenRate2021: #REF!
Name AdvPenRate2022: #REF!
Name AdvPenRate2023: #REF!
Name AdvPenRate2024: #REF!
Name AllReportList: #REF!
Name Amount_act: #REF!
Name Amount_CF: #REF!
Name Amount_F: #REF!
Name Amount_KPI_act: #REF!
Name approval: #REF!
Name approval: #REF!
Name Attribute_F: #REF!
Name B: #REF!
Name b2bSpr: #REF!
Name BaoHanhSuaChua: #REF!
Name be_KPI_bud: #REF!
Name be2B: #REF!
Name bf: #REF!
Name bf: #REF!

Sheet NOTE
A1: SAP MODEL - OVERDRAFT
N2: KHN | O2: v5 | P2: 20251001
B3: 1. Notes and disclaimer
C4: a. Giới thiệu về SAP
D5: - SAP: Single Account Profitability (Hiệu quả sản phẩm trên từng đơn vị sản phẩm)
D6: - Model SAP được sử dụng như một (01) mô hình dự đoán hiệu quả vòng đời của sản phẩm.
D7: - Do sự phức tạp của sản phẩm, các hệ thống vận hành (hệ thống hạch kế toán, hệ thống quản trị rủi ro, hệ thống quản trị…), hành vi người sử dụng hành vi người sử dụng, model chỉ có thể mô phỏng tương đối trung bình vòng đời của sản phẩm.
D8: - Do tính chất thời điểm, mô hình được xây dựng mô phỏng theo cách vận hành sản phẩm tại thời điểm phát hành. Trường hợp hệ thống thay đổi, sản phẩm thay đổi, mô hình sẽ không thể phản ánh đúng bản chất vận hành sản phẩm.
D9: - Mô hình được tính toán dựa vào các yếu tố đầu vào xác định tại thời điểm, do đó kết quả của mô hình có thể có sự khác biệt so với thực tế vận hành sản phẩm.
D10: - Mô hình SAP Overdraft tính hiệu quả dự kiến của 1 tài khoản Overdraft mở trong kỳ hoạt động 12 tháng
C12: b. Giới thiệu về PnL
D13: - Trong file tính này, Profit & Lost (PnL) được dự phóng từ trung bình cộng kết quả kinh doanh trên từng sản phẩm (SAP) với yếu tố "sale plan" (số giải ngân) qua từng tháng, do đó có thể khác biệt so với kết quả thực tế vận hành.
D14: - Dòng tiền thực tế qua từng tháng có thể khác biệt với mô hình tính toán do nhiều yếu tố tác động bên ngoài thay đổi, do đó, vui lòng chỉ sử dụng mô hình cho mục đích tham khảo.
D15: - Cho mục đích tính dự phòng dòng tiền ngắn và trung hạn, mô hình PnL được cutoff tại thời điểm 5 năm (60 tháng) kể từ ngày bắt đầu khởi chạy sản phẩm đầu tiên.
B17: 2. Instruction
D18: - Dành cho người sử dụng
E19: - Chỉ chỉnh sửa vào các ô màu vàng
E20: - 2 sheets "SAP_Leadsheet" và "Sale plan&PL" cung cấp yếu tố đầu vào và đầu ra để tính toán mô hình SAP cũng như PnL.
F21: - Sheet SAP_Leadsheet được cấu trúc 2 phần, bên trái là các yếu tố đầu vào (input) và bên phải là kết quả dự đoán (output). Đơn vị sử dụng tại bảng tính là triệu VND (mVND) và phần trăm (%)
F22: - Sheet "Sale plan & PL" được cấu trúc 2 phần, bên trên là sale plan và bên dưới là kết quả PnL
E23: - 2 sheets "SAP_Spreadsheet" và "PL projection speadsheet" là các file tính toán cho 2 sheet "SAP_Leadsheet", "Sales plan & PL"
F24: - 2 sheets được cấu trúc từ trên xuống dưới theo thứ tự tính toán mô phỏng để đưa ra kết quả kinh doanh cuối cùng
F25: - 2 sheets đã được tạm khóa. Trường hợp cần mở khóa, điều chỉnh các yếu tố, vui lòng liên hệ với nhóm vận hành để được hỗ trợ.
D27: - Dành riêng cho người vận hành, hiệu chỉnh
E28: - Cần cẩn trọng khi điều chỉnh ở các file "speadsheet" vì 1 khi sai lệch rất khó tìm ra lỗi (VD: sửa nhầm ô, link nhầm vị trí,…)
B31: 3. Legend
C33: GENERAL INPUT
G35: Diễn giải | L35: Chú thích
D36: Risk input | G36: Loại phương pháp tính rủi ro | L36: Lựa chon phương pháp tính rủi ro VAS và IFRS
D37: Write off | G37: Thời điểm WO | L37: Lựa chọn thời điểm ghi nhận WO là 360 hoặc 180
C38: REVENUE INPUT
G40: Diễn giải | L40: Chú thích
C41: Amount & Tenor
D42: Average active balance | G42: Trung bình dư nợ/1 tài khoản có dư nợ/ngày | L42: =toàn bộ dư nợ theo từng ngày của toàn bộ tài khoản có dư nợ/(số ngày có dư nợ * số tài khoản có dư nợ theo từng ngày).
D43: Payment Method | G43: Phương pháp tính lãi | L43: Bullet payment- hàng tháng trả lãi, cuối kỳ trả gốc
D44: Nominal Tenor | G44: Thời hạn vay trung bình (active) | L44: Thời hạn trung bình giữ dư nợ của 1 khoản vay active
D45: Maturity to Termination | G45: Thời hạn từ lúc đáo hạn tới lúc tới khi ra ngoại bảng | L45: Nên để 6 tháng để khớp với hệ thống kế toán, rủi ro đang ghi nhận WO180+
D46: Month on book | G46: Thời gian ghi nhận trên sổ sách | L46: = Nominal tenor + Maturity to termination
C48: Pricing
D49: From- To | G49: Từ tháng… tới tháng
D50: IR | G50: Interest rate- lãi suất khoản vay
D51: COF | G51: Cost of fund - Giá vốn | L51: Sử dụng matrix mua vốn của VPB
D52: NIM | G52: Net interest margin - Biên lãi ròng
C54: Monthly fee | G54: Phí hàng tháng
C55: Loan grant fee | G55: Phí mở tài khoản
C57: COST INPUT
G59: Diễn giải | L59: Chú thích
C60: Inflation rate | G60: Tỉ lệ tăng giá chi phí qua các năm
C62: Acquisition cost | G62: Chi phí mở rộng khách hàng
D63: Sale incentive | G63: Chi phí sales, trả đối tác kinh doanh
D64: Sharing TOI and Risk DPD90+ | G64: Chia sẻ doanh thu, rủi ro(DPD90+) | L64: xem giải thích DPD+ tại đây
D65: Sharing TOI and Risk DPD180+ | G65: Chia sẻ doanh thu, rủi ro(DPD180+) | L65: xem giải thích DPD+ tại đây
D67: Sharing CII (only) | G67: Chỉ chia sẻ doanh thu từ lãi
D68: Sharing COF (only) | G68: Chỉ chia sẻ chi phí vốn
D69: Sharing NFI (only) | G69: Chỉ chia sẻ doanh thu từ vốn
D70: Sharing Risk DPD90+ (Only) | G70: Chỉ chia sẻ rủi ro (DPD90+) | L70: xem giải thích DPD+ tại đây
D71: Sharing Risk DPD180+ (only) | G71: Chỉ chia sẻ rủi ro (DPD180+) | L71: xem giải thích DPD+ tại đây
D73: Partner Lead Acquistion | G73: Chi phí leadgen đối tác
C75: * Chú thích
C76: Chia sẻ rủi ro DPD90/ (DPD180+) là phương pháp tính rủi ro = 100% duy nhất 1 lần tại thời điểm dư nợ DPD90 +(tức quá hạn >90 ngày, chuyển nợ nhóm 3)/ DPD180+(tức qua hạn >180 ngày, chuyển nợ nhóm 4) mà ko tính tại các bucket khác.
C77: Phương pháp này chỉ sử dụng đối với các đối tác chia sẻ doanh thu chi phí.
D79: Marketing cost | G79: Chi phí marketing để mở khoản vay
D81: UW & Disbursal
E82: Underwriting cost & Score | G82: Chi phí kiểm tra điều kiện mở khoản vay
E83: DOP cost | G83: Chi phí luồng DOP (nếu có) (SMS,…)
E84: Disbursement cost | G84: Chi phí mở khoản vay (chi phí esign, sms,…)
E85: Approval rate | G85: Tỉ lệ phê duyệt | L85: Tỉ lệ khách hàng được phê duyệt/khách hàng vào luồng LOS
E86: Disbursement rate | G86: Tỉ lệ giải ngân | L86: Tỉ lệ khách hàng giải ngân/khách hàng được phê duyệt
D88: Collection & AMC
E89: Collections_all | G89: Đơn giá thu nợ tính trung bình cho các khoản vay
D91: Aftersale service
E92: Email & SMS | G92: Chi phí Email, SMS hàng tháng
D94: Supporting units | G94: Chi phí phân bổ
E95: Direct HR | G95: Chi phí nhân sự trực tiếp
E96: Indirect HR | G96: Chi phí nhân sự hỗ trợ
E97: IT | G97: Chi phí IT
E98: Other supports | G98: Chi phí khác (Chi phí thuê VP, CS, khác…)
C100: RISK INPUT
D102: NF | G102: Netflow- Tỉ lệ chuyển nợ
D103: PD | G103: Percentage of debt (tỉ lệ vỡ nợ)
D104: Pro. Rate | G104: Tỉ lệ vỡ nợ đã điều chỉnh thu hồi nợ
D106: Recovery rate | G106: Tỉ lệ thu hồi nợ sau WO | L106: Hiện tại chưa đủ dữ liệu tính nên để =0
B108: Write-off mode | E108: Provision mode
B109: DPD360+ | E109: IFRS
B110: DPD180+ | E110: VAS

Sheet DATA
B1: =Leadsheet!G6 -> Q1
B2: Mapping | C2: Value
A3: Average active balance | B3: AVG Ticket size | C3: =INDEX($F$26:$Y$27,MATCH($B$1,$F$26:$F$27,0),MATCH($B3,$F$26:$Y$26,0)) -> 8.3820479
A4: Nominal Tenor | B4: AVG Tenor | C4: =INDEX($F$26:$Y$27,MATCH($B$1,$F$26:$F$27,0),MATCH($B4,$F$26:$Y$26,0)) -> 9
A5: IR | B5: IR | C5: =INDEX($F$26:$Y$27,MATCH($B$1,$F$26:$F$27,0),MATCH($B5,$F$26:$Y$26,0)) -> 0.34950821
A6: COF | B6: COF | C6: =INDEX($F$26:$Y$27,MATCH($B$1,$F$26:$F$27,0),MATCH($B6,$F$26:$Y$26,0)) -> 0.066359342
A7: Loan grant fee | B7: Limit fee | C7: =INDEX($F$26:$Y$27,MATCH($B$1,$F$26:$F$27,0),MATCH($B7,$F$26:$Y$26,0)) -> 0.1512425
A8: Underwriting cost & Score | B8: UW | C8: =INDEX($F$26:$Y$27,MATCH($B$1,$F$26:$F$27,0),MATCH($B8,$F$26:$Y$26,0)) -> 0.014026942
A9: Disbursement cost | B9: Disburse cost | C9: =INDEX($F$26:$Y$27,MATCH($B$1,$F$26:$F$27,0),MATCH($B9,$F$26:$Y$26,0)) -> 0.00082621508
A10: Approval rate | B10: Aprroval rate | C10: =INDEX($F$26:$Y$27,MATCH($B$1,$F$26:$F$27,0),MATCH($B10,$F$26:$Y$26,0)) -> 0.14382507
A11: Disbursement rate | B11: Signed rate | C11: =INDEX($F$26:$Y$27,MATCH($B$1,$F$26:$F$27,0),MATCH($B11,$F$26:$Y$26,0)) -> 0.85010707
A12: Collections_all | B12: Collection | C12: =INDEX($F$26:$Y$27,MATCH($B$1,$F$26:$F$27,0),MATCH($B12,$F$26:$Y$26,0)) -> 0.004036068
A13: Email & SMS | B13: SMS | C13: =INDEX($F$26:$Y$27,MATCH($B$1,$F$26:$F$27,0),MATCH($B13,$F$26:$Y$26,0)) -> 7.6532027e-06
A14: Direct HR | B14: Direct HR cost | C14: =INDEX($AA$26:$AE$30,MATCH($B14,$AA$26:$AA$30,0),MATCH($B$1,$AA$26:$AE$26,0)) -> 0.0075933848
A15: Indirect HR | B15: Indirect HR cost | C15: =INDEX($AA$26:$AE$30,MATCH($B15,$AA$26:$AA$30,0),MATCH($B$1,$AA$26:$AE$26,0)) -> 0.018032513
A16: IT | B16: Indirect system cost | C16: =INDEX($AA$26:$AE$30,MATCH($B16,$AA$26:$AA$30,0),MATCH($B$1,$AA$26:$AE$26,0)) -> 0.0099529491
A17: Other supports | B17: Other indirect supporting cost | C17: =INDEX($AA$26:$AE$30,MATCH($B17,$AA$26:$AA$30,0),MATCH($B$1,$AA$26:$AE$26,0)) -> 0.0073406551
B19: %Attrition
A20: 0 | B20: =INDEX($F$26:$Y$27,MATCH($B$1,$F$26:$F$27,0),MATCH($A20,$F$26:$Y$26,0)) -> 0.05
A21: 1 | B21: =INDEX($F$26:$Y$27,MATCH($B$1,$F$26:$F$27,0),MATCH($A21,$F$26:$Y$26,0)) -> 0.1
A22: 2 | B22: =INDEX($F$26:$Y$27,MATCH($B$1,$F$26:$F$27,0),MATCH($A22,$F$26:$Y$26,0)) -> 0.03
A26: Group | B26: Partner | C26: Product | D26: Sub Product | E26: Index | F26: Period | G26: Aprroval rate | H26: Signed rate | I26: IR | J26: COF | K26: AVG Ticket size | L26: AVG Tenor | M26: Insurance rate | N26: Insurance penetration | O26: MKT | P26: UW | Q26: Collection | R26: SMS | S26: Disburse cost | T26: Limit fee | U26: Leadgen | V26: Sharing | W26: 0 | X26: 1 | Y26: 2 | AB26: Q1 | AC26: Q2 | AD26: Q3 | AE26: Q4
A27: UPL | B27: Cake | C27: Overdraft | D27: Overdraft | E27: Cake_Overdraft | F27: Q1 | G27: 0.14382507 | H27: 0.85010707 | I27: 0.34950821 | J27: 0.066359342 | K27: 8.3820479 | L27: 9 | O27: 0 | P27: 0.014026942 | Q27: 0.004036068 | R27: 7.6532027e-06 | S27: 0.00082621508 | T27: 0.1512425 | W27: 0.05 | X27: 0.1 | Y27: 0.03 | AA27: Direct HR cost | AB27: 0.0075933848
AA28: Indirect HR cost | AB28: 0.018032513
AA29: Indirect system cost | AB29: 0.0099529491
AA30: Other indirect supporting cost | AB30: 0.0073406551

Sheet Leadsheet
B1: SAP OVERDRAFT MODEL | D1: 1 | E1: =C4&C5&C6&G7&G5&G6&G4 -> OverdraftAllDPD180+Q1IFRS
B2: =NOTE!N2 -> KHN | C2: =NOTE!P2 -> 20251001 | D2: =NOTE!O2 -> v5
B4: Product | C4: Overdraft | D4: UPL | E4: Risk input | G4: IFRS | H4: =G4 -> IFRS
B5: Sub-Product | C5: All | D5: ALL | E5: Write off | G5: DPD180+ | H5: =G5 -> DPD180+
B6: Sub-Segments | D6: ALL | E6: Time | G6: Q1
H7: =G7 -> 0
B9: REVENUE INPUT | H9: Cur: mVND | K9: GENERAL OUTPUT | U9: Cur: mVND
B11: Amount & Tenor | C11: Average active balance | E11: =DATA!C3 -> 8.3820479 | N11: Life time | O11: Year 1 | P11: Year 2 | Q11: Year 3 | R11: Year 4 | S11: Year 5 | T11: % ANR | U11: % Disbursement
C12: Payment Method | E12: Bullet payment | K12: ANR | N12: =N30 -> 4.2346839 | O12: =O30 -> 4.9448101 | P12: =P30 -> 1.3941789 | Q12: =Q30 -> 0 | R12: =R30 -> 0 | S12: =S30 -> 0 | U12: =N12/$E$11 -> 0.50520875
C13: Nominal Tenor | E13: =DATA!C4 -> 9 | F13: Active time (=< 12m) | K13: TOI | N13: =SUM(N14:N16) -> 1.321896 | O13: =SUM(O14:O16) -> 1.3450252 | P13: =SUM(P14:P16) -> -0.023129199 | Q13: =SUM(Q14:Q16) -> 0 | R13: =SUM(R14:R16) -> 0 | S13: =SUM(S14:S16) -> 0 | T13: =N13/$E$15*12/$N$12 -> 0.24972745 | U13: =N13/$E$11 -> 0.15770562
C14: Maturity to Termination | E14: 6 | K14: Net interest income | N14: =N32 -> 1.1706535 | O14: =O32 -> 1.1937827 | P14: =P32 -> -0.023129199 | Q14: =Q32 -> 0 | R14: =R32 -> 0 | S14: =S32 -> 0 | T14: =N14/$E$15*12/$N$12 -> 0.22115531 | U14: =N14/$E$11 -> 0.13966199
C15: Month on book | E15: =E13+E14 -> 15 | K15: Net fee income | N15: =N35 -> 0.1512425 | O15: =O35 -> 0.1512425 | P15: =P35 -> 0 | Q15: =Q35 -> 0 | R15: =R35 -> 0 | S15: =S35 -> 0 | T15: =N15/$E$15*12/$N$12 -> 0.028572145 | U15: =N15/$E$11 -> 0.018043622
K16: Other income | N16: =N39 -> 0 | O16: =O39 -> 0 | P16: =P39 -> 0 | Q16: =Q39 -> 0 | R16: =R39 -> 0 | S16: =S39 -> 0 | T16: =N16/$E$15*12/$N$12 -> 0 | U16: =N16/$E$11 -> 0
B17: Pricing | C17: From | D17: To | E17: IR | F17: COF | G17: NIM | K17: PROVISION | N17: =N40 -> -1.3189242 | O17: =O40 -> -1.308878 | P17: =P40 -> -0.010046183 | Q17: =Q40 -> 0 | R17: =R40 -> 0 | S17: =S40 -> 0 | T17: =N17/$E$15*12/$N$12 -> -0.24916602 | U17: =N17/$E$11 -> -0.15735107
B18: Indue | C18: 1 | D18: =E13 -> 9 | E18: =DATA!C5 -> 0.34950821 | F18: =DATA!C6 -> 0.066359342 | G18: =E18-F18 -> 0.28314887 | K18: OPEX | N18: =SUM(N19:N22) -> -0.33047051 | O18: =SUM(O19:O22) -> -0.32827852 | P18: =SUM(P19:P22) -> -0.0021919861 | Q18: =SUM(Q19:Q22) -> 0 | R18: =SUM(R19:R22) -> 0 | S18: =SUM(S19:S22) -> 0 | T18: =N18/$E$15*12/$N$12 -> -0.062431203 | U18: =N18/$E$11 -> -0.039425987
A19: 1 | B19: Overdue | C19: =IF(D18="","",IF(D18>$E$13,"",D18+1)) -> 10 | D19: =E15 -> 15 | E19: =E18 -> 0.34950821 | F19: =F18 -> 0.066359342 | K19: Acquisition cost | N19: =SUM(N42) -> 0 | O19: =SUM(O42) -> 0 | P19: =SUM(P42) -> 0 | Q19: =SUM(Q42) -> 0 | R19: =SUM(R42) -> 0 | S19: =SUM(S42) -> 0 | T19: =N19/$E$15*12/$N$12 -> 0 | U19: =N19/$E$11 -> 0
A20: 2 | B20: 3 | C20: =IF(D19="","",IF(D19>$E$13,"",D19+1)) | K20: UW & Disbursal | N20: =N46 -> -0.014853157 | O20: =O46 -> -0.014853157 | P20: =P46 -> 0 | Q20: =Q46 -> 0 | R20: =R46 -> 0 | S20: =S46 -> 0 | T20: =N20/$E$15*12/$N$12 -> -0.0028060006 | U20: =N20/$E$11 -> -0.0017720201
A21: 3 | B21: 4 | K21: Collection & aftersale service | N21: =N49 -> -0.032348643 | O21: =O49 -> -0.030156657 | P21: =P49 -> -0.0021919861 | Q21: =Q49 -> 0 | R21: =R49 -> 0 | S21: =S49 -> 0 | T21: =N21/$E$15*12/$N$12 -> -0.0061111797 | U21: =N21/$E$11 -> -0.0038592768
A22: 4 | B22: 5 | K22: Support unit | N22: =N53 -> -0.28326871 | O22: =O53 -> -0.28326871 | P22: =P53 -> 0 | Q22: =Q53 -> 0 | R22: =R53 -> 0 | S22: =S53 -> 0 | T22: =N22/$E$15*12/$N$12 -> -0.053514022 | U22: =N22/$E$11 -> -0.03379469
A23: 5 | B23: 6 | K23: PBT | N23: =N13+N17+N18 -> -0.32749868 | O23: =O13+O17+O18 -> -0.29213131 | P23: =P13+P17+P18 -> -0.035367368 | Q23: =Q13+Q17+Q18 -> 0 | R23: =R13+R17+R18 -> 0 | S23: =S13+S17+S18 -> 0 | T23: =N23/$E$15*12/$N$12 -> -0.061869776 | U23: =N23/$E$11 -> -0.03907144
K24: In which: PROFIT BEFORE SU | N24: =N23-N22 -> -0.044229969 | O24: =O23-O22 -> -0.0088626013 | P24: =P23-P22 -> -0.035367368 | Q24: =Q23-Q22 -> 0 | R24: =R23-R22 -> 0 | S24: =S23-S22 -> 0 | T24: =N24/$E$15*12/$N$12 -> -0.0083557537 | U24: =N24/$E$11 -> -0.0052767498
B25: Early prepayment | C25: From | D25: To | E25: Penalty fee | F25: Penalty IR | G25: %Attrition
B26: Not Active rate | C26: 0 | D26: 0 | G26: =DATA!B20 -> 0.05 | H26: per cohort
B27: Attrition rate | C27: =IF(D26="","",IF(D26>$E$13,"",D26+1)) -> 1 | D27: 1 | G27: =DATA!B21 -> 0.1 | H27: per cohort | K27: PERFORMANCE OUTPUT | U27: Cur: mVND
C28: =IF(D27="","",IF(D27>$E$13,"",D27+1)) -> 2 | D28: =E13 -> 9 | G28: =DATA!B22 -> 0.03 | H28: per cohort
C29: =IF(D28="","",IF(D28>$E$13,"",D28+1)) -> 10 | N29: Life time | O29: Year 1 | P29: Year 2 | Q29: Year 3 | R29: Year 4 | S29: Year 5 | T29: % ANR | U29: % Disbursement
C30: =IF(D29="","",IF(D29>$E$13,"",D29+1)) | E30: =IF(D30="",0,SUMIFS(#REF!,#REF!,Leadsheet!G$24,#REF!,Leadsheet!$A31,#REF!,Leadsheet!$C$4,#REF!,Leadsheet!$G$5,#REF!,Leadsheet!$D$5,#REF!,Leadsheet!G4)) -> 0 | F30: 0 | K30: ANR | N30: =SUM(SAP_Speadsheet!$E$43:$BG$43)/COUNTIF(SAP_Speadsheet!$E$43:$BG$43,">0") -> 4.2346839 | O30: =IFERROR(SUM(SAP_Speadsheet!$E$43:$Q$43)/COUNTIF(SAP_Speadsheet!$E$43:$Q$43,">0"),0) -> 4.9448101 | P30: =IFERROR(SUM(SAP_Speadsheet!$R$43:$AC$43)/COUNTIF(SAP_Speadsheet!$R$43:$AC$43,">0"),0) -> 1.3941789 | Q30: =IFERROR(SUM(SAP_Speadsheet!$AD$43:$AO$43)/COUNTIF(SAP_Speadsheet!$AD$43:$AO$43,">0"),0) -> 0 | R30: =IFERROR(SUM(SAP_Speadsheet!$AP$43:$BA$43)/COUNTIF(SAP_Speadsheet!$AP$43:$BA$43,">0"),0) -> 0 | S30: =IFERROR(SUM(SAP_Speadsheet!$BB$43:$BG$43)/COUNTIF(SAP_Speadsheet!$BB$43:$BG$43,">0"),0) -> 0 | U30: =N30/$E$11 -> 0.50520875
C31: =IF(D30="","",IF(D30>$E$13,"",D30+1)) | E31: =IF(D31="",0,SUMIFS(#REF!,#REF!,Leadsheet!G$24,#REF!,Leadsheet!$A32,#REF!,Leadsheet!$C$4,#REF!,Leadsheet!$G$5,#REF!,Leadsheet!$D$5,#REF!,Leadsheet!G4)) -> 0 | F31: 0 | K31: TOI | N31: =SUM(O31:S31) -> 1.321896 | O31: =SUM(SAP_Speadsheet!$F$48:$Q$48) -> 1.3450252 | P31: =SUM(SAP_Speadsheet!$R$48:$AC$48) -> -0.023129199 | Q31: =SUM(SAP_Speadsheet!$AD$48:$AO$48) -> 0 | R31: =SUM(SAP_Speadsheet!$AP$48:$BA$48) -> 0 | S31: =SUM(SAP_Speadsheet!$BB$48:$BG$48) -> 0 | T31: =N31/$E$15*12/$N$30 -> 0.24972745 | U31: =N31/$E$11 -> 0.15770562
K32: Net interest income | N32: =SUM(O32:S32) -> 1.1706535 | O32: =SUM(SAP_Speadsheet!$F$50:$Q$50) -> 1.1937827 | P32: =SUM(SAP_Speadsheet!$R$50:$AC$50) -> -0.023129199 | Q32: =SUM(SAP_Speadsheet!$AD$50:$AO$50) -> 0 | R32: =SUM(SAP_Speadsheet!$AP$50:$BA$50) -> 0 | S32: =SUM(SAP_Speadsheet!$BB$50:$BG$50) -> 0 | T32: =N32/$E$15*12/$N$30 -> 0.22115531 | U32: =N32/$E$11 -> 0.13966199
B33: Monthly fee | F33: per active account/month | K33: Interest income | N33: =SUM(O33:S33) -> 1.5219171 | O33: =SUM(SAP_Speadsheet!$F$51:$Q$51) -> 1.5219171 | P33: =SUM(SAP_Speadsheet!$R$51:$AC$51) -> 0 | Q33: =SUM(SAP_Speadsheet!$AD$51:$AO$51) -> 0 | R33: =SUM(SAP_Speadsheet!$AP$51:$BA$51) -> 0 | S33: =SUM(SAP_Speadsheet!$BB$51:$BG$51) -> 0 | T33: =N33/$E$15*12/$N$30 -> 0.28751465 | U33: =N33/$E$11 -> 0.18156864
B34: Loan grant fee | E34: =DATA!C7 -> 0.1512425 | F34: per account | K34: Cost of fund | N34: =SUM(O34:S34) -> -0.35126355 | O34: =SUM(SAP_Speadsheet!$F$52:$Q$52) -> -0.32813435 | P34: =SUM(SAP_Speadsheet!$R$52:$AC$52) -> -0.023129199 | Q34: =SUM(SAP_Speadsheet!$AD$52:$AO$52) -> 0 | R34: =SUM(SAP_Speadsheet!$AP$52:$BA$52) -> 0 | S34: =SUM(SAP_Speadsheet!$BB$52:$BG$52) -> 0 | T34: =N34/$E$15*12/$N$30 -> -0.066359342 | U34: =N34/$E$11 -> -0.04190665
K35: Net fee income | N35: =SUM(O35:S35) -> 0.1512425 | O35: =SUM(SAP_Speadsheet!$F$54:$Q$54) -> 0.1512425 | P35: =SUM(SAP_Speadsheet!$R$54:$AC$54) -> 0 | Q35: =SUM(SAP_Speadsheet!$AD$54:$AO$54) -> 0 | R35: =SUM(SAP_Speadsheet!$AP$54:$BA$54) -> 0 | S35: =SUM(SAP_Speadsheet!$BB$54:$BG$54) -> 0 | T35: =N35/$E$15*12/$N$30 -> 0.028572145 | U35: =N35/$E$11 -> 0.018043622
B36: COST INPUT | H36: Cur: mVND | K36: Early termination fee | N36: =SUM(O36:S36) -> 0 | O36: =SUM(SAP_Speadsheet!$F$55:$Q$55) -> 0 | P36: =SUM(SAP_Speadsheet!$R$55:$AC$55) -> 0 | Q36: =SUM(SAP_Speadsheet!$AD$55:$AO$55) -> 0 | R36: =SUM(SAP_Speadsheet!$AP$55:$BA$55) -> 0 | S36: =SUM(SAP_Speadsheet!$BB$55:$BG$55) -> 0 | T36: =N36/$E$15*12/$N$30 -> 0 | U36: =N36/$E$11 -> 0
K37: Monthly fee | N37: =SUM(O37:S37) -> 0 | O37: =SUM(SAP_Speadsheet!$F$56:$Q$56) -> 0 | P37: =SUM(SAP_Speadsheet!$R$56:$AC$56) -> 0 | Q37: =SUM(SAP_Speadsheet!$AD$56:$AO$56) -> 0 | R37: =SUM(SAP_Speadsheet!$AP$56:$BA$56) -> 0 | S37: =SUM(SAP_Speadsheet!$BB$56:$BG$56) -> 0 | T37: =N37/$E$15*12/$N$30 -> 0 | U37: =N37/$E$11 -> 0
B38: Inflation rate | E38: 0.035 | F38: % per month | K38: Support fee | N38: =SUM(O38:S38) -> 0.1512425 | O38: =SUM(SAP_Speadsheet!$F$57:$Q$57) -> 0.1512425 | P38: =SUM(SAP_Speadsheet!$R$57:$AC$57) -> 0 | Q38: =SUM(SAP_Speadsheet!$AD$57:$AO$57) -> 0 | R38: =SUM(SAP_Speadsheet!$AP$57:$BA$57) -> 0 | S38: =SUM(SAP_Speadsheet!$BB$57:$BG$57) -> 0 | T38: =N38/$E$15*12/$N$30 -> 0.028572145 | U38: =N38/$E$11 -> 0.018043622
K39: Other income | N39: =SUM(O39:S39) -> 0 | O39: =SUM(SAP_Speadsheet!$F$59:$Q$59) -> 0 | P39: =SUM(SAP_Speadsheet!$R$59:$AC$59) -> 0 | Q39: =SUM(SAP_Speadsheet!$AD$59:$AO$59) -> 0 | R39: =SUM(SAP_Speadsheet!$AP$59:$BA$59) -> 0 | S39: =SUM(SAP_Speadsheet!$BB$59:$BG$59) -> 0 | T39: =N39/$E$15*12/$N$30 -> 0 | U39: =N39/$E$11 -> 0
B40: Acquisition cost | K40: PROVISION | N40: =SUM(O40:S40) -> -1.3189242 | O40: =SUM(SAP_Speadsheet!$F$171:$Q$171) -> -1.308878 | P40: =SUM(SAP_Speadsheet!$R$171:$AC$171) -> -0.010046183 | Q40: =SUM(SAP_Speadsheet!$AD$171:$AO$171) -> 0 | R40: =SUM(SAP_Speadsheet!$AP$171:$BA$171) -> 0 | S40: =SUM(SAP_Speadsheet!$BB$171:$BG$171) -> 0 | T40: =N40/$E$15*12/$N$30 -> -0.24916602 | U40: =N40/$E$11 -> -0.15735107
C41: Sale incentive | E41: Auto MODE | K41: OPEX | N41: =SUM(O41:S41) -> -0.33047051 | O41: =+SUM(O42,O46,O49,O53) -> -0.32827852 | P41: =+SUM(P42,P46,P49,P53) -> -0.0021919861 | Q41: =+SUM(Q42,Q46,Q49,Q53) -> 0 | R41: =+SUM(R42,R46,R49,R53) -> 0 | S41: =+SUM(S42,S46,S49,S53) -> 0 | T41: =N41/$E$15*12/$N$30 -> -0.062431203 | U41: =N41/$E$11 -> -0.039425987
C42: Sharing TOI and Risk DPD90+ | F42: % per month | K42: Acquisition cost | N42: =SUM(O42:S42) -> 0 | O42: =SUM(O43:O45) -> 0 | P42: =SUM(P43:P45) -> 0 | Q42: =SUM(Q43:Q45) -> 0 | R42: =SUM(R43:R45) -> 0 | S42: =SUM(S43:S45) -> 0 | T42: =N42/$E$15*12/$N$30 -> 0 | U42: =N42/$E$11 -> 0
C43: Sharing TOI and Risk DPD180+ | F43: % per month | K43: Lead Acquisition | N43: =SUM(O43:S43) -> 0 | O43: =SUM(SAP_Speadsheet!$F$64:$Q$64) -> 0 | P43: =SUM(SAP_Speadsheet!$R$64:$AC$64) -> 0 | Q43: =SUM(SAP_Speadsheet!$AD$64:$AO$64) -> 0 | R43: =SUM(SAP_Speadsheet!$AP$64:$BA$64) -> 0 | S43: =SUM(SAP_Speadsheet!$BB$64:$BG$64) -> 0 | T43: =N43/$E$15*12/$N$30 -> 0 | U43: =N43/$E$11 -> 0
E44: Adjust MODE | K44: Sharing performance | N44: =SUM(O44:S44) -> 0 | O44: =SUM(SAP_Speadsheet!$F$65:$Q$65) -> 0 | P44: =SUM(SAP_Speadsheet!$R$65:$AC$65) -> 0 | Q44: =SUM(SAP_Speadsheet!$AD$65:$AO$65) -> 0 | R44: =SUM(SAP_Speadsheet!$AP$65:$BA$65) -> 0 | S44: =SUM(SAP_Speadsheet!$BB$65:$BG$65) -> 0 | T44: =N44/$E$15*12/$N$30 -> 0 | U44: =N44/$E$11 -> 0
C45: Sharing CII (only) | F45: % per month | K45: Marketing | N45: =SUM(O45:S45) -> 0 | O45: =SUM(SAP_Speadsheet!$F$74:$Q$74) -> 0 | P45: =SUM(SAP_Speadsheet!$R$74:$AC$74) -> 0 | Q45: =SUM(SAP_Speadsheet!$AD$74:$AO$74) -> 0 | R45: =SUM(SAP_Speadsheet!$AP$74:$BA$74) -> 0 | S45: =SUM(SAP_Speadsheet!$BB$74:$BG$74) -> 0 | T45: =N45/$E$15*12/$N$30 -> 0 | U45: =N45/$E$11 -> 0
C46: Sharing COF (only) | F46: % per month | K46: UW & Disbursal | N46: =SUM(O46:S46) -> -0.014853157 | O46: =SUM(O47:O48) -> -0.014853157 | P46: =SUM(P47:P48) -> 0 | Q46: =SUM(Q47:Q48) -> 0 | R46: =SUM(R47:R48) -> 0 | S46: =SUM(S47:S48) -> 0 | T46: =N46/$E$15*12/$N$30 -> -0.0028060006 | U46: =N46/$E$11 -> -0.0017720201
C47: Sharing NFI (only) | F47: % per month | K47: Underwriting | N47: =SUM(O47:S47) -> -0.014026942 | O47: =SUM(SAP_Speadsheet!$F$77:$Q$77) -> -0.014026942 | P47: =SUM(SAP_Speadsheet!$R$77:$AC$77) -> 0 | Q47: =SUM(SAP_Speadsheet!$AD$77:$AO$77) -> 0 | R47: =SUM(SAP_Speadsheet!$AP$77:$BA$77) -> 0 | S47: =SUM(SAP_Speadsheet!$BB$77:$BG$77) -> 0 | T47: =N47/$E$15*12/$N$30 -> -0.0026499153 | U47: =N47/$E$11 -> -0.0016734505
C48: Sharing Risk DPD90+ (Only) | F48: % per month | K48: Disbursement | N48: =SUM(O48:S48) -> -0.00082621508 | O48: =SUM(SAP_Speadsheet!$F$78:$Q$78) -> -0.00082621508 | P48: =SUM(SAP_Speadsheet!$R$78:$AC$78) -> 0 | Q48: =SUM(SAP_Speadsheet!$AD$78:$AO$78) -> 0 | R48: =SUM(SAP_Speadsheet!$AP$78:$BA$78) -> 0 | S48: =SUM(SAP_Speadsheet!$BB$78:$BG$78) -> 0 | T48: =N48/$E$15*12/$N$30 -> -0.00015608534 | U48: =N48/$E$11 -> -9.8569597e-05
C49: Sharing Risk DPD180+ (only) | F49: % per month | K49: Collection & after sale service | N49: =SUM(O49:S49) -> -0.032348643 | O49: =SUM(O50:O52) -> -0.030156657 | P49: =SUM(P50:P52) -> -0.0021919861 | Q49: =SUM(Q50:Q52) -> 0 | R49: =SUM(R50:R52) -> 0 | S49: =SUM(S50:S52) -> 0 | T49: =N49/$E$15*12/$N$30 -> -0.0061111797 | U49: =N49/$E$11 -> -0.0038592768
K50: Early collections | N50: =SUM(O50:S50) -> -0.032298132 | O50: =SUM(SAP_Speadsheet!$F$84:$Q$84) -> -0.030106146 | P50: =SUM(SAP_Speadsheet!$R$84:$AC$84) -> -0.0021919861 | Q50: =SUM(SAP_Speadsheet!$AD$84:$AO$84) -> 0 | R50: =SUM(SAP_Speadsheet!$AP$84:$BA$84) -> 0 | S50: =SUM(SAP_Speadsheet!$BB$84:$BG$84) -> 0 | T50: =N50/$E$15*12/$N$30 -> -0.0061016373 | U50: =N50/$E$11 -> -0.0038532507
C51: Partner Lead Acquistion | F51: per account | K51: AMC | N51: =SUM(O51:S51) -> 0 | O51: =SUM(SAP_Speadsheet!$F$85:$Q$85) -> 0 | P51: =SUM(SAP_Speadsheet!$R$85:$AC$85) -> 0 | Q51: =SUM(SAP_Speadsheet!$AD$85:$AO$85) -> 0 | R51: =SUM(SAP_Speadsheet!$AP$85:$BA$85) -> 0 | S51: =SUM(SAP_Speadsheet!$BB$85:$BG$85) -> 0 | T51: =N51/$E$15*12/$N$30 -> 0 | U51: =N51/$E$11 -> 0
F52: per ticketsize | K52: Aftersale service | N52: =SUM(O52:S52) -> -5.0511138e-05 | O52: =SUM(SAP_Speadsheet!$F$87:$Q$87) -> -5.0511138e-05 | P52: =SUM(SAP_Speadsheet!$R$87:$AC$87) -> 0 | Q52: =SUM(SAP_Speadsheet!$AD$87:$AO$87) -> 0 | R52: =SUM(SAP_Speadsheet!$AP$87:$BA$87) -> 0 | S52: =SUM(SAP_Speadsheet!$BB$87:$BG$87) -> 0 | T52: =N52/$E$15*12/$N$30 -> -9.5423675e-06 | U52: =N52/$E$11 -> -6.0261094e-06
K53: Supporting Units | N53: =SUM(O53:S53) -> -0.28326871 | O53: =SUM(O54:O57) -> -0.28326871 | P53: =SUM(P54:P57) -> 0 | Q53: =SUM(Q54:Q57) -> 0 | R53: =SUM(R54:R57) -> 0 | S53: =SUM(S54:S57) -> 0 | T53: =N53/$E$15*12/$N$30 -> -0.053514022 | U53: =N53/$E$11 -> -0.03379469
C54: Marketing cost | K54: Direct HR | N54: =SUM(O54:S54) -> -0.05011634 | O54: =SUM(SAP_Speadsheet!$F$92:$Q$92) -> -0.05011634 | P54: =SUM(SAP_Speadsheet!$R$92:$AC$92) -> 0 | Q54: =SUM(SAP_Speadsheet!$AD$92:$AO$92) -> 0 | R54: =SUM(SAP_Speadsheet!$AP$92:$BA$92) -> 0 | S54: =SUM(SAP_Speadsheet!$BB$92:$BG$92) -> 0 | T54: =N54/$E$15*12/$N$30 -> -0.0094677839 | U54: =N54/$E$11 -> -0.005979009
K55: Indiect HR | N55: =SUM(O55:S55) -> -0.11901458 | O55: =SUM(SAP_Speadsheet!$F$93:$Q$93) -> -0.11901458 | P55: =SUM(SAP_Speadsheet!$R$93:$AC$93) -> 0 | Q55: =SUM(SAP_Speadsheet!$AD$93:$AO$93) -> 0 | R55: =SUM(SAP_Speadsheet!$AP$93:$BA$93) -> 0 | S55: =SUM(SAP_Speadsheet!$BB$93:$BG$93) -> 0 | T55: =N55/$E$15*12/$N$30 -> -0.022483772 | U55: =N55/$E$11 -> -0.014198748
C56: Marketing cost | F56: per account | K56: IT | N56: =SUM(O56:S56) -> -0.065689464 | O56: =SUM(SAP_Speadsheet!$F$94:$Q$94) -> -0.065689464 | P56: =SUM(SAP_Speadsheet!$R$94:$AC$94) -> 0 | Q56: =SUM(SAP_Speadsheet!$AD$94:$AO$94) -> 0 | R56: =SUM(SAP_Speadsheet!$AP$94:$BA$94) -> 0 | S56: =SUM(SAP_Speadsheet!$BB$94:$BG$94) -> 0 | T56: =N56/$E$15*12/$N$30 -> -0.012409798 | U56: =N56/$E$11 -> -0.007836923
K57: Other support units | N57: =SUM(O57:S57) -> -0.048448323 | O57: =SUM(SAP_Speadsheet!$F$95:$Q$95) -> -0.048448323 | P57: =SUM(SAP_Speadsheet!$R$95:$AC$95) -> 0 | Q57: =SUM(SAP_Speadsheet!$AD$95:$AO$95) -> 0 | R57: =SUM(SAP_Speadsheet!$AP$95:$BA$95) -> 0 | S57: =SUM(SAP_Speadsheet!$BB$95:$BG$95) -> 0 | T57: =N57/$E$15*12/$N$30 -> -0.0091526687 | U57: =N57/$E$11 -> -0.0057800103
B58: UW & Disbursal | C58: Underwriting cost & Score | E58: =DATA!C8*E61*E62 -> 0.001715028 | F58: of application | K58: PBT | N58: =SUM(O58:S58) -> -0.32749868 | O58: =SUM(SAP_Speadsheet!$F$177:$Q$177) -> -0.29213131 | P58: =SUM(SAP_Speadsheet!$R$177:$AC$177) -> -0.035367368 | Q58: =SUM(SAP_Speadsheet!$AD$177:$AO$177) -> 0 | R58: =SUM(SAP_Speadsheet!$AP$177:$BA$177) -> 0 | S58: =SUM(SAP_Speadsheet!$BB$177:$BG$177) -> 0 | T58: =N58/$E$15*12/$N$30 -> -0.061869776 | U58: =N58/$E$11 -> -0.03907144
C59: DOP cost | E59: 0 | F59: of account
C60: Disbursement cost | E60: =DATA!C9 -> 0.00082621508 | F60: of account
C61: Approval rate | E61: =DATA!C10 -> 0.14382507 | F61: of submitted application
C62: Disbursement rate | E62: =DATA!C11 -> 0.85010707 | F62: of aproved application
A64: Inflation
A66: Incentive | B66: Collection & AMC | C66: Collections_all | E66: =DATA!C12 -> 0.004036068 | F66: per account/month
A67: Sale team | C67: Collections_B1+ | F67: per account/month
A68: Sale Mgt | C68: AMC_principal collected | F68: per 1mVND collected amount
A69: MA | C69: AMC_interest collected | F69: per 1mVND collected amount
C70: AMC_penalty collected | F70: per 1mVND collected amount
B72: Aftersale service
C73: Email & SMS | E73: =DATA!C13 -> 7.6532027e-06 | F73: per account/month
B76: Supporting units | C76: Direct HR | E76: =DATA!C14 -> 0.0075933848 | F76: per account/month
C77: Indirect HR | E77: =DATA!C15 -> 0.018032513 | F77: per account/month
C78: IT | E78: =DATA!C16 -> 0.0099529491 | F78: per account/month
A79: CPCUW | C79: Other supports | E79: =DATA!C17 -> 0.0073406551 | F79: per account/month
A80: CPCUW_SCORE
A81: CPCCA
A82: Approval rate
B83: RISK INPUT
B85: Net flow | D85: NF | G85: PD | J85: Pro. Rate
D86: Nor_month | E86: Lastmonth | G86: Nor_month | H86: Lastmonth | J86: Nor_month | K86: Lastmonth
A87: AMC_PR | C87: B0 - B1 | D87: 0.021 | E87: 0.2 | G87: =PRODUCT(D87:D$100) -> 0.018680951 | H87: =PRODUCT(E87:E$100) -> 0.11791048 | J87: =G87*(1-$E$106)*(1-$E$107)*(1-$E$108)*(1-$E$109) -> 0.017406538 | K87: =H87*(1-$E$106)*(1-$E$107)*(1-$E$108)*(1-$E$109) -> 0.10986664
C88: B1 - B2 | D88: 0.95 | E88: 0.7 | G88: =PRODUCT(D88:D$100) -> 0.8895691 | H88: =PRODUCT(E88:E$100) -> 0.58955242 | J88: =G88*(1-$E$106)*(1-$E$107)*(1-$E$108)*(1-$E$109) -> 0.82888277 | K88: =H88*(1-$E$106)*(1-$E$107)*(1-$E$108)*(1-$E$109) -> 0.54933321
C89: B2 - B3 | D89: 0.97 | E89: 0.9 | G89: =PRODUCT(D89:D$100) -> 0.93638853 | H89: =PRODUCT(E89:E$100) -> 0.84221775 | J89: =G89*(1-$E$106)*(1-$E$107)*(1-$E$108)*(1-$E$109) -> 0.87250818 | K89: =H89*(1-$E$106)*(1-$E$107)*(1-$E$108)*(1-$E$109) -> 0.78476172
C90: B3 - B4 | D90: 0.98 | E90: 0.95 | G90: =PRODUCT(D90:D$100) -> 0.965349 | H90: =PRODUCT(E90:E$100) -> 0.9357975 | J90: =G90*(1-$E$106)*(1-$E$107)*(1-$E$108)*(1-$E$109) -> 0.89949297 | K90: =H90*(1-$E$106)*(1-$E$107)*(1-$E$108)*(1-$E$109) -> 0.87195747
C91: B4 - B5 | D91: 0.99 | E91: =D91 -> 0.99 | G91: =PRODUCT(D91:D$100) -> 0.98505 | H91: =PRODUCT(E91:E$100) -> 0.98505 | J91: =G91*(1-$E$106)*(1-$E$107)*(1-$E$108)*(1-$E$109) -> 0.91784997 | K91: =H91*(1-$E$106)*(1-$E$107)*(1-$E$108)*(1-$E$109) -> 0.91784997
C92: B5 - B6 | D92: 0.995 | E92: =D92 -> 0.995 | G92: =PRODUCT(D92:D$100) -> 0.995 | H92: =PRODUCT(E92:E$100) -> 0.995 | J92: =G92*(1-$E$106)*(1-$E$107)*(1-$E$108)*(1-$E$109) -> 0.92712118 | K92: =H92*(1-$E$106)*(1-$E$107)*(1-$E$108)*(1-$E$109) -> 0.92712118
C93: B6 - B7 | D93: 1 | E93: 1 | G93: =PRODUCT(D93:D$100) -> 1 | H93: =PRODUCT(E93:E$100) -> 1 | J93: =G93*(1-$E$106)*(1-$E$107)*(1-$E$108)*(1-$E$109) -> 0.93178008 | K93: =H93*(1-$E$106)*(1-$E$107)*(1-$E$108)*(1-$E$109) -> 0.93178008
C94: B7 - B8 | D94: 1 | E94: 1 | G94: =PRODUCT(D94:D$100) -> 1 | H94: =PRODUCT(E94:E$100) -> 1 | J94: =G94*(1-$E$106)*(1-$E$107)*(1-$E$108)*(1-$E$109) -> 0.93178008 | K94: =H94*(1-$E$106)*(1-$E$107)*(1-$E$108)*(1-$E$109) -> 0.93178008
C95: B8 - B9 | D95: 1 | E95: 1 | G95: =PRODUCT(D95:D$100) -> 1 | H95: =PRODUCT(E95:E$100) -> 1 | J95: =G95*(1-$E$107)*(1-$E$108)*(1-$E$109) -> 0.950796 | K95: =H95*(1-$E$107)*(1-$E$108)*(1-$E$109) -> 0.950796
C96: B9 - B10 | D96: 1 | E96: 1 | G96: =PRODUCT(D96:D$100) -> 1 | H96: =PRODUCT(E96:E$100) -> 1 | J96: =G96*(1-$E$107)*(1-$E$108)*(1-$E$109) -> 0.950796 | K96: =H96*(1-$E$107)*(1-$E$108)*(1-$E$109) -> 0.950796
C97: B10 - B11 | D97: 1 | E97: 1 | G97: =PRODUCT(D97:D$100) -> 1 | H97: =PRODUCT(E97:E$100) -> 1 | J97: =G97*(1-$E$107)*(1-$E$108)*(1-$E$109) -> 0.950796 | K97: =H97*(1-$E$107)*(1-$E$108)*(1-$E$109) -> 0.950796
C98: B11 - B12 | D98: 1 | E98: 1 | G98: =PRODUCT(D98:D$100) -> 1 | H98: =PRODUCT(E98:E$100) -> 1 | J98: =G98*(1-$E$107)*(1-$E$108)*(1-$E$109) -> 0.950796 | K98: =H98*(1-$E$107)*(1-$E$108)*(1-$E$109) -> 0.950796
C99: B12 - B13 | D99: 1 | E99: 1 | G99: =PRODUCT(D99:D$100) -> 1 | H99: =PRODUCT(E99:E$100) -> 1 | J99: =G99*(1-$E$107)*(1-$E$108)*(1-$E$109) -> 0.950796 | K99: =H99*(1-$E$107)*(1-$E$108)*(1-$E$109) -> 0.950796
C100: B13-B24 | J100: =(1-$E$107)*(1-$E$108)*(1-$E$109) -> 0.950796 | K100: =(1-$E$107)*(1-$E$108)*(1-$E$109) -> 0.950796
C101: B25-B36 | J101: =(1-$E$108)*(1-$E$109) -> 0.9702 | K101: =(1-$E$108)*(1-$E$109) -> 0.9702
C102: B36+ | J102: =(1-$E$109) -> 0.99 | K102: =(1-$E$109) -> 0.99
C103: Risk cost/ANR active | D103: =N40/E11 -> -0.15735107
C104: Riskcost/ANR | D104: =T40 -> -0.24916602
B106: Recovery rate | C106: B8- B12 | E106: 0.02
A107: Recovery rate B13-B24 | C107: B13-B24 | D107: Recovery rate B13-B24 | E107: 0.02
A108: Recovery rate B24-B36 | C108: B24-B36 | D108: Recovery rate B24-B36 | E108: 0.02
A109: Recovery rate B36+ | C109: B36+ | D109: Recovery rate B36+ | E109: 0.01
B111: %B1A/B1 | E111: =1-D88 -> 0.05

Sheet SAP_Speadsheet
B1: SAP Speadsheet
D3: Method
C4: Month on book | E4: 0 | F4: =E4+1 -> 1 | G4: =F4+1 -> 2 | H4: =G4+1 -> 3 | I4: =H4+1 -> 4 | J4: =I4+1 -> 5 | K4: =J4+1 -> 6 | L4: =K4+1 -> 7 | M4: =L4+1 -> 8 | ... BM4: =BL4+1 -> 60
C5: Oustanding tenor | E5: =IF(Leadsheet!$E$13-SAP_Speadsheet!E4<0,0,Leadsheet!$E$13-SAP_Speadsheet!E4) -> 9 | F5: =IF(Leadsheet!$E$13-SAP_Speadsheet!F4<0,0,Leadsheet!$E$13-SAP_Speadsheet!F4) -> 8 | G5: =IF(Leadsheet!$E$13-SAP_Speadsheet!G4<0,0,Leadsheet!$E$13-SAP_Speadsheet!G4) -> 7 | H5: =IF(Leadsheet!$E$13-SAP_Speadsheet!H4<0,0,Leadsheet!$E$13-SAP_Speadsheet!H4) -> 6 | I5: =IF(Leadsheet!$E$13-SAP_Speadsheet!I4<0,0,Leadsheet!$E$13-SAP_Speadsheet!I4) -> 5 | J5: =IF(Leadsheet!$E$13-SAP_Speadsheet!J4<0,0,Leadsheet!$E$13-SAP_Speadsheet!J4) -> 4 | K5: =IF(Leadsheet!$E$13-SAP_Speadsheet!K4<0,0,Leadsheet!$E$13-SAP_Speadsheet!K4) -> 3 | L5: =IF(Leadsheet!$E$13-SAP_Speadsheet!L4<0,0,Leadsheet!$E$13-SAP_Speadsheet!L4) -> 2 | ... BM5: =IF(Leadsheet!$E$13-SAP_Speadsheet!BM4<0,0,Leadsheet!$E$13-SAP_Speadsheet!BM4) -> 0
C6: Last month on book | D6: Nominal Tenor + Maturity to Termination | F6: =Leadsheet!E14+Leadsheet!E13 -> 15
B8: Balance
B9: Interest rate
C10: INR rate | D10: Input table | E10: =Leadsheet!E18 -> 0.34950821 | F10: =IF(F$4>$F$6,0,VLOOKUP(SAP_Speadsheet!F$4,Leadsheet!$C$18:$F$23,3,1)) -> 0.34950821 | G10: =IF(G$4>$F$6,0,VLOOKUP(SAP_Speadsheet!G$4,Leadsheet!$C$18:$F$23,3,1)) -> 0.34950821 | H10: =IF(H$4>$F$6,0,VLOOKUP(SAP_Speadsheet!H$4,Leadsheet!$C$18:$F$23,3,1)) -> 0.34950821 | I10: =IF(I$4>$F$6,0,VLOOKUP(SAP_Speadsheet!I$4,Leadsheet!$C$18:$F$23,3,1)) -> 0.34950821 | J10: =IF(J$4>$F$6,0,VLOOKUP(SAP_Speadsheet!J$4,Leadsheet!$C$18:$F$23,3,1)) -> 0.34950821 | K10: =IF(K$4>$F$6,0,VLOOKUP(SAP_Speadsheet!K$4,Leadsheet!$C$18:$F$23,3,1)) -> 0.34950821 | L10: =IF(L$4>$F$6,0,VLOOKUP(SAP_Speadsheet!L$4,Leadsheet!$C$18:$F$23,3,1)) -> 0.34950821 | M10: =IF(M$4>$F$6,0,VLOOKUP(SAP_Speadsheet!M$4,Leadsheet!$C$18:$F$23,3,1)) -> 0.34950821 | ... BM10: =IF(BM$4>$F$6,0,VLOOKUP(SAP_Speadsheet!BM$4,Leadsheet!$C$18:$F$23,3,1)) -> 0
C11: COF rate (indue) | D11: Input table | E11: =Leadsheet!F18 -> 0.066359342 | F11: =IF(F$4>$F$6,0,VLOOKUP(SAP_Speadsheet!F$4,Leadsheet!$C$18:$F$23,4,1)) -> 0.066359342 | G11: =IF(G$4>$F$6,0,VLOOKUP(SAP_Speadsheet!G$4,Leadsheet!$C$18:$F$23,4,1)) -> 0.066359342 | H11: =IF(H$4>$F$6,0,VLOOKUP(SAP_Speadsheet!H$4,Leadsheet!$C$18:$F$23,4,1)) -> 0.066359342 | I11: =IF(I$4>$F$6,0,VLOOKUP(SAP_Speadsheet!I$4,Leadsheet!$C$18:$F$23,4,1)) -> 0.066359342 | J11: =IF(J$4>$F$6,0,VLOOKUP(SAP_Speadsheet!J$4,Leadsheet!$C$18:$F$23,4,1)) -> 0.066359342 | K11: =IF(K$4>$F$6,0,VLOOKUP(SAP_Speadsheet!K$4,Leadsheet!$C$18:$F$23,4,1)) -> 0.066359342 | L11: =IF(L$4>$F$6,0,VLOOKUP(SAP_Speadsheet!L$4,Leadsheet!$C$18:$F$23,4,1)) -> 0.066359342 | M11: =IF(M$4>$F$6,0,VLOOKUP(SAP_Speadsheet!M$4,Leadsheet!$C$18:$F$23,4,1)) -> 0.066359342 | ... BM11: =IF(BM$4>$F$6,0,VLOOKUP(SAP_Speadsheet!BM$4,Leadsheet!$C$18:$F$23,4,1)) -> 0
C12: COF rate(overdue) | E12: =IF(E4>$F$6,0,Leadsheet!$F$19) -> 0.066359342 | F12: =IF(F4>$F$6,0,Leadsheet!$F$19) -> 0.066359342 | G12: =IF(G4>$F$6,0,Leadsheet!$F$19) -> 0.066359342 | H12: =IF(H4>$F$6,0,Leadsheet!$F$19) -> 0.066359342 | I12: =IF(I4>$F$6,0,Leadsheet!$F$19) -> 0.066359342 | J12: =IF(J4>$F$6,0,Leadsheet!$F$19) -> 0.066359342 | K12: =IF(K4>$F$6,0,Leadsheet!$F$19) -> 0.066359342 | L12: =IF(L4>$F$6,0,Leadsheet!$F$19) -> 0.066359342 | ... AC12: =IF(AC4>$F$6,0,Leadsheet!$F$19) -> 0
C13: Attrition rate | D13: Input table | E13: =IF(E$4<Leadsheet!$E$13,VLOOKUP(SAP_Speadsheet!E$4,Leadsheet!$C$26:$G$30,5,1),0) -> 0.05 | F13: =IF(F$4<Leadsheet!$E$13,VLOOKUP(SAP_Speadsheet!F$4,Leadsheet!$C$26:$G$30,5,1),0) -> 0.1 | G13: =IF(G$4<Leadsheet!$E$13,VLOOKUP(SAP_Speadsheet!G$4,Leadsheet!$C$26:$G$30,5,1),0) -> 0.03 | H13: =IF(H$4<Leadsheet!$E$13,VLOOKUP(SAP_Speadsheet!H$4,Leadsheet!$C$26:$G$30,5,1),0) -> 0.03 | I13: =IF(I$4<Leadsheet!$E$13,VLOOKUP(SAP_Speadsheet!I$4,Leadsheet!$C$26:$G$30,5,1),0) -> 0.03 | J13: =IF(J$4<Leadsheet!$E$13,VLOOKUP(SAP_Speadsheet!J$4,Leadsheet!$C$26:$G$30,5,1),0) -> 0.03 | K13: =IF(K$4<Leadsheet!$E$13,VLOOKUP(SAP_Speadsheet!K$4,Leadsheet!$C$26:$G$30,5,1),0) -> 0.03 | L13: =IF(L$4<Leadsheet!$E$13,VLOOKUP(SAP_Speadsheet!L$4,Leadsheet!$C$26:$G$30,5,1),0) -> 0.03 | ... BM13: =IF(BM$4<Leadsheet!$E$13,VLOOKUP(SAP_Speadsheet!BM$4,Leadsheet!$C$26:$G$30,5,1),0) -> 0
C14: Prepayment Penalty | D14: Input table | E14: =IF(E$4<Leadsheet!$E$13,VLOOKUP(SAP_Speadsheet!E$4,Leadsheet!$C$26:$F$30,3,1),0) -> 0 | F14: =IF(F$4<Leadsheet!$E$13,VLOOKUP(SAP_Speadsheet!F$4,Leadsheet!$C$26:$F$30,3,1),0) -> 0 | G14: =IF(G$4<Leadsheet!$E$13,VLOOKUP(SAP_Speadsheet!G$4,Leadsheet!$C$26:$F$30,3,1),0) -> 0 | H14: =IF(H$4<Leadsheet!$E$13,VLOOKUP(SAP_Speadsheet!H$4,Leadsheet!$C$26:$F$30,3,1),0) -> 0 | I14: =IF(I$4<Leadsheet!$E$13,VLOOKUP(SAP_Speadsheet!I$4,Leadsheet!$C$26:$F$30,3,1),0) -> 0 | J14: =IF(J$4<Leadsheet!$E$13,VLOOKUP(SAP_Speadsheet!J$4,Leadsheet!$C$26:$F$30,3,1),0) -> 0 | K14: =IF(K$4<Leadsheet!$E$13,VLOOKUP(SAP_Speadsheet!K$4,Leadsheet!$C$26:$F$30,3,1),0) -> 0 | L14: =IF(L$4<Leadsheet!$E$13,VLOOKUP(SAP_Speadsheet!L$4,Leadsheet!$C$26:$F$30,3,1),0) -> 0 | ... BM14: =IF(BM$4<Leadsheet!$E$13,VLOOKUP(SAP_Speadsheet!BM$4,Leadsheet!$C$26:$F$30,3,1),0) -> 0
B16: BRM | C16: Account accumulated | D16: Tỉ lệ khoản vay còn tồn tại | E16: =100%-E13 -> 0.95 | F16: =IF(F4>$F$6,0,E16-F13) -> 0.85 | G16: =IF(G4>$F$6,0,F16-G13) -> 0.82 | H16: =IF(H4>$F$6,0,G16-H13) -> 0.79 | I16: =IF(I4>$F$6,0,H16-I13) -> 0.76 | J16: =IF(J4>$F$6,0,I16-J13) -> 0.73 | K16: =IF(K4>$F$6,0,J16-K13) -> 0.7 | L16: =IF(L4>$F$6,0,K16-L13) -> 0.67 | M16: =IF(M4>$F$6,0,L16-M13) -> 0.64 | ... BM16: =IF(BM4>$F$6,0,BL16-BM13) -> 0
A18: SBV | B18: Overdue | C18: Balance by Bucket/Group
A19: G1 | B19: 0 | C19: B0 | E19: =E37 -> 7.9629455 | F19: =IF(F4>=Leadsheet!$E$13,0,F37-SUM(F20:F33)) -> 6.9575188 | G19: =IF(G4>=Leadsheet!$E$13,0,G37-SUM(G20:G33)) -> 6.5683106 | H19: =IF(H4>=Leadsheet!$E$13,0,H37-SUM(H20:H33)) -> 6.1909859 | I19: =IF(I4>=Leadsheet!$E$13,0,I37-SUM(I20:I33)) -> 5.8236564 | J19: =IF(J4>=Leadsheet!$E$13,0,J37-SUM(J20:J33)) -> 5.4645328 | K19: =IF(K4>=Leadsheet!$E$13,0,K37-SUM(K20:K33)) -> 5.1127454 | L19: =IF(L4>=Leadsheet!$E$13,0,L37-SUM(L20:L33)) -> 4.7674344 | M19: =IF(M4>=Leadsheet!$E$13,0,M37-SUM(M20:M33)) -> 4.4285404 | ... BM19: =IF(BM4>=Leadsheet!$E$13,0,BM37-SUM(BM20:BM33)) -> 0
A20: G2 | B20: 30 | C20: B1 | F20: =IF(F$4>$F$6,0,E19*IF(F$5>=1,Leadsheet!$D87,Leadsheet!$E87)) -> 0.16722186 | G20: =IF(G$4>$F$6,0,F19*IF(G$5>=1,Leadsheet!$D87,Leadsheet!$E87)) -> 0.1461079 | H20: =IF(H$4>$F$6,0,G19*IF(H$5>=1,Leadsheet!$D87,Leadsheet!$E87)) -> 0.13793452 | I20: =IF(I$4>$F$6,0,H19*IF(I$5>=1,Leadsheet!$D87,Leadsheet!$E87)) -> 0.1300107 | J20: =IF(J$4>$F$6,0,I19*IF(J$5>=1,Leadsheet!$D87,Leadsheet!$E87)) -> 0.12229678 | K20: =IF(K$4>$F$6,0,J19*IF(K$5>=1,Leadsheet!$D87,Leadsheet!$E87)) -> 0.11475519 | L20: =IF(L$4>$F$6,0,K19*IF(L$5>=1,Leadsheet!$D87,Leadsheet!$E87)) -> 0.10736765 | M20: =IF(M$4>$F$6,0,L19*IF(M$5>=1,Leadsheet!$D87,Leadsheet!$E87)) -> 0.10011612 | ... AC20: =IF(AC$4>$F$6,0,AB19*IF(AC$5>=1,Leadsheet!$D87,Leadsheet!$E87)) -> 0 | AD20: =IF(AD$4>$F$6,0,AC19*Leadsheet!$D87) -> 0 | AE20: =IF(AE$4>$F$6,0,AD19*Leadsheet!$D87) -> 0 | AF20: =IF(AF$4>$F$6,0,AE19*Leadsheet!$D87) -> 0 | AG20: =IF(AG$4>$F$6,0,AF19*Leadsheet!$D87) -> 0 | AH20: =IF(AH$4>$F$6,0,AG19*Leadsheet!$D87) -> 0 | AI20: =IF(AI$4>$F$6,0,AH19*Leadsheet!$D87) -> 0 | AJ20: =IF(AJ$4>$F$6,0,AI19*Leadsheet!$D87) -> 0 | AK20: =IF(AK$4>$F$6,0,AJ19*Leadsheet!$D87) -> 0 | ... BM20: =IF(BM$4>$F$6,0,BL19*Leadsheet!$D87) -> 0
A21: G2 | B21: 60 | C21: B2 | F21: =IF(F$4>$F$6,0,E20*IF(F$5>=1,Leadsheet!$D88,Leadsheet!$E88)) -> 0 | G21: =IF(G$4>$F$6,0,F20*IF(G$5>=1,Leadsheet!$D88,Leadsheet!$E88)) -> 0.15886076 | H21: =IF(H$4>$F$6,0,G20*IF(H$5>=1,Leadsheet!$D88,Leadsheet!$E88)) -> 0.1388025 | I21: =IF(I$4>$F$6,0,H20*IF(I$5>=1,Leadsheet!$D88,Leadsheet!$E88)) -> 0.1310378 | J21: =IF(J$4>$F$6,0,I20*IF(J$5>=1,Leadsheet!$D88,Leadsheet!$E88)) -> 0.12351017 | K21: =IF(K$4>$F$6,0,J20*IF(K$5>=1,Leadsheet!$D88,Leadsheet!$E88)) -> 0.11618195 | L21: =IF(L$4>$F$6,0,K20*IF(L$5>=1,Leadsheet!$D88,Leadsheet!$E88)) -> 0.10901743 | M21: =IF(M$4>$F$6,0,L20*IF(M$5>=1,Leadsheet!$D88,Leadsheet!$E88)) -> 0.10199927 | ... AC21: =IF(AC$4>$F$6,0,AB20*IF(AC$5>=1,Leadsheet!$D88,Leadsheet!$E88)) -> 0 | AD21: =IF(AD$4>$F$6,0,AC20*Leadsheet!$D88) -> 0 | AE21: =IF(AE$4>$F$6,0,AD20*Leadsheet!$D88) -> 0 | AF21: =IF(AF$4>$F$6,0,AE20*Leadsheet!$D88) -> 0 | AG21: =IF(AG$4>$F$6,0,AF20*Leadsheet!$D88) -> 0 | AH21: =IF(AH$4>$F$6,0,AG20*Leadsheet!$D88) -> 0 | AI21: =IF(AI$4>$F$6,0,AH20*Leadsheet!$D88) -> 0 | AJ21: =IF(AJ$4>$F$6,0,AI20*Leadsheet!$D88) -> 0 | AK21: =IF(AK$4>$F$6,0,AJ20*Leadsheet!$D88) -> 0 | ... BM21: =IF(BM$4>$F$6,0,BL20*Leadsheet!$D88) -> 0
A22: G2 | B22: 90 | C22: B3 | F22: =IF(F$4>$F$6,0,E21*IF(F$5>=1,Leadsheet!$D89,Leadsheet!$E89)) -> 0 | G22: =IF(G$4>$F$6,0,F21*IF(G$5>=1,Leadsheet!$D89,Leadsheet!$E89)) -> 0 | H22: =IF(H$4>$F$6,0,G21*IF(H$5>=1,Leadsheet!$D89,Leadsheet!$E89)) -> 0.15409494 | I22: =IF(I$4>$F$6,0,H21*IF(I$5>=1,Leadsheet!$D89,Leadsheet!$E89)) -> 0.13463843 | J22: =IF(J$4>$F$6,0,I21*IF(J$5>=1,Leadsheet!$D89,Leadsheet!$E89)) -> 0.12710666 | K22: =IF(K$4>$F$6,0,J21*IF(K$5>=1,Leadsheet!$D89,Leadsheet!$E89)) -> 0.11980486 | L22: =IF(L$4>$F$6,0,K21*IF(L$5>=1,Leadsheet!$D89,Leadsheet!$E89)) -> 0.11269649 | M22: =IF(M$4>$F$6,0,L21*IF(M$5>=1,Leadsheet!$D89,Leadsheet!$E89)) -> 0.10574691 | ... AC22: =IF(AC$4>$F$6,0,AB21*IF(AC$5>=1,Leadsheet!$D89,Leadsheet!$E89)) -> 0 | AD22: =IF(AD$4>$F$6,0,AC21*Leadsheet!$D89) -> 0 | AE22: =IF(AE$4>$F$6,0,AD21*Leadsheet!$D89) -> 0 | AF22: =IF(AF$4>$F$6,0,AE21*Leadsheet!$D89) -> 0 | AG22: =IF(AG$4>$F$6,0,AF21*Leadsheet!$D89) -> 0 | AH22: =IF(AH$4>$F$6,0,AG21*Leadsheet!$D89) -> 0 | AI22: =IF(AI$4>$F$6,0,AH21*Leadsheet!$D89) -> 0 | AJ22: =IF(AJ$4>$F$6,0,AI21*Leadsheet!$D89) -> 0 | AK22: =IF(AK$4>$F$6,0,AJ21*Leadsheet!$D89) -> 0 | ... AV22: =IF(AV$4>$F$6,0,AU21*Leadsheet!$D89) -> 0 | AW22: 0 | AX22: =IF(AX$4>$F$6,0,AW21*Leadsheet!$D89) -> 0 | AY22: =IF(AY$4>$F$6,0,AX21*Leadsheet!$D89) -> 0 | AZ22: =IF(AZ$4>$F$6,0,AY21*Leadsheet!$D89) -> 0 | BA22: =IF(BA$4>$F$6,0,AZ21*Leadsheet!$D89) -> 0 | BB22: =IF(BB$4>$F$6,0,BA21*Leadsheet!$D89) -> 0 | BC22: =IF(BC$4>$F$6,0,BB21*Leadsheet!$D89) -> 0 | BD22: =IF(BD$4>$F$6,0,BC21*Leadsheet!$D89) -> 0 | BE22: =IF(BE$4>$F$6,0,BD21*Leadsheet!$D89) -> 0 | ... BM22: =IF(BM$4>$F$6,0,BL21*Leadsheet!$D89) -> 0
A23: G3 | B23: 120 | C23: B4 | F23: =IF(F$4>$F$6,0,E22*IF(F$5>=1,Leadsheet!$D90,Leadsheet!$E90)) -> 0 | G23: =IF(G$4>$F$6,0,F22*IF(G$5>=1,Leadsheet!$D90,Leadsheet!$E90)) -> 0 | H23: =IF(H$4>$F$6,0,G22*IF(H$5>=1,Leadsheet!$D90,Leadsheet!$E90)) -> 0 | I23: =IF(I$4>$F$6,0,H22*IF(I$5>=1,Leadsheet!$D90,Leadsheet!$E90)) -> 0.15101304 | J23: =IF(J$4>$F$6,0,I22*IF(J$5>=1,Leadsheet!$D90,Leadsheet!$E90)) -> 0.13194566 | K23: =IF(K$4>$F$6,0,J22*IF(K$5>=1,Leadsheet!$D90,Leadsheet!$E90)) -> 0.12456453 | L23: =IF(L$4>$F$6,0,K22*IF(L$5>=1,Leadsheet!$D90,Leadsheet!$E90)) -> 0.11740877 | M23: =IF(M$4>$F$6,0,L22*IF(M$5>=1,Leadsheet!$D90,Leadsheet!$E90)) -> 0.11044256 | ... AC23: =IF(AC$4>$F$6,0,AB22*IF(AC$5>=1,Leadsheet!$D90,Leadsheet!$E90)) -> 0 | AD23: =IF(AD$4>$F$6,0,AC22*Leadsheet!$D90) -> 0 | AE23: =IF(AE$4>$F$6,0,AD22*Leadsheet!$D90) -> 0 | AF23: =IF(AF$4>$F$6,0,AE22*Leadsheet!$D90) -> 0 | AG23: =IF(AG$4>$F$6,0,AF22*Leadsheet!$D90) -> 0 | AH23: =IF(AH$4>$F$6,0,AG22*Leadsheet!$D90) -> 0 | AI23: =IF(AI$4>$F$6,0,AH22*Leadsheet!$D90) -> 0 | AJ23: =IF(AJ$4>$F$6,0,AI22*Leadsheet!$D90) -> 0 | AK23: =IF(AK$4>$F$6,0,AJ22*Leadsheet!$D90) -> 0 | ... BM23: =IF(BM$4>$F$6,0,BL22*Leadsheet!$D90) -> 0
A24: G3 | B24: 150 | C24: B5 | F24: =IF(F$4>$F$6,0,E23*IF(F$5>=1,Leadsheet!$D91,Leadsheet!$E91)) -> 0 | G24: =IF(G$4>$F$6,0,F23*IF(G$5>=1,Leadsheet!$D91,Leadsheet!$E91)) -> 0 | H24: =IF(H$4>$F$6,0,G23*IF(H$5>=1,Leadsheet!$D91,Leadsheet!$E91)) -> 0 | I24: =IF(I$4>$F$6,0,H23*IF(I$5>=1,Leadsheet!$D91,Leadsheet!$E91)) -> 0 | J24: =IF(J$4>$F$6,0,I23*IF(J$5>=1,Leadsheet!$D91,Leadsheet!$E91)) -> 0.14950291 | K24: =IF(K$4>$F$6,0,J23*IF(K$5>=1,Leadsheet!$D91,Leadsheet!$E91)) -> 0.1306262 | L24: =IF(L$4>$F$6,0,K23*IF(L$5>=1,Leadsheet!$D91,Leadsheet!$E91)) -> 0.12331888 | M24: =IF(M$4>$F$6,0,L23*IF(M$5>=1,Leadsheet!$D91,Leadsheet!$E91)) -> 0.11623468 | ... AC24: =IF(AC$4>$F$6,0,AB23*IF(AC$5>=1,Leadsheet!$D91,Leadsheet!$E91)) -> 0 | AD24: =IF(AD$4>$F$6,0,AC23*Leadsheet!$D91) -> 0 | AE24: =IF(AE$4>$F$6,0,AD23*Leadsheet!$D91) -> 0 | AF24: =IF(AF$4>$F$6,0,AE23*Leadsheet!$D91) -> 0 | AG24: =IF(AG$4>$F$6,0,AF23*Leadsheet!$D91) -> 0 | AH24: =IF(AH$4>$F$6,0,AG23*Leadsheet!$D91) -> 0 | AI24: =IF(AI$4>$F$6,0,AH23*Leadsheet!$D91) -> 0 | AJ24: =IF(AJ$4>$F$6,0,AI23*Leadsheet!$D91) -> 0 | AK24: =IF(AK$4>$F$6,0,AJ23*Leadsheet!$D91) -> 0 | ... BM24: =IF(BM$4>$F$6,0,BL23*Leadsheet!$D91) -> 0
A25: G3 | B25: 180 | C25: B6 | F25: =IF(F$4>$F$6,0,E24*IF(F$5>=1,Leadsheet!$D92,Leadsheet!$E92)) -> 0 | G25: =IF(G$4>$F$6,0,F24*IF(G$5>=1,Leadsheet!$D92,Leadsheet!$E92)) -> 0 | H25: =IF(H$4>$F$6,0,G24*IF(H$5>=1,Leadsheet!$D92,Leadsheet!$E92)) -> 0 | I25: =IF(I$4>$F$6,0,H24*IF(I$5>=1,Leadsheet!$D92,Leadsheet!$E92)) -> 0 | J25: =IF(J$4>$F$6,0,I24*IF(J$5>=1,Leadsheet!$D92,Leadsheet!$E92)) -> 0 | K25: =IF(K$4>$F$6,0,J24*IF(K$5>=1,Leadsheet!$D92,Leadsheet!$E92)) -> 0.1487554 | L25: =IF(L$4>$F$6,0,K24*IF(L$5>=1,Leadsheet!$D92,Leadsheet!$E92)) -> 0.12997307 | M25: =IF(M$4>$F$6,0,L24*IF(M$5>=1,Leadsheet!$D92,Leadsheet!$E92)) -> 0.12270229 | ... AC25: =IF(AC$4>$F$6,0,AB24*IF(AC$5>=1,Leadsheet!$D92,Leadsheet!$E92)) -> 0 | AD25: =IF(AD$4>$F$6,0,AC24*Leadsheet!$D92) -> 0 | AE25: =IF(AE$4>$F$6,0,AD24*Leadsheet!$D92) -> 0 | AF25: =IF(AF$4>$F$6,0,AE24*Leadsheet!$D92) -> 0 | AG25: =IF(AG$4>$F$6,0,AF24*Leadsheet!$D92) -> 0 | AH25: =IF(AH$4>$F$6,0,AG24*Leadsheet!$D92) -> 0 | AI25: =IF(AI$4>$F$6,0,AH24*Leadsheet!$D92) -> 0 | AJ25: =IF(AJ$4>$F$6,0,AI24*Leadsheet!$D92) -> 0 | AK25: =IF(AK$4>$F$6,0,AJ24*Leadsheet!$D92) -> 0 | ... BM25: =IF(BM$4>$F$6,0,BL24*Leadsheet!$D92) -> 0
A26: G4 | B26: 210 | C26: B7 | F26: =IF(F$4>$F$6,0,E25*IF(F$5>=1,Leadsheet!$D93,Leadsheet!$E93)) -> 0 | G26: =IF(G$4>$F$6,0,F25*IF(G$5>=1,Leadsheet!$D93,Leadsheet!$E93)) -> 0 | H26: =IF(H$4>$F$6,0,G25*IF(H$5>=1,Leadsheet!$D93,Leadsheet!$E93)) -> 0 | I26: =IF(I$4>$F$6,0,H25*IF(I$5>=1,Leadsheet!$D93,Leadsheet!$E93)) -> 0 | J26: =IF(J$4>$F$6,0,I25*IF(J$5>=1,Leadsheet!$D93,Leadsheet!$E93)) -> 0 | K26: =IF(K$4>$F$6,0,J25*IF(K$5>=1,Leadsheet!$D93,Leadsheet!$E93)) -> 0 | L26: =IF(L$4>$F$6,0,K25*IF(L$5>=1,Leadsheet!$D93,Leadsheet!$E93)) -> 0.1487554 | M26: =IF(M$4>$F$6,0,L25*IF(M$5>=1,Leadsheet!$D93,Leadsheet!$E93)) -> 0.12997307 | ... AC26: =IF(AC$4>$F$6,0,AB25*IF(AC$5>=1,Leadsheet!$D93,Leadsheet!$E93)) -> 0 | AD26: =IF(AD$4>$F$6,0,AC25*Leadsheet!$D93) -> 0 | AE26: =IF(AE$4>$F$6,0,AD25*Leadsheet!$D93) -> 0 | AF26: =IF(AF$4>$F$6,0,AE25*Leadsheet!$D93) -> 0 | AG26: =IF(AG$4>$F$6,0,AF25*Leadsheet!$D93) -> 0 | AH26: =IF(AH$4>$F$6,0,AG25*Leadsheet!$D93) -> 0 | AI26: =IF(AI$4>$F$6,0,AH25*Leadsheet!$D93) -> 0 | AJ26: =IF(AJ$4>$F$6,0,AI25*Leadsheet!$D93) -> 0 | AK26: =IF(AK$4>$F$6,0,AJ25*Leadsheet!$D93) -> 0 | ... BM26: =IF(BM$4>$F$6,0,BL25*Leadsheet!$D93) -> 0
A27: G4 | B27: 240 | C27: B8 | F27: =IF(F$4>$F$6,0,E26*IF(F$5>=1,Leadsheet!$D94,Leadsheet!$E94)) -> 0 | G27: =IF(G$4>$F$6,0,F26*IF(G$5>=1,Leadsheet!$D94,Leadsheet!$E94)) -> 0 | H27: =IF(H$4>$F$6,0,G26*IF(H$5>=1,Leadsheet!$D94,Leadsheet!$E94)) -> 0 | I27: =IF(I$4>$F$6,0,H26*IF(I$5>=1,Leadsheet!$D94,Leadsheet!$E94)) -> 0 | J27: =IF(J$4>$F$6,0,I26*IF(J$5>=1,Leadsheet!$D94,Leadsheet!$E94)) -> 0 | K27: =IF(K$4>$F$6,0,J26*IF(K$5>=1,Leadsheet!$D94,Leadsheet!$E94)) -> 0 | L27: =IF(L$4>$F$6,0,K26*IF(L$5>=1,Leadsheet!$D94,Leadsheet!$E94)) -> 0 | M27: =IF(M$4>$F$6,0,L26*IF(M$5>=1,Leadsheet!$D94,Leadsheet!$E94)) -> 0.1487554 | ... AC27: =IF(AC$4>$F$6,0,AB26*IF(AC$5>=1,Leadsheet!$D94,Leadsheet!$E94)) -> 0 | AD27: =IF(AD$4>$F$6,0,AC26*Leadsheet!$D94) -> 0 | AE27: =IF(AE$4>$F$6,0,AD26*Leadsheet!$D94) -> 0 | AF27: =IF(AF$4>$F$6,0,AE26*Leadsheet!$D94) -> 0 | AG27: =IF(AG$4>$F$6,0,AF26*Leadsheet!$D94) -> 0 | AH27: =IF(AH$4>$F$6,0,AG26*Leadsheet!$D94) -> 0 | AI27: =IF(AI$4>$F$6,0,AH26*Leadsheet!$D94) -> 0 | AJ27: =IF(AJ$4>$F$6,0,AI26*Leadsheet!$D94) -> 0 | AK27: =IF(AK$4>$F$6,0,AJ26*Leadsheet!$D94) -> 0 | ... BM27: =IF(BM$4>$F$6,0,BL26*Leadsheet!$D94) -> 0
A28: G4 | B28: 270 | C28: B9 | F28: =IF(F$4>$F$6,0,E27*IF(F$5>=1,Leadsheet!$D95,Leadsheet!$E95)) -> 0 | G28: =IF(G$4>$F$6,0,F27*IF(G$5>=1,Leadsheet!$D95,Leadsheet!$E95)) -> 0 | H28: =IF(H$4>$F$6,0,G27*IF(H$5>=1,Leadsheet!$D95,Leadsheet!$E95)) -> 0 | I28: =IF(I$4>$F$6,0,H27*IF(I$5>=1,Leadsheet!$D95,Leadsheet!$E95)) -> 0 | J28: =IF(J$4>$F$6,0,I27*IF(J$5>=1,Leadsheet!$D95,Leadsheet!$E95)) -> 0 | K28: =IF(K$4>$F$6,0,J27*IF(K$5>=1,Leadsheet!$D95,Leadsheet!$E95)) -> 0 | L28: =IF(L$4>$F$6,0,K27*IF(L$5>=1,Leadsheet!$D95,Leadsheet!$E95)) -> 0 | M28: =IF(M$4>$F$6,0,L27*IF(M$5>=1,Leadsheet!$D95,Leadsheet!$E95)) -> 0 | ... AC28: =IF(AC$4>$F$6,0,AB27*IF(AC$5>=1,Leadsheet!$D95,Leadsheet!$E95)) -> 0 | AD28: =IF(AD$4>$F$6,0,AC27*Leadsheet!$D95) -> 0 | AE28: =IF(AE$4>$F$6,0,AD27*Leadsheet!$D95) -> 0 | AF28: =IF(AF$4>$F$6,0,AE27*Leadsheet!$D95) -> 0 | AG28: =IF(AG$4>$F$6,0,AF27*Leadsheet!$D95) -> 0 | AH28: =IF(AH$4>$F$6,0,AG27*Leadsheet!$D95) -> 0 | AI28: =IF(AI$4>$F$6,0,AH27*Leadsheet!$D95) -> 0 | AJ28: =IF(AJ$4>$F$6,0,AI27*Leadsheet!$D95) -> 0 | AK28: =IF(AK$4>$F$6,0,AJ27*Leadsheet!$D95) -> 0 | ... BM28: =IF(BM$4>$F$6,0,BL27*Leadsheet!$D95) -> 0
A29: G4 | B29: 300 | C29: B10 | F29: =IF(F$4>$F$6,0,E28*IF(F$5>=1,Leadsheet!$D96,Leadsheet!$E96)) -> 0 | G29: =IF(G$4>$F$6,0,F28*IF(G$5>=1,Leadsheet!$D96,Leadsheet!$E96)) -> 0 | H29: =IF(H$4>$F$6,0,G28*IF(H$5>=1,Leadsheet!$D96,Leadsheet!$E96)) -> 0 | I29: =IF(I$4>$F$6,0,H28*IF(I$5>=1,Leadsheet!$D96,Leadsheet!$E96)) -> 0 | J29: =IF(J$4>$F$6,0,I28*IF(J$5>=1,Leadsheet!$D96,Leadsheet!$E96)) -> 0 | K29: =IF(K$4>$F$6,0,J28*IF(K$5>=1,Leadsheet!$D96,Leadsheet!$E96)) -> 0 | L29: =IF(L$4>$F$6,0,K28*IF(L$5>=1,Leadsheet!$D96,Leadsheet!$E96)) -> 0 | M29: =IF(M$4>$F$6,0,L28*IF(M$5>=1,Leadsheet!$D96,Leadsheet!$E96)) -> 0 | ... AC29: =IF(AC$4>$F$6,0,AB28*IF(AC$5>=1,Leadsheet!$D96,Leadsheet!$E96)) -> 0 | AD29: =IF(AD$4>$F$6,0,AC28*Leadsheet!$D96) -> 0 | AE29: =IF(AE$4>$F$6,0,AD28*Leadsheet!$D96) -> 0 | AF29: =IF(AF$4>$F$6,0,AE28*Leadsheet!$D96) -> 0 | AG29: =IF(AG$4>$F$6,0,AF28*Leadsheet!$D96) -> 0 | AH29: =IF(AH$4>$F$6,0,AG28*Leadsheet!$D96) -> 0 | AI29: =IF(AI$4>$F$6,0,AH28*Leadsheet!$D96) -> 0 | AJ29: =IF(AJ$4>$F$6,0,AI28*Leadsheet!$D96) -> 0 | AK29: =IF(AK$4>$F$6,0,AJ28*Leadsheet!$D96) -> 0 | ... BM29: =IF(BM$4>$F$6,0,BL28*Leadsheet!$D96) -> 0
A30: G4 | B30: 330 | C30: B11 | F30: =IF(F$4>$F$6,0,E29*IF(F$5>=1,Leadsheet!$D97,Leadsheet!$E97)) -> 0 | G30: =IF(G$4>$F$6,0,F29*IF(G$5>=1,Leadsheet!$D97,Leadsheet!$E97)) -> 0 | H30: =IF(H$4>$F$6,0,G29*IF(H$5>=1,Leadsheet!$D97,Leadsheet!$E97)) -> 0 | I30: =IF(I$4>$F$6,0,H29*IF(I$5>=1,Leadsheet!$D97,Leadsheet!$E97)) -> 0 | J30: =IF(J$4>$F$6,0,I29*IF(J$5>=1,Leadsheet!$D97,Leadsheet!$E97)) -> 0 | K30: =IF(K$4>$F$6,0,J29*IF(K$5>=1,Leadsheet!$D97,Leadsheet!$E97)) -> 0 | L30: =IF(L$4>$F$6,0,K29*IF(L$5>=1,Leadsheet!$D97,Leadsheet!$E97)) -> 0 | M30: =IF(M$4>$F$6,0,L29*IF(M$5>=1,Leadsheet!$D97,Leadsheet!$E97)) -> 0 | ... AC30: =IF(AC$4>$F$6,0,AB29*IF(AC$5>=1,Leadsheet!$D97,Leadsheet!$E97)) -> 0 | AD30: =IF(AD$4>$F$6,0,AC29*Leadsheet!$D97) -> 0 | AE30: =IF(AE$4>$F$6,0,AD29*Leadsheet!$D97) -> 0 | AF30: =IF(AF$4>$F$6,0,AE29*Leadsheet!$D97) -> 0 | AG30: =IF(AG$4>$F$6,0,AF29*Leadsheet!$D97) -> 0 | AH30: =IF(AH$4>$F$6,0,AG29*Leadsheet!$D97) -> 0 | AI30: =IF(AI$4>$F$6,0,AH29*Leadsheet!$D97) -> 0 | AJ30: =IF(AJ$4>$F$6,0,AI29*Leadsheet!$D97) -> 0 | AK30: =IF(AK$4>$F$6,0,AJ29*Leadsheet!$D97) -> 0 | ... BM30: =IF(BM$4>$F$6,0,BL29*Leadsheet!$D97) -> 0
A31: G4 | B31: 360 | C31: B12 | F31: =IF(F$4>$F$6,0,E30*IF(F$5>=1,Leadsheet!$D98,Leadsheet!$E98)) -> 0 | G31: =IF(G$4>$F$6,0,F30*IF(G$5>=1,Leadsheet!$D98,Leadsheet!$E98)) -> 0 | H31: =IF(H$4>$F$6,0,G30*IF(H$5>=1,Leadsheet!$D98,Leadsheet!$E98)) -> 0 | I31: =IF(I$4>$F$6,0,H30*IF(I$5>=1,Leadsheet!$D98,Leadsheet!$E98)) -> 0 | J31: =IF(J$4>$F$6,0,I30*IF(J$5>=1,Leadsheet!$D98,Leadsheet!$E98)) -> 0 | K31: =IF(K$4>$F$6,0,J30*IF(K$5>=1,Leadsheet!$D98,Leadsheet!$E98)) -> 0 | L31: =IF(L$4>$F$6,0,K30*IF(L$5>=1,Leadsheet!$D98,Leadsheet!$E98)) -> 0 | M31: =IF(M$4>$F$6,0,L30*IF(M$5>=1,Leadsheet!$D98,Leadsheet!$E98)) -> 0 | ... AC31: =IF(AC$4>$F$6,0,AB30*IF(AC$5>=1,Leadsheet!$D98,Leadsheet!$E98)) -> 0 | AD31: =IF(AD$4>$F$6,0,AC30*Leadsheet!$D98) -> 0 | AE31: =IF(AE$4>$F$6,0,AD30*Leadsheet!$D98) -> 0 | AF31: =IF(AF$4>$F$6,0,AE30*Leadsheet!$D98) -> 0 | AG31: =IF(AG$4>$F$6,0,AF30*Leadsheet!$D98) -> 0 | AH31: =IF(AH$4>$F$6,0,AG30*Leadsheet!$D98) -> 0 | AI31: =IF(AI$4>$F$6,0,AH30*Leadsheet!$D98) -> 0 | AJ31: =IF(AJ$4>$F$6,0,AI30*Leadsheet!$D98) -> 0 | AK31: =IF(AK$4>$F$6,0,AJ30*Leadsheet!$D98) -> 0 | ... BM31: =IF(BM$4>$F$6,0,BL30*Leadsheet!$D98) -> 0
A32: G5 | B32: 390 | C32: B13 | F32: =IF(F$4>$F$6,0,E31*IF(F$5>=1,Leadsheet!$D99,Leadsheet!$E99)) -> 0 | G32: =IF(G$4>$F$6,0,F31*IF(G$5>=1,Leadsheet!$D99,Leadsheet!$E99)) -> 0 | H32: =IF(H$4>$F$6,0,G31*IF(H$5>=1,Leadsheet!$D99,Leadsheet!$E99)) -> 0 | I32: =IF(I$4>$F$6,0,H31*IF(I$5>=1,Leadsheet!$D99,Leadsheet!$E99)) -> 0 | J32: =IF(J$4>$F$6,0,I31*IF(J$5>=1,Leadsheet!$D99,Leadsheet!$E99)) -> 0 | K32: =IF(K$4>$F$6,0,J31*IF(K$5>=1,Leadsheet!$D99,Leadsheet!$E99)) -> 0 | L32: =IF(L$4>$F$6,0,K31*IF(L$5>=1,Leadsheet!$D99,Leadsheet!$E99)) -> 0 | M32: =IF(M$4>$F$6,0,L31*IF(M$5>=1,Leadsheet!$D99,Leadsheet!$E99)) -> 0 | ... AC32: =IF(AC$4>$F$6,0,AB31*IF(AC$5>=1,Leadsheet!$D99,Leadsheet!$E99)) -> 0 | AD32: =IF(AD$4>$F$6,0,AC31*Leadsheet!$D99) -> 0 | AE32: =IF(AE$4>$F$6,0,AD31*Leadsheet!$D99) -> 0 | AF32: =IF(AF$4>$F$6,0,AE31*Leadsheet!$D99) -> 0 | AG32: =IF(AG$4>$F$6,0,AF31*Leadsheet!$D99) -> 0 | AH32: =IF(AH$4>$F$6,0,AG31*Leadsheet!$D99) -> 0 | AI32: =IF(AI$4>$F$6,0,AH31*Leadsheet!$D99) -> 0 | AJ32: =IF(AJ$4>$F$6,0,AI31*Leadsheet!$D99) -> 0 | AK32: =IF(AK$4>$F$6,0,AJ31*Leadsheet!$D99) -> 0 | ... BM32: =IF(BM$4>$F$6,0,BL31*Leadsheet!$D99) -> 0
A33: G5 | B33: 420+ | C33: B14+ | F33: =IF(F$4>$F$6,0,E32+E33) -> 0 | G33: =IF(G$4>$F$6,0,F32+F33) -> 0 | H33: =IF(H$4>$F$6,0,G32+G33) -> 0 | I33: =IF(I$4>$F$6,0,H32+H33) -> 0 | J33: =IF(J$4>$F$6,0,I32+I33) -> 0 | K33: =IF(K$4>$F$6,0,J32+J33) -> 0 | L33: =IF(L$4>$F$6,0,K32+K33) -> 0 | M33: =IF(M$4>$F$6,0,L32+L33) -> 0 | ... AC33: =IF(AC$4>$F$6,0,AB32+AB33) -> 0 | AD33: =IF(AD4>$F$6,0,AC32+AC33) -> 0 | AE33: =IF(AE4>$F$6,0,AD32+AD33) -> 0 | AF33: =IF(AF4>$F$6,0,AE32+AE33) -> 0 | AG33: =IF(AG4>$F$6,0,AF32+AF33) -> 0 | AH33: =IF(AH4>$F$6,0,AG32+AG33) -> 0 | AI33: =IF(AI4>$F$6,0,AH32+AH33) -> 0 | AJ33: =IF(AJ4>$F$6,0,AI32+AI33) -> 0 | AK33: =IF(AK4>$F$6,0,AJ32+AJ33) -> 0 | ... BM33: =IF(BM4>$F$6,0,BL32+BL33) -> 0
B36: ENR
C37: Total bank | E37: =IF(E5>0,Leadsheet!$E$11*SAP_Speadsheet!E16,SUM(E20:E33)) -> 7.9629455 | F37: =IF(F5>0,Leadsheet!$E$11*SAP_Speadsheet!F16,SUM(F20:F33)) -> 7.1247407 | G37: =IF(G5>0,Leadsheet!$E$11*SAP_Speadsheet!G16,SUM(G20:G33)) -> 6.8732793 | H37: =IF(H5>0,Leadsheet!$E$11*SAP_Speadsheet!H16,SUM(H20:H33)) -> 6.6218178 | I37: =IF(I5>0,Leadsheet!$E$11*SAP_Speadsheet!I16,SUM(I20:I33)) -> 6.3703564 | J37: =IF(J5>0,Leadsheet!$E$11*SAP_Speadsheet!J16,SUM(J20:J33)) -> 6.1188949 | K37: =IF(K5>0,Leadsheet!$E$11*SAP_Speadsheet!K16,SUM(K20:K33)) -> 5.8674335 | L37: =IF(L5>0,Leadsheet!$E$11*SAP_Speadsheet!L16,SUM(L20:L33)) -> 5.6159721 | ... BM37: =IF(BM5>0,Leadsheet!$E$11*SAP_Speadsheet!BM16,SUM(BM20:BM33)) -> 0
C38: Outstanding balance | E38: {=IF(E4=$F$6,0,_xlfn.IFS(Leadsheet!$G$5="DPD360+",SUM(SAP_Speadsheet!E19:E32),Leadsheet!$G$5="DPD180+",SUM(SAP_Speadsheet!E19:E26)))} -> 7.9629455 | F38: {=IF(F4=$F$6,0,_xlfn.IFS(Leadsheet!$G$5="DPD360+",SUM(SAP_Speadsheet!F19:F32),Leadsheet!$G$5="DPD180+",SUM(SAP_Speadsheet!F19:F26)))} -> 7.1247407 | G38: {=IF(G4=$F$6,0,_xlfn.IFS(Leadsheet!$G$5="DPD360+",SUM(SAP_Speadsheet!G19:G32),Leadsheet!$G$5="DPD180+",SUM(SAP_Speadsheet!G19:G26)))} -> 6.8732793 | H38: {=IF(H4=$F$6,0,_xlfn.IFS(Leadsheet!$G$5="DPD360+",SUM(SAP_Speadsheet!H19:H32),Leadsheet!$G$5="DPD180+",SUM(SAP_Speadsheet!H19:H26)))} -> 6.6218178 | I38: {=IF(I4=$F$6,0,_xlfn.IFS(Leadsheet!$G$5="DPD360+",SUM(SAP_Speadsheet!I19:I32),Leadsheet!$G$5="DPD180+",SUM(SAP_Speadsheet!I19:I26)))} -> 6.3703564 | J38: {=IF(J4=$F$6,0,_xlfn.IFS(Leadsheet!$G$5="DPD360+",SUM(SAP_Speadsheet!J19:J32),Leadsheet!$G$5="DPD180+",SUM(SAP_Speadsheet!J19:J26)))} -> 6.1188949 | K38: {=IF(K4=$F$6,0,_xlfn.IFS(Leadsheet!$G$5="DPD360+",SUM(SAP_Speadsheet!K19:K32),Leadsheet!$G$5="DPD180+",SUM(SAP_Speadsheet!K19:K26)))} -> 5.8674335 | L38: {=IF(L4=$F$6,0,_xlfn.IFS(Leadsheet!$G$5="DPD360+",SUM(SAP_Speadsheet!L19:L32),Leadsheet!$G$5="DPD180+",SUM(SAP_Speadsheet!L19:L26)))} -> 5.6159721 | ... BM38: {=IF(BM4=$F$6,0,_xlfn.IFS(Leadsheet!$G$5="DPD360+",SUM(SAP_Speadsheet!BM19:BM32),Leadsheet!$G$5="DPD180+",SUM(SAP_Speadsheet!BM19:BM26)))} -> 0
C39: Writeoff balance | E39: =E37-E38 -> 0 | F39: =F37-F38 -> 0 | G39: =G37-G38 -> 0 | H39: =H37-H38 -> 0 | I39: =I37-I38 -> 0 | J39: =J37-J38 -> 0 | K39: =K37-K38 -> 0 | L39: =L37-L38 -> 0 | ... BM39: =BM37-BM38 -> 0
C40: Outstanding Bal/TB | E40: =IFERROR(E38/E37,"") -> 1 | F40: =IFERROR(F38/F37,"") -> 1 | G40: =IFERROR(G38/G37,"") -> 1 | H40: =IFERROR(H38/H37,"") -> 1 | I40: =IFERROR(I38/I37,"") -> 1 | J40: =IFERROR(J38/J37,"") -> 1 | K40: =IFERROR(K38/K37,"") -> 1 | L40: =IFERROR(L38/L37,"") -> 1 | ... BM40: =IFERROR(BM38/BM37,"")
B42: ANR
C43: Outstanding balance | D43: Average Balance Projected ENR (t and t-1) | F43: =IF(F4>$F$6,0,AVERAGE(E37:F37)) -> 7.5438431 | G43: =IF(G4>$F$6,0,AVERAGE(F37:G37)) -> 6.99901 | H43: =IF(H4>$F$6,0,AVERAGE(G37:H37)) -> 6.7475485 | I43: =IF(I4>$F$6,0,AVERAGE(H37:I37)) -> 6.4960871 | J43: =IF(J4>$F$6,0,AVERAGE(I37:J37)) -> 6.2446257 | K43: =IF(K4>$F$6,0,AVERAGE(J37:K37)) -> 5.9931642 | L43: =IF(L4>$F$6,0,AVERAGE(K37:L37)) -> 5.7417028 | M43: =IF(M4>$F$6,0,AVERAGE(L37:M37)) -> 5.4902414 | ... BM43: =IF(BM4>$F$6,0,AVERAGE(BL37:BM37)) -> 0
C44: ANR for CII (B0+B1A) | D44: Average Balance B0 only (t and t-1) | F44: =E19*(1-Leadsheet!$D$87)+E20*Leadsheet!$E$111 -> 7.7957236 | G44: =F19*(1-Leadsheet!$D$87)+F20*Leadsheet!$E$111 -> 6.819772 | H44: =G19*(1-Leadsheet!$D$87)+G20*Leadsheet!$E$111 -> 6.4376815 | I44: =H19*(1-Leadsheet!$D$87)+H20*Leadsheet!$E$111 -> 6.0678719 | J44: =I19*(1-Leadsheet!$D$87)+I20*Leadsheet!$E$111 -> 5.7078602 | K44: =J19*(1-Leadsheet!$D$87)+J20*Leadsheet!$E$111 -> 5.3558924 | L44: =K19*(1-Leadsheet!$D$87)+K20*Leadsheet!$E$111 -> 5.0111155 | M44: =L19*(1-Leadsheet!$D$87)+L20*Leadsheet!$E$111 -> 4.6726867 | ... BM44: =BL19*(1-Leadsheet!$D$87)+BL20*Leadsheet!$E$111 -> 0
B46: Performance
B48: TOI | F48: =F50+F54+F59 -> 0.33658125 | G48: =G50+G54+G59 -> 0.15992638 | H48: =H50+H54+H59 -> 0.1501883 | I48: =I50+I54+I59 -> 0.14080791 | J48: =J50+J54+J59 -> 0.13171289 | K48: =K50+K54+K59 -> 0.12285216 | L48: =L50+L54+L59 -> 0.11420086 | M48: =M50+M54+M59 -> 0.10573446 | ... BM48: =BM50+BM54+BM59 -> 0
C50: Net interest income | F50: =F51+F52 -> 0.18533874 | G50: =G51+G52 -> 0.15992638 | H50: =H51+H52 -> 0.1501883 | I50: =I51+I52 -> 0.14080791 | J50: =J51+J52 -> 0.13171289 | K50: =K51+K52 -> 0.12285216 | L50: =L51+L52 -> 0.11420086 | M50: =M51+M52 -> 0.10573446 | ... BM50: =BM51+BM52 -> 0
C51: Interest income | F51: =IFERROR(F$44*E$10/12,0) -> 0.22705578 | G51: =IFERROR(G$44*F$10/12,0) -> 0.19863052 | H51: =IFERROR(H$44*G$10/12,0) -> 0.18750188 | I51: =IFERROR(I$44*H$10/12,0) -> 0.17673092 | J51: =IFERROR(J$44*I$10/12,0) -> 0.16624533 | K51: =IFERROR(K$44*J$10/12,0) -> 0.15599403 | L51: =IFERROR(L$44*K$10/12,0) -> 0.14595217 | M51: =IFERROR(M$44*L$10/12,0) -> 0.13609519 | ... BM51: =IFERROR(BM$44*BL$10/12,0) -> 0
C52: Cost of fund | F52: =-IFERROR((F44*F11/12)+((F43-F44)*F12/12),0) -> -0.041717039 | G52: =-IFERROR((G44*G11/12)+((G43-G44)*G12/12),0) -> -0.038704141 | H52: =-IFERROR((H44*H11/12)+((H43-H44)*H12/12),0) -> -0.037313573 | I52: =-IFERROR((I44*I11/12)+((I43-I44)*I12/12),0) -> -0.035923006 | J52: =-IFERROR((J44*J11/12)+((J43-J44)*J12/12),0) -> -0.034532438 | K52: =-IFERROR((K44*K11/12)+((K43-K44)*K12/12),0) -> -0.03314187 | L52: =-IFERROR((L44*L11/12)+((L43-L44)*L12/12),0) -> -0.031751302 | M52: =-IFERROR((M44*M11/12)+((M43-M44)*M12/12),0) -> -0.030360734 | ... AC52: =-IFERROR((AC44*AC11/12)+((AC43-AC44)*AC12/12),0) -> 0 | AD52: =-IFERROR(AD43*AC11/12,0) -> 0 | AE52: =-IFERROR(AE43*AD11/12,0) -> 0 | AF52: =-IFERROR(AF43*AE11/12,0) -> 0 | AG52: =-IFERROR(AG43*AF11/12,0) -> 0 | AH52: =-IFERROR(AH43*AG11/12,0) -> 0 | AI52: =-IFERROR(AI43*AH11/12,0) -> 0 | AJ52: =-IFERROR(AJ43*AI11/12,0) -> 0 | AK52: =-IFERROR(AK43*AJ11/12,0) -> 0 | ... BM52: =-IFERROR(BM43*BL11/12,0) -> 0
C54: Net fee income | F54: =SUM(F55:F57) -> 0.1512425 | G54: =SUM(G55:G58) -> 0 | H54: =SUM(H55:H58) -> 0 | I54: =SUM(I55:I58) -> 0 | J54: =SUM(J55:J58) -> 0 | K54: =SUM(K55:K58) -> 0 | L54: =SUM(L55:L58) -> 0 | M54: =SUM(M55:M58) -> 0 | N54: =SUM(N55:N58) -> 0 | ... BM54: =SUM(BM55:BM58) -> 0
C55: Early termination fee | D55: Total Prepayment AMT * Eff.prepayment penalty rate
C56: Monthly fee | F56: =AVERAGE(E16:F16)*Leadsheet!$E$33 -> 0 | G56: =AVERAGE(F16:G16)*Leadsheet!$E$33 -> 0 | H56: =AVERAGE(G16:H16)*Leadsheet!$E$33 -> 0 | I56: =AVERAGE(H16:I16)*Leadsheet!$E$33 -> 0 | J56: =AVERAGE(I16:J16)*Leadsheet!$E$33 -> 0 | K56: =AVERAGE(J16:K16)*Leadsheet!$E$33 -> 0 | L56: =AVERAGE(K16:L16)*Leadsheet!$E$33 -> 0 | M56: =AVERAGE(L16:M16)*Leadsheet!$E$33 -> 0 | ... BM56: =AVERAGE(BL16:BM16)*Leadsheet!$E$33 -> 0
C57: Loan grant fee | F57: =Leadsheet!E34 -> 0.1512425
B59: Other Income | F59: =IF(F4=Leadsheet!$E$15,IF(Leadsheet!$G$4="VAS",SAP_Speadsheet!F168-SAP_Speadsheet!F133,0),0) -> 0 | G59: =IF(G4=Leadsheet!$E$15,IF(Leadsheet!$G$4="VAS",SAP_Speadsheet!G168-SAP_Speadsheet!G133,0),0) -> 0 | H59: =IF(H4=Leadsheet!$E$15,IF(Leadsheet!$G$4="VAS",SAP_Speadsheet!H168-SAP_Speadsheet!H133,0),0) -> 0 | I59: =IF(I4=Leadsheet!$E$15,IF(Leadsheet!$G$4="VAS",SAP_Speadsheet!I168-SAP_Speadsheet!I133,0),0) -> 0 | J59: =IF(J4=Leadsheet!$E$15,IF(Leadsheet!$G$4="VAS",SAP_Speadsheet!J168-SAP_Speadsheet!J133,0),0) -> 0 | K59: =IF(K4=Leadsheet!$E$15,IF(Leadsheet!$G$4="VAS",SAP_Speadsheet!K168-SAP_Speadsheet!K133,0),0) -> 0 | L59: =IF(L4=Leadsheet!$E$15,IF(Leadsheet!$G$4="VAS",SAP_Speadsheet!L168-SAP_Speadsheet!L133,0),0) -> 0 | M59: =IF(M4=Leadsheet!$E$15,IF(Leadsheet!$G$4="VAS",SAP_Speadsheet!M168-SAP_Speadsheet!M133,0),0) -> 0 | ... AC59: =IF(AC4=Leadsheet!$E$15,IF(Leadsheet!$G$4="VAS",SAP_Speadsheet!AC168-SAP_Speadsheet!AC133,0),0) -> 0 | AD59: =IF(AD4>$F$6,0,IF(Leadsheet!$G$5="DPD180+",SUM(SAP_Speadsheet!AC27:AC31)-SUM(SAP_Speadsheet!AD28:AD32),0)) -> 0 | AE59: =IF(AE4>$F$6,0,IF(Leadsheet!$G$5="DPD180+",SUM(SAP_Speadsheet!AD27:AD31)-SUM(SAP_Speadsheet!AE28:AE32),0)) -> 0 | AF59: =IF(AF4>$F$6,0,IF(Leadsheet!$G$5="DPD180+",SUM(SAP_Speadsheet!AE27:AE31)-SUM(SAP_Speadsheet!AF28:AF32),0)) -> 0 | AG59: =IF(AG4>$F$6,0,IF(Leadsheet!$G$5="DPD180+",SUM(SAP_Speadsheet!AF27:AF31)-SUM(SAP_Speadsheet!AG28:AG32),0)) -> 0 | AH59: =IF(AH4>$F$6,0,IF(Leadsheet!$G$5="DPD180+",SUM(SAP_Speadsheet!AG27:AG31)-SUM(SAP_Speadsheet!AH28:AH32),0)) -> 0 | AI59: =IF(AI4>$F$6,0,IF(Leadsheet!$G$5="DPD180+",SUM(SAP_Speadsheet!AH27:AH31)-SUM(SAP_Speadsheet!AI28:AI32),0)) -> 0 | AJ59: =IF(AJ4>$F$6,0,IF(Leadsheet!$G$5="DPD180+",SUM(SAP_Speadsheet!AI27:AI31)-SUM(SAP_Speadsheet!AJ28:AJ32),0)) -> 0 | AK59: =IF(AK4>$F$6,0,IF(Leadsheet!$G$5="DPD180+",SUM(SAP_Speadsheet!AJ27:AJ31)-SUM(SAP_Speadsheet!AK28:AK32),0)) -> 0 | ... BM59: =IF(BM4>$F$6,0,IF(Leadsheet!$G$5="DPD180+",SUM(SAP_Speadsheet!BL27:BL31)-SUM(SAP_Speadsheet!BM28:BM32),0)) -> 0
B62: VARIABLE EXPENSES | F62: =F63+F73+F76+F83+F87 -> -0.018693927 | G62: =G63+G73+G76+G83+G87 -> -0.0034369334 | H62: =H63+H73+H76+H83+H87 -> -0.0033156218 | I62: =I63+I73+I76+I83+I87 -> -0.0031943101 | J62: =J63+J73+J76+J83+J87 -> -0.0030729985 | K62: =K63+K73+K76+K83+K87 -> -0.0029516869 | L62: =L63+L73+L76+L83+L87 -> -0.0028303752 | M62: =M63+M73+M76+M83+M87 -> -0.0027090636 | ... BM62: =BM63+BM73+BM76+BM83+BM87 -> 0
B63: Sale incentive | F63: =F64+F65 -> 0 | G63: =G64+G65 -> 0 | H63: =H64+H65 -> 0 | I63: =I64+I65 -> 0 | J63: =J64+J65 -> 0 | K63: =K64+K65 -> 0 | L63: =L64+L65 -> 0 | M63: =M64+M65 -> 0 | ... BM63: =BM64+BM65 -> 0
C64: Lead Acquistion | F64: =-Leadsheet!E51-Leadsheet!E52*Leadsheet!E11 -> 0
C65: Sharing Performance | F65: =SUM(F66:F72) -> 0 | G65: =SUM(G66:G72) -> 0 | H65: =SUM(H66:H72) -> 0 | I65: =SUM(I66:I72) -> 0 | J65: =SUM(J66:J72) -> 0 | K65: =SUM(K66:K72) -> 0 | L65: =SUM(L66:L72) -> 0 | M65: =SUM(M66:M72) -> 0 | ... BM65: =SUM(BM66:BM72) -> 0
C66: Sharing CII (only) | F66: =-SUM(F51:F51)*Leadsheet!$E$45 -> 0 | G66: =-SUM(G51:G51)*Leadsheet!$E$45 -> 0 | H66: =-SUM(H51:H51)*Leadsheet!$E$45 -> 0 | I66: =-SUM(I51:I51)*Leadsheet!$E$45 -> 0 | J66: =-SUM(J51:J51)*Leadsheet!$E$45 -> 0 | K66: =-SUM(K51:K51)*Leadsheet!$E$45 -> 0 | L66: =-SUM(L51:L51)*Leadsheet!$E$45 -> 0 | M66: =-SUM(M51:M51)*Leadsheet!$E$45 -> 0 | ... BM66: =-SUM(BM51:BM51)*Leadsheet!$E$45 -> 0
C67: Sharing COF (only) | F67: =-F52*Leadsheet!$E$46 -> 0 | G67: =-G52*Leadsheet!$E$46 -> 0 | H67: =-H52*Leadsheet!$E$46 -> 0 | I67: =-I52*Leadsheet!$E$46 -> 0 | J67: =-J52*Leadsheet!$E$46 -> 0 | K67: =-K52*Leadsheet!$E$46 -> 0 | L67: =-L52*Leadsheet!$E$46 -> 0 | M67: =-M52*Leadsheet!$E$46 -> 0 | ... BM67: =-BM52*Leadsheet!$E$46 -> 0
C68: Sharing NFI (only) | F68: =-F54*Leadsheet!$E$47 -> 0 | G68: =-G54*Leadsheet!$E$47 -> 0 | H68: =-H54*Leadsheet!$E$47 -> 0 | I68: =-I54*Leadsheet!$E$47 -> 0 | J68: =-J54*Leadsheet!$E$47 -> 0 | K68: =-K54*Leadsheet!$E$47 -> 0 | L68: =-L54*Leadsheet!$E$47 -> 0 | M68: =-M54*Leadsheet!$E$47 -> 0 | ... BM68: =-BM54*Leadsheet!$E$47 -> 0
C69: Sharing Risk DPD90+ (Only) | F69: =IF(F4>$F$6,0,Leadsheet!$E$48*(F23-SUM(E23:E31)+SUM(F24:F32))) -> 0 | G69: =IF(G4>$F$6,0,Leadsheet!$E$48*(G23-SUM(F23:F31)+SUM(G24:G32))) -> 0 | H69: =IF(H4>$F$6,0,Leadsheet!$E$48*(H23-SUM(G23:G31)+SUM(H24:H32))) -> 0 | I69: =IF(I4>$F$6,0,Leadsheet!$E$48*(I23-SUM(H23:H31)+SUM(I24:I32))) -> 0 | J69: =IF(J4>$F$6,0,Leadsheet!$E$48*(J23-SUM(I23:I31)+SUM(J24:J32))) -> 0 | K69: =IF(K4>$F$6,0,Leadsheet!$E$48*(K23-SUM(J23:J31)+SUM(K24:K32))) -> 0 | L69: =IF(L4>$F$6,0,Leadsheet!$E$48*(L23-SUM(K23:K31)+SUM(L24:L32))) -> 0 | M69: =IF(M4>$F$6,0,Leadsheet!$E$48*(M23-SUM(L23:L31)+SUM(M24:M32))) -> 0 | ... BM69: =IF(BM4>$F$6,0,Leadsheet!$E$48*(BM23-SUM(BL23:BL31)+SUM(BM24:BM32))) -> 0
C70: Sharing Risk DPD180+ (only) | F70: =IF(F4>$F$6,0,Leadsheet!$E$49*(F26+SUM(E26:E31)-SUM(F27:F32))) -> 0 | G70: =IF(G4>$F$6,0,Leadsheet!$E$49*(G26+SUM(F26:F31)-SUM(G27:G32))) -> 0 | H70: =IF(H4>$F$6,0,Leadsheet!$E$49*(H26+SUM(G26:G31)-SUM(H27:H32))) -> 0 | I70: =IF(I4>$F$6,0,Leadsheet!$E$49*(I26+SUM(H26:H31)-SUM(I27:I32))) -> 0 | J70: =IF(J4>$F$6,0,Leadsheet!$E$49*(J26+SUM(I26:I31)-SUM(J27:J32))) -> 0 | K70: =IF(K4>$F$6,0,Leadsheet!$E$49*(K26+SUM(J26:J31)-SUM(K27:K32))) -> 0 | L70: =IF(L4>$F$6,0,Leadsheet!$E$49*(L26+SUM(K26:K31)-SUM(L27:L32))) -> 0 | M70: =IF(M4>$F$6,0,Leadsheet!$E$49*(M26+SUM(L26:L31)-SUM(M27:M32))) -> 0 | ... BM70: =IF(BM4>$F$6,0,Leadsheet!$E$49*(BM26+SUM(BL26:BL31)-SUM(BM27:BM32))) -> 0
C71: Sharing TOI+ Risk DPD90+ | F71: =IF(F4>$F$6,0,Leadsheet!$E$42*(-F48+F23-SUM(E23:E31)+SUM(F24:F32))) -> 0 | G71: =IF(G4>$F$6,0,Leadsheet!$E$42*(-G48+G23-SUM(F23:F31)+SUM(G24:G32))) -> 0 | H71: =IF(H4>$F$6,0,Leadsheet!$E$42*(-H48+H23-SUM(G23:G31)+SUM(H24:H32))) -> 0 | I71: =IF(I4>$F$6,0,Leadsheet!$E$42*(-I48+I23-SUM(H23:H31)+SUM(I24:I32))) -> 0 | J71: =IF(J4>$F$6,0,Leadsheet!$E$42*(-J48+J23-SUM(I23:I31)+SUM(J24:J32))) -> 0 | K71: =IF(K4>$F$6,0,Leadsheet!$E$42*(-K48+K23-SUM(J23:J31)+SUM(K24:K32))) -> 0 | L71: =IF(L4>$F$6,0,Leadsheet!$E$42*(-L48+L23-SUM(K23:K31)+SUM(L24:L32))) -> 0 | M71: =IF(M4>$F$6,0,Leadsheet!$E$42*(-M48+M23-SUM(L23:L31)+SUM(M24:M32))) -> 0 | ... BM71: =IF(BM4>$F$6,0,Leadsheet!$E$42*(-BM48+BM23-SUM(BL23:BL31)+SUM(BM24:BM32))) -> 0
C72: Sharing TOI+ Risk DPD180+ | F72: =IF(F4>$F$6,0,Leadsheet!$E$49*(-F48+F26+SUM(E26:E31)-SUM(F27:F32))) -> 0 | G72: =IF(G4>$F$6,0,Leadsheet!$E$49*(-G48+G26+SUM(F26:F31)-SUM(G27:G32))) -> 0 | H72: =IF(H4>$F$6,0,Leadsheet!$E$49*(-H48+H26+SUM(G26:G31)-SUM(H27:H32))) -> 0 | I72: =IF(I4>$F$6,0,Leadsheet!$E$49*(-I48+I26+SUM(H26:H31)-SUM(I27:I32))) -> 0 | J72: =IF(J4>$F$6,0,Leadsheet!$E$49*(-J48+J26+SUM(I26:I31)-SUM(J27:J32))) -> 0 | K72: =IF(K4>$F$6,0,Leadsheet!$E$49*(-K48+K26+SUM(J26:J31)-SUM(K27:K32))) -> 0 | L72: =IF(L4>$F$6,0,Leadsheet!$E$49*(-L48+L26+SUM(K26:K31)-SUM(L27:L32))) -> 0 | M72: =IF(M4>$F$6,0,Leadsheet!$E$49*(-M48+M26+SUM(L26:L31)-SUM(M27:M32))) -> 0 | ... BM72: =IF(BM4>$F$6,0,Leadsheet!$E$49*(-BM48+BM26+SUM(BL26:BL31)-SUM(BM27:BM32))) -> 0
B73: Marketing | F73: =F74+F58 -> 0
C74: Marketing_acquisition | F74: =-Leadsheet!E56 -> 0
B76: UW & Disbursal | F76: =F77+F78+F79 -> -0.014853157
C77: Underwriting Cost | F77: =-Leadsheet!E58/Leadsheet!E61/Leadsheet!E62-Leadsheet!E59 -> -0.014026942
C78: Disbursement cost | F78: =-Leadsheet!E60 -> -0.00082621508
C79: DOP cost | F79: =-Leadsheet!E59 -> 0
C81: Expense Increase | F81: 1 | G81: =IF(G$4>$F$6,0,IF(G$4<12,1,(1+Leadsheet!$E$38)^(ROUNDDOWN(G$4/12,0)))) -> 1 | H81: =IF(H$4>$F$6,0,IF(H$4<12,1,(1+Leadsheet!$E$38)^(ROUNDDOWN(H$4/12,0)))) -> 1 | I81: =IF(I$4>$F$6,0,IF(I$4<12,1,(1+Leadsheet!$E$38)^(ROUNDDOWN(I$4/12,0)))) -> 1 | J81: =IF(J$4>$F$6,0,IF(J$4<12,1,(1+Leadsheet!$E$38)^(ROUNDDOWN(J$4/12,0)))) -> 1 | K81: =IF(K$4>$F$6,0,IF(K$4<12,1,(1+Leadsheet!$E$38)^(ROUNDDOWN(K$4/12,0)))) -> 1 | L81: =IF(L$4>$F$6,0,IF(L$4<12,1,(1+Leadsheet!$E$38)^(ROUNDDOWN(L$4/12,0)))) -> 1 | M81: =IF(M$4>$F$6,0,IF(M$4<12,1,(1+Leadsheet!$E$38)^(ROUNDDOWN(M$4/12,0)))) -> 1 | N81: =IF(N$4>$F$6,0,IF(N$4<12,1,(1+Leadsheet!$E$38)^(ROUNDDOWN(N$4/12,0)))) -> 1 | ... BM81: =IF(BM$4>$F$6,0,IF(BM$4<12,1,(1+Leadsheet!$E$38)^(ROUNDDOWN(BM$4/12,0)))) -> 0
B83: Collection & AMC | F83: =SUM(F84:F85) -> -0.0038342646 | G83: =SUM(G84:G85) -> -0.0034306578 | H83: =SUM(H84:H85) -> -0.0033095757 | I83: =SUM(I84:I85) -> -0.0031884937 | J83: =SUM(J84:J85) -> -0.0030674116 | K83: =SUM(K84:K85) -> -0.0029463296 | L83: =SUM(L84:L85) -> -0.0028252476 | M83: =SUM(M84:M85) -> -0.0027041655 | ... BM83: =SUM(BM84:BM85) -> 0
C84: Early collections | F84: =-IF(F4>Leadsheet!$E$13,Leadsheet!$E$66*F$81*F37/$E$37,Leadsheet!$E$66*F$81*E16) -> -0.0038342646 | G84: =-IF(G4>Leadsheet!$E$13,Leadsheet!$E$66*G$81*G37/$E$37,Leadsheet!$E$66*G$81*F16) -> -0.0034306578 | H84: =-IF(H4>Leadsheet!$E$13,Leadsheet!$E$66*H$81*H37/$E$37,Leadsheet!$E$66*H$81*G16) -> -0.0033095757 | I84: =-IF(I4>Leadsheet!$E$13,Leadsheet!$E$66*I$81*I37/$E$37,Leadsheet!$E$66*I$81*H16) -> -0.0031884937 | J84: =-IF(J4>Leadsheet!$E$13,Leadsheet!$E$66*J$81*J37/$E$37,Leadsheet!$E$66*J$81*I16) -> -0.0030674116 | K84: =-IF(K4>Leadsheet!$E$13,Leadsheet!$E$66*K$81*K37/$E$37,Leadsheet!$E$66*K$81*J16) -> -0.0029463296 | L84: =-IF(L4>Leadsheet!$E$13,Leadsheet!$E$66*L$81*L37/$E$37,Leadsheet!$E$66*L$81*K16) -> -0.0028252476 | M84: =-IF(M4>Leadsheet!$E$13,Leadsheet!$E$66*M$81*M37/$E$37,Leadsheet!$E$66*M$81*L16) -> -0.0027041655 | ... BM84: =-IF(BM4>Leadsheet!$E$13,Leadsheet!$E$66*BM$81*BM37/$E$37,Leadsheet!$E$66*BM$81*BL16) -> 0
C85: AMC
B87: After sale service | F87: =SUM(F88:F89) -> -6.5052223e-06 | G87: =SUM(G88:G89) -> -6.2756262e-06 | H87: =SUM(H88:H89) -> -6.0460301e-06 | I87: =SUM(I88:I89) -> -5.816434e-06 | J87: =SUM(J88:J89) -> -5.586838e-06 | K87: =SUM(K88:K89) -> -5.3572419e-06 | L87: =SUM(L88:L89) -> -5.1276458e-06 | M87: =SUM(M88:M89) -> -4.8980497e-06 | ... BM87: =SUM(BM88:BM89) -> 0
C88: SMS & Email | F88: =IF(F4>Leadsheet!$E$13,0,-F16*Leadsheet!$E$73) -> -6.5052223e-06 | G88: =IF(G4>Leadsheet!$E$13,0,-G16*Leadsheet!$E$73) -> -6.2756262e-06 | H88: =IF(H4>Leadsheet!$E$13,0,-H16*Leadsheet!$E$73) -> -6.0460301e-06 | I88: =IF(I4>Leadsheet!$E$13,0,-I16*Leadsheet!$E$73) -> -5.816434e-06 | J88: =IF(J4>Leadsheet!$E$13,0,-J16*Leadsheet!$E$73) -> -5.586838e-06 | K88: =IF(K4>Leadsheet!$E$13,0,-K16*Leadsheet!$E$73) -> -5.3572419e-06 | L88: =IF(L4>Leadsheet!$E$13,0,-L16*Leadsheet!$E$73) -> -5.1276458e-06 | M88: =IF(M4>Leadsheet!$E$13,0,-M16*Leadsheet!$E$73) -> -4.8980497e-06 | ... BM88: =IF(BM4>Leadsheet!$E$13,0,-BM16*Leadsheet!$E$73) -> 0
B91: OVERHEAD EXPENSES | F91: =SUM(F92:F95) -> -0.036481576 | G91: =SUM(G92:G95) -> -0.035193991 | H91: =SUM(H92:H95) -> -0.033906406 | I91: =SUM(I92:I95) -> -0.032618821 | J91: =SUM(J92:J95) -> -0.031331236 | K91: =SUM(K92:K95) -> -0.030043651 | L91: =SUM(L92:L95) -> -0.028756066 | M91: =SUM(M92:M95) -> -0.027468481 | ... BM91: =SUM(BM92:BM95) -> 0
C92: Direct HR | F92: =-IF(F$4>Leadsheet!$E$13,0,Leadsheet!$E76*SAP_Speadsheet!F$81*F$16) -> -0.0064543771 | G92: =-IF(G$4>Leadsheet!$E$13,0,Leadsheet!$E76*SAP_Speadsheet!G$81*G$16) -> -0.0062265756 | H92: =-IF(H$4>Leadsheet!$E$13,0,Leadsheet!$E76*SAP_Speadsheet!H$81*H$16) -> -0.005998774 | I92: =-IF(I$4>Leadsheet!$E$13,0,Leadsheet!$E76*SAP_Speadsheet!I$81*I$16) -> -0.0057709725 | J92: =-IF(J$4>Leadsheet!$E$13,0,Leadsheet!$E76*SAP_Speadsheet!J$81*J$16) -> -0.0055431709 | K92: =-IF(K$4>Leadsheet!$E$13,0,Leadsheet!$E76*SAP_Speadsheet!K$81*K$16) -> -0.0053153694 | L92: =-IF(L$4>Leadsheet!$E$13,0,Leadsheet!$E76*SAP_Speadsheet!L$81*L$16) -> -0.0050875678 | M92: =-IF(M$4>Leadsheet!$E$13,0,Leadsheet!$E76*SAP_Speadsheet!M$81*M$16) -> -0.0048597663 | ... BM92: =-IF(BM$4>Leadsheet!$E$13,0,Leadsheet!$E76*SAP_Speadsheet!BM$81*BM$16) -> 0
C93: Indirect HR | F93: =-IF(F$4>Leadsheet!$E$13,0,Leadsheet!$E77*SAP_Speadsheet!F$81*F$16) -> -0.015327636 | G93: =-IF(G$4>Leadsheet!$E$13,0,Leadsheet!$E77*SAP_Speadsheet!G$81*G$16) -> -0.01478666 | H93: =-IF(H$4>Leadsheet!$E$13,0,Leadsheet!$E77*SAP_Speadsheet!H$81*H$16) -> -0.014245685 | I93: =-IF(I$4>Leadsheet!$E$13,0,Leadsheet!$E77*SAP_Speadsheet!I$81*I$16) -> -0.01370471 | J93: =-IF(J$4>Leadsheet!$E$13,0,Leadsheet!$E77*SAP_Speadsheet!J$81*J$16) -> -0.013163734 | K93: =-IF(K$4>Leadsheet!$E$13,0,Leadsheet!$E77*SAP_Speadsheet!K$81*K$16) -> -0.012622759 | L93: =-IF(L$4>Leadsheet!$E$13,0,Leadsheet!$E77*SAP_Speadsheet!L$81*L$16) -> -0.012081784 | M93: =-IF(M$4>Leadsheet!$E$13,0,Leadsheet!$E77*SAP_Speadsheet!M$81*M$16) -> -0.011540808 | ... BM93: =-IF(BM$4>Leadsheet!$E$13,0,Leadsheet!$E77*SAP_Speadsheet!BM$81*BM$16) -> 0
C94: IT | F94: =-IF(F$4>Leadsheet!$E$13,0,Leadsheet!$E78*SAP_Speadsheet!F$81*F$16) -> -0.0084600067 | G94: =-IF(G$4>Leadsheet!$E$13,0,Leadsheet!$E78*SAP_Speadsheet!G$81*G$16) -> -0.0081614182 | H94: =-IF(H$4>Leadsheet!$E$13,0,Leadsheet!$E78*SAP_Speadsheet!H$81*H$16) -> -0.0078628298 | I94: =-IF(I$4>Leadsheet!$E$13,0,Leadsheet!$E78*SAP_Speadsheet!I$81*I$16) -> -0.0075642413 | J94: =-IF(J$4>Leadsheet!$E$13,0,Leadsheet!$E78*SAP_Speadsheet!J$81*J$16) -> -0.0072656528 | K94: =-IF(K$4>Leadsheet!$E$13,0,Leadsheet!$E78*SAP_Speadsheet!K$81*K$16) -> -0.0069670644 | L94: =-IF(L$4>Leadsheet!$E$13,0,Leadsheet!$E78*SAP_Speadsheet!L$81*L$16) -> -0.0066684759 | M94: =-IF(M$4>Leadsheet!$E$13,0,Leadsheet!$E78*SAP_Speadsheet!M$81*M$16) -> -0.0063698874 | ... BM94: =-IF(BM$4>Leadsheet!$E$13,0,Leadsheet!$E78*SAP_Speadsheet!BM$81*BM$16) -> 0
C95: Other support units | F95: =-IF(F$4>Leadsheet!$E$13,0,Leadsheet!$E79*SAP_Speadsheet!F$81*F$16) -> -0.0062395568 | G95: =-IF(G$4>Leadsheet!$E$13,0,Leadsheet!$E79*SAP_Speadsheet!G$81*G$16) -> -0.0060193372 | H95: =-IF(H$4>Leadsheet!$E$13,0,Leadsheet!$E79*SAP_Speadsheet!H$81*H$16) -> -0.0057991175 | I95: =-IF(I$4>Leadsheet!$E$13,0,Leadsheet!$E79*SAP_Speadsheet!I$81*I$16) -> -0.0055788979 | J95: =-IF(J$4>Leadsheet!$E$13,0,Leadsheet!$E79*SAP_Speadsheet!J$81*J$16) -> -0.0053586782 | K95: =-IF(K$4>Leadsheet!$E$13,0,Leadsheet!$E79*SAP_Speadsheet!K$81*K$16) -> -0.0051384585 | L95: =-IF(L$4>Leadsheet!$E$13,0,Leadsheet!$E79*SAP_Speadsheet!L$81*L$16) -> -0.0049182389 | M95: =-IF(M$4>Leadsheet!$E$13,0,Leadsheet!$E79*SAP_Speadsheet!M$81*M$16) -> -0.0046980192 | ... BM95: =-IF(BM$4>Leadsheet!$E$13,0,Leadsheet!$E79*SAP_Speadsheet!BM$81*BM$16) -> 0
B98: Provision
C99: Provision Rate | F99: IFRS | K99: VAS360 | L99: VAS180
C100: B0 | F100: =Leadsheet!J87 -> 0.017406538 | G100: =Leadsheet!K87 -> 0.10986664 | K100: 0.0075 | L100: 0.0075
C101: B1 | F101: =Leadsheet!J88 -> 0.82888277 | G101: =Leadsheet!K88 -> 0.54933321 | K101: 0.0575 | L101: 0.0575
C102: B2 | F102: =Leadsheet!J89 -> 0.87250818 | G102: =Leadsheet!K89 -> 0.78476172 | K102: 0.0575 | L102: 0.0575
C103: B3 | F103: =Leadsheet!J90 -> 0.89949297 | G103: =Leadsheet!K90 -> 0.87195747 | K103: 0.0575 | L103: 0.0575
C104: B4 | F104: =Leadsheet!J91 -> 0.91784997 | G104: =Leadsheet!K91 -> 0.91784997 | K104: 0.2075 | L104: 0.2075
C105: B5 | F105: =Leadsheet!J92 -> 0.92712118 | G105: =Leadsheet!K92 -> 0.92712118 | K105: 0.2075 | L105: 0.2075
C106: B6 | F106: =Leadsheet!J93 -> 0.93178008 | G106: =Leadsheet!K93 -> 0.93178008 | K106: 0.2075 | L106: 0.2075
C107: B7 | F107: =Leadsheet!J94 -> 0.93178008 | G107: =Leadsheet!K94 -> 0.93178008 | K107: 0.5075 | L107: 0.5075
C108: B8 | F108: =Leadsheet!J95 -> 0.950796 | G108: =Leadsheet!K95 -> 0.950796 | K108: 0.5075 | L108: 1
C109: B9 | F109: =Leadsheet!J96 -> 0.950796 | G109: =Leadsheet!K96 -> 0.950796 | K109: 0.5075
C110: B10 | F110: =Leadsheet!J97 -> 0.950796 | G110: =Leadsheet!K97 -> 0.950796 | K110: 0.5075
C111: B11 | F111: =Leadsheet!J98 -> 0.950796 | G111: =Leadsheet!K98 -> 0.950796 | K111: 0.5075
C112: B12 | F112: =Leadsheet!J99 -> 0.950796 | G112: =Leadsheet!K99 -> 0.950796 | K112: 0.5075
C113: B13 | F113: =Leadsheet!J100 -> 0.950796 | G113: =Leadsheet!K100 -> 0.950796 | K113: 1
C114: B14+ | F114: =Leadsheet!J101 -> 0.9702 | G114: =Leadsheet!K101 -> 0.9702 | K114: 1
B116: IFRS
C117: Provision cost
C118: B0 | F118: =IF(F$4>$F$6,0,F19*IF(F$5>=1,$F100,$G100)) -> 0.12110632 | G118: =IF(G$4>$F$6,0,G19*IF(G$5>=1,$F100,$G100)) -> 0.11433155 | H118: =IF(H$4>$F$6,0,H19*IF(H$5>=1,$F100,$G100)) -> 0.10776363 | I118: =IF(I$4>$F$6,0,I19*IF(I$5>=1,$F100,$G100)) -> 0.1013697 | J118: =IF(J$4>$F$6,0,J19*IF(J$5>=1,$F100,$G100)) -> 0.095118598 | K118: =IF(K$4>$F$6,0,K19*IF(K$5>=1,$F100,$G100)) -> 0.088995198 | L118: =IF(L$4>$F$6,0,L19*IF(L$5>=1,$F100,$G100)) -> 0.082984529 | M118: =IF(M$4>$F$6,0,M19*IF(M$5>=1,$F100,$G100)) -> 0.077085557 | ... AC118: =IF(AC$4>$F$6,0,AC19*IF(AC$5>=1,$F100,$G100)) -> 0 | AD118: =IF(AD$4>$F$6,0,AD19*$F100) -> 0 | AE118: =IF(AE$4>$F$6,0,AE19*$F100) -> 0 | AF118: =IF(AF$4>$F$6,0,AF19*$F100) -> 0 | AG118: =IF(AG$4>$F$6,0,AG19*$F100) -> 0 | AH118: =IF(AH$4>$F$6,0,AH19*$F100) -> 0 | AI118: =IF(AI$4>$F$6,0,AI19*$F100) -> 0 | AJ118: =IF(AJ$4>$F$6,0,AJ19*$F100) -> 0 | AK118: =IF(AK$4>$F$6,0,AK19*$F100) -> 0 | ... BM118: =IF(BM$4>$F$6,0,BM19*$F100) -> 0
C119: B1 | F119: =IF(F$4>$F$6,0,F20*IF(F$5>=1,$F101,$G101)) -> 0.13860731 | G119: =IF(G$4>$F$6,0,G20*IF(G$5>=1,$F101,$G101)) -> 0.12110632 | H119: =IF(H$4>$F$6,0,H20*IF(H$5>=1,$F101,$G101)) -> 0.11433155 | I119: =IF(I$4>$F$6,0,I20*IF(I$5>=1,$F101,$G101)) -> 0.10776363 | J119: =IF(J$4>$F$6,0,J20*IF(J$5>=1,$F101,$G101)) -> 0.1013697 | K119: =IF(K$4>$F$6,0,K20*IF(K$5>=1,$F101,$G101)) -> 0.095118598 | L119: =IF(L$4>$F$6,0,L20*IF(L$5>=1,$F101,$G101)) -> 0.088995198 | M119: =IF(M$4>$F$6,0,M20*IF(M$5>=1,$F101,$G101)) -> 0.082984529 | ... AC119: =IF(AC$4>$F$6,0,AC20*IF(AC$5>=1,$F101,$G101)) -> 0 | AD119: =IF(AD$4>$F$6,0,AD20*$F101) -> 0 | AE119: =IF(AE$4>$F$6,0,AE20*$F101) -> 0 | AF119: =IF(AF$4>$F$6,0,AF20*$F101) -> 0 | AG119: =IF(AG$4>$F$6,0,AG20*$F101) -> 0 | AH119: =IF(AH$4>$F$6,0,AH20*$F101) -> 0 | AI119: =IF(AI$4>$F$6,0,AI20*$F101) -> 0 | AJ119: =IF(AJ$4>$F$6,0,AJ20*$F101) -> 0 | AK119: =IF(AK$4>$F$6,0,AK20*$F101) -> 0 | ... BM119: =IF(BM$4>$F$6,0,BM20*$F101) -> 0
C120: B2 | F120: =IF(F$4>$F$6,0,F21*IF(F$5>=1,$F102,$G102)) -> 0 | G120: =IF(G$4>$F$6,0,G21*IF(G$5>=1,$F102,$G102)) -> 0.13860731 | H120: =IF(H$4>$F$6,0,H21*IF(H$5>=1,$F102,$G102)) -> 0.12110632 | I120: =IF(I$4>$F$6,0,I21*IF(I$5>=1,$F102,$G102)) -> 0.11433155 | J120: =IF(J$4>$F$6,0,J21*IF(J$5>=1,$F102,$G102)) -> 0.10776363 | K120: =IF(K$4>$F$6,0,K21*IF(K$5>=1,$F102,$G102)) -> 0.1013697 | L120: =IF(L$4>$F$6,0,L21*IF(L$5>=1,$F102,$G102)) -> 0.095118598 | M120: =IF(M$4>$F$6,0,M21*IF(M$5>=1,$F102,$G102)) -> 0.088995198 | ... AC120: =IF(AC$4>$F$6,0,AC21*IF(AC$5>=1,$F102,$G102)) -> 0 | AD120: =IF(AD$4>$F$6,0,AD21*$F102) -> 0 | AE120: =IF(AE$4>$F$6,0,AE21*$F102) -> 0 | AF120: =IF(AF$4>$F$6,0,AF21*$F102) -> 0 | AG120: =IF(AG$4>$F$6,0,AG21*$F102) -> 0 | AH120: =IF(AH$4>$F$6,0,AH21*$F102) -> 0 | AI120: =IF(AI$4>$F$6,0,AI21*$F102) -> 0 | AJ120: =IF(AJ$4>$F$6,0,AJ21*$F102) -> 0 | AK120: =IF(AK$4>$F$6,0,AK21*$F102) -> 0 | ... BM120: =IF(BM$4>$F$6,0,BM21*$F102) -> 0
C121: B3 | F121: =IF(F$4>$F$6,0,F22*IF(F$5>=1,$F103,$G103)) -> 0 | G121: =IF(G$4>$F$6,0,G22*IF(G$5>=1,$F103,$G103)) -> 0 | H121: =IF(H$4>$F$6,0,H22*IF(H$5>=1,$F103,$G103)) -> 0.13860731 | I121: =IF(I$4>$F$6,0,I22*IF(I$5>=1,$F103,$G103)) -> 0.12110632 | J121: =IF(J$4>$F$6,0,J22*IF(J$5>=1,$F103,$G103)) -> 0.11433155 | K121: =IF(K$4>$F$6,0,K22*IF(K$5>=1,$F103,$G103)) -> 0.10776363 | L121: =IF(L$4>$F$6,0,L22*IF(L$5>=1,$F103,$G103)) -> 0.1013697 | M121: =IF(M$4>$F$6,0,M22*IF(M$5>=1,$F103,$G103)) -> 0.095118598 | ... AC121: =IF(AC$4>$F$6,0,AC22*IF(AC$5>=1,$F103,$G103)) -> 0 | AD121: =IF(AD$4>$F$6,0,AD22*$F103) -> 0 | AE121: =IF(AE$4>$F$6,0,AE22*$F103) -> 0 | AF121: =IF(AF$4>$F$6,0,AF22*$F103) -> 0 | AG121: =IF(AG$4>$F$6,0,AG22*$F103) -> 0 | AH121: =IF(AH$4>$F$6,0,AH22*$F103) -> 0 | AI121: =IF(AI$4>$F$6,0,AI22*$F103) -> 0 | AJ121: =IF(AJ$4>$F$6,0,AJ22*$F103) -> 0 | AK121: =IF(AK$4>$F$6,0,AK22*$F103) -> 0 | ... BM121: =IF(BM$4>$F$6,0,BM22*$F103) -> 0
C122: B4 | F122: =IF(F$4>$F$6,0,F23*IF(F$5>=1,$F104,$G104)) -> 0 | G122: =IF(G$4>$F$6,0,G23*IF(G$5>=1,$F104,$G104)) -> 0 | H122: =IF(H$4>$F$6,0,H23*IF(H$5>=1,$F104,$G104)) -> 0 | I122: =IF(I$4>$F$6,0,I23*IF(I$5>=1,$F104,$G104)) -> 0.13860731 | J122: =IF(J$4>$F$6,0,J23*IF(J$5>=1,$F104,$G104)) -> 0.12110632 | K122: =IF(K$4>$F$6,0,K23*IF(K$5>=1,$F104,$G104)) -> 0.11433155 | L122: =IF(L$4>$F$6,0,L23*IF(L$5>=1,$F104,$G104)) -> 0.10776363 | M122: =IF(M$4>$F$6,0,M23*IF(M$5>=1,$F104,$G104)) -> 0.1013697 | ... AC122: =IF(AC$4>$F$6,0,AC23*IF(AC$5>=1,$F104,$G104)) -> 0 | AD122: =IF(AD$4>$F$6,0,AD23*$F104) -> 0 | AE122: =IF(AE$4>$F$6,0,AE23*$F104) -> 0 | AF122: =IF(AF$4>$F$6,0,AF23*$F104) -> 0 | AG122: =IF(AG$4>$F$6,0,AG23*$F104) -> 0 | AH122: =IF(AH$4>$F$6,0,AH23*$F104) -> 0 | AI122: =IF(AI$4>$F$6,0,AI23*$F104) -> 0 | AJ122: =IF(AJ$4>$F$6,0,AJ23*$F104) -> 0 | AK122: =IF(AK$4>$F$6,0,AK23*$F104) -> 0 | ... BM122: =IF(BM$4>$F$6,0,BM23*$F104) -> 0
C123: B5 | F123: =IF(F$4>$F$6,0,F24*IF(F$5>=1,$F105,$G105)) -> 0 | G123: =IF(G$4>$F$6,0,G24*IF(G$5>=1,$F105,$G105)) -> 0 | H123: =IF(H$4>$F$6,0,H24*IF(H$5>=1,$F105,$G105)) -> 0 | I123: =IF(I$4>$F$6,0,I24*IF(I$5>=1,$F105,$G105)) -> 0 | J123: =IF(J$4>$F$6,0,J24*IF(J$5>=1,$F105,$G105)) -> 0.13860731 | K123: =IF(K$4>$F$6,0,K24*IF(K$5>=1,$F105,$G105)) -> 0.12110632 | L123: =IF(L$4>$F$6,0,L24*IF(L$5>=1,$F105,$G105)) -> 0.11433155 | M123: =IF(M$4>$F$6,0,M24*IF(M$5>=1,$F105,$G105)) -> 0.10776363 | ... AC123: =IF(AC$4>$F$6,0,AC24*IF(AC$5>=1,$F105,$G105)) -> 0 | AD123: =IF(AD$4>$F$6,0,AD24*$F105) -> 0 | AE123: =IF(AE$4>$F$6,0,AE24*$F105) -> 0 | AF123: =IF(AF$4>$F$6,0,AF24*$F105) -> 0 | AG123: =IF(AG$4>$F$6,0,AG24*$F105) -> 0 | AH123: =IF(AH$4>$F$6,0,AH24*$F105) -> 0 | AI123: =IF(AI$4>$F$6,0,AI24*$F105) -> 0 | AJ123: =IF(AJ$4>$F$6,0,AJ24*$F105) -> 0 | AK123: =IF(AK$4>$F$6,0,AK24*$F105) -> 0 | ... BM123: =IF(BM$4>$F$6,0,BM24*$F105) -> 0
...

Sheet Saleplan&PnL
C1: PROFIT & LOSS 60M
C2: I. | D2: SALES PLAN
C4: Business month | D4: 45658 | E4: =EOMONTH(D4,1) -> 45716 | F4: =EOMONTH(E4,1) -> 45747 | G4: =EOMONTH(F4,1) -> 45777 | H4: =EOMONTH(G4,1) -> 45808 | I4: =EOMONTH(H4,1) -> 45838 | J4: =EOMONTH(I4,1) -> 45869 | K4: =EOMONTH(J4,1) -> 45900 | L4: =EOMONTH(K4,1) -> 45930 | ... BL4: =EOMONTH(BK4,1) -> 47514
C5: Don't delete | D5: =YEAR(D4) -> 2025 | E5: =YEAR(E4) -> 2025 | F5: =YEAR(F4) -> 2025 | G5: =YEAR(G4) -> 2025 | H5: =YEAR(H4) -> 2025 | I5: =YEAR(I4) -> 2025 | J5: =YEAR(J4) -> 2025 | K5: =YEAR(K4) -> 2025 | ... BL5: =YEAR(BL4) -> 2030
C6: New Account | D6: 1390
C8: II. | D8: PROFIT & LOSS
C10: FISCAL YEAR | D10: Total | F10: =YEAR(D4) -> 2025 | H10: =F10+1 -> 2026 | J10: =H10+1 -> 2027 | L10: =J10+1 -> 2028 | N10: =L10+1 -> 2029 | P10: =N10+1 -> 2030
D11: bVND | F11: bVND | H11: bVND | J11: bVND | L11: bVND | N11: bVND | P11: bVND
C13: NEW ACC | D13: =SUM(F13:P13) -> 1390 | F13: =SUMIF($D$5:$BL$5,F$10,$D$6:$BL$6) -> 1390 | H13: =SUMIF($D$5:$BL$5,H$10,$D$6:$BL$6) -> 0 | J13: =SUMIF($D$5:$BL$5,J$10,$D$6:$BL$6) -> 0 | L13: =SUMIF($D$5:$BL$5,L$10,$D$6:$BL$6) -> 0 | N13: =SUMIF($D$5:$BL$5,N$10,$D$6:$BL$6) -> 0 | P13: =SUMIF($D$5:$BL$5,P$10,$D$6:$BL$6) -> 0
C14: Monthly Acc | D14: =AVERAGE(D6:AM6) -> 1390 | F14: =F13/COUNTIF($D$5:$BL$5,F10) -> 115.83333 | H14: =H13/COUNTIF($D$5:$BL$5,H10) -> 0 | J14: =J13/COUNTIF($D$5:$BL$5,J10) -> 0 | L14: =L13/COUNTIF($D$5:$BL$5,L10) -> 0 | N14: =N13/COUNTIF($D$5:$BL$5,N10) -> 0 | P14: =P13/COUNTIF($D$5:$BL$5,P10) -> 0
C16: EOP | F16: =OFFSET(PnL_Speadsheet!$A$7,0,MATCH(DATE('Saleplan&PnL'!F$10,12,31),PnL_Speadsheet!$B$4:$BI$4,0))/1000 -> 1.9462162 | H16: =OFFSET(PnL_Speadsheet!$A$7,0,MATCH(DATE('Saleplan&PnL'!H$10,12,31),PnL_Speadsheet!$B$4:$BI$4,0))/1000 -> 0 | J16: =OFFSET(PnL_Speadsheet!$A$7,0,MATCH(DATE('Saleplan&PnL'!J$10,12,31),PnL_Speadsheet!$B$4:$BI$4,0))/1000 -> 0 | L16: =OFFSET(PnL_Speadsheet!$A$7,0,MATCH(DATE('Saleplan&PnL'!L$10,12,31),PnL_Speadsheet!$B$4:$BI$4,0))/1000 -> 0 | N16: =OFFSET(PnL_Speadsheet!$A$7,0,MATCH(DATE('Saleplan&PnL'!N$10,12,31),PnL_Speadsheet!$B$4:$BI$4,0))/1000 -> 0 | P16: =IFERROR(OFFSET(PnL_Speadsheet!$A$7,0,MATCH(DATE('Saleplan&PnL'!P$10,12,31),PnL_Speadsheet!$B$4:$BI$4,0))/1000,0) -> 0
C17: ADB | D17: =SUM(PnL_Speadsheet!B8:AK8)/1000/COUNT(PnL_Speadsheet!B3:AK3) -> 2.4525878 | F17: =SUMIF(PnL_Speadsheet!$B$3:$BI$3,F$10,PnL_Speadsheet!$B8:$BI8)/1000/COUNTIF(PnL_Speadsheet!$B$3:$BI$3,'Saleplan&PnL'!F$10) -> 6.8732861 | H17: =SUMIF(PnL_Speadsheet!$B$3:$BI$3,H$10,PnL_Speadsheet!$B8:$BI8)/1000/COUNTIF(PnL_Speadsheet!$B$3:$BI$3,'Saleplan&PnL'!H$10) -> 0.48447718 | J17: =SUMIF(PnL_Speadsheet!$B$3:$BI$3,J$10,PnL_Speadsheet!$B8:$BI8)/1000/COUNTIF(PnL_Speadsheet!$B$3:$BI$3,'Saleplan&PnL'!J$10) -> 0 | L17: =SUMIF(PnL_Speadsheet!$B$3:$BI$3,L$10,PnL_Speadsheet!$B8:$BI8)/1000/COUNTIF(PnL_Speadsheet!$B$3:$BI$3,'Saleplan&PnL'!L$10) -> 0 | N17: =SUMIF(PnL_Speadsheet!$B$3:$BI$3,N$10,PnL_Speadsheet!$B8:$BI8)/1000/COUNTIF(PnL_Speadsheet!$B$3:$BI$3,'Saleplan&PnL'!N$10) -> 0 | P17: =IFERROR(SUMIF(PnL_Speadsheet!$B$3:$BI$3,P$10,PnL_Speadsheet!$B8:$BI8)/1000/COUNTIF(PnL_Speadsheet!$B$3:$BI$3,'Saleplan&PnL'!P$10),0) -> 0
C19: TOI | D19: =SUM(F19:P19) -> 1.8374355 | F19: =SUMIF(PnL_Speadsheet!$B$3:$BI$3,F$10,PnL_Speadsheet!$B9:$BI9)/1000 -> 1.8695851 | H19: =SUMIF(PnL_Speadsheet!$B$3:$BI$3,H$10,PnL_Speadsheet!$B9:$BI9)/1000 -> -0.032149587 | J19: =SUMIF(PnL_Speadsheet!$B$3:$BI$3,J$10,PnL_Speadsheet!$B9:$BI9)/1000 -> 0 | L19: =SUMIF(PnL_Speadsheet!$B$3:$BI$3,L$10,PnL_Speadsheet!$B9:$BI9)/1000 -> 0 | N19: =SUMIF(PnL_Speadsheet!$B$3:$BI$3,N$10,PnL_Speadsheet!$B9:$BI9)/1000 -> 0 | P19: =SUMIF(PnL_Speadsheet!$B$3:$BI$3,P$10,PnL_Speadsheet!$B9:$BI9)/1000 -> 0
C20: NII | D20: =SUM(F20:P20) -> 1.6272084 | F20: =SUMIF(PnL_Speadsheet!$B$3:$BI$3,F$10,PnL_Speadsheet!$B11:$BI11)/1000 -> 1.659358 | H20: =SUMIF(PnL_Speadsheet!$B$3:$BI$3,H$10,PnL_Speadsheet!$B11:$BI11)/1000 -> -0.032149587 | J20: =SUMIF(PnL_Speadsheet!$B$3:$BI$3,J$10,PnL_Speadsheet!$B11:$BI11)/1000 -> 0 | L20: =SUMIF(PnL_Speadsheet!$B$3:$BI$3,L$10,PnL_Speadsheet!$B11:$BI11)/1000 -> 0 | N20: =SUMIF(PnL_Speadsheet!$B$3:$BI$3,N$10,PnL_Speadsheet!$B11:$BI11)/1000 -> 0 | P20: =SUMIF(PnL_Speadsheet!$B$3:$BI$3,P$10,PnL_Speadsheet!$B11:$BI11)/1000 -> 0
C21: NFI | D21: =SUM(F21:P21) -> 0.21022708 | F21: =SUMIF(PnL_Speadsheet!$B$3:$BI$3,F$10,PnL_Speadsheet!$B14:$BI14)/1000 -> 0.21022708 | H21: =SUMIF(PnL_Speadsheet!$B$3:$BI$3,H$10,PnL_Speadsheet!$B14:$BI14)/1000 -> 0 | J21: =SUMIF(PnL_Speadsheet!$B$3:$BI$3,J$10,PnL_Speadsheet!$B14:$BI14)/1000 -> 0 | L21: =SUMIF(PnL_Speadsheet!$B$3:$BI$3,L$10,PnL_Speadsheet!$B14:$BI14)/1000 -> 0 | N21: =SUMIF(PnL_Speadsheet!$B$3:$BI$3,N$10,PnL_Speadsheet!$B14:$BI14)/1000 -> 0 | P21: =SUMIF(PnL_Speadsheet!$B$3:$BI$3,P$10,PnL_Speadsheet!$B14:$BI14)/1000 -> 0
C22: Other TOI | D22: =SUM(F22:P22) -> 0 | F22: =SUMIF(PnL_Speadsheet!$B$3:$BI$3,F$10,PnL_Speadsheet!$B18:$BI18)/1000 -> 0 | H22: =SUMIF(PnL_Speadsheet!$B$3:$BI$3,H$10,PnL_Speadsheet!$B18:$BI18)/1000 -> 0 | J22: =SUMIF(PnL_Speadsheet!$B$3:$BI$3,J$10,PnL_Speadsheet!$B18:$BI18)/1000 -> 0 | L22: =SUMIF(PnL_Speadsheet!$B$3:$BI$3,L$10,PnL_Speadsheet!$B18:$BI18)/1000 -> 0 | N22: =SUMIF(PnL_Speadsheet!$B$3:$BI$3,N$10,PnL_Speadsheet!$B18:$BI18)/1000 -> 0 | P22: =SUMIF(PnL_Speadsheet!$B$3:$BI$3,P$10,PnL_Speadsheet!$B18:$BI18)/1000 -> 0
C23: PROVISION | D23: =SUM(F23:P23) -> -1.8333046 | F23: =SUMIF(PnL_Speadsheet!$B$3:$BI$3,F$10,PnL_Speadsheet!$B31:$BI31)/1000 -> -1.8193404 | H23: =SUMIF(PnL_Speadsheet!$B$3:$BI$3,H$10,PnL_Speadsheet!$B31:$BI31)/1000 -> -0.013964194 | J23: =SUMIF(PnL_Speadsheet!$B$3:$BI$3,J$10,PnL_Speadsheet!$B31:$BI31)/1000 -> 0 | L23: =SUMIF(PnL_Speadsheet!$B$3:$BI$3,L$10,PnL_Speadsheet!$B31:$BI31)/1000 -> 0 | N23: =SUMIF(PnL_Speadsheet!$B$3:$BI$3,N$10,PnL_Speadsheet!$B31:$BI31)/1000 -> 0 | P23: =SUMIF(PnL_Speadsheet!$B$3:$BI$3,P$10,PnL_Speadsheet!$B31:$BI31)/1000 -> 0
C24: OPEX | D24: =SUM(F24:P24) -> -0.45935401 | F24: =SUMIF(PnL_Speadsheet!$B$3:$BI$3,F$10,PnL_Speadsheet!$B19:$BI19)/1000 -> -0.45630715 | H24: =SUMIF(PnL_Speadsheet!$B$3:$BI$3,H$10,PnL_Speadsheet!$B19:$BI19)/1000 -> -0.0030468607 | J24: =SUMIF(PnL_Speadsheet!$B$3:$BI$3,J$10,PnL_Speadsheet!$B19:$BI19)/1000 -> 0 | L24: =SUMIF(PnL_Speadsheet!$B$3:$BI$3,L$10,PnL_Speadsheet!$B19:$BI19)/1000 -> 0 | N24: =SUMIF(PnL_Speadsheet!$B$3:$BI$3,N$10,PnL_Speadsheet!$B19:$BI19)/1000 -> 0 | P24: =SUMIF(PnL_Speadsheet!$B$3:$BI$3,P$10,PnL_Speadsheet!$B19:$BI19)/1000 -> 0
C25: Sales incentives | D25: =SUM(F25:P25) -> 0 | F25: =SUMIF(PnL_Speadsheet!$B$3:$BI$3,F$10,PnL_Speadsheet!$B21:$BI22)/1000 -> 0 | H25: =SUMIF(PnL_Speadsheet!$B$3:$BI$3,H$10,PnL_Speadsheet!$B21:$BI22)/1000 -> 0 | J25: =SUMIF(PnL_Speadsheet!$B$3:$BI$3,J$10,PnL_Speadsheet!$B21:$BI22)/1000 -> 0 | L25: =SUMIF(PnL_Speadsheet!$B$3:$BI$3,L$10,PnL_Speadsheet!$B21:$BI22)/1000 -> 0 | N25: =SUMIF(PnL_Speadsheet!$B$3:$BI$3,N$10,PnL_Speadsheet!$B21:$BI22)/1000 -> 0 | P25: =SUMIF(PnL_Speadsheet!$B$3:$BI$3,P$10,PnL_Speadsheet!$B21:$BI22)/1000 -> 0
C26: Marketing | D26: =SUM(F26:P26) -> 0 | F26: =SUMIF(PnL_Speadsheet!$B$3:$BI$3,F$10,PnL_Speadsheet!$B22:$BI22)/1000 -> 0 | H26: =SUMIF(PnL_Speadsheet!$B$3:$BI$3,H$10,PnL_Speadsheet!$B22:$BI22)/1000 -> 0 | J26: =SUMIF(PnL_Speadsheet!$B$3:$BI$3,J$10,PnL_Speadsheet!$B22:$BI22)/1000 -> 0 | L26: =SUMIF(PnL_Speadsheet!$B$3:$BI$3,L$10,PnL_Speadsheet!$B22:$BI22)/1000 -> 0 | N26: =SUMIF(PnL_Speadsheet!$B$3:$BI$3,N$10,PnL_Speadsheet!$B22:$BI22)/1000 -> 0 | P26: =SUMIF(PnL_Speadsheet!$B$3:$BI$3,P$10,PnL_Speadsheet!$B22:$BI22)/1000 -> 0
C27: UW & Disbursal | D27: =SUM(F27:P27) -> -0.020645888 | F27: =SUMIF(PnL_Speadsheet!$B$3:$BI$3,F$10,PnL_Speadsheet!$B24:$BI24)/1000 -> -0.020645888 | H27: =SUMIF(PnL_Speadsheet!$B$3:$BI$3,H$10,PnL_Speadsheet!$B24:$BI24)/1000 -> 0 | J27: =SUMIF(PnL_Speadsheet!$B$3:$BI$3,J$10,PnL_Speadsheet!$B24:$BI24)/1000 -> 0 | L27: =SUMIF(PnL_Speadsheet!$B$3:$BI$3,L$10,PnL_Speadsheet!$B24:$BI24)/1000 -> 0 | N27: =SUMIF(PnL_Speadsheet!$B$3:$BI$3,N$10,PnL_Speadsheet!$B24:$BI24)/1000 -> 0 | P27: =SUMIF(PnL_Speadsheet!$B$3:$BI$3,P$10,PnL_Speadsheet!$B24:$BI24)/1000 -> 0
C28: Collection & AMC | D28: =SUM(F28:P28) -> -0.044894403 | F28: =SUMIF(PnL_Speadsheet!$B$3:$BI$3,F$10,PnL_Speadsheet!$B28:$BI28)/1000 -> -0.041847542 | H28: =SUMIF(PnL_Speadsheet!$B$3:$BI$3,H$10,PnL_Speadsheet!$B28:$BI28)/1000 -> -0.0030468607 | J28: =SUMIF(PnL_Speadsheet!$B$3:$BI$3,J$10,PnL_Speadsheet!$B28:$BI28)/1000 -> 0 | L28: =SUMIF(PnL_Speadsheet!$B$3:$BI$3,L$10,PnL_Speadsheet!$B28:$BI28)/1000 -> 0 | N28: =SUMIF(PnL_Speadsheet!$B$3:$BI$3,N$10,PnL_Speadsheet!$B28:$BI28)/1000 -> 0 | P28: =SUMIF(PnL_Speadsheet!$B$3:$BI$3,P$10,PnL_Speadsheet!$B28:$BI28)/1000 -> 0
C29: After-sales services | D29: =SUM(F29:P29) -> -7.0210481e-05 | F29: =SUMIF(PnL_Speadsheet!$B$3:$BI$3,F$10,PnL_Speadsheet!$B29:$BI29)/1000 -> -7.0210481e-05 | H29: =SUMIF(PnL_Speadsheet!$B$3:$BI$3,H$10,PnL_Speadsheet!$B29:$BI29)/1000 -> 0 | J29: =SUMIF(PnL_Speadsheet!$B$3:$BI$3,J$10,PnL_Speadsheet!$B29:$BI29)/1000 -> 0 | L29: =SUMIF(PnL_Speadsheet!$B$3:$BI$3,L$10,PnL_Speadsheet!$B29:$BI29)/1000 -> 0 | N29: =SUMIF(PnL_Speadsheet!$B$3:$BI$3,N$10,PnL_Speadsheet!$B29:$BI29)/1000 -> 0 | P29: =SUMIF(PnL_Speadsheet!$B$3:$BI$3,P$10,PnL_Speadsheet!$B29:$BI29)/1000 -> 0
C30: Other support units | D30: =SUM(F30:P30) -> -0.39374351 | F30: =SUMIF(PnL_Speadsheet!$B$3:$BI$3,F$10,PnL_Speadsheet!$B30:$BI30)/1000 -> -0.39374351 | H30: =SUMIF(PnL_Speadsheet!$B$3:$BI$3,H$10,PnL_Speadsheet!$B30:$BI30)/1000 -> 0 | J30: =SUMIF(PnL_Speadsheet!$B$3:$BI$3,J$10,PnL_Speadsheet!$B30:$BI30)/1000 -> 0 | L30: =SUMIF(PnL_Speadsheet!$B$3:$BI$3,L$10,PnL_Speadsheet!$B30:$BI30)/1000 -> 0 | N30: =SUMIF(PnL_Speadsheet!$B$3:$BI$3,N$10,PnL_Speadsheet!$B30:$BI30)/1000 -> 0 | P30: =SUMIF(PnL_Speadsheet!$B$3:$BI$3,P$10,PnL_Speadsheet!$B30:$BI30)/1000 -> 0
C31: PBT | D31: =SUM(F31:P31) -> -0.45522317 | F31: =SUMIF(PnL_Speadsheet!$B$3:$BI$3,F$10,PnL_Speadsheet!$B32:$BI32)/1000 -> -0.40606252 | H31: =SUMIF(PnL_Speadsheet!$B$3:$BI$3,H$10,PnL_Speadsheet!$B32:$BI32)/1000 -> -0.049160642 | J31: =SUMIF(PnL_Speadsheet!$B$3:$BI$3,J$10,PnL_Speadsheet!$B32:$BI32)/1000 -> 0 | L31: =SUMIF(PnL_Speadsheet!$B$3:$BI$3,L$10,PnL_Speadsheet!$B32:$BI32)/1000 -> 0 | N31: =SUMIF(PnL_Speadsheet!$B$3:$BI$3,N$10,PnL_Speadsheet!$B32:$BI32)/1000 -> 0 | P31: =SUMIF(PnL_Speadsheet!$B$3:$BI$3,P$10,PnL_Speadsheet!$B32:$BI32)/1000 -> 0
C32: In which: PROFIT BEFORE SU | D32: =D19+D23+SUM(D25:D29) -> -0.061479657 | F32: =F19+F23+SUM(F25:F29) -> -0.012319016 | H32: =H19+H23+SUM(H25:H29) -> -0.049160642 | J32: =J19+J23+SUM(J25:J29) -> 0 | L32: =L19+L23+SUM(L25:L29) -> 0 | N32: =N19+N23+SUM(N25:N29) -> 0 | P32: =P19+P23+SUM(P25:P29) -> 0

Sheet PnL_Speadsheet
A1: PL PROJECTION
A2: 60 months
B3: =YEAR(B4) -> 2025 | C3: =YEAR(C4) -> 2025 | D3: =YEAR(D4) -> 2025 | E3: =YEAR(E4) -> 2025 | F3: =YEAR(F4) -> 2025 | G3: =YEAR(G4) -> 2025 | H3: =YEAR(H4) -> 2025 | I3: =YEAR(I4) -> 2025 | ... BI3: =YEAR(BI4) -> 2029
A4: Business month | B4: ='Saleplan&PnL'!D4 -> 45658 | C4: ='Saleplan&PnL'!E4 -> 45716 | D4: ='Saleplan&PnL'!F4 -> 45747 | E4: ='Saleplan&PnL'!G4 -> 45777 | F4: ='Saleplan&PnL'!H4 -> 45808 | G4: ='Saleplan&PnL'!I4 -> 45838 | H4: ='Saleplan&PnL'!J4 -> 45869 | I4: ='Saleplan&PnL'!K4 -> 45900 | ... BI4: ='Saleplan&PnL'!BK4 -> 47483
A5: Month on board | B5: 1 | C5: 2 | D5: 3 | E5: 4 | F5: 5 | G5: 6 | H5: 7 | I5: 8 | J5: 9 | K5: 10 | L5: 11 | M5: 12 | N5: 13 | O5: 14 | P5: 15 | Q5: 16 | R5: 17 | S5: 18 | T5: 19 | U5: 20 | V5: 21 | W5: 22 | X5: 23 | Y5: 24 | Z5: 25 | AA5: 26 | AB5: 27 | AC5: 28 | AD5: 29 | AE5: 30 | AF5: 31 | AG5: 32 | AH5: 33 | AI5: 34 | AJ5: 35 | AK5: 36 | AL5: =AK5+1 -> 37 | AM5: =AL5+1 -> 38 | AN5: =AM5+1 -> 39 | AO5: =AN5+1 -> 40 | AP5: =AO5+1 -> 41 | AQ5: =AP5+1 -> 42 | AR5: =AQ5+1 -> 43 | AS5: =AR5+1 -> 44 | ... BI5: =BH5+1 -> 60
A6: Unit: mVND
A7: ENR | B7: {=SUMPRODUCT(B$55:B$114,TRANSPOSE(SAP_Speadsheet!$F$37:$BM$37))} -> 9903.3896 | C7: {=SUMPRODUCT(C$55:C$114,TRANSPOSE(SAP_Speadsheet!$F$37:$BM$37))} -> 9553.8582 | D7: {=SUMPRODUCT(D$55:D$114,TRANSPOSE(SAP_Speadsheet!$F$37:$BM$37))} -> 9204.3268 | E7: {=SUMPRODUCT(E$55:E$114,TRANSPOSE(SAP_Speadsheet!$F$37:$BM$37))} -> 8854.7954 | F7: {=SUMPRODUCT(F$55:F$114,TRANSPOSE(SAP_Speadsheet!$F$37:$BM$37))} -> 8505.264 | G7: {=SUMPRODUCT(G$55:G$114,TRANSPOSE(SAP_Speadsheet!$F$37:$BM$37))} -> 8155.7326 | H7: {=SUMPRODUCT(H$55:H$114,TRANSPOSE(SAP_Speadsheet!$F$37:$BM$37))} -> 7806.2012 | I7: {=SUMPRODUCT(I$55:I$114,TRANSPOSE(SAP_Speadsheet!$F$37:$BM$37))} -> 7456.6698 | ... BI7: {=SUMPRODUCT(BI$55:BI$114,TRANSPOSE(SAP_Speadsheet!$F$37:$BM$37))} -> 0
A8: ANR | B8: {=SUMPRODUCT(B$55:B$114,TRANSPOSE(SAP_Speadsheet!$F$43:$BM$43))} -> 10485.942 | C8: {=SUMPRODUCT(C$55:C$114,TRANSPOSE(SAP_Speadsheet!$F$43:$BM$43))} -> 9728.6239 | D8: {=SUMPRODUCT(D$55:D$114,TRANSPOSE(SAP_Speadsheet!$F$43:$BM$43))} -> 9379.0925 | E8: {=SUMPRODUCT(E$55:E$114,TRANSPOSE(SAP_Speadsheet!$F$43:$BM$43))} -> 9029.5611 | F8: {=SUMPRODUCT(F$55:F$114,TRANSPOSE(SAP_Speadsheet!$F$43:$BM$43))} -> 8680.0297 | G8: {=SUMPRODUCT(G$55:G$114,TRANSPOSE(SAP_Speadsheet!$F$43:$BM$43))} -> 8330.4983 | H8: {=SUMPRODUCT(H$55:H$114,TRANSPOSE(SAP_Speadsheet!$F$43:$BM$43))} -> 7980.9669 | I8: {=SUMPRODUCT(I$55:I$114,TRANSPOSE(SAP_Speadsheet!$F$43:$BM$43))} -> 7631.4355 | ... BI8: {=SUMPRODUCT(BI$55:BI$114,TRANSPOSE(SAP_Speadsheet!$F$43:$BM$43))} -> 0
A9: TOI | B9: {=SUMPRODUCT(B$55:B$114,TRANSPOSE(SAP_Speadsheet!$F$48:$BM$48))} -> 467.84793 | C9: {=SUMPRODUCT(C$55:C$114,TRANSPOSE(SAP_Speadsheet!$F$48:$BM$48))} -> 222.29767 | D9: {=SUMPRODUCT(D$55:D$114,TRANSPOSE(SAP_Speadsheet!$F$48:$BM$48))} -> 208.76174 | E9: {=SUMPRODUCT(E$55:E$114,TRANSPOSE(SAP_Speadsheet!$F$48:$BM$48))} -> 195.723 | F9: {=SUMPRODUCT(F$55:F$114,TRANSPOSE(SAP_Speadsheet!$F$48:$BM$48))} -> 183.08092 | G9: {=SUMPRODUCT(G$55:G$114,TRANSPOSE(SAP_Speadsheet!$F$48:$BM$48))} -> 170.7645 | H9: {=SUMPRODUCT(H$55:H$114,TRANSPOSE(SAP_Speadsheet!$F$48:$BM$48))} -> 158.7392 | I9: {=SUMPRODUCT(I$55:I$114,TRANSPOSE(SAP_Speadsheet!$F$48:$BM$48))} -> 146.9709 | ... BI9: {=SUMPRODUCT(BI$55:BI$114,TRANSPOSE(SAP_Speadsheet!$F$48:$BM$48))} -> 0
A10: Checking | B10: =B9-B11-B14 -> 0 | C10: =C9-C11-C14 -> 0 | D10: =D9-D11-D14 -> 0 | E10: =E9-E11-E14 -> 0 | F10: =F9-F11-F14 -> 0 | G10: =G9-G11-G14 -> 0 | H10: =H9-H11-H14 -> 0 | I10: =I9-I11-I14 -> 0 | ... BI10: =BI9-BI11-BI14 -> 0
A11: Net interest income | B11: {=SUMPRODUCT(B$55:B$114,TRANSPOSE(SAP_Speadsheet!$F$50:$BM$50))} -> 257.62085 | C11: {=SUMPRODUCT(C$55:C$114,TRANSPOSE(SAP_Speadsheet!$F$50:$BM$50))} -> 222.29767 | D11: {=SUMPRODUCT(D$55:D$114,TRANSPOSE(SAP_Speadsheet!$F$50:$BM$50))} -> 208.76174 | E11: {=SUMPRODUCT(E$55:E$114,TRANSPOSE(SAP_Speadsheet!$F$50:$BM$50))} -> 195.723 | F11: {=SUMPRODUCT(F$55:F$114,TRANSPOSE(SAP_Speadsheet!$F$50:$BM$50))} -> 183.08092 | G11: {=SUMPRODUCT(G$55:G$114,TRANSPOSE(SAP_Speadsheet!$F$50:$BM$50))} -> 170.7645 | H11: {=SUMPRODUCT(H$55:H$114,TRANSPOSE(SAP_Speadsheet!$F$50:$BM$50))} -> 158.7392 | I11: {=SUMPRODUCT(I$55:I$114,TRANSPOSE(SAP_Speadsheet!$F$50:$BM$50))} -> 146.9709 | ... BI11: {=SUMPRODUCT(BI$55:BI$114,TRANSPOSE(SAP_Speadsheet!$F$50:$BM$50))} -> 0
A12: Interest income | B12: {=SUMPRODUCT(B$55:B$114,TRANSPOSE(SAP_Speadsheet!$F$51:$BM$51))} -> 315.60754 | C12: {=SUMPRODUCT(C$55:C$114,TRANSPOSE(SAP_Speadsheet!$F$51:$BM$51))} -> 276.09643 | D12: {=SUMPRODUCT(D$55:D$114,TRANSPOSE(SAP_Speadsheet!$F$51:$BM$51))} -> 260.62761 | E12: {=SUMPRODUCT(E$55:E$114,TRANSPOSE(SAP_Speadsheet!$F$51:$BM$51))} -> 245.65598 | F12: {=SUMPRODUCT(F$55:F$114,TRANSPOSE(SAP_Speadsheet!$F$51:$BM$51))} -> 231.08101 | G12: {=SUMPRODUCT(G$55:G$114,TRANSPOSE(SAP_Speadsheet!$F$51:$BM$51))} -> 216.8317 | H12: {=SUMPRODUCT(H$55:H$114,TRANSPOSE(SAP_Speadsheet!$F$51:$BM$51))} -> 202.87351 | I12: {=SUMPRODUCT(I$55:I$114,TRANSPOSE(SAP_Speadsheet!$F$51:$BM$51))} -> 189.17232 | ... BI12: {=SUMPRODUCT(BI$55:BI$114,TRANSPOSE(SAP_Speadsheet!$F$51:$BM$51))} -> 0
A13: Cost of fund | B13: {=SUMPRODUCT(B$55:B$114,TRANSPOSE(SAP_Speadsheet!$F$52:$BM$52))} -> -57.986684 | C13: {=SUMPRODUCT(C$55:C$114,TRANSPOSE(SAP_Speadsheet!$F$52:$BM$52))} -> -53.798757 | D13: {=SUMPRODUCT(D$55:D$114,TRANSPOSE(SAP_Speadsheet!$F$52:$BM$52))} -> -51.865867 | E13: {=SUMPRODUCT(E$55:E$114,TRANSPOSE(SAP_Speadsheet!$F$52:$BM$52))} -> -49.932978 | F13: {=SUMPRODUCT(F$55:F$114,TRANSPOSE(SAP_Speadsheet!$F$52:$BM$52))} -> -48.000088 | G13: {=SUMPRODUCT(G$55:G$114,TRANSPOSE(SAP_Speadsheet!$F$52:$BM$52))} -> -46.067199 | H13: {=SUMPRODUCT(H$55:H$114,TRANSPOSE(SAP_Speadsheet!$F$52:$BM$52))} -> -44.134309 | I13: {=SUMPRODUCT(I$55:I$114,TRANSPOSE(SAP_Speadsheet!$F$52:$BM$52))} -> -42.20142 | ... BI13: {=SUMPRODUCT(BI$55:BI$114,TRANSPOSE(SAP_Speadsheet!$F$52:$BM$52))} -> 0
A14: Net fee income | B14: {=SUMPRODUCT(B$55:B$114,TRANSPOSE(SAP_Speadsheet!$F$54:$BM$54))} -> 210.22708 | C14: {=SUMPRODUCT(C$55:C$114,TRANSPOSE(SAP_Speadsheet!$F$54:$BM$54))} -> 0 | D14: {=SUMPRODUCT(D$55:D$114,TRANSPOSE(SAP_Speadsheet!$F$54:$BM$54))} -> 0 | E14: {=SUMPRODUCT(E$55:E$114,TRANSPOSE(SAP_Speadsheet!$F$54:$BM$54))} -> 0 | F14: {=SUMPRODUCT(F$55:F$114,TRANSPOSE(SAP_Speadsheet!$F$54:$BM$54))} -> 0 | G14: {=SUMPRODUCT(G$55:G$114,TRANSPOSE(SAP_Speadsheet!$F$54:$BM$54))} -> 0 | H14: {=SUMPRODUCT(H$55:H$114,TRANSPOSE(SAP_Speadsheet!$F$54:$BM$54))} -> 0 | I14: {=SUMPRODUCT(I$55:I$114,TRANSPOSE(SAP_Speadsheet!$F$54:$BM$54))} -> 0 | ... BI14: {=SUMPRODUCT(BI$55:BI$114,TRANSPOSE(SAP_Speadsheet!$F$54:$BM$54))} -> 0
A15: Early termination income | B15: {=SUMPRODUCT(B$55:B$114,TRANSPOSE(SAP_Speadsheet!$F$55:$BM$55))} -> 0 | C15: {=SUMPRODUCT(C$55:C$114,TRANSPOSE(SAP_Speadsheet!$F$55:$BM$55))} -> 0 | D15: {=SUMPRODUCT(D$55:D$114,TRANSPOSE(SAP_Speadsheet!$F$55:$BM$55))} -> 0 | E15: {=SUMPRODUCT(E$55:E$114,TRANSPOSE(SAP_Speadsheet!$F$55:$BM$55))} -> 0 | F15: {=SUMPRODUCT(F$55:F$114,TRANSPOSE(SAP_Speadsheet!$F$55:$BM$55))} -> 0 | G15: {=SUMPRODUCT(G$55:G$114,TRANSPOSE(SAP_Speadsheet!$F$55:$BM$55))} -> 0 | H15: {=SUMPRODUCT(H$55:H$114,TRANSPOSE(SAP_Speadsheet!$F$55:$BM$55))} -> 0 | I15: {=SUMPRODUCT(I$55:I$114,TRANSPOSE(SAP_Speadsheet!$F$55:$BM$55))} -> 0 | ... BI15: {=SUMPRODUCT(BI$55:BI$114,TRANSPOSE(SAP_Speadsheet!$F$55:$BM$55))} -> 0
A16: Monthly fee | B16: {=SUMPRODUCT(B$55:B$114,TRANSPOSE(SAP_Speadsheet!$F$56:$BM$56))} -> 0 | C16: {=SUMPRODUCT(C$55:C$114,TRANSPOSE(SAP_Speadsheet!$F$56:$BM$56))} -> 0 | D16: {=SUMPRODUCT(D$55:D$114,TRANSPOSE(SAP_Speadsheet!$F$56:$BM$56))} -> 0 | E16: {=SUMPRODUCT(E$55:E$114,TRANSPOSE(SAP_Speadsheet!$F$56:$BM$56))} -> 0 | F16: {=SUMPRODUCT(F$55:F$114,TRANSPOSE(SAP_Speadsheet!$F$56:$BM$56))} -> 0 | G16: {=SUMPRODUCT(G$55:G$114,TRANSPOSE(SAP_Speadsheet!$F$56:$BM$56))} -> 0 | H16: {=SUMPRODUCT(H$55:H$114,TRANSPOSE(SAP_Speadsheet!$F$56:$BM$56))} -> 0 | I16: {=SUMPRODUCT(I$55:I$114,TRANSPOSE(SAP_Speadsheet!$F$56:$BM$56))} -> 0 | ... BI16: {=SUMPRODUCT(BI$55:BI$114,TRANSPOSE(SAP_Speadsheet!$F$56:$BM$56))} -> 0
A17: Loan grant fee | B17: {=SUMPRODUCT(B$55:B$114,TRANSPOSE(SAP_Speadsheet!$F$57:$BM$57))} -> 210.22708 | C17: {=SUMPRODUCT(C$55:C$114,TRANSPOSE(SAP_Speadsheet!$F$57:$BM$57))} -> 0 | D17: {=SUMPRODUCT(D$55:D$114,TRANSPOSE(SAP_Speadsheet!$F$57:$BM$57))} -> 0 | E17: {=SUMPRODUCT(E$55:E$114,TRANSPOSE(SAP_Speadsheet!$F$57:$BM$57))} -> 0 | F17: {=SUMPRODUCT(F$55:F$114,TRANSPOSE(SAP_Speadsheet!$F$57:$BM$57))} -> 0 | G17: {=SUMPRODUCT(G$55:G$114,TRANSPOSE(SAP_Speadsheet!$F$57:$BM$57))} -> 0 | H17: {=SUMPRODUCT(H$55:H$114,TRANSPOSE(SAP_Speadsheet!$F$57:$BM$57))} -> 0 | I17: {=SUMPRODUCT(I$55:I$114,TRANSPOSE(SAP_Speadsheet!$F$57:$BM$57))} -> 0 | ... BI17: {=SUMPRODUCT(BI$55:BI$114,TRANSPOSE(SAP_Speadsheet!$F$57:$BM$57))} -> 0
A18: Other income | B18: {=SUMPRODUCT(B$55:B$114,TRANSPOSE(SAP_Speadsheet!$F$59:$BM$59))} -> 0 | C18: {=SUMPRODUCT(C$55:C$114,TRANSPOSE(SAP_Speadsheet!$F$59:$BM$59))} -> 0 | D18: {=SUMPRODUCT(D$55:D$114,TRANSPOSE(SAP_Speadsheet!$F$59:$BM$59))} -> 0 | E18: {=SUMPRODUCT(E$55:E$114,TRANSPOSE(SAP_Speadsheet!$F$59:$BM$59))} -> 0 | F18: {=SUMPRODUCT(F$55:F$114,TRANSPOSE(SAP_Speadsheet!$F$59:$BM$59))} -> 0 | G18: {=SUMPRODUCT(G$55:G$114,TRANSPOSE(SAP_Speadsheet!$F$59:$BM$59))} -> 0 | H18: {=SUMPRODUCT(H$55:H$114,TRANSPOSE(SAP_Speadsheet!$F$59:$BM$59))} -> 0 | I18: {=SUMPRODUCT(I$55:I$114,TRANSPOSE(SAP_Speadsheet!$F$59:$BM$59))} -> 0 | ... BI18: {=SUMPRODUCT(BI$55:BI$114,TRANSPOSE(SAP_Speadsheet!$F$59:$BM$59))} -> 0
A19: OPEX | B19: =B20+B24+B28+B29+B30 -> -76.693949 | C19: =C20+C24+C28+C29+C30 -> -53.696985 | D19: =D20+D24+D28+D29+D30 -> -51.738619 | E19: =E20+E24+E28+E29+E30 -> -49.780253 | F19: =F20+F24+F28+F29+F30 -> -47.821886 | G19: =G20+G24+G28+G29+G30 -> -45.86352 | H19: =H20+H24+H28+H29+H30 -> -43.905153 | I19: =I20+I24+I28+I29+I30 -> -41.946787 | ... BI19: =BI20+BI24+BI28+BI29+BI30 -> 0
A20: Sale incentive&mkt | B20: =SUM(B21:B23) -> 0 | C20: =SUM(C21:C23) -> 0 | D20: =SUM(D21:D23) -> 0 | E20: =SUM(E21:E23) -> 0 | F20: =SUM(F21:F23) -> 0 | G20: =SUM(G21:G23) -> 0 | H20: =SUM(H21:H23) -> 0 | I20: =SUM(I21:I23) -> 0 | ... BI20: =SUM(BI21:BI23) -> 0
A21: Lead Acquisition | B21: {=SUMPRODUCT(B$55:B$114,TRANSPOSE(SAP_Speadsheet!$F$64:$BM$64))} -> 0 | C21: {=SUMPRODUCT(C$55:C$114,TRANSPOSE(SAP_Speadsheet!$F$64:$BM$64))} -> 0 | D21: {=SUMPRODUCT(D$55:D$114,TRANSPOSE(SAP_Speadsheet!$F$64:$BM$64))} -> 0 | E21: {=SUMPRODUCT(E$55:E$114,TRANSPOSE(SAP_Speadsheet!$F$64:$BM$64))} -> 0 | F21: {=SUMPRODUCT(F$55:F$114,TRANSPOSE(SAP_Speadsheet!$F$64:$BM$64))} -> 0 | G21: {=SUMPRODUCT(G$55:G$114,TRANSPOSE(SAP_Speadsheet!$F$64:$BM$64))} -> 0 | H21: {=SUMPRODUCT(H$55:H$114,TRANSPOSE(SAP_Speadsheet!$F$64:$BM$64))} -> 0 | I21: {=SUMPRODUCT(I$55:I$114,TRANSPOSE(SAP_Speadsheet!$F$64:$BM$64))} -> 0 | ... BI21: {=SUMPRODUCT(BI$55:BI$114,TRANSPOSE(SAP_Speadsheet!$F$64:$BM$64))} -> 0
A22: Sharing performance | B22: {=SUMPRODUCT(B$55:B$114,TRANSPOSE(SAP_Speadsheet!$F$65:$BM$65))} -> 0 | C22: {=SUMPRODUCT(C$55:C$114,TRANSPOSE(SAP_Speadsheet!$F$65:$BM$65))} -> 0 | D22: {=SUMPRODUCT(D$55:D$114,TRANSPOSE(SAP_Speadsheet!$F$65:$BM$65))} -> 0 | E22: {=SUMPRODUCT(E$55:E$114,TRANSPOSE(SAP_Speadsheet!$F$65:$BM$65))} -> 0 | F22: {=SUMPRODUCT(F$55:F$114,TRANSPOSE(SAP_Speadsheet!$F$65:$BM$65))} -> 0 | G22: {=SUMPRODUCT(G$55:G$114,TRANSPOSE(SAP_Speadsheet!$F$65:$BM$65))} -> 0 | H22: {=SUMPRODUCT(H$55:H$114,TRANSPOSE(SAP_Speadsheet!$F$65:$BM$65))} -> 0 | I22: {=SUMPRODUCT(I$55:I$114,TRANSPOSE(SAP_Speadsheet!$F$65:$BM$65))} -> 0 | ... BI22: {=SUMPRODUCT(BI$55:BI$114,TRANSPOSE(SAP_Speadsheet!$F$65:$BM$65))} -> 0
A23: Marketing | B23: {=SUMPRODUCT(B$55:B$114,TRANSPOSE(SAP_Speadsheet!$F$74:$BM$74))} -> 0 | C23: {=SUMPRODUCT(C$55:C$114,TRANSPOSE(SAP_Speadsheet!$F$74:$BM$74))} -> 0 | D23: {=SUMPRODUCT(D$55:D$114,TRANSPOSE(SAP_Speadsheet!$F$74:$BM$74))} -> 0 | E23: {=SUMPRODUCT(E$55:E$114,TRANSPOSE(SAP_Speadsheet!$F$74:$BM$74))} -> 0 | F23: {=SUMPRODUCT(F$55:F$114,TRANSPOSE(SAP_Speadsheet!$F$74:$BM$74))} -> 0 | G23: {=SUMPRODUCT(G$55:G$114,TRANSPOSE(SAP_Speadsheet!$F$74:$BM$74))} -> 0 | H23: {=SUMPRODUCT(H$55:H$114,TRANSPOSE(SAP_Speadsheet!$F$74:$BM$74))} -> 0 | I23: {=SUMPRODUCT(I$55:I$114,TRANSPOSE(SAP_Speadsheet!$F$74:$BM$74))} -> 0 | ... AV23: {=SUMPRODUCT(AV$55:AV$114,TRANSPOSE(SAP_Speadsheet!$F$74:$BM$74))} -> 0 | AW23: 0 | AX23: {=SUMPRODUCT(AX$55:AX$114,TRANSPOSE(SAP_Speadsheet!$F$74:$BM$74))} -> 0 | AY23: {=SUMPRODUCT(AY$55:AY$114,TRANSPOSE(SAP_Speadsheet!$F$74:$BM$74))} -> 0 | AZ23: {=SUMPRODUCT(AZ$55:AZ$114,TRANSPOSE(SAP_Speadsheet!$F$74:$BM$74))} -> 0 | BA23: {=SUMPRODUCT(BA$55:BA$114,TRANSPOSE(SAP_Speadsheet!$F$74:$BM$74))} -> 0 | BB23: {=SUMPRODUCT(BB$55:BB$114,TRANSPOSE(SAP_Speadsheet!$F$74:$BM$74))} -> 0 | BC23: {=SUMPRODUCT(BC$55:BC$114,TRANSPOSE(SAP_Speadsheet!$F$74:$BM$74))} -> 0 | BD23: {=SUMPRODUCT(BD$55:BD$114,TRANSPOSE(SAP_Speadsheet!$F$74:$BM$74))} -> 0 | BE23: {=SUMPRODUCT(BE$55:BE$114,TRANSPOSE(SAP_Speadsheet!$F$74:$BM$74))} -> 0 | ... BI23: {=SUMPRODUCT(BI$55:BI$114,TRANSPOSE(SAP_Speadsheet!$F$74:$BM$74))} -> 0
A24: UW & Disbursal | B24: {=SUMPRODUCT(B$55:B$114,TRANSPOSE(SAP_Speadsheet!$F$76:$BM$76))} -> -20.645888 | C24: {=SUMPRODUCT(C$55:C$114,TRANSPOSE(SAP_Speadsheet!$F$76:$BM$76))} -> 0 | D24: {=SUMPRODUCT(D$55:D$114,TRANSPOSE(SAP_Speadsheet!$F$76:$BM$76))} -> 0 | E24: {=SUMPRODUCT(E$55:E$114,TRANSPOSE(SAP_Speadsheet!$F$76:$BM$76))} -> 0 | F24: {=SUMPRODUCT(F$55:F$114,TRANSPOSE(SAP_Speadsheet!$F$76:$BM$76))} -> 0 | G24: {=SUMPRODUCT(G$55:G$114,TRANSPOSE(SAP_Speadsheet!$F$76:$BM$76))} -> 0 | H24: {=SUMPRODUCT(H$55:H$114,TRANSPOSE(SAP_Speadsheet!$F$76:$BM$76))} -> 0 | I24: {=SUMPRODUCT(I$55:I$114,TRANSPOSE(SAP_Speadsheet!$F$76:$BM$76))} -> 0 | ... BI24: {=SUMPRODUCT(BI$55:BI$114,TRANSPOSE(SAP_Speadsheet!$F$76:$BM$76))} -> 0
A25: Underwriting | B25: {=SUMPRODUCT(B$55:B$114,TRANSPOSE(SAP_Speadsheet!$F$77:$BM$77))} -> -19.497449 | C25: {=SUMPRODUCT(C$55:C$114,TRANSPOSE(SAP_Speadsheet!$F$77:$BM$77))} -> 0 | D25: {=SUMPRODUCT(D$55:D$114,TRANSPOSE(SAP_Speadsheet!$F$77:$BM$77))} -> 0 | E25: {=SUMPRODUCT(E$55:E$114,TRANSPOSE(SAP_Speadsheet!$F$77:$BM$77))} -> 0 | F25: {=SUMPRODUCT(F$55:F$114,TRANSPOSE(SAP_Speadsheet!$F$77:$BM$77))} -> 0 | G25: {=SUMPRODUCT(G$55:G$114,TRANSPOSE(SAP_Speadsheet!$F$77:$BM$77))} -> 0 | H25: {=SUMPRODUCT(H$55:H$114,TRANSPOSE(SAP_Speadsheet!$F$77:$BM$77))} -> 0 | I25: {=SUMPRODUCT(I$55:I$114,TRANSPOSE(SAP_Speadsheet!$F$77:$BM$77))} -> 0 | ... BI25: {=SUMPRODUCT(BI$55:BI$114,TRANSPOSE(SAP_Speadsheet!$F$77:$BM$77))} -> 0
A26: Disbursement | B26: {=SUMPRODUCT(B$55:B$114,TRANSPOSE(SAP_Speadsheet!$F$78:$BM$78))} -> -1.148439 | C26: {=SUMPRODUCT(C$55:C$114,TRANSPOSE(SAP_Speadsheet!$F$78:$BM$78))} -> 0 | D26: {=SUMPRODUCT(D$55:D$114,TRANSPOSE(SAP_Speadsheet!$F$78:$BM$78))} -> 0 | E26: {=SUMPRODUCT(E$55:E$114,TRANSPOSE(SAP_Speadsheet!$F$78:$BM$78))} -> 0 | F26: {=SUMPRODUCT(F$55:F$114,TRANSPOSE(SAP_Speadsheet!$F$78:$BM$78))} -> 0 | G26: {=SUMPRODUCT(G$55:G$114,TRANSPOSE(SAP_Speadsheet!$F$78:$BM$78))} -> 0 | H26: {=SUMPRODUCT(H$55:H$114,TRANSPOSE(SAP_Speadsheet!$F$78:$BM$78))} -> 0 | I26: {=SUMPRODUCT(I$55:I$114,TRANSPOSE(SAP_Speadsheet!$F$78:$BM$78))} -> 0 | ... BI26: {=SUMPRODUCT(BI$55:BI$114,TRANSPOSE(SAP_Speadsheet!$F$78:$BM$78))} -> 0
A27: DOP | B27: {=SUMPRODUCT(B$55:B$114,TRANSPOSE(SAP_Speadsheet!$F$79:$BM$79))} -> 0 | C27: {=SUMPRODUCT(C$55:C$114,TRANSPOSE(SAP_Speadsheet!$F$79:$BM$79))} -> 0 | D27: {=SUMPRODUCT(D$55:D$114,TRANSPOSE(SAP_Speadsheet!$F$79:$BM$79))} -> 0 | E27: {=SUMPRODUCT(E$55:E$114,TRANSPOSE(SAP_Speadsheet!$F$79:$BM$79))} -> 0 | F27: {=SUMPRODUCT(F$55:F$114,TRANSPOSE(SAP_Speadsheet!$F$79:$BM$79))} -> 0 | G27: {=SUMPRODUCT(G$55:G$114,TRANSPOSE(SAP_Speadsheet!$F$79:$BM$79))} -> 0 | H27: {=SUMPRODUCT(H$55:H$114,TRANSPOSE(SAP_Speadsheet!$F$79:$BM$79))} -> 0 | I27: {=SUMPRODUCT(I$55:I$114,TRANSPOSE(SAP_Speadsheet!$F$79:$BM$79))} -> 0 | ... BI27: {=SUMPRODUCT(BI$55:BI$114,TRANSPOSE(SAP_Speadsheet!$F$79:$BM$79))} -> 0
A28: Collection | B28: {=SUMPRODUCT(B$55:B$114,TRANSPOSE(SAP_Speadsheet!$F$83:$BM$83))} -> -5.3296277 | C28: {=SUMPRODUCT(C$55:C$114,TRANSPOSE(SAP_Speadsheet!$F$83:$BM$83))} -> -4.7686143 | D28: {=SUMPRODUCT(D$55:D$114,TRANSPOSE(SAP_Speadsheet!$F$83:$BM$83))} -> -4.6003103 | E28: {=SUMPRODUCT(E$55:E$114,TRANSPOSE(SAP_Speadsheet!$F$83:$BM$83))} -> -4.4320062 | F28: {=SUMPRODUCT(F$55:F$114,TRANSPOSE(SAP_Speadsheet!$F$83:$BM$83))} -> -4.2637022 | G28: {=SUMPRODUCT(G$55:G$114,TRANSPOSE(SAP_Speadsheet!$F$83:$BM$83))} -> -4.0953982 | H28: {=SUMPRODUCT(H$55:H$114,TRANSPOSE(SAP_Speadsheet!$F$83:$BM$83))} -> -3.9270941 | I28: {=SUMPRODUCT(I$55:I$114,TRANSPOSE(SAP_Speadsheet!$F$83:$BM$83))} -> -3.7587901 | ... BI28: {=SUMPRODUCT(BI$55:BI$114,TRANSPOSE(SAP_Speadsheet!$F$83:$BM$83))} -> 0
A29: After-sales services | B29: {=SUMPRODUCT(B$55:B$114,TRANSPOSE(SAP_Speadsheet!$F$87:$BM$87))} -> -0.009042259 | C29: {=SUMPRODUCT(C$55:C$114,TRANSPOSE(SAP_Speadsheet!$F$87:$BM$87))} -> -0.0087231204 | D29: {=SUMPRODUCT(D$55:D$114,TRANSPOSE(SAP_Speadsheet!$F$87:$BM$87))} -> -0.0084039819 | E29: {=SUMPRODUCT(E$55:E$114,TRANSPOSE(SAP_Speadsheet!$F$87:$BM$87))} -> -0.0080848433 | F29: {=SUMPRODUCT(F$55:F$114,TRANSPOSE(SAP_Speadsheet!$F$87:$BM$87))} -> -0.0077657048 | G29: {=SUMPRODUCT(G$55:G$114,TRANSPOSE(SAP_Speadsheet!$F$87:$BM$87))} -> -0.0074465662 | H29: {=SUMPRODUCT(H$55:H$114,TRANSPOSE(SAP_Speadsheet!$F$87:$BM$87))} -> -0.0071274277 | I29: {=SUMPRODUCT(I$55:I$114,TRANSPOSE(SAP_Speadsheet!$F$87:$BM$87))} -> -0.0068082891 | ... BI29: {=SUMPRODUCT(BI$55:BI$114,TRANSPOSE(SAP_Speadsheet!$F$87:$BM$87))} -> 0
A30: Other support units | B30: {=SUMPRODUCT(B$55:B$114,TRANSPOSE(SAP_Speadsheet!$F$91:$BM$91))} -> -50.709391 | C30: {=SUMPRODUCT(C$55:C$114,TRANSPOSE(SAP_Speadsheet!$F$91:$BM$91))} -> -48.919648 | D30: {=SUMPRODUCT(D$55:D$114,TRANSPOSE(SAP_Speadsheet!$F$91:$BM$91))} -> -47.129905 | E30: {=SUMPRODUCT(E$55:E$114,TRANSPOSE(SAP_Speadsheet!$F$91:$BM$91))} -> -45.340162 | F30: {=SUMPRODUCT(F$55:F$114,TRANSPOSE(SAP_Speadsheet!$F$91:$BM$91))} -> -43.550418 | G30: {=SUMPRODUCT(G$55:G$114,TRANSPOSE(SAP_Speadsheet!$F$91:$BM$91))} -> -41.760675 | H30: {=SUMPRODUCT(H$55:H$114,TRANSPOSE(SAP_Speadsheet!$F$91:$BM$91))} -> -39.970932 | I30: {=SUMPRODUCT(I$55:I$114,TRANSPOSE(SAP_Speadsheet!$F$91:$BM$91))} -> -38.181189 | ... BI30: {=SUMPRODUCT(BI$55:BI$114,TRANSPOSE(SAP_Speadsheet!$F$91:$BM$91))} -> 0
A31: PROVISION | B31: {=SUMPRODUCT(B$55:B$114,TRANSPOSE(SAP_Speadsheet!$F$171:$BM$171))} -> -361.00195 | C31: {=SUMPRODUCT(C$55:C$114,TRANSPOSE(SAP_Speadsheet!$F$171:$BM$171))} -> -158.92085 | D31: {=SUMPRODUCT(D$55:D$114,TRANSPOSE(SAP_Speadsheet!$F$171:$BM$171))} -> -149.79145 | E31: {=SUMPRODUCT(E$55:E$114,TRANSPOSE(SAP_Speadsheet!$F$171:$BM$171))} -> -140.90388 | F31: {=SUMPRODUCT(F$55:F$114,TRANSPOSE(SAP_Speadsheet!$F$171:$BM$171))} -> -132.21485 | G31: {=SUMPRODUCT(G$55:G$114,TRANSPOSE(SAP_Speadsheet!$F$171:$BM$171))} -> -123.70332 | H31: {=SUMPRODUCT(H$55:H$114,TRANSPOSE(SAP_Speadsheet!$F$171:$BM$171))} -> -115.34849 | I31: {=SUMPRODUCT(I$55:I$114,TRANSPOSE(SAP_Speadsheet!$F$171:$BM$171))} -> -111.08085 | ... BI31: {=SUMPRODUCT(BI$55:BI$114,TRANSPOSE(SAP_Speadsheet!$F$171:$BM$171))} -> 0
A32: PBT | B32: {=SUMPRODUCT(B$55:B$114,TRANSPOSE(SAP_Speadsheet!$F$177:$BM$177))} -> 30.152034 | C32: {=SUMPRODUCT(C$55:C$114,TRANSPOSE(SAP_Speadsheet!$F$177:$BM$177))} -> 9.6798343 | D32: {=SUMPRODUCT(D$55:D$114,TRANSPOSE(SAP_Speadsheet!$F$177:$BM$177))} -> 7.2316734 | E32: {=SUMPRODUCT(E$55:E$114,TRANSPOSE(SAP_Speadsheet!$F$177:$BM$177))} -> 5.0388668 | F32: {=SUMPRODUCT(F$55:F$114,TRANSPOSE(SAP_Speadsheet!$F$177:$BM$177))} -> 3.0441846 | G32: {=SUMPRODUCT(G$55:G$114,TRANSPOSE(SAP_Speadsheet!$F$177:$BM$177))} -> 1.1976579 | H32: {=SUMPRODUCT(H$55:H$114,TRANSPOSE(SAP_Speadsheet!$F$177:$BM$177))} -> -0.51444668 | I32: {=SUMPRODUCT(I$55:I$114,TRANSPOSE(SAP_Speadsheet!$F$177:$BM$177))} -> -6.0567319 | ... BI32: {=SUMPRODUCT(BI$55:BI$114,TRANSPOSE(SAP_Speadsheet!$F$177:$BM$177))} -> 0
A33: Checking | B33: =B9+B19+B31-B32 -> 0 | C33: =C9+C19+C31-C32 -> 0 | D33: =D9+D19+D31-D32 -> 0 | E33: =E9+E19+E31-E32 -> 0 | F33: =F9+F19+F31-F32 -> -2.1316282e-14 | G33: =G9+G19+G31-G32 -> 0 | H33: =H9+H19+H31-H32 -> -1.1768364e-14 | I33: =I9+I19+I31-I32 -> 1.4210855e-14 | ... BI33: =BI9+BI19+BI31-BI32 -> 0
A35: EOP BY BUCKET
A36: B0 | B36: {=SUMPRODUCT(B$55:B$114,TRANSPOSE(SAP_Speadsheet!$F$19:$BM$19))} -> 9670.9512 | C36: {=SUMPRODUCT(C$55:C$114,TRANSPOSE(SAP_Speadsheet!$F$19:$BM$19))} -> 9129.9517 | D36: {=SUMPRODUCT(D$55:D$114,TRANSPOSE(SAP_Speadsheet!$F$19:$BM$19))} -> 8605.4703 | E36: {=SUMPRODUCT(E$55:E$114,TRANSPOSE(SAP_Speadsheet!$F$19:$BM$19))} -> 8094.8824 | F36: {=SUMPRODUCT(F$55:F$114,TRANSPOSE(SAP_Speadsheet!$F$19:$BM$19))} -> 7595.7005 | G36: {=SUMPRODUCT(G$55:G$114,TRANSPOSE(SAP_Speadsheet!$F$19:$BM$19))} -> 7106.7161 | H36: {=SUMPRODUCT(H$55:H$114,TRANSPOSE(SAP_Speadsheet!$F$19:$BM$19))} -> 6626.7338 | I36: {=SUMPRODUCT(I$55:I$114,TRANSPOSE(SAP_Speadsheet!$F$19:$BM$19))} -> 6155.6711 | ... BI36: {=SUMPRODUCT(BI$55:BI$114,TRANSPOSE(SAP_Speadsheet!$F$19:$BM$19))} -> 0
A37: B1 | B37: {=SUMPRODUCT(B$55:B$114,TRANSPOSE(SAP_Speadsheet!$F$20:$BM$20))} -> 232.43838 | C37: {=SUMPRODUCT(C$55:C$114,TRANSPOSE(SAP_Speadsheet!$F$20:$BM$20))} -> 203.08997 | D37: {=SUMPRODUCT(D$55:D$114,TRANSPOSE(SAP_Speadsheet!$F$20:$BM$20))} -> 191.72899 | E37: {=SUMPRODUCT(E$55:E$114,TRANSPOSE(SAP_Speadsheet!$F$20:$BM$20))} -> 180.71488 | F37: {=SUMPRODUCT(F$55:F$114,TRANSPOSE(SAP_Speadsheet!$F$20:$BM$20))} -> 169.99253 | G37: {=SUMPRODUCT(G$55:G$114,TRANSPOSE(SAP_Speadsheet!$F$20:$BM$20))} -> 159.50971 | H37: {=SUMPRODUCT(H$55:H$114,TRANSPOSE(SAP_Speadsheet!$F$20:$BM$20))} -> 149.24104 | I37: {=SUMPRODUCT(I$55:I$114,TRANSPOSE(SAP_Speadsheet!$F$20:$BM$20))} -> 139.16141 | ... BI37: {=SUMPRODUCT(BI$55:BI$114,TRANSPOSE(SAP_Speadsheet!$F$20:$BM$20))} -> 0
A38: B2 | B38: {=SUMPRODUCT(B$55:B$114,TRANSPOSE(SAP_Speadsheet!$F$21:$BM$21))} -> 0 | C38: {=SUMPRODUCT(C$55:C$114,TRANSPOSE(SAP_Speadsheet!$F$21:$BM$21))} -> 220.81646 | D38: {=SUMPRODUCT(D$55:D$114,TRANSPOSE(SAP_Speadsheet!$F$21:$BM$21))} -> 192.93548 | E38: {=SUMPRODUCT(E$55:E$114,TRANSPOSE(SAP_Speadsheet!$F$21:$BM$21))} -> 182.14254 | F38: {=SUMPRODUCT(F$55:F$114,TRANSPOSE(SAP_Speadsheet!$F$21:$BM$21))} -> 171.67913 | G38: {=SUMPRODUCT(G$55:G$114,TRANSPOSE(SAP_Speadsheet!$F$21:$BM$21))} -> 161.4929 | H38: {=SUMPRODUCT(H$55:H$114,TRANSPOSE(SAP_Speadsheet!$F$21:$BM$21))} -> 151.53423 | I38: {=SUMPRODUCT(I$55:I$114,TRANSPOSE(SAP_Speadsheet!$F$21:$BM$21))} -> 141.77899 | ... BI38: {=SUMPRODUCT(BI$55:BI$114,TRANSPOSE(SAP_Speadsheet!$F$21:$BM$21))} -> 0
A39: B3 | B39: {=SUMPRODUCT(B$55:B$114,TRANSPOSE(SAP_Speadsheet!$F$22:$BM$22))} -> 0 | C39: {=SUMPRODUCT(C$55:C$114,TRANSPOSE(SAP_Speadsheet!$F$22:$BM$22))} -> 0 | D39: {=SUMPRODUCT(D$55:D$114,TRANSPOSE(SAP_Speadsheet!$F$22:$BM$22))} -> 214.19197 | E39: {=SUMPRODUCT(E$55:E$114,TRANSPOSE(SAP_Speadsheet!$F$22:$BM$22))} -> 187.14741 | F39: {=SUMPRODUCT(F$55:F$114,TRANSPOSE(SAP_Speadsheet!$F$22:$BM$22))} -> 176.67826 | G39: {=SUMPRODUCT(G$55:G$114,TRANSPOSE(SAP_Speadsheet!$F$22:$BM$22))} -> 166.52876 | H39: {=SUMPRODUCT(H$55:H$114,TRANSPOSE(SAP_Speadsheet!$F$22:$BM$22))} -> 156.64812 | I39: {=SUMPRODUCT(I$55:I$114,TRANSPOSE(SAP_Speadsheet!$F$22:$BM$22))} -> 146.9882 | ... BI39: {=SUMPRODUCT(BI$55:BI$114,TRANSPOSE(SAP_Speadsheet!$F$22:$BM$22))} -> 0
A40: B4 | B40: {=SUMPRODUCT(B$55:B$114,TRANSPOSE(SAP_Speadsheet!$F$23:$BM$23))} -> 0 | C40: {=SUMPRODUCT(C$55:C$114,TRANSPOSE(SAP_Speadsheet!$F$23:$BM$23))} -> 0 | D40: {=SUMPRODUCT(D$55:D$114,TRANSPOSE(SAP_Speadsheet!$F$23:$BM$23))} -> 0 | E40: {=SUMPRODUCT(E$55:E$114,TRANSPOSE(SAP_Speadsheet!$F$23:$BM$23))} -> 209.90813 | F40: {=SUMPRODUCT(F$55:F$114,TRANSPOSE(SAP_Speadsheet!$F$23:$BM$23))} -> 183.40446 | G40: {=SUMPRODUCT(G$55:G$114,TRANSPOSE(SAP_Speadsheet!$F$23:$BM$23))} -> 173.1447 | H40: {=SUMPRODUCT(H$55:H$114,TRANSPOSE(SAP_Speadsheet!$F$23:$BM$23))} -> 163.19818 | I40: {=SUMPRODUCT(I$55:I$114,TRANSPOSE(SAP_Speadsheet!$F$23:$BM$23))} -> 153.51515 | ... BI40: {=SUMPRODUCT(BI$55:BI$114,TRANSPOSE(SAP_Speadsheet!$F$23:$BM$23))} -> 0
A41: B5 | B41: {=SUMPRODUCT(B$55:B$114,TRANSPOSE(SAP_Speadsheet!$F$24:$BM$24))} -> 0 | C41: {=SUMPRODUCT(C$55:C$114,TRANSPOSE(SAP_Speadsheet!$F$24:$BM$24))} -> 0 | D41: {=SUMPRODUCT(D$55:D$114,TRANSPOSE(SAP_Speadsheet!$F$24:$BM$24))} -> 0 | E41: {=SUMPRODUCT(E$55:E$114,TRANSPOSE(SAP_Speadsheet!$F$24:$BM$24))} -> 0 | F41: {=SUMPRODUCT(F$55:F$114,TRANSPOSE(SAP_Speadsheet!$F$24:$BM$24))} -> 207.80905 | G41: {=SUMPRODUCT(G$55:G$114,TRANSPOSE(SAP_Speadsheet!$F$24:$BM$24))} -> 181.57042 | H41: {=SUMPRODUCT(H$55:H$114,TRANSPOSE(SAP_Speadsheet!$F$24:$BM$24))} -> 171.41325 | I41: {=SUMPRODUCT(I$55:I$114,TRANSPOSE(SAP_Speadsheet!$F$24:$BM$24))} -> 161.5662 | ... BI41: {=SUMPRODUCT(BI$55:BI$114,TRANSPOSE(SAP_Speadsheet!$F$24:$BM$24))} -> 0
A42: B6 | B42: {=SUMPRODUCT(B$55:B$114,TRANSPOSE(SAP_Speadsheet!$F$25:$BM$25))} -> 0 | C42: {=SUMPRODUCT(C$55:C$114,TRANSPOSE(SAP_Speadsheet!$F$25:$BM$25))} -> 0 | D42: {=SUMPRODUCT(D$55:D$114,TRANSPOSE(SAP_Speadsheet!$F$25:$BM$25))} -> 0 | E42: {=SUMPRODUCT(E$55:E$114,TRANSPOSE(SAP_Speadsheet!$F$25:$BM$25))} -> 0 | F42: {=SUMPRODUCT(F$55:F$114,TRANSPOSE(SAP_Speadsheet!$F$25:$BM$25))} -> 0 | G42: {=SUMPRODUCT(G$55:G$114,TRANSPOSE(SAP_Speadsheet!$F$25:$BM$25))} -> 206.77 | H42: {=SUMPRODUCT(H$55:H$114,TRANSPOSE(SAP_Speadsheet!$F$25:$BM$25))} -> 180.66257 | I42: {=SUMPRODUCT(I$55:I$114,TRANSPOSE(SAP_Speadsheet!$F$25:$BM$25))} -> 170.55618 | ... BI42: {=SUMPRODUCT(BI$55:BI$114,TRANSPOSE(SAP_Speadsheet!$F$25:$BM$25))} -> 0
A43: B7 | B43: {=SUMPRODUCT(B$55:B$114,TRANSPOSE(SAP_Speadsheet!$F$26:$BM$26))} -> 0 | C43: {=SUMPRODUCT(C$55:C$114,TRANSPOSE(SAP_Speadsheet!$F$26:$BM$26))} -> 0 | D43: {=SUMPRODUCT(D$55:D$114,TRANSPOSE(SAP_Speadsheet!$F$26:$BM$26))} -> 0 | E43: {=SUMPRODUCT(E$55:E$114,TRANSPOSE(SAP_Speadsheet!$F$26:$BM$26))} -> 0 | F43: {=SUMPRODUCT(F$55:F$114,TRANSPOSE(SAP_Speadsheet!$F$26:$BM$26))} -> 0 | G43: {=SUMPRODUCT(G$55:G$114,TRANSPOSE(SAP_Speadsheet!$F$26:$BM$26))} -> 0 | H43: {=SUMPRODUCT(H$55:H$114,TRANSPOSE(SAP_Speadsheet!$F$26:$BM$26))} -> 206.77 | I43: {=SUMPRODUCT(I$55:I$114,TRANSPOSE(SAP_Speadsheet!$F$26:$BM$26))} -> 180.66257 | ... BI43: {=SUMPRODUCT(BI$55:BI$114,TRANSPOSE(SAP_Speadsheet!$F$26:$BM$26))} -> 0
A44: B8 | B44: {=SUMPRODUCT(B$55:B$114,TRANSPOSE(SAP_Speadsheet!$F$27:$BM$27))} -> 0 | C44: {=SUMPRODUCT(C$55:C$114,TRANSPOSE(SAP_Speadsheet!$F$27:$BM$27))} -> 0 | D44: {=SUMPRODUCT(D$55:D$114,TRANSPOSE(SAP_Speadsheet!$F$27:$BM$27))} -> 0 | E44: {=SUMPRODUCT(E$55:E$114,TRANSPOSE(SAP_Speadsheet!$F$27:$BM$27))} -> 0 | F44: {=SUMPRODUCT(F$55:F$114,TRANSPOSE(SAP_Speadsheet!$F$27:$BM$27))} -> 0 | G44: {=SUMPRODUCT(G$55:G$114,TRANSPOSE(SAP_Speadsheet!$F$27:$BM$27))} -> 0 | H44: {=SUMPRODUCT(H$55:H$114,TRANSPOSE(SAP_Speadsheet!$F$27:$BM$27))} -> 0 | I44: {=SUMPRODUCT(I$55:I$114,TRANSPOSE(SAP_Speadsheet!$F$27:$BM$27))} -> 206.77 | ... BI44: {=SUMPRODUCT(BI$55:BI$114,TRANSPOSE(SAP_Speadsheet!$F$27:$BM$27))} -> 0
A45: B9 | B45: {=SUMPRODUCT(B$55:B$114,TRANSPOSE(SAP_Speadsheet!$F$28:$BM$28))} -> 0 | C45: {=SUMPRODUCT(C$55:C$114,TRANSPOSE(SAP_Speadsheet!$F$28:$BM$28))} -> 0 | D45: {=SUMPRODUCT(D$55:D$114,TRANSPOSE(SAP_Speadsheet!$F$28:$BM$28))} -> 0 | E45: {=SUMPRODUCT(E$55:E$114,TRANSPOSE(SAP_Speadsheet!$F$28:$BM$28))} -> 0 | F45: {=SUMPRODUCT(F$55:F$114,TRANSPOSE(SAP_Speadsheet!$F$28:$BM$28))} -> 0 | G45: {=SUMPRODUCT(G$55:G$114,TRANSPOSE(SAP_Speadsheet!$F$28:$BM$28))} -> 0 | H45: {=SUMPRODUCT(H$55:H$114,TRANSPOSE(SAP_Speadsheet!$F$28:$BM$28))} -> 0 | I45: {=SUMPRODUCT(I$55:I$114,TRANSPOSE(SAP_Speadsheet!$F$28:$BM$28))} -> 0 | ... BI45: {=SUMPRODUCT(BI$55:BI$114,TRANSPOSE(SAP_Speadsheet!$F$28:$BM$28))} -> 0
A46: B10 | B46: {=SUMPRODUCT(B$55:B$114,TRANSPOSE(SAP_Speadsheet!$F$29:$BM$29))} -> 0 | C46: {=SUMPRODUCT(C$55:C$114,TRANSPOSE(SAP_Speadsheet!$F$29:$BM$29))} -> 0 | D46: {=SUMPRODUCT(D$55:D$114,TRANSPOSE(SAP_Speadsheet!$F$29:$BM$29))} -> 0 | E46: {=SUMPRODUCT(E$55:E$114,TRANSPOSE(SAP_Speadsheet!$F$29:$BM$29))} -> 0 | F46: {=SUMPRODUCT(F$55:F$114,TRANSPOSE(SAP_Speadsheet!$F$29:$BM$29))} -> 0 | G46: {=SUMPRODUCT(G$55:G$114,TRANSPOSE(SAP_Speadsheet!$F$29:$BM$29))} -> 0 | H46: {=SUMPRODUCT(H$55:H$114,TRANSPOSE(SAP_Speadsheet!$F$29:$BM$29))} -> 0 | I46: {=SUMPRODUCT(I$55:I$114,TRANSPOSE(SAP_Speadsheet!$F$29:$BM$29))} -> 0 | ... BI46: {=SUMPRODUCT(BI$55:BI$114,TRANSPOSE(SAP_Speadsheet!$F$29:$BM$29))} -> 0
A47: B11 | B47: {=SUMPRODUCT(B$55:B$114,TRANSPOSE(SAP_Speadsheet!$F$30:$BM$30))} -> 0 | C47: {=SUMPRODUCT(C$55:C$114,TRANSPOSE(SAP_Speadsheet!$F$30:$BM$30))} -> 0 | D47: {=SUMPRODUCT(D$55:D$114,TRANSPOSE(SAP_Speadsheet!$F$30:$BM$30))} -> 0 | E47: {=SUMPRODUCT(E$55:E$114,TRANSPOSE(SAP_Speadsheet!$F$30:$BM$30))} -> 0 | F47: {=SUMPRODUCT(F$55:F$114,TRANSPOSE(SAP_Speadsheet!$F$30:$BM$30))} -> 0 | G47: {=SUMPRODUCT(G$55:G$114,TRANSPOSE(SAP_Speadsheet!$F$30:$BM$30))} -> 0 | H47: {=SUMPRODUCT(H$55:H$114,TRANSPOSE(SAP_Speadsheet!$F$30:$BM$30))} -> 0 | I47: {=SUMPRODUCT(I$55:I$114,TRANSPOSE(SAP_Speadsheet!$F$30:$BM$30))} -> 0 | ... BI47: {=SUMPRODUCT(BI$55:BI$114,TRANSPOSE(SAP_Speadsheet!$F$30:$BM$30))} -> 0
A48: B12 | B48: {=SUMPRODUCT(B$55:B$114,TRANSPOSE(SAP_Speadsheet!$F$31:$BM$31))} -> 0 | C48: {=SUMPRODUCT(C$55:C$114,TRANSPOSE(SAP_Speadsheet!$F$31:$BM$31))} -> 0 | D48: {=SUMPRODUCT(D$55:D$114,TRANSPOSE(SAP_Speadsheet!$F$31:$BM$31))} -> 0 | E48: {=SUMPRODUCT(E$55:E$114,TRANSPOSE(SAP_Speadsheet!$F$31:$BM$31))} -> 0 | F48: {=SUMPRODUCT(F$55:F$114,TRANSPOSE(SAP_Speadsheet!$F$31:$BM$31))} -> 0 | G48: {=SUMPRODUCT(G$55:G$114,TRANSPOSE(SAP_Speadsheet!$F$31:$BM$31))} -> 0 | H48: {=SUMPRODUCT(H$55:H$114,TRANSPOSE(SAP_Speadsheet!$F$31:$BM$31))} -> 0 | I48: {=SUMPRODUCT(I$55:I$114,TRANSPOSE(SAP_Speadsheet!$F$31:$BM$31))} -> 0 | ... BI48: {=SUMPRODUCT(BI$55:BI$114,TRANSPOSE(SAP_Speadsheet!$F$31:$BM$31))} -> 0
A49: B13+ | B49: {=SUMPRODUCT(B$55:B$114,TRANSPOSE(SAP_Speadsheet!$F$32:$BM$32))} -> 0 | C49: {=SUMPRODUCT(C$55:C$114,TRANSPOSE(SAP_Speadsheet!$F$32:$BM$32))} -> 0 | D49: {=SUMPRODUCT(D$55:D$114,TRANSPOSE(SAP_Speadsheet!$F$32:$BM$32))} -> 0 | E49: {=SUMPRODUCT(E$55:E$114,TRANSPOSE(SAP_Speadsheet!$F$32:$BM$32))} -> 0 | F49: {=SUMPRODUCT(F$55:F$114,TRANSPOSE(SAP_Speadsheet!$F$32:$BM$32))} -> 0 | G49: {=SUMPRODUCT(G$55:G$114,TRANSPOSE(SAP_Speadsheet!$F$32:$BM$32))} -> 0 | H49: {=SUMPRODUCT(H$55:H$114,TRANSPOSE(SAP_Speadsheet!$F$32:$BM$32))} -> 0 | I49: {=SUMPRODUCT(I$55:I$114,TRANSPOSE(SAP_Speadsheet!$F$32:$BM$32))} -> 0 | ... BI49: {=SUMPRODUCT(BI$55:BI$114,TRANSPOSE(SAP_Speadsheet!$F$32:$BM$32))} -> 0
A50: B14+ | B50: {=SUMPRODUCT(B$55:B$114,TRANSPOSE(SAP_Speadsheet!$F$33:$BM$33))} -> 0 | C50: {=SUMPRODUCT(C$55:C$114,TRANSPOSE(SAP_Speadsheet!$F$33:$BM$33))} -> 0 | D50: {=SUMPRODUCT(D$55:D$114,TRANSPOSE(SAP_Speadsheet!$F$33:$BM$33))} -> 0 | E50: {=SUMPRODUCT(E$55:E$114,TRANSPOSE(SAP_Speadsheet!$F$33:$BM$33))} -> 0 | F50: {=SUMPRODUCT(F$55:F$114,TRANSPOSE(SAP_Speadsheet!$F$33:$BM$33))} -> 0 | G50: {=SUMPRODUCT(G$55:G$114,TRANSPOSE(SAP_Speadsheet!$F$33:$BM$33))} -> 0 | H50: {=SUMPRODUCT(H$55:H$114,TRANSPOSE(SAP_Speadsheet!$F$33:$BM$33))} -> 0 | I50: {=SUMPRODUCT(I$55:I$114,TRANSPOSE(SAP_Speadsheet!$F$33:$BM$33))} -> 0 | ... BI50: {=SUMPRODUCT(BI$55:BI$114,TRANSPOSE(SAP_Speadsheet!$F$33:$BM$33))} -> 0
A51: Checking | B51: =SUM(B36:B50)-B7 -> 0 | C51: =SUM(C36:C50)-C7 -> 0 | D51: =SUM(D36:D50)-D7 -> 0 | E51: =SUM(E36:E50)-E7 -> 0 | F51: =SUM(F36:F50)-F7 -> 0 | G51: =SUM(G36:G50)-G7 -> 0 | H51: =SUM(H36:H50)-H7 -> 0 | I51: =SUM(I36:I50)-I7 -> 0 | ... BI51: =SUM(BI36:BI50)-BI7 -> 0
A54: No. of account | B54: =ROUND('Saleplan&PnL'!D6,0) -> 1390 | C54: =ROUND('Saleplan&PnL'!E6,0) -> 0 | D54: =ROUND('Saleplan&PnL'!F6,0) -> 0 | E54: =ROUND('Saleplan&PnL'!G6,0) -> 0 | F54: =ROUND('Saleplan&PnL'!H6,0) -> 0 | G54: =ROUND('Saleplan&PnL'!I6,0) -> 0 | H54: =ROUND('Saleplan&PnL'!J6,0) -> 0 | I54: =ROUND('Saleplan&PnL'!K6,0) -> 0 | ... BI54: =ROUND('Saleplan&PnL'!BK6,0) -> 0
A55: 1 | B55: =IF($A55>B$5,"",OFFSET(B$54,0,-($A55-1))) -> 1390 | C55: =IF($A55>C$5,"",OFFSET(C$54,0,-($A55-1))) -> 0 | D55: =IF($A55>D$5,"",OFFSET(D$54,0,-($A55-1))) -> 0 | E55: =IF($A55>E$5,"",OFFSET(E$54,0,-($A55-1))) -> 0 | F55: =IF($A55>F$5,"",OFFSET(F$54,0,-($A55-1))) -> 0 | G55: =IF($A55>G$5,"",OFFSET(G$54,0,-($A55-1))) -> 0 | H55: =IF($A55>H$5,"",OFFSET(H$54,0,-($A55-1))) -> 0 | I55: =IF($A55>I$5,"",OFFSET(I$54,0,-($A55-1))) -> 0 | ... BI55: =IF($A55>BI$5,"",OFFSET(BI$54,0,-($A55-1))) -> 0
A56: 2 | B56: =IF($A56>B$5,"",OFFSET(B$54,0,-($A56-1))) | C56: =IF($A56>C$5,"",OFFSET(C$54,0,-($A56-1))) -> 1390 | D56: =IF($A56>D$5,"",OFFSET(D$54,0,-($A56-1))) -> 0 | E56: =IF($A56>E$5,"",OFFSET(E$54,0,-($A56-1))) -> 0 | F56: =IF($A56>F$5,"",OFFSET(F$54,0,-($A56-1))) -> 0 | G56: =IF($A56>G$5,"",OFFSET(G$54,0,-($A56-1))) -> 0 | H56: =IF($A56>H$5,"",OFFSET(H$54,0,-($A56-1))) -> 0 | I56: =IF($A56>I$5,"",OFFSET(I$54,0,-($A56-1))) -> 0 | ... BI56: =IF($A56>BI$5,"",OFFSET(BI$54,0,-($A56-1))) -> 0
A57: 3 | B57: =IF($A57>B$5,"",OFFSET(B$54,0,-($A57-1))) | C57: =IF($A57>C$5,"",OFFSET(C$54,0,-($A57-1))) | D57: =IF($A57>D$5,"",OFFSET(D$54,0,-($A57-1))) -> 1390 | E57: =IF($A57>E$5,"",OFFSET(E$54,0,-($A57-1))) -> 0 | F57: =IF($A57>F$5,"",OFFSET(F$54,0,-($A57-1))) -> 0 | G57: =IF($A57>G$5,"",OFFSET(G$54,0,-($A57-1))) -> 0 | H57: =IF($A57>H$5,"",OFFSET(H$54,0,-($A57-1))) -> 0 | I57: =IF($A57>I$5,"",OFFSET(I$54,0,-($A57-1))) -> 0 | ... BI57: =IF($A57>BI$5,"",OFFSET(BI$54,0,-($A57-1))) -> 0
A58: 4 | B58: =IF($A58>B$5,"",OFFSET(B$54,0,-($A58-1))) | C58: =IF($A58>C$5,"",OFFSET(C$54,0,-($A58-1))) | D58: =IF($A58>D$5,"",OFFSET(D$54,0,-($A58-1))) | E58: =IF($A58>E$5,"",OFFSET(E$54,0,-($A58-1))) -> 1390 | F58: =IF($A58>F$5,"",OFFSET(F$54,0,-($A58-1))) -> 0 | G58: =IF($A58>G$5,"",OFFSET(G$54,0,-($A58-1))) -> 0 | H58: =IF($A58>H$5,"",OFFSET(H$54,0,-($A58-1))) -> 0 | I58: =IF($A58>I$5,"",OFFSET(I$54,0,-($A58-1))) -> 0 | ... BI58: =IF($A58>BI$5,"",OFFSET(BI$54,0,-($A58-1))) -> 0
A59: 5 | B59: =IF($A59>B$5,"",OFFSET(B$54,0,-($A59-1))) | C59: =IF($A59>C$5,"",OFFSET(C$54,0,-($A59-1))) | D59: =IF($A59>D$5,"",OFFSET(D$54,0,-($A59-1))) | E59: =IF($A59>E$5,"",OFFSET(E$54,0,-($A59-1))) | F59: =IF($A59>F$5,"",OFFSET(F$54,0,-($A59-1))) -> 1390 | G59: =IF($A59>G$5,"",OFFSET(G$54,0,-($A59-1))) -> 0 | H59: =IF($A59>H$5,"",OFFSET(H$54,0,-($A59-1))) -> 0 | I59: =IF($A59>I$5,"",OFFSET(I$54,0,-($A59-1))) -> 0 | ... BI59: =IF($A59>BI$5,"",OFFSET(BI$54,0,-($A59-1))) -> 0
A60: 6 | B60: =IF($A60>B$5,"",OFFSET(B$54,0,-($A60-1))) | C60: =IF($A60>C$5,"",OFFSET(C$54,0,-($A60-1))) | D60: =IF($A60>D$5,"",OFFSET(D$54,0,-($A60-1))) | E60: =IF($A60>E$5,"",OFFSET(E$54,0,-($A60-1))) | F60: =IF($A60>F$5,"",OFFSET(F$54,0,-($A60-1))) | G60: =IF($A60>G$5,"",OFFSET(G$54,0,-($A60-1))) -> 1390 | H60: =IF($A60>H$5,"",OFFSET(H$54,0,-($A60-1))) -> 0 | I60: =IF($A60>I$5,"",OFFSET(I$54,0,-($A60-1))) -> 0 | ... BI60: =IF($A60>BI$5,"",OFFSET(BI$54,0,-($A60-1))) -> 0
A61: 7 | B61: =IF($A61>B$5,"",OFFSET(B$54,0,-($A61-1))) | C61: =IF($A61>C$5,"",OFFSET(C$54,0,-($A61-1))) | D61: =IF($A61>D$5,"",OFFSET(D$54,0,-($A61-1))) | E61: =IF($A61>E$5,"",OFFSET(E$54,0,-($A61-1))) | F61: =IF($A61>F$5,"",OFFSET(F$54,0,-($A61-1))) | G61: =IF($A61>G$5,"",OFFSET(G$54,0,-($A61-1))) | H61: =IF($A61>H$5,"",OFFSET(H$54,0,-($A61-1))) -> 1390 | I61: =IF($A61>I$5,"",OFFSET(I$54,0,-($A61-1))) -> 0 | ... BI61: =IF($A61>BI$5,"",OFFSET(BI$54,0,-($A61-1))) -> 0
A62: 8 | B62: =IF($A62>B$5,"",OFFSET(B$54,0,-($A62-1))) | C62: =IF($A62>C$5,"",OFFSET(C$54,0,-($A62-1))) | D62: =IF($A62>D$5,"",OFFSET(D$54,0,-($A62-1))) | E62: =IF($A62>E$5,"",OFFSET(E$54,0,-($A62-1))) | F62: =IF($A62>F$5,"",OFFSET(F$54,0,-($A62-1))) | G62: =IF($A62>G$5,"",OFFSET(G$54,0,-($A62-1))) | H62: =IF($A62>H$5,"",OFFSET(H$54,0,-($A62-1))) | I62: =IF($A62>I$5,"",OFFSET(I$54,0,-($A62-1))) -> 1390 | ... BI62: =IF($A62>BI$5,"",OFFSET(BI$54,0,-($A62-1))) -> 0
A63: 9 | B63: =IF($A63>B$5,"",OFFSET(B$54,0,-($A63-1))) | C63: =IF($A63>C$5,"",OFFSET(C$54,0,-($A63-1))) | D63: =IF($A63>D$5,"",OFFSET(D$54,0,-($A63-1))) | E63: =IF($A63>E$5,"",OFFSET(E$54,0,-($A63-1))) | F63: =IF($A63>F$5,"",OFFSET(F$54,0,-($A63-1))) | G63: =IF($A63>G$5,"",OFFSET(G$54,0,-($A63-1))) | H63: =IF($A63>H$5,"",OFFSET(H$54,0,-($A63-1))) | I63: =IF($A63>I$5,"",OFFSET(I$54,0,-($A63-1))) | ... BI63: =IF($A63>BI$5,"",OFFSET(BI$54,0,-($A63-1))) -> 0
A64: 10 | B64: =IF($A64>B$5,"",OFFSET(B$54,0,-($A64-1))) | C64: =IF($A64>C$5,"",OFFSET(C$54,0,-($A64-1))) | D64: =IF($A64>D$5,"",OFFSET(D$54,0,-($A64-1))) | E64: =IF($A64>E$5,"",OFFSET(E$54,0,-($A64-1))) | F64: =IF($A64>F$5,"",OFFSET(F$54,0,-($A64-1))) | G64: =IF($A64>G$5,"",OFFSET(G$54,0,-($A64-1))) | H64: =IF($A64>H$5,"",OFFSET(H$54,0,-($A64-1))) | I64: =IF($A64>I$5,"",OFFSET(I$54,0,-($A64-1))) | ... BI64: =IF($A64>BI$5,"",OFFSET(BI$54,0,-($A64-1))) -> 0
A65: 11 | B65: =IF($A65>B$5,"",OFFSET(B$54,0,-($A65-1))) | C65: =IF($A65>C$5,"",OFFSET(C$54,0,-($A65-1))) | D65: =IF($A65>D$5,"",OFFSET(D$54,0,-($A65-1))) | E65: =IF($A65>E$5,"",OFFSET(E$54,0,-($A65-1))) | F65: =IF($A65>F$5,"",OFFSET(F$54,0,-($A65-1))) | G65: =IF($A65>G$5,"",OFFSET(G$54,0,-($A65-1))) | H65: =IF($A65>H$5,"",OFFSET(H$54,0,-($A65-1))) | I65: =IF($A65>I$5,"",OFFSET(I$54,0,-($A65-1))) | ... BI65: =IF($A65>BI$5,"",OFFSET(BI$54,0,-($A65-1))) -> 0
A66: 12 | B66: =IF($A66>B$5,"",OFFSET(B$54,0,-($A66-1))) | C66: =IF($A66>C$5,"",OFFSET(C$54,0,-($A66-1))) | D66: =IF($A66>D$5,"",OFFSET(D$54,0,-($A66-1))) | E66: =IF($A66>E$5,"",OFFSET(E$54,0,-($A66-1))) | F66: =IF($A66>F$5,"",OFFSET(F$54,0,-($A66-1))) | G66: =IF($A66>G$5,"",OFFSET(G$54,0,-($A66-1))) | H66: =IF($A66>H$5,"",OFFSET(H$54,0,-($A66-1))) | I66: =IF($A66>I$5,"",OFFSET(I$54,0,-($A66-1))) | ... BI66: =IF($A66>BI$5,"",OFFSET(BI$54,0,-($A66-1))) -> 0
... A114: 60 | B114: =IF($A114>B$5,"",OFFSET(B$54,0,-($A114-1))) | C114: =IF($A114>C$5,"",OFFSET(C$54,0,-($A114-1))) | D114: =IF($A114>D$5,"",OFFSET(D$54,0,-($A114-1))) | E114: =IF($A114>E$5,"",OFFSET(E$54,0,-($A114-1))) | F114: =IF($A114>F$5,"",OFFSET(F$54,0,-($A114-1))) | G114: =IF($A114>G$5,"",OFFSET(G$54,0,-($A114-1))) | H114: =IF($A114>H$5,"",OFFSET(H$54,0,-($A114-1))) | I114: =IF($A114>I$5,"",OFFSET(I$54,0,-($A114-1))) | ... BI114: =IF($A114>BI$5,"",OFFSET(BI$54,0,-($A114-1))) -> 1390

Sheet Sheet1
