Workbook
Name __S1: {"Book1"}
Name __S1: {"Book1"}
Name _a1: {"'Sheet1'!$L$16"}
Name _a1: {"'Sheet1'!$L$16"}
Name _S1: {"Book1"}
Name _S1: {"Book1"}
Name Ă: #REF!
Name Ạ196: #REF!
Name â259: #REF!
Name â259: #REF!
Name â312: #REF!
Name â312: #REF!
Name Acquisition_PlanA: #REF!
Name Acquisition_PlanB: #REF!
Name Actual: (PeriodInActual*(#REF!>0))*PeriodInPlan
Name Actual: (PeriodInActual*(#REF!>0))*PeriodInPlan
Name ActualBeyond: PeriodInActual*(#REF!>0)
Name ActualBeyond: PeriodInActual*(#REF!>0)
Name adf: #REF!
Name adf: #REF!
Name AdvIncQ12020: #REF!
Name AdvIncQ12021: #REF!
Name AdvIncQ12022: #REF!
Name AdvIncQ12023: #REF!
Name AdvIncQ12024: #REF!
Name AdvIncQ22020: #REF!
Name AdvIncQ22021: #REF!
Name AdvIncQ22022: #REF!
Name AdvIncQ22023: #REF!
Name AdvIncQ22024: #REF!
Name AdvIncQ32020: #REF!
Name AdvIncQ32021: #REF!
Name AdvIncQ32022: #REF!
Name AdvIncQ32023: #REF!
Name AdvIncQ32024: #REF!
Name AdvIncQ42020: #REF!
Name AdvIncQ42021: #REF!
Name AdvIncQ42022: #REF!
Name AdvIncQ42023: #REF!
Name AdvIncQ42024: #REF!
Name AdvPenRate2020: #REF!
Name AdvPenRate2021: #REF!
Name AdvPenRate2022: #REF!
Name AdvPenRate2023: #REF!
Name AdvPenRate2024: #REF!
Name AllReportList: #REF!
Name Amount_act: #REF!
Name Amount_CF: #REF!
Name Amount_F: #REF!
Name Amount_KPI_act: #REF!
Name approval: #REF!
Name approval: #REF!
Name Attribute_F: #REF!
Name B: #REF!
Name b2bSpr: #REF!
Name BaoHanhSuaChua: #REF!
Name be_KPI_bud: #REF!
Name be2B: #REF!
Name bf: #REF!
Name bf: #REF!

Sheet NOTE
A1: SAP MODEL - CASHLOAN
B2: OFFICIAL | N2: HKN | O2: v9 | P2: 20251001
B3: 1. Notes and disclaimer
C4: a. Giới thiệu về SAP
D5: - SAP: Single Account Profitability (Hiệu quả sản phẩm trên từng đơn vị sản phẩm)
D6: - Model SAP được sử dụng như một (01) trong các mô hình dự đoán hiệu quả vòng đời của sản phẩm.
D7: - Do sự phức tạp của sản phẩm, các hệ thống vận hành (hệ thống hạch kế toán, hệ thống quản trị rủi ro, hệ thống quản trị…), hành vi người sử dụng hành vi người sử dụng, model chỉ có thể mô phỏng tương đối trung bình vòng đời của sản phẩm.
D8: - Do tính chất thời điểm, mô hình được xây dựng mô phỏng theo cách vận hành sản phẩm tại thời điểm phát hành. Trường hợp hệ thống thay đổi, sản phẩm thay đổi, mô hình sẽ không thể phản ánh đúng bản chất vận hành sản phẩm.
D9: - Mô hình được tính toán dựa vào các yếu tố đầu vào xác định tại một thời điểm xác định, do đó kết quả của mô hình có thể có sự khác biệt so với thực tế vận hành sản phẩm.
D10: - Mô hình SAP Cashloan tính hiệu quả của khoản vay giải ngân và thời hạn tối đa được áp dụng là 5 năm ( 60 tháng) kể từ ngày bắt đầu sản phẩm đối với sử dụng phương pháp dự phòng IFRS
E11: - Lưu ý rằng trường hợp áp dụng cho khoản vay 5 năm, thì các chi phí sẽ không được tính toán đầy đủ do chi phí COF cho thời gian từ lúc khoản vay kết thúc tới lúc được xóa trên sổ kế toán.
E12: - Chỉ nên sử dụng với khoản vay dưới 4 năm (48 tháng) để được tính toán đầy đủ chi phí
E13: - Đối với phương pháp tính rủi ro VAS, thời hạn khoản vay tối đa sử dụng là 4 năm (48 tháng)
C15: b. Giới thiệu về PnL
D16: - Trong file tính này, Profit & Lost (PnL) được dự phóng từ trung bình cộng kết quả kinh doanh trên từng sản phẩm (SAP) với yếu tố "sale plan" (số giải ngân) qua từng tháng, do đó có thể khác biệt so với kết quả thực tế vận hành.
D17: - Dòng tiền thực tế qua từng tháng có thể khác biệt với mô hình tính toán do nhiều yếu tố tác động bên ngoài thay đổi, do đó, vui lòng chỉ sử dụng mô hình cho mục đích tham khảo.
D18: - Cho mục đích tính dự phòng dòng tiền ngắn và trung hạn, mô hình PnL được cutoff tại thời điểm 5 năm (60 tháng) kể từ ngày bắt đầu khởi chạy sản phẩm đầu tiên.
B20: 2. Instruction
D21: - Dành cho người sử dụng
E22: - Chỉ chỉnh sửa vào các ô màu vàng
E23: - 2 sheets "SAP_Leadsheet" và "Sale plan&PnL" cung cấp yếu tố đầu vào và đầu ra để tính toán mô hình SAP cũng như PnL.
F24: - Sheet SAP_Leadsheet được cấu trúc 2 phần, bên trái là các yếu tố đầu vào (input) và bên phải là kết quả dự đoán (output). Đơn vị sử dụng tại bảng tính là triệu VND (mVND) và phần trăm (%)
F25: - Sheet "Sale plan & PL" được cấu trúc 2 phần, bên trên là sale plan và bên dưới là kết quả PnL
E26: - 2 sheets "SAP_Spreadsheet" và "PL projection speadsheet" là các file tính toán cho 2 sheet "SAP_Leadsheet", "Sales plan & PL"
F27: - 2 sheets được cấu trúc từ trên xuống dưới theo thứ tự tính toán mô phỏng để đưa ra kết quả kinh doanh cuối cùng
F28: - 2 sheets đã được tạm khóa. Trường hợp cần mở khóa, điều chỉnh các yếu tố, vui lòng liên hệ với nhóm vận hành để được hỗ trợ.
D30: - Dành riêng cho người vận hành, hiệu chỉnh
E31: - Cần cẩn trọng khi điều chỉnh ở các file "speadsheet" vì 1 khi sai lệch rất khó tìm ra lỗi (VD: sửa nhầm ô, link nhầm vị trí,…)
B34: 3. Legend
C35: GENERAL INPUT
G37: Diễn giải | L37: Chú thích
D38: Risk input | G38: Loại phương pháp tính rủi ro | L38: Lựa chon phương pháp tính rủi ro VAS và IFRS
D39: Write off | G39: Thời điểm WO | L39: Lựa chọn thời điểm ghi nhận WO là 360 hoặc 180
C40: REVENUE INPUT
G42: Diễn giải | L42: Chú thích
C43: Amount & Tenor
D44: Loan amount | G44: Số tiền vay giải ngân (có thể bao gồm bảo hiểm hoặc không) | L44: Trường hợp số tiền giải ngân > giá trị hàng hóa, chỉ ghi = số thực tế giải ngân
D45: Payment Method | G45: Phương pháp tính lãi | L45: EMI (Equated monthly Installment)- số tiền thanh toán cố định hàng tháng
D46: Nominal Tenor | G46: Thời hạn vay | L46: Thời hạn ghi nhận trên khoản vay ( VD: 1 tháng, 3 tháng, 12 tháng,…)
D47: Maturity to Termination | G47: Thời hạn từ lúc đáo hạn tới lúc tới khi ra ngoại bảng | L47: Nên để 6 tháng để khớp với hệ thống kế toán, rủi ro đang ghi nhận WO180+
D48: Month on book | G48: Thời gian ghi nhận trên sổ sách | L48: = Nominal tenor + Maturity to termination
C50: Pricing
D51: From- To | G51: Từ tháng… tới tháng
D52: IR | G52: Interest rate- lãi suất khoản vay
D53: COF | G53: Cost of fund - Giá vốn | L53: Sử dụng matrix mua vốn của VPB
D54: NIM | G54: Net interest margin - Biên lãi ròng
C56: Early prepayment
D57: From- To | G57: Từ tháng… tới tháng
D58: Penalty fee | G58: Phí phạt
D59: Penalty IR | G59: Lãi phạt
D60: %Attrition | G60: Tỉ lệ trả trước hạn | L60: Tỉ lệ trả trước tính theo cohort, thông thường quan sát trung bình 6 tháng
C61: Credit insurrance
D62: Banca Premium (excl. in loan) | G62: Tỉ lệ bảo hiểm khoản vay (dư nợ không bao gồm bảo hiểm khoản vay) | L62: VD: 7% khoản vay, 8% khoản vay
D63: Banca Premium (incl. in loan) | G63: Tỉ lệ bảo hiểm khoản vay (dư nợ có bao gồm bảo hiểm khoản vay)
D64: Penetration | G64: Tỉ lệ khoản vay có bảo hiểm/tổng khoản vay giải ngân
D65: Commission to CAKE | G65: Tỉ lệ nhận được từ số tiền bảo hiểm | L65: Hiện tai, số này là khoàng 85% tổng số tiền thu từ bảo hiểm
C66: Support fee
D67: Các khoản thu khác | L67: Hiện tại chưa có
C72: COST INPUT
G74: Diễn giải | L74: Chú thích
C75: Inflation rate | G75: Tỉ lệ tăng giá chi phí qua các năm
C77: Acquisition cost | G77: Chi phí mở rộng khách hàng
D78: Sale incentive | G78: Chi phí sales, trả đối tác kinh doanh
D79: Sharing TOI and Risk DPD90+ | G79: Chia sẻ doanh thu, rủi ro(DPD90+) | L79: xem giải thích DPD+ tại đây
D80: Sharing TOI and Risk DPD180+ | G80: Chia sẻ doanh thu, rủi ro(DPD180+) | L80: xem giải thích DPD+ tại đây
D82: Sharing CII (only) | G82: Chỉ chia sẻ doanh thu từ lãi
D83: Sharing COF (only) | G83: Chỉ chia sẻ chi phí vốn
D84: Sharing NFI (only) | G84: Chỉ chia sẻ doanh thu từ vốn
D85: Sharing Risk DPD90+ (Only) | G85: Chỉ chia sẻ rủi ro (DPD90+) | L85: xem giải thích DPD+ tại đây
D86: Sharing Risk DPD180+ (only) | G86: Chỉ chia sẻ rủi ro (DPD180+) | L86: xem giải thích DPD+ tại đây
D88: Partner Lead Acquistion | G88: Chi phí leadgen đối tác
C90: * Chú thích
C91: Chia sẻ rủi ro DPD90/ (DPD180+) là phương pháp tính rủi ro = 100% duy nhất 1 lần tại thời điểm dư nợ DPD90 +(tức quá hạn >90 ngày, chuyển nợ nhóm 3)/ DPD180+(tức qua hạn >180 ngày, chuyển nợ nhóm 4) mà ko tính tại các bucket khác.
C92: Phương pháp này chỉ sử dụng đối với các đối tác chia sẻ doanh thu chi phí.
D94: Marketing cost | G94: Chi phí marketing để mở khoản vay
D96: UW & Disbursal
E97: Underwriting cost & Score | G97: Chi phí kiểm tra điều kiện mở khoản vay
E98: DOP cost | G98: Chi phí luồng DOP (nếu có) (SMS,…)
E99: Disbursement cost | G99: Chi phí mở khoản vay (chi phí esign, sms,…)
E100: Approval rate | G100: Tỉ lệ phê duyệt | L100: Tỉ lệ khách hàng được phê duyệt/khách hàng vào luồng LOS
E101: Disbursement rate | G101: Tỉ lệ giải ngân | L101: Tỉ lệ khách hàng giải ngân/khách hàng được phê duyệt
D103: Collection & AMC
E104: Collections_all | G104: Đơn giá thu nợ tính trung bình cho các khoản vay
D106: Aftersale service
E107: Email & SMS | G107: Chi phí Email, SMS hàng tháng
D109: Supporting units | G109: Chi phí phân bổ
E110: Direct HR | G110: Chi phí nhân sự trực tiếp
E111: Indirect HR | G111: Chi phí nhân sự hỗ trợ
E112: IT | G112: Chi phí IT
E113: Other supports | G113: Chi phí khác (Chi phí thuê VP, CS, khác…)
C115: RISK INPUT
D117: NF | G117: Netflow- Tỉ lệ chuyển nợ
D118: PD | G118: Percentage of debt (tỉ lệ vỡ nợ)
D119: Pro. Rate | G119: Tỉ lệ vỡ nợ đã điều chỉnh thu hồi nợ
D121: Recovery rate | G121: Tỉ lệ thu hồi nợ sau WO
D122: Collect after WO
D123: Fee and others | G123: Tỉ lệ thu được phí, phạt, khác
B128: Write-off mode | E128: Provision mode
B129: DPD360+ | E129: IFRS
B130: DPD180+ | E130: VAS

Sheet Leadsheet
B1: SAP CASHLOAN MODEL | D1: 1
B2: =NOTE!N2 -> HKN | C2: =NOTE!P2 -> 20251001 | D2: =NOTE!O2 -> v9 | K2: NOTE
K3: Please read carefully about before using model
B4: Product | C4: Unsecured Cashloan | D4: UPL | E4: Risk input | G4: IFRS | H4: =G4 -> IFRS | L4: Disclaimer
B5: Sub-Product | C5: Cashloan | D5: ALL | E5: Write off | G5: DPD180+ | H5: =G5 -> DPD180+ | L5: Instruction
B6: Sub-Segments | C6: VNPAY | D6: ALL | E6: Quarter | G6: 2025 | H6: =G6 -> 2025 | L6: Legend
B8: REVENUE INPUT | H8: Cur: mVND | K8: GENERAL OUTPUT | U8: Cur: mVND
B10: Amount & Tenor | C10: Loan amount | E10: =DATA!G25 -> 14.837554 | N10: Life time | O10: Year 1 | P10: Year 2 | Q10: Year 3 | R10: Year 4 | S10: Year 5 | T10: % ANR | U10: % Disbursement
C11: Payment Method | E11: EMI | K11: ANR | N11: =N29 -> 4.7456492 | O11: =O29 -> 8.0917437 | P11: =P29 -> 0.73033581 | Q11: =Q29 -> 0 | R11: =R29 -> 0 | S11: =S29 -> 0 | U11: =N11/$E$10 -> 0.31984041
C12: Nominal Tenor | E12: =DATA!H25 -> 16 | K12: TOI | N12: =SUM(N13:N15) -> 3.5729466 | O12: =SUM(O13:O15) -> 3.4390338 | P12: =SUM(P13:P15) -> 0.13391282 | Q12: =SUM(Q13:Q15) -> 0 | R12: =SUM(R13:R15) -> 0 | S12: =SUM(S13:S15) -> 0 | T12: =N12/$E$14*12/$N$11 -> 0.41066667 | U12: =N12/$E$10 -> 0.24080429
C13: Maturity to Termination | E13: 6 | K13: Net interest income | N13: =N31 -> 2.6903516 | O13: =O31 -> 2.5637561 | P13: =P31 -> 0.12659546 | Q13: =Q31 -> 0 | R13: =R31 -> 0 | S13: =S31 -> 0 | T13: =N13/$E$14*12/$N$11 -> 0.30922313 | U13: =N13/$E$10 -> 0.18132043
C14: Month on book | E14: =E12+E13 -> 22 | K14: Net fee income | N14: =N34 -> 0.88259504 | O14: =O34 -> 0.87527767 | P14: =P34 -> 0.0073173634 | Q14: =Q34 -> 0 | R14: =R34 -> 0 | S14: =S34 -> 0 | T14: =N14/$E$14*12/$N$11 -> 0.10144354 | U14: =N14/$E$10 -> 0.059483865
K15: Other income | N15: =N38 -> 0 | O15: =O38 -> 0 | P15: =P38 -> 0 | Q15: =Q38 -> 0 | R15: =R38 -> 0 | S15: =S38 -> 0 | T15: =N15/$E$14*12/$N$11 -> 0 | U15: =N15/$E$10 -> 0
K16: PROVISION | N16: =N39 -> -2.2889776 | O16: =O39 -> -2.1659984 | P16: =P39 -> -0.12297927 | Q16: =Q39 -> 0 | R16: =R39 -> 0 | S16: =S39 -> 0 | T16: =N16/$E$14*12/$N$11 -> -0.26309009 | U16: =N16/$E$10 -> -0.15426921
B17: Pricing | C17: From | D17: To | E17: IR | F17: COF | G17: NIM | K17: OPEX | N17: =SUM(N18:N21) -> -1.1152233 | O17: =SUM(O18:O21) -> -0.95965086 | P17: =SUM(P18:P21) -> -0.15557244 | Q17: =SUM(Q18:Q21) -> 0 | R17: =SUM(R18:R21) -> 0 | S17: =SUM(S18:S21) -> 0 | T17: =N17/$E$14*12/$N$11 -> -0.12818133 | U17: =N17/$E$10 -> -0.075162208
A18: 1 | B18: 1 | C18: 1 | D18: =E12 -> 16 | E18: =DATA!D33 -> 0.45290894 | F18: =DATA!D37 -> 0.074 | G18: =E18-F18 -> 0.37890894 | K18: Acquisition cost | N18: =SUM(N41) -> -0.29675107 | O18: =SUM(O41) -> -0.29675107 | P18: =SUM(P41) -> 0 | Q18: =SUM(Q41) -> 0 | R18: =SUM(R41) -> 0 | S18: =SUM(S41) -> 0 | T18: =N18/$E$14*12/$N$11 -> -0.03410792 | U18: =N18/$E$10 -> -0.02
A19: 2 | B19: 2 | C19: =IF(D18="","",IF(D18>$E$12,"",D18+1)) -> 17 | D19: =E14 -> 22 | E19: =E18 -> 0.45290894 | F19: =F18 -> 0.074 | G19: =E19-F19 -> 0.37890894 | K19: UW & Disbursal | N19: =N45 -> -0.066001863 | O19: =O45 -> -0.066001863 | P19: =P45 -> 0 | Q19: =Q45 -> 0 | R19: =R45 -> 0 | S19: =S45 -> 0 | T19: =N19/$E$14*12/$N$11 -> -0.0075861098 | U19: =N19/$E$10 -> -0.0044482982
A20: 3 | B20: 3 | K20: Collection & aftersale service | N20: =N48 -> -0.10776352 | O20: =O48 -> -0.080036365 | P20: =P48 -> -0.027727156 | Q20: =Q48 -> 0 | R20: =R48 -> 0 | S20: =S48 -> 0 | T20: =N20/$E$14*12/$N$11 -> -0.012386103 | U20: =N20/$E$10 -> -0.00726289
A21: 4 | B21: 4 | K21: Support unit | N21: =N52 -> -0.64470685 | O21: =O52 -> -0.51686156 | P21: =P52 -> -0.12784529 | Q21: =Q52 -> 0 | R21: =R52 -> 0 | S21: =S52 -> 0 | T21: =N21/$E$14*12/$N$11 -> -0.074101195 | U21: =N21/$E$10 -> -0.04345102
A22: 5 | B22: 5 | K22: PBT | N22: =N12+N16+N17 -> 0.16874568 | O22: =O12+O16+O17 -> 0.31338457 | P22: =P12+P16+P17 -> -0.14463889 | Q22: =Q12+Q16+Q17 -> 0 | R22: =R12+R16+R17 -> 0 | S22: =S12+S16+S17 -> 0 | T22: =N22/$E$14*12/$N$11 -> 0.01939526 | U22: =N22/$E$10 -> 0.011372878
B23: 6 | K23: In which: PROFIT BEFORE SU | N23: =N22-N21 -> 0.81345253 | O23: =O22-O21 -> 0.83024613 | P23: =P22-P21 -> -0.016793604 | Q23: =Q22-Q21 -> 0 | R23: =R22-R21 -> 0 | S23: =S22-S21 -> 0 | T23: =N23/$E$14*12/$N$11 -> 0.093496455 | U23: =N23/$E$10 -> 0.054823898
B25: Early prepayment | C25: From | D25: To | E25: Penalty fee | F25: Penalty IR | G25: %Attrition
B26: 1 | C26: 1 | D26: 1 | E26: =DATA!E125 -> 0.0608466 | G26: 0.08 | H26: per cohort | K26: PERFORMANCE OUTPUT | U26: Cur: mVND
B27: 2 | C27: =D26+1 -> 2 | D27: 3 | E27: =E26 -> 0.0608466 | G27: 0.06 | H27: per cohort
B28: 3 | C28: =D27+1 -> 4 | D28: 14 | E28: 0.05 | G28: 0.025 | H28: per cohort | N28: Life time | O28: Year 1 | P28: Year 2 | Q28: Year 3 | R28: Year 4 | S28: Year 5 | T28: % ANR | U28: % Disbursement
B29: 4 | C29: =IF(D28="","",IF(D28>$E$12,"",D28+1)) -> 15 | K29: ANR | N29: =SUM(SAP_Speadsheet!$D$50:$BF$50)/COUNTIF(SAP_Speadsheet!$D$50:$BF$50,">0") -> 4.7456492 | O29: =IFERROR(SUM(SAP_Speadsheet!$D$50:$P$50)/COUNTIF(SAP_Speadsheet!$D$50:$P$50,">0"),0) -> 8.0917437 | P29: =IFERROR(SUM(SAP_Speadsheet!$Q$50:$AB$50)/COUNTIF(SAP_Speadsheet!$Q$50:$AB$50,">0"),0) -> 0.73033581 | Q29: =IFERROR(SUM(SAP_Speadsheet!$AC$50:$AN$50)/COUNTIF(SAP_Speadsheet!$AC$50:$AN$50,">0"),0) -> 0 | R29: =IFERROR(SUM(SAP_Speadsheet!$AO$50:$AZ$50)/COUNTIF(SAP_Speadsheet!$AO$50:$AZ$50,">0"),0) -> 0 | S29: =IFERROR(SUM(SAP_Speadsheet!$BA$50:$BF$50)/COUNTIF(SAP_Speadsheet!$BA$50:$BF$50,">0"),0) -> 0 | U29: =N29/$E$10 -> 0.31984041
B30: 5 | C30: =IF(D29="","",IF(D29>$E$12,"",D29+1)) | E30: =IF(D30="",0,SUMIFS(#REF!,#REF!,Leadsheet!G$24,#REF!,Leadsheet!$A30,#REF!,Leadsheet!$C$4,#REF!,Leadsheet!$G$5,#REF!,Leadsheet!$D$5,#REF!,Leadsheet!G4)) -> 0 | F30: 0 | K30: TOI | N30: =SUM(O30:S30) -> 3.5729466 | O30: =SUM(SAP_Speadsheet!$E$55:$P$55) -> 3.4390338 | P30: =SUM(SAP_Speadsheet!$Q$55:$AB$55) -> 0.13391282 | Q30: =SUM(SAP_Speadsheet!$AC$55:$AN$55) -> 0 | R30: =SUM(SAP_Speadsheet!$AO$55:$AZ$55) -> 0 | S30: =SUM(SAP_Speadsheet!$BA$55:$BF$55) -> 0 | T30: =N30/$E$14*12/$N$29 -> 0.41066667 | U30: =N30/$E$10 -> 0.24080429
B31: 6 | C31: =IF(D30="","",IF(D30>$E$12,"",D30+1)) | E31: =IF(D31="",0,SUMIFS(#REF!,#REF!,Leadsheet!G$24,#REF!,Leadsheet!$A31,#REF!,Leadsheet!$C$4,#REF!,Leadsheet!$G$5,#REF!,Leadsheet!$D$5,#REF!,Leadsheet!G4)) -> 0 | F31: 0 | K31: Net interest income | N31: =SUM(O31:S31) -> 2.6903516 | O31: =SUM(SAP_Speadsheet!$E$57:$P$57) -> 2.5637561 | P31: =SUM(SAP_Speadsheet!$Q$57:$AB$57) -> 0.12659546 | Q31: =SUM(SAP_Speadsheet!$AC$57:$AN$57) -> 0 | R31: =SUM(SAP_Speadsheet!$AO$57:$AZ$57) -> 0 | S31: =SUM(SAP_Speadsheet!$BA$57:$BF$57) -> 0 | T31: =N31/$E$14*12/$N$29 -> 0.30922313 | U31: =N31/$E$10 -> 0.18132043
K32: Interest income | N32: =SUM(O32:S32) -> 3.334178 | O32: =SUM(SAP_Speadsheet!$E$58:$P$58) -> 3.1625452 | P32: =SUM(SAP_Speadsheet!$Q$58:$AB$58) -> 0.17163283 | Q32: =SUM(SAP_Speadsheet!$AC$58:$AN$58) -> 0 | R32: =SUM(SAP_Speadsheet!$AO$58:$AZ$58) -> 0 | S32: =SUM(SAP_Speadsheet!$BA$58:$BF$58) -> 0 | T32: =N32/$E$14*12/$N$29 -> 0.38322313 | U32: =N32/$E$10 -> 0.22471211
B33: Credit insurrance | C33: Banca Premium (excl. in loan) | F33: per disbursement amount | K33: Cost of fund | N33: =SUM(O33:S33) -> -0.64382641 | O33: =SUM(SAP_Speadsheet!$E$59:$P$59) -> -0.59878904 | P33: =SUM(SAP_Speadsheet!$Q$59:$AB$59) -> -0.045037375 | Q33: =SUM(SAP_Speadsheet!$AC$59:$AN$59) -> 0 | R33: =SUM(SAP_Speadsheet!$AO$59:$AZ$59) -> 0 | S33: =SUM(SAP_Speadsheet!$BA$59:$BF$59) -> 0 | T33: =N33/$E$14*12/$N$29 -> -0.074 | U33: =N33/$E$10 -> -0.043391682
C34: Banca Premium (incl. in loan) | E34: =DATA!J25 -> 0.069722407 | F34: per disbursement amount | K34: Net fee income | N34: =SUM(O34:S34) -> 0.88259504 | O34: =SUM(SAP_Speadsheet!$E$61:$P$61) -> 0.87527767 | P34: =SUM(SAP_Speadsheet!$Q$61:$AB$61) -> 0.0073173634 | Q34: =SUM(SAP_Speadsheet!$AC$61:$AN$61) -> 0 | R34: =SUM(SAP_Speadsheet!$AO$61:$AZ$61) -> 0 | S34: =SUM(SAP_Speadsheet!$BA$61:$BF$61) -> 0 | T34: =N34/$E$14*12/$N$29 -> 0.10144354 | U34: =N34/$E$10 -> 0.059483865
C35: Penetration | E35: =DATA!K25 -> 0.74160583 | F35: per disbursement amount | K35: Early termination fee | N35: =SUM(O35:S35) -> 0.25816039 | O35: =SUM(SAP_Speadsheet!$E$62:$P$62) -> 0.25084302 | P35: =SUM(SAP_Speadsheet!$Q$62:$AB$62) -> 0.0073173634 | Q35: =SUM(SAP_Speadsheet!$AC$62:$AN$62) -> 0 | R35: =SUM(SAP_Speadsheet!$AO$62:$AZ$62) -> 0 | S35: =SUM(SAP_Speadsheet!$BA$62:$BF$62) -> 0 | T35: =N35/$E$14*12/$N$29 -> 0.02967239 | U35: =N35/$E$10 -> 0.017399121
C36: Commission to CAKE | E36: 0.856 | F36: per disbursement amount | H36: done | K36: Insurance commission | N36: =SUM(O36:S36) -> 0.62443465 | O36: =SUM(SAP_Speadsheet!$E$63:$P$63) -> 0.62443465 | P36: =SUM(SAP_Speadsheet!$Q$63:$AB$63) -> 0 | Q36: =SUM(SAP_Speadsheet!$AC$63:$AN$63) -> 0 | R36: =SUM(SAP_Speadsheet!$AO$63:$AZ$63) -> 0 | S36: =SUM(SAP_Speadsheet!$BA$63:$BF$63) -> 0 | T36: =N36/$E$14*12/$N$29 -> 0.071771154 | U36: =N36/$E$10 -> 0.042084744
H37: done | K37: Support fee | N37: =SUM(O37:S37) -> 0 | O37: =SUM(SAP_Speadsheet!$E$64:$P$64) -> 0 | P37: =SUM(SAP_Speadsheet!$Q$64:$AB$64) -> 0 | Q37: =SUM(SAP_Speadsheet!$AC$64:$AN$64) -> 0 | R37: =SUM(SAP_Speadsheet!$AO$64:$AZ$64) -> 0 | S37: =SUM(SAP_Speadsheet!$BA$64:$BF$64) -> 0 | T37: =N37/$E$14*12/$N$29 -> 0 | U37: =N37/$E$10 -> 0
B38: Support fee | C38: One-time | F38: $ per account | K38: Other income | N38: =SUM(O38:S38) -> 0 | O38: =SUM(SAP_Speadsheet!$E$68:$P$68) -> 0 | P38: =SUM(SAP_Speadsheet!$Q$68:$AB$68) -> 0 | Q38: =SUM(SAP_Speadsheet!$AC$68:$AN$68) -> 0 | R38: =SUM(SAP_Speadsheet!$AO$68:$AZ$68) -> 0 | S38: =SUM(SAP_Speadsheet!$BA$68:$BF$68) -> 0 | T38: =N38/$E$14*12/$N$29 -> 0 | U38: =N38/$E$10 -> 0
C39: One-time | F39: % per ticketsize | K39: PROVISION | N39: =SUM(O39:S39) -> -2.2889776 | O39: =SUM(SAP_Speadsheet!$E$183:$P$183) -> -2.1659984 | P39: =SUM(SAP_Speadsheet!$Q$183:$AB$183) -> -0.12297927 | Q39: =SUM(SAP_Speadsheet!$AC$183:$AN$183) -> 0 | R39: =SUM(SAP_Speadsheet!$AO$183:$AZ$183) -> 0 | S39: =SUM(SAP_Speadsheet!$BA$183:$BF$183) -> 0 | T39: =N39/$E$14*12/$N$29 -> -0.26309009 | U39: =N39/$E$10 -> -0.15426921
C40: Monthly fee | F40: %monthly per ticketsize | K40: OPEX | N40: =SUM(O40:S40) -> -1.1152233 | O40: =+SUM(O41,O45,O48,O52) -> -0.95965086 | P40: =+SUM(P41,P45,P48,P52) -> -0.15557244 | Q40: =+SUM(Q41,Q45,Q48,Q52) -> 0 | R40: =+SUM(R41,R45,R48,R52) -> 0 | S40: =+SUM(S41,S45,S48,S52) -> 0 | T40: =N40/$E$14*12/$N$29 -> -0.12818133 | U40: =N40/$E$10 -> -0.075162208
B41: COST INPUT | H41: Cur: mVND | K41: Acquisition cost | N41: =SUM(O41:S41) -> -0.29675107 | O41: =SUM(O42:O44) -> -0.29675107 | P41: =SUM(P42:P44) -> 0 | Q41: =SUM(Q42:Q44) -> 0 | R41: =SUM(R42:R44) -> 0 | S41: =SUM(S42:S44) -> 0 | T41: =N41/$E$14*12/$N$29 -> -0.03410792 | U41: =N41/$E$10 -> -0.02
K42: Lead Acquisition | N42: =SUM(O42:S42) -> -0.29675107 | O42: =SUM(SAP_Speadsheet!$E$73:$P$73) -> -0.29675107 | P42: =SUM(SAP_Speadsheet!$Q$73:$AB$73) -> 0 | Q42: =SUM(SAP_Speadsheet!$AC$73:$AN$73) -> 0 | R42: =SUM(SAP_Speadsheet!$AO$73:$AZ$73) -> 0 | S42: =SUM(SAP_Speadsheet!$BA$73:$BF$73) -> 0 | T42: =N42/$E$14*12/$N$29 -> -0.03410792 | U42: =N42/$E$10 -> -0.02
B43: Inflation rate | E43: 0.035 | F43: % per year | K43: Sharing performance | N43: =SUM(O43:S43) -> 0 | O43: =SUM(SAP_Speadsheet!$E$74:$P$74) -> 0 | P43: =SUM(SAP_Speadsheet!$Q$74:$AB$74) -> 0 | Q43: =SUM(SAP_Speadsheet!$AC$74:$AN$74) -> 0 | R43: =SUM(SAP_Speadsheet!$AO$74:$AZ$74) -> 0 | S43: =SUM(SAP_Speadsheet!$BA$74:$BF$74) -> 0 | T43: =N43/$E$14*12/$N$29 -> 0 | U43: =N43/$E$10 -> 0
K44: Marketing | N44: =SUM(O44:S44) -> 0 | O44: =SUM(SAP_Speadsheet!$E$86:$P$86) -> 0 | P44: =SUM(SAP_Speadsheet!$Q$86:$AB$86) -> 0 | Q44: =SUM(SAP_Speadsheet!$AC$86:$AN$86) -> 0 | R44: =SUM(SAP_Speadsheet!$AO$86:$AZ$86) -> 0 | S44: =SUM(SAP_Speadsheet!$BA$86:$BF$86) -> 0 | T44: =N44/$E$14*12/$N$29 -> 0 | U44: =N44/$E$10 -> 0
B45: Acquisition cost | K45: UW & Disbursal | N45: =SUM(O45:S45) -> -0.066001863 | O45: =SUM(O46:O47) -> -0.066001863 | P45: =SUM(P46:P47) -> 0 | Q45: =SUM(Q46:Q47) -> 0 | R45: =SUM(R46:R47) -> 0 | S45: =SUM(S46:S47) -> 0 | T45: =N45/$E$14*12/$N$29 -> -0.0075861098 | U45: =N45/$E$10 -> -0.0044482982
C46: Sale incentive | E46: Auto MODE | K46: Underwriting | N46: =SUM(O46:S46) -> -0.063721031 | O46: =SUM(SAP_Speadsheet!$E$89:$P$89) -> -0.063721031 | P46: =SUM(SAP_Speadsheet!$Q$89:$AB$89) -> 0 | Q46: =SUM(SAP_Speadsheet!$AC$89:$AN$89) -> 0 | R46: =SUM(SAP_Speadsheet!$AO$89:$AZ$89) -> 0 | S46: =SUM(SAP_Speadsheet!$BA$89:$BF$89) -> 0 | T46: =N46/$E$14*12/$N$29 -> -0.0073239559 | U46: =N46/$E$10 -> -0.0042945779
C47: Sharing TOI and Risk DPD90+ | F47: % per month | K47: Disbursement | N47: =SUM(O47:S47) -> -0.0022808325 | O47: =SUM(SAP_Speadsheet!$E$90:$P$90) -> -0.0022808325 | P47: =SUM(SAP_Speadsheet!$Q$90:$AB$90) -> 0 | Q47: =SUM(SAP_Speadsheet!$AC$90:$AN$90) -> 0 | R47: =SUM(SAP_Speadsheet!$AO$90:$AZ$90) -> 0 | S47: =SUM(SAP_Speadsheet!$BA$90:$BF$90) -> 0 | T47: =N47/$E$14*12/$N$29 -> -0.0002621539 | U47: =N47/$E$10 -> -0.00015372025
C48: Sharing TOI and Risk DPD180+ | F48: % per month | K48: Collection & after sale service | N48: =SUM(O48:S48) -> -0.10776352 | O48: =SUM(O49:O51) -> -0.080036365 | P48: =SUM(P49:P51) -> -0.027727156 | Q48: =SUM(Q49:Q51) -> 0 | R48: =SUM(R49:R51) -> 0 | S48: =SUM(S49:S51) -> 0 | T48: =N48/$E$14*12/$N$29 -> -0.012386103 | U48: =N48/$E$10 -> -0.00726289
E49: Adjust MODE | K49: Early collections | N49: =SUM(O49:S49) -> -0.098760427 | O49: =SUM(SAP_Speadsheet!$E$96:$P$96) -> -0.072808 | P49: =SUM(SAP_Speadsheet!$Q$96:$AB$96) -> -0.025952427 | Q49: =SUM(SAP_Speadsheet!$AC$96:$AN$96) -> 0 | R49: =SUM(SAP_Speadsheet!$AO$96:$AZ$96) -> 0 | S49: =SUM(SAP_Speadsheet!$BA$96:$BF$96) -> 0 | T49: =N49/$E$14*12/$N$29 -> -0.011351308 | U49: =N49/$E$10 -> -0.0066561126
C50: Sharing CII (only) | F50: % per month | K50: AMC | N50: =SUM(O50:S50) -> 0 | O50: =SUM(SAP_Speadsheet!$E$97:$P$97) -> 0 | P50: =SUM(SAP_Speadsheet!$Q$97:$AB$97) -> 0 | Q50: =SUM(SAP_Speadsheet!$AC$97:$AN$97) -> 0 | R50: =SUM(SAP_Speadsheet!$AO$97:$AZ$97) -> 0 | S50: =SUM(SAP_Speadsheet!$BA$97:$BF$97) -> 0 | T50: =N50/$E$14*12/$N$29 -> 0 | U50: =N50/$E$10 -> 0
C51: Sharing COF (only) | F51: % per month | K51: Aftersale service | N51: =SUM(O51:S51) -> -0.0090030935 | O51: =SUM(SAP_Speadsheet!$E$99:$P$99) -> -0.0072283649 | P51: =SUM(SAP_Speadsheet!$Q$99:$AB$99) -> -0.0017747285 | Q51: =SUM(SAP_Speadsheet!$AC$99:$AN$99) -> 0 | R51: =SUM(SAP_Speadsheet!$AO$99:$AZ$99) -> 0 | S51: =SUM(SAP_Speadsheet!$BA$99:$BF$99) -> 0 | T51: =N51/$E$14*12/$N$29 -> -0.0010347959 | U51: =N51/$E$10 -> -0.00060677748
C52: Sharing NFI (only) | F52: % per month | K52: Supporting Units | N52: =SUM(O52:S52) -> -0.64470685 | O52: =SUM(O53:O56) -> -0.51686156 | P52: =SUM(P53:P56) -> -0.12784529 | Q52: =SUM(Q53:Q56) -> 0 | R52: =SUM(R53:R56) -> 0 | S52: =SUM(S53:S56) -> 0 | T52: =N52/$E$14*12/$N$29 -> -0.074101195 | U52: =N52/$E$10 -> -0.04345102
C53: Sharing Risk DPD90+ (Only) | F53: % per month | K53: Direct HR | N53: =SUM(O53:S53) -> -0.10304645 | O53: =SUM(SAP_Speadsheet!$E$104:$P$104) -> -0.082612349 | P53: =SUM(SAP_Speadsheet!$Q$104:$AB$104) -> -0.020434098 | Q53: =SUM(SAP_Speadsheet!$AC$104:$AN$104) -> 0 | R53: =SUM(SAP_Speadsheet!$AO$104:$AZ$104) -> 0 | S53: =SUM(SAP_Speadsheet!$BA$104:$BF$104) -> 0 | T53: =N53/$E$14*12/$N$29 -> -0.011843933 | U53: =N53/$E$10 -> -0.0069449755
C54: Sharing Risk DPD180+ (only) | F54: % per month | K54: Indiect HR | N54: =SUM(O54:S54) -> -0.27606847 | O54: =SUM(SAP_Speadsheet!$E$105:$P$105) -> -0.22132413 | P54: =SUM(SAP_Speadsheet!$Q$105:$AB$105) -> -0.054744344 | Q54: =SUM(SAP_Speadsheet!$AC$105:$AN$105) -> 0 | R54: =SUM(SAP_Speadsheet!$AO$105:$AZ$105) -> 0 | S54: =SUM(SAP_Speadsheet!$BA$105:$BF$105) -> 0 | T54: =N54/$E$14*12/$N$29 -> -0.031730706 | U54: =N54/$E$10 -> -0.018606064
C55: Risk share from | F55: disbursement | K55: IT | N55: =SUM(O55:S55) -> -0.1324389 | O55: =SUM(SAP_Speadsheet!$E$106:$P$106) -> -0.10617628 | P55: =SUM(SAP_Speadsheet!$Q$106:$AB$106) -> -0.026262617 | Q55: =SUM(SAP_Speadsheet!$AC$106:$AN$106) -> 0 | R55: =SUM(SAP_Speadsheet!$AO$106:$AZ$106) -> 0 | S55: =SUM(SAP_Speadsheet!$BA$106:$BF$106) -> 0 | T55: =N55/$E$14*12/$N$29 -> -0.015222237 | U55: =N55/$E$10 -> -0.0089259255
C56: Partner Lead Acquistion | F56: per account | K56: Other support units | N56: =SUM(O56:S56) -> -0.13315303 | O56: =SUM(SAP_Speadsheet!$E$107:$P$107) -> -0.1067488 | P56: =SUM(SAP_Speadsheet!$Q$107:$AB$107) -> -0.026404229 | Q56: =SUM(SAP_Speadsheet!$AC$107:$AN$107) -> 0 | R56: =SUM(SAP_Speadsheet!$AO$107:$AZ$107) -> 0 | S56: =SUM(SAP_Speadsheet!$BA$107:$BF$107) -> 0 | T56: =N56/$E$14*12/$N$29 -> -0.015304318 | U56: =N56/$E$10 -> -0.0089740554
E57: 0.02 | F57: per ticketsize | K57: PBT | N57: =SUM(O57:S57) -> 0.16874568 | O57: =SUM(SAP_Speadsheet!$E$189:$P$189) -> 0.31338457 | P57: =SUM(SAP_Speadsheet!$Q$189:$AB$189) -> -0.14463889 | Q57: =SUM(SAP_Speadsheet!$AC$189:$AN$189) -> 0 | R57: =SUM(SAP_Speadsheet!$AO$189:$AZ$189) -> 0 | S57: =SUM(SAP_Speadsheet!$BA$189:$BF$189) -> 0 | T57: =N57/$E$14*12/$N$29 -> 0.01939526 | U57: =N57/$E$10 -> 0.011372878
C59: Marketing cost
C61: Marketing cost | E61: =DATA!D64 -> 0 | F61: per account
B63: UW & Disbursal | C63: Underwriting cost & Score | E63: =DATA!D65*Leadsheet!E66*Leadsheet!E67 -> 0.016424351 | F63: of application
A64: Inflation | C64: DOP cost | F64: of account
C65: Disbursement cost | E65: =DATA!D69 -> 0.0022808325 | F65: of account
A66: Incentive | C66: Approval rate | E66: =DATA!E7 -> 0.361 | F66: of submitted application
A67: Sale team | C67: Disbursement rate | E67: =DATA!E8 -> 0.714 | F67: of aproved application
A68: Sale Mgt
A69: MA
B71: Collection & AMC | C71: Collections_all | E71: =DATA!D66 -> 0.008 | F71: per account/month
C72: Collections_B1+ | F72: per account/month
C73: AMC_principal collected | F73: per 1mVND collected amount
C74: AMC_interest collected | F74: per 1mVND collected amount
C75: AMC_penalty collected | F75: per 1mVND collected amount
B77: Aftersale service
C78: Email & SMS | E78: =DATA!D67 -> 0.00083516637 | F78: per account/month
A79: CPCUW
A80: CPCUW_SCORE
A81: CPCCA | B81: Supporting units | C81: Direct HR | E81: 0.0090772826 | F81: per account/month
A82: Approval rate | C82: Indirect HR | E82: 0.02431866 | F82: per account/month
C83: IT | E83: 0.011666441 | F83: per account/month
C84: Other supports | E84: 0.011729348 | F84: per account/month
A86: AMC_PR
B88: RISK INPUT
B90: Net flow | D90: NF | E90: PD | F90: Pro. Rate
C91: B0 - B1 | D91: =DATA!D84 -> 0.05 | E91: =PRODUCT(D91:$D$104) -> 0.025893226 | F91: =E91*(1-$E$110)*(1-$E$111)*(1-$E$112)*(1-$E$113) -> 0.024126792
C92: B1 - B2 | D92: =DATA!D85 -> 0.671 | E92: =PRODUCT(D92:$D$104) -> 0.51786452 | F92: =E92*(1-$E$110)*(1-$E$111)*(1-$E$112)*(1-$E$113) -> 0.48253584
C93: B2 - B3 | D93: =DATA!D86 -> 0.91 | E93: =PRODUCT(D93:$D$104) -> 0.77178021 | F93: =E93*(1-$E$110)*(1-$E$111)*(1-$E$112)*(1-$E$113) -> 0.71912942
C94: B3 - B4 | D94: =DATA!D87 -> 0.952 | E94: =PRODUCT(D94:$D$104) -> 0.84811012 | F94: =E94*(1-$E$110)*(1-$E$111)*(1-$E$112)*(1-$E$113) -> 0.79025212
C95: B4 - B5 | D95: =DATA!D88 -> 0.96041089 | E95: =PRODUCT(D95:$D$104) -> 0.89087197 | F95: =E95*(1-$E$110)*(1-$E$111)*(1-$E$112)*(1-$E$113) -> 0.83009676
C96: B5 - B6 | D96: =DATA!D89 -> 0.94496137 | E96: =PRODUCT(D96:$D$104) -> 0.92759462 | F96: =E96*(1-$E$110)*(1-$E$111)*(1-$E$112)*(1-$E$113) -> 0.86431419
C97: B6 - B7 | D97: =DATA!D90 -> 0.98754205 | E97: =PRODUCT(D97:$D$104) -> 0.98162174 | F97: =E97*(1-$E$110)*(1-$E$111)*(1-$E$112)*(1-$E$113) -> 0.91465558
C98: B7 - B8 | D98: =DATA!D91 -> 0.995 | E98: =PRODUCT(D98:$D$104) -> 0.994005 | F98: =E98*(1-$E$110)*(1-$E$111)*(1-$E$112)*(1-$E$113) -> 0.92619406
C99: B8 - B9 | D99: =DATA!D92 -> 0.999 | E99: =PRODUCT(D99:$D$104) -> 0.999 | F99: =E99*(1-$E$111)*(1-$E$112)*(1-$E$113) -> 0.9498452
C100: B9 - B10 | D100: 1 | E100: =PRODUCT(D100:$D$104) -> 1 | F100: =E100*(1-$E$111)*(1-$E$112)*(1-$E$113) -> 0.950796
C101: B10 - B11 | D101: 1 | E101: =PRODUCT(D101:$D$104) -> 1 | F101: =E101*(1-$E$111)*(1-$E$112)*(1-$E$113) -> 0.950796
C102: B11 - B12 | D102: 1 | E102: =PRODUCT(D102:$D$104) -> 1 | F102: =E102*(1-$E$111)*(1-$E$112)*(1-$E$113) -> 0.950796
C103: B12 - B13 | D103: 1 | E103: =PRODUCT(D103:$D$104) -> 1 | F103: =E103*(1-$E$111)*(1-$E$112)*(1-$E$113) -> 0.950796
C104: B13-B24 | F104: =(1-$E$111)*(1-$E$112)*(1-$E$113) -> 0.950796
C105: B25-B36 | F105: =(1-$E$112)*(1-$E$113) -> 0.9702
A106: Recovery rate B13-B24 | C106: B36+ | F106: =(1-$E$113) -> 0.99
A107: Recovery rate B24-B36 | C107: Risk cost/ Disburse | D107: =N39/E10 -> -0.15426921
A108: Recovery rate B36+ | C108: Riskcost/ANR | D108: =T39 -> -0.26309009
B110: Recovery rate | C110: B8- B12 | E110: 0.02
C111: B13-B24 | D111: Recovery rate B13-B24 | E111: 0.02
C112: B24-B36 | D112: Recovery rate B24-B36 | E112: 0.02
...

Sheet DATA
B1: HKN-TTA
B2: 20260119
B5: 1 | C5: Aproval rate, signed rate
C7: aprroval rate | E7: 0.361
C8: Signed rate | E8: 0.714
B17: 2 | C17: Disburse, Tenor, Insurance, IR, COF
C19: Disburse date | D19: # Disburse | E19: Disburse amount (VND) | F19: Current balance (VND) | G19: Ticket size (VND) | H19: Avg tenor (Month) | I19: Avg IR (%) | J19: Insurance fee (VND) | K19: % Insurance penetration by date
C20: 45992 | D20: 1395 | E20: 21697550000 | G20: 15553799 | H20: 16.288172 | I20: 0.46336918 | J20: 1054550000 | K20: 0.73261649 | L20: =E20-J20 -> 20643000000
C21: 45962 | D21: 1413 | E21: 19620350000 | G21: 13885598 | H21: 15.781316 | I21: 0.46266808 | J21: 973350000 | K21: 0.74663836 | L21: =E21-J21 -> 18647000000
C22: 45931 | D22: 1476 | E22: 22246180000 | G22: 15071938 | H22: 16.036585 | I22: 0.46270325 | J22: 1097180000 | K22: 0.74593496 | L22: =E22-J22 -> 21149000000
C25: AVG | G25: =SUM(E20:E22)/SUM(D20:D22)/10^6 -> 14.837554 | H25: =ROUND(SUMPRODUCT(H20:H22,E20:E22)/SUM(E20:E22),0) -> 16 | I25: =SUMPRODUCT(I20:I22,E20:E22)/SUM(E20:E22) -> 0.46291971 | J25: =SUM(J20:J22)/SUMPRODUCT(K20:K22,L20:L22) -> 0.069722407 | K25: =SUMPRODUCT(K20:K22,E20:E22)/SUM(E20:E22) -> 0.74160583
D28: 10 | E28: =D28+1 -> 11 | F28: =E28+1 -> 12
C29: ENR | D29: 101068876374 | E29: 107157807951 | F29: 114324863034
D30: =E22 -> 22246180000 | E30: =E21 -> 19620350000 | F30: =E20 -> 21697550000
E32: Cân nhắc xem lại
C33: IR | D33: =E33 -> 0.45290894 | E33: =SUM(D35:F35)/SUM(D34:F34)*365 -> 0.45290894
C34: Balance by day | D34: 2646528857360 | E34: 2803832735492 | F34: 3008910958344
C35: Thu lãi vay | D35: 3293167691 | E35: 3487480127 | F35: 3716010119
C37: COF | D37: 0.074
C39: Years (BUSINESS_DATE) | D39: Months (BUSINESS_DATE) | E39: Sum of BALANCE | F39: Sum of Lai DCV
C40: 2025 | D40: Oct | E40: 2976030609952 | F40: 5.7012589e+08
D41: Nov | E41: 3170699687949 | F41: 6.2131961e+08
D42: Dec | E42: 3089737356645 | F42: 6.1744428e+08
M48: =M49/D52 -> 6.9132791
M49: =D53-L53 -> 10204
B50: 3 | C50: UW, collection, MKT
D51: 10 | E51: =D51+1 -> 11 | F51: =E51+1 -> 12
C52: New ACC | D52: 1476 | E52: 1413 | F52: 1395
C53: Active acc | D53: 10204 | E53: 10704 | F53: 11056
C55: MKT acquisition
C56: UW | D56: 95580912 | E56: 93154244 | F56: 84245739
C57: Collection | D57: 28426097 | E57: 43427799 | F57: 38729442
C58: SMS | D58: 9210396.9 | E58: 9053041.7 | F58: 8431819.3
C59: Partner acquisition | D59: 422980000 | E59: 372940000 | F59: 412860000
C60: Econtract | D60: 1086785 | E60: 1024658 | F60: 1027878
C61: NFC | D61: 2277938 | E61: 1971115.7 | F61: 2382711.5
C64: MKT acquisition | D64: =SUM(D55:L55)/SUM(D52:L52)/10^6 -> 0
C65: UW | D65: =SUM(D56:F56)/SUM(D52:F52)/10^6 -> 0.063721031
C66: Collection | D66: =8000/10^6 -> 0.008 | E66: Sử dụng mức tương đương Q2 do quý 3 thay đổi collection, chi phí ko đầy đủ
C67: SMS | D67: =SUM(D58:F58)/SUM(D53:F53)/10^6 -> 0.00083516637
C68: Partner acquisition | D68: =SUM(D59:F59)/SUM(E20:E22) -> 0.019016715
C69: Disbursement cost | D69: =SUM(D60:F61)/SUM(D52:F52)/10^6 -> 0.0022808325
B71: 4 | C71: Allocation
C73: Direct HR | D73: 0.0080701706
C74: Indirect HR | D74: 0.016933316
C75: System | D75: 0.0061217502
C76: Other | D76: 0.0089101169
B80: 5 | C80: RR
D83: Adjust | E83: SUM | F83: 202510 | G83: 11 | H83: 12
C84: B00 | D84: 0.05 | E84: =AVERAGE(F84:H84) -> 0.05122621 | F84: =N102/M101 -> 0.053774001 | G84: =O102/N101 -> 0.051858983 | H84: =P102/O101 -> 0.048045647
C85: B01 | D85: 0.671 | E85: =AVERAGE(F85:H85) -> 0.68055804 | F85: =N103/M102 -> 0.62578913 | G85: =O103/N102 -> 0.6999042 | H85: =P103/O102 -> 0.7159808
C86: B02 | D86: 0.91 | E86: =AVERAGE(F86:H86) -> 0.93093819 | F86: =N104/M103 -> 0.91231423 | G86: =O104/N103 -> 0.93441235 | H86: =P104/O103 -> 0.94608799
C87: B03 | D87: 0.952 | E87: =AVERAGE(F87:H87) -> 0.97750216 | F87: =N105/M104 -> 0.98182008 | G87: =O105/N104 -> 0.96030122 | H87: =P105/O104 -> 0.99038519
C88: B04 | D88: =E88*99% -> 0.96041089 | E88: =AVERAGE(F88:H88) -> 0.97011201 | F88: =N106/M105 -> 0.97108931 | G88: =O106/N105 -> 0.97077178 | H88: =P106/O105 -> 0.96847493
C89: B05 | D89: =E89*99% -> 0.94496137 | E89: =AVERAGE(F89:H89) -> 0.95450643 | F89: =N107/M106 -> 0.97508855 | G89: =O107/N106 -> 0.98442081 | H89: =P107/O106 -> 0.90400994
C90: B06 | D90: =E90*99% -> 0.98754205 | E90: =AVERAGE(F90:H90) -> 0.99751722 | F90: =N108/M107 -> 0.99420634 | G90: =O108/N107 -> 0.99834533 | H90: 1
C91: B07 | D91: 0.995 | E91: =AVERAGE(F91:H91) -> 0.96963102 | F91: =N109/M108 -> 0.92118185 | G91: =O109/N108 -> 0.98771121 | H91: 1
C92: B08 | D92: 0.999 | E92: =AVERAGE(F92:H92) -> 0.98644572 | F92: =N110/M109 -> 0.95933715 | G92: =O110/N109 -> 1 | H92: 1
C93: B09 | F93: 1 | G93: 1 | H93: 1
C94: B10+
C99: Sum of principal_balance_at_report_month | D99: Column Labels
C100: Row Labels | D100: 202412 | E100: 202501 | F100: 202502 | G100: 202503 | H100: 202504 | I100: 202505 | J100: 202506 | K100: 202507 | L100: 202508 | M100: 202509 | N100: 202510 | O100: 202511 | P100: 202512
C101: B00 | D101: 3382579464 | E101: 13358014616 | F101: 20886756018 | G101: 30559653757 | H101: 40289319449 | I101: 54191302606 | J101: 63315830655 | K101: 68679537673 | L101: 71247584742 | M101: 79952553855 | N101: 88082122938 | O101: 92768484578 | P101: 99173467204
C102: B01 | E102: 111416305 | F102: 807339693 | G102: 896330074 | H102: 1499190052 | I102: 1696568932 | J102: 2644553730 | K102: 2755878002 | L102: 3179847550 | M102: 3936172334 | N102: 4299368678 | O102: 4567849283 | P102: 4457121839
C103: B02 | F103: 84996305 | G103: 417531388 | H103: 546002970 | I103: 1007341529 | J103: 1207002681 | K103: 1625450607 | L103: 1822682961 | M103: 2015305191 | N103: 2463213877 | O103: 3009146180 | P103: 3270492382
C104: B03 | G104: 84996305 | H104: 380446879 | I104: 579654173 | J104: 905755416 | K104: 1064451858 | L104: 1515370444 | M104: 1669975970 | N104: 1838591605 | O104: 2301657467 | P104: 2846917072
C105: B04 | H105: 84996305 | I105: 373570379 | J105: 556796443 | K105: 909589717 | L105: 1099823236 | M105: 1443528947 | N105: 1639615936 | O105: 1765601769 | P105: 2279527475
C106: B05 | I106: 84996305 | J106: 352170379 | K106: 523718388 | L106: 895445480 | M106: 1081533638 | N106: 1401795530 | O106: 1591692886 | P106: 1709941058
C107: B06 | J107: 74296305 | K107: 373027232 | L107: 557217499 | M107: 875786181 | N107: 1054591072 | O107: 1379956689 | P107: 1438906186
C108: B07 | K108: 74296305 | L108: 370919415 | M108: 534053281 | N108: 870712174 | O108: 1052846072 | P108: 1409869512
C109: B08 | L109: 52896305 | M109: 360669423 | N109: 491960190 | O109: 860012174 | P109: 1091748678
C110: B09 | M110: 52896305 | N110: 346003578 | O110: 491960190 | P110: 885892459
C111: B10+ | N111: 98177641 | O111: 444181219 | P111: 941141409
C112: Grand Total | D112: 3382579464 | E112: 13469430921 | F112: 21779092016 | G112: 31958511524 | H112: 42799955655 | I112: 57933433924 | J112: 69056405609 | K112: 76005949782 | L112: 80741787632 | M112: 91922475125 | N112: 102586153219 | O112: 110233388507 | P112: 119505025274
B117: 6 | C117: Early repayment
D119: 1 | E119: 2 | F119: =E119+1 -> 3 | G119: =F119+1 -> 4 | H119: =G119+1 -> 5 | I119: =H119+1 -> 6 | J119: =I119+1 -> 7 | K119: =J119+1 -> 8 | L119: =K119+1 -> 9 | M119: =L119+1 -> 10 | ... O119: =N119+1 -> 12
C120: MOB13 | D120: 0.03 | E120: 0.03 | F120: 0.03 | G120: 0.03 | H120: 0.03 | I120: 0.03 | J120: 0.03 | K120: 0.08 | L120: 0.08 | M120: 0.08 | N120: 0.08 | O120: 0.08
C121: MOB4-other | D121: 0.03 | E121: 0.03 | F121: 0.03 | G121: 0.03 | H121: 0.03 | I121: 0.03 | J121: 0.03 | K121: 0.08 | L121: 0.08 | M121: 0.08 | N121: 0.08 | O121: 0.08
E124: MOB1-3 | F124: MOB4
C125: CL | D125: VNPAY | E125: 0.0608466 | F125: 0.0608466

Sheet SAP_Speadsheet
B1: SAP Speadsheet
C4: Method
C5: Month on book | D5: 0 | E5: =D5+1 -> 1 | F5: =E5+1 -> 2 | G5: =F5+1 -> 3 | H5: =G5+1 -> 4 | I5: =H5+1 -> 5 | J5: =I5+1 -> 6 | K5: =J5+1 -> 7 | L5: =K5+1 -> 8 | ... BL5: =BK5+1 -> 60
C6: Oustanding tenor | D6: =IF(Leadsheet!$E$12-SAP_Speadsheet!D5<0,0,Leadsheet!$E$12-SAP_Speadsheet!D5) -> 16 | E6: =IF(Leadsheet!$E$12-SAP_Speadsheet!E5<0,0,Leadsheet!$E$12-SAP_Speadsheet!E5) -> 15 | F6: =IF(Leadsheet!$E$12-SAP_Speadsheet!F5<0,0,Leadsheet!$E$12-SAP_Speadsheet!F5) -> 14 | G6: =IF(Leadsheet!$E$12-SAP_Speadsheet!G5<0,0,Leadsheet!$E$12-SAP_Speadsheet!G5) -> 13 | H6: =IF(Leadsheet!$E$12-SAP_Speadsheet!H5<0,0,Leadsheet!$E$12-SAP_Speadsheet!H5) -> 12 | I6: =IF(Leadsheet!$E$12-SAP_Speadsheet!I5<0,0,Leadsheet!$E$12-SAP_Speadsheet!I5) -> 11 | J6: =IF(Leadsheet!$E$12-SAP_Speadsheet!J5<0,0,Leadsheet!$E$12-SAP_Speadsheet!J5) -> 10 | K6: =IF(Leadsheet!$E$12-SAP_Speadsheet!K5<0,0,Leadsheet!$E$12-SAP_Speadsheet!K5) -> 9 | ... BL6: =IF(Leadsheet!$E$12-SAP_Speadsheet!BL5<0,0,Leadsheet!$E$12-SAP_Speadsheet!BL5) -> 0
C7: Last month on book | D7: =Leadsheet!E13+Leadsheet!E12 -> 22
B9: Balance
B10: Interest rate
C11: INR rate | D11: =Leadsheet!E18 -> 0.45290894 | E11: =IF(E$5>$D$7,0,VLOOKUP(SAP_Speadsheet!E$5,Leadsheet!$C$18:$F$23,3,1)) -> 0.45290894 | F11: =IF(F$5>$D$7,0,VLOOKUP(SAP_Speadsheet!F$5,Leadsheet!$C$18:$F$23,3,1)) -> 0.45290894 | G11: =IF(G$5>$D$7,0,VLOOKUP(SAP_Speadsheet!G$5,Leadsheet!$C$18:$F$23,3,1)) -> 0.45290894 | H11: =IF(H$5>$D$7,0,VLOOKUP(SAP_Speadsheet!H$5,Leadsheet!$C$18:$F$23,3,1)) -> 0.45290894 | I11: =IF(I$5>$D$7,0,VLOOKUP(SAP_Speadsheet!I$5,Leadsheet!$C$18:$F$23,3,1)) -> 0.45290894 | J11: =IF(J$5>$D$7,0,VLOOKUP(SAP_Speadsheet!J$5,Leadsheet!$C$18:$F$23,3,1)) -> 0.45290894 | K11: =IF(K$5>$D$7,0,VLOOKUP(SAP_Speadsheet!K$5,Leadsheet!$C$18:$F$23,3,1)) -> 0.45290894 | L11: =IF(L$5>$D$7,0,VLOOKUP(SAP_Speadsheet!L$5,Leadsheet!$C$18:$F$23,3,1)) -> 0.45290894 | ... BL11: =IF(BL$5>$D$7,0,VLOOKUP(SAP_Speadsheet!BL$5,Leadsheet!$C$18:$F$23,3,1)) -> 0
C12: COF rate | D12: =Leadsheet!F18 -> 0.074 | E12: =IF(E$5>$D$7,0,VLOOKUP(SAP_Speadsheet!E$5,Leadsheet!$C$18:$F$23,4,1)) -> 0.074 | F12: =IF(F$5>$D$7,0,VLOOKUP(SAP_Speadsheet!F$5,Leadsheet!$C$18:$F$23,4,1)) -> 0.074 | G12: =IF(G$5>$D$7,0,VLOOKUP(SAP_Speadsheet!G$5,Leadsheet!$C$18:$F$23,4,1)) -> 0.074 | H12: =IF(H$5>$D$7,0,VLOOKUP(SAP_Speadsheet!H$5,Leadsheet!$C$18:$F$23,4,1)) -> 0.074 | I12: =IF(I$5>$D$7,0,VLOOKUP(SAP_Speadsheet!I$5,Leadsheet!$C$18:$F$23,4,1)) -> 0.074 | J12: =IF(J$5>$D$7,0,VLOOKUP(SAP_Speadsheet!J$5,Leadsheet!$C$18:$F$23,4,1)) -> 0.074 | K12: =IF(K$5>$D$7,0,VLOOKUP(SAP_Speadsheet!K$5,Leadsheet!$C$18:$F$23,4,1)) -> 0.074 | L12: =IF(L$5>$D$7,0,VLOOKUP(SAP_Speadsheet!L$5,Leadsheet!$C$18:$F$23,4,1)) -> 0.074 | ... BL12: =IF(BL$5>$D$7,0,VLOOKUP(SAP_Speadsheet!BL$5,Leadsheet!$C$18:$F$23,4,1)) -> 0
C13: Attrition rate | E13: =IF(E$5<Leadsheet!$E$12,VLOOKUP(SAP_Speadsheet!E$5,Leadsheet!$C$26:$G$30,5,1),0) -> 0.08 | F13: =IF(F$5<Leadsheet!$E$12,VLOOKUP(SAP_Speadsheet!F$5,Leadsheet!$C$26:$G$30,5,1),0) -> 0.06 | G13: =IF(G$5<Leadsheet!$E$12,VLOOKUP(SAP_Speadsheet!G$5,Leadsheet!$C$26:$G$30,5,1),0) -> 0.06 | H13: =IF(H$5<Leadsheet!$E$12,VLOOKUP(SAP_Speadsheet!H$5,Leadsheet!$C$26:$G$30,5,1),0) -> 0.025 | I13: =IF(I$5<Leadsheet!$E$12,VLOOKUP(SAP_Speadsheet!I$5,Leadsheet!$C$26:$G$30,5,1),0) -> 0.025 | J13: =IF(J$5<Leadsheet!$E$12,VLOOKUP(SAP_Speadsheet!J$5,Leadsheet!$C$26:$G$30,5,1),0) -> 0.025 | K13: =IF(K$5<Leadsheet!$E$12,VLOOKUP(SAP_Speadsheet!K$5,Leadsheet!$C$26:$G$30,5,1),0) -> 0.025 | L13: =IF(L$5<Leadsheet!$E$12,VLOOKUP(SAP_Speadsheet!L$5,Leadsheet!$C$26:$G$30,5,1),0) -> 0.025 | ... BL13: =IF(BL$5<Leadsheet!$E$12,VLOOKUP(SAP_Speadsheet!BL$5,Leadsheet!$C$26:$G$30,5,1),0) -> 0
C14: Prepayment Penalty | E14: =IF(E$5<Leadsheet!$E$12,VLOOKUP(SAP_Speadsheet!E$5,Leadsheet!$C$26:$F$30,3,1),0) -> 0.0608466 | F14: =IF(F$5<Leadsheet!$E$12,VLOOKUP(SAP_Speadsheet!F$5,Leadsheet!$C$26:$F$30,3,1),0) -> 0.0608466 | G14: =IF(G$5<Leadsheet!$E$12,VLOOKUP(SAP_Speadsheet!G$5,Leadsheet!$C$26:$F$30,3,1),0) -> 0.0608466 | H14: =IF(H$5<Leadsheet!$E$12,VLOOKUP(SAP_Speadsheet!H$5,Leadsheet!$C$26:$F$30,3,1),0) -> 0.05 | I14: =IF(I$5<Leadsheet!$E$12,VLOOKUP(SAP_Speadsheet!I$5,Leadsheet!$C$26:$F$30,3,1),0) -> 0.05 | J14: =IF(J$5<Leadsheet!$E$12,VLOOKUP(SAP_Speadsheet!J$5,Leadsheet!$C$26:$F$30,3,1),0) -> 0.05 | K14: =IF(K$5<Leadsheet!$E$12,VLOOKUP(SAP_Speadsheet!K$5,Leadsheet!$C$26:$F$30,3,1),0) -> 0.05 | L14: =IF(L$5<Leadsheet!$E$12,VLOOKUP(SAP_Speadsheet!L$5,Leadsheet!$C$26:$F$30,3,1),0) -> 0.05 | ... BL14: =IF(BL$5<Leadsheet!$E$12,VLOOKUP(SAP_Speadsheet!BL$5,Leadsheet!$C$26:$F$30,3,1),0) -> 0
B16: EMI | C16: Account accumulated | D16: 1 | E16: =IF(E5>$D$7,0,D16-E13) -> 0.92 | F16: =IF(F5>$D$7,0,E16-F13) -> 0.86 | G16: =IF(G5>$D$7,0,F16-G13) -> 0.8 | H16: =IF(H5>$D$7,0,G16-H13) -> 0.775 | I16: =IF(I5>$D$7,0,H16-I13) -> 0.75 | J16: =IF(J5>$D$7,0,I16-J13) -> 0.725 | K16: =IF(K5>$D$7,0,J16-K13) -> 0.7 | L16: =IF(L5>$D$7,0,K16-L13) -> 0.675 | ... BL16: =IF(BL5>$D$7,0,BK16-BL13) -> 0
C17: Nominal ENR | D17: =Leadsheet!E10 -> 14.837554 | E17: =IF(E$5>Leadsheet!$E$12,0,D17+E21+E18) -> 12.958311 | F17: =IF(F$5>Leadsheet!$E$12,0,SAP_Speadsheet!E17+SAP_Speadsheet!F21+F18) -> 11.501246 | G17: =IF(G$5>Leadsheet!$E$12,0,SAP_Speadsheet!F17+SAP_Speadsheet!G21+G18) -> 10.130648 | H17: =IF(H$5>Leadsheet!$E$12,0,SAP_Speadsheet!G17+SAP_Speadsheet!H21+H18) -> 9.2336188 | I17: =IF(I$5>Leadsheet!$E$12,0,SAP_Speadsheet!H17+SAP_Speadsheet!I21+I18) -> 8.3557068 | J17: =IF(J$5>Leadsheet!$E$12,0,SAP_Speadsheet!I17+SAP_Speadsheet!J21+J18) -> 7.4964378 | K17: =IF(K$5>Leadsheet!$E$12,0,SAP_Speadsheet!J17+SAP_Speadsheet!K21+K18) -> 6.6550052 | L17: =IF(L$5>Leadsheet!$E$12,0,SAP_Speadsheet!K17+SAP_Speadsheet!L21+L18) -> 5.8314685 | M17: =IF(M$5>Leadsheet!$E$12,0,SAP_Speadsheet!L17+SAP_Speadsheet!M21+M18) -> 5.0260463 | ... BL17: =IF(BL$5>Leadsheet!$E$12,0,SAP_Speadsheet!BK17+SAP_Speadsheet!BL21+BL18) -> 0
C18: Fully Prepayment Amount | E18: =-IF(E6>0,IFERROR(D27*(D16-E16)/D16,0),0) -> -1.1870043 | F18: =-IF(F6>0,IFERROR(E27*(E16-F16)/E16,0),0) -> -0.79898121 | G18: =-IF(G6>0,IFERROR(F27*(F16-G16)/F16,0),0) -> -0.73203714 | H18: =-IF(H6>0,IFERROR(G27*(G16-H16)/G16,0),0) -> -0.27902412 | I18: =-IF(I6>0,IFERROR(H27*(H16-I16)/H16,0),0) -> -0.25539339 | J18: =-IF(J6>0,IFERROR(I27*(I16-J16)/I16,0),0) -> -0.23241501 | K18: =-IF(K6>0,IFERROR(J27*(J16-K16)/J16,0),0) -> -0.21048116 | L18: =-IF(L6>0,IFERROR(K27*(K16-L16)/K16,0),0) -> -0.18884539 | ... BL18: =-IF(BL6>0,IFERROR(BK27*(BK16-BL16)/BK16,0),0) -> 0
C19: EMI payment | E19: =-IFERROR(PMT(D11/12,D6,-D17),0) -> -1.2522435 | F19: =-IFERROR(PMT(E11/12,E6,-E17),0) -> -1.1471615 | G19: =-IFERROR(PMT(F11/12,F6,-F17),0) -> -1.0726458 | H19: =-IFERROR(PMT(G11/12,G6,-G17),0) -> -1.0003601 | I19: =-IFERROR(PMT(H11/12,H6,-H17),0) -> -0.97101761 | J19: =-IFERROR(PMT(I11/12,I6,-I17),0) -> -0.94221856 | K19: =-IFERROR(PMT(J11/12,J6,-J17),0) -> -0.91388503 | L19: =-IFERROR(PMT(K11/12,K6,-K17),0) -> -0.88586726 | ... BL19: =-IFERROR(PMT(BK11/12,BK6,-BK17),0) -> 0
C20: Nominal Interest | E20: =-IF(E5>$D$6,0,D17*D11/12) -> -0.56000506 | F20: =-IF(F5>$D$6,0,E17*E11/12) -> -0.4890779 | G20: =-IF(G5>$D$6,0,F17*F11/12) -> -0.43408476 | H20: =-IF(H5>$D$6,0,G17*G11/12) -> -0.38235508 | I20: =-IF(I5>$D$6,0,H17*H11/12) -> -0.34849904 | J20: =-IF(J5>$D$6,0,I17*I11/12) -> -0.31536453 | K20: =-IF(K5>$D$6,0,J17*J11/12) -> -0.28293364 | L20: =-IF(L5>$D$6,0,K17*K11/12) -> -0.25117595 | ... BL20: =-IF(BL5>$D$6,0,BK17*BK11/12) -> 0
C21: Nominal Payment | E21: =E19-E20 -> -0.69223848 | F21: =F19-F20 -> -0.65808361 | G21: =G19-G20 -> -0.63856101 | H21: =H19-H20 -> -0.61800501 | I21: =I19-I20 -> -0.62251857 | J21: =J19-J20 -> -0.62685404 | K21: =K19-K20 -> -0.63095139 | L21: =L19-L20 -> -0.63469131 | ... BL21: =BL19-BL20 -> 0
C24: Schedule Payment | E24: =IF(E5>Leadsheet!$E$12,0,IFERROR(E21/D17*D27*(1-Leadsheet!$D$91)+E18,0)) -> -1.8446309 | F24: =IF(F5>Leadsheet!$E$12,0,IFERROR(F21/E17*E27*(1-Leadsheet!$D$91)+F18,0)) -> -1.3900383 | G24: =IF(G5>Leadsheet!$E$12,0,IFERROR(G21/F17*F27*(1-Leadsheet!$D$91)+G18,0)) -> -1.2854655 | H24: =IF(H5>Leadsheet!$E$12,0,IFERROR(H21/G17*G27*(1-Leadsheet!$D$91)+H18,0)) -> -0.79647617 | I24: =IF(I5>Leadsheet!$E$12,0,IFERROR(I21/H17*H27*(1-Leadsheet!$D$91)+I18,0)) -> -0.76247205 | J24: =IF(J5>Leadsheet!$E$12,0,IFERROR(J21/I17*I27*(1-Leadsheet!$D$91)+J18,0)) -> -0.72934164 | K24: =IF(K5>Leadsheet!$E$12,0,IFERROR(K21/J17*J27*(1-Leadsheet!$D$91)+K18,0)) -> -0.69854405 | L24: =IF(L5>Leadsheet!$E$12,0,IFERROR(L21/K17*K27*(1-Leadsheet!$D$91)+L18,0)) -> -0.66791891 | ... BL24: =IF(BL5>Leadsheet!$E$12,0,IFERROR(BL21/BK17*BK27*(1-Leadsheet!$D$91)+BL18,0)) -> 0
A26: SBV | B26: Overdue | C26: Balance by Bucket/Group
A27: G1 | B27: 0 | C27: B0 | D27: =Leadsheet!E10 -> 14.837554 | E27: =IF(E5>=Leadsheet!$E$12,0,D44+E24-SUM(E28:E41)) -> 12.251045 | F27: =IF(F5>=Leadsheet!$E$12,0,E44+F24-SUM(F28:F41)) -> 10.492532 | G27: =IF(G5>=Leadsheet!$E$12,0,F44+G24-SUM(G28:G41)) -> 8.9287719 | H27: =IF(H5>=Leadsheet!$E$12,0,G44+H24-SUM(H28:H41)) -> 7.9171952 | I27: =IF(I5>=Leadsheet!$E$12,0,H44+I24-SUM(I28:I41)) -> 6.9724504 | J27: =IF(J5>=Leadsheet!$E$12,0,I44+J24-SUM(J28:J41)) -> 6.1039536 | K27: =IF(K5>=Leadsheet!$E$12,0,J44+K24-SUM(K28:K41)) -> 5.2876708 | L27: =IF(L5>=Leadsheet!$E$12,0,K44+L24-SUM(L28:L41)) -> 4.5207869 | ... BL27: =IF(BL5>=Leadsheet!$E$12,0,BK44+BL24-SUM(BL28:BL41)) -> 0
A28: G2 | B28: 30 | C28: B1 | E28: =IF(E$5>$D$7,0,D27*Leadsheet!$D91) -> 0.74187768 | F28: =IF(F$5>$D$7,0,E27*Leadsheet!$D91) -> 0.61255226 | G28: =IF(G$5>$D$7,0,F27*Leadsheet!$D91) -> 0.52462662 | H28: =IF(H$5>$D$7,0,G27*Leadsheet!$D91) -> 0.4464386 | I28: =IF(I$5>$D$7,0,H27*Leadsheet!$D91) -> 0.39585976 | J28: =IF(J$5>$D$7,0,I27*Leadsheet!$D91) -> 0.34862252 | K28: =IF(K$5>$D$7,0,J27*Leadsheet!$D91) -> 0.30519768 | L28: =IF(L$5>$D$7,0,K27*Leadsheet!$D91) -> 0.26438354 | ... BL28: =IF(BL$5>$D$7,0,BK27*Leadsheet!$D91) -> 0
A29: G2 | B29: 60 | C29: B2 | E29: =IF(E$5>$D$7,0,D28*Leadsheet!$D92) -> 0 | F29: =IF(F$5>$D$7,0,E28*Leadsheet!$D92) -> 0.49779993 | G29: =IF(G$5>$D$7,0,F28*Leadsheet!$D92) -> 0.41102256 | H29: =IF(H$5>$D$7,0,G28*Leadsheet!$D92) -> 0.35202446 | I29: =IF(I$5>$D$7,0,H28*Leadsheet!$D92) -> 0.2995603 | J29: =IF(J$5>$D$7,0,I28*Leadsheet!$D92) -> 0.2656219 | K29: =IF(K$5>$D$7,0,J28*Leadsheet!$D92) -> 0.23392571 | L29: =IF(L$5>$D$7,0,K28*Leadsheet!$D92) -> 0.20478764 | ... BL29: =IF(BL$5>$D$7,0,BK28*Leadsheet!$D92) -> 0
A30: G2 | B30: 90 | C30: B3 | E30: =IF(E$5>$D$7,0,D29*Leadsheet!$D93) -> 0 | F30: =IF(F$5>$D$7,0,E29*Leadsheet!$D93) -> 0 | G30: =IF(G$5>$D$7,0,F29*Leadsheet!$D93) -> 0.45299793 | H30: =IF(H$5>$D$7,0,G29*Leadsheet!$D93) -> 0.37403053 | I30: =IF(I$5>$D$7,0,H29*Leadsheet!$D93) -> 0.32034226 | J30: =IF(J$5>$D$7,0,I29*Leadsheet!$D93) -> 0.27259987 | K30: =IF(K$5>$D$7,0,J29*Leadsheet!$D93) -> 0.24171593 | L30: =IF(L$5>$D$7,0,K29*Leadsheet!$D93) -> 0.2128724 | ... AU30: =IF(AU$5>$D$7,0,AT29*Leadsheet!$D93) -> 0 | AV30: 0 | AW30: =IF(AW$5>$D$7,0,AV29*Leadsheet!$D93) -> 0 | AX30: =IF(AX$5>$D$7,0,AW29*Leadsheet!$D93) -> 0 | AY30: =IF(AY$5>$D$7,0,AX29*Leadsheet!$D93) -> 0 | AZ30: =IF(AZ$5>$D$7,0,AY29*Leadsheet!$D93) -> 0 | BA30: =IF(BA$5>$D$7,0,AZ29*Leadsheet!$D93) -> 0 | BB30: =IF(BB$5>$D$7,0,BA29*Leadsheet!$D93) -> 0 | BC30: =IF(BC$5>$D$7,0,BB29*Leadsheet!$D93) -> 0 | BD30: =IF(BD$5>$D$7,0,BC29*Leadsheet!$D93) -> 0 | ... BL30: =IF(BL$5>$D$7,0,BK29*Leadsheet!$D93) -> 0
A31: G3 | B31: 120 | C31: B4 | E31: =IF(E$5>$D$7,0,D30*Leadsheet!$D94) -> 0 | F31: =IF(F$5>$D$7,0,E30*Leadsheet!$D94) -> 0 | G31: =IF(G$5>$D$7,0,F30*Leadsheet!$D94) -> 0 | H31: =IF(H$5>$D$7,0,G30*Leadsheet!$D94) -> 0.43125403 | I31: =IF(I$5>$D$7,0,H30*Leadsheet!$D94) -> 0.35607707 | J31: =IF(J$5>$D$7,0,I30*Leadsheet!$D94) -> 0.30496583 | K31: =IF(K$5>$D$7,0,J30*Leadsheet!$D94) -> 0.25951508 | L31: =IF(L$5>$D$7,0,K30*Leadsheet!$D94) -> 0.23011356 | ... BL31: =IF(BL$5>$D$7,0,BK30*Leadsheet!$D94) -> 0
A32: G3 | B32: 150 | C32: B5 | E32: =IF(E$5>$D$7,0,D31*Leadsheet!$D95) -> 0 | F32: =IF(F$5>$D$7,0,E31*Leadsheet!$D95) -> 0 | G32: =IF(G$5>$D$7,0,F31*Leadsheet!$D95) -> 0 | H32: =IF(H$5>$D$7,0,G31*Leadsheet!$D95) -> 0 | I32: =IF(I$5>$D$7,0,H31*Leadsheet!$D95) -> 0.41418107 | J32: =IF(J$5>$D$7,0,I31*Leadsheet!$D95) -> 0.34198029 | K32: =IF(K$5>$D$7,0,J31*Leadsheet!$D95) -> 0.2928925 | L32: =IF(L$5>$D$7,0,K31*Leadsheet!$D95) -> 0.24924111 | ... BL32: =IF(BL$5>$D$7,0,BK31*Leadsheet!$D95) -> 0
A33: G3 | B33: 180 | C33: B6 | E33: =IF(E$5>$D$7,0,D32*Leadsheet!$D96) -> 0 | F33: =IF(F$5>$D$7,0,E32*Leadsheet!$D96) -> 0 | G33: =IF(G$5>$D$7,0,F32*Leadsheet!$D96) -> 0 | H33: =IF(H$5>$D$7,0,G32*Leadsheet!$D96) -> 0 | I33: =IF(I$5>$D$7,0,H32*Leadsheet!$D96) -> 0 | J33: =IF(J$5>$D$7,0,I32*Leadsheet!$D96) -> 0.39138511 | K33: =IF(K$5>$D$7,0,J32*Leadsheet!$D96) -> 0.32315817 | L33: =IF(L$5>$D$7,0,K32*Leadsheet!$D96) -> 0.2767721 | ... BL33: =IF(BL$5>$D$7,0,BK32*Leadsheet!$D96) -> 0
A34: G4 | B34: 210 | C34: B7 | E34: =IF(E$5>$D$7,0,D33*Leadsheet!$D97) -> 0 | F34: =IF(F$5>$D$7,0,E33*Leadsheet!$D97) -> 0 | G34: =IF(G$5>$D$7,0,F33*Leadsheet!$D97) -> 0 | H34: =IF(H$5>$D$7,0,G33*Leadsheet!$D97) -> 0 | I34: =IF(I$5>$D$7,0,H33*Leadsheet!$D97) -> 0 | J34: =IF(J$5>$D$7,0,I33*Leadsheet!$D97) -> 0 | K34: =IF(K$5>$D$7,0,J33*Leadsheet!$D97) -> 0.38650925 | L34: =IF(L$5>$D$7,0,K33*Leadsheet!$D97) -> 0.31913228 | ... BL34: =IF(BL$5>$D$7,0,BK33*Leadsheet!$D97) -> 0
A35: G4 | B35: 240 | C35: B8 | E35: =IF(E$5>$D$7,0,D34*Leadsheet!$D98) -> 0 | F35: =IF(F$5>$D$7,0,E34*Leadsheet!$D98) -> 0 | G35: =IF(G$5>$D$7,0,F34*Leadsheet!$D98) -> 0 | H35: =IF(H$5>$D$7,0,G34*Leadsheet!$D98) -> 0 | I35: =IF(I$5>$D$7,0,H34*Leadsheet!$D98) -> 0 | J35: =IF(J$5>$D$7,0,I34*Leadsheet!$D98) -> 0 | K35: =IF(K$5>$D$7,0,J34*Leadsheet!$D98) -> 0 | L35: =IF(L$5>$D$7,0,K34*Leadsheet!$D98) -> 0.38457671 | ... BL35: =IF(BL$5>$D$7,0,BK34*Leadsheet!$D98) -> 0
A36: G4 | B36: 270 | C36: B9 | E36: =IF(E$5>$D$7,0,D35*Leadsheet!$D99) -> 0 | F36: =IF(F$5>$D$7,0,E35*Leadsheet!$D99) -> 0 | G36: =IF(G$5>$D$7,0,F35*Leadsheet!$D99) -> 0 | H36: =IF(H$5>$D$7,0,G35*Leadsheet!$D99) -> 0 | I36: =IF(I$5>$D$7,0,H35*Leadsheet!$D99) -> 0 | J36: =IF(J$5>$D$7,0,I35*Leadsheet!$D99) -> 0 | K36: =IF(K$5>$D$7,0,J35*Leadsheet!$D99) -> 0 | L36: =IF(L$5>$D$7,0,K35*Leadsheet!$D99) -> 0 | ... BL36: =IF(BL$5>$D$7,0,BK35*Leadsheet!$D99) -> 0
A37: G4 | B37: 300 | C37: B10 | E37: =IF(E$5>$D$7,0,D36*Leadsheet!$D100) -> 0 | F37: =IF(F$5>$D$7,0,E36*Leadsheet!$D100) -> 0 | G37: =IF(G$5>$D$7,0,F36*Leadsheet!$D100) -> 0 | H37: =IF(H$5>$D$7,0,G36*Leadsheet!$D100) -> 0 | I37: =IF(I$5>$D$7,0,H36*Leadsheet!$D100) -> 0 | J37: =IF(J$5>$D$7,0,I36*Leadsheet!$D100) -> 0 | K37: =IF(K$5>$D$7,0,J36*Leadsheet!$D100) -> 0 | L37: =IF(L$5>$D$7,0,K36*Leadsheet!$D100) -> 0 | ... BL37: =IF(BL$5>$D$7,0,BK36*Leadsheet!$D100) -> 0
A38: G4 | B38: 330 | C38: B11 | E38: =IF(E$5>$D$7,0,D37*Leadsheet!$D101) -> 0 | F38: =IF(F$5>$D$7,0,E37*Leadsheet!$D101) -> 0 | G38: =IF(G$5>$D$7,0,F37*Leadsheet!$D101) -> 0 | H38: =IF(H$5>$D$7,0,G37*Leadsheet!$D101) -> 0 | I38: =IF(I$5>$D$7,0,H37*Leadsheet!$D101) -> 0 | J38: =IF(J$5>$D$7,0,I37*Leadsheet!$D101) -> 0 | K38: =IF(K$5>$D$7,0,J37*Leadsheet!$D101) -> 0 | L38: =IF(L$5>$D$7,0,K37*Leadsheet!$D101) -> 0 | ... BL38: =IF(BL$5>$D$7,0,BK37*Leadsheet!$D101) -> 0
A39: G4 | B39: 360 | C39: B12 | E39: =IF(E$5>$D$7,0,D38*Leadsheet!$D102) -> 0 | F39: =IF(F$5>$D$7,0,E38*Leadsheet!$D102) -> 0 | G39: =IF(G$5>$D$7,0,F38*Leadsheet!$D102) -> 0 | H39: =IF(H$5>$D$7,0,G38*Leadsheet!$D102) -> 0 | I39: =IF(I$5>$D$7,0,H38*Leadsheet!$D102) -> 0 | J39: =IF(J$5>$D$7,0,I38*Leadsheet!$D102) -> 0 | K39: =IF(K$5>$D$7,0,J38*Leadsheet!$D102) -> 0 | L39: =IF(L$5>$D$7,0,K38*Leadsheet!$D102) -> 0 | ... BL39: =IF(BL$5>$D$7,0,BK38*Leadsheet!$D102) -> 0
A40: G5 | B40: 390 | C40: B13 | E40: =IF(E$5>$D$7,0,D39*Leadsheet!$D103) -> 0 | F40: =IF(F$5>$D$7,0,E39*Leadsheet!$D103) -> 0 | G40: =IF(G$5>$D$7,0,F39*Leadsheet!$D103) -> 0 | H40: =IF(H$5>$D$7,0,G39*Leadsheet!$D103) -> 0 | I40: =IF(I$5>$D$7,0,H39*Leadsheet!$D103) -> 0 | J40: =IF(J$5>$D$7,0,I39*Leadsheet!$D103) -> 0 | K40: =IF(K$5>$D$7,0,J39*Leadsheet!$D103) -> 0 | L40: =IF(L$5>$D$7,0,K39*Leadsheet!$D103) -> 0 | ... BL40: =IF(BL$5>$D$7,0,BK39*Leadsheet!$D103) -> 0
A41: G5 | B41: 420+ | C41: B14+ | E41: =IF(E5>$D$7,0,D40+D41) -> 0 | F41: =IF(F5>$D$7,0,E40+E41) -> 0 | G41: =IF(G5>$D$7,0,F40+F41) -> 0 | H41: =IF(H5>$D$7,0,G40+G41) -> 0 | I41: =IF(I5>$D$7,0,H40+H41) -> 0 | J41: =IF(J5>$D$7,0,I40+I41) -> 0 | K41: =IF(K5>$D$7,0,J40+J41) -> 0 | L41: =IF(L5>$D$7,0,K40+K41) -> 0 | ... BL41: =IF(BL5>$D$7,0,BK40+BK41) -> 0
B43: ENR
C44: Total bank | D44: =SUM(D27:D41) -> 14.837554 | E44: =SUM(E27:E41) -> 12.992923 | F44: =SUM(F27:F41) -> 11.602885 | G44: =SUM(G27:G41) -> 10.317419 | H44: =SUM(H27:H41) -> 9.5209429 | I44: =SUM(I27:I41) -> 8.7584708 | J44: =SUM(J27:J41) -> 8.0291292 | K44: =SUM(K27:K41) -> 7.3305851 | ... BL44: =SUM(BL27:BL41) -> 0
C45: Outstanding balance | D45: {=IF(D5=$D$7,0,_xlfn.IFS(Leadsheet!$G$5="DPD360+",SUM(SAP_Speadsheet!D27:D40),Leadsheet!$G$5="DPD180+",SUM(SAP_Speadsheet!D27:D34)))} -> 14.837554 | E45: {=IF(E5=$D$7,0,_xlfn.IFS(Leadsheet!$G$5="DPD360+",SUM(SAP_Speadsheet!E27:E40),Leadsheet!$G$5="DPD180+",SUM(SAP_Speadsheet!E27:E34)))} -> 12.992923 | F45: {=IF(F5=$D$7,0,_xlfn.IFS(Leadsheet!$G$5="DPD360+",SUM(SAP_Speadsheet!F27:F40),Leadsheet!$G$5="DPD180+",SUM(SAP_Speadsheet!F27:F34)))} -> 11.602885 | G45: {=IF(G5=$D$7,0,_xlfn.IFS(Leadsheet!$G$5="DPD360+",SUM(SAP_Speadsheet!G27:G40),Leadsheet!$G$5="DPD180+",SUM(SAP_Speadsheet!G27:G34)))} -> 10.317419 | H45: {=IF(H5=$D$7,0,_xlfn.IFS(Leadsheet!$G$5="DPD360+",SUM(SAP_Speadsheet!H27:H40),Leadsheet!$G$5="DPD180+",SUM(SAP_Speadsheet!H27:H34)))} -> 9.5209429 | I45: {=IF(I5=$D$7,0,_xlfn.IFS(Leadsheet!$G$5="DPD360+",SUM(SAP_Speadsheet!I27:I40),Leadsheet!$G$5="DPD180+",SUM(SAP_Speadsheet!I27:I34)))} -> 8.7584708 | J45: {=IF(J5=$D$7,0,_xlfn.IFS(Leadsheet!$G$5="DPD360+",SUM(SAP_Speadsheet!J27:J40),Leadsheet!$G$5="DPD180+",SUM(SAP_Speadsheet!J27:J34)))} -> 8.0291292 | K45: {=IF(K5=$D$7,0,_xlfn.IFS(Leadsheet!$G$5="DPD360+",SUM(SAP_Speadsheet!K27:K40),Leadsheet!$G$5="DPD180+",SUM(SAP_Speadsheet!K27:K34)))} -> 7.3305851 | ... BL45: {=IF(BL5=$D$7,0,_xlfn.IFS(Leadsheet!$G$5="DPD360+",SUM(SAP_Speadsheet!BL27:BL40),Leadsheet!$G$5="DPD180+",SUM(SAP_Speadsheet!BL27:BL34)))} -> 0
C46: Writeoff balance | D46: =D44-D45 -> 0 | E46: =E44-E45 -> 0 | F46: =F44-F45 -> 0 | G46: =G44-G45 -> 0 | H46: =H44-H45 -> 0 | I46: =I44-I45 -> 0 | J46: =J44-J45 -> 0 | K46: =K44-K45 -> 0 | ... BL46: =BL44-BL45 -> 0
C47: Outstanding Bal/TB | D47: =IFERROR(D45/D44,"") -> 1 | E47: =IFERROR(E45/E44,"") -> 1 | F47: =IFERROR(F45/F44,"") -> 1 | G47: =IFERROR(G45/G44,"") -> 1 | H47: =IFERROR(H45/H44,"") -> 1 | I47: =IFERROR(I45/I44,"") -> 1 | J47: =IFERROR(J45/J44,"") -> 1 | K47: =IFERROR(K45/K44,"") -> 1 | ... BL47: =IFERROR(BL45/BL44,"")
B49: ANR
C50: Outstanding balance | E50: =IF(E5>$D$7,0,AVERAGE(D45:E45)) -> 13.915238 | F50: =IF(F5>$D$7,0,AVERAGE(E45:F45)) -> 12.297904 | G50: =IF(G5>$D$7,0,AVERAGE(F45:G45)) -> 10.960152 | H50: =IF(H5>$D$7,0,AVERAGE(G45:H45)) -> 9.9191809 | I50: =IF(I5>$D$7,0,AVERAGE(H45:I45)) -> 9.1397068 | J50: =IF(J5>$D$7,0,AVERAGE(I45:J45)) -> 8.3938 | K50: =IF(K5>$D$7,0,AVERAGE(J45:K45)) -> 7.6798571 | L50: =IF(L5>$D$7,0,AVERAGE(K45:L45)) -> 6.8043373 | ... BL50: =IF(BL5>$D$7,0,AVERAGE(BK45:BL45)) -> 0
C51: ANR for CII (B0+B1A) | E51: =D27*(1-Leadsheet!$D$91)+D28*Leadsheet!$E$117 -> 14.095676 | F51: =E27*(1-Leadsheet!$D$91)+E28*Leadsheet!$E$117 -> 11.882571 | G51: =F27*(1-Leadsheet!$D$91)+F28*Leadsheet!$E$117 -> 10.169435 | H51: =G27*(1-Leadsheet!$D$91)+G28*Leadsheet!$E$117 -> 8.6549355 | I51: =H27*(1-Leadsheet!$D$91)+H28*Leadsheet!$E$117 -> 7.6682138 | J51: =I27*(1-Leadsheet!$D$91)+I28*Leadsheet!$E$117 -> 6.7540657 | K51: =J27*(1-Leadsheet!$D$91)+J28*Leadsheet!$E$117 -> 5.9134528 | L51: =K27*(1-Leadsheet!$D$91)+K28*Leadsheet!$E$117 -> 5.1236973 | ... BL51: =BK27*(1-Leadsheet!$D$91)+BK28*Leadsheet!$E$117 -> 0
B53: Performance
B55: TOI | E55: =E57+E61+E68 -> 1.142854 | F55: =F57+F61+F68 -> 0.42125509 | G55: =G57+G61+G68 -> 0.36077339 | H55: =H57+H61+H68 -> 0.27944106 | I55: =I57+I61+I68 -> 0.24582502 | J55: =J57+J61+J68 -> 0.21477371 | K55: =K57+K61+K68 -> 0.18635291 | L55: =L57+L61+L68 -> 0.16086288 | ... BL55: =BL57+BL61+BL68 -> 0
C57: Net interest income | E57: =E58+E59 -> 0.44619417 | F57: =F58+F59 -> 0.3726398 | G57: =G58+G59 -> 0.31623141 | H57: =H58+H59 -> 0.26548985 | I57: =I58+I59 -> 0.23305535 | J57: =J58+J59 -> 0.20315296 | K57: =K58+K59 -> 0.17582885 | L57: =L58+L59 -> 0.15142061 | ... BL57: =BL58+BL59 -> 0
C58: Interest income | E58: =IFERROR(E$51*D$11/12,0) -> 0.5320048 | F58: =IFERROR(F$51*E$11/12,0) -> 0.44847687 | G58: =IFERROR(G$51*F$11/12,0) -> 0.38381902 | H58: =IFERROR(H$51*G$11/12,0) -> 0.32665814 | I58: =IFERROR(I$51*H$11/12,0) -> 0.28941688 | J58: =IFERROR(J$51*I$11/12,0) -> 0.25491473 | K58: =IFERROR(K$51*J$11/12,0) -> 0.22318797 | L58: =IFERROR(L$51*K$11/12,0) -> 0.19338069 | ... BL58: =IFERROR(BL$51*BK$11/12,0) -> 0
C59: Cost of fund | E59: =-IFERROR(E50*D12/12,0) -> -0.085810636 | F59: =-IFERROR(F50*E12/12,0) -> -0.075837073 | G59: =-IFERROR(G50*F12/12,0) -> -0.067587603 | H59: =-IFERROR(H50*G12/12,0) -> -0.061168282 | I59: =-IFERROR(I50*H12/12,0) -> -0.056361525 | J59: =-IFERROR(J50*I12/12,0) -> -0.051761767 | K59: =-IFERROR(K50*J12/12,0) -> -0.047359119 | L59: =-IFERROR(L50*K12/12,0) -> -0.04196008 | ... BL59: =-IFERROR(BL50*BK12/12,0) -> 0
C61: Net fee income | E61: =SUM(E62:E64) -> 0.69665983 | F61: =SUM(F62:F64) -> 0.04861529 | G61: =SUM(G62:G64) -> 0.044541971 | H61: =SUM(H62:H64) -> 0.013951206 | I61: =SUM(I62:I64) -> 0.01276967 | J61: =SUM(J62:J64) -> 0.011620751 | K61: =SUM(K62:K64) -> 0.010524058 | L61: =SUM(L62:L64) -> 0.0094422693 | ... BL61: =SUM(BL62:BL64) -> 0
C62: Early termination fee | E62: =-E18*E14 -> 0.072225175 | F62: =-F18*F14 -> 0.04861529 | G62: =-G18*G14 -> 0.044541971 | H62: =-H18*H14 -> 0.013951206 | I62: =-I18*I14 -> 0.01276967 | J62: =-J18*J14 -> 0.011620751 | K62: =-K18*K14 -> 0.010524058 | L62: =-L18*L14 -> 0.0094422693 | ... BL62: =-BL18*BL14 -> 0
C63: Insurrance fee | E63: =Leadsheet!E10*Leadsheet!E33*Leadsheet!E35*Leadsheet!E36+Leadsheet!E10/(1+Leadsheet!E34*Leadsheet!E35)*Leadsheet!E34*Leadsheet!E35*Leadsheet!E36 -> 0.62443465
C64: Support fee | E64: =SUM(E65:E66) -> 0 | F64: =SUM(F65:F66) -> 0 | G64: =SUM(G65:G66) -> 0 | H64: =SUM(H65:H66) -> 0 | I64: =SUM(I65:I66) -> 0 | J64: =SUM(J65:J66) -> 0 | K64: =SUM(K65:K66) -> 0 | L64: =SUM(L65:L66) -> 0 | ... BL64: =SUM(BL65:BL66) -> 0
C65: One-time | E65: =Leadsheet!E10*Leadsheet!E39+Leadsheet!E38 -> 0
C66: Monthly fee | E66: =IF(E5>$D$6,0,$D$17*Leadsheet!$E$40*D16*((D27*(1-Leadsheet!$D$91)+D28*Leadsheet!$E$117)/D45)) -> 0 | F66: =IF(F5>$D$6,0,$D$17*Leadsheet!$E$40*E16*((E27*(1-Leadsheet!$D$91)+E28*Leadsheet!$E$117)/E45)) -> 0 | G66: =IF(G5>$D$6,0,$D$17*Leadsheet!$E$40*F16*((F27*(1-Leadsheet!$D$91)+F28*Leadsheet!$E$117)/F45)) -> 0 | H66: =IF(H5>$D$6,0,$D$17*Leadsheet!$E$40*G16*((G27*(1-Leadsheet!$D$91)+G28*Leadsheet!$E$117)/G45)) -> 0 | I66: =IF(I5>$D$6,0,$D$17*Leadsheet!$E$40*H16*((H27*(1-Leadsheet!$D$91)+H28*Leadsheet!$E$117)/H45)) -> 0 | J66: =IF(J5>$D$6,0,$D$17*Leadsheet!$E$40*I16*((I27*(1-Leadsheet!$D$91)+I28*Leadsheet!$E$117)/I45)) -> 0 | K66: =IF(K5>$D$6,0,$D$17*Leadsheet!$E$40*J16*((J27*(1-Leadsheet!$D$91)+J28*Leadsheet!$E$117)/J45)) -> 0 | L66: =IF(L5>$D$6,0,$D$17*Leadsheet!$E$40*K16*((K27*(1-Leadsheet!$D$91)+K28*Leadsheet!$E$117)/K45)) -> 0 | ... BL66: =IF(BL5>$D$6,0,$D$17*Leadsheet!$E$40*BK16*((BK27*(1-Leadsheet!$D$91)+BK28*Leadsheet!$E$117)/BK45)) -> 0
B68: Other Income | E68: {=IF(E5=$D$7,_xlfn.IFS(Leadsheet!$G$4="IFRS",0,Leadsheet!$G$5="DPD180+",(E180-E145)*(1+Leadsheet!$E$115),Leadsheet!$G$5="DPD360+",(E165-E145)*(1+Leadsheet!$E$115)),0)} -> 0 | F68: {=IF(F5=$D$7,_xlfn.IFS(Leadsheet!$G$4="IFRS",0,Leadsheet!$G$5="DPD180+",(F180-F145)*(1+Leadsheet!$E$115),Leadsheet!$G$5="DPD360+",(F165-F145)*(1+Leadsheet!$E$115)),0)} -> 0 | G68: {=IF(G5=$D$7,_xlfn.IFS(Leadsheet!$G$4="IFRS",0,Leadsheet!$G$5="DPD180+",(G180-G145)*(1+Leadsheet!$E$115),Leadsheet!$G$5="DPD360+",(G165-G145)*(1+Leadsheet!$E$115)),0)} -> 0 | H68: {=IF(H5=$D$7,_xlfn.IFS(Leadsheet!$G$4="IFRS",0,Leadsheet!$G$5="DPD180+",(H180-H145)*(1+Leadsheet!$E$115),Leadsheet!$G$5="DPD360+",(H165-H145)*(1+Leadsheet!$E$115)),0)} -> 0 | I68: {=IF(I5=$D$7,_xlfn.IFS(Leadsheet!$G$4="IFRS",0,Leadsheet!$G$5="DPD180+",(I180-I145)*(1+Leadsheet!$E$115),Leadsheet!$G$5="DPD360+",(I165-I145)*(1+Leadsheet!$E$115)),0)} -> 0 | J68: {=IF(J5=$D$7,_xlfn.IFS(Leadsheet!$G$4="IFRS",0,Leadsheet!$G$5="DPD180+",(J180-J145)*(1+Leadsheet!$E$115),Leadsheet!$G$5="DPD360+",(J165-J145)*(1+Leadsheet!$E$115)),0)} -> 0 | K68: {=IF(K5=$D$7,_xlfn.IFS(Leadsheet!$G$4="IFRS",0,Leadsheet!$G$5="DPD180+",(K180-K145)*(1+Leadsheet!$E$115),Leadsheet!$G$5="DPD360+",(K165-K145)*(1+Leadsheet!$E$115)),0)} -> 0 | L68: {=IF(L5=$D$7,_xlfn.IFS(Leadsheet!$G$4="IFRS",0,Leadsheet!$G$5="DPD180+",(L180-L145)*(1+Leadsheet!$E$115),Leadsheet!$G$5="DPD360+",(L165-L145)*(1+Leadsheet!$E$115)),0)} -> 0 | ... BL68: {=IF(BL5=$D$7,_xlfn.IFS(Leadsheet!$G$4="IFRS",0,Leadsheet!$G$5="DPD180+",(BL180-BL145)*(1+Leadsheet!$E$115),Leadsheet!$G$5="DPD360+",(BL165-BL145)*(1+Leadsheet!$E$115)),0)} -> 0
B71: VARIABLE EXPENSES | E71: =E72+E85+E88+E95+E99 -> -0.37152129 | F71: =F72+F85+F88+F95+F99 -> -0.0080782431 | G71: =G72+G85+G88+G95+G99 -> -0.0075481331 | H71: =H72+H85+H88+H95+H99 -> -0.0070472539 | I71: =I72+I85+I88+I95+I99 -> -0.0068263748 | J71: =J72+J85+J88+J95+J99 -> -0.0066054956 | K71: =K72+K85+K88+K95+K99 -> -0.0063846165 | L71: =L72+L85+L88+L95+L99 -> -0.0061637373 | ... BL71: =BL72+BL85+BL88+BL95+BL99 -> 0
B72: Sale incentive | E72: =E73+E74 -> -0.29675107 | F72: =F73+F74 -> 0 | G72: =G73+G74 -> 0 | H72: =H73+H74 -> 0 | I72: =I73+I74 -> 0 | J72: =J73+J74 -> 0 | K72: =K73+K74 -> 0 | L72: =L73+L74 -> 0 | ... BL72: =BL73+BL74 -> 0
C73: Lead Acquistion | E73: =-Leadsheet!E56-Leadsheet!E57*Leadsheet!E10 -> -0.29675107
C74: Sharing Performance | E74: =SUM(E75:E82) -> 0 | F74: =SUM(F75:F82) -> 0 | G74: =SUM(G75:G82) -> 0 | H74: =SUM(H75:H82) -> 0 | I74: =SUM(I75:I82) -> 0 | J74: =SUM(J75:J82) -> 0 | K74: =SUM(K75:K82) -> 0 | L74: =SUM(L75:L82) -> 0 | ... BL74: =SUM(BL75:BL82) -> 0
C75: Sharing CII (only) | E75: =-SUM(E58:E58)*Leadsheet!$E$50 -> 0 | F75: =-SUM(F58:F58)*Leadsheet!$E$50 -> 0 | G75: =-SUM(G58:G58)*Leadsheet!$E$50 -> 0 | H75: =-SUM(H58:H58)*Leadsheet!$E$50 -> 0 | I75: =-SUM(I58:I58)*Leadsheet!$E$50 -> 0 | J75: =-SUM(J58:J58)*Leadsheet!$E$50 -> 0 | K75: =-SUM(K58:K58)*Leadsheet!$E$50 -> 0 | L75: =-SUM(L58:L58)*Leadsheet!$E$50 -> 0 | ... BL75: =-SUM(BL58:BL58)*Leadsheet!$E$50 -> 0
C76: Sharing COF (only) | E76: =-E59*Leadsheet!$E$51 -> 0 | F76: =-F59*Leadsheet!$E$51 -> 0 | G76: =-G59*Leadsheet!$E$51 -> 0 | H76: =-H59*Leadsheet!$E$51 -> 0 | I76: =-I59*Leadsheet!$E$51 -> 0 | J76: =-J59*Leadsheet!$E$51 -> 0 | K76: =-K59*Leadsheet!$E$51 -> 0 | L76: =-L59*Leadsheet!$E$51 -> 0 | ... BL76: =-BL59*Leadsheet!$E$51 -> 0
C77: Sharing NFI (only) | E77: =-E61*Leadsheet!$E$52 -> 0 | F77: =-F61*Leadsheet!$E$52 -> 0 | G77: =-G61*Leadsheet!$E$52 -> 0 | H77: =-H61*Leadsheet!$E$52 -> 0 | I77: =-I61*Leadsheet!$E$52 -> 0 | J77: =-J61*Leadsheet!$E$52 -> 0 | K77: =-K61*Leadsheet!$E$52 -> 0 | L77: =-L61*Leadsheet!$E$52 -> 0 | ... BL77: =-BL61*Leadsheet!$E$52 -> 0
C78: Sharing Risk DPD90+ (Only) | E78: =IF(E5>$D$7,0,Leadsheet!$E$53*(E31-SUM(D31:D39)+SUM(E32:E40))) -> 0 | F78: =IF(F5>$D$7,0,Leadsheet!$E$53*(F31-SUM(E31:E39)+SUM(F32:F40))) -> 0 | G78: =IF(G5>$D$7,0,Leadsheet!$E$53*(G31-SUM(F31:F39)+SUM(G32:G40))) -> 0 | H78: =IF(H5>$D$7,0,Leadsheet!$E$53*(H31-SUM(G31:G39)+SUM(H32:H40))) -> 0 | I78: =IF(I5>$D$7,0,Leadsheet!$E$53*(I31-SUM(H31:H39)+SUM(I32:I40))) -> 0 | J78: =IF(J5>$D$7,0,Leadsheet!$E$53*(J31-SUM(I31:I39)+SUM(J32:J40))) -> 0 | K78: =IF(K5>$D$7,0,Leadsheet!$E$53*(K31-SUM(J31:J39)+SUM(K32:K40))) -> 0 | L78: =IF(L5>$D$7,0,Leadsheet!$E$53*(L31-SUM(K31:K39)+SUM(L32:L40))) -> 0 | ... BL78: =IF(BL5>$D$7,0,Leadsheet!$E$53*(BL31-SUM(BK31:BK39)+SUM(BL32:BL40))) -> 0
C79: Sharing Risk DPD180+ (only) | E79: =IF(E5>$D$7,0,Leadsheet!$E$54*(E34-SUM(D34:D39)+SUM(E35:E40))) -> 0 | F79: =IF(F5>$D$7,0,Leadsheet!$E$54*(F34-SUM(E34:E39)+SUM(F35:F40))) -> 0 | G79: =IF(G5>$D$7,0,Leadsheet!$E$54*(G34-SUM(F34:F39)+SUM(G35:G40))) -> 0 | H79: =IF(H5>$D$7,0,Leadsheet!$E$54*(H34-SUM(G34:G39)+SUM(H35:H40))) -> 0 | I79: =IF(I5>$D$7,0,Leadsheet!$E$54*(I34-SUM(H34:H39)+SUM(I35:I40))) -> 0 | J79: =IF(J5>$D$7,0,Leadsheet!$E$54*(J34-SUM(I34:I39)+SUM(J35:J40))) -> 0 | K79: =IF(K5>$D$7,0,Leadsheet!$E$54*(K34-SUM(J34:J39)+SUM(K35:K40))) -> 0 | L79: =IF(L5>$D$7,0,Leadsheet!$E$54*(L34-SUM(K34:K39)+SUM(L35:L40))) -> 0 | ... BL79: =IF(BL5>$D$7,0,Leadsheet!$E$54*(BL34-SUM(BK34:BK39)+SUM(BL35:BL40))) -> 0
C80: Risk cap to CAKE | G80: =IF(SUM(SAP_Speadsheet!E78:BL79)>(SAP_Speadsheet!E84*Leadsheet!E53+SAP_Speadsheet!E84*Leadsheet!E54),-Leadsheet!E10*Leadsheet!E55,-SUM(SAP_Speadsheet!E78:BL79)) -> 0
C81: Sharing TOI+ Risk DPD90+ | E81: =IF(E5>$D$7,0,Leadsheet!$E$47*(-(E57+E61)+E31-SUM(D31:D39)+SUM(E32:E40))) -> 0 | F81: =IF(F5>$D$7,0,Leadsheet!$E$47*(-(F57+F61)+F31-SUM(E31:E39)+SUM(F32:F40))) -> 0 | G81: =IF(G5>$D$7,0,Leadsheet!$E$47*(-(G57+G61)+G31-SUM(F31:F39)+SUM(G32:G40))) -> 0 | H81: =IF(H5>$D$7,0,Leadsheet!$E$47*(-(H57+H61)+H31-SUM(G31:G39)+SUM(H32:H40))) -> 0 | I81: =IF(I5>$D$7,0,Leadsheet!$E$47*(-(I57+I61)+I31-SUM(H31:H39)+SUM(I32:I40))) -> 0 | J81: =IF(J5>$D$7,0,Leadsheet!$E$47*(-(J57+J61)+J31-SUM(I31:I39)+SUM(J32:J40))) -> 0 | K81: =IF(K5>$D$7,0,Leadsheet!$E$47*(-(K57+K61)+K31-SUM(J31:J39)+SUM(K32:K40))) -> 0 | L81: =IF(L5>$D$7,0,Leadsheet!$E$47*(-(L57+L61)+L31-SUM(K31:K39)+SUM(L32:L40))) -> 0 | ... BL81: =IF(BL5>$D$7,0,Leadsheet!$E$47*(-(BL57+BL61)+BL31-SUM(BK31:BK39)+SUM(BL32:BL40))) -> 0
C82: Sharing TOI+ Risk DPD180+ | E82: =IF(E5>$D$7,0,Leadsheet!$E$48*(-(E57+E61)+E34-SUM(D34:D39)+SUM(E35:E40))) -> 0 | F82: =IF(F5>$D$7,0,Leadsheet!$E$48*(-(F57+F61)+F34-SUM(E34:E39)+SUM(F35:F40))) -> 0 | G82: =IF(G5>$D$7,0,Leadsheet!$E$48*(-(G57+G61)+G34-SUM(F34:F39)+SUM(G35:G40))) -> 0 | H82: =IF(H5>$D$7,0,Leadsheet!$E$48*(-(H57+H61)+H34-SUM(G34:G39)+SUM(H35:H40))) -> 0 | I82: =IF(I5>$D$7,0,Leadsheet!$E$48*(-(I57+I61)+I34-SUM(H34:H39)+SUM(I35:I40))) -> 0 | J82: =IF(J5>$D$7,0,Leadsheet!$E$48*(-(J57+J61)+J34-SUM(I34:I39)+SUM(J35:J40))) -> 0 | K82: =IF(K5>$D$7,0,Leadsheet!$E$48*(-(K57+K61)+K34-SUM(J34:J39)+SUM(K35:K40))) -> 0 | L82: =IF(L5>$D$7,0,Leadsheet!$E$48*(-(L57+L61)+L34-SUM(K34:K39)+SUM(L35:L40))) -> 0 | ... BL82: =IF(BL5>$D$7,0,Leadsheet!$E$48*(-(BL57+BL61)+BL34-SUM(BK34:BK39)+SUM(BL35:BL40))) -> 0
B85: Marketing | E85: =E86+E67 -> 0
C86: Marketing_acquisition | E86: =-Leadsheet!E61 -> 0
B88: UW & Disbursal | E88: =E89+E90+E91 -> -0.066001863
C89: Underwriting Cost | E89: =-Leadsheet!E63/Leadsheet!E66/Leadsheet!E67-Leadsheet!E64 -> -0.063721031
C90: Disbursement cost | E90: =-Leadsheet!E65 -> -0.0022808325
C91: DOP cost | E91: =-Leadsheet!E64 -> 0
C93: Expense Increase | E93: 1 | F93: =IF(F$5>$D$7,0,IF(F$5<12,1,(1+Leadsheet!$E$43)^(ROUNDDOWN(F$5/12,0)))) -> 1 | G93: =IF(G$5>$D$7,0,IF(G$5<12,1,(1+Leadsheet!$E$43)^(ROUNDDOWN(G$5/12,0)))) -> 1 | H93: =IF(H$5>$D$7,0,IF(H$5<12,1,(1+Leadsheet!$E$43)^(ROUNDDOWN(H$5/12,0)))) -> 1 | I93: =IF(I$5>$D$7,0,IF(I$5<12,1,(1+Leadsheet!$E$43)^(ROUNDDOWN(I$5/12,0)))) -> 1 | J93: =IF(J$5>$D$7,0,IF(J$5<12,1,(1+Leadsheet!$E$43)^(ROUNDDOWN(J$5/12,0)))) -> 1 | K93: =IF(K$5>$D$7,0,IF(K$5<12,1,(1+Leadsheet!$E$43)^(ROUNDDOWN(K$5/12,0)))) -> 1 | L93: =IF(L$5>$D$7,0,IF(L$5<12,1,(1+Leadsheet!$E$43)^(ROUNDDOWN(L$5/12,0)))) -> 1 | M93: =IF(M$5>$D$7,0,IF(M$5<12,1,(1+Leadsheet!$E$43)^(ROUNDDOWN(M$5/12,0)))) -> 1 | ... BL93: =IF(BL$5>$D$7,0,IF(BL$5<12,1,(1+Leadsheet!$E$43)^(ROUNDDOWN(BL$5/12,0)))) -> 0
B95: Collection & AMC | E95: =SUM(E96:E97) -> -0.008 | F95: =SUM(F96:F97) -> -0.00736 | G95: =SUM(G96:G97) -> -0.00688 | H95: =SUM(H96:H97) -> -0.0064 | I95: =SUM(I96:I97) -> -0.0062 | J95: =SUM(J96:J97) -> -0.006 | K95: =SUM(K96:K97) -> -0.0058 | L95: =SUM(L96:L97) -> -0.0056 | ... BL95: =SUM(BL96:BL97) -> 0
C96: Early collections | E96: =-IF(E5>Leadsheet!$E$12,Leadsheet!$E$71*E$93*E44/$D$44,Leadsheet!$E$71*E$93*D16) -> -0.008 | F96: =-IF(F5>Leadsheet!$E$12,Leadsheet!$E$71*F$93*F44/$D$44,Leadsheet!$E$71*F$93*E16) -> -0.00736 | G96: =-IF(G5>Leadsheet!$E$12,Leadsheet!$E$71*G$93*G44/$D$44,Leadsheet!$E$71*G$93*F16) -> -0.00688 | H96: =-IF(H5>Leadsheet!$E$12,Leadsheet!$E$71*H$93*H44/$D$44,Leadsheet!$E$71*H$93*G16) -> -0.0064 | I96: =-IF(I5>Leadsheet!$E$12,Leadsheet!$E$71*I$93*I44/$D$44,Leadsheet!$E$71*I$93*H16) -> -0.0062 | J96: =-IF(J5>Leadsheet!$E$12,Leadsheet!$E$71*J$93*J44/$D$44,Leadsheet!$E$71*J$93*I16) -> -0.006 | K96: =-IF(K5>Leadsheet!$E$12,Leadsheet!$E$71*K$93*K44/$D$44,Leadsheet!$E$71*K$93*J16) -> -0.0058 | L96: =-IF(L5>Leadsheet!$E$12,Leadsheet!$E$71*L$93*L44/$D$44,Leadsheet!$E$71*L$93*K16) -> -0.0056 | ... BL96: =-IF(BL5>Leadsheet!$E$12,Leadsheet!$E$71*BL$93*BL44/$D$44,Leadsheet!$E$71*BL$93*BK16) -> 0
C97: AMC
B99: After sale service | E99: =SUM(E100:E101) -> -0.00076835306 | F99: =SUM(F100:F101) -> -0.00071824308 | G99: =SUM(G100:G101) -> -0.0006681331 | H99: =SUM(H100:H101) -> -0.00064725394 | I99: =SUM(I100:I101) -> -0.00062637478 | J99: =SUM(J100:J101) -> -0.00060549562 | K99: =SUM(K100:K101) -> -0.00058461646 | L99: =SUM(L100:L101) -> -0.0005637373 | ... BL99: =SUM(BL100:BL101) -> 0
C100: SMS & Email | E100: =IF(E5>Leadsheet!$E$12,0,-E16*Leadsheet!$E$78) -> -0.00076835306 | F100: =IF(F5>Leadsheet!$E$12,0,-F16*Leadsheet!$E$78) -> -0.00071824308 | G100: =IF(G5>Leadsheet!$E$12,0,-G16*Leadsheet!$E$78) -> -0.0006681331 | H100: =IF(H5>Leadsheet!$E$12,0,-H16*Leadsheet!$E$78) -> -0.00064725394 | I100: =IF(I5>Leadsheet!$E$12,0,-I16*Leadsheet!$E$78) -> -0.00062637478 | J100: =IF(J5>Leadsheet!$E$12,0,-J16*Leadsheet!$E$78) -> -0.00060549562 | K100: =IF(K5>Leadsheet!$E$12,0,-K16*Leadsheet!$E$78) -> -0.00058461646 | L100: =IF(L5>Leadsheet!$E$12,0,-L16*Leadsheet!$E$78) -> -0.0005637373 | ... BL100: =IF(BL5>Leadsheet!$E$12,0,-BL16*Leadsheet!$E$78) -> 0
B103: OVERHEAD EXPENSES | E103: =SUM(E104:E107) -> -0.056791732 | F103: =SUM(F104:F107) -> -0.052248394 | G103: =SUM(G104:G107) -> -0.04884089 | H103: =SUM(H104:H107) -> -0.045433386 | I103: =SUM(I104:I107) -> -0.044013593 | J103: =SUM(J104:J107) -> -0.042593799 | K103: =SUM(K104:K107) -> -0.041174006 | L103: =SUM(L104:L107) -> -0.039754213 | ... BL103: =SUM(BL104:BL107) -> 0
C104: Direct HR | E104: =-IF(E$5>Leadsheet!$E$12,0,Leadsheet!$E81*SAP_Speadsheet!E$93*D$16) -> -0.0090772826 | F104: =-IF(F$5>Leadsheet!$E$12,0,Leadsheet!$E81*SAP_Speadsheet!F$93*E$16) -> -0.0083511 | G104: =-IF(G$5>Leadsheet!$E$12,0,Leadsheet!$E81*SAP_Speadsheet!G$93*F$16) -> -0.0078064631 | H104: =-IF(H$5>Leadsheet!$E$12,0,Leadsheet!$E81*SAP_Speadsheet!H$93*G$16) -> -0.0072618261 | I104: =-IF(I$5>Leadsheet!$E$12,0,Leadsheet!$E81*SAP_Speadsheet!I$93*H$16) -> -0.007034894 | J104: =-IF(J$5>Leadsheet!$E$12,0,Leadsheet!$E81*SAP_Speadsheet!J$93*I$16) -> -0.006807962 | K104: =-IF(K$5>Leadsheet!$E$12,0,Leadsheet!$E81*SAP_Speadsheet!K$93*J$16) -> -0.0065810299 | L104: =-IF(L$5>Leadsheet!$E$12,0,Leadsheet!$E81*SAP_Speadsheet!L$93*K$16) -> -0.0063540978 | ... BL104: =-IF(BL$5>Leadsheet!$E$12,0,Leadsheet!$E81*SAP_Speadsheet!BL$93*BK$16) -> 0
C105: Indirect HR | E105: =-IF(E$5>Leadsheet!$E$12,0,Leadsheet!$E82*SAP_Speadsheet!E$93*D$16) -> -0.02431866 | F105: =-IF(F$5>Leadsheet!$E$12,0,Leadsheet!$E82*SAP_Speadsheet!F$93*E$16) -> -0.022373167 | G105: =-IF(G$5>Leadsheet!$E$12,0,Leadsheet!$E82*SAP_Speadsheet!G$93*F$16) -> -0.020914048 | H105: =-IF(H$5>Leadsheet!$E$12,0,Leadsheet!$E82*SAP_Speadsheet!H$93*G$16) -> -0.019454928 | I105: =-IF(I$5>Leadsheet!$E$12,0,Leadsheet!$E82*SAP_Speadsheet!I$93*H$16) -> -0.018846962 | J105: =-IF(J$5>Leadsheet!$E$12,0,Leadsheet!$E82*SAP_Speadsheet!J$93*I$16) -> -0.018238995 | K105: =-IF(K$5>Leadsheet!$E$12,0,Leadsheet!$E82*SAP_Speadsheet!K$93*J$16) -> -0.017631029 | L105: =-IF(L$5>Leadsheet!$E$12,0,Leadsheet!$E82*SAP_Speadsheet!L$93*K$16) -> -0.017023062 | ... BL105: =-IF(BL$5>Leadsheet!$E$12,0,Leadsheet!$E82*SAP_Speadsheet!BL$93*BK$16) -> 0
C106: IT | E106: =-IF(E$5>Leadsheet!$E$12,0,Leadsheet!$E83*SAP_Speadsheet!E$93*D$16) -> -0.011666441 | F106: =-IF(F$5>Leadsheet!$E$12,0,Leadsheet!$E83*SAP_Speadsheet!F$93*E$16) -> -0.010733126 | G106: =-IF(G$5>Leadsheet!$E$12,0,Leadsheet!$E83*SAP_Speadsheet!G$93*F$16) -> -0.010033139 | H106: =-IF(H$5>Leadsheet!$E$12,0,Leadsheet!$E83*SAP_Speadsheet!H$93*G$16) -> -0.0093331529 | I106: =-IF(I$5>Leadsheet!$E$12,0,Leadsheet!$E83*SAP_Speadsheet!I$93*H$16) -> -0.0090414919 | J106: =-IF(J$5>Leadsheet!$E$12,0,Leadsheet!$E83*SAP_Speadsheet!J$93*I$16) -> -0.0087498309 | K106: =-IF(K$5>Leadsheet!$E$12,0,Leadsheet!$E83*SAP_Speadsheet!K$93*J$16) -> -0.0084581699 | L106: =-IF(L$5>Leadsheet!$E$12,0,Leadsheet!$E83*SAP_Speadsheet!L$93*K$16) -> -0.0081665088 | ... BL106: =-IF(BL$5>Leadsheet!$E$12,0,Leadsheet!$E83*SAP_Speadsheet!BL$93*BK$16) -> 0
C107: Other support units | E107: =-IF(E$5>Leadsheet!$E$12,0,Leadsheet!$E84*SAP_Speadsheet!E$93*D$16) -> -0.011729348 | F107: =-IF(F$5>Leadsheet!$E$12,0,Leadsheet!$E84*SAP_Speadsheet!F$93*E$16) -> -0.010791 | G107: =-IF(G$5>Leadsheet!$E$12,0,Leadsheet!$E84*SAP_Speadsheet!G$93*F$16) -> -0.01008724 | H107: =-IF(H$5>Leadsheet!$E$12,0,Leadsheet!$E84*SAP_Speadsheet!H$93*G$16) -> -0.0093834787 | I107: =-IF(I$5>Leadsheet!$E$12,0,Leadsheet!$E84*SAP_Speadsheet!I$93*H$16) -> -0.009090245 | J107: =-IF(J$5>Leadsheet!$E$12,0,Leadsheet!$E84*SAP_Speadsheet!J$93*I$16) -> -0.0087970113 | K107: =-IF(K$5>Leadsheet!$E$12,0,Leadsheet!$E84*SAP_Speadsheet!K$93*J$16) -> -0.0085037775 | L107: =-IF(L$5>Leadsheet!$E$12,0,Leadsheet!$E84*SAP_Speadsheet!L$93*K$16) -> -0.0082105438 | ... BL107: =-IF(BL$5>Leadsheet!$E$12,0,Leadsheet!$E84*SAP_Speadsheet!BL$93*BK$16) -> 0
B110: Provision
C111: Provision Rate | E111: IFRS | F111: VAS360 | G111: VAS180
C112: B0 | E112: =Leadsheet!F91 -> 0.024126792 | F112: 0.0075 | G112: 0.0075
C113: B1 | E113: =Leadsheet!F92 -> 0.48253584 | F113: 0.0575 | G113: 0.0575
C114: B2 | E114: =Leadsheet!F93 -> 0.71912942 | F114: 0.0575 | G114: 0.0575
C115: B3 | E115: =Leadsheet!F94 -> 0.79025212 | F115: 0.0575 | G115: 0.0575
C116: B4 | E116: =Leadsheet!F95 -> 0.83009676 | F116: 0.2075 | G116: 0.2075
C117: B5 | E117: =Leadsheet!F96 -> 0.86431419 | F117: 0.2075 | G117: 0.2075
C118: B6 | E118: =Leadsheet!F97 -> 0.91465558 | F118: 0.2075 | G118: 0.2075
C119: B7 | E119: =Leadsheet!F98 -> 0.92619406 | F119: 0.5075 | G119: 0.5075
C120: B8 | E120: =Leadsheet!F99 -> 0.9498452 | F120: 0.5075 | G120: 1
C121: B9 | E121: =Leadsheet!F100 -> 0.950796 | F121: 0.5075
C122: B10 | E122: =Leadsheet!F101 -> 0.950796 | F122: 0.5075
C123: B11 | E123: =Leadsheet!F102 -> 0.950796 | F123: 0.5075
C124: B12 | E124: =Leadsheet!F103 -> 0.950796 | F124: 0.5075
C125: B13 | E125: =Leadsheet!F104 -> 0.950796 | F125: 1
C126: B14+ | E126: =Leadsheet!F105 -> 0.9702 | F126: 1
...

Sheet Saleplan&PnL
C1: PROFIT & LOSS 60M
C2: I. | D2: SALES PLAN
C4: Business month | D4: 45658 | E4: =EOMONTH(D4,1) -> 45716 | F4: =EOMONTH(E4,1) -> 45747 | G4: =EOMONTH(F4,1) -> 45777 | H4: =EOMONTH(G4,1) -> 45808 | I4: =EOMONTH(H4,1) -> 45838 | J4: =EOMONTH(I4,1) -> 45869 | K4: =EOMONTH(J4,1) -> 45900 | L4: =EOMONTH(K4,1) -> 45930 | ... BL4: =EOMONTH(BK4,1) -> 47514
C5: Don't delete | D5: =YEAR(D4) -> 2025 | E5: =YEAR(E4) -> 2025 | F5: =YEAR(F4) -> 2025 | G5: =YEAR(G4) -> 2025 | H5: =YEAR(H4) -> 2025 | I5: =YEAR(I4) -> 2025 | J5: =YEAR(J4) -> 2025 | K5: =YEAR(K4) -> 2025 | ... BL5: =YEAR(BL4) -> 2030
C6: New disbursement (bVND) | J6: =DATA!#REF!/10^9 -> #REF! | K6: =DATA!#REF!/10^9 -> #REF! | L6: =DATA!#REF!/10^9 -> #REF!
C8: II. | D8: PROFIT & LOSS
C10: FISCAL YEAR | E10: Total | F10: =YEAR(D4) -> 2025 | G10: =F10+1 -> 2026 | H10: =G10+1 -> 2027 | I10: =H10+1 -> 2028 | J10: =I10+1 -> 2029 | K10: =J10+1 -> 2030
E11: bVND | F11: bVND | G11: bVND | H11: bVND | I11: bVND | J11: bVND | K11: bVND
C13: NEW DISBURSAL | E13: =SUM(F13:O13) -> #REF! | F13: =SUMIF($D$5:$BL$5,F$10,$D$6:$BL$6) -> #REF! | G13: =SUMIF($D$5:$BL$5,G$10,$D$6:$BL$6) -> 0 | H13: =SUMIF($D$5:$BL$5,H$10,$D$6:$BL$6) -> 0 | I13: =SUMIF($D$5:$BL$5,I$10,$D$6:$BL$6) -> 0 | J13: =SUMIF($D$5:$BL$5,J$10,$D$6:$BL$6) -> 0 | K13: =SUMIF($D$5:$BL$5,K$10,$D$6:$BL$6) -> 0
C14: Monthly disbursement | E14: =AVERAGE(D6:AM6) -> #REF! | F14: =IFERROR(F13/COUNTIFS($D$5:$BL$5,F10,$D$6:$BL$6,"<>"&""),0) -> 0 | G14: =IFERROR(G13/COUNTIFS($D$5:$BL$5,G10,$D$6:$BL$6,"<>"&""),0) -> 0 | H14: =IFERROR(H13/COUNTIFS($D$5:$BL$5,H10,$D$6:$BL$6,"<>"&""),0) -> 0 | I14: =IFERROR(I13/COUNTIFS($D$5:$BL$5,I10,$D$6:$BL$6,"<>"&""),0) -> 0 | J14: =IFERROR(J13/COUNTIFS($D$5:$BL$5,J10,$D$6:$BL$6,"<>"&""),0) -> 0 | K14: =IFERROR(K13/COUNTIFS($D$5:$BL$5,K10,$D$6:$BL$6,"<>"&""),0) -> 0
C16: EOP | F16: =OFFSET(PnL_Speadsheet!$A$7,0,MATCH(DATE('Saleplan&PnL'!F$10,12,31),PnL_Speadsheet!$B$4:$BI$4,0))/1000 -> #REF! | G16: =OFFSET(PnL_Speadsheet!$A$7,0,MATCH(DATE('Saleplan&PnL'!G$10,12,31),PnL_Speadsheet!$B$4:$BI$4,0))/1000 -> #REF! | H16: =OFFSET(PnL_Speadsheet!$A$7,0,MATCH(DATE('Saleplan&PnL'!H$10,12,31),PnL_Speadsheet!$B$4:$BI$4,0))/1000 -> #REF! | I16: =OFFSET(PnL_Speadsheet!$A$7,0,MATCH(DATE('Saleplan&PnL'!I$10,12,31),PnL_Speadsheet!$B$4:$BI$4,0))/1000 -> #REF! | J16: =OFFSET(PnL_Speadsheet!$A$7,0,MATCH(DATE('Saleplan&PnL'!J$10,12,31),PnL_Speadsheet!$B$4:$BI$4,0))/1000 -> #REF! | K16: =IFERROR(OFFSET(PnL_Speadsheet!$A$7,0,MATCH(DATE('Saleplan&PnL'!K$10,12,31),PnL_Speadsheet!$B$4:$BI$4,0))/1000,0) -> 0
C17: ADB | E17: =IFERROR(SUM(PnL_Speadsheet!B8:AK8)/1000/COUNTIF(PnL_Speadsheet!B8:BI8,"<>0"),0) -> 0 | F17: =IFERROR(SUMIF(PnL_Speadsheet!$B$3:$BI$3,F$10,PnL_Speadsheet!$B8:$BI8)/1000/COUNTIFS(PnL_Speadsheet!$B$3:$BI$3,'Saleplan&PnL'!F$10,PnL_Speadsheet!$B$8:$BI$8,"<>0"),0) -> 0 | G17: =IFERROR(SUMIF(PnL_Speadsheet!$B$3:$BI$3,G$10,PnL_Speadsheet!$B8:$BI8)/1000/COUNTIFS(PnL_Speadsheet!$B$3:$BI$3,'Saleplan&PnL'!G$10,PnL_Speadsheet!$B$8:$BI$8,"<>0"),0) -> 0 | H17: =IFERROR(SUMIF(PnL_Speadsheet!$B$3:$BI$3,H$10,PnL_Speadsheet!$B8:$BI8)/1000/COUNTIFS(PnL_Speadsheet!$B$3:$BI$3,'Saleplan&PnL'!H$10,PnL_Speadsheet!$B$8:$BI$8,"<>0"),0) -> 0 | I17: =IFERROR(SUMIF(PnL_Speadsheet!$B$3:$BI$3,I$10,PnL_Speadsheet!$B8:$BI8)/1000/COUNTIFS(PnL_Speadsheet!$B$3:$BI$3,'Saleplan&PnL'!I$10,PnL_Speadsheet!$B$8:$BI$8,"<>0"),0) -> 0 | J17: =IFERROR(SUMIF(PnL_Speadsheet!$B$3:$BI$3,J$10,PnL_Speadsheet!$B8:$BI8)/1000/COUNTIFS(PnL_Speadsheet!$B$3:$BI$3,'Saleplan&PnL'!J$10,PnL_Speadsheet!$B$8:$BI$8,"<>0"),0) -> 0 | K17: =IFERROR(SUMIF(PnL_Speadsheet!$B$3:$BI$3,K$10,PnL_Speadsheet!$B8:$BI8)/1000/COUNTIFS(PnL_Speadsheet!$B$3:$BI$3,'Saleplan&PnL'!K$10,PnL_Speadsheet!$B$8:$BI$8,"<>0"),0) -> 0
C19: TOI | E19: =SUM(F19:O19) -> #REF! | F19: =SUMIF(PnL_Speadsheet!$B$3:$BI$3,F$10,PnL_Speadsheet!$B9:$BI9)/1000 -> #REF! | G19: =SUMIF(PnL_Speadsheet!$B$3:$BI$3,G$10,PnL_Speadsheet!$B9:$BI9)/1000 -> #REF! | H19: =SUMIF(PnL_Speadsheet!$B$3:$BI$3,H$10,PnL_Speadsheet!$B9:$BI9)/1000 -> #REF! | I19: =SUMIF(PnL_Speadsheet!$B$3:$BI$3,I$10,PnL_Speadsheet!$B9:$BI9)/1000 -> #REF! | J19: =SUMIF(PnL_Speadsheet!$B$3:$BI$3,J$10,PnL_Speadsheet!$B9:$BI9)/1000 -> #REF! | K19: =SUMIF(PnL_Speadsheet!$B$3:$BI$3,K$10,PnL_Speadsheet!$B9:$BI9)/1000 -> 0
C20: NII | E20: =SUM(F20:O20) -> #REF! | F20: =SUMIF(PnL_Speadsheet!$B$3:$BI$3,F$10,PnL_Speadsheet!$B11:$BI11)/1000 -> #REF! | G20: =SUMIF(PnL_Speadsheet!$B$3:$BI$3,G$10,PnL_Speadsheet!$B11:$BI11)/1000 -> #REF! | H20: =SUMIF(PnL_Speadsheet!$B$3:$BI$3,H$10,PnL_Speadsheet!$B11:$BI11)/1000 -> #REF! | I20: =SUMIF(PnL_Speadsheet!$B$3:$BI$3,I$10,PnL_Speadsheet!$B11:$BI11)/1000 -> #REF! | J20: =SUMIF(PnL_Speadsheet!$B$3:$BI$3,J$10,PnL_Speadsheet!$B11:$BI11)/1000 -> #REF! | K20: =SUMIF(PnL_Speadsheet!$B$3:$BI$3,K$10,PnL_Speadsheet!$B11:$BI11)/1000 -> 0
C21: NFI | E21: =SUM(F21:O21) -> #REF! | F21: =SUMIF(PnL_Speadsheet!$B$3:$BI$3,F$10,PnL_Speadsheet!$B14:$BI14)/1000 -> #REF! | G21: =SUMIF(PnL_Speadsheet!$B$3:$BI$3,G$10,PnL_Speadsheet!$B14:$BI14)/1000 -> #REF! | H21: =SUMIF(PnL_Speadsheet!$B$3:$BI$3,H$10,PnL_Speadsheet!$B14:$BI14)/1000 -> #REF! | I21: =SUMIF(PnL_Speadsheet!$B$3:$BI$3,I$10,PnL_Speadsheet!$B14:$BI14)/1000 -> #REF! | J21: =SUMIF(PnL_Speadsheet!$B$3:$BI$3,J$10,PnL_Speadsheet!$B14:$BI14)/1000 -> #REF! | K21: =SUMIF(PnL_Speadsheet!$B$3:$BI$3,K$10,PnL_Speadsheet!$B14:$BI14)/1000 -> 0
C22: Other TOI | E22: =SUM(F22:O22) -> #REF! | F22: =SUMIF(PnL_Speadsheet!$B$3:$BI$3,F$10,PnL_Speadsheet!$B18:$BI18)/1000 -> #REF! | G22: =SUMIF(PnL_Speadsheet!$B$3:$BI$3,G$10,PnL_Speadsheet!$B18:$BI18)/1000 -> #REF! | H22: =SUMIF(PnL_Speadsheet!$B$3:$BI$3,H$10,PnL_Speadsheet!$B18:$BI18)/1000 -> #REF! | I22: =SUMIF(PnL_Speadsheet!$B$3:$BI$3,I$10,PnL_Speadsheet!$B18:$BI18)/1000 -> #REF! | J22: =SUMIF(PnL_Speadsheet!$B$3:$BI$3,J$10,PnL_Speadsheet!$B18:$BI18)/1000 -> #REF! | K22: =SUMIF(PnL_Speadsheet!$B$3:$BI$3,K$10,PnL_Speadsheet!$B18:$BI18)/1000 -> 0
C23: PROVISION | E23: =SUM(F23:O23) -> #REF! | F23: =SUMIF(PnL_Speadsheet!$B$3:$BI$3,F$10,PnL_Speadsheet!$B31:$BI31)/1000 -> #REF! | G23: =SUMIF(PnL_Speadsheet!$B$3:$BI$3,G$10,PnL_Speadsheet!$B31:$BI31)/1000 -> #REF! | H23: =SUMIF(PnL_Speadsheet!$B$3:$BI$3,H$10,PnL_Speadsheet!$B31:$BI31)/1000 -> #REF! | I23: =SUMIF(PnL_Speadsheet!$B$3:$BI$3,I$10,PnL_Speadsheet!$B31:$BI31)/1000 -> #REF! | J23: =SUMIF(PnL_Speadsheet!$B$3:$BI$3,J$10,PnL_Speadsheet!$B31:$BI31)/1000 -> #REF! | K23: =SUMIF(PnL_Speadsheet!$B$3:$BI$3,K$10,PnL_Speadsheet!$B31:$BI31)/1000 -> 0
C24: OPEX | E24: =SUM(F24:O24) -> #REF! | F24: =SUMIF(PnL_Speadsheet!$B$3:$BI$3,F$10,PnL_Speadsheet!$B19:$BI19)/1000 -> #REF! | G24: =SUMIF(PnL_Speadsheet!$B$3:$BI$3,G$10,PnL_Speadsheet!$B19:$BI19)/1000 -> #REF! | H24: =SUMIF(PnL_Speadsheet!$B$3:$BI$3,H$10,PnL_Speadsheet!$B19:$BI19)/1000 -> #REF! | I24: =SUMIF(PnL_Speadsheet!$B$3:$BI$3,I$10,PnL_Speadsheet!$B19:$BI19)/1000 -> #REF! | J24: =SUMIF(PnL_Speadsheet!$B$3:$BI$3,J$10,PnL_Speadsheet!$B19:$BI19)/1000 -> #REF! | K24: =SUMIF(PnL_Speadsheet!$B$3:$BI$3,K$10,PnL_Speadsheet!$B19:$BI19)/1000 -> 0
C25: Sales incentives | E25: =SUM(F25:O25) -> #REF! | F25: =(SUMIF(PnL_Speadsheet!$B$3:$BI$3,F$10,PnL_Speadsheet!$B21:$BI22)/1000+SUMIF(PnL_Speadsheet!$B$3:$BI$3,F$10,PnL_Speadsheet!$B22:$BI22)/1000) -> #REF! | G25: =(SUMIF(PnL_Speadsheet!$B$3:$BI$3,G$10,PnL_Speadsheet!$B21:$BI22)/1000+SUMIF(PnL_Speadsheet!$B$3:$BI$3,G$10,PnL_Speadsheet!$B22:$BI22)/1000) -> #REF! | H25: =(SUMIF(PnL_Speadsheet!$B$3:$BI$3,H$10,PnL_Speadsheet!$B21:$BI22)/1000+SUMIF(PnL_Speadsheet!$B$3:$BI$3,H$10,PnL_Speadsheet!$B22:$BI22)/1000) -> #REF! | I25: =(SUMIF(PnL_Speadsheet!$B$3:$BI$3,I$10,PnL_Speadsheet!$B21:$BI22)/1000+SUMIF(PnL_Speadsheet!$B$3:$BI$3,I$10,PnL_Speadsheet!$B22:$BI22)/1000) -> #REF! | J25: =(SUMIF(PnL_Speadsheet!$B$3:$BI$3,J$10,PnL_Speadsheet!$B21:$BI22)/1000+SUMIF(PnL_Speadsheet!$B$3:$BI$3,J$10,PnL_Speadsheet!$B22:$BI22)/1000) -> #REF! | K25: =(SUMIF(PnL_Speadsheet!$B$3:$BI$3,K$10,PnL_Speadsheet!$B21:$BI22)/1000+SUMIF(PnL_Speadsheet!$B$3:$BI$3,K$10,PnL_Speadsheet!$B22:$BI22)/1000) -> 0
C26: Marketing | E26: =SUM(F26:O26) -> #REF! | F26: =SUMIF(PnL_Speadsheet!$B$3:$BI$3,F$10,PnL_Speadsheet!$B23:$BI23)/1000 -> #REF! | G26: =SUMIF(PnL_Speadsheet!$B$3:$BI$3,G$10,PnL_Speadsheet!$B23:$BI23)/1000 -> #REF! | H26: =SUMIF(PnL_Speadsheet!$B$3:$BI$3,H$10,PnL_Speadsheet!$B23:$BI23)/1000 -> #REF! | I26: =SUMIF(PnL_Speadsheet!$B$3:$BI$3,I$10,PnL_Speadsheet!$B23:$BI23)/1000 -> #REF! | J26: =SUMIF(PnL_Speadsheet!$B$3:$BI$3,J$10,PnL_Speadsheet!$B23:$BI23)/1000 -> #REF! | K26: =SUMIF(PnL_Speadsheet!$B$3:$BI$3,K$10,PnL_Speadsheet!$B23:$BI23)/1000 -> 0
C27: UW & Disbursal | E27: =SUM(F27:O27) -> #REF! | F27: =SUMIF(PnL_Speadsheet!$B$3:$BI$3,F$10,PnL_Speadsheet!$B24:$BI24)/1000 -> #REF! | G27: =SUMIF(PnL_Speadsheet!$B$3:$BI$3,G$10,PnL_Speadsheet!$B24:$BI24)/1000 -> #REF! | H27: =SUMIF(PnL_Speadsheet!$B$3:$BI$3,H$10,PnL_Speadsheet!$B24:$BI24)/1000 -> #REF! | I27: =SUMIF(PnL_Speadsheet!$B$3:$BI$3,I$10,PnL_Speadsheet!$B24:$BI24)/1000 -> #REF! | J27: =SUMIF(PnL_Speadsheet!$B$3:$BI$3,J$10,PnL_Speadsheet!$B24:$BI24)/1000 -> #REF! | K27: =SUMIF(PnL_Speadsheet!$B$3:$BI$3,K$10,PnL_Speadsheet!$B24:$BI24)/1000 -> 0
C28: Collection & AMC | E28: =SUM(F28:O28) -> #REF! | F28: =SUMIF(PnL_Speadsheet!$B$3:$BI$3,F$10,PnL_Speadsheet!$B28:$BI28)/1000 -> #REF! | G28: =SUMIF(PnL_Speadsheet!$B$3:$BI$3,G$10,PnL_Speadsheet!$B28:$BI28)/1000 -> #REF! | H28: =SUMIF(PnL_Speadsheet!$B$3:$BI$3,H$10,PnL_Speadsheet!$B28:$BI28)/1000 -> #REF! | I28: =SUMIF(PnL_Speadsheet!$B$3:$BI$3,I$10,PnL_Speadsheet!$B28:$BI28)/1000 -> #REF! | J28: =SUMIF(PnL_Speadsheet!$B$3:$BI$3,J$10,PnL_Speadsheet!$B28:$BI28)/1000 -> #REF! | K28: =SUMIF(PnL_Speadsheet!$B$3:$BI$3,K$10,PnL_Speadsheet!$B28:$BI28)/1000 -> 0
C29: After-sales services | E29: =SUM(F29:O29) -> #REF! | F29: =SUMIF(PnL_Speadsheet!$B$3:$BI$3,F$10,PnL_Speadsheet!$B29:$BI29)/1000 -> #REF! | G29: =SUMIF(PnL_Speadsheet!$B$3:$BI$3,G$10,PnL_Speadsheet!$B29:$BI29)/1000 -> #REF! | H29: =SUMIF(PnL_Speadsheet!$B$3:$BI$3,H$10,PnL_Speadsheet!$B29:$BI29)/1000 -> #REF! | I29: =SUMIF(PnL_Speadsheet!$B$3:$BI$3,I$10,PnL_Speadsheet!$B29:$BI29)/1000 -> #REF! | J29: =SUMIF(PnL_Speadsheet!$B$3:$BI$3,J$10,PnL_Speadsheet!$B29:$BI29)/1000 -> #REF! | K29: =SUMIF(PnL_Speadsheet!$B$3:$BI$3,K$10,PnL_Speadsheet!$B29:$BI29)/1000 -> 0
C30: Other support units | E30: =SUM(F30:O30) -> #REF! | F30: =SUMIF(PnL_Speadsheet!$B$3:$BI$3,F$10,PnL_Speadsheet!$B30:$BI30)/1000 -> #REF! | G30: =SUMIF(PnL_Speadsheet!$B$3:$BI$3,G$10,PnL_Speadsheet!$B30:$BI30)/1000 -> #REF! | H30: =SUMIF(PnL_Speadsheet!$B$3:$BI$3,H$10,PnL_Speadsheet!$B30:$BI30)/1000 -> #REF! | I30: =SUMIF(PnL_Speadsheet!$B$3:$BI$3,I$10,PnL_Speadsheet!$B30:$BI30)/1000 -> #REF! | J30: =SUMIF(PnL_Speadsheet!$B$3:$BI$3,J$10,PnL_Speadsheet!$B30:$BI30)/1000 -> #REF! | K30: =SUMIF(PnL_Speadsheet!$B$3:$BI$3,K$10,PnL_Speadsheet!$B30:$BI30)/1000 -> 0
C31: PBT | E31: =SUM(F31:O31) -> #REF! | F31: =SUMIF(PnL_Speadsheet!$B$3:$BI$3,F$10,PnL_Speadsheet!$B32:$BI32)/1000 -> #REF! | G31: =SUMIF(PnL_Speadsheet!$B$3:$BI$3,G$10,PnL_Speadsheet!$B32:$BI32)/1000 -> #REF! | H31: =SUMIF(PnL_Speadsheet!$B$3:$BI$3,H$10,PnL_Speadsheet!$B32:$BI32)/1000 -> #REF! | I31: =SUMIF(PnL_Speadsheet!$B$3:$BI$3,I$10,PnL_Speadsheet!$B32:$BI32)/1000 -> #REF! | J31: =SUMIF(PnL_Speadsheet!$B$3:$BI$3,J$10,PnL_Speadsheet!$B32:$BI32)/1000 -> #REF! | K31: =SUMIF(PnL_Speadsheet!$B$3:$BI$3,K$10,PnL_Speadsheet!$B32:$BI32)/1000 -> 0
C32: In which: PROFIT BEFORE SU | E32: =E19+E23+SUM(E25:E29) -> #REF! | F32: =F19+F23+SUM(F25:F29) -> #REF! | G32: =G19+G23+SUM(G25:G29) -> #REF! | H32: =H19+H23+SUM(H25:H29) -> #REF! | I32: =I19+I23+SUM(I25:I29) -> #REF! | J32: =J19+J23+SUM(J25:J29) -> #REF! | K32: =K19+K23+SUM(K25:K29) -> 0

Sheet PnL_Speadsheet
A1: PL PROJECTION
A2: 60 months
B3: =YEAR(B4) -> 2025 | C3: =YEAR(C4) -> 2025 | D3: =YEAR(D4) -> 2025 | E3: =YEAR(E4) -> 2025 | F3: =YEAR(F4) -> 2025 | G3: =YEAR(G4) -> 2025 | H3: =YEAR(H4) -> 2025 | I3: =YEAR(I4) -> 2025 | ... BI3: =YEAR(BI4) -> 2029
A4: Business month | B4: ='Saleplan&PnL'!D4 -> 45658 | C4: ='Saleplan&PnL'!E4 -> 45716 | D4: ='Saleplan&PnL'!F4 -> 45747 | E4: ='Saleplan&PnL'!G4 -> 45777 | F4: ='Saleplan&PnL'!H4 -> 45808 | G4: ='Saleplan&PnL'!I4 -> 45838 | H4: ='Saleplan&PnL'!J4 -> 45869 | I4: ='Saleplan&PnL'!K4 -> 45900 | ... BI4: ='Saleplan&PnL'!BK4 -> 47483
A5: Month on board | B5: 1 | C5: 2 | D5: 3 | E5: 4 | F5: 5 | G5: 6 | H5: 7 | I5: 8 | J5: 9 | K5: 10 | L5: 11 | M5: 12 | N5: 13 | O5: 14 | P5: 15 | Q5: 16 | R5: 17 | S5: 18 | T5: 19 | U5: 20 | V5: 21 | W5: 22 | X5: 23 | Y5: 24 | Z5: 25 | AA5: 26 | AB5: 27 | AC5: 28 | AD5: 29 | AE5: 30 | AF5: 31 | AG5: 32 | AH5: 33 | AI5: 34 | AJ5: 35 | AK5: 36 | AL5: =AK5+1 -> 37 | AM5: =AL5+1 -> 38 | AN5: =AM5+1 -> 39 | AO5: =AN5+1 -> 40 | AP5: =AO5+1 -> 41 | AQ5: =AP5+1 -> 42 | AR5: =AQ5+1 -> 43 | AS5: =AR5+1 -> 44 | ... BI5: =BH5+1 -> 60
A6: Unit: mVND
A7: ENR | B7: {=SUMPRODUCT(B$55:B$114,TRANSPOSE(SAP_Speadsheet!$E$44:$BL$44))} -> 0 | C7: {=SUMPRODUCT(C$55:C$114,TRANSPOSE(SAP_Speadsheet!$E$44:$BL$44))} -> 0 | D7: {=SUMPRODUCT(D$55:D$114,TRANSPOSE(SAP_Speadsheet!$E$44:$BL$44))} -> 0 | E7: {=SUMPRODUCT(E$55:E$114,TRANSPOSE(SAP_Speadsheet!$E$44:$BL$44))} -> 0 | F7: {=SUMPRODUCT(F$55:F$114,TRANSPOSE(SAP_Speadsheet!$E$44:$BL$44))} -> 0 | G7: {=SUMPRODUCT(G$55:G$114,TRANSPOSE(SAP_Speadsheet!$E$44:$BL$44))} -> 0 | H7: {=SUMPRODUCT(H$55:H$114,TRANSPOSE(SAP_Speadsheet!$E$44:$BL$44))} -> #REF! | I7: {=SUMPRODUCT(I$55:I$114,TRANSPOSE(SAP_Speadsheet!$E$44:$BL$44))} -> #REF! | ... BI7: {=SUMPRODUCT(BI$55:BI$114,TRANSPOSE(SAP_Speadsheet!$E$44:$BL$44))} -> #REF!
A8: ANR | B8: {=SUMPRODUCT(B$55:B$114,TRANSPOSE(SAP_Speadsheet!$E$50:$BL$50))} -> 0 | C8: {=SUMPRODUCT(C$55:C$114,TRANSPOSE(SAP_Speadsheet!$E$50:$BL$50))} -> 0 | D8: {=SUMPRODUCT(D$55:D$114,TRANSPOSE(SAP_Speadsheet!$E$50:$BL$50))} -> 0 | E8: {=SUMPRODUCT(E$55:E$114,TRANSPOSE(SAP_Speadsheet!$E$50:$BL$50))} -> 0 | F8: {=SUMPRODUCT(F$55:F$114,TRANSPOSE(SAP_Speadsheet!$E$50:$BL$50))} -> 0 | G8: {=SUMPRODUCT(G$55:G$114,TRANSPOSE(SAP_Speadsheet!$E$50:$BL$50))} -> 0 | H8: {=SUMPRODUCT(H$55:H$114,TRANSPOSE(SAP_Speadsheet!$E$50:$BL$50))} -> #REF! | I8: {=SUMPRODUCT(I$55:I$114,TRANSPOSE(SAP_Speadsheet!$E$50:$BL$50))} -> #REF! | ... BI8: {=SUMPRODUCT(BI$55:BI$114,TRANSPOSE(SAP_Speadsheet!$E$50:$BL$50))} -> #REF!
A9: TOI | B9: {=SUMPRODUCT(B$55:B$114,TRANSPOSE(SAP_Speadsheet!$E$55:$BL$55))} -> 0 | C9: {=SUMPRODUCT(C$55:C$114,TRANSPOSE(SAP_Speadsheet!$E$55:$BL$55))} -> 0 | D9: {=SUMPRODUCT(D$55:D$114,TRANSPOSE(SAP_Speadsheet!$E$55:$BL$55))} -> 0 | E9: {=SUMPRODUCT(E$55:E$114,TRANSPOSE(SAP_Speadsheet!$E$55:$BL$55))} -> 0 | F9: {=SUMPRODUCT(F$55:F$114,TRANSPOSE(SAP_Speadsheet!$E$55:$BL$55))} -> 0 | G9: {=SUMPRODUCT(G$55:G$114,TRANSPOSE(SAP_Speadsheet!$E$55:$BL$55))} -> 0 | H9: {=SUMPRODUCT(H$55:H$114,TRANSPOSE(SAP_Speadsheet!$E$55:$BL$55))} -> #REF! | I9: {=SUMPRODUCT(I$55:I$114,TRANSPOSE(SAP_Speadsheet!$E$55:$BL$55))} -> #REF! | ... BI9: {=SUMPRODUCT(BI$55:BI$114,TRANSPOSE(SAP_Speadsheet!$E$55:$BL$55))} -> #REF!
A10: Checking | B10: =B9-B11-B14 -> 0 | C10: =C9-C11-C14 -> 0 | D10: =D9-D11-D14 -> 0 | E10: =E9-E11-E14 -> 0 | F10: =F9-F11-F14 -> 0 | G10: =G9-G11-G14 -> 0 | H10: =H9-H11-H14 -> #REF! | I10: =I9-I11-I14 -> #REF! | ... BI10: =BI9-BI11-BI14 -> #REF!
A11: Net interest income | B11: {=SUMPRODUCT(B$55:B$114,TRANSPOSE(SAP_Speadsheet!$E$57:$BL$57))} -> 0 | C11: {=SUMPRODUCT(C$55:C$114,TRANSPOSE(SAP_Speadsheet!$E$57:$BL$57))} -> 0 | D11: {=SUMPRODUCT(D$55:D$114,TRANSPOSE(SAP_Speadsheet!$E$57:$BL$57))} -> 0 | E11: {=SUMPRODUCT(E$55:E$114,TRANSPOSE(SAP_Speadsheet!$E$57:$BL$57))} -> 0 | F11: {=SUMPRODUCT(F$55:F$114,TRANSPOSE(SAP_Speadsheet!$E$57:$BL$57))} -> 0 | G11: {=SUMPRODUCT(G$55:G$114,TRANSPOSE(SAP_Speadsheet!$E$57:$BL$57))} -> 0 | H11: {=SUMPRODUCT(H$55:H$114,TRANSPOSE(SAP_Speadsheet!$E$57:$BL$57))} -> #REF! | I11: {=SUMPRODUCT(I$55:I$114,TRANSPOSE(SAP_Speadsheet!$E$57:$BL$57))} -> #REF! | ... BI11: {=SUMPRODUCT(BI$55:BI$114,TRANSPOSE(SAP_Speadsheet!$E$57:$BL$57))} -> #REF!
A12: Interest income | B12: {=SUMPRODUCT(B$55:B$114,TRANSPOSE(SAP_Speadsheet!$E$58:$BL$58))} -> 0 | C12: {=SUMPRODUCT(C$55:C$114,TRANSPOSE(SAP_Speadsheet!$E$58:$BL$58))} -> 0 | D12: {=SUMPRODUCT(D$55:D$114,TRANSPOSE(SAP_Speadsheet!$E$58:$BL$58))} -> 0 | E12: {=SUMPRODUCT(E$55:E$114,TRANSPOSE(SAP_Speadsheet!$E$58:$BL$58))} -> 0 | F12: {=SUMPRODUCT(F$55:F$114,TRANSPOSE(SAP_Speadsheet!$E$58:$BL$58))} -> 0 | G12: {=SUMPRODUCT(G$55:G$114,TRANSPOSE(SAP_Speadsheet!$E$58:$BL$58))} -> 0 | H12: {=SUMPRODUCT(H$55:H$114,TRANSPOSE(SAP_Speadsheet!$E$58:$BL$58))} -> #REF! | I12: {=SUMPRODUCT(I$55:I$114,TRANSPOSE(SAP_Speadsheet!$E$58:$BL$58))} -> #REF! | ... BI12: {=SUMPRODUCT(BI$55:BI$114,TRANSPOSE(SAP_Speadsheet!$E$58:$BL$58))} -> #REF!
A13: Cost of fund | B13: {=SUMPRODUCT(B$55:B$114,TRANSPOSE(SAP_Speadsheet!$E$59:$BL$59))} -> 0 | C13: {=SUMPRODUCT(C$55:C$114,TRANSPOSE(SAP_Speadsheet!$E$59:$BL$59))} -> 0 | D13: {=SUMPRODUCT(D$55:D$114,TRANSPOSE(SAP_Speadsheet!$E$59:$BL$59))} -> 0 | E13: {=SUMPRODUCT(E$55:E$114,TRANSPOSE(SAP_Speadsheet!$E$59:$BL$59))} -> 0 | F13: {=SUMPRODUCT(F$55:F$114,TRANSPOSE(SAP_Speadsheet!$E$59:$BL$59))} -> 0 | G13: {=SUMPRODUCT(G$55:G$114,TRANSPOSE(SAP_Speadsheet!$E$59:$BL$59))} -> 0 | H13: {=SUMPRODUCT(H$55:H$114,TRANSPOSE(SAP_Speadsheet!$E$59:$BL$59))} -> #REF! | I13: {=SUMPRODUCT(I$55:I$114,TRANSPOSE(SAP_Speadsheet!$E$59:$BL$59))} -> #REF! | ... BI13: {=SUMPRODUCT(BI$55:BI$114,TRANSPOSE(SAP_Speadsheet!$E$59:$BL$59))} -> #REF!
A14: Net fee income | B14: {=SUMPRODUCT(B$55:B$114,TRANSPOSE(SAP_Speadsheet!$E$61:$BL$61))} -> 0 | C14: {=SUMPRODUCT(C$55:C$114,TRANSPOSE(SAP_Speadsheet!$E$61:$BL$61))} -> 0 | D14: {=SUMPRODUCT(D$55:D$114,TRANSPOSE(SAP_Speadsheet!$E$61:$BL$61))} -> 0 | E14: {=SUMPRODUCT(E$55:E$114,TRANSPOSE(SAP_Speadsheet!$E$61:$BL$61))} -> 0 | F14: {=SUMPRODUCT(F$55:F$114,TRANSPOSE(SAP_Speadsheet!$E$61:$BL$61))} -> 0 | G14: {=SUMPRODUCT(G$55:G$114,TRANSPOSE(SAP_Speadsheet!$E$61:$BL$61))} -> 0 | H14: {=SUMPRODUCT(H$55:H$114,TRANSPOSE(SAP_Speadsheet!$E$61:$BL$61))} -> #REF! | I14: {=SUMPRODUCT(I$55:I$114,TRANSPOSE(SAP_Speadsheet!$E$61:$BL$61))} -> #REF! | ... BI14: {=SUMPRODUCT(BI$55:BI$114,TRANSPOSE(SAP_Speadsheet!$E$61:$BL$61))} -> #REF!
A15: Early termination income | B15: {=SUMPRODUCT(B$55:B$114,TRANSPOSE(SAP_Speadsheet!$E$62:$BL$62))} -> 0 | C15: {=SUMPRODUCT(C$55:C$114,TRANSPOSE(SAP_Speadsheet!$E$62:$BL$62))} -> 0 | D15: {=SUMPRODUCT(D$55:D$114,TRANSPOSE(SAP_Speadsheet!$E$62:$BL$62))} -> 0 | E15: {=SUMPRODUCT(E$55:E$114,TRANSPOSE(SAP_Speadsheet!$E$62:$BL$62))} -> 0 | F15: {=SUMPRODUCT(F$55:F$114,TRANSPOSE(SAP_Speadsheet!$E$62:$BL$62))} -> 0 | G15: {=SUMPRODUCT(G$55:G$114,TRANSPOSE(SAP_Speadsheet!$E$62:$BL$62))} -> 0 | H15: {=SUMPRODUCT(H$55:H$114,TRANSPOSE(SAP_Speadsheet!$E$62:$BL$62))} -> #REF! | I15: {=SUMPRODUCT(I$55:I$114,TRANSPOSE(SAP_Speadsheet!$E$62:$BL$62))} -> #REF! | ... BI15: {=SUMPRODUCT(BI$55:BI$114,TRANSPOSE(SAP_Speadsheet!$E$62:$BL$62))} -> #REF!
A16: Insurance fee | B16: {=SUMPRODUCT(B$55:B$114,TRANSPOSE(SAP_Speadsheet!$E$63:$BL$63))} -> 0 | C16: {=SUMPRODUCT(C$55:C$114,TRANSPOSE(SAP_Speadsheet!$E$63:$BL$63))} -> 0 | D16: {=SUMPRODUCT(D$55:D$114,TRANSPOSE(SAP_Speadsheet!$E$63:$BL$63))} -> 0 | E16: {=SUMPRODUCT(E$55:E$114,TRANSPOSE(SAP_Speadsheet!$E$63:$BL$63))} -> 0 | F16: {=SUMPRODUCT(F$55:F$114,TRANSPOSE(SAP_Speadsheet!$E$63:$BL$63))} -> 0 | G16: {=SUMPRODUCT(G$55:G$114,TRANSPOSE(SAP_Speadsheet!$E$63:$BL$63))} -> 0 | H16: {=SUMPRODUCT(H$55:H$114,TRANSPOSE(SAP_Speadsheet!$E$63:$BL$63))} -> #REF! | I16: {=SUMPRODUCT(I$55:I$114,TRANSPOSE(SAP_Speadsheet!$E$63:$BL$63))} -> #REF! | ... BI16: {=SUMPRODUCT(BI$55:BI$114,TRANSPOSE(SAP_Speadsheet!$E$63:$BL$63))} -> #REF!
A17: Support fee | B17: {=SUMPRODUCT(B$55:B$114,TRANSPOSE(SAP_Speadsheet!$E$64:$BL$64))} -> 0 | C17: {=SUMPRODUCT(C$55:C$114,TRANSPOSE(SAP_Speadsheet!$E$64:$BL$64))} -> 0 | D17: {=SUMPRODUCT(D$55:D$114,TRANSPOSE(SAP_Speadsheet!$E$64:$BL$64))} -> 0 | E17: {=SUMPRODUCT(E$55:E$114,TRANSPOSE(SAP_Speadsheet!$E$64:$BL$64))} -> 0 | F17: {=SUMPRODUCT(F$55:F$114,TRANSPOSE(SAP_Speadsheet!$E$64:$BL$64))} -> 0 | G17: {=SUMPRODUCT(G$55:G$114,TRANSPOSE(SAP_Speadsheet!$E$64:$BL$64))} -> 0 | H17: {=SUMPRODUCT(H$55:H$114,TRANSPOSE(SAP_Speadsheet!$E$64:$BL$64))} -> #REF! | I17: {=SUMPRODUCT(I$55:I$114,TRANSPOSE(SAP_Speadsheet!$E$64:$BL$64))} -> #REF! | ... BI17: {=SUMPRODUCT(BI$55:BI$114,TRANSPOSE(SAP_Speadsheet!$E$64:$BL$64))} -> #REF!
A18: Other income | B18: {=SUMPRODUCT(B$55:B$114,TRANSPOSE(SAP_Speadsheet!$E$68:$BL$68))} -> 0 | C18: {=SUMPRODUCT(C$55:C$114,TRANSPOSE(SAP_Speadsheet!$E$68:$BL$68))} -> 0 | D18: {=SUMPRODUCT(D$55:D$114,TRANSPOSE(SAP_Speadsheet!$E$68:$BL$68))} -> 0 | E18: {=SUMPRODUCT(E$55:E$114,TRANSPOSE(SAP_Speadsheet!$E$68:$BL$68))} -> 0 | F18: {=SUMPRODUCT(F$55:F$114,TRANSPOSE(SAP_Speadsheet!$E$68:$BL$68))} -> 0 | G18: {=SUMPRODUCT(G$55:G$114,TRANSPOSE(SAP_Speadsheet!$E$68:$BL$68))} -> 0 | H18: {=SUMPRODUCT(H$55:H$114,TRANSPOSE(SAP_Speadsheet!$E$68:$BL$68))} -> #REF! | I18: {=SUMPRODUCT(I$55:I$114,TRANSPOSE(SAP_Speadsheet!$E$68:$BL$68))} -> #REF! | ... BI18: {=SUMPRODUCT(BI$55:BI$114,TRANSPOSE(SAP_Speadsheet!$E$68:$BL$68))} -> #REF!
A19: OPEX | B19: =B20+B24+B28+B29+B30 -> 0 | C19: =C20+C24+C28+C29+C30 -> 0 | D19: =D20+D24+D28+D29+D30 -> 0 | E19: =E20+E24+E28+E29+E30 -> 0 | F19: =F20+F24+F28+F29+F30 -> 0 | G19: =G20+G24+G28+G29+G30 -> 0 | H19: =H20+H24+H28+H29+H30 -> #REF! | I19: =I20+I24+I28+I29+I30 -> #REF! | ... BI19: =BI20+BI24+BI28+BI29+BI30 -> #REF!
A20: Sale incentive&mkt | B20: =SUM(B21:B23) -> 0 | C20: =SUM(C21:C23) -> 0 | D20: =SUM(D21:D23) -> 0 | E20: =SUM(E21:E23) -> 0 | F20: =SUM(F21:F23) -> 0 | G20: =SUM(G21:G23) -> 0 | H20: =SUM(H21:H23) -> #REF! | I20: =SUM(I21:I23) -> #REF! | ... BI20: =SUM(BI21:BI23) -> #REF!
A21: Lead Acquisition | B21: {=SUMPRODUCT(B$55:B$114,TRANSPOSE(SAP_Speadsheet!$E$73:$BL$73))} -> 0 | C21: {=SUMPRODUCT(C$55:C$114,TRANSPOSE(SAP_Speadsheet!$E$73:$BL$73))} -> 0 | D21: {=SUMPRODUCT(D$55:D$114,TRANSPOSE(SAP_Speadsheet!$E$73:$BL$73))} -> 0 | E21: {=SUMPRODUCT(E$55:E$114,TRANSPOSE(SAP_Speadsheet!$E$73:$BL$73))} -> 0 | F21: {=SUMPRODUCT(F$55:F$114,TRANSPOSE(SAP_Speadsheet!$E$73:$BL$73))} -> 0 | G21: {=SUMPRODUCT(G$55:G$114,TRANSPOSE(SAP_Speadsheet!$E$73:$BL$73))} -> 0 | H21: {=SUMPRODUCT(H$55:H$114,TRANSPOSE(SAP_Speadsheet!$E$73:$BL$73))} -> #REF! | I21: {=SUMPRODUCT(I$55:I$114,TRANSPOSE(SAP_Speadsheet!$E$73:$BL$73))} -> #REF! | ... BI21: {=SUMPRODUCT(BI$55:BI$114,TRANSPOSE(SAP_Speadsheet!$E$73:$BL$73))} -> #REF!
A22: Sharing performance | B22: {=SUMPRODUCT(B$55:B$114,TRANSPOSE(SAP_Speadsheet!$E$74:$BL$74))} -> 0 | C22: {=SUMPRODUCT(C$55:C$114,TRANSPOSE(SAP_Speadsheet!$E$74:$BL$74))} -> 0 | D22: {=SUMPRODUCT(D$55:D$114,TRANSPOSE(SAP_Speadsheet!$E$74:$BL$74))} -> 0 | E22: {=SUMPRODUCT(E$55:E$114,TRANSPOSE(SAP_Speadsheet!$E$74:$BL$74))} -> 0 | F22: {=SUMPRODUCT(F$55:F$114,TRANSPOSE(SAP_Speadsheet!$E$74:$BL$74))} -> 0 | G22: {=SUMPRODUCT(G$55:G$114,TRANSPOSE(SAP_Speadsheet!$E$74:$BL$74))} -> 0 | H22: {=SUMPRODUCT(H$55:H$114,TRANSPOSE(SAP_Speadsheet!$E$74:$BL$74))} -> #REF! | I22: {=SUMPRODUCT(I$55:I$114,TRANSPOSE(SAP_Speadsheet!$E$74:$BL$74))} -> #REF! | ... BI22: {=SUMPRODUCT(BI$55:BI$114,TRANSPOSE(SAP_Speadsheet!$E$74:$BL$74))} -> #REF!
A23: Marketing | B23: {=SUMPRODUCT(B$55:B$114,TRANSPOSE(SAP_Speadsheet!$E$86:$BL$86))} -> 0 | C23: {=SUMPRODUCT(C$55:C$114,TRANSPOSE(SAP_Speadsheet!$E$86:$BL$86))} -> 0 | D23: {=SUMPRODUCT(D$55:D$114,TRANSPOSE(SAP_Speadsheet!$E$86:$BL$86))} -> 0 | E23: {=SUMPRODUCT(E$55:E$114,TRANSPOSE(SAP_Speadsheet!$E$86:$BL$86))} -> 0 | F23: {=SUMPRODUCT(F$55:F$114,TRANSPOSE(SAP_Speadsheet!$E$86:$BL$86))} -> 0 | G23: {=SUMPRODUCT(G$55:G$114,TRANSPOSE(SAP_Speadsheet!$E$86:$BL$86))} -> 0 | H23: {=SUMPRODUCT(H$55:H$114,TRANSPOSE(SAP_Speadsheet!$E$86:$BL$86))} -> #REF! | I23: {=SUMPRODUCT(I$55:I$114,TRANSPOSE(SAP_Speadsheet!$E$86:$BL$86))} -> #REF! | ... AV23: {=SUMPRODUCT(AV$55:AV$114,TRANSPOSE(SAP_Speadsheet!$E$86:$BL$86))} -> #REF! | AW23: 0 | AX23: {=SUMPRODUCT(AX$55:AX$114,TRANSPOSE(SAP_Speadsheet!$E$86:$BL$86))} -> #REF! | AY23: {=SUMPRODUCT(AY$55:AY$114,TRANSPOSE(SAP_Speadsheet!$E$86:$BL$86))} -> #REF! | AZ23: {=SUMPRODUCT(AZ$55:AZ$114,TRANSPOSE(SAP_Speadsheet!$E$86:$BL$86))} -> #REF! | BA23: {=SUMPRODUCT(BA$55:BA$114,TRANSPOSE(SAP_Speadsheet!$E$86:$BL$86))} -> #REF! | BB23: {=SUMPRODUCT(BB$55:BB$114,TRANSPOSE(SAP_Speadsheet!$E$86:$BL$86))} -> #REF! | BC23: {=SUMPRODUCT(BC$55:BC$114,TRANSPOSE(SAP_Speadsheet!$E$86:$BL$86))} -> #REF! | BD23: {=SUMPRODUCT(BD$55:BD$114,TRANSPOSE(SAP_Speadsheet!$E$86:$BL$86))} -> #REF! | BE23: {=SUMPRODUCT(BE$55:BE$114,TRANSPOSE(SAP_Speadsheet!$E$86:$BL$86))} -> #REF! | ... BI23: {=SUMPRODUCT(BI$55:BI$114,TRANSPOSE(SAP_Speadsheet!$E$86:$BL$86))} -> #REF!
A24: UW & Disbursal | B24: {=SUMPRODUCT(B$55:B$114,TRANSPOSE(SAP_Speadsheet!$E$88:$BL$88))} -> 0 | C24: {=SUMPRODUCT(C$55:C$114,TRANSPOSE(SAP_Speadsheet!$E$88:$BL$88))} -> 0 | D24: {=SUMPRODUCT(D$55:D$114,TRANSPOSE(SAP_Speadsheet!$E$88:$BL$88))} -> 0 | E24: {=SUMPRODUCT(E$55:E$114,TRANSPOSE(SAP_Speadsheet!$E$88:$BL$88))} -> 0 | F24: {=SUMPRODUCT(F$55:F$114,TRANSPOSE(SAP_Speadsheet!$E$88:$BL$88))} -> 0 | G24: {=SUMPRODUCT(G$55:G$114,TRANSPOSE(SAP_Speadsheet!$E$88:$BL$88))} -> 0 | H24: {=SUMPRODUCT(H$55:H$114,TRANSPOSE(SAP_Speadsheet!$E$88:$BL$88))} -> #REF! | I24: {=SUMPRODUCT(I$55:I$114,TRANSPOSE(SAP_Speadsheet!$E$88:$BL$88))} -> #REF! | ... BI24: {=SUMPRODUCT(BI$55:BI$114,TRANSPOSE(SAP_Speadsheet!$E$88:$BL$88))} -> #REF!
A25: Underwriting | B25: {=SUMPRODUCT(B$55:B$114,TRANSPOSE(SAP_Speadsheet!$E$89:$BL$89))} -> 0 | C25: {=SUMPRODUCT(C$55:C$114,TRANSPOSE(SAP_Speadsheet!$E$89:$BL$89))} -> 0 | D25: {=SUMPRODUCT(D$55:D$114,TRANSPOSE(SAP_Speadsheet!$E$89:$BL$89))} -> 0 | E25: {=SUMPRODUCT(E$55:E$114,TRANSPOSE(SAP_Speadsheet!$E$89:$BL$89))} -> 0 | F25: {=SUMPRODUCT(F$55:F$114,TRANSPOSE(SAP_Speadsheet!$E$89:$BL$89))} -> 0 | G25: {=SUMPRODUCT(G$55:G$114,TRANSPOSE(SAP_Speadsheet!$E$89:$BL$89))} -> 0 | H25: {=SUMPRODUCT(H$55:H$114,TRANSPOSE(SAP_Speadsheet!$E$89:$BL$89))} -> #REF! | I25: {=SUMPRODUCT(I$55:I$114,TRANSPOSE(SAP_Speadsheet!$E$89:$BL$89))} -> #REF! | ... BI25: {=SUMPRODUCT(BI$55:BI$114,TRANSPOSE(SAP_Speadsheet!$E$89:$BL$89))} -> #REF!
A26: Disbursement | B26: {=SUMPRODUCT(B$55:B$114,TRANSPOSE(SAP_Speadsheet!$E$90:$BL$90))} -> 0 | C26: {=SUMPRODUCT(C$55:C$114,TRANSPOSE(SAP_Speadsheet!$E$90:$BL$90))} -> 0 | D26: {=SUMPRODUCT(D$55:D$114,TRANSPOSE(SAP_Speadsheet!$E$90:$BL$90))} -> 0 | E26: {=SUMPRODUCT(E$55:E$114,TRANSPOSE(SAP_Speadsheet!$E$90:$BL$90))} -> 0 | F26: {=SUMPRODUCT(F$55:F$114,TRANSPOSE(SAP_Speadsheet!$E$90:$BL$90))} -> 0 | G26: {=SUMPRODUCT(G$55:G$114,TRANSPOSE(SAP_Speadsheet!$E$90:$BL$90))} -> 0 | H26: {=SUMPRODUCT(H$55:H$114,TRANSPOSE(SAP_Speadsheet!$E$90:$BL$90))} -> #REF! | I26: {=SUMPRODUCT(I$55:I$114,TRANSPOSE(SAP_Speadsheet!$E$90:$BL$90))} -> #REF! | ... BI26: {=SUMPRODUCT(BI$55:BI$114,TRANSPOSE(SAP_Speadsheet!$E$90:$BL$90))} -> #REF!
A27: DOP | B27: {=SUMPRODUCT(B$55:B$114,TRANSPOSE(SAP_Speadsheet!$E$91:$BL$91))} -> 0 | C27: {=SUMPRODUCT(C$55:C$114,TRANSPOSE(SAP_Speadsheet!$E$91:$BL$91))} -> 0 | D27: {=SUMPRODUCT(D$55:D$114,TRANSPOSE(SAP_Speadsheet!$E$91:$BL$91))} -> 0 | E27: {=SUMPRODUCT(E$55:E$114,TRANSPOSE(SAP_Speadsheet!$E$91:$BL$91))} -> 0 | F27: {=SUMPRODUCT(F$55:F$114,TRANSPOSE(SAP_Speadsheet!$E$91:$BL$91))} -> 0 | G27: {=SUMPRODUCT(G$55:G$114,TRANSPOSE(SAP_Speadsheet!$E$91:$BL$91))} -> 0 | H27: {=SUMPRODUCT(H$55:H$114,TRANSPOSE(SAP_Speadsheet!$E$91:$BL$91))} -> #REF! | I27: {=SUMPRODUCT(I$55:I$114,TRANSPOSE(SAP_Speadsheet!$E$91:$BL$91))} -> #REF! | ... BI27: {=SUMPRODUCT(BI$55:BI$114,TRANSPOSE(SAP_Speadsheet!$E$91:$BL$91))} -> #REF!
A28: Collection | B28: {=SUMPRODUCT(B$55:B$114,TRANSPOSE(SAP_Speadsheet!$E$95:$BL$95))} -> 0 | C28: {=SUMPRODUCT(C$55:C$114,TRANSPOSE(SAP_Speadsheet!$E$95:$BL$95))} -> 0 | D28: {=SUMPRODUCT(D$55:D$114,TRANSPOSE(SAP_Speadsheet!$E$95:$BL$95))} -> 0 | E28: {=SUMPRODUCT(E$55:E$114,TRANSPOSE(SAP_Speadsheet!$E$95:$BL$95))} -> 0 | F28: {=SUMPRODUCT(F$55:F$114,TRANSPOSE(SAP_Speadsheet!$E$95:$BL$95))} -> 0 | G28: {=SUMPRODUCT(G$55:G$114,TRANSPOSE(SAP_Speadsheet!$E$95:$BL$95))} -> 0 | H28: {=SUMPRODUCT(H$55:H$114,TRANSPOSE(SAP_Speadsheet!$E$95:$BL$95))} -> #REF! | I28: {=SUMPRODUCT(I$55:I$114,TRANSPOSE(SAP_Speadsheet!$E$95:$BL$95))} -> #REF! | ... BI28: {=SUMPRODUCT(BI$55:BI$114,TRANSPOSE(SAP_Speadsheet!$E$95:$BL$95))} -> #REF!
A29: After-sales services | B29: {=SUMPRODUCT(B$55:B$114,TRANSPOSE(SAP_Speadsheet!$E$99:$BL$99))} -> 0 | C29: {=SUMPRODUCT(C$55:C$114,TRANSPOSE(SAP_Speadsheet!$E$99:$BL$99))} -> 0 | D29: {=SUMPRODUCT(D$55:D$114,TRANSPOSE(SAP_Speadsheet!$E$99:$BL$99))} -> 0 | E29: {=SUMPRODUCT(E$55:E$114,TRANSPOSE(SAP_Speadsheet!$E$99:$BL$99))} -> 0 | F29: {=SUMPRODUCT(F$55:F$114,TRANSPOSE(SAP_Speadsheet!$E$99:$BL$99))} -> 0 | G29: {=SUMPRODUCT(G$55:G$114,TRANSPOSE(SAP_Speadsheet!$E$99:$BL$99))} -> 0 | H29: {=SUMPRODUCT(H$55:H$114,TRANSPOSE(SAP_Speadsheet!$E$99:$BL$99))} -> #REF! | I29: {=SUMPRODUCT(I$55:I$114,TRANSPOSE(SAP_Speadsheet!$E$99:$BL$99))} -> #REF! | ... BI29: {=SUMPRODUCT(BI$55:BI$114,TRANSPOSE(SAP_Speadsheet!$E$99:$BL$99))} -> #REF!
A30: Other support units | B30: {=SUMPRODUCT(B$55:B$114,TRANSPOSE(SAP_Speadsheet!$E$103:$BL$103))} -> 0 | C30: {=SUMPRODUCT(C$55:C$114,TRANSPOSE(SAP_Speadsheet!$E$103:$BL$103))} -> 0 | D30: {=SUMPRODUCT(D$55:D$114,TRANSPOSE(SAP_Speadsheet!$E$103:$BL$103))} -> 0 | E30: {=SUMPRODUCT(E$55:E$114,TRANSPOSE(SAP_Speadsheet!$E$103:$BL$103))} -> 0 | F30: {=SUMPRODUCT(F$55:F$114,TRANSPOSE(SAP_Speadsheet!$E$103:$BL$103))} -> 0 | G30: {=SUMPRODUCT(G$55:G$114,TRANSPOSE(SAP_Speadsheet!$E$103:$BL$103))} -> 0 | H30: {=SUMPRODUCT(H$55:H$114,TRANSPOSE(SAP_Speadsheet!$E$103:$BL$103))} -> #REF! | I30: {=SUMPRODUCT(I$55:I$114,TRANSPOSE(SAP_Speadsheet!$E$103:$BL$103))} -> #REF! | ... BI30: {=SUMPRODUCT(BI$55:BI$114,TRANSPOSE(SAP_Speadsheet!$E$103:$BL$103))} -> #REF!
A31: PROVISION | B31: {=SUMPRODUCT(B$55:B$114,TRANSPOSE(SAP_Speadsheet!$E$183:$BL$183))} -> 0 | C31: {=SUMPRODUCT(C$55:C$114,TRANSPOSE(SAP_Speadsheet!$E$183:$BL$183))} -> 0 | D31: {=SUMPRODUCT(D$55:D$114,TRANSPOSE(SAP_Speadsheet!$E$183:$BL$183))} -> 0 | E31: {=SUMPRODUCT(E$55:E$114,TRANSPOSE(SAP_Speadsheet!$E$183:$BL$183))} -> 0 | F31: {=SUMPRODUCT(F$55:F$114,TRANSPOSE(SAP_Speadsheet!$E$183:$BL$183))} -> 0 | G31: {=SUMPRODUCT(G$55:G$114,TRANSPOSE(SAP_Speadsheet!$E$183:$BL$183))} -> 0 | H31: {=SUMPRODUCT(H$55:H$114,TRANSPOSE(SAP_Speadsheet!$E$183:$BL$183))} -> #REF! | I31: {=SUMPRODUCT(I$55:I$114,TRANSPOSE(SAP_Speadsheet!$E$183:$BL$183))} -> #REF! | ... BI31: {=SUMPRODUCT(BI$55:BI$114,TRANSPOSE(SAP_Speadsheet!$E$183:$BL$183))} -> #REF!
A32: PBT | B32: {=SUMPRODUCT(B$55:B$114,TRANSPOSE(SAP_Speadsheet!$E$189:$BL$189))} -> 0 | C32: {=SUMPRODUCT(C$55:C$114,TRANSPOSE(SAP_Speadsheet!$E$189:$BL$189))} -> 0 | D32: {=SUMPRODUCT(D$55:D$114,TRANSPOSE(SAP_Speadsheet!$E$189:$BL$189))} -> 0 | E32: {=SUMPRODUCT(E$55:E$114,TRANSPOSE(SAP_Speadsheet!$E$189:$BL$189))} -> 0 | F32: {=SUMPRODUCT(F$55:F$114,TRANSPOSE(SAP_Speadsheet!$E$189:$BL$189))} -> 0 | G32: {=SUMPRODUCT(G$55:G$114,TRANSPOSE(SAP_Speadsheet!$E$189:$BL$189))} -> 0 | H32: {=SUMPRODUCT(H$55:H$114,TRANSPOSE(SAP_Speadsheet!$E$189:$BL$189))} -> #REF! | I32: {=SUMPRODUCT(I$55:I$114,TRANSPOSE(SAP_Speadsheet!$E$189:$BL$189))} -> #REF! | ... BI32: {=SUMPRODUCT(BI$55:BI$114,TRANSPOSE(SAP_Speadsheet!$E$189:$BL$189))} -> #REF!
A33: Checking | B33: =B9+B19+B31-B32 -> 0 | C33: =C9+C19+C31-C32 -> 0 | D33: =D9+D19+D31-D32 -> 0 | E33: =E9+E19+E31-E32 -> 0 | F33: =F9+F19+F31-F32 -> 0 | G33: =G9+G19+G31-G32 -> 0 | H33: =H9+H19+H31-H32 -> #REF! | I33: =I9+I19+I31-I32 -> #REF! | ... BI33: =BI9+BI19+BI31-BI32 -> #REF!
A35: EOP BY BUCKET
A36: B0 | B36: {=SUMPRODUCT(B$55:B$114,TRANSPOSE(SAP_Speadsheet!$E$27:$BL$27))} -> 0 | C36: {=SUMPRODUCT(C$55:C$114,TRANSPOSE(SAP_Speadsheet!$E$27:$BL$27))} -> 0 | D36: {=SUMPRODUCT(D$55:D$114,TRANSPOSE(SAP_Speadsheet!$E$27:$BL$27))} -> 0 | E36: {=SUMPRODUCT(E$55:E$114,TRANSPOSE(SAP_Speadsheet!$E$27:$BL$27))} -> 0 | F36: {=SUMPRODUCT(F$55:F$114,TRANSPOSE(SAP_Speadsheet!$E$27:$BL$27))} -> 0 | G36: {=SUMPRODUCT(G$55:G$114,TRANSPOSE(SAP_Speadsheet!$E$27:$BL$27))} -> 0 | H36: {=SUMPRODUCT(H$55:H$114,TRANSPOSE(SAP_Speadsheet!$E$27:$BL$27))} -> #REF! | I36: {=SUMPRODUCT(I$55:I$114,TRANSPOSE(SAP_Speadsheet!$E$27:$BL$27))} -> #REF! | ... BI36: {=SUMPRODUCT(BI$55:BI$114,TRANSPOSE(SAP_Speadsheet!$E$27:$BL$27))} -> #REF!
A37: B1 | B37: {=SUMPRODUCT(B$55:B$114,TRANSPOSE(SAP_Speadsheet!$E$28:$BL$28))} -> 0 | C37: {=SUMPRODUCT(C$55:C$114,TRANSPOSE(SAP_Speadsheet!$E$28:$BL$28))} -> 0 | D37: {=SUMPRODUCT(D$55:D$114,TRANSPOSE(SAP_Speadsheet!$E$28:$BL$28))} -> 0 | E37: {=SUMPRODUCT(E$55:E$114,TRANSPOSE(SAP_Speadsheet!$E$28:$BL$28))} -> 0 | F37: {=SUMPRODUCT(F$55:F$114,TRANSPOSE(SAP_Speadsheet!$E$28:$BL$28))} -> 0 | G37: {=SUMPRODUCT(G$55:G$114,TRANSPOSE(SAP_Speadsheet!$E$28:$BL$28))} -> 0 | H37: {=SUMPRODUCT(H$55:H$114,TRANSPOSE(SAP_Speadsheet!$E$28:$BL$28))} -> #REF! | I37: {=SUMPRODUCT(I$55:I$114,TRANSPOSE(SAP_Speadsheet!$E$28:$BL$28))} -> #REF! | ... BI37: {=SUMPRODUCT(BI$55:BI$114,TRANSPOSE(SAP_Speadsheet!$E$28:$BL$28))} -> #REF!
A38: B2 | B38: {=SUMPRODUCT(B$55:B$114,TRANSPOSE(SAP_Speadsheet!$E$29:$BL$29))} -> 0 | C38: {=SUMPRODUCT(C$55:C$114,TRANSPOSE(SAP_Speadsheet!$E$29:$BL$29))} -> 0 | D38: {=SUMPRODUCT(D$55:D$114,TRANSPOSE(SAP_Speadsheet!$E$29:$BL$29))} -> 0 | E38: {=SUMPRODUCT(E$55:E$114,TRANSPOSE(SAP_Speadsheet!$E$29:$BL$29))} -> 0 | F38: {=SUMPRODUCT(F$55:F$114,TRANSPOSE(SAP_Speadsheet!$E$29:$BL$29))} -> 0 | G38: {=SUMPRODUCT(G$55:G$114,TRANSPOSE(SAP_Speadsheet!$E$29:$BL$29))} -> 0 | H38: {=SUMPRODUCT(H$55:H$114,TRANSPOSE(SAP_Speadsheet!$E$29:$BL$29))} -> #REF! | I38: {=SUMPRODUCT(I$55:I$114,TRANSPOSE(SAP_Speadsheet!$E$29:$BL$29))} -> #REF! | ... BI38: {=SUMPRODUCT(BI$55:BI$114,TRANSPOSE(SAP_Speadsheet!$E$29:$BL$29))} -> #REF!
A39: B3 | B39: {=SUMPRODUCT(B$55:B$114,TRANSPOSE(SAP_Speadsheet!$E$30:$BL$30))} -> 0 | C39: {=SUMPRODUCT(C$55:C$114,TRANSPOSE(SAP_Speadsheet!$E$30:$BL$30))} -> 0 | D39: {=SUMPRODUCT(D$55:D$114,TRANSPOSE(SAP_Speadsheet!$E$30:$BL$30))} -> 0 | E39: {=SUMPRODUCT(E$55:E$114,TRANSPOSE(SAP_Speadsheet!$E$30:$BL$30))} -> 0 | F39: {=SUMPRODUCT(F$55:F$114,TRANSPOSE(SAP_Speadsheet!$E$30:$BL$30))} -> 0 | G39: {=SUMPRODUCT(G$55:G$114,TRANSPOSE(SAP_Speadsheet!$E$30:$BL$30))} -> 0 | H39: {=SUMPRODUCT(H$55:H$114,TRANSPOSE(SAP_Speadsheet!$E$30:$BL$30))} -> #REF! | I39: {=SUMPRODUCT(I$55:I$114,TRANSPOSE(SAP_Speadsheet!$E$30:$BL$30))} -> #REF! | ... BI39: {=SUMPRODUCT(BI$55:BI$114,TRANSPOSE(SAP_Speadsheet!$E$30:$BL$30))} -> #REF!
A40: B4 | B40: {=SUMPRODUCT(B$55:B$114,TRANSPOSE(SAP_Speadsheet!$E$31:$BL$31))} -> 0 | C40: {=SUMPRODUCT(C$55:C$114,TRANSPOSE(SAP_Speadsheet!$E$31:$BL$31))} -> 0 | D40: {=SUMPRODUCT(D$55:D$114,TRANSPOSE(SAP_Speadsheet!$E$31:$BL$31))} -> 0 | E40: {=SUMPRODUCT(E$55:E$114,TRANSPOSE(SAP_Speadsheet!$E$31:$BL$31))} -> 0 | F40: {=SUMPRODUCT(F$55:F$114,TRANSPOSE(SAP_Speadsheet!$E$31:$BL$31))} -> 0 | G40: {=SUMPRODUCT(G$55:G$114,TRANSPOSE(SAP_Speadsheet!$E$31:$BL$31))} -> 0 | H40: {=SUMPRODUCT(H$55:H$114,TRANSPOSE(SAP_Speadsheet!$E$31:$BL$31))} -> #REF! | I40: {=SUMPRODUCT(I$55:I$114,TRANSPOSE(SAP_Speadsheet!$E$31:$BL$31))} -> #REF! | ... BI40: {=SUMPRODUCT(BI$55:BI$114,TRANSPOSE(SAP_Speadsheet!$E$31:$BL$31))} -> #REF!
A41: B5 | B41: {=SUMPRODUCT(B$55:B$114,TRANSPOSE(SAP_Speadsheet!$E$32:$BL$32))} -> 0 | C41: {=SUMPRODUCT(C$55:C$114,TRANSPOSE(SAP_Speadsheet!$E$32:$BL$32))} -> 0 | D41: {=SUMPRODUCT(D$55:D$114,TRANSPOSE(SAP_Speadsheet!$E$32:$BL$32))} -> 0 | E41: {=SUMPRODUCT(E$55:E$114,TRANSPOSE(SAP_Speadsheet!$E$32:$BL$32))} -> 0 | F41: {=SUMPRODUCT(F$55:F$114,TRANSPOSE(SAP_Speadsheet!$E$32:$BL$32))} -> 0 | G41: {=SUMPRODUCT(G$55:G$114,TRANSPOSE(SAP_Speadsheet!$E$32:$BL$32))} -> 0 | H41: {=SUMPRODUCT(H$55:H$114,TRANSPOSE(SAP_Speadsheet!$E$32:$BL$32))} -> #REF! | I41: {=SUMPRODUCT(I$55:I$114,TRANSPOSE(SAP_Speadsheet!$E$32:$BL$32))} -> #REF! | ... BI41: {=SUMPRODUCT(BI$55:BI$114,TRANSPOSE(SAP_Speadsheet!$E$32:$BL$32))} -> #REF!
A42: B6 | B42: {=SUMPRODUCT(B$55:B$114,TRANSPOSE(SAP_Speadsheet!$E$33:$BL$33))} -> 0 | C42: {=SUMPRODUCT(C$55:C$114,TRANSPOSE(SAP_Speadsheet!$E$33:$BL$33))} -> 0 | D42: {=SUMPRODUCT(D$55:D$114,TRANSPOSE(SAP_Speadsheet!$E$33:$BL$33))} -> 0 | E42: {=SUMPRODUCT(E$55:E$114,TRANSPOSE(SAP_Speadsheet!$E$33:$BL$33))} -> 0 | F42: {=SUMPRODUCT(F$55:F$114,TRANSPOSE(SAP_Speadsheet!$E$33:$BL$33))} -> 0 | G42: {=SUMPRODUCT(G$55:G$114,TRANSPOSE(SAP_Speadsheet!$E$33:$BL$33))} -> 0 | H42: {=SUMPRODUCT(H$55:H$114,TRANSPOSE(SAP_Speadsheet!$E$33:$BL$33))} -> #REF! | I42: {=SUMPRODUCT(I$55:I$114,TRANSPOSE(SAP_Speadsheet!$E$33:$BL$33))} -> #REF! | ... BI42: {=SUMPRODUCT(BI$55:BI$114,TRANSPOSE(SAP_Speadsheet!$E$33:$BL$33))} -> #REF!
A43: B7 | B43: {=SUMPRODUCT(B$55:B$114,TRANSPOSE(SAP_Speadsheet!$E$34:$BL$34))} -> 0 | C43: {=SUMPRODUCT(C$55:C$114,TRANSPOSE(SAP_Speadsheet!$E$34:$BL$34))} -> 0 | D43: {=SUMPRODUCT(D$55:D$114,TRANSPOSE(SAP_Speadsheet!$E$34:$BL$34))} -> 0 | E43: {=SUMPRODUCT(E$55:E$114,TRANSPOSE(SAP_Speadsheet!$E$34:$BL$34))} -> 0 | F43: {=SUMPRODUCT(F$55:F$114,TRANSPOSE(SAP_Speadsheet!$E$34:$BL$34))} -> 0 | G43: {=SUMPRODUCT(G$55:G$114,TRANSPOSE(SAP_Speadsheet!$E$34:$BL$34))} -> 0 | H43: {=SUMPRODUCT(H$55:H$114,TRANSPOSE(SAP_Speadsheet!$E$34:$BL$34))} -> #REF! | I43: {=SUMPRODUCT(I$55:I$114,TRANSPOSE(SAP_Speadsheet!$E$34:$BL$34))} -> #REF! | ... BI43: {=SUMPRODUCT(BI$55:BI$114,TRANSPOSE(SAP_Speadsheet!$E$34:$BL$34))} -> #REF!
A44: B8 | B44: {=SUMPRODUCT(B$55:B$114,TRANSPOSE(SAP_Speadsheet!$E$35:$BL$35))} -> 0 | C44: {=SUMPRODUCT(C$55:C$114,TRANSPOSE(SAP_Speadsheet!$E$35:$BL$35))} -> 0 | D44: {=SUMPRODUCT(D$55:D$114,TRANSPOSE(SAP_Speadsheet!$E$35:$BL$35))} -> 0 | E44: {=SUMPRODUCT(E$55:E$114,TRANSPOSE(SAP_Speadsheet!$E$35:$BL$35))} -> 0 | F44: {=SUMPRODUCT(F$55:F$114,TRANSPOSE(SAP_Speadsheet!$E$35:$BL$35))} -> 0 | G44: {=SUMPRODUCT(G$55:G$114,TRANSPOSE(SAP_Speadsheet!$E$35:$BL$35))} -> 0 | H44: {=SUMPRODUCT(H$55:H$114,TRANSPOSE(SAP_Speadsheet!$E$35:$BL$35))} -> #REF! | I44: {=SUMPRODUCT(I$55:I$114,TRANSPOSE(SAP_Speadsheet!$E$35:$BL$35))} -> #REF! | ... BI44: {=SUMPRODUCT(BI$55:BI$114,TRANSPOSE(SAP_Speadsheet!$E$35:$BL$35))} -> #REF!
A45: B9 | B45: {=SUMPRODUCT(B$55:B$114,TRANSPOSE(SAP_Speadsheet!$E$36:$BL$36))} -> 0 | C45: {=SUMPRODUCT(C$55:C$114,TRANSPOSE(SAP_Speadsheet!$E$36:$BL$36))} -> 0 | D45: {=SUMPRODUCT(D$55:D$114,TRANSPOSE(SAP_Speadsheet!$E$36:$BL$36))} -> 0 | E45: {=SUMPRODUCT(E$55:E$114,TRANSPOSE(SAP_Speadsheet!$E$36:$BL$36))} -> 0 | F45: {=SUMPRODUCT(F$55:F$114,TRANSPOSE(SAP_Speadsheet!$E$36:$BL$36))} -> 0 | G45: {=SUMPRODUCT(G$55:G$114,TRANSPOSE(SAP_Speadsheet!$E$36:$BL$36))} -> 0 | H45: {=SUMPRODUCT(H$55:H$114,TRANSPOSE(SAP_Speadsheet!$E$36:$BL$36))} -> #REF! | I45: {=SUMPRODUCT(I$55:I$114,TRANSPOSE(SAP_Speadsheet!$E$36:$BL$36))} -> #REF! | ... BI45: {=SUMPRODUCT(BI$55:BI$114,TRANSPOSE(SAP_Speadsheet!$E$36:$BL$36))} -> #REF!
A46: B10 | B46: {=SUMPRODUCT(B$55:B$114,TRANSPOSE(SAP_Speadsheet!$E$37:$BL$37))} -> 0 | C46: {=SUMPRODUCT(C$55:C$114,TRANSPOSE(SAP_Speadsheet!$E$37:$BL$37))} -> 0 | D46: {=SUMPRODUCT(D$55:D$114,TRANSPOSE(SAP_Speadsheet!$E$37:$BL$37))} -> 0 | E46: {=SUMPRODUCT(E$55:E$114,TRANSPOSE(SAP_Speadsheet!$E$37:$BL$37))} -> 0 | F46: {=SUMPRODUCT(F$55:F$114,TRANSPOSE(SAP_Speadsheet!$E$37:$BL$37))} -> 0 | G46: {=SUMPRODUCT(G$55:G$114,TRANSPOSE(SAP_Speadsheet!$E$37:$BL$37))} -> 0 | H46: {=SUMPRODUCT(H$55:H$114,TRANSPOSE(SAP_Speadsheet!$E$37:$BL$37))} -> #REF! | I46: {=SUMPRODUCT(I$55:I$114,TRANSPOSE(SAP_Speadsheet!$E$37:$BL$37))} -> #REF! | ... BI46: {=SUMPRODUCT(BI$55:BI$114,TRANSPOSE(SAP_Speadsheet!$E$37:$BL$37))} -> #REF!
A47: B11 | B47: {=SUMPRODUCT(B$55:B$114,TRANSPOSE(SAP_Speadsheet!$E$38:$BL$38))} -> 0 | C47: {=SUMPRODUCT(C$55:C$114,TRANSPOSE(SAP_Speadsheet!$E$38:$BL$38))} -> 0 | D47: {=SUMPRODUCT(D$55:D$114,TRANSPOSE(SAP_Speadsheet!$E$38:$BL$38))} -> 0 | E47: {=SUMPRODUCT(E$55:E$114,TRANSPOSE(SAP_Speadsheet!$E$38:$BL$38))} -> 0 | F47: {=SUMPRODUCT(F$55:F$114,TRANSPOSE(SAP_Speadsheet!$E$38:$BL$38))} -> 0 | G47: {=SUMPRODUCT(G$55:G$114,TRANSPOSE(SAP_Speadsheet!$E$38:$BL$38))} -> 0 | H47: {=SUMPRODUCT(H$55:H$114,TRANSPOSE(SAP_Speadsheet!$E$38:$BL$38))} -> #REF! | I47: {=SUMPRODUCT(I$55:I$114,TRANSPOSE(SAP_Speadsheet!$E$38:$BL$38))} -> #REF! | ... BI47: {=SUMPRODUCT(BI$55:BI$114,TRANSPOSE(SAP_Speadsheet!$E$38:$BL$38))} -> #REF!
A48: B12 | B48: {=SUMPRODUCT(B$55:B$114,TRANSPOSE(SAP_Speadsheet!$E$39:$BL$39))} -> 0 | C48: {=SUMPRODUCT(C$55:C$114,TRANSPOSE(SAP_Speadsheet!$E$39:$BL$39))} -> 0 | D48: {=SUMPRODUCT(D$55:D$114,TRANSPOSE(SAP_Speadsheet!$E$39:$BL$39))} -> 0 | E48: {=SUMPRODUCT(E$55:E$114,TRANSPOSE(SAP_Speadsheet!$E$39:$BL$39))} -> 0 | F48: {=SUMPRODUCT(F$55:F$114,TRANSPOSE(SAP_Speadsheet!$E$39:$BL$39))} -> 0 | G48: {=SUMPRODUCT(G$55:G$114,TRANSPOSE(SAP_Speadsheet!$E$39:$BL$39))} -> 0 | H48: {=SUMPRODUCT(H$55:H$114,TRANSPOSE(SAP_Speadsheet!$E$39:$BL$39))} -> #REF! | I48: {=SUMPRODUCT(I$55:I$114,TRANSPOSE(SAP_Speadsheet!$E$39:$BL$39))} -> #REF! | ... BI48: {=SUMPRODUCT(BI$55:BI$114,TRANSPOSE(SAP_Speadsheet!$E$39:$BL$39))} -> #REF!
A49: B13+ | B49: {=SUMPRODUCT(B$55:B$114,TRANSPOSE(SAP_Speadsheet!$E$40:$BL$40))} -> 0 | C49: {=SUMPRODUCT(C$55:C$114,TRANSPOSE(SAP_Speadsheet!$E$40:$BL$40))} -> 0 | D49: {=SUMPRODUCT(D$55:D$114,TRANSPOSE(SAP_Speadsheet!$E$40:$BL$40))} -> 0 | E49: {=SUMPRODUCT(E$55:E$114,TRANSPOSE(SAP_Speadsheet!$E$40:$BL$40))} -> 0 | F49: {=SUMPRODUCT(F$55:F$114,TRANSPOSE(SAP_Speadsheet!$E$40:$BL$40))} -> 0 | G49: {=SUMPRODUCT(G$55:G$114,TRANSPOSE(SAP_Speadsheet!$E$40:$BL$40))} -> 0 | H49: {=SUMPRODUCT(H$55:H$114,TRANSPOSE(SAP_Speadsheet!$E$40:$BL$40))} -> #REF! | I49: {=SUMPRODUCT(I$55:I$114,TRANSPOSE(SAP_Speadsheet!$E$40:$BL$40))} -> #REF! | ... BI49: {=SUMPRODUCT(BI$55:BI$114,TRANSPOSE(SAP_Speadsheet!$E$40:$BL$40))} -> #REF!
A50: B14+ | B50: {=SUMPRODUCT(B$55:B$114,TRANSPOSE(SAP_Speadsheet!$E$41:$BL$41))} -> 0 | C50: {=SUMPRODUCT(C$55:C$114,TRANSPOSE(SAP_Speadsheet!$E$41:$BL$41))} -> 0 | D50: {=SUMPRODUCT(D$55:D$114,TRANSPOSE(SAP_Speadsheet!$E$41:$BL$41))} -> 0 | E50: {=SUMPRODUCT(E$55:E$114,TRANSPOSE(SAP_Speadsheet!$E$41:$BL$41))} -> 0 | F50: {=SUMPRODUCT(F$55:F$114,TRANSPOSE(SAP_Speadsheet!$E$41:$BL$41))} -> 0 | G50: {=SUMPRODUCT(G$55:G$114,TRANSPOSE(SAP_Speadsheet!$E$41:$BL$41))} -> 0 | H50: {=SUMPRODUCT(H$55:H$114,TRANSPOSE(SAP_Speadsheet!$E$41:$BL$41))} -> #REF! | I50: {=SUMPRODUCT(I$55:I$114,TRANSPOSE(SAP_Speadsheet!$E$41:$BL$41))} -> #REF! | ... BI50: {=SUMPRODUCT(BI$55:BI$114,TRANSPOSE(SAP_Speadsheet!$E$41:$BL$41))} -> #REF!
A51: Checking | B51: =SUM(B36:B50)-B7 -> 0 | C51: =SUM(C36:C50)-C7 -> 0 | D51: =SUM(D36:D50)-D7 -> 0 | E51: =SUM(E36:E50)-E7 -> 0 | F51: =SUM(F36:F50)-F7 -> 0 | G51: =SUM(G36:G50)-G7 -> 0 | H51: =SUM(H36:H50)-H7 -> #REF! | I51: =SUM(I36:I50)-I7 -> #REF! | ... BI51: =SUM(BI36:BI50)-BI7 -> #REF!
A54: No. of account | B54: =ROUND('Saleplan&PnL'!D6*1000/Leadsheet!$E$10,0) -> 0 | C54: =ROUND('Saleplan&PnL'!E6*1000/Leadsheet!$E$10,0) -> 0 | D54: =ROUND('Saleplan&PnL'!F6*1000/Leadsheet!$E$10,0) -> 0 | E54: =ROUND('Saleplan&PnL'!G6*1000/Leadsheet!$E$10,0) -> 0 | F54: =ROUND('Saleplan&PnL'!H6*1000/Leadsheet!$E$10,0) -> 0 | G54: =ROUND('Saleplan&PnL'!I6*1000/Leadsheet!$E$10,0) -> 0 | H54: =ROUND('Saleplan&PnL'!J6*1000/Leadsheet!$E$10,0) -> #REF! | I54: =ROUND('Saleplan&PnL'!K6*1000/Leadsheet!$E$10,0) -> #REF! | ... BI54: =ROUND('Saleplan&PnL'!BK6*1000/Leadsheet!$E$10,0) -> 0
A55: 1 | B55: =IF($A55>B$5,"",OFFSET(B$54,0,-($A55-1))) -> 0 | C55: =IF($A55>C$5,"",OFFSET(C$54,0,-($A55-1))) -> 0 | D55: =IF($A55>D$5,"",OFFSET(D$54,0,-($A55-1))) -> 0 | E55: =IF($A55>E$5,"",OFFSET(E$54,0,-($A55-1))) -> 0 | F55: =IF($A55>F$5,"",OFFSET(F$54,0,-($A55-1))) -> 0 | G55: =IF($A55>G$5,"",OFFSET(G$54,0,-($A55-1))) -> 0 | H55: =IF($A55>H$5,"",OFFSET(H$54,0,-($A55-1))) -> #REF! | I55: =IF($A55>I$5,"",OFFSET(I$54,0,-($A55-1))) -> #REF! | ... BI55: =IF($A55>BI$5,"",OFFSET(BI$54,0,-($A55-1))) -> 0
A56: 2 | B56: =IF($A56>B$5,"",OFFSET(B$54,0,-($A56-1))) | C56: =IF($A56>C$5,"",OFFSET(C$54,0,-($A56-1))) -> 0 | D56: =IF($A56>D$5,"",OFFSET(D$54,0,-($A56-1))) -> 0 | E56: =IF($A56>E$5,"",OFFSET(E$54,0,-($A56-1))) -> 0 | F56: =IF($A56>F$5,"",OFFSET(F$54,0,-($A56-1))) -> 0 | G56: =IF($A56>G$5,"",OFFSET(G$54,0,-($A56-1))) -> 0 | H56: =IF($A56>H$5,"",OFFSET(H$54,0,-($A56-1))) -> 0 | I56: =IF($A56>I$5,"",OFFSET(I$54,0,-($A56-1))) -> #REF! | ... BI56: =IF($A56>BI$5,"",OFFSET(BI$54,0,-($A56-1))) -> 0
A57: 3 | B57: =IF($A57>B$5,"",OFFSET(B$54,0,-($A57-1))) | C57: =IF($A57>C$5,"",OFFSET(C$54,0,-($A57-1))) | D57: =IF($A57>D$5,"",OFFSET(D$54,0,-($A57-1))) -> 0 | E57: =IF($A57>E$5,"",OFFSET(E$54,0,-($A57-1))) -> 0 | F57: =IF($A57>F$5,"",OFFSET(F$54,0,-($A57-1))) -> 0 | G57: =IF($A57>G$5,"",OFFSET(G$54,0,-($A57-1))) -> 0 | H57: =IF($A57>H$5,"",OFFSET(H$54,0,-($A57-1))) -> 0 | I57: =IF($A57>I$5,"",OFFSET(I$54,0,-($A57-1))) -> 0 | ... BI57: =IF($A57>BI$5,"",OFFSET(BI$54,0,-($A57-1))) -> 0
A58: 4 | B58: =IF($A58>B$5,"",OFFSET(B$54,0,-($A58-1))) | C58: =IF($A58>C$5,"",OFFSET(C$54,0,-($A58-1))) | D58: =IF($A58>D$5,"",OFFSET(D$54,0,-($A58-1))) | E58: =IF($A58>E$5,"",OFFSET(E$54,0,-($A58-1))) -> 0 | F58: =IF($A58>F$5,"",OFFSET(F$54,0,-($A58-1))) -> 0 | G58: =IF($A58>G$5,"",OFFSET(G$54,0,-($A58-1))) -> 0 | H58: =IF($A58>H$5,"",OFFSET(H$54,0,-($A58-1))) -> 0 | I58: =IF($A58>I$5,"",OFFSET(I$54,0,-($A58-1))) -> 0 | ... BI58: =IF($A58>BI$5,"",OFFSET(BI$54,0,-($A58-1))) -> 0
A59: 5 | B59: =IF($A59>B$5,"",OFFSET(B$54,0,-($A59-1))) | C59: =IF($A59>C$5,"",OFFSET(C$54,0,-($A59-1))) | D59: =IF($A59>D$5,"",OFFSET(D$54,0,-($A59-1))) | E59: =IF($A59>E$5,"",OFFSET(E$54,0,-($A59-1))) | F59: =IF($A59>F$5,"",OFFSET(F$54,0,-($A59-1))) -> 0 | G59: =IF($A59>G$5,"",OFFSET(G$54,0,-($A59-1))) -> 0 | H59: =IF($A59>H$5,"",OFFSET(H$54,0,-($A59-1))) -> 0 | I59: =IF($A59>I$5,"",OFFSET(I$54,0,-($A59-1))) -> 0 | ... BI59: =IF($A59>BI$5,"",OFFSET(BI$54,0,-($A59-1))) -> 0
A60: 6 | B60: =IF($A60>B$5,"",OFFSET(B$54,0,-($A60-1))) | C60: =IF($A60>C$5,"",OFFSET(C$54,0,-($A60-1))) | D60: =IF($A60>D$5,"",OFFSET(D$54,0,-($A60-1))) | E60: =IF($A60>E$5,"",OFFSET(E$54,0,-($A60-1))) | F60: =IF($A60>F$5,"",OFFSET(F$54,0,-($A60-1))) | G60: =IF($A60>G$5,"",OFFSET(G$54,0,-($A60-1))) -> 0 | H60: =IF($A60>H$5,"",OFFSET(H$54,0,-($A60-1))) -> 0 | I60: =IF($A60>I$5,"",OFFSET(I$54,0,-($A60-1))) -> 0 | ... BI60: =IF($A60>BI$5,"",OFFSET(BI$54,0,-($A60-1))) -> 0
A61: 7 | B61: =IF($A61>B$5,"",OFFSET(B$54,0,-($A61-1))) | C61: =IF($A61>C$5,"",OFFSET(C$54,0,-($A61-1))) | D61: =IF($A61>D$5,"",OFFSET(D$54,0,-($A61-1))) | E61: =IF($A61>E$5,"",OFFSET(E$54,0,-($A61-1))) | F61: =IF($A61>F$5,"",OFFSET(F$54,0,-($A61-1))) | G61: =IF($A61>G$5,"",OFFSET(G$54,0,-($A61-1))) | H61: =IF($A61>H$5,"",OFFSET(H$54,0,-($A61-1))) -> 0 | I61: =IF($A61>I$5,"",OFFSET(I$54,0,-($A61-1))) -> 0 | ... BI61: =IF($A61>BI$5,"",OFFSET(BI$54,0,-($A61-1))) -> 0
A62: 8 | B62: =IF($A62>B$5,"",OFFSET(B$54,0,-($A62-1))) | C62: =IF($A62>C$5,"",OFFSET(C$54,0,-($A62-1))) | D62: =IF($A62>D$5,"",OFFSET(D$54,0,-($A62-1))) | E62: =IF($A62>E$5,"",OFFSET(E$54,0,-($A62-1))) | F62: =IF($A62>F$5,"",OFFSET(F$54,0,-($A62-1))) | G62: =IF($A62>G$5,"",OFFSET(G$54,0,-($A62-1))) | H62: =IF($A62>H$5,"",OFFSET(H$54,0,-($A62-1))) | I62: =IF($A62>I$5,"",OFFSET(I$54,0,-($A62-1))) -> 0 | ... BI62: =IF($A62>BI$5,"",OFFSET(BI$54,0,-($A62-1))) -> 0
A63: 9 | B63: =IF($A63>B$5,"",OFFSET(B$54,0,-($A63-1))) | C63: =IF($A63>C$5,"",OFFSET(C$54,0,-($A63-1))) | D63: =IF($A63>D$5,"",OFFSET(D$54,0,-($A63-1))) | E63: =IF($A63>E$5,"",OFFSET(E$54,0,-($A63-1))) | F63: =IF($A63>F$5,"",OFFSET(F$54,0,-($A63-1))) | G63: =IF($A63>G$5,"",OFFSET(G$54,0,-($A63-1))) | H63: =IF($A63>H$5,"",OFFSET(H$54,0,-($A63-1))) | I63: =IF($A63>I$5,"",OFFSET(I$54,0,-($A63-1))) | ... BI63: =IF($A63>BI$5,"",OFFSET(BI$54,0,-($A63-1))) -> 0
A64: 10 | B64: =IF($A64>B$5,"",OFFSET(B$54,0,-($A64-1))) | C64: =IF($A64>C$5,"",OFFSET(C$54,0,-($A64-1))) | D64: =IF($A64>D$5,"",OFFSET(D$54,0,-($A64-1))) | E64: =IF($A64>E$5,"",OFFSET(E$54,0,-($A64-1))) | F64: =IF($A64>F$5,"",OFFSET(F$54,0,-($A64-1))) | G64: =IF($A64>G$5,"",OFFSET(G$54,0,-($A64-1))) | H64: =IF($A64>H$5,"",OFFSET(H$54,0,-($A64-1))) | I64: =IF($A64>I$5,"",OFFSET(I$54,0,-($A64-1))) | ... BI64: =IF($A64>BI$5,"",OFFSET(BI$54,0,-($A64-1))) -> 0
A65: 11 | B65: =IF($A65>B$5,"",OFFSET(B$54,0,-($A65-1))) | C65: =IF($A65>C$5,"",OFFSET(C$54,0,-($A65-1))) | D65: =IF($A65>D$5,"",OFFSET(D$54,0,-($A65-1))) | E65: =IF($A65>E$5,"",OFFSET(E$54,0,-($A65-1))) | F65: =IF($A65>F$5,"",OFFSET(F$54,0,-($A65-1))) | G65: =IF($A65>G$5,"",OFFSET(G$54,0,-($A65-1))) | H65: =IF($A65>H$5,"",OFFSET(H$54,0,-($A65-1))) | I65: =IF($A65>I$5,"",OFFSET(I$54,0,-($A65-1))) | ... BI65: =IF($A65>BI$5,"",OFFSET(BI$54,0,-($A65-1))) -> 0
A66: 12 | B66: =IF($A66>B$5,"",OFFSET(B$54,0,-($A66-1))) | C66: =IF($A66>C$5,"",OFFSET(C$54,0,-($A66-1))) | D66: =IF($A66>D$5,"",OFFSET(D$54,0,-($A66-1))) | E66: =IF($A66>E$5,"",OFFSET(E$54,0,-($A66-1))) | F66: =IF($A66>F$5,"",OFFSET(F$54,0,-($A66-1))) | G66: =IF($A66>G$5,"",OFFSET(G$54,0,-($A66-1))) | H66: =IF($A66>H$5,"",OFFSET(H$54,0,-($A66-1))) | I66: =IF($A66>I$5,"",OFFSET(I$54,0,-($A66-1))) | ... BI66: =IF($A66>BI$5,"",OFFSET(BI$54,0,-($A66-1))) -> 0
... A114: 60 | B114: =IF($A114>B$5,"",OFFSET(B$54,0,-($A114-1))) | C114: =IF($A114>C$5,"",OFFSET(C$54,0,-($A114-1))) | D114: =IF($A114>D$5,"",OFFSET(D$54,0,-($A114-1))) | E114: =IF($A114>E$5,"",OFFSET(E$54,0,-($A114-1))) | F114: =IF($A114>F$5,"",OFFSET(F$54,0,-($A114-1))) | G114: =IF($A114>G$5,"",OFFSET(G$54,0,-($A114-1))) | H114: =IF($A114>H$5,"",OFFSET(H$54,0,-($A114-1))) | I114: =IF($A114>I$5,"",OFFSET(I$54,0,-($A114-1))) | ... BI114: =IF($A114>BI$5,"",OFFSET(BI$54,0,-($A114-1))) -> 0

Sheet Sheet1
