Workbook
Name __S1: {"Book1"}
Name __S1: {"Book1"}
Name _a1: {"'Sheet1'!$L$16"}
Name _a1: {"'Sheet1'!$L$16"}
Name _S1: {"Book1"}
Name _S1: {"Book1"}
Name Ă: #REF!
Name Ạ196: #REF!
Name â259: #REF!
Name â312: #REF!
Name Acquisition_PlanA: #REF!
Name Acquisition_PlanB: #REF!
Name Actual: (PeriodInActual*(#REF!>0))*PeriodInPlan
Name ActualBeyond: PeriodInActual*(#REF!>0)
Name adf: #REF!
Name AdvIncQ12020: #REF!
Name AdvIncQ12021: #REF!
Name AdvIncQ12022: #REF!
Name AdvIncQ12023: #REF!
Name AdvIncQ12024: #REF!
Name AdvIncQ22020: #REF!
Name AdvIncQ22021: #REF!
Name AdvIncQ22022: #REF!
Name AdvIncQ22023: #REF!
Name AdvIncQ22024: #REF!
Name AdvIncQ32020: #REF!
Name AdvIncQ32021: #REF!
Name AdvIncQ32022: #REF!
Name AdvIncQ32023: #REF!
Name AdvIncQ32024: #REF!
Name AdvIncQ42020: #REF!
Name AdvIncQ42021: #REF!
Name AdvIncQ42022: #REF!
Name AdvIncQ42023: #REF!
Name AdvIncQ42024: #REF!
Name AdvPenRate2020: #REF!
Name AdvPenRate2021: #REF!
Name AdvPenRate2022: #REF!
Name AdvPenRate2023: #REF!
Name AdvPenRate2024: #REF!
Name AllReportList: #REF!
Name Amount_act: #REF!
Name Amount_CF: #REF!
Name Amount_F: #REF!
Name Amount_KPI_act: #REF!
Name approval: #REF!
Name Attribute_F: #REF!
Name B: #REF!
Name b2bSpr: #REF!
Name BaoHanhSuaChua: #REF!
Name be_KPI_bud: #REF!
Name be2B: #REF!
Name bf: #REF!
Name BieuPhi: #REF!
Name BrMarQ12020: #REF!
Name BrMarQ12021: #REF!
Name BrMarQ12022: #REF!
Name BrMarQ12023: #REF!
Name BrMarQ12024: #REF!
Name BrMarQ22020: #REF!

Sheet Data input
B2: DATE: | C2: 20260121
B3: PIC: | C3: HKN
B5: 1. Approval rate
B7: Approval rate | D7: 0.06642
B8: Issue rate | D8: =16862/23010 -> 0.73281182
B20: 2. Spending
F21: Total | I21: Sum of VND | J21: Column Labels
F22: =GETPIVOTDATA("VND",$I$21)+GETPIVOTDATA("<>VND",$I$37)-GETPIVOTDATA("VND",$I$21,"NAME_OPERATION_SUB_TYPE","On Us Billing") -> 2837771483271 | G22: Loại US billing | I22: Row Labels | J22: ATM | K22: On Us Billing | L22: Purchase ECOM | M22: Purchase POS | N22: Grand Total
C23: %International cash advance | I23: Oct | J23: 47611021040 | L23: 163520074913 | M23: 675071579227 | N23: 886202675180
C24: % Domestics cash advance | D24: =F24/$F$22 -> 0.057421974 | F24: =GETPIVOTDATA("VND",$I$21,"NAME_OPERATION_SUB_TYPE","ATM")+GETPIVOTDATA("<>VND",$I$37,"NAME_OPERATION_SUB_TYPE","ATM") -> 162950439187 | I24: Nov | J24: 54476257011 | L24: 185908871652 | M24: 633793294165 | N24: 874178422828
C25: % Retail spend | D25: =F25/$F$22 -> 0.9288336 | F25: =GETPIVOTDATA("VND",$I$21,"NAME_OPERATION_SUB_TYPE","Purchase ECOM")+GETPIVOTDATA("VND",$I$21,"NAME_OPERATION_SUB_TYPE","Purchase POS") -> 2635817497087 | I25: Dec | J25: 60209091649 | K25: 157982100358 | L25: 177485241597 | M25: 800038435533 | N25: 1195714869137
C26: % International spend | D26: =F26/$F$22 -> 0.013744428 | F26: =GETPIVOTDATA("<>VND",$I$37,"NAME_OPERATION_SUB_TYPE","Purchase ECOM")+GETPIVOTDATA("<>VND",$I$37,"NAME_OPERATION_SUB_TYPE","Purchase POS") -> 39003546997 | I26: Grand Total | J26: 162296369700 | K26: 157982100358 | L26: 526914188162 | M26: 2108903308925 | N26: 2956095967145
I37: Sum of <>VND | J37: Column Labels
I38: Row Labels | J38: ATM | K38: On Us Billing | L38: Purchase ECOM | M38: Purchase POS | N38: Grand Total
I39: Oct | J39: 158181800 | L39: 8771529008 | M39: 602392385 | N39: 9532103193
I40: Nov | J40: 240470987 | L40: 11868537947 | M40: 572935184 | N40: 12681944118
I41: Dec | J41: 255416700 | K41: 0 | L41: 16601224731 | M41: 586927742 | N41: 17443569173
I42: Grand Total | J42: 654069487 | K42: 0 | L42: 37241291686 | M42: 1762255311 | N42: 39657616484
B58: 3. Attrition &Active | I58: Sum of % Active card | J58: Column Labels
I59: Row Labels | J59: 0 | K59: 1 | L59: 2 | M59: 3 | N59: 4 | O59: 5 | P59: 6 | Q59: 7 | R59: 8 | S59: 9 | T59: 10 | U59: 11 | V59: 12 | W59: 13 | X59: 14 | Y59: 15 | Z59: 16 | AA59: 17 | AB59: 18 | AC59: 19 | AD59: 20 | AE59: 21 | AF59: 22 | AG59: 23 | AH59: 24 | AI59: 25 | AJ59: 26 | AK59: 27 | AL59: 28 | AM59: 29 | AN59: 30 | AO59: 31 | AP59: 32 | AQ59: 33 | AR59: 34 | AS59: 35 | AT59: 36 | AU59: 37 | AV59: 38 | AW59: 39 | AX59: 40 | AY59: 41
I60: 44774 | J60: 1 | K60: 1 | L60: 1 | M60: 1 | N60: 1 | O60: 1 | P60: 1 | Q60: 1 | R60: 1 | S60: 1 | T60: 1 | U60: 1 | V60: 1 | W60: 1 | X60: 1 | Y60: 0.97619048 | Z60: 0.96428571 | AA60: 0.96428571 | AB60: 0.96428571 | AC60: 0.96428571 | AD60: 0.95238095 | AE60: 0.95238095 | AF60: 0.94047619 | AG60: 0.94047619 | AH60: 0.94047619 | AI60: 0.94047619 | AJ60: 0.94047619 | AK60: 0.94047619 | AL60: 0.92857143 | AM60: 0.88095238 | AN60: 0.86904762 | AO60: 0.86904762 | AP60: 0.86904762 | AQ60: 0.75 | AR60: 0.67857143 | AS60: 0.67857143 | AT60: 0.67857143 | AU60: 0.6547619 | AV60: 0.64285714 | AW60: 0.64285714 | AX60: 0.64285714 | AY60: 0.63095238
C61: 1 | I61: 44805 | J61: 1 | K61: 1 | L61: 1 | M61: 1 | N61: 1 | O61: 1 | P61: 1 | Q61: 1 | R61: 1 | S61: 1 | T61: 0.99932318 | U61: 0.99864636 | V61: 0.99763113 | W61: 0.99695431 | X61: 0.97563452 | Y61: 0.94077834 | Z61: 0.93637902 | AA61: 0.9319797 | AB61: 0.93028765 | AC61: 0.92724196 | AD61: 0.92318105 | AE61: 0.91708968 | AF61: 0.91336717 | AG61: 0.83553299 | AH61: 0.83147208 | AI61: 0.81725888 | AJ61: 0.8108291 | AK61: 0.79695431 | AL61: 0.74010152 | AM61: 0.69103215 | AN61: 0.65786802 | AO61: 0.6463621 | AP61: 0.64162437 | AQ61: 0.61759729 | AR61: 0.60338409 | AS61: 0.59323181 | AT61: 0.58443316 | AU61: 0.57123519 | AV61: 0.55296108 | AW61: 0.53062606 | AX61: 0.52182741
C62: 0.013 | D62: 0.013 | E62: 0.01 | F62: 0.01 | G62: 0.01 | I62: 44835 | J62: 1 | K62: 1 | L62: 1 | M62: 1 | N62: 1 | O62: 1 | P62: 1 | Q62: 1 | R62: 1 | S62: 0.99899783 | T62: 0.9988308 | U62: 0.99849674 | V62: 0.99816269 | W62: 0.97678303 | X62: 0.94721897 | Y62: 0.94354435 | Z62: 0.93986972 | AA62: 0.9368632 | AB62: 0.93535995 | AC62: 0.93151829 | AD62: 0.92734258 | AE62: 0.92533823 | AF62: 0.78570236 | AG62: 0.78269584 | AH62: 0.76499081 | AI62: 0.75663939 | AJ62: 0.74277601 | AK62: 0.69149825 | AL62: 0.64589945 | AM62: 0.61115751 | AN62: 0.59428762 | AO62: 0.58810757 | AP62: 0.56739602 | AQ62: 0.5590446 | AR62: 0.55052614 | AS62: 0.54217471 | AT62: 0.52998163 | AU62: 0.51895774 | AV62: 0.5064306 | AW62: 0.48972774
C63: 0.02 | D63: 0.018 | E63: 0.017 | F63: 0.015 | G63: 0.015 | I63: 44866 | J63: 1 | K63: 1 | L63: 1 | M63: 1 | N63: 1 | O63: 1 | P63: 1 | Q63: 1 | R63: 0.99926668 | S63: 0.9991852 | T63: 0.99885928 | U63: 0.99845189 | V63: 0.97979304 | W63: 0.95852685 | X63: 0.95486026 | Y63: 0.95160108 | Z63: 0.94915669 | AA63: 0.94769005 | AB63: 0.94443086 | AC63: 0.94198647 | AD63: 0.93962356 | AE63: 0.69306608 | AF63: 0.69176241 | AG63: 0.66666667 | AH63: 0.65884462 | AI63: 0.64189685 | AJ63: 0.60327548 | AK63: 0.56937994 | AL63: 0.5306771 | AM63: 0.51649963 | AN63: 0.5110405 | AO63: 0.49604824 | AP63: 0.48969282 | AQ63: 0.48244113 | AR63: 0.47795975 | AS63: 0.4665526 | AT63: 0.45897499 | AU63: 0.45115294 | AV63: 0.43664956
I64: 44896 | J64: 1 | K64: 1 | L64: 1 | M64: 1 | N64: 1 | O64: 1 | P64: 1 | Q64: 0.9993195 | R64: 0.99846887 | S64: 0.99846887 | T64: 0.99812862 | U64: 0.98213678 | V64: 0.95951004 | W64: 0.95610752 | X64: 0.95423613 | Y64: 0.95219462 | Z64: 0.95049337 | AA64: 0.94709085 | AB64: 0.94334808 | AC64: 0.94113644 | AD64: 0.72303505 | AE64: 0.72167404 | AF64: 0.69037087 | AG64: 0.68084382 | AH64: 0.66212998 | AI64: 0.62861518 | AJ64: 0.59714188 | AK64: 0.55103777 | AL64: 0.53793807 | AM64: 0.53096291 | AN64: 0.51701259 | AO64: 0.50867642 | AP64: 0.49183396 | AQ64: 0.48451854 | AR64: 0.47192923 | AS64: 0.46444369 | AT64: 0.45610752 | AU64: 0.44641034
I65: 44927 | J65: 1 | K65: 1 | L65: 1 | M65: 1 | N65: 1 | O65: 1 | P65: 0.99826255 | Q65: 0.99826255 | R65: 0.99826255 | S65: 0.99787645 | T65: 0.98030888 | U65: 0.95772201 | V65: 0.95444015 | W65: 0.9503861 | X65: 0.9469112 | Y65: 0.9453668 | Z65: 0.94208494 | AA65: 0.93899614 | AB65: 0.93706564 | AC65: 0.74227799 | AD65: 0.74169884 | AE65: 0.70791506 | AF65: 0.6969112 | AG65: 0.67606178 | AH65: 0.64343629 | AI65: 0.61660232 | AJ65: 0.57104247 | AK65: 0.5546332 | AL65: 0.54826255 | AM65: 0.53320463 | AN65: 0.52181467 | AO65: 0.5011583 | AP65: 0.4953668 | AQ65: 0.48127413 | AR65: 0.47451737 | AS65: 0.46679537 | AT65: 0.45849421
I66: 44958 | J66: 1 | K66: 1 | L66: 1 | M66: 1 | N66: 1 | O66: 0.99894375 | P66: 0.99841563 | Q66: 0.99841563 | R66: 0.99841563 | S66: 0.98547663 | T66: 0.96012675 | U66: 0.95405334 | V66: 0.95088461 | W66: 0.94718775 | X66: 0.94454713 | Y66: 0.93926591 | Z66: 0.93372062 | AA66: 0.93108001 | AB66: 0.80380248 | AC66: 0.80195405 | AD66: 0.77766042 | AE66: 0.76841827 | AF66: 0.75125429 | AG66: 0.71296541 | AH66: 0.67995775 | AI66: 0.62978611 | AJ66: 0.61156588 | AK66: 0.60337998 | AL66: 0.5848957 | AM66: 0.57037233 | AN66: 0.54634275 | AO66: 0.53630842 | AP66: 0.52336942 | AQ66: 0.5146554 | AR66: 0.50673356 | AS66: 0.49485081
I67: 44986 | J67: 1 | K67: 1 | L67: 1 | M67: 1 | N67: 0.99955457 | O67: 0.99910913 | P67: 0.99888641 | Q67: 0.99844098 | R67: 0.99175947 | S67: 0.96258352 | T67: 0.95812918 | U67: 0.9518931 | V67: 0.94832962 | W67: 0.94498886 | X67: 0.9376392 | Y67: 0.93385301 | Z67: 0.93006682 | AA67: 0.83340757 | AB67: 0.82939866 | AC67: 0.79265033 | AD67: 0.78708241 | AE67: 0.76302895 | AF67: 0.71893096 | AG67: 0.69109131 | AH67: 0.63719376 | AI67: 0.61915367 | AJ67: 0.61180401 | AK67: 0.59242762 | AL67: 0.5830735 | AM67: 0.55746102 | AN67: 0.54788419 | AO67: 0.53340757 | AP67: 0.52405345 | AQ67: 0.51625835 | AR67: 0.50757238
I68: 45017 | J68: 1 | K68: 1 | L68: 1 | M68: 0.99963912 | N68: 0.99927824 | O68: 0.99855648 | P68: 0.99783472 | Q68: 0.99747384 | R68: 0.96174666 | S68: 0.95705521 | T68: 0.95128113 | U68: 0.9480332 | V68: 0.94370263 | W68: 0.93720678 | X68: 0.93359798 | Y68: 0.93107182 | Z68: 0.84843017 | AA68: 0.84662577 | AB68: 0.81162035 | AC68: 0.80043306 | AD68: 0.7773367 | AE68: 0.73583544 | AF68: 0.70732588 | AG68: 0.64633706 | AH68: 0.62973656 | AI68: 0.62071454 | AJ68: 0.59328762 | AK68: 0.57524359 | AL68: 0.55178636 | AM68: 0.5398773 | AN68: 0.52832912 | AO68: 0.51425478 | AP68: 0.50559365 | AQ68: 0.49224107
I69: 45047 | J69: 1 | K69: 1 | L69: 1 | M69: 1 | N69: 1 | O69: 1 | P69: 0.99955821 | Q69: 0.96929534 | R69: 0.96465651 | S69: 0.95957588 | T69: 0.95515794 | U69: 0.95272808 | V69: 0.94610117 | W69: 0.94035785 | X69: 0.9368235 | Y69: 0.89860835 | Z69: 0.89374862 | AA69: 0.83543185 | AB69: 0.8182019 | AC69: 0.79412414 | AD69: 0.74906119 | AE69: 0.71636846 | AF69: 0.66379501 | AG69: 0.64126353 | AH69: 0.63419483 | AI69: 0.61011708 | AJ69: 0.5946543 | AK69: 0.57079744 | AL69: 0.55864811 | AM69: 0.54163905 | AN69: 0.5314778 | AO69: 0.52264193 | AP69: 0.51137619
I70: 45078 | J70: 1 | K70: 1 | L70: 1 | M70: 1 | N70: 1 | O70: 0.99807591 | P70: 0.97551163 | Q70: 0.97008921 | R70: 0.9648417 | S70: 0.96081861 | T70: 0.95871961 | U70: 0.95294735 | V70: 0.94630051 | W70: 0.94175267 | X70: 0.91743922 | Y70: 0.91446563 | Z70: 0.86548889 | AA70: 0.85114571 | AB70: 0.82158475 | AC70: 0.77033409 | AD70: 0.73535071 | AE70: 0.68392514 | AF70: 0.66363477 | AG70: 0.6566381 | AH70: 0.63127514 | AI70: 0.61938079 | AJ70: 0.59594193 | AK70: 0.57827532 | AL70: 0.55920938 | AM70: 0.54748994 | AN70: 0.53647018 | AO70: 0.52475074
I71: 45108 | J71: 1 | K71: 1 | L71: 1 | M71: 0.99937441 | N71: 0.99843603 | O71: 0.98091961 | P71: 0.9766969 | Q71: 0.97153581 | R71: 0.9677823 | S71: 0.96621833 | T71: 0.9583985 | U71: 0.9535502 | V71: 0.95042227 | W71: 0.9307163 | X71: 0.9257116 | Y71: 0.89881139 | Z71: 0.8705036 | AA71: 0.83468877 | AB71: 0.78589302 | AC71: 0.74569909 | AD71: 0.69080388 | AE71: 0.67328746 | AF71: 0.6665624 | AG71: 0.63950579 | AH71: 0.63027839 | AI71: 0.61307476 | AJ71: 0.59493275 | AK71: 0.56803253 | AL71: 0.55317485 | AM71: 0.54285267 | AN71: 0.52815139
I72: 45139 | J72: 1 | K72: 1 | L72: 1 | M72: 0.99979335 | N72: 0.98388097 | O72: 0.97933457 | P72: 0.97354825 | Q72: 0.96817524 | R72: 0.9661087 | S72: 0.96094234 | T72: 0.9561893 | U72: 0.95288283 | V72: 0.93655714 | W72: 0.93139078 | X72: 0.92085142 | Y72: 0.90659227 | Z72: 0.86278157 | AA72: 0.81773094 | AB72: 0.78280636 | AC72: 0.72039678 | AD72: 0.6972515 | AE72: 0.68629882 | AF72: 0.66191362 | AG72: 0.64951436 | AH72: 0.63752841 | AI72: 0.62182269 | AJ72: 0.58751808 | AK72: 0.56519942 | AL72: 0.5494937 | AM72: 0.53647448
I73: 45170 | J73: 1 | K73: 1 | L73: 1 | M73: 0.99114353 | N73: 0.98619432 | O73: 0.97916124 | P73: 0.97447252 | Q73: 0.97212816 | R73: 0.96613701 | S73: 0.96275072 | T73: 0.95884345 | U73: 0.94946601 | V73: 0.94399583 | W73: 0.932795 | X73: 0.92914822 | Y73: 0.89163845 | Z73: 0.84579318 | AA73: 0.80854389 | AB73: 0.73482678 | AC73: 0.71190414 | AD73: 0.69992185 | AE73: 0.67283147 | AF73: 0.6621516 | AG73: 0.64990883 | AH73: 0.63948945 | AI73: 0.61891117 | AJ73: 0.5949466 | AK73: 0.57098203 | AL73: 0.55405053
I74: 45200 | J74: 1 | K74: 1 | L74: 0.9971223 | M74: 0.98581706 | N74: 0.97410072 | O74: 0.96361768 | P74: 0.95662898 | Q74: 0.94964029 | R74: 0.94265159 | S74: 0.9385406 | T74: 0.92887975 | U74: 0.92250771 | V74: 0.90935252 | W74: 0.90071942 | X74: 0.87687564 | Y74: 0.83843782 | Z74: 0.79177801 | AA74: 0.71181912 | AB74: 0.69516958 | AC74: 0.68591984 | AD74: 0.65734841 | AE74: 0.64892086 | AF74: 0.63782117 | AG74: 0.62651593 | AH74: 0.6049332 | AI74: 0.58890031 | AJ74: 0.56443988 | AK74: 0.54059609
I75: 45231 | J75: 1 | K75: 1 | L75: 0.99750872 | M75: 0.98181365 | N75: 0.96138515 | O75: 0.9529148 | P75: 0.93796712 | Q75: 0.92700548 | R75: 0.92127554 | S75: 0.91155954 | T75: 0.90607872 | U75: 0.89486796 | V75: 0.88863976 | W75: 0.87668161 | X75: 0.84155456 | Y75: 0.79870453 | Z75: 0.70976582 | AA75: 0.68809168 | AB75: 0.68011958 | AC75: 0.65470852 | AD75: 0.64125561 | AE75: 0.62730443 | AF75: 0.61484803 | AG75: 0.59566517 | AH75: 0.58121574 | AI75: 0.56601893 | AJ75: 0.53936223
I76: 45261 | J76: 0.99973205 | K76: 0.99973205 | L76: 0.99732047 | M76: 0.98606645 | N76: 0.97642015 | O76: 0.96436227 | P76: 0.95819936 | Q76: 0.95230439 | R76: 0.9482851 | S76: 0.94185423 | T76: 0.93569132 | U76: 0.92845659 | V76: 0.91666667 | W76: 0.89576635 | X76: 0.87057878 | Y76: 0.79930332 | Z76: 0.78054662 | AA76: 0.77009646 | AB76: 0.74732047 | AC76: 0.73633441 | AD76: 0.71543408 | AE76: 0.69506967 | AF76: 0.67202572 | AG76: 0.65541265 | AH76: 0.63987138 | AI76: 0.61682744
I77: 45292 | J77: 1 | K77: 1 | L77: 0.99615855 | M77: 0.98952331 | N77: 0.97520517 | O77: 0.96560154 | P77: 0.9573948 | Q77: 0.95180723 | R77: 0.94726733 | S77: 0.94098132 | T77: 0.93626681 | U77: 0.92683779 | V77: 0.90326523 | W77: 0.89418544 | X77: 0.81089576 | Y77: 0.78610093 | Z77: 0.77649729 | AA77: 0.7553693 | AB77: 0.744718 | AC77: 0.72655841 | AD77: 0.71189104 | AE77: 0.6884931 | AF77: 0.67190501 | AG77: 0.65793609 | AH77: 0.63872883
I78: 45323 | J78: 1 | K78: 1 | L78: 0.99722553 | M78: 0.98711851 | N78: 0.97661514 | O78: 0.96868807 | P78: 0.96353547 | Q78: 0.95897741 | R78: 0.95402299 | S78: 0.94986128 | T78: 0.94252874 | U78: 0.924891 | V78: 0.91478399 | W78: 0.81906461 | X78: 0.7849782 | Y78: 0.77011494 | Z78: 0.74098296 | AA78: 0.73087594 | AB78: 0.70630202 | AC78: 0.6876734 | AD78: 0.6595323 | AE78: 0.64466904 | AF78: 0.63040032 | AG78: 0.6169243
I79: 45352 | J79: 1 | K79: 1 | L79: 0.9954 | M79: 0.9858 | N79: 0.9732 | O79: 0.9664 | P79: 0.9618 | Q79: 0.9562 | R79: 0.952 | S79: 0.9468 | T79: 0.9212 | U79: 0.9084 | V79: 0.8386 | W79: 0.8092 | X79: 0.7928 | Y79: 0.756 | Z79: 0.7426 | AA79: 0.7196 | AB79: 0.7008 | AC79: 0.6728 | AD79: 0.652 | AE79: 0.6384 | AF79: 0.615
I80: 45383 | J80: 1 | K80: 1 | L80: 0.99762357 | M80: 0.98502852 | N80: 0.97148289 | O80: 0.96031369 | P80: 0.95389734 | Q80: 0.94914449 | R80: 0.94106464 | S80: 0.92514259 | T80: 0.9151616 | U80: 0.86074144 | V80: 0.82984791 | W80: 0.81273764 | X80: 0.7773289 | Y80: 0.7628327 | Z80: 0.73764259 | AA80: 0.71815589 | AB80: 0.68987643 | AC80: 0.66825095 | AD80: 0.6506654 | AE80: 0.63403042
I81: 45413 | J81: 1 | K81: 0.99979773 | L81: 0.99737055 | M81: 0.98665049 | N81: 0.97107605 | O81: 0.96136731 | P81: 0.95368123 | Q81: 0.94902913 | R81: 0.93385922 | S81: 0.92374595 | T81: 0.88592233 | U81: 0.85133495 | V81: 0.8329288 | W81: 0.7973301 | X81: 0.77872168 | Y81: 0.7447411 | Z81: 0.72350324 | AA81: 0.69680421 | AB81: 0.67860032 | AC81: 0.66201456 | AD81: 0.64401294
I82: 45444 | J82: 1 | K82: 1 | L82: 0.99854174 | M82: 0.98833394 | N82: 0.97776157 | O82: 0.96937659 | P82: 0.96190303 | Q82: 0.94567991 | R82: 0.93711265 | S82: 0.92307692 | T82: 0.88497995 | U82: 0.86347065 | V82: 0.82136347 | W82: 0.80185928 | X82: 0.77014218 | Y82: 0.7484506 | Z82: 0.71563981 | AA82: 0.69558877 | AB82: 0.67663143 | AC82: 0.65020051
I83: 45474 | J83: 1 | K83: 1 | L83: 0.99732576 | M83: 0.99264583 | N83: 0.97927461 | O83: 0.96673909 | P83: 0.9555407 | Q83: 0.94718369 | R83: 0.93999666 | S83: 0.91492562 | T83: 0.88935317 | U83: 0.84823667 | V83: 0.83369547 | W83: 0.80461307 | X83: 0.77436069 | Y83: 0.73157279 | Z83: 0.71051312 | AA83: 0.69413338 | AB83: 0.67073375
I84: 45505 | J84: 1 | K84: 1 | L84: 0.99713015 | M84: 0.99124695 | N84: 0.97718467 | O84: 0.96226144 | P84: 0.95523031 | Q84: 0.94604678 | R84: 0.93557182 | S84: 0.89740278 | T84: 0.85363754 | U84: 0.83871431 | V84: 0.8078634 | W84: 0.77988234 | X84: 0.728225 | Y84: 0.69407376 | Z84: 0.67541972 | AA84: 0.65188693
I85: 45536 | J85: 1 | K85: 1 | L85: 0.99750035 | M85: 0.98861269 | N85: 0.96458825 | O85: 0.95528399 | P85: 0.94584086 | Q85: 0.93931398 | R85: 0.93570337 | S85: 0.90556867 | T85: 0.89057075 | U85: 0.84918761 | V85: 0.82085821 | W85: 0.76683794 | X85: 0.72601028 | Y85: 0.68962644 | Z85: 0.65824191
I86: 45566 | J86: 1 | K86: 0.99906682 | L86: 0.99682717 | M86: 0.9837626 | N86: 0.97237775 | O86: 0.96509892 | P86: 0.95744681 | Q86: 0.95726017 | R86: 0.93934304 | S86: 0.92683837 | T86: 0.90369541 | U86: 0.87513998 | V86: 0.81261665 | W86: 0.77902202 | X86: 0.7474804 | Y86: 0.70772676
I87: 45597 | J87: 1 | K87: 1 | L87: 0.99254545 | M87: 0.97872727 | N87: 0.97054545 | O87: 0.96472727 | P87: 0.96472727 | Q87: 0.95145455 | R87: 0.946 | S87: 0.93690909 | T87: 0.90763636 | U87: 0.84272727 | V87: 0.80909091 | W87: 0.77236364 | X87: 0.73381818
I88: 45627 | J88: 1 | K88: 0.9964121 | L88: 0.99265334 | M88: 0.97847258 | N88: 0.9697591 | O88: 0.9697591 | P88: 0.95745771 | Q88: 0.95130702 | R88: 0.94823168 | S88: 0.92807107 | T88: 0.87732787 | U88: 0.84366991 | V88: 0.81530839 | W88: 0.77191184
I89: 45658 | J89: 1 | K89: 0.99665896 | L89: 0.98997687 | M89: 0.97815472 | N89: 0.97815472 | O89: 0.96350553 | P89: 0.95913647 | Q89: 0.95682344 | R89: 0.95065536 | S89: 0.92829607 | T89: 0.89925469 | U89: 0.87458237 | V89: 0.83988692
I90: 45689 | J90: 1 | K90: 0.99548969 | L90: 0.99001289 | M90: 0.99001289 | N90: 0.96939433 | O90: 0.9632732 | P90: 0.96166237 | Q90: 0.95876289 | R90: 0.95070876 | S90: 0.92847938 | T90: 0.90141753 | U90: 0.85889175
I91: 45717 | J91: 1 | K91: 0.99569777 | L91: 0.99569777 | M91: 0.9744555 | N91: 0.96638881 | O91: 0.96020436 | P91: 0.95778435 | Q91: 0.95321323 | R91: 0.93815542 | S91: 0.91718204 | T91: 0.87846195
I92: 45748 | J92: 1 | K92: 1 | L92: 0.98011364 | M92: 0.97130682 | N92: 0.96534091 | O92: 0.96022727 | P92: 0.95738636 | Q92: 0.95170455 | R92: 0.93778409 | S92: 0.90056818
I93: 45778 | J93: 1 | K93: 0.97905157 | L93: 0.9732965 | M93: 0.96546961 | N93: 0.95971455 | O93: 0.9558011 | P93: 0.95165746 | Q93: 0.94705341 | R93: 0.91804788
I94: 45809 | J94: 1 | K94: 0.99471408 | L94: 0.98510332 | M94: 0.97885632 | N94: 0.97236905 | O94: 0.97068717 | P94: 0.96660259 | Q94: 0.95555022
I95: 45839 | J95: 1 | K95: 0.99675926 | L95: 0.99259259 | M95: 0.98587963 | N95: 0.98171296 | O95: 0.9775463 | P95: 0.97268519
I96: 45870 | J96: 1 | K96: 0.9962273 | L96: 0.98891771 | M96: 0.98302287 | N96: 0.97877859 | O96: 0.97429851
I97: 45901 | J97: 1 | K97: 0.9941071 | L97: 0.98923905 | M97: 0.9825775 | N97: 0.97950295
I98: 45931 | J98: 1 | K98: 0.99475479 | L98: 0.98924731 | M98: 0.98478888
I99: 45962 | J99: 1 | K99: 0.996337 | L99: 0.99296703
I100: 45992 | J100: 1 | K100: 0.99566365
B104: 4.Revolving, repayment, , cashback, Interchange, processing fee
C105: 1 | D105: 2 | E105: =D105+1 -> 3 | F105: =E105+1 -> 4 | G105: =F105+1 -> 5 | H105: =G105+1 -> 6 | I105: =H105+1 -> 7 | J105: =I105+1 -> 8 | K105: =J105+1 -> 9 | L105: =K105+1 -> 10 | M105: 11 | N105: 12
B106: Prin total | J106: 1222872741673 | K106: 1288685931838 | L106: 1345398043554 | M106: 1462788996458 | N106: 1526717218023
B107: Install | J107: 21186017880 | K107: 48354775378 | L107: 61740516592 | M107: 70303201476 | N107: 85836911740
B108: Non-install | J108: =J106-J107 -> 1201686723793 | K108: =K106-K107 -> 1240331156460 | L108: =L106-L107 -> 1283657526962 | M108: =M106-M107 -> 1392485794982 | N108: =N106-N107 -> 1440880306283
B109: WO | J109: 15033746671 | K109: 33321186914 | L109: 20628642237 | M109: 19386940783 | N109: 30572034864
B112: Revol | K112: 6.4432298e+11 | L112: 6.6651207e+11 | M112: 6.9459678e+11 | N112: 7.0856535e+11
B113: Spending | K113: 696409205338 | L113: 8.5015952e+11 | M113: =L113 -> 8.5015952e+11 | N113: =M113 -> 8.5015952e+11
B114: Spending (settle)
B117: Repayment | L117: =K106+L113-L106-L109 -> 772818769138 | M117: =L106+M113-M106-M109 -> 713381629404 | N117: =M106+N113-N106-N109 -> 755659266662
B119: Activate Acc | K119: 128255 | L119: 128906 | M119: 132781 | N119: 134124
B120: Active acc | K120: 70137 | L120: 70390 | M120: 73388 | N120: 76116
L122: =AVERAGE(K112:L112)/AVERAGE(J108:K108) -> 0.53678356 | M122: =AVERAGE(L112:M112)/AVERAGE(K108:L108) -> 0.539269 | N122: =AVERAGE(M112:N112)/AVERAGE(L108:M108) -> 0.52432249
L123: =L117/AVERAGE(J108:K108) -> 0.63293457 | M123: =M117/AVERAGE(K108:L108) -> 0.56528116 | N123: =N117/AVERAGE(L108:M108) -> 0.56473752
L124: =L113/L119 -> 6595189.7 | M124: =M113/M119 -> 6402719.7 | N124: =N113/N119 -> 6338608.5 | P124: (loại on us billing)
B127: % Revol | C127: =AVERAGE(L122:N122) -> 0.53345835
B128: % repayment | C128: =AVERAGE(L123:N123) -> 0.58765108
B129: spending | C129: =(SUM(C113:N113)-GETPIVOTDATA("VND",$I$21,"NAME_OPERATION_SUB_TYPE","On Us Billing"))/SUM(C119:N119)/10^6 -> 5.8941158
B131: Interchange | L131: 4383607738 | M131: 3850695292 | N131: 4977336255
B132: Cashback | L132: 3208606111 | M132: 3065811450 | N132: 3162856046
B133: Process-pbc | L133: 342277000 | M133: 1.3856184e+08 | N133: 0
B134: process -visa | L134: =126593966+953148800+1179969 -> 1080922735 | M134: =136733637+1283517146+1534237 -> 1421785020 | N134: =219891249+1300000000 -> 1519891249
B136: Interchange | C136: =SUM(L131:N131)/SUM(L113:N113) -> 0.0051800628
B137: Cashback | C137: =SUM(L132:N132)/SUM(L113:N113) -> 0.0037001972
B138: Process | C138: =SUM(L134:N134)/SUM(L113:N113) -> 0.0015771938
B143: 5. Installment | G143: Sum of DDP amount | H143: Column Labels
G144: Row Labels | H144: 3 | I144: 6 | J144: 9 | K144: 12 | L144: Grand Total
B145: Average tenor | C145: =ROUND(SUMPRODUCT(H155:K155,H156:K156)/SUM(H156:K156),0) -> 9 | G145: Oct | H145: 5296291248 | I145: 7289442346 | J145: 2948473200 | K145: 20739227629 | L145: 36273434423
B146: Average upfront | C146: =SUMPRODUCT(H157:K157,H156:K156)/SUM(H156:K156) -> 0.058932557 | G146: Nov | H146: 3831112043 | I146: 6342703808 | J146: 2397417483 | K146: 18252001122 | L146: 30823234456
B147: Penetration | C147: =GETPIVOTDATA("DDP amount",$G$143)/SUM(L113:N113) -> 0.044248208 | G147: Dec | H147: 5336175998 | I147: 9730016695 | J147: 4113851871 | K147: 26577393370 | L147: 45757437934
G148: Grand Total | H148: 14463579289 | I148: 23362162849 | J148: 9459742554 | K148: 65568622121 | L148: 112854106813
H155: 3 | I155: 6 | J155: 9 | K155: 12
G156: amount | H156: 14463579289 | I156: 23362162849 | J156: 9459742554 | K156: 65568622121
G157: Fee | H157: 0.0199 | I157: 0.0499 | J157: 0.0649 | K157: 0.0699
B160: 6. Cost
C163: 1 | D163: 2 | E163: =D163+1 -> 3 | F163: =E163+1 -> 4 | G163: =F163+1 -> 5 | H163: =G163+1 -> 6 | I163: =H163+1 -> 7 | J163: =I163+1 -> 8 | K163: =J163+1 -> 9 | L163: =K163+1 -> 10 | M163: 11 | N163: 12
B164: New acc | L164: 3813 | M164: 6824 | N164: 5303
B165: Activated acc | K165: =K119 -> 128255 | L165: =L119 -> 128906 | M165: =M119 -> 132781 | N165: =N119 -> 134124
B168: UW | L168: 6.283449e+08 | M168: 680208404 | N168: 624583086
...

Sheet NOTE
A1: SAP MODEL - CREDIT CARD
N2: KHN | O2: v9 | P2: 20251101
B3: 1. Notes and disclaimer
C4: a. Giới thiệu về SAP
D5: - SAP: Single Account Profitability (Hiệu quả sản phẩm trên từng đơn vị sản phẩm)
D6: - Model SAP được sử dụng như 1 mô hình dự đoán hiệu quả vòng đời của sản phẩm.
D7: - Do sự phức tạp của sản phẩm, các hệ thống vận hành (hệ thống hạch kế toán, hệ thống quản trị rủi ro, hệ thống quản trị…), hành vi người sử dụng hành vi người sử dụng, model chỉ có thể mô phỏng tương đối trung bình vòng đời của sản phẩm.
D8: - Mô hình được tính toán dựa vào các yếu tố đầu vào xác định tại thời điểm, do đó kết quả của mô hình có thể có sự khác biệt so với thực tế vận hành sản phẩm.
D9: - Mô hình SAP Credit Card này được tính trên hiệu quả của 1 thẻ mở và được cutoff tại thời điểm 5 năm ( 60 tháng) kể từ ngày bắt đầu sản phẩm. Trường hợp sử dụng phương pháp tính dự phòng VAS, cần ghi nhận thêm chi phí dự phòng năm thứ 6 liên quan tới hiệu quả sản phẩm thẻ 5 năm.
C11: b. Giới thiệu về PnL
D12: - Trong file tính này, Profit & Lost (PnL) được dự phóng từ trung bình cộng kết quả kinh doanh trên từng sản phẩm (SAP) với yếu tố "sale plan" (số thẻ mở mới) qua từng tháng, do đó có thể khác biệt so với kết quả thực tế vận hành.
D13: - Dòng tiền thực tế qua từng tháng có thể khác biệt với mô hình tính toán do nhiều yếu tố tác động bên ngoài thay đổi, do đó, vui lòng chỉ sử dụng mô hình cho mục đích tham khảo.
D14: - Cho mục đích tính dự phòng dòng tiền ngắn và trung hạn, mô hình PnL được cutoff tại thời điểm 5 năm (60 tháng) kể từ ngày bắt đầu thẻ đầu tiên được mở.
B16: 2. Instruction
D17: - Cấu trúc file:
D18: NOTE | E18: Cung cấp các thông tin về file tính, lưu ý, định nghĩa sử dụng,…
D19: SAP_Leadsheet | E19: Các chỉ số và kết quả model SAP
D20: SAP_Speadsheet | E20: Các công thức tính SAP
D21: Sales plan & PL | E21: Số lượng thẻ mở và kết quả dự kiến
D22: PL projection speadsheet | E22: Các công thức tính PL
D24: - Dành cho người sử dụng
E25: - Chỉ chỉnh sửa vào các ô màu vàng
E26: - 2 sheets "SAP_Leadsheet" và "Sale plan&PL" cung cấp yếu tố đầu vào và đầu ra để tính toán mô hình SAP cũng như PnL.
F27: - Sheet SAP_Leadsheet được cấu trúc 2 phần, bên trái là các yếu tố đầu vào (input) và bên phải là kết quả dự đoán (output). Đơn vị sử dụng tại bảng tính là triệu VND (mVND) và phần trăm (%)
F28: - Sheet "Sale plan & PL" được cấu trúc 2 phần, bên trên là sale plan và bên dưới là kết quả PnL
E29: - 2 sheets "SAP_Spreadsheet" và "PL projection speadsheet" là các file tính toán cho 2 sheet "SAP_Leadsheet", "Sales plan & PL"
F30: - 2 sheets được cấu trúc từ trên xuống dưới theo thứ tự tính toán mô phỏng để đưa ra kết quả kinh doanh cuối cùng
F31: - 2 sheets đã được tạm khóa. Trường hợp cần mở khóa, điều chỉnh các yếu tố, vui lòng liên hệ với nhóm vận hành để được hỗ trợ.
D33: - Dành riêng cho người vận hành, hiệu chỉnh
E34: - Cần cẩn trọng khi điều chỉnh ở các file "speadsheet" vì 1 khi sai lệch rất khó tìm ra lỗi (VD: sửa nhầm ô, link nhầm vị trí,…)
B37: 3. Legend
C39: REVENUE INPUT
C41: Card Status
D42: %Activation rate | E42: Tỉ lệ activate thẻ | G42: Lấy activated rate tại tháng 1
D43: Normal attrition rate (others)/cohort | E43: Trung bình tỉ lệ rời bỏ thẻ | G43: Lấy trung bình tỉ lệ rời bỏ thẻ của các tháng (tính theo cohort)
D44: Seasonal attrition rate (month12-24,36,…)/cohort | E44: Tỉ lệ rời bỏ thẻ của các tháng đặc biệt (VD các tháng cuối năm) | G44: Lấy trung bình tỉ lệ rời bỏ thẻ của các tháng (tính theo cohort)
C46: Usage Status
D47: %International cash advance | E47: Tỉ lệ rút tiền mặt quốc tế/ tổng chi tiêu
D48: % Domestics cash advance | E48: Tỉ lệ rút tiền mặt nội địa/ tổng chi tiêu
D49: % Retail spend | E49: Tỉ lệ thanh toán nội địa qua pos,online/tổng chi tiêu
D50: % International spend | E50: Tỉ lệ thanh toán quốc tế qua pos,online/tổng chi tiêu
D51: Spd / activated card | E51: Tổng chi tiêu tiêu tháng/số thẻ activated
C52: Payment status
D53: Minimal Payment
D54: Due date | E54: Ngày tới hạn thanh toán trong tháng, vd ngày 5, ngày 10 hàng tháng
D56: Free-interest period | E56: Thời gian được miễn lãi (VD 45-55 ngày)
D57: Port Revolving rate | E57: Tỉ lệ chuyển đổi dư nợ (được tính là %/ANR tháng trước (exl WO, EMI))
D58: Repayment rate | E58: Tỉ lệ thanh toán dư nợ (được tính %/ANR tháng trước (exl WO, EMI))
C59: Pricing
D60: CII rate | E60: Chi phí lãi vay (annually) | G60: Lấy trung bình tỉ lãi của rút tiền và chi tiêu
D61: COF rate | E61: Chi phí vốn (annually) | G61: Lấy theo BRD
C62: Customer fee
D63: Annual fee | E63: Phí thường niên | G63: Lấy trung bình tỉ lệ các thẻ
D64: Annual Fee waiver | E64: Tỉ lệ miễn phí thường niên (trừ năm 1)
D65: Quarterly fee | E65: Phí hàng quý
D66: Quarterly Fee waiver | E66: Tỉ lệ được miễn phí hàng quý
D67: Monthly fee | E67: Phí hàng tháng (subcription fee,…)
D68: Monthly Fee waiver | E68: Tỉ lệ miễn phí hàng tháng
D69: Issuance fee | E69: Phí mở thẻ vật lý mới
D70: Termination fee | E70: Phí đóng thẻ | G70: Trong trường hợp đóng thẻ trong vòng 1 năm sẽ bị thu phí đóng thẻ
D71: Late payment rate | E71: Phí chậm trả
D72: %Latepayment collected | E72: Tỉ lệ thu hồi chậm trả
D73: Cash advance | E73: Phí rút tiền mặt
D74: Currency conversion (FX rate) | E74: Phí chuyển đổi ngoại tệ
C76: Customer rewards
D77: Cashback | E77: Tỉ lệ cashback (per spending) | G77: Lấy trung bình 6 tháng
C79: Vendor fee
D80: Interchange | E80: Doanh thu interchange (per spending) | G80: Lấy trung bình 6 tháng
D81: Processing fee (VISA) | E81: Chi phí processing
D82: Support processing cost (VISA) | E82: Hoàn phí processing fee của VISA | G82: VISA hoàn phí cho 5 năm đầu tiên hoạt động bắt đầu 8/2022, (2022-2023- tính 100%, năm 2024- tính 75%, 2025-2027-tính 50%, các năm sau đó không được hoàn)
D83: Vendor servicing cost(PBC) | E83: Phí PBC
C85: EMI
D86: EMI Penetration | E86: Tỉ lệ chuyển đổi trả góp/spending trong tháng
D87: Average tenor | E87: Thời hạn chuyển đổi trung bình
D88: Initial fee | E88: Phí trả góp hàng tháng/số dư ban đầu
D89: Upfront fee | E89: Phí chuyển đổi trả góp, trả 1 lần tại thời điểm ban đầu
D90: Early repayment penalty | E90: Phí tất toán trước hạn
D91: % Early repayment | E91: Tỉ lệ tất toán trước hạn của sản phẩm trả góp
C95: COST INPUT
C96: Inflation rate | E96: Tỉ lệ dự kiến tăng chi phí qua các năm
C98: Sales & Marketing
D99: Lead acquisition | E99: Chi phí leadgen trả cho đối tác
D100: Sharing TOI only | E100: Chi phí chia sẻ doanh thu chi phí cho đối tá
D101: Sharing TOI+RISKDPD90+ | E101: Chi phí chia sẻ doanh thu chi phí cho đối tá
D102: Sharing TOI+RISKDPD180+ | E102: Chi phí chia sẻ doanh thu chi phí cho đối tá
D103: Marketing acquisition | E103: Chi phí marketing cho thẻ mở
C105: Marketing promotion
D106: Marketing promotion | E106: Chi phí promotion hàng tháng cho thẻ hoạt động
D107: Marketing promotion | E107: Chi phí promotion/số chi tiêu
C109: UW & Disbursal cost
D110: Underwriting cost | E110: Chi phí underwriting cost/thẻ mở | G110: Chi phí bao gồm (PBC, KLP, CIC,…)
D111: DOP cost | E111: Chi phí luồng DOP | G111: Bao gồm SMS,…
D112: Approval rate | E112: Tỉ lệ chấp thuận mở thẻ | G112: Tỉ lệ số thẻ được chấp thuận/số thẻ vào luồng LOS
D113: Opening rate | E113: Tỉ lệ mở thẻ | G113: Tỉ lệ số thẻ mở /số thẻ được chấp thuận mở
D114: Opening cost | E114: Chi phí mở thẻ | G114: Bao gồm các chi phí hợp đồng, SMS khi mở thẻ
D115: Credit Support | E115: Chi phí khác( hiện tại chưa có)
C117: Physical card | E117: Chi phí mở thẻ vật lý (chi phí phôi, in ấn, EMS, chi phí khấu hao in ấn…)
D118: Physical & Virtual Card | E118: Tỉ lệ thẻ ảo và thẻ vật lý
D119: %Physical Card | E119: Thẻ vật lý
D120: %Virtual Card | E120: Tỉ lệ thẻ ảo (không phát hành thẻ vật lý)
...

Sheet SAP_Leadsheet
B1: SAP MODEL - CREDIT CARD
B2: Leadsheet | C2: =NOTE!O2 -> v9
B3: KHN | C3: =NOTE!P2 -> 20251101
B5: Select model type | G5: NOTE
B6: Write off | C6: DPD180+ | D6: không dùng DPD180 với IFRS | G6: Please read carefully before using model
B7: Provision | C7: IFRS | H7: Disclaimer
B8: Card type | C8: ALL | H8: Instruction
B9: Chanel | C9: ALL | H9: Legend
B10: EMI mode | C10: EMI
B11: Customer type | C11: All | D11: Chưa test xong hiệu quả, ko nên đổi ô này
B12: Quarter | C12: 2025
B14: REVENUE INPUT | K14: Cur: mVND, % | M14: SUMMARY OUTPUT | W14: Cur: mVND, %
O15: Lifetime 5 Years | P15: Year 1 | Q15: Year 2 | R15: Year 3 | S15: Year 4 | T15: Year 5 | U15: =IF(C7="VAS","Year 6","") | V15: % of ANR 5Y | W15: % Spending
E16: Year 1 | F16: Year 2 | G16: Year 3 | H16: Year 4 | I16: Year 5
M17: ANR | O17: =O46 -> 6.3975595 | P17: =P46 -> 9.1247955 | Q17: =Q46 -> 8.0077877 | R17: =R46 -> 6.3347125 | S17: =S46 -> 4.9761104 | T17: =T46 -> 3.5443913 | U17: =U46 -> 0
B18: Card Status | C18: %Activation rate | E18: 0.99 | M18: Spending | O18: =O47 -> 210.77358 | P18: =P47 -> 63.962944 | Q18: =Q47 -> 51.496889 | R18: =R47 -> 40.698869 | S18: =S47 -> 31.728025 | T18: =T47 -> 22.886852
C19: Normal attrition rate (others)/cohort | E19: 0.013 | F19: 0.014 | G19: 0.01 | H19: 0.01 | I19: 0.01 | M19: TOI | O19: =O48 -> 6.5739424 | P19: =P48 -> 1.973176 | Q19: =Q48 -> 1.5624843 | R19: =R48 -> 1.2501523 | S19: =S48 -> 1.0225009 | T19: =T48 -> 0.76562904 | U19: =U48 -> 0 | V19: =O19/$O$46/60*12 -> 0.20551407 | W19: =O19/$O$18 -> 0.031189594
C20: Seasonal attrition rate (month12-24,36,…)/cohort | E20: 0.027 | F20: 0.025 | G20: 0.017 | H20: 0.015 | I20: 0.015 | M20: Net interest income | O20: =O49 -> 3.951425 | P20: =P49 -> 1.0539614 | Q20: =Q49 -> 0.96121531 | R20: =R49 -> 0.77487769 | S20: =S49 -> 0.64377475 | T20: =T49 -> 0.5175958 | U20: =U49 -> 0 | V20: =V49 -> 0.12352914 | W20: =W49 -> 0.01874725
M21: Net fee income | O21: =O52 -> 2.6225175 | P21: =P52 -> 0.91921454 | Q21: =Q52 -> 0.60126894 | R21: =R52 -> 0.47527458 | S21: =S52 -> 0.37872615 | T21: =T52 -> 0.24803324 | U21: =U52 -> 0 | V21: =V52 -> 0.081984934 | W21: =W52 -> 0.012442344
B22: Usage Status | C22: %International cash advance | E22: 0 | M22: Other income | O22: =O70 -> 0 | P22: =P70 -> 0 | Q22: =Q70 -> 0 | R22: =R70 -> 0 | S22: =S70 -> 0 | T22: =T70 -> 0 | U22: =U70 -> 0 | V22: =O22/$O$46/60*12 -> 0 | W22: =O22/$O$18 -> 0
C23: % Domestics cash advance | E23: 0.033 | M23: Provision cost | O23: =O71 -> -4.5992838 | P23: =P71 -> -1.6341193 | Q23: =Q71 -> -1.2327601 | R23: =R71 -> -0.91091959 | S23: =S71 -> -0.53588578 | T23: =T71 -> -0.28559898 | U23: =U71 -> 0 | V23: =O23/$O$46/60*12 -> -0.14378245 | W23: =O23/$O$18 -> -0.021820969
C24: % Retail spend | E24: =1-E23-E25 -> 0.917 | M24: Variable Cost | O24: =SUM(O25:O30) -> -0.81265577 | P24: =SUM(P25:P30) -> -0.54600186 | Q24: =SUM(Q25:Q30) -> -0.093267733 | R24: =SUM(R25:R30) -> -0.073877427 | S24: =SUM(S25:S30) -> -0.05774102 | T24: =SUM(T25:T30) -> -0.041767733 | U24: =SUM(U25:U30) -> 0 | V24: =SUM(V25:V30) -> -0.025405181 | W24: =SUM(W25:W30) -> -0.0038555865
C25: % International spend | E25: 0.05 | M25: Sales & Marketing | O25: =O73 -> -0.2218681 | P25: =P73 -> -0.2218681 | Q25: =Q73 -> 0 | R25: =R73 -> 0 | S25: =S73 -> 0 | T25: =T73 -> 0 | U25: =U73 -> 0 | V25: =V73 -> -0.0069360229 | W25: =W73 -> -0.0010526371
M26: Marketing promotion | O26: =O79 -> -0.10605185 | P26: =P79 -> -0.032183296 | Q26: =Q79 -> -0.025910934 | R26: =R79 -> -0.020477853 | S26: =S79 -> -0.015964125 | T26: =T79 -> -0.011515641 | U26: =U79 -> 0 | V26: =V79 -> -0.0033153846 | W26: =W79 -> -0.00050315533
C27: Spd / activated card | E27: ='Data input'!C129 -> 5.8941158 | F27: =E27 -> 5.8941158 | G27: =F27 -> 5.8941158 | H27: =G27 -> 5.8941158 | I27: =H27 -> 5.8941158 | M27: Physical card | O27: =O80 -> -0.077466542 | P27: =P80 -> -0.077466542 | Q27: =Q80 -> 0 | R27: =R80 -> 0 | S27: =S80 -> 0 | T27: =T80 -> 0 | U27: =U80 -> 0 | V27: =V80 -> -0.0024217529 | W27: =W80 -> -0.00036753441
M28: UW & Disbursal cost | O28: =O81 -> -0.13112345 | P28: =P81 -> -0.13112345 | Q28: =Q81 -> 0 | R28: =R81 -> 0 | S28: =S81 -> 0 | T28: =T81 -> 0 | U28: =U81 -> 0 | V28: =V81 -> -0.0040991709 | W28: =W81 -> -0.00062210571
B29: Payment status | C29: Minimal Payment | E29: 0.05 | F29: perbalance | M29: Collection | O29: =O86 -> -0.25032 | P29: =P86 -> -0.075964 | Q29: =Q86 -> -0.061159 | R29: =R86 -> -0.048335 | S29: =S86 -> -0.037681 | T29: =T86 -> -0.027181 | U29: =U86 -> 0 | V29: =V86 -> -0.0078254841 | W29: =W86 -> -0.0011876251
C30: Due date | E30: 5 | F30: date of month | M30: After-sales services | O30: =O89 -> -0.025825832 | P30: =P89 -> -0.007396473 | Q30: =Q89 -> -0.0061977988 | R30: =R89 -> -0.0050645736 | S30: =S89 -> -0.0040958951 | T30: =T89 -> -0.0030710919 | U30: =U89 -> 0 | V30: =V89 -> -0.00080736513 | W30: =W89 -> -0.00012252879
M31: Overhead cost | O31: =O72-O24 -> -1.2661194 | P31: =P72-P24 -> -0.36261438 | Q31: =Q72-Q24 -> -0.303849 | R31: =R72-R24 -> -0.24829228 | S31: =S72-S24 -> -0.20080252 | T31: =T72-T24 -> -0.15056123 | U31: =U72-U24 -> 0 | V31: =O31/$O$46/60*12 -> -0.039581325 | W31: =O31/$O$18 -> -0.006007012
C32: Free-interest period | E32: 45 | F32: days | M32: PBT | O32: =O92 -> -0.10411658 | P32: =P92 -> -0.5695596 | Q32: =Q92 -> -0.067392621 | R32: =R92 -> 0.017062963 | S32: =S92 -> 0.22807158 | T32: =T92 -> 0.28770109 | U32: =U92 -> 0 | V32: =V92 -> -0.0032548843 | W32: =W92 -> -0.00049397358
C33: Port Revolving rate | E33: ='Data input'!C127 -> 0.53345835 | F33: per ANR T-1 (excl EMI, WO) | M33: In which: Profit before Overhead | O33: =O91 -> 1.1620028 | P33: =P91 -> -0.20694522 | Q33: =Q91 -> 0.23645638 | R33: =R91 -> 0.26535525 | S33: =S91 -> 0.4288741 | T33: =T91 -> 0.43826232 | U33: =U91 -> 0 | V33: =V91 -> 0.036326441 | W33: =W91 -> 0.0055130384
C34: Repayment rate | E34: ='Data input'!C128 -> 0.58765108 | F34: =E34 -> 0.58765108 | G34: =F34 -> 0.58765108 | H34: =G34 -> 0.58765108 | I34: =H34 -> 0.58765108
E35: per ANR T-1
B36: Pricing | C36: CII rate | E36: =G36*(E22+E23)+F36*(E24+E25) -> 0.45066 | F36: 0.45 | G36: 0.47
C37: COF rate | E37: =COF!E2 -> 0.058332905 | F37: 45%spending &47%cashadvance
B39: Customer fee | C39: Annual fee | E39: ='Data input'!C228 -> 0.48176123 | F39: per card/year | G39: Annual Fee waiver | I39: 0.1 | J39: per total port
C40: Quarterly fee | F40: per card/quarter | G40: Quarterly Fee waiver | J40: per total port
C41: Monthly fee | F41: per card/month | G41: Monthly Fee waiver | J41: per total port
M42: PERFORMANCE OUTPUT | W42: Cur: mVND, %
C43: Issuance fee | E43: ='Data input'!C243 -> 0.076251067 | F43: per physical card
C44: Termination fee | E44: ='Data input'!C264 -> 0.31342125 | F44: If closing in year 1 | O44: Lifetime | P44: Year 1 | Q44: Year 2 | R44: Year 3 | S44: Year 4 | T44: Year 5 | U44: =IF(C7="VAS","Year 6","") | V44: % of ANR 5Y | W44: % Spending
C46: Late payment rate | E46: 0.05 | F46: overdue balance/month | G46: %Latepayment collected | I46: =1-E143 -> 0.15 | J46: % overdue balance | M46: ANR | O46: =AVERAGE(SAP_Spreadsheet!G656:BN656) -> 6.3975595 | P46: =AVERAGE(SAP_Spreadsheet!G656:R656) -> 9.1247955 | Q46: =AVERAGE(SAP_Spreadsheet!S656:AD656) -> 8.0077877 | R46: =AVERAGE(SAP_Spreadsheet!AE656:AP656) -> 6.3347125 | S46: =AVERAGE(SAP_Spreadsheet!AQ656:BB656) -> 4.9761104 | T46: =AVERAGE(SAP_Spreadsheet!BC656:BN656) -> 3.5443913
M47: Spending | O47: =SUM(P47:T47) -> 210.77358 | P47: =SUM(SAP_Spreadsheet!G611:R611) -> 63.962944 | Q47: =SUM(SAP_Spreadsheet!S611:AD611) -> 51.496889 | R47: =SUM(SAP_Spreadsheet!AE611:AP611) -> 40.698869 | S47: =SUM(SAP_Spreadsheet!AQ611:BB611) -> 31.728025 | T47: =SUM(SAP_Spreadsheet!BC611:BN611) -> 22.886852
C48: Cash advance | E48: =4% -> 0.04 | F48: per spend/month | M48: TOI | O48: =O49+O52+O70 -> 6.5739424 | P48: =P49+P52+P70 -> 1.973176 | Q48: =Q49+Q52+Q70 -> 1.5624843 | R48: =R49+R52+R70 -> 1.2501523 | S48: =S49+S52+S70 -> 1.0225009 | T48: =T49+T52+T70 -> 0.76562904 | V48: =O48/$O$46/60*12 -> 0.20551407 | W48: =O48/$O$47 -> 0.031189594
C49: Currency conversion (FX rate) | E49: 0.04 | F49: per int' spend/month | M49: Net interest income | O49: =SUM(O50:O51) -> 3.951425 | P49: =SUM(P50:P51) -> 1.0539614 | Q49: =SUM(Q50:Q51) -> 0.96121531 | R49: =SUM(R50:R51) -> 0.77487769 | S49: =SUM(S50:S51) -> 0.64377475 | T49: =SUM(T50:T51) -> 0.5175958 | V49: =O49/$O$46/60*12 -> 0.12352914 | W49: =O49/$O$47 -> 0.01874725
M50: CII | O50: =SUM( SAP_Spreadsheet!G670:BN670) -> 5.8173661 | P50: =SUM(SAP_Spreadsheet!G670:R670) -> 1.5862373 | Q50: =SUM(SAP_Spreadsheet!S670:AD670) -> 1.4283328 | R50: =SUM(SAP_Spreadsheet!AE670:AP670) -> 1.1443999 | S50: =SUM(SAP_Spreadsheet!AQ670:BB670) -> 0.93404573 | T50: =SUM(SAP_Spreadsheet!BC670:BN670) -> 0.72435044 | V50: =O50/$O$46/60*12 -> 0.18186204 | W50: =O50/$O$47 -> 0.027600073
B51: Customer rewards | M51: COF | O51: =SUM( SAP_Spreadsheet!G673:BN673) -> -1.8659411 | P51: =SUM(SAP_Spreadsheet!G673:R673) -> -0.53227583 | Q51: =SUM(SAP_Spreadsheet!S673:AD673) -> -0.46711752 | R51: =SUM(SAP_Spreadsheet!AE673:AP673) -> -0.36952218 | S51: =SUM(SAP_Spreadsheet!AQ673:BB673) -> -0.29027097 | T51: =SUM(SAP_Spreadsheet!BC673:BN673) -> -0.20675464 | V51: =O51/$O$46/60*12 -> -0.058332905 | W51: =O51/$O$47 -> -0.0088528227
C52: Cashback | E52: =SUM(E53:E54) -> 0.0037001972 | F52: per retail spend/month | M52: Net fee income | O52: =SUM(O53:O69) -> 2.6225175 | P52: =SUM(P53:P69) -> 0.91921454 | Q52: =SUM(Q53:Q69) -> 0.60126894 | R52: =SUM(R53:R69) -> 0.47527458 | S52: =SUM(S53:S69) -> 0.37872615 | T52: =SUM(T53:T69) -> 0.24803324 | V52: =O52/$O$46/60*12 -> 0.081984934 | W52: =O52/$O$47 -> 0.012442344
C53: Cash back | E53: ='Data input'!C137 -> 0.0037001972 | F53: per retail spend/month | M53: Annual fee | O53: =SUM( SAP_Spreadsheet!G678:BN678) -> 1.439069 | P53: =SUM(SAP_Spreadsheet!G678:R678) -> 0.42361265 | Q53: =SUM(SAP_Spreadsheet!S678:AD678) -> 0.35250469 | R53: =SUM( SAP_Spreadsheet!AE678:AP678) -> 0.27576013 | S53: =SUM( SAP_Spreadsheet!AQ678:BB678) -> 0.22069482 | T53: =SUM( SAP_Spreadsheet!BC678:BN678) -> 0.16649668 | V53: =O53/$O$46/60*12 -> 0.04498806 | W53: =O53/$O$47 -> 0.0068275586
C54: Loyalty | F54: per retail spend/month | M54: Quarterly fee | O54: =SUM( SAP_Spreadsheet!G679:BN679) -> 0 | P54: =SUM(SAP_Spreadsheet!G679:R679) -> 0 | Q54: =SUM(SAP_Spreadsheet!S679:AD679) -> 0 | R54: =SUM( SAP_Spreadsheet!AE679:AP679) -> 0 | S54: =SUM( SAP_Spreadsheet!AQ679:BB679) -> 0 | T54: =SUM( SAP_Spreadsheet!BC679:BN679) -> 0 | V54: =O54/$O$46/60*12 -> 0 | W54: =O54/$O$47 -> 0
C55: Welcomegift | F55: per primary card | M55: Monthly fee | O55: =SUM( SAP_Spreadsheet!G680:BN680) -> 0 | P55: =SUM(SAP_Spreadsheet!G680:R680) -> 0 | Q55: =SUM(SAP_Spreadsheet!S680:AD680) -> 0 | R55: =SUM( SAP_Spreadsheet!AE680:AP680) -> 0 | S55: =SUM( SAP_Spreadsheet!AQ680:BB680) -> 0 | T55: =SUM( SAP_Spreadsheet!BC680:BN680) -> 0 | V55: =O55/$O$46/60*12 -> 0 | W55: =O55/$O$47 -> 0
C56: Free ship code | M56: Issuance fee | O56: =SUM( SAP_Spreadsheet!G681:BN681) -> 0.076251067 | P56: =SUM(SAP_Spreadsheet!G681:R681) -> 0.076251067 | Q56: =SUM(SAP_Spreadsheet!S681:AD681) -> 0 | R56: =SUM( SAP_Spreadsheet!AE681:AP681) -> 0 | S56: =SUM( SAP_Spreadsheet!AQ681:BB681) -> 0 | T56: =SUM( SAP_Spreadsheet!BC681:BN681) -> 0 | V56: =O56/$O$46/60*12 -> 0.0023837548 | W56: =O56/$O$47 -> 0.00036176767
B57: Vendor fee | M57: Termination fee | O57: =SUM( SAP_Spreadsheet!G682:BN682) -> 0.053281613 | P57: =SUM(SAP_Spreadsheet!G682:R682) -> 0.053281613 | Q57: =SUM(SAP_Spreadsheet!S682:AD682) -> 0 | R57: =SUM( SAP_Spreadsheet!AE682:AP682) -> 0 | S57: =SUM( SAP_Spreadsheet!AQ682:BB682) -> 0 | T57: =SUM( SAP_Spreadsheet!BC682:BN682) -> 0 | V57: =O57/$O$46/60*12 -> 0.0016656856 | W57: =O57/$O$47 -> 0.00025279076
C58: Interchange | E58: ='Data input'!C136 -> 0.0051800628 | F58: per spend/month | M58: Late payment | O58: =SUM( SAP_Spreadsheet!G683:BN683) -> 0.0489412 | P58: =SUM(SAP_Spreadsheet!G683:R683) -> 0.016197395 | Q58: =SUM(SAP_Spreadsheet!S683:AD683) -> 0.012862746 | R58: =SUM( SAP_Spreadsheet!AE683:AP683) -> 0.0097336882 | S58: =SUM( SAP_Spreadsheet!AQ683:BB683) -> 0.0065578776 | T58: =SUM( SAP_Spreadsheet!BC683:BN683) -> 0.0035894929 | V58: =O58/$O$46/60*12 -> 0.0015299959 | W58: =O58/$O$47 -> 0.00023219798
C59: Processing fee (VISA) | E59: ='Data input'!C138 -> 0.0015771938 | F59: per spend/month | M59: Cash advance | O59: =SUM( SAP_Spreadsheet!G684:BN684) -> 0.27822113 | P59: =SUM(SAP_Spreadsheet!G684:R684) -> 0.084431086 | Q59: =SUM(SAP_Spreadsheet!S684:AD684) -> 0.067975894 | R59: =SUM( SAP_Spreadsheet!AE684:AP684) -> 0.053722508 | S59: =SUM( SAP_Spreadsheet!AQ684:BB684) -> 0.041880993 | T59: =SUM( SAP_Spreadsheet!BC684:BN684) -> 0.030210644 | V59: =O59/$O$46/60*12 -> 0.0086977269 | W59: =O59/$O$47 -> 0.00132
M60: Currency conversion | O60: =SUM( SAP_Spreadsheet!G685:BN685) -> 0.42154716 | P60: =SUM(SAP_Spreadsheet!G685:R685) -> 0.12792589 | Q60: =SUM(SAP_Spreadsheet!S685:AD685) -> 0.10299378 | R60: =SUM( SAP_Spreadsheet!AE685:AP685) -> 0.081397739 | S60: =SUM( SAP_Spreadsheet!AQ685:BB685) -> 0.06345605 | T60: =SUM( SAP_Spreadsheet!BC685:BN685) -> 0.045773703 | V60: =O60/$O$46/60*12 -> 0.013178374 | W60: =O60/$O$47 -> 0.002
C61: Vendor servicing cost(PBC) | F61: actived card/month | M61: Insurance fee | O61: =SUM( SAP_Spreadsheet!G686:BN686) -> 0 | P61: =SUM(SAP_Spreadsheet!G686:R686) -> 0 | Q61: =SUM(SAP_Spreadsheet!S686:AD686) -> 0 | R61: =SUM( SAP_Spreadsheet!AE686:AP686) -> 0 | S61: =SUM( SAP_Spreadsheet!AQ686:BB686) -> 0 | T61: =SUM( SAP_Spreadsheet!BC686:BN686) -> 0 | V61: =O61/$O$46/60*12 -> 0 | W61: =O61/$O$47 -> 0
M62: EMI initial fee | O62: =SUM( SAP_Spreadsheet!G694:BN694) -> 0.51232322 | P62: =SUM(SAP_Spreadsheet!G694:R694) -> 0.16679362 | Q62: =SUM(SAP_Spreadsheet!S694:AD694) -> 0.13428638 | R62: =SUM( SAP_Spreadsheet!AE694:AP694) -> 0.10612882 | S62: =SUM( SAP_Spreadsheet!AQ694:BB694) -> 0.082735904 | T62: =SUM( SAP_Spreadsheet!BC694:BN694) -> 0.022378502 | V62: =O62/$O$46/60*12 -> 0.016016208 | W62: =O62/$O$47 -> 0.0024306805
B63: Insurance | M63: EMI early repayment | O63: =SUM( SAP_Spreadsheet!G703:BN703) -> 0 | P63: =SUM(SAP_Spreadsheet!G703:R703) -> 0 | Q63: =SUM(SAP_Spreadsheet!S703:AD703) -> 0 | R63: =SUM( SAP_Spreadsheet!AE703:AP703) -> 0 | S63: =SUM( SAP_Spreadsheet!AQ703:BB703) -> 0 | T63: =SUM( SAP_Spreadsheet!BC703:BN703) -> 0 | V63: =O63/$O$46/60*12 -> 0 | W63: =O63/$O$47 -> 0
C64: Insurance fee | F64: yearly | M64: Customer rewards | O64: =SUM( SAP_Spreadsheet!G691:BN691) -> -0.77990381 | P64: =SUM(SAP_Spreadsheet!G691:R691) -> -0.23667551 | Q64: =SUM(SAP_Spreadsheet!S691:AD691) -> -0.19054865 | R64: =SUM( SAP_Spreadsheet!AE691:AP691) -> -0.15059384 | S64: =SUM( SAP_Spreadsheet!AQ691:BB691) -> -0.11739995 | T64: =SUM( SAP_Spreadsheet!BC691:BN691) -> -0.084685863 | V64: =O64/$O$46/60*12 -> -0.024381291 | W64: =O64/$O$47 -> -0.0037001972
C65: %commission to CAKE | M65: Interchange | O65: =SUM( SAP_Spreadsheet!G687:BN687) -> 1.0918204 | P65: =SUM(SAP_Spreadsheet!G687:R687) -> 0.33133207 | Q65: =SUM(SAP_Spreadsheet!S687:AD687) -> 0.26675712 | R65: =SUM( SAP_Spreadsheet!AE687:AP687) -> 0.2108227 | S65: =SUM( SAP_Spreadsheet!AQ687:BB687) -> 0.16435316 | T65: =SUM( SAP_Spreadsheet!BC687:BN687) -> 0.11855533 | V65: =O65/$O$46/60*12 -> 0.034132403 | W65: =O65/$O$47 -> 0.0051800628
C66: Penetration rate | M66: Vendor servicing cost | O66: =SUM( SAP_Spreadsheet!G688:BN688) -> 0 | P66: =SUM(SAP_Spreadsheet!G688:R688) -> 0 | Q66: =SUM(SAP_Spreadsheet!S688:AD688) -> 0 | R66: =SUM( SAP_Spreadsheet!AE688:AP688) -> 0 | S66: =SUM( SAP_Spreadsheet!AQ688:BB688) -> 0 | T66: =SUM( SAP_Spreadsheet!BC688:BN688) -> 0 | V66: =O66/$O$46/60*12 -> 0 | W66: =O66/$O$47 -> 0
E67: per activated account | M67: Processing cost | O67: =SUM( SAP_Spreadsheet!G689:BN689) -> -0.33243078 | P67: =SUM(SAP_Spreadsheet!G689:R689) -> -0.10088196 | Q67: =SUM(SAP_Spreadsheet!S689:AD689) -> -0.081220575 | R67: =SUM( SAP_Spreadsheet!AE689:AP689) -> -0.064190005 | S67: =SUM( SAP_Spreadsheet!AQ689:BB689) -> -0.050041245 | T67: =SUM( SAP_Spreadsheet!BC689:BN689) -> -0.036097 | V67: =O67/$O$46/60*12 -> -0.010392425 | W67: =O67/$O$47 -> -0.0015771938
B68: EMI | M68: Support processing cost | O68: =SUM( SAP_Spreadsheet!G690:BN690) -> 0 | P68: =SUM(SAP_Spreadsheet!G690:R690) -> 0 | Q68: =SUM(SAP_Spreadsheet!S690:AD690) -> 0 | R68: =SUM( SAP_Spreadsheet!AE690:AP690) -> 0 | S68: =SUM( SAP_Spreadsheet!AQ690:BB690) -> 0 | T68: =SUM( SAP_Spreadsheet!BC690:BN690) -> 0 | V68: =O68/$O$46/60*12 -> 0 | W68: =O68/$O$47 -> 0
C69: CASH INSTALLMENT | M69: Fee suspended | O69: =SUM( SAP_Spreadsheet!G707:BN707) -> -0.1866027 | P69: =SUM(SAP_Spreadsheet!G707:R707) -> -0.023053379 | Q69: =SUM(SAP_Spreadsheet!S707:AD707) -> -0.064342452 | R69: =SUM( SAP_Spreadsheet!AE707:AP707) -> -0.047507156 | S69: =SUM( SAP_Spreadsheet!AQ707:BB707) -> -0.033511461 | T69: =SUM( SAP_Spreadsheet!BC707:BN707) -> -0.018188251 | V69: =O69/$O$46/60*12 -> -0.0058335589 | W69: =O69/$O$47 -> -0.000885323
C70: EMI Penetration | F70: per total spending | M70: Other income | O70: =SUM( SAP_Spreadsheet!G709:BN709) -> 0 | P70: =SUM(SAP_Spreadsheet!G709:R709) -> 0 | Q70: =SUM(SAP_Spreadsheet!S709:AD709) -> 0 | R70: =SUM( SAP_Spreadsheet!AE709:AP709) -> 0 | S70: =SUM( SAP_Spreadsheet!AQ709:BB709) -> 0 | T70: =SUM( SAP_Spreadsheet!BC709:BN709) -> 0 | V70: =O70/$O$46/60*12 -> 0 | W70: =O70/$O$47 -> 0
C71: Average tenor | F71: month | M71: PROVISION | O71: =SUM( SAP_Spreadsheet!G807:BZ807) -> -4.5992838 | P71: =SUM(SAP_Spreadsheet!G807:R807) -> -1.6341193 | Q71: =SUM(SAP_Spreadsheet!S807:AD807) -> -1.2327601 | R71: =SUM( SAP_Spreadsheet!AE807:AP807) -> -0.91091959 | S71: =SUM( SAP_Spreadsheet!AQ807:BB807) -> -0.53588578 | T71: =SUM( SAP_Spreadsheet!BC807:BN807) -> -0.28559898 | U71: =SUM(SAP_Spreadsheet!BO807:BZ807) -> 0 | V71: =O71/$O$46/60*12 -> -0.14378245 | W71: =O71/$O$47 -> -0.021820969
C72: Initial fee | F72: monthly | M72: OPEX | O72: =O73+O79+O81+O89+O86+O90+O80 -> -2.0787752 | P72: =P73+P79+P81+P89+P86+P90+P80 -> -0.90861623 | Q72: =Q73+Q79+Q81+Q89+Q86+Q90+Q80 -> -0.39711674 | R72: =R73+R79+R81+R89+R86+R90+R80 -> -0.32216971 | S72: =S73+S79+S81+S89+S86+S90+S80 -> -0.25854354 | T72: =T73+T79+T81+T89+T86+T90+T80 -> -0.19232896 | V72: =O72/$O$46/60*12 -> -0.064986506 | W72: =O72/$O$47 -> -0.0098625984
C73: Upfront fee | F73: per initial transaction | M73: Sales & Marketing | O73: =SUM(O74:O78) -> -0.2218681 | P73: =SUM(P74:P78) -> -0.2218681 | Q73: =SUM(Q74:Q78) -> 0 | R73: =SUM(R74:R78) -> 0 | S73: =SUM(S74:S78) -> 0 | T73: =SUM(T74:T78) -> 0 | V73: =SUM(V75:V78) -> -0.0069360229 | W73: =O73/$O$47 -> -0.0010526371
C74: Early repayment penalty | F74: outstandingbalance | M74: Lead acquisition | O74: =SUM( SAP_Spreadsheet!G715:BN715) -> 0 | P74: =SUM(SAP_Spreadsheet!G715:R715) -> 0 | Q74: =SUM(SAP_Spreadsheet!S715:AD715) -> 0 | R74: =SUM( SAP_Spreadsheet!AE715:AP715) -> 0 | S74: =SUM( SAP_Spreadsheet!AQ715:BB715) -> 0 | T74: =SUM( SAP_Spreadsheet!BC715:BN715) -> 0 | V74: =O74/$O$46/60*12 -> 0 | W74: =O74/$O$47 -> 0
C75: % Early repayment | F75: per total port/month | M75: TOI only | O75: =SUM( SAP_Spreadsheet!G716:BN716) -> 0 | P75: =SUM(SAP_Spreadsheet!G716:R716) -> 0 | Q75: =SUM(SAP_Spreadsheet!S716:AD716) -> 0 | R75: =SUM( SAP_Spreadsheet!AE716:AP716) -> 0 | S75: =SUM( SAP_Spreadsheet!AQ716:BB716) -> 0 | T75: =SUM( SAP_Spreadsheet!BC716:BN716) -> 0 | V75: =O75/$O$46/60*12 -> 0 | W75: =O75/$O$47 -> 0
M76: TOI+RISKDPD90+ | O76: =SUM( SAP_Spreadsheet!G717:BN717) -> 0 | P76: =SUM(SAP_Spreadsheet!G717:R717) -> 0 | Q76: =SUM(SAP_Spreadsheet!S717:AD717) -> 0 | R76: =SUM( SAP_Spreadsheet!AE717:AP717) -> 0 | S76: =SUM( SAP_Spreadsheet!AQ717:BB717) -> 0 | T76: =SUM( SAP_Spreadsheet!BC717:BN717) -> 0 | V76: =O76/$O$46/60*12 -> 0 | W76: =O76/$O$47 -> 0
C77: RETAIL 1% | M77: TOI+RISKDPD180+ | O77: =SUM( SAP_Spreadsheet!G718:BN718) -> 0 | P77: =SUM(SAP_Spreadsheet!G718:R718) -> 0 | Q77: =SUM(SAP_Spreadsheet!S718:AD718) -> 0 | R77: =SUM( SAP_Spreadsheet!AE718:AP718) -> 0 | S77: =SUM( SAP_Spreadsheet!AQ718:BB718) -> 0 | T77: =SUM( SAP_Spreadsheet!BC718:BN718) -> 0 | V77: =O77/$O$46/60*12 -> 0 | W77: =O77/$O$47 -> 0
C78: EMI Penetration | E78: ='Data input'!C147 -> 0.044248208 | F78: per total spending | M78: Marketing acquisition | O78: =SUM( SAP_Spreadsheet!G719:BN719) -> -0.2218681 | P78: =SUM(SAP_Spreadsheet!G719:R719) -> -0.2218681 | Q78: =SUM(SAP_Spreadsheet!S719:AD719) -> 0 | R78: =SUM( SAP_Spreadsheet!AE719:AP719) -> 0 | S78: =SUM( SAP_Spreadsheet!AQ719:BB719) -> 0 | T78: =SUM( SAP_Spreadsheet!BC719:BN719) -> 0 | V78: =O78/$O$46/60*12 -> -0.0069360229 | W78: =O78/$O$47 -> -0.0010526371
C79: Average tenor | E79: ='Data input'!C145 -> 9 | F79: month | M79: Marketing promotion | O79: =SUM( SAP_Spreadsheet!G722:BN722) -> -0.10605185 | P79: =SUM(SAP_Spreadsheet!G722:R722) -> -0.032183296 | Q79: =SUM(SAP_Spreadsheet!S722:AD722) -> -0.025910934 | R79: =SUM( SAP_Spreadsheet!AE722:AP722) -> -0.020477853 | S79: =SUM( SAP_Spreadsheet!AQ722:BB722) -> -0.015964125 | T79: =SUM( SAP_Spreadsheet!BC722:BN722) -> -0.011515641 | V79: =O79/$O$46/60*12 -> -0.0033153846 | W79: =O79/$O$47 -> -0.00050315533
C80: Initial fee | F80: monthly | M80: Physical card | O80: =SUM( SAP_Spreadsheet!G723:BN723) -> -0.077466542 | P80: =SUM(SAP_Spreadsheet!G723:R723) -> -0.077466542 | Q80: =SUM(SAP_Spreadsheet!S723:AD723) -> 0 | R80: =SUM( SAP_Spreadsheet!AE723:AP723) -> 0 | S80: =SUM( SAP_Spreadsheet!AQ723:BB723) -> 0 | T80: =SUM( SAP_Spreadsheet!BC723:BN723) -> 0 | V80: =O80/$O$46/60*12 -> -0.0024217529 | W80: =O80/$O$47 -> -0.00036753441
C81: Upfront fee | E81: ='Data input'!C146 -> 0.058932557 | F81: per initial transaction | M81: UW & Disbursal cost | O81: =SUM( SAP_Spreadsheet!G729:BN729) -> -0.13112345 | P81: =SUM(SAP_Spreadsheet!G729:R729) -> -0.13112345 | Q81: =SUM(SAP_Spreadsheet!S729:AD729) -> 0 | R81: =SUM( SAP_Spreadsheet!AE729:AP729) -> 0 | S81: =SUM( SAP_Spreadsheet!AQ729:BB729) -> 0 | T81: =SUM( SAP_Spreadsheet!BC729:BN729) -> 0 | V81: =O81/$O$46/60*12 -> -0.0040991709 | W81: =O81/$O$47 -> -0.00062210571
C82: Early repayment penalty | F82: outstandingbalance | M82: Underwriting cost | O82: =SUM( SAP_Spreadsheet!G725:BN725) -> -0.12127581 | P82: =SUM(SAP_Spreadsheet!G725:R725) -> -0.12127581 | Q82: =SUM(SAP_Spreadsheet!S725:AD725) -> 0 | R82: =SUM( SAP_Spreadsheet!AE725:AP725) -> 0 | S82: =SUM( SAP_Spreadsheet!AQ725:BB725) -> 0 | T82: =SUM( SAP_Spreadsheet!BC725:BN725) -> 0 | V82: =O82/$O$46/60*12 -> -0.0037913148 | W82: =O82/$O$47 -> -0.0005753843
C83: % Early repayment | F83: per total port/month | M83: DOP cost | O83: =SUM( SAP_Spreadsheet!G726:BN726) -> 0 | P83: =SUM(SAP_Spreadsheet!G726:R726) -> 0 | Q83: =SUM(SAP_Spreadsheet!S726:AD726) -> 0 | R83: =SUM( SAP_Spreadsheet!AE726:AP726) -> 0 | S83: =SUM( SAP_Spreadsheet!AQ726:BB726) -> 0 | T83: =SUM( SAP_Spreadsheet!BC726:BN726) -> 0 | V83: =O83/$O$46/60*12 -> 0 | W83: =O83/$O$47 -> 0
M84: Disbursal cost | O84: =SUM( SAP_Spreadsheet!G727:BN727) -> -0.0098476384 | P84: =SUM(SAP_Spreadsheet!G727:R727) -> -0.0098476384 | Q84: =SUM(SAP_Spreadsheet!S727:AD727) -> 0 | R84: =SUM( SAP_Spreadsheet!AE727:AP727) -> 0 | S84: =SUM( SAP_Spreadsheet!AQ727:BB727) -> 0 | T84: =SUM( SAP_Spreadsheet!BC727:BN727) -> 0 | V84: =O84/$O$46/60*12 -> -0.00030785609 | W84: =O84/$O$47 -> -4.6721408e-05
C85: RETAIL 0% | M85: Credit support | O85: =SUM( SAP_Spreadsheet!G728:BN728) -> 0 | P85: =SUM(SAP_Spreadsheet!G728:R728) -> 0 | Q85: =SUM(SAP_Spreadsheet!S728:AD728) -> 0 | R85: =SUM( SAP_Spreadsheet!AE728:AP728) -> 0 | S85: =SUM( SAP_Spreadsheet!AQ728:BB728) -> 0 | T85: =SUM( SAP_Spreadsheet!BC728:BN728) -> 0 | V85: =O85/$O$46/60*12 -> 0 | W85: =O85/$O$47 -> 0
C86: EMI Penetration | F86: per total spending | M86: Collection | O86: =SUM(O87:O88) -> -0.25032 | P86: =SUM(P87:P88) -> -0.075964 | Q86: =SUM(Q87:Q88) -> -0.061159 | R86: =SUM(R87:R88) -> -0.048335 | S86: =SUM(S87:S88) -> -0.037681 | T86: =SUM(T87:T88) -> -0.027181 | V86: =O86/$O$46/60*12 -> -0.0078254841 | W86: =O86/$O$47 -> -0.0011876251
C87: Average tenor | F87: month | M87: Early collection | O87: =SUM( SAP_Spreadsheet!G741:BN741) -> -0.25032 | P87: =SUM(SAP_Spreadsheet!G741:R741) -> -0.075964 | Q87: =SUM(SAP_Spreadsheet!S741:AD741) -> -0.061159 | R87: =SUM( SAP_Spreadsheet!AE741:AP741) -> -0.048335 | S87: =SUM( SAP_Spreadsheet!AQ741:BB741) -> -0.037681 | T87: =SUM( SAP_Spreadsheet!BC741:BN741) -> -0.027181 | V87: =O87/$O$46/60*12 -> -0.0078254841 | W87: =O87/$O$47 -> -0.0011876251
C88: Initial fee | F88: monthly | M88: AMC | O88: =SUM( SAP_Spreadsheet!G742:BN743) -> 0 | P88: =SUM(SAP_Spreadsheet!G742:R743) -> 0 | Q88: =SUM(SAP_Spreadsheet!S742:AD743) -> 0 | R88: =SUM( SAP_Spreadsheet!AE742:AP743) -> 0 | S88: =SUM( SAP_Spreadsheet!AQ742:BB743) -> 0 | T88: =SUM( SAP_Spreadsheet!BC742:BN743) -> 0 | V88: =O88/$O$46/60*12 -> 0 | W88: =O88/$O$47 -> 0
C89: Upfront fee | F89: per initial transaction | M89: After-sales services | O89: =SUM( SAP_Spreadsheet!G736:BN736) -> -0.025825832 | P89: =SUM(SAP_Spreadsheet!G736:R736) -> -0.007396473 | Q89: =SUM(SAP_Spreadsheet!S736:AD736) -> -0.0061977988 | R89: =SUM( SAP_Spreadsheet!AE736:AP736) -> -0.0050645736 | S89: =SUM( SAP_Spreadsheet!AQ736:BB736) -> -0.0040958951 | T89: =SUM( SAP_Spreadsheet!BC736:BN736) -> -0.0030710919 | V89: =O89/$O$46/60*12 -> -0.00080736513 | W89: =O89/$O$47 -> -0.00012252879
C90: Early repayment penalty | F90: outstandingbalance | M90: Other support units | O90: =SUM( SAP_Spreadsheet!G746:BN749) -> -1.2661194 | P90: =SUM(SAP_Spreadsheet!G746:R749) -> -0.36261438 | Q90: =SUM(SAP_Spreadsheet!S746:AD749) -> -0.303849 | R90: =SUM( SAP_Spreadsheet!AE746:AP749) -> -0.24829228 | S90: =SUM( SAP_Spreadsheet!AQ746:BB749) -> -0.20080252 | T90: =SUM( SAP_Spreadsheet!BC746:BN749) -> -0.15056123 | V90: =O90/$O$46/60*12 -> -0.039581325 | W90: =O90/$O$47 -> -0.006007012
C91: % Early repayment | F91: per total port/month | M91: PROFIT BEFORE SU | O91: =O48+O71+O72-O90+O70 -> 1.1620028 | P91: =P48+P71+P72-P90+P70 -> -0.20694522 | Q91: =Q48+Q71+Q72-Q90+Q70 -> 0.23645638 | R91: =R48+R71+R72-R90+R70 -> 0.26535525 | S91: =S48+S71+S72-S90+S70 -> 0.4288741 | T91: =T48+T71+T72-T90+T70 -> 0.43826232 | U91: =U48+U71+U72-U90+U70 -> 0 | V91: =O91/$O$46/60*12 -> 0.036326441 | W91: =O91/$O$47 -> 0.0055130384
M92: PBT | O92: =O48+O70+O71+O72 -> -0.10411658 | P92: =P48+P70+P71+P72 -> -0.5695596 | Q92: =Q48+Q70+Q71+Q72 -> -0.067392621 | R92: =R48+R70+R71+R72 -> 0.017062963 | S92: =S48+S70+S71+S72 -> 0.22807158 | T92: =T48+T70+T71+T72 -> 0.28770109 | U92: =U48+U70+U71+U72 -> 0 | V92: =O92/$O$46/60*12 -> -0.0032548843 | W92: =O92/$O$47 -> -0.00049397358
B94: COST INPUT | K94: Cur: mVND, %
B95: Inflation rate
E96: =IF(SAP_Spreadsheet!$D$5="yes",0,3.5%) -> 0.035 | F96: annual rate
B97: Sales & Marketing
C98: Lead acquisition | F98: per new issued card
C99: Sharing TOI only | F99: % permonth | G99: Include( CII,COF,AnnualFee, Fxfee, interchange, processing, cashback)
C100: Sharing TOI+RISKDPD90+ | F100: % permonth
C101: Sharing TOI+RISKDPD180+ | F101: % permonth
C102: Marketing acquisition | E102: ='Data input'!C176 -> 0.2218681 | F102: per new issued card
B104: Marketing promotion | F104: per activated card/month
E105: ='Data input'!C177 -> 0.00050315533 | F105: per spending
B106: UW & Disbursal cost
...

Sheet COF
E2: =SUM(E14:E16)/SUM(D14:D16)*365 -> 0.058332905
D3: Sum of BALANCE | E3: Sum of Lai DCV
B4: 2024 | C4: Dec | D4: 2444137528275 | E4: 308028372
B5: 2025 | C5: Jan | D5: 25799219832926 | E5: 3251409022
C6: Feb | D6: 24126737449976 | E6: 3.0406303e+09
C7: Mar | D7: 26989267925200 | E7: 3.4013937e+09
C8: Apr | D8: 26311152949564 | E8: 3.3161159e+09
C9: May | D9: 30467974367402 | E9: 3.8414955e+09
C10: Jun | D10: 31627213733087 | E10: 4.0213174e+09
C11: Jul | D11: 34742233428138 | E11: 4.7800311e+09
C12: Aug | D12: 37358792399704 | E12: 5.4247014e+09
C13: Sep | D13: 38486365009052 | E13: 5.663474e+09
C14: Oct | D14: 41287758219971 | E14: 6.2669032e+09
C15: Nov | D15: 42266567885886 | E15: 6.3414532e+09
C16: Dec | D16: 42654955260854 | E16: 7.5619285e+09
B17: Grand Total | D17: 404562375990035 | E17: 5.7218881e+10

Sheet SAP_Spreadsheet
A1: Index!A1 | B1: SAP MODEL - CREDIT CARD | G1: =G677/G21 -> 0.091194757 | H1: =H677/H21 -> 0.0064729236 | I1: =I677/I21 -> 0.006470038 | J1: =J677/J21 -> 0.00633684 | K1: =K677/K21 -> 0.0061200761 | L1: =L677/L21 -> 0.0058973063 | M1: =M677/M21 -> 0.0057146858 | N1: =N677/N21 -> 0.0055666625 | ... BN1: =BN677/BN21 -> 0.00083766242
B2: WO model | D2: =SAP_Leadsheet!$C$6 -> DPD180+
B3: Provision model | D3: =SAP_Leadsheet!C7 -> IFRS
B4: Calendar | D4: =(30*4+31*7+28)/12 -> 30.416667
B5: Validation | D5: No | BO5: For VAS only
D6: Year | G6: =ROUNDUP(G7/12,0) -> 1 | H6: =ROUNDUP(H7/12,0) -> 1 | I6: =ROUNDUP(I7/12,0) -> 1 | J6: =ROUNDUP(J7/12,0) -> 1 | K6: =ROUNDUP(K7/12,0) -> 1 | L6: =ROUNDUP(L7/12,0) -> 1 | M6: =ROUNDUP(M7/12,0) -> 1 | N6: =ROUNDUP(N7/12,0) -> 1 | ... BZ6: =ROUNDUP(BZ7/12,0) -> 6
D7: Month | G7: 1 | H7: =G7+1 -> 2 | I7: =H7+1 -> 3 | J7: =I7+1 -> 4 | K7: =J7+1 -> 5 | L7: =K7+1 -> 6 | M7: =L7+1 -> 7 | N7: =M7+1 -> 8 | O7: =N7+1 -> 9 | ... BZ7: =BY7+1 -> 72
B9: CARD OPERATION
C11: Card Status | D11: Issued card | F11: # Card | G11: 1
D12: Activated card | F12: # Card | G12: =G11*SAP_Leadsheet!$E$18 -> 0.99
D13: Attrition rate | F13: % | G13: =IF(G$7=12,SAP_Leadsheet!$E$20,IF(G$7=24,SAP_Leadsheet!$F$20,IF(G$7=36,SAP_Leadsheet!$G$20,IF(G$7=48,SAP_Leadsheet!$H$20,IF(G$7=60,SAP_Leadsheet!$I$20,IF(G$7<12,SAP_Leadsheet!$E$19,IF(G$7<24,SAP_Leadsheet!$F$19,IF(G$7<36,SAP_Leadsheet!$G$19,IF(G$7<48,SAP_Leadsheet!$H$19,SAP_Leadsheet!$I$19))))))))) -> 0.013 | H13: =IF(H$7=12,SAP_Leadsheet!$E$20,IF(H$7=24,SAP_Leadsheet!$F$20,IF(H$7=36,SAP_Leadsheet!$G$20,IF(H$7=48,SAP_Leadsheet!$H$20,IF(H$7=60,SAP_Leadsheet!$I$20,IF(H$7<12,SAP_Leadsheet!$E$19,IF(H$7<24,SAP_Leadsheet!$F$19,IF(H$7<36,SAP_Leadsheet!$G$19,IF(H$7<48,SAP_Leadsheet!$H$19,SAP_Leadsheet!$I$19))))))))) -> 0.013 | I13: =IF(I$7=12,SAP_Leadsheet!$E$20,IF(I$7=24,SAP_Leadsheet!$F$20,IF(I$7=36,SAP_Leadsheet!$G$20,IF(I$7=48,SAP_Leadsheet!$H$20,IF(I$7=60,SAP_Leadsheet!$I$20,IF(I$7<12,SAP_Leadsheet!$E$19,IF(I$7<24,SAP_Leadsheet!$F$19,IF(I$7<36,SAP_Leadsheet!$G$19,IF(I$7<48,SAP_Leadsheet!$H$19,SAP_Leadsheet!$I$19))))))))) -> 0.013 | J13: =IF(J$7=12,SAP_Leadsheet!$E$20,IF(J$7=24,SAP_Leadsheet!$F$20,IF(J$7=36,SAP_Leadsheet!$G$20,IF(J$7=48,SAP_Leadsheet!$H$20,IF(J$7=60,SAP_Leadsheet!$I$20,IF(J$7<12,SAP_Leadsheet!$E$19,IF(J$7<24,SAP_Leadsheet!$F$19,IF(J$7<36,SAP_Leadsheet!$G$19,IF(J$7<48,SAP_Leadsheet!$H$19,SAP_Leadsheet!$I$19))))))))) -> 0.013 | K13: =IF(K$7=12,SAP_Leadsheet!$E$20,IF(K$7=24,SAP_Leadsheet!$F$20,IF(K$7=36,SAP_Leadsheet!$G$20,IF(K$7=48,SAP_Leadsheet!$H$20,IF(K$7=60,SAP_Leadsheet!$I$20,IF(K$7<12,SAP_Leadsheet!$E$19,IF(K$7<24,SAP_Leadsheet!$F$19,IF(K$7<36,SAP_Leadsheet!$G$19,IF(K$7<48,SAP_Leadsheet!$H$19,SAP_Leadsheet!$I$19))))))))) -> 0.013 | L13: =IF(L$7=12,SAP_Leadsheet!$E$20,IF(L$7=24,SAP_Leadsheet!$F$20,IF(L$7=36,SAP_Leadsheet!$G$20,IF(L$7=48,SAP_Leadsheet!$H$20,IF(L$7=60,SAP_Leadsheet!$I$20,IF(L$7<12,SAP_Leadsheet!$E$19,IF(L$7<24,SAP_Leadsheet!$F$19,IF(L$7<36,SAP_Leadsheet!$G$19,IF(L$7<48,SAP_Leadsheet!$H$19,SAP_Leadsheet!$I$19))))))))) -> 0.013 | M13: =IF(M$7=12,SAP_Leadsheet!$E$20,IF(M$7=24,SAP_Leadsheet!$F$20,IF(M$7=36,SAP_Leadsheet!$G$20,IF(M$7=48,SAP_Leadsheet!$H$20,IF(M$7=60,SAP_Leadsheet!$I$20,IF(M$7<12,SAP_Leadsheet!$E$19,IF(M$7<24,SAP_Leadsheet!$F$19,IF(M$7<36,SAP_Leadsheet!$G$19,IF(M$7<48,SAP_Leadsheet!$H$19,SAP_Leadsheet!$I$19))))))))) -> 0.013 | N13: =IF(N$7=12,SAP_Leadsheet!$E$20,IF(N$7=24,SAP_Leadsheet!$F$20,IF(N$7=36,SAP_Leadsheet!$G$20,IF(N$7=48,SAP_Leadsheet!$H$20,IF(N$7=60,SAP_Leadsheet!$I$20,IF(N$7<12,SAP_Leadsheet!$E$19,IF(N$7<24,SAP_Leadsheet!$F$19,IF(N$7<36,SAP_Leadsheet!$G$19,IF(N$7<48,SAP_Leadsheet!$H$19,SAP_Leadsheet!$I$19))))))))) -> 0.013 | ... BN13: =IF(BN$7=12,SAP_Leadsheet!$E$20,IF(BN$7=24,SAP_Leadsheet!$F$20,IF(BN$7=36,SAP_Leadsheet!$G$20,IF(BN$7=48,SAP_Leadsheet!$H$20,IF(BN$7=60,SAP_Leadsheet!$I$20,IF(BN$7<12,SAP_Leadsheet!$E$19,IF(BN$7<24,SAP_Leadsheet!$F$19,IF(BN$7<36,SAP_Leadsheet!$G$19,IF(BN$7<48,SAP_Leadsheet!$H$19,SAP_Leadsheet!$I$19))))))))) -> 0.015
C15: # Activated Card | D15: Beginning Bal | F15: # Card | G15: 0 | H15: =G18 -> 0.977 | I15: =H18 -> 0.964 | J15: =I18 -> 0.951 | K15: =J18 -> 0.938 | L15: =K18 -> 0.925 | M15: =L18 -> 0.912 | N15: =M18 -> 0.899 | O15: =N18 -> 0.886 | ... BN15: =BM18 -> 0.279
D16: Newly activated card | F16: # Card | G16: =G12 -> 0.99 | H16: 0 | I16: 0 | J16: 0 | K16: 0 | L16: 0 | M16: 0 | N16: 0 | O16: 0 | P16: 0 | Q16: 0 | R16: 0 | S16: 0 | T16: 0 | U16: 0 | V16: 0 | W16: 0 | X16: 0 | Y16: 0 | Z16: 0 | AA16: 0 | AB16: 0 | AC16: 0 | AD16: 0 | AE16: 0 | AF16: 0 | AG16: 0 | AH16: 0 | AI16: 0 | AJ16: 0 | AK16: 0 | AL16: 0 | AM16: 0 | AN16: 0 | AO16: 0 | AP16: 0 | AQ16: 0 | AR16: 0 | AS16: 0 | AT16: 0 | AU16: 0 | AV16: 0 | AW16: 0 | AX16: 0 | AY16: 0 | AZ16: 0 | BA16: 0 | BB16: 0 | BC16: 0 | BD16: 0 | BE16: 0 | BF16: 0 | BG16: 0 | BH16: 0 | BI16: 0 | BJ16: 0 | BK16: 0 | BL16: 0 | BM16: 0 | BN16: 0
D17: Attrition # | F17: # Card | G17: =G13 -> 0.013 | H17: =H13 -> 0.013 | I17: =I13 -> 0.013 | J17: =J13 -> 0.013 | K17: =K13 -> 0.013 | L17: =L13 -> 0.013 | M17: =M13 -> 0.013 | N17: =N13 -> 0.013 | ... BN17: =BN13 -> 0.015
D18: Ending Bal | F18: # Card | G18: =G15+G16-G17 -> 0.977 | H18: =H15+H16-H17 -> 0.964 | I18: =I15+I16-I17 -> 0.951 | J18: =J15+J16-J17 -> 0.938 | K18: =K15+K16-K17 -> 0.925 | L18: =L15+L16-L17 -> 0.912 | M18: =M15+M16-M17 -> 0.899 | N18: =N15+N16-N17 -> 0.886 | ... BN18: =BN15+BN16-BN17 -> 0.264
D19: Avg Card | F19: # Card | G19: =AVERAGE(G18:G18) -> 0.977 | H19: =AVERAGE(G18:H18) -> 0.9705 | I19: =AVERAGE(H18:I18) -> 0.9575 | J19: =AVERAGE(I18:J18) -> 0.9445 | K19: =AVERAGE(J18:K18) -> 0.9315 | L19: =AVERAGE(K18:L18) -> 0.9185 | M19: =AVERAGE(L18:M18) -> 0.9055 | N19: =AVERAGE(M18:N18) -> 0.8925 | O19: =AVERAGE(N18:O18) -> 0.8795 | ... BN19: =AVERAGE(BM18:BN18) -> 0.2715
C21: Spending status | D21: Spd per activated card (Port) | F21: mVND | G21: =SAP_Leadsheet!E27 -> 5.8941158 | H21: =G21 -> 5.8941158 | I21: =H21 -> 5.8941158 | J21: =I21 -> 5.8941158 | K21: =J21 -> 5.8941158 | L21: =K21 -> 5.8941158 | M21: =L21 -> 5.8941158 | N21: =M21 -> 5.8941158 | O21: =N21 -> 5.8941158 | ... R21: =Q21 -> 5.8941158 | S21: =SAP_Leadsheet!F27 -> 5.8941158 | T21: =S21 -> 5.8941158 | U21: =T21 -> 5.8941158 | V21: =U21 -> 5.8941158 | W21: =V21 -> 5.8941158 | X21: =W21 -> 5.8941158 | Y21: =X21 -> 5.8941158 | Z21: =Y21 -> 5.8941158 | AA21: =Z21 -> 5.8941158 | ... AD21: =AC21 -> 5.8941158 | AE21: =SAP_Leadsheet!G27 -> 5.8941158 | AF21: =AE21 -> 5.8941158 | AG21: =AF21 -> 5.8941158 | AH21: =AG21 -> 5.8941158 | AI21: =AH21 -> 5.8941158 | AJ21: =AI21 -> 5.8941158 | AK21: =AJ21 -> 5.8941158 | AL21: =AK21 -> 5.8941158 | AM21: =AL21 -> 5.8941158 | ... AP21: =AO21 -> 5.8941158 | AQ21: =SAP_Leadsheet!H27 -> 5.8941158 | AR21: =AQ21 -> 5.8941158 | AS21: =AR21 -> 5.8941158 | AT21: =AS21 -> 5.8941158 | AU21: =AT21 -> 5.8941158 | AV21: =AU21 -> 5.8941158 | AW21: =AV21 -> 5.8941158 | AX21: =AW21 -> 5.8941158 | AY21: =AX21 -> 5.8941158 | ... BB21: =BA21 -> 5.8941158 | BC21: =SAP_Leadsheet!I27 -> 5.8941158 | BD21: =BC21 -> 5.8941158 | BE21: =BD21 -> 5.8941158 | BF21: =BE21 -> 5.8941158 | BG21: =BF21 -> 5.8941158 | BH21: =BG21 -> 5.8941158 | BI21: =BH21 -> 5.8941158 | BJ21: =BI21 -> 5.8941158 | BK21: =BJ21 -> 5.8941158 | ... BN21: =BM21 -> 5.8941158
D23: Card Port | F23: % | G23: 1 | H23: 1 | I23: 1 | J23: 1 | K23: 1 | L23: 1 | M23: 1 | N23: 1 | O23: 1 | P23: 1 | Q23: 1 | R23: 1 | S23: 1 | T23: 1 | U23: 1 | V23: 1 | W23: 1 | X23: 1 | Y23: 1 | Z23: 1 | AA23: 1 | AB23: 1 | AC23: 1 | AD23: 1 | AE23: 1 | AF23: 1 | AG23: 1 | AH23: 1 | AI23: 1 | AJ23: 1 | AK23: 1 | AL23: 1 | AM23: 1 | AN23: 1 | AO23: 1 | AP23: 1 | AQ23: 1 | AR23: 1 | AS23: 1 | AT23: 1 | AU23: 1 | AV23: 1 | AW23: 1 | AX23: 1 | AY23: 1 | AZ23: 1 | BA23: 1 | BB23: 1 | BC23: 1 | BD23: 1 | BE23: 1 | BF23: 1 | BG23: 1 | BH23: 1 | BI23: 1 | BJ23: 1 | BK23: 1 | BL23: 1 | BM23: 1 | BN23: 1
D24: Transactor | F24: % | G24: =1-G25 -> 0.46654165 | H24: =1-H25 -> 0.46654165 | I24: =1-I25 -> 0.46654165 | J24: =1-J25 -> 0.46654165 | K24: =1-K25 -> 0.46654165 | L24: =1-L25 -> 0.46654165 | M24: =1-M25 -> 0.46654165 | N24: =1-N25 -> 0.46654165 | ... BN24: =1-BN25 -> 0.46654165
D25: Revolver | F25: % | G25: =SAP_Leadsheet!$E$33 -> 0.53345835 | H25: =SAP_Leadsheet!$E$33 -> 0.53345835 | I25: =SAP_Leadsheet!$E$33 -> 0.53345835 | J25: =SAP_Leadsheet!$E$33 -> 0.53345835 | K25: =SAP_Leadsheet!$E$33 -> 0.53345835 | L25: =SAP_Leadsheet!$E$33 -> 0.53345835 | M25: =SAP_Leadsheet!$E$33 -> 0.53345835 | N25: =SAP_Leadsheet!$E$33 -> 0.53345835 | ... BN25: =SAP_Leadsheet!$E$33 -> 0.53345835
B27: EMI (Installment)
C29: EMI PORT
C30: CASH installment
D31: Beginning Bal | F31: milVND | G31: 0 | H31: =G156 -> 0 | I31: =H156 -> 0 | J31: =I156 -> 0 | K31: =J156 -> 0 | L31: =K156 -> 0 | M31: =L156 -> 0 | N31: =M156 -> 0 | O31: =N156 -> 0 | ... BN31: =BM156 -> 0
D32: New Billing | F32: milVND | G32: =IF(AND(SAP_Leadsheet!$C$10="EMI",G$7<60+2-SAP_Leadsheet!$E$71),SAP_Spreadsheet!G$611*SAP_Leadsheet!$E$70,0) -> 0 | H32: =IF(AND(SAP_Leadsheet!$C$10="EMI",H$7<60+2-SAP_Leadsheet!$E$71),SAP_Spreadsheet!H$611*SAP_Leadsheet!$E$70,0) -> 0 | I32: =IF(AND(SAP_Leadsheet!$C$10="EMI",I$7<60+2-SAP_Leadsheet!$E$71),SAP_Spreadsheet!I$611*SAP_Leadsheet!$E$70,0) -> 0 | J32: =IF(AND(SAP_Leadsheet!$C$10="EMI",J$7<60+2-SAP_Leadsheet!$E$71),SAP_Spreadsheet!J$611*SAP_Leadsheet!$E$70,0) -> 0 | K32: =IF(AND(SAP_Leadsheet!$C$10="EMI",K$7<60+2-SAP_Leadsheet!$E$71),SAP_Spreadsheet!K$611*SAP_Leadsheet!$E$70,0) -> 0 | L32: =IF(AND(SAP_Leadsheet!$C$10="EMI",L$7<60+2-SAP_Leadsheet!$E$71),SAP_Spreadsheet!L$611*SAP_Leadsheet!$E$70,0) -> 0 | M32: =IF(AND(SAP_Leadsheet!$C$10="EMI",M$7<60+2-SAP_Leadsheet!$E$71),SAP_Spreadsheet!M$611*SAP_Leadsheet!$E$70,0) -> 0 | N32: =IF(AND(SAP_Leadsheet!$C$10="EMI",N$7<60+2-SAP_Leadsheet!$E$71),SAP_Spreadsheet!N$611*SAP_Leadsheet!$E$70,0) -> 0 | ... BN32: =IF(AND(SAP_Leadsheet!$C$10="EMI",BN$7<60+2-SAP_Leadsheet!$E$71),SAP_Spreadsheet!BN$611*SAP_Leadsheet!$E$70,0) -> 0
D33: Paid off | F33: milVND | G33: =G34+G95 -> 0 | H33: =H34+H95 -> 0 | I33: =I34+I95 -> 0 | J33: =J34+J95 -> 0 | K33: =K34+K95 -> 0 | L33: =L34+L95 -> 0 | M33: =M34+M95 -> 0 | N33: =N34+N95 -> 0 | ... BN33: =BN34+BN95 -> 0
D34: Early payment | F34: milVND | G34: =-SUM(G35:G94) -> 0 | H34: =-SUM(H35:H94) -> 0 | I34: =-SUM(I35:I94) -> 0 | J34: =-SUM(J35:J94) -> 0 | K34: =-SUM(K35:K94) -> 0 | L34: =-SUM(L35:L94) -> 0 | M34: =-SUM(M35:M94) -> 0 | N34: =-SUM(N35:N94) -> 0 | ... BN34: =-SUM(BN35:BN94) -> 0
C35: {=TRANSPOSE(G$7:BN$7)} -> 1 | G35: =IF(OR($C96>G$7,$C96+$E96-2<G$7),0,($D96-SUM($F96:F96)-SUM($F35:F35))*SAP_Leadsheet!$E$75) -> 0 | H35: =IF(OR($C96>H$7,$C96+$E96-2<H$7),0,($D96-SUM($F96:G96)-SUM($F35:G35))*SAP_Leadsheet!$E$75) -> 0 | I35: =IF(OR($C96>I$7,$C96+$E96-2<I$7),0,($D96-SUM($F96:H96)-SUM($F35:H35))*SAP_Leadsheet!$E$75) -> 0 | J35: =IF(OR($C96>J$7,$C96+$E96-2<J$7),0,($D96-SUM($F96:I96)-SUM($F35:I35))*SAP_Leadsheet!$E$75) -> 0 | K35: =IF(OR($C96>K$7,$C96+$E96-2<K$7),0,($D96-SUM($F96:J96)-SUM($F35:J35))*SAP_Leadsheet!$E$75) -> 0 | L35: =IF(OR($C96>L$7,$C96+$E96-2<L$7),0,($D96-SUM($F96:K96)-SUM($F35:K35))*SAP_Leadsheet!$E$75) -> 0 | M35: =IF(OR($C96>M$7,$C96+$E96-2<M$7),0,($D96-SUM($F96:L96)-SUM($F35:L35))*SAP_Leadsheet!$E$75) -> 0 | N35: =IF(OR($C96>N$7,$C96+$E96-2<N$7),0,($D96-SUM($F96:M96)-SUM($F35:M35))*SAP_Leadsheet!$E$75) -> 0 | ... BN35: =IF(OR($C96>BN$7,$C96+$E96-2<BN$7),0,($D96-SUM($F96:BM96)-SUM($F35:BM35))*SAP_Leadsheet!$E$75) -> 0
C36: 2 | G36: =IF(OR($C97>G$7,$C97+$E97-2<G$7),0,($D97-SUM($F97:F97)-SUM($F36:F36))*SAP_Leadsheet!$E$75) -> 0 | H36: =IF(OR($C97>H$7,$C97+$E97-2<H$7),0,($D97-SUM($F97:G97)-SUM($F36:G36))*SAP_Leadsheet!$E$75) -> 0 | I36: =IF(OR($C97>I$7,$C97+$E97-2<I$7),0,($D97-SUM($F97:H97)-SUM($F36:H36))*SAP_Leadsheet!$E$75) -> 0 | J36: =IF(OR($C97>J$7,$C97+$E97-2<J$7),0,($D97-SUM($F97:I97)-SUM($F36:I36))*SAP_Leadsheet!$E$75) -> 0 | K36: =IF(OR($C97>K$7,$C97+$E97-2<K$7),0,($D97-SUM($F97:J97)-SUM($F36:J36))*SAP_Leadsheet!$E$75) -> 0 | L36: =IF(OR($C97>L$7,$C97+$E97-2<L$7),0,($D97-SUM($F97:K97)-SUM($F36:K36))*SAP_Leadsheet!$E$75) -> 0 | M36: =IF(OR($C97>M$7,$C97+$E97-2<M$7),0,($D97-SUM($F97:L97)-SUM($F36:L36))*SAP_Leadsheet!$E$75) -> 0 | N36: =IF(OR($C97>N$7,$C97+$E97-2<N$7),0,($D97-SUM($F97:M97)-SUM($F36:M36))*SAP_Leadsheet!$E$75) -> 0 | ... BN36: =IF(OR($C97>BN$7,$C97+$E97-2<BN$7),0,($D97-SUM($F97:BM97)-SUM($F36:BM36))*SAP_Leadsheet!$E$75) -> 0
C37: 3 | G37: =IF(OR($C98>G$7,$C98+$E98-2<G$7),0,($D98-SUM($F98:F98)-SUM($F37:F37))*SAP_Leadsheet!$E$75) -> 0 | H37: =IF(OR($C98>H$7,$C98+$E98-2<H$7),0,($D98-SUM($F98:G98)-SUM($F37:G37))*SAP_Leadsheet!$E$75) -> 0 | I37: =IF(OR($C98>I$7,$C98+$E98-2<I$7),0,($D98-SUM($F98:H98)-SUM($F37:H37))*SAP_Leadsheet!$E$75) -> 0 | J37: =IF(OR($C98>J$7,$C98+$E98-2<J$7),0,($D98-SUM($F98:I98)-SUM($F37:I37))*SAP_Leadsheet!$E$75) -> 0 | K37: =IF(OR($C98>K$7,$C98+$E98-2<K$7),0,($D98-SUM($F98:J98)-SUM($F37:J37))*SAP_Leadsheet!$E$75) -> 0 | L37: =IF(OR($C98>L$7,$C98+$E98-2<L$7),0,($D98-SUM($F98:K98)-SUM($F37:K37))*SAP_Leadsheet!$E$75) -> 0 | M37: =IF(OR($C98>M$7,$C98+$E98-2<M$7),0,($D98-SUM($F98:L98)-SUM($F37:L37))*SAP_Leadsheet!$E$75) -> 0 | N37: =IF(OR($C98>N$7,$C98+$E98-2<N$7),0,($D98-SUM($F98:M98)-SUM($F37:M37))*SAP_Leadsheet!$E$75) -> 0 | ... BN37: =IF(OR($C98>BN$7,$C98+$E98-2<BN$7),0,($D98-SUM($F98:BM98)-SUM($F37:BM37))*SAP_Leadsheet!$E$75) -> 0
C38: 4 | G38: =IF(OR($C99>G$7,$C99+$E99-2<G$7),0,($D99-SUM($F99:F99)-SUM($F38:F38))*SAP_Leadsheet!$E$75) -> 0 | H38: =IF(OR($C99>H$7,$C99+$E99-2<H$7),0,($D99-SUM($F99:G99)-SUM($F38:G38))*SAP_Leadsheet!$E$75) -> 0 | I38: =IF(OR($C99>I$7,$C99+$E99-2<I$7),0,($D99-SUM($F99:H99)-SUM($F38:H38))*SAP_Leadsheet!$E$75) -> 0 | J38: =IF(OR($C99>J$7,$C99+$E99-2<J$7),0,($D99-SUM($F99:I99)-SUM($F38:I38))*SAP_Leadsheet!$E$75) -> 0 | K38: =IF(OR($C99>K$7,$C99+$E99-2<K$7),0,($D99-SUM($F99:J99)-SUM($F38:J38))*SAP_Leadsheet!$E$75) -> 0 | L38: =IF(OR($C99>L$7,$C99+$E99-2<L$7),0,($D99-SUM($F99:K99)-SUM($F38:K38))*SAP_Leadsheet!$E$75) -> 0 | M38: =IF(OR($C99>M$7,$C99+$E99-2<M$7),0,($D99-SUM($F99:L99)-SUM($F38:L38))*SAP_Leadsheet!$E$75) -> 0 | N38: =IF(OR($C99>N$7,$C99+$E99-2<N$7),0,($D99-SUM($F99:M99)-SUM($F38:M38))*SAP_Leadsheet!$E$75) -> 0 | ... BN38: =IF(OR($C99>BN$7,$C99+$E99-2<BN$7),0,($D99-SUM($F99:BM99)-SUM($F38:BM38))*SAP_Leadsheet!$E$75) -> 0
C39: 5 | G39: =IF(OR($C100>G$7,$C100+$E100-2<G$7),0,($D100-SUM($F100:F100)-SUM($F39:F39))*SAP_Leadsheet!$E$75) -> 0 | H39: =IF(OR($C100>H$7,$C100+$E100-2<H$7),0,($D100-SUM($F100:G100)-SUM($F39:G39))*SAP_Leadsheet!$E$75) -> 0 | I39: =IF(OR($C100>I$7,$C100+$E100-2<I$7),0,($D100-SUM($F100:H100)-SUM($F39:H39))*SAP_Leadsheet!$E$75) -> 0 | J39: =IF(OR($C100>J$7,$C100+$E100-2<J$7),0,($D100-SUM($F100:I100)-SUM($F39:I39))*SAP_Leadsheet!$E$75) -> 0 | K39: =IF(OR($C100>K$7,$C100+$E100-2<K$7),0,($D100-SUM($F100:J100)-SUM($F39:J39))*SAP_Leadsheet!$E$75) -> 0 | L39: =IF(OR($C100>L$7,$C100+$E100-2<L$7),0,($D100-SUM($F100:K100)-SUM($F39:K39))*SAP_Leadsheet!$E$75) -> 0 | M39: =IF(OR($C100>M$7,$C100+$E100-2<M$7),0,($D100-SUM($F100:L100)-SUM($F39:L39))*SAP_Leadsheet!$E$75) -> 0 | N39: =IF(OR($C100>N$7,$C100+$E100-2<N$7),0,($D100-SUM($F100:M100)-SUM($F39:M39))*SAP_Leadsheet!$E$75) -> 0 | ... BN39: =IF(OR($C100>BN$7,$C100+$E100-2<BN$7),0,($D100-SUM($F100:BM100)-SUM($F39:BM39))*SAP_Leadsheet!$E$75) -> 0
C40: 6 | G40: =IF(OR($C101>G$7,$C101+$E101-2<G$7),0,($D101-SUM($F101:F101)-SUM($F40:F40))*SAP_Leadsheet!$E$75) -> 0 | H40: =IF(OR($C101>H$7,$C101+$E101-2<H$7),0,($D101-SUM($F101:G101)-SUM($F40:G40))*SAP_Leadsheet!$E$75) -> 0 | I40: =IF(OR($C101>I$7,$C101+$E101-2<I$7),0,($D101-SUM($F101:H101)-SUM($F40:H40))*SAP_Leadsheet!$E$75) -> 0 | J40: =IF(OR($C101>J$7,$C101+$E101-2<J$7),0,($D101-SUM($F101:I101)-SUM($F40:I40))*SAP_Leadsheet!$E$75) -> 0 | K40: =IF(OR($C101>K$7,$C101+$E101-2<K$7),0,($D101-SUM($F101:J101)-SUM($F40:J40))*SAP_Leadsheet!$E$75) -> 0 | L40: =IF(OR($C101>L$7,$C101+$E101-2<L$7),0,($D101-SUM($F101:K101)-SUM($F40:K40))*SAP_Leadsheet!$E$75) -> 0 | M40: =IF(OR($C101>M$7,$C101+$E101-2<M$7),0,($D101-SUM($F101:L101)-SUM($F40:L40))*SAP_Leadsheet!$E$75) -> 0 | N40: =IF(OR($C101>N$7,$C101+$E101-2<N$7),0,($D101-SUM($F101:M101)-SUM($F40:M40))*SAP_Leadsheet!$E$75) -> 0 | ... BN40: =IF(OR($C101>BN$7,$C101+$E101-2<BN$7),0,($D101-SUM($F101:BM101)-SUM($F40:BM40))*SAP_Leadsheet!$E$75) -> 0
C41: 7 | G41: =IF(OR($C102>G$7,$C102+$E102-2<G$7),0,($D102-SUM($F102:F102)-SUM($F41:F41))*SAP_Leadsheet!$E$75) -> 0 | H41: =IF(OR($C102>H$7,$C102+$E102-2<H$7),0,($D102-SUM($F102:G102)-SUM($F41:G41))*SAP_Leadsheet!$E$75) -> 0 | I41: =IF(OR($C102>I$7,$C102+$E102-2<I$7),0,($D102-SUM($F102:H102)-SUM($F41:H41))*SAP_Leadsheet!$E$75) -> 0 | J41: =IF(OR($C102>J$7,$C102+$E102-2<J$7),0,($D102-SUM($F102:I102)-SUM($F41:I41))*SAP_Leadsheet!$E$75) -> 0 | K41: =IF(OR($C102>K$7,$C102+$E102-2<K$7),0,($D102-SUM($F102:J102)-SUM($F41:J41))*SAP_Leadsheet!$E$75) -> 0 | L41: =IF(OR($C102>L$7,$C102+$E102-2<L$7),0,($D102-SUM($F102:K102)-SUM($F41:K41))*SAP_Leadsheet!$E$75) -> 0 | M41: =IF(OR($C102>M$7,$C102+$E102-2<M$7),0,($D102-SUM($F102:L102)-SUM($F41:L41))*SAP_Leadsheet!$E$75) -> 0 | N41: =IF(OR($C102>N$7,$C102+$E102-2<N$7),0,($D102-SUM($F102:M102)-SUM($F41:M41))*SAP_Leadsheet!$E$75) -> 0 | ... BN41: =IF(OR($C102>BN$7,$C102+$E102-2<BN$7),0,($D102-SUM($F102:BM102)-SUM($F41:BM41))*SAP_Leadsheet!$E$75) -> 0
C42: 8 | G42: =IF(OR($C103>G$7,$C103+$E103-2<G$7),0,($D103-SUM($F103:F103)-SUM($F42:F42))*SAP_Leadsheet!$E$75) -> 0 | H42: =IF(OR($C103>H$7,$C103+$E103-2<H$7),0,($D103-SUM($F103:G103)-SUM($F42:G42))*SAP_Leadsheet!$E$75) -> 0 | I42: =IF(OR($C103>I$7,$C103+$E103-2<I$7),0,($D103-SUM($F103:H103)-SUM($F42:H42))*SAP_Leadsheet!$E$75) -> 0 | J42: =IF(OR($C103>J$7,$C103+$E103-2<J$7),0,($D103-SUM($F103:I103)-SUM($F42:I42))*SAP_Leadsheet!$E$75) -> 0 | K42: =IF(OR($C103>K$7,$C103+$E103-2<K$7),0,($D103-SUM($F103:J103)-SUM($F42:J42))*SAP_Leadsheet!$E$75) -> 0 | L42: =IF(OR($C103>L$7,$C103+$E103-2<L$7),0,($D103-SUM($F103:K103)-SUM($F42:K42))*SAP_Leadsheet!$E$75) -> 0 | M42: =IF(OR($C103>M$7,$C103+$E103-2<M$7),0,($D103-SUM($F103:L103)-SUM($F42:L42))*SAP_Leadsheet!$E$75) -> 0 | N42: =IF(OR($C103>N$7,$C103+$E103-2<N$7),0,($D103-SUM($F103:M103)-SUM($F42:M42))*SAP_Leadsheet!$E$75) -> 0 | ... BN42: =IF(OR($C103>BN$7,$C103+$E103-2<BN$7),0,($D103-SUM($F103:BM103)-SUM($F42:BM42))*SAP_Leadsheet!$E$75) -> 0
C43: 9 | G43: =IF(OR($C104>G$7,$C104+$E104-2<G$7),0,($D104-SUM($F104:F104)-SUM($F43:F43))*SAP_Leadsheet!$E$75) -> 0 | H43: =IF(OR($C104>H$7,$C104+$E104-2<H$7),0,($D104-SUM($F104:G104)-SUM($F43:G43))*SAP_Leadsheet!$E$75) -> 0 | I43: =IF(OR($C104>I$7,$C104+$E104-2<I$7),0,($D104-SUM($F104:H104)-SUM($F43:H43))*SAP_Leadsheet!$E$75) -> 0 | J43: =IF(OR($C104>J$7,$C104+$E104-2<J$7),0,($D104-SUM($F104:I104)-SUM($F43:I43))*SAP_Leadsheet!$E$75) -> 0 | K43: =IF(OR($C104>K$7,$C104+$E104-2<K$7),0,($D104-SUM($F104:J104)-SUM($F43:J43))*SAP_Leadsheet!$E$75) -> 0 | L43: =IF(OR($C104>L$7,$C104+$E104-2<L$7),0,($D104-SUM($F104:K104)-SUM($F43:K43))*SAP_Leadsheet!$E$75) -> 0 | M43: =IF(OR($C104>M$7,$C104+$E104-2<M$7),0,($D104-SUM($F104:L104)-SUM($F43:L43))*SAP_Leadsheet!$E$75) -> 0 | N43: =IF(OR($C104>N$7,$C104+$E104-2<N$7),0,($D104-SUM($F104:M104)-SUM($F43:M43))*SAP_Leadsheet!$E$75) -> 0 | ... BN43: =IF(OR($C104>BN$7,$C104+$E104-2<BN$7),0,($D104-SUM($F104:BM104)-SUM($F43:BM43))*SAP_Leadsheet!$E$75) -> 0
C44: 10 | G44: =IF(OR($C105>G$7,$C105+$E105-2<G$7),0,($D105-SUM($F105:F105)-SUM($F44:F44))*SAP_Leadsheet!$E$75) -> 0 | H44: =IF(OR($C105>H$7,$C105+$E105-2<H$7),0,($D105-SUM($F105:G105)-SUM($F44:G44))*SAP_Leadsheet!$E$75) -> 0 | I44: =IF(OR($C105>I$7,$C105+$E105-2<I$7),0,($D105-SUM($F105:H105)-SUM($F44:H44))*SAP_Leadsheet!$E$75) -> 0 | J44: =IF(OR($C105>J$7,$C105+$E105-2<J$7),0,($D105-SUM($F105:I105)-SUM($F44:I44))*SAP_Leadsheet!$E$75) -> 0 | K44: =IF(OR($C105>K$7,$C105+$E105-2<K$7),0,($D105-SUM($F105:J105)-SUM($F44:J44))*SAP_Leadsheet!$E$75) -> 0 | L44: =IF(OR($C105>L$7,$C105+$E105-2<L$7),0,($D105-SUM($F105:K105)-SUM($F44:K44))*SAP_Leadsheet!$E$75) -> 0 | M44: =IF(OR($C105>M$7,$C105+$E105-2<M$7),0,($D105-SUM($F105:L105)-SUM($F44:L44))*SAP_Leadsheet!$E$75) -> 0 | N44: =IF(OR($C105>N$7,$C105+$E105-2<N$7),0,($D105-SUM($F105:M105)-SUM($F44:M44))*SAP_Leadsheet!$E$75) -> 0 | ... BN44: =IF(OR($C105>BN$7,$C105+$E105-2<BN$7),0,($D105-SUM($F105:BM105)-SUM($F44:BM44))*SAP_Leadsheet!$E$75) -> 0
C45: 11 | G45: =IF(OR($C106>G$7,$C106+$E106-2<G$7),0,($D106-SUM($F106:F106)-SUM($F45:F45))*SAP_Leadsheet!$E$75) -> 0 | H45: =IF(OR($C106>H$7,$C106+$E106-2<H$7),0,($D106-SUM($F106:G106)-SUM($F45:G45))*SAP_Leadsheet!$E$75) -> 0 | I45: =IF(OR($C106>I$7,$C106+$E106-2<I$7),0,($D106-SUM($F106:H106)-SUM($F45:H45))*SAP_Leadsheet!$E$75) -> 0 | J45: =IF(OR($C106>J$7,$C106+$E106-2<J$7),0,($D106-SUM($F106:I106)-SUM($F45:I45))*SAP_Leadsheet!$E$75) -> 0 | K45: =IF(OR($C106>K$7,$C106+$E106-2<K$7),0,($D106-SUM($F106:J106)-SUM($F45:J45))*SAP_Leadsheet!$E$75) -> 0 | L45: =IF(OR($C106>L$7,$C106+$E106-2<L$7),0,($D106-SUM($F106:K106)-SUM($F45:K45))*SAP_Leadsheet!$E$75) -> 0 | M45: =IF(OR($C106>M$7,$C106+$E106-2<M$7),0,($D106-SUM($F106:L106)-SUM($F45:L45))*SAP_Leadsheet!$E$75) -> 0 | N45: =IF(OR($C106>N$7,$C106+$E106-2<N$7),0,($D106-SUM($F106:M106)-SUM($F45:M45))*SAP_Leadsheet!$E$75) -> 0 | ... BN45: =IF(OR($C106>BN$7,$C106+$E106-2<BN$7),0,($D106-SUM($F106:BM106)-SUM($F45:BM45))*SAP_Leadsheet!$E$75) -> 0
C46: 12 | G46: =IF(OR($C107>G$7,$C107+$E107-2<G$7),0,($D107-SUM($F107:F107)-SUM($F46:F46))*SAP_Leadsheet!$E$75) -> 0 | H46: =IF(OR($C107>H$7,$C107+$E107-2<H$7),0,($D107-SUM($F107:G107)-SUM($F46:G46))*SAP_Leadsheet!$E$75) -> 0 | I46: =IF(OR($C107>I$7,$C107+$E107-2<I$7),0,($D107-SUM($F107:H107)-SUM($F46:H46))*SAP_Leadsheet!$E$75) -> 0 | J46: =IF(OR($C107>J$7,$C107+$E107-2<J$7),0,($D107-SUM($F107:I107)-SUM($F46:I46))*SAP_Leadsheet!$E$75) -> 0 | K46: =IF(OR($C107>K$7,$C107+$E107-2<K$7),0,($D107-SUM($F107:J107)-SUM($F46:J46))*SAP_Leadsheet!$E$75) -> 0 | L46: =IF(OR($C107>L$7,$C107+$E107-2<L$7),0,($D107-SUM($F107:K107)-SUM($F46:K46))*SAP_Leadsheet!$E$75) -> 0 | M46: =IF(OR($C107>M$7,$C107+$E107-2<M$7),0,($D107-SUM($F107:L107)-SUM($F46:L46))*SAP_Leadsheet!$E$75) -> 0 | N46: =IF(OR($C107>N$7,$C107+$E107-2<N$7),0,($D107-SUM($F107:M107)-SUM($F46:M46))*SAP_Leadsheet!$E$75) -> 0 | ... BN46: =IF(OR($C107>BN$7,$C107+$E107-2<BN$7),0,($D107-SUM($F107:BM107)-SUM($F46:BM46))*SAP_Leadsheet!$E$75) -> 0
C47: 13 | G47: =IF(OR($C108>G$7,$C108+$E108-2<G$7),0,($D108-SUM($F108:F108)-SUM($F47:F47))*SAP_Leadsheet!$E$75) -> 0 | H47: =IF(OR($C108>H$7,$C108+$E108-2<H$7),0,($D108-SUM($F108:G108)-SUM($F47:G47))*SAP_Leadsheet!$E$75) -> 0 | I47: =IF(OR($C108>I$7,$C108+$E108-2<I$7),0,($D108-SUM($F108:H108)-SUM($F47:H47))*SAP_Leadsheet!$E$75) -> 0 | J47: =IF(OR($C108>J$7,$C108+$E108-2<J$7),0,($D108-SUM($F108:I108)-SUM($F47:I47))*SAP_Leadsheet!$E$75) -> 0 | K47: =IF(OR($C108>K$7,$C108+$E108-2<K$7),0,($D108-SUM($F108:J108)-SUM($F47:J47))*SAP_Leadsheet!$E$75) -> 0 | L47: =IF(OR($C108>L$7,$C108+$E108-2<L$7),0,($D108-SUM($F108:K108)-SUM($F47:K47))*SAP_Leadsheet!$E$75) -> 0 | M47: =IF(OR($C108>M$7,$C108+$E108-2<M$7),0,($D108-SUM($F108:L108)-SUM($F47:L47))*SAP_Leadsheet!$E$75) -> 0 | N47: =IF(OR($C108>N$7,$C108+$E108-2<N$7),0,($D108-SUM($F108:M108)-SUM($F47:M47))*SAP_Leadsheet!$E$75) -> 0 | ... BN47: =IF(OR($C108>BN$7,$C108+$E108-2<BN$7),0,($D108-SUM($F108:BM108)-SUM($F47:BM47))*SAP_Leadsheet!$E$75) -> 0
... C94: 60 | G94: =IF(OR($C155>G$7,$C155+$E155-2<G$7),0,($D155-SUM($F155:F155)-SUM($F94:F94))*SAP_Leadsheet!$E$75) -> 0 | H94: =IF(OR($C155>H$7,$C155+$E155-2<H$7),0,($D155-SUM($F155:G155)-SUM($F94:G94))*SAP_Leadsheet!$E$75) -> 0 | I94: =IF(OR($C155>I$7,$C155+$E155-2<I$7),0,($D155-SUM($F155:H155)-SUM($F94:H94))*SAP_Leadsheet!$E$75) -> 0 | J94: =IF(OR($C155>J$7,$C155+$E155-2<J$7),0,($D155-SUM($F155:I155)-SUM($F94:I94))*SAP_Leadsheet!$E$75) -> 0 | K94: =IF(OR($C155>K$7,$C155+$E155-2<K$7),0,($D155-SUM($F155:J155)-SUM($F94:J94))*SAP_Leadsheet!$E$75) -> 0 | L94: =IF(OR($C155>L$7,$C155+$E155-2<L$7),0,($D155-SUM($F155:K155)-SUM($F94:K94))*SAP_Leadsheet!$E$75) -> 0 | M94: =IF(OR($C155>M$7,$C155+$E155-2<M$7),0,($D155-SUM($F155:L155)-SUM($F94:L94))*SAP_Leadsheet!$E$75) -> 0 | N94: =IF(OR($C155>N$7,$C155+$E155-2<N$7),0,($D155-SUM($F155:M155)-SUM($F94:M94))*SAP_Leadsheet!$E$75) -> 0 | ... BN94: =IF(OR($C155>BN$7,$C155+$E155-2<BN$7),0,($D155-SUM($F155:BM155)-SUM($F94:BM94))*SAP_Leadsheet!$E$75) -> 0
D95: Normal payment | F95: milVND | G95: =-SUM(G96:G155) -> 0 | H95: =-SUM(H96:H155) -> 0 | I95: =-SUM(I96:I155) -> 0 | J95: =-SUM(J96:J155) -> 0 | K95: =-SUM(K96:K155) -> 0 | L95: =-SUM(L96:L155) -> 0 | M95: =-SUM(M96:M155) -> 0 | N95: =-SUM(N96:N155) -> 0 | ... BN95: =-SUM(BN96:BN155) -> 0
C96: {=TRANSPOSE(G$7:BN$7)} -> 1 | D96: {=TRANSPOSE(G32:BN32)} -> 0 | E96: =SAP_Leadsheet!E71 -> 0 | G96: =IF(OR($C96>G$7,$C96+$E96-1<G$7),0,($D96-SUM($F96:F96)-SUM($F35:F35))/($E96+$C96-G$7)) -> 0 | H96: =IF(OR($C96>H$7,$C96+$E96-1<H$7),0,($D96-SUM($F96:G96)-SUM($F35:G35))/($E96+$C96-H$7)) -> 0 | I96: =IF(OR($C96>I$7,$C96+$E96-1<I$7),0,($D96-SUM($F96:H96)-SUM($F35:H35))/($E96+$C96-I$7)) -> 0 | J96: =IF(OR($C96>J$7,$C96+$E96-1<J$7),0,($D96-SUM($F96:I96)-SUM($F35:I35))/($E96+$C96-J$7)) -> 0 | K96: =IF(OR($C96>K$7,$C96+$E96-1<K$7),0,($D96-SUM($F96:J96)-SUM($F35:J35))/($E96+$C96-K$7)) -> 0 | L96: =IF(OR($C96>L$7,$C96+$E96-1<L$7),0,($D96-SUM($F96:K96)-SUM($F35:K35))/($E96+$C96-L$7)) -> 0 | M96: =IF(OR($C96>M$7,$C96+$E96-1<M$7),0,($D96-SUM($F96:L96)-SUM($F35:L35))/($E96+$C96-M$7)) -> 0 | N96: =IF(OR($C96>N$7,$C96+$E96-1<N$7),0,($D96-SUM($F96:M96)-SUM($F35:M35))/($E96+$C96-N$7)) -> 0 | ... BN96: =IF(OR($C96>BN$7,$C96+$E96-1<BN$7),0,($D96-SUM($F96:BM96)-SUM($F35:BM35))/($E96+$C96-BN$7)) -> 0
C97: 2 | D97: 0 | E97: =E96 -> 0 | G97: =IF(OR($C97>G$7,$C97+$E97-1<G$7),0,($D97-SUM($F97:F97)-SUM($F36:F36))/($E97+$C97-G$7)) -> 0 | H97: =IF(OR($C97>H$7,$C97+$E97-1<H$7),0,($D97-SUM($F97:G97)-SUM($F36:G36))/($E97+$C97-H$7)) -> 0 | I97: =IF(OR($C97>I$7,$C97+$E97-1<I$7),0,($D97-SUM($F97:H97)-SUM($F36:H36))/($E97+$C97-I$7)) -> 0 | J97: =IF(OR($C97>J$7,$C97+$E97-1<J$7),0,($D97-SUM($F97:I97)-SUM($F36:I36))/($E97+$C97-J$7)) -> 0 | K97: =IF(OR($C97>K$7,$C97+$E97-1<K$7),0,($D97-SUM($F97:J97)-SUM($F36:J36))/($E97+$C97-K$7)) -> 0 | L97: =IF(OR($C97>L$7,$C97+$E97-1<L$7),0,($D97-SUM($F97:K97)-SUM($F36:K36))/($E97+$C97-L$7)) -> 0 | M97: =IF(OR($C97>M$7,$C97+$E97-1<M$7),0,($D97-SUM($F97:L97)-SUM($F36:L36))/($E97+$C97-M$7)) -> 0 | N97: =IF(OR($C97>N$7,$C97+$E97-1<N$7),0,($D97-SUM($F97:M97)-SUM($F36:M36))/($E97+$C97-N$7)) -> 0 | ... BN97: =IF(OR($C97>BN$7,$C97+$E97-1<BN$7),0,($D97-SUM($F97:BM97)-SUM($F36:BM36))/($E97+$C97-BN$7)) -> 0
C98: 3 | D98: 0 | E98: =E97 -> 0 | G98: =IF(OR($C98>G$7,$C98+$E98-1<G$7),0,($D98-SUM($F98:F98)-SUM($F37:F37))/($E98+$C98-G$7)) -> 0 | H98: =IF(OR($C98>H$7,$C98+$E98-1<H$7),0,($D98-SUM($F98:G98)-SUM($F37:G37))/($E98+$C98-H$7)) -> 0 | I98: =IF(OR($C98>I$7,$C98+$E98-1<I$7),0,($D98-SUM($F98:H98)-SUM($F37:H37))/($E98+$C98-I$7)) -> 0 | J98: =IF(OR($C98>J$7,$C98+$E98-1<J$7),0,($D98-SUM($F98:I98)-SUM($F37:I37))/($E98+$C98-J$7)) -> 0 | K98: =IF(OR($C98>K$7,$C98+$E98-1<K$7),0,($D98-SUM($F98:J98)-SUM($F37:J37))/($E98+$C98-K$7)) -> 0 | L98: =IF(OR($C98>L$7,$C98+$E98-1<L$7),0,($D98-SUM($F98:K98)-SUM($F37:K37))/($E98+$C98-L$7)) -> 0 | M98: =IF(OR($C98>M$7,$C98+$E98-1<M$7),0,($D98-SUM($F98:L98)-SUM($F37:L37))/($E98+$C98-M$7)) -> 0 | N98: =IF(OR($C98>N$7,$C98+$E98-1<N$7),0,($D98-SUM($F98:M98)-SUM($F37:M37))/($E98+$C98-N$7)) -> 0 | ... BN98: =IF(OR($C98>BN$7,$C98+$E98-1<BN$7),0,($D98-SUM($F98:BM98)-SUM($F37:BM37))/($E98+$C98-BN$7)) -> 0
C99: 4 | D99: 0 | E99: =E98 -> 0 | G99: =IF(OR($C99>G$7,$C99+$E99-1<G$7),0,($D99-SUM($F99:F99)-SUM($F38:F38))/($E99+$C99-G$7)) -> 0 | H99: =IF(OR($C99>H$7,$C99+$E99-1<H$7),0,($D99-SUM($F99:G99)-SUM($F38:G38))/($E99+$C99-H$7)) -> 0 | I99: =IF(OR($C99>I$7,$C99+$E99-1<I$7),0,($D99-SUM($F99:H99)-SUM($F38:H38))/($E99+$C99-I$7)) -> 0 | J99: =IF(OR($C99>J$7,$C99+$E99-1<J$7),0,($D99-SUM($F99:I99)-SUM($F38:I38))/($E99+$C99-J$7)) -> 0 | K99: =IF(OR($C99>K$7,$C99+$E99-1<K$7),0,($D99-SUM($F99:J99)-SUM($F38:J38))/($E99+$C99-K$7)) -> 0 | L99: =IF(OR($C99>L$7,$C99+$E99-1<L$7),0,($D99-SUM($F99:K99)-SUM($F38:K38))/($E99+$C99-L$7)) -> 0 | M99: =IF(OR($C99>M$7,$C99+$E99-1<M$7),0,($D99-SUM($F99:L99)-SUM($F38:L38))/($E99+$C99-M$7)) -> 0 | N99: =IF(OR($C99>N$7,$C99+$E99-1<N$7),0,($D99-SUM($F99:M99)-SUM($F38:M38))/($E99+$C99-N$7)) -> 0 | ... BN99: =IF(OR($C99>BN$7,$C99+$E99-1<BN$7),0,($D99-SUM($F99:BM99)-SUM($F38:BM38))/($E99+$C99-BN$7)) -> 0
C100: 5 | D100: 0 | E100: =E99 -> 0 | G100: =IF(OR($C100>G$7,$C100+$E100-1<G$7),0,($D100-SUM($F100:F100)-SUM($F39:F39))/($E100+$C100-G$7)) -> 0 | H100: =IF(OR($C100>H$7,$C100+$E100-1<H$7),0,($D100-SUM($F100:G100)-SUM($F39:G39))/($E100+$C100-H$7)) -> 0 | I100: =IF(OR($C100>I$7,$C100+$E100-1<I$7),0,($D100-SUM($F100:H100)-SUM($F39:H39))/($E100+$C100-I$7)) -> 0 | J100: =IF(OR($C100>J$7,$C100+$E100-1<J$7),0,($D100-SUM($F100:I100)-SUM($F39:I39))/($E100+$C100-J$7)) -> 0 | K100: =IF(OR($C100>K$7,$C100+$E100-1<K$7),0,($D100-SUM($F100:J100)-SUM($F39:J39))/($E100+$C100-K$7)) -> 0 | L100: =IF(OR($C100>L$7,$C100+$E100-1<L$7),0,($D100-SUM($F100:K100)-SUM($F39:K39))/($E100+$C100-L$7)) -> 0 | M100: =IF(OR($C100>M$7,$C100+$E100-1<M$7),0,($D100-SUM($F100:L100)-SUM($F39:L39))/($E100+$C100-M$7)) -> 0 | N100: =IF(OR($C100>N$7,$C100+$E100-1<N$7),0,($D100-SUM($F100:M100)-SUM($F39:M39))/($E100+$C100-N$7)) -> 0 | ... BN100: =IF(OR($C100>BN$7,$C100+$E100-1<BN$7),0,($D100-SUM($F100:BM100)-SUM($F39:BM39))/($E100+$C100-BN$7)) -> 0
C101: 6 | D101: 0 | E101: =E100 -> 0 | G101: =IF(OR($C101>G$7,$C101+$E101-1<G$7),0,($D101-SUM($F101:F101)-SUM($F40:F40))/($E101+$C101-G$7)) -> 0 | H101: =IF(OR($C101>H$7,$C101+$E101-1<H$7),0,($D101-SUM($F101:G101)-SUM($F40:G40))/($E101+$C101-H$7)) -> 0 | I101: =IF(OR($C101>I$7,$C101+$E101-1<I$7),0,($D101-SUM($F101:H101)-SUM($F40:H40))/($E101+$C101-I$7)) -> 0 | J101: =IF(OR($C101>J$7,$C101+$E101-1<J$7),0,($D101-SUM($F101:I101)-SUM($F40:I40))/($E101+$C101-J$7)) -> 0 | K101: =IF(OR($C101>K$7,$C101+$E101-1<K$7),0,($D101-SUM($F101:J101)-SUM($F40:J40))/($E101+$C101-K$7)) -> 0 | L101: =IF(OR($C101>L$7,$C101+$E101-1<L$7),0,($D101-SUM($F101:K101)-SUM($F40:K40))/($E101+$C101-L$7)) -> 0 | M101: =IF(OR($C101>M$7,$C101+$E101-1<M$7),0,($D101-SUM($F101:L101)-SUM($F40:L40))/($E101+$C101-M$7)) -> 0 | N101: =IF(OR($C101>N$7,$C101+$E101-1<N$7),0,($D101-SUM($F101:M101)-SUM($F40:M40))/($E101+$C101-N$7)) -> 0 | ... BN101: =IF(OR($C101>BN$7,$C101+$E101-1<BN$7),0,($D101-SUM($F101:BM101)-SUM($F40:BM40))/($E101+$C101-BN$7)) -> 0
C102: 7 | D102: 0 | E102: =E101 -> 0 | G102: =IF(OR($C102>G$7,$C102+$E102-1<G$7),0,($D102-SUM($F102:F102)-SUM($F41:F41))/($E102+$C102-G$7)) -> 0 | H102: =IF(OR($C102>H$7,$C102+$E102-1<H$7),0,($D102-SUM($F102:G102)-SUM($F41:G41))/($E102+$C102-H$7)) -> 0 | I102: =IF(OR($C102>I$7,$C102+$E102-1<I$7),0,($D102-SUM($F102:H102)-SUM($F41:H41))/($E102+$C102-I$7)) -> 0 | J102: =IF(OR($C102>J$7,$C102+$E102-1<J$7),0,($D102-SUM($F102:I102)-SUM($F41:I41))/($E102+$C102-J$7)) -> 0 | K102: =IF(OR($C102>K$7,$C102+$E102-1<K$7),0,($D102-SUM($F102:J102)-SUM($F41:J41))/($E102+$C102-K$7)) -> 0 | L102: =IF(OR($C102>L$7,$C102+$E102-1<L$7),0,($D102-SUM($F102:K102)-SUM($F41:K41))/($E102+$C102-L$7)) -> 0 | M102: =IF(OR($C102>M$7,$C102+$E102-1<M$7),0,($D102-SUM($F102:L102)-SUM($F41:L41))/($E102+$C102-M$7)) -> 0 | N102: =IF(OR($C102>N$7,$C102+$E102-1<N$7),0,($D102-SUM($F102:M102)-SUM($F41:M41))/($E102+$C102-N$7)) -> 0 | ... BN102: =IF(OR($C102>BN$7,$C102+$E102-1<BN$7),0,($D102-SUM($F102:BM102)-SUM($F41:BM41))/($E102+$C102-BN$7)) -> 0
C103: 8 | D103: 0 | E103: =E102 -> 0 | G103: =IF(OR($C103>G$7,$C103+$E103-1<G$7),0,($D103-SUM($F103:F103)-SUM($F42:F42))/($E103+$C103-G$7)) -> 0 | H103: =IF(OR($C103>H$7,$C103+$E103-1<H$7),0,($D103-SUM($F103:G103)-SUM($F42:G42))/($E103+$C103-H$7)) -> 0 | I103: =IF(OR($C103>I$7,$C103+$E103-1<I$7),0,($D103-SUM($F103:H103)-SUM($F42:H42))/($E103+$C103-I$7)) -> 0 | J103: =IF(OR($C103>J$7,$C103+$E103-1<J$7),0,($D103-SUM($F103:I103)-SUM($F42:I42))/($E103+$C103-J$7)) -> 0 | K103: =IF(OR($C103>K$7,$C103+$E103-1<K$7),0,($D103-SUM($F103:J103)-SUM($F42:J42))/($E103+$C103-K$7)) -> 0 | L103: =IF(OR($C103>L$7,$C103+$E103-1<L$7),0,($D103-SUM($F103:K103)-SUM($F42:K42))/($E103+$C103-L$7)) -> 0 | M103: =IF(OR($C103>M$7,$C103+$E103-1<M$7),0,($D103-SUM($F103:L103)-SUM($F42:L42))/($E103+$C103-M$7)) -> 0 | N103: =IF(OR($C103>N$7,$C103+$E103-1<N$7),0,($D103-SUM($F103:M103)-SUM($F42:M42))/($E103+$C103-N$7)) -> 0 | ... BN103: =IF(OR($C103>BN$7,$C103+$E103-1<BN$7),0,($D103-SUM($F103:BM103)-SUM($F42:BM42))/($E103+$C103-BN$7)) -> 0
C104: 9 | D104: 0 | E104: =E103 -> 0 | G104: =IF(OR($C104>G$7,$C104+$E104-1<G$7),0,($D104-SUM($F104:F104)-SUM($F43:F43))/($E104+$C104-G$7)) -> 0 | H104: =IF(OR($C104>H$7,$C104+$E104-1<H$7),0,($D104-SUM($F104:G104)-SUM($F43:G43))/($E104+$C104-H$7)) -> 0 | I104: =IF(OR($C104>I$7,$C104+$E104-1<I$7),0,($D104-SUM($F104:H104)-SUM($F43:H43))/($E104+$C104-I$7)) -> 0 | J104: =IF(OR($C104>J$7,$C104+$E104-1<J$7),0,($D104-SUM($F104:I104)-SUM($F43:I43))/($E104+$C104-J$7)) -> 0 | K104: =IF(OR($C104>K$7,$C104+$E104-1<K$7),0,($D104-SUM($F104:J104)-SUM($F43:J43))/($E104+$C104-K$7)) -> 0 | L104: =IF(OR($C104>L$7,$C104+$E104-1<L$7),0,($D104-SUM($F104:K104)-SUM($F43:K43))/($E104+$C104-L$7)) -> 0 | M104: =IF(OR($C104>M$7,$C104+$E104-1<M$7),0,($D104-SUM($F104:L104)-SUM($F43:L43))/($E104+$C104-M$7)) -> 0 | N104: =IF(OR($C104>N$7,$C104+$E104-1<N$7),0,($D104-SUM($F104:M104)-SUM($F43:M43))/($E104+$C104-N$7)) -> 0 | ... BN104: =IF(OR($C104>BN$7,$C104+$E104-1<BN$7),0,($D104-SUM($F104:BM104)-SUM($F43:BM43))/($E104+$C104-BN$7)) -> 0
C105: 10 | D105: 0 | E105: =E104 -> 0 | G105: =IF(OR($C105>G$7,$C105+$E105-1<G$7),0,($D105-SUM($F105:F105)-SUM($F44:F44))/($E105+$C105-G$7)) -> 0 | H105: =IF(OR($C105>H$7,$C105+$E105-1<H$7),0,($D105-SUM($F105:G105)-SUM($F44:G44))/($E105+$C105-H$7)) -> 0 | I105: =IF(OR($C105>I$7,$C105+$E105-1<I$7),0,($D105-SUM($F105:H105)-SUM($F44:H44))/($E105+$C105-I$7)) -> 0 | J105: =IF(OR($C105>J$7,$C105+$E105-1<J$7),0,($D105-SUM($F105:I105)-SUM($F44:I44))/($E105+$C105-J$7)) -> 0 | K105: =IF(OR($C105>K$7,$C105+$E105-1<K$7),0,($D105-SUM($F105:J105)-SUM($F44:J44))/($E105+$C105-K$7)) -> 0 | L105: =IF(OR($C105>L$7,$C105+$E105-1<L$7),0,($D105-SUM($F105:K105)-SUM($F44:K44))/($E105+$C105-L$7)) -> 0 | M105: =IF(OR($C105>M$7,$C105+$E105-1<M$7),0,($D105-SUM($F105:L105)-SUM($F44:L44))/($E105+$C105-M$7)) -> 0 | N105: =IF(OR($C105>N$7,$C105+$E105-1<N$7),0,($D105-SUM($F105:M105)-SUM($F44:M44))/($E105+$C105-N$7)) -> 0 | ... BN105: =IF(OR($C105>BN$7,$C105+$E105-1<BN$7),0,($D105-SUM($F105:BM105)-SUM($F44:BM44))/($E105+$C105-BN$7)) -> 0
C106: 11 | D106: 0 | E106: =E105 -> 0 | G106: =IF(OR($C106>G$7,$C106+$E106-1<G$7),0,($D106-SUM($F106:F106)-SUM($F45:F45))/($E106+$C106-G$7)) -> 0 | H106: =IF(OR($C106>H$7,$C106+$E106-1<H$7),0,($D106-SUM($F106:G106)-SUM($F45:G45))/($E106+$C106-H$7)) -> 0 | I106: =IF(OR($C106>I$7,$C106+$E106-1<I$7),0,($D106-SUM($F106:H106)-SUM($F45:H45))/($E106+$C106-I$7)) -> 0 | J106: =IF(OR($C106>J$7,$C106+$E106-1<J$7),0,($D106-SUM($F106:I106)-SUM($F45:I45))/($E106+$C106-J$7)) -> 0 | K106: =IF(OR($C106>K$7,$C106+$E106-1<K$7),0,($D106-SUM($F106:J106)-SUM($F45:J45))/($E106+$C106-K$7)) -> 0 | L106: =IF(OR($C106>L$7,$C106+$E106-1<L$7),0,($D106-SUM($F106:K106)-SUM($F45:K45))/($E106+$C106-L$7)) -> 0 | M106: =IF(OR($C106>M$7,$C106+$E106-1<M$7),0,($D106-SUM($F106:L106)-SUM($F45:L45))/($E106+$C106-M$7)) -> 0 | N106: =IF(OR($C106>N$7,$C106+$E106-1<N$7),0,($D106-SUM($F106:M106)-SUM($F45:M45))/($E106+$C106-N$7)) -> 0 | ... BN106: =IF(OR($C106>BN$7,$C106+$E106-1<BN$7),0,($D106-SUM($F106:BM106)-SUM($F45:BM45))/($E106+$C106-BN$7)) -> 0
C107: 12 | D107: 0 | E107: =E106 -> 0 | G107: =IF(OR($C107>G$7,$C107+$E107-1<G$7),0,($D107-SUM($F107:F107)-SUM($F46:F46))/($E107+$C107-G$7)) -> 0 | H107: =IF(OR($C107>H$7,$C107+$E107-1<H$7),0,($D107-SUM($F107:G107)-SUM($F46:G46))/($E107+$C107-H$7)) -> 0 | I107: =IF(OR($C107>I$7,$C107+$E107-1<I$7),0,($D107-SUM($F107:H107)-SUM($F46:H46))/($E107+$C107-I$7)) -> 0 | J107: =IF(OR($C107>J$7,$C107+$E107-1<J$7),0,($D107-SUM($F107:I107)-SUM($F46:I46))/($E107+$C107-J$7)) -> 0 | K107: =IF(OR($C107>K$7,$C107+$E107-1<K$7),0,($D107-SUM($F107:J107)-SUM($F46:J46))/($E107+$C107-K$7)) -> 0 | L107: =IF(OR($C107>L$7,$C107+$E107-1<L$7),0,($D107-SUM($F107:K107)-SUM($F46:K46))/($E107+$C107-L$7)) -> 0 | M107: =IF(OR($C107>M$7,$C107+$E107-1<M$7),0,($D107-SUM($F107:L107)-SUM($F46:L46))/($E107+$C107-M$7)) -> 0 | N107: =IF(OR($C107>N$7,$C107+$E107-1<N$7),0,($D107-SUM($F107:M107)-SUM($F46:M46))/($E107+$C107-N$7)) -> 0 | ... BN107: =IF(OR($C107>BN$7,$C107+$E107-1<BN$7),0,($D107-SUM($F107:BM107)-SUM($F46:BM46))/($E107+$C107-BN$7)) -> 0
C108: 13 | D108: 0 | E108: =E107 -> 0 | G108: =IF(OR($C108>G$7,$C108+$E108-1<G$7),0,($D108-SUM($F108:F108)-SUM($F47:F47))/($E108+$C108-G$7)) -> 0 | H108: =IF(OR($C108>H$7,$C108+$E108-1<H$7),0,($D108-SUM($F108:G108)-SUM($F47:G47))/($E108+$C108-H$7)) -> 0 | I108: =IF(OR($C108>I$7,$C108+$E108-1<I$7),0,($D108-SUM($F108:H108)-SUM($F47:H47))/($E108+$C108-I$7)) -> 0 | J108: =IF(OR($C108>J$7,$C108+$E108-1<J$7),0,($D108-SUM($F108:I108)-SUM($F47:I47))/($E108+$C108-J$7)) -> 0 | K108: =IF(OR($C108>K$7,$C108+$E108-1<K$7),0,($D108-SUM($F108:J108)-SUM($F47:J47))/($E108+$C108-K$7)) -> 0 | L108: =IF(OR($C108>L$7,$C108+$E108-1<L$7),0,($D108-SUM($F108:K108)-SUM($F47:K47))/($E108+$C108-L$7)) -> 0 | M108: =IF(OR($C108>M$7,$C108+$E108-1<M$7),0,($D108-SUM($F108:L108)-SUM($F47:L47))/($E108+$C108-M$7)) -> 0 | N108: =IF(OR($C108>N$7,$C108+$E108-1<N$7),0,($D108-SUM($F108:M108)-SUM($F47:M47))/($E108+$C108-N$7)) -> 0 | ... BN108: =IF(OR($C108>BN$7,$C108+$E108-1<BN$7),0,($D108-SUM($F108:BM108)-SUM($F47:BM47))/($E108+$C108-BN$7)) -> 0
... C155: 60 | D155: 0 | E155: =E154 -> 0 | G155: =IF(OR($C155>G$7,$C155+$E155-1<G$7),0,($D155-SUM($F155:F155)-SUM($F94:F94))/($E155+$C155-G$7)) -> 0 | H155: =IF(OR($C155>H$7,$C155+$E155-1<H$7),0,($D155-SUM($F155:G155)-SUM($F94:G94))/($E155+$C155-H$7)) -> 0 | I155: =IF(OR($C155>I$7,$C155+$E155-1<I$7),0,($D155-SUM($F155:H155)-SUM($F94:H94))/($E155+$C155-I$7)) -> 0 | J155: =IF(OR($C155>J$7,$C155+$E155-1<J$7),0,($D155-SUM($F155:I155)-SUM($F94:I94))/($E155+$C155-J$7)) -> 0 | K155: =IF(OR($C155>K$7,$C155+$E155-1<K$7),0,($D155-SUM($F155:J155)-SUM($F94:J94))/($E155+$C155-K$7)) -> 0 | L155: =IF(OR($C155>L$7,$C155+$E155-1<L$7),0,($D155-SUM($F155:K155)-SUM($F94:K94))/($E155+$C155-L$7)) -> 0 | M155: =IF(OR($C155>M$7,$C155+$E155-1<M$7),0,($D155-SUM($F155:L155)-SUM($F94:L94))/($E155+$C155-M$7)) -> 0 | N155: =IF(OR($C155>N$7,$C155+$E155-1<N$7),0,($D155-SUM($F155:M155)-SUM($F94:M94))/($E155+$C155-N$7)) -> 0 | ... BN155: =IF(OR($C155>BN$7,$C155+$E155-1<BN$7),0,($D155-SUM($F155:BM155)-SUM($F94:BM94))/($E155+$C155-BN$7)) -> 0
D156: Ending Bal | F156: milVND | G156: =G31+G32+G33 -> 0 | H156: =H31+H32+H33 -> 0 | I156: =I31+I32+I33 -> 0 | J156: =J31+J32+J33 -> 0 | K156: =K31+K32+K33 -> 0 | L156: =L31+L32+L33 -> 0 | M156: =M31+M32+M33 -> 0 | N156: =N31+N32+N33 -> 0 | ... BN156: =BN31+BN32+BN33 -> 0
D158: Initial monthly balance | F158: milVND | G158: =SUM(G159:G218) -> 0 | H158: =SUM(H159:H218) -> 0 | I158: =SUM(I159:I218) -> 0 | J158: =SUM(J159:J218) -> 0 | K158: =SUM(K159:K218) -> 0 | L158: =SUM(L159:L218) -> 0 | M158: =SUM(M159:M218) -> 0 | N158: =SUM(N159:N218) -> 0 | ... BN158: =SUM(BN159:BN218) -> 0
C159: {=TRANSPOSE(G$7:BN$7)} -> 1 | D159: {=TRANSPOSE(G32:BN32)} -> 0 | E159: =E96 -> 0 | G159: =IF(OR($C159>G$7,$C159+$E159-1<G$7),0,$D159-SUM($F35:F35)) -> 0 | H159: =IF(OR($C159>H$7,$C159+$E159-1<H$7),0,$D159-SUM($F35:G35)) -> 0 | I159: =IF(OR($C159>I$7,$C159+$E159-1<I$7),0,$D159-SUM($F35:H35)) -> 0 | J159: =IF(OR($C159>J$7,$C159+$E159-1<J$7),0,$D159-SUM($F35:I35)) -> 0 | K159: =IF(OR($C159>K$7,$C159+$E159-1<K$7),0,$D159-SUM($F35:J35)) -> 0 | L159: =IF(OR($C159>L$7,$C159+$E159-1<L$7),0,$D159-SUM($F35:K35)) -> 0 | M159: =IF(OR($C159>M$7,$C159+$E159-1<M$7),0,$D159-SUM($F35:L35)) -> 0 | N159: =IF(OR($C159>N$7,$C159+$E159-1<N$7),0,$D159-SUM($F35:M35)) -> 0 | ... BN159: =IF(OR($C159>BN$7,$C159+$E159-1<BN$7),0,$D159-SUM($F35:BM35)) -> 0
C160: 2 | D160: 0 | E160: =E97 -> 0 | G160: =IF(OR($C160>G$7,$C160+$E160-1<G$7),0,$D160-SUM($F36:F36)) -> 0 | H160: =IF(OR($C160>H$7,$C160+$E160-1<H$7),0,$D160-SUM($F36:G36)) -> 0 | I160: =IF(OR($C160>I$7,$C160+$E160-1<I$7),0,$D160-SUM($F36:H36)) -> 0 | J160: =IF(OR($C160>J$7,$C160+$E160-1<J$7),0,$D160-SUM($F36:I36)) -> 0 | K160: =IF(OR($C160>K$7,$C160+$E160-1<K$7),0,$D160-SUM($F36:J36)) -> 0 | L160: =IF(OR($C160>L$7,$C160+$E160-1<L$7),0,$D160-SUM($F36:K36)) -> 0 | M160: =IF(OR($C160>M$7,$C160+$E160-1<M$7),0,$D160-SUM($F36:L36)) -> 0 | N160: =IF(OR($C160>N$7,$C160+$E160-1<N$7),0,$D160-SUM($F36:M36)) -> 0 | ... BN160: =IF(OR($C160>BN$7,$C160+$E160-1<BN$7),0,$D160-SUM($F36:BM36)) -> 0
C161: 3 | D161: 0 | E161: =E98 -> 0 | G161: =IF(OR($C161>G$7,$C161+$E161-1<G$7),0,$D161-SUM($F37:F37)) -> 0 | H161: =IF(OR($C161>H$7,$C161+$E161-1<H$7),0,$D161-SUM($F37:G37)) -> 0 | I161: =IF(OR($C161>I$7,$C161+$E161-1<I$7),0,$D161-SUM($F37:H37)) -> 0 | J161: =IF(OR($C161>J$7,$C161+$E161-1<J$7),0,$D161-SUM($F37:I37)) -> 0 | K161: =IF(OR($C161>K$7,$C161+$E161-1<K$7),0,$D161-SUM($F37:J37)) -> 0 | L161: =IF(OR($C161>L$7,$C161+$E161-1<L$7),0,$D161-SUM($F37:K37)) -> 0 | M161: =IF(OR($C161>M$7,$C161+$E161-1<M$7),0,$D161-SUM($F37:L37)) -> 0 | N161: =IF(OR($C161>N$7,$C161+$E161-1<N$7),0,$D161-SUM($F37:M37)) -> 0 | ... BN161: =IF(OR($C161>BN$7,$C161+$E161-1<BN$7),0,$D161-SUM($F37:BM37)) -> 0
C162: 4 | D162: 0 | E162: =E99 -> 0 | G162: =IF(OR($C162>G$7,$C162+$E162-1<G$7),0,$D162-SUM($F38:F38)) -> 0 | H162: =IF(OR($C162>H$7,$C162+$E162-1<H$7),0,$D162-SUM($F38:G38)) -> 0 | I162: =IF(OR($C162>I$7,$C162+$E162-1<I$7),0,$D162-SUM($F38:H38)) -> 0 | J162: =IF(OR($C162>J$7,$C162+$E162-1<J$7),0,$D162-SUM($F38:I38)) -> 0 | K162: =IF(OR($C162>K$7,$C162+$E162-1<K$7),0,$D162-SUM($F38:J38)) -> 0 | L162: =IF(OR($C162>L$7,$C162+$E162-1<L$7),0,$D162-SUM($F38:K38)) -> 0 | M162: =IF(OR($C162>M$7,$C162+$E162-1<M$7),0,$D162-SUM($F38:L38)) -> 0 | N162: =IF(OR($C162>N$7,$C162+$E162-1<N$7),0,$D162-SUM($F38:M38)) -> 0 | ... BN162: =IF(OR($C162>BN$7,$C162+$E162-1<BN$7),0,$D162-SUM($F38:BM38)) -> 0
C163: 5 | D163: 0 | E163: =E100 -> 0 | G163: =IF(OR($C163>G$7,$C163+$E163-1<G$7),0,$D163-SUM($F39:F39)) -> 0 | H163: =IF(OR($C163>H$7,$C163+$E163-1<H$7),0,$D163-SUM($F39:G39)) -> 0 | I163: =IF(OR($C163>I$7,$C163+$E163-1<I$7),0,$D163-SUM($F39:H39)) -> 0 | J163: =IF(OR($C163>J$7,$C163+$E163-1<J$7),0,$D163-SUM($F39:I39)) -> 0 | K163: =IF(OR($C163>K$7,$C163+$E163-1<K$7),0,$D163-SUM($F39:J39)) -> 0 | L163: =IF(OR($C163>L$7,$C163+$E163-1<L$7),0,$D163-SUM($F39:K39)) -> 0 | M163: =IF(OR($C163>M$7,$C163+$E163-1<M$7),0,$D163-SUM($F39:L39)) -> 0 | N163: =IF(OR($C163>N$7,$C163+$E163-1<N$7),0,$D163-SUM($F39:M39)) -> 0 | ... BN163: =IF(OR($C163>BN$7,$C163+$E163-1<BN$7),0,$D163-SUM($F39:BM39)) -> 0
C164: 6 | D164: 0 | E164: =E101 -> 0 | G164: =IF(OR($C164>G$7,$C164+$E164-1<G$7),0,$D164-SUM($F40:F40)) -> 0 | H164: =IF(OR($C164>H$7,$C164+$E164-1<H$7),0,$D164-SUM($F40:G40)) -> 0 | I164: =IF(OR($C164>I$7,$C164+$E164-1<I$7),0,$D164-SUM($F40:H40)) -> 0 | J164: =IF(OR($C164>J$7,$C164+$E164-1<J$7),0,$D164-SUM($F40:I40)) -> 0 | K164: =IF(OR($C164>K$7,$C164+$E164-1<K$7),0,$D164-SUM($F40:J40)) -> 0 | L164: =IF(OR($C164>L$7,$C164+$E164-1<L$7),0,$D164-SUM($F40:K40)) -> 0 | M164: =IF(OR($C164>M$7,$C164+$E164-1<M$7),0,$D164-SUM($F40:L40)) -> 0 | N164: =IF(OR($C164>N$7,$C164+$E164-1<N$7),0,$D164-SUM($F40:M40)) -> 0 | ... BN164: =IF(OR($C164>BN$7,$C164+$E164-1<BN$7),0,$D164-SUM($F40:BM40)) -> 0
C165: 7 | D165: 0 | E165: =E102 -> 0 | G165: =IF(OR($C165>G$7,$C165+$E165-1<G$7),0,$D165-SUM($F41:F41)) -> 0 | H165: =IF(OR($C165>H$7,$C165+$E165-1<H$7),0,$D165-SUM($F41:G41)) -> 0 | I165: =IF(OR($C165>I$7,$C165+$E165-1<I$7),0,$D165-SUM($F41:H41)) -> 0 | J165: =IF(OR($C165>J$7,$C165+$E165-1<J$7),0,$D165-SUM($F41:I41)) -> 0 | K165: =IF(OR($C165>K$7,$C165+$E165-1<K$7),0,$D165-SUM($F41:J41)) -> 0 | L165: =IF(OR($C165>L$7,$C165+$E165-1<L$7),0,$D165-SUM($F41:K41)) -> 0 | M165: =IF(OR($C165>M$7,$C165+$E165-1<M$7),0,$D165-SUM($F41:L41)) -> 0 | N165: =IF(OR($C165>N$7,$C165+$E165-1<N$7),0,$D165-SUM($F41:M41)) -> 0 | ... BN165: =IF(OR($C165>BN$7,$C165+$E165-1<BN$7),0,$D165-SUM($F41:BM41)) -> 0
C166: 8 | D166: 0 | E166: =E103 -> 0 | G166: =IF(OR($C166>G$7,$C166+$E166-1<G$7),0,$D166-SUM($F42:F42)) -> 0 | H166: =IF(OR($C166>H$7,$C166+$E166-1<H$7),0,$D166-SUM($F42:G42)) -> 0 | I166: =IF(OR($C166>I$7,$C166+$E166-1<I$7),0,$D166-SUM($F42:H42)) -> 0 | J166: =IF(OR($C166>J$7,$C166+$E166-1<J$7),0,$D166-SUM($F42:I42)) -> 0 | K166: =IF(OR($C166>K$7,$C166+$E166-1<K$7),0,$D166-SUM($F42:J42)) -> 0 | L166: =IF(OR($C166>L$7,$C166+$E166-1<L$7),0,$D166-SUM($F42:K42)) -> 0 | M166: =IF(OR($C166>M$7,$C166+$E166-1<M$7),0,$D166-SUM($F42:L42)) -> 0 | N166: =IF(OR($C166>N$7,$C166+$E166-1<N$7),0,$D166-SUM($F42:M42)) -> 0 | ... BN166: =IF(OR($C166>BN$7,$C166+$E166-1<BN$7),0,$D166-SUM($F42:BM42)) -> 0
C167: 9 | D167: 0 | E167: =E104 -> 0 | G167: =IF(OR($C167>G$7,$C167+$E167-1<G$7),0,$D167-SUM($F43:F43)) -> 0 | H167: =IF(OR($C167>H$7,$C167+$E167-1<H$7),0,$D167-SUM($F43:G43)) -> 0 | I167: =IF(OR($C167>I$7,$C167+$E167-1<I$7),0,$D167-SUM($F43:H43)) -> 0 | J167: =IF(OR($C167>J$7,$C167+$E167-1<J$7),0,$D167-SUM($F43:I43)) -> 0 | K167: =IF(OR($C167>K$7,$C167+$E167-1<K$7),0,$D167-SUM($F43:J43)) -> 0 | L167: =IF(OR($C167>L$7,$C167+$E167-1<L$7),0,$D167-SUM($F43:K43)) -> 0 | M167: =IF(OR($C167>M$7,$C167+$E167-1<M$7),0,$D167-SUM($F43:L43)) -> 0 | N167: =IF(OR($C167>N$7,$C167+$E167-1<N$7),0,$D167-SUM($F43:M43)) -> 0 | ... BN167: =IF(OR($C167>BN$7,$C167+$E167-1<BN$7),0,$D167-SUM($F43:BM43)) -> 0
C168: 10 | D168: 0 | E168: =E105 -> 0 | G168: =IF(OR($C168>G$7,$C168+$E168-1<G$7),0,$D168-SUM($F44:F44)) -> 0 | H168: =IF(OR($C168>H$7,$C168+$E168-1<H$7),0,$D168-SUM($F44:G44)) -> 0 | I168: =IF(OR($C168>I$7,$C168+$E168-1<I$7),0,$D168-SUM($F44:H44)) -> 0 | J168: =IF(OR($C168>J$7,$C168+$E168-1<J$7),0,$D168-SUM($F44:I44)) -> 0 | K168: =IF(OR($C168>K$7,$C168+$E168-1<K$7),0,$D168-SUM($F44:J44)) -> 0 | L168: =IF(OR($C168>L$7,$C168+$E168-1<L$7),0,$D168-SUM($F44:K44)) -> 0 | M168: =IF(OR($C168>M$7,$C168+$E168-1<M$7),0,$D168-SUM($F44:L44)) -> 0 | N168: =IF(OR($C168>N$7,$C168+$E168-1<N$7),0,$D168-SUM($F44:M44)) -> 0 | ... BN168: =IF(OR($C168>BN$7,$C168+$E168-1<BN$7),0,$D168-SUM($F44:BM44)) -> 0
C169: 11 | D169: 0 | E169: =E106 -> 0 | G169: =IF(OR($C169>G$7,$C169+$E169-1<G$7),0,$D169-SUM($F45:F45)) -> 0 | H169: =IF(OR($C169>H$7,$C169+$E169-1<H$7),0,$D169-SUM($F45:G45)) -> 0 | I169: =IF(OR($C169>I$7,$C169+$E169-1<I$7),0,$D169-SUM($F45:H45)) -> 0 | J169: =IF(OR($C169>J$7,$C169+$E169-1<J$7),0,$D169-SUM($F45:I45)) -> 0 | K169: =IF(OR($C169>K$7,$C169+$E169-1<K$7),0,$D169-SUM($F45:J45)) -> 0 | L169: =IF(OR($C169>L$7,$C169+$E169-1<L$7),0,$D169-SUM($F45:K45)) -> 0 | M169: =IF(OR($C169>M$7,$C169+$E169-1<M$7),0,$D169-SUM($F45:L45)) -> 0 | N169: =IF(OR($C169>N$7,$C169+$E169-1<N$7),0,$D169-SUM($F45:M45)) -> 0 | ... BN169: =IF(OR($C169>BN$7,$C169+$E169-1<BN$7),0,$D169-SUM($F45:BM45)) -> 0
C170: 12 | D170: 0 | E170: =E107 -> 0 | G170: =IF(OR($C170>G$7,$C170+$E170-1<G$7),0,$D170-SUM($F46:F46)) -> 0 | H170: =IF(OR($C170>H$7,$C170+$E170-1<H$7),0,$D170-SUM($F46:G46)) -> 0 | I170: =IF(OR($C170>I$7,$C170+$E170-1<I$7),0,$D170-SUM($F46:H46)) -> 0 | J170: =IF(OR($C170>J$7,$C170+$E170-1<J$7),0,$D170-SUM($F46:I46)) -> 0 | K170: =IF(OR($C170>K$7,$C170+$E170-1<K$7),0,$D170-SUM($F46:J46)) -> 0 | L170: =IF(OR($C170>L$7,$C170+$E170-1<L$7),0,$D170-SUM($F46:K46)) -> 0 | M170: =IF(OR($C170>M$7,$C170+$E170-1<M$7),0,$D170-SUM($F46:L46)) -> 0 | N170: =IF(OR($C170>N$7,$C170+$E170-1<N$7),0,$D170-SUM($F46:M46)) -> 0 | ... BN170: =IF(OR($C170>BN$7,$C170+$E170-1<BN$7),0,$D170-SUM($F46:BM46)) -> 0
C171: 13 | D171: 0 | E171: =E108 -> 0 | G171: =IF(OR($C171>G$7,$C171+$E171-1<G$7),0,$D171-SUM($F47:F47)) -> 0 | H171: =IF(OR($C171>H$7,$C171+$E171-1<H$7),0,$D171-SUM($F47:G47)) -> 0 | I171: =IF(OR($C171>I$7,$C171+$E171-1<I$7),0,$D171-SUM($F47:H47)) -> 0 | J171: =IF(OR($C171>J$7,$C171+$E171-1<J$7),0,$D171-SUM($F47:I47)) -> 0 | K171: =IF(OR($C171>K$7,$C171+$E171-1<K$7),0,$D171-SUM($F47:J47)) -> 0 | L171: =IF(OR($C171>L$7,$C171+$E171-1<L$7),0,$D171-SUM($F47:K47)) -> 0 | M171: =IF(OR($C171>M$7,$C171+$E171-1<M$7),0,$D171-SUM($F47:L47)) -> 0 | N171: =IF(OR($C171>N$7,$C171+$E171-1<N$7),0,$D171-SUM($F47:M47)) -> 0 | ... BN171: =IF(OR($C171>BN$7,$C171+$E171-1<BN$7),0,$D171-SUM($F47:BM47)) -> 0
... C218: 60 | D218: 0 | E218: =E155 -> 0 | G218: =IF(OR($C218>G$7,$C218+$E218-1<G$7),0,$D218-SUM($F94:F94)) -> 0 | H218: =IF(OR($C218>H$7,$C218+$E218-1<H$7),0,$D218-SUM($F94:G94)) -> 0 | I218: =IF(OR($C218>I$7,$C218+$E218-1<I$7),0,$D218-SUM($F94:H94)) -> 0 | J218: =IF(OR($C218>J$7,$C218+$E218-1<J$7),0,$D218-SUM($F94:I94)) -> 0 | K218: =IF(OR($C218>K$7,$C218+$E218-1<K$7),0,$D218-SUM($F94:J94)) -> 0 | L218: =IF(OR($C218>L$7,$C218+$E218-1<L$7),0,$D218-SUM($F94:K94)) -> 0 | M218: =IF(OR($C218>M$7,$C218+$E218-1<M$7),0,$D218-SUM($F94:L94)) -> 0 | N218: =IF(OR($C218>N$7,$C218+$E218-1<N$7),0,$D218-SUM($F94:M94)) -> 0 | ... BN218: =IF(OR($C218>BN$7,$C218+$E218-1<BN$7),0,$D218-SUM($F94:BM94)) -> 0
C220: RETAIL 1%
D221: Beginning Bal | F221: milVND | G221: 0 | H221: =G346 -> 0.22649384 | I221: =H346 -> 0.42166221 | J221: =I346 -> 0.58588184 | K221: =J346 -> 0.71952943 | L221: =K346 -> 0.82298171 | M221: =L346 -> 0.89661539 | N221: =M346 -> 0.94080719 | O221: =N346 -> 0.95593382 | ... BN221: =BM346 -> 0.010113402
D222: New Billing | F222: milVND | G222: =IF(AND(SAP_Leadsheet!$C$10="EMI",G$7<60+2-SAP_Leadsheet!$E$79),SAP_Spreadsheet!G$611*SAP_Leadsheet!$E$78,0) -> 0.25480557 | H222: =IF(AND(SAP_Leadsheet!$C$10="EMI",H$7<60+2-SAP_Leadsheet!$E$79),SAP_Spreadsheet!H$611*SAP_Leadsheet!$E$78,0) -> 0.25141512 | I222: =IF(AND(SAP_Leadsheet!$C$10="EMI",I$7<60+2-SAP_Leadsheet!$E$79),SAP_Spreadsheet!I$611*SAP_Leadsheet!$E$78,0) -> 0.24802466 | J222: =IF(AND(SAP_Leadsheet!$C$10="EMI",J$7<60+2-SAP_Leadsheet!$E$79),SAP_Spreadsheet!J$611*SAP_Leadsheet!$E$78,0) -> 0.24463421 | K222: =IF(AND(SAP_Leadsheet!$C$10="EMI",K$7<60+2-SAP_Leadsheet!$E$79),SAP_Spreadsheet!K$611*SAP_Leadsheet!$E$78,0) -> 0.24124376 | L222: =IF(AND(SAP_Leadsheet!$C$10="EMI",L$7<60+2-SAP_Leadsheet!$E$79),SAP_Spreadsheet!L$611*SAP_Leadsheet!$E$78,0) -> 0.2378533 | M222: =IF(AND(SAP_Leadsheet!$C$10="EMI",M$7<60+2-SAP_Leadsheet!$E$79),SAP_Spreadsheet!M$611*SAP_Leadsheet!$E$78,0) -> 0.23446285 | N222: =IF(AND(SAP_Leadsheet!$C$10="EMI",N$7<60+2-SAP_Leadsheet!$E$79),SAP_Spreadsheet!N$611*SAP_Leadsheet!$E$78,0) -> 0.2310724 | ... BN222: =IF(AND(SAP_Leadsheet!$C$10="EMI",BN$7<60+2-SAP_Leadsheet!$E$79),SAP_Spreadsheet!BN$611*SAP_Leadsheet!$E$78,0) -> 0
D223: Paid off | F223: milVND | G223: =G224+G285 -> -0.02831173 | H223: =H224+H285 -> -0.056246743 | I223: =I224+I285 -> -0.083805039 | J223: =J224+J285 -> -0.11098662 | K223: =K224+K285 -> -0.13779148 | L223: =L224+L285 -> -0.16421962 | M223: =M224+M285 -> -0.19027105 | N223: =N224+N285 -> -0.21594576 | ... BN223: =BN224+BN285 -> -0.010113402
D224: Early payment | F224: milVND | G224: =-SUM(G225:G284) -> 0 | H224: =-SUM(H225:H284) -> 0 | I224: =-SUM(I225:I284) -> 0 | J224: =-SUM(J225:J284) -> 0 | K224: =-SUM(K225:K284) -> 0 | L224: =-SUM(L225:L284) -> 0 | M224: =-SUM(M225:M284) -> 0 | N224: =-SUM(N225:N284) -> 0 | ... BN224: =-SUM(BN225:BN284) -> 0
C225: {=TRANSPOSE(G$7:BN$7)} -> 1 | G225: =IF(OR($C286>G$7,$C286+$E286-2<G$7),0,($D286-SUM($F286:F286)-SUM($F225:F225))*SAP_Leadsheet!$E$83) -> 0 | H225: =IF(OR($C286>H$7,$C286+$E286-2<H$7),0,($D286-SUM($F286:G286)-SUM($F225:G225))*SAP_Leadsheet!$E$83) -> 0 | I225: =IF(OR($C286>I$7,$C286+$E286-2<I$7),0,($D286-SUM($F286:H286)-SUM($F225:H225))*SAP_Leadsheet!$E$83) -> 0 | J225: =IF(OR($C286>J$7,$C286+$E286-2<J$7),0,($D286-SUM($F286:I286)-SUM($F225:I225))*SAP_Leadsheet!$E$83) -> 0 | K225: =IF(OR($C286>K$7,$C286+$E286-2<K$7),0,($D286-SUM($F286:J286)-SUM($F225:J225))*SAP_Leadsheet!$E$83) -> 0 | L225: =IF(OR($C286>L$7,$C286+$E286-2<L$7),0,($D286-SUM($F286:K286)-SUM($F225:K225))*SAP_Leadsheet!$E$83) -> 0 | M225: =IF(OR($C286>M$7,$C286+$E286-2<M$7),0,($D286-SUM($F286:L286)-SUM($F225:L225))*SAP_Leadsheet!$E$83) -> 0 | N225: =IF(OR($C286>N$7,$C286+$E286-2<N$7),0,($D286-SUM($F286:M286)-SUM($F225:M225))*SAP_Leadsheet!$E$83) -> 0 | ... BN225: =IF(OR($C286>BN$7,$C286+$E286-2<BN$7),0,($D286-SUM($F286:BM286)-SUM($F225:BM225))*SAP_Leadsheet!$E$83) -> 0
C226: 2 | G226: =IF(OR($C287>G$7,$C287+$E287-2<G$7),0,($D287-SUM($F287:F287)-SUM($F226:F226))*SAP_Leadsheet!$E$83) -> 0 | H226: =IF(OR($C287>H$7,$C287+$E287-2<H$7),0,($D287-SUM($F287:G287)-SUM($F226:G226))*SAP_Leadsheet!$E$83) -> 0 | I226: =IF(OR($C287>I$7,$C287+$E287-2<I$7),0,($D287-SUM($F287:H287)-SUM($F226:H226))*SAP_Leadsheet!$E$83) -> 0 | J226: =IF(OR($C287>J$7,$C287+$E287-2<J$7),0,($D287-SUM($F287:I287)-SUM($F226:I226))*SAP_Leadsheet!$E$83) -> 0 | K226: =IF(OR($C287>K$7,$C287+$E287-2<K$7),0,($D287-SUM($F287:J287)-SUM($F226:J226))*SAP_Leadsheet!$E$83) -> 0 | L226: =IF(OR($C287>L$7,$C287+$E287-2<L$7),0,($D287-SUM($F287:K287)-SUM($F226:K226))*SAP_Leadsheet!$E$83) -> 0 | M226: =IF(OR($C287>M$7,$C287+$E287-2<M$7),0,($D287-SUM($F287:L287)-SUM($F226:L226))*SAP_Leadsheet!$E$83) -> 0 | N226: =IF(OR($C287>N$7,$C287+$E287-2<N$7),0,($D287-SUM($F287:M287)-SUM($F226:M226))*SAP_Leadsheet!$E$83) -> 0 | ... BN226: =IF(OR($C287>BN$7,$C287+$E287-2<BN$7),0,($D287-SUM($F287:BM287)-SUM($F226:BM226))*SAP_Leadsheet!$E$83) -> 0
C227: 3 | G227: =IF(OR($C288>G$7,$C288+$E288-2<G$7),0,($D288-SUM($F288:F288)-SUM($F227:F227))*SAP_Leadsheet!$E$83) -> 0 | H227: =IF(OR($C288>H$7,$C288+$E288-2<H$7),0,($D288-SUM($F288:G288)-SUM($F227:G227))*SAP_Leadsheet!$E$83) -> 0 | I227: =IF(OR($C288>I$7,$C288+$E288-2<I$7),0,($D288-SUM($F288:H288)-SUM($F227:H227))*SAP_Leadsheet!$E$83) -> 0 | J227: =IF(OR($C288>J$7,$C288+$E288-2<J$7),0,($D288-SUM($F288:I288)-SUM($F227:I227))*SAP_Leadsheet!$E$83) -> 0 | K227: =IF(OR($C288>K$7,$C288+$E288-2<K$7),0,($D288-SUM($F288:J288)-SUM($F227:J227))*SAP_Leadsheet!$E$83) -> 0 | L227: =IF(OR($C288>L$7,$C288+$E288-2<L$7),0,($D288-SUM($F288:K288)-SUM($F227:K227))*SAP_Leadsheet!$E$83) -> 0 | M227: =IF(OR($C288>M$7,$C288+$E288-2<M$7),0,($D288-SUM($F288:L288)-SUM($F227:L227))*SAP_Leadsheet!$E$83) -> 0 | N227: =IF(OR($C288>N$7,$C288+$E288-2<N$7),0,($D288-SUM($F288:M288)-SUM($F227:M227))*SAP_Leadsheet!$E$83) -> 0 | ... BN227: =IF(OR($C288>BN$7,$C288+$E288-2<BN$7),0,($D288-SUM($F288:BM288)-SUM($F227:BM227))*SAP_Leadsheet!$E$83) -> 0
C228: 4 | G228: =IF(OR($C289>G$7,$C289+$E289-2<G$7),0,($D289-SUM($F289:F289)-SUM($F228:F228))*SAP_Leadsheet!$E$83) -> 0 | H228: =IF(OR($C289>H$7,$C289+$E289-2<H$7),0,($D289-SUM($F289:G289)-SUM($F228:G228))*SAP_Leadsheet!$E$83) -> 0 | I228: =IF(OR($C289>I$7,$C289+$E289-2<I$7),0,($D289-SUM($F289:H289)-SUM($F228:H228))*SAP_Leadsheet!$E$83) -> 0 | J228: =IF(OR($C289>J$7,$C289+$E289-2<J$7),0,($D289-SUM($F289:I289)-SUM($F228:I228))*SAP_Leadsheet!$E$83) -> 0 | K228: =IF(OR($C289>K$7,$C289+$E289-2<K$7),0,($D289-SUM($F289:J289)-SUM($F228:J228))*SAP_Leadsheet!$E$83) -> 0 | L228: =IF(OR($C289>L$7,$C289+$E289-2<L$7),0,($D289-SUM($F289:K289)-SUM($F228:K228))*SAP_Leadsheet!$E$83) -> 0 | M228: =IF(OR($C289>M$7,$C289+$E289-2<M$7),0,($D289-SUM($F289:L289)-SUM($F228:L228))*SAP_Leadsheet!$E$83) -> 0 | N228: =IF(OR($C289>N$7,$C289+$E289-2<N$7),0,($D289-SUM($F289:M289)-SUM($F228:M228))*SAP_Leadsheet!$E$83) -> 0 | ... BN228: =IF(OR($C289>BN$7,$C289+$E289-2<BN$7),0,($D289-SUM($F289:BM289)-SUM($F228:BM228))*SAP_Leadsheet!$E$83) -> 0
C229: 5 | G229: =IF(OR($C290>G$7,$C290+$E290-2<G$7),0,($D290-SUM($F290:F290)-SUM($F229:F229))*SAP_Leadsheet!$E$83) -> 0 | H229: =IF(OR($C290>H$7,$C290+$E290-2<H$7),0,($D290-SUM($F290:G290)-SUM($F229:G229))*SAP_Leadsheet!$E$83) -> 0 | I229: =IF(OR($C290>I$7,$C290+$E290-2<I$7),0,($D290-SUM($F290:H290)-SUM($F229:H229))*SAP_Leadsheet!$E$83) -> 0 | J229: =IF(OR($C290>J$7,$C290+$E290-2<J$7),0,($D290-SUM($F290:I290)-SUM($F229:I229))*SAP_Leadsheet!$E$83) -> 0 | K229: =IF(OR($C290>K$7,$C290+$E290-2<K$7),0,($D290-SUM($F290:J290)-SUM($F229:J229))*SAP_Leadsheet!$E$83) -> 0 | L229: =IF(OR($C290>L$7,$C290+$E290-2<L$7),0,($D290-SUM($F290:K290)-SUM($F229:K229))*SAP_Leadsheet!$E$83) -> 0 | M229: =IF(OR($C290>M$7,$C290+$E290-2<M$7),0,($D290-SUM($F290:L290)-SUM($F229:L229))*SAP_Leadsheet!$E$83) -> 0 | N229: =IF(OR($C290>N$7,$C290+$E290-2<N$7),0,($D290-SUM($F290:M290)-SUM($F229:M229))*SAP_Leadsheet!$E$83) -> 0 | ... BN229: =IF(OR($C290>BN$7,$C290+$E290-2<BN$7),0,($D290-SUM($F290:BM290)-SUM($F229:BM229))*SAP_Leadsheet!$E$83) -> 0
C230: 6 | G230: =IF(OR($C291>G$7,$C291+$E291-2<G$7),0,($D291-SUM($F291:F291)-SUM($F230:F230))*SAP_Leadsheet!$E$83) -> 0 | H230: =IF(OR($C291>H$7,$C291+$E291-2<H$7),0,($D291-SUM($F291:G291)-SUM($F230:G230))*SAP_Leadsheet!$E$83) -> 0 | I230: =IF(OR($C291>I$7,$C291+$E291-2<I$7),0,($D291-SUM($F291:H291)-SUM($F230:H230))*SAP_Leadsheet!$E$83) -> 0 | J230: =IF(OR($C291>J$7,$C291+$E291-2<J$7),0,($D291-SUM($F291:I291)-SUM($F230:I230))*SAP_Leadsheet!$E$83) -> 0 | K230: =IF(OR($C291>K$7,$C291+$E291-2<K$7),0,($D291-SUM($F291:J291)-SUM($F230:J230))*SAP_Leadsheet!$E$83) -> 0 | L230: =IF(OR($C291>L$7,$C291+$E291-2<L$7),0,($D291-SUM($F291:K291)-SUM($F230:K230))*SAP_Leadsheet!$E$83) -> 0 | M230: =IF(OR($C291>M$7,$C291+$E291-2<M$7),0,($D291-SUM($F291:L291)-SUM($F230:L230))*SAP_Leadsheet!$E$83) -> 0 | N230: =IF(OR($C291>N$7,$C291+$E291-2<N$7),0,($D291-SUM($F291:M291)-SUM($F230:M230))*SAP_Leadsheet!$E$83) -> 0 | ... BN230: =IF(OR($C291>BN$7,$C291+$E291-2<BN$7),0,($D291-SUM($F291:BM291)-SUM($F230:BM230))*SAP_Leadsheet!$E$83) -> 0
C231: 7 | G231: =IF(OR($C292>G$7,$C292+$E292-2<G$7),0,($D292-SUM($F292:F292)-SUM($F231:F231))*SAP_Leadsheet!$E$83) -> 0 | H231: =IF(OR($C292>H$7,$C292+$E292-2<H$7),0,($D292-SUM($F292:G292)-SUM($F231:G231))*SAP_Leadsheet!$E$83) -> 0 | I231: =IF(OR($C292>I$7,$C292+$E292-2<I$7),0,($D292-SUM($F292:H292)-SUM($F231:H231))*SAP_Leadsheet!$E$83) -> 0 | J231: =IF(OR($C292>J$7,$C292+$E292-2<J$7),0,($D292-SUM($F292:I292)-SUM($F231:I231))*SAP_Leadsheet!$E$83) -> 0 | K231: =IF(OR($C292>K$7,$C292+$E292-2<K$7),0,($D292-SUM($F292:J292)-SUM($F231:J231))*SAP_Leadsheet!$E$83) -> 0 | L231: =IF(OR($C292>L$7,$C292+$E292-2<L$7),0,($D292-SUM($F292:K292)-SUM($F231:K231))*SAP_Leadsheet!$E$83) -> 0 | M231: =IF(OR($C292>M$7,$C292+$E292-2<M$7),0,($D292-SUM($F292:L292)-SUM($F231:L231))*SAP_Leadsheet!$E$83) -> 0 | N231: =IF(OR($C292>N$7,$C292+$E292-2<N$7),0,($D292-SUM($F292:M292)-SUM($F231:M231))*SAP_Leadsheet!$E$83) -> 0 | ... BN231: =IF(OR($C292>BN$7,$C292+$E292-2<BN$7),0,($D292-SUM($F292:BM292)-SUM($F231:BM231))*SAP_Leadsheet!$E$83) -> 0
C232: 8 | G232: =IF(OR($C293>G$7,$C293+$E293-2<G$7),0,($D293-SUM($F293:F293)-SUM($F232:F232))*SAP_Leadsheet!$E$83) -> 0 | H232: =IF(OR($C293>H$7,$C293+$E293-2<H$7),0,($D293-SUM($F293:G293)-SUM($F232:G232))*SAP_Leadsheet!$E$83) -> 0 | I232: =IF(OR($C293>I$7,$C293+$E293-2<I$7),0,($D293-SUM($F293:H293)-SUM($F232:H232))*SAP_Leadsheet!$E$83) -> 0 | J232: =IF(OR($C293>J$7,$C293+$E293-2<J$7),0,($D293-SUM($F293:I293)-SUM($F232:I232))*SAP_Leadsheet!$E$83) -> 0 | K232: =IF(OR($C293>K$7,$C293+$E293-2<K$7),0,($D293-SUM($F293:J293)-SUM($F232:J232))*SAP_Leadsheet!$E$83) -> 0 | L232: =IF(OR($C293>L$7,$C293+$E293-2<L$7),0,($D293-SUM($F293:K293)-SUM($F232:K232))*SAP_Leadsheet!$E$83) -> 0 | M232: =IF(OR($C293>M$7,$C293+$E293-2<M$7),0,($D293-SUM($F293:L293)-SUM($F232:L232))*SAP_Leadsheet!$E$83) -> 0 | N232: =IF(OR($C293>N$7,$C293+$E293-2<N$7),0,($D293-SUM($F293:M293)-SUM($F232:M232))*SAP_Leadsheet!$E$83) -> 0 | ... BN232: =IF(OR($C293>BN$7,$C293+$E293-2<BN$7),0,($D293-SUM($F293:BM293)-SUM($F232:BM232))*SAP_Leadsheet!$E$83) -> 0
C233: 9 | G233: =IF(OR($C294>G$7,$C294+$E294-2<G$7),0,($D294-SUM($F294:F294)-SUM($F233:F233))*SAP_Leadsheet!$E$83) -> 0 | H233: =IF(OR($C294>H$7,$C294+$E294-2<H$7),0,($D294-SUM($F294:G294)-SUM($F233:G233))*SAP_Leadsheet!$E$83) -> 0 | I233: =IF(OR($C294>I$7,$C294+$E294-2<I$7),0,($D294-SUM($F294:H294)-SUM($F233:H233))*SAP_Leadsheet!$E$83) -> 0 | J233: =IF(OR($C294>J$7,$C294+$E294-2<J$7),0,($D294-SUM($F294:I294)-SUM($F233:I233))*SAP_Leadsheet!$E$83) -> 0 | K233: =IF(OR($C294>K$7,$C294+$E294-2<K$7),0,($D294-SUM($F294:J294)-SUM($F233:J233))*SAP_Leadsheet!$E$83) -> 0 | L233: =IF(OR($C294>L$7,$C294+$E294-2<L$7),0,($D294-SUM($F294:K294)-SUM($F233:K233))*SAP_Leadsheet!$E$83) -> 0 | M233: =IF(OR($C294>M$7,$C294+$E294-2<M$7),0,($D294-SUM($F294:L294)-SUM($F233:L233))*SAP_Leadsheet!$E$83) -> 0 | N233: =IF(OR($C294>N$7,$C294+$E294-2<N$7),0,($D294-SUM($F294:M294)-SUM($F233:M233))*SAP_Leadsheet!$E$83) -> 0 | ... BN233: =IF(OR($C294>BN$7,$C294+$E294-2<BN$7),0,($D294-SUM($F294:BM294)-SUM($F233:BM233))*SAP_Leadsheet!$E$83) -> 0
C234: 10 | G234: =IF(OR($C295>G$7,$C295+$E295-2<G$7),0,($D295-SUM($F295:F295)-SUM($F234:F234))*SAP_Leadsheet!$E$83) -> 0 | H234: =IF(OR($C295>H$7,$C295+$E295-2<H$7),0,($D295-SUM($F295:G295)-SUM($F234:G234))*SAP_Leadsheet!$E$83) -> 0 | I234: =IF(OR($C295>I$7,$C295+$E295-2<I$7),0,($D295-SUM($F295:H295)-SUM($F234:H234))*SAP_Leadsheet!$E$83) -> 0 | J234: =IF(OR($C295>J$7,$C295+$E295-2<J$7),0,($D295-SUM($F295:I295)-SUM($F234:I234))*SAP_Leadsheet!$E$83) -> 0 | K234: =IF(OR($C295>K$7,$C295+$E295-2<K$7),0,($D295-SUM($F295:J295)-SUM($F234:J234))*SAP_Leadsheet!$E$83) -> 0 | L234: =IF(OR($C295>L$7,$C295+$E295-2<L$7),0,($D295-SUM($F295:K295)-SUM($F234:K234))*SAP_Leadsheet!$E$83) -> 0 | M234: =IF(OR($C295>M$7,$C295+$E295-2<M$7),0,($D295-SUM($F295:L295)-SUM($F234:L234))*SAP_Leadsheet!$E$83) -> 0 | N234: =IF(OR($C295>N$7,$C295+$E295-2<N$7),0,($D295-SUM($F295:M295)-SUM($F234:M234))*SAP_Leadsheet!$E$83) -> 0 | ... BN234: =IF(OR($C295>BN$7,$C295+$E295-2<BN$7),0,($D295-SUM($F295:BM295)-SUM($F234:BM234))*SAP_Leadsheet!$E$83) -> 0
C235: 11 | G235: =IF(OR($C296>G$7,$C296+$E296-2<G$7),0,($D296-SUM($F296:F296)-SUM($F235:F235))*SAP_Leadsheet!$E$83) -> 0 | H235: =IF(OR($C296>H$7,$C296+$E296-2<H$7),0,($D296-SUM($F296:G296)-SUM($F235:G235))*SAP_Leadsheet!$E$83) -> 0 | I235: =IF(OR($C296>I$7,$C296+$E296-2<I$7),0,($D296-SUM($F296:H296)-SUM($F235:H235))*SAP_Leadsheet!$E$83) -> 0 | J235: =IF(OR($C296>J$7,$C296+$E296-2<J$7),0,($D296-SUM($F296:I296)-SUM($F235:I235))*SAP_Leadsheet!$E$83) -> 0 | K235: =IF(OR($C296>K$7,$C296+$E296-2<K$7),0,($D296-SUM($F296:J296)-SUM($F235:J235))*SAP_Leadsheet!$E$83) -> 0 | L235: =IF(OR($C296>L$7,$C296+$E296-2<L$7),0,($D296-SUM($F296:K296)-SUM($F235:K235))*SAP_Leadsheet!$E$83) -> 0 | M235: =IF(OR($C296>M$7,$C296+$E296-2<M$7),0,($D296-SUM($F296:L296)-SUM($F235:L235))*SAP_Leadsheet!$E$83) -> 0 | N235: =IF(OR($C296>N$7,$C296+$E296-2<N$7),0,($D296-SUM($F296:M296)-SUM($F235:M235))*SAP_Leadsheet!$E$83) -> 0 | ... BN235: =IF(OR($C296>BN$7,$C296+$E296-2<BN$7),0,($D296-SUM($F296:BM296)-SUM($F235:BM235))*SAP_Leadsheet!$E$83) -> 0
C236: 12 | G236: =IF(OR($C297>G$7,$C297+$E297-2<G$7),0,($D297-SUM($F297:F297)-SUM($F236:F236))*SAP_Leadsheet!$E$83) -> 0 | H236: =IF(OR($C297>H$7,$C297+$E297-2<H$7),0,($D297-SUM($F297:G297)-SUM($F236:G236))*SAP_Leadsheet!$E$83) -> 0 | I236: =IF(OR($C297>I$7,$C297+$E297-2<I$7),0,($D297-SUM($F297:H297)-SUM($F236:H236))*SAP_Leadsheet!$E$83) -> 0 | J236: =IF(OR($C297>J$7,$C297+$E297-2<J$7),0,($D297-SUM($F297:I297)-SUM($F236:I236))*SAP_Leadsheet!$E$83) -> 0 | K236: =IF(OR($C297>K$7,$C297+$E297-2<K$7),0,($D297-SUM($F297:J297)-SUM($F236:J236))*SAP_Leadsheet!$E$83) -> 0 | L236: =IF(OR($C297>L$7,$C297+$E297-2<L$7),0,($D297-SUM($F297:K297)-SUM($F236:K236))*SAP_Leadsheet!$E$83) -> 0 | M236: =IF(OR($C297>M$7,$C297+$E297-2<M$7),0,($D297-SUM($F297:L297)-SUM($F236:L236))*SAP_Leadsheet!$E$83) -> 0 | N236: =IF(OR($C297>N$7,$C297+$E297-2<N$7),0,($D297-SUM($F297:M297)-SUM($F236:M236))*SAP_Leadsheet!$E$83) -> 0 | ... BN236: =IF(OR($C297>BN$7,$C297+$E297-2<BN$7),0,($D297-SUM($F297:BM297)-SUM($F236:BM236))*SAP_Leadsheet!$E$83) -> 0
C237: 13 | G237: =IF(OR($C298>G$7,$C298+$E298-2<G$7),0,($D298-SUM($F298:F298)-SUM($F237:F237))*SAP_Leadsheet!$E$83) -> 0 | H237: =IF(OR($C298>H$7,$C298+$E298-2<H$7),0,($D298-SUM($F298:G298)-SUM($F237:G237))*SAP_Leadsheet!$E$83) -> 0 | I237: =IF(OR($C298>I$7,$C298+$E298-2<I$7),0,($D298-SUM($F298:H298)-SUM($F237:H237))*SAP_Leadsheet!$E$83) -> 0 | J237: =IF(OR($C298>J$7,$C298+$E298-2<J$7),0,($D298-SUM($F298:I298)-SUM($F237:I237))*SAP_Leadsheet!$E$83) -> 0 | K237: =IF(OR($C298>K$7,$C298+$E298-2<K$7),0,($D298-SUM($F298:J298)-SUM($F237:J237))*SAP_Leadsheet!$E$83) -> 0 | L237: =IF(OR($C298>L$7,$C298+$E298-2<L$7),0,($D298-SUM($F298:K298)-SUM($F237:K237))*SAP_Leadsheet!$E$83) -> 0 | M237: =IF(OR($C298>M$7,$C298+$E298-2<M$7),0,($D298-SUM($F298:L298)-SUM($F237:L237))*SAP_Leadsheet!$E$83) -> 0 | N237: =IF(OR($C298>N$7,$C298+$E298-2<N$7),0,($D298-SUM($F298:M298)-SUM($F237:M237))*SAP_Leadsheet!$E$83) -> 0 | ... BN237: =IF(OR($C298>BN$7,$C298+$E298-2<BN$7),0,($D298-SUM($F298:BM298)-SUM($F237:BM237))*SAP_Leadsheet!$E$83) -> 0
... C284: 60 | G284: =IF(OR($C345>G$7,$C345+$E345-2<G$7),0,($D345-SUM($F345:F345)-SUM($F284:F284))*SAP_Leadsheet!$E$83) -> 0 | H284: =IF(OR($C345>H$7,$C345+$E345-2<H$7),0,($D345-SUM($F345:G345)-SUM($F284:G284))*SAP_Leadsheet!$E$83) -> 0 | I284: =IF(OR($C345>I$7,$C345+$E345-2<I$7),0,($D345-SUM($F345:H345)-SUM($F284:H284))*SAP_Leadsheet!$E$83) -> 0 | J284: =IF(OR($C345>J$7,$C345+$E345-2<J$7),0,($D345-SUM($F345:I345)-SUM($F284:I284))*SAP_Leadsheet!$E$83) -> 0 | K284: =IF(OR($C345>K$7,$C345+$E345-2<K$7),0,($D345-SUM($F345:J345)-SUM($F284:J284))*SAP_Leadsheet!$E$83) -> 0 | L284: =IF(OR($C345>L$7,$C345+$E345-2<L$7),0,($D345-SUM($F345:K345)-SUM($F284:K284))*SAP_Leadsheet!$E$83) -> 0 | M284: =IF(OR($C345>M$7,$C345+$E345-2<M$7),0,($D345-SUM($F345:L345)-SUM($F284:L284))*SAP_Leadsheet!$E$83) -> 0 | N284: =IF(OR($C345>N$7,$C345+$E345-2<N$7),0,($D345-SUM($F345:M345)-SUM($F284:M284))*SAP_Leadsheet!$E$83) -> 0 | ... BN284: =IF(OR($C345>BN$7,$C345+$E345-2<BN$7),0,($D345-SUM($F345:BM345)-SUM($F284:BM284))*SAP_Leadsheet!$E$83) -> 0
D285: Normal payment | F285: milVND | G285: =-SUM(G286:G345) -> -0.02831173 | H285: =-SUM(H286:H345) -> -0.056246743 | I285: =-SUM(I286:I345) -> -0.083805039 | J285: =-SUM(J286:J345) -> -0.11098662 | K285: =-SUM(K286:K345) -> -0.13779148 | L285: =-SUM(L286:L345) -> -0.16421962 | M285: =-SUM(M286:M345) -> -0.19027105 | N285: =-SUM(N286:N345) -> -0.21594576 | ... BN285: =-SUM(BN286:BN345) -> -0.010113402
C286: {=TRANSPOSE(G$7:BN$7)} -> 1 | D286: {=TRANSPOSE(G222:BN222)} -> 0.25480557 | E286: =SAP_Leadsheet!E79 -> 9 | G286: =IF(OR($C286>G$7,$C286+$E286-1<G$7),0,($D286-SUM($F286:F286)-SUM($F225:F225))/($E286+$C286-G$7)) -> 0.02831173 | H286: =IF(OR($C286>H$7,$C286+$E286-1<H$7),0,($D286-SUM($F286:G286)-SUM($F225:G225))/($E286+$C286-H$7)) -> 0.02831173 | I286: =IF(OR($C286>I$7,$C286+$E286-1<I$7),0,($D286-SUM($F286:H286)-SUM($F225:H225))/($E286+$C286-I$7)) -> 0.02831173 | J286: =IF(OR($C286>J$7,$C286+$E286-1<J$7),0,($D286-SUM($F286:I286)-SUM($F225:I225))/($E286+$C286-J$7)) -> 0.02831173 | K286: =IF(OR($C286>K$7,$C286+$E286-1<K$7),0,($D286-SUM($F286:J286)-SUM($F225:J225))/($E286+$C286-K$7)) -> 0.02831173 | L286: =IF(OR($C286>L$7,$C286+$E286-1<L$7),0,($D286-SUM($F286:K286)-SUM($F225:K225))/($E286+$C286-L$7)) -> 0.02831173 | M286: =IF(OR($C286>M$7,$C286+$E286-1<M$7),0,($D286-SUM($F286:L286)-SUM($F225:L225))/($E286+$C286-M$7)) -> 0.02831173 | N286: =IF(OR($C286>N$7,$C286+$E286-1<N$7),0,($D286-SUM($F286:M286)-SUM($F225:M225))/($E286+$C286-N$7)) -> 0.02831173 | ... BN286: =IF(OR($C286>BN$7,$C286+$E286-1<BN$7),0,($D286-SUM($F286:BM286)-SUM($F225:BM225))/($E286+$C286-BN$7)) -> 0
C287: 2 | D287: 0.25141512 | E287: =E286 -> 9 | G287: =IF(OR($C287>G$7,$C287+$E287-1<G$7),0,($D287-SUM($F287:F287)-SUM($F226:F226))/($E287+$C287-G$7)) -> 0 | H287: =IF(OR($C287>H$7,$C287+$E287-1<H$7),0,($D287-SUM($F287:G287)-SUM($F226:G226))/($E287+$C287-H$7)) -> 0.027935013 | I287: =IF(OR($C287>I$7,$C287+$E287-1<I$7),0,($D287-SUM($F287:H287)-SUM($F226:H226))/($E287+$C287-I$7)) -> 0.027935013 | J287: =IF(OR($C287>J$7,$C287+$E287-1<J$7),0,($D287-SUM($F287:I287)-SUM($F226:I226))/($E287+$C287-J$7)) -> 0.027935013 | K287: =IF(OR($C287>K$7,$C287+$E287-1<K$7),0,($D287-SUM($F287:J287)-SUM($F226:J226))/($E287+$C287-K$7)) -> 0.027935013 | L287: =IF(OR($C287>L$7,$C287+$E287-1<L$7),0,($D287-SUM($F287:K287)-SUM($F226:K226))/($E287+$C287-L$7)) -> 0.027935013 | M287: =IF(OR($C287>M$7,$C287+$E287-1<M$7),0,($D287-SUM($F287:L287)-SUM($F226:L226))/($E287+$C287-M$7)) -> 0.027935013 | N287: =IF(OR($C287>N$7,$C287+$E287-1<N$7),0,($D287-SUM($F287:M287)-SUM($F226:M226))/($E287+$C287-N$7)) -> 0.027935013 | ... BN287: =IF(OR($C287>BN$7,$C287+$E287-1<BN$7),0,($D287-SUM($F287:BM287)-SUM($F226:BM226))/($E287+$C287-BN$7)) -> 0
C288: 3 | D288: 0.24802466 | E288: =E287 -> 9 | G288: =IF(OR($C288>G$7,$C288+$E288-1<G$7),0,($D288-SUM($F288:F288)-SUM($F227:F227))/($E288+$C288-G$7)) -> 0 | H288: =IF(OR($C288>H$7,$C288+$E288-1<H$7),0,($D288-SUM($F288:G288)-SUM($F227:G227))/($E288+$C288-H$7)) -> 0 | I288: =IF(OR($C288>I$7,$C288+$E288-1<I$7),0,($D288-SUM($F288:H288)-SUM($F227:H227))/($E288+$C288-I$7)) -> 0.027558296 | J288: =IF(OR($C288>J$7,$C288+$E288-1<J$7),0,($D288-SUM($F288:I288)-SUM($F227:I227))/($E288+$C288-J$7)) -> 0.027558296 | K288: =IF(OR($C288>K$7,$C288+$E288-1<K$7),0,($D288-SUM($F288:J288)-SUM($F227:J227))/($E288+$C288-K$7)) -> 0.027558296 | L288: =IF(OR($C288>L$7,$C288+$E288-1<L$7),0,($D288-SUM($F288:K288)-SUM($F227:K227))/($E288+$C288-L$7)) -> 0.027558296 | M288: =IF(OR($C288>M$7,$C288+$E288-1<M$7),0,($D288-SUM($F288:L288)-SUM($F227:L227))/($E288+$C288-M$7)) -> 0.027558296 | N288: =IF(OR($C288>N$7,$C288+$E288-1<N$7),0,($D288-SUM($F288:M288)-SUM($F227:M227))/($E288+$C288-N$7)) -> 0.027558296 | ... BN288: =IF(OR($C288>BN$7,$C288+$E288-1<BN$7),0,($D288-SUM($F288:BM288)-SUM($F227:BM227))/($E288+$C288-BN$7)) -> 0
C289: 4 | D289: 0.24463421 | E289: =E288 -> 9 | G289: =IF(OR($C289>G$7,$C289+$E289-1<G$7),0,($D289-SUM($F289:F289)-SUM($F228:F228))/($E289+$C289-G$7)) -> 0 | H289: =IF(OR($C289>H$7,$C289+$E289-1<H$7),0,($D289-SUM($F289:G289)-SUM($F228:G228))/($E289+$C289-H$7)) -> 0 | I289: =IF(OR($C289>I$7,$C289+$E289-1<I$7),0,($D289-SUM($F289:H289)-SUM($F228:H228))/($E289+$C289-I$7)) -> 0 | J289: =IF(OR($C289>J$7,$C289+$E289-1<J$7),0,($D289-SUM($F289:I289)-SUM($F228:I228))/($E289+$C289-J$7)) -> 0.027181579 | K289: =IF(OR($C289>K$7,$C289+$E289-1<K$7),0,($D289-SUM($F289:J289)-SUM($F228:J228))/($E289+$C289-K$7)) -> 0.027181579 | L289: =IF(OR($C289>L$7,$C289+$E289-1<L$7),0,($D289-SUM($F289:K289)-SUM($F228:K228))/($E289+$C289-L$7)) -> 0.027181579 | M289: =IF(OR($C289>M$7,$C289+$E289-1<M$7),0,($D289-SUM($F289:L289)-SUM($F228:L228))/($E289+$C289-M$7)) -> 0.027181579 | N289: =IF(OR($C289>N$7,$C289+$E289-1<N$7),0,($D289-SUM($F289:M289)-SUM($F228:M228))/($E289+$C289-N$7)) -> 0.027181579 | ... BN289: =IF(OR($C289>BN$7,$C289+$E289-1<BN$7),0,($D289-SUM($F289:BM289)-SUM($F228:BM228))/($E289+$C289-BN$7)) -> 0
C290: 5 | D290: 0.24124376 | E290: =E289 -> 9 | G290: =IF(OR($C290>G$7,$C290+$E290-1<G$7),0,($D290-SUM($F290:F290)-SUM($F229:F229))/($E290+$C290-G$7)) -> 0 | H290: =IF(OR($C290>H$7,$C290+$E290-1<H$7),0,($D290-SUM($F290:G290)-SUM($F229:G229))/($E290+$C290-H$7)) -> 0 | I290: =IF(OR($C290>I$7,$C290+$E290-1<I$7),0,($D290-SUM($F290:H290)-SUM($F229:H229))/($E290+$C290-I$7)) -> 0 | J290: =IF(OR($C290>J$7,$C290+$E290-1<J$7),0,($D290-SUM($F290:I290)-SUM($F229:I229))/($E290+$C290-J$7)) -> 0 | K290: =IF(OR($C290>K$7,$C290+$E290-1<K$7),0,($D290-SUM($F290:J290)-SUM($F229:J229))/($E290+$C290-K$7)) -> 0.026804862 | L290: =IF(OR($C290>L$7,$C290+$E290-1<L$7),0,($D290-SUM($F290:K290)-SUM($F229:K229))/($E290+$C290-L$7)) -> 0.026804862 | M290: =IF(OR($C290>M$7,$C290+$E290-1<M$7),0,($D290-SUM($F290:L290)-SUM($F229:L229))/($E290+$C290-M$7)) -> 0.026804862 | N290: =IF(OR($C290>N$7,$C290+$E290-1<N$7),0,($D290-SUM($F290:M290)-SUM($F229:M229))/($E290+$C290-N$7)) -> 0.026804862 | ... BN290: =IF(OR($C290>BN$7,$C290+$E290-1<BN$7),0,($D290-SUM($F290:BM290)-SUM($F229:BM229))/($E290+$C290-BN$7)) -> 0
C291: 6 | D291: 0.2378533 | E291: =E290 -> 9 | G291: =IF(OR($C291>G$7,$C291+$E291-1<G$7),0,($D291-SUM($F291:F291)-SUM($F230:F230))/($E291+$C291-G$7)) -> 0 | H291: =IF(OR($C291>H$7,$C291+$E291-1<H$7),0,($D291-SUM($F291:G291)-SUM($F230:G230))/($E291+$C291-H$7)) -> 0 | I291: =IF(OR($C291>I$7,$C291+$E291-1<I$7),0,($D291-SUM($F291:H291)-SUM($F230:H230))/($E291+$C291-I$7)) -> 0 | J291: =IF(OR($C291>J$7,$C291+$E291-1<J$7),0,($D291-SUM($F291:I291)-SUM($F230:I230))/($E291+$C291-J$7)) -> 0 | K291: =IF(OR($C291>K$7,$C291+$E291-1<K$7),0,($D291-SUM($F291:J291)-SUM($F230:J230))/($E291+$C291-K$7)) -> 0 | L291: =IF(OR($C291>L$7,$C291+$E291-1<L$7),0,($D291-SUM($F291:K291)-SUM($F230:K230))/($E291+$C291-L$7)) -> 0.026428145 | M291: =IF(OR($C291>M$7,$C291+$E291-1<M$7),0,($D291-SUM($F291:L291)-SUM($F230:L230))/($E291+$C291-M$7)) -> 0.026428145 | N291: =IF(OR($C291>N$7,$C291+$E291-1<N$7),0,($D291-SUM($F291:M291)-SUM($F230:M230))/($E291+$C291-N$7)) -> 0.026428145 | ... BN291: =IF(OR($C291>BN$7,$C291+$E291-1<BN$7),0,($D291-SUM($F291:BM291)-SUM($F230:BM230))/($E291+$C291-BN$7)) -> 0
C292: 7 | D292: 0.23446285 | E292: =E291 -> 9 | G292: =IF(OR($C292>G$7,$C292+$E292-1<G$7),0,($D292-SUM($F292:F292)-SUM($F231:F231))/($E292+$C292-G$7)) -> 0 | H292: =IF(OR($C292>H$7,$C292+$E292-1<H$7),0,($D292-SUM($F292:G292)-SUM($F231:G231))/($E292+$C292-H$7)) -> 0 | I292: =IF(OR($C292>I$7,$C292+$E292-1<I$7),0,($D292-SUM($F292:H292)-SUM($F231:H231))/($E292+$C292-I$7)) -> 0 | J292: =IF(OR($C292>J$7,$C292+$E292-1<J$7),0,($D292-SUM($F292:I292)-SUM($F231:I231))/($E292+$C292-J$7)) -> 0 | K292: =IF(OR($C292>K$7,$C292+$E292-1<K$7),0,($D292-SUM($F292:J292)-SUM($F231:J231))/($E292+$C292-K$7)) -> 0 | L292: =IF(OR($C292>L$7,$C292+$E292-1<L$7),0,($D292-SUM($F292:K292)-SUM($F231:K231))/($E292+$C292-L$7)) -> 0 | M292: =IF(OR($C292>M$7,$C292+$E292-1<M$7),0,($D292-SUM($F292:L292)-SUM($F231:L231))/($E292+$C292-M$7)) -> 0.026051428 | N292: =IF(OR($C292>N$7,$C292+$E292-1<N$7),0,($D292-SUM($F292:M292)-SUM($F231:M231))/($E292+$C292-N$7)) -> 0.026051428 | ... BN292: =IF(OR($C292>BN$7,$C292+$E292-1<BN$7),0,($D292-SUM($F292:BM292)-SUM($F231:BM231))/($E292+$C292-BN$7)) -> 0
C293: 8 | D293: 0.2310724 | E293: =E292 -> 9 | G293: =IF(OR($C293>G$7,$C293+$E293-1<G$7),0,($D293-SUM($F293:F293)-SUM($F232:F232))/($E293+$C293-G$7)) -> 0 | H293: =IF(OR($C293>H$7,$C293+$E293-1<H$7),0,($D293-SUM($F293:G293)-SUM($F232:G232))/($E293+$C293-H$7)) -> 0 | I293: =IF(OR($C293>I$7,$C293+$E293-1<I$7),0,($D293-SUM($F293:H293)-SUM($F232:H232))/($E293+$C293-I$7)) -> 0 | J293: =IF(OR($C293>J$7,$C293+$E293-1<J$7),0,($D293-SUM($F293:I293)-SUM($F232:I232))/($E293+$C293-J$7)) -> 0 | K293: =IF(OR($C293>K$7,$C293+$E293-1<K$7),0,($D293-SUM($F293:J293)-SUM($F232:J232))/($E293+$C293-K$7)) -> 0 | L293: =IF(OR($C293>L$7,$C293+$E293-1<L$7),0,($D293-SUM($F293:K293)-SUM($F232:K232))/($E293+$C293-L$7)) -> 0 | M293: =IF(OR($C293>M$7,$C293+$E293-1<M$7),0,($D293-SUM($F293:L293)-SUM($F232:L232))/($E293+$C293-M$7)) -> 0 | N293: =IF(OR($C293>N$7,$C293+$E293-1<N$7),0,($D293-SUM($F293:M293)-SUM($F232:M232))/($E293+$C293-N$7)) -> 0.025674711 | ... BN293: =IF(OR($C293>BN$7,$C293+$E293-1<BN$7),0,($D293-SUM($F293:BM293)-SUM($F232:BM232))/($E293+$C293-BN$7)) -> 0
...

Sheet Sales plan & PL
E1: PROFIT & LOSS 60M
A3: Code | B3: Product | C3: Old/new | D3: Item | F3: I. | G3: SALES PLAN
A4: =B4&D4&C4 -> Auto loan | B4: Auto loan
H5: If you want to estimate the mix price & promotion tenor for your product package, please input here & link to Leadsheet properly in term of pricing
A8: =B8&D8&C8 -> Auto loan | B8: Auto loan | H8: Please input your expected disbursement volume with date of lauching out product if you would like to project 60M profit and loss.
A10: =B10&D10&C10 -> Auto loan | B10: Auto loan | H10: Business month | J10: 45658 | K10: =EOMONTH(J10,1) -> 45716 | L10: =EOMONTH(K10,1) -> 45747 | M10: =EOMONTH(L10,1) -> 45777 | N10: =EOMONTH(M10,1) -> 45808 | O10: =EOMONTH(N10,1) -> 45838 | P10: =EOMONTH(O10,1) -> 45869 | Q10: =EOMONTH(P10,1) -> 45900 | R10: =EOMONTH(Q10,1) -> 45930 | ... BR10: =EOMONTH(BQ10,1) -> 47514
H11: Don't delete | J11: =YEAR(J10) -> 2025 | K11: =YEAR(K10) -> 2025 | L11: =YEAR(L10) -> 2025 | M11: =YEAR(M10) -> 2025 | N11: =YEAR(N10) -> 2025 | O11: =YEAR(O10) -> 2025 | P11: =YEAR(P10) -> 2025 | Q11: =YEAR(Q10) -> 2025 | ... BR11: =YEAR(BR10) -> 2030
A12: =B12&D12&C12 -> Auto loan | B12: Auto loan | H12: New disbursement (Card)
H13: Sales Plan 2025 | J13: 5300 | K13: 5400 | L13: 5500 | M13: 5600 | N13: 5700 | O13: 5800 | P13: 5800 | Q13: 5900 | R13: 6000 | S13: 6100 | T13: 6200 | U13: 6300
G14: New limit policy (apply for new cards) | H14: New card Forecast | J14: =J13*70% -> 3710 | K14: =K13*70% -> 3780 | L14: =L13*70% -> 3850 | M14: =M13*70% -> 3920 | N14: =N13*70% -> 3990 | O14: =O13*70% -> 4060 | P14: =P13*70% -> 4060 | Q14: =Q13*70% -> 4130 | ... U14: =U13*70% -> 4410
H15: CIF (new card only) | J15: =J14*60%*99% -> 2203.74 | K15: =K14*60%*99% -> 2245.32 | L15: =L14*60%*99% -> 2286.9 | M15: =M14*60%*99% -> 2328.48 | N15: =N14*60%*99% -> 2370.06 | O15: =O14*60%*99% -> 2411.64 | P15: =P14*60%*99% -> 2411.64 | Q15: =Q14*60%*99% -> 2453.22 | ... U15: =U14*60%*99% -> 2619.54
H16: % Affluent | J16: 0.6 | K16: =J16 -> 0.6 | L16: =K16 -> 0.6 | M16: =L16 -> 0.6 | N16: =M16 -> 0.6 | O16: =N16 -> 0.6 | P16: =O16 -> 0.6 | Q16: =P16 -> 0.6 | R16: =Q16 -> 0.6 | ... U16: =T16 -> 0.6
H17: # Card in Force Affluent | J17: =J15*J16 -> 1322.244 | K17: =K15*K16 -> 1347.192 | L17: =L15*L16 -> 1372.14 | M17: =M15*M16 -> 1397.088 | N17: =N15*N16 -> 1422.036 | O17: =O15*O16 -> 1446.984 | P17: =P15*P16 -> 1446.984 | Q17: =Q15*Q16 -> 1471.932 | ... U17: =U15*U16 -> 1571.724
H18: Limit per card (Mil VNĐ) | J18: 40 | K18: 40 | L18: 40 | M18: 40 | N18: 40 | O18: 40 | P18: 40 | Q18: 40 | R18: 40 | S18: 40 | T18: 40 | U18: 40
H19: Limit ultilization | J19: 0.25 | K19: =J19 -> 0.25 | L19: =K19 -> 0.25 | M19: =L19 -> 0.25 | N19: =M19 -> 0.25 | O19: =N19 -> 0.25 | P19: =O19 -> 0.25 | Q19: =P19 -> 0.25 | R19: =Q19 -> 0.25 | ... U19: =T19 -> 0.25
H20: Spending per card | J20: =J18*J19 -> 10 | K20: =K18*K19 -> 10 | L20: =L18*L19 -> 10 | M20: =M18*M19 -> 10 | N20: =N18*N19 -> 10 | O20: =O18*O19 -> 10 | P20: =P18*P19 -> 10 | Q20: =Q18*Q19 -> 10 | ... U20: =U18*U19 -> 10
H21: % Mass | J21: =1-J16 -> 0.4 | K21: =1-K16 -> 0.4 | L21: =1-L16 -> 0.4 | M21: =1-M16 -> 0.4 | N21: =1-N16 -> 0.4 | O21: =1-O16 -> 0.4 | P21: =1-P16 -> 0.4 | Q21: =1-Q16 -> 0.4 | ... U21: =1-U16 -> 0.4
H22: # Card in Force Mass | J22: =J15*J21 -> 881.496 | K22: =K15*K21 -> 898.128 | L22: =L15*L21 -> 914.76 | M22: =M15*M21 -> 931.392 | N22: =N15*N21 -> 948.024 | O22: =O15*O21 -> 964.656 | P22: =P15*P21 -> 964.656 | Q22: =Q15*Q21 -> 981.288 | ... U22: =U15*U21 -> 1047.816
H23: Limit per card (Mil VNĐ) | J23: 21 | K23: 21 | L23: 21 | M23: 21 | N23: 21 | O23: 21 | P23: 21 | Q23: 21 | R23: 21 | S23: 21 | T23: 21 | U23: 21
H24: Limit ultilization | J24: =30% -> 0.3 | K24: =J24 -> 0.3 | L24: =K24 -> 0.3 | M24: =L24 -> 0.3 | N24: =M24 -> 0.3 | O24: =N24 -> 0.3 | P24: =O24 -> 0.3 | Q24: =P24 -> 0.3 | R24: =Q24 -> 0.3 | ... U24: =T24 -> 0.3
H25: Spending per card | J25: =J23*J24 -> 6.3 | K25: =K23*K24 -> 6.3 | L25: =L23*L24 -> 6.3 | M25: =M23*M24 -> 6.3 | N25: =N23*N24 -> 6.3 | O25: =O23*O24 -> 6.3 | P25: =P23*P24 -> 6.3 | Q25: =Q23*Q24 -> 6.3 | ... U25: =U23*U24 -> 6.3
H26: Total spending (Mil VNĐ) | J26: =J20*J17+J25*J22 -> 18775.865 | K26: =K20*K17+K25*K22 -> 19130.126 | L26: =L20*L17+L25*L22 -> 19484.388 | M26: =M20*M17+M25*M22 -> 19838.65 | N26: =N20*N17+N25*N22 -> 20192.911 | O26: =O20*O17+O25*O22 -> 20547.173 | P26: =P20*P17+P25*P22 -> 20547.173 | Q26: =Q20*Q17+Q25*Q22 -> 20901.434 | ... U26: =U20*U17+U25*U22 -> 22318.481
G27: Current limit policy (2024 current active) | H27: # Card In Force | J27: 88000 | K27: =J27*99% -> 87120 | L27: =K27*99% -> 86248.8 | M27: =L27*99% -> 85386.312 | N27: =M27*99% -> 84532.449 | O27: =N27*99% -> 83687.124 | P27: =O27*99% -> 82850.253 | Q27: =P27*99% -> 82021.751 | R27: =Q27*99% -> 81201.533 | ... U27: =T27*99% -> 78789.766
H28: Spending per card | J28: 5.1 | K28: =J28*1.05 -> 5.355 | L28: =K28 -> 5.355 | M28: =L28*1.1 -> 5.8905 | N28: =M28 -> 5.8905 | O28: =N28*1.1 -> 6.47955 | P28: =O28 -> 6.47955 | Q28: =P28*1.1 -> 7.127505 | R28: =Q28 -> 7.127505 | S28: =R28*1.1 -> 7.8402555 | T28: =S28 -> 7.8402555 | U28: =T28*1.1 -> 8.6242811
H29: Total spending (Mil VNĐ) | J29: =J28*J27 -> 448800 | K29: =K28*K27 -> 466527.6 | L29: =L28*L27 -> 461862.32 | M29: =M28*M27 -> 502968.07 | N29: =N28*N27 -> 497938.39 | O29: =O28*O27 -> 542254.91 | P29: =P28*P27 -> 536832.36 | Q29: =Q28*Q27 -> 584610.44 | ... U29: =U28*U27 -> 679505.09
G30: Total porfolio | H30: # Card In Force | J30: =J27+J15 -> 90203.74 | K30: =J30+K15 -> 92449.06 | L30: =K30+L15 -> 94735.96 | M30: =L30+M15 -> 97064.44 | N30: =M30+N15 -> 99434.5 | O30: =N30+O15 -> 101846.14 | P30: =O30+P15 -> 104257.78 | Q30: =P30+Q15 -> 106711 | R30: =Q30+R15 -> 109205.8 | ... U30: =T30+U15 -> 116939.68
H31: Spending per card | J31: =J32/J30 -> 5.183553 | K31: =K32/K30 -> 5.2532468 | L31: =L32/L30 -> 5.0809293 | M31: =M32/M30 -> 5.3861818 | N31: =N32/N30 -> 5.21078 | O31: =O32/O30 -> 5.526003 | P31: =P32/P30 -> 5.3461673 | Q31: =Q32/Q30 -> 5.6743154 | ... U31: =U32/U30 -> 6.0015862
H32: Total spending (Mil VNĐ) | J32: =J29+J26 -> 467575.86 | K32: =K29+K26 -> 485657.73 | L32: =L29+L26 -> 481346.71 | M32: =M29+M26 -> 522806.72 | N32: =N29+N26 -> 518131.3 | O32: =O29+O26 -> 562802.08 | P32: =P29+P26 -> 557379.53 | Q32: =Q29+Q26 -> 605511.87 | ... U32: =U29+U26 -> 701823.57 | V32: =SUM(J32:U32) -> 6800875.6
G33: Limit increasing Batch | J33: Batch 1 | L33: Batch 2 | N33: Batch 3 | P33: Batch 4 | R33: Batch 5 | T33: Batch 6
G34: Note | J34: spending per active increase 5% (tet holiday) | L34: spending per active increase 10% | N34: 0.1 | P34: 0.1 | R34: 0.1 | T34: 0.1
F35: II. | G35: PROFIT & LOSS
H37: FISCAL YEAR | J37: Total | K37: =J11 -> 2025 | L37: =K37+1 -> 2026 | M37: =L37+1 -> 2027 | N37: =M37+1 -> 2028 | O37: =N37+1 -> 2029 | P37: =O37+1 -> 2030
J38: bVND | K38: bVND | L38: bVND | M38: bVND | N38: bVND | O38: bVND | P38: bVND
H40: NEW DISBURSAL | J40: =SUM(K40:O40) -> 0 | K40: =SUMIF($J$11:$BQ$11,K$37,$J$12:$BQ$12) -> 0 | L40: =SUMIF($J$11:$BQ$11,L$37,$J$12:$BQ$12) -> 0 | M40: =SUMIF($J$11:$BQ$11,M$37,$J$12:$BQ$12) -> 0 | N40: =SUMIF($J$11:$BQ$11,N$37,$J$12:$BQ$12) -> 0 | O40: =SUMIF($J$11:$BQ$11,O$37,$J$12:$BQ$12) -> 0 | P40: =SUMIF($J$11:$BQ$11,P$37,$J$12:$BQ$12) -> 0
H41: Monthly disbursement | J41: =AVERAGE(J12:AS12) -> #DIV/0! | K41: =K40/COUNTIF($J$11:$AS$11,K37) -> 0 | L41: =L40/COUNTIF($J$11:$AS$11,L37) -> 0 | M41: =M40/COUNTIF($J$11:$AS$11,M37) -> 0 | N41: =N40/COUNTIF($J$11:$BQ$11,N37) -> 0 | O41: =O40/COUNTIF($J$11:$BQ$11,O37) -> 0
H43: EOP | J43: =N43 -> 0 | K43: =OFFSET('PL projection speadsheet'!$B$7,0,MATCH(DATE('Sales plan & PL'!K$37,12,31),'PL projection speadsheet'!$C$4:$BJ$4,0))/1000 -> 0 | L43: =OFFSET('PL projection speadsheet'!$B$7,0,MATCH(DATE('Sales plan & PL'!L$37,12,31),'PL projection speadsheet'!$C$4:$BJ$4,0))/1000 -> 0 | M43: =OFFSET('PL projection speadsheet'!$B$7,0,MATCH(DATE('Sales plan & PL'!M$37,12,31),'PL projection speadsheet'!$C$4:$BJ$4,0))/1000 -> 0 | N43: =OFFSET('PL projection speadsheet'!$B$7,0,MATCH(DATE('Sales plan & PL'!N$37,12,31),'PL projection speadsheet'!$C$4:$BJ$4,0))/1000 -> 0 | O43: ='PL projection speadsheet'!BJ7/1000 -> 0 | P43: ='PL projection speadsheet'!BL7/1000 -> 0
H44: ADB | J44: =SUM('PL projection speadsheet'!C8:BI8)/1000/COUNT('PL projection speadsheet'!C3:BI3) -> 0 | K44: =SUMIF('PL projection speadsheet'!$C$3:$BJ$3,K$37,'PL projection speadsheet'!$C8:$BJ8)/1000/COUNTIF('PL projection speadsheet'!$C$3:$BJ$3,'Sales plan & PL'!K$37) -> 0 | L44: =SUMIF('PL projection speadsheet'!$C$3:$BJ$3,L$37,'PL projection speadsheet'!$C8:$BJ8)/1000/COUNTIF('PL projection speadsheet'!$C$3:$BJ$3,'Sales plan & PL'!L$37) -> 0 | M44: =SUMIF('PL projection speadsheet'!$C$3:$BJ$3,M$37,'PL projection speadsheet'!$C8:$BJ8)/1000/COUNTIF('PL projection speadsheet'!$C$3:$BJ$3,'Sales plan & PL'!M$37) -> 0 | N44: =SUMIF('PL projection speadsheet'!$C$3:$BJ$3,N$37,'PL projection speadsheet'!$C8:$BJ8)/1000/COUNTIF('PL projection speadsheet'!$C$3:$BJ$3,'Sales plan & PL'!N$37) -> 0 | O44: =SUMIF('PL projection speadsheet'!$C$3:$BJ$3,O$37,'PL projection speadsheet'!$C8:$BJ8)/1000/COUNTIF('PL projection speadsheet'!$C$3:$BJ$3,'Sales plan & PL'!O$37) -> 0
H46: TOI | J46: =SUM(K46:O46) -> 0 | K46: =SUMIF('PL projection speadsheet'!$C$3:$BJ$3,K$37,'PL projection speadsheet'!$C9:$BJ9)/1000 -> 0 | L46: =SUMIF('PL projection speadsheet'!$C$3:$BJ$3,L$37,'PL projection speadsheet'!$C9:$BJ9)/1000 -> 0 | M46: =SUMIF('PL projection speadsheet'!$C$3:$BJ$3,M$37,'PL projection speadsheet'!$C9:$BJ9)/1000 -> 0 | N46: =SUMIF('PL projection speadsheet'!$C$3:$BJ$3,N$37,'PL projection speadsheet'!$C9:$BJ9)/1000 -> 0 | O46: =SUMIF('PL projection speadsheet'!$C$3:$BJ$3,O$37,'PL projection speadsheet'!$C9:$BJ9)/1000 -> 0 | P46: =SUMIF('PL projection speadsheet'!$C$3:$BJ$3,P$37,'PL projection speadsheet'!$C9:$BJ9)/1000 -> 0
H47: NII | J47: =SUM(K47:O47) -> 0 | K47: =SUMIF('PL projection speadsheet'!$C$3:$BJ$3,K$37,'PL projection speadsheet'!$C11:$BJ11)/1000 -> 0 | L47: =SUMIF('PL projection speadsheet'!$C$3:$BJ$3,L$37,'PL projection speadsheet'!$C11:$BJ11)/1000 -> 0 | M47: =SUMIF('PL projection speadsheet'!$C$3:$BJ$3,M$37,'PL projection speadsheet'!$C11:$BJ11)/1000 -> 0 | N47: =SUMIF('PL projection speadsheet'!$C$3:$BJ$3,N$37,'PL projection speadsheet'!$C11:$BJ11)/1000 -> 0 | O47: =SUMIF('PL projection speadsheet'!$C$3:$BJ$3,O$37,'PL projection speadsheet'!$C11:$BJ11)/1000 -> 0 | P47: =SUMIF('PL projection speadsheet'!$C$3:$BJ$3,P$37,'PL projection speadsheet'!$C11:$BJ11)/1000 -> 0
H48: CII | J48: =SUM(K48:O48) -> 0 | K48: =SUMIF('PL projection speadsheet'!$C$3:$BJ$3,K$37,'PL projection speadsheet'!$C12:$BJ12)/1000 -> 0 | L48: =SUMIF('PL projection speadsheet'!$C$3:$BJ$3,L$37,'PL projection speadsheet'!$C12:$BJ12)/1000 -> 0 | M48: =SUMIF('PL projection speadsheet'!$C$3:$BJ$3,M$37,'PL projection speadsheet'!$C12:$BJ12)/1000 -> 0 | N48: =SUMIF('PL projection speadsheet'!$C$3:$BJ$3,N$37,'PL projection speadsheet'!$C12:$BJ12)/1000 -> 0 | O48: =SUMIF('PL projection speadsheet'!$C$3:$BJ$3,O$37,'PL projection speadsheet'!$C12:$BJ12)/1000 -> 0 | P48: =SUMIF('PL projection speadsheet'!$C$3:$BJ$3,P$37,'PL projection speadsheet'!$C12:$BJ12)/1000 -> 0
H49: COF | J49: =SUM(K49:O49) -> 0 | K49: =SUMIF('PL projection speadsheet'!$C$3:$BJ$3,K$37,'PL projection speadsheet'!$C13:$BJ13)/1000 -> 0 | L49: =SUMIF('PL projection speadsheet'!$C$3:$BJ$3,L$37,'PL projection speadsheet'!$C13:$BJ13)/1000 -> 0 | M49: =SUMIF('PL projection speadsheet'!$C$3:$BJ$3,M$37,'PL projection speadsheet'!$C13:$BJ13)/1000 -> 0 | N49: =SUMIF('PL projection speadsheet'!$C$3:$BJ$3,N$37,'PL projection speadsheet'!$C13:$BJ13)/1000 -> 0 | O49: =SUMIF('PL projection speadsheet'!$C$3:$BJ$3,O$37,'PL projection speadsheet'!$C13:$BJ13)/1000 -> 0 | P49: =SUMIF('PL projection speadsheet'!$C$3:$BJ$3,P$37,'PL projection speadsheet'!$C13:$BJ13)/1000 -> 0
H50: NFI | J50: =SUM(K50:O50) -> 0 | K50: =SUMIF('PL projection speadsheet'!$C$3:$BJ$3,K$37,'PL projection speadsheet'!$C14:$BJ14)/1000 -> 0 | L50: =SUMIF('PL projection speadsheet'!$C$3:$BJ$3,L$37,'PL projection speadsheet'!$C14:$BJ14)/1000 -> 0 | M50: =SUMIF('PL projection speadsheet'!$C$3:$BJ$3,M$37,'PL projection speadsheet'!$C14:$BJ14)/1000 -> 0 | N50: =SUMIF('PL projection speadsheet'!$C$3:$BJ$3,N$37,'PL projection speadsheet'!$C14:$BJ14)/1000 -> 0 | O50: =SUMIF('PL projection speadsheet'!$C$3:$BJ$3,O$37,'PL projection speadsheet'!$C14:$BJ14)/1000 -> 0 | P50: =SUMIF('PL projection speadsheet'!$C$3:$BJ$3,P$37,'PL projection speadsheet'!$C14:$BJ14)/1000 -> 0
H51: Interchange | J51: =SUM(K51:O51) -> 0 | K51: =SUMIF('PL projection speadsheet'!$C$3:$BJ$3,K$37,'PL projection speadsheet'!$C15:$BJ15)/1000 -> 0 | L51: =SUMIF('PL projection speadsheet'!$C$3:$BJ$3,L$37,'PL projection speadsheet'!$C15:$BJ15)/1000 -> 0 | M51: =SUMIF('PL projection speadsheet'!$C$3:$BJ$3,M$37,'PL projection speadsheet'!$C15:$BJ15)/1000 -> 0 | N51: =SUMIF('PL projection speadsheet'!$C$3:$BJ$3,N$37,'PL projection speadsheet'!$C15:$BJ15)/1000 -> 0 | O51: =SUMIF('PL projection speadsheet'!$C$3:$BJ$3,O$37,'PL projection speadsheet'!$C15:$BJ15)/1000 -> 0 | P51: =SUMIF('PL projection speadsheet'!$C$3:$BJ$3,P$37,'PL projection speadsheet'!$C15:$BJ15)/1000 -> 0
H52: Annual fee | J52: =SUM(K52:O52) -> 0 | K52: =SUMIF('PL projection speadsheet'!$C$3:$BJ$3,K$37,'PL projection speadsheet'!$C16:$BJ16)/1000 -> 0 | L52: =SUMIF('PL projection speadsheet'!$C$3:$BJ$3,L$37,'PL projection speadsheet'!$C16:$BJ16)/1000 -> 0 | M52: =SUMIF('PL projection speadsheet'!$C$3:$BJ$3,M$37,'PL projection speadsheet'!$C16:$BJ16)/1000 -> 0 | N52: =SUMIF('PL projection speadsheet'!$C$3:$BJ$3,N$37,'PL projection speadsheet'!$C16:$BJ16)/1000 -> 0 | O52: =SUMIF('PL projection speadsheet'!$C$3:$BJ$3,O$37,'PL projection speadsheet'!$C16:$BJ16)/1000 -> 0 | P52: =SUMIF('PL projection speadsheet'!$C$3:$BJ$3,P$37,'PL projection speadsheet'!$C16:$BJ16)/1000 -> 0
H53: Quarterly fee | J53: =SUM(K53:O53) -> 0 | K53: =SUMIF('PL projection speadsheet'!$C$3:$BJ$3,K$37,'PL projection speadsheet'!$C17:$BJ17)/1000 -> 0 | L53: =SUMIF('PL projection speadsheet'!$C$3:$BJ$3,L$37,'PL projection speadsheet'!$C17:$BJ17)/1000 -> 0 | M53: =SUMIF('PL projection speadsheet'!$C$3:$BJ$3,M$37,'PL projection speadsheet'!$C17:$BJ17)/1000 -> 0 | N53: =SUMIF('PL projection speadsheet'!$C$3:$BJ$3,N$37,'PL projection speadsheet'!$C17:$BJ17)/1000 -> 0 | O53: =SUMIF('PL projection speadsheet'!$C$3:$BJ$3,O$37,'PL projection speadsheet'!$C17:$BJ17)/1000 -> 0 | P53: =SUMIF('PL projection speadsheet'!$C$3:$BJ$3,P$37,'PL projection speadsheet'!$C17:$BJ17)/1000 -> 0
H54: Monthly fee | J54: =SUM(K54:O54) -> 0 | K54: =SUMIF('PL projection speadsheet'!$C$3:$BJ$3,K$37,'PL projection speadsheet'!$C18:$BJ18)/1000 -> 0 | L54: =SUMIF('PL projection speadsheet'!$C$3:$BJ$3,L$37,'PL projection speadsheet'!$C18:$BJ18)/1000 -> 0 | M54: =SUMIF('PL projection speadsheet'!$C$3:$BJ$3,M$37,'PL projection speadsheet'!$C18:$BJ18)/1000 -> 0 | N54: =SUMIF('PL projection speadsheet'!$C$3:$BJ$3,N$37,'PL projection speadsheet'!$C18:$BJ18)/1000 -> 0 | O54: =SUMIF('PL projection speadsheet'!$C$3:$BJ$3,O$37,'PL projection speadsheet'!$C18:$BJ18)/1000 -> 0 | P54: =SUMIF('PL projection speadsheet'!$C$3:$BJ$3,P$37,'PL projection speadsheet'!$C18:$BJ18)/1000 -> 0
H55: Issuance fee | J55: =SUM(K55:O55) -> 0 | K55: =SUMIF('PL projection speadsheet'!$C$3:$BJ$3,K$37,'PL projection speadsheet'!$C19:$BJ19)/1000 -> 0 | L55: =SUMIF('PL projection speadsheet'!$C$3:$BJ$3,L$37,'PL projection speadsheet'!$C19:$BJ19)/1000 -> 0 | M55: =SUMIF('PL projection speadsheet'!$C$3:$BJ$3,M$37,'PL projection speadsheet'!$C19:$BJ19)/1000 -> 0 | N55: =SUMIF('PL projection speadsheet'!$C$3:$BJ$3,N$37,'PL projection speadsheet'!$C19:$BJ19)/1000 -> 0 | O55: =SUMIF('PL projection speadsheet'!$C$3:$BJ$3,O$37,'PL projection speadsheet'!$C19:$BJ19)/1000 -> 0 | P55: =SUMIF('PL projection speadsheet'!$C$3:$BJ$3,P$37,'PL projection speadsheet'!$C19:$BJ19)/1000 -> 0
H56: Termination fee | J56: =SUM(K56:O56) -> 0 | K56: =SUMIF('PL projection speadsheet'!$C$3:$BJ$3,K$37,'PL projection speadsheet'!$C20:$BJ20)/1000 -> 0 | L56: =SUMIF('PL projection speadsheet'!$C$3:$BJ$3,L$37,'PL projection speadsheet'!$C20:$BJ20)/1000 -> 0 | M56: =SUMIF('PL projection speadsheet'!$C$3:$BJ$3,M$37,'PL projection speadsheet'!$C20:$BJ20)/1000 -> 0 | N56: =SUMIF('PL projection speadsheet'!$C$3:$BJ$3,N$37,'PL projection speadsheet'!$C20:$BJ20)/1000 -> 0 | O56: =SUMIF('PL projection speadsheet'!$C$3:$BJ$3,O$37,'PL projection speadsheet'!$C20:$BJ20)/1000 -> 0 | P56: =SUMIF('PL projection speadsheet'!$C$3:$BJ$3,P$37,'PL projection speadsheet'!$C20:$BJ20)/1000 -> 0
H57: Late payment | J57: =SUM(K57:O57) -> 0 | K57: =SUMIF('PL projection speadsheet'!$C$3:$BJ$3,K$37,'PL projection speadsheet'!$C21:$BJ21)/1000 -> 0 | L57: =SUMIF('PL projection speadsheet'!$C$3:$BJ$3,L$37,'PL projection speadsheet'!$C21:$BJ21)/1000 -> 0 | M57: =SUMIF('PL projection speadsheet'!$C$3:$BJ$3,M$37,'PL projection speadsheet'!$C21:$BJ21)/1000 -> 0 | N57: =SUMIF('PL projection speadsheet'!$C$3:$BJ$3,N$37,'PL projection speadsheet'!$C21:$BJ21)/1000 -> 0 | O57: =SUMIF('PL projection speadsheet'!$C$3:$BJ$3,O$37,'PL projection speadsheet'!$C21:$BJ21)/1000 -> 0 | P57: =SUMIF('PL projection speadsheet'!$C$3:$BJ$3,P$37,'PL projection speadsheet'!$C21:$BJ21)/1000 -> 0
H58: Cash advance | J58: =SUM(K58:O58) -> 0 | K58: =SUMIF('PL projection speadsheet'!$C$3:$BJ$3,K$37,'PL projection speadsheet'!$C22:$BJ22)/1000 -> 0 | L58: =SUMIF('PL projection speadsheet'!$C$3:$BJ$3,L$37,'PL projection speadsheet'!$C22:$BJ22)/1000 -> 0 | M58: =SUMIF('PL projection speadsheet'!$C$3:$BJ$3,M$37,'PL projection speadsheet'!$C22:$BJ22)/1000 -> 0 | N58: =SUMIF('PL projection speadsheet'!$C$3:$BJ$3,N$37,'PL projection speadsheet'!$C22:$BJ22)/1000 -> 0 | O58: =SUMIF('PL projection speadsheet'!$C$3:$BJ$3,O$37,'PL projection speadsheet'!$C22:$BJ22)/1000 -> 0 | P58: =SUMIF('PL projection speadsheet'!$C$3:$BJ$3,P$37,'PL projection speadsheet'!$C22:$BJ22)/1000 -> 0
... H67: Fee suspended | J67: =SUM(K67:O67) -> 0 | K67: =SUMIF('PL projection speadsheet'!$C$3:$BJ$3,K$37,'PL projection speadsheet'!$C31:$BJ31)/1000 -> 0 | L67: =SUMIF('PL projection speadsheet'!$C$3:$BJ$3,L$37,'PL projection speadsheet'!$C31:$BJ31)/1000 -> 0 | M67: =SUMIF('PL projection speadsheet'!$C$3:$BJ$3,M$37,'PL projection speadsheet'!$C31:$BJ31)/1000 -> 0 | N67: =SUMIF('PL projection speadsheet'!$C$3:$BJ$3,N$37,'PL projection speadsheet'!$C31:$BJ31)/1000 -> 0 | O67: =SUMIF('PL projection speadsheet'!$C$3:$BJ$3,O$37,'PL projection speadsheet'!$C31:$BJ31)/1000 -> 0 | P67: =SUMIF('PL projection speadsheet'!$C$3:$BJ$3,P$37,'PL projection speadsheet'!$C31:$BJ31)/1000 -> 0
H68: Other income | J68: =SUM(K68:O68) -> 0 | K68: =SUMIF('PL projection speadsheet'!$C$3:$BJ$3,K$37,'PL projection speadsheet'!$C49:$BJ49)/1000 -> 0 | L68: =SUMIF('PL projection speadsheet'!$C$3:$BJ$3,L$37,'PL projection speadsheet'!$C49:$BJ49)/1000 -> 0 | M68: =SUMIF('PL projection speadsheet'!$C$3:$BJ$3,M$37,'PL projection speadsheet'!$C49:$BJ49)/1000 -> 0 | N68: =SUMIF('PL projection speadsheet'!$C$3:$BJ$3,N$37,'PL projection speadsheet'!$C49:$BJ49)/1000 -> 0 | O68: =SUMIF('PL projection speadsheet'!$C$3:$BJ$3,O$37,'PL projection speadsheet'!$C49:$BJ49)/1000 -> 0 | P68: =SUMIF('PL projection speadsheet'!$C$3:$BJ$3,P$37,'PL projection speadsheet'!$C49:$BJ49)/1000 -> 0
H69: PROVISION | J69: =SUM(K69:O69) -> 0 | K69: =SUMIF('PL projection speadsheet'!$C$3:$BJ$3,K$37,'PL projection speadsheet'!$C48:$BJ48)/1000 -> 0 | L69: =SUMIF('PL projection speadsheet'!$C$3:$BJ$3,L$37,'PL projection speadsheet'!$C48:$BJ48)/1000 -> 0 | M69: =SUMIF('PL projection speadsheet'!$C$3:$BJ$3,M$37,'PL projection speadsheet'!$C48:$BJ48)/1000 -> 0 | N69: =SUMIF('PL projection speadsheet'!$C$3:$BJ$3,N$37,'PL projection speadsheet'!$C48:$BJ48)/1000 -> 0 | O69: =SUMIF('PL projection speadsheet'!$C$3:$BJ$3,O$37,'PL projection speadsheet'!$C48:$BJ48)/1000 -> 0 | P69: =SUMIF('PL projection speadsheet'!$C$3:$BJ$3,P$37,'PL projection speadsheet'!$C48:$BJ48)/1000 -> 0
H70: OPEX | J70: =SUM(K70:O70) -> 0 | K70: =(SUMIF('PL projection speadsheet'!$C$3:$BJ$3,K$37,'PL projection speadsheet'!$C33:$BJ33)/1000) -> 0 | L70: =(SUMIF('PL projection speadsheet'!$C$3:$BJ$3,L$37,'PL projection speadsheet'!$C33:$BJ33)/1000) -> 0 | M70: =(SUMIF('PL projection speadsheet'!$C$3:$BJ$3,M$37,'PL projection speadsheet'!$C33:$BJ33)/1000) -> 0 | N70: =(SUMIF('PL projection speadsheet'!$C$3:$BJ$3,N$37,'PL projection speadsheet'!$C33:$BJ33)/1000) -> 0 | O70: =(SUMIF('PL projection speadsheet'!$C$3:$BJ$3,O$37,'PL projection speadsheet'!$C33:$BJ33)/1000) -> 0 | P70: =(SUMIF('PL projection speadsheet'!$C$3:$BJ$3,P$37,'PL projection speadsheet'!$C33:$BJ33)/1000) -> 0
H71: Variable Expenses | J71: =SUM(J72:J77) -> 0 | K71: =SUM(K72:K77) -> 0 | L71: =SUM(L72:L77) -> 0 | M71: =SUM(M72:M77) -> 0 | N71: =SUM(N72:N77) -> 0 | O71: =SUM(O72:O77) -> 0 | P71: =SUM(P72:P77) -> 0
H72: Partner Acquisition | J72: =SUM(K72:O72) -> 0 | K72: =(SUMIF('PL projection speadsheet'!$C$3:$BJ$3,K$37,'PL projection speadsheet'!$C35:$BJ38)/1000) -> 0 | L72: =(SUMIF('PL projection speadsheet'!$C$3:$BJ$3,L$37,'PL projection speadsheet'!$C35:$BJ38)/1000) -> 0 | M72: =(SUMIF('PL projection speadsheet'!$C$3:$BJ$3,M$37,'PL projection speadsheet'!$C35:$BJ38)/1000) -> 0 | N72: =(SUMIF('PL projection speadsheet'!$C$3:$BJ$3,N$37,'PL projection speadsheet'!$C35:$BJ38)/1000) -> 0 | O72: =(SUMIF('PL projection speadsheet'!$C$3:$BJ$3,O$37,'PL projection speadsheet'!$C35:$BJ38)/1000) -> 0 | P72: =(SUMIF('PL projection speadsheet'!$C$3:$BJ$3,P$37,'PL projection speadsheet'!$C35:$BJ38)/1000) -> 0
H73: Marketing acquisition | J73: =SUM(K73:O73) -> 0 | K73: =SUMIF('PL projection speadsheet'!$C$3:$BJ$3,K$37,'PL projection speadsheet'!$C39:$BJ39)/1000 -> 0 | L73: =SUMIF('PL projection speadsheet'!$C$3:$BJ$3,L$37,'PL projection speadsheet'!$C34:$BJ34)/1000 -> 0 | M73: =SUMIF('PL projection speadsheet'!$C$3:$BJ$3,M$37,'PL projection speadsheet'!$C34:$BJ34)/1000 -> 0 | N73: =SUMIF('PL projection speadsheet'!$C$3:$BJ$3,N$37,'PL projection speadsheet'!$C34:$BJ34)/1000 -> 0 | O73: =SUMIF('PL projection speadsheet'!$C$3:$BJ$3,O$37,'PL projection speadsheet'!$C34:$BJ34)/1000 -> 0 | P73: =SUMIF('PL projection speadsheet'!$C$3:$BJ$3,P$37,'PL projection speadsheet'!$C34:$BJ34)/1000 -> 0
H74: Marketing Promotion | J74: =SUM(K74:O74) -> 0 | K74: =(SUMIF('PL projection speadsheet'!$C$3:$BJ$3,K$37,'PL projection speadsheet'!$C40:$BJ40)/1000) -> 0 | L74: =(SUMIF('PL projection speadsheet'!$C$3:$BJ$3,L$37,'PL projection speadsheet'!$C40:$BJ40)/1000) -> 0 | M74: =(SUMIF('PL projection speadsheet'!$C$3:$BJ$3,M$37,'PL projection speadsheet'!$C40:$BJ40)/1000) -> 0 | N74: =(SUMIF('PL projection speadsheet'!$C$3:$BJ$3,N$37,'PL projection speadsheet'!$C40:$BJ40)/1000) -> 0 | O74: =(SUMIF('PL projection speadsheet'!$C$3:$BJ$3,O$37,'PL projection speadsheet'!$C40:$BJ40)/1000) -> 0 | P74: =(SUMIF('PL projection speadsheet'!$C$3:$BJ$3,P$37,'PL projection speadsheet'!$C40:$BJ40)/1000) -> 0
H75: UW & Disbursal | J75: =SUM(K75:O75) -> 0 | K75: =(SUMIF('PL projection speadsheet'!$C$3:$BJ$3,K$37,'PL projection speadsheet'!$C42:$BJ42)/1000) -> 0 | L75: =(SUMIF('PL projection speadsheet'!$C$3:$BJ$3,L$37,'PL projection speadsheet'!$C42:$BJ42)/1000) -> 0 | M75: =(SUMIF('PL projection speadsheet'!$C$3:$BJ$3,M$37,'PL projection speadsheet'!$C42:$BJ42)/1000) -> 0 | N75: =(SUMIF('PL projection speadsheet'!$C$3:$BJ$3,N$37,'PL projection speadsheet'!$C42:$BJ42)/1000) -> 0 | O75: =(SUMIF('PL projection speadsheet'!$C$3:$BJ$3,O$37,'PL projection speadsheet'!$C42:$BJ42)/1000) -> 0 | P75: =(SUMIF('PL projection speadsheet'!$C$3:$BJ$3,P$37,'PL projection speadsheet'!$C42:$BJ42)/1000) -> 0
H76: Collection & AMC | J76: =SUM(K76:O76) -> 0 | K76: =(SUMIF('PL projection speadsheet'!$C$3:$BJ$3,K$37,'PL projection speadsheet'!$C43:$BJ43)/1000) -> 0 | L76: =(SUMIF('PL projection speadsheet'!$C$3:$BJ$3,L$37,'PL projection speadsheet'!$C43:$BJ43)/1000) -> 0 | M76: =(SUMIF('PL projection speadsheet'!$C$3:$BJ$3,M$37,'PL projection speadsheet'!$C43:$BJ43)/1000) -> 0 | N76: =(SUMIF('PL projection speadsheet'!$C$3:$BJ$3,N$37,'PL projection speadsheet'!$C43:$BJ43)/1000) -> 0 | O76: =(SUMIF('PL projection speadsheet'!$C$3:$BJ$3,O$37,'PL projection speadsheet'!$C43:$BJ43)/1000) -> 0 | P76: =(SUMIF('PL projection speadsheet'!$C$3:$BJ$3,P$37,'PL projection speadsheet'!$C43:$BJ43)/1000) -> 0
H77: After-sales services | J77: =SUM(K77:O77) -> 0 | K77: =(SUMIF('PL projection speadsheet'!$C$3:$BJ$3,K$37,'PL projection speadsheet'!$C46:$BJ46)/1000) -> 0 | L77: =(SUMIF('PL projection speadsheet'!$C$3:$BJ$3,L$37,'PL projection speadsheet'!$C46:$BJ46)/1000) -> 0 | M77: =(SUMIF('PL projection speadsheet'!$C$3:$BJ$3,M$37,'PL projection speadsheet'!$C46:$BJ46)/1000) -> 0 | N77: =(SUMIF('PL projection speadsheet'!$C$3:$BJ$3,N$37,'PL projection speadsheet'!$C46:$BJ46)/1000) -> 0 | O77: =(SUMIF('PL projection speadsheet'!$C$3:$BJ$3,O$37,'PL projection speadsheet'!$C46:$BJ46)/1000) -> 0 | P77: =(SUMIF('PL projection speadsheet'!$C$3:$BJ$3,P$37,'PL projection speadsheet'!$C46:$BJ46)/1000) -> 0
H78: Overhead Expenses | J78: =SUM(K78:O78) -> 0 | K78: =(SUMIF('PL projection speadsheet'!$C$3:$BJ$3,K$37,'PL projection speadsheet'!$C47:$BJ47)/1000) -> 0 | L78: =(SUMIF('PL projection speadsheet'!$C$3:$BJ$3,L$37,'PL projection speadsheet'!$C47:$BJ47)/1000) -> 0 | M78: =(SUMIF('PL projection speadsheet'!$C$3:$BJ$3,M$37,'PL projection speadsheet'!$C47:$BJ47)/1000) -> 0 | N78: =(SUMIF('PL projection speadsheet'!$C$3:$BJ$3,N$37,'PL projection speadsheet'!$C47:$BJ47)/1000) -> 0 | O78: =(SUMIF('PL projection speadsheet'!$C$3:$BJ$3,O$37,'PL projection speadsheet'!$C47:$BJ47)/1000) -> 0 | P78: =(SUMIF('PL projection speadsheet'!$C$3:$BJ$3,P$37,'PL projection speadsheet'!$C47:$BJ47)/1000) -> 0
H79: PBT | J79: =SUM(K79:O79) -> 0 | K79: =SUMIF('PL projection speadsheet'!$C$3:$BJ$3,K$37,'PL projection speadsheet'!$C50:$BJ50)/1000 -> 0 | L79: =SUMIF('PL projection speadsheet'!$C$3:$BJ$3,L$37,'PL projection speadsheet'!$C50:$BJ50)/1000 -> 0 | M79: =SUMIF('PL projection speadsheet'!$C$3:$BJ$3,M$37,'PL projection speadsheet'!$C50:$BJ50)/1000 -> 0 | N79: =SUMIF('PL projection speadsheet'!$C$3:$BJ$3,N$37,'PL projection speadsheet'!$C50:$BJ50)/1000 -> 0 | O79: =SUMIF('PL projection speadsheet'!$C$3:$BJ$3,O$37,'PL projection speadsheet'!$C50:$BJ50)/1000 -> 0 | P79: =SUMIF('PL projection speadsheet'!$C$3:$BJ$3,P$37,'PL projection speadsheet'!$C50:$BJ50)/1000 -> 0
H81: In which: PROFIT BEFORE SU | J81: =J79-J78 -> 0 | K81: =K79-K78 -> 0 | L81: =L79-L78 -> 0 | M81: =M79-M78 -> 0 | N81: =N79-N78 -> 0 | O81: =O79-O78 -> 0 | P81: =P79-P78 -> 0

Sheet PL projection speadsheet
B1: PL PROJECTION
B2: 60 months
C3: =YEAR(C4) -> 2025 | D3: =YEAR(D4) -> 2025 | E3: =YEAR(E4) -> 2025 | F3: =YEAR(F4) -> 2025 | G3: =YEAR(G4) -> 2025 | H3: =YEAR(H4) -> 2025 | I3: =YEAR(I4) -> 2025 | J3: =YEAR(J4) -> 2025 | ... BJ3: =YEAR(BJ4) -> 2029
B4: Business month | C4: ='Sales plan & PL'!J10 -> 45658 | D4: ='Sales plan & PL'!K10 -> 45716 | E4: ='Sales plan & PL'!L10 -> 45747 | F4: ='Sales plan & PL'!M10 -> 45777 | G4: ='Sales plan & PL'!N10 -> 45808 | H4: ='Sales plan & PL'!O10 -> 45838 | I4: ='Sales plan & PL'!P10 -> 45869 | J4: ='Sales plan & PL'!Q10 -> 45900 | ... BJ4: ='Sales plan & PL'!BQ10 -> 47483
B5: Month on board | C5: 1 | D5: =C5+1 -> 2 | E5: =D5+1 -> 3 | F5: =E5+1 -> 4 | G5: =F5+1 -> 5 | H5: =G5+1 -> 6 | I5: =H5+1 -> 7 | J5: =I5+1 -> 8 | K5: =J5+1 -> 9 | ... BJ5: =BI5+1 -> 60
B6: Unit: mVND
B7: ENR | C7: {=SUMPRODUCT(C$74:C$133,TRANSPOSE(SAP_Spreadsheet!$G$621:$BN$621))} -> 0 | D7: {=SUMPRODUCT(D$74:D$133,TRANSPOSE(SAP_Spreadsheet!$G$621:$BN$621))} -> 0 | E7: {=SUMPRODUCT(E$74:E$133,TRANSPOSE(SAP_Spreadsheet!$G$621:$BN$621))} -> 0 | F7: {=SUMPRODUCT(F$74:F$133,TRANSPOSE(SAP_Spreadsheet!$G$621:$BN$621))} -> 0 | G7: {=SUMPRODUCT(G$74:G$133,TRANSPOSE(SAP_Spreadsheet!$G$621:$BN$621))} -> 0 | H7: {=SUMPRODUCT(H$74:H$133,TRANSPOSE(SAP_Spreadsheet!$G$621:$BN$621))} -> 0 | I7: {=SUMPRODUCT(I$74:I$133,TRANSPOSE(SAP_Spreadsheet!$G$621:$BN$621))} -> 0 | J7: {=SUMPRODUCT(J$74:J$133,TRANSPOSE(SAP_Spreadsheet!$G$621:$BN$621))} -> 0 | ... BJ7: {=SUMPRODUCT(BJ$74:BJ$133,TRANSPOSE(SAP_Spreadsheet!$G$621:$BN$621))} -> 0
B8: ANR | C8: {=SUMPRODUCT(C$74:C$133,TRANSPOSE(SAP_Spreadsheet!$G$652:$BN$652))} -> 0 | D8: {=SUMPRODUCT(D$74:D$133,TRANSPOSE(SAP_Spreadsheet!$G$652:$BN$652))} -> 0 | E8: {=SUMPRODUCT(E$74:E$133,TRANSPOSE(SAP_Spreadsheet!$G$652:$BN$652))} -> 0 | F8: {=SUMPRODUCT(F$74:F$133,TRANSPOSE(SAP_Spreadsheet!$G$652:$BN$652))} -> 0 | G8: {=SUMPRODUCT(G$74:G$133,TRANSPOSE(SAP_Spreadsheet!$G$652:$BN$652))} -> 0 | H8: {=SUMPRODUCT(H$74:H$133,TRANSPOSE(SAP_Spreadsheet!$G$652:$BN$652))} -> 0 | I8: {=SUMPRODUCT(I$74:I$133,TRANSPOSE(SAP_Spreadsheet!$G$652:$BN$652))} -> 0 | J8: {=SUMPRODUCT(J$74:J$133,TRANSPOSE(SAP_Spreadsheet!$G$652:$BN$652))} -> 0 | ... BJ8: {=SUMPRODUCT(BJ$74:BJ$133,TRANSPOSE(SAP_Spreadsheet!$G$652:$BN$652))} -> 0
B9: TOI | C9: {=SUMPRODUCT(C$74:C$133,TRANSPOSE(SAP_Spreadsheet!$G$711:$BN$711))} -> 0 | D9: {=SUMPRODUCT(D$74:D$133,TRANSPOSE(SAP_Spreadsheet!$G$711:$BN$711))} -> 0 | E9: {=SUMPRODUCT(E$74:E$133,TRANSPOSE(SAP_Spreadsheet!$G$711:$BN$711))} -> 0 | F9: {=SUMPRODUCT(F$74:F$133,TRANSPOSE(SAP_Spreadsheet!$G$711:$BN$711))} -> 0 | G9: {=SUMPRODUCT(G$74:G$133,TRANSPOSE(SAP_Spreadsheet!$G$711:$BN$711))} -> 0 | H9: {=SUMPRODUCT(H$74:H$133,TRANSPOSE(SAP_Spreadsheet!$G$711:$BN$711))} -> 0 | I9: {=SUMPRODUCT(I$74:I$133,TRANSPOSE(SAP_Spreadsheet!$G$711:$BN$711))} -> 0 | J9: {=SUMPRODUCT(J$74:J$133,TRANSPOSE(SAP_Spreadsheet!$G$711:$BN$711))} -> 0 | ... BJ9: {=SUMPRODUCT(BJ$74:BJ$133,TRANSPOSE(SAP_Spreadsheet!$G$711:$BN$711))} -> 0
B10: Checking | C10: =C9-C11-C14 -> 0 | D10: =D9-D11-D14 -> 0 | E10: =E9-E11-E14 -> 0 | F10: =F9-F11-F14 -> 0 | G10: =G9-G11-G14 -> 0 | H10: =H9-H11-H14 -> 0 | I10: =I9-I11-I14 -> 0 | J10: =J9-J11-J14 -> 0 | ... BJ10: =BJ9-BJ11-BJ14 -> 0
B11: Net interest income | C11: {=SUMPRODUCT(C$74:C$133,TRANSPOSE(SAP_Spreadsheet!$G$674:$BN$674))} -> 0 | D11: {=SUMPRODUCT(D$74:D$133,TRANSPOSE(SAP_Spreadsheet!$G$674:$BN$674))} -> 0 | E11: {=SUMPRODUCT(E$74:E$133,TRANSPOSE(SAP_Spreadsheet!$G$674:$BN$674))} -> 0 | F11: {=SUMPRODUCT(F$74:F$133,TRANSPOSE(SAP_Spreadsheet!$G$674:$BN$674))} -> 0 | G11: {=SUMPRODUCT(G$74:G$133,TRANSPOSE(SAP_Spreadsheet!$G$674:$BN$674))} -> 0 | H11: {=SUMPRODUCT(H$74:H$133,TRANSPOSE(SAP_Spreadsheet!$G$674:$BN$674))} -> 0 | I11: {=SUMPRODUCT(I$74:I$133,TRANSPOSE(SAP_Spreadsheet!$G$674:$BN$674))} -> 0 | J11: {=SUMPRODUCT(J$74:J$133,TRANSPOSE(SAP_Spreadsheet!$G$674:$BN$674))} -> 0 | ... BJ11: {=SUMPRODUCT(BJ$74:BJ$133,TRANSPOSE(SAP_Spreadsheet!$G$674:$BN$674))} -> 0
B12: CII | C12: {=SUMPRODUCT(C$74:C$133,TRANSPOSE(SAP_Spreadsheet!$G$670:$BN$670))} -> 0 | D12: {=SUMPRODUCT(D$74:D$133,TRANSPOSE(SAP_Spreadsheet!$G$670:$BN$670))} -> 0 | E12: {=SUMPRODUCT(E$74:E$133,TRANSPOSE(SAP_Spreadsheet!$G$670:$BN$670))} -> 0 | F12: {=SUMPRODUCT(F$74:F$133,TRANSPOSE(SAP_Spreadsheet!$G$670:$BN$670))} -> 0 | G12: {=SUMPRODUCT(G$74:G$133,TRANSPOSE(SAP_Spreadsheet!$G$670:$BN$670))} -> 0 | H12: {=SUMPRODUCT(H$74:H$133,TRANSPOSE(SAP_Spreadsheet!$G$670:$BN$670))} -> 0 | I12: {=SUMPRODUCT(I$74:I$133,TRANSPOSE(SAP_Spreadsheet!$G$670:$BN$670))} -> 0 | J12: {=SUMPRODUCT(J$74:J$133,TRANSPOSE(SAP_Spreadsheet!$G$670:$BN$670))} -> 0 | ... BJ12: {=SUMPRODUCT(BJ$74:BJ$133,TRANSPOSE(SAP_Spreadsheet!$G$670:$BN$670))} -> 0
B13: COF | C13: {=SUMPRODUCT(C$74:C$133,TRANSPOSE(SAP_Spreadsheet!$G$673:$BN$673))} -> 0 | D13: {=SUMPRODUCT(D$74:D$133,TRANSPOSE(SAP_Spreadsheet!$G$673:$BN$673))} -> 0 | E13: {=SUMPRODUCT(E$74:E$133,TRANSPOSE(SAP_Spreadsheet!$G$673:$BN$673))} -> 0 | F13: {=SUMPRODUCT(F$74:F$133,TRANSPOSE(SAP_Spreadsheet!$G$673:$BN$673))} -> 0 | G13: {=SUMPRODUCT(G$74:G$133,TRANSPOSE(SAP_Spreadsheet!$G$673:$BN$673))} -> 0 | H13: {=SUMPRODUCT(H$74:H$133,TRANSPOSE(SAP_Spreadsheet!$G$673:$BN$673))} -> 0 | I13: {=SUMPRODUCT(I$74:I$133,TRANSPOSE(SAP_Spreadsheet!$G$673:$BN$673))} -> 0 | J13: {=SUMPRODUCT(J$74:J$133,TRANSPOSE(SAP_Spreadsheet!$G$673:$BN$673))} -> 0 | ... BJ13: {=SUMPRODUCT(BJ$74:BJ$133,TRANSPOSE(SAP_Spreadsheet!$G$673:$BN$673))} -> 0
B14: Net fee income | C14: {=SUMPRODUCT(C$74:C$133,TRANSPOSE(SAP_Spreadsheet!$G$677:$BN$677))} -> 0 | D14: {=SUMPRODUCT(D$74:D$133,TRANSPOSE(SAP_Spreadsheet!$G$677:$BN$677))} -> 0 | E14: {=SUMPRODUCT(E$74:E$133,TRANSPOSE(SAP_Spreadsheet!$G$677:$BN$677))} -> 0 | F14: {=SUMPRODUCT(F$74:F$133,TRANSPOSE(SAP_Spreadsheet!$G$677:$BN$677))} -> 0 | G14: {=SUMPRODUCT(G$74:G$133,TRANSPOSE(SAP_Spreadsheet!$G$677:$BN$677))} -> 0 | H14: {=SUMPRODUCT(H$74:H$133,TRANSPOSE(SAP_Spreadsheet!$G$677:$BN$677))} -> 0 | I14: {=SUMPRODUCT(I$74:I$133,TRANSPOSE(SAP_Spreadsheet!$G$677:$BN$677))} -> 0 | J14: {=SUMPRODUCT(J$74:J$133,TRANSPOSE(SAP_Spreadsheet!$G$677:$BN$677))} -> 0 | ... BJ14: {=SUMPRODUCT(BJ$74:BJ$133,TRANSPOSE(SAP_Spreadsheet!$G$677:$BN$677))} -> 0
B15: Interchange | C15: {=SUMPRODUCT(C$74:C$133,TRANSPOSE(SAP_Spreadsheet!$G$687:$BN$687))} -> 0 | D15: {=SUMPRODUCT(D$74:D$133,TRANSPOSE(SAP_Spreadsheet!$G$687:$BN$687))} -> 0 | E15: {=SUMPRODUCT(E$74:E$133,TRANSPOSE(SAP_Spreadsheet!$G$687:$BN$687))} -> 0 | F15: {=SUMPRODUCT(F$74:F$133,TRANSPOSE(SAP_Spreadsheet!$G$687:$BN$687))} -> 0 | G15: {=SUMPRODUCT(G$74:G$133,TRANSPOSE(SAP_Spreadsheet!$G$687:$BN$687))} -> 0 | H15: {=SUMPRODUCT(H$74:H$133,TRANSPOSE(SAP_Spreadsheet!$G$687:$BN$687))} -> 0 | I15: {=SUMPRODUCT(I$74:I$133,TRANSPOSE(SAP_Spreadsheet!$G$687:$BN$687))} -> 0 | J15: {=SUMPRODUCT(J$74:J$133,TRANSPOSE(SAP_Spreadsheet!$G$687:$BN$687))} -> 0 | ... BJ15: {=SUMPRODUCT(BJ$74:BJ$133,TRANSPOSE(SAP_Spreadsheet!$G$687:$BN$687))} -> 0
B16: Annual fee | C16: {=SUMPRODUCT(C$74:C$133,TRANSPOSE(SAP_Spreadsheet!$G$678:$BN$678))} -> 0 | D16: {=SUMPRODUCT(D$74:D$133,TRANSPOSE(SAP_Spreadsheet!$G$678:$BN$678))} -> 0 | E16: {=SUMPRODUCT(E$74:E$133,TRANSPOSE(SAP_Spreadsheet!$G$678:$BN$678))} -> 0 | F16: {=SUMPRODUCT(F$74:F$133,TRANSPOSE(SAP_Spreadsheet!$G$678:$BN$678))} -> 0 | G16: {=SUMPRODUCT(G$74:G$133,TRANSPOSE(SAP_Spreadsheet!$G$678:$BN$678))} -> 0 | H16: {=SUMPRODUCT(H$74:H$133,TRANSPOSE(SAP_Spreadsheet!$G$678:$BN$678))} -> 0 | I16: {=SUMPRODUCT(I$74:I$133,TRANSPOSE(SAP_Spreadsheet!$G$678:$BN$678))} -> 0 | J16: {=SUMPRODUCT(J$74:J$133,TRANSPOSE(SAP_Spreadsheet!$G$678:$BN$678))} -> 0 | ... BJ16: {=SUMPRODUCT(BJ$74:BJ$133,TRANSPOSE(SAP_Spreadsheet!$G$678:$BN$678))} -> 0
B17: Quarterly fee | C17: {=SUMPRODUCT(C$74:C$133,TRANSPOSE(SAP_Spreadsheet!$G$679:$BN$679))} -> 0 | D17: {=SUMPRODUCT(D$74:D$133,TRANSPOSE(SAP_Spreadsheet!$G$679:$BN$679))} -> 0 | E17: {=SUMPRODUCT(E$74:E$133,TRANSPOSE(SAP_Spreadsheet!$G$679:$BN$679))} -> 0 | F17: {=SUMPRODUCT(F$74:F$133,TRANSPOSE(SAP_Spreadsheet!$G$679:$BN$679))} -> 0 | G17: {=SUMPRODUCT(G$74:G$133,TRANSPOSE(SAP_Spreadsheet!$G$679:$BN$679))} -> 0 | H17: {=SUMPRODUCT(H$74:H$133,TRANSPOSE(SAP_Spreadsheet!$G$679:$BN$679))} -> 0 | I17: {=SUMPRODUCT(I$74:I$133,TRANSPOSE(SAP_Spreadsheet!$G$679:$BN$679))} -> 0 | J17: {=SUMPRODUCT(J$74:J$133,TRANSPOSE(SAP_Spreadsheet!$G$679:$BN$679))} -> 0 | ... BJ17: {=SUMPRODUCT(BJ$74:BJ$133,TRANSPOSE(SAP_Spreadsheet!$G$679:$BN$679))} -> 0
B18: Monthly fee | C18: {=SUMPRODUCT(C$74:C$133,TRANSPOSE(SAP_Spreadsheet!$G$680:$BN$680))} -> 0 | D18: {=SUMPRODUCT(D$74:D$133,TRANSPOSE(SAP_Spreadsheet!$G$680:$BN$680))} -> 0 | E18: {=SUMPRODUCT(E$74:E$133,TRANSPOSE(SAP_Spreadsheet!$G$680:$BN$680))} -> 0 | F18: {=SUMPRODUCT(F$74:F$133,TRANSPOSE(SAP_Spreadsheet!$G$680:$BN$680))} -> 0 | G18: {=SUMPRODUCT(G$74:G$133,TRANSPOSE(SAP_Spreadsheet!$G$680:$BN$680))} -> 0 | H18: {=SUMPRODUCT(H$74:H$133,TRANSPOSE(SAP_Spreadsheet!$G$680:$BN$680))} -> 0 | I18: {=SUMPRODUCT(I$74:I$133,TRANSPOSE(SAP_Spreadsheet!$G$680:$BN$680))} -> 0 | J18: {=SUMPRODUCT(J$74:J$133,TRANSPOSE(SAP_Spreadsheet!$G$680:$BN$680))} -> 0 | ... BJ18: {=SUMPRODUCT(BJ$74:BJ$133,TRANSPOSE(SAP_Spreadsheet!$G$680:$BN$680))} -> 0
B19: Issuance fee | C19: {=SUMPRODUCT(C$74:C$133,TRANSPOSE(SAP_Spreadsheet!$G$681:$BN$681))} -> 0 | D19: {=SUMPRODUCT(D$74:D$133,TRANSPOSE(SAP_Spreadsheet!$G$681:$BN$681))} -> 0 | E19: {=SUMPRODUCT(E$74:E$133,TRANSPOSE(SAP_Spreadsheet!$G$681:$BN$681))} -> 0 | F19: {=SUMPRODUCT(F$74:F$133,TRANSPOSE(SAP_Spreadsheet!$G$681:$BN$681))} -> 0 | G19: {=SUMPRODUCT(G$74:G$133,TRANSPOSE(SAP_Spreadsheet!$G$681:$BN$681))} -> 0 | H19: {=SUMPRODUCT(H$74:H$133,TRANSPOSE(SAP_Spreadsheet!$G$681:$BN$681))} -> 0 | I19: {=SUMPRODUCT(I$74:I$133,TRANSPOSE(SAP_Spreadsheet!$G$681:$BN$681))} -> 0 | J19: {=SUMPRODUCT(J$74:J$133,TRANSPOSE(SAP_Spreadsheet!$G$681:$BN$681))} -> 0 | ... BJ19: {=SUMPRODUCT(BJ$74:BJ$133,TRANSPOSE(SAP_Spreadsheet!$G$681:$BN$681))} -> 0
B20: Termination fee | C20: {=SUMPRODUCT(C$74:C$133,TRANSPOSE(SAP_Spreadsheet!$G$682:$BN$682))} -> 0 | D20: {=SUMPRODUCT(D$74:D$133,TRANSPOSE(SAP_Spreadsheet!$G$682:$BN$682))} -> 0 | E20: {=SUMPRODUCT(E$74:E$133,TRANSPOSE(SAP_Spreadsheet!$G$682:$BN$682))} -> 0 | F20: {=SUMPRODUCT(F$74:F$133,TRANSPOSE(SAP_Spreadsheet!$G$682:$BN$682))} -> 0 | G20: {=SUMPRODUCT(G$74:G$133,TRANSPOSE(SAP_Spreadsheet!$G$682:$BN$682))} -> 0 | H20: {=SUMPRODUCT(H$74:H$133,TRANSPOSE(SAP_Spreadsheet!$G$682:$BN$682))} -> 0 | I20: {=SUMPRODUCT(I$74:I$133,TRANSPOSE(SAP_Spreadsheet!$G$682:$BN$682))} -> 0 | J20: {=SUMPRODUCT(J$74:J$133,TRANSPOSE(SAP_Spreadsheet!$G$682:$BN$682))} -> 0 | ... BJ20: {=SUMPRODUCT(BJ$74:BJ$133,TRANSPOSE(SAP_Spreadsheet!$G$682:$BN$682))} -> 0
B21: Late payment | C21: {=SUMPRODUCT(C$74:C$133,TRANSPOSE(SAP_Spreadsheet!$G$683:$BN$683))} -> 0 | D21: {=SUMPRODUCT(D$74:D$133,TRANSPOSE(SAP_Spreadsheet!$G$683:$BN$683))} -> 0 | E21: {=SUMPRODUCT(E$74:E$133,TRANSPOSE(SAP_Spreadsheet!$G$683:$BN$683))} -> 0 | F21: {=SUMPRODUCT(F$74:F$133,TRANSPOSE(SAP_Spreadsheet!$G$683:$BN$683))} -> 0 | G21: {=SUMPRODUCT(G$74:G$133,TRANSPOSE(SAP_Spreadsheet!$G$683:$BN$683))} -> 0 | H21: {=SUMPRODUCT(H$74:H$133,TRANSPOSE(SAP_Spreadsheet!$G$683:$BN$683))} -> 0 | I21: {=SUMPRODUCT(I$74:I$133,TRANSPOSE(SAP_Spreadsheet!$G$683:$BN$683))} -> 0 | J21: {=SUMPRODUCT(J$74:J$133,TRANSPOSE(SAP_Spreadsheet!$G$683:$BN$683))} -> 0 | ... BJ21: {=SUMPRODUCT(BJ$74:BJ$133,TRANSPOSE(SAP_Spreadsheet!$G$683:$BN$683))} -> 0
B22: Cash advance | C22: {=SUMPRODUCT(C$74:C$133,TRANSPOSE(SAP_Spreadsheet!$G$684:$BN$684))} -> 0 | D22: {=SUMPRODUCT(D$74:D$133,TRANSPOSE(SAP_Spreadsheet!$G$684:$BN$684))} -> 0 | E22: {=SUMPRODUCT(E$74:E$133,TRANSPOSE(SAP_Spreadsheet!$G$684:$BN$684))} -> 0 | F22: {=SUMPRODUCT(F$74:F$133,TRANSPOSE(SAP_Spreadsheet!$G$684:$BN$684))} -> 0 | G22: {=SUMPRODUCT(G$74:G$133,TRANSPOSE(SAP_Spreadsheet!$G$684:$BN$684))} -> 0 | H22: {=SUMPRODUCT(H$74:H$133,TRANSPOSE(SAP_Spreadsheet!$G$684:$BN$684))} -> 0 | I22: {=SUMPRODUCT(I$74:I$133,TRANSPOSE(SAP_Spreadsheet!$G$684:$BN$684))} -> 0 | J22: {=SUMPRODUCT(J$74:J$133,TRANSPOSE(SAP_Spreadsheet!$G$684:$BN$684))} -> 0 | ... BJ22: {=SUMPRODUCT(BJ$74:BJ$133,TRANSPOSE(SAP_Spreadsheet!$G$684:$BN$684))} -> 0
B23: Currency conversion | C23: {=SUMPRODUCT(C$74:C$133,TRANSPOSE(SAP_Spreadsheet!$G$685:$BN$685))} -> 0 | D23: {=SUMPRODUCT(D$74:D$133,TRANSPOSE(SAP_Spreadsheet!$G$685:$BN$685))} -> 0 | E23: {=SUMPRODUCT(E$74:E$133,TRANSPOSE(SAP_Spreadsheet!$G$685:$BN$685))} -> 0 | F23: {=SUMPRODUCT(F$74:F$133,TRANSPOSE(SAP_Spreadsheet!$G$685:$BN$685))} -> 0 | G23: {=SUMPRODUCT(G$74:G$133,TRANSPOSE(SAP_Spreadsheet!$G$685:$BN$685))} -> 0 | H23: {=SUMPRODUCT(H$74:H$133,TRANSPOSE(SAP_Spreadsheet!$G$685:$BN$685))} -> 0 | I23: {=SUMPRODUCT(I$74:I$133,TRANSPOSE(SAP_Spreadsheet!$G$685:$BN$685))} -> 0 | J23: {=SUMPRODUCT(J$74:J$133,TRANSPOSE(SAP_Spreadsheet!$G$685:$BN$685))} -> 0 | ... BJ23: {=SUMPRODUCT(BJ$74:BJ$133,TRANSPOSE(SAP_Spreadsheet!$G$685:$BN$685))} -> 0
B24: Insurance fee | C24: {=SUMPRODUCT(C$74:C$133,TRANSPOSE(SAP_Spreadsheet!$G$686:$BN$686))} -> 0 | D24: {=SUMPRODUCT(D$74:D$133,TRANSPOSE(SAP_Spreadsheet!$G$686:$BN$686))} -> 0 | E24: {=SUMPRODUCT(E$74:E$133,TRANSPOSE(SAP_Spreadsheet!$G$686:$BN$686))} -> 0 | F24: {=SUMPRODUCT(F$74:F$133,TRANSPOSE(SAP_Spreadsheet!$G$686:$BN$686))} -> 0 | G24: {=SUMPRODUCT(G$74:G$133,TRANSPOSE(SAP_Spreadsheet!$G$686:$BN$686))} -> 0 | H24: {=SUMPRODUCT(H$74:H$133,TRANSPOSE(SAP_Spreadsheet!$G$686:$BN$686))} -> 0 | I24: {=SUMPRODUCT(I$74:I$133,TRANSPOSE(SAP_Spreadsheet!$G$686:$BN$686))} -> 0 | J24: {=SUMPRODUCT(J$74:J$133,TRANSPOSE(SAP_Spreadsheet!$G$686:$BN$686))} -> 0 | ... BJ24: {=SUMPRODUCT(BJ$74:BJ$133,TRANSPOSE(SAP_Spreadsheet!$G$686:$BN$686))} -> 0
B25: EMI initial fee | C25: {=SUMPRODUCT(C$74:C$133,TRANSPOSE(SAP_Spreadsheet!$G$694:$BN$694))} -> 0 | D25: {=SUMPRODUCT(D$74:D$133,TRANSPOSE(SAP_Spreadsheet!$G$694:$BN$694))} -> 0 | E25: {=SUMPRODUCT(E$74:E$133,TRANSPOSE(SAP_Spreadsheet!$G$694:$BN$694))} -> 0 | F25: {=SUMPRODUCT(F$74:F$133,TRANSPOSE(SAP_Spreadsheet!$G$694:$BN$694))} -> 0 | G25: {=SUMPRODUCT(G$74:G$133,TRANSPOSE(SAP_Spreadsheet!$G$694:$BN$694))} -> 0 | H25: {=SUMPRODUCT(H$74:H$133,TRANSPOSE(SAP_Spreadsheet!$G$694:$BN$694))} -> 0 | I25: {=SUMPRODUCT(I$74:I$133,TRANSPOSE(SAP_Spreadsheet!$G$694:$BN$694))} -> 0 | J25: {=SUMPRODUCT(J$74:J$133,TRANSPOSE(SAP_Spreadsheet!$G$694:$BN$694))} -> 0 | ... BJ25: {=SUMPRODUCT(BJ$74:BJ$133,TRANSPOSE(SAP_Spreadsheet!$G$694:$BN$694))} -> 0
B26: EMI early repayment fee | C26: {=SUMPRODUCT(C$74:C$133,TRANSPOSE(SAP_Spreadsheet!$G$703:$BN$703))} -> 0 | D26: {=SUMPRODUCT(D$74:D$133,TRANSPOSE(SAP_Spreadsheet!$G$703:$BN$703))} -> 0 | E26: {=SUMPRODUCT(E$74:E$133,TRANSPOSE(SAP_Spreadsheet!$G$703:$BN$703))} -> 0 | F26: {=SUMPRODUCT(F$74:F$133,TRANSPOSE(SAP_Spreadsheet!$G$703:$BN$703))} -> 0 | G26: {=SUMPRODUCT(G$74:G$133,TRANSPOSE(SAP_Spreadsheet!$G$703:$BN$703))} -> 0 | H26: {=SUMPRODUCT(H$74:H$133,TRANSPOSE(SAP_Spreadsheet!$G$703:$BN$703))} -> 0 | I26: {=SUMPRODUCT(I$74:I$133,TRANSPOSE(SAP_Spreadsheet!$G$703:$BN$703))} -> 0 | J26: {=SUMPRODUCT(J$74:J$133,TRANSPOSE(SAP_Spreadsheet!$G$703:$BN$703))} -> 0 | ... BJ26: {=SUMPRODUCT(BJ$74:BJ$133,TRANSPOSE(SAP_Spreadsheet!$G$703:$BN$703))} -> 0
B27: Vendor service fee | C27: {=SUMPRODUCT(C$74:C$133,TRANSPOSE(SAP_Spreadsheet!$G$688:$BN$688))} -> 0 | D27: {=SUMPRODUCT(D$74:D$133,TRANSPOSE(SAP_Spreadsheet!$G$688:$BN$688))} -> 0 | E27: {=SUMPRODUCT(E$74:E$133,TRANSPOSE(SAP_Spreadsheet!$G$688:$BN$688))} -> 0 | F27: {=SUMPRODUCT(F$74:F$133,TRANSPOSE(SAP_Spreadsheet!$G$688:$BN$688))} -> 0 | G27: {=SUMPRODUCT(G$74:G$133,TRANSPOSE(SAP_Spreadsheet!$G$688:$BN$688))} -> 0 | H27: {=SUMPRODUCT(H$74:H$133,TRANSPOSE(SAP_Spreadsheet!$G$688:$BN$688))} -> 0 | I27: {=SUMPRODUCT(I$74:I$133,TRANSPOSE(SAP_Spreadsheet!$G$688:$BN$688))} -> 0 | J27: {=SUMPRODUCT(J$74:J$133,TRANSPOSE(SAP_Spreadsheet!$G$688:$BN$688))} -> 0 | ... BJ27: {=SUMPRODUCT(BJ$74:BJ$133,TRANSPOSE(SAP_Spreadsheet!$G$688:$BN$688))} -> 0
B28: Processing fee | C28: {=SUMPRODUCT(C$74:C$133,TRANSPOSE(SAP_Spreadsheet!$G$689:$BN$689))} -> 0 | D28: {=SUMPRODUCT(D$74:D$133,TRANSPOSE(SAP_Spreadsheet!$G$689:$BN$689))} -> 0 | E28: {=SUMPRODUCT(E$74:E$133,TRANSPOSE(SAP_Spreadsheet!$G$689:$BN$689))} -> 0 | F28: {=SUMPRODUCT(F$74:F$133,TRANSPOSE(SAP_Spreadsheet!$G$689:$BN$689))} -> 0 | G28: {=SUMPRODUCT(G$74:G$133,TRANSPOSE(SAP_Spreadsheet!$G$689:$BN$689))} -> 0 | H28: {=SUMPRODUCT(H$74:H$133,TRANSPOSE(SAP_Spreadsheet!$G$689:$BN$689))} -> 0 | I28: {=SUMPRODUCT(I$74:I$133,TRANSPOSE(SAP_Spreadsheet!$G$689:$BN$689))} -> 0 | J28: {=SUMPRODUCT(J$74:J$133,TRANSPOSE(SAP_Spreadsheet!$G$689:$BN$689))} -> 0 | ... BJ28: {=SUMPRODUCT(BJ$74:BJ$133,TRANSPOSE(SAP_Spreadsheet!$G$689:$BN$689))} -> 0
B29: Support processing fee | C29: {=SUMPRODUCT(C$74:C$133,TRANSPOSE(SAP_Spreadsheet!$G$690:$BN$690))} -> 0 | D29: {=SUMPRODUCT(D$74:D$133,TRANSPOSE(SAP_Spreadsheet!$G$690:$BN$690))} -> 0 | E29: {=SUMPRODUCT(E$74:E$133,TRANSPOSE(SAP_Spreadsheet!$G$690:$BN$690))} -> 0 | F29: {=SUMPRODUCT(F$74:F$133,TRANSPOSE(SAP_Spreadsheet!$G$690:$BN$690))} -> 0 | G29: {=SUMPRODUCT(G$74:G$133,TRANSPOSE(SAP_Spreadsheet!$G$690:$BN$690))} -> 0 | H29: {=SUMPRODUCT(H$74:H$133,TRANSPOSE(SAP_Spreadsheet!$G$690:$BN$690))} -> 0 | I29: {=SUMPRODUCT(I$74:I$133,TRANSPOSE(SAP_Spreadsheet!$G$690:$BN$690))} -> 0 | J29: {=SUMPRODUCT(J$74:J$133,TRANSPOSE(SAP_Spreadsheet!$G$690:$BN$690))} -> 0 | ... BJ29: {=SUMPRODUCT(BJ$74:BJ$133,TRANSPOSE(SAP_Spreadsheet!$G$690:$BN$690))} -> 0
B30: Customer rewards | C30: {=SUMPRODUCT(C$74:C$133,TRANSPOSE(SAP_Spreadsheet!$G$691:$BN$691))} -> 0 | D30: {=SUMPRODUCT(D$74:D$133,TRANSPOSE(SAP_Spreadsheet!$G$691:$BN$691))} -> 0 | E30: {=SUMPRODUCT(E$74:E$133,TRANSPOSE(SAP_Spreadsheet!$G$691:$BN$691))} -> 0 | F30: {=SUMPRODUCT(F$74:F$133,TRANSPOSE(SAP_Spreadsheet!$G$691:$BN$691))} -> 0 | G30: {=SUMPRODUCT(G$74:G$133,TRANSPOSE(SAP_Spreadsheet!$G$691:$BN$691))} -> 0 | H30: {=SUMPRODUCT(H$74:H$133,TRANSPOSE(SAP_Spreadsheet!$G$691:$BN$691))} -> 0 | I30: {=SUMPRODUCT(I$74:I$133,TRANSPOSE(SAP_Spreadsheet!$G$691:$BN$691))} -> 0 | J30: {=SUMPRODUCT(J$74:J$133,TRANSPOSE(SAP_Spreadsheet!$G$691:$BN$691))} -> 0 | ... BJ30: {=SUMPRODUCT(BJ$74:BJ$133,TRANSPOSE(SAP_Spreadsheet!$G$691:$BN$691))} -> 0
B31: Fee Suspends | C31: {=SUMPRODUCT(C$74:C$133,TRANSPOSE(SAP_Spreadsheet!$G$707:$BN$707))} -> 0 | D31: {=SUMPRODUCT(D$74:D$133,TRANSPOSE(SAP_Spreadsheet!$G$707:$BN$707))} -> 0 | E31: {=SUMPRODUCT(E$74:E$133,TRANSPOSE(SAP_Spreadsheet!$G$707:$BN$707))} -> 0 | F31: {=SUMPRODUCT(F$74:F$133,TRANSPOSE(SAP_Spreadsheet!$G$707:$BN$707))} -> 0 | G31: {=SUMPRODUCT(G$74:G$133,TRANSPOSE(SAP_Spreadsheet!$G$707:$BN$707))} -> 0 | H31: {=SUMPRODUCT(H$74:H$133,TRANSPOSE(SAP_Spreadsheet!$G$707:$BN$707))} -> 0 | I31: {=SUMPRODUCT(I$74:I$133,TRANSPOSE(SAP_Spreadsheet!$G$707:$BN$707))} -> 0 | J31: {=SUMPRODUCT(J$74:J$133,TRANSPOSE(SAP_Spreadsheet!$G$707:$BN$707))} -> 0 | ... BJ31: {=SUMPRODUCT(BJ$74:BJ$133,TRANSPOSE(SAP_Spreadsheet!$G$707:$BN$707))} -> 0
B33: OPEX | C33: {=SUMPRODUCT(C$74:C$133,TRANSPOSE(SAP_Spreadsheet!$G$752:$BN$752))} -> 0 | D33: {=SUMPRODUCT(D$74:D$133,TRANSPOSE(SAP_Spreadsheet!$G$752:$BN$752))} -> 0 | E33: {=SUMPRODUCT(E$74:E$133,TRANSPOSE(SAP_Spreadsheet!$G$752:$BN$752))} -> 0 | F33: {=SUMPRODUCT(F$74:F$133,TRANSPOSE(SAP_Spreadsheet!$G$752:$BN$752))} -> 0 | G33: {=SUMPRODUCT(G$74:G$133,TRANSPOSE(SAP_Spreadsheet!$G$752:$BN$752))} -> 0 | H33: {=SUMPRODUCT(H$74:H$133,TRANSPOSE(SAP_Spreadsheet!$G$752:$BN$752))} -> 0 | I33: {=SUMPRODUCT(I$74:I$133,TRANSPOSE(SAP_Spreadsheet!$G$752:$BN$752))} -> 0 | J33: {=SUMPRODUCT(J$74:J$133,TRANSPOSE(SAP_Spreadsheet!$G$752:$BN$752))} -> 0 | ... BJ33: {=SUMPRODUCT(BJ$74:BJ$133,TRANSPOSE(SAP_Spreadsheet!$G$752:$BN$752))} -> 0
B34: Sales team & mgt | C34: =SUM(C36:C39) -> 0 | D34: =SUM(D36:D39) -> 0 | E34: =SUM(E36:E39) -> 0 | F34: =SUM(F36:F39) -> 0 | G34: =SUM(G36:G39) -> 0 | H34: =SUM(H36:H39) -> 0 | I34: =SUM(I36:I39) -> 0 | J34: =SUM(J36:J39) -> 0 | ... BJ34: =SUM(BJ36:BJ39) -> 0
B35: Lead acquisition | C35: {=SUMPRODUCT(C$74:C$133,TRANSPOSE(SAP_Spreadsheet!$G$715:$BN$715))} -> 0 | D35: {=SUMPRODUCT(D$74:D$133,TRANSPOSE(SAP_Spreadsheet!$G$715:$BN$715))} -> 0 | E35: {=SUMPRODUCT(E$74:E$133,TRANSPOSE(SAP_Spreadsheet!$G$715:$BN$715))} -> 0 | F35: {=SUMPRODUCT(F$74:F$133,TRANSPOSE(SAP_Spreadsheet!$G$715:$BN$715))} -> 0 | G35: {=SUMPRODUCT(G$74:G$133,TRANSPOSE(SAP_Spreadsheet!$G$715:$BN$715))} -> 0 | H35: {=SUMPRODUCT(H$74:H$133,TRANSPOSE(SAP_Spreadsheet!$G$715:$BN$715))} -> 0 | I35: {=SUMPRODUCT(I$74:I$133,TRANSPOSE(SAP_Spreadsheet!$G$715:$BN$715))} -> 0 | J35: {=SUMPRODUCT(J$74:J$133,TRANSPOSE(SAP_Spreadsheet!$G$715:$BN$715))} -> 0 | ... BJ35: {=SUMPRODUCT(BJ$74:BJ$133,TRANSPOSE(SAP_Spreadsheet!$G$715:$BN$715))} -> 0
B36: Sharing TOI only | C36: {=SUMPRODUCT(C$74:C$133,TRANSPOSE(SAP_Spreadsheet!$G$716:$BN$716))} -> 0 | D36: {=SUMPRODUCT(D$74:D$133,TRANSPOSE(SAP_Spreadsheet!$G$716:$BN$716))} -> 0 | E36: {=SUMPRODUCT(E$74:E$133,TRANSPOSE(SAP_Spreadsheet!$G$716:$BN$716))} -> 0 | F36: {=SUMPRODUCT(F$74:F$133,TRANSPOSE(SAP_Spreadsheet!$G$716:$BN$716))} -> 0 | G36: {=SUMPRODUCT(G$74:G$133,TRANSPOSE(SAP_Spreadsheet!$G$716:$BN$716))} -> 0 | H36: {=SUMPRODUCT(H$74:H$133,TRANSPOSE(SAP_Spreadsheet!$G$716:$BN$716))} -> 0 | I36: {=SUMPRODUCT(I$74:I$133,TRANSPOSE(SAP_Spreadsheet!$G$716:$BN$716))} -> 0 | J36: {=SUMPRODUCT(J$74:J$133,TRANSPOSE(SAP_Spreadsheet!$G$716:$BN$716))} -> 0 | ... BJ36: {=SUMPRODUCT(BJ$74:BJ$133,TRANSPOSE(SAP_Spreadsheet!$G$716:$BN$716))} -> 0
B37: Sharing TOI+Risk DPD90 | C37: {=SUMPRODUCT(C$74:C$133,TRANSPOSE(SAP_Spreadsheet!$G$717:$BN$717))} -> 0 | D37: {=SUMPRODUCT(D$74:D$133,TRANSPOSE(SAP_Spreadsheet!$G$717:$BN$717))} -> 0 | E37: {=SUMPRODUCT(E$74:E$133,TRANSPOSE(SAP_Spreadsheet!$G$717:$BN$717))} -> 0 | F37: {=SUMPRODUCT(F$74:F$133,TRANSPOSE(SAP_Spreadsheet!$G$717:$BN$717))} -> 0 | G37: {=SUMPRODUCT(G$74:G$133,TRANSPOSE(SAP_Spreadsheet!$G$717:$BN$717))} -> 0 | H37: {=SUMPRODUCT(H$74:H$133,TRANSPOSE(SAP_Spreadsheet!$G$717:$BN$717))} -> 0 | I37: {=SUMPRODUCT(I$74:I$133,TRANSPOSE(SAP_Spreadsheet!$G$717:$BN$717))} -> 0 | J37: {=SUMPRODUCT(J$74:J$133,TRANSPOSE(SAP_Spreadsheet!$G$717:$BN$717))} -> 0 | ... BJ37: {=SUMPRODUCT(BJ$74:BJ$133,TRANSPOSE(SAP_Spreadsheet!$G$717:$BN$717))} -> 0
B38: Sharing TOI+Risk DPD180 | C38: {=SUMPRODUCT(C$74:C$133,TRANSPOSE(SAP_Spreadsheet!$G$718:$BN$718))} -> 0 | D38: {=SUMPRODUCT(D$74:D$133,TRANSPOSE(SAP_Spreadsheet!$G$718:$BN$718))} -> 0 | E38: {=SUMPRODUCT(E$74:E$133,TRANSPOSE(SAP_Spreadsheet!$G$718:$BN$718))} -> 0 | F38: {=SUMPRODUCT(F$74:F$133,TRANSPOSE(SAP_Spreadsheet!$G$718:$BN$718))} -> 0 | G38: {=SUMPRODUCT(G$74:G$133,TRANSPOSE(SAP_Spreadsheet!$G$718:$BN$718))} -> 0 | H38: {=SUMPRODUCT(H$74:H$133,TRANSPOSE(SAP_Spreadsheet!$G$718:$BN$718))} -> 0 | I38: {=SUMPRODUCT(I$74:I$133,TRANSPOSE(SAP_Spreadsheet!$G$718:$BN$718))} -> 0 | J38: {=SUMPRODUCT(J$74:J$133,TRANSPOSE(SAP_Spreadsheet!$G$718:$BN$718))} -> 0 | ... BJ38: {=SUMPRODUCT(BJ$74:BJ$133,TRANSPOSE(SAP_Spreadsheet!$G$718:$BN$718))} -> 0
B39: Marketing acquisition | C39: {=SUMPRODUCT(C$74:C$133,TRANSPOSE(SAP_Spreadsheet!$G$719:$BN$719))} -> 0 | D39: {=SUMPRODUCT(D$74:D$133,TRANSPOSE(SAP_Spreadsheet!$G$719:$BN$719))} -> 0 | E39: {=SUMPRODUCT(E$74:E$133,TRANSPOSE(SAP_Spreadsheet!$G$719:$BN$719))} -> 0 | F39: {=SUMPRODUCT(F$74:F$133,TRANSPOSE(SAP_Spreadsheet!$G$719:$BN$719))} -> 0 | G39: {=SUMPRODUCT(G$74:G$133,TRANSPOSE(SAP_Spreadsheet!$G$719:$BN$719))} -> 0 | H39: {=SUMPRODUCT(H$74:H$133,TRANSPOSE(SAP_Spreadsheet!$G$719:$BN$719))} -> 0 | I39: {=SUMPRODUCT(I$74:I$133,TRANSPOSE(SAP_Spreadsheet!$G$719:$BN$719))} -> 0 | J39: {=SUMPRODUCT(J$74:J$133,TRANSPOSE(SAP_Spreadsheet!$G$719:$BN$719))} -> 0 | ... BJ39: {=SUMPRODUCT(BJ$74:BJ$133,TRANSPOSE(SAP_Spreadsheet!$G$719:$BN$719))} -> 0
B40: Marketing promotion | C40: {=SUMPRODUCT(C$74:C$133,TRANSPOSE(SAP_Spreadsheet!$G$722:$BN$722))} -> 0 | D40: {=SUMPRODUCT(D$74:D$133,TRANSPOSE(SAP_Spreadsheet!$G$722:$BN$722))} -> 0 | E40: {=SUMPRODUCT(E$74:E$133,TRANSPOSE(SAP_Spreadsheet!$G$722:$BN$722))} -> 0 | F40: {=SUMPRODUCT(F$74:F$133,TRANSPOSE(SAP_Spreadsheet!$G$722:$BN$722))} -> 0 | G40: {=SUMPRODUCT(G$74:G$133,TRANSPOSE(SAP_Spreadsheet!$G$722:$BN$722))} -> 0 | H40: {=SUMPRODUCT(H$74:H$133,TRANSPOSE(SAP_Spreadsheet!$G$722:$BN$722))} -> 0 | I40: {=SUMPRODUCT(I$74:I$133,TRANSPOSE(SAP_Spreadsheet!$G$722:$BN$722))} -> 0 | J40: {=SUMPRODUCT(J$74:J$133,TRANSPOSE(SAP_Spreadsheet!$G$722:$BN$722))} -> 0 | ... BJ40: {=SUMPRODUCT(BJ$74:BJ$133,TRANSPOSE(SAP_Spreadsheet!$G$722:$BN$722))} -> 0
B41: Physical card | C41: {=SUMPRODUCT(C$74:C$133,TRANSPOSE(SAP_Spreadsheet!$G$723:$BN$723))} -> 0 | D41: {=SUMPRODUCT(D$74:D$133,TRANSPOSE(SAP_Spreadsheet!$G$723:$BN$723))} -> 0 | E41: {=SUMPRODUCT(E$74:E$133,TRANSPOSE(SAP_Spreadsheet!$G$723:$BN$723))} -> 0 | F41: {=SUMPRODUCT(F$74:F$133,TRANSPOSE(SAP_Spreadsheet!$G$723:$BN$723))} -> 0 | G41: {=SUMPRODUCT(G$74:G$133,TRANSPOSE(SAP_Spreadsheet!$G$723:$BN$723))} -> 0 | H41: {=SUMPRODUCT(H$74:H$133,TRANSPOSE(SAP_Spreadsheet!$G$723:$BN$723))} -> 0 | I41: {=SUMPRODUCT(I$74:I$133,TRANSPOSE(SAP_Spreadsheet!$G$723:$BN$723))} -> 0 | J41: {=SUMPRODUCT(J$74:J$133,TRANSPOSE(SAP_Spreadsheet!$G$723:$BN$723))} -> 0 | ... BJ41: {=SUMPRODUCT(BJ$74:BJ$133,TRANSPOSE(SAP_Spreadsheet!$G$723:$BN$723))} -> 0
B42: UW & Disbursal | C42: {=SUMPRODUCT(C$74:C$133,TRANSPOSE(SAP_Spreadsheet!$G$729:$BN$729))} -> 0 | D42: {=SUMPRODUCT(D$74:D$133,TRANSPOSE(SAP_Spreadsheet!$G$729:$BN$729))} -> 0 | E42: {=SUMPRODUCT(E$74:E$133,TRANSPOSE(SAP_Spreadsheet!$G$729:$BN$729))} -> 0 | F42: {=SUMPRODUCT(F$74:F$133,TRANSPOSE(SAP_Spreadsheet!$G$729:$BN$729))} -> 0 | G42: {=SUMPRODUCT(G$74:G$133,TRANSPOSE(SAP_Spreadsheet!$G$729:$BN$729))} -> 0 | H42: {=SUMPRODUCT(H$74:H$133,TRANSPOSE(SAP_Spreadsheet!$G$729:$BN$729))} -> 0 | I42: {=SUMPRODUCT(I$74:I$133,TRANSPOSE(SAP_Spreadsheet!$G$729:$BN$729))} -> 0 | J42: {=SUMPRODUCT(J$74:J$133,TRANSPOSE(SAP_Spreadsheet!$G$729:$BN$729))} -> 0 | ... BJ42: {=SUMPRODUCT(BJ$74:BJ$133,TRANSPOSE(SAP_Spreadsheet!$G$729:$BN$729))} -> 0
B43: Collection | C43: =C44+C45 -> 0 | D43: =D44+D45 -> 0 | E43: =E44+E45 -> 0 | F43: =F44+F45 -> 0 | G43: =G44+G45 -> 0 | H43: =H44+H45 -> 0 | I43: =I44+I45 -> 0 | J43: =J44+J45 -> 0 | ... BJ43: =BJ44+BJ45 -> 0
B44: Early collections | C44: {=SUMPRODUCT(C$74:C$133,TRANSPOSE(SAP_Spreadsheet!$G$741:$BN$741))} -> 0 | D44: {=SUMPRODUCT(D$74:D$133,TRANSPOSE(SAP_Spreadsheet!$G$741:$BN$741))} -> 0 | E44: {=SUMPRODUCT(E$74:E$133,TRANSPOSE(SAP_Spreadsheet!$G$741:$BN$741))} -> 0 | F44: {=SUMPRODUCT(F$74:F$133,TRANSPOSE(SAP_Spreadsheet!$G$741:$BN$741))} -> 0 | G44: {=SUMPRODUCT(G$74:G$133,TRANSPOSE(SAP_Spreadsheet!$G$741:$BN$741))} -> 0 | H44: {=SUMPRODUCT(H$74:H$133,TRANSPOSE(SAP_Spreadsheet!$G$741:$BN$741))} -> 0 | I44: {=SUMPRODUCT(I$74:I$133,TRANSPOSE(SAP_Spreadsheet!$G$741:$BN$741))} -> 0 | J44: {=SUMPRODUCT(J$74:J$133,TRANSPOSE(SAP_Spreadsheet!$G$741:$BN$741))} -> 0 | ... BJ44: {=SUMPRODUCT(BJ$74:BJ$133,TRANSPOSE(SAP_Spreadsheet!$G$741:$BN$741))} -> 0
B45: AMC | C45: {=SUMPRODUCT(C$74:C$133,TRANSPOSE(SAP_Spreadsheet!$G$742:$BN$742))} -> 0 | D45: {=SUMPRODUCT(D$74:D$133,TRANSPOSE(SAP_Spreadsheet!$G$742:$BN$742))} -> 0 | E45: {=SUMPRODUCT(E$74:E$133,TRANSPOSE(SAP_Spreadsheet!$G$742:$BN$742))} -> 0 | F45: {=SUMPRODUCT(F$74:F$133,TRANSPOSE(SAP_Spreadsheet!$G$742:$BN$742))} -> 0 | G45: {=SUMPRODUCT(G$74:G$133,TRANSPOSE(SAP_Spreadsheet!$G$742:$BN$742))} -> 0 | H45: {=SUMPRODUCT(H$74:H$133,TRANSPOSE(SAP_Spreadsheet!$G$742:$BN$742))} -> 0 | I45: {=SUMPRODUCT(I$74:I$133,TRANSPOSE(SAP_Spreadsheet!$G$742:$BN$742))} -> 0 | J45: {=SUMPRODUCT(J$74:J$133,TRANSPOSE(SAP_Spreadsheet!$G$742:$BN$742))} -> 0 | ... BJ45: {=SUMPRODUCT(BJ$74:BJ$133,TRANSPOSE(SAP_Spreadsheet!$G$742:$BN$742))} -> 0
B46: After-sales services | C46: {=SUMPRODUCT(C$74:C$133,TRANSPOSE(SAP_Spreadsheet!$G$736:$BN$736))} -> 0 | D46: {=SUMPRODUCT(D$74:D$133,TRANSPOSE(SAP_Spreadsheet!$G$736:$BN$736))} -> 0 | E46: {=SUMPRODUCT(E$74:E$133,TRANSPOSE(SAP_Spreadsheet!$G$736:$BN$736))} -> 0 | F46: {=SUMPRODUCT(F$74:F$133,TRANSPOSE(SAP_Spreadsheet!$G$736:$BN$736))} -> 0 | G46: {=SUMPRODUCT(G$74:G$133,TRANSPOSE(SAP_Spreadsheet!$G$736:$BN$736))} -> 0 | H46: {=SUMPRODUCT(H$74:H$133,TRANSPOSE(SAP_Spreadsheet!$G$736:$BN$736))} -> 0 | I46: {=SUMPRODUCT(I$74:I$133,TRANSPOSE(SAP_Spreadsheet!$G$736:$BN$736))} -> 0 | J46: {=SUMPRODUCT(J$74:J$133,TRANSPOSE(SAP_Spreadsheet!$G$736:$BN$736))} -> 0 | ... BJ46: {=SUMPRODUCT(BJ$74:BJ$133,TRANSPOSE(SAP_Spreadsheet!$G$736:$BN$736))} -> 0
B47: Other support units | C47: {=SUMPRODUCT(C$74:C$133,TRANSPOSE(SAP_Spreadsheet!$G$749:$BN$749))} -> 0 | D47: {=SUMPRODUCT(D$74:D$133,TRANSPOSE(SAP_Spreadsheet!$G$749:$BN$749))} -> 0 | E47: {=SUMPRODUCT(E$74:E$133,TRANSPOSE(SAP_Spreadsheet!$G$749:$BN$749))} -> 0 | F47: {=SUMPRODUCT(F$74:F$133,TRANSPOSE(SAP_Spreadsheet!$G$749:$BN$749))} -> 0 | G47: {=SUMPRODUCT(G$74:G$133,TRANSPOSE(SAP_Spreadsheet!$G$749:$BN$749))} -> 0 | H47: {=SUMPRODUCT(H$74:H$133,TRANSPOSE(SAP_Spreadsheet!$G$749:$BN$749))} -> 0 | I47: {=SUMPRODUCT(I$74:I$133,TRANSPOSE(SAP_Spreadsheet!$G$749:$BN$749))} -> 0 | J47: {=SUMPRODUCT(J$74:J$133,TRANSPOSE(SAP_Spreadsheet!$G$749:$BN$749))} -> 0 | ... BJ47: {=SUMPRODUCT(BJ$74:BJ$133,TRANSPOSE(SAP_Spreadsheet!$G$749:$BN$749))} -> 0
B48: PROVISION | C48: {=SUMPRODUCT(C$74:C$133,TRANSPOSE(SAP_Spreadsheet!$G$807:$BN$807))} -> 0 | D48: {=SUMPRODUCT(D$74:D$133,TRANSPOSE(SAP_Spreadsheet!$G$807:$BN$807))} -> 0 | E48: {=SUMPRODUCT(E$74:E$133,TRANSPOSE(SAP_Spreadsheet!$G$807:$BN$807))} -> 0 | F48: {=SUMPRODUCT(F$74:F$133,TRANSPOSE(SAP_Spreadsheet!$G$807:$BN$807))} -> 0 | G48: {=SUMPRODUCT(G$74:G$133,TRANSPOSE(SAP_Spreadsheet!$G$807:$BN$807))} -> 0 | H48: {=SUMPRODUCT(H$74:H$133,TRANSPOSE(SAP_Spreadsheet!$G$807:$BN$807))} -> 0 | I48: {=SUMPRODUCT(I$74:I$133,TRANSPOSE(SAP_Spreadsheet!$G$807:$BN$807))} -> 0 | J48: {=SUMPRODUCT(J$74:J$133,TRANSPOSE(SAP_Spreadsheet!$G$807:$BN$807))} -> 0 | ... BJ48: {=SUMPRODUCT(BJ$74:BJ$133,TRANSPOSE(SAP_Spreadsheet!$G$807:$BN$807))} -> 0
B49: Other Income | C49: {=SUMPRODUCT(C$74:C$133,TRANSPOSE(SAP_Spreadsheet!$G$709:$BN$709))} -> 0 | D49: {=SUMPRODUCT(D$74:D$133,TRANSPOSE(SAP_Spreadsheet!$G$709:$BN$709))} -> 0 | E49: {=SUMPRODUCT(E$74:E$133,TRANSPOSE(SAP_Spreadsheet!$G$709:$BN$709))} -> 0 | F49: {=SUMPRODUCT(F$74:F$133,TRANSPOSE(SAP_Spreadsheet!$G$709:$BN$709))} -> 0 | G49: {=SUMPRODUCT(G$74:G$133,TRANSPOSE(SAP_Spreadsheet!$G$709:$BN$709))} -> 0 | H49: {=SUMPRODUCT(H$74:H$133,TRANSPOSE(SAP_Spreadsheet!$G$709:$BN$709))} -> 0 | I49: {=SUMPRODUCT(I$74:I$133,TRANSPOSE(SAP_Spreadsheet!$G$709:$BN$709))} -> 0 | J49: {=SUMPRODUCT(J$74:J$133,TRANSPOSE(SAP_Spreadsheet!$G$709:$BN$709))} -> 0 | ... BJ49: {=SUMPRODUCT(BJ$74:BJ$133,TRANSPOSE(SAP_Spreadsheet!$G$709:$BN$709))} -> 0
B50: PBT | C50: =C9+C33+C48+C49 -> 0 | D50: =D9+D33+D48+D49 -> 0 | E50: =E9+E33+E48+E49 -> 0 | F50: =F9+F33+F48+F49 -> 0 | G50: =G9+G33+G48+G49 -> 0 | H50: =H9+H33+H48+H49 -> 0 | I50: =I9+I33+I48+I49 -> 0 | J50: =J9+J33+J48+J49 -> 0 | ... BJ50: =BJ9+BJ33+BJ48+BJ49 -> 0
B52: Checking | C52: =C9+C33+C48-C50 -> 0 | D52: =D9+D33+D48-D50 -> 0 | E52: =E9+E33+E48-E50 -> 0 | F52: =F9+F33+F48-F50 -> 0 | G52: =G9+G33+G48-G50 -> 0 | H52: =H9+H33+H48-H50 -> 0 | I52: =I9+I33+I48-I50 -> 0 | J52: =J9+J33+J48-J50 -> 0 | ... BJ52: =BJ9+BJ33+BJ48-BJ50 -> 0
B53: EOP BY BUCKET
B54: B0 | C54: {=SUMPRODUCT(C$74:C$133,TRANSPOSE(SAP_Spreadsheet!$G$632:$BN$632))} -> 0 | D54: {=SUMPRODUCT(D$74:D$133,TRANSPOSE(SAP_Spreadsheet!$G$632:$BN$632))} -> 0 | E54: {=SUMPRODUCT(E$74:E$133,TRANSPOSE(SAP_Spreadsheet!$G$632:$BN$632))} -> 0 | F54: {=SUMPRODUCT(F$74:F$133,TRANSPOSE(SAP_Spreadsheet!$G$632:$BN$632))} -> 0 | G54: {=SUMPRODUCT(G$74:G$133,TRANSPOSE(SAP_Spreadsheet!$G$632:$BN$632))} -> 0 | H54: {=SUMPRODUCT(H$74:H$133,TRANSPOSE(SAP_Spreadsheet!$G$632:$BN$632))} -> 0 | I54: {=SUMPRODUCT(I$74:I$133,TRANSPOSE(SAP_Spreadsheet!$G$632:$BN$632))} -> 0 | J54: {=SUMPRODUCT(J$74:J$133,TRANSPOSE(SAP_Spreadsheet!$G$632:$BN$632))} -> 0 | ... BJ54: {=SUMPRODUCT(BJ$74:BJ$133,TRANSPOSE(SAP_Spreadsheet!$G$632:$BN$632))} -> 0
B55: B1 | C55: {=SUMPRODUCT(C$74:C$133,TRANSPOSE(SAP_Spreadsheet!$G$633:$BN$633))} -> 0 | D55: {=SUMPRODUCT(D$74:D$133,TRANSPOSE(SAP_Spreadsheet!$G$633:$BN$633))} -> 0 | E55: {=SUMPRODUCT(E$74:E$133,TRANSPOSE(SAP_Spreadsheet!$G$633:$BN$633))} -> 0 | F55: {=SUMPRODUCT(F$74:F$133,TRANSPOSE(SAP_Spreadsheet!$G$633:$BN$633))} -> 0 | G55: {=SUMPRODUCT(G$74:G$133,TRANSPOSE(SAP_Spreadsheet!$G$633:$BN$633))} -> 0 | H55: {=SUMPRODUCT(H$74:H$133,TRANSPOSE(SAP_Spreadsheet!$G$633:$BN$633))} -> 0 | I55: {=SUMPRODUCT(I$74:I$133,TRANSPOSE(SAP_Spreadsheet!$G$633:$BN$633))} -> 0 | J55: {=SUMPRODUCT(J$74:J$133,TRANSPOSE(SAP_Spreadsheet!$G$633:$BN$633))} -> 0 | ... BJ55: {=SUMPRODUCT(BJ$74:BJ$133,TRANSPOSE(SAP_Spreadsheet!$G$633:$BN$633))} -> 0
B56: B2 | C56: {=SUMPRODUCT(C$74:C$133,TRANSPOSE(SAP_Spreadsheet!$G$634:$BN$634))} -> 0 | D56: {=SUMPRODUCT(D$74:D$133,TRANSPOSE(SAP_Spreadsheet!$G$634:$BN$634))} -> 0 | E56: {=SUMPRODUCT(E$74:E$133,TRANSPOSE(SAP_Spreadsheet!$G$634:$BN$634))} -> 0 | F56: {=SUMPRODUCT(F$74:F$133,TRANSPOSE(SAP_Spreadsheet!$G$634:$BN$634))} -> 0 | G56: {=SUMPRODUCT(G$74:G$133,TRANSPOSE(SAP_Spreadsheet!$G$634:$BN$634))} -> 0 | H56: {=SUMPRODUCT(H$74:H$133,TRANSPOSE(SAP_Spreadsheet!$G$634:$BN$634))} -> 0 | I56: {=SUMPRODUCT(I$74:I$133,TRANSPOSE(SAP_Spreadsheet!$G$634:$BN$634))} -> 0 | J56: {=SUMPRODUCT(J$74:J$133,TRANSPOSE(SAP_Spreadsheet!$G$634:$BN$634))} -> 0 | ... BJ56: {=SUMPRODUCT(BJ$74:BJ$133,TRANSPOSE(SAP_Spreadsheet!$G$634:$BN$634))} -> 0
B57: B3 | C57: {=SUMPRODUCT(C$74:C$133,TRANSPOSE(SAP_Spreadsheet!$G$635:$BN$635))} -> 0 | D57: {=SUMPRODUCT(D$74:D$133,TRANSPOSE(SAP_Spreadsheet!$G$635:$BN$635))} -> 0 | E57: {=SUMPRODUCT(E$74:E$133,TRANSPOSE(SAP_Spreadsheet!$G$635:$BN$635))} -> 0 | F57: {=SUMPRODUCT(F$74:F$133,TRANSPOSE(SAP_Spreadsheet!$G$635:$BN$635))} -> 0 | G57: {=SUMPRODUCT(G$74:G$133,TRANSPOSE(SAP_Spreadsheet!$G$635:$BN$635))} -> 0 | H57: {=SUMPRODUCT(H$74:H$133,TRANSPOSE(SAP_Spreadsheet!$G$635:$BN$635))} -> 0 | I57: {=SUMPRODUCT(I$74:I$133,TRANSPOSE(SAP_Spreadsheet!$G$635:$BN$635))} -> 0 | J57: {=SUMPRODUCT(J$74:J$133,TRANSPOSE(SAP_Spreadsheet!$G$635:$BN$635))} -> 0 | ... BJ57: {=SUMPRODUCT(BJ$74:BJ$133,TRANSPOSE(SAP_Spreadsheet!$G$635:$BN$635))} -> 0
B58: B4 | C58: {=SUMPRODUCT(C$74:C$133,TRANSPOSE(SAP_Spreadsheet!$G$636:$BN$636))} -> 0 | D58: {=SUMPRODUCT(D$74:D$133,TRANSPOSE(SAP_Spreadsheet!$G$636:$BN$636))} -> 0 | E58: {=SUMPRODUCT(E$74:E$133,TRANSPOSE(SAP_Spreadsheet!$G$636:$BN$636))} -> 0 | F58: {=SUMPRODUCT(F$74:F$133,TRANSPOSE(SAP_Spreadsheet!$G$636:$BN$636))} -> 0 | G58: {=SUMPRODUCT(G$74:G$133,TRANSPOSE(SAP_Spreadsheet!$G$636:$BN$636))} -> 0 | H58: {=SUMPRODUCT(H$74:H$133,TRANSPOSE(SAP_Spreadsheet!$G$636:$BN$636))} -> 0 | I58: {=SUMPRODUCT(I$74:I$133,TRANSPOSE(SAP_Spreadsheet!$G$636:$BN$636))} -> 0 | J58: {=SUMPRODUCT(J$74:J$133,TRANSPOSE(SAP_Spreadsheet!$G$636:$BN$636))} -> 0 | ... BJ58: {=SUMPRODUCT(BJ$74:BJ$133,TRANSPOSE(SAP_Spreadsheet!$G$636:$BN$636))} -> 0
B59: B5 | C59: {=SUMPRODUCT(C$74:C$133,TRANSPOSE(SAP_Spreadsheet!$G$637:$BN$637))} -> 0 | D59: {=SUMPRODUCT(D$74:D$133,TRANSPOSE(SAP_Spreadsheet!$G$637:$BN$637))} -> 0 | E59: {=SUMPRODUCT(E$74:E$133,TRANSPOSE(SAP_Spreadsheet!$G$637:$BN$637))} -> 0 | F59: {=SUMPRODUCT(F$74:F$133,TRANSPOSE(SAP_Spreadsheet!$G$637:$BN$637))} -> 0 | G59: {=SUMPRODUCT(G$74:G$133,TRANSPOSE(SAP_Spreadsheet!$G$637:$BN$637))} -> 0 | H59: {=SUMPRODUCT(H$74:H$133,TRANSPOSE(SAP_Spreadsheet!$G$637:$BN$637))} -> 0 | I59: {=SUMPRODUCT(I$74:I$133,TRANSPOSE(SAP_Spreadsheet!$G$637:$BN$637))} -> 0 | J59: {=SUMPRODUCT(J$74:J$133,TRANSPOSE(SAP_Spreadsheet!$G$637:$BN$637))} -> 0 | ... BJ59: {=SUMPRODUCT(BJ$74:BJ$133,TRANSPOSE(SAP_Spreadsheet!$G$637:$BN$637))} -> 0
B60: B6 | C60: {=SUMPRODUCT(C$74:C$133,TRANSPOSE(SAP_Spreadsheet!$G$638:$BN$638))} -> 0 | D60: {=SUMPRODUCT(D$74:D$133,TRANSPOSE(SAP_Spreadsheet!$G$638:$BN$638))} -> 0 | E60: {=SUMPRODUCT(E$74:E$133,TRANSPOSE(SAP_Spreadsheet!$G$638:$BN$638))} -> 0 | F60: {=SUMPRODUCT(F$74:F$133,TRANSPOSE(SAP_Spreadsheet!$G$638:$BN$638))} -> 0 | G60: {=SUMPRODUCT(G$74:G$133,TRANSPOSE(SAP_Spreadsheet!$G$638:$BN$638))} -> 0 | H60: {=SUMPRODUCT(H$74:H$133,TRANSPOSE(SAP_Spreadsheet!$G$638:$BN$638))} -> 0 | I60: {=SUMPRODUCT(I$74:I$133,TRANSPOSE(SAP_Spreadsheet!$G$638:$BN$638))} -> 0 | J60: {=SUMPRODUCT(J$74:J$133,TRANSPOSE(SAP_Spreadsheet!$G$638:$BN$638))} -> 0 | ... BJ60: {=SUMPRODUCT(BJ$74:BJ$133,TRANSPOSE(SAP_Spreadsheet!$G$638:$BN$638))} -> 0
B61: B7 | C61: {=SUMPRODUCT(C$74:C$133,TRANSPOSE(SAP_Spreadsheet!$G$639:$BN$639))} -> 0 | D61: {=SUMPRODUCT(D$74:D$133,TRANSPOSE(SAP_Spreadsheet!$G$639:$BN$639))} -> 0 | E61: {=SUMPRODUCT(E$74:E$133,TRANSPOSE(SAP_Spreadsheet!$G$639:$BN$639))} -> 0 | F61: {=SUMPRODUCT(F$74:F$133,TRANSPOSE(SAP_Spreadsheet!$G$639:$BN$639))} -> 0 | G61: {=SUMPRODUCT(G$74:G$133,TRANSPOSE(SAP_Spreadsheet!$G$639:$BN$639))} -> 0 | H61: {=SUMPRODUCT(H$74:H$133,TRANSPOSE(SAP_Spreadsheet!$G$639:$BN$639))} -> 0 | I61: {=SUMPRODUCT(I$74:I$133,TRANSPOSE(SAP_Spreadsheet!$G$639:$BN$639))} -> 0 | J61: {=SUMPRODUCT(J$74:J$133,TRANSPOSE(SAP_Spreadsheet!$G$639:$BN$639))} -> 0 | ... BJ61: {=SUMPRODUCT(BJ$74:BJ$133,TRANSPOSE(SAP_Spreadsheet!$G$639:$BN$639))} -> 0
B62: B8 | C62: {=SUMPRODUCT(C$74:C$133,TRANSPOSE(SAP_Spreadsheet!$G$640:$BN$640))} -> 0 | D62: {=SUMPRODUCT(D$74:D$133,TRANSPOSE(SAP_Spreadsheet!$G$640:$BN$640))} -> 0 | E62: {=SUMPRODUCT(E$74:E$133,TRANSPOSE(SAP_Spreadsheet!$G$640:$BN$640))} -> 0 | F62: {=SUMPRODUCT(F$74:F$133,TRANSPOSE(SAP_Spreadsheet!$G$640:$BN$640))} -> 0 | G62: {=SUMPRODUCT(G$74:G$133,TRANSPOSE(SAP_Spreadsheet!$G$640:$BN$640))} -> 0 | H62: {=SUMPRODUCT(H$74:H$133,TRANSPOSE(SAP_Spreadsheet!$G$640:$BN$640))} -> 0 | I62: {=SUMPRODUCT(I$74:I$133,TRANSPOSE(SAP_Spreadsheet!$G$640:$BN$640))} -> 0 | J62: {=SUMPRODUCT(J$74:J$133,TRANSPOSE(SAP_Spreadsheet!$G$640:$BN$640))} -> 0 | ... BJ62: {=SUMPRODUCT(BJ$74:BJ$133,TRANSPOSE(SAP_Spreadsheet!$G$640:$BN$640))} -> 0
B63: B9 | C63: {=SUMPRODUCT(C$74:C$133,TRANSPOSE(SAP_Spreadsheet!$G$641:$BN$641))} -> 0 | D63: {=SUMPRODUCT(D$74:D$133,TRANSPOSE(SAP_Spreadsheet!$G$641:$BN$641))} -> 0 | E63: {=SUMPRODUCT(E$74:E$133,TRANSPOSE(SAP_Spreadsheet!$G$641:$BN$641))} -> 0 | F63: {=SUMPRODUCT(F$74:F$133,TRANSPOSE(SAP_Spreadsheet!$G$641:$BN$641))} -> 0 | G63: {=SUMPRODUCT(G$74:G$133,TRANSPOSE(SAP_Spreadsheet!$G$641:$BN$641))} -> 0 | H63: {=SUMPRODUCT(H$74:H$133,TRANSPOSE(SAP_Spreadsheet!$G$641:$BN$641))} -> 0 | I63: {=SUMPRODUCT(I$74:I$133,TRANSPOSE(SAP_Spreadsheet!$G$641:$BN$641))} -> 0 | J63: {=SUMPRODUCT(J$74:J$133,TRANSPOSE(SAP_Spreadsheet!$G$641:$BN$641))} -> 0 | ... BJ63: {=SUMPRODUCT(BJ$74:BJ$133,TRANSPOSE(SAP_Spreadsheet!$G$641:$BN$641))} -> 0
